{
  "type": "Feature",
  "properties": {
    "gn:admin1_code":"16",
    "gn:asciiname":"Sipai",
    "gn:cc2":"CN",
    "gn:country_code":"CN",
    "gn:dem":159,
    "gn:feature_class":"P",
    "gn:feature_code":"PPL",
    "gn:name":"Sipai",
    "gn:population":0,
    "gn:timezone":"Asia/Shanghai",
    "iso:country":"CN",
    "name:und_x_variant":[
        "Ssu-p\u2019ai-hs\u00fc",
        "Ssu-p\u2019ai",
        "Sipai"
    ],
    "wof:name":"Sipai",
    "wof:placetype":"locality"
},
  "geometry": {"coordinates":[109.99083,24.37583],"type":"Point"}
}