{
  "type": "Feature",
  "properties": {
    "gn:admin1_code":"19.0",
    "gn:asciiname":"Hongqicun",
    "gn:country_code":"CN",
    "gn:dem":327,
    "gn:feature_class":"P",
    "gn:feature_code":"PPL",
    "gn:name":"Hongqicun",
    "gn:population":0,
    "gn:timezone":"Asia/Shanghai",
    "iso:country":"CN",
    "name:zho_x_preferred":[
        "\u7ea2\u65d7\u6751"
    ],
    "wof:name":"Hongqicun",
    "wof:placetype":"locality"
},
  "geometry": {"coordinates":[124.79859999999999,41.62295],"type":"Point"}
}