{
  "type": "Feature",
  "properties": {
    "gn:admin1_code":"7.0",
    "gn:asciiname":"Bishuilin",
    "gn:country_code":"CN",
    "gn:dem":355,
    "gn:feature_class":"P",
    "gn:feature_code":"PPL",
    "gn:name":"Bishuilin",
    "gn:population":0,
    "gn:timezone":"Asia/Shanghai",
    "iso:country":"CN",
    "name:und_x_variant":[
        "\u78a7\u6c34\u6797"
    ],
    "name:zho_x_preferred":[
        "\u78a7\u6c34\u6797"
    ],
    "wof:name":"Bishuilin",
    "wof:placetype":"locality"
},
  "geometry": {"coordinates":[118.47224,26.22543],"type":"Point"}
}