{
  "type": "Feature",
  "properties": {
    "gn:admin1_code":"32.0",
    "gn:asciiname":"Yanjia",
    "gn:country_code":"CN",
    "gn:dem":471,
    "gn:feature_class":"P",
    "gn:feature_code":"PPL",
    "gn:name":"Yanjia",
    "gn:population":0,
    "gn:timezone":"Asia/Shanghai",
    "iso:country":"CN",
    "name:und_x_variant":[
        "Yen-chia-ch\u2019ang",
        "Yanjiachang",
        "Yanjia"
    ],
    "name:zho_x_preferred":[
        "\u9122\u5bb6"
    ],
    "wof:name":"Yanjia",
    "wof:placetype":"locality"
},
  "geometry": {"coordinates":[106.39797,30.71588],"type":"Point"}
}