{
  "type": "Feature",
  "properties": {
    "gn:admin1_code":"12.0",
    "gn:asciiname":"Shuanggang",
    "gn:country_code":"CN",
    "gn:dem":35,
    "gn:feature_class":"P",
    "gn:feature_code":"PPL",
    "gn:name":"Shuanggang",
    "gn:population":0,
    "gn:timezone":"Asia/Shanghai",
    "iso:country":"CN",
    "name:zho_x_preferred":[
        "Shuanggang"
    ],
    "name:zho_x_variant":[
        "\u53cc\u6e2f"
    ],
    "wof:name":"Shuanggang",
    "wof:placetype":"locality"
},
  "geometry": {"coordinates":[115.20681999999999,29.88313],"type":"Point"}
}