{
  "type": "Feature",
  "properties": {
    "gn:admin1_code":"14.0",
    "gn:asciiname":"Yongmengka",
    "gn:country_code":"CN",
    "gn:dem":3898,
    "gn:feature_class":"P",
    "gn:feature_code":"PPL",
    "gn:name":"Yongmengka",
    "gn:population":0,
    "gn:timezone":"Asia/Urumqi",
    "iso:country":"CN",
    "name:zho_x_preferred":[
        "\u6c38\u68a6\u5361"
    ],
    "wof:name":"Yongmengka",
    "wof:placetype":"locality"
},
  "geometry": {"coordinates":[95.67099,31.44035],"type":"Point"}
}