{
  "type": "Feature",
  "properties": {
    "gn:admin1_code":"30",
    "gn:asciiname":"Zhongyangpian",
    "gn:country_code":"CN",
    "gn:dem":196,
    "gn:feature_class":"P",
    "gn:feature_code":"PPL",
    "gn:name":"Zhongyangpian",
    "gn:population":0,
    "gn:timezone":"Asia/Shanghai",
    "iso:country":"CN",
    "name:zho_x_preferred":[
        "\u4e2d\u592e\u7247"
    ],
    "wof:name":"Zhongyangpian",
    "wof:placetype":"locality"
},
  "geometry": {"coordinates":[116.86785999999999,24.28155],"type":"Point"}
}