{
  "type": "Feature",
  "properties": {
    "gn:admin1_code":"9.0",
    "gn:asciiname":"Yinwan",
    "gn:country_code":"CN",
    "gn:dem":103,
    "gn:feature_class":"P",
    "gn:feature_code":"PPL",
    "gn:name":"Yinwan",
    "gn:population":0,
    "gn:timezone":"Asia/Shanghai",
    "iso:country":"CN",
    "name:zho_x_preferred":[
        "\u6bb7\u5846"
    ],
    "wof:name":"Yinwan",
    "wof:placetype":"locality"
},
  "geometry": {"coordinates":[113.81037000000001,32.30551],"type":"Point"}
}