{
  "type": "Feature",
  "properties": {
    "gn:admin1_code":"2.0",
    "gn:asciiname":"Fangqiao",
    "gn:country_code":"CN",
    "gn:dem":30,
    "gn:feature_class":"P",
    "gn:feature_code":"PPL",
    "gn:name":"Fangqiao",
    "gn:population":0,
    "gn:timezone":"Asia/Shanghai",
    "iso:country":"CN",
    "name:zho_x_preferred":[
        "\u65b9\u6865"
    ],
    "wof:name":"Fangqiao",
    "wof:placetype":"locality"
},
  "geometry": {"coordinates":[121.78528,29.72572000000001],"type":"Point"}
}