{
  "type": "Feature",
  "properties": {
    "gn:admin1_code":"26.0",
    "gn:asciiname":"Muguagou",
    "gn:country_code":"CN",
    "gn:dem":1622,
    "gn:feature_class":"P",
    "gn:feature_code":"PPL",
    "gn:name":"Muguagou",
    "gn:population":0,
    "gn:timezone":"Asia/Shanghai",
    "iso:country":"CN",
    "name:zho_x_preferred":[
        "\u6728\u74dc\u6c9f"
    ],
    "wof:name":"Muguagou",
    "wof:placetype":"locality"
},
  "geometry": {"coordinates":[108.44426,37.01357],"type":"Point"}
}