{
  "type": "Feature",
  "properties": {
    "gn:admin1_code":"5.0",
    "gn:asciiname":"Beishantun",
    "gn:country_code":"CN",
    "gn:dem":225,
    "gn:feature_class":"P",
    "gn:feature_code":"PPL",
    "gn:name":"Beishantun",
    "gn:population":0,
    "gn:timezone":"Asia/Shanghai",
    "iso:country":"CN",
    "name:zho_x_preferred":[
        "\u5317\u5c71\u5c6f"
    ],
    "wof:name":"Beishantun",
    "wof:placetype":"locality"
},
  "geometry": {"coordinates":[125.76739999999999,43.85184],"type":"Point"}
}