{
  "type": "Feature",
  "properties": {
    "gn:admin1_code":"3.0",
    "gn:asciiname":"Tangjiashi",
    "gn:country_code":"CN",
    "gn:dem":212,
    "gn:feature_class":"P",
    "gn:feature_code":"PPL",
    "gn:name":"Tangjiashi",
    "gn:population":0,
    "gn:timezone":"Asia/Shanghai",
    "iso:country":"CN",
    "name:zho_x_preferred":[
        "\u5858\u5bb6\u77f3"
    ],
    "wof:name":"Tangjiashi",
    "wof:placetype":"locality"
},
  "geometry": {"coordinates":[114.188,28.0283],"type":"Point"}
}