{
  "type": "Feature",
  "properties": {
    "gn:admin1_code":"18",
    "gn:asciiname":"Qishupo",
    "gn:country_code":"CN",
    "gn:dem":1244,
    "gn:feature_class":"P",
    "gn:feature_code":"PPL",
    "gn:name":"Qishupo",
    "gn:population":0,
    "gn:timezone":"Asia/Shanghai",
    "iso:country":"CN",
    "name:zho_x_preferred":[
        "\u6f06\u6811\u5761"
    ],
    "wof:name":"Qishupo",
    "wof:placetype":"locality"
},
  "geometry": {"coordinates":[106.509,28.0968],"type":"Point"}
}