{
  "type": "Feature",
  "properties": {
    "gn:admin1_code":"1.0",
    "gn:asciiname":"Daxingcun",
    "gn:country_code":"CN",
    "gn:dem":496,
    "gn:feature_class":"P",
    "gn:feature_code":"PPL",
    "gn:name":"Daxingcun",
    "gn:population":0,
    "gn:timezone":"Asia/Shanghai",
    "iso:country":"CN",
    "name:zho_x_preferred":[
        "\u5927\u661f\u6751"
    ],
    "wof:name":"Daxingcun",
    "wof:placetype":"locality"
},
  "geometry": {"coordinates":[117.83411,30.0191],"type":"Point"}
}