{
  "type": "Feature",
  "properties": {
    "gn:admin1_code":"32.0",
    "gn:asciiname":"Gaizitou",
    "gn:country_code":"CN",
    "gn:dem":1102,
    "gn:feature_class":"P",
    "gn:feature_code":"PPL",
    "gn:name":"Gaizitou",
    "gn:population":0,
    "gn:timezone":"Asia/Shanghai",
    "iso:country":"CN",
    "name:zho_x_preferred":[
        "\u76d6\u5b50\u5934"
    ],
    "wof:name":"Gaizitou",
    "wof:placetype":"locality"
},
  "geometry": {"coordinates":[103.24299999999999,29.1962],"type":"Point"}
}