{
  "type": "Feature",
  "properties": {
    "gn:admin1_code":"18",
    "gn:asciiname":"Fenghuoqiang",
    "gn:country_code":"CN",
    "gn:dem":1846,
    "gn:feature_class":"P",
    "gn:feature_code":"PPL",
    "gn:name":"Fenghuoqiang",
    "gn:population":0,
    "gn:timezone":"Asia/Shanghai",
    "iso:country":"CN",
    "name:zho_x_preferred":[
        "\u70fd\u706b\u5899"
    ],
    "wof:name":"Fenghuoqiang",
    "wof:placetype":"locality"
},
  "geometry": {"coordinates":[103.81699999999999,27.2298],"type":"Point"}
}