{
  "type": "Feature",
  "properties": {
    "gn:admin1_code":"07",
    "gn:asciiname":"Shang'an",
    "gn:country_code":"CN",
    "gn:dem":455,
    "gn:feature_class":"P",
    "gn:feature_code":"PPL",
    "gn:name":"Shang\u2019an",
    "gn:population":0,
    "gn:timezone":"Asia/Shanghai",
    "iso:country":"CN",
    "name:und_x_variant":[
        "Shang\u2019an"
    ],
    "name:zho_x_preferred":[
        "\u4e0a\u57b5"
    ],
    "wof:name":"Shang'an",
    "wof:placetype":"locality"
},
  "geometry": {"coordinates":[118.29783999999999,25.47817],"type":"Point"}
}