{
  "type": "Feature",
  "properties": {
    "gn:admin1_code":"20.0",
    "gn:asciiname":"Dianxin",
    "gn:country_code":"CN",
    "gn:dem":451,
    "gn:feature_class":"P",
    "gn:feature_code":"PPL",
    "gn:name":"Dianxin",
    "gn:population":0,
    "gn:timezone":"Asia/Shanghai",
    "iso:country":"CN",
    "name:zho_x_preferred":[
        "\u7538\u5fc3"
    ],
    "wof:name":"Dianxin",
    "wof:placetype":"locality"
},
  "geometry": {"coordinates":[122.43597,47.86407],"type":"Point"}
}