{
  "type": "Feature",
  "properties": {
    "gn:admin1_code":"11.0",
    "gn:asciiname":"Xinzhuanglong",
    "gn:country_code":"CN",
    "gn:dem":194,
    "gn:feature_class":"P",
    "gn:feature_code":"PPL",
    "gn:name":"Xinzhuanglong",
    "gn:population":0,
    "gn:timezone":"Asia/Shanghai",
    "iso:country":"CN",
    "name:zho_x_preferred":[
        "\u65b0\u5e84\u5784"
    ],
    "wof:name":"Xinzhuanglong",
    "wof:placetype":"locality"
},
  "geometry": {"coordinates":[110.52243,27.81622],"type":"Point"}
}