{
  "type": "Feature",
  "properties": {
    "gn:admin1_code":"1.0",
    "gn:asciiname":"Chentuancun",
    "gn:country_code":"CN",
    "gn:dem":21,
    "gn:feature_class":"P",
    "gn:feature_code":"PPL",
    "gn:name":"Chentuancun",
    "gn:population":0,
    "gn:timezone":"Asia/Shanghai",
    "iso:country":"CN",
    "name:zho_x_preferred":[
        "\u6c89\u56e2\u6751"
    ],
    "wof:name":"Chentuancun",
    "wof:placetype":"locality"
},
  "geometry": {"coordinates":[117.05673,30.37887000000001],"type":"Point"}
}