{
  "type": "Feature",
  "properties": {
    "gn:admin1_code":"19.0",
    "gn:asciiname":"Nanlitun",
    "gn:country_code":"CN",
    "gn:dem":178,
    "gn:feature_class":"P",
    "gn:feature_code":"PPL",
    "gn:name":"Nanlitun",
    "gn:population":0,
    "gn:timezone":"Asia/Shanghai",
    "iso:country":"CN",
    "name:und_x_variant":[
        "\u5357\u674e\u5c6f"
    ],
    "wof:name":"Nanlitun",
    "wof:placetype":"locality"
},
  "geometry": {"coordinates":[122.711,40.0034],"type":"Point"}
}