{
  "type": "Feature",
  "properties": {
    "gn:admin1_code":"3.0",
    "gn:asciiname":"Pujia",
    "gn:country_code":"CN",
    "gn:dem":36,
    "gn:feature_class":"P",
    "gn:feature_code":"PPL",
    "gn:name":"Pujia",
    "gn:population":0,
    "gn:timezone":"Asia/Shanghai",
    "iso:country":"CN",
    "name:zho_x_preferred":[
        "\u6fee\u5bb6"
    ],
    "wof:name":"Pujia",
    "wof:placetype":"locality"
},
  "geometry": {"coordinates":[117.321,28.8803],"type":"Point"}
}