{
  "type": "Feature",
  "properties": {
    "gn:admin1_code":"11.0",
    "gn:asciiname":"Panxindong",
    "gn:country_code":"CN",
    "gn:dem":379,
    "gn:feature_class":"P",
    "gn:feature_code":"PPL",
    "gn:name":"Panxindong",
    "gn:population":0,
    "gn:timezone":"Asia/Shanghai",
    "iso:country":"CN",
    "name:zho_x_preferred":[
        "\u6f58\u65b0\u6d1e"
    ],
    "wof:name":"Panxindong",
    "wof:placetype":"locality"
},
  "geometry": {"coordinates":[112.04873000000001,28.33946],"type":"Point"}
}