{
  "type": "Feature",
  "properties": {
    "gn:admin1_code":"13.0",
    "gn:asciiname":"Towurqi",
    "gn:cc2":"CN",
    "gn:country_code":"CN",
    "gn:dem":908,
    "gn:feature_class":"P",
    "gn:feature_code":"PPL",
    "gn:name":"Towurqi",
    "gn:population":0,
    "gn:timezone":"Asia/Urumqi",
    "iso:country":"CN",
    "name:uig_x_preferred":[
        "Towurchi"
    ],
    "name:uig_x_variant":[
        "\u062a\u0648\u06cb\u06c7\u0631\u0686\u0649",
        "\u0422\u043e\u0432\u0443\u0440\u0447\u0438"
    ],
    "name:und_x_variant":[
        "Towurqi Xiang",
        "Toplis",
        "Towurqi"
    ],
    "wof:name":"Towurqi",
    "wof:placetype":"locality"
},
  "geometry": {"coordinates":[85.92389,41.69528],"type":"Point"}
}