{
  "type": "Feature",
  "properties": {
    "gn:admin1_code":"2.0",
    "gn:asciiname":"Guancheng",
    "gn:country_code":"CN",
    "gn:dem":117,
    "gn:feature_class":"P",
    "gn:feature_code":"PPL",
    "gn:name":"Guancheng",
    "gn:population":0,
    "gn:timezone":"Asia/Shanghai",
    "iso:country":"CN",
    "name:ceb_x_preferred":[
        "Guancheng"
    ],
    "name:sco_x_preferred":[
        "Guancheng"
    ],
    "name:und_x_variant":[
        "\u7ba1\u57ce"
    ],
    "wof:name":"Guancheng",
    "wof:placetype":"locality"
},
  "geometry": {"coordinates":[119.8651,30.73101],"type":"Point"}
}