{
  "type": "Feature",
  "properties": {
    "gn:admin1_code":"3.0",
    "gn:asciiname":"Dabali",
    "gn:country_code":"CN",
    "gn:dem":238,
    "gn:feature_class":"P",
    "gn:feature_code":"PPL",
    "gn:name":"Dabali",
    "gn:population":0,
    "gn:timezone":"Asia/Shanghai",
    "iso:country":"CN",
    "name:und_x_variant":[
        "\u5927\u575d\u91cc"
    ],
    "wof:name":"Dabali",
    "wof:placetype":"locality"
},
  "geometry": {"coordinates":[115.24243,25.98111],"type":"Point"}
}