{
  "type": "Feature",
  "properties": {
    "gn:admin1_code":"03",
    "gn:asciiname":"Sanjiang",
    "gn:country_code":"CN",
    "gn:dem":29,
    "gn:feature_class":"P",
    "gn:feature_code":"PPLA4",
    "gn:name":"Sanjiang",
    "gn:population":0,
    "gn:timezone":"Asia/Shanghai",
    "iso:country":"CN",
    "name:ceb_x_preferred":[
        "Sanjiang"
    ],
    "name:deu_x_preferred":[
        "Sanjiang"
    ],
    "name:und_x_variant":[
        "San-chiang-k\u2019ou",
        "Sanjiang",
        "\u4e09\u6c5f",
        "Sanjiangkou",
        "Sanjiang Zhen",
        "\u4e09\u6c5f\u9547"
    ],
    "wof:name":"Sanjiang",
    "wof:placetype":"locality"
},
  "geometry": {"coordinates":[116.00473999999998,28.29269],"type":"Point"}
}