{
  "type": "Feature",
  "properties": {
    "gn:admin1_code":"9.0",
    "gn:asciiname":"Zhaozhuang",
    "gn:country_code":"CN",
    "gn:dem":123,
    "gn:feature_class":"P",
    "gn:feature_code":"PPL",
    "gn:name":"Zhaozhuang",
    "gn:population":0,
    "gn:timezone":"Asia/Shanghai",
    "iso:country":"CN",
    "name:und_x_variant":[
        "\u8d75\u5e84",
        "Zhaozhuang"
    ],
    "wof:name":"Zhaozhuang",
    "wof:placetype":"locality"
},
  "geometry": {"coordinates":[112.96711000000001,33.0487],"type":"Point"}
}