{
  "type": "Feature",
  "properties": {
    "gn:admin1_code":"12.0",
    "gn:asciiname":"Bawangpo",
    "gn:country_code":"CN",
    "gn:dem":1176,
    "gn:feature_class":"P",
    "gn:feature_code":"PPL",
    "gn:name":"Bawangpo",
    "gn:population":0,
    "gn:timezone":"Asia/Shanghai",
    "iso:country":"CN",
    "name:zho_x_preferred":[
        "\u516b\u671b\u5761"
    ],
    "wof:name":"Bawangpo",
    "wof:placetype":"locality"
},
  "geometry": {"coordinates":[109.06631000000002,30.16243],"type":"Point"}
}