{
  "type": "Feature",
  "properties": {
    "gn:admin1_code":"1.0",
    "gn:asciiname":"Chenhucun",
    "gn:country_code":"CN",
    "gn:dem":22,
    "gn:feature_class":"P",
    "gn:feature_code":"PPL",
    "gn:name":"Chenhucun",
    "gn:population":0,
    "gn:timezone":"Asia/Shanghai",
    "iso:country":"CN",
    "name:zho_x_preferred":[
        "\u9648\u6e56\u6751"
    ],
    "wof:name":"Chenhucun",
    "wof:placetype":"locality"
},
  "geometry": {"coordinates":[117.08736,33.48353],"type":"Point"}
}