{
  "type": "Feature",
  "properties": {
    "gn:admin1_code":"14.0",
    "gn:asciiname":"Tongdui",
    "gn:country_code":"CN",
    "gn:dem":3601,
    "gn:feature_class":"P",
    "gn:feature_code":"PPL",
    "gn:name":"Tongdui",
    "gn:population":0,
    "gn:timezone":"Asia/Urumqi",
    "iso:country":"CN",
    "name:zho_x_preferred":[
        "\u901a\u5806"
    ],
    "wof:name":"Tongdui",
    "wof:placetype":"locality"
},
  "geometry": {"coordinates":[95.78187,30.76305],"type":"Point"}
}