{
  "type": "Feature",
  "properties": {
    "gn:admin1_code":"31",
    "gn:asciiname":"Nanlin",
    "gn:country_code":"CN",
    "gn:dem":98,
    "gn:feature_class":"P",
    "gn:feature_code":"PPLA4",
    "gn:name":"Nanlin",
    "gn:population":0,
    "gn:timezone":"Asia/Shanghai",
    "iso:country":"CN",
    "name:und_x_variant":[
        "\u5357\u6797",
        "Nanlin Xiang",
        "\u5357\u6797\u4e61"
    ],
    "wof:name":"Nanlin",
    "wof:placetype":"locality"
},
  "geometry": {"coordinates":[109.60921,18.41307],"type":"Point"}
}