{
  "type": "Feature",
  "properties": {
    "gn:admin1_code":"29.0",
    "gn:asciiname":"Musegu",
    "gn:country_code":"CN",
    "gn:dem":1719,
    "gn:feature_class":"P",
    "gn:feature_code":"PPL",
    "gn:name":"Musegu",
    "gn:population":0,
    "gn:timezone":"Asia/Shanghai",
    "iso:country":"CN",
    "name:zho_x_preferred":[
        "\u5e55\u8272\u8c37"
    ],
    "wof:name":"Musegu",
    "wof:placetype":"locality"
},
  "geometry": {"coordinates":[104.667,25.2259],"type":"Point"}
}