{
  "type": "Feature",
  "properties": {
    "gn:admin1_code":"26",
    "gn:asciiname":"Taoquhe",
    "gn:country_code":"CN",
    "gn:dem":1221,
    "gn:feature_class":"P",
    "gn:feature_code":"PPL",
    "gn:name":"Taoquhe",
    "gn:population":0,
    "gn:timezone":"Asia/Shanghai",
    "iso:country":"CN",
    "name:zho_x_preferred":[
        "\u6843\u6e20\u6cb3"
    ],
    "wof:name":"Taoquhe",
    "wof:placetype":"locality"
},
  "geometry": {"coordinates":[108.59999999999999,34.95611],"type":"Point"}
}