{
  "type": "Feature",
  "properties": {
    "gn:admin1_code":"14.0",
    "gn:asciiname":"Zhengka",
    "gn:country_code":"CN",
    "gn:dem":4232,
    "gn:feature_class":"P",
    "gn:feature_code":"PPL",
    "gn:name":"Zhengka",
    "gn:population":0,
    "gn:timezone":"Asia/Urumqi",
    "iso:country":"CN",
    "name:zho_x_preferred":[
        "\u4e89\u5361"
    ],
    "wof:name":"Zhengka",
    "wof:placetype":"locality"
},
  "geometry": {"coordinates":[94.68038,31.09307],"type":"Point"}
}