{
  "type": "Feature",
  "properties": {
    "gn:admin1_code":"31.0",
    "gn:asciiname":"Changfa",
    "gn:country_code":"CN",
    "gn:dem":39,
    "gn:feature_class":"P",
    "gn:feature_code":"PPL",
    "gn:name":"Changfa",
    "gn:population":0,
    "gn:timezone":"Asia/Shanghai",
    "iso:country":"CN",
    "name:zho_x_preferred":[
        "Changfa"
    ],
    "name:zho_x_variant":[
        "\u660c\u53d1"
    ],
    "wof:name":"Changfa",
    "wof:placetype":"locality"
},
  "geometry": {"coordinates":[110.86036,19.82212],"type":"Point"}
}