{
  "type": "Feature",
  "properties": {
    "gn:admin1_code":"30.0",
    "gn:asciiname":"Sanwangba",
    "gn:country_code":"CN",
    "gn:dem":43,
    "gn:feature_class":"P",
    "gn:feature_code":"PPL",
    "gn:name":"Sanwangba",
    "gn:population":0,
    "gn:timezone":"Asia/Shanghai",
    "iso:country":"CN",
    "name:und_x_variant":[
        "\u4e09\u738b\u575d"
    ],
    "name:zho_x_preferred":[
        "\u4e09\u738b\u575d"
    ],
    "wof:name":"Sanwangba",
    "wof:placetype":"locality"
},
  "geometry": {"coordinates":[114.70375,23.71067],"type":"Point"}
}