{
  "type": "Feature",
  "properties": {
    "gn:admin1_code":"25.0",
    "gn:asciiname":"Guoxicun",
    "gn:country_code":"CN",
    "gn:dem":11,
    "gn:feature_class":"P",
    "gn:feature_code":"PPL",
    "gn:name":"Guoxicun",
    "gn:population":0,
    "gn:timezone":"Asia/Shanghai",
    "iso:country":"CN",
    "name:zho_x_preferred":[
        "\u90ed\u897f\u6751"
    ],
    "wof:name":"Guoxicun",
    "wof:placetype":"locality"
},
  "geometry": {"coordinates":[118.38502,37.7291],"type":"Point"}
}