{
  "type": "Feature",
  "properties": {
    "gn:admin1_code":"5.0",
    "gn:asciiname":"Laozhifang",
    "gn:country_code":"CN",
    "gn:dem":162,
    "gn:feature_class":"P",
    "gn:feature_code":"PPL",
    "gn:name":"Laozhifang",
    "gn:population":0,
    "gn:timezone":"Asia/Shanghai",
    "iso:country":"CN",
    "name:zho_x_preferred":[
        "\u8001\u7eb8\u574a"
    ],
    "wof:name":"Laozhifang",
    "wof:placetype":"locality"
},
  "geometry": {"coordinates":[126.61691999999999,44.92581],"type":"Point"}
}