{
  "type": "Feature",
  "properties": {
    "gn:admin1_code":"29.0",
    "gn:asciiname":"Xiapuge",
    "gn:country_code":"CN",
    "gn:dem":1513,
    "gn:feature_class":"P",
    "gn:feature_code":"PPL",
    "gn:name":"Xiapuge",
    "gn:population":0,
    "gn:timezone":"Asia/Shanghai",
    "iso:country":"CN",
    "name:zho_x_preferred":[
        "\u4e0b\u666e\u683c"
    ],
    "wof:name":"Xiapuge",
    "wof:placetype":"locality"
},
  "geometry": {"coordinates":[104.30200000000001,24.2765],"type":"Point"}
}