{
  "type": "Feature",
  "properties": {
    "gn:admin1_code":"30",
    "gn:asciiname":"Tugong",
    "gn:country_code":"CN",
    "gn:dem":19,
    "gn:feature_class":"P",
    "gn:feature_code":"PPL",
    "gn:name":"Tugong",
    "gn:population":0,
    "gn:timezone":"Asia/Urumqi",
    "iso:country":"CN",
    "name:und_x_variant":[
        "Tugongxu",
        "Tugong"
    ],
    "name:zho_x_preferred":[
        "T\u2019u-kung-hs\u00fc"
    ],
    "name:zho_x_variant":[
        "\u571f\u8d21"
    ],
    "wof:name":"Tugong",
    "wof:placetype":"locality"
},
  "geometry": {"coordinates":[109.97544000000001,20.51885],"type":"Point"}
}