{
  "type": "Feature",
  "properties": {
    "gn:admin1_code":"16.0",
    "gn:asciiname":"Pingmo",
    "gn:country_code":"CN",
    "gn:dem":896,
    "gn:feature_class":"P",
    "gn:feature_code":"PPL",
    "gn:name":"Pingmo",
    "gn:population":0,
    "gn:timezone":"Asia/Shanghai",
    "iso:country":"CN",
    "name:zho_x_preferred":[
        "\u5e73\u78e8"
    ],
    "wof:name":"Pingmo",
    "wof:placetype":"locality"
},
  "geometry": {"coordinates":[105.155,24.7867],"type":"Point"}
}