{
  "type": "Feature",
  "properties": {
    "gn:admin1_code":"21.0",
    "gn:asciiname":"Huachanao",
    "gn:country_code":"CN",
    "gn:dem":1942,
    "gn:feature_class":"P",
    "gn:feature_code":"PPL",
    "gn:name":"Huachanao",
    "gn:population":0,
    "gn:timezone":"Asia/Shanghai",
    "iso:country":"CN",
    "name:und_x_variant":[
        "\u82b1\u5c94\u57b4"
    ],
    "name:zho_x_preferred":[
        "\u82b1\u5c94\u57b4"
    ],
    "wof:name":"Huachanao",
    "wof:placetype":"locality"
},
  "geometry": {"coordinates":[105.44962,35.8731],"type":"Point"}
}