{
  "type": "Feature",
  "properties": {
    "gn:admin1_code":"10.0",
    "gn:asciiname":"Zhanggezhuang",
    "gn:country_code":"CN",
    "gn:dem":19,
    "gn:feature_class":"P",
    "gn:feature_code":"PPL",
    "gn:name":"Zhanggezhuang",
    "gn:population":0,
    "gn:timezone":"Asia/Shanghai",
    "iso:country":"CN",
    "name:zho_x_preferred":[
        "\u5f20\u5404\u5e84"
    ],
    "name:zho_x_variant":[
        "\u5f20\u683c\u5e84\u9547"
    ],
    "wof:name":"Zhanggezhuang",
    "wof:placetype":"locality"
},
  "geometry": {"coordinates":[119.08114999999999,39.72799000000001],"type":"Point"}
}