{
  "type": "Feature",
  "properties": {
    "gn:admin1_code":"16",
    "gn:asciiname":"Muzi",
    "gn:cc2":"CN",
    "gn:country_code":"CN",
    "gn:dem":65,
    "gn:feature_class":"P",
    "gn:feature_code":"PPL",
    "gn:name":"Muzi",
    "gn:population":0,
    "gn:timezone":"Asia/Shanghai",
    "iso:country":"CN",
    "name:ceb_x_preferred":[
        "Muzi"
    ],
    "name:deu_x_preferred":[
        "Muzi"
    ],
    "name:swe_x_preferred":[
        "Muzi"
    ],
    "name:und_x_variant":[
        "Mu-tzu"
    ],
    "wof:name":"Muzi",
    "wof:placetype":"locality"
},
  "geometry": {"coordinates":[109.62389,22.78028],"type":"Point"}
}