{
  "type": "Feature",
  "properties": {
    "gn:admin1_code":"20",
    "gn:asciiname":"Lo-she-ch'uan-tzu",
    "gn:country_code":"CN",
    "gn:dem":708,
    "gn:feature_class":"P",
    "gn:feature_code":"PPL",
    "gn:name":"Lo-she-ch\u2019\u00fcan-tzu",
    "gn:population":0,
    "gn:timezone":"Asia/Shanghai",
    "iso:country":"CN",
    "wof:name":"Lo-she-ch'uan-tzu",
    "wof:placetype":"locality"
},
  "geometry": {"coordinates":[118.82056,42.61333],"type":"Point"}
}