{
  "type": "Feature",
  "properties": {
    "gn:admin1_code":"9",
    "gn:asciiname":"Yuchi",
    "gn:country_code":"CN",
    "gn:dem":999,
    "gn:feature_class":"P",
    "gn:feature_code":"PPL",
    "gn:name":"Yuchi",
    "gn:population":0,
    "gn:timezone":"Asia/Shanghai",
    "iso:country":"CN",
    "name:cat_x_preferred":[
        "Yuchis"
    ],
    "name:deu_x_preferred":[
        "Yuchi"
    ],
    "name:fra_x_preferred":[
        "Yuchis"
    ],
    "name:hrv_x_preferred":[
        "Yuchi Indijanci"
    ],
    "name:lit_x_preferred":[
        "Ju\u010diai"
    ],
    "name:rus_x_preferred":[
        "\u042e\u0447\u0438"
    ],
    "name:spa_x_preferred":[
        "Yuchi"
    ],
    "name:zho_x_preferred":[
        "\u9c7c\u6c60"
    ],
    "wof:name":"Yuchi",
    "wof:placetype":"locality"
},
  "geometry": {"coordinates":[111.35296,34.56627],"type":"Point"}
}