{
  "type": "Feature",
  "properties": {
    "gn:admin1_code":"24",
    "gn:asciiname":"Runcheng",
    "gn:cc2":"CN",
    "gn:country_code":"CN",
    "gn:dem":497,
    "gn:feature_class":"P",
    "gn:feature_code":"PPL",
    "gn:name":"Runcheng",
    "gn:population":0,
    "gn:timezone":"Asia/Shanghai",
    "iso:country":"CN",
    "name:und_x_variant":[
        "Jun-ch\u2019eng-chen",
        "Jun-ch\u2019eng",
        "Runcheng"
    ],
    "wof:name":"Runcheng",
    "wof:placetype":"locality"
},
  "geometry": {"coordinates":[112.52110999999999,35.495],"type":"Point"}
}