{
  "type": "Feature",
  "properties": {
    "gn:admin1_code":"5.0",
    "gn:asciiname":"Yangchungou",
    "gn:country_code":"CN",
    "gn:dem":536,
    "gn:feature_class":"P",
    "gn:feature_code":"PPL",
    "gn:name":"Yangchungou",
    "gn:population":0,
    "gn:timezone":"Asia/Shanghai",
    "iso:country":"CN",
    "name:und_x_variant":[
        "\u6768\u6625\u6c9f"
    ],
    "wof:name":"Yangchungou",
    "wof:placetype":"locality"
},
  "geometry": {"coordinates":[125.69735,41.7847],"type":"Point"}
}