{
  "type": "Feature",
  "properties": {
    "gn:admin1_code":"8.0",
    "gn:asciiname":"Wenchengcun",
    "gn:country_code":"CN",
    "gn:dem":74,
    "gn:feature_class":"P",
    "gn:feature_code":"PPL",
    "gn:name":"Wenchengcun",
    "gn:population":0,
    "gn:timezone":"Asia/Shanghai",
    "iso:country":"CN",
    "name:zho_x_preferred":[
        "\u6c76\u6f84\u6751"
    ],
    "wof:name":"Wenchengcun",
    "wof:placetype":"locality"
},
  "geometry": {"coordinates":[130.76151000000002,47.06877],"type":"Point"}
}