{
  "type": "Feature",
  "properties": {
    "gn:admin1_code":"10",
    "gn:asciiname":"Mengzhongfeng",
    "gn:country_code":"CN",
    "gn:dem":13,
    "gn:feature_class":"P",
    "gn:feature_code":"PPL",
    "gn:name":"Mengzhongfeng",
    "gn:population":0,
    "gn:timezone":"Asia/Shanghai",
    "iso:country":"CN",
    "name:und_x_variant":[
        "Meng-chung-feng",
        "Mengzhongfeng"
    ],
    "name:zho_x_preferred":[
        "\u5b5f\u4ef2\u5cf0"
    ],
    "wof:name":"Mengzhongfeng",
    "wof:placetype":"locality"
},
  "geometry": {"coordinates":[115.934,38.7463],"type":"Point"}
}