{
  "type": "Feature",
  "properties": {
    "gn:admin1_code":"12.0",
    "gn:asciiname":"Hejiachong",
    "gn:country_code":"CN",
    "gn:dem":109,
    "gn:feature_class":"P",
    "gn:feature_code":"PPL",
    "gn:name":"Hejiachong",
    "gn:population":0,
    "gn:timezone":"Asia/Shanghai",
    "iso:country":"CN",
    "name:zho_x_preferred":[
        "Hejiachong"
    ],
    "name:zho_x_variant":[
        "\u4f55\u5bb6\u51b2"
    ],
    "wof:name":"Hejiachong",
    "wof:placetype":"locality"
},
  "geometry": {"coordinates":[111.4396,30.56048],"type":"Point"}
}