{
  "type": "Feature",
  "properties": {
    "gn:admin1_code":"5.0",
    "gn:asciiname":"Jijia Gouzi",
    "gn:country_code":"CN",
    "gn:dem":198,
    "gn:feature_class":"P",
    "gn:feature_code":"PPL",
    "gn:name":"Jijia Gouzi",
    "gn:population":0,
    "gn:timezone":"Asia/Shanghai",
    "iso:country":"CN",
    "name:zho_x_preferred":[
        "\u7eaa\u5bb6\u6c9f\u5b50"
    ],
    "wof:name":"Jijia Gouzi",
    "wof:placetype":"locality"
},
  "geometry": {"coordinates":[126.55540999999999,45.0317],"type":"Point"}
}