{
  "type": "Feature",
  "properties": {
    "gn:admin1_code":"9",
    "gn:asciiname":"Wangsanzhai",
    "gn:country_code":"CN",
    "gn:dem":60,
    "gn:feature_class":"P",
    "gn:feature_code":"PPL",
    "gn:name":"Wangsanzhai",
    "gn:population":0,
    "gn:timezone":"Asia/Shanghai",
    "iso:country":"CN",
    "name:zho_x_preferred":[
        "\u738b\u4e09\u5be8"
    ],
    "wof:name":"Wangsanzhai",
    "wof:placetype":"locality"
},
  "geometry": {"coordinates":[114.863,35.6437],"type":"Point"}
}