{
  "type": "Feature",
  "properties": {
    "gn:admin1_code":"29.0",
    "gn:asciiname":"Laobanchong",
    "gn:country_code":"CN",
    "gn:dem":2195,
    "gn:feature_class":"P",
    "gn:feature_code":"PPL",
    "gn:name":"Laobanchong",
    "gn:population":0,
    "gn:timezone":"Asia/Shanghai",
    "iso:country":"CN",
    "name:zho_x_preferred":[
        "\u8001\u677f\u51b2"
    ],
    "wof:name":"Laobanchong",
    "wof:placetype":"locality"
},
  "geometry": {"coordinates":[101.379,25.5405],"type":"Point"}
}