{
  "type": "Feature",
  "properties": {
    "gn:admin1_code":"1.0",
    "gn:asciiname":"Bajiaotingcun",
    "gn:country_code":"CN",
    "gn:dem":39,
    "gn:feature_class":"P",
    "gn:feature_code":"PPL",
    "gn:name":"Bajiaotingcun",
    "gn:population":0,
    "gn:timezone":"Asia/Shanghai",
    "iso:country":"CN",
    "name:und_x_variant":[
        "Bajiaoting",
        "\u516b\u89d2\u4ead",
        "Bajiaotingcun"
    ],
    "name:zho_x_preferred":[
        "\u516b\u89d2\u4ead\u6751"
    ],
    "wof:name":"Bajiaotingcun",
    "wof:placetype":"locality"
},
  "geometry": {"coordinates":[118.78076,30.82511],"type":"Point"}
}