{
  "type": "Feature",
  "properties": {
    "gn:admin1_code":"32.0",
    "gn:asciiname":"Landang'er",
    "gn:country_code":"CN",
    "gn:dem":1153,
    "gn:feature_class":"P",
    "gn:feature_code":"PPL",
    "gn:name":"Landang\u2019er",
    "gn:population":0,
    "gn:timezone":"Asia/Shanghai",
    "iso:country":"CN",
    "name:zho_x_preferred":[
        "\u6ee5\u51fc\u513f"
    ],
    "name:zho_x_variant":[
        "Landang\u2019er"
    ],
    "wof:name":"Landang'er",
    "wof:placetype":"locality"
},
  "geometry": {"coordinates":[103.60035999999999,28.66407],"type":"Point"}
}