{
  "type": "Feature",
  "properties": {
    "gn:admin1_code":"16.0",
    "gn:asciiname":"Caogentang",
    "gn:country_code":"CN",
    "gn:dem":18,
    "gn:feature_class":"P",
    "gn:feature_code":"PPL",
    "gn:name":"Caogentang",
    "gn:population":0,
    "gn:timezone":"Asia/Shanghai",
    "iso:country":"CN",
    "name:zho_x_preferred":[
        "\u8349\u6839\u5858"
    ],
    "wof:name":"Caogentang",
    "wof:placetype":"locality"
},
  "geometry": {"coordinates":[109.29300000000001,21.4967],"type":"Point"}
}