{
  "type": "Feature",
  "properties": {
    "gn:admin1_code":"24",
    "gn:asciiname":"Chen'ou",
    "gn:country_code":"CN",
    "gn:dem":921,
    "gn:feature_class":"P",
    "gn:feature_code":"PPL",
    "gn:name":"Chen\u2019ou",
    "gn:population":0,
    "gn:timezone":"Asia/Shanghai",
    "iso:country":"CN",
    "name:und_x_variant":[
        "Ch\u2019en-ou-ts\u2019un",
        "Chen\u2019ou"
    ],
    "wof:name":"Chen'ou",
    "wof:placetype":"locality"
},
  "geometry": {"coordinates":[113.03389,35.84833],"type":"Point"}
}