{
  "type": "Feature",
  "properties": {
    "gn:admin1_code":"26.0",
    "gn:asciiname":"Hujiawan",
    "gn:country_code":"CN",
    "gn:dem":1307,
    "gn:feature_class":"P",
    "gn:feature_code":"PPL",
    "gn:name":"Hujiawan",
    "gn:population":0,
    "gn:timezone":"Asia/Shanghai",
    "iso:country":"CN",
    "name:und_x_variant":[
        "\u80e1\u5bb6\u6e7e"
    ],
    "wof:name":"Hujiawan",
    "wof:placetype":"locality"
},
  "geometry": {"coordinates":[106.92243999999999,33.70281],"type":"Point"}
}