{
  "type": "Feature",
  "properties": {
    "gn:admin1_code":"19.0",
    "gn:asciiname":"Dawoluozi",
    "gn:country_code":"CN",
    "gn:dem":233,
    "gn:feature_class":"P",
    "gn:feature_code":"PPL",
    "gn:name":"Dawoluozi",
    "gn:population":0,
    "gn:timezone":"Asia/Shanghai",
    "iso:country":"CN",
    "name:zho_x_preferred":[
        "\u5927\u7a9d\u9aa1\u5b50"
    ],
    "wof:name":"Dawoluozi",
    "wof:placetype":"locality"
},
  "geometry": {"coordinates":[124.34,40.588],"type":"Point"}
}