{
  "type": "Feature",
  "properties": {
    "gn:admin1_code":"32.0",
    "gn:asciiname":"Deye",
    "gn:country_code":"CN",
    "gn:dem":2909,
    "gn:feature_class":"P",
    "gn:feature_code":"PPL",
    "gn:name":"Deye",
    "gn:population":0,
    "gn:timezone":"Asia/Shanghai",
    "iso:country":"CN",
    "name:zho_x_preferred":[
        "\u5fb7\u4e5f"
    ],
    "wof:name":"Deye",
    "wof:placetype":"locality"
},
  "geometry": {"coordinates":[101.625,31.7717],"type":"Point"}
}