{
  "type": "Feature",
  "properties": {
    "gn:admin1_code":"19.0",
    "gn:asciiname":"Duanzhangzi",
    "gn:country_code":"CN",
    "gn:dem":458,
    "gn:feature_class":"P",
    "gn:feature_code":"PPL",
    "gn:name":"Duanzhangzi",
    "gn:population":0,
    "gn:timezone":"Asia/Shanghai",
    "iso:country":"CN",
    "name:zho_x_preferred":[
        "\u6bb5\u6756\u5b50"
    ],
    "wof:name":"Duanzhangzi",
    "wof:placetype":"locality"
},
  "geometry": {"coordinates":[119.23045,41.24789000000001],"type":"Point"}
}