{
  "type": "Feature",
  "properties": {
    "gn:admin1_code":"9.0",
    "gn:asciiname":"Lutai",
    "gn:country_code":"CN",
    "gn:dem":183,
    "gn:feature_class":"P",
    "gn:feature_code":"PPL",
    "gn:name":"Lutai",
    "gn:population":0,
    "gn:timezone":"Asia/Shanghai",
    "iso:country":"CN",
    "name:deu_x_preferred":[
        "Lutai"
    ],
    "name:fas_x_preferred":[
        "\u0644\u0648\u062a\u0627\u06cc"
    ],
    "name:hun_x_preferred":[
        "Lutai"
    ],
    "name:zho_x_preferred":[
        "\u5362\u53f0"
    ],
    "name:zho_x_variant":[
        "\u82a6\u53f0\u9547"
    ],
    "wof:name":"Lutai",
    "wof:placetype":"locality"
},
  "geometry": {"coordinates":[112.72914,33.26778],"type":"Point"}
}