{
  "type": "Feature",
  "properties": {
    "gn:admin1_code":"4.0",
    "gn:asciiname":"Xixiang",
    "gn:country_code":"CN",
    "gn:dem":23,
    "gn:feature_class":"P",
    "gn:feature_code":"PPL",
    "gn:name":"Xixiang",
    "gn:population":0,
    "gn:timezone":"Asia/Shanghai",
    "iso:country":"CN",
    "name:und_x_variant":[
        "\u897f\u5df7"
    ],
    "name:zho_x_preferred":[
        "\u897f\u5df7"
    ],
    "wof:name":"Xixiang",
    "wof:placetype":"locality"
},
  "geometry": {"coordinates":[120.32916000000002,31.04292],"type":"Point"}
}