{
  "type": "Feature",
  "properties": {
    "gn:admin1_code":"15.0",
    "gn:asciiname":"Mengjiayuan",
    "gn:country_code":"CN",
    "gn:dem":1447,
    "gn:feature_class":"P",
    "gn:feature_code":"PPL",
    "gn:name":"Mengjiayuan",
    "gn:population":0,
    "gn:timezone":"Asia/Shanghai",
    "iso:country":"CN",
    "name:zho_x_preferred":[
        "\u8499\u5bb6\u586c"
    ],
    "wof:name":"Mengjiayuan",
    "wof:placetype":"locality"
},
  "geometry": {"coordinates":[107.202,35.7552],"type":"Point"}
}