{
  "type": "Feature",
  "properties": {
    "gn:admin1_code":"20.0",
    "gn:asciiname":"Deri Sike",
    "gn:country_code":"CN",
    "gn:dem":391,
    "gn:feature_class":"P",
    "gn:feature_code":"PPL",
    "gn:name":"Deri Sike",
    "gn:population":0,
    "gn:timezone":"Asia/Shanghai",
    "iso:country":"CN",
    "name:zho_x_preferred":[
        "\u5fb7\u65e5\u65af\u514b"
    ],
    "wof:name":"Deri Sike",
    "wof:placetype":"locality"
},
  "geometry": {"coordinates":[124.14803999999999,49.24634],"type":"Point"}
}