{
  "type": "Feature",
  "properties": {
    "gn:admin1_code":"19.0",
    "gn:asciiname":"Caijiagoucun",
    "gn:country_code":"CN",
    "gn:dem":96,
    "gn:feature_class":"P",
    "gn:feature_code":"PPL",
    "gn:name":"Caijiagoucun",
    "gn:population":0,
    "gn:timezone":"Asia/Shanghai",
    "iso:country":"CN",
    "name:zho_x_preferred":[
        "\u8521\u5bb6\u6c9f\u6751"
    ],
    "wof:name":"Caijiagoucun",
    "wof:placetype":"locality"
},
  "geometry": {"coordinates":[122.494,39.9437],"type":"Point"}
}