{
  "type": "Feature",
  "properties": {
    "gn:admin1_code":"21.0",
    "gn:asciiname":"Tanyangchang",
    "gn:country_code":"CN",
    "gn:dem":1512,
    "gn:feature_class":"P",
    "gn:feature_code":"PPLF",
    "gn:name":"Tanyangchang",
    "gn:population":0,
    "gn:timezone":"Asia/Shanghai",
    "iso:country":"CN",
    "name:zho_x_preferred":[
        "\u6ee9\u7f8a\u573a"
    ],
    "wof:name":"Tanyangchang",
    "wof:placetype":"locality"
},
  "geometry": {"coordinates":[106.907,37.4434],"type":"Point"}
}