{
  "type": "Feature",
  "properties": {
    "gn:admin1_code":"30.0",
    "gn:asciiname":"Qixiancun",
    "gn:country_code":"CN",
    "gn:dem":187,
    "gn:feature_class":"P",
    "gn:feature_code":"PPL",
    "gn:name":"Qixiancun",
    "gn:population":0,
    "gn:timezone":"Asia/Shanghai",
    "iso:country":"CN",
    "name:zho_x_preferred":[
        "\u4e03\u8d24\u6751"
    ],
    "wof:name":"Qixiancun",
    "wof:placetype":"locality"
},
  "geometry": {"coordinates":[116.01334,24.173],"type":"Point"}
}