{
  "type": "Feature",
  "properties": {
    "gn:admin1_code":"26.0",
    "gn:asciiname":"Zhenggou",
    "gn:country_code":"CN",
    "gn:dem":1616,
    "gn:feature_class":"P",
    "gn:feature_code":"PPL",
    "gn:name":"Zhenggou",
    "gn:population":0,
    "gn:timezone":"Asia/Shanghai",
    "iso:country":"CN",
    "name:und_x_variant":[
        "\u6b63\u6c9f"
    ],
    "wof:name":"Zhenggou",
    "wof:placetype":"locality"
},
  "geometry": {"coordinates":[106.91583,33.9652],"type":"Point"}
}