{
  "type": "Feature",
  "properties": {
    "gn:admin1_code":"1.0",
    "gn:asciiname":"Liloucun",
    "gn:country_code":"CN",
    "gn:dem":39,
    "gn:feature_class":"P",
    "gn:feature_code":"PPL",
    "gn:name":"Liloucun",
    "gn:population":0,
    "gn:timezone":"Asia/Shanghai",
    "iso:country":"CN",
    "name:zho_x_preferred":[
        "\u674e\u697c\u6751"
    ],
    "wof:name":"Liloucun",
    "wof:placetype":"locality"
},
  "geometry": {"coordinates":[115.5801,33.53742],"type":"Point"}
}