{
  "type": "Feature",
  "properties": {
    "gn:admin1_code":"18",
    "gn:asciiname":"Yujiawan",
    "gn:country_code":"CN",
    "gn:dem":1269,
    "gn:feature_class":"P",
    "gn:feature_code":"PPL",
    "gn:name":"Yujiawan",
    "gn:population":0,
    "gn:timezone":"Asia/Shanghai",
    "iso:country":"CN",
    "name:zho_x_preferred":[
        "\u4f59\u5bb6\u5f2f"
    ],
    "wof:name":"Yujiawan",
    "wof:placetype":"locality"
},
  "geometry": {"coordinates":[104.99299999999999,25.1458],"type":"Point"}
}