{
  "type": "Feature",
  "properties": {
    "gn:admin1_code":"14.0",
    "gn:asciiname":"Jielongtangcun",
    "gn:country_code":"CN",
    "gn:dem":4063,
    "gn:feature_class":"P",
    "gn:feature_code":"PPL",
    "gn:name":"Jielongtangcun",
    "gn:population":0,
    "gn:timezone":"Asia/Urumqi",
    "iso:country":"CN",
    "name:zho_x_preferred":[
        "\u7ed3\u9686\u5858\u6751"
    ],
    "wof:name":"Jielongtangcun",
    "wof:placetype":"locality"
},
  "geometry": {"coordinates":[94.60047,31.67329],"type":"Point"}
}