{
  "type": "Feature",
  "properties": {
    "gn:admin1_code":"29.0",
    "gn:asciiname":"Xiaxiaozhai",
    "gn:country_code":"CN",
    "gn:dem":1512,
    "gn:feature_class":"P",
    "gn:feature_code":"PPL",
    "gn:name":"Xiaxiaozhai",
    "gn:population":0,
    "gn:timezone":"Asia/Shanghai",
    "iso:country":"CN",
    "name:zho_x_preferred":[
        "\u4e0b\u5c0f\u5be8"
    ],
    "wof:name":"Xiaxiaozhai",
    "wof:placetype":"locality"
},
  "geometry": {"coordinates":[98.3758,25.092],"type":"Point"}
}