{
  "type": "Feature",
  "properties": {
    "gn:admin1_code":"32.0",
    "gn:asciiname":"Yangdashu",
    "gn:country_code":"CN",
    "gn:dem":1890,
    "gn:feature_class":"P",
    "gn:feature_code":"PPL",
    "gn:name":"Yangdashu",
    "gn:population":0,
    "gn:timezone":"Asia/Shanghai",
    "iso:country":"CN",
    "name:zho_x_preferred":[
        "\u6768\u5927\u6811"
    ],
    "wof:name":"Yangdashu",
    "wof:placetype":"locality"
},
  "geometry": {"coordinates":[102.06999999999999,27.9791],"type":"Point"}
}