{
  "type": "Feature",
  "properties": {
    "gn:admin1_code":"2.0",
    "gn:asciiname":"Lujia",
    "gn:country_code":"CN",
    "gn:dem":126,
    "gn:feature_class":"P",
    "gn:feature_code":"PPL",
    "gn:name":"L\u00fcjia",
    "gn:population":0,
    "gn:timezone":"Asia/Shanghai",
    "iso:country":"CN",
    "name:und_x_variant":[
        "\u5415\u5bb6"
    ],
    "name:zho_x_preferred":[
        "L\u00fcjia"
    ],
    "wof:name":"Lujia",
    "wof:placetype":"locality"
},
  "geometry": {"coordinates":[119.48826,30.11749],"type":"Point"}
}