{
  "type": "Feature",
  "properties": {
    "gn:admin1_code":"18",
    "gn:asciiname":"Tongziba",
    "gn:country_code":"CN",
    "gn:dem":964,
    "gn:feature_class":"P",
    "gn:feature_code":"PPL",
    "gn:name":"Tongziba",
    "gn:population":0,
    "gn:timezone":"Asia/Shanghai",
    "iso:country":"CN",
    "name:zho_x_preferred":[
        "\u6850\u5b50\u575d"
    ],
    "wof:name":"Tongziba",
    "wof:placetype":"locality"
},
  "geometry": {"coordinates":[107.10899999999999,27.2785],"type":"Point"}
}