{
  "type": "Feature",
  "properties": {
    "gn:admin1_code":"02",
    "gn:asciiname":"Shiqu",
    "gn:country_code":"CN",
    "gn:dem":6,
    "gn:feature_class":"P",
    "gn:feature_code":"PPL",
    "gn:name":"Shiqu",
    "gn:population":0,
    "gn:timezone":"Asia/Shanghai",
    "iso:country":"CN",
    "name:und_x_variant":[
        "Shih-chu",
        "Shiqu"
    ],
    "name:zho_x_preferred":[
        "\u77f3\u66f2"
    ],
    "wof:name":"Shiqu",
    "wof:placetype":"locality"
},
  "geometry": {"coordinates":[121.38828999999998,28.56228],"type":"Point"}
}