{
  "type": "Feature",
  "properties": {
    "gn:admin1_code":"14.0",
    "gn:asciiname":"Shebotang",
    "gn:country_code":"CN",
    "gn:dem":4247,
    "gn:feature_class":"P",
    "gn:feature_code":"PPL",
    "gn:name":"Shebotang",
    "gn:population":0,
    "gn:timezone":"Asia/Urumqi",
    "iso:country":"CN",
    "name:zho_x_preferred":[
        "\u820d\u6ce2\u5802"
    ],
    "wof:name":"Shebotang",
    "wof:placetype":"locality"
},
  "geometry": {"coordinates":[91.60713,29.74899000000001],"type":"Point"}
}