{
  "type": "Feature",
  "properties": {
    "gn:admin1_code":"19",
    "gn:asciiname":"Lizifang",
    "gn:cc2":"CN",
    "gn:country_code":"CN",
    "gn:dem":18,
    "gn:feature_class":"P",
    "gn:feature_code":"PPL",
    "gn:name":"Lizifang",
    "gn:population":0,
    "gn:timezone":"Asia/Shanghai",
    "iso:country":"CN",
    "name:und_x_variant":[
        "Li-tzu-fang",
        "Lizifang"
    ],
    "wof:name":"Lizifang",
    "wof:placetype":"locality"
},
  "geometry": {"coordinates":[123.43889,39.87861],"type":"Point"}
}