{
  "type": "Feature",
  "properties": {
    "gn:admin1_code":"11.0",
    "gn:asciiname":"Panjiapeng",
    "gn:country_code":"CN",
    "gn:dem":234,
    "gn:feature_class":"P",
    "gn:feature_code":"PPL",
    "gn:name":"Panjiapeng",
    "gn:population":0,
    "gn:timezone":"Asia/Shanghai",
    "iso:country":"CN",
    "name:zho_x_preferred":[
        "\u6f58\u5bb6\u68da"
    ],
    "wof:name":"Panjiapeng",
    "wof:placetype":"locality"
},
  "geometry": {"coordinates":[113.48907,28.49596],"type":"Point"}
}