{
  "type": "Feature",
  "properties": {
    "gn:admin1_code":"8.0",
    "gn:asciiname":"Jiujiangcun",
    "gn:country_code":"CN",
    "gn:dem":224,
    "gn:feature_class":"P",
    "gn:feature_code":"PPL",
    "gn:name":"Jiujiangcun",
    "gn:population":0,
    "gn:timezone":"Asia/Shanghai",
    "iso:country":"CN",
    "name:zho_x_preferred":[
        "\u4e5d\u6c5f\u6751"
    ],
    "wof:name":"Jiujiangcun",
    "wof:placetype":"locality"
},
  "geometry": {"coordinates":[128.16755000000001,45.03164],"type":"Point"}
}