{
  "type": "Feature",
  "properties": {
    "gn:admin1_code":"4.0",
    "gn:asciiname":"Maoshe",
    "gn:country_code":"CN",
    "gn:dem":3,
    "gn:feature_class":"P",
    "gn:feature_code":"PPL",
    "gn:name":"Maoshe",
    "gn:population":0,
    "gn:timezone":"Asia/Shanghai",
    "iso:country":"CN",
    "name:und_x_variant":[
        "\u8305\u538d"
    ],
    "name:zho_x_preferred":[
        "\u8305\u538d"
    ],
    "wof:name":"Maoshe",
    "wof:placetype":"locality"
},
  "geometry": {"coordinates":[120.97341000000002,31.41619],"type":"Point"}
}