{
  "type": "Feature",
  "properties": {
    "gn:admin1_code":"15.0",
    "gn:asciiname":"Zuitouya",
    "gn:country_code":"CN",
    "gn:dem":1345,
    "gn:feature_class":"P",
    "gn:feature_code":"PPL",
    "gn:name":"Zuitouya",
    "gn:population":0,
    "gn:timezone":"Asia/Shanghai",
    "iso:country":"CN",
    "name:zho_x_preferred":[
        "\u5480\u5934\u5d16"
    ],
    "wof:name":"Zuitouya",
    "wof:placetype":"locality"
},
  "geometry": {"coordinates":[107.509,35.8174],"type":"Point"}
}