{
  "type": "Feature",
  "properties": {
    "gn:admin1_code":"19.0",
    "gn:asciiname":"Sundagou",
    "gn:country_code":"CN",
    "gn:dem":116,
    "gn:feature_class":"P",
    "gn:feature_code":"PPL",
    "gn:name":"Sundagou",
    "gn:population":0,
    "gn:timezone":"Asia/Shanghai",
    "iso:country":"CN",
    "name:und_x_variant":[
        "\u5b59\u5927\u6c9f"
    ],
    "name:zho_x_preferred":[
        "\u5b59\u5927\u6c9f"
    ],
    "wof:name":"Sundagou",
    "wof:placetype":"locality"
},
  "geometry": {"coordinates":[122.81095000000001,39.92358],"type":"Point"}
}