{
  "type": "Feature",
  "properties": {
    "gn:admin1_code":"14.0",
    "gn:asciiname":"Kawaxia",
    "gn:country_code":"CN",
    "gn:dem":4362,
    "gn:feature_class":"P",
    "gn:feature_code":"PPL",
    "gn:name":"Kawaxia",
    "gn:population":0,
    "gn:timezone":"Asia/Urumqi",
    "iso:country":"CN",
    "name:zho_x_preferred":[
        "\u5361\u5a03\u8f96"
    ],
    "wof:name":"Kawaxia",
    "wof:placetype":"locality"
},
  "geometry": {"coordinates":[87.18519999999999,28.6709],"type":"Point"}
}