{
  "type": "Feature",
  "properties": {
    "gn:admin1_code":"4.0",
    "gn:asciiname":"Zhenyou",
    "gn:country_code":"CN",
    "gn:dem":19,
    "gn:feature_class":"P",
    "gn:feature_code":"PPL",
    "gn:name":"Zhenyou",
    "gn:population":0,
    "gn:timezone":"Asia/Shanghai",
    "iso:country":"CN",
    "name:zho_x_preferred":[
        "\u632f\u53cb"
    ],
    "wof:name":"Zhenyou",
    "wof:placetype":"locality"
},
  "geometry": {"coordinates":[118.45099999999999,33.9353],"type":"Point"}
}