{
  "type": "Feature",
  "properties": {
    "gn:admin1_code":"03",
    "gn:asciiname":"Gushi",
    "gn:country_code":"CN",
    "gn:dem":170,
    "gn:feature_class":"P",
    "gn:feature_code":"PPLA4",
    "gn:name":"Gushi",
    "gn:population":0,
    "gn:timezone":"Asia/Shanghai",
    "iso:country":"CN",
    "name:ceb_x_preferred":[
        "Gushi"
    ],
    "name:nld_x_preferred":[
        "Gushi"
    ],
    "name:und_x_variant":[
        "Ku-shih",
        "\u53e4\u5e02",
        "Gushi Zhen",
        "\u53e4\u5e02\u9547"
    ],
    "wof:name":"Gushi",
    "wof:placetype":"locality"
},
  "geometry": {"coordinates":[114.14797,29.06127],"type":"Point"}
}