{
  "type": "Feature",
  "properties": {
    "gn:admin1_code":"33.0",
    "gn:asciiname":"Guojia Diaolou",
    "gn:country_code":"CN",
    "gn:dem":583,
    "gn:feature_class":"P",
    "gn:feature_code":"PPL",
    "gn:name":"Guojia Diaolou",
    "gn:population":0,
    "gn:timezone":"Asia/Shanghai",
    "iso:country":"CN",
    "name:zho_x_preferred":[
        "\u90ed\u5bb6\u7889\u697c"
    ],
    "wof:name":"Guojia Diaolou",
    "wof:placetype":"locality"
},
  "geometry": {"coordinates":[107.73839,30.5114],"type":"Point"}
}