{
  "type": "Feature",
  "properties": {
    "gn:admin1_code":"3.0",
    "gn:asciiname":"Wujiayuan",
    "gn:country_code":"CN",
    "gn:dem":139,
    "gn:feature_class":"P",
    "gn:feature_code":"PPL",
    "gn:name":"Wujiayuan",
    "gn:population":0,
    "gn:timezone":"Asia/Shanghai",
    "iso:country":"CN",
    "name:und_x_variant":[
        "\u5434\u5bb6\u6e90"
    ],
    "wof:name":"Wujiayuan",
    "wof:placetype":"locality"
},
  "geometry": {"coordinates":[116.55296,27.11127],"type":"Point"}
}