{
  "type": "Feature",
  "properties": {
    "gn:admin1_code":"24",
    "gn:asciiname":"Gaoqiangkuang",
    "gn:country_code":"CN",
    "gn:dem":1309,
    "gn:feature_class":"P",
    "gn:feature_code":"PPL",
    "gn:name":"Gaoqiangkuang",
    "gn:population":0,
    "gn:timezone":"Asia/Shanghai",
    "iso:country":"CN",
    "name:und_x_variant":[
        "Kao-ch\u2019iang-k\u2019uang",
        "Gaoqiangkuang",
        "\u9ad8\u5899\u6846"
    ],
    "wof:name":"Gaoqiangkuang",
    "wof:placetype":"locality"
},
  "geometry": {"coordinates":[112.38457,40.07237],"type":"Point"}
}