{
  "type": "Feature",
  "properties": {
    "gn:admin1_code":"33.0",
    "gn:asciiname":"Yanwan",
    "gn:country_code":"CN",
    "gn:dem":702,
    "gn:feature_class":"P",
    "gn:feature_code":"PPL",
    "gn:name":"Yanwan",
    "gn:population":0,
    "gn:timezone":"Asia/Shanghai",
    "iso:country":"CN",
    "name:zho_x_preferred":[
        "\u5830\u5f2f"
    ],
    "wof:name":"Yanwan",
    "wof:placetype":"locality"
},
  "geometry": {"coordinates":[108.53519,31.44325],"type":"Point"}
}