{
  "type": "Feature",
  "properties": {
    "gn:admin1_code":"24.0",
    "gn:asciiname":"Xingjiashan",
    "gn:country_code":"CN",
    "gn:dem":1084,
    "gn:feature_class":"P",
    "gn:feature_code":"PPL",
    "gn:name":"Xingjiashan",
    "gn:population":0,
    "gn:timezone":"Asia/Shanghai",
    "iso:country":"CN",
    "name:zho_x_preferred":[
        "\u90a2\u5bb6\u5c71"
    ],
    "wof:name":"Xingjiashan",
    "wof:placetype":"locality"
},
  "geometry": {"coordinates":[112.47617,38.44211],"type":"Point"}
}