{
  "type": "Feature",
  "properties": {
    "gn:admin1_code":"20.0",
    "gn:asciiname":"Gongjiagou",
    "gn:country_code":"CN",
    "gn:dem":325,
    "gn:feature_class":"P",
    "gn:feature_code":"PPL",
    "gn:name":"Gongjiagou",
    "gn:population":0,
    "gn:timezone":"Asia/Shanghai",
    "iso:country":"CN",
    "name:zho_x_preferred":[
        "\u5bab\u5bb6\u6c9f"
    ],
    "wof:name":"Gongjiagou",
    "wof:placetype":"locality"
},
  "geometry": {"coordinates":[123.50387000000001,48.46342],"type":"Point"}
}