{
  "type": "Feature",
  "properties": {
    "gn:admin1_code":"18.0",
    "gn:asciiname":"Dengjiapeng",
    "gn:country_code":"CN",
    "gn:dem":943,
    "gn:feature_class":"P",
    "gn:feature_code":"PPL",
    "gn:name":"Dengjiapeng",
    "gn:population":0,
    "gn:timezone":"Asia/Shanghai",
    "iso:country":"CN",
    "name:zho_x_preferred":[
        "\u9093\u5bb6\u68da"
    ],
    "wof:name":"Dengjiapeng",
    "wof:placetype":"locality"
},
  "geometry": {"coordinates":[108.51000000000001,27.6754],"type":"Point"}
}