{
  "type": "Feature",
  "properties": {
    "gn:admin1_code":"26.0",
    "gn:asciiname":"Qipocun",
    "gn:country_code":"CN",
    "gn:dem":939,
    "gn:feature_class":"P",
    "gn:feature_code":"PPL",
    "gn:name":"Qipocun",
    "gn:population":0,
    "gn:timezone":"Asia/Shanghai",
    "iso:country":"CN",
    "name:zho_x_preferred":[
        "\u9f50\u5761\u6751"
    ],
    "wof:name":"Qipocun",
    "wof:placetype":"locality"
},
  "geometry": {"coordinates":[110.28816,34.0415],"type":"Point"}
}