{
  "type": "Feature",
  "properties": {
    "gn:admin1_code":"16.0",
    "gn:asciiname":"Gaolao",
    "gn:country_code":"CN",
    "gn:dem":601,
    "gn:feature_class":"P",
    "gn:feature_code":"PPL",
    "gn:name":"Gaolao",
    "gn:population":0,
    "gn:timezone":"Asia/Shanghai",
    "iso:country":"CN",
    "name:fra_x_preferred":[
        "Gaolao"
    ],
    "name:kan_x_preferred":[
        "\u0c97\u0ccc\u0cb3\u0cb5\u0ccd"
    ],
    "name:tam_x_preferred":[
        "\u0b95\u0bcc\u0bb2\u0bb5\u0bcd \u0bae\u0bbe\u0b9f\u0bc1"
    ],
    "name:zho_x_preferred":[
        "\u544a\u52b3"
    ],
    "wof:name":"Gaolao",
    "wof:placetype":"locality"
},
  "geometry": {"coordinates":[106.874,23.6145],"type":"Point"}
}