{
  "type": "Feature",
  "properties": {
    "gn:admin1_code":"5.0",
    "gn:asciiname":"Kaixian Linchang",
    "gn:country_code":"CN",
    "gn:dem":329,
    "gn:feature_class":"P",
    "gn:feature_code":"PPLF",
    "gn:name":"Kaixian Linchang",
    "gn:population":0,
    "gn:timezone":"Asia/Shanghai",
    "iso:country":"CN",
    "name:und_x_variant":[
        "\u5f00\u7ea4\u6797\u573a"
    ],
    "wof:name":"Kaixian Linchang",
    "wof:placetype":"locality"
},
  "geometry": {"coordinates":[129.72723999999999,42.63451],"type":"Point"}
}