{
  "type": "Feature",
  "properties": {
    "gn:admin1_code":"8.0",
    "gn:asciiname":"Chaoyangshancun",
    "gn:country_code":"CN",
    "gn:dem":189,
    "gn:feature_class":"P",
    "gn:feature_code":"PPL",
    "gn:name":"Chaoyangshancun",
    "gn:population":0,
    "gn:timezone":"Asia/Shanghai",
    "iso:country":"CN",
    "name:zho_x_preferred":[
        "\u671d\u9633\u5c71\u6751"
    ],
    "wof:name":"Chaoyangshancun",
    "wof:placetype":"locality"
},
  "geometry": {"coordinates":[131.57366999999999,46.0035],"type":"Point"}
}