{
  "type": "Feature",
  "properties": {
    "gn:admin1_code":"29.0",
    "gn:asciiname":"Daoduishan",
    "gn:country_code":"CN",
    "gn:dem":2114,
    "gn:feature_class":"P",
    "gn:feature_code":"PPL",
    "gn:name":"Daoduishan",
    "gn:population":0,
    "gn:timezone":"Asia/Shanghai",
    "iso:country":"CN",
    "name:zho_x_preferred":[
        "\u7a3b\u5806\u5c71"
    ],
    "wof:name":"Daoduishan",
    "wof:placetype":"locality"
},
  "geometry": {"coordinates":[103.988,25.4562],"type":"Point"}
}