{
  "type": "Feature",
  "properties": {
    "gn:admin1_code":"30",
    "gn:asciiname":"Yangtanggang",
    "gn:country_code":"CN",
    "gn:dem":144,
    "gn:feature_class":"P",
    "gn:feature_code":"PPL",
    "gn:name":"Yangtanggang",
    "gn:population":0,
    "gn:timezone":"Asia/Shanghai",
    "iso:country":"CN",
    "name:und_x_variant":[
        "\u6d0b\u5858\u5c97"
    ],
    "wof:name":"Yangtanggang",
    "wof:placetype":"locality"
},
  "geometry": {"coordinates":[114.76828999999999,24.21306],"type":"Point"}
}