{
  "type": "Feature",
  "properties": {
    "gn:admin1_code":"18",
    "gn:asciiname":"Yanghuogeng",
    "gn:country_code":"CN",
    "gn:dem":935,
    "gn:feature_class":"P",
    "gn:feature_code":"PPL",
    "gn:name":"Yanghuogeng",
    "gn:population":0,
    "gn:timezone":"Asia/Shanghai",
    "iso:country":"CN",
    "name:zho_x_preferred":[
        "\u626c\u706b\u57c2"
    ],
    "wof:name":"Yanghuogeng",
    "wof:placetype":"locality"
},
  "geometry": {"coordinates":[105.754,28.3396],"type":"Point"}
}