{
  "type": "Feature",
  "properties": {
    "gn:admin1_code":"29.0",
    "gn:asciiname":"Laojiezi",
    "gn:country_code":"CN",
    "gn:dem":1107,
    "gn:feature_class":"P",
    "gn:feature_code":"PPL",
    "gn:name":"Laojiezi",
    "gn:population":0,
    "gn:timezone":"Asia/Shanghai",
    "iso:country":"CN",
    "name:zho_x_preferred":[
        "\u8001\u8857\u5b50"
    ],
    "wof:name":"Laojiezi",
    "wof:placetype":"locality"
},
  "geometry": {"coordinates":[100.485,23.7145],"type":"Point"}
}