{
  "type": "Feature",
  "properties": {
    "gn:admin1_code":"4.0",
    "gn:asciiname":"Qushencun",
    "gn:country_code":"CN",
    "gn:dem":2,
    "gn:feature_class":"P",
    "gn:feature_code":"PPL",
    "gn:name":"Qushencun",
    "gn:population":0,
    "gn:timezone":"Asia/Shanghai",
    "iso:country":"CN",
    "name:zho_x_preferred":[
        "\u77bf\u6c88\u6751"
    ],
    "wof:name":"Qushencun",
    "wof:placetype":"locality"
},
  "geometry": {"coordinates":[120.05328,32.9823],"type":"Point"}
}