{
  "type": "Feature",
  "properties": {
    "gn:admin1_code":"26.0",
    "gn:asciiname":"Xingjiagou",
    "gn:country_code":"CN",
    "gn:dem":1341,
    "gn:feature_class":"P",
    "gn:feature_code":"PPL",
    "gn:name":"Xingjiagou",
    "gn:population":0,
    "gn:timezone":"Asia/Shanghai",
    "iso:country":"CN",
    "name:zho_x_preferred":[
        "\u90a2\u5bb6\u6c9f"
    ],
    "wof:name":"Xingjiagou",
    "wof:placetype":"locality"
},
  "geometry": {"coordinates":[109.76615,35.75844],"type":"Point"}
}