{
  "type": "Feature",
  "properties": {
    "gn:admin1_code":"4.0",
    "gn:asciiname":"Daxiangshang",
    "gn:country_code":"CN",
    "gn:dem":8,
    "gn:feature_class":"P",
    "gn:feature_code":"PPL",
    "gn:name":"Daxiangshang",
    "gn:population":0,
    "gn:timezone":"Asia/Shanghai",
    "iso:country":"CN",
    "name:und_x_variant":[
        "\u5927\u5df7\u4e0a"
    ],
    "name:zho_x_preferred":[
        "\u5927\u5df7\u4e0a"
    ],
    "wof:name":"Daxiangshang",
    "wof:placetype":"locality"
},
  "geometry": {"coordinates":[120.15428,31.57492],"type":"Point"}
}