{
  "type": "Feature",
  "properties": {
    "gn:admin1_code":"29.0",
    "gn:asciiname":"Xiayunshanzhai",
    "gn:country_code":"CN",
    "gn:dem":1522,
    "gn:feature_class":"P",
    "gn:feature_code":"PPL",
    "gn:name":"Xiayunshanzhai",
    "gn:population":0,
    "gn:timezone":"Asia/Shanghai",
    "iso:country":"CN",
    "name:zho_x_preferred":[
        "\u4e0b\u4e91\u5c71\u5be8"
    ],
    "wof:name":"Xiayunshanzhai",
    "wof:placetype":"locality"
},
  "geometry": {"coordinates":[99.7859,22.7167],"type":"Point"}
}