{
  "type": "Feature",
  "properties": {
    "gn:admin1_code":"4.0",
    "gn:asciiname":"Jindong",
    "gn:country_code":"CN",
    "gn:dem":4,
    "gn:feature_class":"P",
    "gn:feature_code":"PPL",
    "gn:name":"Jindong",
    "gn:population":0,
    "gn:timezone":"Asia/Shanghai",
    "iso:country":"CN",
    "name:zho_x_preferred":[
        "\u91d1\u4e1c"
    ],
    "wof:name":"Jindong",
    "wof:placetype":"locality"
},
  "geometry": {"coordinates":[120.54998999999999,32.85044],"type":"Point"}
}