{
  "type": "Feature",
  "properties": {
    "gn:admin1_code":"4.0",
    "gn:asciiname":"Huangjiachi",
    "gn:country_code":"CN",
    "gn:dem":2,
    "gn:feature_class":"P",
    "gn:feature_code":"PPL",
    "gn:name":"Huangjiachi",
    "gn:population":0,
    "gn:timezone":"Asia/Shanghai",
    "iso:country":"CN",
    "name:zho_x_preferred":[
        "Huangjiachi"
    ],
    "name:zho_x_variant":[
        "\u9ec4\u5bb6\u6c60"
    ],
    "wof:name":"Huangjiachi",
    "wof:placetype":"locality"
},
  "geometry": {"coordinates":[119.48453000000001,34.40597],"type":"Point"}
}