{
  "type": "Feature",
  "properties": {
    "gn:admin1_code":"4.0",
    "gn:asciiname":"Wangyaozhuang",
    "gn:country_code":"CN",
    "gn:dem":-1,
    "gn:feature_class":"P",
    "gn:feature_code":"PPL",
    "gn:name":"Wangyaozhuang",
    "gn:population":0,
    "gn:timezone":"Asia/Shanghai",
    "iso:country":"CN",
    "name:zho_x_preferred":[
        "Wangyaozhuang"
    ],
    "name:zho_x_variant":[
        "\u6c6a\u8170\u5e84"
    ],
    "wof:name":"Wangyaozhuang",
    "wof:placetype":"locality"
},
  "geometry": {"coordinates":[119.67753,34.31258],"type":"Point"}
}