{
  "type": "Feature",
  "properties": {
    "gn:admin1_code":"13",
    "gn:asciiname":"Jianggale Huoyila",
    "gn:country_code":"CN",
    "gn:dem":1328,
    "gn:feature_class":"P",
    "gn:feature_code":"PPL",
    "gn:name":"Jianggale Huoyila",
    "gn:population":0,
    "gn:timezone":"Asia/Shanghai",
    "iso:country":"CN",
    "name:und_x_variant":[
        "\u6c5f\u560e\u52d2\u970d\u4f0a\u62c9"
    ],
    "wof:name":"Jianggale Huoyila",
    "wof:placetype":"locality"
},
  "geometry": {"coordinates":[77.11839999999999,38.15187],"type":"Point"}
}