{
  "type": "Feature",
  "properties": {
    "gn:admin1_code":"24.0",
    "gn:asciiname":"Dongxinchangcun",
    "gn:country_code":"CN",
    "gn:dem":366,
    "gn:feature_class":"P",
    "gn:feature_code":"PPL",
    "gn:name":"Dongxinchangcun",
    "gn:population":0,
    "gn:timezone":"Asia/Shanghai",
    "iso:country":"CN",
    "name:zho_x_preferred":[
        "\u4e1c\u4fe1\u660c\u6751"
    ],
    "wof:name":"Dongxinchangcun",
    "wof:placetype":"locality"
},
  "geometry": {"coordinates":[110.48026000000002,34.95749],"type":"Point"}
}