{
  "type": "Feature",
  "properties": {
    "gn:admin1_code":"1.0",
    "gn:asciiname":"Zhaotangcun",
    "gn:country_code":"CN",
    "gn:dem":32,
    "gn:feature_class":"P",
    "gn:feature_code":"PPL",
    "gn:name":"Zhaotangcun",
    "gn:population":0,
    "gn:timezone":"Asia/Shanghai",
    "iso:country":"CN",
    "name:zho_x_preferred":[
        "\u8d75\u5858\u6751"
    ],
    "wof:name":"Zhaotangcun",
    "wof:placetype":"locality"
},
  "geometry": {"coordinates":[116.4353,33.45148],"type":"Point"}
}