{
  "type": "Feature",
  "properties": {
    "gn:admin1_code":"11.0",
    "gn:asciiname":"Duping",
    "gn:country_code":"CN",
    "gn:dem":341,
    "gn:feature_class":"P",
    "gn:feature_code":"PPL",
    "gn:name":"Duping",
    "gn:population":0,
    "gn:timezone":"Asia/Shanghai",
    "iso:country":"CN",
    "name:und_x_variant":[
        "\u675c\u576a"
    ],
    "wof:name":"Duping",
    "wof:placetype":"locality"
},
  "geometry": {"coordinates":[111.06816999999999,29.12928],"type":"Point"}
}