{
  "type": "Feature",
  "properties": {
    "gn:admin1_code":"16.0",
    "gn:asciiname":"Yaoshan",
    "gn:country_code":"CN",
    "gn:dem":67,
    "gn:feature_class":"P",
    "gn:feature_code":"PPL",
    "gn:name":"Yaoshan",
    "gn:population":0,
    "gn:timezone":"Asia/Shanghai",
    "iso:country":"CN",
    "name:ceb_x_preferred":[
        "Yaoshan"
    ],
    "name:swe_x_preferred":[
        "Yaoshan"
    ],
    "name:zho_x_preferred":[
        "\u59da\u5c71"
    ],
    "wof:name":"Yaoshan",
    "wof:placetype":"locality"
},
  "geometry": {"coordinates":[109.371,23.1682],"type":"Point"}
}