{
  "type": "Feature",
  "properties": {
    "gn:admin1_code":"7.0",
    "gn:asciiname":"Yaoxia",
    "gn:country_code":"CN",
    "gn:dem":278,
    "gn:feature_class":"P",
    "gn:feature_code":"PPL",
    "gn:name":"Yaoxia",
    "gn:population":0,
    "gn:timezone":"Asia/Shanghai",
    "iso:country":"CN",
    "name:und_x_variant":[
        "\u7a91\u4e0b"
    ],
    "name:zho_x_preferred":[
        "\u7a91\u4e0b"
    ],
    "wof:name":"Yaoxia",
    "wof:placetype":"locality"
},
  "geometry": {"coordinates":[116.39758,25.61924],"type":"Point"}
}