{
  "type": "Feature",
  "properties": {
    "gn:admin1_code":"29.0",
    "gn:asciiname":"Xiaoduogu Dacun",
    "gn:country_code":"CN",
    "gn:dem":2258,
    "gn:feature_class":"P",
    "gn:feature_code":"PPL",
    "gn:name":"Xiaoduogu Dacun",
    "gn:population":0,
    "gn:timezone":"Asia/Shanghai",
    "iso:country":"CN",
    "name:zho_x_preferred":[
        "\u5c0f\u591a\u59d1\u5927\u6751"
    ],
    "wof:name":"Xiaoduogu Dacun",
    "wof:placetype":"locality"
},
  "geometry": {"coordinates":[103.15600000000001,25.6132],"type":"Point"}
}