{
  "type": "Feature",
  "properties": {
    "gn:admin1_code":"12.0",
    "gn:asciiname":"Daijia Dashan",
    "gn:country_code":"CN",
    "gn:dem":36,
    "gn:feature_class":"P",
    "gn:feature_code":"PPL",
    "gn:name":"Daijia Dashan",
    "gn:population":0,
    "gn:timezone":"Asia/Shanghai",
    "iso:country":"CN",
    "name:zho_x_preferred":[
        "\u6234\u5bb6\u5927\u5c71"
    ],
    "wof:name":"Daijia Dashan",
    "wof:placetype":"locality"
},
  "geometry": {"coordinates":[112.16567999999999,29.94708],"type":"Point"}
}