{
  "type": "Feature",
  "properties": {
    "gn:admin1_code":"2.0",
    "gn:asciiname":"Gedi",
    "gn:country_code":"CN",
    "gn:dem":83,
    "gn:feature_class":"P",
    "gn:feature_code":"PPL",
    "gn:name":"Gedi",
    "gn:population":0,
    "gn:timezone":"Asia/Shanghai",
    "iso:country":"CN",
    "name:ceb_x_preferred":[
        "Gedi"
    ],
    "name:ita_x_preferred":[
        "Gedi"
    ],
    "name:swe_x_preferred":[
        "Gedi"
    ],
    "name:zho_x_preferred":[
        "\u9601\u5e95"
    ],
    "wof:name":"Gedi",
    "wof:placetype":"locality"
},
  "geometry": {"coordinates":[118.58887,28.9272],"type":"Point"}
}