{
  "type": "Feature",
  "properties": {
    "gn:admin1_code":"1.0",
    "gn:asciiname":"Jiangtangcun",
    "gn:country_code":"CN",
    "gn:dem":25,
    "gn:feature_class":"P",
    "gn:feature_code":"PPL",
    "gn:name":"Jiangtangcun",
    "gn:population":0,
    "gn:timezone":"Asia/Shanghai",
    "iso:country":"CN",
    "name:zho_x_preferred":[
        "\u6c5f\u5858\u6751"
    ],
    "wof:name":"Jiangtangcun",
    "wof:placetype":"locality"
},
  "geometry": {"coordinates":[117.31073000000001,31.35474],"type":"Point"}
}