{
  "type": "Feature",
  "properties": {
    "gn:admin1_code":"30",
    "gn:asciiname":"Zhaizaicun",
    "gn:country_code":"CN",
    "gn:dem":19,
    "gn:feature_class":"P",
    "gn:feature_code":"PPL",
    "gn:name":"Zhaizaicun",
    "gn:population":0,
    "gn:timezone":"Asia/Urumqi",
    "iso:country":"CN",
    "name:zho_x_preferred":[
        "\u5b85\u4ed4\u6751"
    ],
    "wof:name":"Zhaizaicun",
    "wof:placetype":"locality"
},
  "geometry": {"coordinates":[109.93263,20.99516],"type":"Point"}
}