{
  "type": "Feature",
  "properties": {
    "gn:admin1_code":"12.0",
    "gn:asciiname":"Zhangguan",
    "gn:country_code":"CN",
    "gn:dem":1067,
    "gn:feature_class":"P",
    "gn:feature_code":"PPL",
    "gn:name":"Zhangguan",
    "gn:population":0,
    "gn:timezone":"Asia/Shanghai",
    "iso:country":"CN",
    "name:zho_x_preferred":[
        "Zhangguan"
    ],
    "name:zho_x_variant":[
        "\u5f20\u5b98"
    ],
    "wof:name":"Zhangguan",
    "wof:placetype":"locality"
},
  "geometry": {"coordinates":[109.25091999999999,29.83612],"type":"Point"}
}