{
  "type": "Feature",
  "properties": {
    "gn:admin1_code":"3.0",
    "gn:asciiname":"Gangxia",
    "gn:country_code":"CN",
    "gn:dem":33,
    "gn:feature_class":"P",
    "gn:feature_code":"PPL",
    "gn:name":"Gangxia",
    "gn:population":0,
    "gn:timezone":"Asia/Shanghai",
    "iso:country":"CN",
    "name:und_x_variant":[
        "\u6e2f\u4e0b"
    ],
    "wof:name":"Gangxia",
    "wof:placetype":"locality"
},
  "geometry": {"coordinates":[116.2612,29.43233],"type":"Point"}
}