{
  "type": "Feature",
  "properties": {
    "gn:admin1_code":"32.0",
    "gn:asciiname":"Siji",
    "gn:country_code":"CN",
    "gn:dem":2458,
    "gn:feature_class":"P",
    "gn:feature_code":"PPL",
    "gn:name":"Siji",
    "gn:population":0,
    "gn:timezone":"Asia/Shanghai",
    "iso:country":"CN",
    "name:zho_x_preferred":[
        "\u65af\u57fa"
    ],
    "name:zho_x_variant":[
        "\u53f8\u57fa"
    ],
    "wof:name":"Siji",
    "wof:placetype":"locality"
},
  "geometry": {"coordinates":[102.59099999999999,28.4996],"type":"Point"}
}