{
  "type": "Feature",
  "properties": {
    "gn:admin1_code":"5.0",
    "gn:asciiname":"Caijiayingcun",
    "gn:country_code":"CN",
    "gn:dem":276,
    "gn:feature_class":"P",
    "gn:feature_code":"PPL",
    "gn:name":"Caijiayingcun",
    "gn:population":0,
    "gn:timezone":"Asia/Shanghai",
    "iso:country":"CN",
    "name:zho_x_preferred":[
        "\u8521\u5bb6\u8425\u6751"
    ],
    "wof:name":"Caijiayingcun",
    "wof:placetype":"locality"
},
  "geometry": {"coordinates":[126.88997999999999,43.40123],"type":"Point"}
}