{
  "type": "Feature",
  "properties": {
    "gn:admin1_code":"19.0",
    "gn:asciiname":"Dazhaizicun",
    "gn:country_code":"CN",
    "gn:dem":136,
    "gn:feature_class":"P",
    "gn:feature_code":"PPL",
    "gn:name":"Dazhaizicun",
    "gn:population":0,
    "gn:timezone":"Asia/Shanghai",
    "iso:country":"CN",
    "name:zho_x_preferred":[
        "\u5927\u5be8\u5b50\u6751"
    ],
    "wof:name":"Dazhaizicun",
    "wof:placetype":"locality"
},
  "geometry": {"coordinates":[124.30200000000001,42.2515],"type":"Point"}
}