{
  "type": "Feature",
  "properties": {
    "gn:admin1_code":"32.0",
    "gn:asciiname":"Ximusiman",
    "gn:country_code":"CN",
    "gn:dem":3890,
    "gn:feature_class":"P",
    "gn:feature_code":"PPL",
    "gn:name":"Ximusiman",
    "gn:population":0,
    "gn:timezone":"Asia/Shanghai",
    "iso:country":"CN",
    "name:zho_x_preferred":[
        "\u6089\u6728\u65af\u66fc"
    ],
    "wof:name":"Ximusiman",
    "wof:placetype":"locality"
},
  "geometry": {"coordinates":[102.14718999999999,31.67554],"type":"Point"}
}