{
  "type": "Feature",
  "properties": {
    "gn:admin1_code":"5.0",
    "gn:asciiname":"Moru Gangzi",
    "gn:country_code":"CN",
    "gn:dem":190,
    "gn:feature_class":"P",
    "gn:feature_code":"PPL",
    "gn:name":"Moru Gangzi",
    "gn:population":0,
    "gn:timezone":"Asia/Shanghai",
    "iso:country":"CN",
    "name:zho_x_preferred":[
        "\u8611\u8339\u5c97\u5b50"
    ],
    "wof:name":"Moru Gangzi",
    "wof:placetype":"locality"
},
  "geometry": {"coordinates":[126.54882000000001,45.10162],"type":"Point"}
}