{
  "type": "Feature",
  "properties": {
    "gn:admin1_code":"32.0",
    "gn:asciiname":"Ranguo",
    "gn:country_code":"CN",
    "gn:dem":4044,
    "gn:feature_class":"P",
    "gn:feature_code":"PPL",
    "gn:name":"Ranguo",
    "gn:population":0,
    "gn:timezone":"Asia/Shanghai",
    "iso:country":"CN",
    "name:zho_x_preferred":[
        "\u7136\u679c"
    ],
    "wof:name":"Ranguo",
    "wof:placetype":"locality"
},
  "geometry": {"coordinates":[100.607,29.9111],"type":"Point"}
}