{
  "type": "Feature",
  "properties": {
    "gn:admin1_code":"8.0",
    "gn:asciiname":"Xinyicun",
    "gn:country_code":"CN",
    "gn:dem":114,
    "gn:feature_class":"P",
    "gn:feature_code":"PPL",
    "gn:name":"Xinyicun",
    "gn:population":0,
    "gn:timezone":"Asia/Shanghai",
    "iso:country":"CN",
    "name:zho_x_preferred":[
        "\u4fe1\u4e49\u6751"
    ],
    "wof:name":"Xinyicun",
    "wof:placetype":"locality"
},
  "geometry": {"coordinates":[130.19132999999999,46.40962],"type":"Point"}
}