{
  "type": "Feature",
  "properties": {
    "gn:admin1_code":"16",
    "gn:asciiname":"Meixi",
    "gn:cc2":"CN",
    "gn:country_code":"CN",
    "gn:dem":372,
    "gn:feature_class":"P",
    "gn:feature_code":"PPL",
    "gn:name":"Meixi",
    "gn:population":0,
    "gn:timezone":"Asia/Shanghai",
    "iso:country":"CN",
    "name:und_x_variant":[
        "Mei-hsi",
        "Mei-ch\u2019i-k\u2019ou",
        "Meixi"
    ],
    "wof:name":"Meixi",
    "wof:placetype":"locality"
},
  "geometry": {"coordinates":[110.73083,26.22],"type":"Point"}
}