{
  "type": "Feature",
  "properties": {
    "gn:admin1_code":"8.0",
    "gn:asciiname":"Xingfu",
    "gn:country_code":"CN",
    "gn:dem":227,
    "gn:feature_class":"P",
    "gn:feature_code":"PPL",
    "gn:name":"Xingfu",
    "gn:population":0,
    "gn:timezone":"Asia/Shanghai",
    "iso:country":"CN",
    "name:ceb_x_preferred":[
        "Xingfu"
    ],
    "name:deu_x_preferred":[
        "Xingfu"
    ],
    "name:jpn_x_preferred":[
        "\u5e78\u798f"
    ],
    "name:kor_x_preferred":[
        "\ud589\ubcf5"
    ],
    "name:swe_x_preferred":[
        "Xingfu"
    ],
    "name:zho_x_preferred":[
        "\u5e78\u798f"
    ],
    "wof:name":"Xingfu",
    "wof:placetype":"locality"
},
  "geometry": {"coordinates":[126.93877999999999,47.85166],"type":"Point"}
}