{
  "type": "Feature",
  "properties": {
    "gn:admin1_code":"16.0",
    "gn:asciiname":"Bingqiu",
    "gn:country_code":"CN",
    "gn:dem":11,
    "gn:feature_class":"P",
    "gn:feature_code":"PPL",
    "gn:name":"Bingqiu",
    "gn:population":0,
    "gn:timezone":"Asia/Shanghai",
    "iso:country":"CN",
    "name:zho_x_preferred":[
        "\u5175\u79cb"
    ],
    "wof:name":"Bingqiu",
    "wof:placetype":"locality"
},
  "geometry": {"coordinates":[109.235,21.7584],"type":"Point"}
}