{
  "type": "Feature",
  "properties": {
    "gn:admin1_code":"29",
    "gn:asciiname":"Washimi",
    "gn:country_code":"CN",
    "gn:dem":2056,
    "gn:feature_class":"P",
    "gn:feature_code":"PPL",
    "gn:name":"Washimi",
    "gn:population":0,
    "gn:timezone":"Asia/Shanghai",
    "iso:country":"CN",
    "name:zho_x_preferred":[
        "\u74e6\u4ec0\u7c73"
    ],
    "wof:name":"Washimi",
    "wof:placetype":"locality"
},
  "geometry": {"coordinates":[101.116,25.0081],"type":"Point"}
}