{
  "type": "Feature",
  "properties": {
    "gn:admin1_code":"6.0",
    "gn:asciiname":"Gangca",
    "gn:country_code":"CN",
    "gn:dem":4227,
    "gn:feature_class":"P",
    "gn:feature_code":"PPL",
    "gn:name":"Gangca",
    "gn:population":0,
    "gn:timezone":"Asia/Urumqi",
    "iso:country":"CN",
    "name:zho_x_preferred":[
        "\u521a\u5bdf"
    ],
    "wof:name":"Gangca",
    "wof:placetype":"locality"
},
  "geometry": {"coordinates":[96.16869,33.70265999999999],"type":"Point"}
}