{
  "type": "Feature",
  "properties": {
    "gn:admin1_code":"32.0",
    "gn:asciiname":"Tu'erbu",
    "gn:country_code":"CN",
    "gn:dem":363,
    "gn:feature_class":"P",
    "gn:feature_code":"PPL",
    "gn:name":"Tu\u2019erbu",
    "gn:population":0,
    "gn:timezone":"Asia/Shanghai",
    "iso:country":"CN",
    "name:und_x_variant":[
        "Tu\u2019erbu"
    ],
    "name:zho_x_preferred":[
        "\u5154\u513f\u5821"
    ],
    "wof:name":"Tu'erbu",
    "wof:placetype":"locality"
},
  "geometry": {"coordinates":[106.244,30.4355],"type":"Point"}
}