{
  "type": "Feature",
  "properties": {
    "gn:admin1_code":"26.0",
    "gn:asciiname":"Jiangzhong",
    "gn:country_code":"CN",
    "gn:dem":549,
    "gn:feature_class":"P",
    "gn:feature_code":"PPL",
    "gn:name":"Jiangzhong",
    "gn:population":0,
    "gn:timezone":"Asia/Shanghai",
    "iso:country":"CN",
    "name:und_x_variant":[
        "\u7edb\u4e2d"
    ],
    "wof:name":"Jiangzhong",
    "wof:placetype":"locality"
},
  "geometry": {"coordinates":[107.97114000000001,34.30297],"type":"Point"}
}