{
  "type": "Feature",
  "properties": {
    "gn:admin1_code":"8.0",
    "gn:asciiname":"Yangjia Wopeng",
    "gn:country_code":"CN",
    "gn:dem":121,
    "gn:feature_class":"P",
    "gn:feature_code":"PPL",
    "gn:name":"Yangjia Wopeng",
    "gn:population":0,
    "gn:timezone":"Asia/Shanghai",
    "iso:country":"CN",
    "name:zho_x_preferred":[
        "\u6768\u5bb6\u7a9d\u68da"
    ],
    "wof:name":"Yangjia Wopeng",
    "wof:placetype":"locality"
},
  "geometry": {"coordinates":[126.39399,45.98394],"type":"Point"}
}