{
  "type": "Feature",
  "properties": {
    "gn:admin1_code":"11.0",
    "gn:asciiname":"Beidi",
    "gn:country_code":"CN",
    "gn:dem":420,
    "gn:feature_class":"P",
    "gn:feature_code":"PPL",
    "gn:name":"Beidi",
    "gn:population":0,
    "gn:timezone":"Asia/Shanghai",
    "iso:country":"CN",
    "name:zho_x_preferred":[
        "\u80cc\u5730"
    ],
    "wof:name":"Beidi",
    "wof:placetype":"locality"
},
  "geometry": {"coordinates":[109.57080000000001,26.29649],"type":"Point"}
}