{
  "type": "Feature",
  "properties": {
    "gn:admin1_code":"32.0",
    "gn:asciiname":"Lajiaxi",
    "gn:country_code":"CN",
    "gn:dem":3931,
    "gn:feature_class":"P",
    "gn:feature_code":"PPL",
    "gn:name":"Lajiaxi",
    "gn:population":0,
    "gn:timezone":"Asia/Shanghai",
    "iso:country":"CN",
    "name:zho_x_preferred":[
        "\u62c9\u52a0\u897f"
    ],
    "wof:name":"Lajiaxi",
    "wof:placetype":"locality"
},
  "geometry": {"coordinates":[101.502,30.58878],"type":"Point"}
}