{
  "type": "Feature",
  "properties": {
    "gn:admin1_code":"10",
    "gn:asciiname":"Xigou",
    "gn:country_code":"CN",
    "gn:dem":714,
    "gn:feature_class":"P",
    "gn:feature_code":"PPL",
    "gn:name":"Xigou",
    "gn:population":0,
    "gn:timezone":"Asia/Shanghai",
    "iso:country":"CN",
    "wof:name":"Xigou",
    "wof:placetype":"locality"
},
  "geometry": {"coordinates":[117.45,41.15],"type":"Point"}
}