{
  "type": "Feature",
  "properties": {
    "gn:admin1_code":"4.0",
    "gn:asciiname":"Nanzhangcun",
    "gn:country_code":"CN",
    "gn:dem":6,
    "gn:feature_class":"P",
    "gn:feature_code":"PPL",
    "gn:name":"Nanzhangcun",
    "gn:population":0,
    "gn:timezone":"Asia/Shanghai",
    "iso:country":"CN",
    "name:und_x_variant":[
        "\u5357\u7ae0\u6751"
    ],
    "name:zho_x_preferred":[
        "\u5357\u7ae0\u6751"
    ],
    "wof:name":"Nanzhangcun",
    "wof:placetype":"locality"
},
  "geometry": {"coordinates":[120.3613,31.52833],"type":"Point"}
}