{
  "type": "Feature",
  "properties": {
    "gn:admin1_code":"26.0",
    "gn:asciiname":"Majiayuan",
    "gn:country_code":"CN",
    "gn:dem":913,
    "gn:feature_class":"P",
    "gn:feature_code":"PPL",
    "gn:name":"Majiayuan",
    "gn:population":0,
    "gn:timezone":"Asia/Shanghai",
    "iso:country":"CN",
    "name:und_x_variant":[
        "\u9a6c\u5bb6\u9662"
    ],
    "wof:name":"Majiayuan",
    "wof:placetype":"locality"
},
  "geometry": {"coordinates":[106.35578,32.75455],"type":"Point"}
}