{
  "type": "Feature",
  "properties": {
    "gn:admin1_code":"18.0",
    "gn:asciiname":"Xiegou",
    "gn:country_code":"CN",
    "gn:dem":716,
    "gn:feature_class":"P",
    "gn:feature_code":"PPL",
    "gn:name":"Xiegou",
    "gn:population":0,
    "gn:timezone":"Asia/Shanghai",
    "iso:country":"CN",
    "name:zho_x_preferred":[
        "\u8c22\u6c9f"
    ],
    "wof:name":"Xiegou",
    "wof:placetype":"locality"
},
  "geometry": {"coordinates":[108.889,28.1973],"type":"Point"}
}