{
  "type": "Feature",
  "properties": {
    "gn:admin1_code":"1.0",
    "gn:asciiname":"Baiqiao",
    "gn:country_code":"CN",
    "gn:dem":10,
    "gn:feature_class":"P",
    "gn:feature_code":"PPLA4",
    "gn:name":"Baiqiao",
    "gn:population":0,
    "gn:timezone":"Asia/Shanghai",
    "iso:country":"CN",
    "name:und_x_variant":[
        "Baiqiao Zhen",
        "\u767d\u6865\u9547",
        "Baiqiao"
    ],
    "name:zho_x_preferred":[
        "\u767d\u6865"
    ],
    "wof:name":"Baiqiao",
    "wof:placetype":"locality"
},
  "geometry": {"coordinates":[118.3082,31.53766],"type":"Point"}
}