{
  "type": "Feature",
  "properties": {
    "gn:admin1_code":"9.0",
    "gn:asciiname":"Zhimaochen",
    "gn:country_code":"CN",
    "gn:dem":58,
    "gn:feature_class":"P",
    "gn:feature_code":"PPL",
    "gn:name":"Zhimaochen",
    "gn:population":0,
    "gn:timezone":"Asia/Shanghai",
    "iso:country":"CN",
    "name:zho_x_preferred":[
        "\u652f\u6bdb\u9648"
    ],
    "wof:name":"Zhimaochen",
    "wof:placetype":"locality"
},
  "geometry": {"coordinates":[114.20180999999999,33.62527],"type":"Point"}
}