{
  "type": "Feature",
  "properties": {
    "gn:admin1_code":"5.0",
    "gn:asciiname":"Bajiazicun",
    "gn:country_code":"CN",
    "gn:dem":135,
    "gn:feature_class":"P",
    "gn:feature_code":"PPL",
    "gn:name":"Bajiazicun",
    "gn:population":0,
    "gn:timezone":"Asia/Shanghai",
    "iso:country":"CN",
    "name:zho_x_preferred":[
        "\u516b\u5bb6\u5b50\u6751"
    ],
    "wof:name":"Bajiazicun",
    "wof:placetype":"locality"
},
  "geometry": {"coordinates":[123.90882000000001,46.12657],"type":"Point"}
}