{
  "type": "Feature",
  "properties": {
    "gn:admin1_code":"9",
    "gn:asciiname":"Liuren",
    "gn:country_code":"CN",
    "gn:dem":47,
    "gn:feature_class":"P",
    "gn:feature_code":"PPL",
    "gn:name":"Liuren",
    "gn:population":0,
    "gn:timezone":"Asia/Shanghai",
    "iso:country":"CN",
    "name:zho_x_preferred":[
        "\u5218\u4ec1"
    ],
    "wof:name":"Liuren",
    "wof:placetype":"locality"
},
  "geometry": {"coordinates":[115.80237,35.93958],"type":"Point"}
}