{
  "type": "Feature",
  "properties": {
    "gn:admin1_code":"08",
    "gn:asciiname":"Taiyangsheng",
    "gn:cc2":"CN",
    "gn:country_code":"CN",
    "gn:dem":185,
    "gn:feature_class":"P",
    "gn:feature_code":"PPL",
    "gn:name":"Taiyangsheng",
    "gn:population":0,
    "gn:timezone":"Asia/Shanghai",
    "iso:country":"CN",
    "name:und_x_variant":[
        "Y\u00fc-lin",
        "Taiyangsheng"
    ],
    "wof:name":"Taiyangsheng",
    "wof:placetype":"locality"
},
  "geometry": {"coordinates":[126.28528,46.11306],"type":"Point"}
}