{
  "type": "Feature",
  "properties": {
    "gn:admin1_code":"26",
    "gn:asciiname":"Tangping",
    "gn:cc2":"CN",
    "gn:country_code":"CN",
    "gn:dem":683,
    "gn:feature_class":"P",
    "gn:feature_code":"PPL",
    "gn:name":"Tangping",
    "gn:population":0,
    "gn:timezone":"Asia/Shanghai",
    "iso:country":"CN",
    "name:und_x_variant":[
        "T\u2019ang-p\u2019ing-ho",
        "Tangping"
    ],
    "wof:name":"Tangping",
    "wof:placetype":"locality"
},
  "geometry": {"coordinates":[108.24583,33.31583],"type":"Point"}
}