{
  "type": "Feature",
  "properties": {
    "gn:admin1_code":"12.0",
    "gn:asciiname":"Zhoujiayuanzi",
    "gn:country_code":"CN",
    "gn:dem":31,
    "gn:feature_class":"P",
    "gn:feature_code":"PPL",
    "gn:name":"Zhoujiayuanzi",
    "gn:population":0,
    "gn:timezone":"Asia/Shanghai",
    "iso:country":"CN",
    "name:zho_x_preferred":[
        "\u5468\u5bb6\u57b8\u5b50"
    ],
    "wof:name":"Zhoujiayuanzi",
    "wof:placetype":"locality"
},
  "geometry": {"coordinates":[112.27181000000002,29.82165],"type":"Point"}
}