{
  "type": "Feature",
  "properties": {
    "gn:admin1_code":"3.0",
    "gn:asciiname":"Shiligang Fenchang",
    "gn:country_code":"CN",
    "gn:dem":54,
    "gn:feature_class":"P",
    "gn:feature_code":"PPLF",
    "gn:name":"Shiligang Fenchang",
    "gn:population":0,
    "gn:timezone":"Asia/Shanghai",
    "iso:country":"CN",
    "name:zho_x_preferred":[
        "\u5341\u91cc\u5c97\u5206\u573a"
    ],
    "wof:name":"Shiligang Fenchang",
    "wof:placetype":"locality"
},
  "geometry": {"coordinates":[117.479,28.8947],"type":"Point"}
}