{
  "type": "Feature",
  "properties": {
    "gn:admin1_code":"10",
    "gn:asciiname":"Qijiaying",
    "gn:country_code":"CN",
    "gn:dem":20,
    "gn:feature_class":"P",
    "gn:feature_code":"PPL",
    "gn:name":"Qijiaying",
    "gn:population":0,
    "gn:timezone":"Asia/Shanghai",
    "iso:country":"CN",
    "name:und_x_variant":[
        "Ch\u2019i-chia-ying",
        "Qijiaying"
    ],
    "name:zho_x_preferred":[
        "\u9f50\u5bb6\u8425"
    ],
    "wof:name":"Qijiaying",
    "wof:placetype":"locality"
},
  "geometry": {"coordinates":[115.758,38.4896],"type":"Point"}
}