{
  "type": "Feature",
  "properties": {
    "gn:admin1_code":"9.0",
    "gn:asciiname":"Xiaozhai",
    "gn:country_code":"CN",
    "gn:dem":70,
    "gn:feature_class":"P",
    "gn:feature_code":"PPL",
    "gn:name":"Xiaozhai",
    "gn:population":0,
    "gn:timezone":"Asia/Shanghai",
    "iso:country":"CN",
    "name:zho_x_preferred":[
        "\u5c0f\u5be8"
    ],
    "wof:name":"Xiaozhai",
    "wof:placetype":"locality"
},
  "geometry": {"coordinates":[114.26455,34.36993],"type":"Point"}
}