{
  "type": "Feature",
  "properties": {
    "gn:admin1_code":"4.0",
    "gn:asciiname":"Qidadui",
    "gn:country_code":"CN",
    "gn:dem":3,
    "gn:feature_class":"P",
    "gn:feature_code":"PPLF",
    "gn:name":"Qidadui",
    "gn:population":0,
    "gn:timezone":"Asia/Shanghai",
    "iso:country":"CN",
    "name:zho_x_preferred":[
        "\u4e03\u5927\u961f"
    ],
    "wof:name":"Qidadui",
    "wof:placetype":"locality"
},
  "geometry": {"coordinates":[120.96435,31.85931],"type":"Point"}
}