{
  "type": "Feature",
  "properties": {
    "gn:admin1_code":"25",
    "gn:asciiname":"Guanmu",
    "gn:country_code":"CN",
    "gn:dem":41,
    "gn:feature_class":"P",
    "gn:feature_code":"PPL",
    "gn:name":"Guanmu",
    "gn:population":0,
    "gn:timezone":"Asia/Shanghai",
    "iso:country":"CN",
    "name:zho_x_preferred":[
        "\u5b98\u7267"
    ],
    "wof:name":"Guanmu",
    "wof:placetype":"locality"
},
  "geometry": {"coordinates":[117.40300000000001,34.5509],"type":"Point"}
}