{
  "type": "Feature",
  "properties": {
    "gn:admin1_code":"2.0",
    "gn:asciiname":"Donglongkou",
    "gn:country_code":"CN",
    "gn:dem":52,
    "gn:feature_class":"P",
    "gn:feature_code":"PPL",
    "gn:name":"Donglongkou",
    "gn:population":0,
    "gn:timezone":"Asia/Shanghai",
    "iso:country":"CN",
    "name:zho_x_preferred":[
        "\u4e1c\u9f99\u53e3"
    ],
    "wof:name":"Donglongkou",
    "wof:placetype":"locality"
},
  "geometry": {"coordinates":[119.69736,29.05455],"type":"Point"}
}