{
  "type": "Feature",
  "properties": {
    "gn:admin1_code":"12.0",
    "gn:asciiname":"Liziyuan",
    "gn:country_code":"CN",
    "gn:dem":58,
    "gn:feature_class":"P",
    "gn:feature_code":"PPL",
    "gn:name":"Liziyuan",
    "gn:population":0,
    "gn:timezone":"Asia/Shanghai",
    "iso:country":"CN",
    "name:zho_x_preferred":[
        "\u6817\u6893\u56ed"
    ],
    "wof:name":"Liziyuan",
    "wof:placetype":"locality"
},
  "geometry": {"coordinates":[114.57333,30.97057],"type":"Point"}
}