{
  "type": "Feature",
  "properties": {
    "gn:admin1_code":"9.0",
    "gn:asciiname":"Guanzhuang",
    "gn:country_code":"CN",
    "gn:dem":257,
    "gn:feature_class":"P",
    "gn:feature_code":"PPL",
    "gn:name":"Guanzhuang",
    "gn:population":0,
    "gn:timezone":"Asia/Shanghai",
    "iso:country":"CN",
    "name:zho_x_preferred":[
        "\u5b98\u5e84"
    ],
    "wof:name":"Guanzhuang",
    "wof:placetype":"locality"
},
  "geometry": {"coordinates":[112.40519999999999,34.76946],"type":"Point"}
}