{
  "type": "Feature",
  "properties": {
    "gn:admin1_code":"29.0",
    "gn:asciiname":"Xiaoguangcun",
    "gn:country_code":"CN",
    "gn:dem":2234,
    "gn:feature_class":"P",
    "gn:feature_code":"PPL",
    "gn:name":"Xiaoguangcun",
    "gn:population":0,
    "gn:timezone":"Asia/Shanghai",
    "iso:country":"CN",
    "name:zho_x_preferred":[
        "\u6653\u5149\u6751"
    ],
    "wof:name":"Xiaoguangcun",
    "wof:placetype":"locality"
},
  "geometry": {"coordinates":[102.983,26.0692],"type":"Point"}
}