{
  "type": "Feature",
  "properties": {
    "gn:admin1_code":"32.0",
    "gn:asciiname":"Heicaogou",
    "gn:country_code":"CN",
    "gn:dem":435,
    "gn:feature_class":"P",
    "gn:feature_code":"PPL",
    "gn:name":"Heicaogou",
    "gn:population":0,
    "gn:timezone":"Asia/Shanghai",
    "iso:country":"CN",
    "name:zho_x_preferred":[
        "\u9ed1\u69fd\u6c9f"
    ],
    "wof:name":"Heicaogou",
    "wof:placetype":"locality"
},
  "geometry": {"coordinates":[107.6311,31.02913],"type":"Point"}
}