{
  "type": "Feature",
  "properties": {
    "gn:admin1_code":"1.0",
    "gn:asciiname":"Nannyuancun",
    "gn:country_code":"CN",
    "gn:dem":34,
    "gn:feature_class":"P",
    "gn:feature_code":"PPL",
    "gn:name":"Nannyuancun",
    "gn:population":0,
    "gn:timezone":"Asia/Shanghai",
    "iso:country":"CN",
    "name:zho_x_preferred":[
        "\u5357\u56ed\u6751"
    ],
    "wof:name":"Nannyuancun",
    "wof:placetype":"locality"
},
  "geometry": {"coordinates":[116.86839000000001,33.76335],"type":"Point"}
}