{
  "type": "Feature",
  "properties": {
    "gn:admin1_code":"29.0",
    "gn:asciiname":"Xitanjie",
    "gn:country_code":"CN",
    "gn:dem":2268,
    "gn:feature_class":"P",
    "gn:feature_code":"PPL",
    "gn:name":"Xitanjie",
    "gn:population":0,
    "gn:timezone":"Asia/Shanghai",
    "iso:country":"CN",
    "name:zho_x_preferred":[
        "\u897f\u70ad\u8857"
    ],
    "wof:name":"Xitanjie",
    "wof:placetype":"locality"
},
  "geometry": {"coordinates":[100.16200000000001,26.309],"type":"Point"}
}