{
  "type": "Feature",
  "properties": {
    "gn:admin1_code":"29.0",
    "gn:asciiname":"Fengmingcun",
    "gn:country_code":"CN",
    "gn:dem":2071,
    "gn:feature_class":"P",
    "gn:feature_code":"PPL",
    "gn:name":"Fengmingcun",
    "gn:population":0,
    "gn:timezone":"Asia/Shanghai",
    "iso:country":"CN",
    "name:zho_x_preferred":[
        "\u51e4\u9e23\u6751"
    ],
    "wof:name":"Fengmingcun",
    "wof:placetype":"locality"
},
  "geometry": {"coordinates":[104.163,25.6525],"type":"Point"}
}