{
  "type": "Feature",
  "properties": {
    "gn:admin1_code":"4.0",
    "gn:asciiname":"Zhuanshuidun",
    "gn:country_code":"CN",
    "gn:dem":6,
    "gn:feature_class":"P",
    "gn:feature_code":"PPL",
    "gn:name":"Zhuanshuidun",
    "gn:population":0,
    "gn:timezone":"Asia/Shanghai",
    "iso:country":"CN",
    "name:zho_x_preferred":[
        "\u8f6c\u6c34\u58a9"
    ],
    "wof:name":"Zhuanshuidun",
    "wof:placetype":"locality"
},
  "geometry": {"coordinates":[120.84611,32.12175],"type":"Point"}
}