{
  "type": "Feature",
  "properties": {
    "gn:admin1_code":"10",
    "gn:asciiname":"Yongchengzhang",
    "gn:country_code":"CN",
    "gn:dem":1411,
    "gn:feature_class":"P",
    "gn:feature_code":"PPL",
    "gn:name":"Yongchengzhang",
    "gn:population":0,
    "gn:timezone":"Asia/Shanghai",
    "iso:country":"CN",
    "name:zho_x_preferred":[
        "\u6c38\u6210\u7ae0"
    ],
    "wof:name":"Yongchengzhang",
    "wof:placetype":"locality"
},
  "geometry": {"coordinates":[115.574,41.62408],"type":"Point"}
}