{
  "type": "Feature",
  "properties": {
    "gn:admin1_code":"24.0",
    "gn:asciiname":"Wangjiajian",
    "gn:country_code":"CN",
    "gn:dem":1079,
    "gn:feature_class":"P",
    "gn:feature_code":"PPL",
    "gn:name":"Wangjiajian",
    "gn:population":0,
    "gn:timezone":"Asia/Shanghai",
    "iso:country":"CN",
    "name:und_x_variant":[
        "\u738b\u5bb6\u6da7"
    ],
    "wof:name":"Wangjiajian",
    "wof:placetype":"locality"
},
  "geometry": {"coordinates":[112.79431,39.51495],"type":"Point"}
}