{
  "type": "Feature",
  "properties": {
    "gn:admin1_code":"9.0",
    "gn:asciiname":"Liwangzhuang",
    "gn:country_code":"CN",
    "gn:dem":216,
    "gn:feature_class":"P",
    "gn:feature_code":"PPL",
    "gn:name":"Liwangzhuang",
    "gn:population":0,
    "gn:timezone":"Asia/Shanghai",
    "iso:country":"CN",
    "name:und_x_variant":[
        "\u91cc\u738b\u5e84",
        "Liwangzhuang"
    ],
    "wof:name":"Liwangzhuang",
    "wof:placetype":"locality"
},
  "geometry": {"coordinates":[112.90582999999999,33.6256],"type":"Point"}
}