{
  "type": "Feature",
  "properties": {
    "gn:admin1_code":"10",
    "gn:asciiname":"Houliu",
    "gn:country_code":"CN",
    "gn:dem":72,
    "gn:feature_class":"P",
    "gn:feature_code":"PPL",
    "gn:name":"Houliu",
    "gn:population":0,
    "gn:timezone":"Asia/Shanghai",
    "iso:country":"CN",
    "name:zho_x_preferred":[
        "\u540e\u7559"
    ],
    "wof:name":"Houliu",
    "wof:placetype":"locality"
},
  "geometry": {"coordinates":[114.55200000000001,37.4617],"type":"Point"}
}