{
  "type": "Feature",
  "properties": {
    "gn:admin1_code":"10",
    "gn:asciiname":"Waigoumen",
    "gn:cc2":"CN",
    "gn:country_code":"CN",
    "gn:dem":1160,
    "gn:feature_class":"P",
    "gn:feature_code":"PPL",
    "gn:name":"Waigoumen",
    "gn:population":0,
    "gn:timezone":"Asia/Shanghai",
    "iso:country":"CN",
    "name:und_x_variant":[
        "Wai-kou-men",
        "Waigoumen"
    ],
    "wof:name":"Waigoumen",
    "wof:placetype":"locality"
},
  "geometry": {"coordinates":[116.28139,41.3775],"type":"Point"}
}