{
  "type": "Feature",
  "properties": {
    "gn:admin1_code":"8.0",
    "gn:asciiname":"Shangshengcun",
    "gn:country_code":"CN",
    "gn:dem":251,
    "gn:feature_class":"P",
    "gn:feature_code":"PPL",
    "gn:name":"Shangshengcun",
    "gn:population":0,
    "gn:timezone":"Asia/Shanghai",
    "iso:country":"CN",
    "name:zho_x_preferred":[
        "\u4e0a\u5347\u6751"
    ],
    "wof:name":"Shangshengcun",
    "wof:placetype":"locality"
},
  "geometry": {"coordinates":[126.25163000000001,47.85964],"type":"Point"}
}