{
  "type": "Feature",
  "properties": {
    "gn:admin1_code":"11.0",
    "gn:asciiname":"Yuanshe",
    "gn:country_code":"CN",
    "gn:dem":122,
    "gn:feature_class":"P",
    "gn:feature_code":"PPL",
    "gn:name":"Yuanshe",
    "gn:population":0,
    "gn:timezone":"Asia/Shanghai",
    "iso:country":"CN",
    "name:zho_x_preferred":[
        "\u539f\u820d"
    ],
    "wof:name":"Yuanshe",
    "wof:placetype":"locality"
},
  "geometry": {"coordinates":[112.82342,26.24821],"type":"Point"}
}