{
  "type": "Feature",
  "properties": {
    "gn:admin1_code":"4.0",
    "gn:asciiname":"Huangdangcun",
    "gn:country_code":"CN",
    "gn:dem":-2,
    "gn:feature_class":"P",
    "gn:feature_code":"PPL",
    "gn:name":"Huangdangcun",
    "gn:population":0,
    "gn:timezone":"Asia/Shanghai",
    "iso:country":"CN",
    "name:zho_x_preferred":[
        "\u9ec4\u8361\u6751"
    ],
    "wof:name":"Huangdangcun",
    "wof:placetype":"locality"
},
  "geometry": {"coordinates":[119.51947,33.34369],"type":"Point"}
}