{
  "type": "Feature",
  "properties": {
    "gn:admin1_code":"3.0",
    "gn:asciiname":"Tongjia",
    "gn:country_code":"CN",
    "gn:dem":51,
    "gn:feature_class":"P",
    "gn:feature_code":"PPL",
    "gn:name":"Tongjia",
    "gn:population":0,
    "gn:timezone":"Asia/Shanghai",
    "iso:country":"CN",
    "name:und_x_variant":[
        "\u7ae5\u5bb6"
    ],
    "wof:name":"Tongjia",
    "wof:placetype":"locality"
},
  "geometry": {"coordinates":[116.62372999999999,27.82678],"type":"Point"}
}