{
  "type": "Feature",
  "properties": {
    "gn:admin1_code":"29.0",
    "gn:asciiname":"Weijia",
    "gn:country_code":"CN",
    "gn:dem":1651,
    "gn:feature_class":"P",
    "gn:feature_code":"PPL",
    "gn:name":"Weijia",
    "gn:population":0,
    "gn:timezone":"Asia/Shanghai",
    "iso:country":"CN",
    "name:zho_x_preferred":[
        "\u9b4f\u5bb6"
    ],
    "wof:name":"Weijia",
    "wof:placetype":"locality"
},
  "geometry": {"coordinates":[99.2383,25.1297],"type":"Point"}
}