{
  "type": "Feature",
  "properties": {
    "gn:admin1_code":"7.0",
    "gn:asciiname":"Tianzangdi",
    "gn:country_code":"CN",
    "gn:dem":277,
    "gn:feature_class":"P",
    "gn:feature_code":"PPL",
    "gn:name":"Tianzangdi",
    "gn:population":0,
    "gn:timezone":"Asia/Shanghai",
    "iso:country":"CN",
    "name:und_x_variant":[
        "\u5929\u846c\u5730"
    ],
    "name:zho_x_preferred":[
        "\u5929\u846c\u5730"
    ],
    "wof:name":"Tianzangdi",
    "wof:placetype":"locality"
},
  "geometry": {"coordinates":[116.34026,25.56866],"type":"Point"}
}