{
  "type": "Feature",
  "properties": {
    "gn:admin1_code":"24",
    "gn:asciiname":"Qiji",
    "gn:country_code":"CN",
    "gn:dem":377,
    "gn:feature_class":"P",
    "gn:feature_code":"PPL",
    "gn:name":"Qiji",
    "gn:population":0,
    "gn:timezone":"Asia/Shanghai",
    "iso:country":"CN",
    "name:ceb_x_preferred":[
        "Qiji"
    ],
    "name:swe_x_preferred":[
        "Qiji"
    ],
    "wof:name":"Qiji",
    "wof:placetype":"locality"
},
  "geometry": {"coordinates":[110.53917,35.00583],"type":"Point"}
}