{
  "type": "Feature",
  "properties": {
    "gn:admin1_code":"32.0",
    "gn:asciiname":"Zacaogou",
    "gn:country_code":"CN",
    "gn:dem":1152,
    "gn:feature_class":"P",
    "gn:feature_code":"PPL",
    "gn:name":"Zacaogou",
    "gn:population":0,
    "gn:timezone":"Asia/Shanghai",
    "iso:country":"CN",
    "name:zho_x_preferred":[
        "\u6742\u8349\u6c9f"
    ],
    "wof:name":"Zacaogou",
    "wof:placetype":"locality"
},
  "geometry": {"coordinates":[105.83499999999999,28.1564],"type":"Point"}
}