{
  "type": "Feature",
  "properties": {
    "gn:admin1_code":"8.0",
    "gn:asciiname":"Simajiacun",
    "gn:country_code":"CN",
    "gn:dem":94,
    "gn:feature_class":"P",
    "gn:feature_code":"PPL",
    "gn:name":"Simajiacun",
    "gn:population":0,
    "gn:timezone":"Asia/Shanghai",
    "iso:country":"CN",
    "name:zho_x_preferred":[
        "\u56db\u9a6c\u67b6\u6751"
    ],
    "wof:name":"Simajiacun",
    "wof:placetype":"locality"
},
  "geometry": {"coordinates":[131.54916,46.6743],"type":"Point"}
}