{
  "type": "Feature",
  "properties": {
    "gn:admin1_code":"5.0",
    "gn:asciiname":"Mingzicun",
    "gn:country_code":"CN",
    "gn:dem":147,
    "gn:feature_class":"P",
    "gn:feature_code":"PPL",
    "gn:name":"Mingzicun",
    "gn:population":0,
    "gn:timezone":"Asia/Shanghai",
    "iso:country":"CN",
    "name:zho_x_preferred":[
        "\u9e23\u5b57\u6751"
    ],
    "wof:name":"Mingzicun",
    "wof:placetype":"locality"
},
  "geometry": {"coordinates":[123.99553,44.9609],"type":"Point"}
}