{
  "type": "Feature",
  "properties": {
    "gn:admin1_code":"19.0",
    "gn:asciiname":"Dabucun",
    "gn:country_code":"CN",
    "gn:dem":191,
    "gn:feature_class":"P",
    "gn:feature_code":"PPL",
    "gn:name":"Dabucun",
    "gn:population":0,
    "gn:timezone":"Asia/Shanghai",
    "iso:country":"CN",
    "name:zho_x_preferred":[
        "\u5927\u5821\u6751"
    ],
    "wof:name":"Dabucun",
    "wof:placetype":"locality"
},
  "geometry": {"coordinates":[124.54000000000001,41.8055],"type":"Point"}
}