{
  "type": "Feature",
  "properties": {
    "gn:admin1_code":"19.0",
    "gn:asciiname":"Weili",
    "gn:country_code":"CN",
    "gn:dem":92,
    "gn:feature_class":"P",
    "gn:feature_code":"PPL",
    "gn:name":"Weili",
    "gn:population":0,
    "gn:timezone":"Asia/Shanghai",
    "iso:country":"CN",
    "name:zho_x_preferred":[
        "\u9688\u91cc"
    ],
    "wof:name":"Weili",
    "wof:placetype":"locality"
},
  "geometry": {"coordinates":[123.98797999999999,40.58919],"type":"Point"}
}