{
  "type": "Feature",
  "properties": {
    "gn:admin1_code":"16.0",
    "gn:asciiname":"Nongli",
    "gn:country_code":"CN",
    "gn:dem":877,
    "gn:feature_class":"P",
    "gn:feature_code":"PPL",
    "gn:name":"Nongli",
    "gn:population":0,
    "gn:timezone":"Asia/Shanghai",
    "iso:country":"CN",
    "name:zho_x_preferred":[
        "\u5f04\u529b"
    ],
    "wof:name":"Nongli",
    "wof:placetype":"locality"
},
  "geometry": {"coordinates":[107.72799999999999,24.1133],"type":"Point"}
}