{
  "type": "Feature",
  "properties": {
    "gn:admin1_code":"18",
    "gn:asciiname":"Le'er",
    "gn:country_code":"CN",
    "gn:dem":795,
    "gn:feature_class":"P",
    "gn:feature_code":"PPL",
    "gn:name":"Le\u2019er",
    "gn:population":0,
    "gn:timezone":"Asia/Shanghai",
    "iso:country":"CN",
    "name:und_x_variant":[
        "Le\u2019er"
    ],
    "name:zho_x_preferred":[
        "\u4e50\u8033"
    ],
    "wof:name":"Le'er",
    "wof:placetype":"locality"
},
  "geometry": {"coordinates":[105.042,24.9498],"type":"Point"}
}