{
  "type": "Feature",
  "properties": {
    "gn:admin1_code":"30",
    "gn:asciiname":"Dalin",
    "gn:country_code":"CN",
    "gn:dem":3,
    "gn:feature_class":"P",
    "gn:feature_code":"PPL",
    "gn:name":"Dalin",
    "gn:population":0,
    "gn:timezone":"Asia/Urumqi",
    "iso:country":"CN",
    "name:deu_x_preferred":[
        "Dalin"
    ],
    "name:fra_x_preferred":[
        "Dalin"
    ],
    "name:pol_x_preferred":[
        "Dalin"
    ],
    "name:zho_x_preferred":[
        "\u5927\u6797"
    ],
    "wof:name":"Dalin",
    "wof:placetype":"locality"
},
  "geometry": {"coordinates":[110.32365,20.74695],"type":"Point"}
}