{
  "type": "Feature",
  "properties": {
    "gn:admin1_code":"32.0",
    "gn:asciiname":"Gaqiwojiao",
    "gn:country_code":"CN",
    "gn:dem":2020,
    "gn:feature_class":"P",
    "gn:feature_code":"PPL",
    "gn:name":"Gaqiwojiao",
    "gn:population":0,
    "gn:timezone":"Asia/Shanghai",
    "iso:country":"CN",
    "name:zho_x_preferred":[
        "\u560e\u671f\u6da1\u89d2"
    ],
    "wof:name":"Gaqiwojiao",
    "wof:placetype":"locality"
},
  "geometry": {"coordinates":[103.19199999999999,28.7907],"type":"Point"}
}