{
  "type": "Feature",
  "properties": {
    "gn:admin1_code":"14.0",
    "gn:asciiname":"Nuru",
    "gn:country_code":"CN",
    "gn:dem":4281,
    "gn:feature_class":"P",
    "gn:feature_code":"PPL",
    "gn:name":"Nuru",
    "gn:population":0,
    "gn:timezone":"Asia/Urumqi",
    "iso:country":"CN",
    "name:ita_x_preferred":[
        "Nuru"
    ],
    "name:zho_x_preferred":[
        "\u52aa\u5982"
    ],
    "wof:name":"Nuru",
    "wof:placetype":"locality"
},
  "geometry": {"coordinates":[88.1028,28.516],"type":"Point"}
}