{
  "type": "Feature",
  "properties": {
    "gn:admin1_code":"4.0",
    "gn:asciiname":"Tulouxia",
    "gn:country_code":"CN",
    "gn:dem":6,
    "gn:feature_class":"P",
    "gn:feature_code":"PPL",
    "gn:name":"Tulouxia",
    "gn:population":0,
    "gn:timezone":"Asia/Shanghai",
    "iso:country":"CN",
    "name:zho_x_preferred":[
        "\u571f\u697c\u4e0b"
    ],
    "wof:name":"Tulouxia",
    "wof:placetype":"locality"
},
  "geometry": {"coordinates":[119.54107999999999,31.46776],"type":"Point"}
}