{
  "type": "Feature",
  "properties": {
    "gn:admin1_code":"26",
    "gn:asciiname":"Xiagaopo",
    "gn:country_code":"CN",
    "gn:dem":553,
    "gn:feature_class":"P",
    "gn:feature_code":"PPL",
    "gn:name":"Xiagaopo",
    "gn:population":0,
    "gn:timezone":"Asia/Shanghai",
    "iso:country":"CN",
    "name:und_x_variant":[
        "\u4e0b\u9ad8\u5761"
    ],
    "name:zho_x_preferred":[
        "\u4e0b\u9ad8\u5761"
    ],
    "wof:name":"Xiagaopo",
    "wof:placetype":"locality"
},
  "geometry": {"coordinates":[108.54306,34.61083],"type":"Point"}
}