{
  "type": "Feature",
  "properties": {
    "gn:admin1_code":"11.0",
    "gn:asciiname":"Shanglishan",
    "gn:country_code":"CN",
    "gn:dem":381,
    "gn:feature_class":"P",
    "gn:feature_code":"PPL",
    "gn:name":"Shanglishan",
    "gn:population":0,
    "gn:timezone":"Asia/Shanghai",
    "iso:country":"CN",
    "name:zho_x_preferred":[
        "\u4e0a\u6817\u5c71"
    ],
    "wof:name":"Shanglishan",
    "wof:placetype":"locality"
},
  "geometry": {"coordinates":[112.40913,25.53637],"type":"Point"}
}