{
  "type": "Feature",
  "properties": {
    "gn:admin1_code":"24.0",
    "gn:asciiname":"Dazhaozhuang",
    "gn:country_code":"CN",
    "gn:dem":1472,
    "gn:feature_class":"P",
    "gn:feature_code":"PPL",
    "gn:name":"Dazhaozhuang",
    "gn:population":0,
    "gn:timezone":"Asia/Shanghai",
    "iso:country":"CN",
    "name:und_x_variant":[
        "\u5927\u8d75\u5e84"
    ],
    "name:zho_x_preferred":[
        "\u5927\u8d75\u5e84"
    ],
    "wof:name":"Dazhaozhuang",
    "wof:placetype":"locality"
},
  "geometry": {"coordinates":[112.07265,39.12337],"type":"Point"}
}