{
  "type": "Feature",
  "properties": {
    "gn:admin1_code":"29.0",
    "gn:asciiname":"Shixia",
    "gn:country_code":"CN",
    "gn:dem":1846,
    "gn:feature_class":"P",
    "gn:feature_code":"PPL",
    "gn:name":"Shixia",
    "gn:population":0,
    "gn:timezone":"Asia/Shanghai",
    "iso:country":"CN",
    "name:deu_x_preferred":[
        "Shixia"
    ],
    "name:zho_x_preferred":[
        "\u77f3\u867e"
    ],
    "wof:name":"Shixia",
    "wof:placetype":"locality"
},
  "geometry": {"coordinates":[100.455,25.4301],"type":"Point"}
}