{
  "type": "Feature",
  "properties": {
    "gn:admin1_code":"15.0",
    "gn:asciiname":"Shuangshigeda",
    "gn:country_code":"CN",
    "gn:dem":2924,
    "gn:feature_class":"P",
    "gn:feature_code":"PPL",
    "gn:name":"Shuangshigeda",
    "gn:population":0,
    "gn:timezone":"Asia/Shanghai",
    "iso:country":"CN",
    "name:zho_x_preferred":[
        "\u53cc\u77f3\u7599\u7629"
    ],
    "wof:name":"Shuangshigeda",
    "wof:placetype":"locality"
},
  "geometry": {"coordinates":[102.02,37.9369],"type":"Point"}
}