{
  "type": "Feature",
  "properties": {
    "gn:admin1_code":"16",
    "gn:asciiname":"Deli",
    "gn:country_code":"CN",
    "gn:dem":291,
    "gn:feature_class":"P",
    "gn:feature_code":"PPL",
    "gn:name":"Deli",
    "gn:population":0,
    "gn:timezone":"Asia/Shanghai",
    "iso:country":"CN",
    "name:ceb_x_preferred":[
        "Deli"
    ],
    "name:ces_x_preferred":[
        "Deli"
    ],
    "name:deu_x_preferred":[
        "Deli"
    ],
    "name:fin_x_preferred":[
        "Deli"
    ],
    "name:fra_x_preferred":[
        "Deli"
    ],
    "name:hun_x_preferred":[
        "Deli"
    ],
    "name:kur_x_preferred":[
        "D\u00een"
    ],
    "name:nld_x_preferred":[
        "Deli"
    ],
    "name:swe_x_preferred":[
        "Deli"
    ],
    "name:tur_x_preferred":[
        "Deli"
    ],
    "name:zho_x_preferred":[
        "\u5fb7\u7acb"
    ],
    "name:zho_x_variant":[
        "Deli"
    ],
    "wof:name":"Deli",
    "wof:placetype":"locality"
},
  "geometry": {"coordinates":[107.33,22.8162],"type":"Point"}
}