{
  "type": "Feature",
  "properties": {
    "gn:admin1_code":"16.0",
    "gn:asciiname":"Jinniutang",
    "gn:country_code":"CN",
    "gn:dem":21,
    "gn:feature_class":"P",
    "gn:feature_code":"PPL",
    "gn:name":"Jinniutang",
    "gn:population":0,
    "gn:timezone":"Asia/Shanghai",
    "iso:country":"CN",
    "name:zho_x_preferred":[
        "\u8fdb\u725b\u5858"
    ],
    "wof:name":"Jinniutang",
    "wof:placetype":"locality"
},
  "geometry": {"coordinates":[109.277,21.8252],"type":"Point"}
}