{
  "type": "Feature",
  "properties": {
    "gn:admin1_code":"11",
    "gn:asciiname":"Dongshuidang",
    "gn:country_code":"CN",
    "gn:dem":81,
    "gn:feature_class":"P",
    "gn:feature_code":"PPL",
    "gn:name":"Dongshuidang",
    "gn:population":0,
    "gn:timezone":"Asia/Shanghai",
    "iso:country":"CN",
    "name:zho_x_preferred":[
        "\u51bb\u6c34\u51fc"
    ],
    "wof:name":"Dongshuidang",
    "wof:placetype":"locality"
},
  "geometry": {"coordinates":[112.32687,26.48396],"type":"Point"}
}