{
  "type": "Feature",
  "properties": {
    "gn:admin1_code":"29.0",
    "gn:asciiname":"Xiaohe",
    "gn:country_code":"CN",
    "gn:dem":955,
    "gn:feature_class":"P",
    "gn:feature_code":"PPL",
    "gn:name":"Xiaohe",
    "gn:population":0,
    "gn:timezone":"Asia/Shanghai",
    "iso:country":"CN",
    "name:ceb_x_preferred":[
        "Xiaohe"
    ],
    "name:deu_x_preferred":[
        "Xiaohe"
    ],
    "name:nor_x_preferred":[
        "Xiaohe"
    ],
    "name:swe_x_preferred":[
        "Xiaohe"
    ],
    "name:und_x_variant":[
        "\u5c0f\u6cb3"
    ],
    "wof:name":"Xiaohe",
    "wof:placetype":"locality"
},
  "geometry": {"coordinates":[103.89308,27.99652],"type":"Point"}
}