{
  "type": "Feature",
  "properties": {
    "gn:admin1_code":"19.0",
    "gn:asciiname":"Renyicun",
    "gn:country_code":"CN",
    "gn:dem":277,
    "gn:feature_class":"P",
    "gn:feature_code":"PPL",
    "gn:name":"Renyicun",
    "gn:population":0,
    "gn:timezone":"Asia/Shanghai",
    "iso:country":"CN",
    "name:zho_x_preferred":[
        "\u4ec1\u4e49\u6751"
    ],
    "wof:name":"Renyicun",
    "wof:placetype":"locality"
},
  "geometry": {"coordinates":[124.92471999999999,42.6314],"type":"Point"}
}