{
  "type": "Feature",
  "properties": {
    "gn:admin1_code":"20.0",
    "gn:asciiname":"Ershiyi Gongli",
    "gn:country_code":"CN",
    "gn:dem":731,
    "gn:feature_class":"P",
    "gn:feature_code":"PPL",
    "gn:name":"Ershiyi Gongli",
    "gn:population":0,
    "gn:timezone":"Asia/Shanghai",
    "iso:country":"CN",
    "name:zho_x_preferred":[
        "\u4e8c\u5341\u4e00\u516c\u91cc"
    ],
    "wof:name":"Ershiyi Gongli",
    "wof:placetype":"locality"
},
  "geometry": {"coordinates":[121.22829,50.7241],"type":"Point"}
}