{
  "type": "Feature",
  "properties": {
    "gn:admin1_code":"02",
    "gn:asciiname":"Xiafengcha",
    "gn:cc2":"CN",
    "gn:country_code":"CN",
    "gn:dem":18,
    "gn:feature_class":"P",
    "gn:feature_code":"PPL",
    "gn:name":"Xiafengcha",
    "gn:population":0,
    "gn:timezone":"Asia/Shanghai",
    "iso:country":"CN",
    "name:und_x_variant":[
        "Hsia-feng-ch\u2019a",
        "Xiafengcha"
    ],
    "name:zho_x_preferred":[
        "\u4e0b\u67ab\u69ce"
    ],
    "wof:name":"Xiafengcha",
    "wof:placetype":"locality"
},
  "geometry": {"coordinates":[121.45222,29.24417],"type":"Point"}
}