{
  "type": "Feature",
  "properties": {
    "gn:admin1_code":"8.0",
    "gn:asciiname":"Hujia Weizi",
    "gn:country_code":"CN",
    "gn:dem":228,
    "gn:feature_class":"P",
    "gn:feature_code":"PPL",
    "gn:name":"Hujia Weizi",
    "gn:population":0,
    "gn:timezone":"Asia/Shanghai",
    "iso:country":"CN",
    "name:zho_x_preferred":[
        "\u80e1\u5bb6\u56f4\u5b50"
    ],
    "wof:name":"Hujia Weizi",
    "wof:placetype":"locality"
},
  "geometry": {"coordinates":[126.93604000000001,47.47284000000001],"type":"Point"}
}