{
  "type": "Feature",
  "properties": {
    "gn:admin1_code":"12.0",
    "gn:asciiname":"Laojingyan",
    "gn:country_code":"CN",
    "gn:dem":27,
    "gn:feature_class":"P",
    "gn:feature_code":"PPL",
    "gn:name":"Laojingyan",
    "gn:population":0,
    "gn:timezone":"Asia/Shanghai",
    "iso:country":"CN",
    "name:zho_x_preferred":[
        "\u8001\u7ecf\u5944"
    ],
    "wof:name":"Laojingyan",
    "wof:placetype":"locality"
},
  "geometry": {"coordinates":[112.34730999999999,30.31452],"type":"Point"}
}