{
  "type": "Feature",
  "properties": {
    "gn:admin1_code":"8.0",
    "gn:asciiname":"Jinhecun",
    "gn:country_code":"CN",
    "gn:dem":46,
    "gn:feature_class":"P",
    "gn:feature_code":"PPL",
    "gn:name":"Jinhecun",
    "gn:population":0,
    "gn:timezone":"Asia/Shanghai",
    "iso:country":"CN",
    "name:zho_x_preferred":[
        "\u91d1\u6cb3\u6751"
    ],
    "wof:name":"Jinhecun",
    "wof:placetype":"locality"
},
  "geometry": {"coordinates":[133.79657,48.04148],"type":"Point"}
}