{
  "type": "Feature",
  "properties": {
    "gn:admin1_code":"32.0",
    "gn:asciiname":"Tianhuachang",
    "gn:country_code":"CN",
    "gn:dem":347,
    "gn:feature_class":"P",
    "gn:feature_code":"PPL",
    "gn:name":"Tianhuachang",
    "gn:population":0,
    "gn:timezone":"Asia/Shanghai",
    "iso:country":"CN",
    "name:zho_x_preferred":[
        "\u5929\u534e\u573a"
    ],
    "wof:name":"Tianhuachang",
    "wof:placetype":"locality"
},
  "geometry": {"coordinates":[105.29452000000001,29.52782],"type":"Point"}
}