{
  "type": "Feature",
  "properties": {
    "gn:admin1_code":"32.0",
    "gn:asciiname":"Jianggou",
    "gn:country_code":"CN",
    "gn:dem":682,
    "gn:feature_class":"P",
    "gn:feature_code":"PPL",
    "gn:name":"Jianggou",
    "gn:population":0,
    "gn:timezone":"Asia/Shanghai",
    "iso:country":"CN",
    "name:zho_x_preferred":[
        "\u5c06\u6c9f"
    ],
    "name:zho_x_variant":[
        "\u848b\u6c9f"
    ],
    "wof:name":"Jianggou",
    "wof:placetype":"locality"
},
  "geometry": {"coordinates":[103.348,30.0874],"type":"Point"}
}