{
  "type": "Feature",
  "properties": {
    "gn:admin1_code":"25.0",
    "gn:asciiname":"Dawacun",
    "gn:country_code":"CN",
    "gn:dem":127,
    "gn:feature_class":"P",
    "gn:feature_code":"PPL",
    "gn:name":"Dawacun",
    "gn:population":0,
    "gn:timezone":"Asia/Shanghai",
    "iso:country":"CN",
    "name:zho_x_preferred":[
        "\u5927\u6d3c\u6751"
    ],
    "wof:name":"Dawacun",
    "wof:placetype":"locality"
},
  "geometry": {"coordinates":[118.68035,35.01309000000001],"type":"Point"}
}