{
  "type": "Feature",
  "properties": {
    "gn:admin1_code":"30",
    "gn:asciiname":"Chengkengli",
    "gn:country_code":"CN",
    "gn:dem":178,
    "gn:feature_class":"P",
    "gn:feature_code":"PPL",
    "gn:name":"Chengkengli",
    "gn:population":0,
    "gn:timezone":"Asia/Shanghai",
    "iso:country":"CN",
    "name:zho_x_preferred":[
        "\u7a0b\u5751\u91cc"
    ],
    "wof:name":"Chengkengli",
    "wof:placetype":"locality"
},
  "geometry": {"coordinates":[115.9337,24.63568],"type":"Point"}
}