{
  "type": "Feature",
  "properties": {
    "gn:admin1_code":"2.0",
    "gn:asciiname":"Kongkengtou",
    "gn:country_code":"CN",
    "gn:dem":800,
    "gn:feature_class":"P",
    "gn:feature_code":"PPL",
    "gn:name":"Kongkengtou",
    "gn:population":0,
    "gn:timezone":"Asia/Shanghai",
    "iso:country":"CN",
    "name:zho_x_preferred":[
        "\u7a7a\u5751\u5934"
    ],
    "wof:name":"Kongkengtou",
    "wof:placetype":"locality"
},
  "geometry": {"coordinates":[119.16930000000001,27.96038],"type":"Point"}
}