{
  "type": "Feature",
  "properties": {
    "gn:admin1_code":"32.0",
    "gn:asciiname":"Jiezu",
    "gn:country_code":"CN",
    "gn:dem":1947,
    "gn:feature_class":"P",
    "gn:feature_code":"PPL",
    "gn:name":"Jiezu",
    "gn:population":0,
    "gn:timezone":"Asia/Shanghai",
    "iso:country":"CN",
    "name:zho_x_preferred":[
        "\u7ed3\u7956"
    ],
    "wof:name":"Jiezu",
    "wof:placetype":"locality"
},
  "geometry": {"coordinates":[103.018,27.7063],"type":"Point"}
}