{
  "type": "Feature",
  "properties": {
    "gn:admin1_code":"25",
    "gn:asciiname":"Xinghua Guanzhuang",
    "gn:country_code":"CN",
    "gn:dem":178,
    "gn:feature_class":"P",
    "gn:feature_code":"PPL",
    "gn:name":"Xinghua Guanzhuang",
    "gn:population":0,
    "gn:timezone":"Asia/Shanghai",
    "iso:country":"CN",
    "name:zho_x_preferred":[
        "\u674f\u82b1\u5b98\u5e84"
    ],
    "wof:name":"Xinghua Guanzhuang",
    "wof:placetype":"locality"
},
  "geometry": {"coordinates":[119.01300000000001,35.3243],"type":"Point"}
}