{
  "type": "Feature",
  "properties": {
    "gn:admin1_code":"12.0",
    "gn:asciiname":"Wangjiawan",
    "gn:country_code":"CN",
    "gn:dem":130,
    "gn:feature_class":"P",
    "gn:feature_code":"PPL",
    "gn:name":"Wangjiawan",
    "gn:population":0,
    "gn:timezone":"Asia/Shanghai",
    "iso:country":"CN",
    "name:deu_x_preferred":[
        "Wangjiawan"
    ],
    "name:zho_x_preferred":[
        "\u738b\u5bb6\u5846"
    ],
    "wof:name":"Wangjiawan",
    "wof:placetype":"locality"
},
  "geometry": {"coordinates":[113.47123999999999,32.01799],"type":"Point"}
}