{
  "type": "Feature",
  "properties": {
    "gn:admin1_code":"11.0",
    "gn:asciiname":"Dayuanjia",
    "gn:country_code":"CN",
    "gn:dem":67,
    "gn:feature_class":"P",
    "gn:feature_code":"PPL",
    "gn:name":"Dayuanjia",
    "gn:population":0,
    "gn:timezone":"Asia/Shanghai",
    "iso:country":"CN",
    "name:zho_x_preferred":[
        "\u5927\u8881\u5bb6"
    ],
    "wof:name":"Dayuanjia",
    "wof:placetype":"locality"
},
  "geometry": {"coordinates":[113.19917,29.18836],"type":"Point"}
}