{
  "type": "Feature",
  "properties": {
    "gn:admin1_code":"16.0",
    "gn:asciiname":"Danzhu",
    "gn:country_code":"CN",
    "gn:dem":370,
    "gn:feature_class":"P",
    "gn:feature_code":"PPL",
    "gn:name":"Danzhu",
    "gn:population":0,
    "gn:timezone":"Asia/Shanghai",
    "iso:country":"CN",
    "name:amh_x_preferred":[
        "\u12f3\u1295\u12e1"
    ],
    "name:hun_x_preferred":[
        "Tan-csu"
    ],
    "name:vie_x_preferred":[
        "\u0110an Chu"
    ],
    "name:zho_x_preferred":[
        "\u4e39\u7af9"
    ],
    "wof:name":"Danzhu",
    "wof:placetype":"locality"
},
  "geometry": {"coordinates":[109.38800000000001,25.4939],"type":"Point"}
}