{
  "type": "Feature",
  "properties": {
    "gn:admin1_code":"07",
    "gn:asciiname":"Banding",
    "gn:country_code":"CN",
    "gn:dem":217,
    "gn:feature_class":"P",
    "gn:feature_code":"PPL",
    "gn:name":"Banding",
    "gn:population":0,
    "gn:timezone":"Asia/Shanghai",
    "iso:country":"CN",
    "name:zho_x_preferred":[
        "\u5742\u9876"
    ],
    "wof:name":"Banding",
    "wof:placetype":"locality"
},
  "geometry": {"coordinates":[118.04639,25.14278],"type":"Point"}
}