{
  "type": "Feature",
  "properties": {
    "gn:admin1_code":"29.0",
    "gn:asciiname":"Datiantou",
    "gn:country_code":"CN",
    "gn:dem":2007,
    "gn:feature_class":"P",
    "gn:feature_code":"PPL",
    "gn:name":"Datiantou",
    "gn:population":0,
    "gn:timezone":"Asia/Shanghai",
    "iso:country":"CN",
    "name:zho_x_preferred":[
        "\u5927\u7530\u5934"
    ],
    "wof:name":"Datiantou",
    "wof:placetype":"locality"
},
  "geometry": {"coordinates":[98.97450000000001,25.4289],"type":"Point"}
}