{
  "type": "Feature",
  "properties": {
    "gn:admin1_code":"15.0",
    "gn:asciiname":"Guaibaqiao",
    "gn:country_code":"CN",
    "gn:dem":1424,
    "gn:feature_class":"P",
    "gn:feature_code":"PPL",
    "gn:name":"Guaibaqiao",
    "gn:population":0,
    "gn:timezone":"Asia/Shanghai",
    "iso:country":"CN",
    "name:zho_x_preferred":[
        "\u62d0\u575d\u6865"
    ],
    "wof:name":"Guaibaqiao",
    "wof:placetype":"locality"
},
  "geometry": {"coordinates":[98.5817,39.7962],"type":"Point"}
}