{
  "type": "Feature",
  "properties": {
    "gn:admin1_code":"20.0",
    "gn:asciiname":"Bolihe",
    "gn:country_code":"CN",
    "gn:dem":454,
    "gn:feature_class":"P",
    "gn:feature_code":"PPL",
    "gn:name":"Bolihe",
    "gn:population":0,
    "gn:timezone":"Asia/Shanghai",
    "iso:country":"CN",
    "name:zho_x_preferred":[
        "\u52c3\u529b\u6cb3"
    ],
    "wof:name":"Bolihe",
    "wof:placetype":"locality"
},
  "geometry": {"coordinates":[123.26503999999998,50.09409],"type":"Point"}
}