{
  "type": "Feature",
  "properties": {
    "gn:admin1_code":"4.0",
    "gn:asciiname":"Laoxiaoxucun",
    "gn:country_code":"CN",
    "gn:dem":10,
    "gn:feature_class":"P",
    "gn:feature_code":"PPL",
    "gn:name":"Laoxiaoxucun",
    "gn:population":0,
    "gn:timezone":"Asia/Shanghai",
    "iso:country":"CN",
    "name:zho_x_preferred":[
        "\u8001\u5c0f\u5729\u6751"
    ],
    "wof:name":"Laoxiaoxucun",
    "wof:placetype":"locality"
},
  "geometry": {"coordinates":[118.63849,33.96887],"type":"Point"}
}