{
  "type": "Feature",
  "properties": {
    "gn:admin1_code":"8.0",
    "gn:asciiname":"Xiaoheihe",
    "gn:country_code":"CN",
    "gn:dem":111,
    "gn:feature_class":"P",
    "gn:feature_code":"PPL",
    "gn:name":"Xiaoheihe",
    "gn:population":0,
    "gn:timezone":"Asia/Shanghai",
    "iso:country":"CN",
    "name:zho_x_preferred":[
        "\u5c0f\u9ed1\u6cb3"
    ],
    "wof:name":"Xiaoheihe",
    "wof:placetype":"locality"
},
  "geometry": {"coordinates":[132.38815,45.563],"type":"Point"}
}