{
  "type": "Feature",
  "properties": {
    "gn:admin1_code":"13.0",
    "gn:asciiname":"Sidaohezi",
    "gn:country_code":"CN",
    "gn:dem":357,
    "gn:feature_class":"P",
    "gn:feature_code":"PPLA4",
    "gn:name":"Sidaohezi",
    "gn:population":0,
    "gn:timezone":"Asia/Urumqi",
    "iso:country":"CN",
    "name:und_x_variant":[
        "Sidaohezi Zhen"
    ],
    "name:zho_x_preferred":[
        "\u56db\u9053\u6cb3\u5b50"
    ],
    "name:zho_x_variant":[
        "\u56db\u9053\u6cb3\u5b50\u9547"
    ],
    "wof:name":"Sidaohezi",
    "wof:placetype":"locality"
},
  "geometry": {"coordinates":[85.70456,44.68907],"type":"Point"}
}