{
  "type": "Feature",
  "properties": {
    "gn:admin1_code":"24",
    "gn:asciiname":"Shangsangyuan",
    "gn:country_code":"CN",
    "gn:dem":1123,
    "gn:feature_class":"P",
    "gn:feature_code":"PPL",
    "gn:name":"Shangsangyuan",
    "gn:population":0,
    "gn:timezone":"Asia/Shanghai",
    "iso:country":"CN",
    "name:und_x_variant":[
        "Shang-sang-y\u00fcan",
        "Sangyuan",
        "Shangsangyuan"
    ],
    "name:zho_x_preferred":[
        "\u4e0a\u6851\u539f"
    ],
    "wof:name":"Shangsangyuan",
    "wof:placetype":"locality"
},
  "geometry": {"coordinates":[111.50335,36.68535],"type":"Point"}
}