{
  "type": "Feature",
  "properties": {
    "gn:admin1_code":"04",
    "gn:asciiname":"Dongchengwei",
    "gn:cc2":"CN",
    "gn:country_code":"CN",
    "gn:dem":3,
    "gn:feature_class":"P",
    "gn:feature_code":"PPL",
    "gn:name":"Dongchengwei",
    "gn:population":0,
    "gn:timezone":"Asia/Shanghai",
    "iso:country":"CN",
    "name:und_x_variant":[
        "Tung-ch\u2019eng-yu",
        "Dongchengwei"
    ],
    "wof:name":"Dongchengwei",
    "wof:placetype":"locality"
},
  "geometry": {"coordinates":[120.59083,31.07583],"type":"Point"}
}