{
  "type": "Feature",
  "properties": {
    "gn:admin1_code":"14.0",
    "gn:asciiname":"Tuolading",
    "gn:country_code":"CN",
    "gn:dem":3832,
    "gn:feature_class":"P",
    "gn:feature_code":"PPL",
    "gn:name":"Tuolading",
    "gn:population":0,
    "gn:timezone":"Asia/Urumqi",
    "iso:country":"CN",
    "name:zho_x_preferred":[
        "\u62d6\u62c9\u9876"
    ],
    "wof:name":"Tuolading",
    "wof:placetype":"locality"
},
  "geometry": {"coordinates":[98.58752,29.59538],"type":"Point"}
}