{
  "type": "Feature",
  "properties": {
    "gn:admin1_code":"1.0",
    "gn:asciiname":"Bamaoxiangcun",
    "gn:country_code":"CN",
    "gn:dem":21,
    "gn:feature_class":"P",
    "gn:feature_code":"PPL",
    "gn:name":"Bamaoxiangcun",
    "gn:population":0,
    "gn:timezone":"Asia/Shanghai",
    "iso:country":"CN",
    "name:zho_x_preferred":[
        "\u82ad\u8305\u5df7\u6751"
    ],
    "wof:name":"Bamaoxiangcun",
    "wof:placetype":"locality"
},
  "geometry": {"coordinates":[117.06634,30.5377],"type":"Point"}
}