{
  "type": "Feature",
  "properties": {
    "gn:admin1_code":"11.0",
    "gn:asciiname":"Ma'anpu",
    "gn:country_code":"CN",
    "gn:dem":39,
    "gn:feature_class":"P",
    "gn:feature_code":"PPL",
    "gn:name":"Ma\u2019anpu",
    "gn:population":0,
    "gn:timezone":"Asia/Shanghai",
    "iso:country":"CN",
    "name:und_x_variant":[
        "Ma\u2019anpu"
    ],
    "name:zho_x_preferred":[
        "\u9a6c\u978d\u94fa"
    ],
    "wof:name":"Ma'anpu",
    "wof:placetype":"locality"
},
  "geometry": {"coordinates":[113.0917,28.36404000000001],"type":"Point"}
}