{
  "type": "Feature",
  "properties": {
    "gn:admin1_code":"31.0",
    "gn:asciiname":"Licai Ershiliudui",
    "gn:country_code":"CN",
    "gn:dem":200,
    "gn:feature_class":"P",
    "gn:feature_code":"PPLF",
    "gn:name":"Licai Ershiliudui",
    "gn:population":0,
    "gn:timezone":"Asia/Shanghai",
    "iso:country":"CN",
    "name:und_x_variant":[
        "\u7acb\u624d\u4e8c\u5341\u516d\u961f"
    ],
    "wof:name":"Licai Ershiliudui",
    "wof:placetype":"locality"
},
  "geometry": {"coordinates":[109.34229000000001,18.50356],"type":"Point"}
}