{
  "type": "Feature",
  "properties": {
    "gn:admin1_code":"14.0",
    "gn:asciiname":"Xiakucun",
    "gn:country_code":"CN",
    "gn:dem":3463,
    "gn:feature_class":"P",
    "gn:feature_code":"PPL",
    "gn:name":"Xiakucun",
    "gn:population":0,
    "gn:timezone":"Asia/Urumqi",
    "iso:country":"CN",
    "name:zho_x_preferred":[
        "\u4e0b\u5e93\u6751"
    ],
    "wof:name":"Xiakucun",
    "wof:placetype":"locality"
},
  "geometry": {"coordinates":[98.14845,29.18319],"type":"Point"}
}