{
  "type": "Feature",
  "properties": {
    "gn:admin1_code":"32.0",
    "gn:asciiname":"Youfangcha Niuchang",
    "gn:country_code":"CN",
    "gn:dem":4388,
    "gn:feature_class":"P",
    "gn:feature_code":"PPLF",
    "gn:name":"Youfangcha Niuchang",
    "gn:population":0,
    "gn:timezone":"Asia/Shanghai",
    "iso:country":"CN",
    "name:zho_x_preferred":[
        "\u6cb9\u623f\u8336\u725b\u573a"
    ],
    "wof:name":"Youfangcha Niuchang",
    "wof:placetype":"locality"
},
  "geometry": {"coordinates":[100.42176000000001,28.15872],"type":"Point"}
}