{
  "type": "Feature",
  "properties": {
    "gn:admin1_code":"19.0",
    "gn:asciiname":"Bajianfang",
    "gn:country_code":"CN",
    "gn:dem":35,
    "gn:feature_class":"P",
    "gn:feature_code":"PPL",
    "gn:name":"Bajianfang",
    "gn:population":0,
    "gn:timezone":"Asia/Shanghai",
    "iso:country":"CN",
    "name:zho_x_preferred":[
        "\u516b\u95f4\u623f"
    ],
    "wof:name":"Bajianfang",
    "wof:placetype":"locality"
},
  "geometry": {"coordinates":[123.12392,41.98505],"type":"Point"}
}