{
  "type": "Feature",
  "properties": {
    "gn:admin1_code":"32.0",
    "gn:asciiname":"Beiwanli",
    "gn:country_code":"CN",
    "gn:dem":857,
    "gn:feature_class":"P",
    "gn:feature_code":"PPL",
    "gn:name":"Beiwanli",
    "gn:population":0,
    "gn:timezone":"Asia/Shanghai",
    "iso:country":"CN",
    "name:zho_x_preferred":[
        "\u7891\u6e7e\u91cc"
    ],
    "wof:name":"Beiwanli",
    "wof:placetype":"locality"
},
  "geometry": {"coordinates":[106.47546,32.52835],"type":"Point"}
}