{
  "type": "Feature",
  "properties": {
    "gn:admin1_code":"14.0",
    "gn:asciiname":"Maxuecun",
    "gn:country_code":"CN",
    "gn:dem":3168,
    "gn:feature_class":"P",
    "gn:feature_code":"PPL",
    "gn:name":"Maxuecun",
    "gn:population":0,
    "gn:timezone":"Asia/Urumqi",
    "iso:country":"CN",
    "name:zho_x_preferred":[
        "\u739b\u5b66\u6751"
    ],
    "wof:name":"Maxuecun",
    "wof:placetype":"locality"
},
  "geometry": {"coordinates":[95.48039,30.14268],"type":"Point"}
}