{
  "type": "Feature",
  "properties": {
    "gn:admin1_code":"19.0",
    "gn:asciiname":"Qian'ertaizi",
    "gn:country_code":"CN",
    "gn:dem":42,
    "gn:feature_class":"P",
    "gn:feature_code":"PPL",
    "gn:name":"Qian\u2019ertaizi",
    "gn:population":0,
    "gn:timezone":"Asia/Shanghai",
    "iso:country":"CN",
    "name:und_x_variant":[
        "\u524d\u4e8c\u53f0\u5b50"
    ],
    "name:zho_x_preferred":[
        "Qian\u2019ertaizi"
    ],
    "name:zho_x_variant":[
        "\u524d\u4e8c\u53f0\u5b50"
    ],
    "wof:name":"Qian'ertaizi",
    "wof:placetype":"locality"
},
  "geometry": {"coordinates":[122.7062,42.06996],"type":"Point"}
}