{
  "type": "Feature",
  "properties": {
    "gn:admin1_code":"16.0",
    "gn:asciiname":"Ziyao",
    "gn:country_code":"CN",
    "gn:dem":148,
    "gn:feature_class":"P",
    "gn:feature_code":"PPL",
    "gn:name":"Ziyao",
    "gn:population":0,
    "gn:timezone":"Asia/Shanghai",
    "iso:country":"CN",
    "name:zho_x_preferred":[
        "\u81ea\u5c27"
    ],
    "wof:name":"Ziyao",
    "wof:placetype":"locality"
},
  "geometry": {"coordinates":[107.803,22.3038],"type":"Point"}
}