{
  "type": "Feature",
  "properties": {
    "gn:admin1_code":"25",
    "gn:asciiname":"Jinzhuang",
    "gn:country_code":"CN",
    "gn:dem":113,
    "gn:feature_class":"P",
    "gn:feature_code":"PPL",
    "gn:name":"Jinzhuang",
    "gn:population":0,
    "gn:timezone":"Asia/Shanghai",
    "iso:country":"CN",
    "name:zho_x_preferred":[
        "\u9773\u5e84"
    ],
    "wof:name":"Jinzhuang",
    "wof:placetype":"locality"
},
  "geometry": {"coordinates":[116.913,36.3786],"type":"Point"}
}