{
  "type": "Feature",
  "properties": {
    "gn:admin1_code":"29.0",
    "gn:asciiname":"Mujiawan",
    "gn:country_code":"CN",
    "gn:dem":1931,
    "gn:feature_class":"P",
    "gn:feature_code":"PPL",
    "gn:name":"Mujiawan",
    "gn:population":0,
    "gn:timezone":"Asia/Shanghai",
    "iso:country":"CN",
    "name:zho_x_preferred":[
        "\u7a46\u5bb6\u6e7e"
    ],
    "wof:name":"Mujiawan",
    "wof:placetype":"locality"
},
  "geometry": {"coordinates":[98.6109,24.9094],"type":"Point"}
}