{
  "type": "Feature",
  "properties": {
    "gn:admin1_code":"12.0",
    "gn:asciiname":"Yanjia Ling",
    "gn:country_code":"CN",
    "gn:dem":27,
    "gn:feature_class":"P",
    "gn:feature_code":"PPL",
    "gn:name":"Yanjia Ling",
    "gn:population":0,
    "gn:timezone":"Asia/Shanghai",
    "iso:country":"CN",
    "name:zho_x_preferred":[
        "\u9122\u5bb6\u5cad"
    ],
    "wof:name":"Yanjia Ling",
    "wof:placetype":"locality"
},
  "geometry": {"coordinates":[112.60287,30.02311],"type":"Point"}
}