{
  "type": "Feature",
  "properties": {
    "gn:admin1_code":"16.0",
    "gn:asciiname":"Fengmuping",
    "gn:country_code":"CN",
    "gn:dem":188,
    "gn:feature_class":"P",
    "gn:feature_code":"PPL",
    "gn:name":"Fengmuping",
    "gn:population":0,
    "gn:timezone":"Asia/Shanghai",
    "iso:country":"CN",
    "name:zho_x_preferred":[
        "\u67ab\u6728\u576a"
    ],
    "wof:name":"Fengmuping",
    "wof:placetype":"locality"
},
  "geometry": {"coordinates":[110.105,22.1924],"type":"Point"}
}