{
  "type": "Feature",
  "properties": {
    "gn:admin1_code":"32.0",
    "gn:asciiname":"Liangban",
    "gn:country_code":"CN",
    "gn:dem":486,
    "gn:feature_class":"P",
    "gn:feature_code":"PPL",
    "gn:name":"Liangban",
    "gn:population":0,
    "gn:timezone":"Asia/Shanghai",
    "iso:country":"CN",
    "name:zho_x_preferred":[
        "\u6881\u677f"
    ],
    "wof:name":"Liangban",
    "wof:placetype":"locality"
},
  "geometry": {"coordinates":[106.96657,30.25592],"type":"Point"}
}