{
  "type": "Feature",
  "properties": {
    "gn:admin1_code":"3",
    "gn:asciiname":"Yaoshang",
    "gn:country_code":"CN",
    "gn:dem":257,
    "gn:feature_class":"P",
    "gn:feature_code":"PPL",
    "gn:name":"Yaoshang",
    "gn:population":0,
    "gn:timezone":"Asia/Shanghai",
    "iso:country":"CN",
    "name:und_x_variant":[
        "\u6447\u4e0a"
    ],
    "wof:name":"Yaoshang",
    "wof:placetype":"locality"
},
  "geometry": {"coordinates":[116.01505,27.32838],"type":"Point"}
}