{
  "type": "Feature",
  "properties": {
    "gn:admin1_code":"18",
    "gn:asciiname":"Jichangcun",
    "gn:country_code":"CN",
    "gn:dem":1596,
    "gn:feature_class":"P",
    "gn:feature_code":"PPLF",
    "gn:name":"Jichangcun",
    "gn:population":0,
    "gn:timezone":"Asia/Shanghai",
    "iso:country":"CN",
    "name:zho_x_preferred":[
        "\u9e21\u573a\u6751"
    ],
    "wof:name":"Jichangcun",
    "wof:placetype":"locality"
},
  "geometry": {"coordinates":[105.413,26.7743],"type":"Point"}
}