{
  "type": "Feature",
  "properties": {
    "gn:admin1_code":"22.0",
    "gn:asciiname":"Guandaocun",
    "gn:country_code":"CN",
    "gn:dem":44,
    "gn:feature_class":"P",
    "gn:feature_code":"PPL",
    "gn:name":"Guandaocun",
    "gn:population":0,
    "gn:timezone":"Asia/Shanghai",
    "iso:country":"CN",
    "name:zho_x_preferred":[
        "\u5b98\u9053\u6751"
    ],
    "wof:name":"Guandaocun",
    "wof:placetype":"locality"
},
  "geometry": {"coordinates":[116.14411,39.67868],"type":"Point"}
}