{
  "type": "Feature",
  "properties": {
    "gn:admin1_code":"32.0",
    "gn:asciiname":"Niulanwan",
    "gn:country_code":"CN",
    "gn:dem":404,
    "gn:feature_class":"P",
    "gn:feature_code":"PPL",
    "gn:name":"Niulanwan",
    "gn:population":0,
    "gn:timezone":"Asia/Shanghai",
    "iso:country":"CN",
    "name:zho_x_preferred":[
        "\u725b\u62e6\u6e7e"
    ],
    "wof:name":"Niulanwan",
    "wof:placetype":"locality"
},
  "geometry": {"coordinates":[104.846,28.8382],"type":"Point"}
}