{
  "type": "Feature",
  "properties": {
    "gn:admin1_code":"29",
    "gn:asciiname":"Shuangjiang",
    "gn:country_code":"CN",
    "gn:dem":1544,
    "gn:feature_class":"P",
    "gn:feature_code":"PPLA3",
    "gn:name":"Shuangjiang",
    "gn:population":0,
    "gn:timezone":"Asia/Shanghai",
    "iso:country":"CN",
    "name:und_x_variant":[
        "Eshan",
        "Hsi-o",
        "Ngeshan-hsien",
        "Sihohsien",
        "O-shan-hsien",
        "O-shan-i-tsu-tzu-chih-hsien",
        "O-shan",
        "Eshan Yizu Zizhixian",
        "Shuangjiang Zhen",
        "Shuangjiang"
    ],
    "name:zho_x_preferred":[
        "O-shan-hsien-i-tsu-tzu-chih-ch\u2019\u00fc"
    ],
    "name:zho_x_variant":[
        "\u53cc\u6c5f",
        "\u53cc\u6c5f\u9547",
        "\u5ce8\u5c71\u5f5d\u65cf\u81ea\u6cbb\u53bf"
    ],
    "wof:name":"Shuangjiang",
    "wof:placetype":"locality"
},
  "geometry": {"coordinates":[102.40049,24.17261],"type":"Point"}
}