{
  "type": "Feature",
  "properties": {
    "gn:admin1_code":"16.0",
    "gn:asciiname":"Jialing",
    "gn:country_code":"CN",
    "gn:dem":95,
    "gn:feature_class":"P",
    "gn:feature_code":"PPL",
    "gn:name":"Jialing",
    "gn:population":0,
    "gn:timezone":"Asia/Shanghai",
    "iso:country":"CN",
    "name:ara_x_preferred":[
        "\u062c\u064a\u0627\u0644\u064a\u0646\u063a"
    ],
    "name:ceb_x_preferred":[
        "Jialing"
    ],
    "name:deu_x_preferred":[
        "Jialing"
    ],
    "name:ell_x_preferred":[
        "\u0393\u03b9\u03b1\u03bb\u03af\u03bd\u03b3\u03ba"
    ],
    "name:fas_x_preferred":[
        "\u062c\u06cc\u0627\u0644\u06cc\u0646\u06af"
    ],
    "name:fra_x_preferred":[
        "Jialing"
    ],
    "name:hin_x_preferred":[
        "\u091c\u093f\u0932\u093f\u0902\u0917"
    ],
    "name:hun_x_preferred":[
        "Jialing"
    ],
    "name:ind_x_preferred":[
        "Jialing"
    ],
    "name:nor_x_preferred":[
        "Jialing"
    ],
    "name:ukr_x_preferred":[
        "\u0414\u0436\u0456\u0430\u043b\u0456\u043d\u044c"
    ],
    "name:urd_x_preferred":[
        "\u062c\u06cc\u0627\u0644\u0646\u06af"
    ],
    "name:zho_x_preferred":[
        "\u7532\u5cad"
    ],
    "wof:name":"Jialing",
    "wof:placetype":"locality"
},
  "geometry": {"coordinates":[109.23999999999999,23.8734],"type":"Point"}
}