{
  "type": "Feature",
  "properties": {
    "gn:admin1_code":"16.0",
    "gn:asciiname":"Jialing",
    "gn:country_code":"CN",
    "gn:dem":95,
    "gn:feature_class":"P",
    "gn:feature_code":"PPL",
    "gn:name":"Jialing",
    "gn:population":0,
    "gn:timezone":"Asia/Shanghai",
    "iso:country":"CN",
    "name:ceb_x_preferred":[
        "Jialing"
    ],
    "name:deu_x_preferred":[
        "Jialing"
    ],
    "name:fra_x_preferred":[
        "Jialing"
    ],
    "name:nor_x_preferred":[
        "Jialing"
    ],
    "name:zho_x_preferred":[
        "\u7532\u5cad"
    ],
    "wof:name":"Jialing",
    "wof:placetype":"locality"
},
  "geometry": {"coordinates":[109.23999999999999,23.8734],"type":"Point"}
}