{
  "type": "Feature",
  "properties": {
    "gn:admin1_code":"4.0",
    "gn:asciiname":"Yediancun",
    "gn:country_code":"CN",
    "gn:dem":1,
    "gn:feature_class":"P",
    "gn:feature_code":"PPL",
    "gn:name":"Yediancun",
    "gn:population":0,
    "gn:timezone":"Asia/Shanghai",
    "iso:country":"CN",
    "name:und_x_variant":[
        "Yedian",
        "\u53f6\u7538",
        "Yediancun"
    ],
    "name:zho_x_preferred":[
        "\u53f6\u7538\u6751"
    ],
    "wof:name":"Yediancun",
    "wof:placetype":"locality"
},
  "geometry": {"coordinates":[119.97553000000001,32.64288],"type":"Point"}
}