{
  "type": "Feature",
  "properties": {
    "gn:admin1_code":"12",
    "gn:asciiname":"Sanyang",
    "gn:country_code":"CN",
    "gn:dem":113,
    "gn:feature_class":"P",
    "gn:feature_code":"PPLA4",
    "gn:name":"Sanyang",
    "gn:population":0,
    "gn:timezone":"Asia/Shanghai",
    "iso:country":"CN",
    "name:ceb_x_preferred":[
        "Sanyang"
    ],
    "name:deu_x_preferred":[
        "Sanyang"
    ],
    "name:swe_x_preferred":[
        "Sanyang"
    ],
    "name:und_x_variant":[
        "\u4e09\u9633",
        "Sanyang Zhen",
        "\u4e09\u9633\u9547"
    ],
    "wof:name":"Sanyang",
    "wof:placetype":"locality"
},
  "geometry": {"coordinates":[113.18447999999999,31.31647],"type":"Point"}
}