{
  "type": "Feature",
  "properties": {
    "gn:admin1_code":"15.0",
    "gn:asciiname":"Xiayangwa",
    "gn:country_code":"CN",
    "gn:dem":1861,
    "gn:feature_class":"P",
    "gn:feature_code":"PPL",
    "gn:name":"Xiayangwa",
    "gn:population":0,
    "gn:timezone":"Asia/Shanghai",
    "iso:country":"CN",
    "name:zho_x_preferred":[
        "\u4e0b\u9633\u6d3c"
    ],
    "wof:name":"Xiayangwa",
    "wof:placetype":"locality"
},
  "geometry": {"coordinates":[105.31699999999999,36.1691],"type":"Point"}
}