{
  "type": "Feature",
  "properties": {
    "gn:admin1_code":"03",
    "gn:asciiname":"Sanxing",
    "gn:country_code":"CN",
    "gn:dem":120,
    "gn:feature_class":"P",
    "gn:feature_code":"PPLA4",
    "gn:name":"Sanxing",
    "gn:population":0,
    "gn:timezone":"Asia/Shanghai",
    "iso:country":"CN",
    "name:und_x_variant":[
        "San-hsing",
        "San-po-ch\u2019iu",
        "San-pai-hsing",
        "San-pai-ch\u2019iu",
        "Sanxing",
        "\u4e09\u5174",
        "Sanxing Zhen",
        "\u4e09\u5174\u9547"
    ],
    "wof:name":"Sanxing",
    "wof:placetype":"locality"
},
  "geometry": {"coordinates":[114.46144,28.21553],"type":"Point"}
}