{
  "type": "Feature",
  "properties": {
    "gn:admin1_code":"21.0",
    "gn:asciiname":"Shijingzihekou",
    "gn:country_code":"CN",
    "gn:dem":1497,
    "gn:feature_class":"P",
    "gn:feature_code":"PPL",
    "gn:name":"Shijingzihekou",
    "gn:population":0,
    "gn:timezone":"Asia/Shanghai",
    "iso:country":"CN",
    "name:zho_x_preferred":[
        "\u77f3\u4e95\u5b50\u6cb3\u53e3"
    ],
    "wof:name":"Shijingzihekou",
    "wof:placetype":"locality"
},
  "geometry": {"coordinates":[106.27291,36.55627],"type":"Point"}
}