{
  "type": "Feature",
  "properties": {
    "gn:admin1_code":"19.0",
    "gn:asciiname":"Guchengzicun",
    "gn:country_code":"CN",
    "gn:dem":29,
    "gn:feature_class":"P",
    "gn:feature_code":"PPL",
    "gn:name":"Guchengzicun",
    "gn:population":0,
    "gn:timezone":"Asia/Shanghai",
    "iso:country":"CN",
    "name:zho_x_preferred":[
        "\u53e4\u57ce\u5b50\u6751"
    ],
    "wof:name":"Guchengzicun",
    "wof:placetype":"locality"
},
  "geometry": {"coordinates":[120.98578999999999,41.02535],"type":"Point"}
}