{
  "type": "Feature",
  "properties": {
    "gn:admin1_code":"29",
    "gn:asciiname":"Zhushiye",
    "gn:country_code":"CN",
    "gn:dem":2125,
    "gn:feature_class":"P",
    "gn:feature_code":"PPL",
    "gn:name":"Zhushiye",
    "gn:population":0,
    "gn:timezone":"Asia/Shanghai",
    "iso:country":"CN",
    "name:zho_x_preferred":[
        "\u73e0\u77f3\u51b6"
    ],
    "wof:name":"Zhushiye",
    "wof:placetype":"locality"
},
  "geometry": {"coordinates":[102.11920000000001,24.60398],"type":"Point"}
}