{
  "type": "Feature",
  "properties": {
    "gn:admin1_code":"16.0",
    "gn:asciiname":"Bakan",
    "gn:country_code":"CN",
    "gn:dem":637,
    "gn:feature_class":"P",
    "gn:feature_code":"PPL",
    "gn:name":"Bakan",
    "gn:population":0,
    "gn:timezone":"Asia/Shanghai",
    "iso:country":"CN",
    "name:ceb_x_preferred":[
        "Bakan"
    ],
    "name:deu_x_preferred":[
        "Bakan"
    ],
    "name:swe_x_preferred":[
        "Bakan"
    ],
    "name:zho_x_preferred":[
        "\u5df4\u574e"
    ],
    "wof:name":"Bakan",
    "wof:placetype":"locality"
},
  "geometry": {"coordinates":[106.598,22.9929],"type":"Point"}
}