{
  "type": "Feature",
  "properties": {
    "gn:admin1_code":"29.0",
    "gn:asciiname":"Fenshantou",
    "gn:country_code":"CN",
    "gn:dem":1778,
    "gn:feature_class":"P",
    "gn:feature_code":"PPL",
    "gn:name":"Fenshantou",
    "gn:population":0,
    "gn:timezone":"Asia/Shanghai",
    "iso:country":"CN",
    "name:zho_x_preferred":[
        "\u575f\u5c71\u5934"
    ],
    "wof:name":"Fenshantou",
    "wof:placetype":"locality"
},
  "geometry": {"coordinates":[101.14,24.3158],"type":"Point"}
}