{
  "type": "Feature",
  "properties": {
    "gn:admin1_code":"31.0",
    "gn:asciiname":"Changhao Yidui",
    "gn:country_code":"CN",
    "gn:dem":410,
    "gn:feature_class":"P",
    "gn:feature_code":"PPLF",
    "gn:name":"Changhao Yidui",
    "gn:population":0,
    "gn:timezone":"Asia/Shanghai",
    "iso:country":"CN",
    "name:und_x_variant":[
        "\u7545\u597d\u4e00\u961f"
    ],
    "wof:name":"Changhao Yidui",
    "wof:placetype":"locality"
},
  "geometry": {"coordinates":[109.55297,18.72193],"type":"Point"}
}