{
  "type": "Feature",
  "properties": {
    "gn:admin1_code":"32.0",
    "gn:asciiname":"Huaishuba",
    "gn:country_code":"CN",
    "gn:dem":729,
    "gn:feature_class":"P",
    "gn:feature_code":"PPL",
    "gn:name":"Huaishuba",
    "gn:population":0,
    "gn:timezone":"Asia/Shanghai",
    "iso:country":"CN",
    "name:zho_x_preferred":[
        "\u69d0\u6811\u575d"
    ],
    "wof:name":"Huaishuba",
    "wof:placetype":"locality"
},
  "geometry": {"coordinates":[105.71314,32.57229],"type":"Point"}
}