{
  "type": "Feature",
  "properties": {
    "gn:admin1_code":"26.0",
    "gn:asciiname":"Xujiacun",
    "gn:country_code":"CN",
    "gn:dem":765,
    "gn:feature_class":"P",
    "gn:feature_code":"PPL",
    "gn:name":"Xujiacun",
    "gn:population":0,
    "gn:timezone":"Asia/Shanghai",
    "iso:country":"CN",
    "name:zho_x_preferred":[
        "\u8bb8\u5bb6\u6751"
    ],
    "wof:name":"Xujiacun",
    "wof:placetype":"locality"
},
  "geometry": {"coordinates":[109.66943000000001,35.2353],"type":"Point"}
}