{
  "type": "Feature",
  "properties": {
    "gn:admin1_code":"26.0",
    "gn:asciiname":"Caohecun",
    "gn:country_code":"CN",
    "gn:dem":1278,
    "gn:feature_class":"P",
    "gn:feature_code":"PPL",
    "gn:name":"Caohecun",
    "gn:population":0,
    "gn:timezone":"Asia/Shanghai",
    "iso:country":"CN",
    "name:zho_x_preferred":[
        "\u66f9\u6cb3\u6751"
    ],
    "wof:name":"Caohecun",
    "wof:placetype":"locality"
},
  "geometry": {"coordinates":[109.15895999999999,36.96939],"type":"Point"}
}