{
  "type": "Feature",
  "properties": {
    "gn:admin1_code":"9.0",
    "gn:asciiname":"Luozhuang",
    "gn:country_code":"CN",
    "gn:dem":189,
    "gn:feature_class":"P",
    "gn:feature_code":"PPL",
    "gn:name":"Luozhuang",
    "gn:population":0,
    "gn:timezone":"Asia/Shanghai",
    "iso:country":"CN",
    "name:und_x_variant":[
        "\u7f57\u5e84",
        "Luozhuang"
    ],
    "wof:name":"Luozhuang",
    "wof:placetype":"locality"
},
  "geometry": {"coordinates":[112.31303,33.06129],"type":"Point"}
}