{
  "type": "Feature",
  "properties": {
    "gn:admin1_code":"9",
    "gn:asciiname":"Diji",
    "gn:country_code":"CN",
    "gn:dem":46,
    "gn:feature_class":"P",
    "gn:feature_code":"PPL",
    "gn:name":"Diji",
    "gn:population":0,
    "gn:timezone":"Asia/Shanghai",
    "iso:country":"CN",
    "name:zho_x_preferred":[
        "\u7fdf\u96c6"
    ],
    "wof:name":"Diji",
    "wof:placetype":"locality"
},
  "geometry": {"coordinates":[115.23099999999999,33.905],"type":"Point"}
}