{
  "type": "Feature",
  "properties": {
    "gn:admin1_code":"15.0",
    "gn:asciiname":"Dagouquan",
    "gn:country_code":"CN",
    "gn:dem":2821,
    "gn:feature_class":"P",
    "gn:feature_code":"PPL",
    "gn:name":"Dagouquan",
    "gn:population":0,
    "gn:timezone":"Asia/Shanghai",
    "iso:country":"CN",
    "name:zho_x_preferred":[
        "\u5927\u6c9f\u5708"
    ],
    "wof:name":"Dagouquan",
    "wof:placetype":"locality"
},
  "geometry": {"coordinates":[103.752,37.0523],"type":"Point"}
}