{
  "type": "Feature",
  "properties": {
    "gn:admin1_code":"12.0",
    "gn:asciiname":"Yangtaiping",
    "gn:country_code":"CN",
    "gn:dem":932,
    "gn:feature_class":"P",
    "gn:feature_code":"PPL",
    "gn:name":"Yangtaiping",
    "gn:population":0,
    "gn:timezone":"Asia/Shanghai",
    "iso:country":"CN",
    "name:zho_x_preferred":[
        "\u9633\u592a\u576a"
    ],
    "wof:name":"Yangtaiping",
    "wof:placetype":"locality"
},
  "geometry": {"coordinates":[111.53579999999999,31.71986],"type":"Point"}
}