{
  "type": "Feature",
  "properties": {
    "gn:admin1_code":"18",
    "gn:asciiname":"Longchang",
    "gn:country_code":"CN",
    "gn:dem":1050,
    "gn:feature_class":"P",
    "gn:feature_code":"PPL",
    "gn:name":"Longchang",
    "gn:population":0,
    "gn:timezone":"Asia/Shanghai",
    "iso:country":"CN",
    "name:ceb_x_preferred":[
        "Longchang Xian"
    ],
    "name:deu_x_preferred":[
        "Longchang"
    ],
    "name:ita_x_preferred":[
        "Longchang"
    ],
    "name:jpn_x_preferred":[
        "\u9686\u660c\u5e02"
    ],
    "name:kor_x_preferred":[
        "\ub8fd\ucc3d\uc2dc"
    ],
    "name:nor_x_preferred":[
        "Longchang"
    ],
    "name:rus_x_preferred":[
        "\u041b\u0443\u043d\u0447\u0430\u043d"
    ],
    "name:swe_x_preferred":[
        "Longchang"
    ],
    "name:vie_x_preferred":[
        "Long X\u01b0\u01a1ng"
    ],
    "name:zho_x_preferred":[
        "\u9686\u660c\u5e02"
    ],
    "wof:name":"Longchang",
    "wof:placetype":"locality"
},
  "geometry": {"coordinates":[105.78222,27.66444000000001],"type":"Point"}
}