{
  "type": "Feature",
  "properties": {
    "gn:admin1_code":"16",
    "gn:asciiname":"Jieshou",
    "gn:cc2":"CN",
    "gn:country_code":"CN",
    "gn:dem":204,
    "gn:feature_class":"P",
    "gn:feature_code":"PPL",
    "gn:name":"Jieshou",
    "gn:population":0,
    "gn:timezone":"Asia/Shanghai",
    "iso:country":"CN",
    "name:und_x_variant":[
        "Chieh-shou",
        "Jieshou"
    ],
    "wof:name":"Jieshou",
    "wof:placetype":"locality"
},
  "geometry": {"coordinates":[110.75778,25.72417],"type":"Point"}
}