{
  "type": "Feature",
  "properties": {
    "gn:admin1_code":"30.0",
    "gn:asciiname":"Daoji",
    "gn:country_code":"CN",
    "gn:dem":42,
    "gn:feature_class":"P",
    "gn:feature_code":"PPL",
    "gn:name":"Daoji",
    "gn:population":0,
    "gn:timezone":"Asia/Shanghai",
    "iso:country":"CN",
    "name:und_x_variant":[
        "\u5230\u5409"
    ],
    "name:zho_x_preferred":[
        "\u5230\u5409"
    ],
    "wof:name":"Daoji",
    "wof:placetype":"locality"
},
  "geometry": {"coordinates":[114.75977,23.78726],"type":"Point"}
}