{
  "type": "Feature",
  "properties": {
    "gn:admin1_code":"15.0",
    "gn:asciiname":"Dangqianzhuang",
    "gn:country_code":"CN",
    "gn:dem":1334,
    "gn:feature_class":"P",
    "gn:feature_code":"PPL",
    "gn:name":"Dangqianzhuang",
    "gn:population":0,
    "gn:timezone":"Asia/Shanghai",
    "iso:country":"CN",
    "name:und_x_variant":[
        "\u515a\u524d\u5e84"
    ],
    "wof:name":"Dangqianzhuang",
    "wof:placetype":"locality"
},
  "geometry": {"coordinates":[107.84986000000001,36.49367],"type":"Point"}
}