{
  "type": "Feature",
  "properties": {
    "gn:admin1_code":"7.0",
    "gn:asciiname":"Nanmenlou",
    "gn:country_code":"CN",
    "gn:dem":243,
    "gn:feature_class":"P",
    "gn:feature_code":"PPL",
    "gn:name":"Nanmenlou",
    "gn:population":0,
    "gn:timezone":"Asia/Shanghai",
    "iso:country":"CN",
    "name:zho_x_preferred":[
        "\u5357\u95e8\u697c"
    ],
    "wof:name":"Nanmenlou",
    "wof:placetype":"locality"
},
  "geometry": {"coordinates":[119.36938000000001,26.96865],"type":"Point"}
}