{
  "type": "Feature",
  "properties": {
    "gn:admin1_code":"33.0",
    "gn:asciiname":"Daling",
    "gn:country_code":"CN",
    "gn:dem":297,
    "gn:feature_class":"P",
    "gn:feature_code":"PPL",
    "gn:name":"Daling",
    "gn:population":0,
    "gn:timezone":"Asia/Shanghai",
    "iso:country":"CN",
    "name:ceb_x_preferred":[
        "Daling"
    ],
    "name:swe_x_preferred":[
        "Daling"
    ],
    "name:zho_x_preferred":[
        "\u5927\u53e6"
    ],
    "wof:name":"Daling",
    "wof:placetype":"locality"
},
  "geometry": {"coordinates":[108.48956,31.21329],"type":"Point"}
}