{
  "type": "Feature",
  "properties": {
    "gn:admin1_code":"11.0",
    "gn:asciiname":"Shuinaoli",
    "gn:country_code":"CN",
    "gn:dem":1021,
    "gn:feature_class":"P",
    "gn:feature_code":"PPL",
    "gn:name":"Shuinaoli",
    "gn:population":0,
    "gn:timezone":"Asia/Shanghai",
    "iso:country":"CN",
    "name:zho_x_preferred":[
        "\u6c34\u8111\u91cc"
    ],
    "wof:name":"Shuinaoli",
    "wof:placetype":"locality"
},
  "geometry": {"coordinates":[113.95407,26.11276],"type":"Point"}
}