{
  "type": "Feature",
  "properties": {
    "gn:admin1_code":"14.0",
    "gn:asciiname":"Zhuori",
    "gn:country_code":"CN",
    "gn:dem":4147,
    "gn:feature_class":"P",
    "gn:feature_code":"PPL",
    "gn:name":"Zhuori",
    "gn:population":0,
    "gn:timezone":"Asia/Urumqi",
    "iso:country":"CN",
    "name:zho_x_preferred":[
        "\u5353\u65e5"
    ],
    "wof:name":"Zhuori",
    "wof:placetype":"locality"
},
  "geometry": {"coordinates":[87.18510000000001,29.1446],"type":"Point"}
}