{
  "type": "Feature",
  "properties": {
    "gn:admin1_code":"8.0",
    "gn:asciiname":"Jijiadian",
    "gn:country_code":"CN",
    "gn:dem":289,
    "gn:feature_class":"P",
    "gn:feature_code":"PPL",
    "gn:name":"Jijiadian",
    "gn:population":0,
    "gn:timezone":"Asia/Shanghai",
    "iso:country":"CN",
    "name:zho_x_preferred":[
        "\u7eaa\u5bb6\u5e97"
    ],
    "wof:name":"Jijiadian",
    "wof:placetype":"locality"
},
  "geometry": {"coordinates":[126.29881,47.67038],"type":"Point"}
}