{
  "type": "Feature",
  "properties": {
    "gn:admin1_code":"15.0",
    "gn:asciiname":"Xingjiashan",
    "gn:country_code":"CN",
    "gn:dem":2402,
    "gn:feature_class":"P",
    "gn:feature_code":"PPL",
    "gn:name":"Xingjiashan",
    "gn:population":0,
    "gn:timezone":"Asia/Shanghai",
    "iso:country":"CN",
    "name:zho_x_preferred":[
        "\u5211\u5bb6\u5c71"
    ],
    "wof:name":"Xingjiashan",
    "wof:placetype":"locality"
},
  "geometry": {"coordinates":[104.00700000000001,35.205],"type":"Point"}
}