{
  "type": "Feature",
  "properties": {
    "gn:admin1_code":"15.0",
    "gn:asciiname":"Xujiagou Erdui",
    "gn:country_code":"CN",
    "gn:dem":1464,
    "gn:feature_class":"P",
    "gn:feature_code":"PPLF",
    "gn:name":"Xujiagou Erdui",
    "gn:population":0,
    "gn:timezone":"Asia/Shanghai",
    "iso:country":"CN",
    "name:zho_x_preferred":[
        "\u5f90\u5bb6\u6c9f\u4e8c\u961f"
    ],
    "wof:name":"Xujiagou Erdui",
    "wof:placetype":"locality"
},
  "geometry": {"coordinates":[96.94329999999999,40.3768],"type":"Point"}
}