{
  "type": "Feature",
  "properties": {
    "gn:admin1_code":"15.0",
    "gn:asciiname":"Lijiayinpo",
    "gn:country_code":"CN",
    "gn:dem":1969,
    "gn:feature_class":"P",
    "gn:feature_code":"PPL",
    "gn:name":"Lijiayinpo",
    "gn:population":0,
    "gn:timezone":"Asia/Shanghai",
    "iso:country":"CN",
    "name:und_x_variant":[
        "\u6817\u5bb6\u9634\u5761"
    ],
    "wof:name":"Lijiayinpo",
    "wof:placetype":"locality"
},
  "geometry": {"coordinates":[104.94199999999999,34.9529],"type":"Point"}
}