{
  "type": "Feature",
  "properties": {
    "gn:admin1_code":"32.0",
    "gn:asciiname":"Shikuang",
    "gn:country_code":"CN",
    "gn:dem":585,
    "gn:feature_class":"P",
    "gn:feature_code":"PPL",
    "gn:name":"Shikuang",
    "gn:population":0,
    "gn:timezone":"Asia/Shanghai",
    "iso:country":"CN",
    "name:und_x_variant":[
        "\u77f3\u77ff",
        "Shikuangxiang",
        "\u77f3\u77ff\u4e61"
    ],
    "wof:name":"Shikuang",
    "wof:placetype":"locality"
},
  "geometry": {"coordinates":[106.79836,32.26641],"type":"Point"}
}