{
  "type": "Feature",
  "properties": {
    "gn:admin1_code":"31",
    "gn:asciiname":"Lanliu",
    "gn:country_code":"CN",
    "gn:dem":25,
    "gn:feature_class":"P",
    "gn:feature_code":"PPL",
    "gn:name":"Lanliu",
    "gn:population":0,
    "gn:timezone":"Asia/Shanghai",
    "iso:country":"CN",
    "name:und_x_variant":[
        "\u5170\u5218"
    ],
    "wof:name":"Lanliu",
    "wof:placetype":"locality"
},
  "geometry": {"coordinates":[109.64333000000001,19.98778],"type":"Point"}
}