{
  "type": "Feature",
  "properties": {
    "gn:admin1_code":"26.0",
    "gn:asciiname":"Punancun",
    "gn:country_code":"CN",
    "gn:dem":628,
    "gn:feature_class":"P",
    "gn:feature_code":"PPL",
    "gn:name":"Punancun",
    "gn:population":0,
    "gn:timezone":"Asia/Shanghai",
    "iso:country":"CN",
    "name:zho_x_preferred":[
        "\u6734\u5357\u6751"
    ],
    "wof:name":"Punancun",
    "wof:placetype":"locality"
},
  "geometry": {"coordinates":[107.22492,34.32705],"type":"Point"}
}