{
  "type": "Feature",
  "properties": {
    "gn:admin1_code":"8.0",
    "gn:asciiname":"Weixingcun",
    "gn:country_code":"CN",
    "gn:dem":173,
    "gn:feature_class":"P",
    "gn:feature_code":"PPL",
    "gn:name":"Weixingcun",
    "gn:population":0,
    "gn:timezone":"Asia/Shanghai",
    "iso:country":"CN",
    "name:zho_x_preferred":[
        "\u536b\u661f\u6751"
    ],
    "wof:name":"Weixingcun",
    "wof:placetype":"locality"
},
  "geometry": {"coordinates":[127.88169000000001,46.25984],"type":"Point"}
}