{
  "type": "Feature",
  "properties": {
    "gn:admin1_code":"31.0",
    "gn:asciiname":"Sangtou",
    "gn:country_code":"CN",
    "gn:dem":26,
    "gn:feature_class":"P",
    "gn:feature_code":"PPL",
    "gn:name":"Sangtou",
    "gn:population":0,
    "gn:timezone":"Asia/Shanghai",
    "iso:country":"CN",
    "name:zho_x_preferred":[
        "\u78c9\u5934"
    ],
    "wof:name":"Sangtou",
    "wof:placetype":"locality"
},
  "geometry": {"coordinates":[110.36002000000001,18.89266],"type":"Point"}
}