{
  "type": "Feature",
  "properties": {
    "gn:admin1_code":"12.0",
    "gn:asciiname":"Zhanjiaji",
    "gn:country_code":"CN",
    "gn:dem":28,
    "gn:feature_class":"P",
    "gn:feature_code":"PPLA4",
    "gn:name":"Zhanjiaji",
    "gn:population":0,
    "gn:timezone":"Asia/Shanghai",
    "iso:country":"CN",
    "name:und_x_variant":[
        "\u6e5b\u5bb6\u77f6",
        "Zhanjiaji Jiedao",
        "\u6e5b\u5bb6\u77f6\u8857\u9053"
    ],
    "wof:name":"Zhanjiaji",
    "wof:placetype":"locality"
},
  "geometry": {"coordinates":[114.3518,30.669],"type":"Point"}
}