{
  "type": "Feature",
  "properties": {
    "gn:admin1_code":"14.0",
    "gn:asciiname":"Cuobu",
    "gn:country_code":"CN",
    "gn:dem":4618,
    "gn:feature_class":"P",
    "gn:feature_code":"PPL",
    "gn:name":"Cuobu",
    "gn:population":0,
    "gn:timezone":"Asia/Urumqi",
    "iso:country":"CN",
    "name:zho_x_preferred":[
        "\u9519\u4e0d"
    ],
    "wof:name":"Cuobu",
    "wof:placetype":"locality"
},
  "geometry": {"coordinates":[90.80119999999999,31.31612],"type":"Point"}
}