{
  "type": "Feature",
  "properties": {
    "gn:admin1_code":"30",
    "gn:asciiname":"Guanlan",
    "gn:country_code":"CN",
    "gn:dem":36,
    "gn:feature_class":"P",
    "gn:feature_code":"PPLA4",
    "gn:name":"Guanlan",
    "gn:population":0,
    "gn:timezone":"Asia/Shanghai",
    "iso:country":"CN",
    "name:und_x_variant":[
        "Kuan-lan-hs\u00fc",
        "Kuan-lan",
        "Guanlan",
        "Guanlan Jiedao",
        "\u89c2\u6f9c\u8857\u9053"
    ],
    "wof:name":"Guanlan",
    "wof:placetype":"locality"
},
  "geometry": {"coordinates":[114.05244,22.7211],"type":"Point"}
}