{
  "type": "Feature",
  "properties": {
    "gn:admin1_code":"19.0",
    "gn:asciiname":"Wumingtuncun",
    "gn:country_code":"CN",
    "gn:dem":86,
    "gn:feature_class":"P",
    "gn:feature_code":"PPL",
    "gn:name":"Wumingtuncun",
    "gn:population":0,
    "gn:timezone":"Asia/Shanghai",
    "iso:country":"CN",
    "name:zho_x_preferred":[
        "\u52a1\u540d\u5c6f\u6751"
    ],
    "wof:name":"Wumingtuncun",
    "wof:placetype":"locality"
},
  "geometry": {"coordinates":[123.48999999999999,42.3215],"type":"Point"}
}