{
  "type": "Feature",
  "properties": {
    "gn:admin1_code":"20.0",
    "gn:asciiname":"Hetaodi Yingzi",
    "gn:country_code":"CN",
    "gn:dem":473,
    "gn:feature_class":"P",
    "gn:feature_code":"PPL",
    "gn:name":"Hetaodi Yingzi",
    "gn:population":0,
    "gn:timezone":"Asia/Shanghai",
    "iso:country":"CN",
    "name:zho_x_preferred":[
        "\u6cb3\u5957\u5730\u8425\u5b50"
    ],
    "wof:name":"Hetaodi Yingzi",
    "wof:placetype":"locality"
},
  "geometry": {"coordinates":[119.81616,51.25514],"type":"Point"}
}