{
  "type": "Feature",
  "properties": {
    "gn:admin1_code":"11.0",
    "gn:asciiname":"Xinwutou",
    "gn:country_code":"CN",
    "gn:dem":642,
    "gn:feature_class":"P",
    "gn:feature_code":"PPL",
    "gn:name":"Xinwutou",
    "gn:population":0,
    "gn:timezone":"Asia/Shanghai",
    "iso:country":"CN",
    "name:zho_x_preferred":[
        "\u65b0\u5c4b\u5934"
    ],
    "wof:name":"Xinwutou",
    "wof:placetype":"locality"
},
  "geometry": {"coordinates":[113.53131,26.08509],"type":"Point"}
}