{
  "type": "Feature",
  "properties": {
    "gn:admin1_code":"13.0",
    "gn:asciiname":"Ha-la-ka-ssu-t'e",
    "gn:country_code":"CN",
    "gn:dem":864,
    "gn:feature_class":"P",
    "gn:feature_code":"PPL",
    "gn:name":"Ha-la-ka-ssu-t\u2019e",
    "gn:population":0,
    "gn:timezone":"Asia/Urumqi",
    "iso:country":"CN",
    "wof:name":"Ha-la-ka-ssu-t'e",
    "wof:placetype":"locality"
},
  "geometry": {"coordinates":[87.14221999999999,40.74278],"type":"Point"}
}