{
  "type": "Feature",
  "properties": {
    "gn:admin1_code":"7.0",
    "gn:asciiname":"Zhongxian",
    "gn:country_code":"CN",
    "gn:dem":680,
    "gn:feature_class":"P",
    "gn:feature_code":"PPLA4",
    "gn:name":"Zhongxian",
    "gn:population":0,
    "gn:timezone":"Asia/Shanghai",
    "iso:country":"CN",
    "name:und_x_variant":[
        "Chung-hsien",
        "Zhongxian",
        "Zhongxian Xiang"
    ],
    "name:zho_x_preferred":[
        "\u4e2d\u4ed9"
    ],
    "name:zho_x_variant":[
        "\u4e2d\u4ed9\u4e61"
    ],
    "wof:name":"Zhongxian",
    "wof:placetype":"locality"
},
  "geometry": {"coordinates":[118.36988999999998,25.95091],"type":"Point"}
}