{
  "type": "Feature",
  "properties": {
    "gn:admin1_code":"16.0",
    "gn:asciiname":"Jianling",
    "gn:country_code":"CN",
    "gn:dem":54,
    "gn:feature_class":"P",
    "gn:feature_code":"PPL",
    "gn:name":"Jianling",
    "gn:population":0,
    "gn:timezone":"Asia/Shanghai",
    "iso:country":"CN",
    "name:zho_x_preferred":[
        "\u5c16\u5cad"
    ],
    "wof:name":"Jianling",
    "wof:placetype":"locality"
},
  "geometry": {"coordinates":[109.79900000000001,23.0157],"type":"Point"}
}