{
  "type": "Feature",
  "properties": {
    "gn:admin1_code":"11.0",
    "gn:asciiname":"Baizhuchong",
    "gn:country_code":"CN",
    "gn:dem":135,
    "gn:feature_class":"P",
    "gn:feature_code":"PPL",
    "gn:name":"Baizhuchong",
    "gn:population":0,
    "gn:timezone":"Asia/Shanghai",
    "iso:country":"CN",
    "name:zho_x_preferred":[
        "\u767d\u7af9\u51b2"
    ],
    "wof:name":"Baizhuchong",
    "wof:placetype":"locality"
},
  "geometry": {"coordinates":[111.78839000000001,28.62941],"type":"Point"}
}