{
  "type": "Feature",
  "properties": {
    "gn:admin1_code":"19.0",
    "gn:asciiname":"Daokou",
    "gn:country_code":"CN",
    "gn:dem":64,
    "gn:feature_class":"P",
    "gn:feature_code":"PPL",
    "gn:name":"Daokou",
    "gn:population":0,
    "gn:timezone":"Asia/Shanghai",
    "iso:country":"CN",
    "name:zho_x_preferred":[
        "\u9053\u53e3"
    ],
    "wof:name":"Daokou",
    "wof:placetype":"locality"
},
  "geometry": {"coordinates":[122.13500000000001,41.9089],"type":"Point"}
}