{
  "type": "Feature",
  "properties": {
    "gn:admin1_code":"29.0",
    "gn:asciiname":"Suoshan",
    "gn:country_code":"CN",
    "gn:dem":1500,
    "gn:feature_class":"P",
    "gn:feature_code":"PPL",
    "gn:name":"Suoshan",
    "gn:population":0,
    "gn:timezone":"Asia/Shanghai",
    "iso:country":"CN",
    "name:zho_x_preferred":[
        "\u68ad\u5c71"
    ],
    "wof:name":"Suoshan",
    "wof:placetype":"locality"
},
  "geometry": {"coordinates":[102.78700000000001,22.8244],"type":"Point"}
}