{
  "type": "Feature",
  "properties": {
    "gn:admin1_code":"22.0",
    "gn:asciiname":"Sanzuo'ancun",
    "gn:country_code":"CN",
    "gn:dem":159,
    "gn:feature_class":"P",
    "gn:feature_code":"PPL",
    "gn:name":"Sanzuo\u2019ancun",
    "gn:population":0,
    "gn:timezone":"Asia/Shanghai",
    "iso:country":"CN",
    "name:und_x_variant":[
        "Sanzuo\u2019ancun"
    ],
    "name:zho_x_preferred":[
        "\u4e09\u5ea7\u5eb5\u6751"
    ],
    "wof:name":"Sanzuo'ancun",
    "wof:placetype":"locality"
},
  "geometry": {"coordinates":[115.8214,39.60846],"type":"Point"}
}