{
  "type": "Feature",
  "properties": {
    "gn:admin1_code":"6.0",
    "gn:asciiname":"Dangba",
    "gn:country_code":"CN",
    "gn:dem":3770,
    "gn:feature_class":"P",
    "gn:feature_code":"PPL",
    "gn:name":"Dangba",
    "gn:population":0,
    "gn:timezone":"Asia/Urumqi",
    "iso:country":"CN",
    "name:zho_x_preferred":[
        "\u5f53\u5df4"
    ],
    "wof:name":"Dangba",
    "wof:placetype":"locality"
},
  "geometry": {"coordinates":[97.29345000000001,33.05937],"type":"Point"}
}