{
  "type": "Feature",
  "properties": {
    "gn:admin1_code":"5.0",
    "gn:asciiname":"Gaoxingcun",
    "gn:country_code":"CN",
    "gn:dem":385,
    "gn:feature_class":"P",
    "gn:feature_code":"PPL",
    "gn:name":"Gaoxingcun",
    "gn:population":0,
    "gn:timezone":"Asia/Shanghai",
    "iso:country":"CN",
    "name:zho_x_preferred":[
        "\u9ad8\u5174\u6751"
    ],
    "wof:name":"Gaoxingcun",
    "wof:placetype":"locality"
},
  "geometry": {"coordinates":[125.23219,42.60522],"type":"Point"}
}