{
  "type": "Feature",
  "properties": {
    "gn:admin1_code":"26.0",
    "gn:asciiname":"Baishizui",
    "gn:country_code":"CN",
    "gn:dem":1360,
    "gn:feature_class":"P",
    "gn:feature_code":"PPL",
    "gn:name":"Baishizui",
    "gn:population":0,
    "gn:timezone":"Asia/Shanghai",
    "iso:country":"CN",
    "name:zho_x_preferred":[
        "\u767d\u77f3\u5480"
    ],
    "wof:name":"Baishizui",
    "wof:placetype":"locality"
},
  "geometry": {"coordinates":[108.14529,36.94237],"type":"Point"}
}