{
  "type": "Feature",
  "properties": {
    "gn:admin1_code":"4.0",
    "gn:asciiname":"Pinzuo",
    "gn:country_code":"CN",
    "gn:dem":3,
    "gn:feature_class":"P",
    "gn:feature_code":"PPL",
    "gn:name":"Pinzuo",
    "gn:population":0,
    "gn:timezone":"Asia/Shanghai",
    "iso:country":"CN",
    "name:zho_x_preferred":[
        "\u54c1\u795a"
    ],
    "wof:name":"Pinzuo",
    "wof:placetype":"locality"
},
  "geometry": {"coordinates":[119.44365000000001,32.94052],"type":"Point"}
}