{
  "type": "Feature",
  "properties": {
    "gn:admin1_code":"25",
    "gn:asciiname":"Zhoucaomiao",
    "gn:country_code":"CN",
    "gn:dem":40,
    "gn:feature_class":"P",
    "gn:feature_code":"PPL",
    "gn:name":"Zhoucaomiao",
    "gn:population":0,
    "gn:timezone":"Asia/Shanghai",
    "iso:country":"CN",
    "name:zho_x_preferred":[
        "\u5468\u8349\u5e99"
    ],
    "wof:name":"Zhoucaomiao",
    "wof:placetype":"locality"
},
  "geometry": {"coordinates":[116.18000000000001,34.9886],"type":"Point"}
}