{
  "type": "Feature",
  "properties": {
    "gn:admin1_code":"3.0",
    "gn:asciiname":"Qiukeng",
    "gn:country_code":"CN",
    "gn:dem":299,
    "gn:feature_class":"P",
    "gn:feature_code":"PPL",
    "gn:name":"Qiukeng",
    "gn:population":0,
    "gn:timezone":"Asia/Shanghai",
    "iso:country":"CN",
    "name:und_x_variant":[
        "\u79cb\u5751"
    ],
    "wof:name":"Qiukeng",
    "wof:placetype":"locality"
},
  "geometry": {"coordinates":[114.91864,24.81701],"type":"Point"}
}