{
  "type": "Feature",
  "properties": {
    "gn:admin1_code":"29.0",
    "gn:asciiname":"Langba",
    "gn:country_code":"CN",
    "gn:dem":2041,
    "gn:feature_class":"P",
    "gn:feature_code":"PPL",
    "gn:name":"Langba",
    "gn:population":0,
    "gn:timezone":"Asia/Shanghai",
    "iso:country":"CN",
    "name:zho_x_preferred":[
        "\u6d6a\u575d"
    ],
    "wof:name":"Langba",
    "wof:placetype":"locality"
},
  "geometry": {"coordinates":[98.9408,25.6843],"type":"Point"}
}