{
  "type": "Feature",
  "properties": {
    "gn:admin1_code":"29.0",
    "gn:asciiname":"Datianyatian",
    "gn:country_code":"CN",
    "gn:dem":1828,
    "gn:feature_class":"P",
    "gn:feature_code":"PPL",
    "gn:name":"Datianyatian",
    "gn:population":0,
    "gn:timezone":"Asia/Shanghai",
    "iso:country":"CN",
    "name:zho_x_preferred":[
        "\u5927\u7530\u57ad\u7530"
    ],
    "wof:name":"Datianyatian",
    "wof:placetype":"locality"
},
  "geometry": {"coordinates":[100.81100000000001,25.0023],"type":"Point"}
}