{
  "type": "Feature",
  "properties": {
    "gn:admin1_code":"3.0",
    "gn:asciiname":"Futan",
    "gn:country_code":"CN",
    "gn:dem":60,
    "gn:feature_class":"P",
    "gn:feature_code":"PPL",
    "gn:name":"Futan",
    "gn:population":0,
    "gn:timezone":"Asia/Shanghai",
    "iso:country":"CN",
    "name:zho_x_preferred":[
        "\u51eb\u6f6d"
    ],
    "wof:name":"Futan",
    "wof:placetype":"locality"
},
  "geometry": {"coordinates":[114.749,27.1855],"type":"Point"}
}