{
  "type": "Feature",
  "properties": {
    "gn:admin1_code":"26.0",
    "gn:asciiname":"Dongjia Shancun",
    "gn:country_code":"CN",
    "gn:dem":1023,
    "gn:feature_class":"P",
    "gn:feature_code":"PPL",
    "gn:name":"Dongjia Shancun",
    "gn:population":0,
    "gn:timezone":"Asia/Shanghai",
    "iso:country":"CN",
    "name:zho_x_preferred":[
        "\u8463\u5bb6\u5c71\u6751"
    ],
    "wof:name":"Dongjia Shancun",
    "wof:placetype":"locality"
},
  "geometry": {"coordinates":[110.58499999999999,37.64],"type":"Point"}
}