{
  "type": "Feature",
  "properties": {
    "gn:admin1_code":"32.0",
    "gn:asciiname":"Fangtian",
    "gn:country_code":"CN",
    "gn:dem":1768,
    "gn:feature_class":"P",
    "gn:feature_code":"PPL",
    "gn:name":"Fangtian",
    "gn:population":0,
    "gn:timezone":"Asia/Shanghai",
    "iso:country":"CN",
    "name:zho_x_preferred":[
        "\u574a\u7530"
    ],
    "wof:name":"Fangtian",
    "wof:placetype":"locality"
},
  "geometry": {"coordinates":[101.92204,26.81484],"type":"Point"}
}