{
  "type": "Feature",
  "properties": {
    "gn:admin1_code":"8.0",
    "gn:asciiname":"Renmin",
    "gn:country_code":"CN",
    "gn:dem":166,
    "gn:feature_class":"P",
    "gn:feature_code":"PPL",
    "gn:name":"Renmin",
    "gn:population":0,
    "gn:timezone":"Asia/Shanghai",
    "iso:country":"CN",
    "name:zho_x_preferred":[
        "\u4eba\u6c11"
    ],
    "wof:name":"Renmin",
    "wof:placetype":"locality"
},
  "geometry": {"coordinates":[123.54224000000001,47.7419],"type":"Point"}
}