{
  "type": "Feature",
  "properties": {
    "gn:admin1_code":"30.0",
    "gn:asciiname":"Gaoyuancun",
    "gn:country_code":"CN",
    "gn:dem":359,
    "gn:feature_class":"P",
    "gn:feature_code":"PPL",
    "gn:name":"Gaoyuancun",
    "gn:population":0,
    "gn:timezone":"Asia/Shanghai",
    "iso:country":"CN",
    "name:zho_x_preferred":[
        "\u9ad8\u539f\u6751"
    ],
    "wof:name":"Gaoyuancun",
    "wof:placetype":"locality"
},
  "geometry": {"coordinates":[116.63306,23.83546],"type":"Point"}
}