{
  "type": "Feature",
  "properties": {
    "gn:admin1_code":"10",
    "gn:asciiname":"Dongsidaogou",
    "gn:country_code":"CN",
    "gn:dem":543,
    "gn:feature_class":"P",
    "gn:feature_code":"PPL",
    "gn:name":"Dongsidaogou",
    "gn:population":0,
    "gn:timezone":"Asia/Shanghai",
    "iso:country":"CN",
    "name:zho_x_preferred":[
        "\u4e1c\u56db\u9053\u6c9f"
    ],
    "wof:name":"Dongsidaogou",
    "wof:placetype":"locality"
},
  "geometry": {"coordinates":[116.91568999999998,40.96167],"type":"Point"}
}