{
  "type": "Feature",
  "properties": {
    "gn:admin1_code":"32.0",
    "gn:asciiname":"Tanjiawan",
    "gn:country_code":"CN",
    "gn:dem":425,
    "gn:feature_class":"P",
    "gn:feature_code":"PPL",
    "gn:name":"Tanjiawan",
    "gn:population":0,
    "gn:timezone":"Asia/Shanghai",
    "iso:country":"CN",
    "name:zho_x_preferred":[
        "\u8c2d\u5bb6\u6e7e"
    ],
    "wof:name":"Tanjiawan",
    "wof:placetype":"locality"
},
  "geometry": {"coordinates":[104.98099999999999,30.07],"type":"Point"}
}