{
  "type": "Feature",
  "properties": {
    "gn:admin1_code":"30.0",
    "gn:asciiname":"Liudong",
    "gn:country_code":"CN",
    "gn:dem":148,
    "gn:feature_class":"P",
    "gn:feature_code":"PPL",
    "gn:name":"Liudong",
    "gn:population":0,
    "gn:timezone":"Asia/Shanghai",
    "iso:country":"CN",
    "name:zho_x_preferred":[
        "Liudong"
    ],
    "name:zho_x_variant":[
        "\u6d41\u6d1e"
    ],
    "wof:name":"Liudong",
    "wof:placetype":"locality"
},
  "geometry": {"coordinates":[114.93044,24.22423],"type":"Point"}
}