{
  "type": "Feature",
  "properties": {
    "gn:admin1_code":"11.0",
    "gn:asciiname":"Chejiahe",
    "gn:country_code":"CN",
    "gn:dem":819,
    "gn:feature_class":"P",
    "gn:feature_code":"PPL",
    "gn:name":"Chejiahe",
    "gn:population":0,
    "gn:timezone":"Asia/Shanghai",
    "iso:country":"CN",
    "name:zho_x_preferred":[
        "\u8f66\u5bb6\u6cb3"
    ],
    "wof:name":"Chejiahe",
    "wof:placetype":"locality"
},
  "geometry": {"coordinates":[110.72765,29.89907],"type":"Point"}
}