{
  "type": "Feature",
  "properties": {
    "gn:admin1_code":"25",
    "gn:asciiname":"Luchangxi",
    "gn:country_code":"CN",
    "gn:dem":18,
    "gn:feature_class":"P",
    "gn:feature_code":"PPL",
    "gn:name":"L\u00fcchangxi",
    "gn:population":0,
    "gn:timezone":"Asia/Shanghai",
    "iso:country":"CN",
    "name:und_x_variant":[
        "L\u00fcchangxi"
    ],
    "name:zho_x_preferred":[
        "\u5415\u5e38\u897f"
    ],
    "wof:name":"Luchangxi",
    "wof:placetype":"locality"
},
  "geometry": {"coordinates":[117.14400000000001,37.1881],"type":"Point"}
}