{
  "type": "Feature",
  "properties": {
    "gn:admin1_code":"10",
    "gn:asciiname":"Zengzhuang",
    "gn:country_code":"CN",
    "gn:dem":14,
    "gn:feature_class":"P",
    "gn:feature_code":"PPL",
    "gn:name":"Zengzhuang",
    "gn:population":0,
    "gn:timezone":"Asia/Shanghai",
    "iso:country":"CN",
    "name:zho_x_preferred":[
        "\u589e\u5e84"
    ],
    "wof:name":"Zengzhuang",
    "wof:placetype":"locality"
},
  "geometry": {"coordinates":[115.773,38.9501],"type":"Point"}
}