{
  "type": "Feature",
  "properties": {
    "gn:admin1_code":"22.0",
    "gn:asciiname":"Louzizhuangcun",
    "gn:country_code":"CN",
    "gn:dem":50,
    "gn:feature_class":"P",
    "gn:feature_code":"PPL",
    "gn:name":"Louzizhuangcun",
    "gn:population":0,
    "gn:timezone":"Asia/Shanghai",
    "iso:country":"CN",
    "name:zho_x_preferred":[
        "\u697c\u5b50\u5e84\u6751"
    ],
    "wof:name":"Louzizhuangcun",
    "wof:placetype":"locality"
},
  "geometry": {"coordinates":[116.21134000000001,40.16426],"type":"Point"}
}