{
  "type": "Feature",
  "properties": {
    "gn:admin1_code":"1.0",
    "gn:asciiname":"Sanzhencun",
    "gn:country_code":"CN",
    "gn:dem":21,
    "gn:feature_class":"P",
    "gn:feature_code":"PPL",
    "gn:name":"Sanzhencun",
    "gn:population":0,
    "gn:timezone":"Asia/Shanghai",
    "iso:country":"CN",
    "name:zho_x_preferred":[
        "\u4e09\u7504\u6751"
    ],
    "wof:name":"Sanzhencun",
    "wof:placetype":"locality"
},
  "geometry": {"coordinates":[118.05486999999999,33.62128],"type":"Point"}
}