{
  "type": "Feature",
  "properties": {
    "gn:admin1_code":"32.0",
    "gn:asciiname":"Dacha",
    "gn:country_code":"CN",
    "gn:dem":1940,
    "gn:feature_class":"P",
    "gn:feature_code":"PPL",
    "gn:name":"Dacha",
    "gn:population":0,
    "gn:timezone":"Asia/Shanghai",
    "iso:country":"CN",
    "name:ara_x_preferred":[
        "\u062f\u0627\u062a\u0634\u0627"
    ],
    "name:bel_x_preferred":[
        "\u0414\u0430\u0447\u0430"
    ],
    "name:bul_x_preferred":[
        "\u0414\u0430\u0447\u0430"
    ],
    "name:cat_x_preferred":[
        "Datxa"
    ],
    "name:dan_x_preferred":[
        "Datja"
    ],
    "name:deu_x_preferred":[
        "Datsche"
    ],
    "name:epo_x_preferred":[
        "Da\u0109o"
    ],
    "name:eus_x_preferred":[
        "Datxa"
    ],
    "name:fin_x_preferred":[
        "Dat\u0161a"
    ],
    "name:fra_x_preferred":[
        "Datcha"
    ],
    "name:heb_x_preferred":[
        "\u05d3\u05d0\u05e6'\u05d4"
    ],
    "name:hrv_x_preferred":[
        "Da\u010da"
    ],
    "name:ind_x_preferred":[
        "Dacha"
    ],
    "name:ita_x_preferred":[
        "Dacia"
    ],
    "name:jpn_x_preferred":[
        "\u30c0\u30fc\u30c1\u30e3"
    ],
    "name:kir_x_preferred":[
        "\u0414\u0430\u0447\u0430"
    ],
    "name:nld_x_preferred":[
        "Datsja"
    ],
    "name:nno_x_preferred":[
        "Datsja"
    ],
    "name:nor_x_preferred":[
        "Datsja"
    ],
    "name:pol_x_preferred":[
        "Dacza"
    ],
    "name:por_x_preferred":[
        "Datcha"
    ],
    "name:ron_x_preferred":[
        "Dacea"
    ],
    "name:rus_x_preferred":[
        "\u0414\u0430\u0447\u0430"
    ],
    "name:spa_x_preferred":[
        "Dacha"
    ],
    "name:srp_x_preferred":[
        "Da\u010da"
    ],
    "name:swe_x_preferred":[
        "Datja"
    ],
    "name:tur_x_preferred":[
        "Da\u00e7a"
    ],
    "name:ukr_x_preferred":[
        "\u0414\u0430\u0447\u0430"
    ],
    "name:vie_x_preferred":[
        "Dacha"
    ],
    "name:yid_x_preferred":[
        "\u05d3\u05d0\u05d8\u05e9\u05e2"
    ],
    "name:zho_x_preferred":[
        "\u5927\u5c94"
    ],
    "wof:name":"Dacha",
    "wof:placetype":"locality"
},
  "geometry": {"coordinates":[104.571,32.451],"type":"Point"}
}