{
  "type": "Feature",
  "properties": {
    "gn:admin1_code":"19.0",
    "gn:asciiname":"Wofotou Goucun",
    "gn:country_code":"CN",
    "gn:dem":157,
    "gn:feature_class":"P",
    "gn:feature_code":"PPL",
    "gn:name":"Wofotou Goucun",
    "gn:population":0,
    "gn:timezone":"Asia/Shanghai",
    "iso:country":"CN",
    "name:zho_x_preferred":[
        "\u5367\u4f5b\u5934\u6c9f\u6751"
    ],
    "wof:name":"Wofotou Goucun",
    "wof:placetype":"locality"
},
  "geometry": {"coordinates":[120.48699999999999,41.2857],"type":"Point"}
}