{
  "type": "Feature",
  "properties": {
    "gn:admin1_code":"20",
    "gn:asciiname":"Baixingt",
    "gn:cc2":"CN",
    "gn:country_code":"CN",
    "gn:dem":282,
    "gn:feature_class":"P",
    "gn:feature_code":"PPL",
    "gn:name":"Baixingt",
    "gn:population":0,
    "gn:timezone":"Asia/Shanghai",
    "iso:country":"CN",
    "name:und_x_variant":[
        "Pa-hsien-t\u2019ung",
        "Baixingt"
    ],
    "wof:name":"Baixingt",
    "wof:placetype":"locality"
},
  "geometry": {"coordinates":[121.06667,43.21667],"type":"Point"}
}