{
  "type": "Feature",
  "properties": {
    "gn:admin1_code":"24.0",
    "gn:asciiname":"Donglinggou",
    "gn:country_code":"CN",
    "gn:dem":1098,
    "gn:feature_class":"P",
    "gn:feature_code":"PPL",
    "gn:name":"Donglinggou",
    "gn:population":0,
    "gn:timezone":"Asia/Shanghai",
    "iso:country":"CN",
    "name:und_x_variant":[
        "\u4e1c\u5cad\u6c9f"
    ],
    "wof:name":"Donglinggou",
    "wof:placetype":"locality"
},
  "geometry": {"coordinates":[111.46614,35.26584000000001],"type":"Point"}
}