{
  "type": "Feature",
  "properties": {
    "gn:admin1_code":"30",
    "gn:asciiname":"Baishicun",
    "gn:country_code":"CN",
    "gn:dem":62,
    "gn:feature_class":"P",
    "gn:feature_code":"PPL",
    "gn:name":"Baishicun",
    "gn:population":0,
    "gn:timezone":"Asia/Urumqi",
    "iso:country":"CN",
    "name:zho_x_preferred":[
        "\u767d\u77f3\u6751"
    ],
    "wof:name":"Baishicun",
    "wof:placetype":"locality"
},
  "geometry": {"coordinates":[111.13588,21.83774],"type":"Point"}
}