{
  "type": "Feature",
  "properties": {
    "gn:admin1_code":"16.0",
    "gn:asciiname":"Hecang",
    "gn:country_code":"CN",
    "gn:dem":79,
    "gn:feature_class":"P",
    "gn:feature_code":"PPL",
    "gn:name":"Hecang",
    "gn:population":0,
    "gn:timezone":"Asia/Shanghai",
    "iso:country":"CN",
    "name:zho_x_preferred":[
        "\u79be\u4ed3"
    ],
    "wof:name":"Hecang",
    "wof:placetype":"locality"
},
  "geometry": {"coordinates":[109.036,22.9238],"type":"Point"}
}