{
  "type": "Feature",
  "properties": {
    "gn:admin1_code":"32.0",
    "gn:asciiname":"Sandaoqiao",
    "gn:country_code":"CN",
    "gn:dem":3141,
    "gn:feature_class":"P",
    "gn:feature_code":"PPL",
    "gn:name":"Sandaoqiao",
    "gn:population":0,
    "gn:timezone":"Asia/Shanghai",
    "iso:country":"CN",
    "name:zho_x_preferred":[
        "\u4e09\u9053\u6865"
    ],
    "wof:name":"Sandaoqiao",
    "wof:placetype":"locality"
},
  "geometry": {"coordinates":[101.06514,30.05909],"type":"Point"}
}