{
  "type": "Feature",
  "properties": {
    "gn:admin1_code":"26.0",
    "gn:asciiname":"Quxijiaocun",
    "gn:country_code":"CN",
    "gn:dem":981,
    "gn:feature_class":"P",
    "gn:feature_code":"PPL",
    "gn:name":"Quxijiaocun",
    "gn:population":0,
    "gn:timezone":"Asia/Shanghai",
    "iso:country":"CN",
    "name:zho_x_preferred":[
        "\u66f2\u6eaa\u4ea4\u6751"
    ],
    "wof:name":"Quxijiaocun",
    "wof:placetype":"locality"
},
  "geometry": {"coordinates":[109.98511000000001,36.98783],"type":"Point"}
}