{
  "type": "Feature",
  "properties": {
    "gn:admin1_code":"19.0",
    "gn:asciiname":"Yulonggou Xiayingzi",
    "gn:country_code":"CN",
    "gn:dem":194,
    "gn:feature_class":"P",
    "gn:feature_code":"PPL",
    "gn:name":"Yulonggou Xiayingzi",
    "gn:population":0,
    "gn:timezone":"Asia/Shanghai",
    "iso:country":"CN",
    "name:zho_x_preferred":[
        "\u4e8e\u9f99\u6c9f\u4e0b\u8425\u5b50"
    ],
    "wof:name":"Yulonggou Xiayingzi",
    "wof:placetype":"locality"
},
  "geometry": {"coordinates":[120.761,41.7273],"type":"Point"}
}