{
  "type": "Feature",
  "properties": {
    "gn:admin1_code":"14.0",
    "gn:asciiname":"Zhangang",
    "gn:country_code":"CN",
    "gn:dem":3174,
    "gn:feature_class":"P",
    "gn:feature_code":"PPL",
    "gn:name":"Zhangang",
    "gn:population":0,
    "gn:timezone":"Asia/Urumqi",
    "iso:country":"CN",
    "name:zho_x_preferred":[
        "\u5360\u5c97"
    ],
    "wof:name":"Zhangang",
    "wof:placetype":"locality"
},
  "geometry": {"coordinates":[85.43810000000001,28.3598],"type":"Point"}
}