{
  "type": "Feature",
  "properties": {
    "gn:admin1_code":"12.0",
    "gn:asciiname":"Hengheyan",
    "gn:country_code":"CN",
    "gn:dem":274,
    "gn:feature_class":"P",
    "gn:feature_code":"PPL",
    "gn:name":"Hengheyan",
    "gn:population":0,
    "gn:timezone":"Asia/Shanghai",
    "iso:country":"CN",
    "name:zho_x_preferred":[
        "Hengheyan"
    ],
    "name:zho_x_variant":[
        "\u6a2a\u6cb3\u5ca9"
    ],
    "wof:name":"Hengheyan",
    "wof:placetype":"locality"
},
  "geometry": {"coordinates":[114.88245000000001,29.64055],"type":"Point"}
}