{
  "type": "Feature",
  "properties": {
    "gn:admin1_code":"15.0",
    "gn:asciiname":"Yangjiafen",
    "gn:country_code":"CN",
    "gn:dem":1665,
    "gn:feature_class":"P",
    "gn:feature_code":"PPL",
    "gn:name":"Yangjiafen",
    "gn:population":0,
    "gn:timezone":"Asia/Shanghai",
    "iso:country":"CN",
    "name:zho_x_preferred":[
        "\u6768\u5bb6\u575f"
    ],
    "wof:name":"Yangjiafen",
    "wof:placetype":"locality"
},
  "geometry": {"coordinates":[106.637,35.6539],"type":"Point"}
}