{
  "type": "Feature",
  "properties": {
    "gn:admin1_code":"7.0",
    "gn:asciiname":"Laohu'ao",
    "gn:country_code":"CN",
    "gn:dem":554,
    "gn:feature_class":"P",
    "gn:feature_code":"PPL",
    "gn:name":"Laohu\u2019ao",
    "gn:population":0,
    "gn:timezone":"Asia/Shanghai",
    "iso:country":"CN",
    "name:zho_x_preferred":[
        "\u8001\u864e\u5773"
    ],
    "name:zho_x_variant":[
        "Laohu\u2019ao"
    ],
    "wof:name":"Laohu'ao",
    "wof:placetype":"locality"
},
  "geometry": {"coordinates":[117.91947999999999,27.19235],"type":"Point"}
}