{
  "type": "Feature",
  "properties": {
    "gn:admin1_code":"2.0",
    "gn:asciiname":"Qiu'ao",
    "gn:country_code":"CN",
    "gn:dem":283,
    "gn:feature_class":"P",
    "gn:feature_code":"PPL",
    "gn:name":"Qiu\u2019ao",
    "gn:population":0,
    "gn:timezone":"Asia/Shanghai",
    "iso:country":"CN",
    "name:zho_x_preferred":[
        "\u88d8\u5c99"
    ],
    "name:zho_x_variant":[
        "Qiu\u2019ao"
    ],
    "wof:name":"Qiu'ao",
    "wof:placetype":"locality"
},
  "geometry": {"coordinates":[121.2165,29.89322],"type":"Point"}
}