{
  "type": "Feature",
  "properties": {
    "gn:admin1_code":"6.0",
    "gn:asciiname":"Haizigou",
    "gn:country_code":"CN",
    "gn:dem":2639,
    "gn:feature_class":"P",
    "gn:feature_code":"PPLA4",
    "gn:name":"Haizigou",
    "gn:population":0,
    "gn:timezone":"Asia/Shanghai",
    "iso:country":"CN",
    "name:und_x_variant":[
        "Haizigou Xiang"
    ],
    "name:zho_x_preferred":[
        "\u6d77\u5b50\u6c9f"
    ],
    "name:zho_x_variant":[
        "\u6d77\u5b50\u6c9f\u4e61"
    ],
    "wof:name":"Haizigou",
    "wof:placetype":"locality"
},
  "geometry": {"coordinates":[101.63811,36.70669],"type":"Point"}
}