{
  "type": "Feature",
  "properties": {
    "gn:admin1_code":"26.0",
    "gn:asciiname":"Yujian",
    "gn:country_code":"CN",
    "gn:dem":1516,
    "gn:feature_class":"P",
    "gn:feature_code":"PPL",
    "gn:name":"Yujian",
    "gn:population":0,
    "gn:timezone":"Asia/Shanghai",
    "iso:country":"CN",
    "name:zho_x_preferred":[
        "\u4fde\u6da7"
    ],
    "wof:name":"Yujian",
    "wof:placetype":"locality"
},
  "geometry": {"coordinates":[108.95166999999999,37.38417000000001],"type":"Point"}
}