{
  "type": "Feature",
  "properties": {
    "gn:admin1_code":"2.0",
    "gn:asciiname":"Wangqian Sancun",
    "gn:country_code":"CN",
    "gn:dem":43,
    "gn:feature_class":"P",
    "gn:feature_code":"PPL",
    "gn:name":"Wangqian Sancun",
    "gn:population":0,
    "gn:timezone":"Asia/Shanghai",
    "iso:country":"CN",
    "name:zho_x_preferred":[
        "\u738b\u9621\u4e09\u6751"
    ],
    "wof:name":"Wangqian Sancun",
    "wof:placetype":"locality"
},
  "geometry": {"coordinates":[119.94029999999999,29.23806],"type":"Point"}
}