{
  "type": "Feature",
  "properties": {
    "gn:admin1_code":"16.0",
    "gn:asciiname":"Yangdiping",
    "gn:country_code":"CN",
    "gn:dem":80,
    "gn:feature_class":"P",
    "gn:feature_code":"PPL",
    "gn:name":"Yangdiping",
    "gn:population":0,
    "gn:timezone":"Asia/Shanghai",
    "iso:country":"CN",
    "name:zho_x_preferred":[
        "\u79e7\u5730\u576a"
    ],
    "wof:name":"Yangdiping",
    "wof:placetype":"locality"
},
  "geometry": {"coordinates":[109.667,22.1001],"type":"Point"}
}