{
  "type": "Feature",
  "properties": {
    "gn:admin1_code":"26.0",
    "gn:asciiname":"Jiaochang Pingcun",
    "gn:country_code":"CN",
    "gn:dem":1020,
    "gn:feature_class":"P",
    "gn:feature_code":"PPL",
    "gn:name":"Jiaochang Pingcun",
    "gn:population":0,
    "gn:timezone":"Asia/Shanghai",
    "iso:country":"CN",
    "name:zho_x_preferred":[
        "\u6559\u573a\u576a\u6751"
    ],
    "wof:name":"Jiaochang Pingcun",
    "wof:placetype":"locality"
},
  "geometry": {"coordinates":[109.601,37.5639],"type":"Point"}
}