{
  "type": "Feature",
  "properties": {
    "gn:admin1_code":"24.0",
    "gn:asciiname":"Xigelaoshan",
    "gn:country_code":"CN",
    "gn:dem":1162,
    "gn:feature_class":"P",
    "gn:feature_code":"PPL",
    "gn:name":"Xigelaoshan",
    "gn:population":0,
    "gn:timezone":"Asia/Shanghai",
    "iso:country":"CN",
    "name:zho_x_preferred":[
        "\u897f\u9601\u8001\u5c71"
    ],
    "wof:name":"Xigelaoshan",
    "wof:placetype":"locality"
},
  "geometry": {"coordinates":[113.65558,40.09094],"type":"Point"}
}