{
  "type": "Feature",
  "properties": {
    "gn:admin1_code":"24.0",
    "gn:asciiname":"Zirun",
    "gn:country_code":"CN",
    "gn:dem":1041,
    "gn:feature_class":"P",
    "gn:feature_code":"PPLA4",
    "gn:name":"Zirun",
    "gn:population":0,
    "gn:timezone":"Asia/Shanghai",
    "iso:country":"CN",
    "name:und_x_variant":[
        "Tzu-jun",
        "Tzu-jun-ts\u2019un",
        "Zirun",
        "\u6ecb\u6da6",
        "Zirun Xiang",
        "\u6ecb\u6da6\u4e61"
    ],
    "wof:name":"Zirun",
    "wof:placetype":"locality"
},
  "geometry": {"coordinates":[112.68358000000001,39.30346],"type":"Point"}
}