{
  "type": "Feature",
  "properties": {
    "gn:admin1_code":"4.0",
    "gn:asciiname":"Caodiancun",
    "gn:country_code":"CN",
    "gn:dem":22,
    "gn:feature_class":"P",
    "gn:feature_code":"PPL",
    "gn:name":"Caodiancun",
    "gn:population":0,
    "gn:timezone":"Asia/Shanghai",
    "iso:country":"CN",
    "name:zho_x_preferred":[
        "\u66f9\u7538\u6751"
    ],
    "wof:name":"Caodiancun",
    "wof:placetype":"locality"
},
  "geometry": {"coordinates":[118.09113000000001,34.11609],"type":"Point"}
}