{
  "type": "Feature",
  "properties": {
    "gn:admin1_code":"32.0",
    "gn:asciiname":"Rongbaca",
    "gn:cc2":"CN",
    "gn:country_code":"CN",
    "gn:dem":3643,
    "gn:feature_class":"P",
    "gn:feature_code":"PPL",
    "gn:name":"Rongbaca",
    "gn:population":0,
    "gn:timezone":"Asia/Shanghai",
    "iso:country":"CN",
    "name:und_x_variant":[
        "Jung-pa-ch\u2019a",
        "Rongbaca"
    ],
    "wof:name":"Rongbaca",
    "wof:placetype":"locality"
},
  "geometry": {"coordinates":[99.66667,31.68333],"type":"Point"}
}