{
  "type": "Feature",
  "properties": {
    "gn:admin1_code":"09",
    "gn:asciiname":"Yingfangwan",
    "gn:cc2":"CN",
    "gn:country_code":"CN",
    "gn:dem":93,
    "gn:feature_class":"P",
    "gn:feature_code":"PPL",
    "gn:name":"Yingfangwan",
    "gn:population":0,
    "gn:timezone":"Asia/Shanghai",
    "iso:country":"CN",
    "name:und_x_variant":[
        "Wei-wan",
        "Yingfangwan"
    ],
    "wof:name":"Yingfangwan",
    "wof:placetype":"locality"
},
  "geometry": {"coordinates":[114.04833000000001,32.08333],"type":"Point"}
}