{
  "type": "Feature",
  "properties": {
    "gn:admin1_code":"32.0",
    "gn:asciiname":"Yongsheng",
    "gn:country_code":"CN",
    "gn:dem":288,
    "gn:feature_class":"P",
    "gn:feature_code":"PPL",
    "gn:name":"Yongsheng",
    "gn:population":0,
    "gn:timezone":"Asia/Shanghai",
    "iso:country":"CN",
    "name:zho_x_preferred":[
        "\u6c38\u80dc"
    ],
    "wof:name":"Yongsheng",
    "wof:placetype":"locality"
},
  "geometry": {"coordinates":[106.91200000000001,30.6389],"type":"Point"}
}