{
  "type": "Feature",
  "properties": {
    "gn:admin1_code":"29.0",
    "gn:asciiname":"Sakedai",
    "gn:country_code":"CN",
    "gn:dem":2513,
    "gn:feature_class":"P",
    "gn:feature_code":"PPL",
    "gn:name":"Sakedai",
    "gn:population":0,
    "gn:timezone":"Asia/Shanghai",
    "iso:country":"CN",
    "name:zho_x_preferred":[
        "\u6492\u514b\u4ee3"
    ],
    "wof:name":"Sakedai",
    "wof:placetype":"locality"
},
  "geometry": {"coordinates":[100.892,26.3391],"type":"Point"}
}