{
  "type": "Feature",
  "properties": {
    "gn:admin1_code":"24.0",
    "gn:asciiname":"Shanshengou",
    "gn:country_code":"CN",
    "gn:dem":905,
    "gn:feature_class":"P",
    "gn:feature_code":"PPL",
    "gn:name":"Shanshengou",
    "gn:population":0,
    "gn:timezone":"Asia/Shanghai",
    "iso:country":"CN",
    "name:zho_x_preferred":[
        "\u5c71\u795e\u6c9f"
    ],
    "wof:name":"Shanshengou",
    "wof:placetype":"locality"
},
  "geometry": {"coordinates":[112.36872,35.70844],"type":"Point"}
}