{
  "type": "Feature",
  "properties": {
    "gn:admin1_code":"24.0",
    "gn:asciiname":"Mingxing",
    "gn:country_code":"CN",
    "gn:dem":1732,
    "gn:feature_class":"P",
    "gn:feature_code":"PPL",
    "gn:name":"Mingxing",
    "gn:population":0,
    "gn:timezone":"Asia/Shanghai",
    "iso:country":"CN",
    "name:und_x_variant":[
        "\u660e\u661f"
    ],
    "name:zho_x_preferred":[
        "\u660e\u661f"
    ],
    "wof:name":"Mingxing",
    "wof:placetype":"locality"
},
  "geometry": {"coordinates":[113.76474,39.20483],"type":"Point"}
}