{
  "type": "Feature",
  "properties": {
    "gn:admin1_code":"05",
    "gn:asciiname":"Kaoshan Chaoxianzucun",
    "gn:country_code":"CN",
    "gn:dem":293,
    "gn:feature_class":"P",
    "gn:feature_code":"PPL",
    "gn:name":"Kaoshan Chaoxianzucun",
    "gn:population":0,
    "gn:timezone":"Asia/Shanghai",
    "iso:country":"CN",
    "name:und_x_variant":[
        "Kaoshantun"
    ],
    "name:zho_x_preferred":[
        "\u9760\u5c71\u671d\u9c9c\u65cf\u6751"
    ],
    "wof:name":"Kaoshan Chaoxianzucun",
    "wof:placetype":"locality"
},
  "geometry": {"coordinates":[126.16083,42.80222],"type":"Point"}
}