{
  "type": "Feature",
  "properties": {
    "gn:admin1_code":"8.0",
    "gn:asciiname":"Lanqicun",
    "gn:country_code":"CN",
    "gn:dem":185,
    "gn:feature_class":"P",
    "gn:feature_code":"PPL",
    "gn:name":"Lanqicun",
    "gn:population":0,
    "gn:timezone":"Asia/Shanghai",
    "iso:country":"CN",
    "name:zho_x_preferred":[
        "\u5170\u65d7\u6751"
    ],
    "wof:name":"Lanqicun",
    "wof:placetype":"locality"
},
  "geometry": {"coordinates":[126.84951,45.43353],"type":"Point"}
}