{
  "type": "Feature",
  "properties": {
    "gn:admin1_code":"29.0",
    "gn:asciiname":"Baizhi Xincun",
    "gn:country_code":"CN",
    "gn:dem":1685,
    "gn:feature_class":"P",
    "gn:feature_code":"PPL",
    "gn:name":"Baizhi Xincun",
    "gn:population":0,
    "gn:timezone":"Asia/Shanghai",
    "iso:country":"CN",
    "name:zho_x_preferred":[
        "\u67cf\u679d\u65b0\u6751"
    ],
    "wof:name":"Baizhi Xincun",
    "wof:placetype":"locality"
},
  "geometry": {"coordinates":[100.444,24.7552],"type":"Point"}
}