{
  "type": "Feature",
  "properties": {
    "gn:admin1_code":"11.0",
    "gn:asciiname":"Ganqiang",
    "gn:country_code":"CN",
    "gn:dem":374,
    "gn:feature_class":"P",
    "gn:feature_code":"PPL",
    "gn:name":"Ganqiang",
    "gn:population":0,
    "gn:timezone":"Asia/Shanghai",
    "iso:country":"CN",
    "name:zho_x_preferred":[
        "\u5e72\u5899"
    ],
    "wof:name":"Ganqiang",
    "wof:placetype":"locality"
},
  "geometry": {"coordinates":[109.77981,26.67938],"type":"Point"}
}