{
  "type": "Feature",
  "properties": {
    "gn:admin1_code":"7",
    "gn:asciiname":"Xinancun",
    "gn:country_code":"CN",
    "gn:dem":570,
    "gn:feature_class":"P",
    "gn:feature_code":"PPL",
    "gn:name":"Xinancun",
    "gn:population":0,
    "gn:timezone":"Asia/Shanghai",
    "iso:country":"CN",
    "name:zho_x_preferred":[
        "\u6eaa\u5357\u6751"
    ],
    "wof:name":"Xinancun",
    "wof:placetype":"locality"
},
  "geometry": {"coordinates":[119.57368999999998,27.40542],"type":"Point"}
}