{
  "type": "Feature",
  "properties": {
    "gn:admin1_code":"26.0",
    "gn:asciiname":"Baichengzecun",
    "gn:country_code":"CN",
    "gn:dem":1140,
    "gn:feature_class":"P",
    "gn:feature_code":"PPL",
    "gn:name":"Baichengzecun",
    "gn:population":0,
    "gn:timezone":"Asia/Shanghai",
    "iso:country":"CN",
    "name:zho_x_preferred":[
        "\u767d\u57ce\u5219\u6751"
    ],
    "wof:name":"Baichengzecun",
    "wof:placetype":"locality"
},
  "geometry": {"coordinates":[108.86433999999998,37.9853],"type":"Point"}
}