{
  "type": "Feature",
  "properties": {
    "gn:admin1_code":"32.0",
    "gn:asciiname":"Luojun",
    "gn:country_code":"CN",
    "gn:dem":3177,
    "gn:feature_class":"P",
    "gn:feature_code":"PPL",
    "gn:name":"Luojun",
    "gn:population":0,
    "gn:timezone":"Asia/Shanghai",
    "iso:country":"CN",
    "name:zho_x_preferred":[
        "\u7f57\u519b"
    ],
    "wof:name":"Luojun",
    "wof:placetype":"locality"
},
  "geometry": {"coordinates":[102.88057000000001,34.22157],"type":"Point"}
}