{
  "type": "Feature",
  "properties": {
    "gn:admin1_code":"2.0",
    "gn:asciiname":"Mantang",
    "gn:country_code":"CN",
    "gn:dem":64,
    "gn:feature_class":"P",
    "gn:feature_code":"PPL",
    "gn:name":"Mantang",
    "gn:population":0,
    "gn:timezone":"Asia/Shanghai",
    "iso:country":"CN",
    "name:und_x_variant":[
        "\u6ee1\u5858",
        "Mantang"
    ],
    "wof:name":"Mantang",
    "wof:placetype":"locality"
},
  "geometry": {"coordinates":[119.86673,29.19911],"type":"Point"}
}