{
  "type": "Feature",
  "properties": {
    "gn:admin1_code":"15.0",
    "gn:asciiname":"Youfang Zuizi",
    "gn:country_code":"CN",
    "gn:dem":1362,
    "gn:feature_class":"P",
    "gn:feature_code":"PPL",
    "gn:name":"Youfang Zuizi",
    "gn:population":0,
    "gn:timezone":"Asia/Shanghai",
    "iso:country":"CN",
    "name:und_x_variant":[
        "\u6cb9\u623f\u5480\u5b50"
    ],
    "wof:name":"Youfang Zuizi",
    "wof:placetype":"locality"
},
  "geometry": {"coordinates":[107.82125000000001,36.69422],"type":"Point"}
}