{
  "type": "Feature",
  "properties": {
    "gn:admin1_code":"12",
    "gn:asciiname":"Liujiage",
    "gn:country_code":"CN",
    "gn:dem":29,
    "gn:feature_class":"P",
    "gn:feature_code":"PPLA4",
    "gn:name":"Liujiage",
    "gn:population":0,
    "gn:timezone":"Asia/Shanghai",
    "iso:country":"CN",
    "name:und_x_variant":[
        "Liu-chia-ko",
        "Liujiage",
        "Liujiage Zhen"
    ],
    "name:zho_x_preferred":[
        "\u5218\u5bb6\u9694"
    ],
    "name:zho_x_variant":[
        "\u5218\u5bb6\u9694\u9547"
    ],
    "wof:name":"Liujiage",
    "wof:placetype":"locality"
},
  "geometry": {"coordinates":[113.80856,30.75802],"type":"Point"}
}