{
  "type": "Feature",
  "properties": {
    "gn:admin1_code":"24.0",
    "gn:asciiname":"Yunquan",
    "gn:country_code":"CN",
    "gn:dem":913,
    "gn:feature_class":"P",
    "gn:feature_code":"PPL",
    "gn:name":"Yunquan",
    "gn:population":0,
    "gn:timezone":"Asia/Shanghai",
    "iso:country":"CN",
    "name:und_x_variant":[
        "Shih-k\u2019ou",
        "Y\u00fcn-ch\u2019\u00fcan",
        "Shih-tzu-k\u2019ou-ts\u2019un",
        "Shikou",
        "Yunquan"
    ],
    "name:zho_x_preferred":[
        "\u4e91\u6cc9"
    ],
    "wof:name":"Yunquan",
    "wof:placetype":"locality"
},
  "geometry": {"coordinates":[113.02643999999999,35.79958],"type":"Point"}
}