{
  "type": "Feature",
  "properties": {
    "gn:admin1_code":"11.0",
    "gn:asciiname":"Jianxin Nongchang Sandadui",
    "gn:country_code":"CN",
    "gn:dem":28,
    "gn:feature_class":"P",
    "gn:feature_code":"PPLF",
    "gn:name":"Jianxin Nongchang Sandadui",
    "gn:population":0,
    "gn:timezone":"Asia/Shanghai",
    "iso:country":"CN",
    "name:zho_x_preferred":[
        "\u5efa\u65b0\u519c\u573a\u4e09\u5927\u961f"
    ],
    "wof:name":"Jianxin Nongchang Sandadui",
    "wof:placetype":"locality"
},
  "geometry": {"coordinates":[112.84519,29.51723],"type":"Point"}
}