{
  "type": "Feature",
  "properties": {
    "gn:admin1_code":"19.0",
    "gn:asciiname":"Tongnaibeigou",
    "gn:country_code":"CN",
    "gn:dem":332,
    "gn:feature_class":"P",
    "gn:feature_code":"PPL",
    "gn:name":"Tongnaibeigou",
    "gn:population":0,
    "gn:timezone":"Asia/Shanghai",
    "iso:country":"CN",
    "name:zho_x_preferred":[
        "\u540c\u4e43\u5317\u6c9f"
    ],
    "wof:name":"Tongnaibeigou",
    "wof:placetype":"locality"
},
  "geometry": {"coordinates":[121.59999999999999,42.1609],"type":"Point"}
}