{
  "type": "Feature",
  "properties": {
    "gn:admin1_code":"9.0",
    "gn:asciiname":"Heidangou",
    "gn:country_code":"CN",
    "gn:dem":750,
    "gn:feature_class":"P",
    "gn:feature_code":"PPL",
    "gn:name":"Heidangou",
    "gn:population":0,
    "gn:timezone":"Asia/Shanghai",
    "iso:country":"CN",
    "name:und_x_variant":[
        "\u9ed1\u65e6\u6c9f",
        "Heidangou"
    ],
    "wof:name":"Heidangou",
    "wof:placetype":"locality"
},
  "geometry": {"coordinates":[112.22320999999999,33.26179],"type":"Point"}
}