{
  "type": "Feature",
  "properties": {
    "gn:admin1_code":"5.0",
    "gn:asciiname":"Wushibahaocun",
    "gn:country_code":"CN",
    "gn:dem":154,
    "gn:feature_class":"P",
    "gn:feature_code":"PPL",
    "gn:name":"Wushibahaocun",
    "gn:population":0,
    "gn:timezone":"Asia/Shanghai",
    "iso:country":"CN",
    "name:zho_x_preferred":[
        "\u4e94\u5341\u516b\u53f7\u6751"
    ],
    "wof:name":"Wushibahaocun",
    "wof:placetype":"locality"
},
  "geometry": {"coordinates":[123.38654,44.29748],"type":"Point"}
}