{
  "type": "Feature",
  "properties": {
    "gn:admin1_code":"19.0",
    "gn:asciiname":"Aoshihacun",
    "gn:country_code":"CN",
    "gn:dem":422,
    "gn:feature_class":"P",
    "gn:feature_code":"PPL",
    "gn:name":"Aoshihacun",
    "gn:population":0,
    "gn:timezone":"Asia/Shanghai",
    "iso:country":"CN",
    "name:zho_x_preferred":[
        "\u6556\u77f3\u54c8\u6751"
    ],
    "wof:name":"Aoshihacun",
    "wof:placetype":"locality"
},
  "geometry": {"coordinates":[124.839,41.9284],"type":"Point"}
}