{
  "type": "Feature",
  "properties": {
    "gn:admin1_code":"31.0",
    "gn:asciiname":"Zi'e",
    "gn:country_code":"CN",
    "gn:dem":143,
    "gn:feature_class":"P",
    "gn:feature_code":"PPL",
    "gn:name":"Zi\u2019e",
    "gn:population":0,
    "gn:timezone":"Asia/Shanghai",
    "iso:country":"CN",
    "name:zho_x_preferred":[
        "Zi\u2019e"
    ],
    "name:zho_x_variant":[
        "\u5b50\u843c"
    ],
    "wof:name":"Zi'e",
    "wof:placetype":"locality"
},
  "geometry": {"coordinates":[109.05719999999999,19.07442],"type":"Point"}
}