{
  "type": "Feature",
  "properties": {
    "gn:admin1_code":"14.0",
    "gn:asciiname":"Ba'en",
    "gn:country_code":"CN",
    "gn:dem":3926,
    "gn:feature_class":"P",
    "gn:feature_code":"PPL",
    "gn:name":"Ba\u2019en",
    "gn:population":0,
    "gn:timezone":"Asia/Urumqi",
    "iso:country":"CN",
    "name:und_x_variant":[
        "Ba\u2019en"
    ],
    "name:zho_x_preferred":[
        "\u5df4\u6069"
    ],
    "wof:name":"Ba'en",
    "wof:placetype":"locality"
},
  "geometry": {"coordinates":[95.21803,31.24551],"type":"Point"}
}