{
  "type": "Feature",
  "properties": {
    "gn:admin1_code":"10",
    "gn:asciiname":"Huying",
    "gn:country_code":"CN",
    "gn:dem":600,
    "gn:feature_class":"P",
    "gn:feature_code":"PPL",
    "gn:name":"Huying",
    "gn:population":0,
    "gn:timezone":"Asia/Shanghai",
    "iso:country":"CN",
    "name:und_x_variant":[
        "Hu-chia-ying"
    ],
    "name:zho_x_preferred":[
        "\u80e1\u8425"
    ],
    "wof:name":"Huying",
    "wof:placetype":"locality"
},
  "geometry": {"coordinates":[117.70583000000001,40.70417],"type":"Point"}
}