{
  "type": "Feature",
  "properties": {
    "gn:admin1_code":"9",
    "gn:asciiname":"Huju",
    "gn:country_code":"CN",
    "gn:dem":59,
    "gn:feature_class":"P",
    "gn:feature_code":"PPL",
    "gn:name":"Huju",
    "gn:population":0,
    "gn:timezone":"Asia/Shanghai",
    "iso:country":"CN",
    "name:zho_x_preferred":[
        "\u80e1\u4e3e"
    ],
    "wof:name":"Huju",
    "wof:placetype":"locality"
},
  "geometry": {"coordinates":[115.25700000000001,34.3927],"type":"Point"}
}