{
  "type": "Feature",
  "properties": {
    "gn:admin1_code":"25.0",
    "gn:asciiname":"Dahuang",
    "gn:cc2":"CN",
    "gn:country_code":"CN",
    "gn:dem":49,
    "gn:feature_class":"P",
    "gn:feature_code":"PPL",
    "gn:name":"Dahuang",
    "gn:population":0,
    "gn:timezone":"Asia/Shanghai",
    "iso:country":"CN",
    "name:zho_x_preferred":[
        "\u5927\u8352"
    ],
    "wof:name":"Dahuang",
    "wof:placetype":"locality"
},
  "geometry": {"coordinates":[120.01506999999999,36.03543],"type":"Point"}
}