{
  "type": "Feature",
  "properties": {
    "gn:admin1_code":"20.0",
    "gn:asciiname":"Erdaogouzi",
    "gn:country_code":"CN",
    "gn:dem":851,
    "gn:feature_class":"P",
    "gn:feature_code":"PPL",
    "gn:name":"Erdaogouzi",
    "gn:population":0,
    "gn:timezone":"Asia/Shanghai",
    "iso:country":"CN",
    "name:zho_x_preferred":[
        "\u4e8c\u9053\u6c9f\u5b50"
    ],
    "wof:name":"Erdaogouzi",
    "wof:placetype":"locality"
},
  "geometry": {"coordinates":[121.30392999999999,48.23878],"type":"Point"}
}