{
  "type": "Feature",
  "properties": {
    "gn:admin1_code":"32",
    "gn:asciiname":"Shiyang",
    "gn:country_code":"CN",
    "gn:dem":638,
    "gn:feature_class":"P",
    "gn:feature_code":"PPL",
    "gn:name":"Shiyang",
    "gn:population":0,
    "gn:timezone":"Asia/Shanghai",
    "iso:country":"CN",
    "name:und_x_variant":[
        "Shih-yang-chen",
        "Shiyangzhen",
        "Shiyangchang",
        "Shiyang"
    ],
    "name:zho_x_preferred":[
        "\u77f3\u7f8a"
    ],
    "wof:name":"Shiyang",
    "wof:placetype":"locality"
},
  "geometry": {"coordinates":[103.64444,30.84461],"type":"Point"}
}