{
  "type": "Feature",
  "properties": {
    "gn:admin1_code":"32.0",
    "gn:asciiname":"Lieniu",
    "gn:country_code":"CN",
    "gn:dem":3377,
    "gn:feature_class":"P",
    "gn:feature_code":"PPL",
    "gn:name":"Lieniu",
    "gn:population":0,
    "gn:timezone":"Asia/Shanghai",
    "iso:country":"CN",
    "name:zho_x_preferred":[
        "\u52a3\u725b"
    ],
    "wof:name":"Lieniu",
    "wof:placetype":"locality"
},
  "geometry": {"coordinates":[101.202,28.4281],"type":"Point"}
}