{
  "type": "Feature",
  "properties": {
    "gn:admin1_code":"18.0",
    "gn:asciiname":"Qingkou",
    "gn:country_code":"CN",
    "gn:dem":1132,
    "gn:feature_class":"P",
    "gn:feature_code":"PPL",
    "gn:name":"Qingkou",
    "gn:population":0,
    "gn:timezone":"Asia/Shanghai",
    "iso:country":"CN",
    "name:zho_x_preferred":[
        "\u7b90\u53e3"
    ],
    "wof:name":"Qingkou",
    "wof:placetype":"locality"
},
  "geometry": {"coordinates":[106.36199999999999,27.079],"type":"Point"}
}