{
  "type": "Feature",
  "properties": {
    "gn:admin1_code":"3.0",
    "gn:asciiname":"Ba'erwo",
    "gn:country_code":"CN",
    "gn:dem":79,
    "gn:feature_class":"P",
    "gn:feature_code":"PPL",
    "gn:name":"Ba\u2019erwo",
    "gn:population":0,
    "gn:timezone":"Asia/Shanghai",
    "iso:country":"CN",
    "name:und_x_variant":[
        "Ba\u2019erwo",
        "\u516b\u8033\u7a9d"
    ],
    "wof:name":"Ba'erwo",
    "wof:placetype":"locality"
},
  "geometry": {"coordinates":[115.16245000000001,28.04178],"type":"Point"}
}