{
  "type": "Feature",
  "properties": {
    "gn:admin1_code":"4.0",
    "gn:asciiname":"Zhuchang",
    "gn:country_code":"CN",
    "gn:dem":17,
    "gn:feature_class":"P",
    "gn:feature_code":"PPLF",
    "gn:name":"Zhuchang",
    "gn:population":0,
    "gn:timezone":"Asia/Shanghai",
    "iso:country":"CN",
    "name:zho_x_preferred":[
        "\u732a\u573a"
    ],
    "wof:name":"Zhuchang",
    "wof:placetype":"locality"
},
  "geometry": {"coordinates":[119.20237,31.75871],"type":"Point"}
}