{
  "type": "Feature",
  "properties": {
    "gn:admin1_code":"26.0",
    "gn:asciiname":"yakoushang",
    "gn:country_code":"CN",
    "gn:dem":1359,
    "gn:feature_class":"P",
    "gn:feature_code":"PPL",
    "gn:name":"yakoushang",
    "gn:population":0,
    "gn:timezone":"Asia/Shanghai",
    "iso:country":"CN",
    "name:zho_x_preferred":[
        "\u57ad\u53e3\u4e0a"
    ],
    "wof:name":"yakoushang",
    "wof:placetype":"locality"
},
  "geometry": {"coordinates":[108.02571,32.41363],"type":"Point"}
}