{
  "type": "Feature",
  "properties": {
    "gn:admin1_code":"26.0",
    "gn:asciiname":"Wangxinzhuang",
    "gn:country_code":"CN",
    "gn:dem":1495,
    "gn:feature_class":"P",
    "gn:feature_code":"PPL",
    "gn:name":"Wangxinzhuang",
    "gn:population":0,
    "gn:timezone":"Asia/Shanghai",
    "iso:country":"CN",
    "name:zho_x_preferred":[
        "\u738b\u65b0\u5e84"
    ],
    "wof:name":"Wangxinzhuang",
    "wof:placetype":"locality"
},
  "geometry": {"coordinates":[108.73746,36.9139],"type":"Point"}
}