{
  "type": "Feature",
  "properties": {
    "gn:admin1_code":"19.0",
    "gn:admin2_code":"2037885.0",
    "gn:asciiname":"Huayuancun",
    "gn:country_code":"CN",
    "gn:dem":1,
    "gn:feature_class":"P",
    "gn:feature_code":"PPL",
    "gn:name":"Huayuancun",
    "gn:population":0,
    "gn:timezone":"Asia/Shanghai",
    "iso:country":"CN",
    "name:zho_x_preferred":[
        "\u82b1\u56ed\u6751"
    ],
    "wof:name":"Huayuancun",
    "wof:placetype":"locality"
},
  "geometry": {"coordinates":[124.3524,40.10634],"type":"Point"}
}