{
  "type": "Feature",
  "properties": {
    "gn:admin1_code":"24.0",
    "gn:asciiname":"Shangquan",
    "gn:country_code":"CN",
    "gn:dem":1106,
    "gn:feature_class":"P",
    "gn:feature_code":"PPL",
    "gn:name":"Shangquan",
    "gn:population":0,
    "gn:timezone":"Asia/Shanghai",
    "iso:country":"CN",
    "name:zho_x_preferred":[
        "\u4e0a\u6cc9"
    ],
    "wof:name":"Shangquan",
    "wof:placetype":"locality"
},
  "geometry": {"coordinates":[113.65012,40.21523],"type":"Point"}
}