{
  "type": "Feature",
  "properties": {
    "gn:admin1_code":"32.0",
    "gn:asciiname":"Dayanggou",
    "gn:country_code":"CN",
    "gn:dem":519,
    "gn:feature_class":"P",
    "gn:feature_code":"PPL",
    "gn:name":"Dayanggou",
    "gn:population":0,
    "gn:timezone":"Asia/Shanghai",
    "iso:country":"CN",
    "name:zho_x_preferred":[
        "\u5927\u6768\u6c9f"
    ],
    "wof:name":"Dayanggou",
    "wof:placetype":"locality"
},
  "geometry": {"coordinates":[103.387,29.9435],"type":"Point"}
}