{
  "type": "Feature",
  "properties": {
    "gn:admin1_code":"9.0",
    "gn:asciiname":"Xinzhen",
    "gn:cc2":"CN",
    "gn:country_code":"CN",
    "gn:dem":66,
    "gn:feature_class":"P",
    "gn:feature_code":"PPL",
    "gn:name":"Xinzhen",
    "gn:population":0,
    "gn:timezone":"Asia/Shanghai",
    "iso:country":"CN",
    "name:und_x_variant":[
        "Sin\u2019chzhen\u2019tszi",
        "Hsin-chen",
        "Hsin-chen-chi",
        "Xinzhen"
    ],
    "wof:name":"Xinzhen",
    "wof:placetype":"locality"
},
  "geometry": {"coordinates":[114.36472000000001,35.50972],"type":"Point"}
}