{
  "type": "Feature",
  "properties": {
    "gn:admin1_code":"03",
    "gn:asciiname":"Kuantian",
    "gn:country_code":"CN",
    "gn:dem":204,
    "gn:feature_class":"P",
    "gn:feature_code":"PPLA4",
    "gn:name":"Kuantian",
    "gn:population":0,
    "gn:timezone":"Asia/Shanghai",
    "iso:country":"CN",
    "name:und_x_variant":[
        "K\u2019uan-t\u2019ien",
        "Kuantian",
        "\u5bbd\u7530",
        "Kuantian Xiang",
        "\u5bbd\u7530\u4e61"
    ],
    "wof:name":"Kuantian",
    "wof:placetype":"locality"
},
  "geometry": {"coordinates":[115.6636,25.99861],"type":"Point"}
}