{
  "type": "Feature",
  "properties": {
    "gn:admin1_code":"32.0",
    "gn:asciiname":"Delazu",
    "gn:country_code":"CN",
    "gn:dem":3866,
    "gn:feature_class":"P",
    "gn:feature_code":"PPL",
    "gn:name":"Delazu",
    "gn:population":0,
    "gn:timezone":"Asia/Shanghai",
    "iso:country":"CN",
    "name:zho_x_preferred":[
        "\u5fb7\u62c9\u8db3"
    ],
    "wof:name":"Delazu",
    "wof:placetype":"locality"
},
  "geometry": {"coordinates":[102.33035,32.0081],"type":"Point"}
}