{
  "type": "Feature",
  "properties": {
    "gn:admin1_code":"26.0",
    "gn:asciiname":"Dongsizhang",
    "gn:country_code":"CN",
    "gn:dem":403,
    "gn:feature_class":"P",
    "gn:feature_code":"PPL",
    "gn:name":"Dongsizhang",
    "gn:population":0,
    "gn:timezone":"Asia/Shanghai",
    "iso:country":"CN",
    "name:zho_x_preferred":[
        "\u4e1c\u5bfa\u7ae0"
    ],
    "wof:name":"Dongsizhang",
    "wof:placetype":"locality"
},
  "geometry": {"coordinates":[108.45171999999999,34.19519],"type":"Point"}
}