{
  "type": "Feature",
  "properties": {
    "gn:admin1_code":"11.0",
    "gn:asciiname":"Jiaochong",
    "gn:country_code":"CN",
    "gn:dem":189,
    "gn:feature_class":"P",
    "gn:feature_code":"PPL",
    "gn:name":"Jiaochong",
    "gn:population":0,
    "gn:timezone":"Asia/Shanghai",
    "iso:country":"CN",
    "name:zho_x_preferred":[
        "\u89d2\u51b2"
    ],
    "wof:name":"Jiaochong",
    "wof:placetype":"locality"
},
  "geometry": {"coordinates":[113.33932,26.72309000000001],"type":"Point"}
}