{
  "type": "Feature",
  "properties": {
    "gn:admin1_code":"08",
    "gn:asciiname":"Hujil Tohom",
    "gn:country_code":"CN",
    "gn:dem":141,
    "gn:feature_class":"P",
    "gn:feature_code":"PPLA4",
    "gn:name":"Hujil Tohom",
    "gn:population":0,
    "gn:timezone":"Asia/Shanghai",
    "iso:country":"CN",
    "name:mon_x_preferred":[
        "Hujil Tohom"
    ],
    "name:und_x_variant":[
        "Huji Tumo",
        "Huji Tumo Zhen"
    ],
    "name:zho_x_preferred":[
        "\u80e1\u5409\u5410\u83ab"
    ],
    "name:zho_x_variant":[
        "\u80e1\u5409\u5410\u83ab\u9547"
    ],
    "wof:name":"Hujil Tohom",
    "wof:placetype":"locality"
},
  "geometry": {"coordinates":[124.13316,46.44751],"type":"Point"}
}