{
  "type": "Feature",
  "properties": {
    "gn:admin1_code":"05",
    "gn:asciiname":"Chelingbeicun",
    "gn:country_code":"CN",
    "gn:dem":497,
    "gn:feature_class":"P",
    "gn:feature_code":"PPL",
    "gn:name":"Chelingbeicun",
    "gn:population":0,
    "gn:timezone":"Asia/Shanghai",
    "iso:country":"CN",
    "name:und_x_variant":[
        "Ch\u2019e-ling-pei",
        "Chelingbei",
        "\u8f66\u5cad\u80cc",
        "Chelingbeicun"
    ],
    "name:zho_x_preferred":[
        "\u8f66\u5cad\u80cc\u6751"
    ],
    "wof:name":"Chelingbeicun",
    "wof:placetype":"locality"
},
  "geometry": {"coordinates":[125.59329,41.81211],"type":"Point"}
}