{
  "type": "Feature",
  "properties": {
    "gn:admin1_code":"04",
    "gn:asciiname":"Fangbang",
    "gn:cc2":"CN",
    "gn:country_code":"CN",
    "gn:dem":2,
    "gn:feature_class":"P",
    "gn:feature_code":"PPL",
    "gn:name":"Fangbang",
    "gn:population":0,
    "gn:timezone":"Asia/Shanghai",
    "iso:country":"CN",
    "name:und_x_variant":[
        "Feng-chia-pang",
        "Fangbang"
    ],
    "wof:name":"Fangbang",
    "wof:placetype":"locality"
},
  "geometry": {"coordinates":[120.58194,31.39472],"type":"Point"}
}