{
  "type": "Feature",
  "properties": {
    "gn:admin1_code":"30",
    "gn:asciiname":"Jiaoma",
    "gn:country_code":"CN",
    "gn:dem":266,
    "gn:feature_class":"P",
    "gn:feature_code":"PPL",
    "gn:name":"Jiaoma",
    "gn:population":0,
    "gn:timezone":"Asia/Shanghai",
    "iso:country":"CN",
    "name:zho_x_preferred":[
        "\u6559\u9a6c"
    ],
    "wof:name":"Jiaoma",
    "wof:placetype":"locality"
},
  "geometry": {"coordinates":[111.73264,22.52827000000001],"type":"Point"}
}