{
  "type": "Feature",
  "properties": {
    "gn:admin1_code":"21.0",
    "gn:asciiname":"Jinggou",
    "gn:country_code":"CN",
    "gn:dem":1451,
    "gn:feature_class":"P",
    "gn:feature_code":"PPL",
    "gn:name":"Jinggou",
    "gn:population":0,
    "gn:timezone":"Asia/Shanghai",
    "iso:country":"CN",
    "name:zho_x_preferred":[
        "\u4e95\u6c9f"
    ],
    "wof:name":"Jinggou",
    "wof:placetype":"locality"
},
  "geometry": {"coordinates":[107.295,37.512],"type":"Point"}
}