{
  "type": "Feature",
  "properties": {
    "gn:admin1_code":"29.0",
    "gn:asciiname":"Poyou",
    "gn:country_code":"CN",
    "gn:dem":1041,
    "gn:feature_class":"P",
    "gn:feature_code":"PPL",
    "gn:name":"Poyou",
    "gn:population":0,
    "gn:timezone":"Asia/Shanghai",
    "iso:country":"CN",
    "name:und_x_variant":[
        "Po-yu"
    ],
    "name:zho_x_preferred":[
        "\u5761\u6cb9"
    ],
    "wof:name":"Poyou",
    "wof:placetype":"locality"
},
  "geometry": {"coordinates":[105.545,23.6453],"type":"Point"}
}