{
  "type": "Feature",
  "properties": {
    "gn:admin1_code":"29.0",
    "gn:asciiname":"Tangxia",
    "gn:country_code":"CN",
    "gn:dem":1561,
    "gn:feature_class":"P",
    "gn:feature_code":"PPL",
    "gn:name":"Tangxia",
    "gn:population":0,
    "gn:timezone":"Asia/Shanghai",
    "iso:country":"CN",
    "name:zho_x_preferred":[
        "\u5858\u4e0b"
    ],
    "wof:name":"Tangxia",
    "wof:placetype":"locality"
},
  "geometry": {"coordinates":[104.18000000000001,23.9393],"type":"Point"}
}