{
  "type": "Feature",
  "properties": {
    "gn:admin1_code":"19.0",
    "gn:asciiname":"Hulutangcun",
    "gn:country_code":"CN",
    "gn:dem":154,
    "gn:feature_class":"P",
    "gn:feature_code":"PPL",
    "gn:name":"Hulutangcun",
    "gn:population":0,
    "gn:timezone":"Asia/Shanghai",
    "iso:country":"CN",
    "name:zho_x_preferred":[
        "\u846b\u82a6\u6c64\u6751"
    ],
    "wof:name":"Hulutangcun",
    "wof:placetype":"locality"
},
  "geometry": {"coordinates":[121.38,41.8596],"type":"Point"}
}