{
  "type": "Feature",
  "properties": {
    "gn:admin1_code":"10",
    "gn:asciiname":"Shibozhen",
    "gn:cc2":"CN",
    "gn:country_code":"CN",
    "gn:dem":526,
    "gn:feature_class":"P",
    "gn:feature_code":"PPL",
    "gn:name":"Shibozhen",
    "gn:population":0,
    "gn:timezone":"Asia/Shanghai",
    "iso:country":"CN",
    "name:und_x_variant":[
        "Shih-po-chen",
        "Shibozhen"
    ],
    "wof:name":"Shibozhen",
    "wof:placetype":"locality"
},
  "geometry": {"coordinates":[113.84999999999999,36.63333],"type":"Point"}
}