{
  "type": "Feature",
  "properties": {
    "gn:admin1_code":"15.0",
    "gn:asciiname":"Fenhuocha",
    "gn:country_code":"CN",
    "gn:dem":2241,
    "gn:feature_class":"P",
    "gn:feature_code":"PPL",
    "gn:name":"Fenhuocha",
    "gn:population":0,
    "gn:timezone":"Asia/Shanghai",
    "iso:country":"CN",
    "name:zho_x_preferred":[
        "\u5206\u8c41\u5c94"
    ],
    "wof:name":"Fenhuocha",
    "wof:placetype":"locality"
},
  "geometry": {"coordinates":[104.051,35.8413],"type":"Point"}
}