{
  "type": "Feature",
  "properties": {
    "gn:admin1_code":"8.0",
    "gn:asciiname":"Xinhua Nongchang Ershisidui",
    "gn:country_code":"CN",
    "gn:dem":83,
    "gn:feature_class":"P",
    "gn:feature_code":"PPLF",
    "gn:name":"Xinhua Nongchang Ershisidui",
    "gn:population":0,
    "gn:timezone":"Asia/Shanghai",
    "iso:country":"CN",
    "name:zho_x_preferred":[
        "\u65b0\u534e\u519c\u573a\u4e8c\u5341\u56db\u961f"
    ],
    "wof:name":"Xinhua Nongchang Ershisidui",
    "wof:placetype":"locality"
},
  "geometry": {"coordinates":[130.41771,47.16702],"type":"Point"}
}