{
  "type": "Feature",
  "properties": {
    "gn:admin1_code":"02",
    "gn:asciiname":"Yu-chia",
    "gn:country_code":"CN",
    "gn:dem":98,
    "gn:feature_class":"P",
    "gn:feature_code":"PPL",
    "gn:name":"Yu-chia",
    "gn:population":0,
    "gn:timezone":"Asia/Shanghai",
    "iso:country":"CN",
    "wof:name":"Yu-chia",
    "wof:placetype":"locality"
},
  "geometry": {"coordinates":[121.47528,29.43361],"type":"Point"}
}