{
  "type": "Feature",
  "properties": {
    "gn:admin1_code":"32.0",
    "gn:asciiname":"Xu'erwan",
    "gn:country_code":"CN",
    "gn:dem":938,
    "gn:feature_class":"P",
    "gn:feature_code":"PPL",
    "gn:name":"Xu\u2019erwan",
    "gn:population":0,
    "gn:timezone":"Asia/Shanghai",
    "iso:country":"CN",
    "name:und_x_variant":[
        "Xu\u2019erwan"
    ],
    "name:zho_x_preferred":[
        "\u5f90\u4e8c\u6e7e"
    ],
    "wof:name":"Xu'erwan",
    "wof:placetype":"locality"
},
  "geometry": {"coordinates":[107.133,32.3633],"type":"Point"}
}