{
  "type": "Feature",
  "properties": {
    "gn:admin1_code":"7.0",
    "gn:asciiname":"Xinnancun",
    "gn:country_code":"CN",
    "gn:dem":32,
    "gn:feature_class":"P",
    "gn:feature_code":"PPL",
    "gn:name":"Xinnancun",
    "gn:population":0,
    "gn:timezone":"Asia/Shanghai",
    "iso:country":"CN",
    "name:zho_x_preferred":[
        "\u65b0\u5357\u6751"
    ],
    "wof:name":"Xinnancun",
    "wof:placetype":"locality"
},
  "geometry": {"coordinates":[118.62072999999999,24.97933],"type":"Point"}
}