{
  "type": "Feature",
  "properties": {
    "gn:admin1_code":"18",
    "gn:asciiname":"Silitai",
    "gn:country_code":"CN",
    "gn:dem":714,
    "gn:feature_class":"P",
    "gn:feature_code":"PPL",
    "gn:name":"Silitai",
    "gn:population":0,
    "gn:timezone":"Asia/Shanghai",
    "iso:country":"CN",
    "name:zho_x_preferred":[
        "\u4e1d\u6817\u53f0"
    ],
    "wof:name":"Silitai",
    "wof:placetype":"locality"
},
  "geometry": {"coordinates":[107.366,28.474],"type":"Point"}
}