{
  "type": "Feature",
  "properties": {
    "gn:admin1_code":"4.0",
    "gn:asciiname":"Weidongcun",
    "gn:country_code":"CN",
    "gn:dem":-1,
    "gn:feature_class":"P",
    "gn:feature_code":"PPL",
    "gn:name":"Weidongcun",
    "gn:population":0,
    "gn:timezone":"Asia/Shanghai",
    "iso:country":"CN",
    "name:zho_x_preferred":[
        "\u536b\u4e1c\u6751"
    ],
    "wof:name":"Weidongcun",
    "wof:placetype":"locality"
},
  "geometry": {"coordinates":[120.09528,34.13708],"type":"Point"}
}