{
  "type": "Feature",
  "properties": {
    "gn:admin1_code":"8.0",
    "gn:asciiname":"Sijiazi",
    "gn:country_code":"CN",
    "gn:dem":308,
    "gn:feature_class":"P",
    "gn:feature_code":"PPL",
    "gn:name":"Sijiazi",
    "gn:population":0,
    "gn:timezone":"Asia/Shanghai",
    "iso:country":"CN",
    "name:zho_x_preferred":[
        "\u56db\u5bb6\u5b50"
    ],
    "wof:name":"Sijiazi",
    "wof:placetype":"locality"
},
  "geometry": {"coordinates":[128.20248999999998,45.62884],"type":"Point"}
}