{
  "type": "Feature",
  "properties": {
    "gn:admin1_code":"3.0",
    "gn:asciiname":"Changgang",
    "gn:country_code":"CN",
    "gn:dem":33,
    "gn:feature_class":"P",
    "gn:feature_code":"PPL",
    "gn:name":"Changgang",
    "gn:population":0,
    "gn:timezone":"Asia/Shanghai",
    "iso:country":"CN",
    "name:und_x_variant":[
        "\u957f\u5c97"
    ],
    "wof:name":"Changgang",
    "wof:placetype":"locality"
},
  "geometry": {"coordinates":[115.54219000000001,28.4873],"type":"Point"}
}