{
  "type": "Feature",
  "properties": {
    "gn:admin1_code":"5.0",
    "gn:asciiname":"Gaogucun",
    "gn:country_code":"CN",
    "gn:dem":274,
    "gn:feature_class":"P",
    "gn:feature_code":"PPL",
    "gn:name":"Gaogucun",
    "gn:population":0,
    "gn:timezone":"Asia/Shanghai",
    "iso:country":"CN",
    "name:zho_x_preferred":[
        "\u9ad8\u53e4\u6751"
    ],
    "wof:name":"Gaogucun",
    "wof:placetype":"locality"
},
  "geometry": {"coordinates":[125.08266999999999,42.97505],"type":"Point"}
}