{
  "type": "Feature",
  "properties": {
    "gn:admin1_code":"10",
    "gn:asciiname":"Houqizhuang",
    "gn:country_code":"CN",
    "gn:dem":1113,
    "gn:feature_class":"P",
    "gn:feature_code":"PPL",
    "gn:name":"Houqizhuang",
    "gn:population":0,
    "gn:timezone":"Asia/Shanghai",
    "iso:country":"CN",
    "name:zho_x_preferred":[
        "\u4faf\u5176\u5e84"
    ],
    "wof:name":"Houqizhuang",
    "wof:placetype":"locality"
},
  "geometry": {"coordinates":[114.59706,40.83752],"type":"Point"}
}