{
  "type": "Feature",
  "properties": {
    "gn:admin1_code":"2.0",
    "gn:asciiname":"Duyu",
    "gn:country_code":"CN",
    "gn:dem":27,
    "gn:feature_class":"P",
    "gn:feature_code":"PPL",
    "gn:name":"Duyu",
    "gn:population":0,
    "gn:timezone":"Asia/Shanghai",
    "iso:country":"CN",
    "name:zho_x_preferred":[
        "\u675c\u9884"
    ],
    "wof:name":"Duyu",
    "wof:placetype":"locality"
},
  "geometry": {"coordinates":[119.59281,29.81583],"type":"Point"}
}