{
  "type": "Feature",
  "properties": {
    "gn:admin1_code":"15.0",
    "gn:asciiname":"Xiajia Hepan",
    "gn:country_code":"CN",
    "gn:dem":1874,
    "gn:feature_class":"P",
    "gn:feature_code":"PPL",
    "gn:name":"Xiajia Hepan",
    "gn:population":0,
    "gn:timezone":"Asia/Shanghai",
    "iso:country":"CN",
    "name:zho_x_preferred":[
        "\u590f\u5bb6\u6cb3\u7554"
    ],
    "wof:name":"Xiajia Hepan",
    "wof:placetype":"locality"
},
  "geometry": {"coordinates":[105.402,36.1423],"type":"Point"}
}