{
  "type": "Feature",
  "properties": {
    "gn:admin1_code":"9.0",
    "gn:asciiname":"Mianyangpo",
    "gn:country_code":"CN",
    "gn:dem":491,
    "gn:feature_class":"P",
    "gn:feature_code":"PPL",
    "gn:name":"Mianyangpo",
    "gn:population":0,
    "gn:timezone":"Asia/Shanghai",
    "iso:country":"CN",
    "name:zho_x_preferred":[
        "\u68c9\u7f8a\u5761"
    ],
    "wof:name":"Mianyangpo",
    "wof:placetype":"locality"
},
  "geometry": {"coordinates":[112.09014999999999,34.2655],"type":"Point"}
}