{
  "type": "Feature",
  "properties": {
    "gn:admin1_code":"24.0",
    "gn:asciiname":"Yangfang",
    "gn:country_code":"CN",
    "gn:dem":1477,
    "gn:feature_class":"P",
    "gn:feature_code":"PPL",
    "gn:name":"Yangfang",
    "gn:population":0,
    "gn:timezone":"Asia/Shanghai",
    "iso:country":"CN",
    "name:zho_x_preferred":[
        "\u7f8a\u65b9"
    ],
    "wof:name":"Yangfang",
    "wof:placetype":"locality"
},
  "geometry": {"coordinates":[111.93698000000001,38.98876],"type":"Point"}
}