{
  "type": "Feature",
  "properties": {
    "gn:admin1_code":"18.0",
    "gn:asciiname":"Laoyangpingchang",
    "gn:country_code":"CN",
    "gn:dem":507,
    "gn:feature_class":"P",
    "gn:feature_code":"PPL",
    "gn:name":"Laoyangpingchang",
    "gn:population":0,
    "gn:timezone":"Asia/Shanghai",
    "iso:country":"CN",
    "name:und_x_variant":[
        "Laoyangping"
    ],
    "name:zho_x_preferred":[
        "\u8001\u7f8a\u576a\u573a"
    ],
    "wof:name":"Laoyangpingchang",
    "wof:placetype":"locality"
},
  "geometry": {"coordinates":[109.06389,27.59111],"type":"Point"}
}