{
  "type": "Feature",
  "properties": {
    "gn:admin1_code":"2.0",
    "gn:asciiname":"Tianwanli",
    "gn:country_code":"CN",
    "gn:dem":5,
    "gn:feature_class":"P",
    "gn:feature_code":"PPL",
    "gn:name":"Tianwanli",
    "gn:population":0,
    "gn:timezone":"Asia/Shanghai",
    "iso:country":"CN",
    "name:und_x_variant":[
        "\u7530\u6e7e\u91cc"
    ],
    "wof:name":"Tianwanli",
    "wof:placetype":"locality"
},
  "geometry": {"coordinates":[120.20769,30.55801],"type":"Point"}
}