{
  "type": "Feature",
  "properties": {
    "gn:admin1_code":"24.0",
    "gn:asciiname":"Hualincun",
    "gn:country_code":"CN",
    "gn:dem":1030,
    "gn:feature_class":"P",
    "gn:feature_code":"PPL",
    "gn:name":"Hualincun",
    "gn:population":0,
    "gn:timezone":"Asia/Shanghai",
    "iso:country":"CN",
    "name:zho_x_preferred":[
        "\u6866\u6797\u6751"
    ],
    "wof:name":"Hualincun",
    "wof:placetype":"locality"
},
  "geometry": {"coordinates":[110.95437,38.01649000000001],"type":"Point"}
}