{
  "type": "Feature",
  "properties": {
    "gn:admin1_code":"4.0",
    "gn:asciiname":"Sunzhuyuan",
    "gn:country_code":"CN",
    "gn:dem":6,
    "gn:feature_class":"P",
    "gn:feature_code":"PPL",
    "gn:name":"Sunzhuyuan",
    "gn:population":0,
    "gn:timezone":"Asia/Shanghai",
    "iso:country":"CN",
    "name:zho_x_preferred":[
        "\u5b59\u7af9\u56ed"
    ],
    "wof:name":"Sunzhuyuan",
    "wof:placetype":"locality"
},
  "geometry": {"coordinates":[119.003,34.0282],"type":"Point"}
}