{
  "type": "Feature",
  "properties": {
    "gn:admin1_code":"8.0",
    "gn:asciiname":"Juxingtun",
    "gn:country_code":"CN",
    "gn:dem":185,
    "gn:feature_class":"P",
    "gn:feature_code":"PPL",
    "gn:name":"Juxingtun",
    "gn:population":0,
    "gn:timezone":"Asia/Shanghai",
    "iso:country":"CN",
    "name:zho_x_preferred":[
        "\u5de8\u5174\u5c6f"
    ],
    "wof:name":"Juxingtun",
    "wof:placetype":"locality"
},
  "geometry": {"coordinates":[127.90326,46.40831],"type":"Point"}
}