{
  "type": "Feature",
  "properties": {
    "gn:admin1_code":"21.0",
    "gn:asciiname":"Hongbao",
    "gn:country_code":"CN",
    "gn:dem":1276,
    "gn:feature_class":"P",
    "gn:feature_code":"PPL",
    "gn:name":"Hongbao",
    "gn:population":0,
    "gn:timezone":"Asia/Shanghai",
    "iso:country":"CN",
    "name:zho_x_preferred":[
        "\u7ea2\u5b9d"
    ],
    "wof:name":"Hongbao",
    "wof:placetype":"locality"
},
  "geometry": {"coordinates":[105.593,37.3864],"type":"Point"}
}