{
  "type": "Feature",
  "properties": {
    "gn:admin1_code":"12.0",
    "gn:asciiname":"Sanwudun",
    "gn:country_code":"CN",
    "gn:dem":23,
    "gn:feature_class":"P",
    "gn:feature_code":"PPL",
    "gn:name":"Sanwudun",
    "gn:population":0,
    "gn:timezone":"Asia/Shanghai",
    "iso:country":"CN",
    "name:zho_x_preferred":[
        "\u4e09\u5c4b\u58a9"
    ],
    "wof:name":"Sanwudun",
    "wof:placetype":"locality"
},
  "geometry": {"coordinates":[113.22381,29.90685],"type":"Point"}
}