{
  "type": "Feature",
  "properties": {
    "gn:admin1_code":"25",
    "gn:asciiname":"Xiajia Dianzi",
    "gn:country_code":"CN",
    "gn:dem":13,
    "gn:feature_class":"P",
    "gn:feature_code":"PPL",
    "gn:name":"Xiajia Dianzi",
    "gn:population":0,
    "gn:timezone":"Asia/Shanghai",
    "iso:country":"CN",
    "name:zho_x_preferred":[
        "\u590f\u5bb6\u5e97\u5b50"
    ],
    "wof:name":"Xiajia Dianzi",
    "wof:placetype":"locality"
},
  "geometry": {"coordinates":[118.67400000000001,36.9549],"type":"Point"}
}