{
  "type": "Feature",
  "properties": {
    "gn:admin1_code":"18.0",
    "gn:asciiname":"Lannichong",
    "gn:country_code":"CN",
    "gn:dem":553,
    "gn:feature_class":"P",
    "gn:feature_code":"PPL",
    "gn:name":"Lannichong",
    "gn:population":0,
    "gn:timezone":"Asia/Shanghai",
    "iso:country":"CN",
    "name:zho_x_preferred":[
        "\u6ee5\u6ce5\u51b2"
    ],
    "wof:name":"Lannichong",
    "wof:placetype":"locality"
},
  "geometry": {"coordinates":[109.199,26.61],"type":"Point"}
}