{
  "type": "Feature",
  "properties": {
    "gn:admin1_code":"29.0",
    "gn:asciiname":"Datuomagou",
    "gn:country_code":"CN",
    "gn:dem":2022,
    "gn:feature_class":"P",
    "gn:feature_code":"PPL",
    "gn:name":"Datuomagou",
    "gn:population":0,
    "gn:timezone":"Asia/Shanghai",
    "iso:country":"CN",
    "name:zho_x_preferred":[
        "\u5927\u62d6\u9a6c\u6c9f"
    ],
    "wof:name":"Datuomagou",
    "wof:placetype":"locality"
},
  "geometry": {"coordinates":[104.136,26.3284],"type":"Point"}
}