{
  "type": "Feature",
  "properties": {
    "gn:admin1_code":"9",
    "gn:asciiname":"Tantou",
    "gn:country_code":"CN",
    "gn:dem":54,
    "gn:feature_class":"P",
    "gn:feature_code":"PPL",
    "gn:name":"Tantou",
    "gn:population":0,
    "gn:timezone":"Asia/Shanghai",
    "iso:country":"CN",
    "name:ceb_x_preferred":[
        "Tantou"
    ],
    "name:deu_x_preferred":[
        "Tantou"
    ],
    "name:fra_x_preferred":[
        "Tantou"
    ],
    "name:swe_x_preferred":[
        "Tantou"
    ],
    "name:zho_x_preferred":[
        "\u6f6d\u5934"
    ],
    "wof:name":"Tantou",
    "wof:placetype":"locality"
},
  "geometry": {"coordinates":[114.88200000000001,35.9846],"type":"Point"}
}