{
  "type": "Feature",
  "properties": {
    "gn:admin1_code":"26.0",
    "gn:asciiname":"Lang'ergou",
    "gn:country_code":"CN",
    "gn:dem":1601,
    "gn:feature_class":"P",
    "gn:feature_code":"PPL",
    "gn:name":"Lang\u2019ergou",
    "gn:population":0,
    "gn:timezone":"Asia/Shanghai",
    "iso:country":"CN",
    "name:und_x_variant":[
        "Lang\u2019ergou"
    ],
    "name:zho_x_preferred":[
        "\u72fc\u513f\u6c9f"
    ],
    "wof:name":"Lang'ergou",
    "wof:placetype":"locality"
},
  "geometry": {"coordinates":[108.74051,37.21762],"type":"Point"}
}