{
  "type": "Feature",
  "properties": {
    "gn:admin1_code":"29.0",
    "gn:asciiname":"Shuidongguawan",
    "gn:country_code":"CN",
    "gn:dem":2225,
    "gn:feature_class":"P",
    "gn:feature_code":"PPL",
    "gn:name":"Shuidongguawan",
    "gn:population":0,
    "gn:timezone":"Asia/Shanghai",
    "iso:country":"CN",
    "name:zho_x_preferred":[
        "\u6c34\u51ac\u74dc\u6e7e"
    ],
    "wof:name":"Shuidongguawan",
    "wof:placetype":"locality"
},
  "geometry": {"coordinates":[103.099,25.9279],"type":"Point"}
}