{
  "type": "Feature",
  "properties": {
    "gn:admin1_code":"26.0",
    "gn:asciiname":"Changzui",
    "gn:country_code":"CN",
    "gn:dem":1468,
    "gn:feature_class":"P",
    "gn:feature_code":"PPL",
    "gn:name":"Changzui",
    "gn:population":0,
    "gn:timezone":"Asia/Shanghai",
    "iso:country":"CN",
    "name:und_x_variant":[
        "\u573a\u5480"
    ],
    "wof:name":"Changzui",
    "wof:placetype":"locality"
},
  "geometry": {"coordinates":[107.51608,34.76215],"type":"Point"}
}