{
  "type": "Feature",
  "properties": {
    "gn:admin1_code":"32.0",
    "gn:asciiname":"Zhangdeng Pingzi",
    "gn:country_code":"CN",
    "gn:dem":1623,
    "gn:feature_class":"P",
    "gn:feature_code":"PPL",
    "gn:name":"Zhangdeng Pingzi",
    "gn:population":0,
    "gn:timezone":"Asia/Shanghai",
    "iso:country":"CN",
    "name:zho_x_preferred":[
        "\u5f20\u706f\u576a\u5b50"
    ],
    "wof:name":"Zhangdeng Pingzi",
    "wof:placetype":"locality"
},
  "geometry": {"coordinates":[103.78121,28.29677],"type":"Point"}
}