{
  "type": "Feature",
  "properties": {
    "gn:admin1_code":"11.0",
    "gn:asciiname":"Jiulingjiao",
    "gn:country_code":"CN",
    "gn:dem":353,
    "gn:feature_class":"P",
    "gn:feature_code":"PPL",
    "gn:name":"Jiulingjiao",
    "gn:population":0,
    "gn:timezone":"Asia/Shanghai",
    "iso:country":"CN",
    "name:zho_x_preferred":[
        "\u4e5d\u5cad\u811a"
    ],
    "wof:name":"Jiulingjiao",
    "wof:placetype":"locality"
},
  "geometry": {"coordinates":[109.71872999999999,26.22511],"type":"Point"}
}