{
  "type": "Feature",
  "properties": {
    "gn:admin1_code":"1.0",
    "gn:asciiname":"Sanlucun",
    "gn:country_code":"CN",
    "gn:dem":26,
    "gn:feature_class":"P",
    "gn:feature_code":"PPL",
    "gn:name":"Sanlucun",
    "gn:population":0,
    "gn:timezone":"Asia/Shanghai",
    "iso:country":"CN",
    "name:zho_x_preferred":[
        "\u4e09\u82a6\u6751"
    ],
    "wof:name":"Sanlucun",
    "wof:placetype":"locality"
},
  "geometry": {"coordinates":[117.67641,33.73218],"type":"Point"}
}