{
  "type": "Feature",
  "properties": {
    "gn:admin1_code":"10",
    "gn:asciiname":"Fuzhangzi",
    "gn:country_code":"CN",
    "gn:dem":349,
    "gn:feature_class":"P",
    "gn:feature_code":"PPL",
    "gn:name":"Fuzhangzi",
    "gn:population":0,
    "gn:timezone":"Asia/Shanghai",
    "iso:country":"CN",
    "name:zho_x_preferred":[
        "\u5085\u6756\u5b50"
    ],
    "wof:name":"Fuzhangzi",
    "wof:placetype":"locality"
},
  "geometry": {"coordinates":[119.41386,40.50429000000001],"type":"Point"}
}