{
  "type": "Feature",
  "properties": {
    "gn:admin1_code":"24",
    "gn:asciiname":"Gudongdao",
    "gn:cc2":"CN",
    "gn:country_code":"CN",
    "gn:dem":1268,
    "gn:feature_class":"P",
    "gn:feature_code":"PPL",
    "gn:name":"Gudongdao",
    "gn:population":0,
    "gn:timezone":"Asia/Shanghai",
    "iso:country":"CN",
    "name:und_x_variant":[
        "Ku-tung-tao",
        "Gudongdao"
    ],
    "wof:name":"Gudongdao",
    "wof:placetype":"locality"
},
  "geometry": {"coordinates":[111.89778,37.70111],"type":"Point"}
}