{
  "type": "Feature",
  "properties": {
    "gn:admin1_code":"12.0",
    "gn:asciiname":"Sijiqing",
    "gn:country_code":"CN",
    "gn:dem":70,
    "gn:feature_class":"P",
    "gn:feature_code":"PPL",
    "gn:name":"Sijiqing",
    "gn:population":0,
    "gn:timezone":"Asia/Shanghai",
    "iso:country":"CN",
    "name:zho_x_preferred":[
        "\u56db\u5b63\u9752"
    ],
    "wof:name":"Sijiqing",
    "wof:placetype":"locality"
},
  "geometry": {"coordinates":[114.80609,31.24482],"type":"Point"}
}