{
  "type": "Feature",
  "properties": {
    "gn:admin1_code":"32.0",
    "gn:asciiname":"Maozishi",
    "gn:country_code":"CN",
    "gn:dem":715,
    "gn:feature_class":"P",
    "gn:feature_code":"PPL",
    "gn:name":"Maozishi",
    "gn:population":0,
    "gn:timezone":"Asia/Shanghai",
    "iso:country":"CN",
    "name:zho_x_preferred":[
        "\u5e3d\u5b50\u77f3"
    ],
    "wof:name":"Maozishi",
    "wof:placetype":"locality"
},
  "geometry": {"coordinates":[105.47799999999999,32.7489],"type":"Point"}
}