{
  "type": "Feature",
  "properties": {
    "gn:admin1_code":"2.0",
    "gn:asciiname":"Meilingxia",
    "gn:country_code":"CN",
    "gn:dem":47,
    "gn:feature_class":"P",
    "gn:feature_code":"PPL",
    "gn:name":"Meilingxia",
    "gn:population":0,
    "gn:timezone":"Asia/Shanghai",
    "iso:country":"CN",
    "name:zho_x_preferred":[
        "\u6885\u5cad\u4e0b"
    ],
    "wof:name":"Meilingxia",
    "wof:placetype":"locality"
},
  "geometry": {"coordinates":[121.39790000000001,29.5638],"type":"Point"}
}