{
  "type": "Feature",
  "properties": {
    "gn:admin1_code":"8.0",
    "gn:asciiname":"Nongjiacun",
    "gn:country_code":"CN",
    "gn:dem":88,
    "gn:feature_class":"P",
    "gn:feature_code":"PPLF",
    "gn:name":"Nongjiacun",
    "gn:population":0,
    "gn:timezone":"Asia/Shanghai",
    "iso:country":"CN",
    "name:zho_x_preferred":[
        "\u519c\u5bb6\u6751"
    ],
    "wof:name":"Nongjiacun",
    "wof:placetype":"locality"
},
  "geometry": {"coordinates":[130.4443,46.77903],"type":"Point"}
}