{
  "type": "Feature",
  "properties": {
    "gn:admin1_code":"1.0",
    "gn:asciiname":"Shupingcun",
    "gn:country_code":"CN",
    "gn:dem":18,
    "gn:feature_class":"P",
    "gn:feature_code":"PPL",
    "gn:name":"Shupingcun",
    "gn:population":0,
    "gn:timezone":"Asia/Shanghai",
    "iso:country":"CN",
    "name:zho_x_preferred":[
        "\u8212\u5e73\u6751"
    ],
    "wof:name":"Shupingcun",
    "wof:placetype":"locality"
},
  "geometry": {"coordinates":[117.08649,31.42688],"type":"Point"}
}