{
  "type": "Feature",
  "properties": {
    "gn:admin1_code":"3",
    "gn:asciiname":"Tangang",
    "gn:country_code":"CN",
    "gn:dem":123,
    "gn:feature_class":"P",
    "gn:feature_code":"PPLA4",
    "gn:name":"Tangang",
    "gn:population":0,
    "gn:timezone":"Asia/Shanghai",
    "iso:country":"CN",
    "name:und_x_variant":[
        "\u6f6d\u6e2f",
        "Tangang Xiang",
        "\u6f6d\u6e2f\u4e61"
    ],
    "wof:name":"Tangang",
    "wof:placetype":"locality"
},
  "geometry": {"coordinates":[115.75305,27.41714],"type":"Point"}
}