{
  "type": "Feature",
  "properties": {
    "gn:admin1_code":"15.0",
    "gn:asciiname":"Dangzhuang",
    "gn:country_code":"CN",
    "gn:dem":1185,
    "gn:feature_class":"P",
    "gn:feature_code":"PPL",
    "gn:name":"Dangzhuang",
    "gn:population":0,
    "gn:timezone":"Asia/Shanghai",
    "iso:country":"CN",
    "name:zho_x_preferred":[
        "\u5f53\u5e84"
    ],
    "wof:name":"Dangzhuang",
    "wof:placetype":"locality"
},
  "geometry": {"coordinates":[107.852,35.6188],"type":"Point"}
}