{
  "type": "Feature",
  "properties": {
    "gn:admin1_code":"32.0",
    "gn:asciiname":"Xiazijueba",
    "gn:country_code":"CN",
    "gn:dem":2494,
    "gn:feature_class":"P",
    "gn:feature_code":"PPL",
    "gn:name":"Xiazijueba",
    "gn:population":0,
    "gn:timezone":"Asia/Shanghai",
    "iso:country":"CN",
    "name:zho_x_preferred":[
        "\u5477\u5b50\u89c9\u628a"
    ],
    "wof:name":"Xiazijueba",
    "wof:placetype":"locality"
},
  "geometry": {"coordinates":[102.99299999999999,27.981],"type":"Point"}
}