{
  "type": "Feature",
  "properties": {
    "gn:admin1_code":"19.0",
    "gn:asciiname":"Tongjiafangcun",
    "gn:country_code":"CN",
    "gn:dem":29,
    "gn:feature_class":"P",
    "gn:feature_code":"PPL",
    "gn:name":"Tongjiafangcun",
    "gn:population":0,
    "gn:timezone":"Asia/Shanghai",
    "iso:country":"CN",
    "name:zho_x_preferred":[
        "\u4f5f\u5bb6\u574a\u6751"
    ],
    "wof:name":"Tongjiafangcun",
    "wof:placetype":"locality"
},
  "geometry": {"coordinates":[122.917,41.8714],"type":"Point"}
}