{
  "type": "Feature",
  "properties": {
    "gn:admin1_code":"5.0",
    "gn:asciiname":"Wenmingcun",
    "gn:country_code":"CN",
    "gn:dem":191,
    "gn:feature_class":"P",
    "gn:feature_code":"PPL",
    "gn:name":"Wenmingcun",
    "gn:population":0,
    "gn:timezone":"Asia/Shanghai",
    "iso:country":"CN",
    "name:zho_x_preferred":[
        "\u6587\u660e\u6751"
    ],
    "wof:name":"Wenmingcun",
    "wof:placetype":"locality"
},
  "geometry": {"coordinates":[126.91785,45.01999],"type":"Point"}
}