{
  "type": "Feature",
  "properties": {
    "gn:admin1_code":"29.0",
    "gn:asciiname":"Shidajiao",
    "gn:country_code":"CN",
    "gn:dem":2317,
    "gn:feature_class":"P",
    "gn:feature_code":"PPL",
    "gn:name":"Shidajiao",
    "gn:population":0,
    "gn:timezone":"Asia/Shanghai",
    "iso:country":"CN",
    "name:zho_x_preferred":[
        "\u77f3\u5927\u811a"
    ],
    "wof:name":"Shidajiao",
    "wof:placetype":"locality"
},
  "geometry": {"coordinates":[103.167,27.308],"type":"Point"}
}