{
  "type": "Feature",
  "properties": {
    "gn:admin1_code":"16",
    "gn:asciiname":"Tangzhuping",
    "gn:country_code":"CN",
    "gn:dem":686,
    "gn:feature_class":"P",
    "gn:feature_code":"PPL",
    "gn:name":"Tangzhuping",
    "gn:population":0,
    "gn:timezone":"Asia/Shanghai",
    "iso:country":"CN",
    "name:zho_x_preferred":[
        "\u5018\u7af9\u576a"
    ],
    "wof:name":"Tangzhuping",
    "wof:placetype":"locality"
},
  "geometry": {"coordinates":[110.714,25.2092],"type":"Point"}
}