{
  "type": "Feature",
  "properties": {
    "gn:admin1_code":"24",
    "gn:asciiname":"Qinshu",
    "gn:country_code":"CN",
    "gn:dem":985,
    "gn:feature_class":"P",
    "gn:feature_code":"PPL",
    "gn:name":"Qinshu",
    "gn:population":0,
    "gn:timezone":"Asia/Shanghai",
    "iso:country":"CN",
    "name:und_x_variant":[
        "Chen-shu-ts\u2019un",
        "Ch\u2019in-shu",
        "Qinshu"
    ],
    "name:zho_x_preferred":[
        "\u79e6\u6811"
    ],
    "wof:name":"Qinshu",
    "wof:placetype":"locality"
},
  "geometry": {"coordinates":[111.89136000000001,36.91411],"type":"Point"}
}