{
  "type": "Feature",
  "properties": {
    "gn:admin1_code":"29.0",
    "gn:asciiname":"Buluchang",
    "gn:country_code":"CN",
    "gn:dem":2535,
    "gn:feature_class":"P",
    "gn:feature_code":"PPL",
    "gn:name":"Buluchang",
    "gn:population":0,
    "gn:timezone":"Asia/Shanghai",
    "iso:country":"CN",
    "name:zho_x_preferred":[
        "\u5e03\u9c81\u660c"
    ],
    "wof:name":"Buluchang",
    "wof:placetype":"locality"
},
  "geometry": {"coordinates":[99.4849,27.2149],"type":"Point"}
}