{
  "type": "Feature",
  "properties": {
    "gn:admin1_code":"33.0",
    "gn:asciiname":"Shidou",
    "gn:country_code":"CN",
    "gn:dem":1574,
    "gn:feature_class":"P",
    "gn:feature_code":"PPL",
    "gn:name":"Shidou",
    "gn:population":0,
    "gn:timezone":"Asia/Shanghai",
    "iso:country":"CN",
    "name:zho_x_preferred":[
        "\u77f3\u6597"
    ],
    "wof:name":"Shidou",
    "wof:placetype":"locality"
},
  "geometry": {"coordinates":[108.60366,32.09898],"type":"Point"}
}