{
  "type": "Feature",
  "properties": {
    "gn:admin1_code":"8.0",
    "gn:asciiname":"Fuluncun",
    "gn:country_code":"CN",
    "gn:dem":182,
    "gn:feature_class":"P",
    "gn:feature_code":"PPL",
    "gn:name":"Fuluncun",
    "gn:population":0,
    "gn:timezone":"Asia/Shanghai",
    "iso:country":"CN",
    "name:zho_x_preferred":[
        "\u798f\u4f26\u6751"
    ],
    "wof:name":"Fuluncun",
    "wof:placetype":"locality"
},
  "geometry": {"coordinates":[126.46523999999999,47.07532],"type":"Point"}
}