{
  "type": "Feature",
  "properties": {
    "gn:admin1_code":"16.0",
    "gn:asciiname":"Menggan",
    "gn:country_code":"CN",
    "gn:dem":517,
    "gn:feature_class":"P",
    "gn:feature_code":"PPL",
    "gn:name":"Menggan",
    "gn:population":0,
    "gn:timezone":"Asia/Shanghai",
    "iso:country":"CN",
    "name:zho_x_preferred":[
        "\u5b5f\u6562"
    ],
    "wof:name":"Menggan",
    "wof:placetype":"locality"
},
  "geometry": {"coordinates":[106.29600000000001,23.9582],"type":"Point"}
}