{
  "type": "Feature",
  "properties": {
    "gn:admin1_code":"16.0",
    "gn:asciiname":"Xinlingnan",
    "gn:country_code":"CN",
    "gn:dem":154,
    "gn:feature_class":"P",
    "gn:feature_code":"PPL",
    "gn:name":"Xinlingnan",
    "gn:population":0,
    "gn:timezone":"Asia/Shanghai",
    "iso:country":"CN",
    "name:zho_x_preferred":[
        "\u65b0\u5cad\u5357"
    ],
    "wof:name":"Xinlingnan",
    "wof:placetype":"locality"
},
  "geometry": {"coordinates":[109.96899999999999,24.0584],"type":"Point"}
}