{
  "type": "Feature",
  "properties": {
    "gn:admin1_code":"07",
    "gn:asciiname":"Cunli",
    "gn:country_code":"CN",
    "gn:dem":274,
    "gn:feature_class":"P",
    "gn:feature_code":"PPL",
    "gn:name":"Cunli",
    "gn:population":0,
    "gn:timezone":"Asia/Shanghai",
    "iso:country":"CN",
    "name:zho_x_preferred":[
        "\u6751\u91cc"
    ],
    "wof:name":"Cunli",
    "wof:placetype":"locality"
},
  "geometry": {"coordinates":[116.42758000000001,24.88803],"type":"Point"}
}