{
  "type": "Feature",
  "properties": {
    "gn:admin1_code":"4.0",
    "gn:asciiname":"Chajiadun",
    "gn:country_code":"CN",
    "gn:dem":7,
    "gn:feature_class":"P",
    "gn:feature_code":"PPL",
    "gn:name":"Chajiadun",
    "gn:population":0,
    "gn:timezone":"Asia/Shanghai",
    "iso:country":"CN",
    "name:und_x_variant":[
        "\u5bdf\u5bb6\u58a9"
    ],
    "wof:name":"Chajiadun",
    "wof:placetype":"locality"
},
  "geometry": {"coordinates":[121.2813,32.33715],"type":"Point"}
}