{
  "type": "Feature",
  "properties": {
    "gn:admin1_code":"7",
    "gn:asciiname":"He'anxia",
    "gn:country_code":"CN",
    "gn:dem":221,
    "gn:feature_class":"P",
    "gn:feature_code":"PPL",
    "gn:name":"He\u2019anxia",
    "gn:population":0,
    "gn:timezone":"Asia/Shanghai",
    "iso:country":"CN",
    "name:und_x_variant":[
        "He\u2019anxiashan",
        "He\u2019anxia"
    ],
    "name:zho_x_preferred":[
        "\u548c\u5b89\u4e0b"
    ],
    "wof:name":"He'anxia",
    "wof:placetype":"locality"
},
  "geometry": {"coordinates":[119.6032,27.11992],"type":"Point"}
}