{
  "type": "Feature",
  "properties": {
    "gn:admin1_code":"26.0",
    "gn:asciiname":"Sanniu Goucun",
    "gn:country_code":"CN",
    "gn:dem":936,
    "gn:feature_class":"P",
    "gn:feature_code":"PPL",
    "gn:name":"Sanniu Goucun",
    "gn:population":0,
    "gn:timezone":"Asia/Shanghai",
    "iso:country":"CN",
    "name:zho_x_preferred":[
        "\u4e09\u725b\u6c9f\u6751"
    ],
    "wof:name":"Sanniu Goucun",
    "wof:placetype":"locality"
},
  "geometry": {"coordinates":[110.55800000000001,37.7801],"type":"Point"}
}