{
  "type": "Feature",
  "properties": {
    "gn:admin1_code":"25.0",
    "gn:asciiname":"Donggou Beituancun",
    "gn:country_code":"CN",
    "gn:dem":69,
    "gn:feature_class":"P",
    "gn:feature_code":"PPL",
    "gn:name":"Donggou Beituancun",
    "gn:population":0,
    "gn:timezone":"Asia/Shanghai",
    "iso:country":"CN",
    "name:zho_x_preferred":[
        "\u4e1c\u6c9f\u5317\u7583\u6751"
    ],
    "wof:name":"Donggou Beituancun",
    "wof:placetype":"locality"
},
  "geometry": {"coordinates":[122.30580999999999,37.14404],"type":"Point"}
}