{
  "type": "Feature",
  "properties": {
    "gn:admin1_code":"20",
    "gn:asciiname":"Gonglama",
    "gn:cc2":"CN",
    "gn:country_code":"CN",
    "gn:dem":1069,
    "gn:feature_class":"P",
    "gn:feature_code":"PPL",
    "gn:name":"Gonglama",
    "gn:population":0,
    "gn:timezone":"Asia/Shanghai",
    "iso:country":"CN",
    "name:und_x_variant":[
        "Kung-la-ma",
        "Gonglama"
    ],
    "wof:name":"Gonglama",
    "wof:placetype":"locality"
},
  "geometry": {"coordinates":[111.84999999999999,40.63333],"type":"Point"}
}