{
  "type": "Feature",
  "properties": {
    "gn:admin1_code":"10",
    "gn:asciiname":"Gougezhuang",
    "gn:cc2":"CN",
    "gn:country_code":"CN",
    "gn:dem":6,
    "gn:feature_class":"P",
    "gn:feature_code":"PPL",
    "gn:name":"Gougezhuang",
    "gn:population":0,
    "gn:timezone":"Asia/Shanghai",
    "iso:country":"CN",
    "name:und_x_variant":[
        "Kou-ko-chuang",
        "Gougezhuang"
    ],
    "wof:name":"Gougezhuang",
    "wof:placetype":"locality"
},
  "geometry": {"coordinates":[116.23333,38.88333],"type":"Point"}
}