{
  "type": "Feature",
  "properties": {
    "gn:admin1_code":"7",
    "gn:asciiname":"Zhuangbian",
    "gn:country_code":"CN",
    "gn:dem":419,
    "gn:feature_class":"P",
    "gn:feature_code":"PPL",
    "gn:name":"Zhuangbian",
    "gn:population":0,
    "gn:timezone":"Asia/Shanghai",
    "iso:country":"CN",
    "name:zho_x_preferred":[
        "\u5e84\u8fb9"
    ],
    "wof:name":"Zhuangbian",
    "wof:placetype":"locality"
},
  "geometry": {"coordinates":[118.92379,25.80277],"type":"Point"}
}