{
  "type": "Feature",
  "properties": {
    "gn:admin1_code":"11.0",
    "gn:asciiname":"Laojiangtian",
    "gn:country_code":"CN",
    "gn:dem":504,
    "gn:feature_class":"P",
    "gn:feature_code":"PPL",
    "gn:name":"Laojiangtian",
    "gn:population":0,
    "gn:timezone":"Asia/Shanghai",
    "iso:country":"CN",
    "name:zho_x_preferred":[
        "\u8001\u6c5f\u7530"
    ],
    "wof:name":"Laojiangtian",
    "wof:placetype":"locality"
},
  "geometry": {"coordinates":[109.56117,28.10807],"type":"Point"}
}