{
  "type": "Feature",
  "properties": {
    "gn:admin1_code":"11",
    "gn:asciiname":"Majiaqiao",
    "gn:country_code":"CN",
    "gn:dem":309,
    "gn:feature_class":"P",
    "gn:feature_code":"PPL",
    "gn:name":"Majiaqiao",
    "gn:population":0,
    "gn:timezone":"Asia/Shanghai",
    "iso:country":"CN",
    "name:zho_x_preferred":[
        "\u9a6c\u5bb6\u6865"
    ],
    "wof:name":"Majiaqiao",
    "wof:placetype":"locality"
},
  "geometry": {"coordinates":[111.10289,27.3482],"type":"Point"}
}