{
  "type": "Feature",
  "properties": {
    "gn:admin1_code":"2.0",
    "gn:asciiname":"Shinongxu",
    "gn:country_code":"CN",
    "gn:dem":263,
    "gn:feature_class":"P",
    "gn:feature_code":"PPL",
    "gn:name":"Shinongxu",
    "gn:population":0,
    "gn:timezone":"Asia/Shanghai",
    "iso:country":"CN",
    "name:zho_x_preferred":[
        "\u77f3\u5f04\u5729"
    ],
    "wof:name":"Shinongxu",
    "wof:placetype":"locality"
},
  "geometry": {"coordinates":[119.87803,28.27264000000001],"type":"Point"}
}