{
  "type": "Feature",
  "properties": {
    "gn:admin1_code":"18.0",
    "gn:asciiname":"Tudiguan",
    "gn:country_code":"CN",
    "gn:dem":1060,
    "gn:feature_class":"P",
    "gn:feature_code":"PPL",
    "gn:name":"Tudiguan",
    "gn:population":0,
    "gn:timezone":"Asia/Shanghai",
    "iso:country":"CN",
    "name:zho_x_preferred":[
        "\u571f\u5730\u5173"
    ],
    "wof:name":"Tudiguan",
    "wof:placetype":"locality"
},
  "geometry": {"coordinates":[107.20699999999999,26.3269],"type":"Point"}
}