{
  "type": "Feature",
  "properties": {
    "gn:admin1_code":"26.0",
    "gn:asciiname":"Dakengyan",
    "gn:country_code":"CN",
    "gn:dem":1353,
    "gn:feature_class":"P",
    "gn:feature_code":"PPL",
    "gn:name":"Dakengyan",
    "gn:population":0,
    "gn:timezone":"Asia/Shanghai",
    "iso:country":"CN",
    "name:zho_x_preferred":[
        "\u5927\u5751\u5830"
    ],
    "wof:name":"Dakengyan",
    "wof:placetype":"locality"
},
  "geometry": {"coordinates":[108.52769000000001,37.62697],"type":"Point"}
}