{
  "type": "Feature",
  "properties": {
    "gn:admin1_code":"24.0",
    "gn:asciiname":"Miaogou",
    "gn:country_code":"CN",
    "gn:dem":1541,
    "gn:feature_class":"P",
    "gn:feature_code":"PPL",
    "gn:name":"Miaogou",
    "gn:population":0,
    "gn:timezone":"Asia/Shanghai",
    "iso:country":"CN",
    "name:zho_x_preferred":[
        "\u5e99\u6c9f"
    ],
    "wof:name":"Miaogou",
    "wof:placetype":"locality"
},
  "geometry": {"coordinates":[112.08154999999999,38.38052],"type":"Point"}
}