{
  "type": "Feature",
  "properties": {
    "gn:admin1_code":"15.0",
    "gn:asciiname":"Shangcha",
    "gn:country_code":"CN",
    "gn:dem":1851,
    "gn:feature_class":"P",
    "gn:feature_code":"PPL",
    "gn:name":"Shangcha",
    "gn:population":0,
    "gn:timezone":"Asia/Shanghai",
    "iso:country":"CN",
    "name:und_x_variant":[
        "\u4e0a\u5c94"
    ],
    "wof:name":"Shangcha",
    "wof:placetype":"locality"
},
  "geometry": {"coordinates":[105.56252000000001,35.38],"type":"Point"}
}