{
  "type": "Feature",
  "properties": {
    "gn:admin1_code":"33.0",
    "gn:asciiname":"Pinghe",
    "gn:country_code":"CN",
    "gn:dem":195,
    "gn:feature_class":"P",
    "gn:feature_code":"PPLA4",
    "gn:name":"Pinghe",
    "gn:population":0,
    "gn:timezone":"Asia/Shanghai",
    "iso:country":"CN",
    "name:und_x_variant":[
        "Pinghe Xiang",
        "Yanchibang"
    ],
    "name:zho_x_preferred":[
        "\u5e73\u6cb3"
    ],
    "name:zho_x_variant":[
        "\u5e73\u6cb3\u4e61",
        "\u71d5\u7fc5\u585d"
    ],
    "wof:name":"Pinghe",
    "wof:placetype":"locality"
},
  "geometry": {"coordinates":[109.94767,31.25999],"type":"Point"}
}