{
  "type": "Feature",
  "properties": {
    "gn:admin1_code":"7.0",
    "gn:asciiname":"Xinling",
    "gn:country_code":"CN",
    "gn:dem":1014,
    "gn:feature_class":"P",
    "gn:feature_code":"PPL",
    "gn:name":"Xinling",
    "gn:population":0,
    "gn:timezone":"Asia/Shanghai",
    "iso:country":"CN",
    "name:zho_x_preferred":[
        "\u65b0\u5cad"
    ],
    "wof:name":"Xinling",
    "wof:placetype":"locality"
},
  "geometry": {"coordinates":[116.92751,25.8477],"type":"Point"}
}