{
  "type": "Feature",
  "properties": {
    "gn:admin1_code":"10",
    "gn:asciiname":"Shizhuliang",
    "gn:country_code":"CN",
    "gn:dem":1350,
    "gn:feature_class":"P",
    "gn:feature_code":"PPL",
    "gn:name":"Shizhuliang",
    "gn:population":0,
    "gn:timezone":"Asia/Shanghai",
    "iso:country":"CN",
    "name:zho_x_preferred":[
        "\u77f3\u67f1\u6881"
    ],
    "wof:name":"Shizhuliang",
    "wof:placetype":"locality"
},
  "geometry": {"coordinates":[114.66697000000001,41.37637],"type":"Point"}
}