{
  "type": "Feature",
  "properties": {
    "gn:admin1_code":"1.0",
    "gn:asciiname":"Dengwancun",
    "gn:country_code":"CN",
    "gn:dem":19,
    "gn:feature_class":"P",
    "gn:feature_code":"PPL",
    "gn:name":"Dengwancun",
    "gn:population":0,
    "gn:timezone":"Asia/Shanghai",
    "iso:country":"CN",
    "name:zho_x_preferred":[
        "\u9093\u6e7e\u6751"
    ],
    "wof:name":"Dengwancun",
    "wof:placetype":"locality"
},
  "geometry": {"coordinates":[117.92121000000002,33.35994],"type":"Point"}
}