{
  "type": "Feature",
  "properties": {
    "gn:admin1_code":"13.0",
    "gn:asciiname":"Nongyishi Batuan",
    "gn:country_code":"CN",
    "gn:dem":1032,
    "gn:feature_class":"P",
    "gn:feature_code":"PPL",
    "gn:name":"Nongyishi Batuan",
    "gn:population":0,
    "gn:timezone":"Asia/Shanghai",
    "iso:country":"CN",
    "name:und_x_variant":[
        "Sheng-li-shih-san-ch\u2019ang",
        "Shengli Shisanchang",
        "Nongyishi Batuan",
        "\u519c\u4e00\u5e08\u516b\u56e2",
        "\u80dc\u5229\u5341\u4e09\u573a"
    ],
    "wof:name":"Nongyishi Batuan",
    "wof:placetype":"locality"
},
  "geometry": {"coordinates":[80.90000000000001,40.75],"type":"Point"}
}