{
  "type": "Feature",
  "properties": {
    "gn:admin1_code":"10",
    "gn:asciiname":"Qianying",
    "gn:cc2":"CN",
    "gn:country_code":"CN",
    "gn:dem":14,
    "gn:feature_class":"P",
    "gn:feature_code":"PPL",
    "gn:name":"Qianying",
    "gn:population":0,
    "gn:timezone":"Asia/Shanghai",
    "iso:country":"CN",
    "name:und_x_variant":[
        "Ch\u2019ien-ying",
        "Chenying",
        "Ch\u2019ien-chia-ying",
        "Qianying"
    ],
    "wof:name":"Qianying",
    "wof:placetype":"locality"
},
  "geometry": {"coordinates":[118.31667,39.56667],"type":"Point"}
}