{
  "type": "Feature",
  "properties": {
    "gn:admin1_code":"32.0",
    "gn:asciiname":"Jingjiagou",
    "gn:country_code":"CN",
    "gn:dem":475,
    "gn:feature_class":"P",
    "gn:feature_code":"PPL",
    "gn:name":"Jingjiagou",
    "gn:population":0,
    "gn:timezone":"Asia/Shanghai",
    "iso:country":"CN",
    "name:zho_x_preferred":[
        "\u666f\u5bb6\u6c9f"
    ],
    "wof:name":"Jingjiagou",
    "wof:placetype":"locality"
},
  "geometry": {"coordinates":[104.917,31.3521],"type":"Point"}
}