{
  "type": "Feature",
  "properties": {
    "gn:admin1_code":"11.0",
    "gn:asciiname":"Fanshang Wujia",
    "gn:country_code":"CN",
    "gn:dem":48,
    "gn:feature_class":"P",
    "gn:feature_code":"PPL",
    "gn:name":"Fanshang Wujia",
    "gn:population":0,
    "gn:timezone":"Asia/Shanghai",
    "iso:country":"CN",
    "name:zho_x_preferred":[
        "\u7548\u4e0a\u5434\u5bb6"
    ],
    "wof:name":"Fanshang Wujia",
    "wof:placetype":"locality"
},
  "geometry": {"coordinates":[113.35966999999999,29.29393],"type":"Point"}
}