{
  "type": "Feature",
  "properties": {
    "gn:admin1_code":"29.0",
    "gn:asciiname":"Xianiuqiejiao",
    "gn:country_code":"CN",
    "gn:dem":1173,
    "gn:feature_class":"P",
    "gn:feature_code":"PPL",
    "gn:name":"Xianiuqiejiao",
    "gn:population":0,
    "gn:timezone":"Asia/Shanghai",
    "iso:country":"CN",
    "name:zho_x_preferred":[
        "\u4e0b\u725b\u4e14\u89d2"
    ],
    "wof:name":"Xianiuqiejiao",
    "wof:placetype":"locality"
},
  "geometry": {"coordinates":[101.858,22.8416],"type":"Point"}
}