{
  "type": "Feature",
  "properties": {
    "gn:admin1_code":"15.0",
    "gn:asciiname":"Xiawaligou",
    "gn:country_code":"CN",
    "gn:dem":2445,
    "gn:feature_class":"P",
    "gn:feature_code":"PPL",
    "gn:name":"Xiawaligou",
    "gn:population":0,
    "gn:timezone":"Asia/Shanghai",
    "iso:country":"CN",
    "name:und_x_variant":[
        "\u4e0b\u6316\u529b\u6c9f"
    ],
    "wof:name":"Xiawaligou",
    "wof:placetype":"locality"
},
  "geometry": {"coordinates":[103.97593999999999,34.67174],"type":"Point"}
}