{
  "type": "Feature",
  "properties": {
    "gn:admin1_code":"2.0",
    "gn:asciiname":"Tanglingtou",
    "gn:country_code":"CN",
    "gn:dem":779,
    "gn:feature_class":"P",
    "gn:feature_code":"PPL",
    "gn:name":"Tanglingtou",
    "gn:population":0,
    "gn:timezone":"Asia/Shanghai",
    "iso:country":"CN",
    "name:zho_x_preferred":[
        "\u5858\u5cad\u5934"
    ],
    "wof:name":"Tanglingtou",
    "wof:placetype":"locality"
},
  "geometry": {"coordinates":[119.10966000000001,28.66051],"type":"Point"}
}