{
  "type": "Feature",
  "properties": {
    "gn:admin1_code":"5.0",
    "gn:asciiname":"Huluxicun",
    "gn:country_code":"CN",
    "gn:dem":348,
    "gn:feature_class":"P",
    "gn:feature_code":"PPL",
    "gn:name":"Huluxicun",
    "gn:population":0,
    "gn:timezone":"Asia/Shanghai",
    "iso:country":"CN",
    "name:zho_x_preferred":[
        "\u846b\u82a6\u7ec6\u6751"
    ],
    "wof:name":"Huluxicun",
    "wof:placetype":"locality"
},
  "geometry": {"coordinates":[125.9331,43.09022],"type":"Point"}
}