{
  "type": "Feature",
  "properties": {
    "gn:admin1_code":"19.0",
    "gn:asciiname":"Dongfangshen",
    "gn:country_code":"CN",
    "gn:dem":18,
    "gn:feature_class":"P",
    "gn:feature_code":"PPL",
    "gn:name":"Dongfangshen",
    "gn:population":0,
    "gn:timezone":"Asia/Shanghai",
    "iso:country":"CN",
    "name:zho_x_preferred":[
        "\u4e1c\u623f\u8eab"
    ],
    "wof:name":"Dongfangshen",
    "wof:placetype":"locality"
},
  "geometry": {"coordinates":[121.67,39.25],"type":"Point"}
}