{
  "type": "Feature",
  "properties": {
    "gn:admin1_code":"4.0",
    "gn:asciiname":"Guanchangcun",
    "gn:country_code":"CN",
    "gn:dem":4,
    "gn:feature_class":"P",
    "gn:feature_code":"PPL",
    "gn:name":"Guanchangcun",
    "gn:population":0,
    "gn:timezone":"Asia/Shanghai",
    "iso:country":"CN",
    "name:zho_x_preferred":[
        "\u5b98\u573a\u6751"
    ],
    "wof:name":"Guanchangcun",
    "wof:placetype":"locality"
},
  "geometry": {"coordinates":[119.55670000000001,34.3429],"type":"Point"}
}