{
  "type": "Feature",
  "properties": {
    "gn:admin1_code":"29.0",
    "gn:asciiname":"Anle",
    "gn:country_code":"CN",
    "gn:dem":1527,
    "gn:feature_class":"P",
    "gn:feature_code":"PPL",
    "gn:name":"Anle",
    "gn:population":0,
    "gn:timezone":"Asia/Shanghai",
    "iso:country":"CN",
    "name:zho_x_preferred":[
        "\u5b89\u4e50"
    ],
    "wof:name":"Anle",
    "wof:placetype":"locality"
},
  "geometry": {"coordinates":[101.327,23.3598],"type":"Point"}
}