{
  "type": "Feature",
  "properties": {
    "gn:admin1_code":"05",
    "gn:asciiname":"Yangdachengzi",
    "gn:cc2":"CN",
    "gn:country_code":"CN",
    "gn:dem":205,
    "gn:feature_class":"P",
    "gn:feature_code":"PPL",
    "gn:name":"Yangdachengzi",
    "gn:population":0,
    "gn:timezone":"Asia/Shanghai",
    "iso:country":"CN",
    "name:und_x_variant":[
        "Yang-ta-ch\u2019eng-tzu",
        "Yangdachengzi"
    ],
    "name:zho_x_preferred":[
        "\u6768\u5927\u57ce\u5b50\u9547"
    ],
    "wof:name":"Yangdachengzi",
    "wof:placetype":"locality"
},
  "geometry": {"coordinates":[124.42471999999999,43.93444],"type":"Point"}
}