{
  "type": "Feature",
  "properties": {
    "gn:admin1_code":"30",
    "gn:asciiname":"Cunhuatang",
    "gn:country_code":"CN",
    "gn:dem":107,
    "gn:feature_class":"P",
    "gn:feature_code":"PPL",
    "gn:name":"Cunhuatang",
    "gn:population":0,
    "gn:timezone":"Asia/Shanghai",
    "iso:country":"CN",
    "name:zho_x_preferred":[
        "\u6751\u534e\u5858"
    ],
    "wof:name":"Cunhuatang",
    "wof:placetype":"locality"
},
  "geometry": {"coordinates":[115.70524,23.9835],"type":"Point"}
}