{
  "type": "Feature",
  "properties": {
    "gn:admin1_code":"15.0",
    "gn:asciiname":"Liangzhuang",
    "gn:country_code":"CN",
    "gn:dem":1471,
    "gn:feature_class":"P",
    "gn:feature_code":"PPL",
    "gn:name":"Liangzhuang",
    "gn:population":0,
    "gn:timezone":"Asia/Shanghai",
    "iso:country":"CN",
    "name:und_x_variant":[
        "\u6881\u5e84"
    ],
    "wof:name":"Liangzhuang",
    "wof:placetype":"locality"
},
  "geometry": {"coordinates":[107.27406000000001,36.84897],"type":"Point"}
}