{
  "type": "Feature",
  "properties": {
    "gn:admin1_code":"25.0",
    "gn:asciiname":"Xinugushancun",
    "gn:country_code":"CN",
    "gn:dem":12,
    "gn:feature_class":"P",
    "gn:feature_code":"PPL",
    "gn:name":"Xin\u00fcgushancun",
    "gn:population":0,
    "gn:timezone":"Asia/Shanghai",
    "iso:country":"CN",
    "name:und_x_variant":[
        "Xin\u00fcgushancun"
    ],
    "name:zho_x_preferred":[
        "\u897f\u5973\u59d1\u5c71\u6751"
    ],
    "wof:name":"Xinugushancun",
    "wof:placetype":"locality"
},
  "geometry": {"coordinates":[120.33811,36.23746],"type":"Point"}
}