{
  "type": "Feature",
  "properties": {
    "gn:admin1_code":"9.0",
    "gn:asciiname":"Jinggangtun",
    "gn:country_code":"CN",
    "gn:dem":64,
    "gn:feature_class":"P",
    "gn:feature_code":"PPL",
    "gn:name":"Jinggangtun",
    "gn:population":0,
    "gn:timezone":"Asia/Shanghai",
    "iso:country":"CN",
    "name:zho_x_preferred":[
        "\u8346\u5c97\u5c6f"
    ],
    "wof:name":"Jinggangtun",
    "wof:placetype":"locality"
},
  "geometry": {"coordinates":[114.6391,35.19579],"type":"Point"}
}