{
  "type": "Feature",
  "properties": {
    "gn:admin1_code":"1.0",
    "gn:asciiname":"Getuloucun",
    "gn:country_code":"CN",
    "gn:dem":37,
    "gn:feature_class":"P",
    "gn:feature_code":"PPL",
    "gn:name":"Getuloucun",
    "gn:population":0,
    "gn:timezone":"Asia/Shanghai",
    "iso:country":"CN",
    "name:zho_x_preferred":[
        "\u845b\u571f\u697c\u6751"
    ],
    "wof:name":"Getuloucun",
    "wof:placetype":"locality"
},
  "geometry": {"coordinates":[115.93655,33.61581],"type":"Point"}
}