{
  "type": "Feature",
  "properties": {
    "gn:admin1_code":"19.0",
    "gn:asciiname":"Shendian Guanjiagou",
    "gn:country_code":"CN",
    "gn:dem":94,
    "gn:feature_class":"P",
    "gn:feature_code":"PPL",
    "gn:name":"Shendian Guanjiagou",
    "gn:population":0,
    "gn:timezone":"Asia/Shanghai",
    "iso:country":"CN",
    "name:und_x_variant":[
        "\u6c88\u7538\u5173\u5bb6\u6c9f"
    ],
    "wof:name":"Shendian Guanjiagou",
    "wof:placetype":"locality"
},
  "geometry": {"coordinates":[123.84972999999999,40.18141],"type":"Point"}
}