{
  "type": "Feature",
  "properties": {
    "gn:admin1_code":"15.0",
    "gn:asciiname":"Nijiazhuang",
    "gn:country_code":"CN",
    "gn:dem":1394,
    "gn:feature_class":"P",
    "gn:feature_code":"PPL",
    "gn:name":"Nijiazhuang",
    "gn:population":0,
    "gn:timezone":"Asia/Shanghai",
    "iso:country":"CN",
    "name:zho_x_preferred":[
        "\u502a\u5bb6\u5e84"
    ],
    "wof:name":"Nijiazhuang",
    "wof:placetype":"locality"
},
  "geometry": {"coordinates":[100.23099999999999,39.2849],"type":"Point"}
}