{
  "type": "Feature",
  "properties": {
    "gn:admin1_code":"9.0",
    "gn:asciiname":"Jingyanzhuang",
    "gn:country_code":"CN",
    "gn:dem":166,
    "gn:feature_class":"P",
    "gn:feature_code":"PPL",
    "gn:name":"Jingyanzhuang",
    "gn:population":0,
    "gn:timezone":"Asia/Shanghai",
    "iso:country":"CN",
    "name:zho_x_preferred":[
        "\u4e95\u6cbf\u5e84"
    ],
    "wof:name":"Jingyanzhuang",
    "wof:placetype":"locality"
},
  "geometry": {"coordinates":[113.70247999999999,32.62207],"type":"Point"}
}