{
  "type": "Feature",
  "properties": {
    "gn:admin1_code":"29.0",
    "gn:asciiname":"Gehezhai",
    "gn:country_code":"CN",
    "gn:dem":1727,
    "gn:feature_class":"P",
    "gn:feature_code":"PPL",
    "gn:name":"Gehezhai",
    "gn:population":0,
    "gn:timezone":"Asia/Shanghai",
    "iso:country":"CN",
    "name:zho_x_preferred":[
        "\u683c\u6cb3\u5be8"
    ],
    "wof:name":"Gehezhai",
    "wof:placetype":"locality"
},
  "geometry": {"coordinates":[103.03700000000001,23.0382],"type":"Point"}
}