{
  "type": "Feature",
  "properties": {
    "gn:admin1_code":"4.0",
    "gn:asciiname":"Kushuyang",
    "gn:country_code":"CN",
    "gn:dem":6,
    "gn:feature_class":"P",
    "gn:feature_code":"PPL",
    "gn:name":"Kushuyang",
    "gn:population":0,
    "gn:timezone":"Asia/Shanghai",
    "iso:country":"CN",
    "name:und_x_variant":[
        "\u67af\u6811\u6d0b"
    ],
    "wof:name":"Kushuyang",
    "wof:placetype":"locality"
},
  "geometry": {"coordinates":[120.71943,32.99392],"type":"Point"}
}