{
  "type": "Feature",
  "properties": {
    "gn:admin1_code":"11.0",
    "gn:asciiname":"Yanzhuping",
    "gn:country_code":"CN",
    "gn:dem":358,
    "gn:feature_class":"P",
    "gn:feature_code":"PPL",
    "gn:name":"Yanzhuping",
    "gn:population":0,
    "gn:timezone":"Asia/Shanghai",
    "iso:country":"CN",
    "name:zho_x_preferred":[
        "\u70df\u7af9\u576a"
    ],
    "wof:name":"Yanzhuping",
    "wof:placetype":"locality"
},
  "geometry": {"coordinates":[113.58172,28.3295],"type":"Point"}
}