{
  "type": "Feature",
  "properties": {
    "gn:admin1_code":"15.0",
    "gn:asciiname":"Gengjiahe",
    "gn:country_code":"CN",
    "gn:dem":1452,
    "gn:feature_class":"P",
    "gn:feature_code":"PPL",
    "gn:name":"Gengjiahe",
    "gn:population":0,
    "gn:timezone":"Asia/Shanghai",
    "iso:country":"CN",
    "name:und_x_variant":[
        "\u803f\u5bb6\u6cb3"
    ],
    "wof:name":"Gengjiahe",
    "wof:placetype":"locality"
},
  "geometry": {"coordinates":[107.41691000000002,36.8929],"type":"Point"}
}