{
  "type": "Feature",
  "properties": {
    "gn:admin1_code":"2.0",
    "gn:asciiname":"Wutuan",
    "gn:country_code":"CN",
    "gn:dem":69,
    "gn:feature_class":"P",
    "gn:feature_code":"PPL",
    "gn:name":"Wutuan",
    "gn:population":0,
    "gn:timezone":"Asia/Shanghai",
    "iso:country":"CN",
    "name:ceb_x_preferred":[
        "Wutuan"
    ],
    "name:swe_x_preferred":[
        "Wutuan"
    ],
    "name:zho_x_preferred":[
        "\u4e94\u56e2"
    ],
    "name:zho_x_variant":[
        "\u4e94\u56e2\u9547"
    ],
    "wof:name":"Wutuan",
    "wof:placetype":"locality"
},
  "geometry": {"coordinates":[121.40809,28.89142],"type":"Point"}
}