{
  "type": "Feature",
  "properties": {
    "gn:admin1_code":"3.0",
    "gn:asciiname":"Waisong",
    "gn:country_code":"CN",
    "gn:dem":362,
    "gn:feature_class":"P",
    "gn:feature_code":"PPL",
    "gn:name":"Waisong",
    "gn:population":0,
    "gn:timezone":"Asia/Shanghai",
    "iso:country":"CN",
    "name:zho_x_preferred":[
        "\u5916\u5b8b"
    ],
    "wof:name":"Waisong",
    "wof:placetype":"locality"
},
  "geometry": {"coordinates":[117.28663,28.72102000000001],"type":"Point"}
}