{
  "type": "Feature",
  "properties": {
    "gn:admin1_code":"9.0",
    "gn:asciiname":"Chaidong",
    "gn:country_code":"CN",
    "gn:dem":234,
    "gn:feature_class":"P",
    "gn:feature_code":"PPL",
    "gn:name":"Chaidong",
    "gn:population":0,
    "gn:timezone":"Asia/Shanghai",
    "iso:country":"CN",
    "name:zho_x_preferred":[
        "\u67f4\u578c"
    ],
    "wof:name":"Chaidong",
    "wof:placetype":"locality"
},
  "geometry": {"coordinates":[113.25494999999999,34.30228],"type":"Point"}
}