{
  "type": "Feature",
  "properties": {
    "gn:admin1_code":"31.0",
    "gn:asciiname":"Houpaitian",
    "gn:country_code":"CN",
    "gn:dem":11,
    "gn:feature_class":"P",
    "gn:feature_code":"PPL",
    "gn:name":"Houpaitian",
    "gn:population":0,
    "gn:timezone":"Asia/Shanghai",
    "iso:country":"CN",
    "name:zho_x_preferred":[
        "Houpaitian"
    ],
    "name:zho_x_variant":[
        "\u540e\u6392\u7530"
    ],
    "wof:name":"Houpaitian",
    "wof:placetype":"locality"
},
  "geometry": {"coordinates":[110.79783,19.6588],"type":"Point"}
}