{
  "type": "Feature",
  "properties": {
    "gn:admin1_code":"32.0",
    "gn:asciiname":"Kuaboluo",
    "gn:country_code":"CN",
    "gn:dem":2637,
    "gn:feature_class":"P",
    "gn:feature_code":"PPL",
    "gn:name":"Kuaboluo",
    "gn:population":0,
    "gn:timezone":"Asia/Shanghai",
    "iso:country":"CN",
    "name:zho_x_preferred":[
        "\u8de8\u83e0\u841d"
    ],
    "wof:name":"Kuaboluo",
    "wof:placetype":"locality"
},
  "geometry": {"coordinates":[101.52202,27.73064],"type":"Point"}
}