{
  "type": "Feature",
  "properties": {
    "gn:admin1_code":"24.0",
    "gn:asciiname":"Beisong",
    "gn:country_code":"CN",
    "gn:dem":1035,
    "gn:feature_class":"P",
    "gn:feature_code":"PPL",
    "gn:name":"Beisong",
    "gn:population":0,
    "gn:timezone":"Asia/Shanghai",
    "iso:country":"CN",
    "name:zho_x_preferred":[
        "\u5317\u5b8b"
    ],
    "wof:name":"Beisong",
    "wof:placetype":"locality"
},
  "geometry": {"coordinates":[113.06740000000001,35.94069000000001],"type":"Point"}
}