{
  "type": "Feature",
  "properties": {
    "gn:admin1_code":"30",
    "gn:asciiname":"Heliaoba",
    "gn:country_code":"CN",
    "gn:dem":138,
    "gn:feature_class":"P",
    "gn:feature_code":"PPL",
    "gn:name":"Heliaoba",
    "gn:population":0,
    "gn:timezone":"Asia/Shanghai",
    "iso:country":"CN",
    "name:und_x_variant":[
        "\u79be\u5be5\u575d"
    ],
    "wof:name":"Heliaoba",
    "wof:placetype":"locality"
},
  "geometry": {"coordinates":[114.81625,23.61171],"type":"Point"}
}