{
  "type": "Feature",
  "properties": {
    "gn:admin1_code":"10",
    "gn:asciiname":"Hongyatun",
    "gn:country_code":"CN",
    "gn:dem":79,
    "gn:feature_class":"P",
    "gn:feature_code":"PPL",
    "gn:name":"Hongyatun",
    "gn:population":0,
    "gn:timezone":"Asia/Shanghai",
    "iso:country":"CN",
    "name:zho_x_preferred":[
        "\u9e3f\u9e2d\u5c6f"
    ],
    "wof:name":"Hongyatun",
    "wof:placetype":"locality"
},
  "geometry": {"coordinates":[118.06574999999999,40.19681],"type":"Point"}
}