{
  "type": "Feature",
  "properties": {
    "gn:admin1_code":"14.0",
    "gn:asciiname":"Shemucun",
    "gn:country_code":"CN",
    "gn:dem":3167,
    "gn:feature_class":"P",
    "gn:feature_code":"PPL",
    "gn:name":"Shemucun",
    "gn:population":0,
    "gn:timezone":"Asia/Urumqi",
    "iso:country":"CN",
    "name:zho_x_preferred":[
        "\u820d\u6728\u6751"
    ],
    "wof:name":"Shemucun",
    "wof:placetype":"locality"
},
  "geometry": {"coordinates":[91.81097,27.92142],"type":"Point"}
}