{
  "type": "Feature",
  "properties": {
    "gn:admin1_code":"25",
    "gn:asciiname":"Nanshendun",
    "gn:country_code":"CN",
    "gn:dem":108,
    "gn:feature_class":"P",
    "gn:feature_code":"PPL",
    "gn:name":"Nanshendun",
    "gn:population":0,
    "gn:timezone":"Asia/Shanghai",
    "iso:country":"CN",
    "name:zho_x_preferred":[
        "\u5357\u795e\u58a9"
    ],
    "wof:name":"Nanshendun",
    "wof:placetype":"locality"
},
  "geometry": {"coordinates":[118.533,35.5421],"type":"Point"}
}