{
  "type": "Feature",
  "properties": {
    "gn:admin1_code":"16.0",
    "gn:asciiname":"Shangdu",
    "gn:country_code":"CN",
    "gn:dem":113,
    "gn:feature_class":"P",
    "gn:feature_code":"PPL",
    "gn:name":"Shangdu",
    "gn:population":0,
    "gn:timezone":"Asia/Shanghai",
    "iso:country":"CN",
    "name:zho_x_preferred":[
        "\u4e0a\u90fd"
    ],
    "wof:name":"Shangdu",
    "wof:placetype":"locality"
},
  "geometry": {"coordinates":[110.575,23.0585],"type":"Point"}
}