{
  "type": "Feature",
  "properties": {
    "gn:admin1_code":"16.0",
    "gn:asciiname":"Shangdu",
    "gn:country_code":"CN",
    "gn:dem":113,
    "gn:feature_class":"P",
    "gn:feature_code":"PPL",
    "gn:name":"Shangdu",
    "gn:population":0,
    "gn:timezone":"Asia/Shanghai",
    "iso:country":"CN",
    "name:afr_x_preferred":[
        "Shangdu"
    ],
    "name:als_x_preferred":[
        "Shangdu"
    ],
    "name:ast_x_preferred":[
        "Xanad\u00fa"
    ],
    "name:bul_x_preferred":[
        "\u0428\u0430\u043d\u0434\u0443"
    ],
    "name:cat_x_preferred":[
        "Xanad\u00fa"
    ],
    "name:ces_x_preferred":[
        "\u0160ang-tu"
    ],
    "name:deu_x_preferred":[
        "Shangdu"
    ],
    "name:est_x_preferred":[
        "Shangdu"
    ],
    "name:eus_x_preferred":[
        "Xanadu"
    ],
    "name:fas_x_preferred":[
        "\u0634\u0627\u0646\u06af\u062f\u0648"
    ],
    "name:fin_x_preferred":[
        "Xanadu"
    ],
    "name:fra_x_preferred":[
        "Shangdu"
    ],
    "name:heb_x_preferred":[
        "\u05d6\u05d0\u05e0\u05d0\u05d3\u05d5"
    ],
    "name:hrv_x_preferred":[
        "Xanadu"
    ],
    "name:hun_x_preferred":[
        "Xanadu"
    ],
    "name:ind_x_preferred":[
        "Xanadu"
    ],
    "name:ita_x_preferred":[
        "Xanadu"
    ],
    "name:kat_x_preferred":[
        "\u10e8\u10d0\u10dc\u10d3\u10e3"
    ],
    "name:kor_x_preferred":[
        "\uc0c1\ub3c4"
    ],
    "name:lit_x_preferred":[
        "\u0160andu"
    ],
    "name:mon_x_preferred":[
        "\u0428\u0430\u043d\u0434\u0443"
    ],
    "name:nld_x_preferred":[
        "Xanadu"
    ],
    "name:nor_x_preferred":[
        "Xanadu"
    ],
    "name:pol_x_preferred":[
        "Xanadu"
    ],
    "name:por_x_preferred":[
        "Shangdu"
    ],
    "name:rus_x_preferred":[
        "\u0428\u0430\u043d\u0434\u0443"
    ],
    "name:spa_x_preferred":[
        "Xanad\u00fa"
    ],
    "name:srp_x_preferred":[
        "\u041a\u0441\u0430\u043d\u0430\u0434\u0443"
    ],
    "name:swe_x_preferred":[
        "Xanadu"
    ],
    "name:tha_x_preferred":[
        "\u0e41\u0e2b\u0e25\u0e48\u0e07\u0e41\u0e0b\u0e19\u0e32\u0e14\u0e39"
    ],
    "name:tur_x_preferred":[
        "Shangdu"
    ],
    "name:ukr_x_preferred":[
        "\u0428\u0430\u043d\u0434\u0443"
    ],
    "name:urd_x_preferred":[
        "\u0633\u0646\u0627\u062f\u0648"
    ],
    "name:vie_x_preferred":[
        "Th\u01b0\u1ee3ng \u0110\u00f4"
    ],
    "name:zho_x_preferred":[
        "\u4e0a\u90fd"
    ],
    "name:zho_x_variant":[
        "\u5143\u4e0a\u90fd"
    ],
    "wof:name":"Shangdu",
    "wof:placetype":"locality"
},
  "geometry": {"coordinates":[110.575,23.0585],"type":"Point"}
}