{
  "type": "Feature",
  "properties": {
    "gn:admin1_code":"0.0",
    "gn:asciiname":"Man-kuo",
    "gn:country_code":"CN",
    "gn:dem":1762,
    "gn:feature_class":"P",
    "gn:feature_code":"PPL",
    "gn:name":"Man-kuo",
    "gn:population":0,
    "gn:timezone":"Asia/Shanghai",
    "iso:country":"CN",
    "wof:name":"Man-kuo",
    "wof:placetype":"locality"
},
  "geometry": {"coordinates":[99.60726,23.37662000000001],"type":"Point"}
}