{
  "type": "Feature",
  "properties": {
    "gn:admin1_code":"9",
    "gn:asciiname":"Liuyangzhuang",
    "gn:country_code":"CN",
    "gn:dem":62,
    "gn:feature_class":"P",
    "gn:feature_code":"PPL",
    "gn:name":"Liuyangzhuang",
    "gn:population":0,
    "gn:timezone":"Asia/Shanghai",
    "iso:country":"CN",
    "name:zho_x_preferred":[
        "\u5218\u6768\u5e84"
    ],
    "wof:name":"Liuyangzhuang",
    "wof:placetype":"locality"
},
  "geometry": {"coordinates":[115.932,34.5644],"type":"Point"}
}