{
  "type": "Feature",
  "properties": {
    "gn:admin1_code":"1.0",
    "gn:asciiname":"Lintangxian",
    "gn:country_code":"CN",
    "gn:dem":27,
    "gn:feature_class":"P",
    "gn:feature_code":"PPL",
    "gn:name":"Lintangxian",
    "gn:population":0,
    "gn:timezone":"Asia/Shanghai",
    "iso:country":"CN",
    "name:zho_x_preferred":[
        "\u6797\u5858\u5c98"
    ],
    "wof:name":"Lintangxian",
    "wof:placetype":"locality"
},
  "geometry": {"coordinates":[118.66931,31.6273],"type":"Point"}
}