{
  "type": "Feature",
  "properties": {
    "gn:admin1_code":"3.0",
    "gn:asciiname":"Yutanli",
    "gn:country_code":"CN",
    "gn:dem":35,
    "gn:feature_class":"P",
    "gn:feature_code":"PPL",
    "gn:name":"Yutanli",
    "gn:population":0,
    "gn:timezone":"Asia/Shanghai",
    "iso:country":"CN",
    "name:und_x_variant":[
        "\u96e8\u6ee9\u91cc"
    ],
    "wof:name":"Yutanli",
    "wof:placetype":"locality"
},
  "geometry": {"coordinates":[115.81683,28.2465],"type":"Point"}
}