{
  "type": "Feature",
  "properties": {
    "gn:admin1_code":"29.0",
    "gn:asciiname":"Yansepo",
    "gn:country_code":"CN",
    "gn:dem":1837,
    "gn:feature_class":"P",
    "gn:feature_code":"PPL",
    "gn:name":"Yansepo",
    "gn:population":0,
    "gn:timezone":"Asia/Shanghai",
    "iso:country":"CN",
    "name:zho_x_preferred":[
        "\u8273\u8272\u5761"
    ],
    "wof:name":"Yansepo",
    "wof:placetype":"locality"
},
  "geometry": {"coordinates":[103.646,24.5226],"type":"Point"}
}