{
  "type": "Feature",
  "properties": {
    "gn:admin1_code":"07",
    "gn:asciiname":"Dongyangshan",
    "gn:country_code":"CN",
    "gn:dem":311,
    "gn:feature_class":"P",
    "gn:feature_code":"PPL",
    "gn:name":"Dongyangshan",
    "gn:population":0,
    "gn:timezone":"Asia/Shanghai",
    "iso:country":"CN",
    "name:zho_x_preferred":[
        "\u4e1c\u6d0b\u5c71"
    ],
    "wof:name":"Dongyangshan",
    "wof:placetype":"locality"
},
  "geometry": {"coordinates":[116.3836,24.83308],"type":"Point"}
}