{
  "type": "Feature",
  "properties": {
    "gn:admin1_code":"14.0",
    "gn:asciiname":"Jiaqionggong",
    "gn:country_code":"CN",
    "gn:dem":4453,
    "gn:feature_class":"P",
    "gn:feature_code":"PPL",
    "gn:name":"Jiaqionggong",
    "gn:population":0,
    "gn:timezone":"Asia/Urumqi",
    "iso:country":"CN",
    "name:zho_x_preferred":[
        "\u52a0\u743c\u8d21"
    ],
    "wof:name":"Jiaqionggong",
    "wof:placetype":"locality"
},
  "geometry": {"coordinates":[98.67784,30.67144],"type":"Point"}
}