{
  "type": "Feature",
  "properties": {
    "gn:admin1_code":"30",
    "gn:asciiname":"Dingchang",
    "gn:country_code":"CN",
    "gn:dem":203,
    "gn:feature_class":"P",
    "gn:feature_code":"PPL",
    "gn:name":"Dingchang",
    "gn:population":0,
    "gn:timezone":"Asia/Shanghai",
    "iso:country":"CN",
    "wof:name":"Dingchang",
    "wof:placetype":"locality"
},
  "geometry": {"coordinates":[116.13861,23.16583],"type":"Point"}
}