{
  "type": "Feature",
  "properties": {
    "gn:admin1_code":"4.0",
    "gn:asciiname":"Shangxigan",
    "gn:country_code":"CN",
    "gn:dem":4,
    "gn:feature_class":"P",
    "gn:feature_code":"PPL",
    "gn:name":"Shangxigan",
    "gn:population":0,
    "gn:timezone":"Asia/Shanghai",
    "iso:country":"CN",
    "name:und_x_variant":[
        "\u4e0a\u897f\u5769"
    ],
    "name:zho_x_preferred":[
        "\u4e0a\u897f\u5769"
    ],
    "wof:name":"Shangxigan",
    "wof:placetype":"locality"
},
  "geometry": {"coordinates":[120.60321999999999,31.08143],"type":"Point"}
}