{
  "type": "Feature",
  "properties": {
    "gn:admin1_code":"13.0",
    "gn:asciiname":"Xiao'erbagexiang Ernongchang",
    "gn:country_code":"CN",
    "gn:dem":1312,
    "gn:feature_class":"P",
    "gn:feature_code":"PPLF",
    "gn:name":"Xiao\u2019erbagexiang Ernongchang",
    "gn:population":0,
    "gn:timezone":"Asia/Shanghai",
    "iso:country":"CN",
    "name:und_x_variant":[
        "Xiao\u2019er Bagexiang Ernongchang"
    ],
    "name:zho_x_preferred":[
        "\u8096\u5c14\u5df4\u683c\u4e61\u4e8c\u519c\u573a"
    ],
    "wof:name":"Xiao'erbagexiang Ernongchang",
    "wof:placetype":"locality"
},
  "geometry": {"coordinates":[79.91186,37.22099],"type":"Point"}
}