{
  "type": "Feature",
  "properties": {
    "gn:admin1_code":"11.0",
    "gn:asciiname":"Yijiashan",
    "gn:country_code":"CN",
    "gn:dem":444,
    "gn:feature_class":"P",
    "gn:feature_code":"PPL",
    "gn:name":"Yijiashan",
    "gn:population":0,
    "gn:timezone":"Asia/Shanghai",
    "iso:country":"CN",
    "name:zho_x_preferred":[
        "\u6613\u5bb6\u5c71"
    ],
    "wof:name":"Yijiashan",
    "wof:placetype":"locality"
},
  "geometry": {"coordinates":[110.98649,29.81656],"type":"Point"}
}