{
  "type": "Feature",
  "properties": {
    "gn:admin1_code":"5.0",
    "gn:asciiname":"Tongjianggou",
    "gn:country_code":"CN",
    "gn:dem":239,
    "gn:feature_class":"P",
    "gn:feature_code":"PPL",
    "gn:name":"Tongjianggou",
    "gn:population":0,
    "gn:timezone":"Asia/Shanghai",
    "iso:country":"CN",
    "name:zho_x_preferred":[
        "\u94dc\u5320\u6c9f"
    ],
    "wof:name":"Tongjianggou",
    "wof:placetype":"locality"
},
  "geometry": {"coordinates":[126.4064,43.80604],"type":"Point"}
}