{
  "type": "Feature",
  "properties": {
    "gn:admin1_code":"29.0",
    "gn:asciiname":"Xiaotangpo",
    "gn:country_code":"CN",
    "gn:dem":1674,
    "gn:feature_class":"P",
    "gn:feature_code":"PPL",
    "gn:name":"Xiaotangpo",
    "gn:population":0,
    "gn:timezone":"Asia/Shanghai",
    "iso:country":"CN",
    "name:zho_x_preferred":[
        "\u785d\u5858\u5761"
    ],
    "wof:name":"Xiaotangpo",
    "wof:placetype":"locality"
},
  "geometry": {"coordinates":[100.075,23.4729],"type":"Point"}
}