{
  "type": "Feature",
  "properties": {
    "gn:admin1_code":"24",
    "gn:asciiname":"Xiaoguancun",
    "gn:country_code":"CN",
    "gn:dem":1150,
    "gn:feature_class":"P",
    "gn:feature_code":"PPL",
    "gn:name":"Xiaoguancun",
    "gn:population":0,
    "gn:timezone":"Asia/Shanghai",
    "iso:country":"CN",
    "wof:name":"Xiaoguancun",
    "wof:placetype":"locality"
},
  "geometry": {"coordinates":[113.01555999999999,39.01222],"type":"Point"}
}