{
  "type": "Feature",
  "properties": {
    "gn:admin1_code":"8.0",
    "gn:asciiname":"Xinglitun",
    "gn:country_code":"CN",
    "gn:dem":302,
    "gn:feature_class":"P",
    "gn:feature_code":"PPL",
    "gn:name":"Xinglitun",
    "gn:population":0,
    "gn:timezone":"Asia/Shanghai",
    "iso:country":"CN",
    "name:zho_x_preferred":[
        "\u5174\u5229\u5c6f"
    ],
    "wof:name":"Xinglitun",
    "wof:placetype":"locality"
},
  "geometry": {"coordinates":[127.83484,45.39277],"type":"Point"}
}