{
  "type": "Feature",
  "properties": {
    "gn:admin1_code":"15.0",
    "gn:asciiname":"Baijiagou",
    "gn:country_code":"CN",
    "gn:dem":1365,
    "gn:feature_class":"P",
    "gn:feature_code":"PPL",
    "gn:name":"Baijiagou",
    "gn:population":0,
    "gn:timezone":"Asia/Shanghai",
    "iso:country":"CN",
    "name:und_x_variant":[
        "\u767e\u5bb6\u6c9f"
    ],
    "wof:name":"Baijiagou",
    "wof:placetype":"locality"
},
  "geometry": {"coordinates":[105.81954,33.1967],"type":"Point"}
}