{
  "type": "Feature",
  "properties": {
    "gn:admin1_code":"3.0",
    "gn:asciiname":"Quantang Lijia",
    "gn:country_code":"CN",
    "gn:dem":32,
    "gn:feature_class":"P",
    "gn:feature_code":"PPL",
    "gn:name":"Quantang Lijia",
    "gn:population":0,
    "gn:timezone":"Asia/Shanghai",
    "iso:country":"CN",
    "name:und_x_variant":[
        "\u6cc9\u5858\u674e\u5bb6"
    ],
    "wof:name":"Quantang Lijia",
    "wof:placetype":"locality"
},
  "geometry": {"coordinates":[115.62658,28.35695],"type":"Point"}
}