{
  "type": "Feature",
  "properties": {
    "gn:admin1_code":"9.0",
    "gn:asciiname":"Zaizhuang",
    "gn:country_code":"CN",
    "gn:dem":113,
    "gn:feature_class":"P",
    "gn:feature_code":"PPL",
    "gn:name":"Zaizhuang",
    "gn:population":0,
    "gn:timezone":"Asia/Shanghai",
    "iso:country":"CN",
    "name:zho_x_preferred":[
        "\u8f7d\u5e84"
    ],
    "wof:name":"Zaizhuang",
    "wof:placetype":"locality"
},
  "geometry": {"coordinates":[114.81941999999999,31.72241],"type":"Point"}
}