{
  "type": "Feature",
  "properties": {
    "gn:admin1_code":"25.0",
    "gn:asciiname":"Hanglicun",
    "gn:country_code":"CN",
    "gn:dem":35,
    "gn:feature_class":"P",
    "gn:feature_code":"PPL",
    "gn:name":"Hanglicun",
    "gn:population":0,
    "gn:timezone":"Asia/Shanghai",
    "iso:country":"CN",
    "name:zho_x_preferred":[
        "\u676d\u91cc\u6751"
    ],
    "wof:name":"Hanglicun",
    "wof:placetype":"locality"
},
  "geometry": {"coordinates":[122.22159000000001,37.18325],"type":"Point"}
}