{
  "type": "Feature",
  "properties": {
    "gn:admin1_code":"24",
    "gn:asciiname":"Daying",
    "gn:country_code":"CN",
    "gn:dem":1001,
    "gn:feature_class":"P",
    "gn:feature_code":"PPL",
    "gn:name":"Daying",
    "gn:population":0,
    "gn:timezone":"Asia/Shanghai",
    "iso:country":"CN",
    "name:und_x_variant":[
        "Ta-ying-ts\u2019un",
        "Ta-ying",
        "Daying",
        "\u5927\u8425"
    ],
    "wof:name":"Daying",
    "wof:placetype":"locality"
},
  "geometry": {"coordinates":[113.02354,39.59778],"type":"Point"}
}