{
  "type": "Feature",
  "properties": {
    "gn:admin1_code":"8.0",
    "gn:asciiname":"Zhendongcun",
    "gn:country_code":"CN",
    "gn:dem":211,
    "gn:feature_class":"P",
    "gn:feature_code":"PPL",
    "gn:name":"Zhendongcun",
    "gn:population":0,
    "gn:timezone":"Asia/Shanghai",
    "iso:country":"CN",
    "name:zho_x_preferred":[
        "\u632f\u4e1c\u6751"
    ],
    "wof:name":"Zhendongcun",
    "wof:placetype":"locality"
},
  "geometry": {"coordinates":[127.21871000000002,47.18616],"type":"Point"}
}