{
  "type": "Feature",
  "properties": {
    "gn:admin1_code":"12.0",
    "gn:asciiname":"Huajiagou",
    "gn:country_code":"CN",
    "gn:dem":262,
    "gn:feature_class":"P",
    "gn:feature_code":"PPL",
    "gn:name":"Huajiagou",
    "gn:population":0,
    "gn:timezone":"Asia/Shanghai",
    "iso:country":"CN",
    "name:zho_x_preferred":[
        "\u534e\u5bb6\u6c9f"
    ],
    "wof:name":"Huajiagou",
    "wof:placetype":"locality"
},
  "geometry": {"coordinates":[113.77306000000002,31.91134000000001],"type":"Point"}
}