{
  "type": "Feature",
  "properties": {
    "gn:admin1_code":"19.0",
    "gn:asciiname":"Xihaiyan",
    "gn:country_code":"CN",
    "gn:dem":2,
    "gn:feature_class":"P",
    "gn:feature_code":"PPL",
    "gn:name":"Xihaiyan",
    "gn:population":0,
    "gn:timezone":"Asia/Shanghai",
    "iso:country":"CN",
    "name:zho_x_preferred":[
        "\u897f\u6d77\u71d5"
    ],
    "wof:name":"Xihaiyan",
    "wof:placetype":"locality"
},
  "geometry": {"coordinates":[121.937,40.9907],"type":"Point"}
}