{
  "type": "Feature",
  "properties": {
    "gn:admin1_code":"4.0",
    "gn:asciiname":"Beiguoxin",
    "gn:country_code":"CN",
    "gn:dem":7,
    "gn:feature_class":"P",
    "gn:feature_code":"PPL",
    "gn:name":"Beiguoxin",
    "gn:population":0,
    "gn:timezone":"Asia/Shanghai",
    "iso:country":"CN",
    "name:zho_x_preferred":[
        "\u5317\u90ed\u65b0"
    ],
    "wof:name":"Beiguoxin",
    "wof:placetype":"locality"
},
  "geometry": {"coordinates":[120.87118999999998,32.02670999999999],"type":"Point"}
}