{
  "type": "Feature",
  "properties": {
    "gn:admin1_code":"16.0",
    "gn:asciiname":"Lupo",
    "gn:country_code":"CN",
    "gn:dem":93,
    "gn:feature_class":"P",
    "gn:feature_code":"PPL",
    "gn:name":"Lupo",
    "gn:population":0,
    "gn:timezone":"Asia/Shanghai",
    "iso:country":"CN",
    "name:ceb_x_preferred":[
        "Lupo"
    ],
    "name:deu_x_preferred":[
        "Lupo"
    ],
    "name:fra_x_preferred":[
        "Lupo"
    ],
    "name:heb_x_preferred":[
        "\u05dc\u05d5\u05e4\u05d5"
    ],
    "name:ina_x_preferred":[
        "Lupo"
    ],
    "name:ita_x_preferred":[
        "Lupo"
    ],
    "name:por_x_preferred":[
        "Lupo"
    ],
    "name:spa_x_preferred":[
        "Lupo"
    ],
    "name:swe_x_preferred":[
        "Lupo"
    ],
    "name:zho_x_preferred":[
        "\u9e7f\u5761"
    ],
    "wof:name":"Lupo",
    "wof:placetype":"locality"
},
  "geometry": {"coordinates":[110.938,23.7174],"type":"Point"}
}