{
  "type": "Feature",
  "properties": {
    "gn:admin1_code":"29.0",
    "gn:asciiname":"Youjiapo",
    "gn:country_code":"CN",
    "gn:dem":1282,
    "gn:feature_class":"P",
    "gn:feature_code":"PPL",
    "gn:name":"Youjiapo",
    "gn:population":0,
    "gn:timezone":"Asia/Shanghai",
    "iso:country":"CN",
    "name:zho_x_preferred":[
        "\u6e38\u5bb6\u5761"
    ],
    "wof:name":"Youjiapo",
    "wof:placetype":"locality"
},
  "geometry": {"coordinates":[105.084,27.9814],"type":"Point"}
}