{
  "type": "Feature",
  "properties": {
    "gn:admin1_code":"26",
    "gn:asciiname":"Zhangjiayao",
    "gn:country_code":"CN",
    "gn:dem":518,
    "gn:feature_class":"P",
    "gn:feature_code":"PPL",
    "gn:name":"Zhangjiayao",
    "gn:population":0,
    "gn:timezone":"Asia/Shanghai",
    "iso:country":"CN",
    "name:zho_x_preferred":[
        "\u5f20\u5bb6\u7a91"
    ],
    "wof:name":"Zhangjiayao",
    "wof:placetype":"locality"
},
  "geometry": {"coordinates":[108.03651000000001,34.39888],"type":"Point"}
}