{
  "type": "Feature",
  "properties": {
    "gn:admin1_code":"15.0",
    "gn:asciiname":"Niuqiaozi",
    "gn:country_code":"CN",
    "gn:dem":1202,
    "gn:feature_class":"P",
    "gn:feature_code":"PPL",
    "gn:name":"Niuqiaozi",
    "gn:population":0,
    "gn:timezone":"Asia/Urumqi",
    "iso:country":"CN",
    "name:zho_x_preferred":[
        "\u725b\u6865\u5b50"
    ],
    "wof:name":"Niuqiaozi",
    "wof:placetype":"locality"
},
  "geometry": {"coordinates":[95.58969999999999,40.3162],"type":"Point"}
}