{
  "type": "Feature",
  "properties": {
    "gn:admin1_code":"16.0",
    "gn:asciiname":"Licai",
    "gn:country_code":"CN",
    "gn:dem":702,
    "gn:feature_class":"P",
    "gn:feature_code":"PPL",
    "gn:name":"Licai",
    "gn:population":0,
    "gn:timezone":"Asia/Shanghai",
    "iso:country":"CN",
    "name:zho_x_preferred":[
        "\u8389\u624d"
    ],
    "wof:name":"Licai",
    "wof:placetype":"locality"
},
  "geometry": {"coordinates":[107.75700000000001,25.154],"type":"Point"}
}