{
  "type": "Feature",
  "properties": {
    "gn:admin1_code":"3",
    "gn:asciiname":"Shashukeng",
    "gn:country_code":"CN",
    "gn:dem":169,
    "gn:feature_class":"P",
    "gn:feature_code":"PPL",
    "gn:name":"Shashukeng",
    "gn:population":0,
    "gn:timezone":"Asia/Shanghai",
    "iso:country":"CN",
    "name:zho_x_preferred":[
        "\u6749\u6811\u5751"
    ],
    "wof:name":"Shashukeng",
    "wof:placetype":"locality"
},
  "geometry": {"coordinates":[114.965,25.3626],"type":"Point"}
}