{
  "type": "Feature",
  "properties": {
    "gn:admin1_code":"15.0",
    "gn:asciiname":"Laoyeling",
    "gn:country_code":"CN",
    "gn:dem":1551,
    "gn:feature_class":"P",
    "gn:feature_code":"PPL",
    "gn:name":"Laoyeling",
    "gn:population":0,
    "gn:timezone":"Asia/Shanghai",
    "iso:country":"CN",
    "name:zho_x_preferred":[
        "\u8001\u7237\u5cad"
    ],
    "wof:name":"Laoyeling",
    "wof:placetype":"locality"
},
  "geometry": {"coordinates":[108.12,36.4112],"type":"Point"}
}