{
  "type": "Feature",
  "properties": {
    "gn:admin1_code":"26",
    "gn:asciiname":"Hutishan Linchang",
    "gn:country_code":"CN",
    "gn:dem":928,
    "gn:feature_class":"P",
    "gn:feature_code":"PPLF",
    "gn:name":"Hutishan Linchang",
    "gn:population":0,
    "gn:timezone":"Asia/Shanghai",
    "iso:country":"CN",
    "wof:name":"Hutishan Linchang",
    "wof:placetype":"locality"
},
  "geometry": {"coordinates":[109.79277999999999,35.39472],"type":"Point"}
}