{
  "type": "Feature",
  "properties": {
    "gn:admin1_code":"15.0",
    "gn:asciiname":"Wujiashan",
    "gn:country_code":"CN",
    "gn:dem":1271,
    "gn:feature_class":"P",
    "gn:feature_code":"PPL",
    "gn:name":"Wujiashan",
    "gn:population":0,
    "gn:timezone":"Asia/Shanghai",
    "iso:country":"CN",
    "name:und_x_variant":[
        "\u6b66\u5bb6\u5c71"
    ],
    "wof:name":"Wujiashan",
    "wof:placetype":"locality"
},
  "geometry": {"coordinates":[105.88094,33.23025],"type":"Point"}
}