{
  "type": "Feature",
  "properties": {
    "gn:admin1_code":"19.0",
    "gn:asciiname":"Dawulancun",
    "gn:country_code":"CN",
    "gn:dem":203,
    "gn:feature_class":"P",
    "gn:feature_code":"PPL",
    "gn:name":"Dawulancun",
    "gn:population":0,
    "gn:timezone":"Asia/Shanghai",
    "iso:country":"CN",
    "name:zho_x_preferred":[
        "\u5927\u4e4c\u5170\u6751"
    ],
    "wof:name":"Dawulancun",
    "wof:placetype":"locality"
},
  "geometry": {"coordinates":[121.11801,41.92851],"type":"Point"}
}