{
  "type": "Feature",
  "properties": {
    "gn:admin1_code":"25",
    "gn:asciiname":"Zhaogaoyu",
    "gn:country_code":"CN",
    "gn:dem":317,
    "gn:feature_class":"P",
    "gn:feature_code":"PPL",
    "gn:name":"Zhaogaoyu",
    "gn:population":0,
    "gn:timezone":"Asia/Shanghai",
    "iso:country":"CN",
    "name:zho_x_preferred":[
        "\u8d75\u9ad8\u5cea"
    ],
    "wof:name":"Zhaogaoyu",
    "wof:placetype":"locality"
},
  "geometry": {"coordinates":[118.304,35.9405],"type":"Point"}
}