{
  "type": "Feature",
  "properties": {
    "gn:admin1_code":"12.0",
    "gn:asciiname":"Fangqiao",
    "gn:country_code":"CN",
    "gn:dem":203,
    "gn:feature_class":"P",
    "gn:feature_code":"PPL",
    "gn:name":"Fangqiao",
    "gn:population":0,
    "gn:timezone":"Asia/Shanghai",
    "iso:country":"CN",
    "name:zho_x_preferred":[
        "\u65b9\u6865"
    ],
    "wof:name":"Fangqiao",
    "wof:placetype":"locality"
},
  "geometry": {"coordinates":[115.78979,30.59124000000001],"type":"Point"}
}