{
  "type": "Feature",
  "properties": {
    "gn:country":"CN",
    "gn:fcode":"PPL",
    "gn:pop":1590,
    "iso:country":"CN",
    "name:unk_x_variant":[
        "Yen-men"
    ],
    "qs:name":"Yanmen",
    "qs:photos_9r":0,
    "qs:photos_sr":0,
    "qs:pop_sr":"3",
    "wd:wordcount":34,
    "wof:name":"Yanmen",
    "wof:placetype":"locality",
    "wof:population":1590
},
  "geometry": {"coordinates":[109.74028,27.855],"type":"Point"}
}