{
  "type": "Feature",
  "properties": {
    "gn:admin1_code":"26.0",
    "gn:asciiname":"Wangliang",
    "gn:country_code":"CN",
    "gn:dem":1410,
    "gn:feature_class":"P",
    "gn:feature_code":"PPL",
    "gn:name":"Wangliang",
    "gn:population":0,
    "gn:timezone":"Asia/Shanghai",
    "iso:country":"CN",
    "name:pol_x_preferred":[
        "Wangliang"
    ],
    "wof:name":"Wangliang",
    "wof:placetype":"locality"
},
  "geometry": {"coordinates":[108.83333,37.38333],"type":"Point"}
}