{
  "type": "Feature",
  "properties": {
    "gn:admin1_code":"29.0",
    "gn:asciiname":"Niudui",
    "gn:country_code":"CN",
    "gn:dem":1608,
    "gn:feature_class":"P",
    "gn:feature_code":"PPL",
    "gn:name":"Niudui",
    "gn:population":0,
    "gn:timezone":"Asia/Shanghai",
    "iso:country":"CN",
    "name:zho_x_preferred":[
        "\u725b\u5806"
    ],
    "wof:name":"Niudui",
    "wof:placetype":"locality"
},
  "geometry": {"coordinates":[101.776,23.3407],"type":"Point"}
}