{
  "type": "Feature",
  "properties": {
    "gn:admin1_code":"30.0",
    "gn:asciiname":"Huangwudong",
    "gn:country_code":"CN",
    "gn:dem":208,
    "gn:feature_class":"P",
    "gn:feature_code":"PPL",
    "gn:name":"Huangwudong",
    "gn:population":0,
    "gn:timezone":"Asia/Shanghai",
    "iso:country":"CN",
    "name:zho_x_preferred":[
        "Huangwudong"
    ],
    "name:zho_x_variant":[
        "\u9ec4\u5c4b\u6d1e"
    ],
    "wof:name":"Huangwudong",
    "wof:placetype":"locality"
},
  "geometry": {"coordinates":[112.24639000000001,25.00944],"type":"Point"}
}