{
  "type": "Feature",
  "properties": {
    "gn:admin1_code":"26.0",
    "gn:asciiname":"Zhengjialing",
    "gn:country_code":"CN",
    "gn:dem":1021,
    "gn:feature_class":"P",
    "gn:feature_code":"PPL",
    "gn:name":"Zhengjialing",
    "gn:population":0,
    "gn:timezone":"Asia/Shanghai",
    "iso:country":"CN",
    "name:zho_x_preferred":[
        "\u90d1\u5bb6\u5cad"
    ],
    "wof:name":"Zhengjialing",
    "wof:placetype":"locality"
},
  "geometry": {"coordinates":[110.15652,36.49414],"type":"Point"}
}