{
  "type": "Feature",
  "properties": {
    "gn:admin1_code":"21.0",
    "gn:asciiname":"Xiazuitou",
    "gn:country_code":"CN",
    "gn:dem":2152,
    "gn:feature_class":"P",
    "gn:feature_code":"PPL",
    "gn:name":"Xiazuitou",
    "gn:population":0,
    "gn:timezone":"Asia/Shanghai",
    "iso:country":"CN",
    "name:zho_x_preferred":[
        "\u4e0b\u5480\u5934"
    ],
    "wof:name":"Xiazuitou",
    "wof:placetype":"locality"
},
  "geometry": {"coordinates":[105.584,36.1327],"type":"Point"}
}