{
  "type": "Feature",
  "properties": {
    "gn:admin1_code":"18",
    "gn:asciiname":"Xiaopanjiang",
    "gn:country_code":"CN",
    "gn:dem":592,
    "gn:feature_class":"P",
    "gn:feature_code":"PPL",
    "gn:name":"Xiaopanjiang",
    "gn:population":0,
    "gn:timezone":"Asia/Shanghai",
    "iso:country":"CN",
    "name:zho_x_preferred":[
        "\u5c0f\u76d8\u6c5f"
    ],
    "wof:name":"Xiaopanjiang",
    "wof:placetype":"locality"
},
  "geometry": {"coordinates":[105.288,25.9279],"type":"Point"}
}