{
  "type": "Feature",
  "properties": {
    "gn:admin1_code":"8.0",
    "gn:asciiname":"Baodong",
    "gn:country_code":"CN",
    "gn:dem":226,
    "gn:feature_class":"P",
    "gn:feature_code":"PPL",
    "gn:name":"Baodong",
    "gn:population":0,
    "gn:timezone":"Asia/Shanghai",
    "iso:country":"CN",
    "name:zho_x_preferred":[
        "\u4fdd\u4e1c"
    ],
    "wof:name":"Baodong",
    "wof:placetype":"locality"
},
  "geometry": {"coordinates":[125.43286000000001,47.58069],"type":"Point"}
}