{
  "type": "Feature",
  "properties": {
    "gn:admin1_code":"10",
    "gn:asciiname":"Lanxiagou",
    "gn:country_code":"CN",
    "gn:dem":1407,
    "gn:feature_class":"P",
    "gn:feature_code":"PPL",
    "gn:name":"Lanxiagou",
    "gn:population":0,
    "gn:timezone":"Asia/Shanghai",
    "iso:country":"CN",
    "name:zho_x_preferred":[
        "\u5170\u5ce1\u6c9f"
    ],
    "wof:name":"Lanxiagou",
    "wof:placetype":"locality"
},
  "geometry": {"coordinates":[115.01647,41.50475],"type":"Point"}
}