{
  "type": "Feature",
  "properties": {
    "gn:admin1_code":"16.0",
    "gn:asciiname":"Ren'ai",
    "gn:country_code":"CN",
    "gn:dem":249,
    "gn:feature_class":"P",
    "gn:feature_code":"PPL",
    "gn:name":"Ren\u2019ai",
    "gn:population":0,
    "gn:timezone":"Asia/Shanghai",
    "iso:country":"CN",
    "name:deu_x_preferred":[
        "Ren\u2019ai"
    ],
    "name:zho_x_preferred":[
        "\u4ec1\u7231"
    ],
    "wof:name":"Ren'ai",
    "wof:placetype":"locality"
},
  "geometry": {"coordinates":[106.771,22.9015],"type":"Point"}
}