{
  "type": "Feature",
  "properties": {
    "gn:admin1_code":"12.0",
    "gn:asciiname":"Caijiaping",
    "gn:country_code":"CN",
    "gn:dem":678,
    "gn:feature_class":"P",
    "gn:feature_code":"PPL",
    "gn:name":"Caijiaping",
    "gn:population":0,
    "gn:timezone":"Asia/Shanghai",
    "iso:country":"CN",
    "name:zho_x_preferred":[
        "Caijiaping"
    ],
    "name:zho_x_variant":[
        "\u8521\u5bb6\u576a"
    ],
    "wof:name":"Caijiaping",
    "wof:placetype":"locality"
},
  "geometry": {"coordinates":[111.07837000000001,30.31709],"type":"Point"}
}