{
  "type": "Feature",
  "properties": {
    "gn:admin1_code":"7.0",
    "gn:asciiname":"Jiangfang",
    "gn:country_code":"CN",
    "gn:dem":366,
    "gn:feature_class":"P",
    "gn:feature_code":"PPL",
    "gn:name":"Jiangfang",
    "gn:population":0,
    "gn:timezone":"Asia/Shanghai",
    "iso:country":"CN",
    "name:und_x_variant":[
        "\u6c5f\u574a"
    ],
    "name:zho_x_preferred":[
        "\u6c5f\u574a"
    ],
    "name:zho_x_variant":[
        "\u848b\u574a\u4e61"
    ],
    "wof:name":"Jiangfang",
    "wof:placetype":"locality"
},
  "geometry": {"coordinates":[116.46375,25.91203],"type":"Point"}
}