{
  "type": "Feature",
  "properties": {
    "gn:admin1_code":"18.0",
    "gn:asciiname":"Pingjing",
    "gn:country_code":"CN",
    "gn:dem":990,
    "gn:feature_class":"P",
    "gn:feature_code":"PPL",
    "gn:name":"Pingjing",
    "gn:population":0,
    "gn:timezone":"Asia/Shanghai",
    "iso:country":"CN",
    "name:zho_x_preferred":[
        "\u5e73\u9756"
    ],
    "wof:name":"Pingjing",
    "wof:placetype":"locality"
},
  "geometry": {"coordinates":[107.58,25.6804],"type":"Point"}
}