{
  "type": "Feature",
  "properties": {
    "gn:admin1_code":"11",
    "gn:asciiname":"Shangyijia",
    "gn:country_code":"CN",
    "gn:dem":305,
    "gn:feature_class":"P",
    "gn:feature_code":"PPL",
    "gn:name":"Shangyijia",
    "gn:population":0,
    "gn:timezone":"Asia/Shanghai",
    "iso:country":"CN",
    "name:zho_x_preferred":[
        "\u4e0a\u6613\u5bb6"
    ],
    "wof:name":"Shangyijia",
    "wof:placetype":"locality"
},
  "geometry": {"coordinates":[111.14778,27.17444],"type":"Point"}
}