{
  "type": "Feature",
  "properties": {
    "gn:admin1_code":"18",
    "gn:asciiname":"Beihouzhai",
    "gn:country_code":"CN",
    "gn:dem":944,
    "gn:feature_class":"P",
    "gn:feature_code":"PPL",
    "gn:name":"Beihouzhai",
    "gn:population":0,
    "gn:timezone":"Asia/Shanghai",
    "iso:country":"CN",
    "name:zho_x_preferred":[
        "\u80cc\u540e\u5be8"
    ],
    "wof:name":"Beihouzhai",
    "wof:placetype":"locality"
},
  "geometry": {"coordinates":[108.032,27.2703],"type":"Point"}
}