{
  "type": "Feature",
  "properties": {
    "gn:admin1_code":"5.0",
    "gn:asciiname":"Zhuguoyingtun",
    "gn:country_code":"CN",
    "gn:dem":196,
    "gn:feature_class":"P",
    "gn:feature_code":"PPL",
    "gn:name":"Zhuguoyingtun",
    "gn:population":0,
    "gn:timezone":"Asia/Shanghai",
    "iso:country":"CN",
    "name:zho_x_preferred":[
        "\u6731\u56fd\u82f1\u5c6f"
    ],
    "wof:name":"Zhuguoyingtun",
    "wof:placetype":"locality"
},
  "geometry": {"coordinates":[124.93000000000001,44.55993],"type":"Point"}
}