{
  "type": "Feature",
  "properties": {
    "gn:admin1_code":"32.0",
    "gn:asciiname":"Mengsha Gongba",
    "gn:country_code":"CN",
    "gn:dem":4198,
    "gn:feature_class":"P",
    "gn:feature_code":"PPL",
    "gn:name":"Mengsha Gongba",
    "gn:population":0,
    "gn:timezone":"Asia/Shanghai",
    "iso:country":"CN",
    "name:und_x_variant":[
        "Mengshacun",
        "Mengsha Gongba"
    ],
    "name:zho_x_preferred":[
        "\u8499\u6c99\u8d21\u5df4"
    ],
    "wof:name":"Mengsha Gongba",
    "wof:placetype":"locality"
},
  "geometry": {"coordinates":[98.25946,33.02451],"type":"Point"}
}