{
  "type": "Feature",
  "properties": {
    "gn:admin1_code":"2.0",
    "gn:asciiname":"Shitoukeng",
    "gn:country_code":"CN",
    "gn:dem":892,
    "gn:feature_class":"P",
    "gn:feature_code":"PPL",
    "gn:name":"Shitoukeng",
    "gn:population":0,
    "gn:timezone":"Asia/Shanghai",
    "iso:country":"CN",
    "name:zho_x_preferred":[
        "\u77f3\u5934\u5751"
    ],
    "wof:name":"Shitoukeng",
    "wof:placetype":"locality"
},
  "geometry": {"coordinates":[119.24041,27.65752],"type":"Point"}
}