{
  "type": "Feature",
  "properties": {
    "gn:admin1_code":"18",
    "gn:asciiname":"Jiangdongchang",
    "gn:country_code":"CN",
    "gn:dem":1354,
    "gn:feature_class":"P",
    "gn:feature_code":"PPL",
    "gn:name":"Jiangdongchang",
    "gn:population":0,
    "gn:timezone":"Asia/Shanghai",
    "iso:country":"CN",
    "name:zho_x_preferred":[
        "\u6c5f\u4e1c\u573a"
    ],
    "wof:name":"Jiangdongchang",
    "wof:placetype":"locality"
},
  "geometry": {"coordinates":[106.59399999999999,27.8086],"type":"Point"}
}