{
  "type": "Feature",
  "properties": {
    "gn:admin1_code":"19.0",
    "gn:asciiname":"Sanlitun",
    "gn:country_code":"CN",
    "gn:dem":7,
    "gn:feature_class":"P",
    "gn:feature_code":"PPL",
    "gn:name":"Sanlitun",
    "gn:population":0,
    "gn:timezone":"Asia/Shanghai",
    "iso:country":"CN",
    "name:und_x_variant":[
        "\u4e09\u91cc\u5c6f"
    ],
    "wof:name":"Sanlitun",
    "wof:placetype":"locality"
},
  "geometry": {"coordinates":[122.51600000000001,40.9339],"type":"Point"}
}