{
  "type": "Feature",
  "properties": {
    "gn:admin1_code":"15.0",
    "gn:asciiname":"Huxiongli",
    "gn:country_code":"CN",
    "gn:dem":1797,
    "gn:feature_class":"P",
    "gn:feature_code":"PPL",
    "gn:name":"Huxiongli",
    "gn:population":0,
    "gn:timezone":"Asia/Shanghai",
    "iso:country":"CN",
    "name:und_x_variant":[
        "\u80e1\u96c4\u91cc"
    ],
    "wof:name":"Huxiongli",
    "wof:placetype":"locality"
},
  "geometry": {"coordinates":[105.12117000000001,32.98483],"type":"Point"}
}