{
  "type": "Feature",
  "properties": {
    "gn:admin1_code":"32.0",
    "gn:asciiname":"Loufanghe",
    "gn:country_code":"CN",
    "gn:dem":901,
    "gn:feature_class":"P",
    "gn:feature_code":"PPL",
    "gn:name":"Loufanghe",
    "gn:population":0,
    "gn:timezone":"Asia/Shanghai",
    "iso:country":"CN",
    "name:und_x_variant":[
        "\u697c\u574a\u6cb3"
    ],
    "wof:name":"Loufanghe",
    "wof:placetype":"locality"
},
  "geometry": {"coordinates":[106.54075,32.39502],"type":"Point"}
}