{
  "type": "Feature",
  "properties": {
    "gn:admin1_code":"18.0",
    "gn:asciiname":"Jieluyuan",
    "gn:country_code":"CN",
    "gn:dem":728,
    "gn:feature_class":"P",
    "gn:feature_code":"PPL",
    "gn:name":"Jieluyuan",
    "gn:population":0,
    "gn:timezone":"Asia/Shanghai",
    "iso:country":"CN",
    "name:zho_x_preferred":[
        "\u89e3\u65c5\u9662"
    ],
    "wof:name":"Jieluyuan",
    "wof:placetype":"locality"
},
  "geometry": {"coordinates":[108.173,27.0723],"type":"Point"}
}