{
  "type": "Feature",
  "properties": {
    "gn:admin1_code":"1.0",
    "gn:asciiname":"Songchencun",
    "gn:country_code":"CN",
    "gn:dem":105,
    "gn:feature_class":"P",
    "gn:feature_code":"PPL",
    "gn:name":"Songchencun",
    "gn:population":0,
    "gn:timezone":"Asia/Shanghai",
    "iso:country":"CN",
    "name:zho_x_preferred":[
        "\u5b8b\u9648\u6751"
    ],
    "wof:name":"Songchencun",
    "wof:placetype":"locality"
},
  "geometry": {"coordinates":[119.45050000000001,30.76111],"type":"Point"}
}