{
  "type": "Feature",
  "properties": {
    "gn:admin1_code":"1.0",
    "gn:asciiname":"Zhuxiaozhuangcun",
    "gn:country_code":"CN",
    "gn:dem":31,
    "gn:feature_class":"P",
    "gn:feature_code":"PPL",
    "gn:name":"Zhuxiaozhuangcun",
    "gn:population":0,
    "gn:timezone":"Asia/Shanghai",
    "iso:country":"CN",
    "name:zho_x_preferred":[
        "\u795d\u5c0f\u5e84\u6751"
    ],
    "wof:name":"Zhuxiaozhuangcun",
    "wof:placetype":"locality"
},
  "geometry": {"coordinates":[116.57643,33.52309],"type":"Point"}
}