{
  "type": "Feature",
  "properties": {
    "gn:admin1_code":"21",
    "gn:asciiname":"Kouzigou",
    "gn:country_code":"CN",
    "gn:dem":1301,
    "gn:feature_class":"P",
    "gn:feature_code":"PPL",
    "gn:name":"Kouzigou",
    "gn:population":0,
    "gn:timezone":"Asia/Shanghai",
    "iso:country":"CN",
    "wof:name":"Kouzigou",
    "wof:placetype":"locality"
},
  "geometry": {"coordinates":[106.51667,37.96667],"type":"Point"}
}