{
  "type": "Feature",
  "properties": {
    "gn:admin1_code":"9.0",
    "gn:asciiname":"Panpo",
    "gn:country_code":"CN",
    "gn:dem":327,
    "gn:feature_class":"P",
    "gn:feature_code":"PPL",
    "gn:name":"Panpo",
    "gn:population":0,
    "gn:timezone":"Asia/Shanghai",
    "iso:country":"CN",
    "name:und_x_variant":[
        "\u76d8\u5761",
        "Panpo"
    ],
    "wof:name":"Panpo",
    "wof:placetype":"locality"
},
  "geometry": {"coordinates":[112.19504999999999,33.13591],"type":"Point"}
}