{
  "type": "Feature",
  "properties": {
    "gn:admin1_code":"29.0",
    "gn:asciiname":"Heliwan",
    "gn:country_code":"CN",
    "gn:dem":1127,
    "gn:feature_class":"P",
    "gn:feature_code":"PPL",
    "gn:name":"Heliwan",
    "gn:population":0,
    "gn:timezone":"Asia/Shanghai",
    "iso:country":"CN",
    "name:zho_x_preferred":[
        "\u6cb3\u91cc\u6e7e"
    ],
    "wof:name":"Heliwan",
    "wof:placetype":"locality"
},
  "geometry": {"coordinates":[103.111,26.1979],"type":"Point"}
}