{
  "type": "Feature",
  "properties": {
    "gn:admin1_code":"12.0",
    "gn:asciiname":"Dalucao",
    "gn:country_code":"CN",
    "gn:dem":1372,
    "gn:feature_class":"P",
    "gn:feature_code":"PPL",
    "gn:name":"Dalucao",
    "gn:population":0,
    "gn:timezone":"Asia/Shanghai",
    "iso:country":"CN",
    "name:zho_x_preferred":[
        "\u5927\u8def\u69fd"
    ],
    "wof:name":"Dalucao",
    "wof:placetype":"locality"
},
  "geometry": {"coordinates":[109.86286,31.64293],"type":"Point"}
}