{
  "type": "Feature",
  "properties": {
    "gn:admin1_code":"9.0",
    "gn:asciiname":"Duijiagoukou",
    "gn:country_code":"CN",
    "gn:dem":552,
    "gn:feature_class":"P",
    "gn:feature_code":"PPL",
    "gn:name":"Duijiagoukou",
    "gn:population":0,
    "gn:timezone":"Asia/Shanghai",
    "iso:country":"CN",
    "name:zho_x_preferred":[
        "\u5bf9\u5bb6\u6c9f\u53e3"
    ],
    "wof:name":"Duijiagoukou",
    "wof:placetype":"locality"
},
  "geometry": {"coordinates":[113.9089,36.30184000000001],"type":"Point"}
}