{
  "type": "Feature",
  "properties": {
    "gn:admin1_code":"28",
    "gn:asciiname":"Donglianzhuang",
    "gn:country_code":"CN",
    "gn:dem":6,
    "gn:feature_class":"P",
    "gn:feature_code":"PPL",
    "gn:name":"Donglianzhuang",
    "gn:population":0,
    "gn:timezone":"Asia/Shanghai",
    "iso:country":"CN",
    "name:zho_x_preferred":[
        "\u8463\u8fde\u5e84"
    ],
    "wof:name":"Donglianzhuang",
    "wof:placetype":"locality"
},
  "geometry": {"coordinates":[117.18532,39.32735],"type":"Point"}
}