{
  "type": "Feature",
  "properties": {
    "gn:admin1_code":"33.0",
    "gn:asciiname":"Siyuanping",
    "gn:country_code":"CN",
    "gn:dem":997,
    "gn:feature_class":"P",
    "gn:feature_code":"PPL",
    "gn:name":"Siyuanping",
    "gn:population":0,
    "gn:timezone":"Asia/Shanghai",
    "iso:country":"CN",
    "name:zho_x_preferred":[
        "\u56db\u9662\u576a"
    ],
    "wof:name":"Siyuanping",
    "wof:placetype":"locality"
},
  "geometry": {"coordinates":[109.01792,28.74779],"type":"Point"}
}