{
  "type": "Feature",
  "properties": {
    "gn:admin1_code":"19.0",
    "gn:asciiname":"Xujiahucun",
    "gn:country_code":"CN",
    "gn:dem":55,
    "gn:feature_class":"P",
    "gn:feature_code":"PPL",
    "gn:name":"Xujiahucun",
    "gn:population":0,
    "gn:timezone":"Asia/Shanghai",
    "iso:country":"CN",
    "name:zho_x_preferred":[
        "\u5f90\u5bb6\u6e56\u6751"
    ],
    "wof:name":"Xujiahucun",
    "wof:placetype":"locality"
},
  "geometry": {"coordinates":[123.627,42.1587],"type":"Point"}
}