{
  "type": "Feature",
  "properties": {
    "gn:admin1_code":"15",
    "gn:asciiname":"Fucheng",
    "gn:country_code":"CN",
    "gn:dem":1125,
    "gn:feature_class":"P",
    "gn:feature_code":"PPL",
    "gn:name":"Fucheng",
    "gn:population":0,
    "gn:timezone":"Asia/Shanghai",
    "iso:country":"CN",
    "name:und_x_variant":[
        "Fou-ch\u2019eng",
        "Fou-tsch\u00f6ng",
        "Fucheng",
        "\u961c\u57ce"
    ],
    "wof:name":"Fucheng",
    "wof:placetype":"locality"
},
  "geometry": {"coordinates":[107.70644,36.17334],"type":"Point"}
}