{
  "type": "Feature",
  "properties": {
    "gn:admin1_code":"29.0",
    "gn:asciiname":"Zhapidi",
    "gn:country_code":"CN",
    "gn:dem":1948,
    "gn:feature_class":"P",
    "gn:feature_code":"PPL",
    "gn:name":"Zhapidi",
    "gn:population":0,
    "gn:timezone":"Asia/Shanghai",
    "iso:country":"CN",
    "name:zho_x_preferred":[
        "\u624e\u4e15\u5730"
    ],
    "wof:name":"Zhapidi",
    "wof:placetype":"locality"
},
  "geometry": {"coordinates":[99.8477,22.9081],"type":"Point"}
}