{
  "type": "Feature",
  "properties": {
    "gn:admin1_code":"26.0",
    "gn:asciiname":"Jiajiagou",
    "gn:country_code":"CN",
    "gn:dem":994,
    "gn:feature_class":"P",
    "gn:feature_code":"PPL",
    "gn:name":"Jiajiagou",
    "gn:population":0,
    "gn:timezone":"Asia/Shanghai",
    "iso:country":"CN",
    "name:und_x_variant":[
        "\u8d3e\u5bb6\u6c9f"
    ],
    "wof:name":"Jiajiagou",
    "wof:placetype":"locality"
},
  "geometry": {"coordinates":[106.73172,32.83796],"type":"Point"}
}