{
  "type": "Feature",
  "properties": {
    "gn:admin1_code":"19.0",
    "gn:asciiname":"Yazipao",
    "gn:country_code":"CN",
    "gn:dem":9,
    "gn:feature_class":"P",
    "gn:feature_code":"PPL",
    "gn:name":"Yazipao",
    "gn:population":0,
    "gn:timezone":"Asia/Shanghai",
    "iso:country":"CN",
    "name:zho_x_preferred":[
        "\u9e2d\u5b50\u6ce1"
    ],
    "wof:name":"Yazipao",
    "wof:placetype":"locality"
},
  "geometry": {"coordinates":[122.80200000000001,41.1844],"type":"Point"}
}