{
  "type": "Feature",
  "properties": {
    "gn:admin1_code":"20.0",
    "gn:asciiname":"Kulun",
    "gn:country_code":"CN",
    "gn:dem":1389,
    "gn:feature_class":"P",
    "gn:feature_code":"PPLA4",
    "gn:name":"Kulun",
    "gn:population":0,
    "gn:timezone":"Asia/Shanghai",
    "iso:country":"CN",
    "name:und_x_variant":[
        "\u5e93\u4f26",
        "Kulun Sumu",
        "Hushaolin",
        "\u5e93\u4f26\u82cf\u6728",
        "\u5ffd\u5c11\u6797"
    ],
    "wof:name":"Kulun",
    "wof:placetype":"locality"
},
  "geometry": {"coordinates":[112.66585000000001,41.75749],"type":"Point"}
}