{
  "type": "Feature",
  "properties": {
    "gn:admin1_code":"10",
    "gn:asciiname":"Gaojiazhai",
    "gn:country_code":"CN",
    "gn:dem":32,
    "gn:feature_class":"P",
    "gn:feature_code":"PPL",
    "gn:name":"Gaojiazhai",
    "gn:population":0,
    "gn:timezone":"Asia/Shanghai",
    "iso:country":"CN",
    "name:und_x_variant":[
        "Kao-chia-chai",
        "Gaojiazhai"
    ],
    "name:zho_x_preferred":[
        "\u9ad8\u5bb6\u5be8"
    ],
    "wof:name":"Gaojiazhai",
    "wof:placetype":"locality"
},
  "geometry": {"coordinates":[115.276,37.3065],"type":"Point"}
}