{
  "type": "Feature",
  "properties": {
    "gn:admin1_code":"9",
    "gn:asciiname":"Zhaojidong",
    "gn:country_code":"CN",
    "gn:dem":54,
    "gn:feature_class":"P",
    "gn:feature_code":"PPL",
    "gn:name":"Zhaojidong",
    "gn:population":0,
    "gn:timezone":"Asia/Shanghai",
    "iso:country":"CN",
    "name:zho_x_preferred":[
        "\u8d75\u96c6\u4e1c"
    ],
    "wof:name":"Zhaojidong",
    "wof:placetype":"locality"
},
  "geometry": {"coordinates":[115.43300000000001,34.4963],"type":"Point"}
}