{
  "type": "Feature",
  "properties": {
    "gn:admin1_code":"25.0",
    "gn:asciiname":"Zhanchangkou",
    "gn:country_code":"CN",
    "gn:dem":106,
    "gn:feature_class":"P",
    "gn:feature_code":"PPL",
    "gn:name":"Zhanchangkou",
    "gn:population":0,
    "gn:timezone":"Asia/Shanghai",
    "iso:country":"CN",
    "name:zho_x_preferred":[
        "\u5360\u660c\u53e3"
    ],
    "wof:name":"Zhanchangkou",
    "wof:placetype":"locality"
},
  "geometry": {"coordinates":[121.65608,37.24051],"type":"Point"}
}