{
  "type": "Feature",
  "properties": {
    "gn:admin1_code":"15.0",
    "gn:asciiname":"Maojiagou",
    "gn:country_code":"CN",
    "gn:dem":1713,
    "gn:feature_class":"P",
    "gn:feature_code":"PPL",
    "gn:name":"Maojiagou",
    "gn:population":0,
    "gn:timezone":"Asia/Shanghai",
    "iso:country":"CN",
    "name:und_x_variant":[
        "\u6bdb\u5bb6\u6c9f"
    ],
    "wof:name":"Maojiagou",
    "wof:placetype":"locality"
},
  "geometry": {"coordinates":[105.25982999999999,33.15378],"type":"Point"}
}