{
  "type": "Feature",
  "properties": {
    "gn:admin1_code":"14.0",
    "gn:asciiname":"Tiewa Nancun",
    "gn:country_code":"CN",
    "gn:dem":4465,
    "gn:feature_class":"P",
    "gn:feature_code":"PPL",
    "gn:name":"Tiewa Nancun",
    "gn:population":0,
    "gn:timezone":"Asia/Urumqi",
    "iso:country":"CN",
    "name:zho_x_preferred":[
        "\u8d34\u6d3c\u5357\u6751"
    ],
    "wof:name":"Tiewa Nancun",
    "wof:placetype":"locality"
},
  "geometry": {"coordinates":[92.32264000000001,30.15607],"type":"Point"}
}