{
  "type": "Feature",
  "properties": {
    "gn:admin1_code":"14.0",
    "gn:asciiname":"Jiedingcun",
    "gn:country_code":"CN",
    "gn:dem":3309,
    "gn:feature_class":"P",
    "gn:feature_code":"PPL",
    "gn:name":"Jiedingcun",
    "gn:population":0,
    "gn:timezone":"Asia/Urumqi",
    "iso:country":"CN",
    "name:zho_x_preferred":[
        "\u7ed3\u5b9a\u6751"
    ],
    "wof:name":"Jiedingcun",
    "wof:placetype":"locality"
},
  "geometry": {"coordinates":[93.56891,29.90119],"type":"Point"}
}