{
  "type": "Feature",
  "properties": {
    "gn:admin1_code":"29",
    "gn:asciiname":"Shuimo",
    "gn:country_code":"CN",
    "gn:dem":1884,
    "gn:feature_class":"P",
    "gn:feature_code":"PPL",
    "gn:name":"Shuimo",
    "gn:population":0,
    "gn:timezone":"Asia/Shanghai",
    "iso:country":"CN",
    "name:zho_x_preferred":[
        "\u6c34\u78e8"
    ],
    "wof:name":"Shuimo",
    "wof:placetype":"locality"
},
  "geometry": {"coordinates":[102.595,24.1888],"type":"Point"}
}