{
  "type": "Feature",
  "properties": {
    "gn:admin1_code":"18",
    "gn:asciiname":"Anshao",
    "gn:country_code":"CN",
    "gn:dem":659,
    "gn:feature_class":"P",
    "gn:feature_code":"PPL",
    "gn:name":"Anshao",
    "gn:population":0,
    "gn:timezone":"Asia/Shanghai",
    "iso:country":"CN",
    "name:zho_x_preferred":[
        "\u978d\u70e7"
    ],
    "wof:name":"Anshao",
    "wof:placetype":"locality"
},
  "geometry": {"coordinates":[106.989,25.5068],"type":"Point"}
}