{
  "type": "Feature",
  "properties": {
    "gn:admin1_code":"9.0",
    "gn:asciiname":"Chepengzhang",
    "gn:country_code":"CN",
    "gn:dem":91,
    "gn:feature_class":"P",
    "gn:feature_code":"PPL",
    "gn:name":"Chepengzhang",
    "gn:population":0,
    "gn:timezone":"Asia/Shanghai",
    "iso:country":"CN",
    "name:zho_x_preferred":[
        "\u626f\u68da\u5f20"
    ],
    "wof:name":"Chepengzhang",
    "wof:placetype":"locality"
},
  "geometry": {"coordinates":[113.97817000000001,34.6472],"type":"Point"}
}