{
  "type": "Feature",
  "properties": {
    "gn:admin1_code":"4.0",
    "gn:asciiname":"Yidong",
    "gn:country_code":"CN",
    "gn:dem":2,
    "gn:feature_class":"P",
    "gn:feature_code":"PPL",
    "gn:name":"Yidong",
    "gn:population":0,
    "gn:timezone":"Asia/Shanghai",
    "iso:country":"CN",
    "name:zho_x_preferred":[
        "Yidong"
    ],
    "name:zho_x_variant":[
        "\u4f0a\u4e1c"
    ],
    "wof:name":"Yidong",
    "wof:placetype":"locality"
},
  "geometry": {"coordinates":[119.26881000000002,34.29377],"type":"Point"}
}