{
  "type": "Feature",
  "properties": {
    "gn:admin1_code":"9.0",
    "gn:asciiname":"Zhangcun",
    "gn:cc2":"CN",
    "gn:country_code":"CN",
    "gn:dem":609,
    "gn:feature_class":"P",
    "gn:feature_code":"PPL",
    "gn:name":"Zhangcun",
    "gn:population":0,
    "gn:timezone":"Asia/Shanghai",
    "iso:country":"CN",
    "name:und_x_variant":[
        "Chang-ts\u2019un",
        "Zhangcun"
    ],
    "wof:name":"Zhangcun",
    "wof:placetype":"locality"
},
  "geometry": {"coordinates":[111.65833000000001,34.795],"type":"Point"}
}