{
  "type": "Feature",
  "properties": {
    "gn:admin1_code":"21.0",
    "gn:asciiname":"Taozi",
    "gn:country_code":"CN",
    "gn:dem":1631,
    "gn:feature_class":"P",
    "gn:feature_code":"PPL",
    "gn:name":"Taozi",
    "gn:population":0,
    "gn:timezone":"Asia/Shanghai",
    "iso:country":"CN",
    "name:und_x_variant":[
        "\u5957\u5b50"
    ],
    "name:zho_x_preferred":[
        "\u5957\u5b50"
    ],
    "wof:name":"Taozi",
    "wof:placetype":"locality"
},
  "geometry": {"coordinates":[106.23428,36.68307],"type":"Point"}
}