{
  "type": "Feature",
  "properties": {
    "gn:admin1_code":"13.0",
    "gn:asciiname":"Tarim",
    "gn:cc2":"CN",
    "gn:country_code":"CN",
    "gn:dem":955,
    "gn:feature_class":"P",
    "gn:feature_code":"PPL",
    "gn:name":"Tarim",
    "gn:population":0,
    "gn:timezone":"Asia/Urumqi",
    "iso:country":"CN",
    "name:uig_x_preferred":[
        "\u062a\u0627\u0631\u0649\u0645"
    ],
    "name:uig_x_variant":[
        "\u0422\u0430\u0440\u0438\u043c"
    ],
    "name:und_x_variant":[
        "T\u2019a-li-mu",
        "Tarim"
    ],
    "wof:name":"Tarim",
    "wof:placetype":"locality"
},
  "geometry": {"coordinates":[83.33194,41.0175],"type":"Point"}
}