{
  "type": "Feature",
  "properties": {
    "gn:admin1_code":"13.0",
    "gn:asciiname":"Tarim",
    "gn:cc2":"CN",
    "gn:country_code":"CN",
    "gn:dem":955,
    "gn:feature_class":"P",
    "gn:feature_code":"PPL",
    "gn:name":"Tarim",
    "gn:population":0,
    "gn:timezone":"Asia/Urumqi",
    "iso:country":"CN",
    "name:cat_x_preferred":[
        "Tarim"
    ],
    "name:ceb_x_preferred":[
        "Tarim"
    ],
    "name:deu_x_preferred":[
        "Tarim"
    ],
    "name:epo_x_preferred":[
        "Tarim"
    ],
    "name:eus_x_preferred":[
        "Tarim"
    ],
    "name:fin_x_preferred":[
        "Tarim"
    ],
    "name:fra_x_preferred":[
        "Tarim"
    ],
    "name:ita_x_preferred":[
        "Tarim"
    ],
    "name:jpn_x_preferred":[
        "\u30bf\u30ea\u30e0"
    ],
    "name:nld_x_preferred":[
        "Tarim"
    ],
    "name:nor_x_preferred":[
        "Tarim"
    ],
    "name:rus_x_preferred":[
        "\u0422\u0430\u0440\u0438\u043c"
    ],
    "name:spa_x_preferred":[
        "Tarim"
    ],
    "name:uig_x_preferred":[
        "\u062a\u0627\u0631\u0649\u0645"
    ],
    "name:uig_x_variant":[
        "\u0422\u0430\u0440\u0438\u043c"
    ],
    "name:und_x_variant":[
        "T\u2019a-li-mu"
    ],
    "wof:name":"Tarim",
    "wof:placetype":"locality"
},
  "geometry": {"coordinates":[83.33194,41.0175],"type":"Point"}
}