{
  "type": "Feature",
  "properties": {
    "gn:admin1_code":"11.0",
    "gn:asciiname":"Xiachangping",
    "gn:country_code":"CN",
    "gn:dem":756,
    "gn:feature_class":"P",
    "gn:feature_code":"PPL",
    "gn:name":"Xiachangping",
    "gn:population":0,
    "gn:timezone":"Asia/Shanghai",
    "iso:country":"CN",
    "name:zho_x_preferred":[
        "\u4e0b\u957f\u576a"
    ],
    "wof:name":"Xiachangping",
    "wof:placetype":"locality"
},
  "geometry": {"coordinates":[110.09311,27.45835],"type":"Point"}
}