{
  "type": "Feature",
  "properties": {
    "gn:admin1_code":"02",
    "gn:asciiname":"Tanghui",
    "gn:country_code":"CN",
    "gn:dem":6,
    "gn:feature_class":"P",
    "gn:feature_code":"PPLA4",
    "gn:name":"Tanghui",
    "gn:population":0,
    "gn:timezone":"Asia/Shanghai",
    "iso:country":"CN",
    "name:und_x_variant":[
        "\u5858\u6c47",
        "Tanghui Jiedao",
        "\u5858\u6c47\u8857\u9053"
    ],
    "wof:name":"Tanghui",
    "wof:placetype":"locality"
},
  "geometry": {"coordinates":[120.77198,30.79466],"type":"Point"}
}