{
  "type": "Feature",
  "properties": {
    "gn:admin1_code":"12.0",
    "gn:asciiname":"Caojianao",
    "gn:country_code":"CN",
    "gn:dem":40,
    "gn:feature_class":"P",
    "gn:feature_code":"PPL",
    "gn:name":"Caojianao",
    "gn:population":0,
    "gn:timezone":"Asia/Shanghai",
    "iso:country":"CN",
    "name:zho_x_preferred":[
        "Caojianao"
    ],
    "name:zho_x_variant":[
        "\u66f9\u5bb6\u57b4"
    ],
    "wof:name":"Caojianao",
    "wof:placetype":"locality"
},
  "geometry": {"coordinates":[111.94358,30.56443],"type":"Point"}
}