{
  "type": "Feature",
  "properties": {
    "gn:admin1_code":"32.0",
    "gn:asciiname":"Dashiban",
    "gn:country_code":"CN",
    "gn:dem":1347,
    "gn:feature_class":"P",
    "gn:feature_code":"PPL",
    "gn:name":"Dashiban",
    "gn:population":0,
    "gn:timezone":"Asia/Shanghai",
    "iso:country":"CN",
    "name:zho_x_preferred":[
        "\u5927\u77f3\u677f"
    ],
    "wof:name":"Dashiban",
    "wof:placetype":"locality"
},
  "geometry": {"coordinates":[102.74302,29.72871],"type":"Point"}
}