{
  "type": "Feature",
  "properties": {
    "gn:admin1_code":"29.0",
    "gn:asciiname":"Chenaha",
    "gn:country_code":"CN",
    "gn:dem":1619,
    "gn:feature_class":"P",
    "gn:feature_code":"PPL",
    "gn:name":"Chenaha",
    "gn:population":0,
    "gn:timezone":"Asia/Shanghai",
    "iso:country":"CN",
    "name:zho_x_preferred":[
        "\u8f66\u90a3\u54c8"
    ],
    "wof:name":"Chenaha",
    "wof:placetype":"locality"
},
  "geometry": {"coordinates":[101.789,23.4085],"type":"Point"}
}