{
  "type": "Feature",
  "properties": {
    "gn:admin1_code":"32.0",
    "gn:asciiname":"Xuetanggou",
    "gn:country_code":"CN",
    "gn:dem":471,
    "gn:feature_class":"P",
    "gn:feature_code":"PPL",
    "gn:name":"Xuetanggou",
    "gn:population":0,
    "gn:timezone":"Asia/Shanghai",
    "iso:country":"CN",
    "name:zho_x_preferred":[
        "\u5b66\u5802\u6c9f"
    ],
    "wof:name":"Xuetanggou",
    "wof:placetype":"locality"
},
  "geometry": {"coordinates":[104.05500000000001,30.2684],"type":"Point"}
}