{
  "type": "Feature",
  "properties": {
    "gn:admin1_code":"29.0",
    "gn:asciiname":"Dashujiao",
    "gn:country_code":"CN",
    "gn:dem":1373,
    "gn:feature_class":"P",
    "gn:feature_code":"PPL",
    "gn:name":"Dashujiao",
    "gn:population":0,
    "gn:timezone":"Asia/Shanghai",
    "iso:country":"CN",
    "name:zho_x_preferred":[
        "\u5927\u6811\u811a"
    ],
    "wof:name":"Dashujiao",
    "wof:placetype":"locality"
},
  "geometry": {"coordinates":[100.63800000000001,22.9676],"type":"Point"}
}