{
  "type": "Feature",
  "properties": {
    "gn:admin1_code":"3.0",
    "gn:asciiname":"Changyuanli",
    "gn:country_code":"CN",
    "gn:dem":217,
    "gn:feature_class":"P",
    "gn:feature_code":"PPL",
    "gn:name":"Changyuanli",
    "gn:population":0,
    "gn:timezone":"Asia/Shanghai",
    "iso:country":"CN",
    "name:und_x_variant":[
        "\u957f\u6e90\u91cc"
    ],
    "wof:name":"Changyuanli",
    "wof:placetype":"locality"
},
  "geometry": {"coordinates":[115.24334,28.88807000000001],"type":"Point"}
}