{
  "type": "Feature",
  "properties": {
    "gn:admin1_code":"11.0",
    "gn:asciiname":"Xinlugou",
    "gn:country_code":"CN",
    "gn:dem":389,
    "gn:feature_class":"P",
    "gn:feature_code":"PPL",
    "gn:name":"Xinlugou",
    "gn:population":0,
    "gn:timezone":"Asia/Shanghai",
    "iso:country":"CN",
    "name:zho_x_preferred":[
        "\u65b0\u8def\u6c9f"
    ],
    "wof:name":"Xinlugou",
    "wof:placetype":"locality"
},
  "geometry": {"coordinates":[111.35312999999999,28.52116],"type":"Point"}
}