{
  "type": "Feature",
  "properties": {
    "gn:admin1_code":"26.0",
    "gn:asciiname":"Gaoshencun",
    "gn:country_code":"CN",
    "gn:dem":1290,
    "gn:feature_class":"P",
    "gn:feature_code":"PPL",
    "gn:name":"Gaoshencun",
    "gn:population":0,
    "gn:timezone":"Asia/Shanghai",
    "iso:country":"CN",
    "name:zho_x_preferred":[
        "\u9ad8\u7533\u6751"
    ],
    "wof:name":"Gaoshencun",
    "wof:placetype":"locality"
},
  "geometry": {"coordinates":[108.92655000000001,37.79862],"type":"Point"}
}