{
  "type": "Feature",
  "properties": {
    "gn:admin1_code":"14.0",
    "gn:asciiname":"Nongqiong",
    "gn:country_code":"CN",
    "gn:dem":4205,
    "gn:feature_class":"P",
    "gn:feature_code":"PPL",
    "gn:name":"Nongqiong",
    "gn:population":0,
    "gn:timezone":"Asia/Urumqi",
    "iso:country":"CN",
    "name:zho_x_preferred":[
        "\u5f04\u7a77"
    ],
    "wof:name":"Nongqiong",
    "wof:placetype":"locality"
},
  "geometry": {"coordinates":[97.40349000000001,30.23515],"type":"Point"}
}