{
  "type": "Feature",
  "properties": {
    "gn:admin1_code":"3",
    "gn:asciiname":"Luozhuba",
    "gn:country_code":"CN",
    "gn:dem":444,
    "gn:feature_class":"P",
    "gn:feature_code":"PPL",
    "gn:name":"Luozhuba",
    "gn:population":0,
    "gn:timezone":"Asia/Shanghai",
    "iso:country":"CN",
    "name:und_x_variant":[
        "\u7f57\u7af9\u575d"
    ],
    "wof:name":"Luozhuba",
    "wof:placetype":"locality"
},
  "geometry": {"coordinates":[114.8203,24.60952],"type":"Point"}
}