{
  "type": "Feature",
  "properties": {
    "gn:admin1_code":"30",
    "gn:asciiname":"Shanyao",
    "gn:country_code":"CN",
    "gn:dem":45,
    "gn:feature_class":"P",
    "gn:feature_code":"PPL",
    "gn:name":"Shanyao",
    "gn:population":0,
    "gn:timezone":"Asia/Urumqi",
    "iso:country":"CN",
    "name:rus_x_preferred":[
        "\u0428\u044d\u043d\u044c\u044f\u043d"
    ],
    "name:zho_x_preferred":[
        "\u5c71\u8000"
    ],
    "wof:name":"Shanyao",
    "wof:placetype":"locality"
},
  "geometry": {"coordinates":[110.66316,21.9414],"type":"Point"}
}