{
  "type": "Feature",
  "properties": {
    "gn:admin1_code":"7.0",
    "gn:asciiname":"Linwei",
    "gn:country_code":"CN",
    "gn:dem":16,
    "gn:feature_class":"P",
    "gn:feature_code":"PPL",
    "gn:name":"Linwei",
    "gn:population":0,
    "gn:timezone":"Asia/Shanghai",
    "iso:country":"CN",
    "name:zho_x_preferred":[
        "\u5eea\u5c3e"
    ],
    "wof:name":"Linwei",
    "wof:placetype":"locality"
},
  "geometry": {"coordinates":[119.77424999999999,26.42883],"type":"Point"}
}