{
  "type": "Feature",
  "properties": {
    "gn:admin1_code":"26.0",
    "gn:asciiname":"Chunshupan",
    "gn:country_code":"CN",
    "gn:dem":1530,
    "gn:feature_class":"P",
    "gn:feature_code":"PPL",
    "gn:name":"Chunshupan",
    "gn:population":0,
    "gn:timezone":"Asia/Shanghai",
    "iso:country":"CN",
    "name:zho_x_preferred":[
        "\u693f\u6811\u7554"
    ],
    "wof:name":"Chunshupan",
    "wof:placetype":"locality"
},
  "geometry": {"coordinates":[108.80165,36.88135],"type":"Point"}
}