{
  "type": "Feature",
  "properties": {
    "gn:admin1_code":"19.0",
    "gn:asciiname":"Chujiatun",
    "gn:country_code":"CN",
    "gn:dem":103,
    "gn:feature_class":"P",
    "gn:feature_code":"PPL",
    "gn:name":"Chujiatun",
    "gn:population":0,
    "gn:timezone":"Asia/Shanghai",
    "iso:country":"CN",
    "name:und_x_variant":[
        "\u891a\u5bb6\u5c6f"
    ],
    "name:zho_x_preferred":[
        "\u891a\u5bb6\u5c6f"
    ],
    "wof:name":"Chujiatun",
    "wof:placetype":"locality"
},
  "geometry": {"coordinates":[121.18631000000001,41.50522],"type":"Point"}
}