{
  "type": "Feature",
  "properties": {
    "gn:admin1_code":"26",
    "gn:asciiname":"Jiangcun",
    "gn:country_code":"CN",
    "gn:dem":589,
    "gn:feature_class":"P",
    "gn:feature_code":"PPLA4",
    "gn:name":"Jiangcun",
    "gn:population":0,
    "gn:timezone":"Asia/Shanghai",
    "iso:country":"CN",
    "name:und_x_variant":[
        "Jiangcun Zhen",
        "Jiangcun"
    ],
    "name:zho_x_preferred":[
        "\u59dc\u6751"
    ],
    "name:zho_x_variant":[
        "\u59dc\u6751\u9547"
    ],
    "wof:name":"Jiangcun",
    "wof:placetype":"locality"
},
  "geometry": {"coordinates":[108.2525,34.39278],"type":"Point"}
}