{
  "type": "Feature",
  "properties": {
    "gn:admin1_code":"11.0",
    "gn:asciiname":"Sifenchang Erdui",
    "gn:country_code":"CN",
    "gn:dem":29,
    "gn:feature_class":"P",
    "gn:feature_code":"PPLF",
    "gn:name":"Sifenchang Erdui",
    "gn:population":0,
    "gn:timezone":"Asia/Shanghai",
    "iso:country":"CN",
    "name:zho_x_preferred":[
        "\u56db\u5206\u573a\u4e8c\u961f"
    ],
    "wof:name":"Sifenchang Erdui",
    "wof:placetype":"locality"
},
  "geometry": {"coordinates":[112.71834,29.35992],"type":"Point"}
}