{
  "type": "Feature",
  "properties": {
    "gn:admin1_code":"25",
    "gn:asciiname":"Zhangchengzhuang",
    "gn:country_code":"CN",
    "gn:dem":22,
    "gn:feature_class":"P",
    "gn:feature_code":"PPL",
    "gn:name":"Zhangchengzhuang",
    "gn:population":0,
    "gn:timezone":"Asia/Shanghai",
    "iso:country":"CN",
    "name:zho_x_preferred":[
        "\u5f20\u7a0b\u5e84"
    ],
    "wof:name":"Zhangchengzhuang",
    "wof:placetype":"locality"
},
  "geometry": {"coordinates":[116.65900000000001,37.6766],"type":"Point"}
}