{
  "type": "Feature",
  "properties": {
    "gn:admin1_code":"11.0",
    "gn:asciiname":"Wenjiashi",
    "gn:country_code":"CN",
    "gn:dem":291,
    "gn:feature_class":"P",
    "gn:feature_code":"PPL",
    "gn:name":"Wenjiashi",
    "gn:population":0,
    "gn:timezone":"Asia/Shanghai",
    "iso:country":"CN",
    "name:jpn_x_preferred":[
        "\u6587\u5bb6\u5e02\u93ae"
    ],
    "name:zho_x_preferred":[
        "\u6587\u5bb6\u5e02\u9547"
    ],
    "wof:name":"Wenjiashi",
    "wof:placetype":"locality"
},
  "geometry": {"coordinates":[113.93639,28.04361],"type":"Point"}
}