{
  "type": "Feature",
  "properties": {
    "gn:admin1_code":"30.0",
    "gn:asciiname":"Niulanjiao",
    "gn:country_code":"CN",
    "gn:dem":-4,
    "gn:feature_class":"P",
    "gn:feature_code":"PPL",
    "gn:name":"Niulanjiao",
    "gn:population":0,
    "gn:timezone":"Asia/Shanghai",
    "iso:country":"CN",
    "name:zho_x_preferred":[
        "\u725b\u680f\u89d2"
    ],
    "wof:name":"Niulanjiao",
    "wof:placetype":"locality"
},
  "geometry": {"coordinates":[113.60566,22.87791],"type":"Point"}
}