{
  "type": "Feature",
  "properties": {
    "gn:admin1_code":"15",
    "gn:asciiname":"Ruoli",
    "gn:cc2":"CN",
    "gn:country_code":"CN",
    "gn:dem":2221,
    "gn:feature_class":"P",
    "gn:feature_code":"PPL",
    "gn:name":"Ruoli",
    "gn:population":0,
    "gn:timezone":"Asia/Shanghai",
    "iso:country":"CN",
    "name:und_x_variant":[
        "Jo-li",
        "Ruoli"
    ],
    "wof:name":"Ruoli",
    "wof:placetype":"locality"
},
  "geometry": {"coordinates":[104.55972,36.26333],"type":"Point"}
}