{
  "type": "Feature",
  "properties": {
    "gn:admin1_code":"14.0",
    "gn:asciiname":"Zanlong",
    "gn:country_code":"CN",
    "gn:dem":4479,
    "gn:feature_class":"P",
    "gn:feature_code":"PPL",
    "gn:name":"Zanlong",
    "gn:population":0,
    "gn:timezone":"Asia/Urumqi",
    "iso:country":"CN",
    "name:zho_x_preferred":[
        "\u54b1\u62e2"
    ],
    "wof:name":"Zanlong",
    "wof:placetype":"locality"
},
  "geometry": {"coordinates":[94.60813,29.58537],"type":"Point"}
}