{
  "type": "Feature",
  "properties": {
    "gn:admin1_code":"30",
    "gn:asciiname":"Datanshan",
    "gn:country_code":"CN",
    "gn:dem":6,
    "gn:feature_class":"P",
    "gn:feature_code":"PPL",
    "gn:name":"Datanshan",
    "gn:population":0,
    "gn:timezone":"Asia/Shanghai",
    "iso:country":"CN",
    "name:zho_x_preferred":[
        "\u5927\u6f6d\u5c71"
    ],
    "wof:name":"Datanshan",
    "wof:placetype":"locality"
},
  "geometry": {"coordinates":[111.76617,21.67561],"type":"Point"}
}