{
  "type": "Feature",
  "properties": {
    "gn:admin1_code":"10",
    "gn:asciiname":"Chenjiayao",
    "gn:country_code":"CN",
    "gn:dem":1491,
    "gn:feature_class":"P",
    "gn:feature_code":"PPL",
    "gn:name":"Chenjiayao",
    "gn:population":0,
    "gn:timezone":"Asia/Shanghai",
    "iso:country":"CN",
    "name:zho_x_preferred":[
        "\u9648\u5bb6\u7a91"
    ],
    "wof:name":"Chenjiayao",
    "wof:placetype":"locality"
},
  "geometry": {"coordinates":[115.79600000000001,41.23043],"type":"Point"}
}