{
  "type": "Feature",
  "properties": {
    "gn:admin1_code":"12.0",
    "gn:asciiname":"Wangdeming",
    "gn:country_code":"CN",
    "gn:dem":43,
    "gn:feature_class":"P",
    "gn:feature_code":"PPL",
    "gn:name":"Wangdeming",
    "gn:population":0,
    "gn:timezone":"Asia/Shanghai",
    "iso:country":"CN",
    "name:und_x_variant":[
        "\u738b\u5fb7\u660e"
    ],
    "wof:name":"Wangdeming",
    "wof:placetype":"locality"
},
  "geometry": {"coordinates":[114.33553999999999,30.21641],"type":"Point"}
}