{
  "type": "Feature",
  "properties": {
    "gn:admin1_code":"9.0",
    "gn:asciiname":"Liubanqiao",
    "gn:country_code":"CN",
    "gn:dem":68,
    "gn:feature_class":"P",
    "gn:feature_code":"PPL",
    "gn:name":"Liubanqiao",
    "gn:population":0,
    "gn:timezone":"Asia/Shanghai",
    "iso:country":"CN",
    "name:zho_x_preferred":[
        "\u5218\u677f\u6865"
    ],
    "wof:name":"Liubanqiao",
    "wof:placetype":"locality"
},
  "geometry": {"coordinates":[114.24632,35.48243],"type":"Point"}
}