{
  "type": "Feature",
  "properties": {
    "gn:admin1_code":"4.0",
    "gn:asciiname":"Erxu",
    "gn:country_code":"CN",
    "gn:dem":6,
    "gn:feature_class":"P",
    "gn:feature_code":"PPL",
    "gn:name":"Erxu",
    "gn:population":0,
    "gn:timezone":"Asia/Shanghai",
    "iso:country":"CN",
    "name:zho_x_preferred":[
        "Erxu"
    ],
    "name:zho_x_variant":[
        "\u4e8c\u5729"
    ],
    "wof:name":"Erxu",
    "wof:placetype":"locality"
},
  "geometry": {"coordinates":[119.08893,33.25895],"type":"Point"}
}