{
  "type": "Feature",
  "properties": {
    "gn:admin1_code":"15",
    "gn:asciiname":"Guanting",
    "gn:country_code":"CN",
    "gn:dem":1428,
    "gn:feature_class":"P",
    "gn:feature_code":"PPLA4",
    "gn:name":"Guanting",
    "gn:population":0,
    "gn:timezone":"Asia/Shanghai",
    "iso:country":"CN",
    "name:deu_x_preferred":[
        "Guanting"
    ],
    "name:und_x_variant":[
        "Guanting Zhen"
    ],
    "name:zho_x_preferred":[
        "Kuan-t\u2019ing"
    ],
    "name:zho_x_variant":[
        "\u5b98\u4ead",
        "\u5b98\u4ead\u9547"
    ],
    "wof:name":"Guanting",
    "wof:placetype":"locality"
},
  "geometry": {"coordinates":[104.53227,33.81652],"type":"Point"}
}