{
  "type": "Feature",
  "properties": {
    "gn:admin1_code":"3.0",
    "gn:asciiname":"Niuzailingxia",
    "gn:country_code":"CN",
    "gn:dem":354,
    "gn:feature_class":"P",
    "gn:feature_code":"PPL",
    "gn:name":"Niuzailingxia",
    "gn:population":0,
    "gn:timezone":"Asia/Shanghai",
    "iso:country":"CN",
    "name:und_x_variant":[
        "\u725b\u4ed4\u5cad\u4e0b"
    ],
    "wof:name":"Niuzailingxia",
    "wof:placetype":"locality"
},
  "geometry": {"coordinates":[115.41965999999999,25.14439],"type":"Point"}
}