{
  "type": "Feature",
  "properties": {
    "gn:admin1_code":"19.0",
    "gn:asciiname":"Dafutun",
    "gn:country_code":"CN",
    "gn:dem":30,
    "gn:feature_class":"P",
    "gn:feature_code":"PPL",
    "gn:name":"Dafutun",
    "gn:population":0,
    "gn:timezone":"Asia/Shanghai",
    "iso:country":"CN",
    "name:und_x_variant":[
        "\u5927\u5bcc\u5c6f"
    ],
    "name:zho_x_preferred":[
        "\u5927\u5bcc\u5c6f"
    ],
    "wof:name":"Dafutun",
    "wof:placetype":"locality"
},
  "geometry": {"coordinates":[121.25238,41.23589000000001],"type":"Point"}
}