{
  "type": "Feature",
  "properties": {
    "gn:admin1_code":"32",
    "gn:asciiname":"Renlong",
    "gn:country_code":"CN",
    "gn:dem":326,
    "gn:feature_class":"P",
    "gn:feature_code":"PPL",
    "gn:name":"Renlong",
    "gn:population":0,
    "gn:timezone":"Asia/Shanghai",
    "iso:country":"CN",
    "name:und_x_variant":[
        "Jen-lung",
        "Renlong"
    ],
    "name:zho_x_preferred":[
        "\u4efb\u9686"
    ],
    "wof:name":"Renlong",
    "wof:placetype":"locality"
},
  "geometry": {"coordinates":[105.75657,30.54206],"type":"Point"}
}