{
  "type": "Feature",
  "properties": {
    "gn:admin1_code":"33.0",
    "gn:asciiname":"Damian",
    "gn:country_code":"CN",
    "gn:dem":154,
    "gn:feature_class":"P",
    "gn:feature_code":"PPL",
    "gn:name":"Damian",
    "gn:population":0,
    "gn:timezone":"Asia/Shanghai",
    "iso:country":"CN",
    "name:bul_x_preferred":[
        "\u0414\u0430\u043c\u044f\u043d"
    ],
    "name:ceb_x_preferred":[
        "Damian"
    ],
    "name:deu_x_preferred":[
        "Damian"
    ],
    "name:ell_x_preferred":[
        "\u0394\u03b1\u03bc\u03b9\u03b1\u03bd\u03cc\u03c2"
    ],
    "name:hun_x_preferred":[
        "Damj\u00e1n"
    ],
    "name:ita_x_preferred":[
        "Damian"
    ],
    "name:jpn_x_preferred":[
        "\u30c0\u30df\u30a2\u30f3"
    ],
    "name:spa_x_preferred":[
        "Dami\u00e1n"
    ],
    "name:swe_x_preferred":[
        "Damian"
    ],
    "name:zho_x_preferred":[
        "\u5927\u9762"
    ],
    "wof:name":"Damian",
    "wof:placetype":"locality"
},
  "geometry": {"coordinates":[108.04237000000001,30.32921],"type":"Point"}
}