{
  "type": "Feature",
  "properties": {
    "gn:admin1_code":"14.0",
    "gn:asciiname":"Chibma",
    "gn:country_code":"CN",
    "gn:dem":4951,
    "gn:feature_class":"P",
    "gn:feature_code":"PPLF",
    "gn:name":"Chibma",
    "gn:population":0,
    "gn:timezone":"Asia/Urumqi",
    "iso:country":"CN",
    "name:bod_x_preferred":[
        "Chibma"
    ],
    "name:msa_x_preferred":[
        "Chibma"
    ],
    "name:zho_x_preferred":[
        "Chima"
    ],
    "name:zho_x_variant":[
        "\u8d64\u9a6c",
        "Xiacuo",
        "\u590f\u9519"
    ],
    "wof:name":"Chibma",
    "wof:placetype":"locality"
},
  "geometry": {"coordinates":[85.59999999999999,30.35],"type":"Point"}
}