{
  "type": "Feature",
  "properties": {
    "gn:admin1_code":"5.0",
    "gn:asciiname":"Xin'antun",
    "gn:country_code":"CN",
    "gn:dem":652,
    "gn:feature_class":"P",
    "gn:feature_code":"PPL",
    "gn:name":"Xin\u2019antun",
    "gn:population":0,
    "gn:timezone":"Asia/Shanghai",
    "iso:country":"CN",
    "name:und_x_variant":[
        "Xin\u2019antun"
    ],
    "name:zho_x_preferred":[
        "\u65b0\u5b89\u5c6f"
    ],
    "wof:name":"Xin'antun",
    "wof:placetype":"locality"
},
  "geometry": {"coordinates":[126.33665999999999,41.96496],"type":"Point"}
}