{
  "type": "Feature",
  "properties": {
    "gn:admin1_code":"14.0",
    "gn:asciiname":"Luoluoxia",
    "gn:country_code":"CN",
    "gn:dem":4447,
    "gn:feature_class":"P",
    "gn:feature_code":"PPL",
    "gn:name":"Luoluoxia",
    "gn:population":0,
    "gn:timezone":"Asia/Urumqi",
    "iso:country":"CN",
    "name:zho_x_preferred":[
        "\u7f57\u7f57\u8f96"
    ],
    "wof:name":"Luoluoxia",
    "wof:placetype":"locality"
},
  "geometry": {"coordinates":[87.21339999999999,28.7206],"type":"Point"}
}