{
  "type": "Feature",
  "properties": {
    "gn:admin1_code":"30",
    "gn:asciiname":"Gaochetang",
    "gn:country_code":"CN",
    "gn:dem":162,
    "gn:feature_class":"P",
    "gn:feature_code":"PPL",
    "gn:name":"Gaochetang",
    "gn:population":0,
    "gn:timezone":"Asia/Shanghai",
    "iso:country":"CN",
    "name:zho_x_preferred":[
        "\u9ad8\u8f66\u5858"
    ],
    "wof:name":"Gaochetang",
    "wof:placetype":"locality"
},
  "geometry": {"coordinates":[115.87529000000001,23.92789],"type":"Point"}
}