{
  "type": "Feature",
  "properties": {
    "gn:admin1_code":"11.0",
    "gn:asciiname":"Zanzhuhu",
    "gn:country_code":"CN",
    "gn:dem":451,
    "gn:feature_class":"P",
    "gn:feature_code":"PPL",
    "gn:name":"Zanzhuhu",
    "gn:population":0,
    "gn:timezone":"Asia/Shanghai",
    "iso:country":"CN",
    "name:zho_x_preferred":[
        "\u54b1\u7af9\u6e56"
    ],
    "wof:name":"Zanzhuhu",
    "wof:placetype":"locality"
},
  "geometry": {"coordinates":[109.35933,28.90672],"type":"Point"}
}