{
  "type": "Feature",
  "properties": {
    "gn:admin1_code":"11.0",
    "gn:asciiname":"Miaogengdao",
    "gn:country_code":"CN",
    "gn:dem":1028,
    "gn:feature_class":"P",
    "gn:feature_code":"PPL",
    "gn:name":"Miaogengdao",
    "gn:population":0,
    "gn:timezone":"Asia/Shanghai",
    "iso:country":"CN",
    "name:zho_x_preferred":[
        "\u5e99\u57c2\u5012"
    ],
    "wof:name":"Miaogengdao",
    "wof:placetype":"locality"
},
  "geometry": {"coordinates":[113.69887,25.9767],"type":"Point"}
}