{
  "type": "Feature",
  "properties": {
    "gn:admin1_code":"32.0",
    "gn:asciiname":"Yinling",
    "gn:country_code":"CN",
    "gn:dem":921,
    "gn:feature_class":"P",
    "gn:feature_code":"PPL",
    "gn:name":"Yinling",
    "gn:population":0,
    "gn:timezone":"Asia/Shanghai",
    "iso:country":"CN",
    "name:jpn_x_preferred":[
        "\u30a4\u30f3\u30ea\u30f3\u30fb\u30aa\u30d6\u30fb\u30b8\u30e7\u30a4\u30c8\u30a4"
    ],
    "name:spa_x_preferred":[
        "Yan Yinling"
    ],
    "name:zho_x_preferred":[
        "\u94f6\u5cad"
    ],
    "wof:name":"Yinling",
    "wof:placetype":"locality"
},
  "geometry": {"coordinates":[104.60899999999999,32.1329],"type":"Point"}
}