{
  "type": "Feature",
  "properties": {
    "gn:admin1_code":"9",
    "gn:asciiname":"Wudian",
    "gn:country_code":"CN",
    "gn:dem":45,
    "gn:feature_class":"P",
    "gn:feature_code":"PPL",
    "gn:name":"Wudian",
    "gn:population":0,
    "gn:timezone":"Asia/Shanghai",
    "iso:country":"CN",
    "name:zho_x_preferred":[
        "\u6b66\u5e97"
    ],
    "wof:name":"Wudian",
    "wof:placetype":"locality"
},
  "geometry": {"coordinates":[115.16800000000001,33.8147],"type":"Point"}
}