{
  "type": "Feature",
  "properties": {
    "gn:admin1_code":"29.0",
    "gn:asciiname":"Shabuzuo",
    "gn:country_code":"CN",
    "gn:dem":1998,
    "gn:feature_class":"P",
    "gn:feature_code":"PPL",
    "gn:name":"Shabuzuo",
    "gn:population":0,
    "gn:timezone":"Asia/Shanghai",
    "iso:country":"CN",
    "name:zho_x_preferred":[
        "\u6c99\u4e0d\u5ea7"
    ],
    "wof:name":"Shabuzuo",
    "wof:placetype":"locality"
},
  "geometry": {"coordinates":[100.83799999999999,26.5353],"type":"Point"}
}