{
  "type": "Feature",
  "properties": {
    "gn:admin1_code":"16.0",
    "gn:asciiname":"Xiangqiao",
    "gn:country_code":"CN",
    "gn:dem":741,
    "gn:feature_class":"P",
    "gn:feature_code":"PPL",
    "gn:name":"Xiangqiao",
    "gn:population":0,
    "gn:timezone":"Asia/Shanghai",
    "iso:country":"CN",
    "name:zho_x_preferred":[
        "\u9999\u6865"
    ],
    "wof:name":"Xiangqiao",
    "wof:placetype":"locality"
},
  "geometry": {"coordinates":[107.145,24.403],"type":"Point"}
}