{
  "type": "Feature",
  "properties": {
    "gn:admin1_code":"7.0",
    "gn:asciiname":"Waiqiankeng",
    "gn:country_code":"CN",
    "gn:dem":346,
    "gn:feature_class":"P",
    "gn:feature_code":"PPL",
    "gn:name":"Waiqiankeng",
    "gn:population":0,
    "gn:timezone":"Asia/Shanghai",
    "iso:country":"CN",
    "name:zho_x_preferred":[
        "\u5916\u524d\u5751"
    ],
    "wof:name":"Waiqiankeng",
    "wof:placetype":"locality"
},
  "geometry": {"coordinates":[117.71080000000001,26.90949],"type":"Point"}
}