{
  "type": "Feature",
  "properties": {
    "gn:admin1_code":"19.0",
    "gn:asciiname":"Yuanbaowa",
    "gn:country_code":"CN",
    "gn:dem":111,
    "gn:feature_class":"P",
    "gn:feature_code":"PPL",
    "gn:name":"Yuanbaowa",
    "gn:population":0,
    "gn:timezone":"Asia/Shanghai",
    "iso:country":"CN",
    "name:zho_x_preferred":[
        "\u5143\u5b9d\u6d3c"
    ],
    "wof:name":"Yuanbaowa",
    "wof:placetype":"locality"
},
  "geometry": {"coordinates":[122.017,42.0274],"type":"Point"}
}