{
  "type": "Feature",
  "properties": {
    "gn:admin1_code":"8.0",
    "gn:asciiname":"Xumaiyantun",
    "gn:country_code":"CN",
    "gn:dem":157,
    "gn:feature_class":"P",
    "gn:feature_code":"PPL",
    "gn:name":"Xumaiyantun",
    "gn:population":0,
    "gn:timezone":"Asia/Shanghai",
    "iso:country":"CN",
    "name:zho_x_preferred":[
        "\u5f90\u5356\u70df\u5c6f"
    ],
    "wof:name":"Xumaiyantun",
    "wof:placetype":"locality"
},
  "geometry": {"coordinates":[125.45593,45.72051],"type":"Point"}
}