{
  "type": "Feature",
  "properties": {
    "gn:admin1_code":"14.0",
    "gn:asciiname":"Geshika",
    "gn:country_code":"CN",
    "gn:dem":4654,
    "gn:feature_class":"P",
    "gn:feature_code":"PPL",
    "gn:name":"Geshika",
    "gn:population":0,
    "gn:timezone":"Asia/Urumqi",
    "iso:country":"CN",
    "name:zho_x_preferred":[
        "\u6208\u8bc6\u5361"
    ],
    "wof:name":"Geshika",
    "wof:placetype":"locality"
},
  "geometry": {"coordinates":[94.04746,31.39649],"type":"Point"}
}