{
  "type": "Feature",
  "properties": {
    "gn:admin1_code":"3.0",
    "gn:asciiname":"Huling",
    "gn:country_code":"CN",
    "gn:dem":266,
    "gn:feature_class":"P",
    "gn:feature_code":"PPL",
    "gn:name":"Huling",
    "gn:population":0,
    "gn:timezone":"Asia/Shanghai",
    "iso:country":"CN",
    "name:zho_x_preferred":[
        "\u6d52\u5cad"
    ],
    "wof:name":"Huling",
    "wof:placetype":"locality"
},
  "geometry": {"coordinates":[113.86499999999999,27.4626],"type":"Point"}
}