{
  "type": "Feature",
  "properties": {
    "gn:admin1_code":"10",
    "gn:asciiname":"Wangshaoquan",
    "gn:country_code":"CN",
    "gn:dem":15,
    "gn:feature_class":"P",
    "gn:feature_code":"PPL",
    "gn:name":"Wangshaoquan",
    "gn:population":0,
    "gn:timezone":"Asia/Shanghai",
    "iso:country":"CN",
    "name:zho_x_preferred":[
        "\u738b\u5c11\u6cc9"
    ],
    "wof:name":"Wangshaoquan",
    "wof:placetype":"locality"
},
  "geometry": {"coordinates":[116.99531,37.91175],"type":"Point"}
}