{
  "type": "Feature",
  "properties": {
    "gn:admin1_code":"29.0",
    "gn:asciiname":"Shuijinghe",
    "gn:country_code":"CN",
    "gn:dem":1290,
    "gn:feature_class":"P",
    "gn:feature_code":"PPL",
    "gn:name":"Shuijinghe",
    "gn:population":0,
    "gn:timezone":"Asia/Shanghai",
    "iso:country":"CN",
    "name:zho_x_preferred":[
        "\u6c34\u4e95\u6cb3"
    ],
    "wof:name":"Shuijinghe",
    "wof:placetype":"locality"
},
  "geometry": {"coordinates":[98.99679999999999,25.0526],"type":"Point"}
}