{
  "type": "Feature",
  "properties": {
    "gn:admin1_code":"8.0",
    "gn:asciiname":"Dongsheng",
    "gn:country_code":"CN",
    "gn:dem":490,
    "gn:feature_class":"P",
    "gn:feature_code":"PPL",
    "gn:name":"Dongsheng",
    "gn:population":0,
    "gn:timezone":"Asia/Shanghai",
    "iso:country":"CN",
    "name:und_x_variant":[
        "\u4e1c\u5347"
    ],
    "wof:name":"Dongsheng",
    "wof:placetype":"locality"
},
  "geometry": {"coordinates":[130.23379,44.11421],"type":"Point"}
}