{
  "type": "Feature",
  "properties": {
    "gn:admin1_code":"14.0",
    "gn:asciiname":"Renda",
    "gn:country_code":"CN",
    "gn:dem":2867,
    "gn:feature_class":"P",
    "gn:feature_code":"PPL",
    "gn:name":"Renda",
    "gn:population":0,
    "gn:timezone":"Asia/Urumqi",
    "iso:country":"CN",
    "name:ita_x_preferred":[
        "Renda"
    ],
    "name:por_x_preferred":[
        "Renda"
    ],
    "name:zho_x_preferred":[
        "\u4ec1\u8fbe"
    ],
    "wof:name":"Renda",
    "wof:placetype":"locality"
},
  "geometry": {"coordinates":[97.30238,30.03104],"type":"Point"}
}