{
  "type": "Feature",
  "properties": {
    "gn:admin1_code":"30",
    "gn:asciiname":"Qiaodongcun",
    "gn:country_code":"CN",
    "gn:dem":5,
    "gn:feature_class":"P",
    "gn:feature_code":"PPL",
    "gn:name":"Qiaodongcun",
    "gn:population":0,
    "gn:timezone":"Asia/Urumqi",
    "iso:country":"CN",
    "name:zho_x_preferred":[
        "\u6865\u4e1c\u6751"
    ],
    "wof:name":"Qiaodongcun",
    "wof:placetype":"locality"
},
  "geometry": {"coordinates":[110.04333,20.89041],"type":"Point"}
}