{
  "type": "Feature",
  "properties": {
    "gn:admin1_code":"29.0",
    "gn:asciiname":"Shanghebian",
    "gn:country_code":"CN",
    "gn:dem":1646,
    "gn:feature_class":"P",
    "gn:feature_code":"PPL",
    "gn:name":"Shanghebian",
    "gn:population":0,
    "gn:timezone":"Asia/Shanghai",
    "iso:country":"CN",
    "name:zho_x_preferred":[
        "\u4e0a\u6cb3\u8fb9"
    ],
    "wof:name":"Shanghebian",
    "wof:placetype":"locality"
},
  "geometry": {"coordinates":[100.643,25.6411],"type":"Point"}
}