{
  "type": "Feature",
  "properties": {
    "gn:admin1_code":"29.0",
    "gn:asciiname":"Sanhedong",
    "gn:country_code":"CN",
    "gn:dem":1865,
    "gn:feature_class":"P",
    "gn:feature_code":"PPL",
    "gn:name":"Sanhedong",
    "gn:population":0,
    "gn:timezone":"Asia/Shanghai",
    "iso:country":"CN",
    "name:zho_x_preferred":[
        "\u4e09\u9e64\u6d1e"
    ],
    "wof:name":"Sanhedong",
    "wof:placetype":"locality"
},
  "geometry": {"coordinates":[100.113,25.2813],"type":"Point"}
}