{
  "type": "Feature",
  "properties": {
    "gn:admin1_code":"3.0",
    "gn:asciiname":"Shangwei",
    "gn:country_code":"CN",
    "gn:dem":636,
    "gn:feature_class":"P",
    "gn:feature_code":"PPL",
    "gn:name":"Shangwei",
    "gn:population":0,
    "gn:timezone":"Asia/Shanghai",
    "iso:country":"CN",
    "name:und_x_variant":[
        "\u4e0a\u56f4"
    ],
    "wof:name":"Shangwei",
    "wof:placetype":"locality"
},
  "geometry": {"coordinates":[114.50288,24.57618],"type":"Point"}
}