{
  "type": "Feature",
  "properties": {
    "gn:admin1_code":"3.0",
    "gn:asciiname":"Miaoxia",
    "gn:country_code":"CN",
    "gn:dem":58,
    "gn:feature_class":"P",
    "gn:feature_code":"PPL",
    "gn:name":"Miaoxia",
    "gn:population":0,
    "gn:timezone":"Asia/Shanghai",
    "iso:country":"CN",
    "name:und_x_variant":[
        "\u5e99\u4e0b"
    ],
    "wof:name":"Miaoxia",
    "wof:placetype":"locality"
},
  "geometry": {"coordinates":[116.05083,28.08568],"type":"Point"}
}