{
  "type": "Feature",
  "properties": {
    "gn:admin1_code":"26.0",
    "gn:asciiname":"Xigouzui",
    "gn:country_code":"CN",
    "gn:dem":1464,
    "gn:feature_class":"P",
    "gn:feature_code":"PPL",
    "gn:name":"Xigouzui",
    "gn:population":0,
    "gn:timezone":"Asia/Shanghai",
    "iso:country":"CN",
    "name:zho_x_preferred":[
        "\u897f\u6c9f\u5480"
    ],
    "wof:name":"Xigouzui",
    "wof:placetype":"locality"
},
  "geometry": {"coordinates":[107.32984,37.17748],"type":"Point"}
}