{
  "type": "Feature",
  "properties": {
    "gn:admin1_code":"14.0",
    "gn:asciiname":"Zhengamai",
    "gn:country_code":"CN",
    "gn:dem":3740,
    "gn:feature_class":"P",
    "gn:feature_code":"PPL",
    "gn:name":"Zhengamai",
    "gn:population":0,
    "gn:timezone":"Asia/Urumqi",
    "iso:country":"CN",
    "name:zho_x_preferred":[
        "\u771f\u560e\u9ea6"
    ],
    "wof:name":"Zhengamai",
    "wof:placetype":"locality"
},
  "geometry": {"coordinates":[91.39758999999999,29.82899],"type":"Point"}
}