{
  "type": "Feature",
  "properties": {
    "gn:admin1_code":"08",
    "gn:asciiname":"Liujianfang",
    "gn:country_code":"CN",
    "gn:dem":159,
    "gn:feature_class":"P",
    "gn:feature_code":"PPL",
    "gn:name":"Liujianfang",
    "gn:population":0,
    "gn:timezone":"Asia/Shanghai",
    "iso:country":"CN",
    "name:und_x_variant":[
        "Liu-chien-fang",
        "Liujianfang"
    ],
    "name:zho_x_preferred":[
        "\u516d\u95f4\u623f"
    ],
    "wof:name":"Liujianfang",
    "wof:placetype":"locality"
},
  "geometry": {"coordinates":[124.12089,47.74681],"type":"Point"}
}