{
  "type": "Feature",
  "properties": {
    "gn:admin1_code":"5.0",
    "gn:asciiname":"Xianfeng Linchang",
    "gn:country_code":"CN",
    "gn:dem":789,
    "gn:feature_class":"P",
    "gn:feature_code":"PPLF",
    "gn:name":"Xianfeng Linchang",
    "gn:population":0,
    "gn:timezone":"Asia/Shanghai",
    "iso:country":"CN",
    "name:und_x_variant":[
        "\u5148\u5cf0\u6797\u573a"
    ],
    "wof:name":"Xianfeng Linchang",
    "wof:placetype":"locality"
},
  "geometry": {"coordinates":[128.75354999999999,42.53346],"type":"Point"}
}