{
  "type": "Feature",
  "properties": {
    "gn:admin1_code":"18",
    "gn:asciiname":"Shebagou",
    "gn:country_code":"CN",
    "gn:dem":726,
    "gn:feature_class":"P",
    "gn:feature_code":"PPL",
    "gn:name":"Shebagou",
    "gn:population":0,
    "gn:timezone":"Asia/Shanghai",
    "iso:country":"CN",
    "name:zho_x_preferred":[
        "\u86c7\u575d\u6c9f"
    ],
    "wof:name":"Shebagou",
    "wof:placetype":"locality"
},
  "geometry": {"coordinates":[107.307,28.2153],"type":"Point"}
}