{
  "type": "Feature",
  "properties": {
    "gn:admin1_code":"9",
    "gn:asciiname":"Heya",
    "gn:country_code":"CN",
    "gn:dem":50,
    "gn:feature_class":"P",
    "gn:feature_code":"PPL",
    "gn:name":"Heya",
    "gn:population":0,
    "gn:timezone":"Asia/Shanghai",
    "iso:country":"CN",
    "name:ceb_x_preferred":[
        "Heya"
    ],
    "name:swe_x_preferred":[
        "Heya"
    ],
    "name:zho_x_preferred":[
        "\u6cb3\u6daf"
    ],
    "wof:name":"Heya",
    "wof:placetype":"locality"
},
  "geometry": {"coordinates":[115.78100000000001,34.2919],"type":"Point"}
}