{
  "type": "Feature",
  "properties": {
    "gn:admin1_code":"12.0",
    "gn:asciiname":"Hujiapu",
    "gn:country_code":"CN",
    "gn:dem":26,
    "gn:feature_class":"P",
    "gn:feature_code":"PPL",
    "gn:name":"Hujiapu",
    "gn:population":0,
    "gn:timezone":"Asia/Shanghai",
    "iso:country":"CN",
    "name:zho_x_preferred":[
        "Hujiapu"
    ],
    "name:zho_x_variant":[
        "\u80e1\u5bb6\u94fa"
    ],
    "wof:name":"Hujiapu",
    "wof:placetype":"locality"
},
  "geometry": {"coordinates":[115.32886999999999,30.16859],"type":"Point"}
}