{
  "type": "Feature",
  "properties": {
    "gn:admin1_code":"16.0",
    "gn:asciiname":"Jianfeng",
    "gn:country_code":"CN",
    "gn:dem":128,
    "gn:feature_class":"P",
    "gn:feature_code":"PPL",
    "gn:name":"Jianfeng",
    "gn:population":0,
    "gn:timezone":"Asia/Shanghai",
    "iso:country":"CN",
    "name:zho_x_preferred":[
        "\u5efa\u4e30"
    ],
    "wof:name":"Jianfeng",
    "wof:placetype":"locality"
},
  "geometry": {"coordinates":[108.128,23.076],"type":"Point"}
}