{
  "type": "Feature",
  "properties": {
    "gn:admin1_code":"2.0",
    "gn:asciiname":"Panjia",
    "gn:country_code":"CN",
    "gn:dem":210,
    "gn:feature_class":"P",
    "gn:feature_code":"PPL",
    "gn:name":"Panjia",
    "gn:population":0,
    "gn:timezone":"Asia/Shanghai",
    "iso:country":"CN",
    "name:und_x_variant":[
        "\u6f58\u5bb6",
        "Panjia"
    ],
    "wof:name":"Panjia",
    "wof:placetype":"locality"
},
  "geometry": {"coordinates":[119.92601999999999,29.64827],"type":"Point"}
}