{
  "type": "Feature",
  "properties": {
    "gn:admin1_code":"32.0",
    "gn:asciiname":"Muzhuling",
    "gn:country_code":"CN",
    "gn:dem":1291,
    "gn:feature_class":"P",
    "gn:feature_code":"PPL",
    "gn:name":"Muzhuling",
    "gn:population":0,
    "gn:timezone":"Asia/Shanghai",
    "iso:country":"CN",
    "name:zho_x_preferred":[
        "\u6728\u7af9\u5cad"
    ],
    "wof:name":"Muzhuling",
    "wof:placetype":"locality"
},
  "geometry": {"coordinates":[106.86238,32.46201],"type":"Point"}
}