{
  "type": "Feature",
  "properties": {
    "gn:country":"CN",
    "gn:fcode":"PPL",
    "gn:pop":0,
    "iso:country":"CN",
    "name:unk_x_variant":[
        "Chen-ju-zhen"
    ],
    "qs:name":"\u771f\u5982",
    "qs:name_adm0":"\u4e2d\u570b",
    "qs:name_adm1":"\u4e0a\u6d77\u76f4\u8f96\u5e02",
    "qs:photos":69,
    "qs:photos_1k":14,
    "qs:photos_9k":1,
    "qs:photos_9r":2,
    "qs:photos_all":69,
    "qs:photos_sr":2,
    "qs:placetype":"Suburb",
    "qs:pop_sr":"0",
    "wof:name":"\u771f\u5982",
    "wof:placetype":"neighbourhood",
    "wof:population":0
},
  "geometry": {"coordinates":[121.39194000000001,31.24722],"type":"Point"}
}