{
  "type": "Feature",
  "properties": {
    "gn:admin1_code":"15.0",
    "gn:asciiname":"Xiacaoba",
    "gn:country_code":"CN",
    "gn:dem":2136,
    "gn:feature_class":"P",
    "gn:feature_code":"PPL",
    "gn:name":"Xiacaoba",
    "gn:population":0,
    "gn:timezone":"Asia/Shanghai",
    "iso:country":"CN",
    "name:und_x_variant":[
        "\u4e0b\u8349\u575d"
    ],
    "wof:name":"Xiacaoba",
    "wof:placetype":"locality"
},
  "geometry": {"coordinates":[104.77809000000001,34.16869000000001],"type":"Point"}
}