{
  "type": "Feature",
  "properties": {
    "gn:admin1_code":"26.0",
    "gn:asciiname":"Laoling",
    "gn:country_code":"CN",
    "gn:dem":1422,
    "gn:feature_class":"P",
    "gn:feature_code":"PPL",
    "gn:name":"Laoling",
    "gn:population":0,
    "gn:timezone":"Asia/Shanghai",
    "iso:country":"CN",
    "name:zho_x_preferred":[
        "\u8001\u5cad"
    ],
    "wof:name":"Laoling",
    "wof:placetype":"locality"
},
  "geometry": {"coordinates":[110.24673,34.34435999999999],"type":"Point"}
}