{
  "type": "Feature",
  "properties": {
    "gn:admin1_code":"26.0",
    "gn:asciiname":"Laoling",
    "gn:country_code":"CN",
    "gn:dem":1422,
    "gn:feature_class":"P",
    "gn:feature_code":"PPL",
    "gn:name":"Laoling",
    "gn:population":0,
    "gn:timezone":"Asia/Shanghai",
    "iso:country":"CN",
    "name:ceb_x_preferred":[
        "Leling Shi"
    ],
    "name:deu_x_preferred":[
        "Laoling"
    ],
    "name:fra_x_preferred":[
        "Leling"
    ],
    "name:ind_x_preferred":[
        "Leling"
    ],
    "name:ita_x_preferred":[
        "Laoling"
    ],
    "name:jpn_x_preferred":[
        "\u697d\u9675\u5e02"
    ],
    "name:kik_x_preferred":[
        "Laoling"
    ],
    "name:kor_x_preferred":[
        "\ub77c\uc624\ub9c1\uc2dc"
    ],
    "name:nld_x_preferred":[
        "Leling"
    ],
    "name:nor_x_preferred":[
        "Leling"
    ],
    "name:rus_x_preferred":[
        "\u041b\u0430\u043e\u043b\u0438\u043d"
    ],
    "name:swe_x_preferred":[
        "Laoling"
    ],
    "name:vie_x_preferred":[
        "L\u1ea1c L\u0103ng"
    ],
    "name:war_x_preferred":[
        "Leling"
    ],
    "name:zho_x_preferred":[
        "\u8001\u5cad"
    ],
    "name:zho_x_variant":[
        "\u4e50\u9675\u5e02"
    ],
    "wof:name":"Laoling",
    "wof:placetype":"locality"
},
  "geometry": {"coordinates":[110.24673,34.34435999999999],"type":"Point"}
}