{
  "type": "Feature",
  "properties": {
    "gn:admin1_code":"19.0",
    "gn:asciiname":"Tujingzi",
    "gn:country_code":"CN",
    "gn:dem":74,
    "gn:feature_class":"P",
    "gn:feature_code":"PPL",
    "gn:name":"Tujingzi",
    "gn:population":0,
    "gn:timezone":"Asia/Shanghai",
    "iso:country":"CN",
    "name:und_x_variant":[
        "\u571f\u4e95\u5b50"
    ],
    "name:zho_x_preferred":[
        "\u571f\u4e95\u5b50"
    ],
    "wof:name":"Tujingzi",
    "wof:placetype":"locality"
},
  "geometry": {"coordinates":[123.28072,42.29747],"type":"Point"}
}