{
  "type": "Feature",
  "properties": {
    "gn:admin1_code":"26.0",
    "gn:asciiname":"Jianjiazui",
    "gn:country_code":"CN",
    "gn:dem":738,
    "gn:feature_class":"P",
    "gn:feature_code":"PPL",
    "gn:name":"Jianjiazui",
    "gn:population":0,
    "gn:timezone":"Asia/Shanghai",
    "iso:country":"CN",
    "name:und_x_variant":[
        "\u8e47\u5bb6\u5480"
    ],
    "wof:name":"Jianjiazui",
    "wof:placetype":"locality"
},
  "geometry": {"coordinates":[106.05222000000001,33.40764],"type":"Point"}
}