{
  "type": "Feature",
  "properties": {
    "gn:admin1_code":"26.0",
    "gn:asciiname":"Nanzhangjia Pingcun",
    "gn:country_code":"CN",
    "gn:dem":940,
    "gn:feature_class":"P",
    "gn:feature_code":"PPL",
    "gn:name":"Nanzhangjia Pingcun",
    "gn:population":0,
    "gn:timezone":"Asia/Shanghai",
    "iso:country":"CN",
    "name:zho_x_preferred":[
        "\u5357\u5f20\u5bb6\u576a\u6751"
    ],
    "wof:name":"Nanzhangjia Pingcun",
    "wof:placetype":"locality"
},
  "geometry": {"coordinates":[110.45399999999999,37.3842],"type":"Point"}
}