{
  "type": "Feature",
  "properties": {
    "gn:admin1_code":"3.0",
    "gn:asciiname":"Sanlitang",
    "gn:country_code":"CN",
    "gn:dem":113,
    "gn:feature_class":"P",
    "gn:feature_code":"PPL",
    "gn:name":"Sanlitang",
    "gn:population":0,
    "gn:timezone":"Asia/Shanghai",
    "iso:country":"CN",
    "name:und_x_variant":[
        "\u4e09\u91cc\u5858"
    ],
    "wof:name":"Sanlitang",
    "wof:placetype":"locality"
},
  "geometry": {"coordinates":[115.06171999999999,29.49374000000001],"type":"Point"}
}