{
  "type": "Feature",
  "properties": {
    "gn:admin1_code":"8.0",
    "gn:asciiname":"Nandian",
    "gn:country_code":"CN",
    "gn:dem":203,
    "gn:feature_class":"P",
    "gn:feature_code":"PPL",
    "gn:name":"Nandian",
    "gn:population":0,
    "gn:timezone":"Asia/Shanghai",
    "iso:country":"CN",
    "name:zho_x_preferred":[
        "\u5357\u5e97"
    ],
    "name:zho_x_variant":[
        "\u5357\u7538\u9547"
    ],
    "wof:name":"Nandian",
    "wof:placetype":"locality"
},
  "geometry": {"coordinates":[126.6688,47.42674],"type":"Point"}
}