{
  "type": "Feature",
  "properties": {
    "gn:admin1_code":"11.0",
    "gn:asciiname":"Qimuwan",
    "gn:country_code":"CN",
    "gn:dem":263,
    "gn:feature_class":"P",
    "gn:feature_code":"PPL",
    "gn:name":"Qimuwan",
    "gn:population":0,
    "gn:timezone":"Asia/Shanghai",
    "iso:country":"CN",
    "name:zho_x_preferred":[
        "\u4e03\u4ea9\u6e7e"
    ],
    "wof:name":"Qimuwan",
    "wof:placetype":"locality"
},
  "geometry": {"coordinates":[112.30513000000001,27.90962],"type":"Point"}
}