{
  "type": "Feature",
  "properties": {
    "gn:admin1_code":"12.0",
    "gn:asciiname":"Tongcaoping",
    "gn:country_code":"CN",
    "gn:dem":780,
    "gn:feature_class":"P",
    "gn:feature_code":"PPL",
    "gn:name":"Tongcaoping",
    "gn:population":0,
    "gn:timezone":"Asia/Shanghai",
    "iso:country":"CN",
    "name:zho_x_preferred":[
        "Tongcaoping"
    ],
    "name:zho_x_variant":[
        "\u901a\u8349\u576a"
    ],
    "wof:name":"Tongcaoping",
    "wof:placetype":"locality"
},
  "geometry": {"coordinates":[110.31281,29.99838],"type":"Point"}
}