{
  "type": "Feature",
  "properties": {
    "gn:admin1_code":"24.0",
    "gn:asciiname":"Zhaoyuantou",
    "gn:country_code":"CN",
    "gn:dem":955,
    "gn:feature_class":"P",
    "gn:feature_code":"PPL",
    "gn:name":"Zhaoyuantou",
    "gn:population":0,
    "gn:timezone":"Asia/Shanghai",
    "iso:country":"CN",
    "name:zho_x_preferred":[
        "\u8d75\u5143\u5934"
    ],
    "wof:name":"Zhaoyuantou",
    "wof:placetype":"locality"
},
  "geometry": {"coordinates":[111.17932999999999,39.11741],"type":"Point"}
}