{
  "type": "Feature",
  "properties": {
    "gn:admin1_code":"16.0",
    "gn:asciiname":"Jiudongtang",
    "gn:country_code":"CN",
    "gn:dem":155,
    "gn:feature_class":"P",
    "gn:feature_code":"PPL",
    "gn:name":"Jiudongtang",
    "gn:population":0,
    "gn:timezone":"Asia/Shanghai",
    "iso:country":"CN",
    "name:zho_x_preferred":[
        "\u4e5d\u51ac\u5858"
    ],
    "wof:name":"Jiudongtang",
    "wof:placetype":"locality"
},
  "geometry": {"coordinates":[108.79300000000001,22.3915],"type":"Point"}
}