{
  "type": "Feature",
  "properties": {
    "gn:admin1_code":"15.0",
    "gn:asciiname":"Majia Xipo",
    "gn:country_code":"CN",
    "gn:dem":2056,
    "gn:feature_class":"P",
    "gn:feature_code":"PPL",
    "gn:name":"Majia Xipo",
    "gn:population":0,
    "gn:timezone":"Asia/Shanghai",
    "iso:country":"CN",
    "name:zho_x_preferred":[
        "\u9a6c\u5bb6\u897f\u5761"
    ],
    "wof:name":"Majia Xipo",
    "wof:placetype":"locality"
},
  "geometry": {"coordinates":[104.691,36.2576],"type":"Point"}
}