{
  "type": "Feature",
  "properties": {
    "gn:admin1_code":"26.0",
    "gn:asciiname":"Liuxishan",
    "gn:country_code":"CN",
    "gn:dem":1107,
    "gn:feature_class":"P",
    "gn:feature_code":"PPL",
    "gn:name":"Liuxishan",
    "gn:population":0,
    "gn:timezone":"Asia/Shanghai",
    "iso:country":"CN",
    "name:zho_x_preferred":[
        "\u5218\u897f\u5c71"
    ],
    "wof:name":"Liuxishan",
    "wof:placetype":"locality"
},
  "geometry": {"coordinates":[109.81194000000001,37.86556],"type":"Point"}
}