{
  "type": "Feature",
  "properties": {
    "gn:admin1_code":"18",
    "gn:asciiname":"Chengmendong",
    "gn:country_code":"CN",
    "gn:dem":819,
    "gn:feature_class":"P",
    "gn:feature_code":"PPL",
    "gn:name":"Chengmendong",
    "gn:population":0,
    "gn:timezone":"Asia/Shanghai",
    "iso:country":"CN",
    "name:zho_x_preferred":[
        "\u57ce\u95e8\u6d1e"
    ],
    "wof:name":"Chengmendong",
    "wof:placetype":"locality"
},
  "geometry": {"coordinates":[105.965,28.4835],"type":"Point"}
}