{
  "type": "Feature",
  "properties": {
    "gn:admin1_code":"32.0",
    "gn:asciiname":"Caiguo",
    "gn:country_code":"CN",
    "gn:dem":4146,
    "gn:feature_class":"P",
    "gn:feature_code":"PPL",
    "gn:name":"Caiguo",
    "gn:population":0,
    "gn:timezone":"Asia/Shanghai",
    "iso:country":"CN",
    "name:zho_x_preferred":[
        "\u83dc\u679c"
    ],
    "wof:name":"Caiguo",
    "wof:placetype":"locality"
},
  "geometry": {"coordinates":[97.6645,32.5864],"type":"Point"}
}