{
  "type": "Feature",
  "properties": {
    "gn:admin1_code":"10",
    "gn:asciiname":"Guangliangwa",
    "gn:country_code":"CN",
    "gn:dem":1188,
    "gn:feature_class":"P",
    "gn:feature_code":"PPL",
    "gn:name":"Guangliangwa",
    "gn:population":0,
    "gn:timezone":"Asia/Shanghai",
    "iso:country":"CN",
    "name:zho_x_preferred":[
        "\u5149\u6881\u6d3c"
    ],
    "wof:name":"Guangliangwa",
    "wof:placetype":"locality"
},
  "geometry": {"coordinates":[115.64188,40.61372],"type":"Point"}
}