{
  "type": "Feature",
  "properties": {
    "gn:admin1_code":"15.0",
    "gn:asciiname":"Lanxinzhuang",
    "gn:country_code":"CN",
    "gn:dem":1669,
    "gn:feature_class":"P",
    "gn:feature_code":"PPL",
    "gn:name":"Lanxinzhuang",
    "gn:population":0,
    "gn:timezone":"Asia/Shanghai",
    "iso:country":"CN",
    "name:und_x_variant":[
        "\u5170\u65b0\u5e84"
    ],
    "wof:name":"Lanxinzhuang",
    "wof:placetype":"locality"
},
  "geometry": {"coordinates":[106.80418,36.86746],"type":"Point"}
}