{
  "type": "Feature",
  "properties": {
    "gn:admin1_code":"7",
    "gn:asciiname":"Shanbian",
    "gn:country_code":"CN",
    "gn:dem":811,
    "gn:feature_class":"P",
    "gn:feature_code":"PPL",
    "gn:name":"Shanbian",
    "gn:population":0,
    "gn:timezone":"Asia/Shanghai",
    "iso:country":"CN",
    "name:und_x_variant":[
        "\u5c71\u8fb9"
    ],
    "wof:name":"Shanbian",
    "wof:placetype":"locality"
},
  "geometry": {"coordinates":[119.55353999999998,27.49998],"type":"Point"}
}