{
  "type": "Feature",
  "properties": {
    "gn:admin1_code":"19.0",
    "gn:asciiname":"Linjia Wopeng",
    "gn:country_code":"CN",
    "gn:dem":12,
    "gn:feature_class":"P",
    "gn:feature_code":"PPL",
    "gn:name":"Linjia Wopeng",
    "gn:population":0,
    "gn:timezone":"Asia/Shanghai",
    "iso:country":"CN",
    "name:zho_x_preferred":[
        "\u6797\u5bb6\u7a9d\u68da"
    ],
    "wof:name":"Linjia Wopeng",
    "wof:placetype":"locality"
},
  "geometry": {"coordinates":[122.91800000000001,41.2634],"type":"Point"}
}