{
  "type": "Feature",
  "properties": {
    "gn:admin1_code":"19.0",
    "gn:asciiname":"Zhuanshanzicun",
    "gn:country_code":"CN",
    "gn:dem":64,
    "gn:feature_class":"P",
    "gn:feature_code":"PPL",
    "gn:name":"Zhuanshanzicun",
    "gn:population":0,
    "gn:timezone":"Asia/Shanghai",
    "iso:country":"CN",
    "name:zho_x_preferred":[
        "\u8f6c\u5c71\u5b50\u6751"
    ],
    "wof:name":"Zhuanshanzicun",
    "wof:placetype":"locality"
},
  "geometry": {"coordinates":[123.13399,42.45096],"type":"Point"}
}