{
  "type": "Feature",
  "properties": {
    "gn:admin1_code":"13.0",
    "gn:asciiname":"Karayulgun",
    "gn:cc2":"CN",
    "gn:country_code":"CN",
    "gn:dem":908,
    "gn:feature_class":"P",
    "gn:feature_code":"PPL",
    "gn:name":"Karayulgun",
    "gn:population":0,
    "gn:timezone":"Asia/Urumqi",
    "iso:country":"CN",
    "name:uig_x_preferred":[
        "K\u0329arayul\u01a3un"
    ],
    "name:uig_x_variant":[
        "Qarayulghun",
        "\u0642\u0627\u0631\u0627\u064a\u06c7\u0644\u063a\u06c7\u0646",
        "\u049a\u0430\u0440\u0430\u044e\u043b\u0493\u0443\u043d"
    ],
    "name:und_x_variant":[
        "Karayulgun Xiang",
        "Karayulgun"
    ],
    "wof:name":"Karayulgun",
    "wof:placetype":"locality"
},
  "geometry": {"coordinates":[86.05444,41.59806],"type":"Point"}
}