{
  "type": "Feature",
  "properties": {
    "gn:admin1_code":"03",
    "gn:asciiname":"Pengze",
    "gn:cc2":"CN",
    "gn:country_code":"CN",
    "gn:dem":51,
    "gn:feature_class":"P",
    "gn:feature_code":"PPL",
    "gn:name":"Pengze",
    "gn:population":0,
    "gn:timezone":"Asia/Shanghai",
    "iso:country":"CN",
    "name:und_x_variant":[
        "P\u2019eng-tse",
        "P\u2019eng-tse-hsien",
        "Pengtseh-hsien",
        "Pengtsch",
        "P\u2019eng-tse-hsien-ch\u2019eng",
        "Pengze",
        "Pengtseh",
        "Pang-tsis Hien"
    ],
    "wof:name":"Pengze",
    "wof:placetype":"locality"
},
  "geometry": {"coordinates":[116.54572,29.89885],"type":"Point"}
}