{
  "type": "Feature",
  "properties": {
    "gn:admin1_code":"03",
    "gn:asciiname":"Pengze",
    "gn:cc2":"CN",
    "gn:country_code":"CN",
    "gn:dem":51,
    "gn:feature_class":"P",
    "gn:feature_code":"PPL",
    "gn:name":"Pengze",
    "gn:population":0,
    "gn:timezone":"Asia/Shanghai",
    "iso:country":"CN",
    "name:deu_x_preferred":[
        "Pengze"
    ],
    "name:fas_x_preferred":[
        "\u0634\u0647\u0631\u0633\u062a\u0627\u0646 \u067e\u0646\u06af\u0632\u0647"
    ],
    "name:jpn_x_preferred":[
        "\u5f6d\u6ca2\u770c"
    ],
    "name:kor_x_preferred":[
        "\ud391\uca4c\ud604"
    ],
    "name:nor_x_preferred":[
        "Pengze"
    ],
    "name:swe_x_preferred":[
        "Pengze"
    ],
    "name:und_x_variant":[
        "P\u2019eng-tse",
        "P\u2019eng-tse-hsien",
        "Pengtseh-hsien",
        "Pengtsch",
        "P\u2019eng-tse-hsien-ch\u2019eng",
        "Pengze",
        "Pengtseh",
        "Pang-tsis Hien"
    ],
    "name:vie_x_preferred":[
        "B\u00e0nh Tr\u1ea1ch"
    ],
    "name:zho_x_preferred":[
        "\u5f6d\u6cfd\u53bf"
    ],
    "wof:name":"Pengze",
    "wof:placetype":"locality"
},
  "geometry": {"coordinates":[116.54572,29.89885],"type":"Point"}
}