{
  "type": "Feature",
  "properties": {
    "gn:admin1_code":"15.0",
    "gn:asciiname":"Liming",
    "gn:country_code":"CN",
    "gn:dem":1514,
    "gn:feature_class":"P",
    "gn:feature_code":"PPL",
    "gn:name":"Liming",
    "gn:population":0,
    "gn:timezone":"Asia/Shanghai",
    "iso:country":"CN",
    "name:ceb_x_preferred":[
        "Liming"
    ],
    "name:deu_x_preferred":[
        "Liming"
    ],
    "name:swe_x_preferred":[
        "Liming"
    ],
    "name:zho_x_preferred":[
        "\u9ece\u660e"
    ],
    "wof:name":"Liming",
    "wof:placetype":"locality"
},
  "geometry": {"coordinates":[106.61799999999999,35.2383],"type":"Point"}
}