{
  "type": "Feature",
  "properties": {
    "gn:admin1_code":"20",
    "gn:asciiname":"Dashuwan",
    "gn:cc2":"CN",
    "gn:country_code":"CN",
    "gn:dem":1003,
    "gn:feature_class":"P",
    "gn:feature_code":"PPL",
    "gn:name":"Dashuwan",
    "gn:population":0,
    "gn:timezone":"Asia/Shanghai",
    "iso:country":"CN",
    "name:und_x_variant":[
        "Ta-shu-wan",
        "Dashuwan"
    ],
    "wof:name":"Dashuwan",
    "wof:placetype":"locality"
},
  "geometry": {"coordinates":[109.96056000000002,40.48722],"type":"Point"}
}