{
  "type": "Feature",
  "properties": {
    "gn:admin1_code":"09",
    "gn:asciiname":"Luyimiao",
    "gn:cc2":"CN",
    "gn:country_code":"CN",
    "gn:dem":221,
    "gn:feature_class":"P",
    "gn:feature_code":"PPL",
    "gn:name":"Luyimiao",
    "gn:population":0,
    "gn:timezone":"Asia/Shanghai",
    "iso:country":"CN",
    "name:und_x_variant":[
        "Lu-i-miao",
        "Luyimiao"
    ],
    "wof:name":"Luyimiao",
    "wof:placetype":"locality"
},
  "geometry": {"coordinates":[112.05,33.11667],"type":"Point"}
}