{
  "type": "Feature",
  "properties": {
    "gn:admin1_code":"32.0",
    "gn:asciiname":"Jialinggang",
    "gn:country_code":"CN",
    "gn:dem":434,
    "gn:feature_class":"P",
    "gn:feature_code":"PPL",
    "gn:name":"Jialinggang",
    "gn:population":0,
    "gn:timezone":"Asia/Shanghai",
    "iso:country":"CN",
    "name:zho_x_preferred":[
        "\u8d3e\u5cad\u5c97"
    ],
    "wof:name":"Jialinggang",
    "wof:placetype":"locality"
},
  "geometry": {"coordinates":[105.68899999999999,31.2964],"type":"Point"}
}