{
  "type": "Feature",
  "properties": {
    "gn:admin1_code":"30",
    "gn:asciiname":"Dongjian",
    "gn:country_code":"CN",
    "gn:dem":30,
    "gn:feature_class":"P",
    "gn:feature_code":"PPLA4",
    "gn:name":"Dongjian",
    "gn:population":0,
    "gn:timezone":"Asia/Urumqi",
    "iso:country":"CN",
    "name:und_x_variant":[
        "\u4e1c\u7b80",
        "Dongjian",
        "Dongjian Zhen",
        "\u4e1c\u7b80\u9547"
    ],
    "wof:name":"Dongjian",
    "wof:placetype":"locality"
},
  "geometry": {"coordinates":[110.49542,21.03658],"type":"Point"}
}