{
  "type": "Feature",
  "properties": {
    "gn:admin1_code":"18",
    "gn:asciiname":"Longchang",
    "gn:country_code":"CN",
    "gn:dem":1227,
    "gn:feature_class":"P",
    "gn:feature_code":"PPL",
    "gn:name":"Longchang",
    "gn:population":0,
    "gn:timezone":"Asia/Shanghai",
    "iso:country":"CN",
    "name:zho_x_preferred":[
        "\u9f99\u573a"
    ],
    "wof:name":"Longchang",
    "wof:placetype":"locality"
},
  "geometry": {"coordinates":[105.48399999999999,25.8061],"type":"Point"}
}