{
  "type": "Feature",
  "properties": {
    "gn:admin1_code":"12.0",
    "gn:asciiname":"Tangjiawudahu",
    "gn:country_code":"CN",
    "gn:dem":28,
    "gn:feature_class":"P",
    "gn:feature_code":"PPL",
    "gn:name":"Tangjiawudahu",
    "gn:population":0,
    "gn:timezone":"Asia/Shanghai",
    "iso:country":"CN",
    "name:zho_x_preferred":[
        "\u5510\u5bb6\u4e94\u5927\u6237"
    ],
    "wof:name":"Tangjiawudahu",
    "wof:placetype":"locality"
},
  "geometry": {"coordinates":[112.66621000000001,29.92888],"type":"Point"}
}