{
  "type": "Feature",
  "properties": {
    "gn:admin1_code":"23.0",
    "gn:asciiname":"Dahong",
    "gn:country_code":"CN",
    "gn:dem":4,
    "gn:feature_class":"P",
    "gn:feature_code":"PPL",
    "gn:name":"Dahong",
    "gn:population":0,
    "gn:timezone":"Asia/Shanghai",
    "iso:country":"CN",
    "name:zho_x_preferred":[
        "Dahong"
    ],
    "name:zho_x_variant":[
        "\u5927\u6d2a"
    ],
    "wof:name":"Dahong",
    "wof:placetype":"locality"
},
  "geometry": {"coordinates":[121.73048,31.19201],"type":"Point"}
}