{
  "type": "Feature",
  "properties": {
    "gn:admin1_code":"29.0",
    "gn:asciiname":"Kaya",
    "gn:country_code":"CN",
    "gn:dem":1723,
    "gn:feature_class":"P",
    "gn:feature_code":"PPL",
    "gn:name":"Kaya",
    "gn:population":0,
    "gn:timezone":"Asia/Shanghai",
    "iso:country":"CN",
    "name:bel_x_preferred":[
        "\u041a\u0430\u044f"
    ],
    "name:ceb_x_preferred":[
        "Kaya"
    ],
    "name:deu_x_preferred":[
        "Kaya"
    ],
    "name:fra_x_preferred":[
        "Kaya"
    ],
    "name:heb_x_preferred":[
        "\u05e7\u05d0\u05d9\u05d4"
    ],
    "name:hun_x_preferred":[
        "Kaya"
    ],
    "name:ind_x_preferred":[
        "Kaya"
    ],
    "name:ita_x_preferred":[
        "Kaya"
    ],
    "name:jpn_x_preferred":[
        "\u30ab\u30e4"
    ],
    "name:kaz_x_preferred":[
        "\u041a\u0430\u044f"
    ],
    "name:msa_x_preferred":[
        "Kaya"
    ],
    "name:nld_x_preferred":[
        "Kaya"
    ],
    "name:nor_x_preferred":[
        "Kaya"
    ],
    "name:pol_x_preferred":[
        "Kaya"
    ],
    "name:por_x_preferred":[
        "Kaya"
    ],
    "name:rus_x_preferred":[
        "\u041a\u0430\u044f"
    ],
    "name:spa_x_preferred":[
        "Kaya"
    ],
    "name:srp_x_preferred":[
        "\u041a\u0430\u0458\u0430"
    ],
    "name:swe_x_preferred":[
        "Kaya"
    ],
    "name:ukr_x_preferred":[
        "\u041a\u0430\u044f"
    ],
    "name:zho_x_preferred":[
        "\u5361\u7259"
    ],
    "wof:name":"Kaya",
    "wof:placetype":"locality"
},
  "geometry": {"coordinates":[97.7907,24.7017],"type":"Point"}
}