{
  "type": "Feature",
  "properties": {
    "gn:admin1_code":"26",
    "gn:asciiname":"Shishucun",
    "gn:country_code":"CN",
    "gn:dem":420,
    "gn:feature_class":"P",
    "gn:feature_code":"PPL",
    "gn:name":"Shishucun",
    "gn:population":0,
    "gn:timezone":"Asia/Shanghai",
    "iso:country":"CN",
    "name:und_x_variant":[
        "\u67ff\u6811\u6751",
        "Shishucun"
    ],
    "wof:name":"Shishucun",
    "wof:placetype":"locality"
},
  "geometry": {"coordinates":[109.10382,34.68169],"type":"Point"}
}