{
  "type": "Feature",
  "properties": {
    "gn:admin1_code":"19.0",
    "gn:asciiname":"Sandaogou",
    "gn:country_code":"CN",
    "gn:dem":156,
    "gn:feature_class":"P",
    "gn:feature_code":"PPL",
    "gn:name":"Sandaogou",
    "gn:population":0,
    "gn:timezone":"Asia/Shanghai",
    "iso:country":"CN",
    "name:und_x_variant":[
        "\u4e09\u9053\u6c9f"
    ],
    "name:zho_x_preferred":[
        "\u4e09\u9053\u6c9f"
    ],
    "wof:name":"Sandaogou",
    "wof:placetype":"locality"
},
  "geometry": {"coordinates":[124.58176,40.45157],"type":"Point"}
}