{
  "type": "Feature",
  "properties": {
    "gn:admin1_code":"29.0",
    "gn:asciiname":"Xialuga",
    "gn:country_code":"CN",
    "gn:dem":1611,
    "gn:feature_class":"P",
    "gn:feature_code":"PPL",
    "gn:name":"Xialuga",
    "gn:population":0,
    "gn:timezone":"Asia/Shanghai",
    "iso:country":"CN",
    "name:zho_x_preferred":[
        "\u4e0b\u9c81\u560e"
    ],
    "wof:name":"Xialuga",
    "wof:placetype":"locality"
},
  "geometry": {"coordinates":[103.413,23.1335],"type":"Point"}
}