{
  "type": "Feature",
  "properties": {
    "gn:admin1_code":"11.0",
    "gn:asciiname":"Liangwandong",
    "gn:country_code":"CN",
    "gn:dem":315,
    "gn:feature_class":"P",
    "gn:feature_code":"PPL",
    "gn:name":"Liangwandong",
    "gn:population":0,
    "gn:timezone":"Asia/Shanghai",
    "iso:country":"CN",
    "name:zho_x_preferred":[
        "\u4e24\u6e7e\u6d1e"
    ],
    "wof:name":"Liangwandong",
    "wof:placetype":"locality"
},
  "geometry": {"coordinates":[113.0384,25.57362],"type":"Point"}
}