{
  "type": "Feature",
  "properties": {
    "gn:admin1_code":"12.0",
    "gn:asciiname":"Chengdegang",
    "gn:country_code":"CN",
    "gn:dem":48,
    "gn:feature_class":"P",
    "gn:feature_code":"PPL",
    "gn:name":"Chengdegang",
    "gn:population":0,
    "gn:timezone":"Asia/Shanghai",
    "iso:country":"CN",
    "name:zho_x_preferred":[
        "Chengdegang"
    ],
    "name:zho_x_variant":[
        "\u7a0b\u5fb7\u5c97"
    ],
    "wof:name":"Chengdegang",
    "wof:placetype":"locality"
},
  "geometry": {"coordinates":[115.0502,30.63177],"type":"Point"}
}