{
  "type": "Feature",
  "properties": {
    "gn:admin1_code":"2.0",
    "gn:asciiname":"Meijia",
    "gn:country_code":"CN",
    "gn:dem":304,
    "gn:feature_class":"P",
    "gn:feature_code":"PPL",
    "gn:name":"Meijia",
    "gn:population":0,
    "gn:timezone":"Asia/Shanghai",
    "iso:country":"CN",
    "name:und_x_variant":[
        "\u6885\u5bb6"
    ],
    "wof:name":"Meijia",
    "wof:placetype":"locality"
},
  "geometry": {"coordinates":[119.50678000000001,30.33148],"type":"Point"}
}