{
  "type": "Feature",
  "properties": {
    "gn:admin1_code":"18",
    "gn:asciiname":"Lanbazi",
    "gn:country_code":"CN",
    "gn:dem":1217,
    "gn:feature_class":"P",
    "gn:feature_code":"PPL",
    "gn:name":"Lanbazi",
    "gn:population":0,
    "gn:timezone":"Asia/Shanghai",
    "iso:country":"CN",
    "name:zho_x_preferred":[
        "\u70c2\u575d\u5b50"
    ],
    "wof:name":"Lanbazi",
    "wof:placetype":"locality"
},
  "geometry": {"coordinates":[106.03400000000001,27.5809],"type":"Point"}
}