{
  "type": "Feature",
  "properties": {
    "gn:admin1_code":"9.0",
    "gn:asciiname":"Shangzhuanchong",
    "gn:country_code":"CN",
    "gn:dem":216,
    "gn:feature_class":"P",
    "gn:feature_code":"PPL",
    "gn:name":"Shangzhuanchong",
    "gn:population":0,
    "gn:timezone":"Asia/Shanghai",
    "iso:country":"CN",
    "name:zho_x_preferred":[
        "\u4e0a\u8d5a\u51b2"
    ],
    "wof:name":"Shangzhuanchong",
    "wof:placetype":"locality"
},
  "geometry": {"coordinates":[115.26666000000002,31.59412],"type":"Point"}
}