{
  "type": "Feature",
  "properties": {
    "gn:admin1_code":"7.0",
    "gn:asciiname":"Meixi",
    "gn:country_code":"CN",
    "gn:dem":435,
    "gn:feature_class":"P",
    "gn:feature_code":"PPL",
    "gn:name":"Meixi",
    "gn:population":0,
    "gn:timezone":"Asia/Shanghai",
    "iso:country":"CN",
    "name:und_x_variant":[
        "\u6885\u6eaa"
    ],
    "name:zho_x_preferred":[
        "\u6885\u6eaa"
    ],
    "wof:name":"Meixi",
    "wof:placetype":"locality"
},
  "geometry": {"coordinates":[117.27495999999999,26.90239],"type":"Point"}
}