{
  "type": "Feature",
  "properties": {
    "gn:admin1_code":"29.0",
    "gn:asciiname":"Xiadawan",
    "gn:country_code":"CN",
    "gn:dem":1730,
    "gn:feature_class":"P",
    "gn:feature_code":"PPL",
    "gn:name":"Xiadawan",
    "gn:population":0,
    "gn:timezone":"Asia/Shanghai",
    "iso:country":"CN",
    "name:zho_x_preferred":[
        "\u4e0b\u5927\u6e7e"
    ],
    "wof:name":"Xiadawan",
    "wof:placetype":"locality"
},
  "geometry": {"coordinates":[100.43899999999999,27.5576],"type":"Point"}
}