{
  "type": "Feature",
  "properties": {
    "gn:admin1_code":"4.0",
    "gn:asciiname":"Shaduncun",
    "gn:country_code":"CN",
    "gn:dem":11,
    "gn:feature_class":"P",
    "gn:feature_code":"PPL",
    "gn:name":"Shaduncun",
    "gn:population":0,
    "gn:timezone":"Asia/Shanghai",
    "iso:country":"CN",
    "name:zho_x_preferred":[
        "\u6c99\u58a9\u6751"
    ],
    "wof:name":"Shaduncun",
    "wof:placetype":"locality"
},
  "geometry": {"coordinates":[119.04388,34.87293],"type":"Point"}
}