{
  "type": "Feature",
  "properties": {
    "gn:admin1_code":"9",
    "gn:asciiname":"Tangping",
    "gn:country_code":"CN",
    "gn:dem":617,
    "gn:feature_class":"P",
    "gn:feature_code":"PPL",
    "gn:name":"Tangping",
    "gn:population":0,
    "gn:timezone":"Asia/Shanghai",
    "iso:country":"CN",
    "name:zho_x_preferred":[
        "\u5802\u576a"
    ],
    "wof:name":"Tangping",
    "wof:placetype":"locality"
},
  "geometry": {"coordinates":[111.45169,33.62272],"type":"Point"}
}