{
  "type": "Feature",
  "properties": {
    "gn:admin1_code":"29.0",
    "gn:asciiname":"Miaogou",
    "gn:country_code":"CN",
    "gn:dem":1097,
    "gn:feature_class":"P",
    "gn:feature_code":"PPL",
    "gn:name":"Miaogou",
    "gn:population":0,
    "gn:timezone":"Asia/Shanghai",
    "iso:country":"CN",
    "name:und_x_variant":[
        "\u5e99\u6c9f"
    ],
    "wof:name":"Miaogou",
    "wof:placetype":"locality"
},
  "geometry": {"coordinates":[104.81820999999999,27.81592],"type":"Point"}
}