{
  "type": "Feature",
  "properties": {
    "gn:admin1_code":"9.0",
    "gn:asciiname":"Mairendian",
    "gn:country_code":"CN",
    "gn:dem":144,
    "gn:feature_class":"P",
    "gn:feature_code":"PPL",
    "gn:name":"Mairendian",
    "gn:population":0,
    "gn:timezone":"Asia/Shanghai",
    "iso:country":"CN",
    "name:zho_x_preferred":[
        "\u9ea6\u4ec1\u5e97"
    ],
    "wof:name":"Mairendian",
    "wof:placetype":"locality"
},
  "geometry": {"coordinates":[112.62272,33.20728],"type":"Point"}
}