{
  "type": "Feature",
  "properties": {
    "gn:admin1_code":"2.0",
    "gn:asciiname":"Jianxiaonong",
    "gn:country_code":"CN",
    "gn:dem":28,
    "gn:feature_class":"P",
    "gn:feature_code":"PPL",
    "gn:name":"Jianxiaonong",
    "gn:population":0,
    "gn:timezone":"Asia/Shanghai",
    "iso:country":"CN",
    "name:zho_x_preferred":[
        "\u7bad\u7b71\u5f04"
    ],
    "wof:name":"Jianxiaonong",
    "wof:placetype":"locality"
},
  "geometry": {"coordinates":[120.40089999999999,29.77175],"type":"Point"}
}