{
  "type": "Feature",
  "properties": {
    "gn:admin1_code":"12.0",
    "gn:asciiname":"Bianjie",
    "gn:country_code":"CN",
    "gn:dem":61,
    "gn:feature_class":"P",
    "gn:feature_code":"PPL",
    "gn:name":"Bianjie",
    "gn:population":0,
    "gn:timezone":"Asia/Shanghai",
    "iso:country":"CN",
    "name:zho_x_preferred":[
        "\u8fb9\u8857"
    ],
    "wof:name":"Bianjie",
    "wof:placetype":"locality"
},
  "geometry": {"coordinates":[115.74621999999999,30.2842],"type":"Point"}
}