{
  "type": "Feature",
  "properties": {
    "gn:admin1_code":"1.0",
    "gn:asciiname":"Xiangyangcun",
    "gn:country_code":"CN",
    "gn:dem":57,
    "gn:feature_class":"P",
    "gn:feature_code":"PPL",
    "gn:name":"Xiangyangcun",
    "gn:population":0,
    "gn:timezone":"Asia/Shanghai",
    "iso:country":"CN",
    "name:zho_x_preferred":[
        "\u5411\u9633\u6751"
    ],
    "wof:name":"Xiangyangcun",
    "wof:placetype":"locality"
},
  "geometry": {"coordinates":[116.88986,31.74449000000001],"type":"Point"}
}