{
  "type": "Feature",
  "properties": {
    "gn:admin1_code":"19.0",
    "gn:asciiname":"Xiaojiahecun",
    "gn:country_code":"CN",
    "gn:dem":162,
    "gn:feature_class":"P",
    "gn:feature_code":"PPL",
    "gn:name":"Xiaojiahecun",
    "gn:population":0,
    "gn:timezone":"Asia/Shanghai",
    "iso:country":"CN",
    "name:zho_x_preferred":[
        "\u8096\u5bb6\u6cb3\u6751"
    ],
    "wof:name":"Xiaojiahecun",
    "wof:placetype":"locality"
},
  "geometry": {"coordinates":[123.92019999999999,41.44964],"type":"Point"}
}