{
  "type": "Feature",
  "properties": {
    "gn:admin1_code":"1.0",
    "gn:asciiname":"Shili",
    "gn:country_code":"CN",
    "gn:dem":49,
    "gn:feature_class":"P",
    "gn:feature_code":"PPL",
    "gn:name":"Shili",
    "gn:population":0,
    "gn:timezone":"Asia/Shanghai",
    "iso:country":"CN",
    "name:ara_x_preferred":[
        "\u0634\u064a\u0644\u064a"
    ],
    "name:fas_x_preferred":[
        "\u0634\u06cc\u0644\u06cc"
    ],
    "name:msa_x_preferred":[
        "Shili"
    ],
    "name:und_x_variant":[
        "\u5341\u91cc",
        "\u5341\u91cc\u4e61"
    ],
    "name:zho_x_preferred":[
        "Shilixiang"
    ],
    "wof:name":"Shili",
    "wof:placetype":"locality"
},
  "geometry": {"coordinates":[119.36905,30.90718],"type":"Point"}
}