{
  "type": "Feature",
  "properties": {
    "gn:admin1_code":"32.0",
    "gn:asciiname":"Laoshengyuan",
    "gn:country_code":"CN",
    "gn:dem":721,
    "gn:feature_class":"P",
    "gn:feature_code":"PPL",
    "gn:name":"Laoshengyuan",
    "gn:population":0,
    "gn:timezone":"Asia/Shanghai",
    "iso:country":"CN",
    "name:zho_x_preferred":[
        "\u8001\u751f\u5143"
    ],
    "wof:name":"Laoshengyuan",
    "wof:placetype":"locality"
},
  "geometry": {"coordinates":[108.09511000000001,31.80872],"type":"Point"}
}