{
  "type": "Feature",
  "properties": {
    "gn:admin1_code":"18.0",
    "gn:asciiname":"Guizheng",
    "gn:country_code":"CN",
    "gn:dem":495,
    "gn:feature_class":"P",
    "gn:feature_code":"PPL",
    "gn:name":"Guizheng",
    "gn:population":0,
    "gn:timezone":"Asia/Shanghai",
    "iso:country":"CN",
    "name:zho_x_preferred":[
        "\u89c4\u6b63"
    ],
    "wof:name":"Guizheng",
    "wof:placetype":"locality"
},
  "geometry": {"coordinates":[109.274,26.1537],"type":"Point"}
}