{
  "type": "Feature",
  "properties": {
    "gn:admin1_code":"4.0",
    "gn:asciiname":"Jixiaoyuan",
    "gn:country_code":"CN",
    "gn:dem":8,
    "gn:feature_class":"P",
    "gn:feature_code":"PPL",
    "gn:name":"Jixiaoyuan",
    "gn:population":0,
    "gn:timezone":"Asia/Shanghai",
    "iso:country":"CN",
    "name:zho_x_preferred":[
        "Jixiaoyuan"
    ],
    "name:zho_x_variant":[
        "\u5b63\u5c0f\u56ed"
    ],
    "wof:name":"Jixiaoyuan",
    "wof:placetype":"locality"
},
  "geometry": {"coordinates":[119.15973,33.93697],"type":"Point"}
}