{
  "type": "Feature",
  "properties": {
    "gn:admin1_code":"10.0",
    "gn:asciiname":"Daizhuang",
    "gn:country_code":"CN",
    "gn:dem":66,
    "gn:feature_class":"P",
    "gn:feature_code":"PPL",
    "gn:name":"Daizhuang",
    "gn:population":0,
    "gn:timezone":"Asia/Shanghai",
    "iso:country":"CN",
    "name:zho_x_preferred":[
        "\u4ee3\u5e84"
    ],
    "wof:name":"Daizhuang",
    "wof:placetype":"locality"
},
  "geometry": {"coordinates":[118.58806,39.88843],"type":"Point"}
}