{
  "type": "Feature",
  "properties": {
    "gn:admin1_code":"32.0",
    "gn:asciiname":"Rika",
    "gn:country_code":"CN",
    "gn:dem":3205,
    "gn:feature_class":"P",
    "gn:feature_code":"PPL",
    "gn:name":"Rika",
    "gn:population":0,
    "gn:timezone":"Asia/Shanghai",
    "iso:country":"CN",
    "name:ceb_x_preferred":[
        "Rika"
    ],
    "name:deu_x_preferred":[
        "Rika"
    ],
    "name:fra_x_preferred":[
        "Rika"
    ],
    "name:hrv_x_preferred":[
        "Rika"
    ],
    "name:ita_x_preferred":[
        "Rika"
    ],
    "name:nld_x_preferred":[
        "Rika"
    ],
    "name:rus_x_preferred":[
        "\u0420\u0438\u043a\u0430"
    ],
    "name:srp_x_preferred":[
        "\u0420\u0438\u043a\u0430"
    ],
    "name:swe_x_preferred":[
        "Rika"
    ],
    "name:zho_x_preferred":[
        "\u65e5\u5361"
    ],
    "wof:name":"Rika",
    "wof:placetype":"locality"
},
  "geometry": {"coordinates":[101.54300000000001,31.0507],"type":"Point"}
}