{
  "type": "Feature",
  "properties": {
    "gn:admin1_code":"32.0",
    "gn:asciiname":"Fengxiangtuo",
    "gn:country_code":"CN",
    "gn:dem":641,
    "gn:feature_class":"P",
    "gn:feature_code":"PPL",
    "gn:name":"Fengxiangtuo",
    "gn:population":0,
    "gn:timezone":"Asia/Shanghai",
    "iso:country":"CN",
    "name:und_x_variant":[
        "\u67ab\u9999\u6cb1"
    ],
    "wof:name":"Fengxiangtuo",
    "wof:placetype":"locality"
},
  "geometry": {"coordinates":[106.34985,32.42086],"type":"Point"}
}