{
  "type": "Feature",
  "properties": {
    "gn:admin1_code":"2.0",
    "gn:asciiname":"Renhuling",
    "gn:country_code":"CN",
    "gn:dem":393,
    "gn:feature_class":"P",
    "gn:feature_code":"PPL",
    "gn:name":"Renhuling",
    "gn:population":0,
    "gn:timezone":"Asia/Shanghai",
    "iso:country":"CN",
    "name:zho_x_preferred":[
        "\u4efb\u80e1\u5cad"
    ],
    "wof:name":"Renhuling",
    "wof:placetype":"locality"
},
  "geometry": {"coordinates":[120.87248,29.38463],"type":"Point"}
}