{
  "type": "Feature",
  "properties": {
    "gn:admin1_code":"32.0",
    "gn:asciiname":"Linziwan",
    "gn:country_code":"CN",
    "gn:dem":595,
    "gn:feature_class":"P",
    "gn:feature_code":"PPL",
    "gn:name":"Linziwan",
    "gn:population":0,
    "gn:timezone":"Asia/Shanghai",
    "iso:country":"CN",
    "name:zho_x_preferred":[
        "\u6797\u5b50\u6e7e"
    ],
    "wof:name":"Linziwan",
    "wof:placetype":"locality"
},
  "geometry": {"coordinates":[107.07899999999999,31.91800000000001],"type":"Point"}
}