{
  "type": "Feature",
  "properties": {
    "gn:admin1_code":"2.0",
    "gn:asciiname":"Chenbanshan",
    "gn:country_code":"CN",
    "gn:dem":503,
    "gn:feature_class":"P",
    "gn:feature_code":"PPL",
    "gn:name":"Chenbanshan",
    "gn:population":0,
    "gn:timezone":"Asia/Shanghai",
    "iso:country":"CN",
    "name:zho_x_preferred":[
        "\u9648\u534a\u5c71"
    ],
    "wof:name":"Chenbanshan",
    "wof:placetype":"locality"
},
  "geometry": {"coordinates":[118.97096999999999,27.95107],"type":"Point"}
}