{
  "type": "Feature",
  "properties": {
    "gn:admin1_code":"9.0",
    "gn:asciiname":"Shimengying",
    "gn:country_code":"CN",
    "gn:dem":44,
    "gn:feature_class":"P",
    "gn:feature_code":"PPL",
    "gn:name":"Shimengying",
    "gn:population":0,
    "gn:timezone":"Asia/Shanghai",
    "iso:country":"CN",
    "name:zho_x_preferred":[
        "\u53f2\u68a6\u8425"
    ],
    "wof:name":"Shimengying",
    "wof:placetype":"locality"
},
  "geometry": {"coordinates":[115.08157,33.6339],"type":"Point"}
}