{
  "type": "Feature",
  "properties": {
    "gn:admin1_code":"5.0",
    "gn:asciiname":"Houchang Shanbu",
    "gn:country_code":"CN",
    "gn:dem":147,
    "gn:feature_class":"P",
    "gn:feature_code":"PPL",
    "gn:name":"Houchang Shanbu",
    "gn:population":0,
    "gn:timezone":"Asia/Shanghai",
    "iso:country":"CN",
    "name:zho_x_preferred":[
        "\u540e\u957f\u5c71\u5821"
    ],
    "wof:name":"Houchang Shanbu",
    "wof:placetype":"locality"
},
  "geometry": {"coordinates":[122.84601000000001,45.11716],"type":"Point"}
}