{
  "type": "Feature",
  "properties": {
    "gn:admin1_code":"1.0",
    "gn:asciiname":"Liuyaopucun",
    "gn:country_code":"CN",
    "gn:dem":33,
    "gn:feature_class":"P",
    "gn:feature_code":"PPL",
    "gn:name":"Liuyaopucun",
    "gn:population":0,
    "gn:timezone":"Asia/Shanghai",
    "iso:country":"CN",
    "name:zho_x_preferred":[
        "\u5218\u836f\u94fa\u6751"
    ],
    "wof:name":"Liuyaopucun",
    "wof:placetype":"locality"
},
  "geometry": {"coordinates":[116.0942,33.13226],"type":"Point"}
}