{
  "type": "Feature",
  "properties": {
    "gn:admin1_code":"12.0",
    "gn:asciiname":"Songtang",
    "gn:country_code":"CN",
    "gn:dem":53,
    "gn:feature_class":"P",
    "gn:feature_code":"PPL",
    "gn:name":"Songtang",
    "gn:population":0,
    "gn:timezone":"Asia/Shanghai",
    "iso:country":"CN",
    "name:zho_x_preferred":[
        "Songtang"
    ],
    "name:zho_x_variant":[
        "\u5b8b\u5858"
    ],
    "wof:name":"Songtang",
    "wof:placetype":"locality"
},
  "geometry": {"coordinates":[115.50962,30.37039],"type":"Point"}
}