{
  "type": "Feature",
  "properties": {
    "gn:admin1_code":"8.0",
    "gn:asciiname":"Nuanquanzi",
    "gn:country_code":"CN",
    "gn:dem":729,
    "gn:feature_class":"P",
    "gn:feature_code":"PPL",
    "gn:name":"Nuanquanzi",
    "gn:population":0,
    "gn:timezone":"Asia/Shanghai",
    "iso:country":"CN",
    "name:und_x_variant":[
        "\u6696\u6cc9\u5b50"
    ],
    "wof:name":"Nuanquanzi",
    "wof:placetype":"locality"
},
  "geometry": {"coordinates":[131.02668,43.53785],"type":"Point"}
}