{
  "type": "Feature",
  "properties": {
    "gn:admin1_code":"19.0",
    "gn:asciiname":"Dai'erwancun",
    "gn:country_code":"CN",
    "gn:dem":8,
    "gn:feature_class":"P",
    "gn:feature_code":"PPL",
    "gn:name":"Dai\u2019erwancun",
    "gn:population":0,
    "gn:timezone":"Asia/Shanghai",
    "iso:country":"CN",
    "name:und_x_variant":[
        "Dai\u2019erwancun"
    ],
    "name:zho_x_preferred":[
        "\u4ee3\u8033\u6e7e\u6751"
    ],
    "wof:name":"Dai'erwancun",
    "wof:placetype":"locality"
},
  "geometry": {"coordinates":[122.82949000000001,41.30029],"type":"Point"}
}