{
  "type": "Feature",
  "properties": {
    "gn:admin1_code":"12.0",
    "gn:asciiname":"Bashi",
    "gn:country_code":"CN",
    "gn:dem":33,
    "gn:feature_class":"P",
    "gn:feature_code":"PPL",
    "gn:name":"Bashi",
    "gn:population":0,
    "gn:timezone":"Asia/Shanghai",
    "iso:country":"CN",
    "name:ceb_x_preferred":[
        "B\u0101sh\u012b"
    ],
    "name:fas_x_preferred":[
        "\u0628\u0627\u0634\u06cc"
    ],
    "name:msa_x_preferred":[
        "Bashi"
    ],
    "name:pol_x_preferred":[
        "Baszi"
    ],
    "name:swe_x_preferred":[
        "B\u0101sh\u012b"
    ],
    "name:zho_x_preferred":[
        "\u8019\u5e02"
    ],
    "wof:name":"Bashi",
    "wof:placetype":"locality"
},
  "geometry": {"coordinates":[113.09694,30.549],"type":"Point"}
}