{
  "type": "Feature",
  "properties": {
    "gn:admin1_code":"11.0",
    "gn:asciiname":"Nijiaolong",
    "gn:country_code":"CN",
    "gn:dem":943,
    "gn:feature_class":"P",
    "gn:feature_code":"PPL",
    "gn:name":"Nijiaolong",
    "gn:population":0,
    "gn:timezone":"Asia/Shanghai",
    "iso:country":"CN",
    "name:zho_x_preferred":[
        "\u576d\u811a\u5784"
    ],
    "wof:name":"Nijiaolong",
    "wof:placetype":"locality"
},
  "geometry": {"coordinates":[113.45668999999999,25.48267],"type":"Point"}
}