{
  "type": "Feature",
  "properties": {
    "gn:admin1_code":"15.0",
    "gn:asciiname":"Guanyinba",
    "gn:country_code":"CN",
    "gn:dem":1760,
    "gn:feature_class":"P",
    "gn:feature_code":"PPL",
    "gn:name":"Guanyinba",
    "gn:population":0,
    "gn:timezone":"Asia/Shanghai",
    "iso:country":"CN",
    "name:zho_x_preferred":[
        "\u89c2\u97f3\u575d"
    ],
    "wof:name":"Guanyinba",
    "wof:placetype":"locality"
},
  "geometry": {"coordinates":[104.74075999999999,33.0662],"type":"Point"}
}