{
  "type": "Feature",
  "properties": {
    "gn:admin1_code":"1.0",
    "gn:asciiname":"Jiaxucun",
    "gn:country_code":"CN",
    "gn:dem":56,
    "gn:feature_class":"P",
    "gn:feature_code":"PPL",
    "gn:name":"Jiaxucun",
    "gn:population":0,
    "gn:timezone":"Asia/Shanghai",
    "iso:country":"CN",
    "name:zho_x_preferred":[
        "\u8d3e\u5729\u6751"
    ],
    "wof:name":"Jiaxucun",
    "wof:placetype":"locality"
},
  "geometry": {"coordinates":[117.86074000000001,32.57966],"type":"Point"}
}