{
  "type": "Feature",
  "properties": {
    "gn:admin1_code":"12.0",
    "gn:asciiname":"Lashuyan",
    "gn:country_code":"CN",
    "gn:dem":147,
    "gn:feature_class":"P",
    "gn:feature_code":"PPL",
    "gn:name":"Lashuyan",
    "gn:population":0,
    "gn:timezone":"Asia/Shanghai",
    "iso:country":"CN",
    "name:zho_x_preferred":[
        "Lashuyan"
    ],
    "name:zho_x_variant":[
        "\u814a\u6811\u5830"
    ],
    "wof:name":"Lashuyan",
    "wof:placetype":"locality"
},
  "geometry": {"coordinates":[111.52616999999999,29.93874000000001],"type":"Point"}
}