{
  "type": "Feature",
  "properties": {
    "gn:admin1_code":"25",
    "gn:asciiname":"Longwantao",
    "gn:country_code":"CN",
    "gn:dem":142,
    "gn:feature_class":"P",
    "gn:feature_code":"PPL",
    "gn:name":"Longwantao",
    "gn:population":0,
    "gn:timezone":"Asia/Shanghai",
    "iso:country":"CN",
    "name:zho_x_preferred":[
        "\u9f99\u6e7e\u5957"
    ],
    "wof:name":"Longwantao",
    "wof:placetype":"locality"
},
  "geometry": {"coordinates":[117.29600000000001,35.5985],"type":"Point"}
}