{
  "type": "Feature",
  "properties": {
    "gn:admin1_code":"3",
    "gn:asciiname":"Xialongfeng",
    "gn:country_code":"CN",
    "gn:dem":260,
    "gn:feature_class":"P",
    "gn:feature_code":"PPL",
    "gn:name":"Xialongfeng",
    "gn:population":0,
    "gn:timezone":"Asia/Shanghai",
    "iso:country":"CN",
    "name:zho_x_preferred":[
        "\u4e0b\u9f99\u51e4"
    ],
    "wof:name":"Xialongfeng",
    "wof:placetype":"locality"
},
  "geometry": {"coordinates":[114.07599999999999,25.7005],"type":"Point"}
}