{
  "type": "Feature",
  "properties": {
    "gn:admin1_code":"2.0",
    "gn:asciiname":"Hengtang",
    "gn:country_code":"CN",
    "gn:dem":14,
    "gn:feature_class":"P",
    "gn:feature_code":"PPL",
    "gn:name":"Hengtang",
    "gn:population":0,
    "gn:timezone":"Asia/Shanghai",
    "iso:country":"CN",
    "name:und_x_variant":[
        "\u6a2a\u5858"
    ],
    "wof:name":"Hengtang",
    "wof:placetype":"locality"
},
  "geometry": {"coordinates":[119.69271999999999,30.74422],"type":"Point"}
}