{
  "type": "Feature",
  "properties": {
    "gn:admin1_code":"32.0",
    "gn:asciiname":"Wayaoping",
    "gn:country_code":"CN",
    "gn:dem":2241,
    "gn:feature_class":"P",
    "gn:feature_code":"PPL",
    "gn:name":"Wayaoping",
    "gn:population":0,
    "gn:timezone":"Asia/Shanghai",
    "iso:country":"CN",
    "name:zho_x_preferred":[
        "\u74e6\u7a91\u576a"
    ],
    "wof:name":"Wayaoping",
    "wof:placetype":"locality"
},
  "geometry": {"coordinates":[101.91,28.5707],"type":"Point"}
}