{
  "type": "Feature",
  "properties": {
    "gn:admin1_code":"5.0",
    "gn:asciiname":"Wanfatun",
    "gn:country_code":"CN",
    "gn:dem":216,
    "gn:feature_class":"P",
    "gn:feature_code":"PPL",
    "gn:name":"Wanfatun",
    "gn:population":0,
    "gn:timezone":"Asia/Shanghai",
    "iso:country":"CN",
    "name:zho_x_preferred":[
        "\u4e07\u53d1\u5c6f"
    ],
    "wof:name":"Wanfatun",
    "wof:placetype":"locality"
},
  "geometry": {"coordinates":[126.26595,44.88743],"type":"Point"}
}