{
  "type": "Feature",
  "properties": {
    "gn:admin1_code":"16.0",
    "gn:asciiname":"Waihuangzhu",
    "gn:country_code":"CN",
    "gn:dem":112,
    "gn:feature_class":"P",
    "gn:feature_code":"PPL",
    "gn:name":"Waihuangzhu",
    "gn:population":0,
    "gn:timezone":"Asia/Shanghai",
    "iso:country":"CN",
    "name:zho_x_preferred":[
        "\u5916\u7687\u4e3b"
    ],
    "wof:name":"Waihuangzhu",
    "wof:placetype":"locality"
},
  "geometry": {"coordinates":[108.626,23.4098],"type":"Point"}
}