{
  "type": "Feature",
  "properties": {
    "gn:admin1_code":"02",
    "gn:asciiname":"Nanyan",
    "gn:country_code":"CN",
    "gn:dem":34,
    "gn:feature_class":"P",
    "gn:feature_code":"PPL",
    "gn:name":"Nanyan",
    "gn:population":0,
    "gn:timezone":"Asia/Shanghai",
    "iso:country":"CN",
    "name:rus_x_preferred":[
        "\u041d\u0430\u043d\u044c\u044f\u043d"
    ],
    "name:und_x_variant":[
        "Kantou",
        "Nanyan"
    ],
    "name:zho_x_preferred":[
        "\u5357\u96c1"
    ],
    "wof:name":"Nanyan",
    "wof:placetype":"locality"
},
  "geometry": {"coordinates":[120.25109999999999,27.61446],"type":"Point"}
}