{
  "type": "Feature",
  "properties": {
    "gn:admin1_code":"32.0",
    "gn:asciiname":"Dewa",
    "gn:country_code":"CN",
    "gn:dem":3119,
    "gn:feature_class":"P",
    "gn:feature_code":"PPL",
    "gn:name":"Dewa",
    "gn:population":0,
    "gn:timezone":"Asia/Shanghai",
    "iso:country":"CN",
    "name:ceb_x_preferred":[
        "Dewa"
    ],
    "name:deu_x_preferred":[
        "Dewa"
    ],
    "name:nld_x_preferred":[
        "Dewa"
    ],
    "name:pol_x_preferred":[
        "Dewa"
    ],
    "name:rus_x_preferred":[
        "\u0414\u044d\u0432\u0430"
    ],
    "name:swe_x_preferred":[
        "Dewa"
    ],
    "name:ukr_x_preferred":[
        "\u0414\u0435\u0432\u0430"
    ],
    "name:vie_x_preferred":[
        "Dewa"
    ],
    "name:zho_x_preferred":[
        "\u5fb7\u74e6"
    ],
    "wof:name":"Dewa",
    "wof:placetype":"locality"
},
  "geometry": {"coordinates":[101.89100000000001,31.8311],"type":"Point"}
}