{
  "type": "Feature",
  "properties": {
    "gn:admin1_code":"11",
    "gn:asciiname":"Chenjia Xinwu",
    "gn:country_code":"CN",
    "gn:dem":191,
    "gn:feature_class":"P",
    "gn:feature_code":"PPL",
    "gn:name":"Chenjia Xinwu",
    "gn:population":0,
    "gn:timezone":"Asia/Shanghai",
    "iso:country":"CN",
    "name:zho_x_preferred":[
        "\u9648\u5bb6\u65b0\u5c4b"
    ],
    "wof:name":"Chenjia Xinwu",
    "wof:placetype":"locality"
},
  "geometry": {"coordinates":[111.91698999999998,26.86985],"type":"Point"}
}