{
  "type": "Feature",
  "properties": {
    "gn:admin1_code":"29.0",
    "gn:asciiname":"Raolangjie",
    "gn:country_code":"CN",
    "gn:dem":1888,
    "gn:feature_class":"P",
    "gn:feature_code":"PPL",
    "gn:name":"Raolangjie",
    "gn:population":0,
    "gn:timezone":"Asia/Shanghai",
    "iso:country":"CN",
    "name:zho_x_preferred":[
        "\u7ed5\u5eca\u8857"
    ],
    "wof:name":"Raolangjie",
    "wof:placetype":"locality"
},
  "geometry": {"coordinates":[98.8665,24.5778],"type":"Point"}
}