{
  "type": "Feature",
  "properties": {
    "gn:admin1_code":"10.0",
    "gn:asciiname":"Chaigezhuang",
    "gn:country_code":"CN",
    "gn:dem":41,
    "gn:feature_class":"P",
    "gn:feature_code":"PPL",
    "gn:name":"Chaigezhuang",
    "gn:population":0,
    "gn:timezone":"Asia/Shanghai",
    "iso:country":"CN",
    "name:zho_x_preferred":[
        "\u67f4\u5404\u5e84"
    ],
    "wof:name":"Chaigezhuang",
    "wof:placetype":"locality"
},
  "geometry": {"coordinates":[118.69058,39.68302],"type":"Point"}
}