{
  "type": "Feature",
  "properties": {
    "gn:admin1_code":"31.0",
    "gn:asciiname":"Jinbo Laocun",
    "gn:country_code":"CN",
    "gn:dem":141,
    "gn:feature_class":"P",
    "gn:feature_code":"PPL",
    "gn:name":"Jinbo Laocun",
    "gn:population":0,
    "gn:timezone":"Asia/Shanghai",
    "iso:country":"CN",
    "name:zho_x_preferred":[
        "\u91d1\u6ce2\u8001\u6751"
    ],
    "wof:name":"Jinbo Laocun",
    "wof:placetype":"locality"
},
  "geometry": {"coordinates":[109.13688,19.22071],"type":"Point"}
}