{
  "type": "Feature",
  "properties": {
    "gn:country":"CN",
    "gn:fcode":"PPLA3",
    "gn:pop":79655,
    "iso:country":"CN",
    "name:unk_x_variant":[
        "T\u2019ai-hsing-chen"
    ],
    "qs:name":"\u6cf0\u5174\u5e02",
    "qs:name_adm0":"\u4e2d\u570b",
    "qs:name_adm1":"\u6c5f\u82cf\u7701",
    "qs:photos_9k":1,
    "qs:photos_9r":2,
    "qs:photos_all":29,
    "qs:photos_sr":0,
    "qs:placetype":"LocalAdmin",
    "qs:pop_sr":"8",
    "wof:name":"\u6cf0\u5174\u5e02",
    "wof:placetype":"localadmin",
    "wof:population":79655
},
  "geometry": {"coordinates":[120.01361,32.16667],"type":"Point"}
}