{
  "type": "Feature",
  "properties": {
    "gn:admin1_code":"8.0",
    "gn:asciiname":"Qianshuangjing",
    "gn:country_code":"CN",
    "gn:dem":125,
    "gn:feature_class":"P",
    "gn:feature_code":"PPL",
    "gn:name":"Qianshuangjing",
    "gn:population":0,
    "gn:timezone":"Asia/Shanghai",
    "iso:country":"CN",
    "name:zho_x_preferred":[
        "\u524d\u53cc\u4e95"
    ],
    "wof:name":"Qianshuangjing",
    "wof:placetype":"locality"
},
  "geometry": {"coordinates":[127.42332,46.011],"type":"Point"}
}