{
  "type": "Feature",
  "properties": {
    "gn:admin1_code":"21.0",
    "gn:asciiname":"Shacongwa",
    "gn:country_code":"CN",
    "gn:dem":2012,
    "gn:feature_class":"P",
    "gn:feature_code":"PPL",
    "gn:name":"Shacongwa",
    "gn:population":0,
    "gn:timezone":"Asia/Shanghai",
    "iso:country":"CN",
    "name:zho_x_preferred":[
        "\u6c99\u8471\u5c72"
    ],
    "wof:name":"Shacongwa",
    "wof:placetype":"locality"
},
  "geometry": {"coordinates":[105.669,36.0053],"type":"Point"}
}