{
  "type": "Feature",
  "properties": {
    "gn:admin1_code":"26.0",
    "gn:asciiname":"Wujia'ao",
    "gn:country_code":"CN",
    "gn:dem":1011,
    "gn:feature_class":"P",
    "gn:feature_code":"PPL",
    "gn:name":"Wujia\u2019ao",
    "gn:population":0,
    "gn:timezone":"Asia/Shanghai",
    "iso:country":"CN",
    "name:und_x_variant":[
        "Wujia\u2019ao"
    ],
    "name:zho_x_preferred":[
        "\u5434\u5bb6\u51f9"
    ],
    "wof:name":"Wujia'ao",
    "wof:placetype":"locality"
},
  "geometry": {"coordinates":[108.98374,33.43097],"type":"Point"}
}