{
  "type": "Feature",
  "properties": {
    "gn:admin1_code":"32.0",
    "gn:asciiname":"Diya",
    "gn:country_code":"CN",
    "gn:dem":3067,
    "gn:feature_class":"P",
    "gn:feature_code":"PPL",
    "gn:name":"Diya",
    "gn:population":0,
    "gn:timezone":"Asia/Shanghai",
    "iso:country":"CN",
    "name:ceb_x_preferred":[
        "Diya"
    ],
    "name:deu_x_preferred":[
        "Diya"
    ],
    "name:hin_x_preferred":[
        "\u0926\u0940\u092f\u093e"
    ],
    "name:zho_x_preferred":[
        "\u5e95\u4e9a"
    ],
    "wof:name":"Diya",
    "wof:placetype":"locality"
},
  "geometry": {"coordinates":[101.00789,30.43691],"type":"Point"}
}