{
  "type": "Feature",
  "properties": {
    "gn:admin1_code":"9.0",
    "gn:asciiname":"Hongshiyao",
    "gn:country_code":"CN",
    "gn:dem":847,
    "gn:feature_class":"P",
    "gn:feature_code":"PPL",
    "gn:name":"Hongshiyao",
    "gn:population":0,
    "gn:timezone":"Asia/Shanghai",
    "iso:country":"CN",
    "name:und_x_variant":[
        "\u7ea2\u77f3\u7a91",
        "Hongshiyao"
    ],
    "wof:name":"Hongshiyao",
    "wof:placetype":"locality"
},
  "geometry": {"coordinates":[112.17801,33.34805],"type":"Point"}
}