{
  "type": "Feature",
  "properties": {
    "gn:admin1_code":"2.0",
    "gn:asciiname":"Xiaochendu",
    "gn:country_code":"CN",
    "gn:dem":10,
    "gn:feature_class":"P",
    "gn:feature_code":"PPL",
    "gn:name":"Xiaochendu",
    "gn:population":0,
    "gn:timezone":"Asia/Shanghai",
    "iso:country":"CN",
    "name:und_x_variant":[
        "\u5c0f\u6c89\u8bfb"
    ],
    "wof:name":"Xiaochendu",
    "wof:placetype":"locality"
},
  "geometry": {"coordinates":[120.06664000000001,30.98956],"type":"Point"}
}