{
  "type": "Feature",
  "properties": {
    "gn:admin1_code":"30.0",
    "gn:asciiname":"Gaoche",
    "gn:country_code":"CN",
    "gn:dem":193,
    "gn:feature_class":"P",
    "gn:feature_code":"PPL",
    "gn:name":"Gaoche",
    "gn:population":0,
    "gn:timezone":"Asia/Urumqi",
    "iso:country":"CN",
    "name:zho_x_preferred":[
        "\u9ad8\u8f66"
    ],
    "wof:name":"Gaoche",
    "wof:placetype":"locality"
},
  "geometry": {"coordinates":[110.8165,22.55108],"type":"Point"}
}