{
  "type": "Feature",
  "properties": {
    "gn:admin1_code":"11",
    "gn:asciiname":"Dongzichong",
    "gn:country_code":"CN",
    "gn:dem":291,
    "gn:feature_class":"P",
    "gn:feature_code":"PPL",
    "gn:name":"Dongzichong",
    "gn:population":0,
    "gn:timezone":"Asia/Shanghai",
    "iso:country":"CN",
    "name:zho_x_preferred":[
        "\u4e1c\u5b50\u51b2"
    ],
    "wof:name":"Dongzichong",
    "wof:placetype":"locality"
},
  "geometry": {"coordinates":[110.99388999999999,27.17139],"type":"Point"}
}