{
  "type": "Feature",
  "properties": {
    "gn:admin1_code":"3",
    "gn:asciiname":"Zhudong",
    "gn:country_code":"CN",
    "gn:dem":468,
    "gn:feature_class":"P",
    "gn:feature_code":"PPL",
    "gn:name":"Zhudong",
    "gn:population":0,
    "gn:timezone":"Asia/Shanghai",
    "iso:country":"CN",
    "name:hak_x_preferred":[
        "Chuk-t\u00fbng-ch\u1e73\u0301n"
    ],
    "name:jpn_x_preferred":[
        "\u7af9\u6771\u93ae"
    ],
    "name:kor_x_preferred":[
        "\uc8fc\ub465\uc9c4"
    ],
    "name:vie_x_preferred":[
        "Tr\u00fac \u0110\u00f4ng"
    ],
    "name:zho_x_preferred":[
        "\u73e0\u6d1e"
    ],
    "name:zho_x_variant":[
        "\u7af9\u6771\u93ae"
    ],
    "wof:name":"Zhudong",
    "wof:placetype":"locality"
},
  "geometry": {"coordinates":[114.252,25.5066],"type":"Point"}
}