{
  "type": "Feature",
  "properties": {
    "gn:admin1_code":"26.0",
    "gn:asciiname":"Chenmahe",
    "gn:country_code":"CN",
    "gn:dem":568,
    "gn:feature_class":"P",
    "gn:feature_code":"PPL",
    "gn:name":"Chenmahe",
    "gn:population":0,
    "gn:timezone":"Asia/Shanghai",
    "iso:country":"CN",
    "name:und_x_variant":[
        "\u9648\u9a6c\u6cb3"
    ],
    "wof:name":"Chenmahe",
    "wof:placetype":"locality"
},
  "geometry": {"coordinates":[107.78198999999999,34.35284],"type":"Point"}
}