{
  "type": "Feature",
  "properties": {
    "gn:admin1_code":"3.0",
    "gn:asciiname":"Shangbi",
    "gn:country_code":"CN",
    "gn:dem":157,
    "gn:feature_class":"P",
    "gn:feature_code":"PPL",
    "gn:name":"Shangbi",
    "gn:population":0,
    "gn:timezone":"Asia/Shanghai",
    "iso:country":"CN",
    "name:und_x_variant":[
        "\u4e0a\u6bd5",
        "Xiabi"
    ],
    "wof:name":"Shangbi",
    "wof:placetype":"locality"
},
  "geometry": {"coordinates":[115.30367,29.58035],"type":"Point"}
}