{
  "type": "Feature",
  "properties": {
    "gn:admin1_code":"5.0",
    "gn:asciiname":"Linjiangcun",
    "gn:country_code":"CN",
    "gn:dem":172,
    "gn:feature_class":"P",
    "gn:feature_code":"PPL",
    "gn:name":"Linjiangcun",
    "gn:population":0,
    "gn:timezone":"Asia/Shanghai",
    "iso:country":"CN",
    "name:zho_x_preferred":[
        "\u4e34\u6c5f\u6751"
    ],
    "wof:name":"Linjiangcun",
    "wof:placetype":"locality"
},
  "geometry": {"coordinates":[126.48248999999998,44.26003],"type":"Point"}
}