{
  "type": "Feature",
  "properties": {
    "gn:admin1_code":"19.0",
    "gn:asciiname":"Xianianmazhoucun",
    "gn:country_code":"CN",
    "gn:dem":129,
    "gn:feature_class":"P",
    "gn:feature_code":"PPL",
    "gn:name":"Xianianmazhoucun",
    "gn:population":0,
    "gn:timezone":"Asia/Shanghai",
    "iso:country":"CN",
    "name:zho_x_preferred":[
        "\u4e0b\u5e74\u9a6c\u6d32\u6751"
    ],
    "wof:name":"Xianianmazhoucun",
    "wof:placetype":"locality"
},
  "geometry": {"coordinates":[124.133,41.9983],"type":"Point"}
}