{
  "type": "Feature",
  "properties": {
    "gn:admin1_code":"19.0",
    "gn:asciiname":"Hejia Wopeng",
    "gn:country_code":"CN",
    "gn:dem":115,
    "gn:feature_class":"P",
    "gn:feature_code":"PPL",
    "gn:name":"Hejia Wopeng",
    "gn:population":0,
    "gn:timezone":"Asia/Shanghai",
    "iso:country":"CN",
    "name:zho_x_preferred":[
        "\u8d3a\u5bb6\u7a9d\u68da"
    ],
    "wof:name":"Hejia Wopeng",
    "wof:placetype":"locality"
},
  "geometry": {"coordinates":[124.128,42.6502],"type":"Point"}
}