{
  "type": "Feature",
  "properties": {
    "gn:admin1_code":"29.0",
    "gn:asciiname":"Puxunxun",
    "gn:country_code":"CN",
    "gn:dem":1802,
    "gn:feature_class":"P",
    "gn:feature_code":"PPL",
    "gn:name":"Puxunxun",
    "gn:population":0,
    "gn:timezone":"Asia/Shanghai",
    "iso:country":"CN",
    "name:zho_x_preferred":[
        "\u666e\u8baf\u8baf"
    ],
    "wof:name":"Puxunxun",
    "wof:placetype":"locality"
},
  "geometry": {"coordinates":[103.792,23.181],"type":"Point"}
}