{
  "type": "Feature",
  "properties": {
    "gn:admin1_code":"32.0",
    "gn:asciiname":"Xincang",
    "gn:country_code":"CN",
    "gn:dem":2162,
    "gn:feature_class":"P",
    "gn:feature_code":"PPL",
    "gn:name":"Xincang",
    "gn:population":0,
    "gn:timezone":"Asia/Shanghai",
    "iso:country":"CN",
    "name:zho_x_preferred":[
        "\u65b0\u85cf"
    ],
    "wof:name":"Xincang",
    "wof:placetype":"locality"
},
  "geometry": {"coordinates":[100.67400000000001,28.3151],"type":"Point"}
}