{
  "type": "Feature",
  "properties": {
    "gn:admin1_code":"11",
    "gn:asciiname":"Panshixu",
    "gn:country_code":"CN",
    "gn:dem":350,
    "gn:feature_class":"P",
    "gn:feature_code":"PPL",
    "gn:name":"Panshixu",
    "gn:population":0,
    "gn:timezone":"Asia/Shanghai",
    "iso:country":"CN",
    "name:und_x_variant":[
        "\u78d0\u77f3\u5729",
        "Panshixu"
    ],
    "wof:name":"Panshixu",
    "wof:placetype":"locality"
},
  "geometry": {"coordinates":[112.16833,25.60028],"type":"Point"}
}