{
  "type": "Feature",
  "properties": {
    "gn:admin1_code":"12.0",
    "gn:asciiname":"Caoping",
    "gn:country_code":"CN",
    "gn:dem":951,
    "gn:feature_class":"P",
    "gn:feature_code":"PPL",
    "gn:name":"Caoping",
    "gn:population":0,
    "gn:timezone":"Asia/Shanghai",
    "iso:country":"CN",
    "name:zho_x_preferred":[
        "\u8349\u576a"
    ],
    "wof:name":"Caoping",
    "wof:placetype":"locality"
},
  "geometry": {"coordinates":[111.0979,31.84099],"type":"Point"}
}