{
  "type": "Feature",
  "properties": {
    "gn:admin1_code":"30",
    "gn:asciiname":"Bajiaolong",
    "gn:country_code":"CN",
    "gn:dem":449,
    "gn:feature_class":"P",
    "gn:feature_code":"PPL",
    "gn:name":"Bajiaolong",
    "gn:population":0,
    "gn:timezone":"Asia/Shanghai",
    "iso:country":"CN",
    "name:und_x_variant":[
        "\u82ad\u8549\u5785",
        "Daojiaolong"
    ],
    "wof:name":"Bajiaolong",
    "wof:placetype":"locality"
},
  "geometry": {"coordinates":[113.98,25.37],"type":"Point"}
}