{
  "type": "Feature",
  "properties": {
    "gn:admin1_code":"16.0",
    "gn:asciiname":"Shanyangkeng",
    "gn:country_code":"CN",
    "gn:dem":190,
    "gn:feature_class":"P",
    "gn:feature_code":"PPL",
    "gn:name":"Shanyangkeng",
    "gn:population":0,
    "gn:timezone":"Asia/Shanghai",
    "iso:country":"CN",
    "name:zho_x_preferred":[
        "\u5c71\u7f8a\u5751"
    ],
    "wof:name":"Shanyangkeng",
    "wof:placetype":"locality"
},
  "geometry": {"coordinates":[110.291,22.2222],"type":"Point"}
}