{
  "type": "Feature",
  "properties": {
    "gn:admin1_code":"22.0",
    "gn:asciiname":"Jingshaofencun",
    "gn:country_code":"CN",
    "gn:dem":91,
    "gn:feature_class":"P",
    "gn:feature_code":"PPL",
    "gn:name":"Jingshaofencun",
    "gn:population":0,
    "gn:timezone":"Asia/Shanghai",
    "iso:country":"CN",
    "name:zho_x_preferred":[
        "\u8346\u68a2\u575f\u6751"
    ],
    "wof:name":"Jingshaofencun",
    "wof:placetype":"locality"
},
  "geometry": {"coordinates":[116.92950999999999,40.40775],"type":"Point"}
}