{
  "type": "Feature",
  "properties": {
    "gn:admin1_code":"26.0",
    "gn:asciiname":"Dashuituncun",
    "gn:country_code":"CN",
    "gn:dem":422,
    "gn:feature_class":"P",
    "gn:feature_code":"PPL",
    "gn:name":"Dashuituncun",
    "gn:population":0,
    "gn:timezone":"Asia/Shanghai",
    "iso:country":"CN",
    "name:zho_x_preferred":[
        "\u5927\u6c34\u5c6f\u6751"
    ],
    "wof:name":"Dashuituncun",
    "wof:placetype":"locality"
},
  "geometry": {"coordinates":[108.45448,34.12368],"type":"Point"}
}