{
  "type": "Feature",
  "properties": {
    "gn:admin1_code":"32.0",
    "gn:asciiname":"Laijiaping",
    "gn:country_code":"CN",
    "gn:dem":1173,
    "gn:feature_class":"P",
    "gn:feature_code":"PPL",
    "gn:name":"Laijiaping",
    "gn:population":0,
    "gn:timezone":"Asia/Shanghai",
    "iso:country":"CN",
    "name:zho_x_preferred":[
        "\u8d56\u5bb6\u576a"
    ],
    "wof:name":"Laijiaping",
    "wof:placetype":"locality"
},
  "geometry": {"coordinates":[104.69398,31.98693],"type":"Point"}
}