{
  "type": "Feature",
  "properties": {
    "gn:admin1_code":"11.0",
    "gn:asciiname":"Songpochong",
    "gn:country_code":"CN",
    "gn:dem":369,
    "gn:feature_class":"P",
    "gn:feature_code":"PPL",
    "gn:name":"Songpochong",
    "gn:population":0,
    "gn:timezone":"Asia/Shanghai",
    "iso:country":"CN",
    "name:zho_x_preferred":[
        "\u677e\u5761\u51b2"
    ],
    "wof:name":"Songpochong",
    "wof:placetype":"locality"
},
  "geometry": {"coordinates":[110.72026,28.20832],"type":"Point"}
}