{
  "type": "Feature",
  "properties": {
    "gn:admin1_code":"14.0",
    "gn:asciiname":"Caquduikacun",
    "gn:country_code":"CN",
    "gn:dem":4586,
    "gn:feature_class":"P",
    "gn:feature_code":"PPL",
    "gn:name":"Caquduikacun",
    "gn:population":0,
    "gn:timezone":"Asia/Urumqi",
    "iso:country":"CN",
    "name:zho_x_preferred":[
        "\u64e6\u66f2\u5806\u5494\u6751"
    ],
    "wof:name":"Caquduikacun",
    "wof:placetype":"locality"
},
  "geometry": {"coordinates":[91.69307999999999,31.51248],"type":"Point"}
}