{
  "type": "Feature",
  "properties": {
    "gn:admin1_code":"26.0",
    "gn:asciiname":"Fuyuanping",
    "gn:country_code":"CN",
    "gn:dem":1536,
    "gn:feature_class":"P",
    "gn:feature_code":"PPL",
    "gn:name":"Fuyuanping",
    "gn:population":0,
    "gn:timezone":"Asia/Shanghai",
    "iso:country":"CN",
    "name:zho_x_preferred":[
        "\u5bcc\u539f\u576a"
    ],
    "wof:name":"Fuyuanping",
    "wof:placetype":"locality"
},
  "geometry": {"coordinates":[107.25751,32.65261],"type":"Point"}
}