{
  "type": "Feature",
  "properties": {
    "gn:admin1_code":"15.0",
    "gn:asciiname":"Shangquanwan",
    "gn:country_code":"CN",
    "gn:dem":2679,
    "gn:feature_class":"P",
    "gn:feature_code":"PPL",
    "gn:name":"Shangquanwan",
    "gn:population":0,
    "gn:timezone":"Asia/Shanghai",
    "iso:country":"CN",
    "name:zho_x_preferred":[
        "\u4e0a\u5708\u6e7e"
    ],
    "wof:name":"Shangquanwan",
    "wof:placetype":"locality"
},
  "geometry": {"coordinates":[103.42,37.205],"type":"Point"}
}