{
  "type": "Feature",
  "properties": {
    "gn:admin1_code":"5.0",
    "gn:asciiname":"Dawopeng",
    "gn:country_code":"CN",
    "gn:dem":265,
    "gn:feature_class":"P",
    "gn:feature_code":"PPL",
    "gn:name":"Dawopeng",
    "gn:population":0,
    "gn:timezone":"Asia/Shanghai",
    "iso:country":"CN",
    "name:zho_x_preferred":[
        "\u5927\u7a9d\u68da"
    ],
    "wof:name":"Dawopeng",
    "wof:placetype":"locality"
},
  "geometry": {"coordinates":[126.74091,44.06826],"type":"Point"}
}