{
  "type": "Feature",
  "properties": {
    "gn:admin1_code":"14.0",
    "gn:asciiname":"Qudatong",
    "gn:country_code":"CN",
    "gn:dem":4355,
    "gn:feature_class":"P",
    "gn:feature_code":"PPL",
    "gn:name":"Qudatong",
    "gn:population":0,
    "gn:timezone":"Asia/Urumqi",
    "iso:country":"CN",
    "name:zho_x_preferred":[
        "\u66f2\u8fbe\u901a"
    ],
    "wof:name":"Qudatong",
    "wof:placetype":"locality"
},
  "geometry": {"coordinates":[93.23994999999999,32.09388],"type":"Point"}
}