{
  "type": "Feature",
  "properties": {
    "gn:admin1_code":"10",
    "gn:asciiname":"Xiniezhuang",
    "gn:country_code":"CN",
    "gn:dem":55,
    "gn:feature_class":"P",
    "gn:feature_code":"PPL",
    "gn:name":"Xiniezhuang",
    "gn:population":0,
    "gn:timezone":"Asia/Shanghai",
    "iso:country":"CN",
    "name:zho_x_preferred":[
        "\u897f\u8042\u5e84"
    ],
    "wof:name":"Xiniezhuang",
    "wof:placetype":"locality"
},
  "geometry": {"coordinates":[114.61199999999999,36.5462],"type":"Point"}
}