{
  "type": "Feature",
  "properties": {
    "gn:admin1_code":"04",
    "gn:asciiname":"Fengyi",
    "gn:country_code":"CN",
    "gn:dem":9,
    "gn:feature_class":"P",
    "gn:feature_code":"PPL",
    "gn:name":"Fengyi",
    "gn:population":0,
    "gn:timezone":"Asia/Shanghai",
    "iso:country":"CN",
    "name:und_x_variant":[
        "Feng-i-chen",
        "Feng-i",
        "Fengyizhen",
        "Fengyi"
    ],
    "name:zho_x_preferred":[
        "\u4e30\u4e49"
    ],
    "wof:name":"Fengyi",
    "wof:placetype":"locality"
},
  "geometry": {"coordinates":[119.73202999999999,31.54649],"type":"Point"}
}