{
  "type": "Feature",
  "properties": {
    "gn:admin1_code":"15.0",
    "gn:asciiname":"Qinjia Laozhuang",
    "gn:country_code":"CN",
    "gn:dem":1275,
    "gn:feature_class":"P",
    "gn:feature_code":"PPL",
    "gn:name":"Qinjia Laozhuang",
    "gn:population":0,
    "gn:timezone":"Asia/Shanghai",
    "iso:country":"CN",
    "name:zho_x_preferred":[
        "\u79e6\u5bb6\u8001\u5e84"
    ],
    "wof:name":"Qinjia Laozhuang",
    "wof:placetype":"locality"
},
  "geometry": {"coordinates":[107.747,35.5844],"type":"Point"}
}