{
  "type": "Feature",
  "properties": {
    "gn:admin1_code":"10",
    "gn:asciiname":"Dahoucun",
    "gn:cc2":"CN",
    "gn:country_code":"CN",
    "gn:dem":14,
    "gn:feature_class":"P",
    "gn:feature_code":"PPL",
    "gn:name":"Dahoucun",
    "gn:population":0,
    "gn:timezone":"Asia/Shanghai",
    "iso:country":"CN",
    "name:und_x_variant":[
        "Ta-hou-ts\u2019un",
        "Dahoucun"
    ],
    "wof:name":"Dahoucun",
    "wof:placetype":"locality"
},
  "geometry": {"coordinates":[115.63333,38.85],"type":"Point"}
}