{
  "type": "Feature",
  "properties": {
    "gn:admin1_code":"1.0",
    "gn:asciiname":"Eshan",
    "gn:country_code":"CN",
    "gn:dem":18,
    "gn:feature_class":"P",
    "gn:feature_code":"PPLA4",
    "gn:name":"Eshan",
    "gn:population":0,
    "gn:timezone":"Asia/Shanghai",
    "iso:country":"CN",
    "name:zho_x_preferred":[
        "\u5ce8\u5c71"
    ],
    "wof:name":"Eshan",
    "wof:placetype":"locality"
},
  "geometry": {"coordinates":[118.21578999999998,31.06429],"type":"Point"}
}