{
  "type": "Feature",
  "properties": {
    "gn:admin1_code":"24.0",
    "gn:asciiname":"Jinmiaohe",
    "gn:country_code":"CN",
    "gn:dem":824,
    "gn:feature_class":"P",
    "gn:feature_code":"PPL",
    "gn:name":"Jinmiaohe",
    "gn:population":0,
    "gn:timezone":"Asia/Shanghai",
    "iso:country":"CN",
    "name:zho_x_preferred":[
        "\u664b\u5e99\u6cb3"
    ],
    "wof:name":"Jinmiaohe",
    "wof:placetype":"locality"
},
  "geometry": {"coordinates":[112.84531,35.35086],"type":"Point"}
}