{
  "type": "Feature",
  "properties": {
    "gn:admin1_code":"10",
    "gn:asciiname":"Jiaojiemanzi",
    "gn:country_code":"CN",
    "gn:dem":468,
    "gn:feature_class":"P",
    "gn:feature_code":"PPL",
    "gn:name":"Jiaojiemanzi",
    "gn:population":0,
    "gn:timezone":"Asia/Shanghai",
    "iso:country":"CN",
    "name:zho_x_preferred":[
        "\u4ea4\u754c\u6f2b\u5b50"
    ],
    "wof:name":"Jiaojiemanzi",
    "wof:placetype":"locality"
},
  "geometry": {"coordinates":[117.80803,40.66404],"type":"Point"}
}