{
  "type": "Feature",
  "properties": {
    "gn:country":"CN",
    "gn:fcode":"PPL",
    "gn:population":180,
    "iso:country":"CN",
    "name:und_x_variant":[
        "Ta-ling"
    ],
    "name:zho_x_preferred":[
        "\u5927\u5cad\u8857"
    ],
    "qs:name":"Dalingjie",
    "qs:photos_9r":0,
    "qs:photos_sr":0,
    "qs:pop_sr":"1",
    "wof:name":"Dalingjie",
    "wof:placetype":"locality",
    "wof:population":180
},
  "geometry": {"coordinates":[108.61861,27.19611],"type":"Point"}
}