{
  "type": "Feature",
  "properties": {
    "gn:admin1_code":"15.0",
    "gn:asciiname":"Yuancaocun",
    "gn:country_code":"CN",
    "gn:dem":2484,
    "gn:feature_class":"P",
    "gn:feature_code":"PPL",
    "gn:name":"Yuancaocun",
    "gn:population":0,
    "gn:timezone":"Asia/Shanghai",
    "iso:country":"CN",
    "name:und_x_variant":[
        "\u5143\u8349\u6751"
    ],
    "wof:name":"Yuancaocun",
    "wof:placetype":"locality"
},
  "geometry": {"coordinates":[104.46117,34.45908],"type":"Point"}
}