{
  "type": "Feature",
  "properties": {
    "gn:admin1_code":"30.0",
    "gn:asciiname":"Shutouxia",
    "gn:country_code":"CN",
    "gn:dem":315,
    "gn:feature_class":"P",
    "gn:feature_code":"PPL",
    "gn:name":"Shutouxia",
    "gn:population":0,
    "gn:timezone":"Asia/Shanghai",
    "iso:country":"CN",
    "name:zho_x_preferred":[
        "\u6811\u5934\u4e0b"
    ],
    "wof:name":"Shutouxia",
    "wof:placetype":"locality"
},
  "geometry": {"coordinates":[113.98694999999999,24.67024],"type":"Point"}
}