{
  "type": "Feature",
  "properties": {
    "gn:admin1_code":"11.0",
    "gn:asciiname":"Cenpan",
    "gn:country_code":"CN",
    "gn:dem":801,
    "gn:feature_class":"P",
    "gn:feature_code":"PPL",
    "gn:name":"Cenpan",
    "gn:population":0,
    "gn:timezone":"Asia/Shanghai",
    "iso:country":"CN",
    "name:zho_x_preferred":[
        "\u5c91\u7554"
    ],
    "wof:name":"Cenpan",
    "wof:placetype":"locality"
},
  "geometry": {"coordinates":[109.12811000000001,27.07627],"type":"Point"}
}