{
  "type": "Feature",
  "properties": {
    "gn:admin1_code":"7",
    "gn:asciiname":"Xiatieling",
    "gn:country_code":"CN",
    "gn:dem":488,
    "gn:feature_class":"P",
    "gn:feature_code":"PPL",
    "gn:name":"Xiatieling",
    "gn:population":0,
    "gn:timezone":"Asia/Shanghai",
    "iso:country":"CN",
    "name:und_x_variant":[
        "\u4e0b\u94c1\u5cad",
        "Xiatieling"
    ],
    "wof:name":"Xiatieling",
    "wof:placetype":"locality"
},
  "geometry": {"coordinates":[118.86682,27.49505],"type":"Point"}
}