{
  "type": "Feature",
  "properties": {
    "gn:admin1_code":"32.0",
    "gn:asciiname":"Longjingba",
    "gn:country_code":"CN",
    "gn:dem":737,
    "gn:feature_class":"P",
    "gn:feature_code":"PPL",
    "gn:name":"Longjingba",
    "gn:population":0,
    "gn:timezone":"Asia/Shanghai",
    "iso:country":"CN",
    "name:zho_x_preferred":[
        "\u9f99\u4e95\u575d"
    ],
    "wof:name":"Longjingba",
    "wof:placetype":"locality"
},
  "geometry": {"coordinates":[106.242,28.7461],"type":"Point"}
}