{
  "type": "Feature",
  "properties": {
    "gn:admin1_code":"19.0",
    "gn:asciiname":"Dazhangtun",
    "gn:country_code":"CN",
    "gn:dem":95,
    "gn:feature_class":"P",
    "gn:feature_code":"PPL",
    "gn:name":"Dazhangtun",
    "gn:population":0,
    "gn:timezone":"Asia/Shanghai",
    "iso:country":"CN",
    "name:zho_x_preferred":[
        "\u5927\u5f20\u5c6f"
    ],
    "wof:name":"Dazhangtun",
    "wof:placetype":"locality"
},
  "geometry": {"coordinates":[120.05200000000001,40.2981],"type":"Point"}
}