{
  "type": "Feature",
  "properties": {
    "gn:admin1_code":"15.0",
    "gn:asciiname":"Jiudongfang",
    "gn:country_code":"CN",
    "gn:dem":2814,
    "gn:feature_class":"P",
    "gn:feature_code":"PPL",
    "gn:name":"Jiudongfang",
    "gn:population":0,
    "gn:timezone":"Asia/Shanghai",
    "iso:country":"CN",
    "name:zho_x_preferred":[
        "\u4e5d\u680b\u623f"
    ],
    "wof:name":"Jiudongfang",
    "wof:placetype":"locality"
},
  "geometry": {"coordinates":[97.9417,39.3488],"type":"Point"}
}