{
  "type": "Feature",
  "properties": {
    "gn:admin1_code":"1.0",
    "gn:asciiname":"Luanzhuangcun",
    "gn:country_code":"CN",
    "gn:dem":37,
    "gn:feature_class":"P",
    "gn:feature_code":"PPL",
    "gn:name":"Luanzhuangcun",
    "gn:population":0,
    "gn:timezone":"Asia/Shanghai",
    "iso:country":"CN",
    "name:zho_x_preferred":[
        "\u683e\u5e84\u6751"
    ],
    "wof:name":"Luanzhuangcun",
    "wof:placetype":"locality"
},
  "geometry": {"coordinates":[115.44025000000001,32.84354],"type":"Point"}
}