{
  "type": "Feature",
  "properties": {
    "gn:admin1_code":"4.0",
    "gn:asciiname":"Donggu Chunbang",
    "gn:country_code":"CN",
    "gn:dem":6,
    "gn:feature_class":"P",
    "gn:feature_code":"PPL",
    "gn:name":"Donggu Chunbang",
    "gn:population":0,
    "gn:timezone":"Asia/Shanghai",
    "iso:country":"CN",
    "name:und_x_variant":[
        "\u4e1c\u53e4\u6625\u6d5c"
    ],
    "name:zho_x_preferred":[
        "\u4e1c\u53e4\u6625\u6d5c"
    ],
    "wof:name":"Donggu Chunbang",
    "wof:placetype":"locality"
},
  "geometry": {"coordinates":[120.99607,31.3162],"type":"Point"}
}