{
  "type": "Feature",
  "properties": {
    "gn:admin1_code":"26.0",
    "gn:asciiname":"Maliupu",
    "gn:country_code":"CN",
    "gn:dem":1001,
    "gn:feature_class":"P",
    "gn:feature_code":"PPL",
    "gn:name":"Maliupu",
    "gn:population":0,
    "gn:timezone":"Asia/Shanghai",
    "iso:country":"CN",
    "name:und_x_variant":[
        "\u9ebb\u67f3\u94fa"
    ],
    "wof:name":"Maliupu",
    "wof:placetype":"locality"
},
  "geometry": {"coordinates":[106.29872,33.21420999999999],"type":"Point"}
}