{
  "type": "Feature",
  "properties": {
    "gn:admin1_code":"29.0",
    "gn:asciiname":"Xiaoleduo",
    "gn:country_code":"CN",
    "gn:dem":1411,
    "gn:feature_class":"P",
    "gn:feature_code":"PPL",
    "gn:name":"Xiaoleduo",
    "gn:population":0,
    "gn:timezone":"Asia/Shanghai",
    "iso:country":"CN",
    "name:zho_x_preferred":[
        "\u5c0f\u4e50\u591a"
    ],
    "wof:name":"Xiaoleduo",
    "wof:placetype":"locality"
},
  "geometry": {"coordinates":[104.404,24.4499],"type":"Point"}
}