{
  "type": "Feature",
  "properties": {
    "gn:admin1_code":"9.0",
    "gn:asciiname":"Tujia",
    "gn:country_code":"CN",
    "gn:dem":54,
    "gn:feature_class":"P",
    "gn:feature_code":"PPL",
    "gn:name":"Tujia",
    "gn:population":0,
    "gn:timezone":"Asia/Shanghai",
    "iso:country":"CN",
    "name:nld_x_preferred":[
        "Tujia"
    ],
    "name:tur_x_preferred":[
        "Tujia"
    ],
    "name:zho_x_preferred":[
        "\u5c60\u5bb6"
    ],
    "wof:name":"Tujia",
    "wof:placetype":"locality"
},
  "geometry": {"coordinates":[114.38970999999999,33.66398],"type":"Point"}
}