{
  "type": "Feature",
  "properties": {
    "gn:admin1_code":"1.0",
    "gn:asciiname":"Chendiancun",
    "gn:country_code":"CN",
    "gn:dem":45,
    "gn:feature_class":"P",
    "gn:feature_code":"PPL",
    "gn:name":"Chendiancun",
    "gn:population":0,
    "gn:timezone":"Asia/Shanghai",
    "iso:country":"CN",
    "name:zho_x_preferred":[
        "\u9648\u5e97\u6751"
    ],
    "wof:name":"Chendiancun",
    "wof:placetype":"locality"
},
  "geometry": {"coordinates":[115.68228999999999,33.9743],"type":"Point"}
}