{
  "type": "Feature",
  "properties": {
    "gn:admin1_code":"10.0",
    "gn:asciiname":"Laojunying",
    "gn:country_code":"CN",
    "gn:dem":873,
    "gn:feature_class":"P",
    "gn:feature_code":"PPL",
    "gn:name":"Laojunying",
    "gn:population":0,
    "gn:timezone":"Asia/Shanghai",
    "iso:country":"CN",
    "name:zho_x_preferred":[
        "\u8001\u541b\u8425"
    ],
    "wof:name":"Laojunying",
    "wof:placetype":"locality"
},
  "geometry": {"coordinates":[114.51466000000001,40.14419],"type":"Point"}
}