{
  "type": "Feature",
  "properties": {
    "gn:admin1_code":"15.0",
    "gn:asciiname":"Dazhuang",
    "gn:country_code":"CN",
    "gn:dem":2055,
    "gn:feature_class":"P",
    "gn:feature_code":"PPL",
    "gn:name":"Dazhuang",
    "gn:population":0,
    "gn:timezone":"Asia/Shanghai",
    "iso:country":"CN",
    "name:ceb_x_preferred":[
        "Dazhuang"
    ],
    "name:deu_x_preferred":[
        "Dazhuang"
    ],
    "name:swe_x_preferred":[
        "Dazhuang"
    ],
    "name:zho_x_preferred":[
        "\u5927\u5e84"
    ],
    "wof:name":"Dazhuang",
    "wof:placetype":"locality"
},
  "geometry": {"coordinates":[103.166,35.4595],"type":"Point"}
}