{
  "type": "Feature",
  "properties": {
    "gn:admin1_code":"18",
    "gn:asciiname":"Maxi",
    "gn:cc2":"CN",
    "gn:country_code":"CN",
    "gn:dem":911,
    "gn:feature_class":"P",
    "gn:feature_code":"PPL",
    "gn:name":"Maxi",
    "gn:population":0,
    "gn:timezone":"Asia/Shanghai",
    "iso:country":"CN",
    "name:deu_x_preferred":[
        "Maxi"
    ],
    "name:fra_x_preferred":[
        "Maxi"
    ],
    "name:ita_x_preferred":[
        "Maxi"
    ],
    "name:spa_x_preferred":[
        "Maxi"
    ],
    "name:swe_x_preferred":[
        "Maxi"
    ],
    "name:und_x_variant":[
        "Ma-hsi"
    ],
    "wof:name":"Maxi",
    "wof:placetype":"locality"
},
  "geometry": {"coordinates":[108.08722,27.29694000000001],"type":"Point"}
}