{
  "type": "Feature",
  "properties": {
    "gn:admin1_code":"26.0",
    "gn:asciiname":"Qiujia Pingcun",
    "gn:country_code":"CN",
    "gn:dem":978,
    "gn:feature_class":"P",
    "gn:feature_code":"PPL",
    "gn:name":"Qiujia Pingcun",
    "gn:population":0,
    "gn:timezone":"Asia/Shanghai",
    "iso:country":"CN",
    "name:zho_x_preferred":[
        "\u90b1\u5bb6\u576a\u6751"
    ],
    "wof:name":"Qiujia Pingcun",
    "wof:placetype":"locality"
},
  "geometry": {"coordinates":[110.005,37.3755],"type":"Point"}
}