{
  "type": "Feature",
  "properties": {
    "gn:admin1_code":"3.0",
    "gn:asciiname":"Jiangnan",
    "gn:country_code":"CN",
    "gn:dem":58,
    "gn:feature_class":"P",
    "gn:feature_code":"PPL",
    "gn:name":"Jiangnan",
    "gn:population":0,
    "gn:timezone":"Asia/Shanghai",
    "iso:country":"CN",
    "name:cat_x_preferred":[
        "Jiangnan"
    ],
    "name:ces_x_preferred":[
        "\u0164iang-nan"
    ],
    "name:deu_x_preferred":[
        "Jiangnan"
    ],
    "name:epo_x_preferred":[
        "Jiangnano"
    ],
    "name:fra_x_preferred":[
        "Jiangnan"
    ],
    "name:hin_x_preferred":[
        "\u091c\u093f\u092f\u093e\u0902\u0917\u0928\u093e\u0928"
    ],
    "name:ind_x_preferred":[
        "Jiangnan"
    ],
    "name:ita_x_preferred":[
        "Jiangnan"
    ],
    "name:msa_x_preferred":[
        "Jiangnan"
    ],
    "name:nld_x_preferred":[
        "Jiangnan"
    ],
    "name:nor_x_preferred":[
        "Jiangnan"
    ],
    "name:por_x_preferred":[
        "Jiangnan"
    ],
    "name:rus_x_preferred":[
        "\u0426\u0437\u044f\u043d\u043d\u0430\u043d\u044c"
    ],
    "name:spa_x_preferred":[
        "Jiangnan"
    ],
    "name:tha_x_preferred":[
        "\u0e40\u0e08\u0e35\u0e22\u0e07\u0e2b\u0e19\u0e32\u0e19"
    ],
    "name:und_x_variant":[
        "\u6c5f\u5357"
    ],
    "name:vie_x_preferred":[
        "Giang Nam"
    ],
    "wof:name":"Jiangnan",
    "wof:placetype":"locality"
},
  "geometry": {"coordinates":[115.04895999999999,26.90706],"type":"Point"}
}