{
  "type": "Feature",
  "properties": {
    "gn:admin1_code":"14",
    "gn:asciiname":"Qemagog",
    "gn:country_code":"CN",
    "gn:dem":4326,
    "gn:feature_class":"P",
    "gn:feature_code":"PPL",
    "gn:name":"Q\u00eamagog",
    "gn:population":0,
    "gn:timezone":"Asia/Urumqi",
    "iso:country":"CN",
    "name:bod_x_preferred":[
        "\u0f56\u0fb1\u0f7a\u0f0b\u0f58\u0f0b\u0f63\u0f90\u0f7c\u0f42"
    ],
    "wof:name":"Qemagog",
    "wof:placetype":"locality"
},
  "geometry": {"coordinates":[90.48142,30.08105],"type":"Point"}
}