{
  "type": "Feature",
  "properties": {
    "gn:admin1_code":"02",
    "gn:asciiname":"Xiezhangcun",
    "gn:country_code":"CN",
    "gn:dem":14,
    "gn:feature_class":"P",
    "gn:feature_code":"PPL",
    "gn:name":"Xiezhangcun",
    "gn:population":0,
    "gn:timezone":"Asia/Shanghai",
    "iso:country":"CN",
    "name:und_x_variant":[
        "Hsieh-ao",
        "Xiezhang",
        "Xiezhangcun"
    ],
    "name:zho_x_preferred":[
        "\u8c22\u5f20"
    ],
    "name:zho_x_variant":[
        "\u8c22\u5f20\u6751"
    ],
    "wof:name":"Xiezhangcun",
    "wof:placetype":"locality"
},
  "geometry": {"coordinates":[121.45093,28.72028],"type":"Point"}
}