{
  "type": "Feature",
  "properties": {
    "gn:admin1_code":"29.0",
    "gn:asciiname":"Dashidong",
    "gn:country_code":"CN",
    "gn:dem":2103,
    "gn:feature_class":"P",
    "gn:feature_code":"PPL",
    "gn:name":"Dashidong",
    "gn:population":0,
    "gn:timezone":"Asia/Shanghai",
    "iso:country":"CN",
    "name:zho_x_preferred":[
        "\u5927\u77f3\u6d1e"
    ],
    "wof:name":"Dashidong",
    "wof:placetype":"locality"
},
  "geometry": {"coordinates":[102.78,25.5556],"type":"Point"}
}