{
  "type": "Feature",
  "properties": {
    "gn:admin1_code":"32.0",
    "gn:asciiname":"Sanjieqiao",
    "gn:country_code":"CN",
    "gn:dem":367,
    "gn:feature_class":"P",
    "gn:feature_code":"PPL",
    "gn:name":"Sanjieqiao",
    "gn:population":0,
    "gn:timezone":"Asia/Shanghai",
    "iso:country":"CN",
    "name:zho_x_preferred":[
        "\u4e09\u8282\u6865"
    ],
    "wof:name":"Sanjieqiao",
    "wof:placetype":"locality"
},
  "geometry": {"coordinates":[105.958,30.989],"type":"Point"}
}