{
  "type": "Feature",
  "properties": {
    "gn:admin1_code":"30.0",
    "gn:asciiname":"Dakengjiu",
    "gn:country_code":"CN",
    "gn:dem":8,
    "gn:feature_class":"P",
    "gn:feature_code":"PPL",
    "gn:name":"Dakengjiu",
    "gn:population":0,
    "gn:timezone":"Asia/Shanghai",
    "iso:country":"CN",
    "name:zho_x_preferred":[
        "\u5927\u5751\u65e7"
    ],
    "wof:name":"Dakengjiu",
    "wof:placetype":"locality"
},
  "geometry": {"coordinates":[112.76347,21.97039],"type":"Point"}
}