{
  "type": "Feature",
  "properties": {
    "gn:admin1_code":"8.0",
    "gn:asciiname":"Danaodaishan",
    "gn:country_code":"CN",
    "gn:dem":155,
    "gn:feature_class":"P",
    "gn:feature_code":"PPL",
    "gn:name":"Danaodaishan",
    "gn:population":0,
    "gn:timezone":"Asia/Shanghai",
    "iso:country":"CN",
    "name:zho_x_preferred":[
        "\u5927\u8111\u888b\u5c71"
    ],
    "wof:name":"Danaodaishan",
    "wof:placetype":"locality"
},
  "geometry": {"coordinates":[123.19831000000001,46.99011],"type":"Point"}
}