{
  "type": "Feature",
  "properties": {
    "gn:admin1_code":"32.0",
    "gn:asciiname":"Yuexiale",
    "gn:country_code":"CN",
    "gn:dem":2509,
    "gn:feature_class":"P",
    "gn:feature_code":"PPL",
    "gn:name":"Yuexiale",
    "gn:population":0,
    "gn:timezone":"Asia/Shanghai",
    "iso:country":"CN",
    "name:zho_x_preferred":[
        "\u7ea6\u5477\u52d2"
    ],
    "wof:name":"Yuexiale",
    "wof:placetype":"locality"
},
  "geometry": {"coordinates":[102.509,28.3595],"type":"Point"}
}