{
  "type": "Feature",
  "properties": {
    "gn:admin1_code":"3.0",
    "gn:asciiname":"Hukou",
    "gn:country_code":"CN",
    "gn:dem":335,
    "gn:feature_class":"P",
    "gn:feature_code":"PPL",
    "gn:name":"Hukou",
    "gn:population":0,
    "gn:timezone":"Asia/Shanghai",
    "iso:country":"CN",
    "name:und_x_variant":[
        "\u6e56\u53e3"
    ],
    "wof:name":"Hukou",
    "wof:placetype":"locality"
},
  "geometry": {"coordinates":[116.77605,27.63704],"type":"Point"}
}