{
  "type": "Feature",
  "properties": {
    "gn:admin1_code":"29",
    "gn:asciiname":"Awu",
    "gn:country_code":"CN",
    "gn:dem":1549,
    "gn:feature_class":"P",
    "gn:feature_code":"PPL",
    "gn:name":"Awu",
    "gn:population":0,
    "gn:timezone":"Asia/Shanghai",
    "iso:country":"CN",
    "name:zho_x_preferred":[
        "\u963f\u4e4c"
    ],
    "wof:name":"Awu",
    "wof:placetype":"locality"
},
  "geometry": {"coordinates":[103.50774,24.44356],"type":"Point"}
}