{
  "type": "Feature",
  "properties": {
    "gn:admin1_code":"3",
    "gn:asciiname":"Jian'ao",
    "gn:country_code":"CN",
    "gn:dem":795,
    "gn:feature_class":"P",
    "gn:feature_code":"PPL",
    "gn:name":"Jian\u2019ao",
    "gn:population":0,
    "gn:timezone":"Asia/Shanghai",
    "iso:country":"CN",
    "name:und_x_variant":[
        "Jian\u2019ao"
    ],
    "name:zho_x_preferred":[
        "\u67a7\u5773"
    ],
    "wof:name":"Jian'ao",
    "wof:placetype":"locality"
},
  "geometry": {"coordinates":[114.187,26.119],"type":"Point"}
}