{
  "type": "Feature",
  "properties": {
    "gn:admin1_code":"12.0",
    "gn:asciiname":"Damu",
    "gn:country_code":"CN",
    "gn:dem":99,
    "gn:feature_class":"P",
    "gn:feature_code":"PPLA4",
    "gn:name":"Damu",
    "gn:population":0,
    "gn:timezone":"Asia/Shanghai",
    "iso:country":"CN",
    "name:und_x_variant":[
        "Damu Xiang",
        "\u5927\u5e55\u4e61"
    ],
    "name:zho_x_preferred":[
        "Damu"
    ],
    "name:zho_x_variant":[
        "\u5927\u5e55"
    ],
    "wof:name":"Damu",
    "wof:placetype":"locality"
},
  "geometry": {"coordinates":[114.53912,29.80877000000001],"type":"Point"}
}