{
  "type": "Feature",
  "properties": {
    "gn:admin1_code":"8.0",
    "gn:asciiname":"Doujiatun",
    "gn:country_code":"CN",
    "gn:dem":167,
    "gn:feature_class":"P",
    "gn:feature_code":"PPL",
    "gn:name":"Doujiatun",
    "gn:population":0,
    "gn:timezone":"Asia/Shanghai",
    "iso:country":"CN",
    "name:zho_x_preferred":[
        "\u7aa6\u5bb6\u5c6f"
    ],
    "wof:name":"Doujiatun",
    "wof:placetype":"locality"
},
  "geometry": {"coordinates":[128.03513000000001,45.81011],"type":"Point"}
}