{
  "type": "Feature",
  "properties": {
    "gn:admin1_code":"4.0",
    "gn:asciiname":"Qingchuncun",
    "gn:country_code":"CN",
    "gn:dem":7,
    "gn:feature_class":"P",
    "gn:feature_code":"PPL",
    "gn:name":"Qingchuncun",
    "gn:population":0,
    "gn:timezone":"Asia/Shanghai",
    "iso:country":"CN",
    "name:zho_x_preferred":[
        "\u9752\u6625\u6751"
    ],
    "wof:name":"Qingchuncun",
    "wof:placetype":"locality"
},
  "geometry": {"coordinates":[118.98029,34.04492],"type":"Point"}
}