{
  "type": "Feature",
  "properties": {
    "gn:admin1_code":"29.0",
    "gn:asciiname":"Changjiaozhai",
    "gn:country_code":"CN",
    "gn:dem":1963,
    "gn:feature_class":"P",
    "gn:feature_code":"PPL",
    "gn:name":"Changjiaozhai",
    "gn:population":0,
    "gn:timezone":"Asia/Shanghai",
    "iso:country":"CN",
    "name:zho_x_preferred":[
        "\u957f\u811a\u5be8"
    ],
    "wof:name":"Changjiaozhai",
    "wof:placetype":"locality"
},
  "geometry": {"coordinates":[99.7252,27.1379],"type":"Point"}
}