{
  "type": "Feature",
  "properties": {
    "gn:admin1_code":"16",
    "gn:asciiname":"Tongren",
    "gn:country_code":"CN",
    "gn:dem":429,
    "gn:feature_class":"P",
    "gn:feature_code":"PPL",
    "gn:name":"Tongren",
    "gn:population":0,
    "gn:timezone":"Asia/Shanghai",
    "iso:country":"CN",
    "name:zho_x_preferred":[
        "\u540c\u4ec1"
    ],
    "wof:name":"Tongren",
    "wof:placetype":"locality"
},
  "geometry": {"coordinates":[111.24299999999999,25.7227],"type":"Point"}
}