{
  "type": "Feature",
  "properties": {
    "gn:admin1_code":"16",
    "gn:asciiname":"Tongren",
    "gn:country_code":"CN",
    "gn:dem":429,
    "gn:feature_class":"P",
    "gn:feature_code":"PPL",
    "gn:name":"Tongren",
    "gn:population":0,
    "gn:timezone":"Asia/Shanghai",
    "iso:country":"CN",
    "name:ara_x_preferred":[
        "\u062a\u0648\u0646\u063a\u0631\u0627\u0646"
    ],
    "name:cdo_x_preferred":[
        "D\u00e8\u0324ng-\u00ecng"
    ],
    "name:ceb_x_preferred":[
        "Tongren Diqu"
    ],
    "name:cym_x_preferred":[
        "Tongren"
    ],
    "name:dan_x_preferred":[
        "Tongren"
    ],
    "name:deu_x_preferred":[
        "Tongren"
    ],
    "name:eus_x_preferred":[
        "Tongren"
    ],
    "name:fas_x_preferred":[
        "\u062a\u0627\u0646\u06af\u0631\u0646"
    ],
    "name:fin_x_preferred":[
        "Tongren"
    ],
    "name:ita_x_preferred":[
        "Tongren"
    ],
    "name:jpn_x_preferred":[
        "\u9285\u4ec1\u5e02"
    ],
    "name:kik_x_preferred":[
        "Tongren"
    ],
    "name:kor_x_preferred":[
        "\ud241\ub7f0\uc2dc"
    ],
    "name:mlg_x_preferred":[
        "Tongren"
    ],
    "name:nld_x_preferred":[
        "Tongren"
    ],
    "name:nno_x_preferred":[
        "Tongren"
    ],
    "name:nor_x_preferred":[
        "Tongren"
    ],
    "name:pol_x_preferred":[
        "Tongren"
    ],
    "name:rus_x_preferred":[
        "\u0422\u0443\u043d\u0436\u044d\u043d\u044c"
    ],
    "name:spa_x_preferred":[
        "Tong'r\u00e9n"
    ],
    "name:swe_x_preferred":[
        "Tongren"
    ],
    "name:tur_x_preferred":[
        "Tongren"
    ],
    "name:urd_x_preferred":[
        "\u062a\u0648\u0646\u06af\u0631\u0646"
    ],
    "name:vie_x_preferred":[
        "\u0110\u1ed3ng Nh\u00e2n"
    ],
    "name:zho_x_preferred":[
        "\u540c\u4ec1"
    ],
    "name:zho_x_variant":[
        "\u94dc\u4ec1\u5e02"
    ],
    "wof:name":"Tongren",
    "wof:placetype":"locality"
},
  "geometry": {"coordinates":[111.24299999999999,25.7227],"type":"Point"}
}