{
  "type": "Feature",
  "properties": {
    "gn:admin1_code":"32.0",
    "gn:asciiname":"Zhagu",
    "gn:country_code":"CN",
    "gn:dem":448,
    "gn:feature_class":"P",
    "gn:feature_code":"PPL",
    "gn:name":"Zhagu",
    "gn:population":0,
    "gn:timezone":"Asia/Shanghai",
    "iso:country":"CN",
    "name:zho_x_preferred":[
        "\u69a8\u9f13"
    ],
    "wof:name":"Zhagu",
    "wof:placetype":"locality"
},
  "geometry": {"coordinates":[103.9894,29.08753],"type":"Point"}
}