{
  "type": "Feature",
  "properties": {
    "gn:admin1_code":"28",
    "gn:asciiname":"Changliuzhuang",
    "gn:country_code":"CN",
    "gn:dem":5,
    "gn:feature_class":"P",
    "gn:feature_code":"PPL",
    "gn:name":"Changliuzhuang",
    "gn:population":0,
    "gn:timezone":"Asia/Shanghai",
    "iso:country":"CN",
    "name:zho_x_preferred":[
        "\u5e38\u6d41\u5e84"
    ],
    "wof:name":"Changliuzhuang",
    "wof:placetype":"locality"
},
  "geometry": {"coordinates":[117.23542,38.81964],"type":"Point"}
}