{
  "type": "Feature",
  "properties": {
    "gn:admin1_code":"19.0",
    "gn:asciiname":"Xiamatai",
    "gn:country_code":"CN",
    "gn:dem":11,
    "gn:feature_class":"P",
    "gn:feature_code":"PPL",
    "gn:name":"Xiamatai",
    "gn:population":0,
    "gn:timezone":"Asia/Shanghai",
    "iso:country":"CN",
    "name:und_x_variant":[
        "\u4e0b\u9a6c\u53f0"
    ],
    "name:zho_x_preferred":[
        "\u4e0b\u9a6c\u53f0"
    ],
    "wof:name":"Xiamatai",
    "wof:placetype":"locality"
},
  "geometry": {"coordinates":[121.56135999999999,41.22712],"type":"Point"}
}