{
  "type": "Feature",
  "properties": {
    "gn:admin1_code":"7.0",
    "gn:asciiname":"Cunxiacun",
    "gn:country_code":"CN",
    "gn:dem":25,
    "gn:feature_class":"P",
    "gn:feature_code":"PPL",
    "gn:name":"Cunxiacun",
    "gn:population":0,
    "gn:timezone":"Asia/Shanghai",
    "iso:country":"CN",
    "name:zho_x_preferred":[
        "\u6751\u4e0b\u6751"
    ],
    "wof:name":"Cunxiacun",
    "wof:placetype":"locality"
},
  "geometry": {"coordinates":[118.81197,25.03103],"type":"Point"}
}