{
  "type": "Feature",
  "properties": {
    "gn:admin1_code":"32.0",
    "gn:asciiname":"Ganjiawan",
    "gn:country_code":"CN",
    "gn:dem":788,
    "gn:feature_class":"P",
    "gn:feature_code":"PPL",
    "gn:name":"Ganjiawan",
    "gn:population":0,
    "gn:timezone":"Asia/Shanghai",
    "iso:country":"CN",
    "name:zho_x_preferred":[
        "\u5e72\u5bb6\u6e7e"
    ],
    "wof:name":"Ganjiawan",
    "wof:placetype":"locality"
},
  "geometry": {"coordinates":[104.72,28.0758],"type":"Point"}
}