{
  "type": "Feature",
  "properties": {
    "gn:admin1_code":"7",
    "gn:asciiname":"Xiaxiong",
    "gn:country_code":"CN",
    "gn:dem":11,
    "gn:feature_class":"P",
    "gn:feature_code":"PPL",
    "gn:name":"Xiaxiong",
    "gn:population":0,
    "gn:timezone":"Asia/Shanghai",
    "iso:country":"CN",
    "name:zho_x_preferred":[
        "\u4e0b\u96c4"
    ],
    "wof:name":"Xiaxiong",
    "wof:placetype":"locality"
},
  "geometry": {"coordinates":[117.75238,24.31064],"type":"Point"}
}