{
  "type": "Feature",
  "properties": {
    "gn:admin1_code":"26.0",
    "gn:asciiname":"Dayangshu",
    "gn:country_code":"CN",
    "gn:dem":1555,
    "gn:feature_class":"P",
    "gn:feature_code":"PPL",
    "gn:name":"Dayangshu",
    "gn:population":0,
    "gn:timezone":"Asia/Shanghai",
    "iso:country":"CN",
    "name:zho_x_preferred":[
        "\u5927\u6768\u6811"
    ],
    "wof:name":"Dayangshu",
    "wof:placetype":"locality"
},
  "geometry": {"coordinates":[109.84643,35.68899000000001],"type":"Point"}
}