{
  "type": "Feature",
  "properties": {
    "gn:admin1_code":"20",
    "gn:asciiname":"Dagat",
    "gn:cc2":"CN",
    "gn:country_code":"CN",
    "gn:dem":1384,
    "gn:feature_class":"P",
    "gn:feature_code":"PPL",
    "gn:name":"Dagat",
    "gn:population":0,
    "gn:timezone":"Asia/Shanghai",
    "iso:country":"CN",
    "name:und_x_variant":[
        "Ta-kai-t\u2019an",
        "Dagat Xiang",
        "Dagaitan",
        "Dagat"
    ],
    "wof:name":"Dagat",
    "wof:placetype":"locality"
},
  "geometry": {"coordinates":[114.45806,42.08722],"type":"Point"}
}