{
  "type": "Feature",
  "properties": {
    "gn:admin1_code":"26.0",
    "gn:asciiname":"Xigoukoucun",
    "gn:country_code":"CN",
    "gn:dem":592,
    "gn:feature_class":"P",
    "gn:feature_code":"PPL",
    "gn:name":"Xigoukoucun",
    "gn:population":0,
    "gn:timezone":"Asia/Shanghai",
    "iso:country":"CN",
    "name:und_x_variant":[
        "Hsi-kou-k\u2019ou",
        "Xigoukou",
        "Xigoukoucun"
    ],
    "name:zho_x_preferred":[
        "\u897f\u6c9f\u53e3\u6751"
    ],
    "wof:name":"Xigoukoucun",
    "wof:placetype":"locality"
},
  "geometry": {"coordinates":[109.72418,33.44309000000001],"type":"Point"}
}