{
  "type": "Feature",
  "properties": {
    "gn:admin1_code":"21.0",
    "gn:asciiname":"Mashagou",
    "gn:country_code":"CN",
    "gn:dem":1437,
    "gn:feature_class":"P",
    "gn:feature_code":"PPL",
    "gn:name":"Mashagou",
    "gn:population":0,
    "gn:timezone":"Asia/Shanghai",
    "iso:country":"CN",
    "name:und_x_variant":[
        "\u9ebb\u6c99\u6c9f"
    ],
    "name:zho_x_preferred":[
        "\u9ebb\u6c99\u6c9f"
    ],
    "wof:name":"Mashagou",
    "wof:placetype":"locality"
},
  "geometry": {"coordinates":[106.06048,36.70033],"type":"Point"}
}