{
  "type": "Feature",
  "properties": {
    "gn:admin1_code":"15.0",
    "gn:asciiname":"Dalushang",
    "gn:country_code":"CN",
    "gn:dem":1090,
    "gn:feature_class":"P",
    "gn:feature_code":"PPL",
    "gn:name":"Dalushang",
    "gn:population":0,
    "gn:timezone":"Asia/Shanghai",
    "iso:country":"CN",
    "name:und_x_variant":[
        "\u5927\u8def\u4e0a"
    ],
    "wof:name":"Dalushang",
    "wof:placetype":"locality"
},
  "geometry": {"coordinates":[105.48134,33.594],"type":"Point"}
}