{
  "type": "Feature",
  "properties": {
    "gn:admin1_code":"6.0",
    "gn:asciiname":"Langjia",
    "gn:country_code":"CN",
    "gn:dem":2468,
    "gn:feature_class":"P",
    "gn:feature_code":"PPL",
    "gn:name":"Langjia",
    "gn:population":0,
    "gn:timezone":"Asia/Shanghai",
    "iso:country":"CN",
    "name:und_x_variant":[
        "\u6d6a\u52a0"
    ],
    "wof:name":"Langjia",
    "wof:placetype":"locality"
},
  "geometry": {"coordinates":[102.11089,35.61082000000001],"type":"Point"}
}