{
  "type": "Feature",
  "properties": {
    "gn:admin1_code":"32.0",
    "gn:asciiname":"Jiyi",
    "gn:country_code":"CN",
    "gn:dem":3809,
    "gn:feature_class":"P",
    "gn:feature_code":"PPL",
    "gn:name":"Jiyi",
    "gn:population":0,
    "gn:timezone":"Asia/Shanghai",
    "iso:country":"CN",
    "name:zho_x_preferred":[
        "\u5409\u4e59"
    ],
    "wof:name":"Jiyi",
    "wof:placetype":"locality"
},
  "geometry": {"coordinates":[100.23399999999999,29.1033],"type":"Point"}
}