{
  "type": "Feature",
  "properties": {
    "gn:admin1_code":"10",
    "gn:asciiname":"Xigangou",
    "gn:country_code":"CN",
    "gn:dem":622,
    "gn:feature_class":"P",
    "gn:feature_code":"PPL",
    "gn:name":"Xigangou",
    "gn:population":0,
    "gn:timezone":"Asia/Shanghai",
    "iso:country":"CN",
    "name:zho_x_preferred":[
        "\u897f\u5e72\u6c9f"
    ],
    "wof:name":"Xigangou",
    "wof:placetype":"locality"
},
  "geometry": {"coordinates":[118.45882,40.91272],"type":"Point"}
}