{
  "type": "Feature",
  "properties": {
    "gn:admin1_code":"26.0",
    "gn:asciiname":"Lizhaizi",
    "gn:country_code":"CN",
    "gn:dem":1712,
    "gn:feature_class":"P",
    "gn:feature_code":"PPL",
    "gn:name":"Lizhaizi",
    "gn:population":0,
    "gn:timezone":"Asia/Shanghai",
    "iso:country":"CN",
    "name:zho_x_preferred":[
        "\u674e\u5be8\u5b50"
    ],
    "wof:name":"Lizhaizi",
    "wof:placetype":"locality"
},
  "geometry": {"coordinates":[107.34134,37.31486],"type":"Point"}
}