{
  "type": "Feature",
  "properties": {
    "gn:admin1_code":"07",
    "gn:asciiname":"Jimei",
    "gn:country_code":"CN",
    "gn:dem":6,
    "gn:feature_class":"P",
    "gn:feature_code":"PPL",
    "gn:name":"Jimei",
    "gn:population":0,
    "gn:timezone":"Asia/Shanghai",
    "iso:country":"CN",
    "name:und_x_variant":[
        "Chi-mei",
        "\u96c6\u7f8e",
        "Jimei"
    ],
    "wof:name":"Jimei",
    "wof:placetype":"locality"
},
  "geometry": {"coordinates":[118.09559,24.56048],"type":"Point"}
}