{
  "type": "Feature",
  "properties": {
    "gn:admin1_code":"1.0",
    "gn:asciiname":"Zhenrencun",
    "gn:country_code":"CN",
    "gn:dem":93,
    "gn:feature_class":"P",
    "gn:feature_code":"PPL",
    "gn:name":"Zhenrencun",
    "gn:population":0,
    "gn:timezone":"Asia/Shanghai",
    "iso:country":"CN",
    "name:zho_x_preferred":[
        "\u771f\u4eba\u6751"
    ],
    "name:zho_x_variant":[
        "\u771f\u4ec1\u6751"
    ],
    "wof:name":"Zhenrencun",
    "wof:placetype":"locality"
},
  "geometry": {"coordinates":[116.57629,31.24011],"type":"Point"}
}