{
  "type": "Feature",
  "properties": {
    "gn:admin1_code":"19.0",
    "gn:asciiname":"Beisantai",
    "gn:country_code":"CN",
    "gn:dem":25,
    "gn:feature_class":"P",
    "gn:feature_code":"PPL",
    "gn:name":"Beisantai",
    "gn:population":0,
    "gn:timezone":"Asia/Shanghai",
    "iso:country":"CN",
    "name:und_x_variant":[
        "\u5317\u4e09\u53f0"
    ],
    "name:zho_x_preferred":[
        "\u5317\u4e09\u53f0"
    ],
    "wof:name":"Beisantai",
    "wof:placetype":"locality"
},
  "geometry": {"coordinates":[123.05992000000001,41.6274],"type":"Point"}
}