{
  "type": "Feature",
  "properties": {
    "gn:admin1_code":"10",
    "gn:asciiname":"Zhangxiangcui",
    "gn:country_code":"CN",
    "gn:dem":18,
    "gn:feature_class":"P",
    "gn:feature_code":"PPL",
    "gn:name":"Zhangxiangcui",
    "gn:population":0,
    "gn:timezone":"Asia/Shanghai",
    "iso:country":"CN",
    "name:zho_x_preferred":[
        "\u4ec9\u7965\u5d14"
    ],
    "wof:name":"Zhangxiangcui",
    "wof:placetype":"locality"
},
  "geometry": {"coordinates":[116.86792,37.86235],"type":"Point"}
}