{
  "type": "Feature",
  "properties": {
    "gn:admin1_code":"9",
    "gn:asciiname":"Nanchaojie",
    "gn:country_code":"CN",
    "gn:dem":662,
    "gn:feature_class":"P",
    "gn:feature_code":"PPL",
    "gn:name":"Nanchaojie",
    "gn:population":0,
    "gn:timezone":"Asia/Shanghai",
    "iso:country":"CN",
    "wof:name":"Nanchaojie",
    "wof:placetype":"locality"
},
  "geometry": {"coordinates":[110.96472,34.48083],"type":"Point"}
}