{
  "type": "Feature",
  "properties": {
    "gn:admin1_code":"24.0",
    "gn:asciiname":"Mazhuangying",
    "gn:country_code":"CN",
    "gn:dem":735,
    "gn:feature_class":"P",
    "gn:feature_code":"PPL",
    "gn:name":"Mazhuangying",
    "gn:population":0,
    "gn:timezone":"Asia/Shanghai",
    "iso:country":"CN",
    "name:zho_x_preferred":[
        "\u9a6c\u5e84\u8425"
    ],
    "wof:name":"Mazhuangying",
    "wof:placetype":"locality"
},
  "geometry": {"coordinates":[111.8477,37.13096],"type":"Point"}
}