{
  "type": "Feature",
  "properties": {
    "gn:admin1_code":"18",
    "gn:asciiname":"Danjialing",
    "gn:country_code":"CN",
    "gn:dem":1352,
    "gn:feature_class":"P",
    "gn:feature_code":"PPL",
    "gn:name":"Danjialing",
    "gn:population":0,
    "gn:timezone":"Asia/Shanghai",
    "iso:country":"CN",
    "name:zho_x_preferred":[
        "\u5355\u5bb6\u5cad"
    ],
    "wof:name":"Danjialing",
    "wof:placetype":"locality"
},
  "geometry": {"coordinates":[105.482,27.7445],"type":"Point"}
}