{
  "type": "Feature",
  "properties": {
    "gn:admin1_code":"5.0",
    "gn:asciiname":"Longfeng",
    "gn:country_code":"CN",
    "gn:dem":636,
    "gn:feature_class":"P",
    "gn:feature_code":"PPL",
    "gn:name":"Longfeng",
    "gn:population":0,
    "gn:timezone":"Asia/Shanghai",
    "iso:country":"CN",
    "name:ceb_x_preferred":[
        "Longfeng"
    ],
    "name:deu_x_preferred":[
        "Longfeng"
    ],
    "name:mlg_x_preferred":[
        "Longfeng"
    ],
    "name:und_x_variant":[
        "\u9f99\u4e30"
    ],
    "wof:name":"Longfeng",
    "wof:placetype":"locality"
},
  "geometry": {"coordinates":[129.00963000000002,43.19974000000001],"type":"Point"}
}