{
  "type": "Feature",
  "properties": {
    "gn:admin1_code":"32.0",
    "gn:asciiname":"Xintangwan",
    "gn:country_code":"CN",
    "gn:dem":275,
    "gn:feature_class":"P",
    "gn:feature_code":"PPL",
    "gn:name":"Xintangwan",
    "gn:population":0,
    "gn:timezone":"Asia/Shanghai",
    "iso:country":"CN",
    "name:zho_x_preferred":[
        "\u65b0\u5858\u6e7e"
    ],
    "wof:name":"Xintangwan",
    "wof:placetype":"locality"
},
  "geometry": {"coordinates":[104.98924,29.13565],"type":"Point"}
}