{
  "type": "Feature",
  "properties": {
    "gn:admin1_code":"11.0",
    "gn:asciiname":"Tanjiawan",
    "gn:country_code":"CN",
    "gn:dem":113,
    "gn:feature_class":"P",
    "gn:feature_code":"PPL",
    "gn:name":"Tanjiawan",
    "gn:population":0,
    "gn:timezone":"Asia/Shanghai",
    "iso:country":"CN",
    "name:zho_x_preferred":[
        "\u8c2d\u5bb6\u6e7e"
    ],
    "wof:name":"Tanjiawan",
    "wof:placetype":"locality"
},
  "geometry": {"coordinates":[112.81214,27.27319],"type":"Point"}
}