{
  "type": "Feature",
  "properties": {
    "gn:admin1_code":"29.0",
    "gn:asciiname":"Xiaozhecha",
    "gn:country_code":"CN",
    "gn:dem":1338,
    "gn:feature_class":"P",
    "gn:feature_code":"PPL",
    "gn:name":"Xiaozhecha",
    "gn:population":0,
    "gn:timezone":"Asia/Shanghai",
    "iso:country":"CN",
    "name:zho_x_preferred":[
        "\u5c0f\u8005\u8336"
    ],
    "wof:name":"Xiaozhecha",
    "wof:placetype":"locality"
},
  "geometry": {"coordinates":[102.91200000000001,23.3466],"type":"Point"}
}