{
  "type": "Feature",
  "properties": {
    "gn:admin1_code":"30.0",
    "gn:asciiname":"Huangshidong",
    "gn:country_code":"CN",
    "gn:dem":403,
    "gn:feature_class":"P",
    "gn:feature_code":"PPL",
    "gn:name":"Huangshidong",
    "gn:population":0,
    "gn:timezone":"Asia/Shanghai",
    "iso:country":"CN",
    "name:zho_x_preferred":[
        "\u9ec4\u72ee\u6d1e"
    ],
    "wof:name":"Huangshidong",
    "wof:placetype":"locality"
},
  "geometry": {"coordinates":[112.94833,24.44861],"type":"Point"}
}