{
  "type": "Feature",
  "properties": {
    "gn:admin1_code":"20.0",
    "gn:asciiname":"Degejilehu",
    "gn:country_code":"CN",
    "gn:dem":413,
    "gn:feature_class":"P",
    "gn:feature_code":"PPL",
    "gn:name":"Degejilehu",
    "gn:population":0,
    "gn:timezone":"Asia/Shanghai",
    "iso:country":"CN",
    "name:zho_x_preferred":[
        "\u5fb7\u683c\u5409\u52d2\u80e1"
    ],
    "wof:name":"Degejilehu",
    "wof:placetype":"locality"
},
  "geometry": {"coordinates":[122.10209,47.39511],"type":"Point"}
}