{
  "type": "Feature",
  "properties": {
    "gn:admin1_code":"24.0",
    "gn:asciiname":"Quanyangtou",
    "gn:country_code":"CN",
    "gn:dem":1650,
    "gn:feature_class":"P",
    "gn:feature_code":"PPL",
    "gn:name":"Quanyangtou",
    "gn:population":0,
    "gn:timezone":"Asia/Shanghai",
    "iso:country":"CN",
    "name:und_x_variant":[
        "\u5168\u7f8a\u5934"
    ],
    "name:zho_x_preferred":[
        "\u5168\u7f8a\u5934"
    ],
    "wof:name":"Quanyangtou",
    "wof:placetype":"locality"
},
  "geometry": {"coordinates":[112.83969999999999,39.89297],"type":"Point"}
}