{
  "type": "Feature",
  "properties": {
    "gn:admin1_code":"11.0",
    "gn:asciiname":"Zimuchong",
    "gn:country_code":"CN",
    "gn:dem":394,
    "gn:feature_class":"P",
    "gn:feature_code":"PPL",
    "gn:name":"Zimuchong",
    "gn:population":0,
    "gn:timezone":"Asia/Shanghai",
    "iso:country":"CN",
    "name:zho_x_preferred":[
        "\u6893\u6728\u51b2"
    ],
    "wof:name":"Zimuchong",
    "wof:placetype":"locality"
},
  "geometry": {"coordinates":[110.49207,28.03703],"type":"Point"}
}