{
  "type": "Feature",
  "properties": {
    "gn:admin1_code":"16.0",
    "gn:asciiname":"Shijie",
    "gn:country_code":"CN",
    "gn:dem":352,
    "gn:feature_class":"P",
    "gn:feature_code":"PPL",
    "gn:name":"Shijie",
    "gn:population":0,
    "gn:timezone":"Asia/Shanghai",
    "iso:country":"CN",
    "name:deu_x_preferred":[
        "Shijie"
    ],
    "name:zho_x_preferred":[
        "\u4e16\u754c"
    ],
    "wof:name":"Shijie",
    "wof:placetype":"locality"
},
  "geometry": {"coordinates":[108.962,24.3761],"type":"Point"}
}