{
  "type": "Feature",
  "properties": {
    "gn:admin1_code":"4.0",
    "gn:asciiname":"Yudongcun",
    "gn:country_code":"CN",
    "gn:dem":8,
    "gn:feature_class":"P",
    "gn:feature_code":"PPL",
    "gn:name":"Yudongcun",
    "gn:population":0,
    "gn:timezone":"Asia/Shanghai",
    "iso:country":"CN",
    "name:zho_x_preferred":[
        "\u4f59\u4e1c\u6751"
    ],
    "wof:name":"Yudongcun",
    "wof:placetype":"locality"
},
  "geometry": {"coordinates":[119.20752,33.8457],"type":"Point"}
}