{
  "type": "Feature",
  "properties": {
    "gn:admin1_code":"7.0",
    "gn:asciiname":"Gaodongcun",
    "gn:country_code":"CN",
    "gn:dem":607,
    "gn:feature_class":"P",
    "gn:feature_code":"PPL",
    "gn:name":"Gaodongcun",
    "gn:population":0,
    "gn:timezone":"Asia/Shanghai",
    "iso:country":"CN",
    "name:zho_x_preferred":[
        "\u9ad8\u4e1c\u6751"
    ],
    "wof:name":"Gaodongcun",
    "wof:placetype":"locality"
},
  "geometry": {"coordinates":[117.01616,24.65623],"type":"Point"}
}