{
  "type": "Feature",
  "properties": {
    "gn:admin1_code":"3.0",
    "gn:asciiname":"Fenglong",
    "gn:country_code":"CN",
    "gn:dem":279,
    "gn:feature_class":"P",
    "gn:feature_code":"PPL",
    "gn:name":"Fenglong",
    "gn:population":0,
    "gn:timezone":"Asia/Shanghai",
    "iso:country":"CN",
    "name:und_x_variant":[
        "\u4e30\u9f99"
    ],
    "wof:name":"Fenglong",
    "wof:placetype":"locality"
},
  "geometry": {"coordinates":[115.79226,25.72744],"type":"Point"}
}