{
  "type": "Feature",
  "properties": {
    "gn:admin1_code":"10",
    "gn:asciiname":"Huihan",
    "gn:country_code":"CN",
    "gn:dem":1192,
    "gn:feature_class":"P",
    "gn:feature_code":"PPL",
    "gn:name":"Huihan",
    "gn:population":0,
    "gn:timezone":"Asia/Shanghai",
    "iso:country":"CN",
    "name:zho_x_preferred":[
        "\u56de\u6c49"
    ],
    "wof:name":"Huihan",
    "wof:placetype":"locality"
},
  "geometry": {"coordinates":[117.66795999999999,42.19413],"type":"Point"}
}