{
  "type": "Feature",
  "properties": {
    "gn:admin1_code":"2.0",
    "gn:asciiname":"Tianxinli",
    "gn:country_code":"CN",
    "gn:dem":7,
    "gn:feature_class":"P",
    "gn:feature_code":"PPL",
    "gn:name":"Tianxinli",
    "gn:population":0,
    "gn:timezone":"Asia/Shanghai",
    "iso:country":"CN",
    "name:und_x_variant":[
        "\u7530\u5fc3\u91cc"
    ],
    "wof:name":"Tianxinli",
    "wof:placetype":"locality"
},
  "geometry": {"coordinates":[120.37054999999999,30.49835],"type":"Point"}
}