{
  "type": "Feature",
  "properties": {
    "gn:admin1_code":"29",
    "gn:asciiname":"Malutang",
    "gn:country_code":"CN",
    "gn:dem":1568,
    "gn:feature_class":"P",
    "gn:feature_code":"PPL",
    "gn:name":"Malutang",
    "gn:population":0,
    "gn:timezone":"Asia/Shanghai",
    "iso:country":"CN",
    "name:zho_x_preferred":[
        "\u9a6c\u9e7f\u5858"
    ],
    "wof:name":"Malutang",
    "wof:placetype":"locality"
},
  "geometry": {"coordinates":[101.712,24.1495],"type":"Point"}
}