{
  "type": "Feature",
  "properties": {
    "gn:admin1_code":"30.0",
    "gn:asciiname":"Binheng",
    "gn:country_code":"CN",
    "gn:dem":25,
    "gn:feature_class":"P",
    "gn:feature_code":"PPLA4",
    "gn:name":"Binheng",
    "gn:population":0,
    "gn:timezone":"Asia/Shanghai",
    "iso:country":"CN",
    "name:und_x_variant":[
        "Binheng Zhen",
        "\u5bbe\u4ea8\u9547"
    ],
    "name:zho_x_preferred":[
        "\u5bbe\u4ea8"
    ],
    "wof:name":"Binheng",
    "wof:placetype":"locality"
},
  "geometry": {"coordinates":[112.42142,23.47065],"type":"Point"}
}