{
  "type": "Feature",
  "properties": {
    "gn:admin1_code":"33.0",
    "gn:asciiname":"Tieshi",
    "gn:country_code":"CN",
    "gn:dem":341,
    "gn:feature_class":"P",
    "gn:feature_code":"PPL",
    "gn:name":"Tieshi",
    "gn:population":0,
    "gn:timezone":"Asia/Shanghai",
    "iso:country":"CN",
    "name:zho_x_preferred":[
        "\u94c1\u77f3"
    ],
    "wof:name":"Tieshi",
    "wof:placetype":"locality"
},
  "geometry": {"coordinates":[108.27576999999999,30.46058],"type":"Point"}
}