{
  "type": "Feature",
  "properties": {
    "gn:admin1_code":"15.0",
    "gn:asciiname":"Hanjia'ao",
    "gn:country_code":"CN",
    "gn:dem":1531,
    "gn:feature_class":"P",
    "gn:feature_code":"PPL",
    "gn:name":"Hanjia\u2019ao",
    "gn:population":0,
    "gn:timezone":"Asia/Shanghai",
    "iso:country":"CN",
    "name:und_x_variant":[
        "Hanjia\u2019ao"
    ],
    "name:zho_x_preferred":[
        "\u97e9\u5bb6\u5773"
    ],
    "wof:name":"Hanjia'ao",
    "wof:placetype":"locality"
},
  "geometry": {"coordinates":[108.437,35.549],"type":"Point"}
}