{
  "type": "Feature",
  "properties": {
    "gn:admin1_code":"29.0",
    "gn:asciiname":"Yageluo",
    "gn:country_code":"CN",
    "gn:dem":2432,
    "gn:feature_class":"P",
    "gn:feature_code":"PPL",
    "gn:name":"Yageluo",
    "gn:population":0,
    "gn:timezone":"Asia/Shanghai",
    "iso:country":"CN",
    "name:zho_x_preferred":[
        "\u4e2b\u6b4c\u7f57"
    ],
    "wof:name":"Yageluo",
    "wof:placetype":"locality"
},
  "geometry": {"coordinates":[100.58499999999999,26.8948],"type":"Point"}
}