{
  "type": "Feature",
  "properties": {
    "gn:admin1_code":"32.0",
    "gn:asciiname":"Shuilou",
    "gn:country_code":"CN",
    "gn:dem":2474,
    "gn:feature_class":"P",
    "gn:feature_code":"PPL",
    "gn:name":"Shuilou",
    "gn:population":0,
    "gn:timezone":"Asia/Shanghai",
    "iso:country":"CN",
    "name:zho_x_preferred":[
        "\u6c34\u6d1b"
    ],
    "wof:name":"Shuilou",
    "wof:placetype":"locality"
},
  "geometry": {"coordinates":[100.65326,28.28884],"type":"Point"}
}