{
  "type": "Feature",
  "properties": {
    "gn:admin1_code":"30",
    "gn:asciiname":"Liuzengcun",
    "gn:country_code":"CN",
    "gn:dem":55,
    "gn:feature_class":"P",
    "gn:feature_code":"PPL",
    "gn:name":"Liuzengcun",
    "gn:population":0,
    "gn:timezone":"Asia/Urumqi",
    "iso:country":"CN",
    "name:zho_x_preferred":[
        "\u516d\u8d60\u6751"
    ],
    "wof:name":"Liuzengcun",
    "wof:placetype":"locality"
},
  "geometry": {"coordinates":[110.3806,22.00941],"type":"Point"}
}