{
  "type": "Feature",
  "properties": {
    "gn:admin1_code":"2.0",
    "gn:asciiname":"Jiaoshanwu",
    "gn:country_code":"CN",
    "gn:dem":96,
    "gn:feature_class":"P",
    "gn:feature_code":"PPL",
    "gn:name":"Jiaoshanwu",
    "gn:population":0,
    "gn:timezone":"Asia/Shanghai",
    "iso:country":"CN",
    "name:zho_x_preferred":[
        "\u6912\u5c71\u575e"
    ],
    "wof:name":"Jiaoshanwu",
    "wof:placetype":"locality"
},
  "geometry": {"coordinates":[120.10455,29.60574],"type":"Point"}
}