{
  "type": "Feature",
  "properties": {
    "gn:admin1_code":"12.0",
    "gn:asciiname":"Daliujiawan",
    "gn:country_code":"CN",
    "gn:dem":60,
    "gn:feature_class":"P",
    "gn:feature_code":"PPL",
    "gn:name":"Daliujiawan",
    "gn:population":0,
    "gn:timezone":"Asia/Shanghai",
    "iso:country":"CN",
    "name:zho_x_preferred":[
        "\u5927\u5218\u5bb6\u6e7e"
    ],
    "wof:name":"Daliujiawan",
    "wof:placetype":"locality"
},
  "geometry": {"coordinates":[112.70508999999998,31.24995],"type":"Point"}
}