{
  "type": "Feature",
  "properties": {
    "gn:admin1_code":"3.0",
    "gn:asciiname":"Yangfuping",
    "gn:country_code":"CN",
    "gn:dem":57,
    "gn:feature_class":"P",
    "gn:feature_code":"PPL",
    "gn:name":"Yangfuping",
    "gn:population":0,
    "gn:timezone":"Asia/Shanghai",
    "iso:country":"CN",
    "name:und_x_variant":[
        "\u6768\u5bcc\u576a"
    ],
    "wof:name":"Yangfuping",
    "wof:placetype":"locality"
},
  "geometry": {"coordinates":[117.66866,29.09326],"type":"Point"}
}