{
  "type": "Feature",
  "properties": {
    "gn:admin1_code":"32.0",
    "gn:asciiname":"Shuangdian",
    "gn:country_code":"CN",
    "gn:dem":829,
    "gn:feature_class":"P",
    "gn:feature_code":"PPL",
    "gn:name":"Shuangdian",
    "gn:population":0,
    "gn:timezone":"Asia/Shanghai",
    "iso:country":"CN",
    "name:zho_x_preferred":[
        "\u53cc\u7535"
    ],
    "wof:name":"Shuangdian",
    "wof:placetype":"locality"
},
  "geometry": {"coordinates":[104.261,31.6423],"type":"Point"}
}