{
  "type": "Feature",
  "properties": {
    "gn:admin1_code":"8.0",
    "gn:asciiname":"Jizhencun",
    "gn:country_code":"CN",
    "gn:dem":59,
    "gn:feature_class":"P",
    "gn:feature_code":"PPL",
    "gn:name":"Jizhencun",
    "gn:population":0,
    "gn:timezone":"Asia/Shanghai",
    "iso:country":"CN",
    "name:zho_x_preferred":[
        "\u5409\u73cd\u6751"
    ],
    "wof:name":"Jizhencun",
    "wof:placetype":"locality"
},
  "geometry": {"coordinates":[131.91776999999999,47.36268],"type":"Point"}
}