{
  "type": "Feature",
  "properties": {
    "gn:admin1_code":"1.0",
    "gn:asciiname":"Hezuocun",
    "gn:country_code":"CN",
    "gn:dem":12,
    "gn:feature_class":"P",
    "gn:feature_code":"PPL",
    "gn:name":"Hezuocun",
    "gn:population":0,
    "gn:timezone":"Asia/Shanghai",
    "iso:country":"CN",
    "name:zho_x_preferred":[
        "\u5408\u4f5c\u6751"
    ],
    "wof:name":"Hezuocun",
    "wof:placetype":"locality"
},
  "geometry": {"coordinates":[117.74999,30.96448],"type":"Point"}
}