{
  "type": "Feature",
  "properties": {
    "gn:admin1_code":"8.0",
    "gn:asciiname":"Xilijia",
    "gn:country_code":"CN",
    "gn:dem":172,
    "gn:feature_class":"P",
    "gn:feature_code":"PPL",
    "gn:name":"Xilijia",
    "gn:population":0,
    "gn:timezone":"Asia/Shanghai",
    "iso:country":"CN",
    "name:zho_x_preferred":[
        "\u897f\u674e\u5bb6"
    ],
    "wof:name":"Xilijia",
    "wof:placetype":"locality"
},
  "geometry": {"coordinates":[127.08448,45.008],"type":"Point"}
}