{
  "type": "Feature",
  "properties": {
    "gn:admin1_code":"32.0",
    "gn:asciiname":"Guodu",
    "gn:country_code":"CN",
    "gn:dem":3384,
    "gn:feature_class":"P",
    "gn:feature_code":"PPL",
    "gn:name":"Guodu",
    "gn:population":0,
    "gn:timezone":"Asia/Shanghai",
    "iso:country":"CN",
    "name:zho_x_preferred":[
        "\u8fc7\u90fd"
    ],
    "wof:name":"Guodu",
    "wof:placetype":"locality"
},
  "geometry": {"coordinates":[101.2188,30.16337],"type":"Point"}
}