{
  "type": "Feature",
  "properties": {
    "gn:admin1_code":"22",
    "gn:asciiname":"Shibadian",
    "gn:country_code":"CN",
    "gn:dem":36,
    "gn:feature_class":"P",
    "gn:feature_code":"PPL",
    "gn:name":"Shibadian",
    "gn:population":0,
    "gn:timezone":"Asia/Shanghai",
    "iso:country":"CN",
    "name:und_x_variant":[
        "Shibalidian"
    ],
    "name:zho_x_preferred":[
        "\u5341\u516b\u5e97"
    ],
    "wof:name":"Shibadian",
    "wof:placetype":"locality"
},
  "geometry": {"coordinates":[116.48278000000001,39.84278],"type":"Point"}
}