{
  "type": "Feature",
  "properties": {
    "gn:admin1_code":"19.0",
    "gn:asciiname":"Bawanggoucun",
    "gn:country_code":"CN",
    "gn:dem":289,
    "gn:feature_class":"P",
    "gn:feature_code":"PPL",
    "gn:name":"Bawanggoucun",
    "gn:population":0,
    "gn:timezone":"Asia/Shanghai",
    "iso:country":"CN",
    "name:zho_x_preferred":[
        "\u9738\u738b\u6c9f\u6751"
    ],
    "wof:name":"Bawanggoucun",
    "wof:placetype":"locality"
},
  "geometry": {"coordinates":[124.68600000000001,41.9685],"type":"Point"}
}