{
  "type": "Feature",
  "properties": {
    "gn:admin1_code":"20.0",
    "gn:asciiname":"Tuanjie Nongyedian",
    "gn:country_code":"CN",
    "gn:dem":693,
    "gn:feature_class":"P",
    "gn:feature_code":"PPL",
    "gn:name":"Tuanjie Nongyedian",
    "gn:population":0,
    "gn:timezone":"Asia/Shanghai",
    "iso:country":"CN",
    "name:zho_x_preferred":[
        "\u56e2\u7ed3\u519c\u4e1a\u70b9"
    ],
    "wof:name":"Tuanjie Nongyedian",
    "wof:placetype":"locality"
},
  "geometry": {"coordinates":[120.95780999999999,49.12971],"type":"Point"}
}