{
  "type": "Feature",
  "properties": {
    "gn:admin1_code":"4.0",
    "gn:asciiname":"Hengfeng",
    "gn:country_code":"CN",
    "gn:dem":3,
    "gn:feature_class":"P",
    "gn:feature_code":"PPL",
    "gn:name":"Hengfeng",
    "gn:population":0,
    "gn:timezone":"Asia/Shanghai",
    "iso:country":"CN",
    "name:und_x_variant":[
        "\u6052\u4e30"
    ],
    "wof:name":"Hengfeng",
    "wof:placetype":"locality"
},
  "geometry": {"coordinates":[121.75469,31.92655],"type":"Point"}
}