{
  "type": "Feature",
  "properties": {
    "gn:admin1_code":"2.0",
    "gn:asciiname":"Nanshan'ao",
    "gn:country_code":"CN",
    "gn:dem":66,
    "gn:feature_class":"P",
    "gn:feature_code":"PPL",
    "gn:name":"Nanshan\u2019ao",
    "gn:population":0,
    "gn:timezone":"Asia/Shanghai",
    "iso:country":"CN",
    "name:und_x_variant":[
        "Nanshan\u2019ao"
    ],
    "name:zho_x_preferred":[
        "\u5357\u5c71\u5c99"
    ],
    "wof:name":"Nanshan'ao",
    "wof:placetype":"locality"
},
  "geometry": {"coordinates":[121.41106000000001,28.24963],"type":"Point"}
}