{
  "type": "Feature",
  "properties": {
    "gn:admin1_code":"30",
    "gn:asciiname":"Shilou",
    "gn:country_code":"CN",
    "gn:dem":8,
    "gn:feature_class":"P",
    "gn:feature_code":"PPLA4",
    "gn:name":"Shilou",
    "gn:population":0,
    "gn:timezone":"Asia/Shanghai",
    "iso:country":"CN",
    "name:und_x_variant":[
        "Shih-lou",
        "Shilou",
        "\u77f3\u697c",
        "Shilou Zhen",
        "\u77f3\u697c\u9547"
    ],
    "wof:name":"Shilou",
    "wof:placetype":"locality"
},
  "geometry": {"coordinates":[113.48718,22.97341],"type":"Point"}
}