{
  "type": "Feature",
  "properties": {
    "gn:admin1_code":"25",
    "gn:asciiname":"Weifang",
    "gn:country_code":"CN",
    "gn:dem":73,
    "gn:feature_class":"P",
    "gn:feature_code":"PPL",
    "gn:name":"Weifang",
    "gn:population":0,
    "gn:timezone":"Asia/Shanghai",
    "iso:country":"CN",
    "name:afr_x_preferred":[
        "Weifang"
    ],
    "name:ara_x_preferred":[
        "\u064a\u0641\u0627\u0646\u063a"
    ],
    "name:cdo_x_preferred":[
        "M\u00ec-hu\u014fng"
    ],
    "name:ceb_x_preferred":[
        "Weifang"
    ],
    "name:ces_x_preferred":[
        "Wej-fang"
    ],
    "name:dan_x_preferred":[
        "Weifang"
    ],
    "name:deu_x_preferred":[
        "Weifang"
    ],
    "name:epo_x_preferred":[
        "Vejfang"
    ],
    "name:eus_x_preferred":[
        "Weifang"
    ],
    "name:fas_x_preferred":[
        "\u0648\u06cc\u0641\u0627\u0646\u06af"
    ],
    "name:fin_x_preferred":[
        "Weifang"
    ],
    "name:fra_x_preferred":[
        "Weifang"
    ],
    "name:ind_x_preferred":[
        "Weifang"
    ],
    "name:ita_x_preferred":[
        "Weifang"
    ],
    "name:jpn_x_preferred":[
        "\u30a4\u574a\u5e02"
    ],
    "name:kaz_x_preferred":[
        "\u0412\u044d\u0439\u0444\u0430\u043d"
    ],
    "name:kik_x_preferred":[
        "Weifang"
    ],
    "name:kor_x_preferred":[
        "\uc6e8\uc774\ud321\uc2dc"
    ],
    "name:lit_x_preferred":[
        "Veifangas"
    ],
    "name:mlg_x_preferred":[
        "Weifang"
    ],
    "name:nld_x_preferred":[
        "Weifang"
    ],
    "name:nno_x_preferred":[
        "Weifang"
    ],
    "name:nor_x_preferred":[
        "Weifang"
    ],
    "name:pol_x_preferred":[
        "Weifang"
    ],
    "name:por_x_preferred":[
        "Weifang"
    ],
    "name:rus_x_preferred":[
        "\u0412\u044d\u0439\u0444\u0430\u043d"
    ],
    "name:spa_x_preferred":[
        "Weifang"
    ],
    "name:srp_x_preferred":[
        "\u0412\u0435\u0458\u0444\u0430\u043d\u0433"
    ],
    "name:swe_x_preferred":[
        "Weifang"
    ],
    "name:tgl_x_preferred":[
        "Weifang"
    ],
    "name:tur_x_preferred":[
        "Weifang"
    ],
    "name:ukr_x_preferred":[
        "\u0412\u0435\u0439\u0444\u0430\u043d"
    ],
    "name:urd_x_preferred":[
        "\u0648\u06cc\u0641\u0627\u0646\u06af"
    ],
    "name:vie_x_preferred":[
        "Duy Ph\u01b0\u1eddng"
    ],
    "name:war_x_preferred":[
        "Weifang"
    ],
    "name:wuu_x_preferred":[
        "\u6f4d\u574a\u5e02"
    ],
    "name:zho_x_preferred":[
        "\u9b4f\u574a"
    ],
    "name:zho_x_variant":[
        "\u6f4d\u574a\u5e02"
    ],
    "wof:name":"Weifang",
    "wof:placetype":"locality"
},
  "geometry": {"coordinates":[116.60299999999999,36.1007],"type":"Point"}
}