{
  "type": "Feature",
  "properties": {
    "gn:admin1_code":"4.0",
    "gn:asciiname":"Yinmu",
    "gn:country_code":"CN",
    "gn:dem":5,
    "gn:feature_class":"P",
    "gn:feature_code":"PPL",
    "gn:name":"Yinmu",
    "gn:population":0,
    "gn:timezone":"Asia/Shanghai",
    "iso:country":"CN",
    "name:zho_x_preferred":[
        "\u94f6\u7a46"
    ],
    "wof:name":"Yinmu",
    "wof:placetype":"locality"
},
  "geometry": {"coordinates":[120.17343,32.50534],"type":"Point"}
}