{
  "type": "Feature",
  "properties": {
    "gn:admin1_code":"29.0",
    "gn:asciiname":"Yinjia Wanzi",
    "gn:country_code":"CN",
    "gn:dem":2241,
    "gn:feature_class":"P",
    "gn:feature_code":"PPL",
    "gn:name":"Yinjia Wanzi",
    "gn:population":0,
    "gn:timezone":"Asia/Shanghai",
    "iso:country":"CN",
    "name:zho_x_preferred":[
        "\u6bb7\u5bb6\u6e7e\u5b50"
    ],
    "wof:name":"Yinjia Wanzi",
    "wof:placetype":"locality"
},
  "geometry": {"coordinates":[103.21299999999999,27.072],"type":"Point"}
}