{
  "type": "Feature",
  "properties": {
    "gn:admin1_code":"18",
    "gn:asciiname":"Gaishang",
    "gn:country_code":"CN",
    "gn:dem":1062,
    "gn:feature_class":"P",
    "gn:feature_code":"PPL",
    "gn:name":"Gaishang",
    "gn:population":0,
    "gn:timezone":"Asia/Shanghai",
    "iso:country":"CN",
    "name:zho_x_preferred":[
        "\u76d6\u4e0a"
    ],
    "wof:name":"Gaishang",
    "wof:placetype":"locality"
},
  "geometry": {"coordinates":[106.81699999999999,25.6066],"type":"Point"}
}