{
  "type": "Feature",
  "properties": {
    "gn:admin1_code":"4.0",
    "gn:asciiname":"Lizhaicun",
    "gn:country_code":"CN",
    "gn:dem":10,
    "gn:feature_class":"P",
    "gn:feature_code":"PPL",
    "gn:name":"Lizhaicun",
    "gn:population":0,
    "gn:timezone":"Asia/Shanghai",
    "iso:country":"CN",
    "name:zho_x_preferred":[
        "\u674e\u5b85\u6751"
    ],
    "wof:name":"Lizhaicun",
    "wof:placetype":"locality"
},
  "geometry": {"coordinates":[119.08629999999999,34.9397],"type":"Point"}
}