{
  "type": "Feature",
  "properties": {
    "gn:admin1_code":"4.0",
    "gn:asciiname":"Jiandong Nongchang",
    "gn:country_code":"CN",
    "gn:dem":3,
    "gn:feature_class":"P",
    "gn:feature_code":"PPLF",
    "gn:name":"Jiandong Nongchang",
    "gn:population":0,
    "gn:timezone":"Asia/Shanghai",
    "iso:country":"CN",
    "name:und_x_variant":[
        "\u5251\u4e1c\u519c\u573a"
    ],
    "wof:name":"Jiandong Nongchang",
    "wof:placetype":"locality"
},
  "geometry": {"coordinates":[120.80973,33.0386],"type":"Point"}
}