{
  "type": "Feature",
  "properties": {
    "gn:admin1_code":"30.0",
    "gn:asciiname":"Nanzhu",
    "gn:country_code":"CN",
    "gn:dem":2,
    "gn:feature_class":"P",
    "gn:feature_code":"PPL",
    "gn:name":"Nanzhu",
    "gn:population":0,
    "gn:timezone":"Asia/Shanghai",
    "iso:country":"CN",
    "name:zho_x_preferred":[
        "\u5357\u7af9"
    ],
    "wof:name":"Nanzhu",
    "wof:placetype":"locality"
},
  "geometry": {"coordinates":[112.93120999999999,22.49786],"type":"Point"}
}