{
  "type": "Feature",
  "properties": {
    "gn:admin1_code":"02",
    "gn:asciiname":"Man'aocun",
    "gn:country_code":"CN",
    "gn:dem":22,
    "gn:feature_class":"P",
    "gn:feature_code":"PPL",
    "gn:name":"Man\u2019aocun",
    "gn:population":0,
    "gn:timezone":"Asia/Shanghai",
    "iso:country":"CN",
    "name:und_x_variant":[
        "Man-tou",
        "\u66fc\u5c99",
        "Man\u2019aocun"
    ],
    "name:zho_x_preferred":[
        "Man\u2019ao"
    ],
    "name:zho_x_variant":[
        "\u66fc\u5c99",
        "\u66fc\u5c99\u6751"
    ],
    "wof:name":"Man'aocun",
    "wof:placetype":"locality"
},
  "geometry": {"coordinates":[121.43622000000001,29.13975],"type":"Point"}
}