{
  "type": "Feature",
  "properties": {
    "gn:admin1_code":"29",
    "gn:asciiname":"Xiapuchang",
    "gn:country_code":"CN",
    "gn:dem":1427,
    "gn:feature_class":"P",
    "gn:feature_code":"PPL",
    "gn:name":"Xiapuchang",
    "gn:population":0,
    "gn:timezone":"Asia/Shanghai",
    "iso:country":"CN",
    "name:zho_x_preferred":[
        "\u4e0b\u666e\u5382"
    ],
    "wof:name":"Xiapuchang",
    "wof:placetype":"locality"
},
  "geometry": {"coordinates":[102.00381,24.81651],"type":"Point"}
}