{
  "type": "Feature",
  "properties": {
    "gn:admin1_code":"33.0",
    "gn:asciiname":"Chaoyangping",
    "gn:country_code":"CN",
    "gn:dem":2085,
    "gn:feature_class":"P",
    "gn:feature_code":"PPL",
    "gn:name":"Chaoyangping",
    "gn:population":0,
    "gn:timezone":"Asia/Shanghai",
    "iso:country":"CN",
    "name:zho_x_preferred":[
        "\u671d\u9633\u576a"
    ],
    "wof:name":"Chaoyangping",
    "wof:placetype":"locality"
},
  "geometry": {"coordinates":[110.14675,31.29053],"type":"Point"}
}