{
  "type": "Feature",
  "properties": {
    "gn:admin1_code":"11.0",
    "gn:asciiname":"Jinzipo",
    "gn:country_code":"CN",
    "gn:dem":387,
    "gn:feature_class":"P",
    "gn:feature_code":"PPL",
    "gn:name":"Jinzipo",
    "gn:population":0,
    "gn:timezone":"Asia/Shanghai",
    "iso:country":"CN",
    "name:zho_x_preferred":[
        "\u91d1\u5b50\u5761"
    ],
    "wof:name":"Jinzipo",
    "wof:placetype":"locality"
},
  "geometry": {"coordinates":[109.74372,27.57497],"type":"Point"}
}