{
  "type": "Feature",
  "properties": {
    "gn:admin1_code":"30",
    "gn:asciiname":"Shangxikeng",
    "gn:country_code":"CN",
    "gn:dem":285,
    "gn:feature_class":"P",
    "gn:feature_code":"PPL",
    "gn:name":"Shangxikeng",
    "gn:population":0,
    "gn:timezone":"Asia/Shanghai",
    "iso:country":"CN",
    "name:zho_x_preferred":[
        "\u4e0a\u897f\u5751"
    ],
    "wof:name":"Shangxikeng",
    "wof:placetype":"locality"
},
  "geometry": {"coordinates":[116.58093,24.43722],"type":"Point"}
}