{
  "type": "Feature",
  "properties": {
    "gn:admin1_code":"7.0",
    "gn:asciiname":"Gaofeng",
    "gn:country_code":"CN",
    "gn:dem":884,
    "gn:feature_class":"P",
    "gn:feature_code":"PPL",
    "gn:name":"Gaofeng",
    "gn:population":0,
    "gn:timezone":"Asia/Shanghai",
    "iso:country":"CN",
    "name:und_x_variant":[
        "\u9ad8\u5cf0",
        "Gaofeng"
    ],
    "wof:name":"Gaofeng",
    "wof:placetype":"locality"
},
  "geometry": {"coordinates":[119.74415999999999,27.15748],"type":"Point"}
}