{
  "type": "Feature",
  "properties": {
    "gn:admin1_code":"8.0",
    "gn:asciiname":"Hongyan Hougou",
    "gn:country_code":"CN",
    "gn:dem":449,
    "gn:feature_class":"P",
    "gn:feature_code":"PPL",
    "gn:name":"Hongyan Hougou",
    "gn:population":0,
    "gn:timezone":"Asia/Shanghai",
    "iso:country":"CN",
    "name:zho_x_preferred":[
        "\u7ea2\u5ca9\u540e\u6c9f"
    ],
    "wof:name":"Hongyan Hougou",
    "wof:placetype":"locality"
},
  "geometry": {"coordinates":[130.36351000000002,44.49311],"type":"Point"}
}