{
  "type": "Feature",
  "properties": {
    "gn:admin1_code":"11.0",
    "gn:asciiname":"Shangbaitu",
    "gn:country_code":"CN",
    "gn:dem":940,
    "gn:feature_class":"P",
    "gn:feature_code":"PPL",
    "gn:name":"Shangbaitu",
    "gn:population":0,
    "gn:timezone":"Asia/Shanghai",
    "iso:country":"CN",
    "name:zho_x_preferred":[
        "\u4e0a\u767d\u571f"
    ],
    "wof:name":"Shangbaitu",
    "wof:placetype":"locality"
},
  "geometry": {"coordinates":[110.79043,27.67329],"type":"Point"}
}