{
  "type": "Feature",
  "properties": {
    "gn:admin1_code":"12.0",
    "gn:asciiname":"Maodaowan",
    "gn:country_code":"CN",
    "gn:dem":203,
    "gn:feature_class":"P",
    "gn:feature_code":"PPL",
    "gn:name":"Maodaowan",
    "gn:population":0,
    "gn:timezone":"Asia/Shanghai",
    "iso:country":"CN",
    "name:zho_x_preferred":[
        "\u6bdb\u9053\u6e7e"
    ],
    "wof:name":"Maodaowan",
    "wof:placetype":"locality"
},
  "geometry": {"coordinates":[111.33418,32.05544],"type":"Point"}
}