{
  "type": "Feature",
  "properties": {
    "gn:admin1_code":"3.0",
    "gn:asciiname":"Shiling Wangjia",
    "gn:country_code":"CN",
    "gn:dem":74,
    "gn:feature_class":"P",
    "gn:feature_code":"PPL",
    "gn:name":"Shiling Wangjia",
    "gn:population":0,
    "gn:timezone":"Asia/Shanghai",
    "iso:country":"CN",
    "name:zho_x_preferred":[
        "\u77f3\u5cad\u6c6a\u5bb6"
    ],
    "wof:name":"Shiling Wangjia",
    "wof:placetype":"locality"
},
  "geometry": {"coordinates":[117.17095,28.13768],"type":"Point"}
}