{
  "type": "Feature",
  "properties": {
    "gn:admin1_code":"29.0",
    "gn:asciiname":"Masangqing",
    "gn:country_code":"CN",
    "gn:dem":1796,
    "gn:feature_class":"P",
    "gn:feature_code":"PPL",
    "gn:name":"Masangqing",
    "gn:population":0,
    "gn:timezone":"Asia/Shanghai",
    "iso:country":"CN",
    "name:zho_x_preferred":[
        "\u9a6c\u6851\u7b90"
    ],
    "wof:name":"Masangqing",
    "wof:placetype":"locality"
},
  "geometry": {"coordinates":[103.518,23.5726],"type":"Point"}
}