{
  "type": "Feature",
  "properties": {
    "gn:admin1_code":"11.0",
    "gn:asciiname":"Shangyawu",
    "gn:country_code":"CN",
    "gn:dem":496,
    "gn:feature_class":"P",
    "gn:feature_code":"PPL",
    "gn:name":"Shangyawu",
    "gn:population":0,
    "gn:timezone":"Asia/Shanghai",
    "iso:country":"CN",
    "name:zho_x_preferred":[
        "\u4e0a\u7259\u543e"
    ],
    "wof:name":"Shangyawu",
    "wof:placetype":"locality"
},
  "geometry": {"coordinates":[109.5896,28.893],"type":"Point"}
}