{
  "type": "Feature",
  "properties": {
    "gn:admin1_code":"12.0",
    "gn:asciiname":"Meishanya",
    "gn:country_code":"CN",
    "gn:dem":1498,
    "gn:feature_class":"P",
    "gn:feature_code":"PPL",
    "gn:name":"Meishanya",
    "gn:population":0,
    "gn:timezone":"Asia/Shanghai",
    "iso:country":"CN",
    "name:zho_x_preferred":[
        "\u6885\u5c71\u57ad"
    ],
    "wof:name":"Meishanya",
    "wof:placetype":"locality"
},
  "geometry": {"coordinates":[110.32043,29.9213],"type":"Point"}
}