{
  "type": "Feature",
  "properties": {
    "gn:admin1_code":"1.0",
    "gn:asciiname":"Fuxiucun",
    "gn:country_code":"CN",
    "gn:dem":223,
    "gn:feature_class":"P",
    "gn:feature_code":"PPL",
    "gn:name":"Fuxiucun",
    "gn:population":0,
    "gn:timezone":"Asia/Shanghai",
    "iso:country":"CN",
    "name:zho_x_preferred":[
        "\u51eb\u79c0\u6751"
    ],
    "wof:name":"Fuxiucun",
    "wof:placetype":"locality"
},
  "geometry": {"coordinates":[118.58429,30.33112],"type":"Point"}
}