{
  "type": "Feature",
  "properties": {
    "gn:admin1_code":"3.0",
    "gn:asciiname":"Shali",
    "gn:country_code":"CN",
    "gn:dem":114,
    "gn:feature_class":"P",
    "gn:feature_code":"PPL",
    "gn:name":"Shali",
    "gn:population":0,
    "gn:timezone":"Asia/Shanghai",
    "iso:country":"CN",
    "name:bel_x_preferred":[
        "\u0428\u0430\u043b\u0456"
    ],
    "name:ceb_x_preferred":[
        "Shali"
    ],
    "name:rus_x_preferred":[
        "\u0428\u0430\u043b\u0438"
    ],
    "name:swe_x_preferred":[
        "Shali"
    ],
    "name:tgl_x_preferred":[
        "Shali"
    ],
    "name:tur_x_preferred":[
        "\u015eali"
    ],
    "name:ukr_x_preferred":[
        "\u0428\u0430\u043b\u0456"
    ],
    "name:und_x_variant":[
        "\u6c99\u91cc"
    ],
    "wof:name":"Shali",
    "wof:placetype":"locality"
},
  "geometry": {"coordinates":[114.68812,28.36426],"type":"Point"}
}