{
  "type": "Feature",
  "properties": {
    "gn:admin1_code":"2",
    "gn:asciiname":"Lingtou",
    "gn:country_code":"CN",
    "gn:dem":945,
    "gn:feature_class":"P",
    "gn:feature_code":"PPLA4",
    "gn:name":"Lingtou",
    "gn:population":0,
    "gn:timezone":"Asia/Shanghai",
    "iso:country":"CN",
    "name:und_x_variant":[
        "\u5cad\u5934",
        "Lingtou",
        "Lingtou Xiang"
    ],
    "name:zho_x_preferred":[
        "\u5cad\u5934\u4e61"
    ],
    "wof:name":"Lingtou",
    "wof:placetype":"locality"
},
  "geometry": {"coordinates":[119.24621999999999,27.55251],"type":"Point"}
}