{
  "type": "Feature",
  "properties": {
    "gn:admin1_code":"15.0",
    "gn:asciiname":"Laodou",
    "gn:country_code":"CN",
    "gn:dem":3054,
    "gn:feature_class":"P",
    "gn:feature_code":"PPL",
    "gn:name":"Laodou",
    "gn:population":0,
    "gn:timezone":"Asia/Shanghai",
    "iso:country":"CN",
    "name:zho_x_preferred":[
        "\u8001\u6597"
    ],
    "wof:name":"Laodou",
    "wof:placetype":"locality"
},
  "geometry": {"coordinates":[102.845,34.7477],"type":"Point"}
}