{
  "type": "Feature",
  "properties": {
    "gn:admin1_code":"11",
    "gn:asciiname":"Guiyang Chengguanzhen",
    "gn:country_code":"CN",
    "gn:dem":319,
    "gn:feature_class":"P",
    "gn:feature_code":"PPLA3",
    "gn:name":"Guiyang Chengguanzhen",
    "gn:population":0,
    "gn:timezone":"Asia/Shanghai",
    "iso:country":"CN",
    "name:und_x_variant":[
        "Kweiyang-hsien",
        "Kweiyang",
        "Kweiyangchow",
        "Kuei-yang",
        "Kuei-yang-hsien",
        "Guiyang",
        "Guiyang Chengguanzhen"
    ],
    "name:zho_x_preferred":[
        "Kuei-yang-ch\u2019eng"
    ],
    "name:zho_x_variant":[
        "\u6842\u9633\u57ce\u5173\u9547"
    ],
    "wof:name":"Guiyang Chengguanzhen",
    "wof:placetype":"locality"
},
  "geometry": {"coordinates":[112.74589,25.73333],"type":"Point"}
}