{
  "type": "Feature",
  "properties": {
    "gn:admin1_code":"4.0",
    "gn:asciiname":"Haohu",
    "gn:country_code":"CN",
    "gn:dem":1,
    "gn:feature_class":"P",
    "gn:feature_code":"PPL",
    "gn:name":"Haohu",
    "gn:population":0,
    "gn:timezone":"Asia/Shanghai",
    "iso:country":"CN",
    "name:zho_x_preferred":[
        "Haohu"
    ],
    "name:zho_x_variant":[
        "\u90dd\u6e56"
    ],
    "wof:name":"Haohu",
    "wof:placetype":"locality"
},
  "geometry": {"coordinates":[119.4542,34.0555],"type":"Point"}
}