{
  "type": "Feature",
  "properties": {
    "gn:admin1_code":"5.0",
    "gn:asciiname":"Houxiajia Wobu",
    "gn:country_code":"CN",
    "gn:dem":142,
    "gn:feature_class":"P",
    "gn:feature_code":"PPL",
    "gn:name":"Houxiajia Wobu",
    "gn:population":0,
    "gn:timezone":"Asia/Shanghai",
    "iso:country":"CN",
    "name:zho_x_preferred":[
        "\u540e\u590f\u5bb6\u7a9d\u5821"
    ],
    "wof:name":"Houxiajia Wobu",
    "wof:placetype":"locality"
},
  "geometry": {"coordinates":[123.44043000000001,45.06188],"type":"Point"}
}