{
  "type": "Feature",
  "properties": {
    "gn:admin1_code":"12.0",
    "gn:asciiname":"Dazhushan",
    "gn:country_code":"CN",
    "gn:dem":253,
    "gn:feature_class":"P",
    "gn:feature_code":"PPL",
    "gn:name":"Dazhushan",
    "gn:population":0,
    "gn:timezone":"Asia/Shanghai",
    "iso:country":"CN",
    "name:zho_x_preferred":[
        "Dazhushan"
    ],
    "name:zho_x_variant":[
        "\u5927\u7af9\u5c71"
    ],
    "wof:name":"Dazhushan",
    "wof:placetype":"locality"
},
  "geometry": {"coordinates":[114.20001999999999,29.68981],"type":"Point"}
}