{
  "type": "Feature",
  "properties": {
    "gn:admin1_code":"29",
    "gn:asciiname":"Laowo",
    "gn:country_code":"CN",
    "gn:dem":1589,
    "gn:feature_class":"P",
    "gn:feature_code":"PPL",
    "gn:name":"Laowo",
    "gn:population":0,
    "gn:timezone":"Asia/Shanghai",
    "iso:country":"CN",
    "name:zho_x_preferred":[
        "\u8001\u5367"
    ],
    "wof:name":"Laowo",
    "wof:placetype":"locality"
},
  "geometry": {"coordinates":[104.93899999999999,23.68],"type":"Point"}
}