{
  "type": "Feature",
  "properties": {
    "gn:admin1_code":"10.0",
    "gn:asciiname":"Beiyihou",
    "gn:country_code":"CN",
    "gn:dem":23,
    "gn:feature_class":"P",
    "gn:feature_code":"PPL",
    "gn:name":"Beiyihou",
    "gn:population":0,
    "gn:timezone":"Asia/Shanghai",
    "iso:country":"CN",
    "name:zho_x_preferred":[
        "\u5317\u4e49\u539a"
    ],
    "wof:name":"Beiyihou",
    "wof:placetype":"locality"
},
  "geometry": {"coordinates":[116.31383,39.34818],"type":"Point"}
}