{
  "type": "Feature",
  "properties": {
    "gn:admin1_code":"26",
    "gn:asciiname":"Badu",
    "gn:cc2":"CN",
    "gn:country_code":"CN",
    "gn:dem":1121,
    "gn:feature_class":"P",
    "gn:feature_code":"PPL",
    "gn:name":"Badu",
    "gn:population":0,
    "gn:timezone":"Asia/Shanghai",
    "iso:country":"CN",
    "name:ceb_x_preferred":[
        "Badu"
    ],
    "name:deu_x_preferred":[
        "Badu"
    ],
    "name:fra_x_preferred":[
        "Badu"
    ],
    "name:rus_x_preferred":[
        "\u0411\u0430\u0434\u0443"
    ],
    "name:swe_x_preferred":[
        "Badu"
    ],
    "name:und_x_variant":[
        "Pa-tu-chen",
        "Pa-tu"
    ],
    "wof:name":"Badu",
    "wof:placetype":"locality"
},
  "geometry": {"coordinates":[106.86667,34.76667],"type":"Point"}
}