{
  "type": "Feature",
  "properties": {
    "gn:admin1_code":"30",
    "gn:asciiname":"Huluping",
    "gn:country_code":"CN",
    "gn:dem":303,
    "gn:feature_class":"P",
    "gn:feature_code":"PPL",
    "gn:name":"Huluping",
    "gn:population":0,
    "gn:timezone":"Asia/Shanghai",
    "iso:country":"CN",
    "name:und_x_variant":[
        "\u846b\u82a6\u576a"
    ],
    "wof:name":"Huluping",
    "wof:placetype":"locality"
},
  "geometry": {"coordinates":[113.49822,25.19014],"type":"Point"}
}