{
  "type": "Feature",
  "properties": {
    "gn:admin1_code":"25",
    "gn:asciiname":"Changweiya",
    "gn:country_code":"CN",
    "gn:dem":107,
    "gn:feature_class":"P",
    "gn:feature_code":"PPL",
    "gn:name":"Changweiya",
    "gn:population":0,
    "gn:timezone":"Asia/Shanghai",
    "iso:country":"CN",
    "name:zho_x_preferred":[
        "\u957f\u5c3e\u5d16"
    ],
    "wof:name":"Changweiya",
    "wof:placetype":"locality"
},
  "geometry": {"coordinates":[116.324,36.1164],"type":"Point"}
}