{
  "type": "Feature",
  "properties": {
    "gn:admin1_code":"16.0",
    "gn:asciiname":"Yaoteng",
    "gn:country_code":"CN",
    "gn:dem":671,
    "gn:feature_class":"P",
    "gn:feature_code":"PPL",
    "gn:name":"Yaoteng",
    "gn:population":0,
    "gn:timezone":"Asia/Shanghai",
    "iso:country":"CN",
    "name:zho_x_preferred":[
        "\u5c27\u817e"
    ],
    "wof:name":"Yaoteng",
    "wof:placetype":"locality"
},
  "geometry": {"coordinates":[108.33799999999999,25.3602],"type":"Point"}
}