{
  "type": "Feature",
  "properties": {
    "gn:admin1_code":"16.0",
    "gn:asciiname":"Oudong",
    "gn:country_code":"CN",
    "gn:dem":653,
    "gn:feature_class":"P",
    "gn:feature_code":"PPL",
    "gn:name":"Oudong",
    "gn:population":0,
    "gn:timezone":"Asia/Shanghai",
    "iso:country":"CN",
    "name:zho_x_preferred":[
        "\u85d5\u6d1e"
    ],
    "wof:name":"Oudong",
    "wof:placetype":"locality"
},
  "geometry": {"coordinates":[111.849,24.2498],"type":"Point"}
}