{
  "type": "Feature",
  "properties": {
    "gn:admin1_code":"21",
    "gn:asciiname":"Pingfeng",
    "gn:country_code":"CN",
    "gn:dem":2067,
    "gn:feature_class":"P",
    "gn:feature_code":"PPLA4",
    "gn:name":"Pingfeng",
    "gn:population":0,
    "gn:timezone":"Asia/Shanghai",
    "iso:country":"CN",
    "name:und_x_variant":[
        "\u5e73\u5cf0"
    ],
    "wof:name":"Pingfeng",
    "wof:placetype":"locality"
},
  "geometry": {"coordinates":[105.56197,35.74182000000001],"type":"Point"}
}