{
  "type": "Feature",
  "properties": {
    "gn:admin1_code":"30",
    "gn:asciiname":"Gangbeitang",
    "gn:country_code":"CN",
    "gn:dem":41,
    "gn:feature_class":"P",
    "gn:feature_code":"PPL",
    "gn:name":"Gangbeitang",
    "gn:population":0,
    "gn:timezone":"Asia/Shanghai",
    "iso:country":"CN",
    "name:zho_x_preferred":[
        "\u5c97\u80cc\u5858"
    ],
    "wof:name":"Gangbeitang",
    "wof:placetype":"locality"
},
  "geometry": {"coordinates":[111.83110000000001,22.35416],"type":"Point"}
}