{
  "type": "Feature",
  "properties": {
    "gn:admin1_code":"8.0",
    "gn:asciiname":"Sanping",
    "gn:country_code":"CN",
    "gn:dem":273,
    "gn:feature_class":"P",
    "gn:feature_code":"PPLA4",
    "gn:name":"Sanping",
    "gn:population":0,
    "gn:timezone":"Asia/Urumqi",
    "iso:country":"CN",
    "name:und_x_variant":[
        "Sanping Jiedao Banshichu"
    ],
    "name:zho_x_preferred":[
        "\u4e09\u5e73"
    ],
    "name:zho_x_variant":[
        "\u4e09\u5e73\u8857\u9053\u529e\u4e8b\u5904"
    ],
    "wof:name":"Sanping",
    "wof:placetype":"locality"
},
  "geometry": {"coordinates":[85.05703000000003,45.61898],"type":"Point"}
}