{
  "type": "Feature",
  "properties": {
    "gn:admin1_code":"1.0",
    "gn:asciiname":"Fengxiaomiao",
    "gn:cc2":"CN",
    "gn:country_code":"CN",
    "gn:dem":37,
    "gn:feature_class":"P",
    "gn:feature_code":"PPL",
    "gn:name":"Fengxiaomiao",
    "gn:population":0,
    "gn:timezone":"Asia/Shanghai",
    "iso:country":"CN",
    "name:und_x_variant":[
        "Feng-hsiao-miao",
        "Fengxiaomiao"
    ],
    "wof:name":"Fengxiaomiao",
    "wof:placetype":"locality"
},
  "geometry": {"coordinates":[115.65139000000001,33.52111],"type":"Point"}
}