{
  "type": "Feature",
  "properties": {
    "gn:admin1_code":"25.0",
    "gn:asciiname":"Maloucun",
    "gn:country_code":"CN",
    "gn:dem":43,
    "gn:feature_class":"P",
    "gn:feature_code":"PPL",
    "gn:name":"Maloucun",
    "gn:population":0,
    "gn:timezone":"Asia/Shanghai",
    "iso:country":"CN",
    "name:zho_x_preferred":[
        "\u9a6c\u697c\u6751"
    ],
    "wof:name":"Maloucun",
    "wof:placetype":"locality"
},
  "geometry": {"coordinates":[116.34314999999999,34.75008],"type":"Point"}
}