{
  "type": "Feature",
  "properties": {
    "gn:admin1_code":"14.0",
    "gn:asciiname":"Zhuxue",
    "gn:country_code":"CN",
    "gn:dem":4621,
    "gn:feature_class":"P",
    "gn:feature_code":"PPL",
    "gn:name":"Zhuxue",
    "gn:population":0,
    "gn:timezone":"Asia/Urumqi",
    "iso:country":"CN",
    "name:zho_x_preferred":[
        "\u7af9\u5b66"
    ],
    "wof:name":"Zhuxue",
    "wof:placetype":"locality"
},
  "geometry": {"coordinates":[92.02235,31.30787],"type":"Point"}
}