{
  "type": "Feature",
  "properties": {
    "gn:admin1_code":"32.0",
    "gn:asciiname":"Xinzha",
    "gn:country_code":"CN",
    "gn:dem":3295,
    "gn:feature_class":"P",
    "gn:feature_code":"PPL",
    "gn:name":"Xinzha",
    "gn:population":0,
    "gn:timezone":"Asia/Shanghai",
    "iso:country":"CN",
    "name:zho_x_preferred":[
        "\u4fe1\u624e"
    ],
    "wof:name":"Xinzha",
    "wof:placetype":"locality"
},
  "geometry": {"coordinates":[103.98425,33.18776],"type":"Point"}
}