{
  "type": "Feature",
  "properties": {
    "gn:admin1_code":"8.0",
    "gn:asciiname":"Liuhaigou",
    "gn:country_code":"CN",
    "gn:dem":232,
    "gn:feature_class":"P",
    "gn:feature_code":"PPL",
    "gn:name":"Liuhaigou",
    "gn:population":0,
    "gn:timezone":"Asia/Shanghai",
    "iso:country":"CN",
    "name:zho_x_preferred":[
        "\u5218\u8fd8\u6c9f"
    ],
    "wof:name":"Liuhaigou",
    "wof:placetype":"locality"
},
  "geometry": {"coordinates":[127.50917,45.14406],"type":"Point"}
}