{
  "type": "Feature",
  "properties": {
    "gn:admin1_code":"26",
    "gn:asciiname":"Guguanzhen",
    "gn:cc2":"CN",
    "gn:country_code":"CN",
    "gn:dem":1256,
    "gn:feature_class":"P",
    "gn:feature_code":"PPL",
    "gn:name":"Guguanzhen",
    "gn:population":0,
    "gn:timezone":"Asia/Shanghai",
    "iso:country":"CN",
    "name:und_x_variant":[
        "Ku-kuan-chen",
        "Guguan",
        "Ku-kuan",
        "Guguanzhen"
    ],
    "wof:name":"Guguanzhen",
    "wof:placetype":"locality"
},
  "geometry": {"coordinates":[106.63333,34.96667],"type":"Point"}
}