{
  "type": "Feature",
  "properties": {
    "gn:admin1_code":"9.0",
    "gn:asciiname":"Dashenzhuang",
    "gn:country_code":"CN",
    "gn:dem":52,
    "gn:feature_class":"P",
    "gn:feature_code":"PPL",
    "gn:name":"Dashenzhuang",
    "gn:population":0,
    "gn:timezone":"Asia/Shanghai",
    "iso:country":"CN",
    "name:zho_x_preferred":[
        "\u5927\u7533\u5e84"
    ],
    "wof:name":"Dashenzhuang",
    "wof:placetype":"locality"
},
  "geometry": {"coordinates":[114.71966,33.86289],"type":"Point"}
}