{
  "type": "Feature",
  "properties": {
    "gn:admin1_code":"5.0",
    "gn:asciiname":"Xiahuolong",
    "gn:country_code":"CN",
    "gn:dem":231,
    "gn:feature_class":"P",
    "gn:feature_code":"PPL",
    "gn:name":"Xiahuolong",
    "gn:population":0,
    "gn:timezone":"Asia/Shanghai",
    "iso:country":"CN",
    "name:und_x_variant":[
        "\u4e0b\u6d3b\u9f99"
    ],
    "wof:name":"Xiahuolong",
    "wof:placetype":"locality"
},
  "geometry": {"coordinates":[126.09456000000002,41.01454],"type":"Point"}
}