{
  "type": "Feature",
  "properties": {
    "gn:admin1_code":"8.0",
    "gn:asciiname":"Xidicun",
    "gn:country_code":"CN",
    "gn:dem":232,
    "gn:feature_class":"P",
    "gn:feature_code":"PPL",
    "gn:name":"Xidicun",
    "gn:population":0,
    "gn:timezone":"Asia/Shanghai",
    "iso:country":"CN",
    "name:zho_x_preferred":[
        "\u897f\u5730\u6751"
    ],
    "wof:name":"Xidicun",
    "wof:placetype":"locality"
},
  "geometry": {"coordinates":[127.24823000000001,49.41412],"type":"Point"}
}