{
  "type": "Feature",
  "properties": {
    "gn:admin1_code":"23.0",
    "gn:asciiname":"Shiqiao",
    "gn:country_code":"CN",
    "gn:dem":3,
    "gn:feature_class":"P",
    "gn:feature_code":"PPL",
    "gn:name":"Shiqiao",
    "gn:population":0,
    "gn:timezone":"Asia/Shanghai",
    "iso:country":"CN",
    "name:ceb_x_preferred":[
        "Shiqiao"
    ],
    "name:deu_x_preferred":[
        "Shiqiao"
    ],
    "name:swe_x_preferred":[
        "Shiqiao"
    ],
    "name:zho_x_preferred":[
        "Shiqiao"
    ],
    "name:zho_x_variant":[
        "\u65f6\u6865"
    ],
    "wof:name":"Shiqiao",
    "wof:placetype":"locality"
},
  "geometry": {"coordinates":[121.57107000000001,31.60618],"type":"Point"}
}