{
  "type": "Feature",
  "properties": {
    "gn:admin1_code":"30.0",
    "gn:asciiname":"Hongshan",
    "gn:country_code":"CN",
    "gn:dem":24,
    "gn:feature_class":"P",
    "gn:feature_code":"PPL",
    "gn:name":"Hongshan",
    "gn:population":0,
    "gn:timezone":"Asia/Shanghai",
    "iso:country":"CN",
    "name:ceb_x_preferred":[
        "Hongshan"
    ],
    "name:deu_x_preferred":[
        "Hongshan"
    ],
    "name:fra_x_preferred":[
        "Hongshan"
    ],
    "name:kor_x_preferred":[
        "\ud6d9\uc0b0\uad6c"
    ],
    "name:nor_x_preferred":[
        "Hongshan"
    ],
    "name:swe_x_preferred":[
        "Hongshan"
    ],
    "name:zho_x_preferred":[
        "\u7d05\u5c71"
    ],
    "wof:name":"Hongshan",
    "wof:placetype":"locality"
},
  "geometry": {"coordinates":[113.01452999999999,22.30939],"type":"Point"}
}