{
  "type": "Feature",
  "properties": {
    "gn:admin1_code":"19.0",
    "gn:asciiname":"Qingshiliang",
    "gn:country_code":"CN",
    "gn:dem":383,
    "gn:feature_class":"P",
    "gn:feature_code":"PPL",
    "gn:name":"Qingshiliang",
    "gn:population":0,
    "gn:timezone":"Asia/Shanghai",
    "iso:country":"CN",
    "name:und_x_variant":[
        "\u9752\u77f3\u6881"
    ],
    "name:zho_x_preferred":[
        "\u9752\u77f3\u6881"
    ],
    "wof:name":"Qingshiliang",
    "wof:placetype":"locality"
},
  "geometry": {"coordinates":[121.21252,41.93171],"type":"Point"}
}