{
  "type": "Feature",
  "properties": {
    "gn:admin1_code":"3",
    "gn:asciiname":"Laoyanjia",
    "gn:country_code":"CN",
    "gn:dem":239,
    "gn:feature_class":"P",
    "gn:feature_code":"PPL",
    "gn:name":"Laoyanjia",
    "gn:population":0,
    "gn:timezone":"Asia/Shanghai",
    "iso:country":"CN",
    "wof:name":"Laoyanjia",
    "wof:placetype":"locality"
},
  "geometry": {"coordinates":[114.29971999999999,26.75222],"type":"Point"}
}