{
  "type": "Feature",
  "properties": {
    "gn:admin1_code":"4.0",
    "gn:asciiname":"Jiufenzi",
    "gn:country_code":"CN",
    "gn:dem":10,
    "gn:feature_class":"P",
    "gn:feature_code":"PPL",
    "gn:name":"Jiufenzi",
    "gn:population":0,
    "gn:timezone":"Asia/Shanghai",
    "iso:country":"CN",
    "name:zho_x_preferred":[
        "Jiufenzi"
    ],
    "name:zho_x_variant":[
        "\u4e5d\u4efd\u5b50"
    ],
    "wof:name":"Jiufenzi",
    "wof:placetype":"locality"
},
  "geometry": {"coordinates":[119.11205,33.84517],"type":"Point"}
}