{
  "type": "Feature",
  "properties": {
    "gn:admin1_code":"16.0",
    "gn:asciiname":"Gupu",
    "gn:country_code":"CN",
    "gn:dem":210,
    "gn:feature_class":"P",
    "gn:feature_code":"PPL",
    "gn:name":"Gupu",
    "gn:population":0,
    "gn:timezone":"Asia/Shanghai",
    "iso:country":"CN",
    "name:zho_x_preferred":[
        "\u53e4\u6734"
    ],
    "wof:name":"Gupu",
    "wof:placetype":"locality"
},
  "geometry": {"coordinates":[109.78100000000001,23.8066],"type":"Point"}
}