{
  "type": "Feature",
  "properties": {
    "gn:admin1_code":"16.0",
    "gn:asciiname":"Luduyuan",
    "gn:country_code":"CN",
    "gn:dem":71,
    "gn:feature_class":"P",
    "gn:feature_code":"PPL",
    "gn:name":"Luduyuan",
    "gn:population":0,
    "gn:timezone":"Asia/Shanghai",
    "iso:country":"CN",
    "name:zho_x_preferred":[
        "\u9e93\u809a\u56ed"
    ],
    "wof:name":"Luduyuan",
    "wof:placetype":"locality"
},
  "geometry": {"coordinates":[109.879,22.2604],"type":"Point"}
}