{
  "type": "Feature",
  "properties": {
    "gn:admin1_code":"26.0",
    "gn:asciiname":"Dayuanzi",
    "gn:country_code":"CN",
    "gn:dem":1525,
    "gn:feature_class":"P",
    "gn:feature_code":"PPL",
    "gn:name":"Dayuanzi",
    "gn:population":0,
    "gn:timezone":"Asia/Shanghai",
    "iso:country":"CN",
    "name:und_x_variant":[
        "\u5927\u9662\u5b50"
    ],
    "wof:name":"Dayuanzi",
    "wof:placetype":"locality"
},
  "geometry": {"coordinates":[107.21513,34.01755],"type":"Point"}
}