{
  "type": "Feature",
  "properties": {
    "gn:admin1_code":"26.0",
    "gn:asciiname":"Zhonghuagou",
    "gn:country_code":"CN",
    "gn:dem":1423,
    "gn:feature_class":"P",
    "gn:feature_code":"PPL",
    "gn:name":"Zhonghuagou",
    "gn:population":0,
    "gn:timezone":"Asia/Shanghai",
    "iso:country":"CN",
    "name:zho_x_preferred":[
        "\u4e2d\u534e\u6c9f"
    ],
    "wof:name":"Zhonghuagou",
    "wof:placetype":"locality"
},
  "geometry": {"coordinates":[108.96441000000002,33.65696],"type":"Point"}
}