{
  "type": "Feature",
  "properties": {
    "gn:admin1_code":"9.0",
    "gn:asciiname":"Xinqiao",
    "gn:cc2":"CN",
    "gn:country_code":"CN",
    "gn:dem":42,
    "gn:feature_class":"P",
    "gn:feature_code":"PPL",
    "gn:name":"Xinqiao",
    "gn:population":0,
    "gn:timezone":"Asia/Shanghai",
    "iso:country":"CN",
    "name:ceb_x_preferred":[
        "Xinqiao"
    ],
    "name:deu_x_preferred":[
        "Xinqiao"
    ],
    "name:swe_x_preferred":[
        "Xinqiao"
    ],
    "name:und_x_variant":[
        "Hsin-ch\u2019iao",
        "Hsin-ch\u2019iao-chi",
        "Xinqiao"
    ],
    "wof:name":"Xinqiao",
    "wof:placetype":"locality"
},
  "geometry": {"coordinates":[114.95,33.18333],"type":"Point"}
}