{
  "type": "Feature",
  "properties": {
    "gn:admin1_code":"3.0",
    "gn:asciiname":"Dianxiacun",
    "gn:country_code":"CN",
    "gn:dem":74,
    "gn:feature_class":"P",
    "gn:feature_code":"PPL",
    "gn:name":"Dianxiacun",
    "gn:population":0,
    "gn:timezone":"Asia/Shanghai",
    "iso:country":"CN",
    "name:und_x_variant":[
        "\u6bbf\u4e0b\u6751"
    ],
    "wof:name":"Dianxiacun",
    "wof:placetype":"locality"
},
  "geometry": {"coordinates":[116.67083999999998,28.21637],"type":"Point"}
}