{
  "type": "Feature",
  "properties": {
    "gn:admin1_code":"29.0",
    "gn:asciiname":"Tasa",
    "gn:country_code":"CN",
    "gn:dem":1964,
    "gn:feature_class":"P",
    "gn:feature_code":"PPL",
    "gn:name":"Tasa",
    "gn:population":0,
    "gn:timezone":"Asia/Shanghai",
    "iso:country":"CN",
    "name:ceb_x_preferred":[
        "Tasa"
    ],
    "name:fra_x_preferred":[
        "Tasa"
    ],
    "name:ita_x_preferred":[
        "Tasa"
    ],
    "name:nld_x_preferred":[
        "Tasa"
    ],
    "name:ron_x_preferred":[
        "Tasa"
    ],
    "name:swe_x_preferred":[
        "Tasa"
    ],
    "name:vie_x_preferred":[
        "Tasa"
    ],
    "name:war_x_preferred":[
        "Tasa"
    ],
    "name:zho_x_preferred":[
        "\u4ed6\u6492"
    ],
    "wof:name":"Tasa",
    "wof:placetype":"locality"
},
  "geometry": {"coordinates":[102.39400000000001,23.238],"type":"Point"}
}