{
  "type": "Feature",
  "properties": {
    "gn:admin1_code":"26.0",
    "gn:asciiname":"Liangjiachacun",
    "gn:country_code":"CN",
    "gn:dem":962,
    "gn:feature_class":"P",
    "gn:feature_code":"PPL",
    "gn:name":"Liangjiachacun",
    "gn:population":0,
    "gn:timezone":"Asia/Shanghai",
    "iso:country":"CN",
    "name:zho_x_preferred":[
        "\u6881\u5bb6\u5c94\u6751"
    ],
    "wof:name":"Liangjiachacun",
    "wof:placetype":"locality"
},
  "geometry": {"coordinates":[110.19208999999999,36.99319000000001],"type":"Point"}
}