{
  "type": "Feature",
  "properties": {
    "gn:admin1_code":"3.0",
    "gn:asciiname":"Zuolong",
    "gn:country_code":"CN",
    "gn:dem":70,
    "gn:feature_class":"P",
    "gn:feature_code":"PPLA4",
    "gn:name":"Zuolong",
    "gn:population":0,
    "gn:timezone":"Asia/Shanghai",
    "iso:country":"CN",
    "name:und_x_variant":[
        "\u4f50\u9f99",
        "Zuolong Xiang",
        "\u4f50\u9f99\u4e61"
    ],
    "wof:name":"Zuolong",
    "wof:placetype":"locality"
},
  "geometry": {"coordinates":[115.40903,27.31388],"type":"Point"}
}