{
  "type": "Feature",
  "properties": {
    "gn:admin1_code":"30.0",
    "gn:asciiname":"Shangkuicun",
    "gn:country_code":"CN",
    "gn:dem":85,
    "gn:feature_class":"P",
    "gn:feature_code":"PPL",
    "gn:name":"Shangkuicun",
    "gn:population":0,
    "gn:timezone":"Asia/Shanghai",
    "iso:country":"CN",
    "name:zho_x_preferred":[
        "\u4e0a\u8475\u6751"
    ],
    "wof:name":"Shangkuicun",
    "wof:placetype":"locality"
},
  "geometry": {"coordinates":[116.83781,24.06792],"type":"Point"}
}