{
  "type": "Feature",
  "properties": {
    "gn:admin1_code":"18.0",
    "gn:asciiname":"Baodong",
    "gn:country_code":"CN",
    "gn:dem":624,
    "gn:feature_class":"P",
    "gn:feature_code":"PPL",
    "gn:name":"Baodong",
    "gn:population":0,
    "gn:timezone":"Asia/Shanghai",
    "iso:country":"CN",
    "name:zho_x_preferred":[
        "\u62a5\u6d1e"
    ],
    "wof:name":"Baodong",
    "wof:placetype":"locality"
},
  "geometry": {"coordinates":[109.017,26.2991],"type":"Point"}
}