{
  "type": "Feature",
  "properties": {
    "gn:admin1_code":"29.0",
    "gn:asciiname":"Houhecun",
    "gn:country_code":"CN",
    "gn:dem":2114,
    "gn:feature_class":"P",
    "gn:feature_code":"PPL",
    "gn:name":"Houhecun",
    "gn:population":0,
    "gn:timezone":"Asia/Shanghai",
    "iso:country":"CN",
    "name:zho_x_preferred":[
        "\u540e\u6cb3\u6751"
    ],
    "wof:name":"Houhecun",
    "wof:placetype":"locality"
},
  "geometry": {"coordinates":[103.994,25.9602],"type":"Point"}
}