{
  "type": "Feature",
  "properties": {
    "gn:admin1_code":"24",
    "gn:asciiname":"Tantou",
    "gn:cc2":"CN",
    "gn:country_code":"CN",
    "gn:dem":844,
    "gn:feature_class":"P",
    "gn:feature_code":"PPL",
    "gn:name":"Tantou",
    "gn:population":0,
    "gn:timezone":"Asia/Shanghai",
    "iso:country":"CN",
    "name:ceb_x_preferred":[
        "Tantou"
    ],
    "name:deu_x_preferred":[
        "Tantou"
    ],
    "name:fra_x_preferred":[
        "Tantou"
    ],
    "name:swe_x_preferred":[
        "Tantou"
    ],
    "name:und_x_variant":[
        "T\u2019an-t\u2019ou-ts\u2019un",
        "Tantou"
    ],
    "wof:name":"Tantou",
    "wof:placetype":"locality"
},
  "geometry": {"coordinates":[110.78333000000001,38.43333],"type":"Point"}
}