{
  "type": "Feature",
  "properties": {
    "gn:admin1_code":"11.0",
    "gn:asciiname":"Baxingcha",
    "gn:country_code":"CN",
    "gn:dem":35,
    "gn:feature_class":"P",
    "gn:feature_code":"PPL",
    "gn:name":"Baxingcha",
    "gn:population":0,
    "gn:timezone":"Asia/Shanghai",
    "iso:country":"CN",
    "name:zho_x_preferred":[
        "\u516b\u5f62\u6c4a"
    ],
    "wof:name":"Baxingcha",
    "wof:placetype":"locality"
},
  "geometry": {"coordinates":[112.34433,28.9724],"type":"Point"}
}