{
  "type": "Feature",
  "properties": {
    "gn:admin1_code":"11.0",
    "gn:asciiname":"Jiepichong",
    "gn:country_code":"CN",
    "gn:dem":344,
    "gn:feature_class":"P",
    "gn:feature_code":"PPL",
    "gn:name":"Jiepichong",
    "gn:population":0,
    "gn:timezone":"Asia/Shanghai",
    "iso:country":"CN",
    "name:zho_x_preferred":[
        "\u754c\u76ae\u51b2"
    ],
    "wof:name":"Jiepichong",
    "wof:placetype":"locality"
},
  "geometry": {"coordinates":[110.04489,28.12109],"type":"Point"}
}