{
  "type": "Feature",
  "properties": {
    "gn:admin1_code":"12.0",
    "gn:asciiname":"Hongjiaping",
    "gn:country_code":"CN",
    "gn:dem":1461,
    "gn:feature_class":"P",
    "gn:feature_code":"PPL",
    "gn:name":"Hongjiaping",
    "gn:population":0,
    "gn:timezone":"Asia/Shanghai",
    "iso:country":"CN",
    "name:zho_x_preferred":[
        "Hongjiaping"
    ],
    "name:zho_x_variant":[
        "\u6d2a\u5bb6\u576a"
    ],
    "wof:name":"Hongjiaping",
    "wof:placetype":"locality"
},
  "geometry": {"coordinates":[109.66293,29.96284],"type":"Point"}
}