{
  "type": "Feature",
  "properties": {
    "gn:admin1_code":"3.0",
    "gn:asciiname":"Xiaguanzhai",
    "gn:country_code":"CN",
    "gn:dem":114,
    "gn:feature_class":"P",
    "gn:feature_code":"PPL",
    "gn:name":"Xiaguanzhai",
    "gn:population":0,
    "gn:timezone":"Asia/Shanghai",
    "iso:country":"CN",
    "name:zho_x_preferred":[
        "\u4e0b\u5b98\u5b85"
    ],
    "wof:name":"Xiaguanzhai",
    "wof:placetype":"locality"
},
  "geometry": {"coordinates":[118.37642,28.63734],"type":"Point"}
}