{
  "type": "Feature",
  "properties": {
    "gn:admin1_code":"4.0",
    "gn:asciiname":"Dazhao",
    "gn:country_code":"CN",
    "gn:dem":1,
    "gn:feature_class":"P",
    "gn:feature_code":"PPL",
    "gn:name":"Dazhao",
    "gn:population":0,
    "gn:timezone":"Asia/Shanghai",
    "iso:country":"CN",
    "name:zho_x_preferred":[
        "Dazhao"
    ],
    "name:zho_x_variant":[
        "\u5927\u8d75"
    ],
    "wof:name":"Dazhao",
    "wof:placetype":"locality"
},
  "geometry": {"coordinates":[119.50499000000001,33.55395],"type":"Point"}
}