{
  "type": "Feature",
  "properties": {
    "gn:admin1_code":"31.0",
    "gn:asciiname":"Buyi",
    "gn:country_code":"CN",
    "gn:dem":49,
    "gn:feature_class":"P",
    "gn:feature_code":"PPL",
    "gn:name":"Buyi",
    "gn:population":0,
    "gn:timezone":"Asia/Shanghai",
    "iso:country":"CN",
    "name:zho_x_preferred":[
        "\u535c\u88d4"
    ],
    "wof:name":"Buyi",
    "wof:placetype":"locality"
},
  "geometry": {"coordinates":[110.29595999999999,19.79263],"type":"Point"}
}