{
  "type": "Feature",
  "properties": {
    "gn:admin1_code":"11.0",
    "gn:asciiname":"Beizhuangshan",
    "gn:country_code":"CN",
    "gn:dem":166,
    "gn:feature_class":"P",
    "gn:feature_code":"PPL",
    "gn:name":"Beizhuangshan",
    "gn:population":0,
    "gn:timezone":"Asia/Shanghai",
    "iso:country":"CN",
    "name:zho_x_preferred":[
        "\u5317\u5e84\u5c71"
    ],
    "wof:name":"Beizhuangshan",
    "wof:placetype":"locality"
},
  "geometry": {"coordinates":[113.4361,29.22662],"type":"Point"}
}