{
  "type": "Feature",
  "properties": {
    "gn:admin1_code":"08",
    "gn:asciiname":"Huolongmen",
    "gn:country_code":"CN",
    "gn:dem":315,
    "gn:feature_class":"P",
    "gn:feature_code":"PPLA4",
    "gn:name":"Huolongmen",
    "gn:population":0,
    "gn:timezone":"Asia/Shanghai",
    "iso:country":"CN",
    "name:und_x_variant":[
        "Hongfeng",
        "Huo-lung-men",
        "Huolongmen",
        "Huolongmen Xiang"
    ],
    "name:zho_x_preferred":[
        "\u970d\u9f99\u95e8"
    ],
    "name:zho_x_variant":[
        "\u970d\u9f99\u95e8\u4e61"
    ],
    "wof:name":"Huolongmen",
    "wof:placetype":"locality"
},
  "geometry": {"coordinates":[125.77767,49.80162],"type":"Point"}
}