{
  "type": "Feature",
  "properties": {
    "gn:admin1_code":"10",
    "gn:asciiname":"Jinshuikou",
    "gn:country_code":"CN",
    "gn:dem":742,
    "gn:feature_class":"P",
    "gn:feature_code":"PPL",
    "gn:name":"Jinshuikou",
    "gn:population":0,
    "gn:timezone":"Asia/Shanghai",
    "iso:country":"CN",
    "name:und_x_variant":[
        "Chin-shui-k\u2019ou",
        "Jinshuikou"
    ],
    "name:zho_x_preferred":[
        "\u91d1\u6c34\u53e3"
    ],
    "wof:name":"Jinshuikou",
    "wof:placetype":"locality"
},
  "geometry": {"coordinates":[115.05104,39.59778],"type":"Point"}
}