{
  "type": "Feature",
  "properties": {
    "gn:admin1_code":"7.0",
    "gn:asciiname":"Taotian",
    "gn:country_code":"CN",
    "gn:dem":106,
    "gn:feature_class":"P",
    "gn:feature_code":"PPL",
    "gn:name":"Taotian",
    "gn:population":0,
    "gn:timezone":"Asia/Shanghai",
    "iso:country":"CN",
    "name:zho_x_preferred":[
        "Taotian"
    ],
    "name:zho_x_variant":[
        "\u6843\u7530"
    ],
    "wof:name":"Taotian",
    "wof:placetype":"locality"
},
  "geometry": {"coordinates":[119.23326000000002,26.16538],"type":"Point"}
}