{
  "type": "Feature",
  "properties": {
    "gn:admin1_code":"19.0",
    "gn:asciiname":"Xiejia Buzi",
    "gn:country_code":"CN",
    "gn:dem":437,
    "gn:feature_class":"P",
    "gn:feature_code":"PPL",
    "gn:name":"Xiejia Buzi",
    "gn:population":0,
    "gn:timezone":"Asia/Shanghai",
    "iso:country":"CN",
    "name:und_x_variant":[
        "Xiejia Puzi",
        "\u8c22\u5bb6\u5821\u5b50",
        "Xiejia Buzi"
    ],
    "name:zho_x_preferred":[
        "\u8c22\u5bb6\u5821\u5b50"
    ],
    "wof:name":"Xiejia Buzi",
    "wof:placetype":"locality"
},
  "geometry": {"coordinates":[122.69864,40.08464],"type":"Point"}
}