{
  "type": "Feature",
  "properties": {
    "gn:admin1_code":"14.0",
    "gn:asciiname":"Dawengcun",
    "gn:country_code":"CN",
    "gn:dem":3925,
    "gn:feature_class":"P",
    "gn:feature_code":"PPL",
    "gn:name":"Dawengcun",
    "gn:population":0,
    "gn:timezone":"Asia/Urumqi",
    "iso:country":"CN",
    "name:zho_x_preferred":[
        "\u8fbe\u7fc1\u6751"
    ],
    "wof:name":"Dawengcun",
    "wof:placetype":"locality"
},
  "geometry": {"coordinates":[95.55632,30.77043],"type":"Point"}
}