{
  "type": "Feature",
  "properties": {
    "gn:admin1_code":"18.0",
    "gn:asciiname":"Yindi",
    "gn:country_code":"CN",
    "gn:dem":1329,
    "gn:feature_class":"P",
    "gn:feature_code":"PPL",
    "gn:name":"Yindi",
    "gn:population":0,
    "gn:timezone":"Asia/Shanghai",
    "iso:country":"CN",
    "name:zho_x_preferred":[
        "\u5f15\u5e95"
    ],
    "wof:name":"Yindi",
    "wof:placetype":"locality"
},
  "geometry": {"coordinates":[105.139,27.0038],"type":"Point"}
}