{
  "type": "Feature",
  "properties": {
    "gn:admin1_code":"31.0",
    "gn:asciiname":"Zengshan",
    "gn:country_code":"CN",
    "gn:dem":27,
    "gn:feature_class":"P",
    "gn:feature_code":"PPL",
    "gn:name":"Zengshan",
    "gn:population":0,
    "gn:timezone":"Asia/Shanghai",
    "iso:country":"CN",
    "name:und_x_variant":[
        "\u66fe\u5c71"
    ],
    "wof:name":"Zengshan",
    "wof:placetype":"locality"
},
  "geometry": {"coordinates":[110.00702,18.56377],"type":"Point"}
}