{
  "type": "Feature",
  "properties": {
    "gn:admin1_code":"1.0",
    "gn:asciiname":"Zhangbacun",
    "gn:country_code":"CN",
    "gn:dem":24,
    "gn:feature_class":"P",
    "gn:feature_code":"PPL",
    "gn:name":"Zhangbacun",
    "gn:population":0,
    "gn:timezone":"Asia/Shanghai",
    "iso:country":"CN",
    "name:zho_x_preferred":[
        "\u5f20\u575d\u6751"
    ],
    "wof:name":"Zhangbacun",
    "wof:placetype":"locality"
},
  "geometry": {"coordinates":[116.92925,33.1641],"type":"Point"}
}