{
  "type": "Feature",
  "properties": {
    "gn:admin1_code":"1.0",
    "gn:asciiname":"Niaoguanzuicun",
    "gn:country_code":"CN",
    "gn:dem":93,
    "gn:feature_class":"P",
    "gn:feature_code":"PPL",
    "gn:name":"Niaoguanzuicun",
    "gn:population":0,
    "gn:timezone":"Asia/Shanghai",
    "iso:country":"CN",
    "name:zho_x_preferred":[
        "\u9e1f\u9e73\u5634\u6751"
    ],
    "wof:name":"Niaoguanzuicun",
    "wof:placetype":"locality"
},
  "geometry": {"coordinates":[116.40273000000001,31.37124],"type":"Point"}
}