{
  "type": "Feature",
  "properties": {
    "gn:admin1_code":"30",
    "gn:asciiname":"Heshikeng",
    "gn:country_code":"CN",
    "gn:dem":256,
    "gn:feature_class":"P",
    "gn:feature_code":"PPL",
    "gn:name":"Heshikeng",
    "gn:population":0,
    "gn:timezone":"Asia/Shanghai",
    "iso:country":"CN",
    "name:zho_x_preferred":[
        "\u79be\u77f3\u5751"
    ],
    "wof:name":"Heshikeng",
    "wof:placetype":"locality"
},
  "geometry": {"coordinates":[116.67140999999999,24.45021],"type":"Point"}
}