{
  "type": "Feature",
  "properties": {
    "gn:admin1_code":"30.0",
    "gn:asciiname":"Baizhu'ao",
    "gn:country_code":"CN",
    "gn:dem":59,
    "gn:feature_class":"P",
    "gn:feature_code":"PPL",
    "gn:name":"Baizhu\u2019ao",
    "gn:population":0,
    "gn:timezone":"Asia/Shanghai",
    "iso:country":"CN",
    "name:zho_x_preferred":[
        "Baizhu\u2019ao"
    ],
    "name:zho_x_variant":[
        "\u767d\u7af9\u51f9"
    ],
    "wof:name":"Baizhu'ao",
    "wof:placetype":"locality"
},
  "geometry": {"coordinates":[112.71138999999999,24.39],"type":"Point"}
}