{
  "type": "Feature",
  "properties": {
    "gn:admin1_code":"13",
    "gn:asciiname":"Tikebu Ladahuang",
    "gn:country_code":"CN",
    "gn:dem":1753,
    "gn:feature_class":"P",
    "gn:feature_code":"PPL",
    "gn:name":"Tikebu Ladahuang",
    "gn:population":0,
    "gn:timezone":"Asia/Urumqi",
    "iso:country":"CN",
    "name:zho_x_preferred":[
        "\u63d0\u514b\u4e0d\u62c9\u5927\u9ec4"
    ],
    "wof:name":"Tikebu Ladahuang",
    "wof:placetype":"locality"
},
  "geometry": {"coordinates":[87.67644,41.27251],"type":"Point"}
}