{
  "type": "Feature",
  "properties": {
    "gn:admin1_code":"2.0",
    "gn:asciiname":"Hangxing",
    "gn:country_code":"CN",
    "gn:dem":465,
    "gn:feature_class":"P",
    "gn:feature_code":"PPL",
    "gn:name":"Hangxing",
    "gn:population":0,
    "gn:timezone":"Asia/Shanghai",
    "iso:country":"CN",
    "name:zho_x_preferred":[
        "\u676d\u5174"
    ],
    "wof:name":"Hangxing",
    "wof:placetype":"locality"
},
  "geometry": {"coordinates":[118.15313,29.0926],"type":"Point"}
}