{
  "type": "Feature",
  "properties": {
    "gn:admin1_code":"30.0",
    "gn:asciiname":"Xia'ou",
    "gn:country_code":"CN",
    "gn:dem":209,
    "gn:feature_class":"P",
    "gn:feature_code":"PPL",
    "gn:name":"Xia\u2019ou",
    "gn:population":0,
    "gn:timezone":"Asia/Shanghai",
    "iso:country":"CN",
    "name:zho_x_preferred":[
        "Xia\u2019ou"
    ],
    "name:zho_x_variant":[
        "\u4e0b\u6b27"
    ],
    "wof:name":"Xia'ou",
    "wof:placetype":"locality"
},
  "geometry": {"coordinates":[114.39684,23.88939],"type":"Point"}
}