{
  "type": "Feature",
  "properties": {
    "gn:admin1_code":"19.0",
    "gn:asciiname":"Caojia Buzi",
    "gn:country_code":"CN",
    "gn:dem":69,
    "gn:feature_class":"P",
    "gn:feature_code":"PPL",
    "gn:name":"Caojia Buzi",
    "gn:population":0,
    "gn:timezone":"Asia/Shanghai",
    "iso:country":"CN",
    "name:und_x_variant":[
        "Caojiabaozi",
        "\u66f9\u5bb6\u5821\u5b50",
        "Caojia Buzi"
    ],
    "name:zho_x_preferred":[
        "\u66f9\u5bb6\u5821\u5b50"
    ],
    "wof:name":"Caojia Buzi",
    "wof:placetype":"locality"
},
  "geometry": {"coordinates":[124.05933,40.53533],"type":"Point"}
}