{
  "type": "Feature",
  "properties": {
    "gn:admin1_code":"30",
    "gn:asciiname":"Tangpeng",
    "gn:country_code":"CN",
    "gn:dem":64,
    "gn:feature_class":"P",
    "gn:feature_code":"PPLA4",
    "gn:name":"Tangpeng",
    "gn:population":0,
    "gn:timezone":"Asia/Urumqi",
    "iso:country":"CN",
    "name:und_x_variant":[
        "T\u2019ang-p\u2019eng-hs\u00fc",
        "Tangpeng",
        "Tangpeng Zhen",
        "\u5858\u84ec\u9547"
    ],
    "name:zho_x_preferred":[
        "\u5858\u84ec"
    ],
    "wof:name":"Tangpeng",
    "wof:placetype":"locality"
},
  "geometry": {"coordinates":[110.11233,21.79431],"type":"Point"}
}