{
  "type": "Feature",
  "properties": {
    "gn:admin1_code":"29.0",
    "gn:asciiname":"Shangzaopo",
    "gn:country_code":"CN",
    "gn:dem":1758,
    "gn:feature_class":"P",
    "gn:feature_code":"PPL",
    "gn:name":"Shangzaopo",
    "gn:population":0,
    "gn:timezone":"Asia/Shanghai",
    "iso:country":"CN",
    "name:zho_x_preferred":[
        "\u4e0a\u65e9\u5761"
    ],
    "wof:name":"Shangzaopo",
    "wof:placetype":"locality"
},
  "geometry": {"coordinates":[98.43429999999999,25.4757],"type":"Point"}
}