{
  "type": "Feature",
  "properties": {
    "gn:admin1_code":"32.0",
    "gn:asciiname":"Banjietu",
    "gn:country_code":"CN",
    "gn:dem":409,
    "gn:feature_class":"P",
    "gn:feature_code":"PPL",
    "gn:name":"Banjietu",
    "gn:population":0,
    "gn:timezone":"Asia/Shanghai",
    "iso:country":"CN",
    "name:zho_x_preferred":[
        "\u534a\u8282\u571f"
    ],
    "wof:name":"Banjietu",
    "wof:placetype":"locality"
},
  "geometry": {"coordinates":[106.44307999999999,31.2184],"type":"Point"}
}