{
  "type": "Feature",
  "properties": {
    "gn:admin1_code":"8.0",
    "gn:asciiname":"Longshengcun",
    "gn:country_code":"CN",
    "gn:dem":110,
    "gn:feature_class":"P",
    "gn:feature_code":"PPL",
    "gn:name":"Longshengcun",
    "gn:population":0,
    "gn:timezone":"Asia/Shanghai",
    "iso:country":"CN",
    "name:zho_x_preferred":[
        "\u9f99\u80dc\u6751"
    ],
    "wof:name":"Longshengcun",
    "wof:placetype":"locality"
},
  "geometry": {"coordinates":[130.58088999999998,46.74058],"type":"Point"}
}