{
  "type": "Feature",
  "properties": {
    "gn:admin1_code":"15.0",
    "gn:asciiname":"Luling",
    "gn:country_code":"CN",
    "gn:dem":1314,
    "gn:feature_class":"P",
    "gn:feature_code":"PPL",
    "gn:name":"Luling",
    "gn:population":0,
    "gn:timezone":"Asia/Shanghai",
    "iso:country":"CN",
    "name:zho_x_preferred":[
        "\u8def\u5cad"
    ],
    "wof:name":"Luling",
    "wof:placetype":"locality"
},
  "geometry": {"coordinates":[107.47499999999999,35.5203],"type":"Point"}
}