{
  "type": "Feature",
  "properties": {
    "gn:admin1_code":"14.0",
    "gn:asciiname":"Panggacun",
    "gn:country_code":"CN",
    "gn:dem":4150,
    "gn:feature_class":"P",
    "gn:feature_code":"PPL",
    "gn:name":"Panggacun",
    "gn:population":0,
    "gn:timezone":"Asia/Urumqi",
    "iso:country":"CN",
    "name:zho_x_preferred":[
        "\u65c1\u560e\u6751"
    ],
    "wof:name":"Panggacun",
    "wof:placetype":"locality"
},
  "geometry": {"coordinates":[94.236,31.77917],"type":"Point"}
}