{
  "type": "Feature",
  "properties": {
    "gn:admin1_code":"19.0",
    "gn:asciiname":"Chengjiabu",
    "gn:country_code":"CN",
    "gn:dem":247,
    "gn:feature_class":"P",
    "gn:feature_code":"PPL",
    "gn:name":"Chengjiabu",
    "gn:population":0,
    "gn:timezone":"Asia/Shanghai",
    "iso:country":"CN",
    "name:und_x_variant":[
        "Chengjiabao",
        "Chengjiabu"
    ],
    "name:zho_x_preferred":[
        "\u7a0b\u5bb6\u5821"
    ],
    "wof:name":"Chengjiabu",
    "wof:placetype":"locality"
},
  "geometry": {"coordinates":[124.31304,40.77972000000001],"type":"Point"}
}