{
  "type": "Feature",
  "properties": {
    "gn:admin1_code":"29.0",
    "gn:asciiname":"Xiaoyuanzi",
    "gn:country_code":"CN",
    "gn:dem":1903,
    "gn:feature_class":"P",
    "gn:feature_code":"PPL",
    "gn:name":"Xiaoyuanzi",
    "gn:population":0,
    "gn:timezone":"Asia/Shanghai",
    "iso:country":"CN",
    "name:zho_x_preferred":[
        "\u5c0f\u56ed\u5b50"
    ],
    "wof:name":"Xiaoyuanzi",
    "wof:placetype":"locality"
},
  "geometry": {"coordinates":[98.4599,24.7895],"type":"Point"}
}