{
  "type": "Feature",
  "properties": {
    "gn:admin1_code":"25",
    "gn:asciiname":"Houmacao",
    "gn:country_code":"CN",
    "gn:dem":220,
    "gn:feature_class":"P",
    "gn:feature_code":"PPL",
    "gn:name":"Houmacao",
    "gn:population":0,
    "gn:timezone":"Asia/Shanghai",
    "iso:country":"CN",
    "name:zho_x_preferred":[
        "\u540e\u9a6c\u69fd"
    ],
    "wof:name":"Houmacao",
    "wof:placetype":"locality"
},
  "geometry": {"coordinates":[117.467,35.3604],"type":"Point"}
}