{
  "type": "Feature",
  "properties": {
    "gn:admin1_code":"16.0",
    "gn:asciiname":"Nanchangtang",
    "gn:country_code":"CN",
    "gn:dem":125,
    "gn:feature_class":"P",
    "gn:feature_code":"PPL",
    "gn:name":"Nanchangtang",
    "gn:population":0,
    "gn:timezone":"Asia/Shanghai",
    "iso:country":"CN",
    "name:zho_x_preferred":[
        "\u5357\u660c\u5858"
    ],
    "wof:name":"Nanchangtang",
    "wof:placetype":"locality"
},
  "geometry": {"coordinates":[110.221,23.2309],"type":"Point"}
}