{
  "type": "Feature",
  "properties": {
    "gn:admin1_code":"26.0",
    "gn:asciiname":"Maichagou",
    "gn:country_code":"CN",
    "gn:dem":1252,
    "gn:feature_class":"P",
    "gn:feature_code":"PPL",
    "gn:name":"Maichagou",
    "gn:population":0,
    "gn:timezone":"Asia/Shanghai",
    "iso:country":"CN",
    "name:zho_x_preferred":[
        "\u9ea6\u5c94\u6c9f"
    ],
    "wof:name":"Maichagou",
    "wof:placetype":"locality"
},
  "geometry": {"coordinates":[110.41355,34.28287],"type":"Point"}
}