{
  "type": "Feature",
  "properties": {
    "gn:admin1_code":"25.0",
    "gn:asciiname":"Dabuhou",
    "gn:country_code":"CN",
    "gn:dem":47,
    "gn:feature_class":"P",
    "gn:feature_code":"PPL",
    "gn:name":"Dabuhou",
    "gn:population":0,
    "gn:timezone":"Asia/Shanghai",
    "iso:country":"CN",
    "name:zho_x_preferred":[
        "\u5927\u57e0\u540e"
    ],
    "wof:name":"Dabuhou",
    "wof:placetype":"locality"
},
  "geometry": {"coordinates":[119.26682,36.47391],"type":"Point"}
}