{
  "type": "Feature",
  "properties": {
    "gn:admin1_code":"19.0",
    "gn:asciiname":"Jinjiacun",
    "gn:country_code":"CN",
    "gn:dem":9,
    "gn:feature_class":"P",
    "gn:feature_code":"PPL",
    "gn:name":"Jinjiacun",
    "gn:population":0,
    "gn:timezone":"Asia/Shanghai",
    "iso:country":"CN",
    "name:zho_x_preferred":[
        "\u9773\u5bb6\u6751"
    ],
    "wof:name":"Jinjiacun",
    "wof:placetype":"locality"
},
  "geometry": {"coordinates":[121.437,41.01600000000001],"type":"Point"}
}