{
  "type": "Feature",
  "properties": {
    "gn:admin1_code":"12.0",
    "gn:asciiname":"Yihe",
    "gn:country_code":"CN",
    "gn:dem":62,
    "gn:feature_class":"P",
    "gn:feature_code":"PPLA4",
    "gn:name":"Yihe",
    "gn:population":0,
    "gn:timezone":"Asia/Shanghai",
    "iso:country":"CN",
    "name:und_x_variant":[
        "Yihe Zhen"
    ],
    "name:zho_x_preferred":[
        "\u4e49\u548c"
    ],
    "name:zho_x_variant":[
        "\u4e49\u548c\u9547"
    ],
    "wof:name":"Yihe",
    "wof:placetype":"locality"
},
  "geometry": {"coordinates":[113.19549000000001,30.93769],"type":"Point"}
}