{
  "type": "Feature",
  "properties": {
    "gn:admin1_code":"32.0",
    "gn:asciiname":"Baiyangwan",
    "gn:country_code":"CN",
    "gn:dem":542,
    "gn:feature_class":"P",
    "gn:feature_code":"PPL",
    "gn:name":"Baiyangwan",
    "gn:population":0,
    "gn:timezone":"Asia/Shanghai",
    "iso:country":"CN",
    "name:zho_x_preferred":[
        "\u67cf\u6768\u6e7e"
    ],
    "wof:name":"Baiyangwan",
    "wof:placetype":"locality"
},
  "geometry": {"coordinates":[104.32456999999999,28.78649],"type":"Point"}
}