{
  "type": "Feature",
  "properties": {
    "gn:admin1_code":"19.0",
    "gn:asciiname":"Kunduyingzi",
    "gn:country_code":"CN",
    "gn:dem":406,
    "gn:feature_class":"P",
    "gn:feature_code":"PPL",
    "gn:name":"Kunduyingzi",
    "gn:population":0,
    "gn:timezone":"Asia/Shanghai",
    "iso:country":"CN",
    "name:zho_x_preferred":[
        "\u5764\u90fd\u8425\u5b50"
    ],
    "wof:name":"Kunduyingzi",
    "wof:placetype":"locality"
},
  "geometry": {"coordinates":[119.68375,40.68047],"type":"Point"}
}