{
  "type": "Feature",
  "properties": {
    "gn:admin1_code":"15.0",
    "gn:asciiname":"Chenshan",
    "gn:country_code":"CN",
    "gn:dem":1910,
    "gn:feature_class":"P",
    "gn:feature_code":"PPL",
    "gn:name":"Chenshan",
    "gn:population":0,
    "gn:timezone":"Asia/Shanghai",
    "iso:country":"CN",
    "name:und_x_variant":[
        "\u9648\u5c71"
    ],
    "wof:name":"Chenshan",
    "wof:placetype":"locality"
},
  "geometry": {"coordinates":[105.38106000000001,35.11282],"type":"Point"}
}