{
  "type": "Feature",
  "properties": {
    "gn:admin1_code":"5.0",
    "gn:asciiname":"Daqiaocun",
    "gn:country_code":"CN",
    "gn:dem":194,
    "gn:feature_class":"P",
    "gn:feature_code":"PPL",
    "gn:name":"Daqiaocun",
    "gn:population":0,
    "gn:timezone":"Asia/Shanghai",
    "iso:country":"CN",
    "name:zho_x_preferred":[
        "\u5927\u6865\u6751"
    ],
    "wof:name":"Daqiaocun",
    "wof:placetype":"locality"
},
  "geometry": {"coordinates":[126.10648999999999,43.90329000000001],"type":"Point"}
}