{
  "type": "Feature",
  "properties": {
    "gn:admin1_code":"31",
    "gn:asciiname":"Honghai",
    "gn:country_code":"CN",
    "gn:dem":132,
    "gn:feature_class":"P",
    "gn:feature_code":"PPL",
    "gn:name":"Honghai",
    "gn:population":0,
    "gn:timezone":"Asia/Shanghai",
    "iso:country":"CN",
    "name:und_x_variant":[
        "\u7ea2\u6d77"
    ],
    "wof:name":"Honghai",
    "wof:placetype":"locality"
},
  "geometry": {"coordinates":[111.01806000000001,19.66139],"type":"Point"}
}