{
  "type": "Feature",
  "properties": {
    "gn:admin1_code":"11",
    "gn:asciiname":"Yuwangchong",
    "gn:country_code":"CN",
    "gn:dem":900,
    "gn:feature_class":"P",
    "gn:feature_code":"PPL",
    "gn:name":"Yuwangchong",
    "gn:population":0,
    "gn:timezone":"Asia/Shanghai",
    "iso:country":"CN",
    "name:zho_x_preferred":[
        "\u96e8\u738b\u51b2"
    ],
    "wof:name":"Yuwangchong",
    "wof:placetype":"locality"
},
  "geometry": {"coordinates":[111.80376,25.23777],"type":"Point"}
}