{
  "type": "Feature",
  "properties": {
    "gn:admin1_code":"30.0",
    "gn:asciiname":"Fengtang",
    "gn:country_code":"CN",
    "gn:dem":281,
    "gn:feature_class":"P",
    "gn:feature_code":"PPL",
    "gn:name":"Fengtang",
    "gn:population":0,
    "gn:timezone":"Asia/Shanghai",
    "iso:country":"CN",
    "name:zho_x_preferred":[
        "Fengtang"
    ],
    "name:zho_x_variant":[
        "\u51e4\u5858"
    ],
    "wof:name":"Fengtang",
    "wof:placetype":"locality"
},
  "geometry": {"coordinates":[112.39028,24.67306],"type":"Point"}
}