{
  "type": "Feature",
  "properties": {
    "gn:admin1_code":"7",
    "gn:asciiname":"Wuzhu",
    "gn:country_code":"CN",
    "gn:dem":12,
    "gn:feature_class":"P",
    "gn:feature_code":"PPL",
    "gn:name":"Wuzhu",
    "gn:population":0,
    "gn:timezone":"Asia/Shanghai",
    "iso:country":"CN",
    "name:rus_x_preferred":[
        "\u0412\u0430\u043d\u044c\u044f\u043d\u044c \u0423\u0447\u0436\u0443"
    ],
    "name:und_x_variant":[
        "Wu-chu",
        "Wuzhu"
    ],
    "name:vie_x_preferred":[
        "Ng\u1ed9t Tru\u1eadt"
    ],
    "name:zho_x_preferred":[
        "\u4e94\u7af9"
    ],
    "wof:name":"Wuzhu",
    "wof:placetype":"locality"
},
  "geometry": {"coordinates":[119.51000999999999,25.99616],"type":"Point"}
}