{
  "type": "Feature",
  "properties": {
    "gn:admin1_code":"3",
    "gn:asciiname":"Luodong",
    "gn:country_code":"CN",
    "gn:dem":269,
    "gn:feature_class":"P",
    "gn:feature_code":"PPL",
    "gn:name":"Luodong",
    "gn:population":0,
    "gn:timezone":"Asia/Shanghai",
    "iso:country":"CN",
    "name:zho_x_preferred":[
        "\u7f57\u6d1e"
    ],
    "wof:name":"Luodong",
    "wof:placetype":"locality"
},
  "geometry": {"coordinates":[114.59480000000001,26.13808],"type":"Point"}
}