{
  "type": "Feature",
  "properties": {
    "gn:admin1_code":"02",
    "gn:asciiname":"Kengkou",
    "gn:country_code":"CN",
    "gn:dem":371,
    "gn:feature_class":"P",
    "gn:feature_code":"PPL",
    "gn:name":"Kengkou",
    "gn:population":0,
    "gn:timezone":"Asia/Shanghai",
    "iso:country":"CN",
    "wof:name":"Kengkou",
    "wof:placetype":"locality"
},
  "geometry": {"coordinates":[120.05284,27.61799],"type":"Point"}
}