{
  "type": "Feature",
  "properties": {
    "gn:admin1_code":"5.0",
    "gn:asciiname":"Tuanshanzicun",
    "gn:country_code":"CN",
    "gn:dem":488,
    "gn:feature_class":"P",
    "gn:feature_code":"PPL",
    "gn:name":"Tuanshanzicun",
    "gn:population":0,
    "gn:timezone":"Asia/Shanghai",
    "iso:country":"CN",
    "name:zho_x_preferred":[
        "\u56e2\u5c71\u5b50\u6751"
    ],
    "wof:name":"Tuanshanzicun",
    "wof:placetype":"locality"
},
  "geometry": {"coordinates":[128.08584999999999,43.5419],"type":"Point"}
}