{
  "type": "Feature",
  "properties": {
    "gn:admin1_code":"4.0",
    "gn:asciiname":"Chendayuan",
    "gn:country_code":"CN",
    "gn:dem":12,
    "gn:feature_class":"P",
    "gn:feature_code":"PPL",
    "gn:name":"Chendayuan",
    "gn:population":0,
    "gn:timezone":"Asia/Shanghai",
    "iso:country":"CN",
    "name:zho_x_preferred":[
        "\u9648\u5927\u56ed"
    ],
    "wof:name":"Chendayuan",
    "wof:placetype":"locality"
},
  "geometry": {"coordinates":[118.74811,33.71228],"type":"Point"}
}