{
  "type": "Feature",
  "properties": {
    "gn:admin1_code":"18",
    "gn:asciiname":"Nagu",
    "gn:country_code":"CN",
    "gn:dem":1644,
    "gn:feature_class":"P",
    "gn:feature_code":"PPL",
    "gn:name":"Nagu",
    "gn:population":0,
    "gn:timezone":"Asia/Shanghai",
    "iso:country":"CN",
    "name:ceb_x_preferred":[
        "Nagu"
    ],
    "name:deu_x_preferred":[
        "Nagu"
    ],
    "name:est_x_preferred":[
        "Nagu"
    ],
    "name:fin_x_preferred":[
        "Nauvo"
    ],
    "name:fra_x_preferred":[
        "Nagu"
    ],
    "name:ita_x_preferred":[
        "Nagu"
    ],
    "name:nld_x_preferred":[
        "Nagu"
    ],
    "name:nor_x_preferred":[
        "Nagu"
    ],
    "name:ron_x_preferred":[
        "Nagu"
    ],
    "name:sme_x_preferred":[
        "Nauvo"
    ],
    "name:swe_x_preferred":[
        "Nagu"
    ],
    "name:vie_x_preferred":[
        "Nagu"
    ],
    "name:zho_x_preferred":[
        "\u7eb3\u59d1"
    ],
    "wof:name":"Nagu",
    "wof:placetype":"locality"
},
  "geometry": {"coordinates":[104.789,25.1235],"type":"Point"}
}