{
  "type": "Feature",
  "properties": {
    "gn:admin1_code":"22.0",
    "gn:asciiname":"Dacaolingcun",
    "gn:country_code":"CN",
    "gn:dem":630,
    "gn:feature_class":"P",
    "gn:feature_code":"PPL",
    "gn:name":"Dacaolingcun",
    "gn:population":0,
    "gn:timezone":"Asia/Shanghai",
    "iso:country":"CN",
    "name:zho_x_preferred":[
        "\u5927\u8349\u5cad\u6751"
    ],
    "wof:name":"Dacaolingcun",
    "wof:placetype":"locality"
},
  "geometry": {"coordinates":[115.80591,39.74558],"type":"Point"}
}