{
  "type": "Feature",
  "properties": {
    "gn:admin1_code":"25",
    "gn:asciiname":"Lijiazhuang",
    "gn:country_code":"CN",
    "gn:dem":199,
    "gn:feature_class":"P",
    "gn:feature_code":"PPL",
    "gn:name":"Lijiazhuang",
    "gn:population":0,
    "gn:timezone":"Asia/Shanghai",
    "iso:country":"CN",
    "name:zho_x_preferred":[
        "\u674e\u5bb6\u5e84"
    ],
    "wof:name":"Lijiazhuang",
    "wof:placetype":"locality"
},
  "geometry": {"coordinates":[117.246,36.3118],"type":"Point"}
}