{
  "type": "Feature",
  "properties": {
    "gn:admin1_code":"02",
    "gn:asciiname":"Shangbucun",
    "gn:country_code":"CN",
    "gn:dem":170,
    "gn:feature_class":"P",
    "gn:feature_code":"PPL",
    "gn:name":"Shangbucun",
    "gn:population":0,
    "gn:timezone":"Asia/Shanghai",
    "iso:country":"CN",
    "name:und_x_variant":[
        "Kai-t\u2019ou",
        "Shangbu",
        "Shangbucun"
    ],
    "name:zho_x_preferred":[
        "\u4e0a\u57e0"
    ],
    "name:zho_x_variant":[
        "\u4e0a\u57e0\u6751"
    ],
    "wof:name":"Shangbucun",
    "wof:placetype":"locality"
},
  "geometry": {"coordinates":[120.86929000000001,28.39879],"type":"Point"}
}