{
  "type": "Feature",
  "properties": {
    "gn:admin1_code":"7.0",
    "gn:asciiname":"Guchong",
    "gn:country_code":"CN",
    "gn:dem":346,
    "gn:feature_class":"P",
    "gn:feature_code":"PPL",
    "gn:name":"Guchong",
    "gn:population":0,
    "gn:timezone":"Asia/Shanghai",
    "iso:country":"CN",
    "name:zho_x_preferred":[
        "\u56fa\u5145"
    ],
    "wof:name":"Guchong",
    "wof:placetype":"locality"
},
  "geometry": {"coordinates":[118.39225999999999,27.94812],"type":"Point"}
}