{
  "type": "Feature",
  "properties": {
    "gn:admin1_code":"15.0",
    "gn:asciiname":"Paqiao",
    "gn:country_code":"CN",
    "gn:dem":2896,
    "gn:feature_class":"P",
    "gn:feature_code":"PPL",
    "gn:name":"Paqiao",
    "gn:population":0,
    "gn:timezone":"Asia/Shanghai",
    "iso:country":"CN",
    "name:und_x_variant":[
        "\u6015\u4e54"
    ],
    "wof:name":"Paqiao",
    "wof:placetype":"locality"
},
  "geometry": {"coordinates":[103.01476,34.67249],"type":"Point"}
}