{
  "type": "Feature",
  "properties": {
    "gn:admin1_code":"9.0",
    "gn:asciiname":"Dianlou",
    "gn:country_code":"CN",
    "gn:dem":134,
    "gn:feature_class":"P",
    "gn:feature_code":"PPL",
    "gn:name":"Dianlou",
    "gn:population":0,
    "gn:timezone":"Asia/Shanghai",
    "iso:country":"CN",
    "name:und_x_variant":[
        "\u6bbf\u697c"
    ],
    "name:zho_x_preferred":[
        "\u6bbf\u697c"
    ],
    "wof:name":"Dianlou",
    "wof:placetype":"locality"
},
  "geometry": {"coordinates":[113.34677000000001,33.16639],"type":"Point"}
}