{
  "type": "Feature",
  "properties": {
    "gn:admin1_code":"6.0",
    "gn:asciiname":"Juhula",
    "gn:country_code":"CN",
    "gn:dem":2686,
    "gn:feature_class":"P",
    "gn:feature_code":"PPL",
    "gn:name":"Juhula",
    "gn:population":0,
    "gn:timezone":"Asia/Shanghai",
    "iso:country":"CN",
    "name:und_x_variant":[
        "\u5c45\u4e4e\u62c9"
    ],
    "wof:name":"Juhula",
    "wof:placetype":"locality"
},
  "geometry": {"coordinates":[100.89131,35.94962],"type":"Point"}
}