{
  "type": "Feature",
  "properties": {
    "gn:admin1_code":"30",
    "gn:asciiname":"Caolang",
    "gn:country_code":"CN",
    "gn:dem":81,
    "gn:feature_class":"P",
    "gn:feature_code":"PPL",
    "gn:name":"Caolang",
    "gn:population":0,
    "gn:timezone":"Asia/Urumqi",
    "iso:country":"CN",
    "name:zho_x_preferred":[
        "\u8349\u6717"
    ],
    "wof:name":"Caolang",
    "wof:placetype":"locality"
},
  "geometry": {"coordinates":[110.25986,20.73249],"type":"Point"}
}