{
  "type": "Feature",
  "properties": {
    "gn:admin1_code":"14.0",
    "gn:asciiname":"Chawo",
    "gn:country_code":"CN",
    "gn:dem":4509,
    "gn:feature_class":"P",
    "gn:feature_code":"PPL",
    "gn:name":"Chawo",
    "gn:population":0,
    "gn:timezone":"Asia/Urumqi",
    "iso:country":"CN",
    "name:zho_x_preferred":[
        "\u67e5\u5367"
    ],
    "wof:name":"Chawo",
    "wof:placetype":"locality"
},
  "geometry": {"coordinates":[88.1529,29.0404],"type":"Point"}
}