{
  "type": "Feature",
  "properties": {
    "gn:admin1_code":"32.0",
    "gn:asciiname":"Ertuqiao",
    "gn:country_code":"CN",
    "gn:dem":516,
    "gn:feature_class":"P",
    "gn:feature_code":"PPL",
    "gn:name":"Ertuqiao",
    "gn:population":0,
    "gn:timezone":"Asia/Shanghai",
    "iso:country":"CN",
    "name:zho_x_preferred":[
        "\u4e8c\u571f\u6865"
    ],
    "wof:name":"Ertuqiao",
    "wof:placetype":"locality"
},
  "geometry": {"coordinates":[103.91333,30.67457000000001],"type":"Point"}
}