{
  "type": "Feature",
  "properties": {
    "gn:admin1_code":"10.0",
    "gn:asciiname":"Langyanshan",
    "gn:country_code":"CN",
    "gn:dem":1026,
    "gn:feature_class":"P",
    "gn:feature_code":"PPL",
    "gn:name":"Langyanshan",
    "gn:population":0,
    "gn:timezone":"Asia/Shanghai",
    "iso:country":"CN",
    "name:zho_x_preferred":[
        "\u72fc\u70df\u5c71"
    ],
    "wof:name":"Langyanshan",
    "wof:placetype":"locality"
},
  "geometry": {"coordinates":[115.25942999999999,39.85464],"type":"Point"}
}