{
  "type": "Feature",
  "properties": {
    "gn:admin1_code":"18.0",
    "gn:asciiname":"Zailang",
    "gn:country_code":"CN",
    "gn:dem":408,
    "gn:feature_class":"P",
    "gn:feature_code":"PPL",
    "gn:name":"Zailang",
    "gn:population":0,
    "gn:timezone":"Asia/Shanghai",
    "iso:country":"CN",
    "name:zho_x_preferred":[
        "\u5bb0\u90ce"
    ],
    "wof:name":"Zailang",
    "wof:placetype":"locality"
},
  "geometry": {"coordinates":[108.515,25.6379],"type":"Point"}
}