{
  "type": "Feature",
  "properties": {
    "gn:admin1_code":"21.0",
    "gn:asciiname":"Ninghua Yidui",
    "gn:country_code":"CN",
    "gn:dem":1130,
    "gn:feature_class":"P",
    "gn:feature_code":"PPLF",
    "gn:name":"Ninghua Yidui",
    "gn:population":0,
    "gn:timezone":"Asia/Shanghai",
    "iso:country":"CN",
    "name:zho_x_preferred":[
        "\u5b81\u5316\u4e00\u961f"
    ],
    "wof:name":"Ninghua Yidui",
    "wof:placetype":"locality"
},
  "geometry": {"coordinates":[106.033,38.2115],"type":"Point"}
}