{
  "type": "Feature",
  "properties": {
    "gn:admin1_code":"33.0",
    "gn:asciiname":"Oujiaba",
    "gn:country_code":"CN",
    "gn:dem":559,
    "gn:feature_class":"P",
    "gn:feature_code":"PPL",
    "gn:name":"Oujiaba",
    "gn:population":0,
    "gn:timezone":"Asia/Shanghai",
    "iso:country":"CN",
    "name:zho_x_preferred":[
        "\u6b27\u5bb6\u575d"
    ],
    "wof:name":"Oujiaba",
    "wof:placetype":"locality"
},
  "geometry": {"coordinates":[106.779,28.8705],"type":"Point"}
}