{
  "type": "Feature",
  "properties": {
    "gn:admin1_code":"3.0",
    "gn:asciiname":"Songshanbei",
    "gn:country_code":"CN",
    "gn:dem":345,
    "gn:feature_class":"P",
    "gn:feature_code":"PPL",
    "gn:name":"Songshanbei",
    "gn:population":0,
    "gn:timezone":"Asia/Shanghai",
    "iso:country":"CN",
    "name:und_x_variant":[
        "\u677e\u5c71\u80cc"
    ],
    "wof:name":"Songshanbei",
    "wof:placetype":"locality"
},
  "geometry": {"coordinates":[116.09644,26.48508],"type":"Point"}
}