{
  "type": "Feature",
  "properties": {
    "gn:admin1_code":"7.0",
    "gn:asciiname":"Jiazibei",
    "gn:country_code":"CN",
    "gn:dem":430,
    "gn:feature_class":"P",
    "gn:feature_code":"PPL",
    "gn:name":"Jiazibei",
    "gn:population":0,
    "gn:timezone":"Asia/Shanghai",
    "iso:country":"CN",
    "name:zho_x_preferred":[
        "\u7532\u5b50\u80cc"
    ],
    "wof:name":"Jiazibei",
    "wof:placetype":"locality"
},
  "geometry": {"coordinates":[116.89713,24.81166],"type":"Point"}
}