{
  "type": "Feature",
  "properties": {
    "gn:admin1_code":"11",
    "gn:asciiname":"Shibichong",
    "gn:country_code":"CN",
    "gn:dem":988,
    "gn:feature_class":"P",
    "gn:feature_code":"PPL",
    "gn:name":"Shibichong",
    "gn:population":0,
    "gn:timezone":"Asia/Shanghai",
    "iso:country":"CN",
    "name:und_x_variant":[
        "\u77f3\u58c1\u51b2",
        "Shibichong"
    ],
    "wof:name":"Shibichong",
    "wof:placetype":"locality"
},
  "geometry": {"coordinates":[112.05889000000001,25.04389],"type":"Point"}
}