{
  "type": "Feature",
  "properties": {
    "gn:admin1_code":"19.0",
    "gn:asciiname":"Yeshacun",
    "gn:country_code":"CN",
    "gn:dem":11,
    "gn:feature_class":"P",
    "gn:feature_code":"PPL",
    "gn:name":"Yeshacun",
    "gn:population":0,
    "gn:timezone":"Asia/Shanghai",
    "iso:country":"CN",
    "name:zho_x_preferred":[
        "\u53f6\u6c99\u6751"
    ],
    "wof:name":"Yeshacun",
    "wof:placetype":"locality"
},
  "geometry": {"coordinates":[122.3844,41.56148],"type":"Point"}
}