{
  "type": "Feature",
  "properties": {
    "gn:admin1_code":"02",
    "gn:asciiname":"Shirencun",
    "gn:country_code":"CN",
    "gn:dem":171,
    "gn:feature_class":"P",
    "gn:feature_code":"PPL",
    "gn:name":"Shirencun",
    "gn:population":0,
    "gn:timezone":"Asia/Shanghai",
    "iso:country":"CN",
    "name:und_x_variant":[
        "Shih-jen",
        "Shiren",
        "Shirencun"
    ],
    "name:zho_x_preferred":[
        "\u77f3\u4eba"
    ],
    "name:zho_x_variant":[
        "\u77f3\u4eba\u6751"
    ],
    "wof:name":"Shirencun",
    "wof:placetype":"locality"
},
  "geometry": {"coordinates":[120.76515000000001,28.69732],"type":"Point"}
}