{
  "type": "Feature",
  "properties": {
    "gn:admin1_code":"26.0",
    "gn:asciiname":"Hanzhuangke",
    "gn:country_code":"CN",
    "gn:dem":1328,
    "gn:feature_class":"P",
    "gn:feature_code":"PPL",
    "gn:name":"Hanzhuangke",
    "gn:population":0,
    "gn:timezone":"Asia/Shanghai",
    "iso:country":"CN",
    "name:zho_x_preferred":[
        "\u97e9\u5e84\u79d1"
    ],
    "wof:name":"Hanzhuangke",
    "wof:placetype":"locality"
},
  "geometry": {"coordinates":[109.21787999999999,37.24874000000001],"type":"Point"}
}