{
  "type": "Feature",
  "properties": {
    "gn:admin1_code":"02",
    "gn:asciiname":"Leishicun",
    "gn:country_code":"CN",
    "gn:dem":20,
    "gn:feature_class":"P",
    "gn:feature_code":"PPL",
    "gn:name":"Leishicun",
    "gn:population":0,
    "gn:timezone":"Asia/Shanghai",
    "iso:country":"CN",
    "name:und_x_variant":[
        "Lei-shih",
        "Leishi",
        "Leishicun"
    ],
    "name:zho_x_preferred":[
        "\u78ca\u77f3"
    ],
    "name:zho_x_variant":[
        "\u78ca\u77f3\u6751"
    ],
    "wof:name":"Leishicun",
    "wof:placetype":"locality"
},
  "geometry": {"coordinates":[121.45375,28.32647],"type":"Point"}
}