{
  "type": "Feature",
  "properties": {
    "gn:admin1_code":"11",
    "gn:asciiname":"Tanfu",
    "gn:country_code":"CN",
    "gn:dem":157,
    "gn:feature_class":"P",
    "gn:feature_code":"PPL",
    "gn:name":"Tanfu",
    "gn:population":0,
    "gn:timezone":"Asia/Shanghai",
    "iso:country":"CN",
    "name:zho_x_preferred":[
        "\u5766\u590d"
    ],
    "wof:name":"Tanfu",
    "wof:placetype":"locality"
},
  "geometry": {"coordinates":[111.34148,26.0408],"type":"Point"}
}