{
  "type": "Feature",
  "properties": {
    "gn:admin1_code":"16.0",
    "gn:asciiname":"Guiliucun",
    "gn:country_code":"CN",
    "gn:dem":1152,
    "gn:feature_class":"P",
    "gn:feature_code":"PPL",
    "gn:name":"Guiliucun",
    "gn:population":0,
    "gn:timezone":"Asia/Shanghai",
    "iso:country":"CN",
    "name:zho_x_preferred":[
        "\u89c4\u516d\u6751"
    ],
    "wof:name":"Guiliucun",
    "wof:placetype":"locality"
},
  "geometry": {"coordinates":[105.754,23.1822],"type":"Point"}
}