{
  "type": "Feature",
  "properties": {
    "gn:admin1_code":"24",
    "gn:asciiname":"Nanyujiao",
    "gn:cc2":"CN",
    "gn:country_code":"CN",
    "gn:dem":1031,
    "gn:feature_class":"P",
    "gn:feature_code":"PPL",
    "gn:name":"Nanyujiao",
    "gn:population":0,
    "gn:timezone":"Asia/Shanghai",
    "iso:country":"CN",
    "name:und_x_variant":[
        "Nan-y\u00fc-chiao",
        "Nanyujiao"
    ],
    "wof:name":"Nanyujiao",
    "wof:placetype":"locality"
},
  "geometry": {"coordinates":[112.58333,36.65],"type":"Point"}
}