{
  "type": "Feature",
  "properties": {
    "gn:admin1_code":"30",
    "gn:asciiname":"Yunancun",
    "gn:country_code":"CN",
    "gn:dem":5,
    "gn:feature_class":"P",
    "gn:feature_code":"PPL",
    "gn:name":"Yunancun",
    "gn:population":0,
    "gn:timezone":"Asia/Shanghai",
    "iso:country":"CN",
    "name:zho_x_preferred":[
        "\u5c7f\u5357\u6751"
    ],
    "wof:name":"Yunancun",
    "wof:placetype":"locality"
},
  "geometry": {"coordinates":[116.38249,23.32117],"type":"Point"}
}