{
  "type": "Feature",
  "properties": {
    "gn:admin1_code":"29.0",
    "gn:asciiname":"Laotucheng",
    "gn:country_code":"CN",
    "gn:dem":2012,
    "gn:feature_class":"P",
    "gn:feature_code":"PPL",
    "gn:name":"Laotucheng",
    "gn:population":0,
    "gn:timezone":"Asia/Shanghai",
    "iso:country":"CN",
    "name:zho_x_preferred":[
        "\u8001\u571f\u57ce"
    ],
    "wof:name":"Laotucheng",
    "wof:placetype":"locality"
},
  "geometry": {"coordinates":[103.078,25.9917],"type":"Point"}
}