{
  "type": "Feature",
  "properties": {
    "gn:admin1_code":"15.0",
    "gn:asciiname":"Liudongzhan",
    "gn:country_code":"CN",
    "gn:dem":1779,
    "gn:feature_class":"P",
    "gn:feature_code":"PPL",
    "gn:name":"Liudongzhan",
    "gn:population":0,
    "gn:timezone":"Asia/Urumqi",
    "iso:country":"CN",
    "name:zho_x_preferred":[
        "\u67f3\u4e1c\u7ad9"
    ],
    "wof:name":"Liudongzhan",
    "wof:placetype":"locality"
},
  "geometry": {"coordinates":[95.5993,41.0538],"type":"Point"}
}