{
  "type": "Feature",
  "properties": {
    "gn:admin1_code":"7",
    "gn:asciiname":"Xiacang",
    "gn:country_code":"CN",
    "gn:dem":291,
    "gn:feature_class":"P",
    "gn:feature_code":"PPL",
    "gn:name":"Xiacang",
    "gn:population":0,
    "gn:timezone":"Asia/Shanghai",
    "iso:country":"CN",
    "name:und_x_variant":[
        "\u4e0b\u4ed3"
    ],
    "wof:name":"Xiacang",
    "wof:placetype":"locality"
},
  "geometry": {"coordinates":[118.68805999999999,27.665],"type":"Point"}
}