{
  "type": "Feature",
  "properties": {
    "gn:admin1_code":"22.0",
    "gn:asciiname":"Niantaicun",
    "gn:country_code":"CN",
    "gn:dem":612,
    "gn:feature_class":"P",
    "gn:feature_code":"PPL",
    "gn:name":"Niantaicun",
    "gn:population":0,
    "gn:timezone":"Asia/Shanghai",
    "iso:country":"CN",
    "name:zho_x_preferred":[
        "\u78be\u53f0\u6751"
    ],
    "wof:name":"Niantaicun",
    "wof:placetype":"locality"
},
  "geometry": {"coordinates":[115.68810000000001,40.11031],"type":"Point"}
}