{
  "type": "Feature",
  "properties": {
    "gn:admin1_code":"29",
    "gn:asciiname":"Nagua",
    "gn:country_code":"CN",
    "gn:dem":907,
    "gn:feature_class":"P",
    "gn:feature_code":"PPL",
    "gn:name":"Nagua",
    "gn:population":0,
    "gn:timezone":"Asia/Shanghai",
    "iso:country":"CN",
    "name:ara_x_preferred":[
        "\u0646\u0627\u063a\u0648\u0627"
    ],
    "name:ceb_x_preferred":[
        "Nagua"
    ],
    "name:fas_x_preferred":[
        "\u0646\u0627\u06af\u0648\u0627"
    ],
    "name:fra_x_preferred":[
        "Nagua"
    ],
    "name:heb_x_preferred":[
        "\u05e0\u05d2\u05d5\u05d0\u05d4"
    ],
    "name:hun_x_preferred":[
        "Nagua"
    ],
    "name:ita_x_preferred":[
        "Nagua"
    ],
    "name:nld_x_preferred":[
        "Nagua"
    ],
    "name:pol_x_preferred":[
        "Nagua"
    ],
    "name:por_x_preferred":[
        "Nagua"
    ],
    "name:rus_x_preferred":[
        "\u041d\u0430\u0433\u0443\u0430"
    ],
    "name:slv_x_preferred":[
        "Nagua"
    ],
    "name:spa_x_preferred":[
        "Nagua"
    ],
    "name:swe_x_preferred":[
        "Nagua"
    ],
    "name:ukr_x_preferred":[
        "\u041d\u0430\u0433\u0443\u0430"
    ],
    "name:urd_x_preferred":[
        "\u0646\u0627\u06af\u0648\u0627"
    ],
    "name:war_x_preferred":[
        "Nagua"
    ],
    "name:zho_x_preferred":[
        "\u90a3\u6302"
    ],
    "wof:name":"Nagua",
    "wof:placetype":"locality"
},
  "geometry": {"coordinates":[105.518,23.8358],"type":"Point"}
}