{
  "type": "Feature",
  "properties": {
    "gn:admin1_code":"1.0",
    "gn:asciiname":"Gaotangcun",
    "gn:country_code":"CN",
    "gn:dem":32,
    "gn:feature_class":"P",
    "gn:feature_code":"PPL",
    "gn:name":"Gaotangcun",
    "gn:population":0,
    "gn:timezone":"Asia/Shanghai",
    "iso:country":"CN",
    "name:zho_x_preferred":[
        "\u9ad8\u5858\u6751"
    ],
    "wof:name":"Gaotangcun",
    "wof:placetype":"locality"
},
  "geometry": {"coordinates":[117.21953000000001,30.88971],"type":"Point"}
}