{
  "type": "Feature",
  "properties": {
    "gn:admin1_code":"24.0",
    "gn:asciiname":"Zhangjiayuan",
    "gn:country_code":"CN",
    "gn:dem":1141,
    "gn:feature_class":"P",
    "gn:feature_code":"PPL",
    "gn:name":"Zhangjiayuan",
    "gn:population":0,
    "gn:timezone":"Asia/Shanghai",
    "iso:country":"CN",
    "name:zho_x_preferred":[
        "\u5f20\u5bb6\u586c"
    ],
    "wof:name":"Zhangjiayuan",
    "wof:placetype":"locality"
},
  "geometry": {"coordinates":[110.91388000000001,36.36575],"type":"Point"}
}