{
  "type": "Feature",
  "properties": {
    "gn:admin1_code":"12.0",
    "gn:asciiname":"Xiaolindian",
    "gn:cc2":"CN",
    "gn:country_code":"CN",
    "gn:dem":134,
    "gn:feature_class":"P",
    "gn:feature_code":"PPL",
    "gn:name":"Xiaolindian",
    "gn:population":0,
    "gn:timezone":"Asia/Shanghai",
    "iso:country":"CN",
    "name:und_x_variant":[
        "Hsiao-lin-tien",
        "Xiaolindian"
    ],
    "wof:name":"Xiaolindian",
    "wof:placetype":"locality"
},
  "geometry": {"coordinates":[112.73333,32.31667],"type":"Point"}
}