{
  "type": "Feature",
  "properties": {
    "gn:admin1_code":"16.0",
    "gn:asciiname":"Nagan",
    "gn:country_code":"CN",
    "gn:dem":226,
    "gn:feature_class":"P",
    "gn:feature_code":"PPL",
    "gn:name":"Nagan",
    "gn:population":0,
    "gn:timezone":"Asia/Shanghai",
    "iso:country":"CN",
    "name:zho_x_preferred":[
        "\u7eb3\u6562"
    ],
    "wof:name":"Nagan",
    "wof:placetype":"locality"
},
  "geometry": {"coordinates":[108.84399999999999,25.0678],"type":"Point"}
}