{
  "type": "Feature",
  "properties": {
    "gn:admin1_code":"26.0",
    "gn:asciiname":"Dushancun",
    "gn:country_code":"CN",
    "gn:dem":733,
    "gn:feature_class":"P",
    "gn:feature_code":"PPL",
    "gn:name":"Dushancun",
    "gn:population":0,
    "gn:timezone":"Asia/Shanghai",
    "iso:country":"CN",
    "name:zho_x_preferred":[
        "\u72ec\u5c71\u6751"
    ],
    "wof:name":"Dushancun",
    "wof:placetype":"locality"
},
  "geometry": {"coordinates":[107.69444,34.46069],"type":"Point"}
}