{
  "type": "Feature",
  "properties": {
    "gn:admin1_code":"16.0",
    "gn:asciiname":"Huoshaoliao",
    "gn:country_code":"CN",
    "gn:dem":35,
    "gn:feature_class":"P",
    "gn:feature_code":"PPL",
    "gn:name":"Huoshaoliao",
    "gn:population":0,
    "gn:timezone":"Asia/Shanghai",
    "iso:country":"CN",
    "name:zho_x_preferred":[
        "\u706b\u70e7\u5bee"
    ],
    "wof:name":"Huoshaoliao",
    "wof:placetype":"locality"
},
  "geometry": {"coordinates":[110.523,23.4341],"type":"Point"}
}