{
  "type": "Feature",
  "properties": {
    "gn:admin1_code":"26.0",
    "gn:asciiname":"Zhuzhuang",
    "gn:cc2":"CN",
    "gn:country_code":"CN",
    "gn:dem":1500,
    "gn:feature_class":"P",
    "gn:feature_code":"PPL",
    "gn:name":"Zhuzhuang",
    "gn:population":0,
    "gn:timezone":"Asia/Shanghai",
    "iso:country":"CN",
    "name:und_x_variant":[
        "Chu-chia-chuang",
        "Chu-chuang",
        "Zhuzhuang"
    ],
    "wof:name":"Zhuzhuang",
    "wof:placetype":"locality"
},
  "geometry": {"coordinates":[108.56667,36.55],"type":"Point"}
}