{
  "type": "Feature",
  "properties": {
    "gn:admin1_code":"25",
    "gn:asciiname":"Jiezhang",
    "gn:country_code":"CN",
    "gn:dem":59,
    "gn:feature_class":"P",
    "gn:feature_code":"PPL",
    "gn:name":"Jiezhang",
    "gn:population":0,
    "gn:timezone":"Asia/Shanghai",
    "iso:country":"CN",
    "name:zho_x_preferred":[
        "\u89e3\u5f20"
    ],
    "wof:name":"Jiezhang",
    "wof:placetype":"locality"
},
  "geometry": {"coordinates":[115.34999999999999,35.5309],"type":"Point"}
}