{
  "type": "Feature",
  "properties": {
    "gn:admin1_code":"32.0",
    "gn:asciiname":"Banliwan",
    "gn:country_code":"CN",
    "gn:dem":372,
    "gn:feature_class":"P",
    "gn:feature_code":"PPL",
    "gn:name":"Banliwan",
    "gn:population":0,
    "gn:timezone":"Asia/Shanghai",
    "iso:country":"CN",
    "name:zho_x_preferred":[
        "\u677f\u6817\u6e7e"
    ],
    "wof:name":"Banliwan",
    "wof:placetype":"locality"
},
  "geometry": {"coordinates":[104.71559000000001,29.15485],"type":"Point"}
}