{
  "type": "Feature",
  "properties": {
    "gn:admin1_code":"25.0",
    "gn:asciiname":"Zhujiaqigoucun",
    "gn:country_code":"CN",
    "gn:dem":23,
    "gn:feature_class":"P",
    "gn:feature_code":"PPL",
    "gn:name":"Zhujiaqigoucun",
    "gn:population":0,
    "gn:timezone":"Asia/Shanghai",
    "iso:country":"CN",
    "name:zho_x_preferred":[
        "\u6731\u5bb6\u4e03\u6c9f\u6751"
    ],
    "wof:name":"Zhujiaqigoucun",
    "wof:placetype":"locality"
},
  "geometry": {"coordinates":[119.50921,36.58546],"type":"Point"}
}