{
  "type": "Feature",
  "properties": {
    "gn:admin1_code":"11.0",
    "gn:asciiname":"Zhoujiayan",
    "gn:country_code":"CN",
    "gn:dem":79,
    "gn:feature_class":"P",
    "gn:feature_code":"PPL",
    "gn:name":"Zhoujiayan",
    "gn:population":0,
    "gn:timezone":"Asia/Shanghai",
    "iso:country":"CN",
    "name:zho_x_preferred":[
        "Zhoujiayan"
    ],
    "name:zho_x_variant":[
        "\u5468\u5bb6\u5830"
    ],
    "wof:name":"Zhoujiayan",
    "wof:placetype":"locality"
},
  "geometry": {"coordinates":[111.79737,29.30251],"type":"Point"}
}