{
  "type": "Feature",
  "properties": {
    "gn:admin1_code":"9.0",
    "gn:asciiname":"Yangguanying",
    "gn:country_code":"CN",
    "gn:dem":126,
    "gn:feature_class":"P",
    "gn:feature_code":"PPL",
    "gn:name":"Yangguanying",
    "gn:population":0,
    "gn:timezone":"Asia/Shanghai",
    "iso:country":"CN",
    "name:zho_x_preferred":[
        "\u6768\u5b98\u8425"
    ],
    "wof:name":"Yangguanying",
    "wof:placetype":"locality"
},
  "geometry": {"coordinates":[112.60557,32.98388],"type":"Point"}
}