{
  "type": "Feature",
  "properties": {
    "gn:admin1_code":"29",
    "gn:asciiname":"Yujiawei",
    "gn:country_code":"CN",
    "gn:dem":1850,
    "gn:feature_class":"P",
    "gn:feature_code":"PPL",
    "gn:name":"Yujiawei",
    "gn:population":0,
    "gn:timezone":"Asia/Shanghai",
    "iso:country":"CN",
    "name:und_x_variant":[
        "\u4f59\u5bb6\u5729"
    ],
    "wof:name":"Yujiawei",
    "wof:placetype":"locality"
},
  "geometry": {"coordinates":[103.84996,25.45762],"type":"Point"}
}