{
  "type": "Feature",
  "properties": {
    "gn:admin1_code":"14.0",
    "gn:asciiname":"Maqiandangma",
    "gn:country_code":"CN",
    "gn:dem":4681,
    "gn:feature_class":"P",
    "gn:feature_code":"PPL",
    "gn:name":"Maqiandangma",
    "gn:population":0,
    "gn:timezone":"Asia/Urumqi",
    "iso:country":"CN",
    "name:bod_x_preferred":[
        "Marq\u00eand\u00eangma"
    ],
    "name:zho_x_preferred":[
        "Maqiandangma"
    ],
    "name:zho_x_variant":[
        "\u739b\u8fc1\u5f53\u739b"
    ],
    "wof:name":"Maqiandangma",
    "wof:placetype":"locality"
},
  "geometry": {"coordinates":[86.801,32.201],"type":"Point"}
}