{
  "type": "Feature",
  "properties": {
    "gn:admin1_code":"16.0",
    "gn:asciiname":"Baiduan",
    "gn:country_code":"CN",
    "gn:dem":570,
    "gn:feature_class":"P",
    "gn:feature_code":"PPL",
    "gn:name":"Baiduan",
    "gn:population":0,
    "gn:timezone":"Asia/Shanghai",
    "iso:country":"CN",
    "name:zho_x_preferred":[
        "\u767e\u7aef"
    ],
    "wof:name":"Baiduan",
    "wof:placetype":"locality"
},
  "geometry": {"coordinates":[106.812,24.1558],"type":"Point"}
}