{
  "type": "Feature",
  "properties": {
    "gn:admin1_code":"16.0",
    "gn:asciiname":"Xihekou",
    "gn:country_code":"CN",
    "gn:dem":178,
    "gn:feature_class":"P",
    "gn:feature_code":"PPL",
    "gn:name":"Xihekou",
    "gn:population":0,
    "gn:timezone":"Asia/Shanghai",
    "iso:country":"CN",
    "name:zho_x_preferred":[
        "\u897f\u6cb3\u53e3"
    ],
    "wof:name":"Xihekou",
    "wof:placetype":"locality"
},
  "geometry": {"coordinates":[111.087,23.4567],"type":"Point"}
}