{
  "type": "Feature",
  "properties": {
    "gn:admin1_code":"18",
    "gn:asciiname":"Buti",
    "gn:country_code":"CN",
    "gn:dem":1342,
    "gn:feature_class":"P",
    "gn:feature_code":"PPL",
    "gn:name":"Buti",
    "gn:population":0,
    "gn:timezone":"Asia/Shanghai",
    "iso:country":"CN",
    "name:zho_x_preferred":[
        "\u5e03\u63d0"
    ],
    "wof:name":"Buti",
    "wof:placetype":"locality"
},
  "geometry": {"coordinates":[105.24299999999999,26.2298],"type":"Point"}
}