{
  "type": "Feature",
  "properties": {
    "gn:admin1_code":"20",
    "gn:asciiname":"Hsia-hao-lai-kou",
    "gn:country_code":"CN",
    "gn:dem":479,
    "gn:feature_class":"P",
    "gn:feature_code":"PPL",
    "gn:name":"Hsia-hao-lai-kou",
    "gn:population":0,
    "gn:timezone":"Asia/Shanghai",
    "iso:country":"CN",
    "wof:name":"Hsia-hao-lai-kou",
    "wof:placetype":"locality"
},
  "geometry": {"coordinates":[119.4325,42.44167],"type":"Point"}
}