{
  "type": "Feature",
  "properties": {
    "gn:admin1_code":"1.0",
    "gn:asciiname":"Dongwuji",
    "gn:country_code":"CN",
    "gn:dem":13,
    "gn:feature_class":"P",
    "gn:feature_code":"PPL",
    "gn:name":"Dongwuji",
    "gn:population":0,
    "gn:timezone":"Asia/Shanghai",
    "iso:country":"CN",
    "name:zho_x_preferred":[
        "\u8463\u5c4b\u57fa"
    ],
    "wof:name":"Dongwuji",
    "wof:placetype":"locality"
},
  "geometry": {"coordinates":[118.46869,31.14449],"type":"Point"}
}