{
  "type": "Feature",
  "properties": {
    "gn:admin1_code":"29.0",
    "gn:asciiname":"Xiangshuicun",
    "gn:country_code":"CN",
    "gn:dem":2081,
    "gn:feature_class":"P",
    "gn:feature_code":"PPL",
    "gn:name":"Xiangshuicun",
    "gn:population":0,
    "gn:timezone":"Asia/Shanghai",
    "iso:country":"CN",
    "name:zho_x_preferred":[
        "\u54cd\u6c34\u6751"
    ],
    "wof:name":"Xiangshuicun",
    "wof:placetype":"locality"
},
  "geometry": {"coordinates":[102.93600000000001,25.1753],"type":"Point"}
}