{
  "type": "Feature",
  "properties": {
    "gn:admin1_code":"3.0",
    "gn:asciiname":"Shizigang",
    "gn:country_code":"CN",
    "gn:dem":284,
    "gn:feature_class":"P",
    "gn:feature_code":"PPL",
    "gn:name":"Shizigang",
    "gn:population":0,
    "gn:timezone":"Asia/Shanghai",
    "iso:country":"CN",
    "name:und_x_variant":[
        "\u77f3\u6893\u5c97"
    ],
    "wof:name":"Shizigang",
    "wof:placetype":"locality"
},
  "geometry": {"coordinates":[114.03341,29.10566],"type":"Point"}
}