{
  "type": "Feature",
  "properties": {
    "gn:admin1_code":"20.0",
    "gn:asciiname":"Xixiangyang",
    "gn:country_code":"CN",
    "gn:dem":261,
    "gn:feature_class":"P",
    "gn:feature_code":"PPL",
    "gn:name":"Xixiangyang",
    "gn:population":0,
    "gn:timezone":"Asia/Shanghai",
    "iso:country":"CN",
    "name:zho_x_preferred":[
        "\u897f\u5411\u9633"
    ],
    "wof:name":"Xixiangyang",
    "wof:placetype":"locality"
},
  "geometry": {"coordinates":[124.19701999999999,48.7257],"type":"Point"}
}