{
  "type": "Feature",
  "properties": {
    "gn:admin1_code":"5.0",
    "gn:asciiname":"Liudifangtun",
    "gn:country_code":"CN",
    "gn:dem":246,
    "gn:feature_class":"P",
    "gn:feature_code":"PPL",
    "gn:name":"Liudifangtun",
    "gn:population":0,
    "gn:timezone":"Asia/Shanghai",
    "iso:country":"CN",
    "name:zho_x_preferred":[
        "\u5218\u5730\u65b9\u5c6f"
    ],
    "wof:name":"Liudifangtun",
    "wof:placetype":"locality"
},
  "geometry": {"coordinates":[125.28868,43.43782],"type":"Point"}
}