{
  "type": "Feature",
  "properties": {
    "gn:admin1_code":"18.0",
    "gn:asciiname":"Dangjiao",
    "gn:country_code":"CN",
    "gn:dem":603,
    "gn:feature_class":"P",
    "gn:feature_code":"PPL",
    "gn:name":"Dangjiao",
    "gn:population":0,
    "gn:timezone":"Asia/Shanghai",
    "iso:country":"CN",
    "name:zho_x_preferred":[
        "\u515a\u811a"
    ],
    "wof:name":"Dangjiao",
    "wof:placetype":"locality"
},
  "geometry": {"coordinates":[108.35899999999999,25.9472],"type":"Point"}
}