{
  "type": "Feature",
  "properties": {
    "gn:admin1_code":"12.0",
    "gn:asciiname":"Beigoukou",
    "gn:country_code":"CN",
    "gn:dem":563,
    "gn:feature_class":"P",
    "gn:feature_code":"PPL",
    "gn:name":"Beigoukou",
    "gn:population":0,
    "gn:timezone":"Asia/Shanghai",
    "iso:country":"CN",
    "name:zho_x_preferred":[
        "\u5317\u6c9f\u53e3"
    ],
    "wof:name":"Beigoukou",
    "wof:placetype":"locality"
},
  "geometry": {"coordinates":[110.93049999999999,31.95361],"type":"Point"}
}