{
  "type": "Feature",
  "properties": {
    "gn:admin1_code":"25",
    "gn:asciiname":"Jiajiazhuang",
    "gn:country_code":"CN",
    "gn:dem":118,
    "gn:feature_class":"P",
    "gn:feature_code":"PPL",
    "gn:name":"Jiajiazhuang",
    "gn:population":0,
    "gn:timezone":"Asia/Shanghai",
    "iso:country":"CN",
    "name:zho_x_preferred":[
        "\u8d3e\u5bb6\u5e84"
    ],
    "wof:name":"Jiajiazhuang",
    "wof:placetype":"locality"
},
  "geometry": {"coordinates":[118.55500000000001,35.6383],"type":"Point"}
}