{
  "type": "Feature",
  "properties": {
    "gn:admin1_code":"26.0",
    "gn:asciiname":"Longbeiqu",
    "gn:country_code":"CN",
    "gn:dem":1721,
    "gn:feature_class":"P",
    "gn:feature_code":"PPL",
    "gn:name":"Longbeiqu",
    "gn:population":0,
    "gn:timezone":"Asia/Shanghai",
    "iso:country":"CN",
    "name:zho_x_preferred":[
        "\u9f99\u80cc\u6e20"
    ],
    "wof:name":"Longbeiqu",
    "wof:placetype":"locality"
},
  "geometry": {"coordinates":[107.88513,37.38143],"type":"Point"}
}