{
  "type": "Feature",
  "properties": {
    "gn:admin1_code":"3.0",
    "gn:asciiname":"Hongqun",
    "gn:country_code":"CN",
    "gn:dem":324,
    "gn:feature_class":"P",
    "gn:feature_code":"PPL",
    "gn:name":"Hongqun",
    "gn:population":0,
    "gn:timezone":"Asia/Shanghai",
    "iso:country":"CN",
    "name:und_x_variant":[
        "\u7ea2\u7fa4"
    ],
    "wof:name":"Hongqun",
    "wof:placetype":"locality"
},
  "geometry": {"coordinates":[114.66482999999999,28.67771],"type":"Point"}
}