{
  "type": "Feature",
  "properties": {
    "gn:admin1_code":"1.0",
    "gn:asciiname":"Damengzhuangcun",
    "gn:country_code":"CN",
    "gn:dem":50,
    "gn:feature_class":"P",
    "gn:feature_code":"PPL",
    "gn:name":"Damengzhuangcun",
    "gn:population":0,
    "gn:timezone":"Asia/Shanghai",
    "iso:country":"CN",
    "name:zho_x_preferred":[
        "\u5927\u5b5f\u5e84\u6751"
    ],
    "wof:name":"Damengzhuangcun",
    "wof:placetype":"locality"
},
  "geometry": {"coordinates":[116.45694,34.53955999999999],"type":"Point"}
}