{
  "type": "Feature",
  "properties": {
    "gn:admin1_code":"29.0",
    "gn:asciiname":"Nada",
    "gn:country_code":"CN",
    "gn:dem":1518,
    "gn:feature_class":"P",
    "gn:feature_code":"PPL",
    "gn:name":"Nada",
    "gn:population":0,
    "gn:timezone":"Asia/Shanghai",
    "iso:country":"CN",
    "name:ceb_x_preferred":[
        "Nada"
    ],
    "name:deu_x_preferred":[
        "Nada"
    ],
    "name:est_x_preferred":[
        "Nada"
    ],
    "name:fra_x_preferred":[
        "Nada"
    ],
    "name:hrv_x_preferred":[
        "Nada"
    ],
    "name:ita_x_preferred":[
        "Nada"
    ],
    "name:msa_x_preferred":[
        "Nada"
    ],
    "name:new_x_preferred":[
        "\u0928\u093e\u0921\u093e"
    ],
    "name:por_x_preferred":[
        "Nada"
    ],
    "name:rus_x_preferred":[
        "\u041d\u0430\u0434\u0430"
    ],
    "name:spa_x_preferred":[
        "Nada"
    ],
    "name:ukr_x_preferred":[
        "\u041d\u0430\u0434\u0430"
    ],
    "name:zho_x_preferred":[
        "\u90a3\u6253"
    ],
    "wof:name":"Nada",
    "wof:placetype":"locality"
},
  "geometry": {"coordinates":[101.027,24.0582],"type":"Point"}
}