{
  "type": "Feature",
  "properties": {
    "gn:admin1_code":"26.0",
    "gn:asciiname":"Xiangchacun",
    "gn:country_code":"CN",
    "gn:dem":792,
    "gn:feature_class":"P",
    "gn:feature_code":"PPL",
    "gn:name":"Xiangchacun",
    "gn:population":0,
    "gn:timezone":"Asia/Shanghai",
    "iso:country":"CN",
    "name:zho_x_preferred":[
        "\u9999\u8336\u6751"
    ],
    "wof:name":"Xiangchacun",
    "wof:placetype":"locality"
},
  "geometry": {"coordinates":[108.18803,32.72626],"type":"Point"}
}