{
  "type": "Feature",
  "properties": {
    "gn:admin1_code":"5.0",
    "gn:asciiname":"Bashisanliudui Wobu",
    "gn:country_code":"CN",
    "gn:dem":146,
    "gn:feature_class":"P",
    "gn:feature_code":"PPLF",
    "gn:name":"Bashisanliudui Wobu",
    "gn:population":0,
    "gn:timezone":"Asia/Shanghai",
    "iso:country":"CN",
    "name:zho_x_preferred":[
        "\u516b\u5341\u4e09\u516d\u961f\u7a9d\u5821"
    ],
    "wof:name":"Bashisanliudui Wobu",
    "wof:placetype":"locality"
},
  "geometry": {"coordinates":[123.55506,44.39426],"type":"Point"}
}