{
  "type": "Feature",
  "properties": {
    "gn:admin1_code":"25",
    "gn:asciiname":"Cuzhuangqian",
    "gn:country_code":"CN",
    "gn:dem":58,
    "gn:feature_class":"P",
    "gn:feature_code":"PPL",
    "gn:name":"Cuzhuangqian",
    "gn:population":0,
    "gn:timezone":"Asia/Shanghai",
    "iso:country":"CN",
    "name:zho_x_preferred":[
        "\u918b\u5e84\u524d"
    ],
    "wof:name":"Cuzhuangqian",
    "wof:placetype":"locality"
},
  "geometry": {"coordinates":[118.51900000000001,34.8962],"type":"Point"}
}