{
  "type": "Feature",
  "properties": {
    "gn:admin1_code":"24",
    "gn:asciiname":"Madihui",
    "gn:cc2":"CN",
    "gn:country_code":"CN",
    "gn:dem":1216,
    "gn:feature_class":"P",
    "gn:feature_code":"PPL",
    "gn:name":"Madihui",
    "gn:population":0,
    "gn:timezone":"Asia/Shanghai",
    "iso:country":"CN",
    "name:und_x_variant":[
        "Ma-ti-hui",
        "Madihui"
    ],
    "wof:name":"Madihui",
    "wof:placetype":"locality"
},
  "geometry": {"coordinates":[111.26278000000001,37.93722],"type":"Point"}
}