{
  "type": "Feature",
  "properties": {
    "gn:admin1_code":"9.0",
    "gn:asciiname":"Diaolou",
    "gn:country_code":"CN",
    "gn:dem":40,
    "gn:feature_class":"P",
    "gn:feature_code":"PPL",
    "gn:name":"Diaolou",
    "gn:population":0,
    "gn:timezone":"Asia/Shanghai",
    "iso:country":"CN",
    "name:ast_x_preferred":[
        "Diaolou"
    ],
    "name:cat_x_preferred":[
        "Diaolou"
    ],
    "name:ces_x_preferred":[
        "Tiao-lou"
    ],
    "name:deu_x_preferred":[
        "Diaolou"
    ],
    "name:fin_x_preferred":[
        "Kaipingin diaolout"
    ],
    "name:fra_x_preferred":[
        "Diaolou"
    ],
    "name:ita_x_preferred":[
        "Diaolou"
    ],
    "name:jpn_x_preferred":[
        "\u958b\u5e73\u697c\u95a3\u3068\u6751\u843d"
    ],
    "name:kat_x_preferred":[
        "\u10d3\u10d8\u10d0\u10dd\u10da\u10dd\u10e3"
    ],
    "name:mal_x_preferred":[
        "\u0d15\u0d48\u0d2a\u0d3f\u0d19\u0d4d \u0d21\u0d3f\u0d2f\u0d3e\u0d35\u0d4d\u0d32\u0d41"
    ],
    "name:nld_x_preferred":[
        "Diaolou"
    ],
    "name:nor_x_preferred":[
        "Diaolou"
    ],
    "name:pol_x_preferred":[
        "Diaolou"
    ],
    "name:rus_x_preferred":[
        "\u0414\u044f\u043e\u043b\u043e\u0443"
    ],
    "name:slk_x_preferred":[
        "Tiao-lou"
    ],
    "name:spa_x_preferred":[
        "Diaolou"
    ],
    "name:swe_x_preferred":[
        "Diaolou"
    ],
    "name:tha_x_preferred":[
        "\u0e2b\u0e2d\u0e15\u0e23\u0e27\u0e08\u0e01\u0e32\u0e23\u0e13\u0e4c\u0e41\u0e25\u0e30\u0e2b\u0e21\u0e39\u0e48\u0e1a\u0e49\u0e32\u0e19\u0e41\u0e2b\u0e48\u0e07\u0e44\u0e04\u0e1c\u0e34\u0e07"
    ],
    "name:tur_x_preferred":[
        "Diaolou"
    ],
    "name:ukr_x_preferred":[
        "\u0414\u044f\u043e\u043b\u043e\u0443"
    ],
    "name:zho_x_preferred":[
        "\u5201\u697c"
    ],
    "name:zho_x_variant":[
        "\u5f00\u5e73\u7889\u697c"
    ],
    "wof:name":"Diaolou",
    "wof:placetype":"locality"
},
  "geometry": {"coordinates":[115.60330999999999,33.62649],"type":"Point"}
}