{
  "type": "Feature",
  "properties": {
    "gn:admin1_code":"30",
    "gn:asciiname":"Haizhou",
    "gn:cc2":"CN",
    "gn:country_code":"CN",
    "gn:dem":1,
    "gn:feature_class":"P",
    "gn:feature_code":"PPL",
    "gn:name":"Haizhou",
    "gn:population":0,
    "gn:timezone":"Asia/Shanghai",
    "iso:country":"CN",
    "name:ceb_x_preferred":[
        "Haizhou"
    ],
    "name:deu_x_preferred":[
        "Haizhou"
    ],
    "name:fra_x_preferred":[
        "Haizhou"
    ],
    "name:kor_x_preferred":[
        "\ud558\uc774\uc800\uc6b0\uad6c"
    ],
    "name:mlg_x_preferred":[
        "Haizhou"
    ],
    "name:nor_x_preferred":[
        "Haizhou"
    ],
    "name:rus_x_preferred":[
        "\u0425\u0430\u0439\u0447\u0436\u043e\u0443"
    ],
    "name:swe_x_preferred":[
        "Haizhou"
    ],
    "name:und_x_variant":[
        "Hoichau",
        "Hai-chou",
        "Hoichou",
        "\u6d77\u6d32"
    ],
    "name:vie_x_preferred":[
        "H\u1ea3i Ch\u00e2u"
    ],
    "wof:name":"Haizhou",
    "wof:placetype":"locality"
},
  "geometry": {"coordinates":[113.1725,22.66778],"type":"Point"}
}