{
  "type": "Feature",
  "properties": {
    "gn:admin1_code":"30.0",
    "gn:asciiname":"Lianfenggusha",
    "gn:country_code":"CN",
    "gn:dem":948,
    "gn:feature_class":"P",
    "gn:feature_code":"PPL",
    "gn:name":"Lianfenggusha",
    "gn:population":0,
    "gn:timezone":"Asia/Shanghai",
    "iso:country":"CN",
    "name:zho_x_preferred":[
        "\u83b2\u5cf0\u53e4\u6740"
    ],
    "wof:name":"Lianfenggusha",
    "wof:placetype":"locality"
},
  "geometry": {"coordinates":[115.23482,23.06776],"type":"Point"}
}