{
  "type": "Feature",
  "properties": {
    "gn:admin1_code":"1.0",
    "gn:asciiname":"Liangtingcun",
    "gn:country_code":"CN",
    "gn:dem":22,
    "gn:feature_class":"P",
    "gn:feature_code":"PPL",
    "gn:name":"Liangtingcun",
    "gn:population":0,
    "gn:timezone":"Asia/Shanghai",
    "iso:country":"CN",
    "name:zho_x_preferred":[
        "\u51c9\u4ead\u6751"
    ],
    "wof:name":"Liangtingcun",
    "wof:placetype":"locality"
},
  "geometry": {"coordinates":[116.2041,32.46112],"type":"Point"}
}