{
  "type": "Feature",
  "properties": {
    "gn:admin1_code":"7",
    "gn:asciiname":"Gunongcun",
    "gn:country_code":"CN",
    "gn:dem":20,
    "gn:feature_class":"P",
    "gn:feature_code":"PPLF",
    "gn:name":"Gunongcun",
    "gn:population":0,
    "gn:timezone":"Asia/Shanghai",
    "iso:country":"CN",
    "name:zho_x_preferred":[
        "\u53e4\u519c\u6751"
    ],
    "wof:name":"Gunongcun",
    "wof:placetype":"locality"
},
  "geometry": {"coordinates":[117.77246,24.6898],"type":"Point"}
}