{
  "type": "Feature",
  "properties": {
    "gn:admin1_code":"7.0",
    "gn:asciiname":"Xiadangwei",
    "gn:country_code":"CN",
    "gn:dem":33,
    "gn:feature_class":"P",
    "gn:feature_code":"PPL",
    "gn:name":"Xiadangwei",
    "gn:population":0,
    "gn:timezone":"Asia/Shanghai",
    "iso:country":"CN",
    "name:zho_x_preferred":[
        "\u867e\u8361\u5c3e"
    ],
    "wof:name":"Xiadangwei",
    "wof:placetype":"locality"
},
  "geometry": {"coordinates":[119.80561000000002,26.61554000000001],"type":"Point"}
}