{
  "type": "Feature",
  "properties": {
    "gn:admin1_code":"02",
    "gn:asciiname":"Wangjiayangcun",
    "gn:country_code":"CN",
    "gn:dem":338,
    "gn:feature_class":"P",
    "gn:feature_code":"PPL",
    "gn:name":"Wangjiayangcun",
    "gn:population":0,
    "gn:timezone":"Asia/Shanghai",
    "iso:country":"CN",
    "name:und_x_variant":[
        "Wangjiayang",
        "Wangjiayangcun"
    ],
    "name:zho_x_preferred":[
        "\u738b\u5bb6\u579f"
    ],
    "name:zho_x_variant":[
        "\u738b\u5bb6\u579f\u6751"
    ],
    "wof:name":"Wangjiayangcun",
    "wof:placetype":"locality"
},
  "geometry": {"coordinates":[120.4177,27.39173],"type":"Point"}
}