{
  "type": "Feature",
  "properties": {
    "gn:admin1_code":"18",
    "gn:asciiname":"Sami",
    "gn:country_code":"CN",
    "gn:dem":1270,
    "gn:feature_class":"P",
    "gn:feature_code":"PPL",
    "gn:name":"Sami",
    "gn:population":0,
    "gn:timezone":"Asia/Shanghai",
    "iso:country":"CN",
    "name:zho_x_preferred":[
        "\u6492\u7c73"
    ],
    "wof:name":"Sami",
    "wof:placetype":"locality"
},
  "geometry": {"coordinates":[106.65300000000001,25.9095],"type":"Point"}
}