{
  "type": "Feature",
  "properties": {
    "gn:admin1_code":"11.0",
    "gn:asciiname":"Leijiashan",
    "gn:country_code":"CN",
    "gn:dem":591,
    "gn:feature_class":"P",
    "gn:feature_code":"PPL",
    "gn:name":"Leijiashan",
    "gn:population":0,
    "gn:timezone":"Asia/Shanghai",
    "iso:country":"CN",
    "name:zho_x_preferred":[
        "Leijiashan"
    ],
    "name:zho_x_variant":[
        "\u96f7\u5bb6\u5c71"
    ],
    "wof:name":"Leijiashan",
    "wof:placetype":"locality"
},
  "geometry": {"coordinates":[110.60684999999999,28.97593],"type":"Point"}
}