{
  "type": "Feature",
  "properties": {
    "gn:admin1_code":"8.0",
    "gn:asciiname":"Xingguocun",
    "gn:country_code":"CN",
    "gn:dem":264,
    "gn:feature_class":"P",
    "gn:feature_code":"PPL",
    "gn:name":"Xingguocun",
    "gn:population":0,
    "gn:timezone":"Asia/Shanghai",
    "iso:country":"CN",
    "name:zho_x_preferred":[
        "\u5174\u56fd\u6751"
    ],
    "wof:name":"Xingguocun",
    "wof:placetype":"locality"
},
  "geometry": {"coordinates":[126.19551,47.55365],"type":"Point"}
}