{
  "type": "Feature",
  "properties": {
    "gn:admin1_code":"12.0",
    "gn:asciiname":"Da'anzi",
    "gn:country_code":"CN",
    "gn:dem":749,
    "gn:feature_class":"P",
    "gn:feature_code":"PPL",
    "gn:name":"Da\u2019anzi",
    "gn:population":0,
    "gn:timezone":"Asia/Shanghai",
    "iso:country":"CN",
    "name:und_x_variant":[
        "Da\u2019anzi"
    ],
    "name:zho_x_preferred":[
        "\u5927\u978d\u5b50"
    ],
    "wof:name":"Da'anzi",
    "wof:placetype":"locality"
},
  "geometry": {"coordinates":[110.58801,33.01477],"type":"Point"}
}