{
  "type": "Feature",
  "properties": {
    "gn:admin1_code":"4.0",
    "gn:asciiname":"Guanwang",
    "gn:country_code":"CN",
    "gn:dem":32,
    "gn:feature_class":"P",
    "gn:feature_code":"PPL",
    "gn:name":"Guanwang",
    "gn:population":0,
    "gn:timezone":"Asia/Shanghai",
    "iso:country":"CN",
    "name:zho_x_preferred":[
        "\u5b98\u738b"
    ],
    "wof:name":"Guanwang",
    "wof:placetype":"locality"
},
  "geometry": {"coordinates":[118.47561,34.27415999999999],"type":"Point"}
}