{
  "type": "Feature",
  "properties": {
    "gn:admin1_code":"14.0",
    "gn:asciiname":"Zangdo",
    "gn:country_code":"CN",
    "gn:dem":4722,
    "gn:feature_class":"P",
    "gn:feature_code":"PPL",
    "gn:name":"Zangdo",
    "gn:population":0,
    "gn:timezone":"Asia/Urumqi",
    "iso:country":"CN",
    "name:bod_x_preferred":[
        "Zangdo"
    ],
    "name:zho_x_preferred":[
        "Zangduo"
    ],
    "name:zho_x_variant":[
        "\u85cf\u591a"
    ],
    "wof:name":"Zangdo",
    "wof:placetype":"locality"
},
  "geometry": {"coordinates":[93.303,30.603],"type":"Point"}
}