{
  "type": "Feature",
  "properties": {
    "gn:admin1_code":"11.0",
    "gn:asciiname":"Bashixi",
    "gn:country_code":"CN",
    "gn:dem":202,
    "gn:feature_class":"P",
    "gn:feature_code":"PPL",
    "gn:name":"Bashixi",
    "gn:population":0,
    "gn:timezone":"Asia/Shanghai",
    "iso:country":"CN",
    "name:zho_x_preferred":[
        "\u516b\u4ed5\u6eaa"
    ],
    "wof:name":"Bashixi",
    "wof:placetype":"locality"
},
  "geometry": {"coordinates":[110.61125,28.54491],"type":"Point"}
}