{
  "type": "Feature",
  "properties": {
    "gn:admin1_code":"25.0",
    "gn:asciiname":"Zhaojiapanwangcun",
    "gn:country_code":"CN",
    "gn:dem":79,
    "gn:feature_class":"P",
    "gn:feature_code":"PPL",
    "gn:name":"Zhaojiapanwangcun",
    "gn:population":0,
    "gn:timezone":"Asia/Shanghai",
    "iso:country":"CN",
    "name:zho_x_preferred":[
        "\u8d75\u5bb6\u6f58\u65fa\u6751"
    ],
    "wof:name":"Zhaojiapanwangcun",
    "wof:placetype":"locality"
},
  "geometry": {"coordinates":[119.48502000000001,36.0134],"type":"Point"}
}