{
  "type": "Feature",
  "properties": {
    "gn:admin1_code":"12.0",
    "gn:asciiname":"Yangsimiao",
    "gn:country_code":"CN",
    "gn:dem":779,
    "gn:feature_class":"P",
    "gn:feature_code":"PPL",
    "gn:name":"Yangsimiao",
    "gn:population":0,
    "gn:timezone":"Asia/Shanghai",
    "iso:country":"CN",
    "name:zho_x_preferred":[
        "\u6768\u6cd7\u5e99"
    ],
    "wof:name":"Yangsimiao",
    "wof:placetype":"locality"
},
  "geometry": {"coordinates":[109.57459,30.59923],"type":"Point"}
}