{
  "type": "Feature",
  "properties": {
    "gn:admin1_code":"12.0",
    "gn:asciiname":"Jubaoyuan",
    "gn:country_code":"CN",
    "gn:dem":37,
    "gn:feature_class":"P",
    "gn:feature_code":"PPL",
    "gn:name":"Jubaoyuan",
    "gn:population":0,
    "gn:timezone":"Asia/Shanghai",
    "iso:country":"CN",
    "name:zho_x_preferred":[
        "Jubaoyuan"
    ],
    "name:zho_x_variant":[
        "\u805a\u5b9d\u57b8"
    ],
    "wof:name":"Jubaoyuan",
    "wof:placetype":"locality"
},
  "geometry": {"coordinates":[111.85069,30.1575],"type":"Point"}
}