{
  "type": "Feature",
  "properties": {
    "gn:admin1_code":"15.0",
    "gn:asciiname":"Yijiashan",
    "gn:country_code":"CN",
    "gn:dem":1197,
    "gn:feature_class":"P",
    "gn:feature_code":"PPL",
    "gn:name":"Yijiashan",
    "gn:population":0,
    "gn:timezone":"Asia/Shanghai",
    "iso:country":"CN",
    "name:zho_x_preferred":[
        "\u4f0a\u5bb6\u5c71"
    ],
    "wof:name":"Yijiashan",
    "wof:placetype":"locality"
},
  "geometry": {"coordinates":[107.45,35.1058],"type":"Point"}
}