{
  "type": "Feature",
  "properties": {
    "gn:admin1_code":"32.0",
    "gn:asciiname":"Rejigou Guoying Muchang",
    "gn:country_code":"CN",
    "gn:dem":3837,
    "gn:feature_class":"P",
    "gn:feature_code":"PPLF",
    "gn:name":"Rejigou Guoying Muchang",
    "gn:population":0,
    "gn:timezone":"Asia/Shanghai",
    "iso:country":"CN",
    "name:zho_x_preferred":[
        "\u70ed\u57fa\u6c9f\u56fd\u8425\u7267\u573a"
    ],
    "wof:name":"Rejigou Guoying Muchang",
    "wof:placetype":"locality"
},
  "geometry": {"coordinates":[100.70081,32.31618],"type":"Point"}
}