{
  "type": "Feature",
  "properties": {
    "gn:admin1_code":"29.0",
    "gn:asciiname":"Shenjiazhai",
    "gn:country_code":"CN",
    "gn:dem":1393,
    "gn:feature_class":"P",
    "gn:feature_code":"PPL",
    "gn:name":"Shenjiazhai",
    "gn:population":0,
    "gn:timezone":"Asia/Shanghai",
    "iso:country":"CN",
    "name:zho_x_preferred":[
        "\u6c88\u5bb6\u5be8"
    ],
    "wof:name":"Shenjiazhai",
    "wof:placetype":"locality"
},
  "geometry": {"coordinates":[100.33,23.7437],"type":"Point"}
}