{
  "type": "Feature",
  "properties": {
    "gn:admin1_code":"16.0",
    "gn:asciiname":"Miaoshandui",
    "gn:country_code":"CN",
    "gn:dem":14,
    "gn:feature_class":"P",
    "gn:feature_code":"PPL",
    "gn:name":"Miaoshandui",
    "gn:population":0,
    "gn:timezone":"Asia/Shanghai",
    "iso:country":"CN",
    "name:zho_x_preferred":[
        "\u5e99\u5c71\u961f"
    ],
    "wof:name":"Miaoshandui",
    "wof:placetype":"locality"
},
  "geometry": {"coordinates":[109.262,21.5257],"type":"Point"}
}