{
  "type": "Feature",
  "properties": {
    "gn:admin1_code":"32.0",
    "gn:asciiname":"Dingdianshan",
    "gn:country_code":"CN",
    "gn:dem":371,
    "gn:feature_class":"P",
    "gn:feature_code":"PPL",
    "gn:name":"Dingdianshan",
    "gn:population":0,
    "gn:timezone":"Asia/Shanghai",
    "iso:country":"CN",
    "name:zho_x_preferred":[
        "\u9876\u5178\u5c71"
    ],
    "wof:name":"Dingdianshan",
    "wof:placetype":"locality"
},
  "geometry": {"coordinates":[104.48735000000001,29.41703],"type":"Point"}
}