{
  "type": "Feature",
  "properties": {
    "gn:admin1_code":"19.0",
    "gn:asciiname":"Dawolonggang",
    "gn:country_code":"CN",
    "gn:dem":142,
    "gn:feature_class":"P",
    "gn:feature_code":"PPL",
    "gn:name":"Dawolonggang",
    "gn:population":0,
    "gn:timezone":"Asia/Shanghai",
    "iso:country":"CN",
    "name:und_x_variant":[
        "\u5927\u5367\u9f99\u5c97"
    ],
    "name:zho_x_preferred":[
        "\u5927\u5367\u9f99\u5c97"
    ],
    "wof:name":"Dawolonggang",
    "wof:placetype":"locality"
},
  "geometry": {"coordinates":[122.05731000000002,42.42464],"type":"Point"}
}