{
  "type": "Feature",
  "properties": {
    "gn:admin1_code":"19.0",
    "gn:asciiname":"Dongzhuangtun",
    "gn:country_code":"CN",
    "gn:dem":27,
    "gn:feature_class":"P",
    "gn:feature_code":"PPL",
    "gn:name":"Dongzhuangtun",
    "gn:population":0,
    "gn:timezone":"Asia/Shanghai",
    "iso:country":"CN",
    "name:zho_x_preferred":[
        "\u4e1c\u5e84\u5c6f"
    ],
    "wof:name":"Dongzhuangtun",
    "wof:placetype":"locality"
},
  "geometry": {"coordinates":[121.88257,41.58372],"type":"Point"}
}