{
  "type": "Feature",
  "properties": {
    "gn:admin1_code":"25",
    "gn:asciiname":"Xixiaoshui",
    "gn:cc2":"CN",
    "gn:country_code":"CN",
    "gn:dem":34,
    "gn:feature_class":"P",
    "gn:feature_code":"PPL",
    "gn:name":"Xixiaoshui",
    "gn:population":0,
    "gn:timezone":"Asia/Shanghai",
    "iso:country":"CN",
    "name:und_x_variant":[
        "Hsi-hsiao-shui",
        "Xixiaoshui"
    ],
    "name:zho_x_preferred":[
        "\u897f\u5c0f\u6c34"
    ],
    "wof:name":"Xixiaoshui",
    "wof:placetype":"locality"
},
  "geometry": {"coordinates":[120.42139,36.2375],"type":"Point"}
}