{
  "type": "Feature",
  "properties": {
    "gn:admin1_code":"25",
    "gn:asciiname":"Xinmazhuang",
    "gn:country_code":"CN",
    "gn:dem":45,
    "gn:feature_class":"P",
    "gn:feature_code":"PPL",
    "gn:name":"Xinmazhuang",
    "gn:population":0,
    "gn:timezone":"Asia/Shanghai",
    "iso:country":"CN",
    "name:zho_x_preferred":[
        "\u65b0\u9a6c\u5e84"
    ],
    "wof:name":"Xinmazhuang",
    "wof:placetype":"locality"
},
  "geometry": {"coordinates":[117.896,34.8208],"type":"Point"}
}