{
  "type": "Feature",
  "properties": {
    "gn:admin1_code":"21.0",
    "gn:asciiname":"Wugeyao",
    "gn:country_code":"CN",
    "gn:dem":1252,
    "gn:feature_class":"P",
    "gn:feature_code":"PPL",
    "gn:name":"Wugeyao",
    "gn:population":0,
    "gn:timezone":"Asia/Shanghai",
    "iso:country":"CN",
    "name:zho_x_preferred":[
        "\u4e94\u4e2a\u7a91"
    ],
    "wof:name":"Wugeyao",
    "wof:placetype":"locality"
},
  "geometry": {"coordinates":[105.56699999999999,37.4204],"type":"Point"}
}