{
  "type": "Feature",
  "properties": {
    "gn:admin1_code":"24.0",
    "gn:asciiname":"Yongningcun",
    "gn:country_code":"CN",
    "gn:dem":406,
    "gn:feature_class":"P",
    "gn:feature_code":"PPL",
    "gn:name":"Yongningcun",
    "gn:population":0,
    "gn:timezone":"Asia/Shanghai",
    "iso:country":"CN",
    "name:zho_x_preferred":[
        "\u6c38\u5b81\u6751"
    ],
    "wof:name":"Yongningcun",
    "wof:placetype":"locality"
},
  "geometry": {"coordinates":[110.91871,35.59825],"type":"Point"}
}