{
  "type": "Feature",
  "properties": {
    "gn:admin1_code":"02",
    "gn:asciiname":"Changmeishan",
    "gn:country_code":"CN",
    "gn:dem":231,
    "gn:feature_class":"P",
    "gn:feature_code":"PPL",
    "gn:name":"Changmeishan",
    "gn:population":0,
    "gn:timezone":"Asia/Shanghai",
    "iso:country":"CN",
    "name:zho_x_preferred":[
        "\u573a\u6885\u5c71"
    ],
    "wof:name":"Changmeishan",
    "wof:placetype":"locality"
},
  "geometry": {"coordinates":[120.31492,27.70128],"type":"Point"}
}