{
  "type": "Feature",
  "properties": {
    "gn:admin1_code":"31.0",
    "gn:asciiname":"Zhichao",
    "gn:country_code":"CN",
    "gn:dem":185,
    "gn:feature_class":"P",
    "gn:feature_code":"PPL",
    "gn:name":"Zhichao",
    "gn:population":0,
    "gn:timezone":"Asia/Shanghai",
    "iso:country":"CN",
    "name:und_x_variant":[
        "\u53ea\u671d"
    ],
    "wof:name":"Zhichao",
    "wof:placetype":"locality"
},
  "geometry": {"coordinates":[109.25821000000001,18.71705],"type":"Point"}
}