{
  "type": "Feature",
  "properties": {
    "gn:admin1_code":"26.0",
    "gn:asciiname":"Qiaoquanliangcun",
    "gn:country_code":"CN",
    "gn:dem":1384,
    "gn:feature_class":"P",
    "gn:feature_code":"PPL",
    "gn:name":"Qiaoquanliangcun",
    "gn:population":0,
    "gn:timezone":"Asia/Shanghai",
    "iso:country":"CN",
    "name:zho_x_preferred":[
        "\u4e54\u5708\u6881\u6751"
    ],
    "wof:name":"Qiaoquanliangcun",
    "wof:placetype":"locality"
},
  "geometry": {"coordinates":[108.13897,37.52205],"type":"Point"}
}