{
  "type": "Feature",
  "properties": {
    "gn:admin1_code":"13",
    "gn:asciiname":"Wulasi Taichagan",
    "gn:country_code":"CN",
    "gn:dem":2188,
    "gn:feature_class":"P",
    "gn:feature_code":"PPL",
    "gn:name":"Wulasi Taichagan",
    "gn:population":0,
    "gn:timezone":"Asia/Urumqi",
    "iso:country":"CN",
    "name:zho_x_preferred":[
        "\u4e4c\u62c9\u65af\u53f0\u67e5\u5e72"
    ],
    "wof:name":"Wulasi Taichagan",
    "wof:placetype":"locality"
},
  "geometry": {"coordinates":[87.23415,42.83243],"type":"Point"}
}