{
  "type": "Feature",
  "properties": {
    "gn:admin1_code":"16.0",
    "gn:asciiname":"Xi'an",
    "gn:country_code":"CN",
    "gn:dem":76,
    "gn:feature_class":"P",
    "gn:feature_code":"PPL",
    "gn:name":"Xi\u2019an",
    "gn:population":0,
    "gn:timezone":"Asia/Shanghai",
    "iso:country":"CN",
    "name:und_x_variant":[
        "Xi\u2019an"
    ],
    "name:zho_x_preferred":[
        "\u897f\u5cb8"
    ],
    "wof:name":"Xi'an",
    "wof:placetype":"locality"
},
  "geometry": {"coordinates":[110.155,23.1668],"type":"Point"}
}