{
  "type": "Feature",
  "properties": {
    "gn:admin1_code":"26.0",
    "gn:asciiname":"Beiliangcun",
    "gn:country_code":"CN",
    "gn:dem":1633,
    "gn:feature_class":"P",
    "gn:feature_code":"PPL",
    "gn:name":"Beiliangcun",
    "gn:population":0,
    "gn:timezone":"Asia/Shanghai",
    "iso:country":"CN",
    "name:zho_x_preferred":[
        "\u5317\u6881\u6751"
    ],
    "wof:name":"Beiliangcun",
    "wof:placetype":"locality"
},
  "geometry": {"coordinates":[107.84007,37.18788],"type":"Point"}
}