{
  "type": "Feature",
  "properties": {
    "gn:admin1_code":"26.0",
    "gn:asciiname":"Liutianjia",
    "gn:country_code":"CN",
    "gn:dem":1019,
    "gn:feature_class":"P",
    "gn:feature_code":"PPL",
    "gn:name":"Liutianjia",
    "gn:population":0,
    "gn:timezone":"Asia/Shanghai",
    "iso:country":"CN",
    "name:zho_x_preferred":[
        "\u5218\u7530\u5bb6"
    ],
    "wof:name":"Liutianjia",
    "wof:placetype":"locality"
},
  "geometry": {"coordinates":[108.32061000000002,35.01884],"type":"Point"}
}