{
  "type": "Feature",
  "properties": {
    "gn:admin1_code":"6.0",
    "gn:asciiname":"Bangzha",
    "gn:country_code":"CN",
    "gn:dem":3227,
    "gn:feature_class":"P",
    "gn:feature_code":"PPL",
    "gn:name":"Bangzha",
    "gn:population":0,
    "gn:timezone":"Asia/Shanghai",
    "iso:country":"CN",
    "name:zho_x_preferred":[
        "\u90a6\u624e"
    ],
    "wof:name":"Bangzha",
    "wof:placetype":"locality"
},
  "geometry": {"coordinates":[101.84260999999999,35.33337],"type":"Point"}
}