{
  "type": "Feature",
  "properties": {
    "gn:admin1_code":"18",
    "gn:asciiname":"Dahegou",
    "gn:country_code":"CN",
    "gn:dem":1183,
    "gn:feature_class":"P",
    "gn:feature_code":"PPL",
    "gn:name":"Dahegou",
    "gn:population":0,
    "gn:timezone":"Asia/Shanghai",
    "iso:country":"CN",
    "name:zho_x_preferred":[
        "\u5927\u6cb3\u6c9f"
    ],
    "wof:name":"Dahegou",
    "wof:placetype":"locality"
},
  "geometry": {"coordinates":[106.465,27.7912],"type":"Point"}
}