{
  "type": "Feature",
  "properties": {
    "gn:admin1_code":"11",
    "gn:asciiname":"Yangzaitou",
    "gn:country_code":"CN",
    "gn:dem":448,
    "gn:feature_class":"P",
    "gn:feature_code":"PPL",
    "gn:name":"Yangzaitou",
    "gn:population":0,
    "gn:timezone":"Asia/Shanghai",
    "iso:country":"CN",
    "name:und_x_variant":[
        "\u7f8a\u4ed4\u5934",
        "Yangzaitou"
    ],
    "wof:name":"Yangzaitou",
    "wof:placetype":"locality"
},
  "geometry": {"coordinates":[111.94167,25.82444],"type":"Point"}
}