{
  "type": "Feature",
  "properties": {
    "gn:admin1_code":"24.0",
    "gn:asciiname":"Houduanjiagou",
    "gn:country_code":"CN",
    "gn:dem":1436,
    "gn:feature_class":"P",
    "gn:feature_code":"PPL",
    "gn:name":"Houduanjiagou",
    "gn:population":0,
    "gn:timezone":"Asia/Shanghai",
    "iso:country":"CN",
    "name:zho_x_preferred":[
        "\u540e\u6bb5\u5bb6\u6c9f"
    ],
    "wof:name":"Houduanjiagou",
    "wof:placetype":"locality"
},
  "geometry": {"coordinates":[111.17659,36.2665],"type":"Point"}
}