{
  "type": "Feature",
  "properties": {
    "gn:admin1_code":"4.0",
    "gn:asciiname":"Yanghebian",
    "gn:country_code":"CN",
    "gn:dem":4,
    "gn:feature_class":"P",
    "gn:feature_code":"PPL",
    "gn:name":"Yanghebian",
    "gn:population":0,
    "gn:timezone":"Asia/Shanghai",
    "iso:country":"CN",
    "name:zho_x_preferred":[
        "Yanghebian"
    ],
    "name:zho_x_variant":[
        "\u6768\u6cb3\u8fb9"
    ],
    "wof:name":"Yanghebian",
    "wof:placetype":"locality"
},
  "geometry": {"coordinates":[119.43248,33.21849],"type":"Point"}
}