{
  "type": "Feature",
  "properties": {
    "gn:admin1_code":"4.0",
    "gn:asciiname":"Nanxiaodai",
    "gn:country_code":"CN",
    "gn:dem":5,
    "gn:feature_class":"P",
    "gn:feature_code":"PPL",
    "gn:name":"Nanxiaodai",
    "gn:population":0,
    "gn:timezone":"Asia/Shanghai",
    "iso:country":"CN",
    "name:zho_x_preferred":[
        "\u5357\u8096\u5788"
    ],
    "wof:name":"Nanxiaodai",
    "wof:placetype":"locality"
},
  "geometry": {"coordinates":[120.33969999999999,32.1578],"type":"Point"}
}