{
  "type": "Feature",
  "properties": {
    "gn:admin1_code":"30.0",
    "gn:asciiname":"Lutian",
    "gn:country_code":"CN",
    "gn:dem":73,
    "gn:feature_class":"P",
    "gn:feature_code":"PPL",
    "gn:name":"Lutian",
    "gn:population":0,
    "gn:timezone":"Asia/Shanghai",
    "iso:country":"CN",
    "name:zho_x_preferred":[
        "\u9e7f\u7530"
    ],
    "wof:name":"Lutian",
    "wof:placetype":"locality"
},
  "geometry": {"coordinates":[112.40286999999999,22.74647],"type":"Point"}
}