{
  "type": "Feature",
  "properties": {
    "gn:admin1_code":"25",
    "gn:asciiname":"Shangjiazhuang",
    "gn:country_code":"CN",
    "gn:dem":233,
    "gn:feature_class":"P",
    "gn:feature_code":"PPL",
    "gn:name":"Shangjiazhuang",
    "gn:population":0,
    "gn:timezone":"Asia/Shanghai",
    "iso:country":"CN",
    "name:zho_x_preferred":[
        "\u5c1a\u5bb6\u5e84"
    ],
    "wof:name":"Shangjiazhuang",
    "wof:placetype":"locality"
},
  "geometry": {"coordinates":[118.06100000000001,35.702],"type":"Point"}
}