{
  "type": "Feature",
  "properties": {
    "gn:admin1_code":"14.0",
    "gn:asciiname":"Lagba",
    "gn:country_code":"CN",
    "gn:dem":3410,
    "gn:feature_class":"P",
    "gn:feature_code":"PPL",
    "gn:name":"Lagba",
    "gn:population":0,
    "gn:timezone":"Asia/Urumqi",
    "iso:country":"CN",
    "name:bod_x_preferred":[
        "Lagba"
    ],
    "name:zho_x_preferred":[
        "Laba"
    ],
    "name:zho_x_variant":[
        "\u62c9\u5df4"
    ],
    "wof:name":"Lagba",
    "wof:placetype":"locality"
},
  "geometry": {"coordinates":[97.12045000000001,30.1905],"type":"Point"}
}