{
  "type": "Feature",
  "properties": {
    "gn:admin1_code":"2.0",
    "gn:asciiname":"Erjieling",
    "gn:country_code":"CN",
    "gn:dem":28,
    "gn:feature_class":"P",
    "gn:feature_code":"PPLA4",
    "gn:name":"Erjieling",
    "gn:population":0,
    "gn:timezone":"Asia/Shanghai",
    "iso:country":"CN",
    "name:und_x_variant":[
        "\u4e8c\u754c\u5cad",
        "Erjieling Xiang",
        "\u4e8c\u754c\u5cad\u4e61"
    ],
    "wof:name":"Erjieling",
    "wof:placetype":"locality"
},
  "geometry": {"coordinates":[119.61360999999999,30.94829],"type":"Point"}
}