{
  "type": "Feature",
  "properties": {
    "gn:admin1_code":"18",
    "gn:asciiname":"Nanmuyan",
    "gn:country_code":"CN",
    "gn:dem":1228,
    "gn:feature_class":"P",
    "gn:feature_code":"PPL",
    "gn:name":"Nanmuyan",
    "gn:population":0,
    "gn:timezone":"Asia/Shanghai",
    "iso:country":"CN",
    "name:zho_x_preferred":[
        "\u6960\u6728\u5ca9"
    ],
    "wof:name":"Nanmuyan",
    "wof:placetype":"locality"
},
  "geometry": {"coordinates":[106.33199999999999,28.3376],"type":"Point"}
}