{
  "type": "Feature",
  "properties": {
    "gn:admin1_code":"18",
    "gn:asciiname":"Jiangbiantou",
    "gn:country_code":"CN",
    "gn:dem":775,
    "gn:feature_class":"P",
    "gn:feature_code":"PPL",
    "gn:name":"Jiangbiantou",
    "gn:population":0,
    "gn:timezone":"Asia/Shanghai",
    "iso:country":"CN",
    "name:zho_x_preferred":[
        "\u6c5f\u8fb9\u5934"
    ],
    "wof:name":"Jiangbiantou",
    "wof:placetype":"locality"
},
  "geometry": {"coordinates":[108.146,28.7931],"type":"Point"}
}