{
  "type": "Feature",
  "properties": {
    "gn:admin1_code":"15.0",
    "gn:asciiname":"Huaqiang",
    "gn:country_code":"CN",
    "gn:dem":1419,
    "gn:feature_class":"P",
    "gn:feature_code":"PPL",
    "gn:name":"Huaqiang",
    "gn:population":0,
    "gn:timezone":"Asia/Shanghai",
    "iso:country":"CN",
    "name:zho_x_preferred":[
        "\u534e\u5f3a"
    ],
    "wof:name":"Huaqiang",
    "wof:placetype":"locality"
},
  "geometry": {"coordinates":[100.17400000000001,39.2208],"type":"Point"}
}