{
  "type": "Feature",
  "properties": {
    "gn:admin1_code":"26.0",
    "gn:asciiname":"Luojiaping",
    "gn:country_code":"CN",
    "gn:dem":1207,
    "gn:feature_class":"P",
    "gn:feature_code":"PPL",
    "gn:name":"Luojiaping",
    "gn:population":0,
    "gn:timezone":"Asia/Shanghai",
    "iso:country":"CN",
    "name:zho_x_preferred":[
        "\u7f57\u5bb6\u576a"
    ],
    "wof:name":"Luojiaping",
    "wof:placetype":"locality"
},
  "geometry": {"coordinates":[108.41216,32.87909000000001],"type":"Point"}
}