{
  "type": "Feature",
  "properties": {
    "gn:admin1_code":"18",
    "gn:asciiname":"Sangu Yuanzi",
    "gn:country_code":"CN",
    "gn:dem":2226,
    "gn:feature_class":"P",
    "gn:feature_code":"PPL",
    "gn:name":"Sangu Yuanzi",
    "gn:population":0,
    "gn:timezone":"Asia/Shanghai",
    "iso:country":"CN",
    "name:zho_x_preferred":[
        "\u4e09\u59d1\u9662\u5b50"
    ],
    "wof:name":"Sangu Yuanzi",
    "wof:placetype":"locality"
},
  "geometry": {"coordinates":[103.845,26.9868],"type":"Point"}
}