{
  "type": "Feature",
  "properties": {
    "gn:admin1_code":"19.0",
    "gn:asciiname":"Liuyu",
    "gn:country_code":"CN",
    "gn:dem":125,
    "gn:feature_class":"P",
    "gn:feature_code":"PPL",
    "gn:name":"Liuyu",
    "gn:population":0,
    "gn:timezone":"Asia/Shanghai",
    "iso:country":"CN",
    "name:und_x_variant":[
        "\u67f3\u5cea"
    ],
    "name:zho_x_preferred":[
        "\u67f3\u5cea"
    ],
    "wof:name":"Liuyu",
    "wof:placetype":"locality"
},
  "geometry": {"coordinates":[123.67457,41.47578],"type":"Point"}
}