{
  "type": "Feature",
  "properties": {
    "gn:admin1_code":"15.0",
    "gn:asciiname":"Xizhai",
    "gn:country_code":"CN",
    "gn:dem":2045,
    "gn:feature_class":"P",
    "gn:feature_code":"PPL",
    "gn:name":"Xizhai",
    "gn:population":0,
    "gn:timezone":"Asia/Shanghai",
    "iso:country":"CN",
    "name:zho_x_preferred":[
        "\u897f\u5be8"
    ],
    "wof:name":"Xizhai",
    "wof:placetype":"locality"
},
  "geometry": {"coordinates":[100.836,38.5558],"type":"Point"}
}