{
  "type": "Feature",
  "properties": {
    "gn:admin1_code":"16",
    "gn:asciiname":"Shishan'ai",
    "gn:country_code":"CN",
    "gn:dem":174,
    "gn:feature_class":"P",
    "gn:feature_code":"PPL",
    "gn:name":"Shishan\u2019ai",
    "gn:population":0,
    "gn:timezone":"Asia/Shanghai",
    "iso:country":"CN",
    "name:und_x_variant":[
        "Shishan\u2019ai"
    ],
    "name:zho_x_preferred":[
        "\u77f3\u5c71\u9698"
    ],
    "wof:name":"Shishan'ai",
    "wof:placetype":"locality"
},
  "geometry": {"coordinates":[110.34099999999999,24.8891],"type":"Point"}
}