{
  "type": "Feature",
  "properties": {
    "gn:admin1_code":"26.0",
    "gn:asciiname":"Taibaicun",
    "gn:country_code":"CN",
    "gn:dem":594,
    "gn:feature_class":"P",
    "gn:feature_code":"PPL",
    "gn:name":"Taibaicun",
    "gn:population":0,
    "gn:timezone":"Asia/Shanghai",
    "iso:country":"CN",
    "name:zho_x_preferred":[
        "\u592a\u767d\u6751"
    ],
    "wof:name":"Taibaicun",
    "wof:placetype":"locality"
},
  "geometry": {"coordinates":[109.1966,34.91504],"type":"Point"}
}