{
  "type": "Feature",
  "properties": {
    "gn:admin1_code":"3.0",
    "gn:asciiname":"Qiaoxia",
    "gn:country_code":"CN",
    "gn:dem":183,
    "gn:feature_class":"P",
    "gn:feature_code":"PPL",
    "gn:name":"Qiaoxia",
    "gn:population":0,
    "gn:timezone":"Asia/Shanghai",
    "iso:country":"CN",
    "name:und_x_variant":[
        "\u6865\u4e0b"
    ],
    "wof:name":"Qiaoxia",
    "wof:placetype":"locality"
},
  "geometry": {"coordinates":[115.03085,25.21149],"type":"Point"}
}