{
  "type": "Feature",
  "properties": {
    "gn:admin1_code":"11",
    "gn:asciiname":"Lanniwan",
    "gn:country_code":"CN",
    "gn:dem":565,
    "gn:feature_class":"P",
    "gn:feature_code":"PPL",
    "gn:name":"Lanniwan",
    "gn:population":0,
    "gn:timezone":"Asia/Shanghai",
    "iso:country":"CN",
    "name:zho_x_preferred":[
        "\u70c2\u6ce5\u6e7e"
    ],
    "wof:name":"Lanniwan",
    "wof:placetype":"locality"
},
  "geometry": {"coordinates":[110.78789999999999,27.64454000000001],"type":"Point"}
}