{
  "type": "Feature",
  "properties": {
    "gn:admin1_code":"30",
    "gn:asciiname":"Chenwu",
    "gn:country_code":"CN",
    "gn:dem":31,
    "gn:feature_class":"P",
    "gn:feature_code":"PPL",
    "gn:name":"Chenwu",
    "gn:population":0,
    "gn:timezone":"Asia/Urumqi",
    "iso:country":"CN",
    "name:zho_x_preferred":[
        "\u9648\u5c4b"
    ],
    "wof:name":"Chenwu",
    "wof:placetype":"locality"
},
  "geometry": {"coordinates":[110.74833,21.82334],"type":"Point"}
}