{
  "type": "Feature",
  "properties": {
    "gn:admin1_code":"32.0",
    "gn:asciiname":"Simadu",
    "gn:country_code":"CN",
    "gn:dem":2717,
    "gn:feature_class":"P",
    "gn:feature_code":"PPL",
    "gn:name":"Simadu",
    "gn:population":0,
    "gn:timezone":"Asia/Shanghai",
    "iso:country":"CN",
    "name:zho_x_preferred":[
        "\u65af\u739b\u90fd"
    ],
    "wof:name":"Simadu",
    "wof:placetype":"locality"
},
  "geometry": {"coordinates":[101.63800000000001,31.7876],"type":"Point"}
}