{
  "type": "Feature",
  "properties": {
    "gn:admin1_code":"30.0",
    "gn:asciiname":"Dengxinhu",
    "gn:country_code":"CN",
    "gn:dem":342,
    "gn:feature_class":"P",
    "gn:feature_code":"PPL",
    "gn:name":"Dengxinhu",
    "gn:population":0,
    "gn:timezone":"Asia/Shanghai",
    "iso:country":"CN",
    "name:zho_x_preferred":[
        "\u706f\u5fc3\u6e56"
    ],
    "wof:name":"Dengxinhu",
    "wof:placetype":"locality"
},
  "geometry": {"coordinates":[115.45406,23.98182000000001],"type":"Point"}
}