{
  "type": "Feature",
  "properties": {
    "gn:admin1_code":"9.0",
    "gn:asciiname":"Guofuzhuang",
    "gn:country_code":"CN",
    "gn:dem":146,
    "gn:feature_class":"P",
    "gn:feature_code":"PPL",
    "gn:name":"Guofuzhuang",
    "gn:population":0,
    "gn:timezone":"Asia/Shanghai",
    "iso:country":"CN",
    "name:zho_x_preferred":[
        "\u56fd\u5bcc\u5e84"
    ],
    "wof:name":"Guofuzhuang",
    "wof:placetype":"locality"
},
  "geometry": {"coordinates":[111.82989000000001,32.60709],"type":"Point"}
}