{
  "type": "Feature",
  "properties": {
    "gn:admin1_code":"30.0",
    "gn:asciiname":"Tangtianjiu",
    "gn:country_code":"CN",
    "gn:dem":29,
    "gn:feature_class":"P",
    "gn:feature_code":"PPL",
    "gn:name":"Tangtianjiu",
    "gn:population":0,
    "gn:timezone":"Asia/Shanghai",
    "iso:country":"CN",
    "name:zho_x_preferred":[
        "\u5858\u7530\u65e7"
    ],
    "wof:name":"Tangtianjiu",
    "wof:placetype":"locality"
},
  "geometry": {"coordinates":[112.94776,22.69454],"type":"Point"}
}