{
  "type": "Feature",
  "properties": {
    "gn:admin1_code":"16.0",
    "gn:asciiname":"Xuzhongcun",
    "gn:country_code":"CN",
    "gn:dem":93,
    "gn:feature_class":"P",
    "gn:feature_code":"PPL",
    "gn:name":"Xuzhongcun",
    "gn:population":0,
    "gn:timezone":"Asia/Shanghai",
    "iso:country":"CN",
    "name:zho_x_preferred":[
        "\u5729\u4e2d\u6751"
    ],
    "wof:name":"Xuzhongcun",
    "wof:placetype":"locality"
},
  "geometry": {"coordinates":[108.003,22.8853],"type":"Point"}
}