{
  "type": "Feature",
  "properties": {
    "gn:admin1_code":"26.0",
    "gn:asciiname":"Yangjiacun",
    "gn:country_code":"CN",
    "gn:dem":580,
    "gn:feature_class":"P",
    "gn:feature_code":"PPL",
    "gn:name":"Yangjiacun",
    "gn:population":0,
    "gn:timezone":"Asia/Shanghai",
    "iso:country":"CN",
    "name:zho_x_preferred":[
        "\u6768\u5bb6\u6751"
    ],
    "wof:name":"Yangjiacun",
    "wof:placetype":"locality"
},
  "geometry": {"coordinates":[109.25736999999999,34.36678],"type":"Point"}
}