{
  "type": "Feature",
  "properties": {
    "gn:admin1_code":"32.0",
    "gn:asciiname":"Duran",
    "gn:country_code":"CN",
    "gn:dem":3632,
    "gn:feature_class":"P",
    "gn:feature_code":"PPL",
    "gn:name":"Duran",
    "gn:population":0,
    "gn:timezone":"Asia/Shanghai",
    "iso:country":"CN",
    "name:cat_x_preferred":[
        "Duran"
    ],
    "name:ceb_x_preferred":[
        "Duran"
    ],
    "name:deu_x_preferred":[
        "Duran"
    ],
    "name:epo_x_preferred":[
        "Duran"
    ],
    "name:fra_x_preferred":[
        "Duran"
    ],
    "name:heb_x_preferred":[
        "\u05d3\u05d5\u05e8\u05d0\u05df"
    ],
    "name:ita_x_preferred":[
        "Duran"
    ],
    "name:pol_x_preferred":[
        "Duran"
    ],
    "name:por_x_preferred":[
        "Duran"
    ],
    "name:rus_x_preferred":[
        "\u0414\u0443\u0440\u0430\u043d"
    ],
    "name:swe_x_preferred":[
        "Duran"
    ],
    "name:tur_x_preferred":[
        "Duran"
    ],
    "name:zho_x_preferred":[
        "\u90fd\u7136"
    ],
    "wof:name":"Duran",
    "wof:placetype":"locality"
},
  "geometry": {"coordinates":[100.26600000000001,27.9868],"type":"Point"}
}