{
  "type": "Feature",
  "properties": {
    "gn:admin1_code":"19.0",
    "gn:asciiname":"Baixiangtuncun",
    "gn:country_code":"CN",
    "gn:dem":242,
    "gn:feature_class":"P",
    "gn:feature_code":"PPL",
    "gn:name":"Baixiangtuncun",
    "gn:population":0,
    "gn:timezone":"Asia/Shanghai",
    "iso:country":"CN",
    "name:zho_x_preferred":[
        "\u767d\u76f8\u5c6f\u6751"
    ],
    "wof:name":"Baixiangtuncun",
    "wof:placetype":"locality"
},
  "geometry": {"coordinates":[121.07006,41.82897],"type":"Point"}
}