{
  "type": "Feature",
  "properties": {
    "gn:admin1_code":"25",
    "gn:asciiname":"Dongzaohu",
    "gn:country_code":"CN",
    "gn:dem":11,
    "gn:feature_class":"P",
    "gn:feature_code":"PPL",
    "gn:name":"Dongzaohu",
    "gn:population":0,
    "gn:timezone":"Asia/Shanghai",
    "iso:country":"CN",
    "name:zho_x_preferred":[
        "\u4e1c\u7682\u6237"
    ],
    "wof:name":"Dongzaohu",
    "wof:placetype":"locality"
},
  "geometry": {"coordinates":[118.03100000000001,37.2836],"type":"Point"}
}