{
  "type": "Feature",
  "properties": {
    "gn:admin1_code":"10",
    "gn:asciiname":"Su-chi-ha-la",
    "gn:country_code":"CN",
    "gn:dem":1239,
    "gn:feature_class":"P",
    "gn:feature_code":"PPL",
    "gn:name":"Su-chi-ha-la",
    "gn:population":0,
    "gn:timezone":"Asia/Shanghai",
    "iso:country":"CN",
    "wof:name":"Su-chi-ha-la",
    "wof:placetype":"locality"
},
  "geometry": {"coordinates":[116.94499999999999,42.13472],"type":"Point"}
}