{
  "type": "Feature",
  "properties": {
    "gn:admin1_code":"6.0",
    "gn:asciiname":"Qinghaihuxiang",
    "gn:country_code":"CN",
    "gn:dem":3256,
    "gn:feature_class":"P",
    "gn:feature_code":"PPL",
    "gn:name":"Qinghaihuxiang",
    "gn:population":0,
    "gn:timezone":"Asia/Shanghai",
    "iso:country":"CN",
    "name:und_x_variant":[
        "\u9752\u6d77\u6e56\u4e61"
    ],
    "wof:name":"Qinghaihuxiang",
    "wof:placetype":"locality"
},
  "geometry": {"coordinates":[100.85373,36.85458],"type":"Point"}
}