{
  "type": "Feature",
  "properties": {
    "gn:admin1_code":"8.0",
    "gn:asciiname":"Menjiatun",
    "gn:country_code":"CN",
    "gn:dem":207,
    "gn:feature_class":"P",
    "gn:feature_code":"PPL",
    "gn:name":"Menjiatun",
    "gn:population":0,
    "gn:timezone":"Asia/Shanghai",
    "iso:country":"CN",
    "name:zho_x_preferred":[
        "\u95e8\u5bb6\u5c6f"
    ],
    "wof:name":"Menjiatun",
    "wof:placetype":"locality"
},
  "geometry": {"coordinates":[127.26611,46.68619],"type":"Point"}
}