{
  "type": "Feature",
  "properties": {
    "gn:admin1_code":"11.0",
    "gn:asciiname":"Xiejia'ao",
    "gn:country_code":"CN",
    "gn:dem":401,
    "gn:feature_class":"P",
    "gn:feature_code":"PPL",
    "gn:name":"Xiejia\u2019ao",
    "gn:population":0,
    "gn:timezone":"Asia/Shanghai",
    "iso:country":"CN",
    "name:und_x_variant":[
        "Xiejia\u2019ao"
    ],
    "name:zho_x_preferred":[
        "\u8c22\u5bb6\u5773"
    ],
    "wof:name":"Xiejia'ao",
    "wof:placetype":"locality"
},
  "geometry": {"coordinates":[113.74673,26.38735],"type":"Point"}
}