{
  "type": "Feature",
  "properties": {
    "gn:admin1_code":"15.0",
    "gn:asciiname":"Luoza",
    "gn:country_code":"CN",
    "gn:dem":2477,
    "gn:feature_class":"P",
    "gn:feature_code":"PPL",
    "gn:name":"Luoza",
    "gn:population":0,
    "gn:timezone":"Asia/Shanghai",
    "iso:country":"CN",
    "name:und_x_variant":[
        "\u6d1b\u6742"
    ],
    "name:zho_x_preferred":[
        "\u6d1b\u6742"
    ],
    "wof:name":"Luoza",
    "wof:placetype":"locality"
},
  "geometry": {"coordinates":[104.25584000000001,33.86144],"type":"Point"}
}