{
  "type": "Feature",
  "properties": {
    "gn:admin1_code":"26.0",
    "gn:asciiname":"Laojunsi",
    "gn:country_code":"CN",
    "gn:dem":1240,
    "gn:feature_class":"P",
    "gn:feature_code":"PPL",
    "gn:name":"Laojunsi",
    "gn:population":0,
    "gn:timezone":"Asia/Shanghai",
    "iso:country":"CN",
    "name:zho_x_preferred":[
        "\u8001\u541b\u5bfa"
    ],
    "wof:name":"Laojunsi",
    "wof:placetype":"locality"
},
  "geometry": {"coordinates":[108.99778000000001,36.57369],"type":"Point"}
}