{
  "type": "Feature",
  "properties": {
    "gn:admin1_code":"12.0",
    "gn:asciiname":"Qianjialin",
    "gn:country_code":"CN",
    "gn:dem":1529,
    "gn:feature_class":"P",
    "gn:feature_code":"PPL",
    "gn:name":"Qianjialin",
    "gn:population":0,
    "gn:timezone":"Asia/Shanghai",
    "iso:country":"CN",
    "name:zho_x_preferred":[
        "\u5343\u5bb6\u6797"
    ],
    "wof:name":"Qianjialin",
    "wof:placetype":"locality"
},
  "geometry": {"coordinates":[111.30683000000001,31.70629000000001],"type":"Point"}
}