{
  "type": "Feature",
  "properties": {
    "gn:admin1_code":"3.0",
    "gn:asciiname":"Lingxie",
    "gn:country_code":"CN",
    "gn:dem":535,
    "gn:feature_class":"P",
    "gn:feature_code":"PPL",
    "gn:name":"Lingxie",
    "gn:population":0,
    "gn:timezone":"Asia/Shanghai",
    "iso:country":"CN",
    "name:und_x_variant":[
        "\u5cad\u659c"
    ],
    "wof:name":"Lingxie",
    "wof:placetype":"locality"
},
  "geometry": {"coordinates":[114.74087,28.96139],"type":"Point"}
}