{
  "type": "Feature",
  "properties": {
    "gn:admin1_code":"24",
    "gn:asciiname":"Hongya",
    "gn:country_code":"CN",
    "gn:dem":1524,
    "gn:feature_class":"P",
    "gn:feature_code":"PPL",
    "gn:name":"Hongya",
    "gn:population":0,
    "gn:timezone":"Asia/Shanghai",
    "iso:country":"CN",
    "name:deu_x_preferred":[
        "Hongya"
    ],
    "name:rus_x_preferred":[
        "\u0425\u0443\u043d\u044a\u044f"
    ],
    "name:und_x_variant":[
        "Hung-ya",
        "Hung-yai",
        "Hung-yai-ts\u2019un"
    ],
    "name:zho_x_preferred":[
        "\u7ea2\u5d16"
    ],
    "wof:name":"Hongya",
    "wof:placetype":"locality"
},
  "geometry": {"coordinates":[113.31435,37.53132],"type":"Point"}
}