{
  "type": "Feature",
  "properties": {
    "gn:admin1_code":"29.0",
    "gn:asciiname":"Zoumadi",
    "gn:country_code":"CN",
    "gn:dem":2073,
    "gn:feature_class":"P",
    "gn:feature_code":"PPL",
    "gn:name":"Zoumadi",
    "gn:population":0,
    "gn:timezone":"Asia/Shanghai",
    "iso:country":"CN",
    "name:zho_x_preferred":[
        "\u8d70\u9a6c\u5730"
    ],
    "wof:name":"Zoumadi",
    "wof:placetype":"locality"
},
  "geometry": {"coordinates":[102.16800000000001,25.4398],"type":"Point"}
}