{
  "type": "Feature",
  "properties": {
    "gn:admin1_code":"3.0",
    "gn:asciiname":"Xiaoming",
    "gn:country_code":"CN",
    "gn:dem":46,
    "gn:feature_class":"P",
    "gn:feature_code":"PPL",
    "gn:name":"Xiaoming",
    "gn:population":0,
    "gn:timezone":"Asia/Shanghai",
    "iso:country":"CN",
    "name:und_x_variant":[
        "\u6653\u660e"
    ],
    "wof:name":"Xiaoming",
    "wof:placetype":"locality"
},
  "geometry": {"coordinates":[116.75466000000002,29.20091],"type":"Point"}
}