{
  "type": "Feature",
  "properties": {
    "gn:admin1_code":"32.0",
    "gn:asciiname":"Zhongxiao",
    "gn:country_code":"CN",
    "gn:dem":399,
    "gn:feature_class":"P",
    "gn:feature_code":"PPL",
    "gn:name":"Zhongxiao",
    "gn:population":0,
    "gn:timezone":"Asia/Shanghai",
    "iso:country":"CN",
    "name:zho_x_preferred":[
        "\u5fe0\u5b5d"
    ],
    "wof:name":"Zhongxiao",
    "wof:placetype":"locality"
},
  "geometry": {"coordinates":[105.19862999999999,31.28755],"type":"Point"}
}