{
  "type": "Feature",
  "properties": {
    "gn:admin1_code":"9.0",
    "gn:asciiname":"Houshuangmiao",
    "gn:country_code":"CN",
    "gn:dem":67,
    "gn:feature_class":"P",
    "gn:feature_code":"PPL",
    "gn:name":"Houshuangmiao",
    "gn:population":0,
    "gn:timezone":"Asia/Shanghai",
    "iso:country":"CN",
    "name:zho_x_preferred":[
        "\u540e\u53cc\u5e99"
    ],
    "wof:name":"Houshuangmiao",
    "wof:placetype":"locality"
},
  "geometry": {"coordinates":[114.37324,34.31816],"type":"Point"}
}