{
  "type": "Feature",
  "properties": {
    "gn:admin1_code":"7.0",
    "gn:asciiname":"Zhangtiancun",
    "gn:country_code":"CN",
    "gn:dem":461,
    "gn:feature_class":"P",
    "gn:feature_code":"PPL",
    "gn:name":"Zhangtiancun",
    "gn:population":0,
    "gn:timezone":"Asia/Shanghai",
    "iso:country":"CN",
    "name:zho_x_preferred":[
        "\u5f20\u7530\u6751"
    ],
    "wof:name":"Zhangtiancun",
    "wof:placetype":"locality"
},
  "geometry": {"coordinates":[117.80369,26.19169],"type":"Point"}
}