{
  "type": "Feature",
  "properties": {
    "gn:admin1_code":"16",
    "gn:asciiname":"Baohe",
    "gn:country_code":"CN",
    "gn:dem":401,
    "gn:feature_class":"P",
    "gn:feature_code":"PPL",
    "gn:name":"Baohe",
    "gn:population":0,
    "gn:timezone":"Asia/Shanghai",
    "iso:country":"CN",
    "name:zho_x_preferred":[
        "\u4fdd\u548c"
    ],
    "wof:name":"Baohe",
    "wof:placetype":"locality"
},
  "geometry": {"coordinates":[110.798,25.4763],"type":"Point"}
}