{
  "type": "Feature",
  "properties": {
    "gn:admin1_code":"32.0",
    "gn:asciiname":"Hanuogu",
    "gn:country_code":"CN",
    "gn:dem":2359,
    "gn:feature_class":"P",
    "gn:feature_code":"PPL",
    "gn:name":"Hanuogu",
    "gn:population":0,
    "gn:timezone":"Asia/Shanghai",
    "iso:country":"CN",
    "name:zho_x_preferred":[
        "\u54c8\u8bfa\u53e4"
    ],
    "wof:name":"Hanuogu",
    "wof:placetype":"locality"
},
  "geometry": {"coordinates":[102.974,27.7834],"type":"Point"}
}