{
  "type": "Feature",
  "properties": {
    "gn:admin1_code":"18",
    "gn:asciiname":"Guyu",
    "gn:country_code":"CN",
    "gn:dem":1381,
    "gn:feature_class":"P",
    "gn:feature_code":"PPL",
    "gn:name":"Guyu",
    "gn:population":0,
    "gn:timezone":"Asia/Shanghai",
    "iso:country":"CN",
    "name:afr_x_preferred":[
        "Guyu"
    ],
    "name:cdo_x_preferred":[
        "G\u00f3k-\u1e73\u0304"
    ],
    "name:hak_x_preferred":[
        "Kuk-y\u00ed"
    ],
    "name:ind_x_preferred":[
        "Guyu"
    ],
    "name:swe_x_preferred":[
        "Guyu"
    ],
    "name:vie_x_preferred":[
        "C\u1ed1c v\u0169"
    ],
    "name:zha_x_preferred":[
        "Goekhawx"
    ],
    "name:zho_x_preferred":[
        "\u8c37\u96e8"
    ],
    "wof:name":"Guyu",
    "wof:placetype":"locality"
},
  "geometry": {"coordinates":[105.471,26.0024],"type":"Point"}
}