{
  "type": "Feature",
  "properties": {
    "gn:admin1_code":"18.0",
    "gn:asciiname":"Lantan",
    "gn:country_code":"CN",
    "gn:dem":1769,
    "gn:feature_class":"P",
    "gn:feature_code":"PPL",
    "gn:name":"Lantan",
    "gn:population":0,
    "gn:timezone":"Asia/Shanghai",
    "iso:country":"CN",
    "name:zho_x_preferred":[
        "\u6ee5\u6ee9"
    ],
    "wof:name":"Lantan",
    "wof:placetype":"locality"
},
  "geometry": {"coordinates":[104.57599999999999,25.5771],"type":"Point"}
}