{
  "type": "Feature",
  "properties": {
    "gn:admin1_code":"30.0",
    "gn:asciiname":"Shangjiao",
    "gn:country_code":"CN",
    "gn:dem":141,
    "gn:feature_class":"P",
    "gn:feature_code":"PPL",
    "gn:name":"Shangjiao",
    "gn:population":0,
    "gn:timezone":"Asia/Shanghai",
    "iso:country":"CN",
    "name:und_x_variant":[
        "\u4e0a\u89d2"
    ],
    "name:zho_x_preferred":[
        "\u4e0a\u89d2"
    ],
    "wof:name":"Shangjiao",
    "wof:placetype":"locality"
},
  "geometry": {"coordinates":[113.42113000000001,23.23231],"type":"Point"}
}