{
  "type": "Feature",
  "properties": {
    "gn:admin1_code":"30.0",
    "gn:asciiname":"Chengguo",
    "gn:country_code":"CN",
    "gn:dem":88,
    "gn:feature_class":"P",
    "gn:feature_code":"PPL",
    "gn:name":"Chengguo",
    "gn:population":0,
    "gn:timezone":"Asia/Urumqi",
    "iso:country":"CN",
    "name:zho_x_preferred":[
        "\u6210\u57da"
    ],
    "wof:name":"Chengguo",
    "wof:placetype":"locality"
},
  "geometry": {"coordinates":[110.25951999999999,20.36597],"type":"Point"}
}