{
  "type": "Feature",
  "properties": {
    "gn:admin1_code":"29.0",
    "gn:asciiname":"Xiaojiluo",
    "gn:country_code":"CN",
    "gn:dem":1994,
    "gn:feature_class":"P",
    "gn:feature_code":"PPL",
    "gn:name":"Xiaojiluo",
    "gn:population":0,
    "gn:timezone":"Asia/Shanghai",
    "iso:country":"CN",
    "name:zho_x_preferred":[
        "\u5c0f\u7eaa\u7f57"
    ],
    "wof:name":"Xiaojiluo",
    "wof:placetype":"locality"
},
  "geometry": {"coordinates":[100.452,25.2523],"type":"Point"}
}