{
  "type": "Feature",
  "properties": {
    "gn:admin1_code":"2.0",
    "gn:asciiname":"Jiulingjiao",
    "gn:country_code":"CN",
    "gn:dem":363,
    "gn:feature_class":"P",
    "gn:feature_code":"PPL",
    "gn:name":"Jiulingjiao",
    "gn:population":0,
    "gn:timezone":"Asia/Shanghai",
    "iso:country":"CN",
    "name:und_x_variant":[
        "\u4e5d\u5cad\u811a"
    ],
    "name:zho_x_preferred":[
        "Jiulingjiao"
    ],
    "wof:name":"Jiulingjiao",
    "wof:placetype":"locality"
},
  "geometry": {"coordinates":[119.03328999999999,29.99478],"type":"Point"}
}