{
  "type": "Feature",
  "properties": {
    "gn:admin1_code":"7",
    "gn:asciiname":"Gongdong",
    "gn:country_code":"CN",
    "gn:dem":477,
    "gn:feature_class":"P",
    "gn:feature_code":"PPL",
    "gn:name":"Gongdong",
    "gn:population":0,
    "gn:timezone":"Asia/Shanghai",
    "iso:country":"CN",
    "name:zho_x_preferred":[
        "\u5bab\u4e1c"
    ],
    "wof:name":"Gongdong",
    "wof:placetype":"locality"
},
  "geometry": {"coordinates":[118.83149,25.63099],"type":"Point"}
}