{
  "type": "Feature",
  "properties": {
    "gn:admin1_code":"1.0",
    "gn:asciiname":"Housuzhuangcun",
    "gn:country_code":"CN",
    "gn:dem":31,
    "gn:feature_class":"P",
    "gn:feature_code":"PPL",
    "gn:name":"Housuzhuangcun",
    "gn:population":0,
    "gn:timezone":"Asia/Shanghai",
    "iso:country":"CN",
    "name:zho_x_preferred":[
        "\u540e\u82cf\u5e84\u6751"
    ],
    "wof:name":"Housuzhuangcun",
    "wof:placetype":"locality"
},
  "geometry": {"coordinates":[116.11015,33.21684],"type":"Point"}
}