{
  "type": "Feature",
  "properties": {
    "gn:admin1_code":"30.0",
    "gn:asciiname":"Xiakengkou",
    "gn:country_code":"CN",
    "gn:dem":98,
    "gn:feature_class":"P",
    "gn:feature_code":"PPL",
    "gn:name":"Xiakengkou",
    "gn:population":0,
    "gn:timezone":"Asia/Shanghai",
    "iso:country":"CN",
    "name:zho_x_preferred":[
        "\u4e0b\u5751\u53e3"
    ],
    "wof:name":"Xiakengkou",
    "wof:placetype":"locality"
},
  "geometry": {"coordinates":[112.20205,23.17209],"type":"Point"}
}