{
  "type": "Feature",
  "properties": {
    "gn:admin1_code":"5.0",
    "gn:asciiname":"Shanhetun",
    "gn:country_code":"CN",
    "gn:dem":307,
    "gn:feature_class":"P",
    "gn:feature_code":"PPL",
    "gn:name":"Shanhetun",
    "gn:population":0,
    "gn:timezone":"Asia/Shanghai",
    "iso:country":"CN",
    "name:zho_x_preferred":[
        "\u5c71\u6cb3\u5c6f"
    ],
    "wof:name":"Shanhetun",
    "wof:placetype":"locality"
},
  "geometry": {"coordinates":[126.67227,43.18293],"type":"Point"}
}