{
  "type": "Feature",
  "properties": {
    "gn:admin1_code":"5.0",
    "gn:asciiname":"Kongyandong",
    "gn:country_code":"CN",
    "gn:dem":302,
    "gn:feature_class":"P",
    "gn:feature_code":"PPL",
    "gn:name":"Kongyandong",
    "gn:population":0,
    "gn:timezone":"Asia/Shanghai",
    "iso:country":"CN",
    "name:und_x_variant":[
        "\u5b54\u5ca9\u6d1e"
    ],
    "wof:name":"Kongyandong",
    "wof:placetype":"locality"
},
  "geometry": {"coordinates":[129.68442999999999,42.46306],"type":"Point"}
}