{
  "type": "Feature",
  "properties": {
    "gn:admin1_code":"7.0",
    "gn:asciiname":"Yikou",
    "gn:cc2":"CN",
    "gn:country_code":"CN",
    "gn:dem":293,
    "gn:feature_class":"P",
    "gn:feature_code":"PPL",
    "gn:name":"Yikou",
    "gn:population":0,
    "gn:timezone":"Asia/Shanghai",
    "iso:country":"CN",
    "name:und_x_variant":[
        "I-k\u2019ou",
        "Yikou"
    ],
    "wof:name":"Yikou",
    "wof:placetype":"locality"
},
  "geometry": {"coordinates":[117.01667,26.78333],"type":"Point"}
}