{
  "type": "Feature",
  "properties": {
    "gn:admin1_code":"29.0",
    "gn:asciiname":"Zhongdian",
    "gn:country_code":"CN",
    "gn:dem":1987,
    "gn:feature_class":"P",
    "gn:feature_code":"PPL",
    "gn:name":"Zhongdian",
    "gn:population":0,
    "gn:timezone":"Asia/Shanghai",
    "iso:country":"CN",
    "name:zho_x_preferred":[
        "\u4e2d\u7538"
    ],
    "wof:name":"Zhongdian",
    "wof:placetype":"locality"
},
  "geometry": {"coordinates":[100.127,25.7829],"type":"Point"}
}