{
  "type": "Feature",
  "properties": {
    "gn:admin1_code":"10",
    "gn:asciiname":"Shanhaiguan",
    "gn:country_code":"CN",
    "gn:dem":13,
    "gn:feature_class":"P",
    "gn:feature_code":"PPLA3",
    "gn:name":"Shanhaiguan",
    "gn:population":140000,
    "gn:timezone":"Asia/Shanghai",
    "iso:country":"CN",
    "name:eng_x_preferred":[
        "Shanhaiguan"
    ],
    "name:rus_x_preferred":[
        "\u0428\u0430\u043d\u044c\u0445\u0430\u0439\u0433\u0443\u0430\u043d\u044c"
    ],
    "name:und_x_variant":[
        "Lin-y\u00fc",
        "Shan-hai-kuan",
        "Shanhaikwan",
        "Shanhaiguan"
    ],
    "name:zho_x_preferred":[
        "\u5c71\u6d77\u5173"
    ],
    "wof:name":"Shanhaiguan",
    "wof:placetype":"locality",
    "wof:population":140000
},
  "geometry": {"coordinates":[119.74889,40.0025],"type":"Point"}
}