{
  "type": "Feature",
  "properties": {
    "gn:admin1_code":"10",
    "gn:asciiname":"Shanhaiguan",
    "gn:country_code":"CN",
    "gn:dem":13,
    "gn:feature_class":"P",
    "gn:feature_code":"PPLA3",
    "gn:name":"Shanhaiguan",
    "gn:population":140000,
    "gn:timezone":"Asia/Shanghai",
    "iso:country":"CN",
    "name:deu_x_preferred":[
        "Shanhaiguan"
    ],
    "name:eng_x_preferred":[
        "Shanhaiguan"
    ],
    "name:jpn_x_preferred":[
        "\u5c71\u6d77\u95a2\u533a"
    ],
    "name:kor_x_preferred":[
        "\uc0b0\ud558\uc774\uad00\uad6c"
    ],
    "name:rus_x_preferred":[
        "\u0428\u0430\u043d\u044c\u0445\u0430\u0439\u0433\u0443\u0430\u043d\u044c"
    ],
    "name:swe_x_preferred":[
        "Shanhaiguan"
    ],
    "name:ukr_x_preferred":[
        "\u0428\u0430\u043d\u044c\u0445\u0430\u0439\u0433\u0443\u0430\u043d\u044c"
    ],
    "name:und_x_variant":[
        "Lin-y\u00fc",
        "Shan-hai-kuan",
        "Shanhaikwan"
    ],
    "name:urd_x_preferred":[
        "\u0634\u0627\u0646\u06c1\u0627\u06cc\u06af\u0648\u0627\u0646 \u0636\u0644\u0639"
    ],
    "name:zho_x_preferred":[
        "\u5c71\u6d77\u5173"
    ],
    "name:zho_x_variant":[
        "\u5c71\u6d77\u5173\u533a"
    ],
    "wof:name":"Shanhaiguan",
    "wof:placetype":"locality",
    "wof:population":140000
},
  "geometry": {"coordinates":[119.74889,40.0025],"type":"Point"}
}