{
  "type": "Feature",
  "properties": {
    "gn:admin1_code":"29.0",
    "gn:asciiname":"Tuanshanzhai",
    "gn:country_code":"CN",
    "gn:dem":1255,
    "gn:feature_class":"P",
    "gn:feature_code":"PPL",
    "gn:name":"Tuanshanzhai",
    "gn:population":0,
    "gn:timezone":"Asia/Shanghai",
    "iso:country":"CN",
    "name:zho_x_preferred":[
        "\u56e2\u5c71\u5be8"
    ],
    "wof:name":"Tuanshanzhai",
    "wof:placetype":"locality"
},
  "geometry": {"coordinates":[101.51600000000001,22.7313],"type":"Point"}
}