{
  "type": "Feature",
  "properties": {
    "gn:admin1_code":"26.0",
    "gn:asciiname":"Daxigoukou",
    "gn:country_code":"CN",
    "gn:dem":1187,
    "gn:feature_class":"P",
    "gn:feature_code":"PPL",
    "gn:name":"Daxigoukou",
    "gn:population":0,
    "gn:timezone":"Asia/Shanghai",
    "iso:country":"CN",
    "name:zho_x_preferred":[
        "\u5927\u897f\u6c9f\u53e3"
    ],
    "wof:name":"Daxigoukou",
    "wof:placetype":"locality"
},
  "geometry": {"coordinates":[109.29279,33.46288],"type":"Point"}
}