{
  "type": "Feature",
  "properties": {
    "gn:admin1_code":"19.0",
    "gn:asciiname":"Luzhangzi",
    "gn:country_code":"CN",
    "gn:dem":285,
    "gn:feature_class":"P",
    "gn:feature_code":"PPL",
    "gn:name":"L\u00fczhangzi",
    "gn:population":0,
    "gn:timezone":"Asia/Shanghai",
    "iso:country":"CN",
    "name:zho_x_preferred":[
        "\u5415\u6756\u5b50"
    ],
    "name:zho_x_variant":[
        "L\u00fczhangzi"
    ],
    "wof:name":"Luzhangzi",
    "wof:placetype":"locality"
},
  "geometry": {"coordinates":[119.65000000000001,40.3912],"type":"Point"}
}