{
  "type": "Feature",
  "properties": {
    "gn:admin1_code":"15.0",
    "gn:asciiname":"Qijia Zhaizi",
    "gn:country_code":"CN",
    "gn:dem":1920,
    "gn:feature_class":"P",
    "gn:feature_code":"PPL",
    "gn:name":"Qijia Zhaizi",
    "gn:population":0,
    "gn:timezone":"Asia/Shanghai",
    "iso:country":"CN",
    "name:zho_x_preferred":[
        "\u7941\u5bb6\u5be8\u5b50"
    ],
    "wof:name":"Qijia Zhaizi",
    "wof:placetype":"locality"
},
  "geometry": {"coordinates":[103.70099999999999,37.5092],"type":"Point"}
}