{
  "type": "Feature",
  "properties": {
    "gn:admin1_code":"31.0",
    "gn:asciiname":"Xiaxizai",
    "gn:country_code":"CN",
    "gn:dem":46,
    "gn:feature_class":"P",
    "gn:feature_code":"PPL",
    "gn:name":"Xiaxizai",
    "gn:population":0,
    "gn:timezone":"Asia/Shanghai",
    "iso:country":"CN",
    "name:und_x_variant":[
        "\u4e0b\u6eaa\u4ed4"
    ],
    "wof:name":"Xiaxizai",
    "wof:placetype":"locality"
},
  "geometry": {"coordinates":[110.25557999999999,18.70489],"type":"Point"}
}