{
  "type": "Feature",
  "properties": {
    "gn:admin1_code":"24.0",
    "gn:asciiname":"Sanqingliang",
    "gn:country_code":"CN",
    "gn:dem":1348,
    "gn:feature_class":"P",
    "gn:feature_code":"PPL",
    "gn:name":"Sanqingliang",
    "gn:population":0,
    "gn:timezone":"Asia/Shanghai",
    "iso:country":"CN",
    "name:zho_x_preferred":[
        "\u4e09\u9752\u6881"
    ],
    "wof:name":"Sanqingliang",
    "wof:placetype":"locality"
},
  "geometry": {"coordinates":[112.2799,39.32989],"type":"Point"}
}