{
  "type": "Feature",
  "properties": {
    "gn:admin1_code":"26.0",
    "gn:asciiname":"Gaochao",
    "gn:country_code":"CN",
    "gn:dem":833,
    "gn:feature_class":"P",
    "gn:feature_code":"PPL",
    "gn:name":"Gaochao",
    "gn:population":0,
    "gn:timezone":"Asia/Shanghai",
    "iso:country":"CN",
    "name:zho_x_preferred":[
        "\u9ad8\u671d"
    ],
    "wof:name":"Gaochao",
    "wof:placetype":"locality"
},
  "geometry": {"coordinates":[110.61189,33.76362],"type":"Point"}
}