{
  "type": "Feature",
  "properties": {
    "gn:admin1_code":"3.0",
    "gn:asciiname":"Henggangcun",
    "gn:country_code":"CN",
    "gn:dem":44,
    "gn:feature_class":"P",
    "gn:feature_code":"PPL",
    "gn:name":"Henggangcun",
    "gn:population":0,
    "gn:timezone":"Asia/Shanghai",
    "iso:country":"CN",
    "name:und_x_variant":[
        "\u6a2a\u5c97\u6751"
    ],
    "wof:name":"Henggangcun",
    "wof:placetype":"locality"
},
  "geometry": {"coordinates":[116.69001000000002,28.47328],"type":"Point"}
}