{
  "type": "Feature",
  "properties": {
    "gn:admin1_code":"30.0",
    "gn:asciiname":"Niu'equ",
    "gn:country_code":"CN",
    "gn:dem":39,
    "gn:feature_class":"P",
    "gn:feature_code":"PPL",
    "gn:name":"Niu\u2019equ",
    "gn:population":0,
    "gn:timezone":"Asia/Shanghai",
    "iso:country":"CN",
    "name:zho_x_preferred":[
        "\u725b\u8f6d\u66f2"
    ],
    "name:zho_x_variant":[
        "Niu\u2019equ"
    ],
    "wof:name":"Niu'equ",
    "wof:placetype":"locality"
},
  "geometry": {"coordinates":[114.35577000000001,23.41352],"type":"Point"}
}