{
  "type": "Feature",
  "properties": {
    "gn:admin1_code":"30",
    "gn:asciiname":"Shangfeng",
    "gn:country_code":"CN",
    "gn:dem":511,
    "gn:feature_class":"P",
    "gn:feature_code":"PPL",
    "gn:name":"Shangfeng",
    "gn:population":0,
    "gn:timezone":"Asia/Shanghai",
    "iso:country":"CN",
    "name:und_x_variant":[
        "Shangshe",
        "Shangfeng"
    ],
    "name:zho_x_preferred":[
        "\u4e0a\u5cef"
    ],
    "wof:name":"Shangfeng",
    "wof:placetype":"locality"
},
  "geometry": {"coordinates":[115.66336,24.53388],"type":"Point"}
}