{
  "type": "Feature",
  "properties": {
    "gn:admin1_code":"14.0",
    "gn:asciiname":"Zheqingtang",
    "gn:country_code":"CN",
    "gn:dem":4458,
    "gn:feature_class":"P",
    "gn:feature_code":"PPL",
    "gn:name":"Zheqingtang",
    "gn:population":0,
    "gn:timezone":"Asia/Urumqi",
    "iso:country":"CN",
    "name:zho_x_preferred":[
        "\u54f2\u5e86\u5858"
    ],
    "wof:name":"Zheqingtang",
    "wof:placetype":"locality"
},
  "geometry": {"coordinates":[93.84275,31.76979],"type":"Point"}
}