{
  "type": "Feature",
  "properties": {
    "gn:admin1_code":"30.0",
    "gn:asciiname":"Sanjiaohu",
    "gn:country_code":"CN",
    "gn:dem":599,
    "gn:feature_class":"P",
    "gn:feature_code":"PPL",
    "gn:name":"Sanjiaohu",
    "gn:population":0,
    "gn:timezone":"Asia/Shanghai",
    "iso:country":"CN",
    "name:zho_x_preferred":[
        "Sanjiaohu"
    ],
    "name:zho_x_variant":[
        "\u4e09\u89d2\u6e56"
    ],
    "wof:name":"Sanjiaohu",
    "wof:placetype":"locality"
},
  "geometry": {"coordinates":[114.67037000000001,24.50318],"type":"Point"}
}