{
  "type": "Feature",
  "properties": {
    "gn:admin1_code":"15.0",
    "gn:asciiname":"Yangwa",
    "gn:country_code":"CN",
    "gn:dem":1930,
    "gn:feature_class":"P",
    "gn:feature_code":"PPL",
    "gn:name":"Yangwa",
    "gn:population":0,
    "gn:timezone":"Asia/Shanghai",
    "iso:country":"CN",
    "name:und_x_variant":[
        "\u9633\u5c72"
    ],
    "wof:name":"Yangwa",
    "wof:placetype":"locality"
},
  "geometry": {"coordinates":[105.38303000000001,35.19994000000001],"type":"Point"}
}