{
  "type": "Feature",
  "properties": {
    "gn:admin1_code":"24.0",
    "gn:asciiname":"Hejiadi",
    "gn:country_code":"CN",
    "gn:dem":1008,
    "gn:feature_class":"P",
    "gn:feature_code":"PPL",
    "gn:name":"Hejiadi",
    "gn:population":0,
    "gn:timezone":"Asia/Shanghai",
    "iso:country":"CN",
    "name:und_x_variant":[
        "\u8d3a\u5bb6\u5730"
    ],
    "wof:name":"Hejiadi",
    "wof:placetype":"locality"
},
  "geometry": {"coordinates":[113.04656,39.45891],"type":"Point"}
}