{
  "type": "Feature",
  "properties": {
    "gn:admin1_code":"30.0",
    "gn:asciiname":"Geli",
    "gn:country_code":"CN",
    "gn:dem":47,
    "gn:feature_class":"P",
    "gn:feature_code":"PPL",
    "gn:name":"Geli",
    "gn:population":0,
    "gn:timezone":"Asia/Shanghai",
    "iso:country":"CN",
    "name:ceb_x_preferred":[
        "Geli"
    ],
    "name:deu_x_preferred":[
        "Geli"
    ],
    "name:swe_x_preferred":[
        "Geli"
    ],
    "name:zho_x_preferred":[
        "\u683c\u6ca5"
    ],
    "wof:name":"Geli",
    "wof:placetype":"locality"
},
  "geometry": {"coordinates":[114.71785,23.49915],"type":"Point"}
}