{
  "type": "Feature",
  "properties": {
    "gn:admin1_code":"11.0",
    "gn:asciiname":"Yangshanmiao",
    "gn:country_code":"CN",
    "gn:dem":94,
    "gn:feature_class":"P",
    "gn:feature_code":"PPL",
    "gn:name":"Yangshanmiao",
    "gn:population":0,
    "gn:timezone":"Asia/Shanghai",
    "iso:country":"CN",
    "name:zho_x_preferred":[
        "\u4ef0\u5c71\u5e99"
    ],
    "wof:name":"Yangshanmiao",
    "wof:placetype":"locality"
},
  "geometry": {"coordinates":[112.80859,26.75393],"type":"Point"}
}