{
  "type": "Feature",
  "properties": {
    "gn:admin1_code":"3.0",
    "gn:asciiname":"Hubin",
    "gn:country_code":"CN",
    "gn:dem":26,
    "gn:feature_class":"P",
    "gn:feature_code":"PPL",
    "gn:name":"Hubin",
    "gn:population":0,
    "gn:timezone":"Asia/Shanghai",
    "iso:country":"CN",
    "name:und_x_variant":[
        "\u6e56\u6ee8",
        "Hubinxiang",
        "\u6e56\u6ee8\u4e61"
    ],
    "wof:name":"Hubin",
    "wof:placetype":"locality"
},
  "geometry": {"coordinates":[116.65921000000002,29.37612],"type":"Point"}
}