{
  "type": "Feature",
  "properties": {
    "gn:admin1_code":"29.0",
    "gn:asciiname":"Tanyao",
    "gn:country_code":"CN",
    "gn:dem":2138,
    "gn:feature_class":"P",
    "gn:feature_code":"PPL",
    "gn:name":"Tanyao",
    "gn:population":0,
    "gn:timezone":"Asia/Shanghai",
    "iso:country":"CN",
    "name:zho_x_preferred":[
        "\u70ad\u7a91"
    ],
    "wof:name":"Tanyao",
    "wof:placetype":"locality"
},
  "geometry": {"coordinates":[102.557,25.1195],"type":"Point"}
}