{
  "type": "Feature",
  "properties": {
    "gn:admin1_code":"24",
    "gn:asciiname":"Fanqiao",
    "gn:cc2":"CN",
    "gn:country_code":"CN",
    "gn:dem":377,
    "gn:feature_class":"P",
    "gn:feature_code":"PPL",
    "gn:name":"Fanqiao",
    "gn:population":0,
    "gn:timezone":"Asia/Shanghai",
    "iso:country":"CN",
    "name:und_x_variant":[
        "Fan-ch\u2019iao-ts\u2019un",
        "Fan-ch\u2019iao",
        "Fanqiao"
    ],
    "wof:name":"Fanqiao",
    "wof:placetype":"locality"
},
  "geometry": {"coordinates":[110.60583,35.05611],"type":"Point"}
}