{
  "type": "Feature",
  "properties": {
    "gn:admin1_code":"15.0",
    "gn:asciiname":"Shahekou",
    "gn:country_code":"CN",
    "gn:dem":1446,
    "gn:feature_class":"P",
    "gn:feature_code":"PPL",
    "gn:name":"Shahekou",
    "gn:population":0,
    "gn:timezone":"Asia/Shanghai",
    "iso:country":"CN",
    "name:zho_x_preferred":[
        "\u6c99\u6cb3\u53e3"
    ],
    "wof:name":"Shahekou",
    "wof:placetype":"locality"
},
  "geometry": {"coordinates":[104.384,36.4314],"type":"Point"}
}