{
  "type": "Feature",
  "properties": {
    "gn:admin1_code":"5.0",
    "gn:asciiname":"Xiaowopeng",
    "gn:country_code":"CN",
    "gn:dem":154,
    "gn:feature_class":"P",
    "gn:feature_code":"PPL",
    "gn:name":"Xiaowopeng",
    "gn:population":0,
    "gn:timezone":"Asia/Shanghai",
    "iso:country":"CN",
    "name:zho_x_preferred":[
        "\u5c0f\u7a9d\u68da"
    ],
    "wof:name":"Xiaowopeng",
    "wof:placetype":"locality"
},
  "geometry": {"coordinates":[123.68214,43.76701],"type":"Point"}
}