{
  "type": "Feature",
  "properties": {
    "gn:admin1_code":"30.0",
    "gn:asciiname":"Xinxiangshan",
    "gn:country_code":"CN",
    "gn:dem":30,
    "gn:feature_class":"P",
    "gn:feature_code":"PPL",
    "gn:name":"Xinxiangshan",
    "gn:population":0,
    "gn:timezone":"Asia/Shanghai",
    "iso:country":"CN",
    "name:zho_x_preferred":[
        "\u65b0\u9999\u5c71"
    ],
    "wof:name":"Xinxiangshan",
    "wof:placetype":"locality"
},
  "geometry": {"coordinates":[114.55828,23.22008],"type":"Point"}
}