{
  "type": "Feature",
  "properties": {
    "gn:admin1_code":"19.0",
    "gn:asciiname":"Digou",
    "gn:country_code":"CN",
    "gn:dem":173,
    "gn:feature_class":"P",
    "gn:feature_code":"PPL",
    "gn:name":"Digou",
    "gn:population":0,
    "gn:timezone":"Asia/Shanghai",
    "iso:country":"CN",
    "name:zho_x_preferred":[
        "\u5730\u6c9f"
    ],
    "wof:name":"Digou",
    "wof:placetype":"locality"
},
  "geometry": {"coordinates":[124.20412,42.50498],"type":"Point"}
}