{
  "type": "Feature",
  "properties": {
    "gn:admin1_code":"30.0",
    "gn:asciiname":"Shuangwucun",
    "gn:country_code":"CN",
    "gn:dem":12,
    "gn:feature_class":"P",
    "gn:feature_code":"PPL",
    "gn:name":"Shuangwucun",
    "gn:population":0,
    "gn:timezone":"Asia/Shanghai",
    "iso:country":"CN",
    "name:zho_x_preferred":[
        "\u53cc\u68a7\u6751"
    ],
    "wof:name":"Shuangwucun",
    "wof:placetype":"locality"
},
  "geometry": {"coordinates":[116.30410999999999,23.51297000000001],"type":"Point"}
}