{
  "type": "Feature",
  "properties": {
    "gn:admin1_code":"25",
    "gn:asciiname":"Jiaojiazhuang",
    "gn:country_code":"CN",
    "gn:dem":57,
    "gn:feature_class":"P",
    "gn:feature_code":"PPL",
    "gn:name":"Jiaojiazhuang",
    "gn:population":0,
    "gn:timezone":"Asia/Shanghai",
    "iso:country":"CN",
    "name:zho_x_preferred":[
        "\u7126\u5bb6\u5e84"
    ],
    "wof:name":"Jiaojiazhuang",
    "wof:placetype":"locality"
},
  "geometry": {"coordinates":[119.187,36.4541],"type":"Point"}
}