{
  "type": "Feature",
  "properties": {
    "gn:admin1_code":"14.0",
    "gn:asciiname":"Shaxiongpu",
    "gn:country_code":"CN",
    "gn:dem":4298,
    "gn:feature_class":"P",
    "gn:feature_code":"PPL",
    "gn:name":"Shaxiongpu",
    "gn:population":0,
    "gn:timezone":"Asia/Urumqi",
    "iso:country":"CN",
    "name:zho_x_preferred":[
        "\u6740\u51f6\u666e"
    ],
    "wof:name":"Shaxiongpu",
    "wof:placetype":"locality"
},
  "geometry": {"coordinates":[93.74278,31.93282],"type":"Point"}
}