{
  "type": "Feature",
  "properties": {
    "gn:admin1_code":"25",
    "gn:asciiname":"Shanhexi",
    "gn:country_code":"CN",
    "gn:dem":92,
    "gn:feature_class":"P",
    "gn:feature_code":"PPL",
    "gn:name":"Shanhexi",
    "gn:population":0,
    "gn:timezone":"Asia/Shanghai",
    "iso:country":"CN",
    "name:zho_x_preferred":[
        "\u5c71\u6cb3\u897f"
    ],
    "wof:name":"Shanhexi",
    "wof:placetype":"locality"
},
  "geometry": {"coordinates":[117.113,35.6723],"type":"Point"}
}