{
  "type": "Feature",
  "properties": {
    "gn:admin1_code":"15.0",
    "gn:asciiname":"Xiqian",
    "gn:country_code":"CN",
    "gn:dem":3120,
    "gn:feature_class":"P",
    "gn:feature_code":"PPL",
    "gn:name":"Xiqian",
    "gn:population":0,
    "gn:timezone":"Asia/Shanghai",
    "iso:country":"CN",
    "name:zho_x_preferred":[
        "\u897f\u6b20"
    ],
    "wof:name":"Xiqian",
    "wof:placetype":"locality"
},
  "geometry": {"coordinates":[102.738,34.7002],"type":"Point"}
}