{
  "type": "Feature",
  "properties": {
    "gn:admin1_code":"6.0",
    "gn:asciiname":"Gujilai",
    "gn:country_code":"CN",
    "gn:dem":2069,
    "gn:feature_class":"P",
    "gn:feature_code":"PPL",
    "gn:name":"Gujilai",
    "gn:population":0,
    "gn:timezone":"Asia/Shanghai",
    "iso:country":"CN",
    "name:und_x_variant":[
        "\u53e4\u53ca\u6765"
    ],
    "wof:name":"Gujilai",
    "wof:placetype":"locality"
},
  "geometry": {"coordinates":[102.42129,35.81343],"type":"Point"}
}