{
  "type": "Feature",
  "properties": {
    "gn:admin1_code":"30",
    "gn:asciiname":"Danzhutang",
    "gn:country_code":"CN",
    "gn:dem":30,
    "gn:feature_class":"P",
    "gn:feature_code":"PPL",
    "gn:name":"Danzhutang",
    "gn:population":0,
    "gn:timezone":"Asia/Urumqi",
    "iso:country":"CN",
    "name:zho_x_preferred":[
        "\u4e39\u7af9\u5858"
    ],
    "wof:name":"Danzhutang",
    "wof:placetype":"locality"
},
  "geometry": {"coordinates":[110.25501,21.5269],"type":"Point"}
}