{
  "type": "Feature",
  "properties": {
    "gn:admin1_code":"6.0",
    "gn:asciiname":"Youyun",
    "gn:country_code":"CN",
    "gn:dem":4211,
    "gn:feature_class":"P",
    "gn:feature_code":"PPLA4",
    "gn:name":"Youyun",
    "gn:population":0,
    "gn:timezone":"Asia/Shanghai",
    "iso:country":"CN",
    "name:und_x_variant":[
        "Youyun Xiang",
        "Zhongxinzhan"
    ],
    "name:zho_x_preferred":[
        "\u4f18\u4e91"
    ],
    "name:zho_x_variant":[
        "\u4f18\u4e91\u4e61",
        "\u4e2d\u5fc3\u7ad9"
    ],
    "wof:name":"Youyun",
    "wof:placetype":"locality"
},
  "geometry": {"coordinates":[99.19088000000001,34.2714],"type":"Point"}
}