{
  "type": "Feature",
  "properties": {
    "gn:admin1_code":"29.0",
    "gn:asciiname":"Huangcaoping",
    "gn:country_code":"CN",
    "gn:dem":349,
    "gn:feature_class":"P",
    "gn:feature_code":"PPL",
    "gn:name":"Huangcaoping",
    "gn:population":0,
    "gn:timezone":"Asia/Shanghai",
    "iso:country":"CN",
    "name:zho_x_preferred":[
        "\u9ec4\u8349\u576a"
    ],
    "wof:name":"Huangcaoping",
    "wof:placetype":"locality"
},
  "geometry": {"coordinates":[103.194,23.0767],"type":"Point"}
}