{
  "type": "Feature",
  "properties": {
    "gn:admin1_code":"29.0",
    "gn:asciiname":"Hachong",
    "gn:country_code":"CN",
    "gn:dem":2315,
    "gn:feature_class":"P",
    "gn:feature_code":"PPL",
    "gn:name":"Hachong",
    "gn:population":0,
    "gn:timezone":"Asia/Shanghai",
    "iso:country":"CN",
    "name:zho_x_preferred":[
        "\u54c8\u5145"
    ],
    "wof:name":"Hachong",
    "wof:placetype":"locality"
},
  "geometry": {"coordinates":[99.33029999999999,28.2077],"type":"Point"}
}