{
  "type": "Feature",
  "properties": {
    "gn:admin1_code":"25.0",
    "gn:asciiname":"Sunjiaxinzhuang",
    "gn:country_code":"CN",
    "gn:dem":35,
    "gn:feature_class":"P",
    "gn:feature_code":"PPL",
    "gn:name":"Sunjiaxinzhuang",
    "gn:population":0,
    "gn:timezone":"Asia/Shanghai",
    "iso:country":"CN",
    "name:zho_x_preferred":[
        "\u5b59\u5bb6\u8f9b\u5e84"
    ],
    "wof:name":"Sunjiaxinzhuang",
    "wof:placetype":"locality"
},
  "geometry": {"coordinates":[120.5016,36.61239000000001],"type":"Point"}
}