{
  "type": "Feature",
  "properties": {
    "gn:admin1_code":"20.0",
    "gn:asciiname":"Ke'erlun",
    "gn:country_code":"CN",
    "gn:dem":619,
    "gn:feature_class":"P",
    "gn:feature_code":"PPLA4",
    "gn:name":"Ke\u2019erlun",
    "gn:population":0,
    "gn:timezone":"Asia/Shanghai",
    "iso:country":"CN",
    "name:und_x_variant":[
        "Ke\u2019erlun",
        "Ke\u2019erlun Sumu"
    ],
    "name:zho_x_preferred":[
        "\u514b\u5c14\u4f26"
    ],
    "name:zho_x_variant":[
        "\u514b\u5c14\u4f26\u82cf\u6728"
    ],
    "wof:name":"Ke'erlun",
    "wof:placetype":"locality"
},
  "geometry": {"coordinates":[115.85682,48.16445],"type":"Point"}
}