{
  "type": "Feature",
  "properties": {
    "gn:admin1_code":"25.0",
    "gn:asciiname":"Pantuncun",
    "gn:country_code":"CN",
    "gn:dem":39,
    "gn:feature_class":"P",
    "gn:feature_code":"PPL",
    "gn:name":"Pantuncun",
    "gn:population":0,
    "gn:timezone":"Asia/Shanghai",
    "iso:country":"CN",
    "name:zho_x_preferred":[
        "\u6f58\u5c6f\u6751"
    ],
    "wof:name":"Pantuncun",
    "wof:placetype":"locality"
},
  "geometry": {"coordinates":[115.9325,36.39625],"type":"Point"}
}