{
  "type": "Feature",
  "properties": {
    "gn:admin1_code":"29.0",
    "gn:asciiname":"Daguanzhai",
    "gn:country_code":"CN",
    "gn:dem":1444,
    "gn:feature_class":"P",
    "gn:feature_code":"PPL",
    "gn:name":"Daguanzhai",
    "gn:population":0,
    "gn:timezone":"Asia/Shanghai",
    "iso:country":"CN",
    "name:zho_x_preferred":[
        "\u5927\u5173\u5be8"
    ],
    "wof:name":"Daguanzhai",
    "wof:placetype":"locality"
},
  "geometry": {"coordinates":[103.89,27.9282],"type":"Point"}
}