{
  "type": "Feature",
  "properties": {
    "gn:admin1_code":"30.0",
    "gn:asciiname":"Xiahuang Gutian",
    "gn:country_code":"CN",
    "gn:dem":333,
    "gn:feature_class":"P",
    "gn:feature_code":"PPL",
    "gn:name":"Xiahuang Gutian",
    "gn:population":0,
    "gn:timezone":"Asia/Shanghai",
    "iso:country":"CN",
    "name:zho_x_preferred":[
        "\u4e0b\u9ec4\u8c37\u7530"
    ],
    "wof:name":"Xiahuang Gutian",
    "wof:placetype":"locality"
},
  "geometry": {"coordinates":[113.78607,23.80778],"type":"Point"}
}