{
  "type": "Feature",
  "properties": {
    "gn:admin1_code":"8.0",
    "gn:asciiname":"Xudong",
    "gn:country_code":"CN",
    "gn:dem":161,
    "gn:feature_class":"P",
    "gn:feature_code":"PPL",
    "gn:name":"Xudong",
    "gn:population":0,
    "gn:timezone":"Asia/Shanghai",
    "iso:country":"CN",
    "name:zho_x_preferred":[
        "\u65ed\u4e1c"
    ],
    "wof:name":"Xudong",
    "wof:placetype":"locality"
},
  "geometry": {"coordinates":[124.70504,47.54495],"type":"Point"}
}