{
  "type": "Feature",
  "properties": {
    "gn:admin1_code":"32.0",
    "gn:asciiname":"Zhulinwan",
    "gn:country_code":"CN",
    "gn:dem":524,
    "gn:feature_class":"P",
    "gn:feature_code":"PPL",
    "gn:name":"Zhulinwan",
    "gn:population":0,
    "gn:timezone":"Asia/Shanghai",
    "iso:country":"CN",
    "name:zho_x_preferred":[
        "\u7af9\u6797\u6e7e"
    ],
    "wof:name":"Zhulinwan",
    "wof:placetype":"locality"
},
  "geometry": {"coordinates":[105.672,28.646],"type":"Point"}
}