{
  "type": "Feature",
  "properties": {
    "gn:admin1_code":"30.0",
    "gn:asciiname":"Junliaodong",
    "gn:country_code":"CN",
    "gn:dem":373,
    "gn:feature_class":"P",
    "gn:feature_code":"PPL",
    "gn:name":"Junliaodong",
    "gn:population":0,
    "gn:timezone":"Asia/Shanghai",
    "iso:country":"CN",
    "name:zho_x_preferred":[
        "Junliaodong"
    ],
    "name:zho_x_variant":[
        "\u519b\u5bee\u6d1e"
    ],
    "wof:name":"Junliaodong",
    "wof:placetype":"locality"
},
  "geometry": {"coordinates":[112.20111,24.67361],"type":"Point"}
}