{
  "type": "Feature",
  "properties": {
    "gn:admin1_code":"2.0",
    "gn:asciiname":"Paijukou",
    "gn:country_code":"CN",
    "gn:dem":405,
    "gn:feature_class":"P",
    "gn:feature_code":"PPL",
    "gn:name":"Paijukou",
    "gn:population":0,
    "gn:timezone":"Asia/Shanghai",
    "iso:country":"CN",
    "name:zho_x_preferred":[
        "\u6392\u5c45\u53e3"
    ],
    "wof:name":"Paijukou",
    "wof:placetype":"locality"
},
  "geometry": {"coordinates":[119.29467,28.34951],"type":"Point"}
}