{
  "type": "Feature",
  "properties": {
    "gn:admin1_code":"25",
    "gn:asciiname":"Xiajianggan",
    "gn:country_code":"CN",
    "gn:dem":411,
    "gn:feature_class":"P",
    "gn:feature_code":"PPL",
    "gn:name":"Xiajianggan",
    "gn:population":0,
    "gn:timezone":"Asia/Shanghai",
    "iso:country":"CN",
    "name:zho_x_preferred":[
        "\u4e0b\u964d\u7518"
    ],
    "wof:name":"Xiajianggan",
    "wof:placetype":"locality"
},
  "geometry": {"coordinates":[117.235,36.4561],"type":"Point"}
}