{
  "type": "Feature",
  "properties": {
    "gn:admin1_code":"32.0",
    "gn:asciiname":"Wa'erma",
    "gn:country_code":"CN",
    "gn:dem":3353,
    "gn:feature_class":"P",
    "gn:feature_code":"PPLA4",
    "gn:name":"Wa\u2019erma",
    "gn:population":0,
    "gn:timezone":"Asia/Shanghai",
    "iso:country":"CN",
    "name:und_x_variant":[
        "Wa\u2019erma Xiang"
    ],
    "name:zho_x_preferred":[
        "\u54c7\u5c14\u739b"
    ],
    "name:zho_x_variant":[
        "Wa\u2019erma",
        "\u54c7\u5c14\u739b\u4e61"
    ],
    "wof:name":"Wa'erma",
    "wof:placetype":"locality"
},
  "geometry": {"coordinates":[101.71999,32.92365],"type":"Point"}
}