{
  "type": "Feature",
  "properties": {
    "gn:admin1_code":"18.0",
    "gn:asciiname":"Pingdingsi",
    "gn:country_code":"CN",
    "gn:dem":759,
    "gn:feature_class":"P",
    "gn:feature_code":"PPL",
    "gn:name":"Pingdingsi",
    "gn:population":0,
    "gn:timezone":"Asia/Shanghai",
    "iso:country":"CN",
    "name:zho_x_preferred":[
        "\u5e73\u5b9a\u53f8"
    ],
    "wof:name":"Pingdingsi",
    "wof:placetype":"locality"
},
  "geometry": {"coordinates":[107.68600000000001,26.3889],"type":"Point"}
}