{
  "type": "Feature",
  "properties": {
    "gn:admin1_code":"3.0",
    "gn:asciiname":"Shizixia",
    "gn:country_code":"CN",
    "gn:dem":255,
    "gn:feature_class":"P",
    "gn:feature_code":"PPL",
    "gn:name":"Shizixia",
    "gn:population":0,
    "gn:timezone":"Asia/Shanghai",
    "iso:country":"CN",
    "name:und_x_variant":[
        "\u77f3\u5b50\u4e0b"
    ],
    "wof:name":"Shizixia",
    "wof:placetype":"locality"
},
  "geometry": {"coordinates":[115.86108,25.42222000000001],"type":"Point"}
}