{
  "type": "Feature",
  "properties": {
    "gn:admin1_code":"16.0",
    "gn:asciiname":"Jiaoqiang",
    "gn:country_code":"CN",
    "gn:dem":180,
    "gn:feature_class":"P",
    "gn:feature_code":"PPL",
    "gn:name":"Jiaoqiang",
    "gn:population":0,
    "gn:timezone":"Asia/Shanghai",
    "iso:country":"CN",
    "name:zho_x_preferred":[
        "\u53eb\u7f8c"
    ],
    "wof:name":"Jiaoqiang",
    "wof:placetype":"locality"
},
  "geometry": {"coordinates":[108.01000000000001,22.3246],"type":"Point"}
}