{
  "type": "Feature",
  "properties": {
    "gn:admin1_code":"30.0",
    "gn:asciiname":"Shuangdi",
    "gn:country_code":"CN",
    "gn:dem":119,
    "gn:feature_class":"P",
    "gn:feature_code":"PPL",
    "gn:name":"Shuangdi",
    "gn:population":0,
    "gn:timezone":"Asia/Shanghai",
    "iso:country":"CN",
    "name:zho_x_preferred":[
        "\u53cc\u8fea"
    ],
    "wof:name":"Shuangdi",
    "wof:placetype":"locality"
},
  "geometry": {"coordinates":[112.08222000000001,23.73525],"type":"Point"}
}