{
  "type": "Feature",
  "properties": {
    "gn:admin1_code":"4.0",
    "gn:asciiname":"Baofengcun",
    "gn:country_code":"CN",
    "gn:dem":3,
    "gn:feature_class":"P",
    "gn:feature_code":"PPL",
    "gn:name":"Baofengcun",
    "gn:population":0,
    "gn:timezone":"Asia/Shanghai",
    "iso:country":"CN",
    "name:zho_x_preferred":[
        "\u4fdd\u4e30\u6751"
    ],
    "wof:name":"Baofengcun",
    "wof:placetype":"locality"
},
  "geometry": {"coordinates":[119.5061,32.7179],"type":"Point"}
}