{
  "type": "Feature",
  "properties": {
    "gn:admin1_code":"15.0",
    "gn:asciiname":"Dongjiahe",
    "gn:country_code":"CN",
    "gn:dem":1804,
    "gn:feature_class":"P",
    "gn:feature_code":"PPL",
    "gn:name":"Dongjiahe",
    "gn:population":0,
    "gn:timezone":"Asia/Shanghai",
    "iso:country":"CN",
    "name:zho_x_preferred":[
        "\u8463\u5bb6\u6cb3"
    ],
    "wof:name":"Dongjiahe",
    "wof:placetype":"locality"
},
  "geometry": {"coordinates":[106.396,34.743],"type":"Point"}
}