{
  "type": "Feature",
  "properties": {
    "gn:admin1_code":"7.0",
    "gn:asciiname":"Hengkengcun",
    "gn:country_code":"CN",
    "gn:dem":288,
    "gn:feature_class":"P",
    "gn:feature_code":"PPL",
    "gn:name":"Hengkengcun",
    "gn:population":0,
    "gn:timezone":"Asia/Shanghai",
    "iso:country":"CN",
    "name:und_x_variant":[
        "\u6a2a\u5751\u6751"
    ],
    "name:zho_x_preferred":[
        "\u6a2a\u5751\u6751"
    ],
    "wof:name":"Hengkengcun",
    "wof:placetype":"locality"
},
  "geometry": {"coordinates":[117.36253000000001,26.22323],"type":"Point"}
}