{
  "type": "Feature",
  "properties": {
    "gn:admin1_code":"10",
    "gn:asciiname":"Jiangjiaying",
    "gn:country_code":"CN",
    "gn:dem":100,
    "gn:feature_class":"P",
    "gn:feature_code":"PPL",
    "gn:name":"Jiangjiaying",
    "gn:population":0,
    "gn:timezone":"Asia/Shanghai",
    "iso:country":"CN",
    "wof:name":"Jiangjiaying",
    "wof:placetype":"locality"
},
  "geometry": {"coordinates":[118.23333,39.86667],"type":"Point"}
}