{
  "type": "Feature",
  "properties": {
    "gn:admin1_code":"9.0",
    "gn:asciiname":"Gaobiangen",
    "gn:country_code":"CN",
    "gn:dem":866,
    "gn:feature_class":"P",
    "gn:feature_code":"PPL",
    "gn:name":"Gaobiangen",
    "gn:population":0,
    "gn:timezone":"Asia/Shanghai",
    "iso:country":"CN",
    "name:zho_x_preferred":[
        "\u9ad8\u8fb9\u6839"
    ],
    "wof:name":"Gaobiangen",
    "wof:placetype":"locality"
},
  "geometry": {"coordinates":[111.09711,33.93308],"type":"Point"}
}