{
  "type": "Feature",
  "properties": {
    "gn:admin1_code":"32.0",
    "gn:asciiname":"Tuqiaopu",
    "gn:country_code":"CN",
    "gn:dem":346,
    "gn:feature_class":"P",
    "gn:feature_code":"PPL",
    "gn:name":"Tuqiaopu",
    "gn:population":0,
    "gn:timezone":"Asia/Shanghai",
    "iso:country":"CN",
    "name:zho_x_preferred":[
        "\u571f\u6865\u94fa"
    ],
    "wof:name":"Tuqiaopu",
    "wof:placetype":"locality"
},
  "geometry": {"coordinates":[105.16762,30.22468],"type":"Point"}
}