{
  "type": "Feature",
  "properties": {
    "gn:admin1_code":"10",
    "gn:asciiname":"Koumenzi",
    "gn:country_code":"CN",
    "gn:dem":216,
    "gn:feature_class":"P",
    "gn:feature_code":"PPL",
    "gn:name":"Koumenzi",
    "gn:population":0,
    "gn:timezone":"Asia/Shanghai",
    "iso:country":"CN",
    "name:zho_x_preferred":[
        "\u53e3\u95e8\u5b50"
    ],
    "wof:name":"Koumenzi",
    "wof:placetype":"locality"
},
  "geometry": {"coordinates":[117.91396,40.28532],"type":"Point"}
}