{
  "type": "Feature",
  "properties": {
    "gn:admin1_code":"24",
    "gn:asciiname":"Baishansi",
    "gn:cc2":"CN",
    "gn:country_code":"CN",
    "gn:dem":1086,
    "gn:feature_class":"P",
    "gn:feature_code":"PPL",
    "gn:name":"Baishansi",
    "gn:population":0,
    "gn:timezone":"Asia/Shanghai",
    "iso:country":"CN",
    "name:und_x_variant":[
        "Pai-shan-ssu",
        "Baishansi"
    ],
    "wof:name":"Baishansi",
    "wof:placetype":"locality"
},
  "geometry": {"coordinates":[110.58056000000001,35.99139],"type":"Point"}
}