{
  "type": "Feature",
  "properties": {
    "gn:admin1_code":"15.0",
    "gn:asciiname":"Dongzhai",
    "gn:country_code":"CN",
    "gn:dem":2047,
    "gn:feature_class":"P",
    "gn:feature_code":"PPL",
    "gn:name":"Dongzhai",
    "gn:population":0,
    "gn:timezone":"Asia/Shanghai",
    "iso:country":"CN",
    "name:zho_x_preferred":[
        "\u4e1c\u5be8"
    ],
    "wof:name":"Dongzhai",
    "wof:placetype":"locality"
},
  "geometry": {"coordinates":[100.85899999999999,38.5624],"type":"Point"}
}