{
  "type": "Feature",
  "properties": {
    "gn:admin1_code":"1.0",
    "gn:asciiname":"Daiyingcun",
    "gn:country_code":"CN",
    "gn:dem":25,
    "gn:feature_class":"P",
    "gn:feature_code":"PPL",
    "gn:name":"Daiyingcun",
    "gn:population":0,
    "gn:timezone":"Asia/Shanghai",
    "iso:country":"CN",
    "name:zho_x_preferred":[
        "\u6234\u90e2\u6751"
    ],
    "wof:name":"Daiyingcun",
    "wof:placetype":"locality"
},
  "geometry": {"coordinates":[116.61699,32.40368],"type":"Point"}
}