{
  "type": "Feature",
  "properties": {
    "gn:admin1_code":"11.0",
    "gn:asciiname":"Jiangjiachong",
    "gn:country_code":"CN",
    "gn:dem":48,
    "gn:feature_class":"P",
    "gn:feature_code":"PPL",
    "gn:name":"Jiangjiachong",
    "gn:population":0,
    "gn:timezone":"Asia/Shanghai",
    "iso:country":"CN",
    "name:zho_x_preferred":[
        "\u59dc\u5bb6\u51b2"
    ],
    "wof:name":"Jiangjiachong",
    "wof:placetype":"locality"
},
  "geometry": {"coordinates":[111.72769,28.87735],"type":"Point"}
}