{
  "type": "Feature",
  "properties": {
    "gn:admin1_code":"8.0",
    "gn:asciiname":"Wanghongzhang",
    "gn:country_code":"CN",
    "gn:dem":191,
    "gn:feature_class":"P",
    "gn:feature_code":"PPL",
    "gn:name":"Wanghongzhang",
    "gn:population":0,
    "gn:timezone":"Asia/Shanghai",
    "iso:country":"CN",
    "name:zho_x_preferred":[
        "\u738b\u6d2a\u7ae0"
    ],
    "wof:name":"Wanghongzhang",
    "wof:placetype":"locality"
},
  "geometry": {"coordinates":[127.38679999999999,46.47349000000001],"type":"Point"}
}