{
  "type": "Feature",
  "properties": {
    "gn:admin1_code":"18",
    "gn:asciiname":"Zhongba",
    "gn:country_code":"CN",
    "gn:dem":1352,
    "gn:feature_class":"P",
    "gn:feature_code":"PPL",
    "gn:name":"Zhongba",
    "gn:population":0,
    "gn:timezone":"Asia/Shanghai",
    "iso:country":"CN",
    "name:zho_x_preferred":[
        "\u4e2d\u575d"
    ],
    "wof:name":"Zhongba",
    "wof:placetype":"locality"
},
  "geometry": {"coordinates":[105.28400000000001,26.9736],"type":"Point"}
}