{
  "type": "Feature",
  "properties": {
    "gn:admin1_code":"32.0",
    "gn:asciiname":"Jinhe",
    "gn:country_code":"CN",
    "gn:dem":333,
    "gn:feature_class":"P",
    "gn:feature_code":"PPL",
    "gn:name":"Jinhe",
    "gn:population":0,
    "gn:timezone":"Asia/Shanghai",
    "iso:country":"CN",
    "name:zho_x_preferred":[
        "\u91d1\u9e64"
    ],
    "wof:name":"Jinhe",
    "wof:placetype":"locality"
},
  "geometry": {"coordinates":[105.48267,30.83667],"type":"Point"}
}