{
  "type": "Feature",
  "properties": {
    "gn:admin1_code":"24.0",
    "gn:asciiname":"Xiaojiangjiatun",
    "gn:country_code":"CN",
    "gn:dem":1385,
    "gn:feature_class":"P",
    "gn:feature_code":"PPL",
    "gn:name":"Xiaojiangjiatun",
    "gn:population":0,
    "gn:timezone":"Asia/Shanghai",
    "iso:country":"CN",
    "name:und_x_variant":[
        "\u5c0f\u848b\u5bb6\u5c6f"
    ],
    "name:zho_x_preferred":[
        "\u5c0f\u848b\u5bb6\u5c6f"
    ],
    "wof:name":"Xiaojiangjiatun",
    "wof:placetype":"locality"
},
  "geometry": {"coordinates":[112.40134999999999,40.01359],"type":"Point"}
}