{
  "type": "Feature",
  "properties": {
    "gn:admin1_code":"3.0",
    "gn:asciiname":"Daxi",
    "gn:country_code":"CN",
    "gn:dem":43,
    "gn:feature_class":"P",
    "gn:feature_code":"PPL",
    "gn:name":"Daxi",
    "gn:population":0,
    "gn:timezone":"Asia/Shanghai",
    "iso:country":"CN",
    "name:ceb_x_preferred":[
        "Daxi"
    ],
    "name:deu_x_preferred":[
        "Daxi"
    ],
    "name:swe_x_preferred":[
        "Daxi"
    ],
    "name:und_x_variant":[
        "\u5927\u6eaa"
    ],
    "wof:name":"Daxi",
    "wof:placetype":"locality"
},
  "geometry": {"coordinates":[115.14648,27.45305],"type":"Point"}
}