{
  "type": "Feature",
  "properties": {
    "gn:admin1_code":"11",
    "gn:asciiname":"Guanghuayuan",
    "gn:country_code":"CN",
    "gn:dem":30,
    "gn:feature_class":"P",
    "gn:feature_code":"PPL",
    "gn:name":"Guanghuayuan",
    "gn:population":0,
    "gn:timezone":"Asia/Shanghai",
    "iso:country":"CN",
    "name:zho_x_preferred":[
        "\u5149\u534e\u57b8"
    ],
    "wof:name":"Guanghuayuan",
    "wof:placetype":"locality"
},
  "geometry": {"coordinates":[112.63934999999999,28.91831],"type":"Point"}
}