{
  "type": "Feature",
  "properties": {
    "gn:admin1_code":"14.0",
    "gn:asciiname":"Zomngoi",
    "gn:country_code":"CN",
    "gn:dem":4104,
    "gn:feature_class":"P",
    "gn:feature_code":"PPL",
    "gn:name":"Zomngoi",
    "gn:population":0,
    "gn:timezone":"Asia/Urumqi",
    "iso:country":"CN",
    "name:bod_x_preferred":[
        "Zomngoi"
    ],
    "name:zho_x_preferred":[
        "Zong\u2019e"
    ],
    "name:zho_x_variant":[
        "\u5b97\u9102"
    ],
    "wof:name":"Zomngoi",
    "wof:placetype":"locality"
},
  "geometry": {"coordinates":[98.304,29.904],"type":"Point"}
}