{
  "type": "Feature",
  "properties": {
    "gn:admin1_code":"11",
    "gn:asciiname":"Qingjiangshan",
    "gn:country_code":"CN",
    "gn:dem":510,
    "gn:feature_class":"P",
    "gn:feature_code":"PPL",
    "gn:name":"Qingjiangshan",
    "gn:population":0,
    "gn:timezone":"Asia/Shanghai",
    "iso:country":"CN",
    "name:zho_x_preferred":[
        "\u6e05\u6c5f\u5c71"
    ],
    "wof:name":"Qingjiangshan",
    "wof:placetype":"locality"
},
  "geometry": {"coordinates":[109.51340999999999,26.61367000000001],"type":"Point"}
}