{
  "type": "Feature",
  "properties": {
    "gn:admin1_code":"6.0",
    "gn:asciiname":"Manong",
    "gn:country_code":"CN",
    "gn:dem":4168,
    "gn:feature_class":"P",
    "gn:feature_code":"PPL",
    "gn:name":"Manong",
    "gn:population":0,
    "gn:timezone":"Asia/Urumqi",
    "iso:country":"CN",
    "name:zho_x_preferred":[
        "\u739b\u5f04"
    ],
    "wof:name":"Manong",
    "wof:placetype":"locality"
},
  "geometry": {"coordinates":[96.16370000000001,32.0666],"type":"Point"}
}