{
  "type": "Feature",
  "properties": {
    "gn:admin1_code":"19.0",
    "gn:asciiname":"Anjinggou",
    "gn:country_code":"CN",
    "gn:dem":210,
    "gn:feature_class":"P",
    "gn:feature_code":"PPL",
    "gn:name":"Anjinggou",
    "gn:population":0,
    "gn:timezone":"Asia/Shanghai",
    "iso:country":"CN",
    "name:zho_x_preferred":[
        "\u5b89\u9759\u6c9f"
    ],
    "wof:name":"Anjinggou",
    "wof:placetype":"locality"
},
  "geometry": {"coordinates":[124.431,42.5653],"type":"Point"}
}