{
  "type": "Feature",
  "properties": {
    "gn:admin1_code":"29.0",
    "gn:asciiname":"Diantang",
    "gn:country_code":"CN",
    "gn:dem":1366,
    "gn:feature_class":"P",
    "gn:feature_code":"PPL",
    "gn:name":"Diantang",
    "gn:population":0,
    "gn:timezone":"Asia/Shanghai",
    "iso:country":"CN",
    "name:zho_x_preferred":[
        "\u975b\u5858"
    ],
    "wof:name":"Diantang",
    "wof:placetype":"locality"
},
  "geometry": {"coordinates":[103.095,22.8498],"type":"Point"}
}