{
  "type": "Feature",
  "properties": {
    "gn:admin1_code":"26.0",
    "gn:asciiname":"Shigongshanping",
    "gn:country_code":"CN",
    "gn:dem":1787,
    "gn:feature_class":"P",
    "gn:feature_code":"PPL",
    "gn:name":"Shigongshanping",
    "gn:population":0,
    "gn:timezone":"Asia/Shanghai",
    "iso:country":"CN",
    "name:und_x_variant":[
        "\u77f3\u516c\u5c71\u576a"
    ],
    "wof:name":"Shigongshanping",
    "wof:placetype":"locality"
},
  "geometry": {"coordinates":[106.59551999999999,33.49460999999999],"type":"Point"}
}