{
  "type": "Feature",
  "properties": {
    "gn:admin1_code":"15.0",
    "gn:asciiname":"Miaoxiang",
    "gn:country_code":"CN",
    "gn:dem":1384,
    "gn:feature_class":"P",
    "gn:feature_code":"PPLA4",
    "gn:name":"Miaoxiang",
    "gn:population":0,
    "gn:timezone":"Asia/Shanghai",
    "iso:country":"CN",
    "name:und_x_variant":[
        "\u5e99\u5df7",
        "Miaoxiang Xiang",
        "\u5e99\u5df7\u4e61"
    ],
    "wof:name":"Miaoxiang",
    "wof:placetype":"locality"
},
  "geometry": {"coordinates":[107.98688,36.5285],"type":"Point"}
}