{
  "type": "Feature",
  "properties": {
    "gn:admin1_code":"9",
    "gn:asciiname":"Miaoguo",
    "gn:country_code":"CN",
    "gn:dem":48,
    "gn:feature_class":"P",
    "gn:feature_code":"PPL",
    "gn:name":"Miaoguo",
    "gn:population":0,
    "gn:timezone":"Asia/Shanghai",
    "iso:country":"CN",
    "name:zho_x_preferred":[
        "\u82d7\u90ed"
    ],
    "wof:name":"Miaoguo",
    "wof:placetype":"locality"
},
  "geometry": {"coordinates":[115.37090999999999,36.05496],"type":"Point"}
}