{
  "type": "Feature",
  "properties": {
    "gn:admin1_code":"12.0",
    "gn:asciiname":"Yangjiaba",
    "gn:country_code":"CN",
    "gn:dem":661,
    "gn:feature_class":"P",
    "gn:feature_code":"PPL",
    "gn:name":"Yangjiaba",
    "gn:population":0,
    "gn:timezone":"Asia/Shanghai",
    "iso:country":"CN",
    "name:zho_x_preferred":[
        "\u6768\u5bb6\u575d"
    ],
    "wof:name":"Yangjiaba",
    "wof:placetype":"locality"
},
  "geometry": {"coordinates":[110.12577,32.4001],"type":"Point"}
}