{
  "type": "Feature",
  "properties": {
    "gn:admin1_code":"26.0",
    "gn:asciiname":"Kangpingcun",
    "gn:country_code":"CN",
    "gn:dem":990,
    "gn:feature_class":"P",
    "gn:feature_code":"PPL",
    "gn:name":"Kangpingcun",
    "gn:population":0,
    "gn:timezone":"Asia/Shanghai",
    "iso:country":"CN",
    "name:zho_x_preferred":[
        "\u5eb7\u576a\u6751"
    ],
    "wof:name":"Kangpingcun",
    "wof:placetype":"locality"
},
  "geometry": {"coordinates":[109.57355,36.73614],"type":"Point"}
}