{
  "type": "Feature",
  "properties": {
    "gn:admin1_code":"19.0",
    "gn:asciiname":"Dabainiugou",
    "gn:country_code":"CN",
    "gn:dem":217,
    "gn:feature_class":"P",
    "gn:feature_code":"PPL",
    "gn:name":"Dabainiugou",
    "gn:population":0,
    "gn:timezone":"Asia/Shanghai",
    "iso:country":"CN",
    "name:und_x_variant":[
        "\u5927\u767d\u725b\u6c9f"
    ],
    "name:zho_x_preferred":[
        "\u5927\u767d\u725b\u6c9f"
    ],
    "wof:name":"Dabainiugou",
    "wof:placetype":"locality"
},
  "geometry": {"coordinates":[125.31471000000001,41.06419],"type":"Point"}
}