{
  "type": "Feature",
  "properties": {
    "gn:admin1_code":"12.0",
    "gn:asciiname":"Xinhua",
    "gn:country_code":"CN",
    "gn:dem":963,
    "gn:feature_class":"P",
    "gn:feature_code":"PPL",
    "gn:name":"Xinhua",
    "gn:population":0,
    "gn:timezone":"Asia/Shanghai",
    "iso:country":"CN",
    "name:zho_x_preferred":[
        "\u65b0\u534e"
    ],
    "wof:name":"Xinhua",
    "wof:placetype":"locality"
},
  "geometry": {"coordinates":[109.03613,30.10513],"type":"Point"}
}