{
  "type": "Feature",
  "properties": {
    "gn:admin1_code":"15.0",
    "gn:asciiname":"Luanyaozi",
    "gn:country_code":"CN",
    "gn:dem":2043,
    "gn:feature_class":"P",
    "gn:feature_code":"PPL",
    "gn:name":"Luanyaozi",
    "gn:population":0,
    "gn:timezone":"Asia/Shanghai",
    "iso:country":"CN",
    "name:zho_x_preferred":[
        "\u4e71\u7a91\u5b50"
    ],
    "wof:name":"Luanyaozi",
    "wof:placetype":"locality"
},
  "geometry": {"coordinates":[103.944,36.7409],"type":"Point"}
}