{
  "type": "Feature",
  "properties": {
    "gn:admin1_code":"25",
    "gn:asciiname":"Beidatian",
    "gn:cc2":"CN",
    "gn:country_code":"CN",
    "gn:dem":114,
    "gn:feature_class":"P",
    "gn:feature_code":"PPL",
    "gn:name":"Beidatian",
    "gn:population":0,
    "gn:timezone":"Asia/Shanghai",
    "iso:country":"CN",
    "name:und_x_variant":[
        "Pei-ta-t\u2019ien",
        "Beidatian"
    ],
    "wof:name":"Beidatian",
    "wof:placetype":"locality"
},
  "geometry": {"coordinates":[120.105,36.96389],"type":"Point"}
}