{
  "type": "Feature",
  "properties": {
    "gn:admin1_code":"8.0",
    "gn:asciiname":"Quncecun",
    "gn:country_code":"CN",
    "gn:dem":146,
    "gn:feature_class":"P",
    "gn:feature_code":"PPL",
    "gn:name":"Quncecun",
    "gn:population":0,
    "gn:timezone":"Asia/Shanghai",
    "iso:country":"CN",
    "name:zho_x_preferred":[
        "\u7fa4\u7b56\u6751"
    ],
    "wof:name":"Quncecun",
    "wof:placetype":"locality"
},
  "geometry": {"coordinates":[125.91101,45.29375],"type":"Point"}
}