{
  "type": "Feature",
  "properties": {
    "gn:admin1_code":"29.0",
    "gn:asciiname":"Yinchangping",
    "gn:country_code":"CN",
    "gn:dem":2476,
    "gn:feature_class":"P",
    "gn:feature_code":"PPL",
    "gn:name":"Yinchangping",
    "gn:population":0,
    "gn:timezone":"Asia/Shanghai",
    "iso:country":"CN",
    "name:zho_x_preferred":[
        "\u94f6\u5382\u576a"
    ],
    "wof:name":"Yinchangping",
    "wof:placetype":"locality"
},
  "geometry": {"coordinates":[99.0183,25.9139],"type":"Point"}
}