{
  "type": "Feature",
  "properties": {
    "gn:admin1_code":"30",
    "gn:asciiname":"Shanpingzhai",
    "gn:country_code":"CN",
    "gn:dem":394,
    "gn:feature_class":"P",
    "gn:feature_code":"PPL",
    "gn:name":"Shanpingzhai",
    "gn:population":0,
    "gn:timezone":"Asia/Shanghai",
    "iso:country":"CN",
    "name:zho_x_preferred":[
        "\u5c71\u576a\u5be8"
    ],
    "wof:name":"Shanpingzhai",
    "wof:placetype":"locality"
},
  "geometry": {"coordinates":[111.49241000000001,22.28098],"type":"Point"}
}