{
  "type": "Feature",
  "properties": {
    "gn:admin1_code":"26",
    "gn:asciiname":"Qinjiahe",
    "gn:country_code":"CN",
    "gn:dem":560,
    "gn:feature_class":"P",
    "gn:feature_code":"PPL",
    "gn:name":"Qinjiahe",
    "gn:population":0,
    "gn:timezone":"Asia/Shanghai",
    "iso:country":"CN",
    "name:und_x_variant":[
        "\u79e6\u5bb6\u6cb3",
        "Chenjiahe",
        "Qinjiahe"
    ],
    "wof:name":"Qinjiahe",
    "wof:placetype":"locality"
},
  "geometry": {"coordinates":[109.00142,34.80240999999999],"type":"Point"}
}