{
  "type": "Feature",
  "properties": {
    "gn:admin1_code":"10",
    "gn:asciiname":"Laodibei",
    "gn:country_code":"CN",
    "gn:dem":48,
    "gn:feature_class":"P",
    "gn:feature_code":"PPL",
    "gn:name":"Laodibei",
    "gn:population":0,
    "gn:timezone":"Asia/Shanghai",
    "iso:country":"CN",
    "name:zho_x_preferred":[
        "\u8001\u5824\u5317"
    ],
    "wof:name":"Laodibei",
    "wof:placetype":"locality"
},
  "geometry": {"coordinates":[115.11955,36.25402],"type":"Point"}
}