{
  "type": "Feature",
  "properties": {
    "gn:admin1_code":"4.0",
    "gn:asciiname":"Heizaying",
    "gn:country_code":"CN",
    "gn:dem":6,
    "gn:feature_class":"P",
    "gn:feature_code":"PPL",
    "gn:name":"Heizaying",
    "gn:population":0,
    "gn:timezone":"Asia/Shanghai",
    "iso:country":"CN",
    "name:zho_x_preferred":[
        "\u9ed1\u624e\u8425"
    ],
    "wof:name":"Heizaying",
    "wof:placetype":"locality"
},
  "geometry": {"coordinates":[118.64396000000001,32.21465999999999],"type":"Point"}
}