{
  "type": "Feature",
  "properties": {
    "gn:admin1_code":"26.0",
    "gn:asciiname":"Xigou",
    "gn:country_code":"CN",
    "gn:dem":1136,
    "gn:feature_class":"P",
    "gn:feature_code":"PPL",
    "gn:name":"Xigou",
    "gn:population":0,
    "gn:timezone":"Asia/Shanghai",
    "iso:country":"CN",
    "name:und_x_variant":[
        "\u897f\u6c9f"
    ],
    "wof:name":"Xigou",
    "wof:placetype":"locality"
},
  "geometry": {"coordinates":[107.96198,33.39457],"type":"Point"}
}