{
  "type": "Feature",
  "properties": {
    "gn:admin1_code":"14.0",
    "gn:asciiname":"Jiakongding",
    "gn:country_code":"CN",
    "gn:dem":3830,
    "gn:feature_class":"P",
    "gn:feature_code":"PPL",
    "gn:name":"Jiakongding",
    "gn:population":0,
    "gn:timezone":"Asia/Urumqi",
    "iso:country":"CN",
    "name:zho_x_preferred":[
        "\u52a0\u7a7a\u9876"
    ],
    "wof:name":"Jiakongding",
    "wof:placetype":"locality"
},
  "geometry": {"coordinates":[98.70269999999999,29.48047],"type":"Point"}
}