{
  "type": "Feature",
  "properties": {
    "gn:admin1_code":"3.0",
    "gn:asciiname":"Dawu Yujia",
    "gn:country_code":"CN",
    "gn:dem":292,
    "gn:feature_class":"P",
    "gn:feature_code":"PPL",
    "gn:name":"Dawu Yujia",
    "gn:population":0,
    "gn:timezone":"Asia/Shanghai",
    "iso:country":"CN",
    "name:und_x_variant":[
        "\u5927\u5c4b\u4f59\u5bb6"
    ],
    "wof:name":"Dawu Yujia",
    "wof:placetype":"locality"
},
  "geometry": {"coordinates":[115.34726000000001,29.55647],"type":"Point"}
}