{
  "type": "Feature",
  "properties": {
    "gn:admin1_code":"12.0",
    "gn:asciiname":"Qianhuling",
    "gn:country_code":"CN",
    "gn:dem":33,
    "gn:feature_class":"P",
    "gn:feature_code":"PPL",
    "gn:name":"Qianhuling",
    "gn:population":0,
    "gn:timezone":"Asia/Shanghai",
    "iso:country":"CN",
    "name:zho_x_preferred":[
        "\u524d\u80e1\u5cad"
    ],
    "wof:name":"Qianhuling",
    "wof:placetype":"locality"
},
  "geometry": {"coordinates":[113.11393,30.41406],"type":"Point"}
}