{
  "type": "Feature",
  "properties": {
    "gn:admin1_code":"10",
    "gn:asciiname":"Dongguan",
    "gn:cc2":"CN",
    "gn:country_code":"CN",
    "gn:dem":7,
    "gn:feature_class":"P",
    "gn:feature_code":"PPL",
    "gn:name":"Dongguan",
    "gn:population":0,
    "gn:timezone":"Asia/Shanghai",
    "iso:country":"CN",
    "name:und_x_variant":[
        "Tung-kuan",
        "Dongguan"
    ],
    "wof:name":"Dongguan",
    "wof:placetype":"locality"
},
  "geometry": {"coordinates":[117.01667,38.21667],"type":"Point"}
}