{
  "type": "Feature",
  "properties": {
    "gn:admin1_code":"32.0",
    "gn:asciiname":"Guanyinge",
    "gn:country_code":"CN",
    "gn:dem":375,
    "gn:feature_class":"P",
    "gn:feature_code":"PPL",
    "gn:name":"Guanyinge",
    "gn:population":0,
    "gn:timezone":"Asia/Shanghai",
    "iso:country":"CN",
    "name:zho_x_preferred":[
        "\u89c2\u97f3\u9601"
    ],
    "wof:name":"Guanyinge",
    "wof:placetype":"locality"
},
  "geometry": {"coordinates":[104.99021999999999,30.75017],"type":"Point"}
}