{
  "type": "Feature",
  "properties": {
    "gn:admin1_code":"26",
    "gn:asciiname":"Caiziping",
    "gn:cc2":"CN",
    "gn:country_code":"CN",
    "gn:dem":1612,
    "gn:feature_class":"P",
    "gn:feature_code":"PPL",
    "gn:name":"Caiziping",
    "gn:population":0,
    "gn:timezone":"Asia/Shanghai",
    "iso:country":"CN",
    "name:und_x_variant":[
        "Ts\u2019ai-tzu-p\u2019ing",
        "Caiziping"
    ],
    "wof:name":"Caiziping",
    "wof:placetype":"locality"
},
  "geometry": {"coordinates":[108.33167,33.74222],"type":"Point"}
}