{
  "type": "Feature",
  "properties": {
    "gn:admin1_code":"24.0",
    "gn:asciiname":"Xinlifang",
    "gn:country_code":"CN",
    "gn:dem":461,
    "gn:feature_class":"P",
    "gn:feature_code":"PPL",
    "gn:name":"Xinlifang",
    "gn:population":0,
    "gn:timezone":"Asia/Shanghai",
    "iso:country":"CN",
    "name:und_x_variant":[
        "\u65b0\u674e\u623f"
    ],
    "wof:name":"Xinlifang",
    "wof:placetype":"locality"
},
  "geometry": {"coordinates":[111.21066999999999,35.31791],"type":"Point"}
}