{
  "type": "Feature",
  "properties": {
    "gn:admin1_code":"24",
    "gn:asciiname":"Buzihui",
    "gn:country_code":"CN",
    "gn:dem":1545,
    "gn:feature_class":"P",
    "gn:feature_code":"PPL",
    "gn:name":"Buzihui",
    "gn:population":0,
    "gn:timezone":"Asia/Shanghai",
    "iso:country":"CN",
    "name:und_x_variant":[
        "Pao-tzu-hui",
        "Buzihui"
    ],
    "name:zho_x_preferred":[
        "\u5821\u5b50\u4f1a"
    ],
    "wof:name":"Buzihui",
    "wof:placetype":"locality"
},
  "geometry": {"coordinates":[112.24839,38.39263],"type":"Point"}
}