{
  "type": "Feature",
  "properties": {
    "gn:admin1_code":"29",
    "gn:asciiname":"Zhedeqing",
    "gn:country_code":"CN",
    "gn:dem":1954,
    "gn:feature_class":"P",
    "gn:feature_code":"PPL",
    "gn:name":"Zhedeqing",
    "gn:population":0,
    "gn:timezone":"Asia/Shanghai",
    "iso:country":"CN",
    "name:zho_x_preferred":[
        "\u8005\u5fb7\u7b90"
    ],
    "wof:name":"Zhedeqing",
    "wof:placetype":"locality"
},
  "geometry": {"coordinates":[102.05665999999999,24.75165],"type":"Point"}
}