{
  "type": "Feature",
  "properties": {
    "gn:admin1_code":"19.0",
    "gn:asciiname":"Maquanzi",
    "gn:country_code":"CN",
    "gn:dem":16,
    "gn:feature_class":"P",
    "gn:feature_code":"PPL",
    "gn:name":"Maquanzi",
    "gn:population":0,
    "gn:timezone":"Asia/Shanghai",
    "iso:country":"CN",
    "name:und_x_variant":[
        "\u9a6c\u5708\u5b50"
    ],
    "wof:name":"Maquanzi",
    "wof:placetype":"locality"
},
  "geometry": {"coordinates":[122.16248,40.25122],"type":"Point"}
}