{
  "type": "Feature",
  "properties": {
    "gn:admin1_code":"05",
    "gn:asciiname":"Yimianshan",
    "gn:cc2":"CN",
    "gn:country_code":"CN",
    "gn:dem":379,
    "gn:feature_class":"P",
    "gn:feature_code":"PPL",
    "gn:name":"Yimianshan",
    "gn:population":0,
    "gn:timezone":"Asia/Shanghai",
    "iso:country":"CN",
    "name:und_x_variant":[
        "I-mien-shan",
        "Yimianshan"
    ],
    "wof:name":"Yimianshan",
    "wof:placetype":"locality"
},
  "geometry": {"coordinates":[125.34972,42.50417],"type":"Point"}
}