{
  "type": "Feature",
  "properties": {
    "gn:admin1_code":"10",
    "gn:asciiname":"Zhenzigou",
    "gn:country_code":"CN",
    "gn:dem":703,
    "gn:feature_class":"P",
    "gn:feature_code":"PPL",
    "gn:name":"Zhenzigou",
    "gn:population":0,
    "gn:timezone":"Asia/Shanghai",
    "iso:country":"CN",
    "name:zho_x_preferred":[
        "\u699b\u5b50\u6c9f"
    ],
    "wof:name":"Zhenzigou",
    "wof:placetype":"locality"
},
  "geometry": {"coordinates":[117.53077,41.23082],"type":"Point"}
}