{
  "type": "Feature",
  "properties": {
    "gn:admin1_code":"2.0",
    "gn:asciiname":"Gaoyang",
    "gn:country_code":"CN",
    "gn:dem":11,
    "gn:feature_class":"P",
    "gn:feature_code":"PPL",
    "gn:name":"Gaoyang",
    "gn:population":0,
    "gn:timezone":"Asia/Shanghai",
    "iso:country":"CN",
    "name:ceb_x_preferred":[
        "Gaoyang"
    ],
    "name:deu_x_preferred":[
        "Gaoyang"
    ],
    "name:fra_x_preferred":[
        "Gaoyang"
    ],
    "name:nor_x_preferred":[
        "Gaoyang"
    ],
    "name:zho_x_preferred":[
        "\u9ad8\u6d0b"
    ],
    "wof:name":"Gaoyang",
    "wof:placetype":"locality"
},
  "geometry": {"coordinates":[121.11977,28.5951],"type":"Point"}
}