{
  "type": "Feature",
  "properties": {
    "gn:admin1_code":"32.0",
    "gn:asciiname":"Rilong'e",
    "gn:country_code":"CN",
    "gn:dem":3198,
    "gn:feature_class":"P",
    "gn:feature_code":"PPL",
    "gn:name":"Rilong\u2019e",
    "gn:population":0,
    "gn:timezone":"Asia/Shanghai",
    "iso:country":"CN",
    "name:und_x_variant":[
        "Rilong\u2019e"
    ],
    "name:zho_x_preferred":[
        "\u65e5\u9647\u4fc4"
    ],
    "wof:name":"Rilong'e",
    "wof:placetype":"locality"
},
  "geometry": {"coordinates":[103.372,33.5746],"type":"Point"}
}