{
  "type": "Feature",
  "properties": {
    "gn:admin1_code":"32.0",
    "gn:asciiname":"Zhengshankou",
    "gn:country_code":"CN",
    "gn:dem":493,
    "gn:feature_class":"P",
    "gn:feature_code":"PPL",
    "gn:name":"Zhengshankou",
    "gn:population":0,
    "gn:timezone":"Asia/Shanghai",
    "iso:country":"CN",
    "name:zho_x_preferred":[
        "\u6b63\u5c71\u53e3"
    ],
    "wof:name":"Zhengshankou",
    "wof:placetype":"locality"
},
  "geometry": {"coordinates":[103.68510999999999,30.17037],"type":"Point"}
}