{
  "type": "Feature",
  "properties": {
    "gn:admin1_code":"5.0",
    "gn:asciiname":"Guanglongcun",
    "gn:country_code":"CN",
    "gn:dem":194,
    "gn:feature_class":"P",
    "gn:feature_code":"PPL",
    "gn:name":"Guanglongcun",
    "gn:population":0,
    "gn:timezone":"Asia/Shanghai",
    "iso:country":"CN",
    "name:zho_x_preferred":[
        "\u5e7f\u9686\u6751"
    ],
    "wof:name":"Guanglongcun",
    "wof:placetype":"locality"
},
  "geometry": {"coordinates":[126.07025,44.8454],"type":"Point"}
}