{
  "type": "Feature",
  "properties": {
    "gn:admin1_code":"26.0",
    "gn:asciiname":"Qishuba",
    "gn:country_code":"CN",
    "gn:dem":946,
    "gn:feature_class":"P",
    "gn:feature_code":"PPLA4",
    "gn:name":"Qishuba",
    "gn:population":0,
    "gn:timezone":"Asia/Shanghai",
    "iso:country":"CN",
    "name:und_x_variant":[
        "\u6f06\u6811\u575d"
    ],
    "wof:name":"Qishuba",
    "wof:placetype":"locality"
},
  "geometry": {"coordinates":[106.59285,32.95795],"type":"Point"}
}