{
  "type": "Feature",
  "properties": {
    "gn:admin1_code":"11",
    "gn:asciiname":"Yalan",
    "gn:country_code":"CN",
    "gn:dem":28,
    "gn:feature_class":"P",
    "gn:feature_code":"PPL",
    "gn:name":"Yalan",
    "gn:population":0,
    "gn:timezone":"Asia/Shanghai",
    "iso:country":"CN",
    "name:tur_x_preferred":[
        "Yalan"
    ],
    "name:zho_x_preferred":[
        "\u9e2d\u680f"
    ],
    "wof:name":"Yalan",
    "wof:placetype":"locality"
},
  "geometry": {"coordinates":[113.3477,29.66424],"type":"Point"}
}