{
  "type": "Feature",
  "properties": {
    "gn:admin1_code":"32.0",
    "gn:asciiname":"Xujiawan",
    "gn:country_code":"CN",
    "gn:dem":352,
    "gn:feature_class":"P",
    "gn:feature_code":"PPL",
    "gn:name":"Xujiawan",
    "gn:population":0,
    "gn:timezone":"Asia/Shanghai",
    "iso:country":"CN",
    "name:zho_x_preferred":[
        "\u80e5\u5bb6\u6e7e"
    ],
    "wof:name":"Xujiawan",
    "wof:placetype":"locality"
},
  "geometry": {"coordinates":[105.99299999999999,31.1154],"type":"Point"}
}