{
  "type": "Feature",
  "properties": {
    "gn:admin1_code":"5.0",
    "gn:asciiname":"Sihe Tun Wopeng",
    "gn:country_code":"CN",
    "gn:dem":168,
    "gn:feature_class":"P",
    "gn:feature_code":"PPL",
    "gn:name":"Sihe Tun Wopeng",
    "gn:population":0,
    "gn:timezone":"Asia/Shanghai",
    "iso:country":"CN",
    "name:zho_x_preferred":[
        "\u56db\u5408\u5c6f\u7a9d\u68da"
    ],
    "wof:name":"Sihe Tun Wopeng",
    "wof:placetype":"locality"
},
  "geometry": {"coordinates":[122.35652,44.56079],"type":"Point"}
}