{
  "type": "Feature",
  "properties": {
    "gn:admin1_code":"12.0",
    "gn:asciiname":"Xiaodangyang",
    "gn:country_code":"CN",
    "gn:dem":1547,
    "gn:feature_class":"P",
    "gn:feature_code":"PPL",
    "gn:name":"Xiaodangyang",
    "gn:population":0,
    "gn:timezone":"Asia/Shanghai",
    "iso:country":"CN",
    "name:zho_x_preferred":[
        "\u5c0f\u5f53\u9633"
    ],
    "wof:name":"Xiaodangyang",
    "wof:placetype":"locality"
},
  "geometry": {"coordinates":[110.08238,31.4513],"type":"Point"}
}