{
  "type": "Feature",
  "properties": {
    "gn:admin1_code":"2.0",
    "gn:asciiname":"Wangjianian",
    "gn:country_code":"CN",
    "gn:dem":92,
    "gn:feature_class":"P",
    "gn:feature_code":"PPL",
    "gn:name":"Wangjianian",
    "gn:population":0,
    "gn:timezone":"Asia/Shanghai",
    "iso:country":"CN",
    "name:zho_x_preferred":[
        "\u738b\u5bb6\u5e74"
    ],
    "wof:name":"Wangjianian",
    "wof:placetype":"locality"
},
  "geometry": {"coordinates":[120.41029,29.56206],"type":"Point"}
}