{
  "type": "Feature",
  "properties": {
    "gn:admin1_code":"11.0",
    "gn:asciiname":"Mapingling",
    "gn:country_code":"CN",
    "gn:dem":96,
    "gn:feature_class":"P",
    "gn:feature_code":"PPL",
    "gn:name":"Mapingling",
    "gn:population":0,
    "gn:timezone":"Asia/Shanghai",
    "iso:country":"CN",
    "name:zho_x_preferred":[
        "\u9a6c\u576a\u5cad"
    ],
    "wof:name":"Mapingling",
    "wof:placetype":"locality"
},
  "geometry": {"coordinates":[111.89496,26.41134000000001],"type":"Point"}
}