{
  "type": "Feature",
  "properties": {
    "gn:admin1_code":"30.0",
    "gn:asciiname":"Xiagong Toushui",
    "gn:country_code":"CN",
    "gn:dem":53,
    "gn:feature_class":"P",
    "gn:feature_code":"PPL",
    "gn:name":"Xiagong Toushui",
    "gn:population":0,
    "gn:timezone":"Asia/Shanghai",
    "iso:country":"CN",
    "name:zho_x_preferred":[
        "\u867e\u516c\u900f\u6c34"
    ],
    "wof:name":"Xiagong Toushui",
    "wof:placetype":"locality"
},
  "geometry": {"coordinates":[112.53061,23.2205],"type":"Point"}
}