{
  "type": "Feature",
  "properties": {
    "gn:admin1_code":"02",
    "gn:asciiname":"Qingxinting",
    "gn:country_code":"CN",
    "gn:dem":5,
    "gn:feature_class":"P",
    "gn:feature_code":"PPL",
    "gn:name":"Qingxinting",
    "gn:population":0,
    "gn:timezone":"Asia/Shanghai",
    "iso:country":"CN",
    "name:und_x_variant":[
        "\u8bf7\u5fc3\u4ead"
    ],
    "wof:name":"Qingxinting",
    "wof:placetype":"locality"
},
  "geometry": {"coordinates":[121.28480999999999,30.22375],"type":"Point"}
}