{
  "type": "Feature",
  "properties": {
    "gn:admin1_code":"1.0",
    "gn:asciiname":"Jinjilong",
    "gn:country_code":"CN",
    "gn:dem":72,
    "gn:feature_class":"P",
    "gn:feature_code":"PPL",
    "gn:name":"Jinjilong",
    "gn:population":0,
    "gn:timezone":"Asia/Shanghai",
    "iso:country":"CN",
    "name:und_x_variant":[
        "\u91d1\u9e21\u9f99"
    ],
    "name:zho_x_preferred":[
        "Jinjilong"
    ],
    "wof:name":"Jinjilong",
    "wof:placetype":"locality"
},
  "geometry": {"coordinates":[119.4816,31.079],"type":"Point"}
}