{
  "type": "Feature",
  "properties": {
    "gn:admin1_code":"25",
    "gn:asciiname":"Fenggezhuang",
    "gn:cc2":"CN",
    "gn:country_code":"CN",
    "gn:dem":65,
    "gn:feature_class":"P",
    "gn:feature_code":"PPL",
    "gn:name":"Fenggezhuang",
    "gn:population":0,
    "gn:timezone":"Asia/Shanghai",
    "iso:country":"CN",
    "name:und_x_variant":[
        "Feng-ko-chuang",
        "Fenggezhuang"
    ],
    "wof:name":"Fenggezhuang",
    "wof:placetype":"locality"
},
  "geometry": {"coordinates":[120.60972,36.91444],"type":"Point"}
}