{
  "type": "Feature",
  "properties": {
    "gn:admin1_code":"7.0",
    "gn:asciiname":"Shang'ao",
    "gn:country_code":"CN",
    "gn:dem":10,
    "gn:feature_class":"P",
    "gn:feature_code":"PPL",
    "gn:name":"Shang\u2019ao",
    "gn:population":0,
    "gn:timezone":"Asia/Shanghai",
    "iso:country":"CN",
    "name:und_x_variant":[
        "Shang\u2019ao"
    ],
    "name:zho_x_preferred":[
        "\u4e0a\u6fb3"
    ],
    "wof:name":"Shang'ao",
    "wof:placetype":"locality"
},
  "geometry": {"coordinates":[119.74713,26.55027],"type":"Point"}
}