{
  "type": "Feature",
  "properties": {
    "gn:admin1_code":"9.0",
    "gn:asciiname":"Gaoji",
    "gn:country_code":"CN",
    "gn:dem":55,
    "gn:feature_class":"P",
    "gn:feature_code":"PPL",
    "gn:name":"Gaoji",
    "gn:population":0,
    "gn:timezone":"Asia/Shanghai",
    "iso:country":"CN",
    "name:zho_x_preferred":[
        "\u9ad8\u96c6"
    ],
    "wof:name":"Gaoji",
    "wof:placetype":"locality"
},
  "geometry": {"coordinates":[114.67274999999999,33.92389],"type":"Point"}
}