{
  "type": "Feature",
  "properties": {
    "gn:admin1_code":"30",
    "gn:asciiname":"Nanqiutang",
    "gn:country_code":"CN",
    "gn:dem":44,
    "gn:feature_class":"P",
    "gn:feature_code":"PPL",
    "gn:name":"Nanqiutang",
    "gn:population":0,
    "gn:timezone":"Asia/Urumqi",
    "iso:country":"CN",
    "name:zho_x_preferred":[
        "\u90a3\u4e18\u5858"
    ],
    "wof:name":"Nanqiutang",
    "wof:placetype":"locality"
},
  "geometry": {"coordinates":[110.08993999999998,21.30515],"type":"Point"}
}