{
  "type": "Feature",
  "properties": {
    "gn:admin1_code":"5.0",
    "gn:asciiname":"Huojiajie",
    "gn:country_code":"CN",
    "gn:dem":341,
    "gn:feature_class":"P",
    "gn:feature_code":"PPL",
    "gn:name":"Huojiajie",
    "gn:population":0,
    "gn:timezone":"Asia/Shanghai",
    "iso:country":"CN",
    "name:zho_x_preferred":[
        "\u970d\u5bb6\u8857"
    ],
    "wof:name":"Huojiajie",
    "wof:placetype":"locality"
},
  "geometry": {"coordinates":[125.72474,42.92986],"type":"Point"}
}