{
  "type": "Feature",
  "properties": {
    "gn:admin1_code":"26.0",
    "gn:asciiname":"Dahecun",
    "gn:country_code":"CN",
    "gn:dem":791,
    "gn:feature_class":"P",
    "gn:feature_code":"PPL",
    "gn:name":"Dahecun",
    "gn:population":0,
    "gn:timezone":"Asia/Shanghai",
    "iso:country":"CN",
    "name:zho_x_preferred":[
        "\u5927\u6cb3\u6751"
    ],
    "wof:name":"Dahecun",
    "wof:placetype":"locality"
},
  "geometry": {"coordinates":[109.47159000000001,33.58624],"type":"Point"}
}