{
  "type": "Feature",
  "properties": {
    "gn:admin1_code":"30.0",
    "gn:asciiname":"Huangbaokengcun",
    "gn:country_code":"CN",
    "gn:dem":13,
    "gn:feature_class":"P",
    "gn:feature_code":"PPL",
    "gn:name":"Huangbaokengcun",
    "gn:population":0,
    "gn:timezone":"Asia/Shanghai",
    "iso:country":"CN",
    "name:zho_x_preferred":[
        "\u9ec4\u5b9d\u5751\u6751"
    ],
    "wof:name":"Huangbaokengcun",
    "wof:placetype":"locality"
},
  "geometry": {"coordinates":[113.00606999999999,22.78308],"type":"Point"}
}