{
  "type": "Feature",
  "properties": {
    "gn:admin1_code":"1.0",
    "gn:asciiname":"Zhengtaicun",
    "gn:country_code":"CN",
    "gn:dem":36,
    "gn:feature_class":"P",
    "gn:feature_code":"PPL",
    "gn:name":"Zhengtaicun",
    "gn:population":0,
    "gn:timezone":"Asia/Shanghai",
    "iso:country":"CN",
    "name:zho_x_preferred":[
        "\u90d1\u53f0\u6751"
    ],
    "wof:name":"Zhengtaicun",
    "wof:placetype":"locality"
},
  "geometry": {"coordinates":[116.98265000000001,34.13193],"type":"Point"}
}