{
  "type": "Feature",
  "properties": {
    "gn:admin1_code":"30.0",
    "gn:asciiname":"Minwei",
    "gn:country_code":"CN",
    "gn:dem":40,
    "gn:feature_class":"P",
    "gn:feature_code":"PPL",
    "gn:name":"Minwei",
    "gn:population":0,
    "gn:timezone":"Asia/Shanghai",
    "iso:country":"CN",
    "name:zho_x_preferred":[
        "\u6c11\u56f4"
    ],
    "wof:name":"Minwei",
    "wof:placetype":"locality"
},
  "geometry": {"coordinates":[112.22271000000001,22.25054],"type":"Point"}
}