{
  "type": "Feature",
  "properties": {
    "gn:admin1_code":"9.0",
    "gn:asciiname":"Liu'ao",
    "gn:country_code":"CN",
    "gn:dem":382,
    "gn:feature_class":"P",
    "gn:feature_code":"PPL",
    "gn:name":"Liu\u2019ao",
    "gn:population":0,
    "gn:timezone":"Asia/Shanghai",
    "iso:country":"CN",
    "name:und_x_variant":[
        "Liu\u2019ao"
    ],
    "name:zho_x_preferred":[
        "\u5218\u51f9"
    ],
    "wof:name":"Liu'ao",
    "wof:placetype":"locality"
},
  "geometry": {"coordinates":[111.55638999999999,33.02441],"type":"Point"}
}