{
  "type": "Feature",
  "properties": {
    "gn:admin1_code":"3.0",
    "gn:asciiname":"Lishang",
    "gn:country_code":"CN",
    "gn:dem":63,
    "gn:feature_class":"P",
    "gn:feature_code":"PPL",
    "gn:name":"Lishang",
    "gn:population":0,
    "gn:timezone":"Asia/Shanghai",
    "iso:country":"CN",
    "name:und_x_variant":[
        "\u529b\u4e0a"
    ],
    "wof:name":"Lishang",
    "wof:placetype":"locality"
},
  "geometry": {"coordinates":[115.21643,27.83523],"type":"Point"}
}