{
  "type": "Feature",
  "properties": {
    "gn:admin1_code":"21",
    "gn:asciiname":"Changtan",
    "gn:country_code":"CN",
    "gn:dem":1177,
    "gn:feature_class":"P",
    "gn:feature_code":"PPL",
    "gn:name":"Changtan",
    "gn:population":0,
    "gn:timezone":"Asia/Shanghai",
    "iso:country":"CN",
    "name:und_x_variant":[
        "Changtan Xiang"
    ],
    "name:zho_x_preferred":[
        "\u957f\u6ee9"
    ],
    "name:zho_x_variant":[
        "\u957f\u6ee9\u4e61"
    ],
    "wof:name":"Changtan",
    "wof:placetype":"locality"
},
  "geometry": {"coordinates":[105.83239,37.53056],"type":"Point"}
}