{
  "type": "Feature",
  "properties": {
    "gn:admin1_code":"12.0",
    "gn:asciiname":"Jiaohuazipo",
    "gn:country_code":"CN",
    "gn:dem":125,
    "gn:feature_class":"P",
    "gn:feature_code":"PPL",
    "gn:name":"Jiaohuazipo",
    "gn:population":0,
    "gn:timezone":"Asia/Shanghai",
    "iso:country":"CN",
    "name:zho_x_preferred":[
        "Jiaohuazipo"
    ],
    "name:zho_x_variant":[
        "\u53eb\u5316\u5b50\u5761"
    ],
    "wof:name":"Jiaohuazipo",
    "wof:placetype":"locality"
},
  "geometry": {"coordinates":[111.43456999999999,30.63776],"type":"Point"}
}