{
  "type": "Feature",
  "properties": {
    "gn:admin1_code":"12.0",
    "gn:asciiname":"Youfanggoukou",
    "gn:country_code":"CN",
    "gn:dem":517,
    "gn:feature_class":"P",
    "gn:feature_code":"PPL",
    "gn:name":"Youfanggoukou",
    "gn:population":0,
    "gn:timezone":"Asia/Shanghai",
    "iso:country":"CN",
    "name:zho_x_preferred":[
        "\u6cb9\u574a\u6c9f\u53e3"
    ],
    "wof:name":"Youfanggoukou",
    "wof:placetype":"locality"
},
  "geometry": {"coordinates":[111.31650999999999,31.76197],"type":"Point"}
}