{
  "type": "Feature",
  "properties": {
    "gn:admin1_code":"29.0",
    "gn:asciiname":"Woma",
    "gn:country_code":"CN",
    "gn:dem":1297,
    "gn:feature_class":"P",
    "gn:feature_code":"PPL",
    "gn:name":"Woma",
    "gn:population":0,
    "gn:timezone":"Asia/Shanghai",
    "iso:country":"CN",
    "name:zho_x_preferred":[
        "\u5367\u9a6c"
    ],
    "wof:name":"Woma",
    "wof:placetype":"locality"
},
  "geometry": {"coordinates":[101.892,22.8897],"type":"Point"}
}