{
  "type": "Feature",
  "properties": {
    "gn:admin1_code":"30",
    "gn:asciiname":"Lizhixu",
    "gn:country_code":"CN",
    "gn:dem":36,
    "gn:feature_class":"P",
    "gn:feature_code":"PPL",
    "gn:name":"Lizhixu",
    "gn:population":0,
    "gn:timezone":"Asia/Urumqi",
    "iso:country":"CN",
    "name:zho_x_preferred":[
        "\u8354\u679d\u5729"
    ],
    "wof:name":"Lizhixu",
    "wof:placetype":"locality"
},
  "geometry": {"coordinates":[110.83062,21.91212],"type":"Point"}
}