{
  "type": "Feature",
  "properties": {
    "gn:admin1_code":"9.0",
    "gn:asciiname":"Yue'erwan",
    "gn:country_code":"CN",
    "gn:dem":50,
    "gn:feature_class":"P",
    "gn:feature_code":"PPL",
    "gn:name":"Yue\u2019erwan",
    "gn:population":0,
    "gn:timezone":"Asia/Shanghai",
    "iso:country":"CN",
    "name:und_x_variant":[
        "Yue\u2019erwan"
    ],
    "name:zho_x_preferred":[
        "\u6708\u513f\u6e7e"
    ],
    "wof:name":"Yue'erwan",
    "wof:placetype":"locality"
},
  "geometry": {"coordinates":[114.58792,32.3179],"type":"Point"}
}