{
  "type": "Feature",
  "properties": {
    "gn:admin1_code":"8.0",
    "gn:asciiname":"Bijiagou",
    "gn:country_code":"CN",
    "gn:dem":176,
    "gn:feature_class":"P",
    "gn:feature_code":"PPL",
    "gn:name":"Bijiagou",
    "gn:population":0,
    "gn:timezone":"Asia/Shanghai",
    "iso:country":"CN",
    "name:zho_x_preferred":[
        "\u6bd5\u5bb6\u6c9f"
    ],
    "wof:name":"Bijiagou",
    "wof:placetype":"locality"
},
  "geometry": {"coordinates":[126.51751000000002,46.85676],"type":"Point"}
}