{
  "type": "Feature",
  "properties": {
    "gn:admin1_code":"1.0",
    "gn:asciiname":"Banmaocao",
    "gn:country_code":"CN",
    "gn:dem":12,
    "gn:feature_class":"P",
    "gn:feature_code":"PPL",
    "gn:name":"Banmaocao",
    "gn:population":0,
    "gn:timezone":"Asia/Shanghai",
    "iso:country":"CN",
    "name:zho_x_preferred":[
        "\u73ed\u6bdb\u8349"
    ],
    "wof:name":"Banmaocao",
    "wof:placetype":"locality"
},
  "geometry": {"coordinates":[118.4089,31.37199],"type":"Point"}
}