{
  "type": "Feature",
  "properties": {
    "iso:country":"CN",
    "name:deu_x_preferred":[
        "Qinglong"
    ],
    "name:gan_x_preferred":[
        "\u9752\u9f99\u6ee1\u65cf\u81ea\u6cbb\u53bf"
    ],
    "name:jpn_x_preferred":[
        "\u9752\u7adc\u6e80\u65cf\u81ea\u6cbb\u770c"
    ],
    "name:nob_x_preferred":[
        "Qinglong"
    ],
    "name:swe_x_preferred":[
        "Qinglong"
    ],
    "name:vie_x_preferred":[
        "Thanh Long"
    ],
    "name:wuu_x_preferred":[
        "\u9752\u9f99\u6ee1\u65cf\u81ea\u6cbb\u53bf"
    ],
    "name:zho_x_preferred":[
        "\u9752\u9f99\u6ee1\u65cf\u81ea\u6cbb\u53bf"
    ],
    "qs:name":"\u9752\u9f99\u6ee1\u65cf\u81ea\u6cbb\u53bf",
    "qs:name_adm0":"\u4e2d\u570b",
    "qs:name_adm1":"\u6cb3\u5317\u7701",
    "qs:photos":50,
    "qs:photos_1k":10,
    "qs:photos_9k":1,
    "qs:photos_9r":3,
    "qs:photos_all":140,
    "qs:photos_sr":2,
    "qs:placetype":"LocalAdmin",
    "qs:pop_sr":"0",
    "wd:wordcount":280,
    "wof:name":"\u9752\u9f99\u6ee1\u65cf\u81ea\u6cbb\u53bf",
    "wof:placetype":"localadmin"
},
  "geometry": {"coordinates":[118.95741599999999,40.406333],"type":"Point"}
}