{
  "type": "Feature",
  "properties": {
    "gn:admin1_code":"7.0",
    "gn:asciiname":"Dadi",
    "gn:country_code":"CN",
    "gn:dem":711,
    "gn:feature_class":"P",
    "gn:feature_code":"PPL",
    "gn:name":"Dadi",
    "gn:population":0,
    "gn:timezone":"Asia/Shanghai",
    "iso:country":"CN",
    "name:ceb_x_preferred":[
        "Dadi"
    ],
    "name:deu_x_preferred":[
        "Dadi"
    ],
    "name:ita_x_preferred":[
        "Dadi"
    ],
    "name:pol_x_preferred":[
        "Dadi"
    ],
    "name:rus_x_preferred":[
        "Dadi"
    ],
    "name:swe_x_preferred":[
        "Dadi"
    ],
    "name:und_x_variant":[
        "\u5927\u5730"
    ],
    "name:zho_x_preferred":[
        "\u5927\u5730"
    ],
    "wof:name":"Dadi",
    "wof:placetype":"locality"
},
  "geometry": {"coordinates":[116.86026,25.67382000000001],"type":"Point"}
}