{
  "type": "Feature",
  "properties": {
    "gn:admin1_code":"9",
    "gn:asciiname":"Songcaiyuan",
    "gn:country_code":"CN",
    "gn:dem":49,
    "gn:feature_class":"P",
    "gn:feature_code":"PPL",
    "gn:name":"Songcaiyuan",
    "gn:population":0,
    "gn:timezone":"Asia/Shanghai",
    "iso:country":"CN",
    "name:zho_x_preferred":[
        "\u5b8b\u83dc\u56ed"
    ],
    "wof:name":"Songcaiyuan",
    "wof:placetype":"locality"
},
  "geometry": {"coordinates":[115.63,34.361],"type":"Point"}
}