{
  "type": "Feature",
  "properties": {
    "gn:admin1_code":"25.0",
    "gn:asciiname":"Guanqiaocun",
    "gn:country_code":"CN",
    "gn:dem":13,
    "gn:feature_class":"P",
    "gn:feature_code":"PPL",
    "gn:name":"Guanqiaocun",
    "gn:population":0,
    "gn:timezone":"Asia/Shanghai",
    "iso:country":"CN",
    "name:zho_x_preferred":[
        "\u5b98\u6865\u6751"
    ],
    "wof:name":"Guanqiaocun",
    "wof:placetype":"locality"
},
  "geometry": {"coordinates":[119.27651000000002,36.79043],"type":"Point"}
}