{
  "type": "Feature",
  "properties": {
    "gn:admin1_code":"30.0",
    "gn:asciiname":"Youguling",
    "gn:country_code":"CN",
    "gn:dem":37,
    "gn:feature_class":"P",
    "gn:feature_code":"PPL",
    "gn:name":"Youguling",
    "gn:population":0,
    "gn:timezone":"Asia/Shanghai",
    "iso:country":"CN",
    "name:zho_x_preferred":[
        "\u6cb9\u53e4\u5cad"
    ],
    "wof:name":"Youguling",
    "wof:placetype":"locality"
},
  "geometry": {"coordinates":[113.81882,22.88918],"type":"Point"}
}