{
  "type": "Feature",
  "properties": {
    "gn:admin1_code":"5.0",
    "gn:asciiname":"Xiangyang",
    "gn:country_code":"CN",
    "gn:dem":100,
    "gn:feature_class":"P",
    "gn:feature_code":"PPL",
    "gn:name":"Xiangyang",
    "gn:population":0,
    "gn:timezone":"Asia/Shanghai",
    "iso:country":"CN",
    "name:und_x_variant":[
        "\u5411\u9633"
    ],
    "wof:name":"Xiangyang",
    "wof:placetype":"locality"
},
  "geometry": {"coordinates":[129.79560000000001,43.01104],"type":"Point"}
}