{
  "type": "Feature",
  "properties": {
    "gn:admin1_code":"3.0",
    "gn:asciiname":"Yunjiang",
    "gn:country_code":"CN",
    "gn:dem":333,
    "gn:feature_class":"P",
    "gn:feature_code":"PPL",
    "gn:name":"Yunjiang",
    "gn:population":0,
    "gn:timezone":"Asia/Shanghai",
    "iso:country":"CN",
    "name:und_x_variant":[
        "\u4e91\u6c5f"
    ],
    "wof:name":"Yunjiang",
    "wof:placetype":"locality"
},
  "geometry": {"coordinates":[114.25388,27.50208],"type":"Point"}
}