{
  "type": "Feature",
  "properties": {
    "gn:admin1_code":"07",
    "gn:asciiname":"Shipaiqian",
    "gn:country_code":"CN",
    "gn:dem":787,
    "gn:feature_class":"P",
    "gn:feature_code":"PPL",
    "gn:name":"Shipaiqian",
    "gn:population":0,
    "gn:timezone":"Asia/Shanghai",
    "iso:country":"CN",
    "name:zho_x_preferred":[
        "\u77f3\u724c\u524d"
    ],
    "wof:name":"Shipaiqian",
    "wof:placetype":"locality"
},
  "geometry": {"coordinates":[117.28667,25.07972],"type":"Point"}
}