{
  "type": "Feature",
  "properties": {
    "gn:admin1_code":"22.0",
    "gn:asciiname":"Songlanbucun",
    "gn:country_code":"CN",
    "gn:dem":42,
    "gn:feature_class":"P",
    "gn:feature_code":"PPL",
    "gn:name":"Songlanbucun",
    "gn:population":0,
    "gn:timezone":"Asia/Shanghai",
    "iso:country":"CN",
    "name:zho_x_preferred":[
        "\u677e\u5170\u5821\u6751"
    ],
    "wof:name":"Songlanbucun",
    "wof:placetype":"locality"
},
  "geometry": {"coordinates":[116.29331000000001,40.1496],"type":"Point"}
}