{
  "type": "Feature",
  "properties": {
    "gn:admin1_code":"11.0",
    "gn:asciiname":"Malinguang",
    "gn:country_code":"CN",
    "gn:dem":902,
    "gn:feature_class":"P",
    "gn:feature_code":"PPL",
    "gn:name":"Malinguang",
    "gn:population":0,
    "gn:timezone":"Asia/Shanghai",
    "iso:country":"CN",
    "name:zho_x_preferred":[
        "\u9a6c\u6797\u5149"
    ],
    "wof:name":"Malinguang",
    "wof:placetype":"locality"
},
  "geometry": {"coordinates":[109.74218999999999,29.60976],"type":"Point"}
}