{
  "type": "Feature",
  "properties": {
    "gn:admin1_code":"20.0",
    "gn:asciiname":"Chengyuanyao",
    "gn:country_code":"CN",
    "gn:dem":1259,
    "gn:feature_class":"P",
    "gn:feature_code":"PPL",
    "gn:name":"Chengyuanyao",
    "gn:population":0,
    "gn:timezone":"Asia/Shanghai",
    "iso:country":"CN",
    "name:und_x_variant":[
        "\u6210\u8fdc\u7a91"
    ],
    "wof:name":"Chengyuanyao",
    "wof:placetype":"locality"
},
  "geometry": {"coordinates":[111.82262,39.97871],"type":"Point"}
}