{
  "type": "Feature",
  "properties": {
    "gn:admin1_code":"4.0",
    "gn:asciiname":"Huabangcun",
    "gn:country_code":"CN",
    "gn:dem":6,
    "gn:feature_class":"P",
    "gn:feature_code":"PPL",
    "gn:name":"Huabangcun",
    "gn:population":0,
    "gn:timezone":"Asia/Shanghai",
    "iso:country":"CN",
    "name:zho_x_preferred":[
        "\u534e\u5e2e\u6751"
    ],
    "wof:name":"Huabangcun",
    "wof:placetype":"locality"
},
  "geometry": {"coordinates":[119.01208,33.97528],"type":"Point"}
}