{
  "type": "Feature",
  "properties": {
    "gn:admin1_code":"29.0",
    "gn:asciiname":"Shangrenhe",
    "gn:country_code":"CN",
    "gn:dem":1394,
    "gn:feature_class":"P",
    "gn:feature_code":"PPL",
    "gn:name":"Shangrenhe",
    "gn:population":0,
    "gn:timezone":"Asia/Shanghai",
    "iso:country":"CN",
    "name:zho_x_preferred":[
        "\u4e0a\u4ec1\u6cb3"
    ],
    "wof:name":"Shangrenhe",
    "wof:placetype":"locality"
},
  "geometry": {"coordinates":[99.0437,24.9795],"type":"Point"}
}