{
  "type": "Feature",
  "properties": {
    "gn:admin1_code":"9.0",
    "gn:asciiname":"Niche",
    "gn:country_code":"CN",
    "gn:dem":80,
    "gn:feature_class":"P",
    "gn:feature_code":"PPL",
    "gn:name":"Niche",
    "gn:population":0,
    "gn:timezone":"Asia/Shanghai",
    "iso:country":"CN",
    "name:aze_x_preferred":[
        "Oyuq"
    ],
    "name:bre_x_preferred":[
        "Kustod"
    ],
    "name:cat_x_preferred":[
        "N\u00ednxol"
    ],
    "name:dan_x_preferred":[
        "Niche"
    ],
    "name:deu_x_preferred":[
        "Nische"
    ],
    "name:fin_x_preferred":[
        "Niche"
    ],
    "name:fra_x_preferred":[
        "Niche"
    ],
    "name:ita_x_preferred":[
        "Nicchia"
    ],
    "name:nld_x_preferred":[
        "Niche"
    ],
    "name:nor_x_preferred":[
        "Nisje"
    ],
    "name:pol_x_preferred":[
        "Nisza"
    ],
    "name:ron_x_preferred":[
        "Ni\u0219\u0103"
    ],
    "name:ukr_x_preferred":[
        "\u041d\u0456\u0448\u0430"
    ],
    "name:zho_x_preferred":[
        "\u6ce5\u8f66"
    ],
    "wof:name":"Niche",
    "wof:placetype":"locality"
},
  "geometry": {"coordinates":[113.54176,33.70679000000001],"type":"Point"}
}