{
  "type": "Feature",
  "properties": {
    "gn:admin1_code":"9",
    "gn:asciiname":"Qianlihai",
    "gn:country_code":"CN",
    "gn:dem":54,
    "gn:feature_class":"P",
    "gn:feature_code":"PPL",
    "gn:name":"Qianlihai",
    "gn:population":0,
    "gn:timezone":"Asia/Shanghai",
    "iso:country":"CN",
    "name:zho_x_preferred":[
        "\u524d\u674e\u6d77"
    ],
    "wof:name":"Qianlihai",
    "wof:placetype":"locality"
},
  "geometry": {"coordinates":[115.33445,35.70379000000001],"type":"Point"}
}