{
  "type": "Feature",
  "properties": {
    "gn:admin1_code":"1.0",
    "gn:asciiname":"Yumiaocun",
    "gn:country_code":"CN",
    "gn:dem":17,
    "gn:feature_class":"P",
    "gn:feature_code":"PPL",
    "gn:name":"Yumiaocun",
    "gn:population":0,
    "gn:timezone":"Asia/Shanghai",
    "iso:country":"CN",
    "name:und_x_variant":[
        "Yumiao"
    ],
    "name:zho_x_preferred":[
        "\u79b9\u5e99\u6751"
    ],
    "wof:name":"Yumiaocun",
    "wof:placetype":"locality"
},
  "geometry": {"coordinates":[117.425,33.18611],"type":"Point"}
}