{
  "type": "Feature",
  "properties": {
    "gn:admin1_code":"14.0",
    "gn:asciiname":"Zinggang",
    "gn:country_code":"CN",
    "gn:dem":4182,
    "gn:feature_class":"P",
    "gn:feature_code":"PPLF",
    "gn:name":"Zinggang",
    "gn:population":0,
    "gn:timezone":"Asia/Urumqi",
    "iso:country":"CN",
    "name:bod_x_preferred":[
        "Zinggang"
    ],
    "name:zho_x_preferred":[
        "Zengga"
    ],
    "name:zho_x_variant":[
        "\u589e\u560e",
        "Zenggalangsuo",
        "\u589e\u560e\u90ce\u6240"
    ],
    "wof:name":"Zinggang",
    "wof:placetype":"locality"
},
  "geometry": {"coordinates":[92.26855,29.05134],"type":"Point"}
}