{
  "type": "Feature",
  "properties": {
    "gn:admin1_code":"3",
    "gn:asciiname":"Xinlongxi",
    "gn:country_code":"CN",
    "gn:dem":76,
    "gn:feature_class":"P",
    "gn:feature_code":"PPL",
    "gn:name":"Xinlongxi",
    "gn:population":0,
    "gn:timezone":"Asia/Shanghai",
    "iso:country":"CN",
    "name:zho_x_preferred":[
        "\u65b0\u9f99\u6eaa"
    ],
    "wof:name":"Xinlongxi",
    "wof:placetype":"locality"
},
  "geometry": {"coordinates":[114.98,26.8534],"type":"Point"}
}