{
  "type": "Feature",
  "properties": {
    "gn:admin1_code":"9.0",
    "gn:asciiname":"Tangyingzi",
    "gn:country_code":"CN",
    "gn:dem":36,
    "gn:feature_class":"P",
    "gn:feature_code":"PPL",
    "gn:name":"Tangyingzi",
    "gn:population":0,
    "gn:timezone":"Asia/Shanghai",
    "iso:country":"CN",
    "name:zho_x_preferred":[
        "\u5510\u8425\u5b50"
    ],
    "wof:name":"Tangyingzi",
    "wof:placetype":"locality"
},
  "geometry": {"coordinates":[115.48728,32.33174],"type":"Point"}
}