{
  "type": "Feature",
  "properties": {
    "gn:admin1_code":"19.0",
    "gn:asciiname":"Baixintai",
    "gn:country_code":"CN",
    "gn:dem":42,
    "gn:feature_class":"P",
    "gn:feature_code":"PPL",
    "gn:name":"Baixintai",
    "gn:population":0,
    "gn:timezone":"Asia/Shanghai",
    "iso:country":"CN",
    "name:und_x_variant":[
        "\u767d\u8f9b\u53f0"
    ],
    "name:zho_x_preferred":[
        "\u767d\u8f9b\u53f0"
    ],
    "wof:name":"Baixintai",
    "wof:placetype":"locality"
},
  "geometry": {"coordinates":[123.3117,41.97002],"type":"Point"}
}