{
  "type": "Feature",
  "properties": {
    "gn:admin1_code":"3",
    "gn:asciiname":"Bailubu",
    "gn:country_code":"CN",
    "gn:dem":37,
    "gn:feature_class":"P",
    "gn:feature_code":"PPL",
    "gn:name":"Bailubu",
    "gn:population":0,
    "gn:timezone":"Asia/Shanghai",
    "iso:country":"CN",
    "name:und_x_variant":[
        "\u767d\u9e7f\u57e0"
    ],
    "wof:name":"Bailubu",
    "wof:placetype":"locality"
},
  "geometry": {"coordinates":[116.88943999999999,28.98306],"type":"Point"}
}