{
  "type": "Feature",
  "properties": {
    "gn:admin1_code":"02",
    "gn:asciiname":"Qianhengcun",
    "gn:country_code":"CN",
    "gn:dem":14,
    "gn:feature_class":"P",
    "gn:feature_code":"PPL",
    "gn:name":"Qianhengcun",
    "gn:population":0,
    "gn:timezone":"Asia/Shanghai",
    "iso:country":"CN",
    "name:und_x_variant":[
        "Ch\u2019ien-heng-ts\u2019un",
        "Qianheng",
        "Qianhengcun"
    ],
    "name:zho_x_preferred":[
        "\u524d\u6a2a"
    ],
    "name:zho_x_variant":[
        "\u524d\u6a2a\u6751"
    ],
    "wof:name":"Qianhengcun",
    "wof:placetype":"locality"
},
  "geometry": {"coordinates":[121.62372000000001,29.2309],"type":"Point"}
}