{
  "type": "Feature",
  "properties": {
    "gn:admin1_code":"32.0",
    "gn:asciiname":"Laochangbu",
    "gn:country_code":"CN",
    "gn:dem":2646,
    "gn:feature_class":"P",
    "gn:feature_code":"PPL",
    "gn:name":"Laochangbu",
    "gn:population":0,
    "gn:timezone":"Asia/Shanghai",
    "iso:country":"CN",
    "name:zho_x_preferred":[
        "\u8001\u573a\u90e8"
    ],
    "wof:name":"Laochangbu",
    "wof:placetype":"locality"
},
  "geometry": {"coordinates":[102.86969000000001,31.39155],"type":"Point"}
}