{
  "type": "Feature",
  "properties": {
    "gn:admin1_code":"32.0",
    "gn:asciiname":"Xiongpu",
    "gn:country_code":"CN",
    "gn:dem":1859,
    "gn:feature_class":"P",
    "gn:feature_code":"PPL",
    "gn:name":"Xiongpu",
    "gn:population":0,
    "gn:timezone":"Asia/Shanghai",
    "iso:country":"CN",
    "name:zho_x_preferred":[
        "\u718a\u666e"
    ],
    "wof:name":"Xiongpu",
    "wof:placetype":"locality"
},
  "geometry": {"coordinates":[102.515,26.486],"type":"Point"}
}