{
  "type": "Feature",
  "properties": {
    "gn:admin1_code":"20.0",
    "gn:asciiname":"Shuiquangou",
    "gn:country_code":"CN",
    "gn:dem":1511,
    "gn:feature_class":"P",
    "gn:feature_code":"PPL",
    "gn:name":"Shuiquangou",
    "gn:population":0,
    "gn:timezone":"Asia/Shanghai",
    "iso:country":"CN",
    "name:und_x_variant":[
        "\u6c34\u6cc9\u6c9f"
    ],
    "wof:name":"Shuiquangou",
    "wof:placetype":"locality"
},
  "geometry": {"coordinates":[109.84859,41.0692],"type":"Point"}
}