{
  "type": "Feature",
  "properties": {
    "gn:admin1_code":"21.0",
    "gn:asciiname":"Jinjiatai",
    "gn:country_code":"CN",
    "gn:dem":1392,
    "gn:feature_class":"P",
    "gn:feature_code":"PPL",
    "gn:name":"Jinjiatai",
    "gn:population":0,
    "gn:timezone":"Asia/Shanghai",
    "iso:country":"CN",
    "name:zho_x_preferred":[
        "\u91d1\u5bb6\u53f0"
    ],
    "wof:name":"Jinjiatai",
    "wof:placetype":"locality"
},
  "geometry": {"coordinates":[106.504,37.2887],"type":"Point"}
}