{
  "type": "Feature",
  "properties": {
    "gn:admin1_code":"25.0",
    "gn:asciiname":"Zhengjiabucun",
    "gn:country_code":"CN",
    "gn:dem":79,
    "gn:feature_class":"P",
    "gn:feature_code":"PPL",
    "gn:name":"Zhengjiabucun",
    "gn:population":0,
    "gn:timezone":"Asia/Shanghai",
    "iso:country":"CN",
    "name:zho_x_preferred":[
        "\u90d1\u5bb6\u57e0\u6751"
    ],
    "wof:name":"Zhengjiabucun",
    "wof:placetype":"locality"
},
  "geometry": {"coordinates":[119.99585999999999,37.19079],"type":"Point"}
}