{
  "type": "Feature",
  "properties": {
    "gn:admin1_code":"25",
    "gn:asciiname":"Dongdaozhuang",
    "gn:country_code":"CN",
    "gn:dem":50,
    "gn:feature_class":"P",
    "gn:feature_code":"PPL",
    "gn:name":"Dongdaozhuang",
    "gn:population":0,
    "gn:timezone":"Asia/Shanghai",
    "iso:country":"CN",
    "name:zho_x_preferred":[
        "\u4e1c\u9053\u5e84"
    ],
    "wof:name":"Dongdaozhuang",
    "wof:placetype":"locality"
},
  "geometry": {"coordinates":[118.20999999999999,34.8628],"type":"Point"}
}