{
  "type": "Feature",
  "properties": {
    "gn:admin1_code":"1.0",
    "gn:asciiname":"Wancuncun",
    "gn:country_code":"CN",
    "gn:dem":46,
    "gn:feature_class":"P",
    "gn:feature_code":"PPL",
    "gn:name":"Wancuncun",
    "gn:population":0,
    "gn:timezone":"Asia/Shanghai",
    "iso:country":"CN",
    "name:zho_x_preferred":[
        "\u4e07\u6751\u6751"
    ],
    "wof:name":"Wancuncun",
    "wof:placetype":"locality"
},
  "geometry": {"coordinates":[118.5675,31.05908],"type":"Point"}
}