{
  "type": "Feature",
  "properties": {
    "gn:admin1_code":"19.0",
    "gn:asciiname":"Qianjiashancun",
    "gn:country_code":"CN",
    "gn:dem":26,
    "gn:feature_class":"P",
    "gn:feature_code":"PPL",
    "gn:name":"Qianjiashancun",
    "gn:population":0,
    "gn:timezone":"Asia/Shanghai",
    "iso:country":"CN",
    "name:zho_x_preferred":[
        "\u524d\u5939\u5c71\u6751"
    ],
    "wof:name":"Qianjiashancun",
    "wof:placetype":"locality"
},
  "geometry": {"coordinates":[121.23103,38.87331],"type":"Point"}
}