{
  "type": "Feature",
  "properties": {
    "gn:admin1_code":"26.0",
    "gn:asciiname":"Dangjiatuncun",
    "gn:country_code":"CN",
    "gn:dem":938,
    "gn:feature_class":"P",
    "gn:feature_code":"PPL",
    "gn:name":"Dangjiatuncun",
    "gn:population":0,
    "gn:timezone":"Asia/Shanghai",
    "iso:country":"CN",
    "name:zho_x_preferred":[
        "\u515a\u5bb6\u5c6f\u6751"
    ],
    "wof:name":"Dangjiatuncun",
    "wof:placetype":"locality"
},
  "geometry": {"coordinates":[109.87036999999999,36.57525],"type":"Point"}
}