{
  "type": "Feature",
  "properties": {
    "gn:admin1_code":"19.0",
    "gn:asciiname":"Heshuntuncun",
    "gn:country_code":"CN",
    "gn:dem":76,
    "gn:feature_class":"P",
    "gn:feature_code":"PPL",
    "gn:name":"Heshuntuncun",
    "gn:population":0,
    "gn:timezone":"Asia/Shanghai",
    "iso:country":"CN",
    "name:zho_x_preferred":[
        "\u548c\u987a\u5c6f\u6751"
    ],
    "wof:name":"Heshuntuncun",
    "wof:placetype":"locality"
},
  "geometry": {"coordinates":[123.90174,42.55242],"type":"Point"}
}