{
  "type": "Feature",
  "properties": {
    "gn:admin1_code":"2.0",
    "gn:asciiname":"Huangliyang",
    "gn:country_code":"CN",
    "gn:dem":58,
    "gn:feature_class":"P",
    "gn:feature_code":"PPL",
    "gn:name":"Huangliyang",
    "gn:population":0,
    "gn:timezone":"Asia/Shanghai",
    "iso:country":"CN",
    "name:und_x_variant":[
        "\u9ec4\u7acb\u579f",
        "Huangliyang"
    ],
    "wof:name":"Huangliyang",
    "wof:placetype":"locality"
},
  "geometry": {"coordinates":[119.51439000000001,29.60826],"type":"Point"}
}