{
  "type": "Feature",
  "properties": {
    "gn:admin1_code":"15.0",
    "gn:asciiname":"Hanjiazhuang",
    "gn:country_code":"CN",
    "gn:dem":1436,
    "gn:feature_class":"P",
    "gn:feature_code":"PPL",
    "gn:name":"Hanjiazhuang",
    "gn:population":0,
    "gn:timezone":"Asia/Shanghai",
    "iso:country":"CN",
    "name:zho_x_preferred":[
        "\u97e9\u5bb6\u5e84"
    ],
    "wof:name":"Hanjiazhuang",
    "wof:placetype":"locality"
},
  "geometry": {"coordinates":[108.182,35.9195],"type":"Point"}
}