{
  "type": "Feature",
  "properties": {
    "gn:admin1_code":"24.0",
    "gn:asciiname":"Hujiagang",
    "gn:country_code":"CN",
    "gn:dem":1156,
    "gn:feature_class":"P",
    "gn:feature_code":"PPL",
    "gn:name":"Hujiagang",
    "gn:population":0,
    "gn:timezone":"Asia/Shanghai",
    "iso:country":"CN",
    "name:zho_x_preferred":[
        "\u62a4\u9a7e\u5c97"
    ],
    "wof:name":"Hujiagang",
    "wof:placetype":"locality"
},
  "geometry": {"coordinates":[113.26828999999999,39.43385],"type":"Point"}
}