{
  "type": "Feature",
  "properties": {
    "gn:admin1_code":"11.0",
    "gn:asciiname":"Huaishubu",
    "gn:country_code":"CN",
    "gn:dem":176,
    "gn:feature_class":"P",
    "gn:feature_code":"PPL",
    "gn:name":"Huaishubu",
    "gn:population":0,
    "gn:timezone":"Asia/Shanghai",
    "iso:country":"CN",
    "name:zho_x_preferred":[
        "\u69d0\u6811\u57e0"
    ],
    "wof:name":"Huaishubu",
    "wof:placetype":"locality"
},
  "geometry": {"coordinates":[113.58105999999999,28.16998],"type":"Point"}
}