{
  "type": "Feature",
  "properties": {
    "gn:admin1_code":"4.0",
    "gn:asciiname":"Gaolaoqiao",
    "gn:country_code":"CN",
    "gn:dem":7,
    "gn:feature_class":"P",
    "gn:feature_code":"PPL",
    "gn:name":"Gaolaoqiao",
    "gn:population":0,
    "gn:timezone":"Asia/Shanghai",
    "iso:country":"CN",
    "name:zho_x_preferred":[
        "\u9ad8\u8001\u6865"
    ],
    "wof:name":"Gaolaoqiao",
    "wof:placetype":"locality"
},
  "geometry": {"coordinates":[119.9312,31.87856],"type":"Point"}
}