{
  "type": "Feature",
  "properties": {
    "gn:admin1_code":"11.0",
    "gn:asciiname":"Wangjia'ao",
    "gn:country_code":"CN",
    "gn:dem":509,
    "gn:feature_class":"P",
    "gn:feature_code":"PPL",
    "gn:name":"Wangjia\u2019ao",
    "gn:population":0,
    "gn:timezone":"Asia/Shanghai",
    "iso:country":"CN",
    "name:und_x_variant":[
        "Wangjia\u2019ao"
    ],
    "name:zho_x_preferred":[
        "\u738b\u5bb6\u5773"
    ],
    "wof:name":"Wangjia'ao",
    "wof:placetype":"locality"
},
  "geometry": {"coordinates":[110.52356,27.40312],"type":"Point"}
}