{
  "type": "Feature",
  "properties": {
    "gn:admin1_code":"19.0",
    "gn:asciiname":"Tongshicun",
    "gn:country_code":"CN",
    "gn:dem":247,
    "gn:feature_class":"P",
    "gn:feature_code":"PPL",
    "gn:name":"Tongshicun",
    "gn:population":0,
    "gn:timezone":"Asia/Shanghai",
    "iso:country":"CN",
    "name:zho_x_preferred":[
        "\u901a\u4ec0\u6751"
    ],
    "wof:name":"Tongshicun",
    "wof:placetype":"locality"
},
  "geometry": {"coordinates":[124.12134,41.6828],"type":"Point"}
}