{
  "type": "Feature",
  "properties": {
    "gn:admin1_code":"7.0",
    "gn:asciiname":"Baiyan Qiancun",
    "gn:country_code":"CN",
    "gn:dem":602,
    "gn:feature_class":"P",
    "gn:feature_code":"PPL",
    "gn:name":"Baiyan Qiancun",
    "gn:population":0,
    "gn:timezone":"Asia/Shanghai",
    "iso:country":"CN",
    "name:zho_x_preferred":[
        "\u767d\u5ca9\u524d\u6751"
    ],
    "wof:name":"Baiyan Qiancun",
    "wof:placetype":"locality"
},
  "geometry": {"coordinates":[117.13523000000001,25.09202],"type":"Point"}
}