{
  "type": "Feature",
  "properties": {
    "gn:admin1_code":"13.0",
    "gn:asciiname":"Bakka",
    "gn:country_code":"CN",
    "gn:dem":496,
    "gn:feature_class":"P",
    "gn:feature_code":"PPL",
    "gn:name":"Bakka",
    "gn:population":0,
    "gn:timezone":"Asia/Urumqi",
    "iso:country":"CN",
    "name:uig_x_preferred":[
        "\u0628\u0627\u0643\u0643\u0627"
    ],
    "name:uig_x_variant":[
        "\u0411\u0430\u043a\u043a\u0430"
    ],
    "name:und_x_variant":[
        "Baka"
    ],
    "name:zho_x_preferred":[
        "\u5df4\u5580"
    ],
    "wof:name":"Bakka",
    "wof:placetype":"locality"
},
  "geometry": {"coordinates":[90.42449000000001,42.98063],"type":"Point"}
}