{
  "type": "Feature",
  "properties": {
    "gn:admin1_code":"8.0",
    "gn:asciiname":"Shuguang",
    "gn:country_code":"CN",
    "gn:dem":151,
    "gn:feature_class":"P",
    "gn:feature_code":"PPL",
    "gn:name":"Shuguang",
    "gn:population":0,
    "gn:timezone":"Asia/Shanghai",
    "iso:country":"CN",
    "name:ceb_x_preferred":[
        "Shuguang"
    ],
    "name:deu_x_preferred":[
        "Shuguang"
    ],
    "name:swe_x_preferred":[
        "Shuguang"
    ],
    "name:zho_x_preferred":[
        "\u66d9\u5149"
    ],
    "wof:name":"Shuguang",
    "wof:placetype":"locality"
},
  "geometry": {"coordinates":[124.79424,47.06371],"type":"Point"}
}