{
  "type": "Feature",
  "properties": {
    "gn:admin1_code":"32.0",
    "gn:asciiname":"Tonglu",
    "gn:country_code":"CN",
    "gn:dem":415,
    "gn:feature_class":"P",
    "gn:feature_code":"PPL",
    "gn:name":"Tongl\u00fc",
    "gn:population":0,
    "gn:timezone":"Asia/Shanghai",
    "iso:country":"CN",
    "name:zho_x_preferred":[
        "\u901a\u65c5"
    ],
    "name:zho_x_variant":[
        "Tongl\u00fc"
    ],
    "wof:name":"Tonglu",
    "wof:placetype":"locality"
},
  "geometry": {"coordinates":[105.07737,30.08873],"type":"Point"}
}