{
  "type": "Feature",
  "properties": {
    "gn:admin1_code":"19.0",
    "gn:asciiname":"Lijia Buzi",
    "gn:country_code":"CN",
    "gn:dem":361,
    "gn:feature_class":"P",
    "gn:feature_code":"PPL",
    "gn:name":"Lijia Buzi",
    "gn:population":0,
    "gn:timezone":"Asia/Shanghai",
    "iso:country":"CN",
    "name:und_x_variant":[
        "Lijiapuzi",
        "\u674e\u5bb6\u5821\u5b50",
        "Lijia Buzi"
    ],
    "wof:name":"Lijia Buzi",
    "wof:placetype":"locality"
},
  "geometry": {"coordinates":[123.16048000000001,40.63731],"type":"Point"}
}