{
  "type": "Feature",
  "properties": {
    "gn:admin1_code":"18",
    "gn:asciiname":"Jiancha",
    "gn:country_code":"CN",
    "gn:dem":800,
    "gn:feature_class":"P",
    "gn:feature_code":"PPLA4",
    "gn:name":"Jiancha",
    "gn:population":0,
    "gn:timezone":"Asia/Shanghai",
    "iso:country":"CN",
    "name:und_x_variant":[
        "Chien-ch\u2019a\u2019-hsi",
        "Jiancha Zhen",
        "Jianchaxi",
        "Jiancha"
    ],
    "name:zho_x_preferred":[
        "\u714e\u8336"
    ],
    "name:zho_x_variant":[
        "\u714e\u8336\u9547",
        "\u714e\u8336\u6eaa"
    ],
    "wof:name":"Jiancha",
    "wof:placetype":"locality"
},
  "geometry": {"coordinates":[107.97230999999999,28.1493],"type":"Point"}
}