{
  "type": "Feature",
  "properties": {
    "gn:admin1_code":"11",
    "gn:asciiname":"Dajiangbian",
    "gn:country_code":"CN",
    "gn:dem":313,
    "gn:feature_class":"P",
    "gn:feature_code":"PPL",
    "gn:name":"Dajiangbian",
    "gn:population":0,
    "gn:timezone":"Asia/Shanghai",
    "iso:country":"CN",
    "name:zho_x_preferred":[
        "\u5927\u6c5f\u8fb9"
    ],
    "wof:name":"Dajiangbian",
    "wof:placetype":"locality"
},
  "geometry": {"coordinates":[111.70038999999998,27.4044],"type":"Point"}
}