{
  "type": "Feature",
  "properties": {
    "gn:admin1_code":"18.0",
    "gn:asciiname":"Zhangjiazhai",
    "gn:country_code":"CN",
    "gn:dem":830,
    "gn:feature_class":"P",
    "gn:feature_code":"PPL",
    "gn:name":"Zhangjiazhai",
    "gn:population":0,
    "gn:timezone":"Asia/Shanghai",
    "iso:country":"CN",
    "wof:name":"Zhangjiazhai",
    "wof:placetype":"locality"
},
  "geometry": {"coordinates":[108.10611000000002,27.98667],"type":"Point"}
}