{
  "type": "Feature",
  "properties": {
    "gn:admin1_code":"12.0",
    "gn:asciiname":"Zengjiayuan",
    "gn:country_code":"CN",
    "gn:dem":803,
    "gn:feature_class":"P",
    "gn:feature_code":"PPL",
    "gn:name":"Zengjiayuan",
    "gn:population":0,
    "gn:timezone":"Asia/Shanghai",
    "iso:country":"CN",
    "name:zho_x_preferred":[
        "\u66fe\u5bb6\u9662"
    ],
    "wof:name":"Zengjiayuan",
    "wof:placetype":"locality"
},
  "geometry": {"coordinates":[111.06605999999999,31.87403],"type":"Point"}
}