{
  "type": "Feature",
  "properties": {
    "gn:admin1_code":"3.0",
    "gn:asciiname":"Tongshukeng",
    "gn:country_code":"CN",
    "gn:dem":227,
    "gn:feature_class":"P",
    "gn:feature_code":"PPL",
    "gn:name":"Tongshukeng",
    "gn:population":0,
    "gn:timezone":"Asia/Shanghai",
    "iso:country":"CN",
    "name:und_x_variant":[
        "\u6850\u6811\u5751"
    ],
    "wof:name":"Tongshukeng",
    "wof:placetype":"locality"
},
  "geometry": {"coordinates":[116.28896,26.23092],"type":"Point"}
}