{
  "type": "Feature",
  "properties": {
    "gn:admin1_code":"18",
    "gn:asciiname":"Tunpo",
    "gn:country_code":"CN",
    "gn:dem":887,
    "gn:feature_class":"P",
    "gn:feature_code":"PPL",
    "gn:name":"Tunpo",
    "gn:population":0,
    "gn:timezone":"Asia/Shanghai",
    "iso:country":"CN",
    "name:zho_x_preferred":[
        "\u5c6f\u5761"
    ],
    "wof:name":"Tunpo",
    "wof:placetype":"locality"
},
  "geometry": {"coordinates":[108.30500000000001,27.2974],"type":"Point"}
}