{
  "type": "Feature",
  "properties": {
    "gn:admin1_code":"18",
    "gn:asciiname":"Dongguantun",
    "gn:country_code":"CN",
    "gn:dem":1440,
    "gn:feature_class":"P",
    "gn:feature_code":"PPL",
    "gn:name":"Dongguantun",
    "gn:population":0,
    "gn:timezone":"Asia/Shanghai",
    "iso:country":"CN",
    "name:zho_x_preferred":[
        "\u8463\u5b98\u5c6f"
    ],
    "wof:name":"Dongguantun",
    "wof:placetype":"locality"
},
  "geometry": {"coordinates":[106.05500000000001,26.3756],"type":"Point"}
}