{
  "type": "Feature",
  "properties": {
    "gn:admin1_code":"26.0",
    "gn:asciiname":"Shangyuanzi",
    "gn:country_code":"CN",
    "gn:dem":554,
    "gn:feature_class":"P",
    "gn:feature_code":"PPL",
    "gn:name":"Shangyuanzi",
    "gn:population":0,
    "gn:timezone":"Asia/Shanghai",
    "iso:country":"CN",
    "name:zho_x_preferred":[
        "\u4e0a\u9662\u5b50"
    ],
    "wof:name":"Shangyuanzi",
    "wof:placetype":"locality"
},
  "geometry": {"coordinates":[109.09695000000001,32.58079],"type":"Point"}
}