{
  "type": "Feature",
  "properties": {
    "gn:admin1_code":"11",
    "gn:asciiname":"Xinwujian",
    "gn:country_code":"CN",
    "gn:dem":127,
    "gn:feature_class":"P",
    "gn:feature_code":"PPL",
    "gn:name":"Xinwujian",
    "gn:population":0,
    "gn:timezone":"Asia/Shanghai",
    "iso:country":"CN",
    "name:zho_x_preferred":[
        "\u65b0\u5c4b\u6da7"
    ],
    "wof:name":"Xinwujian",
    "wof:placetype":"locality"
},
  "geometry": {"coordinates":[112.01756,26.646],"type":"Point"}
}