{
  "type": "Feature",
  "properties": {
    "gn:admin1_code":"19.0",
    "gn:asciiname":"Xiangli",
    "gn:country_code":"CN",
    "gn:dem":267,
    "gn:feature_class":"P",
    "gn:feature_code":"PPL",
    "gn:name":"Xiangli",
    "gn:population":0,
    "gn:timezone":"Asia/Shanghai",
    "iso:country":"CN",
    "name:und_x_variant":[
        "\u76f8\u91cc"
    ],
    "name:zho_x_preferred":[
        "\u76f8\u91cc"
    ],
    "wof:name":"Xiangli",
    "wof:placetype":"locality"
},
  "geometry": {"coordinates":[119.82599999999999,40.5379],"type":"Point"}
}