{
  "type": "Feature",
  "properties": {
    "gn:admin1_code":"9.0",
    "gn:asciiname":"Huzhumiao",
    "gn:country_code":"CN",
    "gn:dem":241,
    "gn:feature_class":"P",
    "gn:feature_code":"PPL",
    "gn:name":"Huzhumiao",
    "gn:population":0,
    "gn:timezone":"Asia/Shanghai",
    "iso:country":"CN",
    "name:zho_x_preferred":[
        "\u6e56\u4f4f\u5e99"
    ],
    "wof:name":"Huzhumiao",
    "wof:placetype":"locality"
},
  "geometry": {"coordinates":[112.25198,33.51206],"type":"Point"}
}