{
  "type": "Feature",
  "properties": {
    "gn:admin1_code":"9.0",
    "gn:asciiname":"Daniuying",
    "gn:country_code":"CN",
    "gn:dem":46,
    "gn:feature_class":"P",
    "gn:feature_code":"PPL",
    "gn:name":"Daniuying",
    "gn:population":0,
    "gn:timezone":"Asia/Shanghai",
    "iso:country":"CN",
    "name:zho_x_preferred":[
        "\u5927\u725b\u8425"
    ],
    "wof:name":"Daniuying",
    "wof:placetype":"locality"
},
  "geometry": {"coordinates":[114.96006,33.50187],"type":"Point"}
}