{
  "type": "Feature",
  "properties": {
    "gn:admin1_code":"8.0",
    "gn:asciiname":"Changshengcun",
    "gn:country_code":"CN",
    "gn:dem":144,
    "gn:feature_class":"P",
    "gn:feature_code":"PPL",
    "gn:name":"Changshengcun",
    "gn:population":0,
    "gn:timezone":"Asia/Shanghai",
    "iso:country":"CN",
    "name:zho_x_preferred":[
        "\u957f\u80dc\u6751"
    ],
    "wof:name":"Changshengcun",
    "wof:placetype":"locality"
},
  "geometry": {"coordinates":[125.17323,46.11376],"type":"Point"}
}