{
  "type": "Feature",
  "properties": {
    "gn:admin1_code":"32.0",
    "gn:asciiname":"Pingfeng",
    "gn:country_code":"CN",
    "gn:dem":276,
    "gn:feature_class":"P",
    "gn:feature_code":"PPL",
    "gn:name":"Pingfeng",
    "gn:population":0,
    "gn:timezone":"Asia/Shanghai",
    "iso:country":"CN",
    "name:zho_x_preferred":[
        "\u5c4f\u5cf0"
    ],
    "wof:name":"Pingfeng",
    "wof:placetype":"locality"
},
  "geometry": {"coordinates":[105.17100000000001,29.0026],"type":"Point"}
}