{
  "type": "Feature",
  "properties": {
    "gn:admin1_code":"29",
    "gn:asciiname":"Mada",
    "gn:country_code":"CN",
    "gn:dem":1871,
    "gn:feature_class":"P",
    "gn:feature_code":"PPL",
    "gn:name":"Mada",
    "gn:population":0,
    "gn:timezone":"Asia/Shanghai",
    "iso:country":"CN",
    "name:fra_x_preferred":[
        "Mada"
    ],
    "name:zho_x_preferred":[
        "\u5417\u8fbe"
    ],
    "wof:name":"Mada",
    "wof:placetype":"locality"
},
  "geometry": {"coordinates":[102.88442999999999,24.14684],"type":"Point"}
}