{
  "type": "Feature",
  "properties": {
    "gn:admin1_code":"8.0",
    "gn:asciiname":"Longyingpan",
    "gn:country_code":"CN",
    "gn:dem":288,
    "gn:feature_class":"P",
    "gn:feature_code":"PPL",
    "gn:name":"Longyingpan",
    "gn:population":0,
    "gn:timezone":"Asia/Shanghai",
    "iso:country":"CN",
    "name:zho_x_preferred":[
        "\u9f99\u8425\u76d8"
    ],
    "wof:name":"Longyingpan",
    "wof:placetype":"locality"
},
  "geometry": {"coordinates":[127.33996,45.59575],"type":"Point"}
}