{
  "type": "Feature",
  "properties": {
    "gn:admin1_code":"26.0",
    "gn:asciiname":"Heiwan",
    "gn:country_code":"CN",
    "gn:dem":940,
    "gn:feature_class":"P",
    "gn:feature_code":"PPL",
    "gn:name":"Heiwan",
    "gn:population":0,
    "gn:timezone":"Asia/Shanghai",
    "iso:country":"CN",
    "name:und_x_variant":[
        "\u9ed1\u6e7e"
    ],
    "wof:name":"Heiwan",
    "wof:placetype":"locality"
},
  "geometry": {"coordinates":[108.01714,33.28744],"type":"Point"}
}