{
  "type": "Feature",
  "properties": {
    "gn:admin1_code":"13.0",
    "gn:asciiname":"Ergaizi Maili",
    "gn:country_code":"CN",
    "gn:dem":1340,
    "gn:feature_class":"P",
    "gn:feature_code":"PPL",
    "gn:name":"Ergaizi Maili",
    "gn:population":0,
    "gn:timezone":"Asia/Shanghai",
    "iso:country":"CN",
    "name:zho_x_preferred":[
        "\u513f\u76d6\u5b5c\u4e70\u91cc"
    ],
    "wof:name":"Ergaizi Maili",
    "wof:placetype":"locality"
},
  "geometry": {"coordinates":[79.85211,37.16986],"type":"Point"}
}