{
  "type": "Feature",
  "properties": {
    "gn:admin1_code":"8.0",
    "gn:asciiname":"Luanxigui",
    "gn:country_code":"CN",
    "gn:dem":187,
    "gn:feature_class":"P",
    "gn:feature_code":"PPL",
    "gn:name":"Luanxigui",
    "gn:population":0,
    "gn:timezone":"Asia/Shanghai",
    "iso:country":"CN",
    "name:zho_x_preferred":[
        "\u683e\u559c\u8d35"
    ],
    "wof:name":"Luanxigui",
    "wof:placetype":"locality"
},
  "geometry": {"coordinates":[127.16218000000001,46.37019],"type":"Point"}
}