{
  "type": "Feature",
  "properties": {
    "gn:admin1_code":"2.0",
    "gn:asciiname":"Wangsizhou",
    "gn:country_code":"CN",
    "gn:dem":74,
    "gn:feature_class":"P",
    "gn:feature_code":"PPL",
    "gn:name":"Wangsizhou",
    "gn:population":0,
    "gn:timezone":"Asia/Shanghai",
    "iso:country":"CN",
    "name:zho_x_preferred":[
        "\u738b\u6cd7\u6d32"
    ],
    "wof:name":"Wangsizhou",
    "wof:placetype":"locality"
},
  "geometry": {"coordinates":[120.96029,29.47235],"type":"Point"}
}