{
  "type": "Feature",
  "properties": {
    "gn:admin1_code":"24.0",
    "gn:asciiname":"Wujiayaocun",
    "gn:country_code":"CN",
    "gn:dem":1283,
    "gn:feature_class":"P",
    "gn:feature_code":"PPL",
    "gn:name":"Wujiayaocun",
    "gn:population":0,
    "gn:timezone":"Asia/Shanghai",
    "iso:country":"CN",
    "name:zho_x_preferred":[
        "\u90ac\u5bb6\u7a91\u6751"
    ],
    "wof:name":"Wujiayaocun",
    "wof:placetype":"locality"
},
  "geometry": {"coordinates":[114.25147,40.39567],"type":"Point"}
}