{
  "type": "Feature",
  "properties": {
    "gn:admin1_code":"1.0",
    "gn:asciiname":"Le'an",
    "gn:country_code":"CN",
    "gn:dem":10,
    "gn:feature_class":"P",
    "gn:feature_code":"PPL",
    "gn:name":"Le\u2019an",
    "gn:population":0,
    "gn:timezone":"Asia/Shanghai",
    "iso:country":"CN",
    "name:zho_x_preferred":[
        "Le\u2019an"
    ],
    "name:zho_x_variant":[
        "\u4e50\u5b89"
    ],
    "wof:name":"Le'an",
    "wof:placetype":"locality"
},
  "geometry": {"coordinates":[118.39966,30.92407],"type":"Point"}
}