{
  "type": "Feature",
  "properties": {
    "gn:admin1_code":"18",
    "gn:asciiname":"Fengdong",
    "gn:country_code":"CN",
    "gn:dem":1411,
    "gn:feature_class":"P",
    "gn:feature_code":"PPL",
    "gn:name":"Fengdong",
    "gn:population":0,
    "gn:timezone":"Asia/Shanghai",
    "iso:country":"CN",
    "name:zho_x_preferred":[
        "\u5cf0\u6d1e"
    ],
    "wof:name":"Fengdong",
    "wof:placetype":"locality"
},
  "geometry": {"coordinates":[105.229,25.4371],"type":"Point"}
}