{
  "type": "Feature",
  "properties": {
    "gn:admin1_code":"2.0",
    "gn:asciiname":"Dianlai",
    "gn:country_code":"CN",
    "gn:dem":53,
    "gn:feature_class":"P",
    "gn:feature_code":"PPL",
    "gn:name":"Dianlai",
    "gn:population":0,
    "gn:timezone":"Asia/Shanghai",
    "iso:country":"CN",
    "name:und_x_variant":[
        "\u5e97\u6765",
        "Dianlai"
    ],
    "wof:name":"Dianlai",
    "wof:placetype":"locality"
},
  "geometry": {"coordinates":[119.96075,29.45194],"type":"Point"}
}