{
  "type": "Feature",
  "properties": {
    "gn:admin1_code":"23.0",
    "gn:asciiname":"Yuejin Nongchang",
    "gn:country_code":"CN",
    "gn:dem":3,
    "gn:feature_class":"P",
    "gn:feature_code":"PPLF",
    "gn:name":"Yuejin Nongchang",
    "gn:population":0,
    "gn:timezone":"Asia/Shanghai",
    "iso:country":"CN",
    "name:und_x_variant":[
        "Yuejin",
        "Yuejin Nongchang"
    ],
    "wof:name":"Yuejin Nongchang",
    "wof:placetype":"locality"
},
  "geometry": {"coordinates":[121.2375,31.81778],"type":"Point"}
}