{
  "type": "Feature",
  "properties": {
    "gn:admin1_code":"30.0",
    "gn:asciiname":"Chang'anxu",
    "gn:country_code":"CN",
    "gn:dem":29,
    "gn:feature_class":"P",
    "gn:feature_code":"PPL",
    "gn:name":"Chang\u2019anxu",
    "gn:population":0,
    "gn:timezone":"Asia/Shanghai",
    "iso:country":"CN",
    "name:zho_x_preferred":[
        "\u957f\u5b89\u5729"
    ],
    "name:zho_x_variant":[
        "Chang\u2019anxu"
    ],
    "wof:name":"Chang'anxu",
    "wof:placetype":"locality"
},
  "geometry": {"coordinates":[114.00413,22.84066],"type":"Point"}
}