{
  "type": "Feature",
  "properties": {
    "gn:admin1_code":"7.0",
    "gn:asciiname":"Lanjiadi",
    "gn:country_code":"CN",
    "gn:dem":335,
    "gn:feature_class":"P",
    "gn:feature_code":"PPL",
    "gn:name":"Lanjiadi",
    "gn:population":0,
    "gn:timezone":"Asia/Shanghai",
    "iso:country":"CN",
    "name:zho_x_preferred":[
        "\u5170\u5bb6\u5730"
    ],
    "wof:name":"Lanjiadi",
    "wof:placetype":"locality"
},
  "geometry": {"coordinates":[116.17098,25.30827],"type":"Point"}
}