{
  "type": "Feature",
  "properties": {
    "gn:admin1_code":"3.0",
    "gn:asciiname":"Zhangling",
    "gn:country_code":"CN",
    "gn:dem":172,
    "gn:feature_class":"P",
    "gn:feature_code":"PPL",
    "gn:name":"Zhangling",
    "gn:population":0,
    "gn:timezone":"Asia/Shanghai",
    "iso:country":"CN",
    "name:zho_x_preferred":[
        "\u5f20\u5cad"
    ],
    "wof:name":"Zhangling",
    "wof:placetype":"locality"
},
  "geometry": {"coordinates":[118.15900000000001,28.8547],"type":"Point"}
}