{
  "type": "Feature",
  "properties": {
    "gn:admin1_code":"24",
    "gn:asciiname":"Qinglancun",
    "gn:country_code":"CN",
    "gn:dem":728,
    "gn:feature_class":"P",
    "gn:feature_code":"PPL",
    "gn:name":"Qinglancun",
    "gn:population":0,
    "gn:timezone":"Asia/Shanghai",
    "iso:country":"CN",
    "name:und_x_variant":[
        "Ch\u2019ing-lan",
        "Ch\u2019ing-lan-ts\u2019un",
        "Qinglan",
        "Qinglancun"
    ],
    "name:zho_x_preferred":[
        "\u6674\u5c9a\u6751"
    ],
    "wof:name":"Qinglancun",
    "wof:placetype":"locality"
},
  "geometry": {"coordinates":[111.23088,34.9511],"type":"Point"}
}