{
  "type": "Feature",
  "properties": {
    "gn:admin1_code":"18",
    "gn:asciiname":"Nalongtian",
    "gn:country_code":"CN",
    "gn:dem":1159,
    "gn:feature_class":"P",
    "gn:feature_code":"PPL",
    "gn:name":"Nalongtian",
    "gn:population":0,
    "gn:timezone":"Asia/Shanghai",
    "iso:country":"CN",
    "name:zho_x_preferred":[
        "\u7eb3\u9647\u7530"
    ],
    "wof:name":"Nalongtian",
    "wof:placetype":"locality"
},
  "geometry": {"coordinates":[105.291,25.0841],"type":"Point"}
}