{
  "type": "Feature",
  "properties": {
    "gn:admin1_code":"20",
    "gn:asciiname":"Qianming",
    "gn:cc2":"CN",
    "gn:country_code":"CN",
    "gn:dem":1006,
    "gn:feature_class":"P",
    "gn:feature_code":"PPL",
    "gn:name":"Qianming",
    "gn:population":0,
    "gn:timezone":"Asia/Shanghai",
    "iso:country":"CN",
    "name:und_x_variant":[
        "Qianming Xiang",
        "Qianming"
    ],
    "wof:name":"Qianming",
    "wof:placetype":"locality"
},
  "geometry": {"coordinates":[109.97333,40.545],"type":"Point"}
}