{
  "type": "Feature",
  "properties": {
    "gn:admin1_code":"3",
    "gn:asciiname":"Tantouxu",
    "gn:country_code":"CN",
    "gn:dem":163,
    "gn:feature_class":"P",
    "gn:feature_code":"PPL",
    "gn:name":"Tantouxu",
    "gn:population":0,
    "gn:timezone":"Asia/Shanghai",
    "iso:country":"CN",
    "wof:name":"Tantouxu",
    "wof:placetype":"locality"
},
  "geometry": {"coordinates":[115.50972,25.94528],"type":"Point"}
}