{
  "type": "Feature",
  "properties": {
    "gn:admin1_code":"12.0",
    "gn:asciiname":"Lishutu",
    "gn:country_code":"CN",
    "gn:dem":703,
    "gn:feature_class":"P",
    "gn:feature_code":"PPL",
    "gn:name":"Lishutu",
    "gn:population":0,
    "gn:timezone":"Asia/Shanghai",
    "iso:country":"CN",
    "name:zho_x_preferred":[
        "\u68a8\u6811\u51f8"
    ],
    "wof:name":"Lishutu",
    "wof:placetype":"locality"
},
  "geometry": {"coordinates":[111.56046000000001,31.5651],"type":"Point"}
}