{
  "type": "Feature",
  "properties": {
    "gn:admin1_code":"2.0",
    "gn:asciiname":"Hangtou",
    "gn:country_code":"CN",
    "gn:dem":340,
    "gn:feature_class":"P",
    "gn:feature_code":"PPL",
    "gn:name":"Hangtou",
    "gn:population":0,
    "gn:timezone":"Asia/Shanghai",
    "iso:country":"CN",
    "name:zho_x_preferred":[
        "\u822a\u5934"
    ],
    "wof:name":"Hangtou",
    "wof:placetype":"locality"
},
  "geometry": {"coordinates":[119.40022999999999,28.61066],"type":"Point"}
}