{
  "type": "Feature",
  "properties": {
    "gn:admin1_code":"14.0",
    "gn:asciiname":"Dajiacun",
    "gn:country_code":"CN",
    "gn:dem":4005,
    "gn:feature_class":"P",
    "gn:feature_code":"PPL",
    "gn:name":"Dajiacun",
    "gn:population":0,
    "gn:timezone":"Asia/Urumqi",
    "iso:country":"CN",
    "name:zho_x_preferred":[
        "\u8fbe\u52a0\u6751"
    ],
    "wof:name":"Dajiacun",
    "wof:placetype":"locality"
},
  "geometry": {"coordinates":[93.80359,31.50274000000001],"type":"Point"}
}