{
  "type": "Feature",
  "properties": {
    "gn:admin1_code":"31.0",
    "gn:asciiname":"Longfashan",
    "gn:country_code":"CN",
    "gn:dem":13,
    "gn:feature_class":"P",
    "gn:feature_code":"PPL",
    "gn:name":"Longfashan",
    "gn:population":0,
    "gn:timezone":"Asia/Shanghai",
    "iso:country":"CN",
    "name:zho_x_preferred":[
        "Longfashan"
    ],
    "name:zho_x_variant":[
        "\u9f99\u53d1\u5c71"
    ],
    "wof:name":"Longfashan",
    "wof:placetype":"locality"
},
  "geometry": {"coordinates":[110.60823000000001,19.85015],"type":"Point"}
}