{
  "type": "Feature",
  "properties": {
    "gn:admin1_code":"14.0",
    "gn:asciiname":"Xiayaduo",
    "gn:country_code":"CN",
    "gn:dem":4201,
    "gn:feature_class":"P",
    "gn:feature_code":"PPL",
    "gn:name":"Xiayaduo",
    "gn:population":0,
    "gn:timezone":"Asia/Urumqi",
    "iso:country":"CN",
    "name:zho_x_preferred":[
        "\u4e0b\u7259\u591a"
    ],
    "wof:name":"Xiayaduo",
    "wof:placetype":"locality"
},
  "geometry": {"coordinates":[97.91645,31.30829],"type":"Point"}
}