{
  "type": "Feature",
  "properties": {
    "gn:admin1_code":"4.0",
    "gn:asciiname":"Hongzhuangcun",
    "gn:country_code":"CN",
    "gn:dem":27,
    "gn:feature_class":"P",
    "gn:feature_code":"PPL",
    "gn:name":"Hongzhuangcun",
    "gn:population":0,
    "gn:timezone":"Asia/Shanghai",
    "iso:country":"CN",
    "name:und_x_variant":[
        "\u6d2a\u5e84\u6751"
    ],
    "wof:name":"Hongzhuangcun",
    "wof:placetype":"locality"
},
  "geometry": {"coordinates":[118.60107000000001,34.47052],"type":"Point"}
}