{
  "type": "Feature",
  "properties": {
    "gn:admin1_code":"18",
    "gn:asciiname":"Jinzhong",
    "gn:cc2":"CN",
    "gn:country_code":"CN",
    "gn:dem":2126,
    "gn:feature_class":"P",
    "gn:feature_code":"PPL",
    "gn:name":"Jinzhong",
    "gn:population":0,
    "gn:timezone":"Asia/Shanghai",
    "iso:country":"CN",
    "name:und_x_variant":[
        "Chin-chung",
        "Jinzhong"
    ],
    "wof:name":"Jinzhong",
    "wof:placetype":"locality"
},
  "geometry": {"coordinates":[104.43333,26.76667],"type":"Point"}
}