{
  "type": "Feature",
  "properties": {
    "gn:admin1_code":"26",
    "gn:asciiname":"Songjiashan",
    "gn:country_code":"CN",
    "gn:dem":773,
    "gn:feature_class":"P",
    "gn:feature_code":"PPL",
    "gn:name":"Songjiashan",
    "gn:population":0,
    "gn:timezone":"Asia/Shanghai",
    "iso:country":"CN",
    "name:zho_x_preferred":[
        "\u5b8b\u5bb6\u5c71"
    ],
    "wof:name":"Songjiashan",
    "wof:placetype":"locality"
},
  "geometry": {"coordinates":[108.60138999999999,34.68333],"type":"Point"}
}