{
  "type": "Feature",
  "properties": {
    "gn:admin1_code":"30.0",
    "gn:asciiname":"Daling",
    "gn:country_code":"CN",
    "gn:dem":115,
    "gn:feature_class":"P",
    "gn:feature_code":"PPL",
    "gn:name":"Daling",
    "gn:population":0,
    "gn:timezone":"Asia/Shanghai",
    "iso:country":"CN",
    "name:ara_x_preferred":[
        "\u062f\u0627\u0644\u064a\u0646\u063a"
    ],
    "name:ben_x_preferred":[
        "\u09a6\u09be\u09b2\u09bf\u0982"
    ],
    "name:ceb_x_preferred":[
        "Daling"
    ],
    "name:deu_x_preferred":[
        "Daling"
    ],
    "name:ell_x_preferred":[
        "\u039d\u03c4\u03ac\u03bb\u03b9\u03bd\u03b3\u03ba"
    ],
    "name:fas_x_preferred":[
        "\u062f\u0627\u0644\u06cc\u0646\u06af"
    ],
    "name:fra_x_preferred":[
        "Daling"
    ],
    "name:heb_x_preferred":[
        "\u05d3\u05d0\u05dc\u05d9\u05e0\u05d2"
    ],
    "name:hin_x_preferred":[
        "\u0921\u093e\u0932\u093f\u0902\u0917"
    ],
    "name:hun_x_preferred":[
        "Daling"
    ],
    "name:ind_x_preferred":[
        "Daling"
    ],
    "name:ita_x_preferred":[
        "Daling"
    ],
    "name:nld_x_preferred":[
        "Daling"
    ],
    "name:pol_x_preferred":[
        "Daling"
    ],
    "name:por_x_preferred":[
        "Daling"
    ],
    "name:spa_x_preferred":[
        "Daling"
    ],
    "name:swe_x_preferred":[
        "Daling"
    ],
    "name:tur_x_preferred":[
        "Daling"
    ],
    "name:ukr_x_preferred":[
        "\u0414\u0430\u043b\u0456\u043d\u0433"
    ],
    "name:urd_x_preferred":[
        "\u0688\u0627\u0644\u0646\u06af"
    ],
    "name:vie_x_preferred":[
        "S\u00f4ng Daling"
    ],
    "name:zho_x_preferred":[
        "\u5927\u5cad"
    ],
    "wof:name":"Daling",
    "wof:placetype":"locality"
},
  "geometry": {"coordinates":[111.69681,23.2874],"type":"Point"}
}