{
  "type": "Feature",
  "properties": {
    "gn:admin1_code":"10.0",
    "gn:asciiname":"Zhangmo",
    "gn:cc2":"CN",
    "gn:country_code":"CN",
    "gn:dem":369,
    "gn:feature_class":"P",
    "gn:feature_code":"PPL",
    "gn:name":"Zhangmo",
    "gn:population":0,
    "gn:timezone":"Asia/Shanghai",
    "iso:country":"CN",
    "name:und_x_variant":[
        "Chang-mo",
        "Zhangmo"
    ],
    "wof:name":"Zhangmo",
    "wof:placetype":"locality"
},
  "geometry": {"coordinates":[114.20583000000001,37.35],"type":"Point"}
}