{
  "type": "Feature",
  "properties": {
    "gn:admin1_code":"26.0",
    "gn:asciiname":"Chenjia Goucun",
    "gn:country_code":"CN",
    "gn:dem":903,
    "gn:feature_class":"P",
    "gn:feature_code":"PPL",
    "gn:name":"Chenjia Goucun",
    "gn:population":0,
    "gn:timezone":"Asia/Shanghai",
    "iso:country":"CN",
    "name:zho_x_preferred":[
        "\u9648\u5bb6\u6c9f\u6751"
    ],
    "wof:name":"Chenjia Goucun",
    "wof:placetype":"locality"
},
  "geometry": {"coordinates":[110.44499999999999,37.9277],"type":"Point"}
}