{
  "type": "Feature",
  "properties": {
    "gn:admin1_code":"2.0",
    "gn:asciiname":"Gongshan",
    "gn:country_code":"CN",
    "gn:dem":953,
    "gn:feature_class":"P",
    "gn:feature_code":"PPL",
    "gn:name":"Gongshan",
    "gn:population":0,
    "gn:timezone":"Asia/Shanghai",
    "iso:country":"CN",
    "name:zho_x_preferred":[
        "\u4f9b\u5c71"
    ],
    "wof:name":"Gongshan",
    "wof:placetype":"locality"
},
  "geometry": {"coordinates":[119.26566,28.05526],"type":"Point"}
}