{
  "type": "Feature",
  "properties": {
    "gn:admin1_code":"25.0",
    "gn:asciiname":"Ta'ertou",
    "gn:country_code":"CN",
    "gn:dem":136,
    "gn:feature_class":"P",
    "gn:feature_code":"PPL",
    "gn:name":"Ta\u2019ertou",
    "gn:population":0,
    "gn:timezone":"Asia/Shanghai",
    "iso:country":"CN",
    "name:und_x_variant":[
        "Ta\u2019ertou"
    ],
    "name:zho_x_preferred":[
        "\u5854\u8033\u5934"
    ],
    "wof:name":"Ta'ertou",
    "wof:placetype":"locality"
},
  "geometry": {"coordinates":[120.19656000000001,37.10704000000001],"type":"Point"}
}