{
  "type": "Feature",
  "properties": {
    "gn:admin1_code":"33.0",
    "gn:asciiname":"Jintang",
    "gn:country_code":"CN",
    "gn:dem":782,
    "gn:feature_class":"P",
    "gn:feature_code":"PPL",
    "gn:name":"Jintang",
    "gn:population":0,
    "gn:timezone":"Asia/Shanghai",
    "iso:country":"CN",
    "name:ceb_x_preferred":[
        "Jintang"
    ],
    "name:deu_x_preferred":[
        "Jintang"
    ],
    "name:rus_x_preferred":[
        "\u0426\u0437\u0438\u043d\u044c\u0442\u0430\u043d"
    ],
    "name:zho_x_preferred":[
        "\u91d1\u5858"
    ],
    "wof:name":"Jintang",
    "wof:placetype":"locality"
},
  "geometry": {"coordinates":[108.61393,29.42114],"type":"Point"}
}