{
  "type": "Feature",
  "properties": {
    "gn:admin1_code":"11",
    "gn:asciiname":"Qiutianpu",
    "gn:country_code":"CN",
    "gn:dem":444,
    "gn:feature_class":"P",
    "gn:feature_code":"PPL",
    "gn:name":"Qiutianpu",
    "gn:population":0,
    "gn:timezone":"Asia/Shanghai",
    "iso:country":"CN",
    "name:zho_x_preferred":[
        "\u79cb\u7530\u94fa"
    ],
    "wof:name":"Qiutianpu",
    "wof:placetype":"locality"
},
  "geometry": {"coordinates":[111.00946,27.44238],"type":"Point"}
}