{
  "type": "Feature",
  "properties": {
    "gn:admin1_code":"26.0",
    "gn:asciiname":"Guojiaba",
    "gn:country_code":"CN",
    "gn:dem":1368,
    "gn:feature_class":"P",
    "gn:feature_code":"PPL",
    "gn:name":"Guojiaba",
    "gn:population":0,
    "gn:timezone":"Asia/Shanghai",
    "iso:country":"CN",
    "name:und_x_variant":[
        "\u90ed\u5bb6\u575d"
    ],
    "wof:name":"Guojiaba",
    "wof:placetype":"locality"
},
  "geometry": {"coordinates":[107.24373,33.75905],"type":"Point"}
}