{
  "type": "Feature",
  "properties": {
    "gn:admin1_code":"29.0",
    "gn:asciiname":"Luoqiu",
    "gn:country_code":"CN",
    "gn:dem":2105,
    "gn:feature_class":"P",
    "gn:feature_code":"PPL",
    "gn:name":"Luoqiu",
    "gn:population":0,
    "gn:timezone":"Asia/Shanghai",
    "iso:country":"CN",
    "name:und_x_variant":[
        "\u9a86\u5775"
    ],
    "wof:name":"Luoqiu",
    "wof:placetype":"locality"
},
  "geometry": {"coordinates":[103.42055999999999,27.69776],"type":"Point"}
}