{
  "type": "Feature",
  "properties": {
    "gn:admin1_code":"22",
    "gn:asciiname":"Xibozi",
    "gn:cc2":"CN",
    "gn:country_code":"CN",
    "gn:dem":669,
    "gn:feature_class":"P",
    "gn:feature_code":"PPL",
    "gn:name":"Xibozi",
    "gn:population":0,
    "gn:timezone":"Asia/Shanghai",
    "iso:country":"CN",
    "name:und_x_variant":[
        "Hsi-po-tzu",
        "Xibozi"
    ],
    "wof:name":"Xibozi",
    "wof:placetype":"locality"
},
  "geometry": {"coordinates":[115.99583,40.35417],"type":"Point"}
}