{
  "type": "Feature",
  "properties": {
    "gn:admin1_code":"11",
    "gn:asciiname":"Zhujiaqiao",
    "gn:country_code":"CN",
    "gn:dem":87,
    "gn:feature_class":"P",
    "gn:feature_code":"PPL",
    "gn:name":"Zhujiaqiao",
    "gn:population":0,
    "gn:timezone":"Asia/Shanghai",
    "iso:country":"CN",
    "name:zho_x_preferred":[
        "\u682a\u5bb6\u6865"
    ],
    "wof:name":"Zhujiaqiao",
    "wof:placetype":"locality"
},
  "geometry": {"coordinates":[113.31657,28.17969],"type":"Point"}
}