{
  "type": "Feature",
  "properties": {
    "gn:admin1_code":"4.0",
    "gn:asciiname":"Qizicun",
    "gn:country_code":"CN",
    "gn:dem":2,
    "gn:feature_class":"P",
    "gn:feature_code":"PPL",
    "gn:name":"Qizicun",
    "gn:population":0,
    "gn:timezone":"Asia/Shanghai",
    "iso:country":"CN",
    "name:zho_x_preferred":[
        "\u4e03\u5b50\u6751"
    ],
    "wof:name":"Qizicun",
    "wof:placetype":"locality"
},
  "geometry": {"coordinates":[120.10107000000001,32.87512],"type":"Point"}
}