{
  "type": "Feature",
  "properties": {
    "gn:admin1_code":"21.0",
    "gn:asciiname":"Baozishan",
    "gn:country_code":"CN",
    "gn:dem":2104,
    "gn:feature_class":"P",
    "gn:feature_code":"PPL",
    "gn:name":"Baozishan",
    "gn:population":0,
    "gn:timezone":"Asia/Shanghai",
    "iso:country":"CN",
    "name:zho_x_preferred":[
        "\u5821\u5b50\u5c71"
    ],
    "wof:name":"Baozishan",
    "wof:placetype":"locality"
},
  "geometry": {"coordinates":[105.95634,35.87425],"type":"Point"}
}