{
  "type": "Feature",
  "properties": {
    "gn:admin1_code":"7.0",
    "gn:asciiname":"Cuncun Houcun",
    "gn:country_code":"CN",
    "gn:dem":489,
    "gn:feature_class":"P",
    "gn:feature_code":"PPL",
    "gn:name":"Cuncun Houcun",
    "gn:population":0,
    "gn:timezone":"Asia/Shanghai",
    "iso:country":"CN",
    "name:und_x_variant":[
        "Cunhou",
        "Cuncun Houcun"
    ],
    "name:zho_x_preferred":[
        "\u5b58\u540e"
    ],
    "name:zho_x_variant":[
        "\u6751\u5b58\u540e\u6751"
    ],
    "wof:name":"Cuncun Houcun",
    "wof:placetype":"locality"
},
  "geometry": {"coordinates":[119.38318999999998,26.33061],"type":"Point"}
}