{
  "type": "Feature",
  "properties": {
    "gn:admin1_code":"23.0",
    "gn:asciiname":"Lingbang",
    "gn:country_code":"CN",
    "gn:dem":6,
    "gn:feature_class":"P",
    "gn:feature_code":"PPL",
    "gn:name":"Lingbang",
    "gn:population":0,
    "gn:timezone":"Asia/Shanghai",
    "iso:country":"CN",
    "name:und_x_variant":[
        "\u83f1\u6d5c"
    ],
    "wof:name":"Lingbang",
    "wof:placetype":"locality"
},
  "geometry": {"coordinates":[121.02343999999999,30.97615],"type":"Point"}
}