{
  "type": "Feature",
  "properties": {
    "gn:admin1_code":"13.0",
    "gn:asciiname":"Qiman",
    "gn:country_code":"CN",
    "gn:dem":1005,
    "gn:feature_class":"P",
    "gn:feature_code":"PPLA4",
    "gn:name":"Qiman",
    "gn:population":0,
    "gn:timezone":"Asia/Urumqi",
    "iso:country":"CN",
    "name:uig_x_preferred":[
        "Qim\u0259n"
    ],
    "name:uig_x_variant":[
        "Chimen",
        "\u0686\u0649\u0645\u06d5\u0646",
        "\u0427\u0438\u043c\u04d9\u043d"
    ],
    "name:und_x_variant":[
        "Qiman Zhen"
    ],
    "name:zho_x_preferred":[
        "\u9f50\u6ee1"
    ],
    "name:zho_x_variant":[
        "\u9f50\u6ee1\u9547"
    ],
    "wof:name":"Qiman",
    "wof:placetype":"locality"
},
  "geometry": {"coordinates":[82.91139,41.53778],"type":"Point"}
}