{
  "type": "Feature",
  "properties": {
    "gn:admin1_code":"26.0",
    "gn:asciiname":"Banbanqiao",
    "gn:country_code":"CN",
    "gn:dem":864,
    "gn:feature_class":"P",
    "gn:feature_code":"PPL",
    "gn:name":"Banbanqiao",
    "gn:population":0,
    "gn:timezone":"Asia/Shanghai",
    "iso:country":"CN",
    "name:und_x_variant":[
        "\u677f\u677f\u6865"
    ],
    "wof:name":"Banbanqiao",
    "wof:placetype":"locality"
},
  "geometry": {"coordinates":[106.80636,32.85276],"type":"Point"}
}