{
  "type": "Feature",
  "properties": {
    "gn:admin1_code":"26",
    "gn:asciiname":"Dongliangjia",
    "gn:country_code":"CN",
    "gn:dem":1057,
    "gn:feature_class":"P",
    "gn:feature_code":"PPL",
    "gn:name":"Dongliangjia",
    "gn:population":0,
    "gn:timezone":"Asia/Shanghai",
    "iso:country":"CN",
    "name:zho_x_preferred":[
        "\u4e1c\u6881\u5bb6"
    ],
    "wof:name":"Dongliangjia",
    "wof:placetype":"locality"
},
  "geometry": {"coordinates":[108.50388999999998,34.85417],"type":"Point"}
}