{
  "type": "Feature",
  "properties": {
    "gn:admin1_code":"25.0",
    "gn:asciiname":"Zhonghuabu",
    "gn:country_code":"CN",
    "gn:dem":11,
    "gn:feature_class":"P",
    "gn:feature_code":"PPL",
    "gn:name":"Zhonghuabu",
    "gn:population":0,
    "gn:timezone":"Asia/Shanghai",
    "iso:country":"CN",
    "name:zho_x_preferred":[
        "\u4e2d\u534e\u57e0"
    ],
    "wof:name":"Zhonghuabu",
    "wof:placetype":"locality"
},
  "geometry": {"coordinates":[120.25,36.33333],"type":"Point"}
}