{
  "type": "Feature",
  "properties": {
    "gn:admin1_code":"10",
    "gn:asciiname":"Yangshu Goumen",
    "gn:country_code":"CN",
    "gn:dem":476,
    "gn:feature_class":"P",
    "gn:feature_code":"PPL",
    "gn:name":"Yangshu Goumen",
    "gn:population":0,
    "gn:timezone":"Asia/Shanghai",
    "iso:country":"CN",
    "name:zho_x_preferred":[
        "\u6768\u6811\u6c9f\u95e8"
    ],
    "wof:name":"Yangshu Goumen",
    "wof:placetype":"locality"
},
  "geometry": {"coordinates":[117.65076000000001,41.17737],"type":"Point"}
}