{
  "type": "Feature",
  "properties": {
    "gn:admin1_code":"32.0",
    "gn:asciiname":"Shuilazhu Pingzi",
    "gn:country_code":"CN",
    "gn:dem":1798,
    "gn:feature_class":"P",
    "gn:feature_code":"PPL",
    "gn:name":"Shuilazhu Pingzi",
    "gn:population":0,
    "gn:timezone":"Asia/Shanghai",
    "iso:country":"CN",
    "name:zho_x_preferred":[
        "\u6c34\u8721\u70db\u576a\u5b50"
    ],
    "wof:name":"Shuilazhu Pingzi",
    "wof:placetype":"locality"
},
  "geometry": {"coordinates":[101.89849,27.2136],"type":"Point"}
}