{
  "type": "Feature",
  "properties": {
    "gn:admin1_code":"6.0",
    "gn:asciiname":"Shanggongma",
    "gn:country_code":"CN",
    "gn:dem":4185,
    "gn:feature_class":"P",
    "gn:feature_code":"PPLA4",
    "gn:name":"Shanggongma",
    "gn:population":0,
    "gn:timezone":"Asia/Shanghai",
    "iso:country":"CN",
    "name:und_x_variant":[
        "Shang-kung-ma",
        "Shanggongma",
        "Shanggongma Xiang",
        "Tanggegei"
    ],
    "name:zho_x_preferred":[
        "\u4e0a\u8d21\u9ebb"
    ],
    "name:zho_x_variant":[
        "\u4e0a\u8d21\u9ebb\u4e61",
        "\u5510\u683c\u7ed9"
    ],
    "wof:name":"Shanggongma",
    "wof:placetype":"locality"
},
  "geometry": {"coordinates":[99.66667,33.83333],"type":"Point"}
}