{
  "type": "Feature",
  "properties": {
    "gn:admin1_code":"12.0",
    "gn:asciiname":"Pilisi",
    "gn:country_code":"CN",
    "gn:dem":525,
    "gn:feature_class":"P",
    "gn:feature_code":"PPL",
    "gn:name":"Pilisi",
    "gn:population":0,
    "gn:timezone":"Asia/Shanghai",
    "iso:country":"CN",
    "name:zho_x_preferred":[
        "\u9739\u96f3\u5bfa"
    ],
    "wof:name":"Pilisi",
    "wof:placetype":"locality"
},
  "geometry": {"coordinates":[110.33710000000001,32.37009],"type":"Point"}
}