{
  "type": "Feature",
  "properties": {
    "gn:admin1_code":"11.0",
    "gn:asciiname":"Zetu",
    "gn:country_code":"CN",
    "gn:dem":355,
    "gn:feature_class":"P",
    "gn:feature_code":"PPL",
    "gn:name":"Zetu",
    "gn:population":0,
    "gn:timezone":"Asia/Shanghai",
    "iso:country":"CN",
    "name:zho_x_preferred":[
        "\u62e9\u571f"
    ],
    "wof:name":"Zetu",
    "wof:placetype":"locality"
},
  "geometry": {"coordinates":[109.43165,28.83609],"type":"Point"}
}