{
  "type": "Feature",
  "properties": {
    "gn:admin1_code":"08",
    "gn:asciiname":"Liushu",
    "gn:country_code":"CN",
    "gn:dem":310,
    "gn:feature_class":"P",
    "gn:feature_code":"PPLA4",
    "gn:name":"Liushu",
    "gn:population":0,
    "gn:timezone":"Asia/Shanghai",
    "iso:country":"CN",
    "name:und_x_variant":[
        "Liushuhe",
        "Liushu Zhen"
    ],
    "name:zho_x_preferred":[
        "\u67f3\u6811"
    ],
    "name:zho_x_variant":[
        "\u67f3\u6811\u9547"
    ],
    "wof:name":"Liushu",
    "wof:placetype":"locality"
},
  "geometry": {"coordinates":[130.00778,44.90902],"type":"Point"}
}