{
  "type": "Feature",
  "properties": {
    "gn:admin1_code":"26.0",
    "gn:asciiname":"Yazi",
    "gn:country_code":"CN",
    "gn:dem":657,
    "gn:feature_class":"P",
    "gn:feature_code":"PPL",
    "gn:name":"Yazi",
    "gn:population":0,
    "gn:timezone":"Asia/Shanghai",
    "iso:country":"CN",
    "name:und_x_variant":[
        "\u4e9a\u5b50"
    ],
    "wof:name":"Yazi",
    "wof:placetype":"locality"
},
  "geometry": {"coordinates":[107.35856,34.39700999999999],"type":"Point"}
}