{
  "type": "Feature",
  "properties": {
    "gn:admin1_code":"10.0",
    "gn:asciiname":"Zhenzhuang",
    "gn:country_code":"CN",
    "gn:dem":81,
    "gn:feature_class":"P",
    "gn:feature_code":"PPL",
    "gn:name":"Zhenzhuang",
    "gn:population":0,
    "gn:timezone":"Asia/Shanghai",
    "iso:country":"CN",
    "name:zho_x_preferred":[
        "\u7504\u5e84"
    ],
    "wof:name":"Zhenzhuang",
    "wof:placetype":"locality"
},
  "geometry": {"coordinates":[118.18255000000001,40.04111],"type":"Point"}
}