{
  "type": "Feature",
  "properties": {
    "gn:admin1_code":"32.0",
    "gn:asciiname":"Yizuo Laohan",
    "gn:country_code":"CN",
    "gn:dem":2985,
    "gn:feature_class":"P",
    "gn:feature_code":"PPL",
    "gn:name":"Yizuo Laohan",
    "gn:population":0,
    "gn:timezone":"Asia/Shanghai",
    "iso:country":"CN",
    "name:zho_x_preferred":[
        "\u8863\u4f5c\u8001\u542b"
    ],
    "wof:name":"Yizuo Laohan",
    "wof:placetype":"locality"
},
  "geometry": {"coordinates":[102.886,27.7089],"type":"Point"}
}