{
  "type": "Feature",
  "properties": {
    "gn:admin1_code":"18.0",
    "gn:asciiname":"Yintan Shangzhai",
    "gn:country_code":"CN",
    "gn:dem":658,
    "gn:feature_class":"P",
    "gn:feature_code":"PPL",
    "gn:name":"Yintan Shangzhai",
    "gn:population":0,
    "gn:timezone":"Asia/Shanghai",
    "iso:country":"CN",
    "name:zho_x_preferred":[
        "\u94f6\u6f6d\u4e0a\u5be8"
    ],
    "wof:name":"Yintan Shangzhai",
    "wof:placetype":"locality"
},
  "geometry": {"coordinates":[108.84399999999999,25.8353],"type":"Point"}
}