{
  "type": "Feature",
  "properties": {
    "gn:admin1_code":"18",
    "gn:asciiname":"Guojiatun",
    "gn:country_code":"CN",
    "gn:dem":1466,
    "gn:feature_class":"P",
    "gn:feature_code":"PPL",
    "gn:name":"Guojiatun",
    "gn:population":0,
    "gn:timezone":"Asia/Shanghai",
    "iso:country":"CN",
    "name:zho_x_preferred":[
        "\u90ed\u5bb6\u5c6f"
    ],
    "wof:name":"Guojiatun",
    "wof:placetype":"locality"
},
  "geometry": {"coordinates":[105.95999999999999,26.3522],"type":"Point"}
}