{
  "type": "Feature",
  "properties": {
    "gn:admin1_code":"24",
    "gn:asciiname":"Beidong",
    "gn:country_code":"CN",
    "gn:dem":511,
    "gn:feature_class":"P",
    "gn:feature_code":"PPLA4",
    "gn:name":"Beidong",
    "gn:population":0,
    "gn:timezone":"Asia/Shanghai",
    "iso:country":"CN",
    "name:und_x_variant":[
        "Pei-tung-ts\u2019un",
        "Pei-tung",
        "Beidong",
        "\u5317\u8463",
        "Beidong Xiang",
        "\u5317\u8463\u4e61"
    ],
    "wof:name":"Beidong",
    "wof:placetype":"locality"
},
  "geometry": {"coordinates":[111.54264999999999,35.616],"type":"Point"}
}