{
  "type": "Feature",
  "properties": {
    "gn:admin1_code":"1.0",
    "gn:asciiname":"Doumu",
    "gn:country_code":"CN",
    "gn:dem":71,
    "gn:feature_class":"P",
    "gn:feature_code":"PPL",
    "gn:name":"Doumu",
    "gn:population":0,
    "gn:timezone":"Asia/Shanghai",
    "iso:country":"CN",
    "name:deu_x_preferred":[
        "Doumu"
    ],
    "name:heb_x_preferred":[
        "\u05d3\u05d5\u05de\u05d5"
    ],
    "name:jpn_x_preferred":[
        "\u6597\u6bcd\u5143\u541b"
    ],
    "name:rus_x_preferred":[
        "\u0414\u043e\u0443-\u043c\u0443"
    ],
    "name:zho_x_preferred":[
        "\u6597\u59e5\u5143\u541b"
    ],
    "wof:name":"Doumu",
    "wof:placetype":"locality"
},
  "geometry": {"coordinates":[116.48333,30.61667000000001],"type":"Point"}
}