{
  "type": "Feature",
  "properties": {
    "gn:admin1_code":"25",
    "gn:asciiname":"Qianding Guanzhuang",
    "gn:country_code":"CN",
    "gn:dem":44,
    "gn:feature_class":"P",
    "gn:feature_code":"PPL",
    "gn:name":"Qianding Guanzhuang",
    "gn:population":0,
    "gn:timezone":"Asia/Shanghai",
    "iso:country":"CN",
    "name:zho_x_preferred":[
        "\u524d\u4e01\u5b98\u5e84"
    ],
    "wof:name":"Qianding Guanzhuang",
    "wof:placetype":"locality"
},
  "geometry": {"coordinates":[118.425,36.824],"type":"Point"}
}