{
  "type": "Feature",
  "properties": {
    "gn:admin1_code":"30",
    "gn:asciiname":"Tandian",
    "gn:country_code":"CN",
    "gn:dem":8,
    "gn:feature_class":"P",
    "gn:feature_code":"PPL",
    "gn:name":"Tandian",
    "gn:population":0,
    "gn:timezone":"Asia/Urumqi",
    "iso:country":"CN",
    "name:pan_x_preferred":[
        "\u0a1f\u0a3e\u0a02\u0a21\u0a40\u0a06"
    ],
    "name:zho_x_preferred":[
        "\u6f6d\u5178"
    ],
    "wof:name":"Tandian",
    "wof:placetype":"locality"
},
  "geometry": {"coordinates":[109.97329000000001,20.46649],"type":"Point"}
}