{
  "type": "Feature",
  "properties": {
    "gn:admin1_code":"24.0",
    "gn:asciiname":"Baozidian",
    "gn:country_code":"CN",
    "gn:dem":1027,
    "gn:feature_class":"P",
    "gn:feature_code":"PPL",
    "gn:name":"Baozidian",
    "gn:population":0,
    "gn:timezone":"Asia/Shanghai",
    "iso:country":"CN",
    "name:und_x_variant":[
        "\u5821\u5b50\u5e97"
    ],
    "name:zho_x_preferred":[
        "\u5821\u5b50\u5e97"
    ],
    "wof:name":"Baozidian",
    "wof:placetype":"locality"
},
  "geometry": {"coordinates":[113.18406,39.95812],"type":"Point"}
}