{
  "type": "Feature",
  "properties": {
    "gn:admin1_code":"15.0",
    "gn:asciiname":"Jiugoujing",
    "gn:country_code":"CN",
    "gn:dem":1351,
    "gn:feature_class":"P",
    "gn:feature_code":"PPL",
    "gn:name":"Jiugoujing",
    "gn:population":0,
    "gn:timezone":"Asia/Shanghai",
    "iso:country":"CN",
    "name:zho_x_preferred":[
        "\u4e5d\u6c9f\u4e95"
    ],
    "wof:name":"Jiugoujing",
    "wof:placetype":"locality"
},
  "geometry": {"coordinates":[102.446,38.9086],"type":"Point"}
}