{
  "type": "Feature",
  "properties": {
    "gn:admin1_code":"30.0",
    "gn:asciiname":"Tangjiaocun",
    "gn:country_code":"CN",
    "gn:dem":6,
    "gn:feature_class":"P",
    "gn:feature_code":"PPL",
    "gn:name":"Tangjiaocun",
    "gn:population":0,
    "gn:timezone":"Asia/Shanghai",
    "iso:country":"CN",
    "name:zho_x_preferred":[
        "\u5858\u89d2\u6751"
    ],
    "wof:name":"Tangjiaocun",
    "wof:placetype":"locality"
},
  "geometry": {"coordinates":[111.91598,21.94918],"type":"Point"}
}