{
  "type": "Feature",
  "properties": {
    "gn:admin1_code":"30",
    "gn:asciiname":"Baishuipo",
    "gn:country_code":"CN",
    "gn:dem":23,
    "gn:feature_class":"P",
    "gn:feature_code":"PPL",
    "gn:name":"Baishuipo",
    "gn:population":0,
    "gn:timezone":"Asia/Urumqi",
    "iso:country":"CN",
    "name:zho_x_preferred":[
        "\u767d\u6c34\u5761"
    ],
    "wof:name":"Baishuipo",
    "wof:placetype":"locality"
},
  "geometry": {"coordinates":[110.33839,21.2352],"type":"Point"}
}