{
  "type": "Feature",
  "properties": {
    "gn:admin1_code":"18.0",
    "gn:asciiname":"Xiejing",
    "gn:country_code":"CN",
    "gn:dem":504,
    "gn:feature_class":"P",
    "gn:feature_code":"PPL",
    "gn:name":"Xiejing",
    "gn:population":0,
    "gn:timezone":"Asia/Shanghai",
    "iso:country":"CN",
    "name:zho_x_preferred":[
        "\u659c\u4e95"
    ],
    "wof:name":"Xiejing",
    "wof:placetype":"locality"
},
  "geometry": {"coordinates":[108.98399999999999,27.3812],"type":"Point"}
}