{
  "type": "Feature",
  "properties": {
    "gn:admin1_code":"11.0",
    "gn:asciiname":"Shuijingtang",
    "gn:country_code":"CN",
    "gn:dem":454,
    "gn:feature_class":"P",
    "gn:feature_code":"PPL",
    "gn:name":"Shuijingtang",
    "gn:population":0,
    "gn:timezone":"Asia/Shanghai",
    "iso:country":"CN",
    "name:zho_x_preferred":[
        "\u6c34\u6676\u5858"
    ],
    "wof:name":"Shuijingtang",
    "wof:placetype":"locality"
},
  "geometry": {"coordinates":[110.82671999999999,29.30111],"type":"Point"}
}