{
  "type": "Feature",
  "properties": {
    "gn:admin1_code":"21.0",
    "gn:asciiname":"Xipancha",
    "gn:country_code":"CN",
    "gn:dem":1887,
    "gn:feature_class":"P",
    "gn:feature_code":"PPL",
    "gn:name":"Xipancha",
    "gn:population":0,
    "gn:timezone":"Asia/Shanghai",
    "iso:country":"CN",
    "name:zho_x_preferred":[
        "\u897f\u76d8\u5c94"
    ],
    "wof:name":"Xipancha",
    "wof:placetype":"locality"
},
  "geometry": {"coordinates":[105.43856,35.81602],"type":"Point"}
}