{
  "type": "Feature",
  "properties": {
    "gn:admin1_code":"32.0",
    "gn:asciiname":"Baozi",
    "gn:country_code":"CN",
    "gn:dem":2231,
    "gn:feature_class":"P",
    "gn:feature_code":"PPL",
    "gn:name":"Baozi",
    "gn:population":0,
    "gn:timezone":"Asia/Shanghai",
    "iso:country":"CN",
    "name:zho_x_preferred":[
        "\u5305\u5b50"
    ],
    "wof:name":"Baozi",
    "wof:placetype":"locality"
},
  "geometry": {"coordinates":[102.006,28.3997],"type":"Point"}
}