{
  "type": "Feature",
  "properties": {
    "gn:admin1_code":"32.0",
    "gn:asciiname":"Baozi",
    "gn:country_code":"CN",
    "gn:dem":2231,
    "gn:feature_class":"P",
    "gn:feature_code":"PPL",
    "gn:name":"Baozi",
    "gn:population":0,
    "gn:timezone":"Asia/Shanghai",
    "iso:country":"CN",
    "name:ara_x_preferred":[
        "\u0628\u0627\u0648\u0632\u064a"
    ],
    "name:bjn_x_preferred":[
        "Bakpao"
    ],
    "name:bul_x_preferred":[
        "\u041f\u0430\u0443\u0447\u0438"
    ],
    "name:cat_x_preferred":[
        "Baozi"
    ],
    "name:deu_x_preferred":[
        "Baozi"
    ],
    "name:fin_x_preferred":[
        "Baozi"
    ],
    "name:fra_x_preferred":[
        "Baozi"
    ],
    "name:ind_x_preferred":[
        "Bakpao"
    ],
    "name:ita_x_preferred":[
        "Baozi"
    ],
    "name:jav_x_preferred":[
        "Bakpao"
    ],
    "name:kor_x_preferred":[
        "\ubc14\uc624\ucbd4"
    ],
    "name:msa_x_preferred":[
        "Pau"
    ],
    "name:mya_x_preferred":[
        "\u1015\u1031\u102b\u1000\u103a\u1005\u102e"
    ],
    "name:nor_x_preferred":[
        "Baozi"
    ],
    "name:pol_x_preferred":[
        "Baozi"
    ],
    "name:por_x_preferred":[
        "Baozi"
    ],
    "name:rus_x_preferred":[
        "\u0411\u0430\u043e\u0446\u0437\u044b"
    ],
    "name:spa_x_preferred":[
        "Baozi"
    ],
    "name:swe_x_preferred":[
        "Baozi"
    ],
    "name:tur_x_preferred":[
        "Baozi"
    ],
    "name:ukr_x_preferred":[
        "\u0411\u0430\u043e\u0446\u0437\u0438"
    ],
    "name:vie_x_preferred":[
        "B\u00e1nh bao"
    ],
    "name:zho_x_preferred":[
        "\u5305\u5b50"
    ],
    "wof:name":"Baozi",
    "wof:placetype":"locality"
},
  "geometry": {"coordinates":[102.006,28.3997],"type":"Point"}
}