{
  "type": "Feature",
  "properties": {
    "gn:admin1_code":"29.0",
    "gn:asciiname":"Qiduzha",
    "gn:country_code":"CN",
    "gn:dem":1873,
    "gn:feature_class":"P",
    "gn:feature_code":"PPL",
    "gn:name":"Qiduzha",
    "gn:population":0,
    "gn:timezone":"Asia/Shanghai",
    "iso:country":"CN",
    "name:zho_x_preferred":[
        "\u8d77\u675c\u6e23"
    ],
    "wof:name":"Qiduzha",
    "wof:placetype":"locality"
},
  "geometry": {"coordinates":[103.351,24.9762],"type":"Point"}
}