{
  "type": "Feature",
  "properties": {
    "gn:admin1_code":"25",
    "gn:asciiname":"Houduanzhai",
    "gn:country_code":"CN",
    "gn:dem":68,
    "gn:feature_class":"P",
    "gn:feature_code":"PPL",
    "gn:name":"Houduanzhai",
    "gn:population":0,
    "gn:timezone":"Asia/Shanghai",
    "iso:country":"CN",
    "name:zho_x_preferred":[
        "\u540e\u6bb5\u5b85"
    ],
    "wof:name":"Houduanzhai",
    "wof:placetype":"locality"
},
  "geometry": {"coordinates":[118.47499999999999,34.7857],"type":"Point"}
}