{
  "type": "Feature",
  "properties": {
    "gn:admin1_code":"13",
    "gn:asciiname":"Yalegu Zibage",
    "gn:country_code":"CN",
    "gn:dem":1330,
    "gn:feature_class":"P",
    "gn:feature_code":"PPL",
    "gn:name":"Yalegu Zibage",
    "gn:population":0,
    "gn:timezone":"Asia/Shanghai",
    "iso:country":"CN",
    "name:und_x_variant":[
        "\u4e9a\u52d2\u53e4\u5b5c\u5df4\u683c"
    ],
    "wof:name":"Yalegu Zibage",
    "wof:placetype":"locality"
},
  "geometry": {"coordinates":[77.14359,38.10225],"type":"Point"}
}