{
  "type": "Feature",
  "properties": {
    "gn:admin1_code":"12.0",
    "gn:asciiname":"Xianshimiao",
    "gn:country_code":"CN",
    "gn:dem":28,
    "gn:feature_class":"P",
    "gn:feature_code":"PPL",
    "gn:name":"Xianshimiao",
    "gn:population":0,
    "gn:timezone":"Asia/Shanghai",
    "iso:country":"CN",
    "name:zho_x_preferred":[
        "\u4ed9\u5e08\u5e99"
    ],
    "wof:name":"Xianshimiao",
    "wof:placetype":"locality"
},
  "geometry": {"coordinates":[113.02442000000001,30.39378],"type":"Point"}
}