{
  "type": "Feature",
  "properties": {
    "gn:admin1_code":"24",
    "gn:asciiname":"Jialing",
    "gn:cc2":"CN",
    "gn:country_code":"CN",
    "gn:dem":1011,
    "gn:feature_class":"P",
    "gn:feature_code":"PPL",
    "gn:name":"Jialing",
    "gn:population":0,
    "gn:timezone":"Asia/Shanghai",
    "iso:country":"CN",
    "name:und_x_variant":[
        "Chia-ling",
        "Jialing"
    ],
    "wof:name":"Jialing",
    "wof:placetype":"locality"
},
  "geometry": {"coordinates":[112.27056,35.42139],"type":"Point"}
}