{
  "type": "Feature",
  "properties": {
    "gn:admin1_code":"12.0",
    "gn:asciiname":"Wangjiatan",
    "gn:country_code":"CN",
    "gn:dem":982,
    "gn:feature_class":"P",
    "gn:feature_code":"PPL",
    "gn:name":"Wangjiatan",
    "gn:population":0,
    "gn:timezone":"Asia/Shanghai",
    "iso:country":"CN",
    "name:zho_x_preferred":[
        "\u6c6a\u5bb6\u5766"
    ],
    "wof:name":"Wangjiatan",
    "wof:placetype":"locality"
},
  "geometry": {"coordinates":[109.9314,30.54657000000001],"type":"Point"}
}