{
  "type": "Feature",
  "properties": {
    "gn:admin1_code":"19.0",
    "gn:asciiname":"Shifo",
    "gn:country_code":"CN",
    "gn:dem":6,
    "gn:feature_class":"P",
    "gn:feature_code":"PPL",
    "gn:name":"Shifo",
    "gn:population":0,
    "gn:timezone":"Asia/Shanghai",
    "iso:country":"CN",
    "name:und_x_variant":[
        "\u77f3\u4f5b"
    ],
    "name:zho_x_preferred":[
        "\u77f3\u4f5b"
    ],
    "wof:name":"Shifo",
    "wof:placetype":"locality"
},
  "geometry": {"coordinates":[124.17168999999998,39.92762000000001],"type":"Point"}
}