{
  "type": "Feature",
  "properties": {
    "gn:admin1_code":"11.0",
    "gn:asciiname":"Shanpotou",
    "gn:country_code":"CN",
    "gn:dem":367,
    "gn:feature_class":"P",
    "gn:feature_code":"PPL",
    "gn:name":"Shanpotou",
    "gn:population":0,
    "gn:timezone":"Asia/Shanghai",
    "iso:country":"CN",
    "name:zho_x_preferred":[
        "\u5c71\u5761\u5934"
    ],
    "wof:name":"Shanpotou",
    "wof:placetype":"locality"
},
  "geometry": {"coordinates":[109.645,26.70285],"type":"Point"}
}