{
  "type": "Feature",
  "properties": {
    "gn:admin1_code":"11.0",
    "gn:asciiname":"Tang'erdu",
    "gn:country_code":"CN",
    "gn:dem":673,
    "gn:feature_class":"P",
    "gn:feature_code":"PPL",
    "gn:name":"Tang\u2019erdu",
    "gn:population":0,
    "gn:timezone":"Asia/Shanghai",
    "iso:country":"CN",
    "name:und_x_variant":[
        "Tang\u2019erdu"
    ],
    "name:zho_x_preferred":[
        "\u5510\u5c14\u5ea6"
    ],
    "wof:name":"Tang'erdu",
    "wof:placetype":"locality"
},
  "geometry": {"coordinates":[109.80718,28.56571],"type":"Point"}
}