{
  "type": "Feature",
  "properties": {
    "gn:admin1_code":"5.0",
    "gn:asciiname":"Yujiacun",
    "gn:country_code":"CN",
    "gn:dem":218,
    "gn:feature_class":"P",
    "gn:feature_code":"PPL",
    "gn:name":"Yujiacun",
    "gn:population":0,
    "gn:timezone":"Asia/Shanghai",
    "iso:country":"CN",
    "name:zho_x_preferred":[
        "\u4e8e\u5bb6\u6751"
    ],
    "wof:name":"Yujiacun",
    "wof:placetype":"locality"
},
  "geometry": {"coordinates":[125.63227000000001,43.55302],"type":"Point"}
}