{
  "type": "Feature",
  "properties": {
    "gn:admin1_code":"32.0",
    "gn:asciiname":"Dadiwan",
    "gn:country_code":"CN",
    "gn:dem":448,
    "gn:feature_class":"P",
    "gn:feature_code":"PPL",
    "gn:name":"Dadiwan",
    "gn:population":0,
    "gn:timezone":"Asia/Shanghai",
    "iso:country":"CN",
    "name:deu_x_preferred":[
        "Dadiwan"
    ],
    "name:fas_x_preferred":[
        "\u0641\u0631\u0647\u0646\u06af \u062f\u0627\u062f\u06cc\u200c\u0648\u0627\u0646"
    ],
    "name:jpn_x_preferred":[
        "\u8001\u5b98\u53f0\u6587\u5316"
    ],
    "name:kor_x_preferred":[
        "\ub77c\uc624\uad00\ud0c0\uc774 \ubb38\ud654"
    ],
    "name:nor_x_preferred":[
        "Dadiwankulturen"
    ],
    "name:zho_x_preferred":[
        "\u5927\u5730\u6e7e"
    ],
    "name:zho_x_variant":[
        "\u8001\u5b98\u53f0\u6587\u5316"
    ],
    "wof:name":"Dadiwan",
    "wof:placetype":"locality"
},
  "geometry": {"coordinates":[105.04498,31.23706],"type":"Point"}
}