{
  "type": "Feature",
  "properties": {
    "gn:admin1_code":"19.0",
    "gn:asciiname":"Shanghebei",
    "gn:country_code":"CN",
    "gn:dem":371,
    "gn:feature_class":"P",
    "gn:feature_code":"PPL",
    "gn:name":"Shanghebei",
    "gn:population":0,
    "gn:timezone":"Asia/Shanghai",
    "iso:country":"CN",
    "name:und_x_variant":[
        "\u4e0a\u6cb3\u5317"
    ],
    "wof:name":"Shanghebei",
    "wof:placetype":"locality"
},
  "geometry": {"coordinates":[122.96507,40.35852],"type":"Point"}
}