{
  "type": "Feature",
  "properties": {
    "gn:admin1_code":"4.0",
    "gn:asciiname":"Xijiao",
    "gn:country_code":"CN",
    "gn:dem":8,
    "gn:feature_class":"P",
    "gn:feature_code":"PPL",
    "gn:name":"Xijiao",
    "gn:population":0,
    "gn:timezone":"Asia/Shanghai",
    "iso:country":"CN",
    "name:zho_x_preferred":[
        "Xijiao"
    ],
    "name:zho_x_variant":[
        "\u897f\u90ca"
    ],
    "wof:name":"Xijiao",
    "wof:placetype":"locality"
},
  "geometry": {"coordinates":[121.08447,31.43988],"type":"Point"}
}