{
  "type": "Feature",
  "properties": {
    "gn:admin1_code":"11",
    "gn:asciiname":"Datoushan",
    "gn:country_code":"CN",
    "gn:dem":189,
    "gn:feature_class":"P",
    "gn:feature_code":"PPL",
    "gn:name":"Datoushan",
    "gn:population":0,
    "gn:timezone":"Asia/Shanghai",
    "iso:country":"CN",
    "name:und_x_variant":[
        "\u8fbe\u5934\u5c71",
        "Datoushan"
    ],
    "wof:name":"Datoushan",
    "wof:placetype":"locality"
},
  "geometry": {"coordinates":[111.54472,25.37806],"type":"Point"}
}