{
  "type": "Feature",
  "properties": {
    "gn:admin1_code":"26.0",
    "gn:asciiname":"Dujiapo",
    "gn:country_code":"CN",
    "gn:dem":1799,
    "gn:feature_class":"P",
    "gn:feature_code":"PPL",
    "gn:name":"Dujiapo",
    "gn:population":0,
    "gn:timezone":"Asia/Shanghai",
    "iso:country":"CN",
    "name:zho_x_preferred":[
        "\u675c\u5bb6\u5761"
    ],
    "wof:name":"Dujiapo",
    "wof:placetype":"locality"
},
  "geometry": {"coordinates":[106.52522,34.68886],"type":"Point"}
}