{
  "type": "Feature",
  "properties": {
    "gn:admin1_code":"14.0",
    "gn:asciiname":"Jialaji",
    "gn:country_code":"CN",
    "gn:dem":3791,
    "gn:feature_class":"P",
    "gn:feature_code":"PPL",
    "gn:name":"Jialaji",
    "gn:population":0,
    "gn:timezone":"Asia/Urumqi",
    "iso:country":"CN",
    "name:zho_x_preferred":[
        "\u7532\u62c9\u5409"
    ],
    "wof:name":"Jialaji",
    "wof:placetype":"locality"
},
  "geometry": {"coordinates":[98.70947,30.1177],"type":"Point"}
}