{
  "type": "Feature",
  "properties": {
    "gn:admin1_code":"19.0",
    "gn:asciiname":"Badaogou",
    "gn:country_code":"CN",
    "gn:dem":548,
    "gn:feature_class":"P",
    "gn:feature_code":"PPL",
    "gn:name":"Badaogou",
    "gn:population":0,
    "gn:timezone":"Asia/Shanghai",
    "iso:country":"CN",
    "name:zho_x_preferred":[
        "\u516b\u9053\u6c9f"
    ],
    "wof:name":"Badaogou",
    "wof:placetype":"locality"
},
  "geometry": {"coordinates":[119.34444000000001,40.69785],"type":"Point"}
}