{
  "type": "Feature",
  "properties": {
    "gn:admin1_code":"03",
    "gn:asciiname":"Hongshuizhai",
    "gn:country_code":"CN",
    "gn:dem":351,
    "gn:feature_class":"P",
    "gn:feature_code":"PPL",
    "gn:name":"Hongshuizhai",
    "gn:population":0,
    "gn:timezone":"Asia/Shanghai",
    "iso:country":"CN",
    "name:und_x_variant":[
        "Hung-shui-chai",
        "Hongshuizhai"
    ],
    "name:zho_x_preferred":[
        "\u6d2a\u6c34\u5be8"
    ],
    "wof:name":"Hongshuizhai",
    "wof:placetype":"locality"
},
  "geometry": {"coordinates":[114.23999999999999,25.4912],"type":"Point"}
}