{
  "type": "Feature",
  "properties": {
    "gn:admin1_code":"30.0",
    "gn:asciiname":"Chanliping",
    "gn:country_code":"CN",
    "gn:dem":596,
    "gn:feature_class":"P",
    "gn:feature_code":"PPL",
    "gn:name":"Chanliping",
    "gn:population":0,
    "gn:timezone":"Asia/Shanghai",
    "iso:country":"CN",
    "name:zho_x_preferred":[
        "\u8749\u68a8\u576a"
    ],
    "wof:name":"Chanliping",
    "wof:placetype":"locality"
},
  "geometry": {"coordinates":[113.97808999999999,24.00726],"type":"Point"}
}