{
  "type": "Feature",
  "properties": {
    "gn:admin1_code":"29.0",
    "gn:asciiname":"Laoliuku",
    "gn:country_code":"CN",
    "gn:dem":969,
    "gn:feature_class":"P",
    "gn:feature_code":"PPL",
    "gn:name":"Laoliuku",
    "gn:population":0,
    "gn:timezone":"Asia/Shanghai",
    "iso:country":"CN",
    "name:zho_x_preferred":[
        "\u8001\u516d\u5e93"
    ],
    "wof:name":"Laoliuku",
    "wof:placetype":"locality"
},
  "geometry": {"coordinates":[98.8595,25.8615],"type":"Point"}
}