{
  "type": "Feature",
  "properties": {
    "gn:admin1_code":"16.0",
    "gn:asciiname":"Paiba",
    "gn:country_code":"CN",
    "gn:dem":405,
    "gn:feature_class":"P",
    "gn:feature_code":"PPL",
    "gn:name":"Paiba",
    "gn:population":0,
    "gn:timezone":"Asia/Shanghai",
    "iso:country":"CN",
    "name:zho_x_preferred":[
        "\u6392\u5c9c"
    ],
    "wof:name":"Paiba",
    "wof:placetype":"locality"
},
  "geometry": {"coordinates":[108.417,23.649],"type":"Point"}
}