{
  "type": "Feature",
  "properties": {
    "gn:admin1_code":"29.0",
    "gn:asciiname":"Dahai",
    "gn:country_code":"CN",
    "gn:dem":2545,
    "gn:feature_class":"P",
    "gn:feature_code":"PPL",
    "gn:name":"Dahai",
    "gn:population":0,
    "gn:timezone":"Asia/Shanghai",
    "iso:country":"CN",
    "name:und_x_variant":[
        "\u5927\u6d77"
    ],
    "wof:name":"Dahai",
    "wof:placetype":"locality"
},
  "geometry": {"coordinates":[103.18899999999999,26.96153],"type":"Point"}
}