{
  "type": "Feature",
  "properties": {
    "gn:admin1_code":"16.0",
    "gn:asciiname":"Simen",
    "gn:country_code":"CN",
    "gn:dem":91,
    "gn:feature_class":"P",
    "gn:feature_code":"PPL",
    "gn:name":"Simen",
    "gn:population":0,
    "gn:timezone":"Asia/Shanghai",
    "iso:country":"CN",
    "name:deu_x_preferred":[
        "Simen"
    ],
    "name:nor_x_preferred":[
        "Simen"
    ],
    "name:zho_x_preferred":[
        "\u6cd7\u95e8"
    ],
    "wof:name":"Simen",
    "wof:placetype":"locality"
},
  "geometry": {"coordinates":[111.126,23.2668],"type":"Point"}
}