{
  "type": "Feature",
  "properties": {
    "gn:admin1_code":"32.0",
    "gn:asciiname":"Aguolaoda",
    "gn:country_code":"CN",
    "gn:dem":2162,
    "gn:feature_class":"P",
    "gn:feature_code":"PPL",
    "gn:name":"Aguolaoda",
    "gn:population":0,
    "gn:timezone":"Asia/Shanghai",
    "iso:country":"CN",
    "name:zho_x_preferred":[
        "\u963f\u679c\u8001\u6253"
    ],
    "wof:name":"Aguolaoda",
    "wof:placetype":"locality"
},
  "geometry": {"coordinates":[102.62341000000001,27.28168],"type":"Point"}
}