{
  "type": "Feature",
  "properties": {
    "gn:admin1_code":"3.0",
    "gn:asciiname":"Kangyuancun",
    "gn:country_code":"CN",
    "gn:dem":24,
    "gn:feature_class":"P",
    "gn:feature_code":"PPL",
    "gn:name":"Kangyuancun",
    "gn:population":0,
    "gn:timezone":"Asia/Shanghai",
    "iso:country":"CN",
    "name:und_x_variant":[
        "\u6297\u63f4\u6751"
    ],
    "wof:name":"Kangyuancun",
    "wof:placetype":"locality"
},
  "geometry": {"coordinates":[115.64265,28.35254],"type":"Point"}
}