{
  "type": "Feature",
  "properties": {
    "gn:admin1_code":"18",
    "gn:asciiname":"Shashuping",
    "gn:country_code":"CN",
    "gn:dem":911,
    "gn:feature_class":"P",
    "gn:feature_code":"PPL",
    "gn:name":"Shashuping",
    "gn:population":0,
    "gn:timezone":"Asia/Shanghai",
    "iso:country":"CN",
    "name:zho_x_preferred":[
        "\u6749\u6811\u576a"
    ],
    "wof:name":"Shashuping",
    "wof:placetype":"locality"
},
  "geometry": {"coordinates":[105.70999999999999,28.4309],"type":"Point"}
}