{
  "type": "Feature",
  "properties": {
    "gn:admin1_code":"9.0",
    "gn:asciiname":"Beiyinpo",
    "gn:country_code":"CN",
    "gn:dem":194,
    "gn:feature_class":"P",
    "gn:feature_code":"PPL",
    "gn:name":"Beiyinpo",
    "gn:population":0,
    "gn:timezone":"Asia/Shanghai",
    "iso:country":"CN",
    "name:und_x_variant":[
        "\u80cc\u9634\u5761",
        "Beiyinpo"
    ],
    "wof:name":"Beiyinpo",
    "wof:placetype":"locality"
},
  "geometry": {"coordinates":[112.48475000000001,33.42273],"type":"Point"}
}