{
  "type": "Feature",
  "properties": {
    "gn:admin1_code":"26.0",
    "gn:asciiname":"Baishuba",
    "gn:country_code":"CN",
    "gn:dem":1404,
    "gn:feature_class":"P",
    "gn:feature_code":"PPL",
    "gn:name":"Baishuba",
    "gn:population":0,
    "gn:timezone":"Asia/Shanghai",
    "iso:country":"CN",
    "name:und_x_variant":[
        "\u67cf\u6811\u575d"
    ],
    "wof:name":"Baishuba",
    "wof:placetype":"locality"
},
  "geometry": {"coordinates":[106.51206999999999,33.48818],"type":"Point"}
}