{
  "type": "Feature",
  "properties": {
    "gn:admin1_code":"18",
    "gn:asciiname":"Dianzibian",
    "gn:country_code":"CN",
    "gn:dem":965,
    "gn:feature_class":"P",
    "gn:feature_code":"PPL",
    "gn:name":"Dianzibian",
    "gn:population":0,
    "gn:timezone":"Asia/Shanghai",
    "iso:country":"CN",
    "name:zho_x_preferred":[
        "\u5e97\u5b50\u8fb9"
    ],
    "wof:name":"Dianzibian",
    "wof:placetype":"locality"
},
  "geometry": {"coordinates":[106.964,25.6693],"type":"Point"}
}