{
  "type": "Feature",
  "properties": {
    "gn:admin1_code":"11.0",
    "gn:asciiname":"Cangjingdian",
    "gn:country_code":"CN",
    "gn:dem":1085,
    "gn:feature_class":"P",
    "gn:feature_code":"PPL",
    "gn:name":"Cangjingdian",
    "gn:population":0,
    "gn:timezone":"Asia/Shanghai",
    "iso:country":"CN",
    "name:zho_x_preferred":[
        "\u85cf\u7ecf\u6bbf"
    ],
    "wof:name":"Cangjingdian",
    "wof:placetype":"locality"
},
  "geometry": {"coordinates":[112.67426,27.27767],"type":"Point"}
}