{
  "type": "Feature",
  "properties": {
    "gn:admin1_code":"8.0",
    "gn:asciiname":"Huazishancun",
    "gn:country_code":"CN",
    "gn:dem":125,
    "gn:feature_class":"P",
    "gn:feature_code":"PPL",
    "gn:name":"Huazishancun",
    "gn:population":0,
    "gn:timezone":"Asia/Shanghai",
    "iso:country":"CN",
    "name:zho_x_preferred":[
        "\u94e7\u5b50\u5c71\u6751"
    ],
    "wof:name":"Huazishancun",
    "wof:placetype":"locality"
},
  "geometry": {"coordinates":[128.67751999999999,46.04909],"type":"Point"}
}