{
  "type": "Feature",
  "properties": {
    "gn:admin1_code":"24.0",
    "gn:asciiname":"Shanzhuangtou",
    "gn:country_code":"CN",
    "gn:dem":1517,
    "gn:feature_class":"P",
    "gn:feature_code":"PPL",
    "gn:name":"Shanzhuangtou",
    "gn:population":0,
    "gn:timezone":"Asia/Shanghai",
    "iso:country":"CN",
    "name:zho_x_preferred":[
        "\u5c71\u5e84\u5934"
    ],
    "wof:name":"Shanzhuangtou",
    "wof:placetype":"locality"
},
  "geometry": {"coordinates":[111.63405,37.94501],"type":"Point"}
}