{
  "type": "Feature",
  "properties": {
    "gn:admin1_code":"02",
    "gn:asciiname":"Meilingcun",
    "gn:country_code":"CN",
    "gn:dem":168,
    "gn:feature_class":"P",
    "gn:feature_code":"PPL",
    "gn:name":"Meilingcun",
    "gn:population":0,
    "gn:timezone":"Asia/Shanghai",
    "iso:country":"CN",
    "name:und_x_variant":[
        "Meiling"
    ],
    "name:zho_x_preferred":[
        "\u6885\u5cad\u6751"
    ],
    "wof:name":"Meilingcun",
    "wof:placetype":"locality"
},
  "geometry": {"coordinates":[121.65096,29.66389],"type":"Point"}
}