{
  "type": "Feature",
  "properties": {
    "gn:admin1_code":"11.0",
    "gn:asciiname":"Donghuang",
    "gn:country_code":"CN",
    "gn:dem":430,
    "gn:feature_class":"P",
    "gn:feature_code":"PPL",
    "gn:name":"Donghuang",
    "gn:population":0,
    "gn:timezone":"Asia/Shanghai",
    "iso:country":"CN",
    "name:zho_x_preferred":[
        "\u4e1c\u9ec4"
    ],
    "wof:name":"Donghuang",
    "wof:placetype":"locality"
},
  "geometry": {"coordinates":[113.70658,27.05432],"type":"Point"}
}