{
  "type": "Feature",
  "properties": {
    "gn:admin1_code":"18",
    "gn:asciiname":"Mawan",
    "gn:country_code":"CN",
    "gn:dem":1130,
    "gn:feature_class":"P",
    "gn:feature_code":"PPL",
    "gn:name":"Mawan",
    "gn:population":0,
    "gn:timezone":"Asia/Shanghai",
    "iso:country":"CN",
    "name:ceb_x_preferred":[
        "Mawan"
    ],
    "name:swe_x_preferred":[
        "Mawan"
    ],
    "name:zho_x_preferred":[
        "\u9ebb\u6e7e"
    ],
    "wof:name":"Mawan",
    "wof:placetype":"locality"
},
  "geometry": {"coordinates":[108.04600000000001,27.3547],"type":"Point"}
}