{
  "type": "Feature",
  "properties": {
    "gn:admin1_code":"06",
    "gn:asciiname":"Batan",
    "gn:country_code":"CN",
    "gn:dem":3272,
    "gn:feature_class":"P",
    "gn:feature_code":"PPL",
    "gn:name":"Batan",
    "gn:population":0,
    "gn:timezone":"Asia/Shanghai",
    "iso:country":"CN",
    "name:ceb_x_preferred":[
        "Batan"
    ],
    "name:deu_x_preferred":[
        "Batan"
    ],
    "name:fra_x_preferred":[
        "Batan"
    ],
    "name:ilo_x_preferred":[
        "Batan"
    ],
    "name:ita_x_preferred":[
        "Batan"
    ],
    "name:nld_x_preferred":[
        "Batan"
    ],
    "name:pol_x_preferred":[
        "Batan"
    ],
    "name:rus_x_preferred":[
        "\u0411\u0430\u0442\u0430\u043d"
    ],
    "name:spa_x_preferred":[
        "Bat\u00e1n"
    ],
    "name:swe_x_preferred":[
        "Batan"
    ],
    "name:ukr_x_preferred":[
        "\u0411\u0430\u0442\u0430\u043d"
    ],
    "wof:name":"Batan",
    "wof:placetype":"locality"
},
  "geometry": {"coordinates":[100.59999999999999,35.25],"type":"Point"}
}