{
  "type": "Feature",
  "properties": {
    "gn:admin1_code":"5.0",
    "gn:asciiname":"Dongxingtun",
    "gn:country_code":"CN",
    "gn:dem":368,
    "gn:feature_class":"P",
    "gn:feature_code":"PPL",
    "gn:name":"Dongxingtun",
    "gn:population":0,
    "gn:timezone":"Asia/Shanghai",
    "iso:country":"CN",
    "name:und_x_variant":[
        "\u4e1c\u5174\u5c6f"
    ],
    "wof:name":"Dongxingtun",
    "wof:placetype":"locality"
},
  "geometry": {"coordinates":[127.27052999999999,43.04528],"type":"Point"}
}