{
  "type": "Feature",
  "properties": {
    "gn:admin1_code":"29.0",
    "gn:asciiname":"Shangcang",
    "gn:country_code":"CN",
    "gn:dem":1857,
    "gn:feature_class":"P",
    "gn:feature_code":"PPL",
    "gn:name":"Shangcang",
    "gn:population":0,
    "gn:timezone":"Asia/Shanghai",
    "iso:country":"CN",
    "name:zho_x_preferred":[
        "\u4e0a\u6ca7"
    ],
    "wof:name":"Shangcang",
    "wof:placetype":"locality"
},
  "geometry": {"coordinates":[100.354,25.818],"type":"Point"}
}