{
  "type": "Feature",
  "properties": {
    "gn:admin1_code":"15.0",
    "gn:asciiname":"Kangfeng",
    "gn:country_code":"CN",
    "gn:dem":2967,
    "gn:feature_class":"P",
    "gn:feature_code":"PPL",
    "gn:name":"Kangfeng",
    "gn:population":0,
    "gn:timezone":"Asia/Shanghai",
    "iso:country":"CN",
    "name:zho_x_preferred":[
        "\u5eb7\u4e30"
    ],
    "wof:name":"Kangfeng",
    "wof:placetype":"locality"
},
  "geometry": {"coordinates":[99.86839999999999,38.809],"type":"Point"}
}