{
  "type": "Feature",
  "properties": {
    "gn:admin1_code":"12.0",
    "gn:asciiname":"Jinzhuyuan",
    "gn:country_code":"CN",
    "gn:dem":691,
    "gn:feature_class":"P",
    "gn:feature_code":"PPL",
    "gn:name":"Jinzhuyuan",
    "gn:population":0,
    "gn:timezone":"Asia/Shanghai",
    "iso:country":"CN",
    "name:zho_x_preferred":[
        "\u91d1\u7af9\u56ed"
    ],
    "wof:name":"Jinzhuyuan",
    "wof:placetype":"locality"
},
  "geometry": {"coordinates":[109.67298,30.55956],"type":"Point"}
}