{
  "type": "Feature",
  "properties": {
    "gn:admin1_code":"03",
    "gn:asciiname":"Hukeng",
    "gn:country_code":"CN",
    "gn:dem":235,
    "gn:feature_class":"P",
    "gn:feature_code":"PPLA4",
    "gn:name":"Hukeng",
    "gn:population":0,
    "gn:timezone":"Asia/Shanghai",
    "iso:country":"CN",
    "name:und_x_variant":[
        "\u6d52\u5751",
        "Hukeng Zhen",
        "\u6d52\u5751\u9547"
    ],
    "wof:name":"Hukeng",
    "wof:placetype":"locality"
},
  "geometry": {"coordinates":[114.30843,27.47302],"type":"Point"}
}