{
  "type": "Feature",
  "properties": {
    "gn:admin1_code":"24",
    "gn:asciiname":"Shijiazhuang",
    "gn:cc2":"CN",
    "gn:country_code":"CN",
    "gn:dem":1103,
    "gn:feature_class":"P",
    "gn:feature_code":"PPL",
    "gn:name":"Shijiazhuang",
    "gn:population":0,
    "gn:timezone":"Asia/Shanghai",
    "iso:country":"CN",
    "name:rus_x_preferred":[
        "\u0428\u0438\u0446\u0437\u044f\u0447\u0436\u0443\u0430\u043d"
    ],
    "name:und_x_variant":[
        "Huashan",
        "Shih-chia-chuang",
        "Shijiazhuang"
    ],
    "wof:name":"Shijiazhuang",
    "wof:placetype":"locality"
},
  "geometry": {"coordinates":[114.14722,39.505],"type":"Point"}
}