{
  "type": "Feature",
  "properties": {
    "gn:admin1_code":"4.0",
    "gn:asciiname":"Wangkengcun",
    "gn:country_code":"CN",
    "gn:dem":39,
    "gn:feature_class":"P",
    "gn:feature_code":"PPL",
    "gn:name":"Wangkengcun",
    "gn:population":0,
    "gn:timezone":"Asia/Shanghai",
    "iso:country":"CN",
    "name:und_x_variant":[
        "Wangkeng",
        "Wangkengcun"
    ],
    "name:zho_x_preferred":[
        "\u738b\u5751"
    ],
    "name:zho_x_variant":[
        "\u738b\u5751\u6751"
    ],
    "wof:name":"Wangkengcun",
    "wof:placetype":"locality"
},
  "geometry": {"coordinates":[116.89507999999999,34.85248],"type":"Point"}
}