{
  "type": "Feature",
  "properties": {
    "gn:admin1_code":"03",
    "gn:asciiname":"Minhe",
    "gn:cc2":"CN",
    "gn:country_code":"CN",
    "gn:dem":39,
    "gn:feature_class":"P",
    "gn:feature_code":"PPL",
    "gn:name":"Minhe",
    "gn:population":0,
    "gn:timezone":"Asia/Shanghai",
    "iso:country":"CN",
    "name:und_x_variant":[
        "Jinxian",
        "Chin-hsien-hsien-ch\u2019eng",
        "Tsinsien",
        "Chin-hsien-hsien",
        "Tsinsienhsien",
        "Chin-hsien",
        "Minhe"
    ],
    "wof:name":"Minhe",
    "wof:placetype":"locality"
},
  "geometry": {"coordinates":[116.23333,28.36667000000001],"type":"Point"}
}