{
  "type": "Feature",
  "properties": {
    "gn:admin1_code":"16",
    "gn:asciiname":"Ganshanping",
    "gn:country_code":"CN",
    "gn:dem":378,
    "gn:feature_class":"P",
    "gn:feature_code":"PPL",
    "gn:name":"Ganshanping",
    "gn:population":0,
    "gn:timezone":"Asia/Shanghai",
    "iso:country":"CN",
    "name:zho_x_preferred":[
        "\u5e72\u5c71\u576a"
    ],
    "wof:name":"Ganshanping",
    "wof:placetype":"locality"
},
  "geometry": {"coordinates":[111.137,25.7638],"type":"Point"}
}