{
  "type": "Feature",
  "properties": {
    "gn:admin1_code":"19.0",
    "gn:asciiname":"Congjiagou",
    "gn:country_code":"CN",
    "gn:dem":686,
    "gn:feature_class":"P",
    "gn:feature_code":"PPL",
    "gn:name":"Congjiagou",
    "gn:population":0,
    "gn:timezone":"Asia/Shanghai",
    "iso:country":"CN",
    "name:zho_x_preferred":[
        "\u4e1b\u5bb6\u6c9f"
    ],
    "wof:name":"Congjiagou",
    "wof:placetype":"locality"
},
  "geometry": {"coordinates":[119.791,41.6882],"type":"Point"}
}