{
  "type": "Feature",
  "properties": {
    "gn:admin1_code":"26.0",
    "gn:asciiname":"Qinshancun",
    "gn:country_code":"CN",
    "gn:dem":935,
    "gn:feature_class":"P",
    "gn:feature_code":"PPL",
    "gn:name":"Qinshancun",
    "gn:population":0,
    "gn:timezone":"Asia/Shanghai",
    "iso:country":"CN",
    "name:zho_x_preferred":[
        "\u79e6\u5c71\u6751"
    ],
    "wof:name":"Qinshancun",
    "wof:placetype":"locality"
},
  "geometry": {"coordinates":[110.09743,37.88535],"type":"Point"}
}