{
  "type": "Feature",
  "properties": {
    "gn:admin1_code":"26.0",
    "gn:asciiname":"Yukoucun",
    "gn:country_code":"CN",
    "gn:dem":892,
    "gn:feature_class":"P",
    "gn:feature_code":"PPL",
    "gn:name":"Yukoucun",
    "gn:population":0,
    "gn:timezone":"Asia/Shanghai",
    "iso:country":"CN",
    "name:zho_x_preferred":[
        "\u5cea\u53e3\u6751"
    ],
    "wof:name":"Yukoucun",
    "wof:placetype":"locality"
},
  "geometry": {"coordinates":[109.35456000000001,35.84366],"type":"Point"}
}