{
  "type": "Feature",
  "properties": {
    "gn:admin1_code":"12.0",
    "gn:asciiname":"Zhoucao",
    "gn:country_code":"CN",
    "gn:dem":29,
    "gn:feature_class":"P",
    "gn:feature_code":"PPL",
    "gn:name":"Zhoucao",
    "gn:population":0,
    "gn:timezone":"Asia/Shanghai",
    "iso:country":"CN",
    "name:und_x_variant":[
        "\u5468\u66f9"
    ],
    "wof:name":"Zhoucao",
    "wof:placetype":"locality"
},
  "geometry": {"coordinates":[114.52928,30.57324],"type":"Point"}
}