{
  "type": "Feature",
  "properties": {
    "gn:admin1_code":"33.0",
    "gn:asciiname":"Longtiao",
    "gn:country_code":"CN",
    "gn:dem":976,
    "gn:feature_class":"P",
    "gn:feature_code":"PPL",
    "gn:name":"Longtiao",
    "gn:population":0,
    "gn:timezone":"Asia/Shanghai",
    "iso:country":"CN",
    "name:zho_x_preferred":[
        "\u9f99\u773a"
    ],
    "wof:name":"Longtiao",
    "wof:placetype":"locality"
},
  "geometry": {"coordinates":[108.37645000000001,31.45009000000001],"type":"Point"}
}