{
  "type": "Feature",
  "properties": {
    "gn:admin1_code":"29.0",
    "gn:asciiname":"Xingyang",
    "gn:country_code":"CN",
    "gn:dem":1724,
    "gn:feature_class":"P",
    "gn:feature_code":"PPL",
    "gn:name":"Xingyang",
    "gn:population":0,
    "gn:timezone":"Asia/Shanghai",
    "iso:country":"CN",
    "name:deu_x_preferred":[
        "Xingyang"
    ],
    "name:eus_x_preferred":[
        "Xingyang"
    ],
    "name:fra_x_preferred":[
        "Xingyang"
    ],
    "name:ita_x_preferred":[
        "Xingyang"
    ],
    "name:jpn_x_preferred":[
        "\u30b1\u30a4\u967d\u5e02"
    ],
    "name:kik_x_preferred":[
        "Xingyang"
    ],
    "name:kor_x_preferred":[
        "\uc2f1\uc591\uc2dc"
    ],
    "name:nor_x_preferred":[
        "Xingyang"
    ],
    "name:pam_x_preferred":[
        "Xingyang"
    ],
    "name:rus_x_preferred":[
        "\u0421\u0438\u043d\u044a\u044f\u043d"
    ],
    "name:spa_x_preferred":[
        "Xingyang"
    ],
    "name:swe_x_preferred":[
        "Xingyang"
    ],
    "name:urd_x_preferred":[
        "\u0634\u0646\u06af\u06cc\u0627\u0646\u06af"
    ],
    "name:vie_x_preferred":[
        "Hu\u1ef3nh D\u01b0\u01a1ng"
    ],
    "name:zho_x_preferred":[
        "\u8365\u9633"
    ],
    "name:zho_x_variant":[
        "\u8365\u9633\u5e02"
    ],
    "wof:name":"Xingyang",
    "wof:placetype":"locality"
},
  "geometry": {"coordinates":[98.5031,25.2942],"type":"Point"}
}