{
  "type": "Feature",
  "properties": {
    "gn:admin1_code":"14.0",
    "gn:asciiname":"Chimoin",
    "gn:country_code":"CN",
    "gn:dem":3604,
    "gn:feature_class":"P",
    "gn:feature_code":"PPLF",
    "gn:name":"Chimoin",
    "gn:population":0,
    "gn:timezone":"Asia/Urumqi",
    "iso:country":"CN",
    "name:bod_x_preferred":[
        "Chimoin"
    ],
    "name:zho_x_preferred":[
        "Chemen"
    ],
    "name:zho_x_variant":[
        "\u8f66\u95e8",
        "Sangzhugang",
        "\u6851\u73e0\u5c97"
    ],
    "wof:name":"Chimoin",
    "wof:placetype":"locality"
},
  "geometry": {"coordinates":[91.83595,29.32301],"type":"Point"}
}