{
  "type": "Feature",
  "properties": {
    "gn:admin1_code":"26",
    "gn:asciiname":"Qiaobai",
    "gn:country_code":"CN",
    "gn:dem":382,
    "gn:feature_class":"P",
    "gn:feature_code":"PPL",
    "gn:name":"Qiaobai",
    "gn:population":0,
    "gn:timezone":"Asia/Shanghai",
    "iso:country":"CN",
    "name:und_x_variant":[
        "\u6865\u767d",
        "Qiaobai"
    ],
    "wof:name":"Qiaobai",
    "wof:placetype":"locality"
},
  "geometry": {"coordinates":[109.12671,34.59743],"type":"Point"}
}