{
  "type": "Feature",
  "properties": {
    "gn:admin1_code":"5.0",
    "gn:asciiname":"Xiangfutun",
    "gn:country_code":"CN",
    "gn:dem":316,
    "gn:feature_class":"P",
    "gn:feature_code":"PPL",
    "gn:name":"Xiangfutun",
    "gn:population":0,
    "gn:timezone":"Asia/Shanghai",
    "iso:country":"CN",
    "name:zho_x_preferred":[
        "\u5411\u5bcc\u5c6f"
    ],
    "wof:name":"Xiangfutun",
    "wof:placetype":"locality"
},
  "geometry": {"coordinates":[125.19150999999999,42.84795],"type":"Point"}
}