{
  "type": "Feature",
  "properties": {
    "gn:admin1_code":"19.0",
    "gn:asciiname":"Xingyuanmao",
    "gn:country_code":"CN",
    "gn:dem":192,
    "gn:feature_class":"P",
    "gn:feature_code":"PPL",
    "gn:name":"Xingyuanmao",
    "gn:population":0,
    "gn:timezone":"Asia/Shanghai",
    "iso:country":"CN",
    "name:zho_x_preferred":[
        "\u5174\u6e90\u8302"
    ],
    "wof:name":"Xingyuanmao",
    "wof:placetype":"locality"
},
  "geometry": {"coordinates":[122.273,39.9003],"type":"Point"}
}