{
  "type": "Feature",
  "properties": {
    "gn:admin1_code":"16",
    "gn:asciiname":"He'an",
    "gn:country_code":"CN",
    "gn:dem":143,
    "gn:feature_class":"P",
    "gn:feature_code":"PPL",
    "gn:name":"He\u2019an",
    "gn:population":0,
    "gn:timezone":"Asia/Shanghai",
    "iso:country":"CN",
    "name:und_x_variant":[
        "He\u2019an"
    ],
    "name:zho_x_preferred":[
        "\u5408\u5b89"
    ],
    "wof:name":"He'an",
    "wof:placetype":"locality"
},
  "geometry": {"coordinates":[110.43300000000001,24.5737],"type":"Point"}
}