{
  "type": "Feature",
  "properties": {
    "gn:admin1_code":"10.0",
    "gn:asciiname":"Gengxinzhuang",
    "gn:country_code":"CN",
    "gn:dem":107,
    "gn:feature_class":"P",
    "gn:feature_code":"PPL",
    "gn:name":"Gengxinzhuang",
    "gn:population":0,
    "gn:timezone":"Asia/Shanghai",
    "iso:country":"CN",
    "name:zho_x_preferred":[
        "\u66f4\u65b0\u5e84"
    ],
    "wof:name":"Gengxinzhuang",
    "wof:placetype":"locality"
},
  "geometry": {"coordinates":[118.63339000000001,40.19026],"type":"Point"}
}