{
  "type": "Feature",
  "properties": {
    "gn:admin1_code":"14.0",
    "gn:asciiname":"Sangdeng",
    "gn:country_code":"CN",
    "gn:dem":3809,
    "gn:feature_class":"P",
    "gn:feature_code":"PPL",
    "gn:name":"Sangdeng",
    "gn:population":0,
    "gn:timezone":"Asia/Urumqi",
    "iso:country":"CN",
    "name:zho_x_preferred":[
        "\u6851\u767b"
    ],
    "wof:name":"Sangdeng",
    "wof:placetype":"locality"
},
  "geometry": {"coordinates":[91.09804,29.7204],"type":"Point"}
}