{
  "type": "Feature",
  "properties": {
    "gn:admin1_code":"26.0",
    "gn:asciiname":"Qishuwan",
    "gn:country_code":"CN",
    "gn:dem":480,
    "gn:feature_class":"P",
    "gn:feature_code":"PPL",
    "gn:name":"Qishuwan",
    "gn:population":0,
    "gn:timezone":"Asia/Shanghai",
    "iso:country":"CN",
    "name:zho_x_preferred":[
        "\u6f06\u6811\u6e7e"
    ],
    "wof:name":"Qishuwan",
    "wof:placetype":"locality"
},
  "geometry": {"coordinates":[109.30271,32.44168],"type":"Point"}
}