{
  "type": "Feature",
  "properties": {
    "gn:admin1_code":"26.0",
    "gn:asciiname":"Matitacun",
    "gn:country_code":"CN",
    "gn:dem":895,
    "gn:feature_class":"P",
    "gn:feature_code":"PPL",
    "gn:name":"Matitacun",
    "gn:population":0,
    "gn:timezone":"Asia/Shanghai",
    "iso:country":"CN",
    "name:zho_x_preferred":[
        "\u9a6c\u8e44\u584c\u6751"
    ],
    "wof:name":"Matitacun",
    "wof:placetype":"locality"
},
  "geometry": {"coordinates":[110.66997000000001,37.74706],"type":"Point"}
}