{
  "type": "Feature",
  "properties": {
    "gn:admin1_code":"16.0",
    "gn:asciiname":"Dingziling",
    "gn:country_code":"CN",
    "gn:dem":38,
    "gn:feature_class":"P",
    "gn:feature_code":"PPL",
    "gn:name":"Dingziling",
    "gn:population":0,
    "gn:timezone":"Asia/Shanghai",
    "iso:country":"CN",
    "name:zho_x_preferred":[
        "\u5b9a\u5b50\u5cad"
    ],
    "wof:name":"Dingziling",
    "wof:placetype":"locality"
},
  "geometry": {"coordinates":[110.23699999999999,23.5796],"type":"Point"}
}