{
  "type": "Feature",
  "properties": {
    "gn:admin1_code":"19.0",
    "gn:asciiname":"Yangzhu",
    "gn:country_code":"CN",
    "gn:dem":55,
    "gn:feature_class":"P",
    "gn:feature_code":"PPL",
    "gn:name":"Yangzhu",
    "gn:population":0,
    "gn:timezone":"Asia/Shanghai",
    "iso:country":"CN",
    "name:und_x_variant":[
        "\u517b\u7af9"
    ],
    "name:zho_x_preferred":[
        "\u517b\u7af9"
    ],
    "wof:name":"Yangzhu",
    "wof:placetype":"locality"
},
  "geometry": {"coordinates":[123.57599,41.7702],"type":"Point"}
}