{
  "type": "Feature",
  "properties": {
    "gn:admin1_code":"15.0",
    "gn:asciiname":"Zuopu",
    "gn:country_code":"CN",
    "gn:dem":2544,
    "gn:feature_class":"P",
    "gn:feature_code":"PPL",
    "gn:name":"Zuopu",
    "gn:population":0,
    "gn:timezone":"Asia/Shanghai",
    "iso:country":"CN",
    "name:und_x_variant":[
        "\u4f50\u666e"
    ],
    "wof:name":"Zuopu",
    "wof:placetype":"locality"
},
  "geometry": {"coordinates":[102.80668,35.22264000000001],"type":"Point"}
}