{
  "type": "Feature",
  "properties": {
    "gn:admin1_code":"30.0",
    "gn:asciiname":"Aozai",
    "gn:country_code":"CN",
    "gn:dem":397,
    "gn:feature_class":"P",
    "gn:feature_code":"PPL",
    "gn:name":"Aozai",
    "gn:population":0,
    "gn:timezone":"Asia/Shanghai",
    "iso:country":"CN",
    "name:zho_x_preferred":[
        "\u51f9\u4ed4"
    ],
    "wof:name":"Aozai",
    "wof:placetype":"locality"
},
  "geometry": {"coordinates":[111.9834,22.92971],"type":"Point"}
}