{
  "type": "Feature",
  "properties": {
    "gn:admin1_code":"29.0",
    "gn:asciiname":"Egeng",
    "gn:country_code":"CN",
    "gn:dem":2605,
    "gn:feature_class":"P",
    "gn:feature_code":"PPL",
    "gn:name":"Egeng",
    "gn:population":0,
    "gn:timezone":"Asia/Shanghai",
    "iso:country":"CN",
    "name:zho_x_preferred":[
        "\u4fc4\u803f"
    ],
    "wof:name":"Egeng",
    "wof:placetype":"locality"
},
  "geometry": {"coordinates":[99.7088,25.8018],"type":"Point"}
}