{
  "type": "Feature",
  "properties": {
    "gn:admin1_code":"25",
    "gn:asciiname":"Maosunjia",
    "gn:country_code":"CN",
    "gn:dem":16,
    "gn:feature_class":"P",
    "gn:feature_code":"PPL",
    "gn:name":"Maosunjia",
    "gn:population":0,
    "gn:timezone":"Asia/Shanghai",
    "iso:country":"CN",
    "name:zho_x_preferred":[
        "\u8302\u5b59\u5bb6"
    ],
    "wof:name":"Maosunjia",
    "wof:placetype":"locality"
},
  "geometry": {"coordinates":[116.86499999999999,37.747],"type":"Point"}
}