{
  "type": "Feature",
  "properties": {
    "gn:admin1_code":"12.0",
    "gn:asciiname":"Songjiawan",
    "gn:country_code":"CN",
    "gn:dem":23,
    "gn:feature_class":"P",
    "gn:feature_code":"PPL",
    "gn:name":"Songjiawan",
    "gn:population":0,
    "gn:timezone":"Asia/Shanghai",
    "iso:country":"CN",
    "name:und_x_variant":[
        "\u5b8b\u5bb6\u5846"
    ],
    "wof:name":"Songjiawan",
    "wof:placetype":"locality"
},
  "geometry": {"coordinates":[114.78425,30.4165],"type":"Point"}
}