{
  "type": "Feature",
  "properties": {
    "gn:admin1_code":"14.0",
    "gn:asciiname":"Dangaxiajuecun",
    "gn:country_code":"CN",
    "gn:dem":3012,
    "gn:feature_class":"P",
    "gn:feature_code":"PPL",
    "gn:name":"Dangaxiajuecun",
    "gn:population":0,
    "gn:timezone":"Asia/Urumqi",
    "iso:country":"CN",
    "name:zho_x_preferred":[
        "\u5355\u560e\u4e0b\u89c9\u6751"
    ],
    "wof:name":"Dangaxiajuecun",
    "wof:placetype":"locality"
},
  "geometry": {"coordinates":[93.52639000000001,29.1779],"type":"Point"}
}