{
  "type": "Feature",
  "properties": {
    "gn:admin1_code":"26.0",
    "gn:asciiname":"Songchayucun",
    "gn:country_code":"CN",
    "gn:dem":1108,
    "gn:feature_class":"P",
    "gn:feature_code":"PPL",
    "gn:name":"Songchayucun",
    "gn:population":0,
    "gn:timezone":"Asia/Shanghai",
    "iso:country":"CN",
    "name:zho_x_preferred":[
        "\u5d69\u5c94\u5cea\u6751"
    ],
    "wof:name":"Songchayucun",
    "wof:placetype":"locality"
},
  "geometry": {"coordinates":[109.96644999999999,37.26367],"type":"Point"}
}