{
  "type": "Feature",
  "properties": {
    "gn:admin1_code":"14.0",
    "gn:asciiname":"Malaci",
    "gn:country_code":"CN",
    "gn:dem":4128,
    "gn:feature_class":"P",
    "gn:feature_code":"PPL",
    "gn:name":"Malaci",
    "gn:population":0,
    "gn:timezone":"Asia/Urumqi",
    "iso:country":"CN",
    "name:zho_x_preferred":[
        "\u9a6c\u62c9\u6b64"
    ],
    "wof:name":"Malaci",
    "wof:placetype":"locality"
},
  "geometry": {"coordinates":[96.52298,29.44206],"type":"Point"}
}