{
  "type": "Feature",
  "properties": {
    "gn:admin1_code":"29",
    "gn:asciiname":"Zhaojiacun",
    "gn:country_code":"CN",
    "gn:dem":1995,
    "gn:feature_class":"P",
    "gn:feature_code":"PPL",
    "gn:name":"Zhaojiacun",
    "gn:population":0,
    "gn:timezone":"Asia/Shanghai",
    "iso:country":"CN",
    "name:zho_x_preferred":[
        "\u8d75\u5bb6\u6751"
    ],
    "wof:name":"Zhaojiacun",
    "wof:placetype":"locality"
},
  "geometry": {"coordinates":[102.11465,24.86505],"type":"Point"}
}