{
  "type": "Feature",
  "properties": {
    "gn:admin1_code":"24.0",
    "gn:asciiname":"Yulincun",
    "gn:country_code":"CN",
    "gn:dem":841,
    "gn:feature_class":"P",
    "gn:feature_code":"PPL",
    "gn:name":"Yulincun",
    "gn:population":0,
    "gn:timezone":"Asia/Shanghai",
    "iso:country":"CN",
    "name:zho_x_preferred":[
        "\u96e8\u6797\u6751"
    ],
    "wof:name":"Yulincun",
    "wof:placetype":"locality"
},
  "geometry": {"coordinates":[110.47387000000001,36.6565],"type":"Point"}
}