{
  "type": "Feature",
  "properties": {
    "gn:admin1_code":"2.0",
    "gn:asciiname":"Jiuli",
    "gn:country_code":"CN",
    "gn:dem":115,
    "gn:feature_class":"P",
    "gn:feature_code":"PPL",
    "gn:name":"Jiuli",
    "gn:population":0,
    "gn:timezone":"Asia/Shanghai",
    "iso:country":"CN",
    "name:ceb_x_preferred":[
        "Jiuli"
    ],
    "name:deu_x_preferred":[
        "Jiuli"
    ],
    "name:swe_x_preferred":[
        "Jiuli"
    ],
    "name:und_x_variant":[
        "\u4e5d\u91cc"
    ],
    "wof:name":"Jiuli",
    "wof:placetype":"locality"
},
  "geometry": {"coordinates":[119.42489,30.18546],"type":"Point"}
}