{
  "type": "Feature",
  "properties": {
    "gn:admin1_code":"05",
    "gn:asciiname":"Donggaojiatun",
    "gn:country_code":"CN",
    "gn:dem":250,
    "gn:feature_class":"P",
    "gn:feature_code":"PPL",
    "gn:name":"Donggaojiatun",
    "gn:population":0,
    "gn:timezone":"Asia/Shanghai",
    "iso:country":"CN",
    "wof:name":"Donggaojiatun",
    "wof:placetype":"locality"
},
  "geometry": {"coordinates":[125.17278,43.38611],"type":"Point"}
}