{
  "type": "Feature",
  "properties": {
    "gn:admin1_code":"12",
    "gn:asciiname":"Tingqian",
    "gn:country_code":"CN",
    "gn:dem":69,
    "gn:feature_class":"P",
    "gn:feature_code":"PPLA4",
    "gn:name":"Tingqian",
    "gn:population":0,
    "gn:timezone":"Asia/Shanghai",
    "iso:country":"CN",
    "name:und_x_variant":[
        "T\u2019ing-ch\u2019ien-i",
        "T\u2019ing-ch\u2019ien",
        "Tingqian",
        "Tingqian Zhen",
        "\u505c\u524d\u9547"
    ],
    "name:zho_x_preferred":[
        "\u505c\u524d"
    ],
    "wof:name":"Tingqian",
    "wof:placetype":"locality"
},
  "geometry": {"coordinates":[115.97707,30.21277000000001],"type":"Point"}
}