{
  "type": "Feature",
  "properties": {
    "gn:admin1_code":"4.0",
    "gn:asciiname":"Liangshacun",
    "gn:country_code":"CN",
    "gn:dem":5,
    "gn:feature_class":"P",
    "gn:feature_code":"PPL",
    "gn:name":"Liangshacun",
    "gn:population":0,
    "gn:timezone":"Asia/Shanghai",
    "iso:country":"CN",
    "name:zho_x_preferred":[
        "\u6881\u6c99\u6751"
    ],
    "wof:name":"Liangshacun",
    "wof:placetype":"locality"
},
  "geometry": {"coordinates":[119.19128000000001,34.91711],"type":"Point"}
}