{
  "type": "Feature",
  "properties": {
    "gn:admin1_code":"4.0",
    "gn:asciiname":"Xingang",
    "gn:country_code":"CN",
    "gn:dem":5,
    "gn:feature_class":"P",
    "gn:feature_code":"PPL",
    "gn:name":"Xingang",
    "gn:population":0,
    "gn:timezone":"Asia/Shanghai",
    "iso:country":"CN",
    "name:und_x_variant":[
        "Hsin-chiang-chen",
        "Hsin-kang-chen",
        "Xingang",
        "\u65b0\u6e2f",
        "Xingang Zhen"
    ],
    "wof:name":"Xingang",
    "wof:placetype":"locality"
},
  "geometry": {"coordinates":[120.90664,31.94256],"type":"Point"}
}