{
  "type": "Feature",
  "properties": {
    "gn:admin1_code":"25.0",
    "gn:asciiname":"Wangzhuangcun",
    "gn:country_code":"CN",
    "gn:dem":52,
    "gn:feature_class":"P",
    "gn:feature_code":"PPL",
    "gn:name":"Wangzhuangcun",
    "gn:population":0,
    "gn:timezone":"Asia/Shanghai",
    "iso:country":"CN",
    "name:zho_x_preferred":[
        "\u738b\u5e84\u6751"
    ],
    "wof:name":"Wangzhuangcun",
    "wof:placetype":"locality"
},
  "geometry": {"coordinates":[117.54528999999999,34.74431],"type":"Point"}
}