{
  "type": "Feature",
  "properties": {
    "gn:admin1_code":"26",
    "gn:asciiname":"Xishicun",
    "gn:country_code":"CN",
    "gn:dem":478,
    "gn:feature_class":"P",
    "gn:feature_code":"PPL",
    "gn:name":"Xishicun",
    "gn:population":0,
    "gn:timezone":"Asia/Shanghai",
    "iso:country":"CN",
    "name:und_x_variant":[
        "Xishi",
        "\u897f\u77f3",
        "Xishicun"
    ],
    "name:zho_x_preferred":[
        "\u897f\u77f3"
    ],
    "name:zho_x_variant":[
        "\u897f\u77f3\u6751"
    ],
    "wof:name":"Xishicun",
    "wof:placetype":"locality"
},
  "geometry": {"coordinates":[108.68216,34.3855],"type":"Point"}
}