{
  "type": "Feature",
  "properties": {
    "gn:admin1_code":"12.0",
    "gn:asciiname":"Daduanqiying",
    "gn:country_code":"CN",
    "gn:dem":66,
    "gn:feature_class":"P",
    "gn:feature_code":"PPL",
    "gn:name":"Daduanqiying",
    "gn:population":0,
    "gn:timezone":"Asia/Shanghai",
    "iso:country":"CN",
    "name:zho_x_preferred":[
        "\u5927\u6bb5\u65d7\u8425"
    ],
    "wof:name":"Daduanqiying",
    "wof:placetype":"locality"
},
  "geometry": {"coordinates":[112.27158,31.63403],"type":"Point"}
}