{
  "type": "Feature",
  "properties": {
    "gn:admin1_code":"4.0",
    "gn:asciiname":"Xiaoyangjia",
    "gn:country_code":"CN",
    "gn:dem":6,
    "gn:feature_class":"P",
    "gn:feature_code":"PPL",
    "gn:name":"Xiaoyangjia",
    "gn:population":0,
    "gn:timezone":"Asia/Shanghai",
    "iso:country":"CN",
    "name:zho_x_preferred":[
        "\u5c0f\u6768\u5bb6"
    ],
    "wof:name":"Xiaoyangjia",
    "wof:placetype":"locality"
},
  "geometry": {"coordinates":[119.78534999999999,32.05403],"type":"Point"}
}