{
  "type": "Feature",
  "properties": {
    "gn:admin1_code":"29.0",
    "gn:asciiname":"Hou'erwan",
    "gn:country_code":"CN",
    "gn:dem":1278,
    "gn:feature_class":"P",
    "gn:feature_code":"PPL",
    "gn:name":"Hou\u2019erwan",
    "gn:population":0,
    "gn:timezone":"Asia/Shanghai",
    "iso:country":"CN",
    "name:und_x_variant":[
        "Hou\u2019erwan"
    ],
    "name:zho_x_preferred":[
        "\u4faf\u4e8c\u6e7e"
    ],
    "wof:name":"Hou'erwan",
    "wof:placetype":"locality"
},
  "geometry": {"coordinates":[103.976,22.7789],"type":"Point"}
}