{
  "type": "Feature",
  "properties": {
    "gn:admin1_code":"15.0",
    "gn:asciiname":"Chaomianzhuang",
    "gn:country_code":"CN",
    "gn:dem":2807,
    "gn:feature_class":"P",
    "gn:feature_code":"PPL",
    "gn:name":"Chaomianzhuang",
    "gn:population":0,
    "gn:timezone":"Asia/Shanghai",
    "iso:country":"CN",
    "name:zho_x_preferred":[
        "\u7092\u9762\u5e84"
    ],
    "wof:name":"Chaomianzhuang",
    "wof:placetype":"locality"
},
  "geometry": {"coordinates":[100.938,38.238],"type":"Point"}
}