{
  "type": "Feature",
  "properties": {
    "gn:admin1_code":"24.0",
    "gn:asciiname":"Gouxicun",
    "gn:country_code":"CN",
    "gn:dem":763,
    "gn:feature_class":"P",
    "gn:feature_code":"PPL",
    "gn:name":"Gouxicun",
    "gn:population":0,
    "gn:timezone":"Asia/Shanghai",
    "iso:country":"CN",
    "name:zho_x_preferred":[
        "\u6c9f\u897f\u6751"
    ],
    "wof:name":"Gouxicun",
    "wof:placetype":"locality"
},
  "geometry": {"coordinates":[110.98053,35.32919000000001],"type":"Point"}
}