{
  "type": "Feature",
  "properties": {
    "gn:admin1_code":"30.0",
    "gn:asciiname":"Chongxiashui",
    "gn:country_code":"CN",
    "gn:dem":204,
    "gn:feature_class":"P",
    "gn:feature_code":"PPL",
    "gn:name":"Chongxiashui",
    "gn:population":0,
    "gn:timezone":"Asia/Shanghai",
    "iso:country":"CN",
    "name:zho_x_preferred":[
        "\u51b2\u4e0b\u6c34"
    ],
    "wof:name":"Chongxiashui",
    "wof:placetype":"locality"
},
  "geometry": {"coordinates":[114.23761,25.23525],"type":"Point"}
}