{
  "type": "Feature",
  "properties": {
    "gn:admin1_code":"29.0",
    "gn:asciiname":"Caobashan",
    "gn:country_code":"CN",
    "gn:dem":1885,
    "gn:feature_class":"P",
    "gn:feature_code":"PPL",
    "gn:name":"Caobashan",
    "gn:population":0,
    "gn:timezone":"Asia/Shanghai",
    "iso:country":"CN",
    "name:zho_x_preferred":[
        "\u8349\u575d\u5c71"
    ],
    "wof:name":"Caobashan",
    "wof:placetype":"locality"
},
  "geometry": {"coordinates":[99.74169999999999,24.1236],"type":"Point"}
}