{
  "type": "Feature",
  "properties": {
    "gn:admin1_code":"24.0",
    "gn:asciiname":"Xikang",
    "gn:country_code":"CN",
    "gn:dem":547,
    "gn:feature_class":"P",
    "gn:feature_code":"PPL",
    "gn:name":"Xikang",
    "gn:population":0,
    "gn:timezone":"Asia/Shanghai",
    "iso:country":"CN",
    "name:ast_x_preferred":[
        "Xikang"
    ],
    "name:deu_x_preferred":[
        "Xikang"
    ],
    "name:fra_x_preferred":[
        "Xikang"
    ],
    "name:ind_x_preferred":[
        "Xikang"
    ],
    "name:ita_x_preferred":[
        "Xikang"
    ],
    "name:jpn_x_preferred":[
        "\u897f\u5eb7\u7701"
    ],
    "name:kor_x_preferred":[
        "\uc2dc\uce89\uc131"
    ],
    "name:pol_x_preferred":[
        "Xikang"
    ],
    "name:rus_x_preferred":[
        "\u0421\u0438\u043a\u0430\u043d"
    ],
    "name:spa_x_preferred":[
        "Xikang"
    ],
    "name:swe_x_preferred":[
        "Sikang"
    ],
    "name:und_x_variant":[
        "\u897f\u5eb7"
    ],
    "name:vie_x_preferred":[
        "T\u00e2y Khang"
    ],
    "name:zho_x_preferred":[
        "\u897f\u5eb7\u7701"
    ],
    "wof:name":"Xikang",
    "wof:placetype":"locality"
},
  "geometry": {"coordinates":[111.16124000000001,35.49321],"type":"Point"}
}