{
  "type": "Feature",
  "properties": {
    "gn:admin1_code":"8.0",
    "gn:asciiname":"Chengxicun",
    "gn:country_code":"CN",
    "gn:dem":191,
    "gn:feature_class":"P",
    "gn:feature_code":"PPL",
    "gn:name":"Chengxicun",
    "gn:population":0,
    "gn:timezone":"Asia/Shanghai",
    "iso:country":"CN",
    "name:zho_x_preferred":[
        "\u57ce\u897f\u6751"
    ],
    "wof:name":"Chengxicun",
    "wof:placetype":"locality"
},
  "geometry": {"coordinates":[130.51083,45.79841],"type":"Point"}
}