{
  "type": "Feature",
  "properties": {
    "gn:admin1_code":"13.0",
    "gn:asciiname":"Kekerouma",
    "gn:country_code":"CN",
    "gn:dem":1358,
    "gn:feature_class":"P",
    "gn:feature_code":"PPL",
    "gn:name":"Kekerouma",
    "gn:population":0,
    "gn:timezone":"Asia/Urumqi",
    "iso:country":"CN",
    "name:zho_x_preferred":[
        "\u79d1\u514b\u8089\u739b"
    ],
    "wof:name":"Kekerouma",
    "wof:placetype":"locality"
},
  "geometry": {"coordinates":[82.78057,37.2759],"type":"Point"}
}