{
  "type": "Feature",
  "properties": {
    "gn:admin1_code":"24",
    "gn:asciiname":"Duzhuang",
    "gn:country_code":"CN",
    "gn:dem":968,
    "gn:feature_class":"P",
    "gn:feature_code":"PPL",
    "gn:name":"Duzhuang",
    "gn:population":0,
    "gn:timezone":"Asia/Shanghai",
    "iso:country":"CN",
    "name:und_x_variant":[
        "She-chuang",
        "Tu-chuang",
        "Tu-chuang-ts\u2019un",
        "Duzhuang"
    ],
    "name:zho_x_preferred":[
        "\u675c\u5e84"
    ],
    "wof:name":"Duzhuang",
    "wof:placetype":"locality"
},
  "geometry": {"coordinates":[113.66804999999999,37.51246],"type":"Point"}
}