{
  "type": "Feature",
  "properties": {
    "gn:admin1_code":"24.0",
    "gn:asciiname":"Yandongwa",
    "gn:country_code":"CN",
    "gn:dem":1424,
    "gn:feature_class":"P",
    "gn:feature_code":"PPL",
    "gn:name":"Yandongwa",
    "gn:population":0,
    "gn:timezone":"Asia/Shanghai",
    "iso:country":"CN",
    "name:zho_x_preferred":[
        "\u70df\u6d1e\u7a8a"
    ],
    "wof:name":"Yandongwa",
    "wof:placetype":"locality"
},
  "geometry": {"coordinates":[111.85713,39.05419000000001],"type":"Point"}
}