{
  "type": "Feature",
  "properties": {
    "gn:admin1_code":"8.0",
    "gn:asciiname":"Qingbeicun",
    "gn:country_code":"CN",
    "gn:dem":343,
    "gn:feature_class":"P",
    "gn:feature_code":"PPL",
    "gn:name":"Qingbeicun",
    "gn:population":0,
    "gn:timezone":"Asia/Shanghai",
    "iso:country":"CN",
    "name:zho_x_preferred":[
        "\u9752\u80cc\u6751"
    ],
    "wof:name":"Qingbeicun",
    "wof:placetype":"locality"
},
  "geometry": {"coordinates":[129.82268999999999,44.64465],"type":"Point"}
}