{
  "type": "Feature",
  "properties": {
    "gn:admin1_code":"29.0",
    "gn:asciiname":"Manshai",
    "gn:country_code":"CN",
    "gn:dem":911,
    "gn:feature_class":"P",
    "gn:feature_code":"PPL",
    "gn:name":"Manshai",
    "gn:population":0,
    "gn:timezone":"Asia/Shanghai",
    "iso:country":"CN",
    "name:zho_x_preferred":[
        "\u86ee\u6652"
    ],
    "wof:name":"Manshai",
    "wof:placetype":"locality"
},
  "geometry": {"coordinates":[100.651,23.4299],"type":"Point"}
}