{
  "type": "Feature",
  "properties": {
    "gn:admin1_code":"12.0",
    "gn:asciiname":"Chailinshan",
    "gn:country_code":"CN",
    "gn:dem":761,
    "gn:feature_class":"P",
    "gn:feature_code":"PPL",
    "gn:name":"Chailinshan",
    "gn:population":0,
    "gn:timezone":"Asia/Shanghai",
    "iso:country":"CN",
    "name:zho_x_preferred":[
        "\u67f4\u6797\u5c71"
    ],
    "wof:name":"Chailinshan",
    "wof:placetype":"locality"
},
  "geometry": {"coordinates":[109.69215,30.62893],"type":"Point"}
}