{
  "type": "Feature",
  "properties": {
    "gn:admin1_code":"11.0",
    "gn:asciiname":"Tongyuan",
    "gn:country_code":"CN",
    "gn:dem":260,
    "gn:feature_class":"P",
    "gn:feature_code":"PPL",
    "gn:name":"Tongyuan",
    "gn:population":0,
    "gn:timezone":"Asia/Shanghai",
    "iso:country":"CN",
    "name:zho_x_preferred":[
        "\u6850\u6e90"
    ],
    "wof:name":"Tongyuan",
    "wof:placetype":"locality"
},
  "geometry": {"coordinates":[113.80083999999999,27.29165],"type":"Point"}
}