{
  "type": "Feature",
  "properties": {
    "gn:admin1_code":"11.0",
    "gn:asciiname":"Yangziba",
    "gn:country_code":"CN",
    "gn:dem":44,
    "gn:feature_class":"P",
    "gn:feature_code":"PPL",
    "gn:name":"Yangziba",
    "gn:population":0,
    "gn:timezone":"Asia/Shanghai",
    "iso:country":"CN",
    "name:zho_x_preferred":[
        "\u6768\u6893\u575d"
    ],
    "wof:name":"Yangziba",
    "wof:placetype":"locality"
},
  "geometry": {"coordinates":[113.08889000000001,28.20204],"type":"Point"}
}