{
  "type": "Feature",
  "properties": {
    "gn:admin1_code":"11",
    "gn:asciiname":"Boshu",
    "gn:country_code":"CN",
    "gn:dem":330,
    "gn:feature_class":"P",
    "gn:feature_code":"PPL",
    "gn:name":"Boshu",
    "gn:population":0,
    "gn:timezone":"Asia/Shanghai",
    "iso:country":"CN",
    "name:deu_x_preferred":[
        "Boshu"
    ],
    "name:zho_x_preferred":[
        "\u623f\u5dde"
    ],
    "wof:name":"Boshu",
    "wof:placetype":"locality"
},
  "geometry": {"coordinates":[111.82861,28.01111],"type":"Point"}
}