{
  "type": "Feature",
  "properties": {
    "gn:admin1_code":"15.0",
    "gn:asciiname":"Xiaojia",
    "gn:country_code":"CN",
    "gn:dem":2251,
    "gn:feature_class":"P",
    "gn:feature_code":"PPL",
    "gn:name":"Xiaojia",
    "gn:population":0,
    "gn:timezone":"Asia/Shanghai",
    "iso:country":"CN",
    "name:und_x_variant":[
        "\u8096\u5bb6"
    ],
    "wof:name":"Xiaojia",
    "wof:placetype":"locality"
},
  "geometry": {"coordinates":[102.77708,35.75421],"type":"Point"}
}