{
  "type": "Feature",
  "properties": {
    "gn:admin1_code":"10.0",
    "gn:asciiname":"Luwangzhuang",
    "gn:country_code":"CN",
    "gn:dem":9,
    "gn:feature_class":"P",
    "gn:feature_code":"PPL",
    "gn:name":"Luwangzhuang",
    "gn:population":0,
    "gn:timezone":"Asia/Shanghai",
    "iso:country":"CN",
    "name:zho_x_preferred":[
        "\u5362\u738b\u5e84"
    ],
    "wof:name":"Luwangzhuang",
    "wof:placetype":"locality"
},
  "geometry": {"coordinates":[119.33924,39.83241],"type":"Point"}
}