{
  "type": "Feature",
  "properties": {
    "gn:admin1_code":"14.0",
    "gn:asciiname":"Baijingcun",
    "gn:country_code":"CN",
    "gn:dem":4168,
    "gn:feature_class":"P",
    "gn:feature_code":"PPL",
    "gn:name":"Baijingcun",
    "gn:population":0,
    "gn:timezone":"Asia/Urumqi",
    "iso:country":"CN",
    "name:zho_x_preferred":[
        "\u767d\u4eac\u6751"
    ],
    "wof:name":"Baijingcun",
    "wof:placetype":"locality"
},
  "geometry": {"coordinates":[92.39363,29.40367],"type":"Point"}
}