{
  "type": "Feature",
  "properties": {
    "gn:admin1_code":"14.0",
    "gn:asciiname":"Leiguo",
    "gn:country_code":"CN",
    "gn:dem":4515,
    "gn:feature_class":"P",
    "gn:feature_code":"PPL",
    "gn:name":"Leiguo",
    "gn:population":0,
    "gn:timezone":"Asia/Urumqi",
    "iso:country":"CN",
    "name:zho_x_preferred":[
        "\u96f7\u679c"
    ],
    "wof:name":"Leiguo",
    "wof:placetype":"locality"
},
  "geometry": {"coordinates":[94.13934999999999,29.88286],"type":"Point"}
}