{
  "type": "Feature",
  "properties": {
    "gn:admin1_code":"14.0",
    "gn:asciiname":"Reduocun",
    "gn:country_code":"CN",
    "gn:dem":4666,
    "gn:feature_class":"P",
    "gn:feature_code":"PPL",
    "gn:name":"Reduocun",
    "gn:population":0,
    "gn:timezone":"Asia/Urumqi",
    "iso:country":"CN",
    "name:zho_x_preferred":[
        "\u70ed\u591a\u6751"
    ],
    "wof:name":"Reduocun",
    "wof:placetype":"locality"
},
  "geometry": {"coordinates":[90.98908,31.29283],"type":"Point"}
}