{
  "type": "Feature",
  "properties": {
    "gn:admin1_code":"25.0",
    "gn:asciiname":"Majiagoucun",
    "gn:country_code":"CN",
    "gn:dem":114,
    "gn:feature_class":"P",
    "gn:feature_code":"PPL",
    "gn:name":"Majiagoucun",
    "gn:population":0,
    "gn:timezone":"Asia/Shanghai",
    "iso:country":"CN",
    "name:zho_x_preferred":[
        "\u9a6c\u5bb6\u6c9f\u6751"
    ],
    "wof:name":"Majiagoucun",
    "wof:placetype":"locality"
},
  "geometry": {"coordinates":[121.11967,37.075],"type":"Point"}
}