{
  "type": "Feature",
  "properties": {
    "gn:admin1_code":"30.0",
    "gn:asciiname":"Niugukou",
    "gn:country_code":"CN",
    "gn:dem":412,
    "gn:feature_class":"P",
    "gn:feature_code":"PPL",
    "gn:name":"Niugukou",
    "gn:population":0,
    "gn:timezone":"Asia/Shanghai",
    "iso:country":"CN",
    "name:zho_x_preferred":[
        "\u725b\u9aa8\u53e3"
    ],
    "wof:name":"Niugukou",
    "wof:placetype":"locality"
},
  "geometry": {"coordinates":[111.56856999999999,23.06486],"type":"Point"}
}