{
  "type": "Feature",
  "properties": {
    "gn:admin1_code":"22.0",
    "gn:asciiname":"Shichangcun",
    "gn:country_code":"CN",
    "gn:dem":119,
    "gn:feature_class":"P",
    "gn:feature_code":"PPL",
    "gn:name":"Shichangcun",
    "gn:population":0,
    "gn:timezone":"Asia/Shanghai",
    "iso:country":"CN",
    "name:zho_x_preferred":[
        "\u77f3\u5382\u6751"
    ],
    "wof:name":"Shichangcun",
    "wof:placetype":"locality"
},
  "geometry": {"coordinates":[116.08872,39.88682],"type":"Point"}
}