{
  "type": "Feature",
  "properties": {
    "gn:admin1_code":"16.0",
    "gn:asciiname":"Dachegang",
    "gn:country_code":"CN",
    "gn:dem":291,
    "gn:feature_class":"P",
    "gn:feature_code":"PPL",
    "gn:name":"Dachegang",
    "gn:population":0,
    "gn:timezone":"Asia/Shanghai",
    "iso:country":"CN",
    "name:zho_x_preferred":[
        "\u5927\u8f66\u5c97"
    ],
    "wof:name":"Dachegang",
    "wof:placetype":"locality"
},
  "geometry": {"coordinates":[110.55,22.5939],"type":"Point"}
}