{
  "type": "Feature",
  "properties": {
    "gn:admin1_code":"26.0",
    "gn:asciiname":"Santancun",
    "gn:country_code":"CN",
    "gn:dem":1217,
    "gn:feature_class":"P",
    "gn:feature_code":"PPL",
    "gn:name":"Santancun",
    "gn:population":0,
    "gn:timezone":"Asia/Shanghai",
    "iso:country":"CN",
    "name:zho_x_preferred":[
        "\u4e09\u6ee9\u6751"
    ],
    "wof:name":"Santancun",
    "wof:placetype":"locality"
},
  "geometry": {"coordinates":[109.72777000000001,38.56779],"type":"Point"}
}