{
  "type": "Feature",
  "properties": {
    "gn:admin1_code":"32.0",
    "gn:asciiname":"Niukouba",
    "gn:country_code":"CN",
    "gn:dem":278,
    "gn:feature_class":"P",
    "gn:feature_code":"PPL",
    "gn:name":"Niukouba",
    "gn:population":0,
    "gn:timezone":"Asia/Shanghai",
    "iso:country":"CN",
    "name:zho_x_preferred":[
        "\u725b\u53e3\u575d"
    ],
    "wof:name":"Niukouba",
    "wof:placetype":"locality"
},
  "geometry": {"coordinates":[104.48322,28.7824],"type":"Point"}
}