{
  "type": "Feature",
  "properties": {
    "gn:admin1_code":"12.0",
    "gn:asciiname":"Chuanxindian",
    "gn:country_code":"CN",
    "gn:dem":928,
    "gn:feature_class":"P",
    "gn:feature_code":"PPL",
    "gn:name":"Chuanxindian",
    "gn:population":0,
    "gn:timezone":"Asia/Shanghai",
    "iso:country":"CN",
    "name:zho_x_preferred":[
        "\u7a7f\u5fc3\u5e97"
    ],
    "wof:name":"Chuanxindian",
    "wof:placetype":"locality"
},
  "geometry": {"coordinates":[111.13947,31.10342],"type":"Point"}
}