{
  "type": "Feature",
  "properties": {
    "gn:admin1_code":"33.0",
    "gn:asciiname":"Chuanbian",
    "gn:country_code":"CN",
    "gn:dem":750,
    "gn:feature_class":"P",
    "gn:feature_code":"PPL",
    "gn:name":"Chuanbian",
    "gn:population":0,
    "gn:timezone":"Asia/Shanghai",
    "iso:country":"CN",
    "name:zho_x_preferred":[
        "\u5ddd\u8fb9"
    ],
    "wof:name":"Chuanbian",
    "wof:placetype":"locality"
},
  "geometry": {"coordinates":[108.65974,29.78499],"type":"Point"}
}