{
  "type": "Feature",
  "properties": {
    "gn:admin1_code":"19.0",
    "gn:asciiname":"Yanjia",
    "gn:country_code":"CN",
    "gn:dem":19,
    "gn:feature_class":"P",
    "gn:feature_code":"PPL",
    "gn:name":"Yanjia",
    "gn:population":0,
    "gn:timezone":"Asia/Shanghai",
    "iso:country":"CN",
    "name:und_x_variant":[
        "\u960e\u5bb6"
    ],
    "name:zho_x_preferred":[
        "\u960e\u5bb6"
    ],
    "wof:name":"Yanjia",
    "wof:placetype":"locality"
},
  "geometry": {"coordinates":[122.33516000000002,41.68954],"type":"Point"}
}