{
  "type": "Feature",
  "properties": {
    "gn:admin1_code":"14.0",
    "gn:asciiname":"Waduicun",
    "gn:country_code":"CN",
    "gn:dem":3752,
    "gn:feature_class":"P",
    "gn:feature_code":"PPL",
    "gn:name":"Waduicun",
    "gn:population":0,
    "gn:timezone":"Asia/Urumqi",
    "iso:country":"CN",
    "name:zho_x_preferred":[
        "\u74e6\u5806\u6751"
    ],
    "wof:name":"Waduicun",
    "wof:placetype":"locality"
},
  "geometry": {"coordinates":[98.42081,30.95509],"type":"Point"}
}