{
  "type": "Feature",
  "properties": {
    "gn:admin1_code":"7",
    "gn:asciiname":"Canghou",
    "gn:country_code":"CN",
    "gn:dem":18,
    "gn:feature_class":"P",
    "gn:feature_code":"PPL",
    "gn:name":"Canghou",
    "gn:population":0,
    "gn:timezone":"Asia/Shanghai",
    "iso:country":"CN",
    "name:zho_x_preferred":[
        "\u82cd\u540e"
    ],
    "wof:name":"Canghou",
    "wof:placetype":"locality"
},
  "geometry": {"coordinates":[119.02806,25.33944],"type":"Point"}
}