{
  "type": "Feature",
  "properties": {
    "gn:admin1_code":"31.0",
    "gn:asciiname":"Shangliao",
    "gn:country_code":"CN",
    "gn:dem":25,
    "gn:feature_class":"P",
    "gn:feature_code":"PPL",
    "gn:name":"Shangliao",
    "gn:population":0,
    "gn:timezone":"Asia/Shanghai",
    "iso:country":"CN",
    "name:zho_x_preferred":[
        "Shangliao"
    ],
    "name:zho_x_variant":[
        "\u4e0a\u50da"
    ],
    "wof:name":"Shangliao",
    "wof:placetype":"locality"
},
  "geometry": {"coordinates":[110.77405,19.65729],"type":"Point"}
}