{
  "type": "Feature",
  "properties": {
    "gn:admin1_code":"29.0",
    "gn:asciiname":"Geluwan",
    "gn:country_code":"CN",
    "gn:dem":1909,
    "gn:feature_class":"P",
    "gn:feature_code":"PPLA4",
    "gn:name":"Geluwan",
    "gn:population":0,
    "gn:timezone":"Asia/Shanghai",
    "iso:country":"CN",
    "name:und_x_variant":[
        "Shangjiang",
        "Shangjiang Xiang"
    ],
    "name:zho_x_preferred":[
        "\u683c\u9c81\u6e7e"
    ],
    "name:zho_x_variant":[
        "\u4e0a\u6c5f",
        "\u4e0a\u6c5f\u4e61"
    ],
    "wof:name":"Geluwan",
    "wof:placetype":"locality"
},
  "geometry": {"coordinates":[99.65607,27.37374],"type":"Point"}
}