{
  "type": "Feature",
  "properties": {
    "gn:admin1_code":"26.0",
    "gn:asciiname":"Yanghuita",
    "gn:cc2":"CN",
    "gn:country_code":"CN",
    "gn:dem":976,
    "gn:feature_class":"P",
    "gn:feature_code":"PPL",
    "gn:name":"Yanghuita",
    "gn:population":0,
    "gn:timezone":"Asia/Shanghai",
    "iso:country":"CN",
    "name:und_x_variant":[
        "Yang-hui-pa",
        "Yanghuita"
    ],
    "wof:name":"Yanghuita",
    "wof:placetype":"locality"
},
  "geometry": {"coordinates":[110.33333,38.38333],"type":"Point"}
}