{
  "type": "Feature",
  "properties": {
    "gn:admin1_code":"9.0",
    "gn:asciiname":"Erlangxiang",
    "gn:country_code":"CN",
    "gn:dem":68,
    "gn:feature_class":"P",
    "gn:feature_code":"PPL",
    "gn:name":"Erlangxiang",
    "gn:population":0,
    "gn:timezone":"Asia/Shanghai",
    "iso:country":"CN",
    "name:zho_x_preferred":[
        "\u4e8c\u90ce\u4e61"
    ],
    "wof:name":"Erlangxiang",
    "wof:placetype":"locality"
},
  "geometry": {"coordinates":[114.0025,33.30493],"type":"Point"}
}