{
  "type": "Feature",
  "properties": {
    "gn:admin1_code":"11.0",
    "gn:asciiname":"Zhaozichong",
    "gn:country_code":"CN",
    "gn:dem":212,
    "gn:feature_class":"P",
    "gn:feature_code":"PPL",
    "gn:name":"Zhaozichong",
    "gn:population":0,
    "gn:timezone":"Asia/Shanghai",
    "iso:country":"CN",
    "name:zho_x_preferred":[
        "\u7f69\u5b50\u51b2"
    ],
    "wof:name":"Zhaozichong",
    "wof:placetype":"locality"
},
  "geometry": {"coordinates":[110.17493,27.82222],"type":"Point"}
}