{
  "type": "Feature",
  "properties": {
    "gn:admin1_code":"05",
    "gn:asciiname":"Toudaohezi",
    "gn:country_code":"CN",
    "gn:dem":159,
    "gn:feature_class":"P",
    "gn:feature_code":"PPL",
    "gn:name":"Toudaohezi",
    "gn:population":0,
    "gn:timezone":"Asia/Shanghai",
    "iso:country":"CN",
    "name:und_x_variant":[
        "\u5934\u9053\u6cb3\u5b50",
        "T\u2019ou-tao-ho-tzu"
    ],
    "wof:name":"Toudaohezi",
    "wof:placetype":"locality"
},
  "geometry": {"coordinates":[125.77361000000001,40.91528],"type":"Point"}
}