{
  "type": "Feature",
  "properties": {
    "gn:admin1_code":"11.0",
    "gn:asciiname":"Zhimushan",
    "gn:cc2":"CN",
    "gn:country_code":"CN",
    "gn:dem":243,
    "gn:feature_class":"P",
    "gn:feature_code":"PPL",
    "gn:name":"Zhimushan",
    "gn:population":0,
    "gn:timezone":"Asia/Shanghai",
    "iso:country":"CN",
    "name:und_x_variant":[
        "Chih-mu-shan",
        "Zhimushan"
    ],
    "wof:name":"Zhimushan",
    "wof:placetype":"locality"
},
  "geometry": {"coordinates":[111.34917,27.19167],"type":"Point"}
}