{
  "type": "Feature",
  "properties": {
    "gn:admin1_code":"32.0",
    "gn:asciiname":"Huangjue",
    "gn:country_code":"CN",
    "gn:dem":555,
    "gn:feature_class":"P",
    "gn:feature_code":"PPL",
    "gn:name":"Huangjue",
    "gn:population":0,
    "gn:timezone":"Asia/Shanghai",
    "iso:country":"CN",
    "name:zho_x_preferred":[
        "\u9ec4\u6877"
    ],
    "wof:name":"Huangjue",
    "wof:placetype":"locality"
},
  "geometry": {"coordinates":[104.84399999999999,28.0777],"type":"Point"}
}