{
  "type": "Feature",
  "properties": {
    "gn:admin1_code":"24.0",
    "gn:asciiname":"Dianshang",
    "gn:country_code":"CN",
    "gn:dem":862,
    "gn:feature_class":"P",
    "gn:feature_code":"PPL",
    "gn:name":"Dianshang",
    "gn:population":0,
    "gn:timezone":"Asia/Shanghai",
    "iso:country":"CN",
    "name:zho_x_preferred":[
        "\u5e97\u4e0a"
    ],
    "wof:name":"Dianshang",
    "wof:placetype":"locality"
},
  "geometry": {"coordinates":[112.94182000000001,35.81804],"type":"Point"}
}