{
  "type": "Feature",
  "properties": {
    "gn:admin1_code":"18",
    "gn:asciiname":"Siqu",
    "gn:country_code":"CN",
    "gn:dem":289,
    "gn:feature_class":"P",
    "gn:feature_code":"PPLA4",
    "gn:name":"Siqu",
    "gn:population":0,
    "gn:timezone":"Asia/Shanghai",
    "iso:country":"CN",
    "name:und_x_variant":[
        "Ssu-ch\u2019\u00fc",
        "Siqu",
        "Siqu Zhen"
    ],
    "name:zho_x_preferred":[
        "\u601d\u6e20"
    ],
    "name:zho_x_variant":[
        "\u601d\u6e20\u9547"
    ],
    "wof:name":"Siqu",
    "wof:placetype":"locality"
},
  "geometry": {"coordinates":[108.33776,28.67335],"type":"Point"}
}