{
  "type": "Feature",
  "properties": {
    "gn:admin1_code":"19.0",
    "gn:asciiname":"Lazigou",
    "gn:country_code":"CN",
    "gn:dem":373,
    "gn:feature_class":"P",
    "gn:feature_code":"PPL",
    "gn:name":"Lazigou",
    "gn:population":0,
    "gn:timezone":"Asia/Shanghai",
    "iso:country":"CN",
    "name:zho_x_preferred":[
        "\u782c\u5b50\u6c9f"
    ],
    "wof:name":"Lazigou",
    "wof:placetype":"locality"
},
  "geometry": {"coordinates":[124.91097000000001,41.61474000000001],"type":"Point"}
}