{
  "type": "Feature",
  "properties": {
    "gn:admin1_code":"19.0",
    "gn:asciiname":"Qianwu Jianfang",
    "gn:country_code":"CN",
    "gn:dem":38,
    "gn:feature_class":"P",
    "gn:feature_code":"PPL",
    "gn:name":"Qianwu Jianfang",
    "gn:population":0,
    "gn:timezone":"Asia/Shanghai",
    "iso:country":"CN",
    "name:zho_x_preferred":[
        "\u524d\u4e94\u95f4\u623f"
    ],
    "wof:name":"Qianwu Jianfang",
    "wof:placetype":"locality"
},
  "geometry": {"coordinates":[122.69937,39.70607],"type":"Point"}
}