{
  "type": "Feature",
  "properties": {
    "gn:admin1_code":"3.0",
    "gn:asciiname":"Wojiang",
    "gn:country_code":"CN",
    "gn:dem":86,
    "gn:feature_class":"P",
    "gn:feature_code":"PPLA4",
    "gn:name":"Wojiang",
    "gn:population":0,
    "gn:timezone":"Asia/Shanghai",
    "iso:country":"CN",
    "name:und_x_variant":[
        "\u6e25\u6c5f",
        "Wojiang Xiang",
        "\u6e25\u6c5f\u4e61"
    ],
    "wof:name":"Wojiang",
    "wof:placetype":"locality"
},
  "geometry": {"coordinates":[114.43694000000001,27.84057],"type":"Point"}
}