{
  "type": "Feature",
  "properties": {
    "gn:admin1_code":"14.0",
    "gn:asciiname":"Tanggo",
    "gn:country_code":"CN",
    "gn:dem":4736,
    "gn:feature_class":"P",
    "gn:feature_code":"PPLF",
    "gn:name":"Tanggo",
    "gn:population":0,
    "gn:timezone":"Asia/Urumqi",
    "iso:country":"CN",
    "name:bod_x_preferred":[
        "Tanggo"
    ],
    "name:msa_x_preferred":[
        "Tanggo"
    ],
    "name:zho_x_preferred":[
        "Tanggu"
    ],
    "name:zho_x_variant":[
        "\u5510\u53e4"
    ],
    "wof:name":"Tanggo",
    "wof:placetype":"locality"
},
  "geometry": {"coordinates":[91.502,30.002],"type":"Point"}
}