{
  "type": "Feature",
  "properties": {
    "gn:admin1_code":"03",
    "gn:asciiname":"Ruilin",
    "gn:country_code":"CN",
    "gn:dem":162,
    "gn:feature_class":"P",
    "gn:feature_code":"PPLA4",
    "gn:name":"Ruilin",
    "gn:population":0,
    "gn:timezone":"Asia/Shanghai",
    "iso:country":"CN",
    "name:und_x_variant":[
        "Jui-lin",
        "Jui-lin-chai",
        "Ruilin",
        "\u745e\u6797",
        "Ruilin Zhen",
        "\u745e\u6797\u9547"
    ],
    "wof:name":"Ruilin",
    "wof:placetype":"locality"
},
  "geometry": {"coordinates":[115.84175,26.16753],"type":"Point"}
}