{
  "type": "Feature",
  "properties": {
    "gn:admin1_code":"08",
    "gn:asciiname":"Bawujiu Nongchang Ershiqi Dui",
    "gn:country_code":"CN",
    "gn:dem":54,
    "gn:feature_class":"P",
    "gn:feature_code":"PPL",
    "gn:name":"Bawujiu Nongchang Ershiqi Dui",
    "gn:population":0,
    "gn:timezone":"Asia/Shanghai",
    "iso:country":"CN",
    "wof:name":"Bawujiu Nongchang Ershiqi Dui",
    "wof:placetype":"locality"
},
  "geometry": {"coordinates":[133.79138999999998,47.65083],"type":"Point"}
}