{
  "type": "Feature",
  "properties": {
    "gn:admin1_code":"12.0",
    "gn:asciiname":"Liujiachong",
    "gn:country_code":"CN",
    "gn:dem":160,
    "gn:feature_class":"P",
    "gn:feature_code":"PPL",
    "gn:name":"Liujiachong",
    "gn:population":0,
    "gn:timezone":"Asia/Shanghai",
    "iso:country":"CN",
    "name:zho_x_preferred":[
        "Liujiachong"
    ],
    "name:zho_x_variant":[
        "\u5218\u5bb6\u51b2"
    ],
    "wof:name":"Liujiachong",
    "wof:placetype":"locality"
},
  "geometry": {"coordinates":[111.26511000000001,30.50301],"type":"Point"}
}