{
  "type": "Feature",
  "properties": {
    "gn:admin1_code":"32.0",
    "gn:asciiname":"Niufang Jiaotou",
    "gn:country_code":"CN",
    "gn:dem":530,
    "gn:feature_class":"P",
    "gn:feature_code":"PPL",
    "gn:name":"Niufang Jiaotou",
    "gn:population":0,
    "gn:timezone":"Asia/Shanghai",
    "iso:country":"CN",
    "name:zho_x_preferred":[
        "\u725b\u623f\u89d2\u5934"
    ],
    "wof:name":"Niufang Jiaotou",
    "wof:placetype":"locality"
},
  "geometry": {"coordinates":[105.681,31.5841],"type":"Point"}
}