{
  "type": "Feature",
  "properties": {
    "gn:admin1_code":"32.0",
    "gn:asciiname":"Luohongyide",
    "gn:country_code":"CN",
    "gn:dem":2331,
    "gn:feature_class":"P",
    "gn:feature_code":"PPL",
    "gn:name":"Luohongyide",
    "gn:population":0,
    "gn:timezone":"Asia/Shanghai",
    "iso:country":"CN",
    "name:zho_x_preferred":[
        "\u7f57\u6d2a\u4f9d\u5f97"
    ],
    "wof:name":"Luohongyide",
    "wof:placetype":"locality"
},
  "geometry": {"coordinates":[102.2285,28.73072],"type":"Point"}
}