{
  "type": "Feature",
  "properties": {
    "gn:admin1_code":"31",
    "gn:asciiname":"Shilan",
    "gn:country_code":"CN",
    "gn:dem":171,
    "gn:feature_class":"P",
    "gn:feature_code":"PPL",
    "gn:name":"Shilan",
    "gn:population":0,
    "gn:timezone":"Asia/Shanghai",
    "iso:country":"CN",
    "name:fas_x_preferred":[
        "\u0634\u06cc\u0644\u0627\u0646"
    ],
    "wof:name":"Shilan",
    "wof:placetype":"locality"
},
  "geometry": {"coordinates":[110.15278000000001,18.89722],"type":"Point"}
}