{
  "type": "Feature",
  "properties": {
    "gn:admin1_code":"23.0",
    "gn:asciiname":"Maohaitou",
    "gn:country_code":"CN",
    "gn:dem":5,
    "gn:feature_class":"P",
    "gn:feature_code":"PPL",
    "gn:name":"Maohaitou",
    "gn:population":0,
    "gn:timezone":"Asia/Shanghai",
    "iso:country":"CN",
    "name:und_x_variant":[
        "\u6cd6\u6d77\u5934"
    ],
    "wof:name":"Maohaitou",
    "wof:placetype":"locality"
},
  "geometry": {"coordinates":[121.1074,30.91747],"type":"Point"}
}