{
  "type": "Feature",
  "properties": {
    "gn:admin1_code":"07",
    "gn:asciiname":"Lieshi",
    "gn:country_code":"CN",
    "gn:dem":514,
    "gn:feature_class":"P",
    "gn:feature_code":"PPL",
    "gn:name":"Lieshi",
    "gn:population":0,
    "gn:timezone":"Asia/Shanghai",
    "iso:country":"CN",
    "name:und_x_variant":[
        "Lieh-shih",
        "Lieshi"
    ],
    "name:zho_x_preferred":[
        "\u5217\u5e02"
    ],
    "wof:name":"Lieshi",
    "wof:placetype":"locality"
},
  "geometry": {"coordinates":[116.80920999999999,24.69694],"type":"Point"}
}