{
  "type": "Feature",
  "properties": {
    "gn:admin1_code":"25",
    "gn:asciiname":"Shengdong",
    "gn:country_code":"CN",
    "gn:dem":18,
    "gn:feature_class":"P",
    "gn:feature_code":"PPL",
    "gn:name":"Shengdong",
    "gn:population":0,
    "gn:timezone":"Asia/Shanghai",
    "iso:country":"CN",
    "name:zho_x_preferred":[
        "\u5723\u4e1c"
    ],
    "wof:name":"Shengdong",
    "wof:placetype":"locality"
},
  "geometry": {"coordinates":[117.48399999999999,37.2691],"type":"Point"}
}