{
  "type": "Feature",
  "properties": {
    "gn:admin1_code":"29.0",
    "gn:asciiname":"Sangaozhuang",
    "gn:country_code":"CN",
    "gn:dem":2618,
    "gn:feature_class":"P",
    "gn:feature_code":"PPL",
    "gn:name":"Sangaozhuang",
    "gn:population":0,
    "gn:timezone":"Asia/Shanghai",
    "iso:country":"CN",
    "name:zho_x_preferred":[
        "\u4e09\u9ad8\u5e84"
    ],
    "wof:name":"Sangaozhuang",
    "wof:placetype":"locality"
},
  "geometry": {"coordinates":[100.872,27.1119],"type":"Point"}
}