{
  "type": "Feature",
  "properties": {
    "gn:admin1_code":"18",
    "gn:asciiname":"Daxiaba",
    "gn:country_code":"CN",
    "gn:dem":880,
    "gn:feature_class":"P",
    "gn:feature_code":"PPL",
    "gn:name":"Daxiaba",
    "gn:population":0,
    "gn:timezone":"Asia/Shanghai",
    "iso:country":"CN",
    "name:zho_x_preferred":[
        "\u5927\u4e0b\u575d"
    ],
    "wof:name":"Daxiaba",
    "wof:placetype":"locality"
},
  "geometry": {"coordinates":[106.542,27.4007],"type":"Point"}
}