{
  "type": "Feature",
  "properties": {
    "gn:admin1_code":"8.0",
    "gn:asciiname":"Houhuandongcun",
    "gn:country_code":"CN",
    "gn:dem":159,
    "gn:feature_class":"P",
    "gn:feature_code":"PPL",
    "gn:name":"Houhuandongcun",
    "gn:population":0,
    "gn:timezone":"Asia/Shanghai",
    "iso:country":"CN",
    "name:zho_x_preferred":[
        "\u540e\u6b22\u6d1e\u6751"
    ],
    "wof:name":"Houhuandongcun",
    "wof:placetype":"locality"
},
  "geometry": {"coordinates":[127.37199,50.04216],"type":"Point"}
}