{
  "type": "Feature",
  "properties": {
    "gn:admin1_code":"19.0",
    "gn:asciiname":"Tongzhuangzicun",
    "gn:country_code":"CN",
    "gn:dem":306,
    "gn:feature_class":"P",
    "gn:feature_code":"PPL",
    "gn:name":"Tongzhuangzicun",
    "gn:population":0,
    "gn:timezone":"Asia/Shanghai",
    "iso:country":"CN",
    "name:zho_x_preferred":[
        "\u4f5f\u5e84\u5b50\u6751"
    ],
    "wof:name":"Tongzhuangzicun",
    "wof:placetype":"locality"
},
  "geometry": {"coordinates":[124.31944,41.65447],"type":"Point"}
}