{
  "type": "Feature",
  "properties": {
    "gn:admin1_code":"8.0",
    "gn:asciiname":"Hanjiayoufang",
    "gn:country_code":"CN",
    "gn:dem":136,
    "gn:feature_class":"P",
    "gn:feature_code":"PPL",
    "gn:name":"Hanjiayoufang",
    "gn:population":0,
    "gn:timezone":"Asia/Shanghai",
    "iso:country":"CN",
    "name:zho_x_preferred":[
        "\u97e9\u5bb6\u6cb9\u623f"
    ],
    "wof:name":"Hanjiayoufang",
    "wof:placetype":"locality"
},
  "geometry": {"coordinates":[126.52337,46.38107],"type":"Point"}
}