{
  "type": "Feature",
  "properties": {
    "gn:admin1_code":"10",
    "gn:asciiname":"Nannigou",
    "gn:country_code":"CN",
    "gn:dem":1293,
    "gn:feature_class":"P",
    "gn:feature_code":"PPL",
    "gn:name":"Nannigou",
    "gn:population":0,
    "gn:timezone":"Asia/Shanghai",
    "iso:country":"CN",
    "name:zho_x_preferred":[
        "\u5357\u6ce5\u6c9f"
    ],
    "wof:name":"Nannigou",
    "wof:placetype":"locality"
},
  "geometry": {"coordinates":[115.13007,41.00166],"type":"Point"}
}