{
  "type": "Feature",
  "properties": {
    "gn:admin1_code":"19.0",
    "gn:asciiname":"Gaolituncun",
    "gn:country_code":"CN",
    "gn:dem":73,
    "gn:feature_class":"P",
    "gn:feature_code":"PPL",
    "gn:name":"Gaolituncun",
    "gn:population":0,
    "gn:timezone":"Asia/Shanghai",
    "iso:country":"CN",
    "name:zho_x_preferred":[
        "\u9ad8\u529b\u5c6f\u6751"
    ],
    "wof:name":"Gaolituncun",
    "wof:placetype":"locality"
},
  "geometry": {"coordinates":[123.49299999999999,42.0137],"type":"Point"}
}