{
  "type": "Feature",
  "properties": {
    "gn:admin1_code":"1.0",
    "gn:asciiname":"Chuankou",
    "gn:country_code":"CN",
    "gn:dem":99,
    "gn:feature_class":"P",
    "gn:feature_code":"PPL",
    "gn:name":"Chuankou",
    "gn:population":0,
    "gn:timezone":"Asia/Shanghai",
    "iso:country":"CN",
    "name:zho_x_preferred":[
        "Chuankou"
    ],
    "name:zho_x_variant":[
        "\u5ddd\u53e3"
    ],
    "wof:name":"Chuankou",
    "wof:placetype":"locality"
},
  "geometry": {"coordinates":[118.92842,30.47888],"type":"Point"}
}