{
  "type": "Feature",
  "properties": {
    "gn:admin1_code":"7.0",
    "gn:asciiname":"Waitankeng",
    "gn:country_code":"CN",
    "gn:dem":440,
    "gn:feature_class":"P",
    "gn:feature_code":"PPL",
    "gn:name":"Waitankeng",
    "gn:population":0,
    "gn:timezone":"Asia/Shanghai",
    "iso:country":"CN",
    "name:zho_x_preferred":[
        "\u5916\u70ad\u5751"
    ],
    "wof:name":"Waitankeng",
    "wof:placetype":"locality"
},
  "geometry": {"coordinates":[117.32998000000001,27.25403],"type":"Point"}
}