{
  "type": "Feature",
  "properties": {
    "gn:admin1_code":"32.0",
    "gn:asciiname":"Jiangjiawan",
    "gn:country_code":"CN",
    "gn:dem":753,
    "gn:feature_class":"P",
    "gn:feature_code":"PPL",
    "gn:name":"Jiangjiawan",
    "gn:population":0,
    "gn:timezone":"Asia/Shanghai",
    "iso:country":"CN",
    "name:zho_x_preferred":[
        "\u6c5f\u5bb6\u6e7e"
    ],
    "wof:name":"Jiangjiawan",
    "wof:placetype":"locality"
},
  "geometry": {"coordinates":[104.126,30.2304],"type":"Point"}
}