{
  "type": "Feature",
  "properties": {
    "gn:admin1_code":"3",
    "gn:asciiname":"Hengyuancaijia",
    "gn:country_code":"CN",
    "gn:dem":79,
    "gn:feature_class":"P",
    "gn:feature_code":"PPL",
    "gn:name":"Hengyuancaijia",
    "gn:population":0,
    "gn:timezone":"Asia/Shanghai",
    "iso:country":"CN",
    "wof:name":"Hengyuancaijia",
    "wof:placetype":"locality"
},
  "geometry": {"coordinates":[116.90278000000001,28.01139],"type":"Point"}
}