{
  "type": "Feature",
  "properties": {
    "gn:admin1_code":"14.0",
    "gn:asciiname":"Qumei",
    "gn:country_code":"CN",
    "gn:dem":4212,
    "gn:feature_class":"P",
    "gn:feature_code":"PPL",
    "gn:name":"Qumei",
    "gn:population":0,
    "gn:timezone":"Asia/Urumqi",
    "iso:country":"CN",
    "name:zho_x_preferred":[
        "\u66f2\u7f8e"
    ],
    "wof:name":"Qumei",
    "wof:placetype":"locality"
},
  "geometry": {"coordinates":[87.9016,28.3626],"type":"Point"}
}