{
  "type": "Feature",
  "properties": {
    "gn:admin1_code":"29.0",
    "gn:asciiname":"Xiangzong",
    "gn:country_code":"CN",
    "gn:dem":2043,
    "gn:feature_class":"P",
    "gn:feature_code":"PPL",
    "gn:name":"Xiangzong",
    "gn:population":0,
    "gn:timezone":"Asia/Shanghai",
    "iso:country":"CN",
    "name:und_x_variant":[
        "\u54cd\u5b97"
    ],
    "wof:name":"Xiangzong",
    "wof:placetype":"locality"
},
  "geometry": {"coordinates":[103.86199999999999,26.0921],"type":"Point"}
}