{
  "type": "Feature",
  "properties": {
    "gn:admin1_code":"5.0",
    "gn:asciiname":"Gongjiacun",
    "gn:country_code":"CN",
    "gn:dem":320,
    "gn:feature_class":"P",
    "gn:feature_code":"PPL",
    "gn:name":"Gongjiacun",
    "gn:population":0,
    "gn:timezone":"Asia/Shanghai",
    "iso:country":"CN",
    "name:und_x_variant":[
        "Kung-chieh-t\u2019un"
    ],
    "name:zho_x_preferred":[
        "\u5bab\u5bb6\u6751"
    ],
    "wof:name":"Gongjiacun",
    "wof:placetype":"locality"
},
  "geometry": {"coordinates":[125.30240000000001,42.76904],"type":"Point"}
}