{
  "type": "Feature",
  "properties": {
    "gn:admin1_code":"14.0",
    "gn:asciiname":"Lalongcun",
    "gn:country_code":"CN",
    "gn:dem":3591,
    "gn:feature_class":"P",
    "gn:feature_code":"PPL",
    "gn:name":"Lalongcun",
    "gn:population":0,
    "gn:timezone":"Asia/Urumqi",
    "iso:country":"CN",
    "name:zho_x_preferred":[
        "\u62c9\u9f99\u6751"
    ],
    "wof:name":"Lalongcun",
    "wof:placetype":"locality"
},
  "geometry": {"coordinates":[92.13102000000001,29.29245],"type":"Point"}
}