{
  "type": "Feature",
  "properties": {
    "gn:admin1_code":"26.0",
    "gn:asciiname":"Hejiagoucun",
    "gn:country_code":"CN",
    "gn:dem":936,
    "gn:feature_class":"P",
    "gn:feature_code":"PPL",
    "gn:name":"Hejiagoucun",
    "gn:population":0,
    "gn:timezone":"Asia/Shanghai",
    "iso:country":"CN",
    "name:zho_x_preferred":[
        "\u8d3a\u5bb6\u6c9f\u6751"
    ],
    "wof:name":"Hejiagoucun",
    "wof:placetype":"locality"
},
  "geometry": {"coordinates":[110.09151,36.99274000000001],"type":"Point"}
}