{
  "type": "Feature",
  "properties": {
    "gn:admin1_code":"32.0",
    "gn:asciiname":"Shiliping",
    "gn:country_code":"CN",
    "gn:dem":1130,
    "gn:feature_class":"P",
    "gn:feature_code":"PPL",
    "gn:name":"Shiliping",
    "gn:population":0,
    "gn:timezone":"Asia/Shanghai",
    "iso:country":"CN",
    "name:zho_x_preferred":[
        "\u5341\u91cc\u576a"
    ],
    "wof:name":"Shiliping",
    "wof:placetype":"locality"
},
  "geometry": {"coordinates":[107.703,31.9393],"type":"Point"}
}