{
  "type": "Feature",
  "properties": {
    "gn:admin1_code":"15.0",
    "gn:asciiname":"Houliangxiang",
    "gn:country_code":"CN",
    "gn:dem":1837,
    "gn:feature_class":"P",
    "gn:feature_code":"PPL",
    "gn:name":"Houliangxiang",
    "gn:population":0,
    "gn:timezone":"Asia/Shanghai",
    "iso:country":"CN",
    "name:und_x_variant":[
        "\u540e\u6881\u4e61"
    ],
    "wof:name":"Houliangxiang",
    "wof:placetype":"locality"
},
  "geometry": {"coordinates":[105.81966,35.29363],"type":"Point"}
}