{
  "type": "Feature",
  "properties": {
    "gn:admin1_code":"4.0",
    "gn:asciiname":"Zaolin",
    "gn:country_code":"CN",
    "gn:dem":25,
    "gn:feature_class":"P",
    "gn:feature_code":"PPL",
    "gn:name":"Zaolin",
    "gn:population":0,
    "gn:timezone":"Asia/Shanghai",
    "iso:country":"CN",
    "name:zho_x_preferred":[
        "\u67a3\u6797"
    ],
    "wof:name":"Zaolin",
    "wof:placetype":"locality"
},
  "geometry": {"coordinates":[119.09325,32.32749],"type":"Point"}
}