{
  "type": "Feature",
  "properties": {
    "gn:admin1_code":"7",
    "gn:asciiname":"Xincaochi",
    "gn:country_code":"CN",
    "gn:dem":484,
    "gn:feature_class":"P",
    "gn:feature_code":"PPL",
    "gn:name":"Xincaochi",
    "gn:population":0,
    "gn:timezone":"Asia/Shanghai",
    "iso:country":"CN",
    "name:zho_x_preferred":[
        "\u65b0\u8349\u6c60"
    ],
    "wof:name":"Xincaochi",
    "wof:placetype":"locality"
},
  "geometry": {"coordinates":[117.61042999999999,24.96204],"type":"Point"}
}