{
  "type": "Feature",
  "properties": {
    "gn:admin1_code":"19.0",
    "gn:asciiname":"Zhuzhangzi",
    "gn:country_code":"CN",
    "gn:dem":539,
    "gn:feature_class":"P",
    "gn:feature_code":"PPL",
    "gn:name":"Zhuzhangzi",
    "gn:population":0,
    "gn:timezone":"Asia/Shanghai",
    "iso:country":"CN",
    "name:und_x_variant":[
        "\u6731\u6756\u5b50"
    ],
    "name:zho_x_preferred":[
        "\u6731\u6756\u5b50"
    ],
    "wof:name":"Zhuzhangzi",
    "wof:placetype":"locality"
},
  "geometry": {"coordinates":[120.03279999999999,41.10847],"type":"Point"}
}