{
  "type": "Feature",
  "properties": {
    "gn:admin1_code":"3.0",
    "gn:asciiname":"Hongmiaoxia",
    "gn:country_code":"CN",
    "gn:dem":95,
    "gn:feature_class":"P",
    "gn:feature_code":"PPL",
    "gn:name":"Hongmiaoxia",
    "gn:population":0,
    "gn:timezone":"Asia/Shanghai",
    "iso:country":"CN",
    "name:und_x_variant":[
        "\u7ea2\u5e99\u4e0b"
    ],
    "wof:name":"Hongmiaoxia",
    "wof:placetype":"locality"
},
  "geometry": {"coordinates":[117.21413,29.25384],"type":"Point"}
}