{
  "type": "Feature",
  "properties": {
    "gn:admin1_code":"20",
    "gn:asciiname":"Xiwopu",
    "gn:cc2":"CN",
    "gn:country_code":"CN",
    "gn:dem":680,
    "gn:feature_class":"P",
    "gn:feature_code":"PPL",
    "gn:name":"Xiwopu",
    "gn:population":0,
    "gn:timezone":"Asia/Shanghai",
    "iso:country":"CN",
    "name:und_x_variant":[
        "Hsi-wo-p\u2019u",
        "Xiwopu"
    ],
    "wof:name":"Xiwopu",
    "wof:placetype":"locality"
},
  "geometry": {"coordinates":[119.01917,42.74444],"type":"Point"}
}