{
  "type": "Feature",
  "properties": {
    "gn:admin1_code":"12.0",
    "gn:asciiname":"Caotouwan",
    "gn:country_code":"CN",
    "gn:dem":607,
    "gn:feature_class":"P",
    "gn:feature_code":"PPL",
    "gn:name":"Caotouwan",
    "gn:population":0,
    "gn:timezone":"Asia/Shanghai",
    "iso:country":"CN",
    "name:zho_x_preferred":[
        "\u69fd\u5934\u6e7e"
    ],
    "wof:name":"Caotouwan",
    "wof:placetype":"locality"
},
  "geometry": {"coordinates":[111.41117,32.10293],"type":"Point"}
}