{
  "type": "Feature",
  "properties": {
    "gn:admin1_code":"23.0",
    "gn:asciiname":"Xiaoshuhe",
    "gn:country_code":"CN",
    "gn:dem":6,
    "gn:feature_class":"P",
    "gn:feature_code":"PPL",
    "gn:name":"Xiaoshuhe",
    "gn:population":0,
    "gn:timezone":"Asia/Shanghai",
    "iso:country":"CN",
    "name:und_x_variant":[
        "Hsiao-shu-ho",
        "Xiaoshuhe",
        "Hsiao-shu-ho-chen",
        "Xiaoshuhezhen",
        "\u5c0f\u7ad6\u6cb3"
    ],
    "wof:name":"Xiaoshuhe",
    "wof:placetype":"locality"
},
  "geometry": {"coordinates":[121.39626,31.73667],"type":"Point"}
}