{
  "type": "Feature",
  "properties": {
    "gn:admin1_code":"32",
    "gn:asciiname":"Zhengjiahe",
    "gn:country_code":"CN",
    "gn:dem":666,
    "gn:feature_class":"P",
    "gn:feature_code":"PPL",
    "gn:name":"Zhengjiahe",
    "gn:population":0,
    "gn:timezone":"Asia/Shanghai",
    "iso:country":"CN",
    "name:zho_x_preferred":[
        "\u90d1\u5bb6\u6cb3"
    ],
    "wof:name":"Zhengjiahe",
    "wof:placetype":"locality"
},
  "geometry": {"coordinates":[105.25767999999999,31.79793],"type":"Point"}
}