{
  "type": "Feature",
  "properties": {
    "gn:admin1_code":"25",
    "gn:asciiname":"Yitandian",
    "gn:country_code":"CN",
    "gn:dem":60,
    "gn:feature_class":"P",
    "gn:feature_code":"PPL",
    "gn:name":"Yitandian",
    "gn:population":0,
    "gn:timezone":"Asia/Shanghai",
    "iso:country":"CN",
    "name:zho_x_preferred":[
        "\u4e49\u6f6d\u5e97"
    ],
    "wof:name":"Yitandian",
    "wof:placetype":"locality"
},
  "geometry": {"coordinates":[120.541,36.8762],"type":"Point"}
}