{
  "type": "Feature",
  "properties": {
    "gn:admin1_code":"20",
    "gn:asciiname":"Sicun",
    "gn:cc2":"CN",
    "gn:country_code":"CN",
    "gn:dem":1009,
    "gn:feature_class":"P",
    "gn:feature_code":"PPL",
    "gn:name":"Sicun",
    "gn:population":0,
    "gn:timezone":"Asia/Shanghai",
    "iso:country":"CN",
    "name:und_x_variant":[
        "Ssu-ts\u2019un",
        "Sicun Xiang",
        "Sicun"
    ],
    "wof:name":"Sicun",
    "wof:placetype":"locality"
},
  "geometry": {"coordinates":[109.52861,40.49806],"type":"Point"}
}