{
  "type": "Feature",
  "properties": {
    "gn:admin1_code":"18",
    "gn:asciiname":"Gujia Dixia",
    "gn:country_code":"CN",
    "gn:dem":2209,
    "gn:feature_class":"P",
    "gn:feature_code":"PPL",
    "gn:name":"Gujia Dixia",
    "gn:population":0,
    "gn:timezone":"Asia/Shanghai",
    "iso:country":"CN",
    "name:zho_x_preferred":[
        "\u987e\u5bb6\u5e95\u4e0b"
    ],
    "wof:name":"Gujia Dixia",
    "wof:placetype":"locality"
},
  "geometry": {"coordinates":[104.238,26.8245],"type":"Point"}
}