{
  "type": "Feature",
  "properties": {
    "gn:admin1_code":"32.0",
    "gn:asciiname":"Chenjiaping",
    "gn:country_code":"CN",
    "gn:dem":692,
    "gn:feature_class":"P",
    "gn:feature_code":"PPL",
    "gn:name":"Chenjiaping",
    "gn:population":0,
    "gn:timezone":"Asia/Shanghai",
    "iso:country":"CN",
    "name:zho_x_preferred":[
        "\u9648\u5bb6\u576a"
    ],
    "wof:name":"Chenjiaping",
    "wof:placetype":"locality"
},
  "geometry": {"coordinates":[107.471,32.1339],"type":"Point"}
}