{
  "type": "Feature",
  "properties": {
    "gn:admin1_code":"29",
    "gn:asciiname":"Guolimei",
    "gn:country_code":"CN",
    "gn:dem":1768,
    "gn:feature_class":"P",
    "gn:feature_code":"PPL",
    "gn:name":"Guolimei",
    "gn:population":0,
    "gn:timezone":"Asia/Shanghai",
    "iso:country":"CN",
    "name:zho_x_preferred":[
        "\u90ed\u4e3d\u7f8e"
    ],
    "wof:name":"Guolimei",
    "wof:placetype":"locality"
},
  "geometry": {"coordinates":[101.22199999999999,24.8551],"type":"Point"}
}