{
  "type": "Feature",
  "properties": {
    "gn:admin1_code":"12.0",
    "gn:asciiname":"Jinqiandong",
    "gn:country_code":"CN",
    "gn:dem":666,
    "gn:feature_class":"P",
    "gn:feature_code":"PPL",
    "gn:name":"Jinqiandong",
    "gn:population":0,
    "gn:timezone":"Asia/Shanghai",
    "iso:country":"CN",
    "name:zho_x_preferred":[
        "\u91d1\u94b1\u6d1e"
    ],
    "wof:name":"Jinqiandong",
    "wof:placetype":"locality"
},
  "geometry": {"coordinates":[111.51752999999999,32.0289],"type":"Point"}
}