{
  "type": "Feature",
  "properties": {
    "gn:admin1_code":"25.0",
    "gn:asciiname":"Hougezhuangcun",
    "gn:country_code":"CN",
    "gn:dem":51,
    "gn:feature_class":"P",
    "gn:feature_code":"PPL",
    "gn:name":"Hougezhuangcun",
    "gn:population":0,
    "gn:timezone":"Asia/Shanghai",
    "iso:country":"CN",
    "name:zho_x_preferred":[
        "\u540e\u6208\u5e84\u6751"
    ],
    "wof:name":"Hougezhuangcun",
    "wof:placetype":"locality"
},
  "geometry": {"coordinates":[119.91965999999999,36.79087],"type":"Point"}
}