{
  "type": "Feature",
  "properties": {
    "gn:admin1_code":"29.0",
    "gn:asciiname":"Luobazha",
    "gn:country_code":"CN",
    "gn:dem":2204,
    "gn:feature_class":"P",
    "gn:feature_code":"PPL",
    "gn:name":"Luobazha",
    "gn:population":0,
    "gn:timezone":"Asia/Shanghai",
    "iso:country":"CN",
    "name:zho_x_preferred":[
        "\u7f57\u5df4\u4e4d"
    ],
    "wof:name":"Luobazha",
    "wof:placetype":"locality"
},
  "geometry": {"coordinates":[101.471,25.7588],"type":"Point"}
}