{
  "type": "Feature",
  "properties": {
    "gn:admin1_code":"11.0",
    "gn:asciiname":"Shan'ao",
    "gn:country_code":"CN",
    "gn:dem":148,
    "gn:feature_class":"P",
    "gn:feature_code":"PPL",
    "gn:name":"Shan\u2019ao",
    "gn:population":0,
    "gn:timezone":"Asia/Shanghai",
    "iso:country":"CN",
    "name:und_x_variant":[
        "Shan\u2019ao"
    ],
    "name:zho_x_preferred":[
        "\u6749\u5773"
    ],
    "wof:name":"Shan'ao",
    "wof:placetype":"locality"
},
  "geometry": {"coordinates":[110.19356000000001,28.06856],"type":"Point"}
}