{
  "type": "Feature",
  "properties": {
    "gn:admin1_code":"1.0",
    "gn:asciiname":"Duanlingcun",
    "gn:country_code":"CN",
    "gn:dem":71,
    "gn:feature_class":"P",
    "gn:feature_code":"PPL",
    "gn:name":"Duanlingcun",
    "gn:population":0,
    "gn:timezone":"Asia/Shanghai",
    "iso:country":"CN",
    "name:zho_x_preferred":[
        "\u6bb5\u5cad\u6751"
    ],
    "wof:name":"Duanlingcun",
    "wof:placetype":"locality"
},
  "geometry": {"coordinates":[116.43747999999999,31.59206],"type":"Point"}
}