{
  "type": "Feature",
  "properties": {
    "gn:admin1_code":"10",
    "gn:asciiname":"Lijiaying",
    "gn:country_code":"CN",
    "gn:dem":880,
    "gn:feature_class":"P",
    "gn:feature_code":"PPL",
    "gn:name":"Lijiaying",
    "gn:population":0,
    "gn:timezone":"Asia/Shanghai",
    "iso:country":"CN",
    "name:zho_x_preferred":[
        "\u674e\u5bb6\u8425"
    ],
    "wof:name":"Lijiaying",
    "wof:placetype":"locality"
},
  "geometry": {"coordinates":[117.90026,41.45894000000001],"type":"Point"}
}