{
  "type": "Feature",
  "properties": {
    "gn:admin1_code":"3.0",
    "gn:asciiname":"Hewanwu",
    "gn:country_code":"CN",
    "gn:dem":88,
    "gn:feature_class":"P",
    "gn:feature_code":"PPL",
    "gn:name":"Hewanwu",
    "gn:population":0,
    "gn:timezone":"Asia/Shanghai",
    "iso:country":"CN",
    "name:und_x_variant":[
        "\u6cb3\u6e7e\u5434"
    ],
    "wof:name":"Hewanwu",
    "wof:placetype":"locality"
},
  "geometry": {"coordinates":[115.59013,29.55062],"type":"Point"}
}