{
  "type": "Feature",
  "properties": {
    "gn:admin1_code":"26.0",
    "gn:asciiname":"Tuqiaocun",
    "gn:country_code":"CN",
    "gn:dem":1106,
    "gn:feature_class":"P",
    "gn:feature_code":"PPL",
    "gn:name":"Tuqiaocun",
    "gn:population":0,
    "gn:timezone":"Asia/Shanghai",
    "iso:country":"CN",
    "name:zho_x_preferred":[
        "\u571f\u6865\u6751"
    ],
    "wof:name":"Tuqiaocun",
    "wof:placetype":"locality"
},
  "geometry": {"coordinates":[109.25618,35.53955],"type":"Point"}
}