{
  "type": "Feature",
  "properties": {
    "gn:admin1_code":"20.0",
    "gn:asciiname":"Kudu'er",
    "gn:country_code":"CN",
    "gn:dem":830,
    "gn:feature_class":"P",
    "gn:feature_code":"PPLA4",
    "gn:name":"Kudu\u2019er",
    "gn:population":0,
    "gn:timezone":"Asia/Shanghai",
    "iso:country":"CN",
    "name:und_x_variant":[
        "Kudu\u2019er",
        "Kudu\u2019er Zhen"
    ],
    "name:zho_x_preferred":[
        "\u5e93\u90fd\u5c14"
    ],
    "name:zho_x_variant":[
        "\u5e93\u90fd\u5c14\u9547"
    ],
    "wof:name":"Kudu'er",
    "wof:placetype":"locality"
},
  "geometry": {"coordinates":[121.61391,50.02963],"type":"Point"}
}