{
  "type": "Feature",
  "properties": {
    "gn:admin1_code":"1.0",
    "gn:asciiname":"Zhudazhuangcun",
    "gn:country_code":"CN",
    "gn:dem":35,
    "gn:feature_class":"P",
    "gn:feature_code":"PPL",
    "gn:name":"Zhudazhuangcun",
    "gn:population":0,
    "gn:timezone":"Asia/Shanghai",
    "iso:country":"CN",
    "name:zho_x_preferred":[
        "\u6731\u5927\u5e84\u6751"
    ],
    "wof:name":"Zhudazhuangcun",
    "wof:placetype":"locality"
},
  "geometry": {"coordinates":[115.53369000000001,32.95111],"type":"Point"}
}