{
  "type": "Feature",
  "properties": {
    "gn:admin1_code":"18",
    "gn:asciiname":"Jiangzhai",
    "gn:country_code":"CN",
    "gn:dem":1125,
    "gn:feature_class":"P",
    "gn:feature_code":"PPL",
    "gn:name":"Jiangzhai",
    "gn:population":0,
    "gn:timezone":"Asia/Shanghai",
    "iso:country":"CN",
    "name:deu_x_preferred":[
        "Jiangzhai"
    ],
    "name:fas_x_preferred":[
        "\u062c\u06cc\u0627\u0646\u06af \u0698\u0627\u06cc"
    ],
    "name:ita_x_preferred":[
        "Jiangzhai"
    ],
    "name:nor_x_preferred":[
        "Jiangzhai"
    ],
    "name:slv_x_preferred":[
        "Jiangzhai"
    ],
    "name:zho_x_preferred":[
        "\u6c5f\u5be8"
    ],
    "name:zho_x_variant":[
        "\u59dc\u5be8\u9057\u5740"
    ],
    "wof:name":"Jiangzhai",
    "wof:placetype":"locality"
},
  "geometry": {"coordinates":[105.155,25.8418],"type":"Point"}
}