{
  "type": "Feature",
  "properties": {
    "gn:admin1_code":"30.0",
    "gn:asciiname":"Niushifen",
    "gn:country_code":"CN",
    "gn:dem":321,
    "gn:feature_class":"P",
    "gn:feature_code":"PPL",
    "gn:name":"Niushifen",
    "gn:population":0,
    "gn:timezone":"Asia/Shanghai",
    "iso:country":"CN",
    "name:zho_x_preferred":[
        "\u725b\u5c4e\u7caa"
    ],
    "wof:name":"Niushifen",
    "wof:placetype":"locality"
},
  "geometry": {"coordinates":[113.80452,23.85492],"type":"Point"}
}