{
  "type": "Feature",
  "properties": {
    "gn:admin1_code":"8.0",
    "gn:asciiname":"Longgushan",
    "gn:country_code":"CN",
    "gn:dem":140,
    "gn:feature_class":"P",
    "gn:feature_code":"PPL",
    "gn:name":"Longgushan",
    "gn:population":0,
    "gn:timezone":"Asia/Shanghai",
    "iso:country":"CN",
    "name:zho_x_preferred":[
        "\u9f99\u9aa8\u5c71"
    ],
    "wof:name":"Longgushan",
    "wof:placetype":"locality"
},
  "geometry": {"coordinates":[130.23887999999999,48.85655],"type":"Point"}
}