{
  "type": "Feature",
  "properties": {
    "gn:admin1_code":"15.0",
    "gn:asciiname":"Jiazishi",
    "gn:country_code":"CN",
    "gn:dem":1698,
    "gn:feature_class":"P",
    "gn:feature_code":"PPL",
    "gn:name":"Jiazishi",
    "gn:population":0,
    "gn:timezone":"Asia/Shanghai",
    "iso:country":"CN",
    "name:und_x_variant":[
        "\u67b6\u5b50\u77f3"
    ],
    "wof:name":"Jiazishi",
    "wof:placetype":"locality"
},
  "geometry": {"coordinates":[105.18349000000001,33.1114],"type":"Point"}
}