{
  "type": "Feature",
  "properties": {
    "gn:admin1_code":"8.0",
    "gn:asciiname":"Haixingcun",
    "gn:country_code":"CN",
    "gn:dem":199,
    "gn:feature_class":"P",
    "gn:feature_code":"PPL",
    "gn:name":"Haixingcun",
    "gn:population":0,
    "gn:timezone":"Asia/Shanghai",
    "iso:country":"CN",
    "name:zho_x_preferred":[
        "\u6d77\u5174\u6751"
    ],
    "wof:name":"Haixingcun",
    "wof:placetype":"locality"
},
  "geometry": {"coordinates":[123.02472,47.38756],"type":"Point"}
}