{
  "type": "Feature",
  "properties": {
    "gn:admin1_code":"25",
    "gn:asciiname":"Qiujiazhuang",
    "gn:country_code":"CN",
    "gn:dem":248,
    "gn:feature_class":"P",
    "gn:feature_code":"PPL",
    "gn:name":"Qiujiazhuang",
    "gn:population":0,
    "gn:timezone":"Asia/Shanghai",
    "iso:country":"CN",
    "name:zho_x_preferred":[
        "\u90b1\u5bb6\u5e84"
    ],
    "wof:name":"Qiujiazhuang",
    "wof:placetype":"locality"
},
  "geometry": {"coordinates":[116.95099999999999,36.174],"type":"Point"}
}