{
  "type": "Feature",
  "properties": {
    "gn:admin1_code":"4.0",
    "gn:asciiname":"Wanjia",
    "gn:country_code":"CN",
    "gn:dem":6,
    "gn:feature_class":"P",
    "gn:feature_code":"PPL",
    "gn:name":"Wanjia",
    "gn:population":0,
    "gn:timezone":"Asia/Shanghai",
    "iso:country":"CN",
    "name:zho_x_preferred":[
        "Wanjia"
    ],
    "name:zho_x_variant":[
        "\u4e07\u5bb6"
    ],
    "wof:name":"Wanjia",
    "wof:placetype":"locality"
},
  "geometry": {"coordinates":[119.40203,33.99964],"type":"Point"}
}