{
  "type": "Feature",
  "properties": {
    "gn:admin1_code":"8.0",
    "gn:asciiname":"Sijingzi",
    "gn:country_code":"CN",
    "gn:dem":213,
    "gn:feature_class":"P",
    "gn:feature_code":"PPL",
    "gn:name":"Sijingzi",
    "gn:population":0,
    "gn:timezone":"Asia/Shanghai",
    "iso:country":"CN",
    "name:zho_x_preferred":[
        "\u56db\u4e95\u5b50"
    ],
    "wof:name":"Sijingzi",
    "wof:placetype":"locality"
},
  "geometry": {"coordinates":[126.83405999999999,47.61368],"type":"Point"}
}