{
  "type": "Feature",
  "properties": {
    "gn:admin1_code":"7.0",
    "gn:asciiname":"Xianliang Zhongchang",
    "gn:country_code":"CN",
    "gn:dem":203,
    "gn:feature_class":"P",
    "gn:feature_code":"PPL",
    "gn:name":"Xianliang Zhongchang",
    "gn:population":0,
    "gn:timezone":"Asia/Shanghai",
    "iso:country":"CN",
    "name:zho_x_preferred":[
        "\u53bf\u826f\u79cd\u573a"
    ],
    "wof:name":"Xianliang Zhongchang",
    "wof:placetype":"locality"
},
  "geometry": {"coordinates":[118.80110000000001,27.53621],"type":"Point"}
}