{
  "type": "Feature",
  "properties": {
    "gn:admin1_code":"32.0",
    "gn:asciiname":"Yuancang",
    "gn:country_code":"CN",
    "gn:dem":797,
    "gn:feature_class":"P",
    "gn:feature_code":"PPL",
    "gn:name":"Yuancang",
    "gn:population":0,
    "gn:timezone":"Asia/Shanghai",
    "iso:country":"CN",
    "name:zho_x_preferred":[
        "\u56ed\u4ed3"
    ],
    "wof:name":"Yuancang",
    "wof:placetype":"locality"
},
  "geometry": {"coordinates":[103.773,31.1184],"type":"Point"}
}