{
  "type": "Feature",
  "properties": {
    "gn:admin1_code":"29.0",
    "gn:asciiname":"Huangliantang",
    "gn:country_code":"CN",
    "gn:dem":1785,
    "gn:feature_class":"P",
    "gn:feature_code":"PPL",
    "gn:name":"Huangliantang",
    "gn:population":0,
    "gn:timezone":"Asia/Shanghai",
    "iso:country":"CN",
    "name:zho_x_preferred":[
        "\u9ec4\u83b2\u5858"
    ],
    "wof:name":"Huangliantang",
    "wof:placetype":"locality"
},
  "geometry": {"coordinates":[101.557,25.3078],"type":"Point"}
}