{
  "type": "Feature",
  "properties": {
    "gn:admin1_code":"5.0",
    "gn:asciiname":"Shangqingcun",
    "gn:country_code":"CN",
    "gn:dem":617,
    "gn:feature_class":"P",
    "gn:feature_code":"PPL",
    "gn:name":"Shangqingcun",
    "gn:population":0,
    "gn:timezone":"Asia/Shanghai",
    "iso:country":"CN",
    "name:zho_x_preferred":[
        "\u4e0a\u9752\u6751"
    ],
    "wof:name":"Shangqingcun",
    "wof:placetype":"locality"
},
  "geometry": {"coordinates":[126.44034000000001,42.03103],"type":"Point"}
}