{
  "type": "Feature",
  "properties": {
    "gn:admin1_code":"12.0",
    "gn:asciiname":"Houying",
    "gn:country_code":"CN",
    "gn:dem":37,
    "gn:feature_class":"P",
    "gn:feature_code":"PPL",
    "gn:name":"Houying",
    "gn:population":0,
    "gn:timezone":"Asia/Shanghai",
    "iso:country":"CN",
    "name:zho_x_preferred":[
        "\u540e\u8425"
    ],
    "name:zho_x_variant":[
        "\u4faf\u8425\u9547"
    ],
    "wof:name":"Houying",
    "wof:placetype":"locality"
},
  "geometry": {"coordinates":[112.61005,30.93538],"type":"Point"}
}