{
  "type": "Feature",
  "properties": {
    "gn:admin1_code":"29.0",
    "gn:asciiname":"Kami",
    "gn:country_code":"CN",
    "gn:dem":786,
    "gn:feature_class":"P",
    "gn:feature_code":"PPL",
    "gn:name":"Kami",
    "gn:population":0,
    "gn:timezone":"Asia/Shanghai",
    "iso:country":"CN",
    "name:ara_x_preferred":[
        "\u0643\u0627\u0645\u064a"
    ],
    "name:aze_x_preferred":[
        "Kami"
    ],
    "name:cat_x_preferred":[
        "Kami"
    ],
    "name:ces_x_preferred":[
        "Kami"
    ],
    "name:dan_x_preferred":[
        "Kami"
    ],
    "name:deu_x_preferred":[
        "Kami"
    ],
    "name:epo_x_preferred":[
        "Kamio"
    ],
    "name:est_x_preferred":[
        "Kami"
    ],
    "name:fas_x_preferred":[
        "\u06a9\u0627\u0645\u06cc"
    ],
    "name:fin_x_preferred":[
        "Kami"
    ],
    "name:fra_x_preferred":[
        "Kami"
    ],
    "name:gla_x_preferred":[
        "Kami"
    ],
    "name:heb_x_preferred":[
        "\u05e7\u05d0\u05de\u05d9"
    ],
    "name:hrv_x_preferred":[
        "Kami"
    ],
    "name:hun_x_preferred":[
        "Kami"
    ],
    "name:hye_x_preferred":[
        "\u053f\u0561\u0574\u056b"
    ],
    "name:ind_x_preferred":[
        "Kami"
    ],
    "name:ita_x_preferred":[
        "Kami"
    ],
    "name:jpn_x_preferred":[
        "\u795e"
    ],
    "name:kat_x_preferred":[
        "\u10d9\u10d0\u10db\u10d8"
    ],
    "name:lfn_x_preferred":[
        "Cami"
    ],
    "name:lit_x_preferred":[
        "Kami"
    ],
    "name:ltz_x_preferred":[
        "Kami"
    ],
    "name:mal_x_preferred":[
        "\u0d15\u0d3e\u0d2e\u0d3f"
    ],
    "name:nah_x_preferred":[
        "Kami"
    ],
    "name:nld_x_preferred":[
        "Kami"
    ],
    "name:nor_x_preferred":[
        "Kami"
    ],
    "name:pol_x_preferred":[
        "Kami"
    ],
    "name:por_x_preferred":[
        "Kami"
    ],
    "name:ron_x_preferred":[
        "Kami"
    ],
    "name:rus_x_preferred":[
        "\u041a\u0430\u043c\u0438"
    ],
    "name:spa_x_preferred":[
        "Kami"
    ],
    "name:srd_x_preferred":[
        "Kami"
    ],
    "name:swe_x_preferred":[
        "Kami"
    ],
    "name:tur_x_preferred":[
        "Kami"
    ],
    "name:ukr_x_preferred":[
        "\u041a\u0430\u043c\u0456"
    ],
    "name:urd_x_preferred":[
        "\u06a9\u0627\u0645\u06cc"
    ],
    "name:vie_x_preferred":[
        "Kami"
    ],
    "name:zho_x_preferred":[
        "\u5361\u54aa"
    ],
    "name:zho_x_variant":[
        "\u795e"
    ],
    "wof:name":"Kami",
    "wof:placetype":"locality"
},
  "geometry": {"coordinates":[101.70399999999999,21.6559],"type":"Point"}
}