{
  "type": "Feature",
  "properties": {
    "gn:admin1_code":"26.0",
    "gn:asciiname":"Yuzhang",
    "gn:country_code":"CN",
    "gn:dem":1574,
    "gn:feature_class":"P",
    "gn:feature_code":"PPL",
    "gn:name":"Yuzhang",
    "gn:population":0,
    "gn:timezone":"Asia/Shanghai",
    "iso:country":"CN",
    "name:zho_x_preferred":[
        "\u6986\u638c"
    ],
    "wof:name":"Yuzhang",
    "wof:placetype":"locality"
},
  "geometry": {"coordinates":[108.18268999999999,36.62549],"type":"Point"}
}