{
  "type": "Feature",
  "properties": {
    "gn:admin1_code":"29.0",
    "gn:asciiname":"Lupizhai",
    "gn:country_code":"CN",
    "gn:dem":1818,
    "gn:feature_class":"P",
    "gn:feature_code":"PPL",
    "gn:name":"L\u00fcpizhai",
    "gn:population":0,
    "gn:timezone":"Asia/Shanghai",
    "iso:country":"CN",
    "name:und_x_variant":[
        "L\u00fcpizhai"
    ],
    "name:zho_x_preferred":[
        "\u7eff\u76ae\u5be8"
    ],
    "wof:name":"Lupizhai",
    "wof:placetype":"locality"
},
  "geometry": {"coordinates":[99.12909999999999,23.7318],"type":"Point"}
}