{
  "type": "Feature",
  "properties": {
    "gn:admin1_code":"19.0",
    "gn:asciiname":"Songshuzui",
    "gn:country_code":"CN",
    "gn:dem":238,
    "gn:feature_class":"P",
    "gn:feature_code":"PPL",
    "gn:name":"Songshuzui",
    "gn:population":0,
    "gn:timezone":"Asia/Shanghai",
    "iso:country":"CN",
    "name:zho_x_preferred":[
        "\u677e\u6811\u5480"
    ],
    "wof:name":"Songshuzui",
    "wof:placetype":"locality"
},
  "geometry": {"coordinates":[124.93711999999999,42.36447],"type":"Point"}
}