{
  "type": "Feature",
  "properties": {
    "gn:admin1_code":"4.0",
    "gn:asciiname":"Diaonan",
    "gn:country_code":"CN",
    "gn:dem":4,
    "gn:feature_class":"P",
    "gn:feature_code":"PPL",
    "gn:name":"Diaonan",
    "gn:population":0,
    "gn:timezone":"Asia/Shanghai",
    "iso:country":"CN",
    "name:zho_x_preferred":[
        "\u7a8e\u5357"
    ],
    "wof:name":"Diaonan",
    "wof:placetype":"locality"
},
  "geometry": {"coordinates":[121.18064,32.17833],"type":"Point"}
}