{
  "type": "Feature",
  "properties": {
    "gn:admin1_code":"29",
    "gn:asciiname":"Guyu",
    "gn:country_code":"CN",
    "gn:dem":971,
    "gn:feature_class":"P",
    "gn:feature_code":"PPL",
    "gn:name":"Guyu",
    "gn:population":0,
    "gn:timezone":"Asia/Shanghai",
    "iso:country":"CN",
    "name:zho_x_preferred":[
        "\u53e4\u9c7c"
    ],
    "wof:name":"Guyu",
    "wof:placetype":"locality"
},
  "geometry": {"coordinates":[104.80500000000001,23.5128],"type":"Point"}
}