{
  "type": "Feature",
  "properties": {
    "gn:admin1_code":"29.0",
    "gn:asciiname":"Niutangzhai",
    "gn:country_code":"CN",
    "gn:dem":776,
    "gn:feature_class":"P",
    "gn:feature_code":"PPL",
    "gn:name":"Niutangzhai",
    "gn:population":0,
    "gn:timezone":"Asia/Shanghai",
    "iso:country":"CN",
    "name:zho_x_preferred":[
        "\u725b\u5858\u5be8"
    ],
    "wof:name":"Niutangzhai",
    "wof:placetype":"locality"
},
  "geometry": {"coordinates":[102.99299999999999,22.7105],"type":"Point"}
}