{
  "type": "Feature",
  "properties": {
    "gn:admin1_code":"25.0",
    "gn:asciiname":"Dahuangbu",
    "gn:country_code":"CN",
    "gn:dem":13,
    "gn:feature_class":"P",
    "gn:feature_code":"PPL",
    "gn:name":"Dahuangbu",
    "gn:population":0,
    "gn:timezone":"Asia/Shanghai",
    "iso:country":"CN",
    "name:zho_x_preferred":[
        "\u5927\u9ec4\u57e0"
    ],
    "wof:name":"Dahuangbu",
    "wof:placetype":"locality"
},
  "geometry": {"coordinates":[119.59844,36.73633],"type":"Point"}
}