{
  "type": "Feature",
  "properties": {
    "gn:admin1_code":"11.0",
    "gn:asciiname":"Hulianping",
    "gn:country_code":"CN",
    "gn:dem":49,
    "gn:feature_class":"P",
    "gn:feature_code":"PPL",
    "gn:name":"Hulianping",
    "gn:population":0,
    "gn:timezone":"Asia/Shanghai",
    "iso:country":"CN",
    "name:zho_x_preferred":[
        "\u6e56\u83b2\u576a"
    ],
    "wof:name":"Hulianping",
    "wof:placetype":"locality"
},
  "geometry": {"coordinates":[111.93246000000001,28.60229],"type":"Point"}
}