{
  "type": "Feature",
  "properties": {
    "gn:admin1_code":"7.0",
    "gn:asciiname":"Liangtian",
    "gn:country_code":"CN",
    "gn:dem":700,
    "gn:feature_class":"P",
    "gn:feature_code":"PPL",
    "gn:name":"Liangtian",
    "gn:population":0,
    "gn:timezone":"Asia/Shanghai",
    "iso:country":"CN",
    "name:zho_x_preferred":[
        "\u826f\u7530"
    ],
    "wof:name":"Liangtian",
    "wof:placetype":"locality"
},
  "geometry": {"coordinates":[117.7971,24.89249],"type":"Point"}
}