{
  "type": "Feature",
  "properties": {
    "gn:admin1_code":"25",
    "gn:asciiname":"Genglou",
    "gn:country_code":"CN",
    "gn:dem":19,
    "gn:feature_class":"P",
    "gn:feature_code":"PPL",
    "gn:name":"Genglou",
    "gn:population":0,
    "gn:timezone":"Asia/Shanghai",
    "iso:country":"CN",
    "name:zho_x_preferred":[
        "\u803f\u697c"
    ],
    "wof:name":"Genglou",
    "wof:placetype":"locality"
},
  "geometry": {"coordinates":[117.01300000000001,37.2706],"type":"Point"}
}