{
  "type": "Feature",
  "properties": {
    "gn:admin1_code":"25.0",
    "gn:asciiname":"Guandao",
    "gn:country_code":"CN",
    "gn:dem":114,
    "gn:feature_class":"P",
    "gn:feature_code":"PPLA4",
    "gn:name":"Guandao",
    "gn:population":0,
    "gn:timezone":"Asia/Shanghai",
    "iso:country":"CN",
    "name:und_x_variant":[
        "Guandao Zhen"
    ],
    "name:zho_x_preferred":[
        "\u5b98\u9053"
    ],
    "name:zho_x_variant":[
        "\u5b98\u9053\u9547"
    ],
    "wof:name":"Guandao",
    "wof:placetype":"locality"
},
  "geometry": {"coordinates":[120.6212,37.21098],"type":"Point"}
}