{
  "type": "Feature",
  "properties": {
    "gn:admin1_code":"25.0",
    "gn:asciiname":"Guandao",
    "gn:country_code":"CN",
    "gn:dem":114,
    "gn:feature_class":"P",
    "gn:feature_code":"PPLA4",
    "gn:name":"Guandao",
    "gn:population":0,
    "gn:timezone":"Asia/Shanghai",
    "iso:country":"CN",
    "name:ces_x_preferred":[
        "Kuan tao"
    ],
    "name:deu_x_preferred":[
        "Guan Dao"
    ],
    "name:ind_x_preferred":[
        "Guan dao"
    ],
    "name:ita_x_preferred":[
        "Guan dao"
    ],
    "name:jpn_x_preferred":[
        "\u5927\u5200"
    ],
    "name:kor_x_preferred":[
        "\uc5b8\uc6d4\ub3c4"
    ],
    "name:lit_x_preferred":[
        "Guandao"
    ],
    "name:nor_x_preferred":[
        "Guan dao"
    ],
    "name:pol_x_preferred":[
        "Guan dao"
    ],
    "name:por_x_preferred":[
        "Guan dao"
    ],
    "name:rus_x_preferred":[
        "\u0413\u0443\u0430\u043d\u044c \u0434\u0430\u043e"
    ],
    "name:spa_x_preferred":[
        "Guan dao"
    ],
    "name:tha_x_preferred":[
        "\u0e07\u0e49\u0e32\u0e27"
    ],
    "name:ukr_x_preferred":[
        "\u0426\u0437\u0456\u043d\u043b\u0443\u043d \u044f\u043d\u044c\u044e\u0435\u0434\u0430\u043e"
    ],
    "name:und_x_variant":[
        "Guandao Zhen"
    ],
    "name:vie_x_preferred":[
        "Quan \u0111ao"
    ],
    "name:zho_x_preferred":[
        "\u5b98\u9053"
    ],
    "name:zho_x_variant":[
        "\u5b98\u9053\u9547",
        "\u5043\u6708\u5200"
    ],
    "wof:name":"Guandao",
    "wof:placetype":"locality"
},
  "geometry": {"coordinates":[120.6212,37.21098],"type":"Point"}
}