{
  "type": "Feature",
  "properties": {
    "gn:admin1_code":"07",
    "gn:asciiname":"Shangkeng",
    "gn:country_code":"CN",
    "gn:dem":852,
    "gn:feature_class":"P",
    "gn:feature_code":"PPL",
    "gn:name":"Shangkeng",
    "gn:population":0,
    "gn:timezone":"Asia/Shanghai",
    "iso:country":"CN",
    "name:zho_x_preferred":[
        "\u4e0a\u5751"
    ],
    "wof:name":"Shangkeng",
    "wof:placetype":"locality"
},
  "geometry": {"coordinates":[118.15582999999999,25.49167000000001],"type":"Point"}
}