{
  "type": "Feature",
  "properties": {
    "gn:admin1_code":"4.0",
    "gn:asciiname":"Wudufangcun",
    "gn:country_code":"CN",
    "gn:dem":20,
    "gn:feature_class":"P",
    "gn:feature_code":"PPL",
    "gn:name":"Wudufangcun",
    "gn:population":0,
    "gn:timezone":"Asia/Shanghai",
    "iso:country":"CN",
    "name:zho_x_preferred":[
        "\u4e94\u5835\u574a\u6751"
    ],
    "wof:name":"Wudufangcun",
    "wof:placetype":"locality"
},
  "geometry": {"coordinates":[119.10250000000001,31.80277],"type":"Point"}
}