{
  "type": "Feature",
  "properties": {
    "gn:admin1_code":"1.0",
    "gn:asciiname":"Houdongcun",
    "gn:country_code":"CN",
    "gn:dem":21,
    "gn:feature_class":"P",
    "gn:feature_code":"PPL",
    "gn:name":"Houdongcun",
    "gn:population":0,
    "gn:timezone":"Asia/Shanghai",
    "iso:country":"CN",
    "name:zho_x_preferred":[
        "\u7334\u6d1e\u6751"
    ],
    "wof:name":"Houdongcun",
    "wof:placetype":"locality"
},
  "geometry": {"coordinates":[117.11479,32.96765],"type":"Point"}
}