{
  "type": "Feature",
  "properties": {
    "gn:admin1_code":"16.0",
    "gn:asciiname":"Lichangtian",
    "gn:country_code":"CN",
    "gn:dem":164,
    "gn:feature_class":"P",
    "gn:feature_code":"PPL",
    "gn:name":"Lichangtian",
    "gn:population":0,
    "gn:timezone":"Asia/Shanghai",
    "iso:country":"CN",
    "name:zho_x_preferred":[
        "\u91cc\u957f\u7530"
    ],
    "wof:name":"Lichangtian",
    "wof:placetype":"locality"
},
  "geometry": {"coordinates":[110.718,22.7142],"type":"Point"}
}