{
  "type": "Feature",
  "properties": {
    "iso:country":"CN",
    "qs:name":"\u8499\u81ea\u53bf",
    "qs:name_adm0":"\u4e2d\u570b",
    "qs:name_adm1":"\u4e91\u5357\u7701",
    "qs:photos":20,
    "qs:photos_1k":4,
    "qs:photos_9k":1,
    "qs:photos_9r":4,
    "qs:photos_all":159,
    "qs:photos_sr":1,
    "qs:placetype":"LocalAdmin",
    "qs:pop_sr":"0",
    "wof:name":"\u8499\u81ea\u53bf",
    "wof:placetype":"localadmin"
},
  "geometry": {"coordinates":[103.38057499999999,23.369992],"type":"Point"}
}