{
  "type": "Feature",
  "properties": {
    "iso:country":"CN",
    "name:ell_x_preferred":[
        "\u039c\u03ad\u03bd\u03b3\u03ba\u03b6\u03b9"
    ],
    "name:eng_x_preferred":[
        "Mengzi"
    ],
    "name:eng_x_variant":[
        "Mengzi County"
    ],
    "name:fas_x_preferred":[
        "\u0645\u0646\u06af\u0632\u06cc"
    ],
    "name:heb_x_preferred":[
        "\u05de\u05e0\u05d2\u05d6\u05d9"
    ],
    "name:hin_x_preferred":[
        "\u092e\u0947\u0902\u0917\u094d\u091c\u093c\u0940"
    ],
    "name:hun_x_preferred":[
        "Mengzi"
    ],
    "name:ind_x_preferred":[
        "Mengzi"
    ],
    "name:nld_x_preferred":[
        "Mengzi"
    ],
    "name:pol_x_preferred":[
        "Mengzi"
    ],
    "name:spa_x_preferred":[
        "Mengzi"
    ],
    "name:tur_x_preferred":[
        "Mengzi"
    ],
    "name:zho_x_preferred":[
        "\u8499\u81ea\u53bf"
    ],
    "qs:name":"\u8499\u81ea\u53bf",
    "qs:name_adm0":"\u4e2d\u570b",
    "qs:name_adm1":"\u4e91\u5357\u7701",
    "qs:photos":20,
    "qs:photos_1k":4,
    "qs:photos_9k":1,
    "qs:photos_9r":4,
    "qs:photos_all":159,
    "qs:photos_sr":1,
    "qs:placetype":"LocalAdmin",
    "qs:pop_sr":"0",
    "wof:name":"Mengzi",
    "wof:placetype":"localadmin"
},
  "geometry": {"coordinates":[103.38057499999999,23.369992],"type":"Point"}
}