{
  "type": "Feature",
  "properties": {
    "gn:admin1_code":"16",
    "gn:asciiname":"Shangjiuping",
    "gn:country_code":"CN",
    "gn:dem":739,
    "gn:feature_class":"P",
    "gn:feature_code":"PPL",
    "gn:name":"Shangjiuping",
    "gn:population":0,
    "gn:timezone":"Asia/Shanghai",
    "iso:country":"CN",
    "name:zho_x_preferred":[
        "\u4e0a\u4e5d\u576a"
    ],
    "wof:name":"Shangjiuping",
    "wof:placetype":"locality"
},
  "geometry": {"coordinates":[109.733,25.5972],"type":"Point"}
}