{
  "type": "Feature",
  "properties": {
    "gn:admin1_code":"4.0",
    "gn:asciiname":"Heshanggou",
    "gn:country_code":"CN",
    "gn:dem":1,
    "gn:feature_class":"P",
    "gn:feature_code":"PPL",
    "gn:name":"Heshanggou",
    "gn:population":0,
    "gn:timezone":"Asia/Shanghai",
    "iso:country":"CN",
    "name:zho_x_preferred":[
        "\u548c\u5c1a\u6c9f"
    ],
    "wof:name":"Heshanggou",
    "wof:placetype":"locality"
},
  "geometry": {"coordinates":[119.9091,32.70169],"type":"Point"}
}