{
  "type": "Feature",
  "properties": {
    "gn:admin1_code":"10.0",
    "gn:asciiname":"Dawantai",
    "gn:country_code":"CN",
    "gn:dem":833,
    "gn:feature_class":"P",
    "gn:feature_code":"PPL",
    "gn:name":"Dawantai",
    "gn:population":0,
    "gn:timezone":"Asia/Shanghai",
    "iso:country":"CN",
    "name:zho_x_preferred":[
        "\u5927\u6e7e\u53f0"
    ],
    "wof:name":"Dawantai",
    "wof:placetype":"locality"
},
  "geometry": {"coordinates":[114.59267,40.20694],"type":"Point"}
}