{
  "type": "Feature",
  "properties": {
    "gn:admin1_code":"1.0",
    "gn:asciiname":"Qianhongcun",
    "gn:country_code":"CN",
    "gn:dem":56,
    "gn:feature_class":"P",
    "gn:feature_code":"PPL",
    "gn:name":"Qianhongcun",
    "gn:population":0,
    "gn:timezone":"Asia/Shanghai",
    "iso:country":"CN",
    "name:zho_x_preferred":[
        "\u524d\u6d2a\u6751"
    ],
    "wof:name":"Qianhongcun",
    "wof:placetype":"locality"
},
  "geometry": {"coordinates":[117.88928,32.77771],"type":"Point"}
}