{
  "type": "Feature",
  "properties": {
    "gn:admin1_code":"15.0",
    "gn:asciiname":"Qialai",
    "gn:country_code":"CN",
    "gn:dem":3185,
    "gn:feature_class":"P",
    "gn:feature_code":"PPL",
    "gn:name":"Qialai",
    "gn:population":0,
    "gn:timezone":"Asia/Shanghai",
    "iso:country":"CN",
    "name:zho_x_preferred":[
        "\u6070\u6765"
    ],
    "wof:name":"Qialai",
    "wof:placetype":"locality"
},
  "geometry": {"coordinates":[103.083,35.2208],"type":"Point"}
}