{
  "type": "Feature",
  "properties": {
    "gn:admin1_code":"05",
    "gn:asciiname":"Sanlincun",
    "gn:country_code":"CN",
    "gn:dem":141,
    "gn:feature_class":"P",
    "gn:feature_code":"PPL",
    "gn:name":"Sanlincun",
    "gn:population":0,
    "gn:timezone":"Asia/Shanghai",
    "iso:country":"CN",
    "name:und_x_variant":[
        "Sanlin"
    ],
    "name:zho_x_preferred":[
        "\u4e09\u6797\u6751"
    ],
    "wof:name":"Sanlincun",
    "wof:placetype":"locality"
},
  "geometry": {"coordinates":[123.34506,44.04756],"type":"Point"}
}