{
  "type": "Feature",
  "properties": {
    "gn:admin1_code":"11",
    "gn:asciiname":"Jinzhushan",
    "gn:cc2":"CN",
    "gn:country_code":"CN",
    "gn:dem":223,
    "gn:feature_class":"P",
    "gn:feature_code":"PPL",
    "gn:name":"Jinzhushan",
    "gn:population":0,
    "gn:timezone":"Asia/Shanghai",
    "iso:country":"CN",
    "name:und_x_variant":[
        "Chin-chu-shan",
        "Jinzhushan"
    ],
    "wof:name":"Jinzhushan",
    "wof:placetype":"locality"
},
  "geometry": {"coordinates":[111.49444,27.60528],"type":"Point"}
}