{
  "type": "Feature",
  "properties": {
    "gn:admin1_code":"3.0",
    "gn:asciiname":"Madi",
    "gn:country_code":"CN",
    "gn:dem":172,
    "gn:feature_class":"P",
    "gn:feature_code":"PPL",
    "gn:name":"Madi",
    "gn:population":0,
    "gn:timezone":"Asia/Shanghai",
    "iso:country":"CN",
    "name:cat_x_preferred":[
        "Madi"
    ],
    "name:ceb_x_preferred":[
        "Madi"
    ],
    "name:deu_x_preferred":[
        "Madi"
    ],
    "name:fra_x_preferred":[
        "Madi"
    ],
    "name:swe_x_preferred":[
        "Madi"
    ],
    "name:zho_x_preferred":[
        "\u9ebb\u5730"
    ],
    "wof:name":"Madi",
    "wof:placetype":"locality"
},
  "geometry": {"coordinates":[117.1961,27.9289],"type":"Point"}
}