{
  "type": "Feature",
  "properties": {
    "gn:admin1_code":"11",
    "gn:asciiname":"Dajie",
    "gn:country_code":"CN",
    "gn:dem":268,
    "gn:feature_class":"P",
    "gn:feature_code":"PPL",
    "gn:name":"Dajie",
    "gn:population":0,
    "gn:timezone":"Asia/Shanghai",
    "iso:country":"CN",
    "name:ceb_x_preferred":[
        "Dajie"
    ],
    "name:deu_x_preferred":[
        "Dajie"
    ],
    "name:swe_x_preferred":[
        "Dajie"
    ],
    "name:und_x_variant":[
        "\u5927\u754c",
        "Dajie"
    ],
    "wof:name":"Dajie",
    "wof:placetype":"locality"
},
  "geometry": {"coordinates":[111.94972,25.48167],"type":"Point"}
}