{
  "type": "Feature",
  "properties": {
    "gn:admin1_code":"7.0",
    "gn:asciiname":"Bingzhou",
    "gn:country_code":"CN",
    "gn:dem":8,
    "gn:feature_class":"P",
    "gn:feature_code":"PPL",
    "gn:name":"Bingzhou",
    "gn:population":0,
    "gn:timezone":"Asia/Shanghai",
    "iso:country":"CN",
    "name:zho_x_preferred":[
        "\u4e19\u6d32"
    ],
    "wof:name":"Bingzhou",
    "wof:placetype":"locality"
},
  "geometry": {"coordinates":[118.17818,24.65364],"type":"Point"}
}