{
  "type": "Feature",
  "properties": {
    "gn:admin1_code":"26.0",
    "gn:asciiname":"Mimiantacun",
    "gn:country_code":"CN",
    "gn:dem":1253,
    "gn:feature_class":"P",
    "gn:feature_code":"PPL",
    "gn:name":"Mimiantacun",
    "gn:population":0,
    "gn:timezone":"Asia/Shanghai",
    "iso:country":"CN",
    "name:zho_x_preferred":[
        "\u7c73\u9762\u5854\u6751"
    ],
    "wof:name":"Mimiantacun",
    "wof:placetype":"locality"
},
  "geometry": {"coordinates":[109.18518,37.30421],"type":"Point"}
}