{
  "type": "Feature",
  "properties": {
    "gn:admin1_code":"33.0",
    "gn:asciiname":"Guochanggou",
    "gn:country_code":"CN",
    "gn:dem":1088,
    "gn:feature_class":"P",
    "gn:feature_code":"PPL",
    "gn:name":"Guochanggou",
    "gn:population":0,
    "gn:timezone":"Asia/Shanghai",
    "iso:country":"CN",
    "name:zho_x_preferred":[
        "\u9505\u5382\u6c9f"
    ],
    "wof:name":"Guochanggou",
    "wof:placetype":"locality"
},
  "geometry": {"coordinates":[108.56337000000001,28.95018],"type":"Point"}
}