{
  "type": "Feature",
  "properties": {
    "gn:admin1_code":"3.0",
    "gn:asciiname":"Xiashancun",
    "gn:country_code":"CN",
    "gn:dem":61,
    "gn:feature_class":"P",
    "gn:feature_code":"PPL",
    "gn:name":"Xiashancun",
    "gn:population":0,
    "gn:timezone":"Asia/Shanghai",
    "iso:country":"CN",
    "name:und_x_variant":[
        "\u971e\u5c71\u6751"
    ],
    "wof:name":"Xiashancun",
    "wof:placetype":"locality"
},
  "geometry": {"coordinates":[115.69226999999999,28.65457],"type":"Point"}
}