{
  "type": "Feature",
  "properties": {
    "gn:admin1_code":"30.0",
    "gn:asciiname":"Hewu",
    "gn:country_code":"CN",
    "gn:dem":124,
    "gn:feature_class":"P",
    "gn:feature_code":"PPL",
    "gn:name":"Hewu",
    "gn:population":0,
    "gn:timezone":"Asia/Shanghai",
    "iso:country":"CN",
    "name:zho_x_preferred":[
        "Hewu"
    ],
    "name:zho_x_variant":[
        "\u4f55\u5c4b"
    ],
    "wof:name":"Hewu",
    "wof:placetype":"locality"
},
  "geometry": {"coordinates":[114.11181000000001,24.89764],"type":"Point"}
}