{
  "type": "Feature",
  "properties": {
    "gn:admin1_code":"29",
    "gn:asciiname":"Shangzuolie",
    "gn:country_code":"CN",
    "gn:dem":1887,
    "gn:feature_class":"P",
    "gn:feature_code":"PPL",
    "gn:name":"Shangzuolie",
    "gn:population":0,
    "gn:timezone":"Asia/Shanghai",
    "iso:country":"CN",
    "name:zho_x_preferred":[
        "\u4e0a\u5de6\u5217"
    ],
    "wof:name":"Shangzuolie",
    "wof:placetype":"locality"
},
  "geometry": {"coordinates":[103.181,24.5766],"type":"Point"}
}