{
  "type": "Feature",
  "properties": {
    "gn:admin1_code":"15.0",
    "gn:asciiname":"Luankutuo",
    "gn:country_code":"CN",
    "gn:dem":2123,
    "gn:feature_class":"P",
    "gn:feature_code":"PPL",
    "gn:name":"Luankutuo",
    "gn:population":0,
    "gn:timezone":"Asia/Shanghai",
    "iso:country":"CN",
    "name:zho_x_preferred":[
        "\u4e71\u5e93\u9a7c"
    ],
    "wof:name":"Luankutuo",
    "wof:placetype":"locality"
},
  "geometry": {"coordinates":[104.173,36.0948],"type":"Point"}
}