{
  "type": "Feature",
  "properties": {
    "gn:admin1_code":"32",
    "gn:asciiname":"Shuanghe",
    "gn:country_code":"CN",
    "gn:dem":647,
    "gn:feature_class":"P",
    "gn:feature_code":"PPL",
    "gn:name":"Shuanghe",
    "gn:population":0,
    "gn:timezone":"Asia/Shanghai",
    "iso:country":"CN",
    "name:und_x_variant":[
        "Lianghekou",
        "Liang-ho-k\u2019ou",
        "Shuanghekou",
        "Shuanghe"
    ],
    "name:zho_x_preferred":[
        "\u53cc\u6cb3"
    ],
    "wof:name":"Shuanghe",
    "wof:placetype":"locality"
},
  "geometry": {"coordinates":[104.88188999999998,31.86653],"type":"Point"}
}