{
  "type": "Feature",
  "properties": {
    "gn:admin1_code":"14.0",
    "gn:asciiname":"Jindakacun",
    "gn:country_code":"CN",
    "gn:dem":3967,
    "gn:feature_class":"P",
    "gn:feature_code":"PPL",
    "gn:name":"Jindakacun",
    "gn:population":0,
    "gn:timezone":"Asia/Urumqi",
    "iso:country":"CN",
    "name:zho_x_preferred":[
        "\u91d1\u8fbe\u5361\u6751"
    ],
    "wof:name":"Jindakacun",
    "wof:placetype":"locality"
},
  "geometry": {"coordinates":[96.55879,31.34819],"type":"Point"}
}