{
  "type": "Feature",
  "properties": {
    "gn:admin1_code":"14.0",
    "gn:asciiname":"Chatuocun",
    "gn:country_code":"CN",
    "gn:dem":3723,
    "gn:feature_class":"P",
    "gn:feature_code":"PPL",
    "gn:name":"Chatuocun",
    "gn:population":0,
    "gn:timezone":"Asia/Urumqi",
    "iso:country":"CN",
    "name:zho_x_preferred":[
        "\u67e5\u6258\u6751"
    ],
    "wof:name":"Chatuocun",
    "wof:placetype":"locality"
},
  "geometry": {"coordinates":[98.35182,30.77742000000001],"type":"Point"}
}