{
  "type": "Feature",
  "properties": {
    "gn:admin1_code":"11.0",
    "gn:asciiname":"Leli",
    "gn:country_code":"CN",
    "gn:dem":797,
    "gn:feature_class":"P",
    "gn:feature_code":"PPL",
    "gn:name":"Leli",
    "gn:population":0,
    "gn:timezone":"Asia/Shanghai",
    "iso:country":"CN",
    "name:zho_x_preferred":[
        "\u52d2\u91cc"
    ],
    "wof:name":"Leli",
    "wof:placetype":"locality"
},
  "geometry": {"coordinates":[113.94875,26.02594],"type":"Point"}
}