{
  "type": "Feature",
  "properties": {
    "gn:admin1_code":"30.0",
    "gn:asciiname":"Zhongliancun",
    "gn:country_code":"CN",
    "gn:dem":6,
    "gn:feature_class":"P",
    "gn:feature_code":"PPL",
    "gn:name":"Zhongliancun",
    "gn:population":0,
    "gn:timezone":"Asia/Shanghai",
    "iso:country":"CN",
    "name:zho_x_preferred":[
        "\u4e2d\u8054\u6751"
    ],
    "wof:name":"Zhongliancun",
    "wof:placetype":"locality"
},
  "geometry": {"coordinates":[116.41057000000001,23.54297],"type":"Point"}
}