{
  "type": "Feature",
  "properties": {
    "gn:admin1_code":"9.0",
    "gn:asciiname":"Qianwan",
    "gn:country_code":"CN",
    "gn:dem":179,
    "gn:feature_class":"P",
    "gn:feature_code":"PPL",
    "gn:name":"Qianwan",
    "gn:population":0,
    "gn:timezone":"Asia/Shanghai",
    "iso:country":"CN",
    "name:und_x_variant":[
        "\u524d\u6e7e",
        "Qianwan"
    ],
    "wof:name":"Qianwan",
    "wof:placetype":"locality"
},
  "geometry": {"coordinates":[112.53594,33.36872],"type":"Point"}
}