{
  "type": "Feature",
  "properties": {
    "gn:admin1_code":"29",
    "gn:asciiname":"Poya",
    "gn:country_code":"CN",
    "gn:dem":458,
    "gn:feature_class":"P",
    "gn:feature_code":"PPL",
    "gn:name":"Poya",
    "gn:population":0,
    "gn:timezone":"Asia/Shanghai",
    "iso:country":"CN",
    "name:sin_x_preferred":[
        "\u0db4\u0ddc\u0dc4\u0ddc\u0dba"
    ],
    "name:ukr_x_preferred":[
        "\u0414\u0435\u043d\u044c \u041f\u043e\u044f"
    ],
    "name:zho_x_preferred":[
        "\u5761\u82bd"
    ],
    "wof:name":"Poya",
    "wof:placetype":"locality"
},
  "geometry": {"coordinates":[106.09399999999999,23.8591],"type":"Point"}
}