{
  "type": "Feature",
  "properties": {
    "gn:admin1_code":"5.0",
    "gn:asciiname":"Dasandaogang",
    "gn:country_code":"CN",
    "gn:dem":198,
    "gn:feature_class":"P",
    "gn:feature_code":"PPL",
    "gn:name":"Dasandaogang",
    "gn:population":0,
    "gn:timezone":"Asia/Shanghai",
    "iso:country":"CN",
    "name:zho_x_preferred":[
        "\u5927\u4e09\u9053\u5c97"
    ],
    "wof:name":"Dasandaogang",
    "wof:placetype":"locality"
},
  "geometry": {"coordinates":[126.78331,44.66507],"type":"Point"}
}