{
  "type": "Feature",
  "properties": {
    "gn:admin1_code":"5.0",
    "gn:asciiname":"Liujia Hekou",
    "gn:country_code":"CN",
    "gn:dem":172,
    "gn:feature_class":"P",
    "gn:feature_code":"PPL",
    "gn:name":"Liujia Hekou",
    "gn:population":0,
    "gn:timezone":"Asia/Shanghai",
    "iso:country":"CN",
    "name:zho_x_preferred":[
        "\u5218\u5bb6\u6cb3\u53e3"
    ],
    "wof:name":"Liujia Hekou",
    "wof:placetype":"locality"
},
  "geometry": {"coordinates":[124.69079000000001,43.5403],"type":"Point"}
}