{
  "type": "Feature",
  "properties": {
    "gn:admin1_code":"29.0",
    "gn:asciiname":"Qiaotoushan",
    "gn:country_code":"CN",
    "gn:dem":1058,
    "gn:feature_class":"P",
    "gn:feature_code":"PPL",
    "gn:name":"Qiaotoushan",
    "gn:population":0,
    "gn:timezone":"Asia/Shanghai",
    "iso:country":"CN",
    "name:zho_x_preferred":[
        "\u6a47\u5934\u5c71"
    ],
    "wof:name":"Qiaotoushan",
    "wof:placetype":"locality"
},
  "geometry": {"coordinates":[101.236,22.188],"type":"Point"}
}