{
  "type": "Feature",
  "properties": {
    "gn:admin1_code":"19",
    "gn:asciiname":"Shuangtacun",
    "gn:country_code":"CN",
    "gn:dem":27,
    "gn:feature_class":"P",
    "gn:feature_code":"PPL",
    "gn:name":"Shuangtacun",
    "gn:population":0,
    "gn:timezone":"Asia/Shanghai",
    "iso:country":"CN",
    "name:und_x_variant":[
        "Shuangta"
    ],
    "name:zho_x_preferred":[
        "\u53cc\u5854\u6751"
    ],
    "wof:name":"Shuangtacun",
    "wof:placetype":"locality"
},
  "geometry": {"coordinates":[122.47968,39.75861],"type":"Point"}
}