{
  "type": "Feature",
  "properties": {
    "gn:admin1_code":"29.0",
    "gn:asciiname":"Mingjing",
    "gn:country_code":"CN",
    "gn:dem":1968,
    "gn:feature_class":"P",
    "gn:feature_code":"PPL",
    "gn:name":"Mingjing",
    "gn:population":0,
    "gn:timezone":"Asia/Shanghai",
    "iso:country":"CN",
    "name:zho_x_preferred":[
        "\u660e\u955c"
    ],
    "wof:name":"Mingjing",
    "wof:placetype":"locality"
},
  "geometry": {"coordinates":[100.73399999999999,25.6053],"type":"Point"}
}