{
  "type": "Feature",
  "properties": {
    "gn:admin1_code":"26.0",
    "gn:asciiname":"Xingshulin",
    "gn:country_code":"CN",
    "gn:dem":1163,
    "gn:feature_class":"P",
    "gn:feature_code":"PPL",
    "gn:name":"Xingshulin",
    "gn:population":0,
    "gn:timezone":"Asia/Shanghai",
    "iso:country":"CN",
    "name:und_x_variant":[
        "\u674f\u6811\u6797"
    ],
    "wof:name":"Xingshulin",
    "wof:placetype":"locality"
},
  "geometry": {"coordinates":[106.31455,33.01978],"type":"Point"}
}