{
  "type": "Feature",
  "properties": {
    "gn:admin1_code":"2.0",
    "gn:asciiname":"Futou",
    "gn:country_code":"CN",
    "gn:dem":192,
    "gn:feature_class":"P",
    "gn:feature_code":"PPL",
    "gn:name":"Futou",
    "gn:population":0,
    "gn:timezone":"Asia/Shanghai",
    "iso:country":"CN",
    "name:kor_x_preferred":[
        "\uc0ac\ubaa8"
    ],
    "name:zho_x_preferred":[
        "\u7829\u5934"
    ],
    "wof:name":"Futou",
    "wof:placetype":"locality"
},
  "geometry": {"coordinates":[120.63853,29.67546],"type":"Point"}
}