{
  "type": "Feature",
  "properties": {
    "gn:admin1_code":"8.0",
    "gn:asciiname":"Hebeicun",
    "gn:country_code":"CN",
    "gn:dem":228,
    "gn:feature_class":"P",
    "gn:feature_code":"PPL",
    "gn:name":"Hebeicun",
    "gn:population":0,
    "gn:timezone":"Asia/Shanghai",
    "iso:country":"CN",
    "name:zho_x_preferred":[
        "\u6cb3\u5317\u6751"
    ],
    "wof:name":"Hebeicun",
    "wof:placetype":"locality"
},
  "geometry": {"coordinates":[130.70410999999999,45.30361],"type":"Point"}
}