{
  "type": "Feature",
  "properties": {
    "gn:admin1_code":"5.0",
    "gn:asciiname":"Suolongcun",
    "gn:country_code":"CN",
    "gn:dem":134,
    "gn:feature_class":"P",
    "gn:feature_code":"PPL",
    "gn:name":"Suolongcun",
    "gn:population":0,
    "gn:timezone":"Asia/Shanghai",
    "iso:country":"CN",
    "name:zho_x_preferred":[
        "\u7d22\u9f99\u6751"
    ],
    "wof:name":"Suolongcun",
    "wof:placetype":"locality"
},
  "geometry": {"coordinates":[123.377,45.88281],"type":"Point"}
}