{
  "type": "Feature",
  "properties": {
    "gn:admin1_code":"2.0",
    "gn:asciiname":"Longquan'ao",
    "gn:country_code":"CN",
    "gn:dem":21,
    "gn:feature_class":"P",
    "gn:feature_code":"PPL",
    "gn:name":"Longquan\u2019ao",
    "gn:population":0,
    "gn:timezone":"Asia/Shanghai",
    "iso:country":"CN",
    "name:und_x_variant":[
        "Longquan\u2019ao"
    ],
    "name:zho_x_preferred":[
        "\u9f99\u6cc9\u5c99"
    ],
    "wof:name":"Longquan'ao",
    "wof:placetype":"locality"
},
  "geometry": {"coordinates":[120.52133000000001,28.06426],"type":"Point"}
}