{
  "type": "Feature",
  "properties": {
    "gn:admin1_code":"5.0",
    "gn:asciiname":"Xichangshu",
    "gn:country_code":"CN",
    "gn:dem":172,
    "gn:feature_class":"P",
    "gn:feature_code":"PPL",
    "gn:name":"Xichangshu",
    "gn:population":0,
    "gn:timezone":"Asia/Shanghai",
    "iso:country":"CN",
    "name:zho_x_preferred":[
        "\u897f\u5e38\u719f"
    ],
    "wof:name":"Xichangshu",
    "wof:placetype":"locality"
},
  "geometry": {"coordinates":[123.84498000000001,43.85263],"type":"Point"}
}