{
  "type": "Feature",
  "properties": {
    "gn:admin1_code":"7",
    "gn:asciiname":"Houfang Nongchang",
    "gn:country_code":"CN",
    "gn:dem":46,
    "gn:feature_class":"P",
    "gn:feature_code":"PPLF",
    "gn:name":"Houfang Nongchang",
    "gn:population":0,
    "gn:timezone":"Asia/Shanghai",
    "iso:country":"CN",
    "wof:name":"Houfang Nongchang",
    "wof:placetype":"locality"
},
  "geometry": {"coordinates":[117.64028,24.60333],"type":"Point"}
}