{
  "type": "Feature",
  "properties": {
    "gn:admin1_code":"10",
    "gn:asciiname":"Niuguanying",
    "gn:country_code":"CN",
    "gn:dem":3,
    "gn:feature_class":"P",
    "gn:feature_code":"PPL",
    "gn:name":"Niuguanying",
    "gn:population":0,
    "gn:timezone":"Asia/Shanghai",
    "iso:country":"CN",
    "name:und_x_variant":[
        "Niu-kuan-ying",
        "Niu-kwan-ying",
        "Niuguanying"
    ],
    "name:zho_x_preferred":[
        "\u725b\u5b98\u8425"
    ],
    "wof:name":"Niuguanying",
    "wof:placetype":"locality"
},
  "geometry": {"coordinates":[119.24952,39.65698],"type":"Point"}
}