{
  "type": "Feature",
  "properties": {
    "gn:admin1_code":"19.0",
    "gn:asciiname":"Jiamatai",
    "gn:country_code":"CN",
    "gn:dem":541,
    "gn:feature_class":"P",
    "gn:feature_code":"PPL",
    "gn:name":"Jiamatai",
    "gn:population":0,
    "gn:timezone":"Asia/Shanghai",
    "iso:country":"CN",
    "name:zho_x_preferred":[
        "\u67b6\u9a6c\u53f0"
    ],
    "wof:name":"Jiamatai",
    "wof:placetype":"locality"
},
  "geometry": {"coordinates":[119.99002,41.81798],"type":"Point"}
}