{
  "type": "Feature",
  "properties": {
    "gn:admin1_code":"10",
    "gn:asciiname":"Houlijia",
    "gn:country_code":"CN",
    "gn:dem":647,
    "gn:feature_class":"P",
    "gn:feature_code":"PPL",
    "gn:name":"Houlijia",
    "gn:population":0,
    "gn:timezone":"Asia/Shanghai",
    "iso:country":"CN",
    "name:zho_x_preferred":[
        "\u540e\u674e\u7532"
    ],
    "wof:name":"Houlijia",
    "wof:placetype":"locality"
},
  "geometry": {"coordinates":[113.89,36.5408],"type":"Point"}
}