{
  "type": "Feature",
  "properties": {
    "gn:admin1_code":"30.0",
    "gn:asciiname":"Danzhukeng",
    "gn:country_code":"CN",
    "gn:dem":513,
    "gn:feature_class":"P",
    "gn:feature_code":"PPL",
    "gn:name":"Danzhukeng",
    "gn:population":0,
    "gn:timezone":"Asia/Shanghai",
    "iso:country":"CN",
    "name:zho_x_preferred":[
        "\u4e39\u7af9\u5751"
    ],
    "wof:name":"Danzhukeng",
    "wof:placetype":"locality"
},
  "geometry": {"coordinates":[113.99755999999999,23.95303],"type":"Point"}
}