{
  "type": "Feature",
  "properties": {
    "gn:admin1_code":"7",
    "gn:asciiname":"Bitou",
    "gn:country_code":"CN",
    "gn:dem":6,
    "gn:feature_class":"P",
    "gn:feature_code":"PPL",
    "gn:name":"Bitou",
    "gn:population":0,
    "gn:timezone":"Asia/Shanghai",
    "iso:country":"CN",
    "name:und_x_variant":[
        "Pi-t\u2019ou",
        "Bitou"
    ],
    "name:zho_x_preferred":[
        "\u58c1\u5934"
    ],
    "wof:name":"Bitou",
    "wof:placetype":"locality"
},
  "geometry": {"coordinates":[119.2968,25.4186],"type":"Point"}
}