{
  "type": "Feature",
  "properties": {
    "gn:admin1_code":"1.0",
    "gn:asciiname":"Lingshan",
    "gn:country_code":"CN",
    "gn:dem":137,
    "gn:feature_class":"P",
    "gn:feature_code":"PPL",
    "gn:name":"Lingshan",
    "gn:population":0,
    "gn:timezone":"Asia/Shanghai",
    "iso:country":"CN",
    "name:ceb_x_preferred":[
        "Lingshan"
    ],
    "name:deu_x_preferred":[
        "Lingshan"
    ],
    "name:swe_x_preferred":[
        "Lingshan"
    ],
    "name:zho_x_preferred":[
        "\u5cba\u5c71"
    ],
    "wof:name":"Lingshan",
    "wof:placetype":"locality"
},
  "geometry": {"coordinates":[118.41061000000001,29.92928],"type":"Point"}
}