{
  "type": "Feature",
  "properties": {
    "gn:admin1_code":"2.0",
    "gn:asciiname":"Benjiwu",
    "gn:country_code":"CN",
    "gn:dem":100,
    "gn:feature_class":"P",
    "gn:feature_code":"PPL",
    "gn:name":"Benjiwu",
    "gn:population":0,
    "gn:timezone":"Asia/Shanghai",
    "iso:country":"CN",
    "name:zho_x_preferred":[
        "\u755a\u7b95\u575e"
    ],
    "wof:name":"Benjiwu",
    "wof:placetype":"locality"
},
  "geometry": {"coordinates":[119.05016000000001,29.66144],"type":"Point"}
}