{
  "type": "Feature",
  "properties": {
    "gn:admin1_code":"25",
    "gn:asciiname":"Qingyexing",
    "gn:country_code":"CN",
    "gn:dem":335,
    "gn:feature_class":"P",
    "gn:feature_code":"PPL",
    "gn:name":"Qingyexing",
    "gn:population":0,
    "gn:timezone":"Asia/Shanghai",
    "iso:country":"CN",
    "name:zho_x_preferred":[
        "\u9752\u51b6\u884c"
    ],
    "wof:name":"Qingyexing",
    "wof:placetype":"locality"
},
  "geometry": {"coordinates":[117.873,36.0278],"type":"Point"}
}