{
  "type": "Feature",
  "properties": {
    "gn:admin1_code":"29.0",
    "gn:asciiname":"Maku",
    "gn:country_code":"CN",
    "gn:dem":1789,
    "gn:feature_class":"P",
    "gn:feature_code":"PPL",
    "gn:name":"Maku",
    "gn:population":0,
    "gn:timezone":"Asia/Shanghai",
    "iso:country":"CN",
    "name:deu_x_preferred":[
        "Maku"
    ],
    "name:fin_x_preferred":[
        "Maku"
    ],
    "name:heb_x_preferred":[
        "\u05de\u05d0\u05e7\u05d5"
    ],
    "name:hrv_x_preferred":[
        "Mak\u00fa"
    ],
    "name:rus_x_preferred":[
        "\u041c\u0430\u043a\u0443"
    ],
    "name:zho_x_preferred":[
        "\u9a6c\u5e93"
    ],
    "wof:name":"Maku",
    "wof:placetype":"locality"
},
  "geometry": {"coordinates":[98.3045,27.6848],"type":"Point"}
}