{
  "type": "Feature",
  "properties": {
    "gn:admin1_code":"9.0",
    "gn:asciiname":"Qianjiaoling",
    "gn:country_code":"CN",
    "gn:dem":935,
    "gn:feature_class":"P",
    "gn:feature_code":"PPL",
    "gn:name":"Qianjiaoling",
    "gn:population":0,
    "gn:timezone":"Asia/Shanghai",
    "iso:country":"CN",
    "name:zho_x_preferred":[
        "\u524d\u7126\u5cad"
    ],
    "wof:name":"Qianjiaoling",
    "wof:placetype":"locality"
},
  "geometry": {"coordinates":[111.08805,34.57884],"type":"Point"}
}