{
  "type": "Feature",
  "properties": {
    "gn:admin1_code":"26.0",
    "gn:asciiname":"Qijiahu",
    "gn:country_code":"CN",
    "gn:dem":1391,
    "gn:feature_class":"P",
    "gn:feature_code":"PPL",
    "gn:name":"Qijiahu",
    "gn:population":0,
    "gn:timezone":"Asia/Shanghai",
    "iso:country":"CN",
    "name:zho_x_preferred":[
        "\u4e03\u5bb6\u6237"
    ],
    "wof:name":"Qijiahu",
    "wof:placetype":"locality"
},
  "geometry": {"coordinates":[108.75803999999999,33.34687],"type":"Point"}
}