{
  "type": "Feature",
  "properties": {
    "gn:admin1_code":"30.0",
    "gn:asciiname":"Zanglongcun",
    "gn:country_code":"CN",
    "gn:dem":10,
    "gn:feature_class":"P",
    "gn:feature_code":"PPL",
    "gn:name":"Zanglongcun",
    "gn:population":0,
    "gn:timezone":"Asia/Shanghai",
    "iso:country":"CN",
    "name:zho_x_preferred":[
        "\u85cf\u9f99\u6751"
    ],
    "wof:name":"Zanglongcun",
    "wof:placetype":"locality"
},
  "geometry": {"coordinates":[116.59502999999999,23.64457],"type":"Point"}
}