{
  "type": "Feature",
  "properties": {
    "gn:admin1_code":"24.0",
    "gn:asciiname":"Shanyanghui",
    "gn:country_code":"CN",
    "gn:dem":1573,
    "gn:feature_class":"P",
    "gn:feature_code":"PPL",
    "gn:name":"Shanyanghui",
    "gn:population":0,
    "gn:timezone":"Asia/Shanghai",
    "iso:country":"CN",
    "name:zho_x_preferred":[
        "\u5c71\u7f8a\u4f1a"
    ],
    "wof:name":"Shanyanghui",
    "wof:placetype":"locality"
},
  "geometry": {"coordinates":[111.70057,38.59233],"type":"Point"}
}