{
  "type": "Feature",
  "properties": {
    "gn:admin1_code":"19.0",
    "gn:asciiname":"Lijiatun Gouli",
    "gn:country_code":"CN",
    "gn:dem":273,
    "gn:feature_class":"P",
    "gn:feature_code":"PPL",
    "gn:name":"Lijiatun Gouli",
    "gn:population":0,
    "gn:timezone":"Asia/Shanghai",
    "iso:country":"CN",
    "name:zho_x_preferred":[
        "\u674e\u5bb6\u5c6f\u6c9f\u91cc"
    ],
    "wof:name":"Lijiatun Gouli",
    "wof:placetype":"locality"
},
  "geometry": {"coordinates":[120.291,40.6771],"type":"Point"}
}