{
  "type": "Feature",
  "properties": {
    "gn:admin1_code":"21.0",
    "gn:asciiname":"Jichangzihe",
    "gn:country_code":"CN",
    "gn:dem":1836,
    "gn:feature_class":"P",
    "gn:feature_code":"PPL",
    "gn:name":"Jichangzihe",
    "gn:population":0,
    "gn:timezone":"Asia/Shanghai",
    "iso:country":"CN",
    "name:zho_x_preferred":[
        "\u9e21\u80a0\u5b50\u6cb3"
    ],
    "wof:name":"Jichangzihe",
    "wof:placetype":"locality"
},
  "geometry": {"coordinates":[105.416,36.6226],"type":"Point"}
}