{
  "type": "Feature",
  "properties": {
    "gn:admin1_code":"29",
    "gn:asciiname":"Xiaoshatian",
    "gn:country_code":"CN",
    "gn:dem":1621,
    "gn:feature_class":"P",
    "gn:feature_code":"PPL",
    "gn:name":"Xiaoshatian",
    "gn:population":0,
    "gn:timezone":"Asia/Shanghai",
    "iso:country":"CN",
    "name:zho_x_preferred":[
        "\u5c0f\u6c99\u7530"
    ],
    "wof:name":"Xiaoshatian",
    "wof:placetype":"locality"
},
  "geometry": {"coordinates":[101.47199999999999,24.4318],"type":"Point"}
}