{
  "type": "Feature",
  "properties": {
    "gn:admin1_code":"11.0",
    "gn:asciiname":"Pengjiagou",
    "gn:country_code":"CN",
    "gn:dem":1021,
    "gn:feature_class":"P",
    "gn:feature_code":"PPL",
    "gn:name":"Pengjiagou",
    "gn:population":0,
    "gn:timezone":"Asia/Shanghai",
    "iso:country":"CN",
    "name:zho_x_preferred":[
        "Pengjiagou"
    ],
    "name:zho_x_variant":[
        "\u5f6d\u5bb6\u6c9f"
    ],
    "wof:name":"Pengjiagou",
    "wof:placetype":"locality"
},
  "geometry": {"coordinates":[110.81901999999999,30.09853],"type":"Point"}
}