{
  "type": "Feature",
  "properties": {
    "gn:admin1_code":"10",
    "gn:asciiname":"Huayuan",
    "gn:country_code":"CN",
    "gn:dem":50,
    "gn:feature_class":"P",
    "gn:feature_code":"PPL",
    "gn:name":"Huayuan",
    "gn:population":0,
    "gn:timezone":"Asia/Shanghai",
    "iso:country":"CN",
    "name:zho_x_preferred":[
        "\u82b1\u56ed"
    ],
    "wof:name":"Huayuan",
    "wof:placetype":"locality"
},
  "geometry": {"coordinates":[114.60899999999999,37.5872],"type":"Point"}
}