{
  "type": "Feature",
  "properties": {
    "gn:admin1_code":"3.0",
    "gn:asciiname":"Nianzhu",
    "gn:country_code":"CN",
    "gn:dem":245,
    "gn:feature_class":"P",
    "gn:feature_code":"PPL",
    "gn:name":"Nianzhu",
    "gn:population":0,
    "gn:timezone":"Asia/Shanghai",
    "iso:country":"CN",
    "name:zho_x_preferred":[
        "\u5e74\u73e0"
    ],
    "wof:name":"Nianzhu",
    "wof:placetype":"locality"
},
  "geometry": {"coordinates":[114.56,27.5727],"type":"Point"}
}