{
  "type": "Feature",
  "properties": {
    "gn:admin1_code":"30.0",
    "gn:asciiname":"Haixi",
    "gn:country_code":"CN",
    "gn:dem":9,
    "gn:feature_class":"P",
    "gn:feature_code":"PPL",
    "gn:name":"Haixi",
    "gn:population":0,
    "gn:timezone":"Asia/Shanghai",
    "iso:country":"CN",
    "name:ceb_x_preferred":[
        "Haixi"
    ],
    "name:nor_x_preferred":[
        "Haixi"
    ],
    "name:zho_x_preferred":[
        "\u6d77\u6eaa"
    ],
    "wof:name":"Haixi",
    "wof:placetype":"locality"
},
  "geometry": {"coordinates":[112.91842,22.85138],"type":"Point"}
}