{
  "type": "Feature",
  "properties": {
    "gn:admin1_code":"12.0",
    "gn:asciiname":"Taoyuhe",
    "gn:country_code":"CN",
    "gn:dem":556,
    "gn:feature_class":"P",
    "gn:feature_code":"PPL",
    "gn:name":"Taoyuhe",
    "gn:population":0,
    "gn:timezone":"Asia/Shanghai",
    "iso:country":"CN",
    "name:zho_x_preferred":[
        "\u6843\u90c1\u6cb3"
    ],
    "wof:name":"Taoyuhe",
    "wof:placetype":"locality"
},
  "geometry": {"coordinates":[111.33781,31.26795],"type":"Point"}
}