{
  "type": "Feature",
  "properties": {
    "gn:admin1_code":"29.0",
    "gn:asciiname":"Qingjiecun",
    "gn:country_code":"CN",
    "gn:dem":1954,
    "gn:feature_class":"P",
    "gn:feature_code":"PPL",
    "gn:name":"Qingjiecun",
    "gn:population":0,
    "gn:timezone":"Asia/Shanghai",
    "iso:country":"CN",
    "name:zho_x_preferred":[
        "\u6e05\u6d01\u6751"
    ],
    "wof:name":"Qingjiecun",
    "wof:placetype":"locality"
},
  "geometry": {"coordinates":[102.277,25.068],"type":"Point"}
}