{
  "type": "Feature",
  "properties": {
    "gn:admin1_code":"11.0",
    "gn:asciiname":"Cuobi",
    "gn:country_code":"CN",
    "gn:dem":288,
    "gn:feature_class":"P",
    "gn:feature_code":"PPL",
    "gn:name":"Cuobi",
    "gn:population":0,
    "gn:timezone":"Asia/Shanghai",
    "iso:country":"CN",
    "name:zho_x_preferred":[
        "\u78cb\u6bd4"
    ],
    "wof:name":"Cuobi",
    "wof:placetype":"locality"
},
  "geometry": {"coordinates":[109.46295000000001,28.73926],"type":"Point"}
}