{
  "type": "Feature",
  "properties": {
    "gn:admin1_code":"30.0",
    "gn:asciiname":"Xintang Xiacun",
    "gn:country_code":"CN",
    "gn:dem":43,
    "gn:feature_class":"P",
    "gn:feature_code":"PPL",
    "gn:name":"Xintang Xiacun",
    "gn:population":0,
    "gn:timezone":"Asia/Shanghai",
    "iso:country":"CN",
    "name:zho_x_preferred":[
        "\u65b0\u5858\u4e0b\u6751"
    ],
    "wof:name":"Xintang Xiacun",
    "wof:placetype":"locality"
},
  "geometry": {"coordinates":[113.59938,23.59365],"type":"Point"}
}