{
  "type": "Feature",
  "properties": {
    "gn:admin1_code":"11.0",
    "gn:asciiname":"Wusu",
    "gn:country_code":"CN",
    "gn:dem":620,
    "gn:feature_class":"P",
    "gn:feature_code":"PPL",
    "gn:name":"Wusu",
    "gn:population":0,
    "gn:timezone":"Asia/Shanghai",
    "iso:country":"CN",
    "name:deu_x_preferred":[
        "Usu"
    ],
    "name:est_x_preferred":[
        "Usu"
    ],
    "name:fra_x_preferred":[
        "Wusu"
    ],
    "name:hun_x_preferred":[
        "Vusu"
    ],
    "name:ita_x_preferred":[
        "Wusu"
    ],
    "name:jpn_x_preferred":[
        "\u30a6\u30b9\u5e02"
    ],
    "name:kik_x_preferred":[
        "Wusu"
    ],
    "name:kor_x_preferred":[
        "\uc6b0\uc464\uc2dc"
    ],
    "name:mon_x_preferred":[
        "\u0423\u0441 \u0445\u043e\u0442"
    ],
    "name:nor_x_preferred":[
        "Wusu"
    ],
    "name:pol_x_preferred":[
        "Wusu"
    ],
    "name:por_x_preferred":[
        "Wusu"
    ],
    "name:rus_x_preferred":[
        "\u0423\u0441\u0443"
    ],
    "name:swe_x_preferred":[
        "Usu"
    ],
    "name:tur_x_preferred":[
        "Usu"
    ],
    "name:uig_x_preferred":[
        "\u0634\u0649\u062e\u06c7 \u0634\u06d5\u06be\u0649\u0631\u0649"
    ],
    "name:urd_x_preferred":[
        "\u0648\u0648\u0633\u0648"
    ],
    "name:vie_x_preferred":[
        "\u00d4 T\u00f4"
    ],
    "name:zho_x_preferred":[
        "\u4e94\u82cf"
    ],
    "name:zho_x_variant":[
        "\u4e4c\u82cf\u5e02"
    ],
    "wof:name":"Wusu",
    "wof:placetype":"locality"
},
  "geometry": {"coordinates":[109.62461,28.52551],"type":"Point"}
}