{
  "type": "Feature",
  "properties": {
    "gn:admin1_code":"15.0",
    "gn:asciiname":"Songjia Goukou",
    "gn:country_code":"CN",
    "gn:dem":2018,
    "gn:feature_class":"P",
    "gn:feature_code":"PPL",
    "gn:name":"Songjia Goukou",
    "gn:population":0,
    "gn:timezone":"Asia/Shanghai",
    "iso:country":"CN",
    "name:zho_x_preferred":[
        "\u5b8b\u5bb6\u6c9f\u53e3"
    ],
    "wof:name":"Songjia Goukou",
    "wof:placetype":"locality"
},
  "geometry": {"coordinates":[104.65900000000001,35.3258],"type":"Point"}
}