{
  "type": "Feature",
  "properties": {
    "gn:admin1_code":"6.0",
    "gn:asciiname":"Dizhizha",
    "gn:country_code":"CN",
    "gn:dem":3762,
    "gn:feature_class":"P",
    "gn:feature_code":"PPL",
    "gn:name":"Dizhizha",
    "gn:population":0,
    "gn:timezone":"Asia/Urumqi",
    "iso:country":"CN",
    "name:zho_x_preferred":[
        "\u5730\u53ea\u624e"
    ],
    "wof:name":"Dizhizha",
    "wof:placetype":"locality"
},
  "geometry": {"coordinates":[96.82973,32.38425],"type":"Point"}
}