{
  "type": "Feature",
  "properties": {
    "gn:admin1_code":"25.0",
    "gn:asciiname":"Shimenkou",
    "gn:country_code":"CN",
    "gn:dem":155,
    "gn:feature_class":"P",
    "gn:feature_code":"PPL",
    "gn:name":"Shimenkou",
    "gn:population":0,
    "gn:timezone":"Asia/Shanghai",
    "iso:country":"CN",
    "name:zho_x_preferred":[
        "\u77f3\u95e8\u53e3"
    ],
    "wof:name":"Shimenkou",
    "wof:placetype":"locality"
},
  "geometry": {"coordinates":[120.74908000000001,37.54753],"type":"Point"}
}