{
  "type": "Feature",
  "properties": {
    "gn:admin1_code":"10",
    "gn:asciiname":"Meitu Goumen",
    "gn:country_code":"CN",
    "gn:dem":1280,
    "gn:feature_class":"P",
    "gn:feature_code":"PPL",
    "gn:name":"Meitu Goumen",
    "gn:population":0,
    "gn:timezone":"Asia/Shanghai",
    "iso:country":"CN",
    "name:zho_x_preferred":[
        "\u6885\u571f\u6c9f\u95e8"
    ],
    "wof:name":"Meitu Goumen",
    "wof:placetype":"locality"
},
  "geometry": {"coordinates":[116.37354000000001,41.62636],"type":"Point"}
}