{
  "type": "Feature",
  "properties": {
    "gn:admin1_code":"16.0",
    "gn:asciiname":"Yangqiqiao",
    "gn:country_code":"CN",
    "gn:dem":53,
    "gn:feature_class":"P",
    "gn:feature_code":"PPL",
    "gn:name":"Yangqiqiao",
    "gn:population":0,
    "gn:timezone":"Asia/Shanghai",
    "iso:country":"CN",
    "name:zho_x_preferred":[
        "\u6d0b\u4e03\u6865"
    ],
    "wof:name":"Yangqiqiao",
    "wof:placetype":"locality"
},
  "geometry": {"coordinates":[109.792,23.0272],"type":"Point"}
}