{
  "type": "Feature",
  "properties": {
    "gn:admin1_code":"33.0",
    "gn:asciiname":"Zhoujiaba",
    "gn:country_code":"CN",
    "gn:dem":318,
    "gn:feature_class":"P",
    "gn:feature_code":"PPLA4",
    "gn:name":"Zhoujiaba",
    "gn:population":0,
    "gn:timezone":"Asia/Shanghai",
    "iso:country":"CN",
    "name:und_x_variant":[
        "Zhoujiaba Jiedao"
    ],
    "name:zho_x_preferred":[
        "\u5468\u5bb6\u575d"
    ],
    "name:zho_x_variant":[
        "\u5468\u5bb6\u575d\u8857\u9053"
    ],
    "wof:name":"Zhoujiaba",
    "wof:placetype":"locality"
},
  "geometry": {"coordinates":[108.36642000000001,30.84349000000001],"type":"Point"}
}