{
  "type": "Feature",
  "properties": {
    "gn:admin1_code":"26.0",
    "gn:asciiname":"Zaolinze Goucun",
    "gn:country_code":"CN",
    "gn:dem":1022,
    "gn:feature_class":"P",
    "gn:feature_code":"PPL",
    "gn:name":"Zaolinze Goucun",
    "gn:population":0,
    "gn:timezone":"Asia/Shanghai",
    "iso:country":"CN",
    "name:zho_x_preferred":[
        "\u67a3\u6797\u5219\u6c9f\u6751"
    ],
    "wof:name":"Zaolinze Goucun",
    "wof:placetype":"locality"
},
  "geometry": {"coordinates":[110.167,37.3271],"type":"Point"}
}