{
  "type": "Feature",
  "properties": {
    "gn:admin1_code":"14.0",
    "gn:asciiname":"Zheru",
    "gn:country_code":"CN",
    "gn:dem":5059,
    "gn:feature_class":"P",
    "gn:feature_code":"PPL",
    "gn:name":"Zheru",
    "gn:population":0,
    "gn:timezone":"Asia/Urumqi",
    "iso:country":"CN",
    "name:bod_x_preferred":[
        "Zh\u00earu"
    ],
    "name:zho_x_preferred":[
        "Zheru"
    ],
    "name:zho_x_variant":[
        "\u6298\u5982"
    ],
    "wof:name":"Zheru",
    "wof:placetype":"locality"
},
  "geometry": {"coordinates":[93.407,32.007],"type":"Point"}
}