{
  "type": "Feature",
  "properties": {
    "gn:admin1_code":"13.0",
    "gn:asciiname":"Daoziya",
    "gn:country_code":"CN",
    "gn:dem":1580,
    "gn:feature_class":"P",
    "gn:feature_code":"PPL",
    "gn:name":"Daoziya",
    "gn:population":0,
    "gn:timezone":"Asia/Shanghai",
    "iso:country":"CN",
    "name:zho_x_preferred":[
        "\u5200\u5b5c\u4e9a"
    ],
    "wof:name":"Daoziya",
    "wof:placetype":"locality"
},
  "geometry": {"coordinates":[79.61166999999998,36.89745],"type":"Point"}
}