{
  "type": "Feature",
  "properties": {
    "gn:admin1_code":"14.0",
    "gn:asciiname":"Chimadun",
    "gn:country_code":"CN",
    "gn:dem":4751,
    "gn:feature_class":"P",
    "gn:feature_code":"PPL",
    "gn:name":"Chimadun",
    "gn:population":0,
    "gn:timezone":"Asia/Urumqi",
    "iso:country":"CN",
    "name:zho_x_preferred":[
        "\u5c3a\u9a6c\u58a9"
    ],
    "wof:name":"Chimadun",
    "wof:placetype":"locality"
},
  "geometry": {"coordinates":[84.40049999999999,29.1376],"type":"Point"}
}