{
  "type": "Feature",
  "properties": {
    "gn:admin1_code":"15.0",
    "gn:asciiname":"Jiahe",
    "gn:country_code":"CN",
    "gn:dem":1378,
    "gn:feature_class":"P",
    "gn:feature_code":"PPL",
    "gn:name":"Jiahe",
    "gn:population":0,
    "gn:timezone":"Asia/Shanghai",
    "iso:country":"CN",
    "name:und_x_variant":[
        "\u8d3e\u6cb3"
    ],
    "wof:name":"Jiahe",
    "wof:placetype":"locality"
},
  "geometry": {"coordinates":[107.994,36.5448],"type":"Point"}
}