{
  "type": "Feature",
  "properties": {
    "gn:admin1_code":"32.0",
    "gn:asciiname":"Lishangeng",
    "gn:country_code":"CN",
    "gn:dem":414,
    "gn:feature_class":"P",
    "gn:feature_code":"PPL",
    "gn:name":"Lishangeng",
    "gn:population":0,
    "gn:timezone":"Asia/Shanghai",
    "iso:country":"CN",
    "name:zho_x_preferred":[
        "\u9ece\u5c71\u57c2"
    ],
    "wof:name":"Lishangeng",
    "wof:placetype":"locality"
},
  "geometry": {"coordinates":[103.59499,29.75784],"type":"Point"}
}