{
  "type": "Feature",
  "properties": {
    "gn:admin1_code":"26.0",
    "gn:asciiname":"Shaocun",
    "gn:country_code":"CN",
    "gn:dem":1101,
    "gn:feature_class":"P",
    "gn:feature_code":"PPL",
    "gn:name":"Shaocun",
    "gn:population":0,
    "gn:timezone":"Asia/Shanghai",
    "iso:country":"CN",
    "name:zho_x_preferred":[
        "\u52fa\u6751"
    ],
    "wof:name":"Shaocun",
    "wof:placetype":"locality"
},
  "geometry": {"coordinates":[110.10984999999999,36.47387],"type":"Point"}
}