{
  "type": "Feature",
  "properties": {
    "gn:admin1_code":"32.0",
    "gn:asciiname":"Sangpi",
    "gn:country_code":"CN",
    "gn:dem":2888,
    "gn:feature_class":"P",
    "gn:feature_code":"PPLA3",
    "gn:name":"Sangpi",
    "gn:population":0,
    "gn:timezone":"Asia/Shanghai",
    "iso:country":"CN",
    "name:und_x_variant":[
        "Sangpi Zhen",
        "Xiangcheng"
    ],
    "name:zho_x_preferred":[
        "\u6851\u62ab"
    ],
    "name:zho_x_variant":[
        "\u6851\u62ab\u9547",
        "\u4e61\u57ce"
    ],
    "wof:name":"Sangpi",
    "wof:placetype":"locality"
},
  "geometry": {"coordinates":[99.79991,28.93391],"type":"Point"}
}