{
  "type": "Feature",
  "properties": {
    "gn:admin1_code":"18",
    "gn:asciiname":"Gangbian",
    "gn:country_code":"CN",
    "gn:dem":402,
    "gn:feature_class":"P",
    "gn:feature_code":"PPL",
    "gn:name":"Gangbian",
    "gn:population":0,
    "gn:timezone":"Asia/Shanghai",
    "iso:country":"CN",
    "wof:name":"Gangbian",
    "wof:placetype":"locality"
},
  "geometry": {"coordinates":[108.63556,25.58917000000001],"type":"Point"}
}