{
  "type": "Feature",
  "properties": {
    "gn:admin1_code":"26.0",
    "gn:asciiname":"Gouchacun",
    "gn:country_code":"CN",
    "gn:dem":1173,
    "gn:feature_class":"P",
    "gn:feature_code":"PPL",
    "gn:name":"Gouchacun",
    "gn:population":0,
    "gn:timezone":"Asia/Shanghai",
    "iso:country":"CN",
    "name:zho_x_preferred":[
        "\u6c9f\u5c94\u6751"
    ],
    "wof:name":"Gouchacun",
    "wof:placetype":"locality"
},
  "geometry": {"coordinates":[110.0367,38.86127000000001],"type":"Point"}
}