{
  "type": "Feature",
  "properties": {
    "gn:admin1_code":"11.0",
    "gn:asciiname":"Zongshatian",
    "gn:country_code":"CN",
    "gn:dem":672,
    "gn:feature_class":"P",
    "gn:feature_code":"PPL",
    "gn:name":"Zongshatian",
    "gn:population":0,
    "gn:timezone":"Asia/Shanghai",
    "iso:country":"CN",
    "name:zho_x_preferred":[
        "\u68d5\u6c99\u7530"
    ],
    "wof:name":"Zongshatian",
    "wof:placetype":"locality"
},
  "geometry": {"coordinates":[110.31833,26.9184],"type":"Point"}
}