{
  "type": "Feature",
  "properties": {
    "gn:admin1_code":"15.0",
    "gn:asciiname":"Hexian",
    "gn:country_code":"CN",
    "gn:dem":2306,
    "gn:feature_class":"P",
    "gn:feature_code":"PPL",
    "gn:name":"Hexian",
    "gn:population":0,
    "gn:timezone":"Asia/Shanghai",
    "iso:country":"CN",
    "name:zho_x_preferred":[
        "\u58d1\u5c98"
    ],
    "wof:name":"Hexian",
    "wof:placetype":"locality"
},
  "geometry": {"coordinates":[103.342,35.5941],"type":"Point"}
}