{
  "type": "Feature",
  "properties": {
    "gn:admin1_code":"25.0",
    "gn:asciiname":"Dalaowacun",
    "gn:country_code":"CN",
    "gn:dem":39,
    "gn:feature_class":"P",
    "gn:feature_code":"PPL",
    "gn:name":"Dalaowacun",
    "gn:population":0,
    "gn:timezone":"Asia/Shanghai",
    "iso:country":"CN",
    "name:zho_x_preferred":[
        "\u5927\u6d9d\u6d3c\u6751"
    ],
    "wof:name":"Dalaowacun",
    "wof:placetype":"locality"
},
  "geometry": {"coordinates":[120.20367,37.47375],"type":"Point"}
}