{
  "type": "Feature",
  "properties": {
    "gn:admin1_code":"15.0",
    "gn:asciiname":"Tongxinbu",
    "gn:country_code":"CN",
    "gn:dem":2295,
    "gn:feature_class":"P",
    "gn:feature_code":"PPL",
    "gn:name":"Tongxinbu",
    "gn:population":0,
    "gn:timezone":"Asia/Shanghai",
    "iso:country":"CN",
    "name:zho_x_preferred":[
        "\u901a\u4fe1\u5821"
    ],
    "wof:name":"Tongxinbu",
    "wof:placetype":"locality"
},
  "geometry": {"coordinates":[101.649,38.2185],"type":"Point"}
}