{
  "type": "Feature",
  "properties": {
    "gn:admin1_code":"18",
    "gn:asciiname":"Luojiaowo",
    "gn:country_code":"CN",
    "gn:dem":1103,
    "gn:feature_class":"P",
    "gn:feature_code":"PPL",
    "gn:name":"Luojiaowo",
    "gn:population":0,
    "gn:timezone":"Asia/Shanghai",
    "iso:country":"CN",
    "name:zho_x_preferred":[
        "\u843d\u811a\u7a9d"
    ],
    "wof:name":"Luojiaowo",
    "wof:placetype":"locality"
},
  "geometry": {"coordinates":[106.34,26.952],"type":"Point"}
}