{
  "type": "Feature",
  "properties": {
    "gn:admin1_code":"14.0",
    "gn:asciiname":"Dabeng",
    "gn:country_code":"CN",
    "gn:dem":3750,
    "gn:feature_class":"P",
    "gn:feature_code":"PPL",
    "gn:name":"Dabeng",
    "gn:population":0,
    "gn:timezone":"Asia/Urumqi",
    "iso:country":"CN",
    "name:zho_x_preferred":[
        "\u5927\u5d29"
    ],
    "wof:name":"Dabeng",
    "wof:placetype":"locality"
},
  "geometry": {"coordinates":[94.48153000000001,29.3272],"type":"Point"}
}