{
  "type": "Feature",
  "properties": {
    "gn:admin1_code":"23.0",
    "gn:asciiname":"Wujiazhai",
    "gn:country_code":"CN",
    "gn:dem":2,
    "gn:feature_class":"P",
    "gn:feature_code":"PPL",
    "gn:name":"Wujiazhai",
    "gn:population":0,
    "gn:timezone":"Asia/Shanghai",
    "iso:country":"CN",
    "name:zho_x_preferred":[
        "Wujiazhai"
    ],
    "name:zho_x_variant":[
        "\u5434\u5bb6\u5b85"
    ],
    "wof:name":"Wujiazhai",
    "wof:placetype":"locality"
},
  "geometry": {"coordinates":[121.67256999999999,31.11967000000001],"type":"Point"}
}