{
  "type": "Feature",
  "properties": {
    "gn:admin1_code":"20.0",
    "gn:asciiname":"Baiyanshan",
    "gn:country_code":"CN",
    "gn:dem":1894,
    "gn:feature_class":"P",
    "gn:feature_code":"PPL",
    "gn:name":"Baiyanshan",
    "gn:population":0,
    "gn:timezone":"Asia/Shanghai",
    "iso:country":"CN",
    "name:und_x_variant":[
        "\u767d\u5f66\u5c71"
    ],
    "wof:name":"Baiyanshan",
    "wof:placetype":"locality"
},
  "geometry": {"coordinates":[111.56881,41.03489],"type":"Point"}
}