{
  "type": "Feature",
  "properties": {
    "gn:admin1_code":"33.0",
    "gn:asciiname":"Baiyang'ao",
    "gn:country_code":"CN",
    "gn:dem":743,
    "gn:feature_class":"P",
    "gn:feature_code":"PPL",
    "gn:name":"Baiyang\u2019ao",
    "gn:population":0,
    "gn:timezone":"Asia/Shanghai",
    "iso:country":"CN",
    "name:und_x_variant":[
        "Baiyang\u2019ao"
    ],
    "name:zho_x_preferred":[
        "\u67cf\u6768\u5773"
    ],
    "wof:name":"Baiyang'ao",
    "wof:placetype":"locality"
},
  "geometry": {"coordinates":[108.62990000000001,28.40904],"type":"Point"}
}