{
  "type": "Feature",
  "properties": {
    "gn:admin1_code":"26.0",
    "gn:asciiname":"Xingtangcun",
    "gn:country_code":"CN",
    "gn:dem":655,
    "gn:feature_class":"P",
    "gn:feature_code":"PPL",
    "gn:name":"Xingtangcun",
    "gn:population":0,
    "gn:timezone":"Asia/Shanghai",
    "iso:country":"CN",
    "name:zho_x_preferred":[
        "\u5174\u5858\u6751"
    ],
    "wof:name":"Xingtangcun",
    "wof:placetype":"locality"
},
  "geometry": {"coordinates":[108.47327,32.72725],"type":"Point"}
}