{
  "type": "Feature",
  "properties": {
    "gn:admin1_code":"5.0",
    "gn:asciiname":"Congjiatun",
    "gn:country_code":"CN",
    "gn:dem":165,
    "gn:feature_class":"P",
    "gn:feature_code":"PPL",
    "gn:name":"Congjiatun",
    "gn:population":0,
    "gn:timezone":"Asia/Shanghai",
    "iso:country":"CN",
    "name:zho_x_preferred":[
        "\u4e1b\u5bb6\u5c6f"
    ],
    "wof:name":"Congjiatun",
    "wof:placetype":"locality"
},
  "geometry": {"coordinates":[124.78153,44.37324],"type":"Point"}
}