{
  "type": "Feature",
  "properties": {
    "gn:admin1_code":"10",
    "gn:asciiname":"Xingjia Wopu",
    "gn:country_code":"CN",
    "gn:dem":584,
    "gn:feature_class":"P",
    "gn:feature_code":"PPL",
    "gn:name":"Xingjia Wopu",
    "gn:population":0,
    "gn:timezone":"Asia/Shanghai",
    "iso:country":"CN",
    "name:zho_x_preferred":[
        "\u90a2\u5bb6\u7a9d\u94fa"
    ],
    "wof:name":"Xingjia Wopu",
    "wof:placetype":"locality"
},
  "geometry": {"coordinates":[116.86391,41.05358],"type":"Point"}
}