{
  "type": "Feature",
  "properties": {
    "gn:admin1_code":"18",
    "gn:asciiname":"Shigao",
    "gn:country_code":"CN",
    "gn:dem":2206,
    "gn:feature_class":"P",
    "gn:feature_code":"PPL",
    "gn:name":"Shigao",
    "gn:population":0,
    "gn:timezone":"Asia/Shanghai",
    "iso:country":"CN",
    "name:zho_x_preferred":[
        "\u77f3\u818f"
    ],
    "wof:name":"Shigao",
    "wof:placetype":"locality"
},
  "geometry": {"coordinates":[104.13800000000001,27.0396],"type":"Point"}
}