{
  "type": "Feature",
  "properties": {
    "gn:admin1_code":"3.0",
    "gn:asciiname":"Dalaojiao",
    "gn:country_code":"CN",
    "gn:dem":409,
    "gn:feature_class":"P",
    "gn:feature_code":"PPL",
    "gn:name":"Dalaojiao",
    "gn:population":0,
    "gn:timezone":"Asia/Shanghai",
    "iso:country":"CN",
    "name:und_x_variant":[
        "\u5927\u8001\u89d2"
    ],
    "wof:name":"Dalaojiao",
    "wof:placetype":"locality"
},
  "geometry": {"coordinates":[115.1443,25.07885],"type":"Point"}
}