{
  "type": "Feature",
  "properties": {
    "gn:admin1_code":"12.0",
    "gn:asciiname":"Yiliuhe",
    "gn:country_code":"CN",
    "gn:dem":59,
    "gn:feature_class":"P",
    "gn:feature_code":"PPL",
    "gn:name":"Yiliuhe",
    "gn:population":0,
    "gn:timezone":"Asia/Shanghai",
    "iso:country":"CN",
    "name:zho_x_preferred":[
        "Yiliuhe"
    ],
    "name:zho_x_variant":[
        "\u6ea2\u6d41\u6cb3"
    ],
    "wof:name":"Yiliuhe",
    "wof:placetype":"locality"
},
  "geometry": {"coordinates":[115.14100999999999,30.72527],"type":"Point"}
}