{
  "type": "Feature",
  "properties": {
    "gn:admin1_code":"15.0",
    "gn:asciiname":"Guanting",
    "gn:country_code":"CN",
    "gn:dem":1075,
    "gn:feature_class":"P",
    "gn:feature_code":"PPL",
    "gn:name":"Guanting",
    "gn:population":0,
    "gn:timezone":"Asia/Shanghai",
    "iso:country":"CN",
    "name:deu_x_preferred":[
        "Guanting"
    ],
    "name:und_x_variant":[
        "\u5b98\u5385"
    ],
    "wof:name":"Guanting",
    "wof:placetype":"locality"
},
  "geometry": {"coordinates":[105.89467,33.81193],"type":"Point"}
}