{
  "type": "Feature",
  "properties": {
    "gn:admin1_code":"4.0",
    "gn:asciiname":"Gangang",
    "gn:country_code":"CN",
    "gn:dem":2,
    "gn:feature_class":"P",
    "gn:feature_code":"PPL",
    "gn:name":"Gangang",
    "gn:population":0,
    "gn:timezone":"Asia/Shanghai",
    "iso:country":"CN",
    "name:und_x_variant":[
        "\u7518\u6e2f"
    ],
    "name:zho_x_preferred":[
        "\u7518\u6e2f"
    ],
    "wof:name":"Gangang",
    "wof:placetype":"locality"
},
  "geometry": {"coordinates":[120.26172,32.92222],"type":"Point"}
}