{
  "type": "Feature",
  "properties": {
    "gn:admin1_code":"26.0",
    "gn:asciiname":"Dayangwan",
    "gn:country_code":"CN",
    "gn:dem":1358,
    "gn:feature_class":"P",
    "gn:feature_code":"PPL",
    "gn:name":"Dayangwan",
    "gn:population":0,
    "gn:timezone":"Asia/Shanghai",
    "iso:country":"CN",
    "name:zho_x_preferred":[
        "\u5927\u9633\u6e7e"
    ],
    "wof:name":"Dayangwan",
    "wof:placetype":"locality"
},
  "geometry": {"coordinates":[109.43111,36.88187],"type":"Point"}
}