{
  "type": "Feature",
  "properties": {
    "gn:admin1_code":"32.0",
    "gn:asciiname":"Qiao'erdang",
    "gn:country_code":"CN",
    "gn:dem":630,
    "gn:feature_class":"P",
    "gn:feature_code":"PPL",
    "gn:name":"Qiao\u2019erdang",
    "gn:population":0,
    "gn:timezone":"Asia/Shanghai",
    "iso:country":"CN",
    "name:und_x_variant":[
        "Qiao\u2019erdang"
    ],
    "name:zho_x_preferred":[
        "\u6865\u513f\u51fc"
    ],
    "wof:name":"Qiao'erdang",
    "wof:placetype":"locality"
},
  "geometry": {"coordinates":[104.452,29.7238],"type":"Point"}
}