{
  "type": "Feature",
  "properties": {
    "gn:admin1_code":"32.0",
    "gn:asciiname":"Hailumei",
    "gn:country_code":"CN",
    "gn:dem":2809,
    "gn:feature_class":"P",
    "gn:feature_code":"PPL",
    "gn:name":"Hailumei",
    "gn:population":0,
    "gn:timezone":"Asia/Shanghai",
    "iso:country":"CN",
    "name:zho_x_preferred":[
        "\u6d77\u9c81\u6ca1"
    ],
    "wof:name":"Hailumei",
    "wof:placetype":"locality"
},
  "geometry": {"coordinates":[102.42700000000001,27.9537],"type":"Point"}
}