{
  "type": "Feature",
  "properties": {
    "gn:admin1_code":"11.0",
    "gn:asciiname":"Pengjia Dawu",
    "gn:country_code":"CN",
    "gn:dem":67,
    "gn:feature_class":"P",
    "gn:feature_code":"PPL",
    "gn:name":"Pengjia Dawu",
    "gn:population":0,
    "gn:timezone":"Asia/Shanghai",
    "iso:country":"CN",
    "name:zho_x_preferred":[
        "\u5f6d\u5bb6\u5927\u5c4b"
    ],
    "wof:name":"Pengjia Dawu",
    "wof:placetype":"locality"
},
  "geometry": {"coordinates":[113.11369999999999,27.45262],"type":"Point"}
}