{
  "type": "Feature",
  "properties": {
    "gn:admin1_code":"30.0",
    "gn:asciiname":"Guyecun",
    "gn:country_code":"CN",
    "gn:dem":86,
    "gn:feature_class":"P",
    "gn:feature_code":"PPL",
    "gn:name":"Guyecun",
    "gn:population":0,
    "gn:timezone":"Asia/Shanghai",
    "iso:country":"CN",
    "name:zho_x_preferred":[
        "\u53e4\u91ce\u6751"
    ],
    "wof:name":"Guyecun",
    "wof:placetype":"locality"
},
  "geometry": {"coordinates":[116.5976,24.20107],"type":"Point"}
}