{
  "type": "Feature",
  "properties": {
    "gn:admin1_code":"3",
    "gn:asciiname":"Maxi",
    "gn:country_code":"CN",
    "gn:dem":650,
    "gn:feature_class":"P",
    "gn:feature_code":"PPL",
    "gn:name":"Maxi",
    "gn:population":0,
    "gn:timezone":"Asia/Shanghai",
    "iso:country":"CN",
    "name:deu_x_preferred":[
        "Maxi"
    ],
    "name:fra_x_preferred":[
        "Maxi"
    ],
    "name:ita_x_preferred":[
        "Maxi"
    ],
    "name:spa_x_preferred":[
        "Maxi"
    ],
    "name:swe_x_preferred":[
        "Maxi"
    ],
    "name:zho_x_preferred":[
        "\u9a6c\u6eaa"
    ],
    "wof:name":"Maxi",
    "wof:placetype":"locality"
},
  "geometry": {"coordinates":[114.28400000000001,26.0686],"type":"Point"}
}