{
  "type": "Feature",
  "properties": {
    "gn:admin1_code":"4.0",
    "gn:asciiname":"Changligangcun",
    "gn:country_code":"CN",
    "gn:dem":23,
    "gn:feature_class":"P",
    "gn:feature_code":"PPL",
    "gn:name":"Changligangcun",
    "gn:population":0,
    "gn:timezone":"Asia/Shanghai",
    "iso:country":"CN",
    "name:zho_x_preferred":[
        "\u957f\u91cc\u5c97\u6751"
    ],
    "wof:name":"Changligangcun",
    "wof:placetype":"locality"
},
  "geometry": {"coordinates":[119.20648,31.84668],"type":"Point"}
}