{
  "type": "Feature",
  "properties": {
    "gn:admin1_code":"32.0",
    "gn:asciiname":"Xiamai",
    "gn:country_code":"CN",
    "gn:dem":3732,
    "gn:feature_class":"P",
    "gn:feature_code":"PPL",
    "gn:name":"Xiamai",
    "gn:population":0,
    "gn:timezone":"Asia/Shanghai",
    "iso:country":"CN",
    "name:zho_x_preferred":[
        "\u4e0b\u9ea6"
    ],
    "wof:name":"Xiamai",
    "wof:placetype":"locality"
},
  "geometry": {"coordinates":[100.539,29.0707],"type":"Point"}
}