{
  "type": "Feature",
  "properties": {
    "gn:admin1_code":"14.0",
    "gn:asciiname":"Cuowabu",
    "gn:country_code":"CN",
    "gn:dem":4503,
    "gn:feature_class":"P",
    "gn:feature_code":"PPL",
    "gn:name":"Cuowabu",
    "gn:population":0,
    "gn:timezone":"Asia/Urumqi",
    "iso:country":"CN",
    "name:zho_x_preferred":[
        "\u64ae\u6316\u5e03"
    ],
    "wof:name":"Cuowabu",
    "wof:placetype":"locality"
},
  "geometry": {"coordinates":[95.02195,30.83115],"type":"Point"}
}