{
  "type": "Feature",
  "properties": {
    "gn:admin1_code":"20",
    "gn:asciiname":"Mandalt Sum",
    "gn:cc2":"CN",
    "gn:country_code":"CN",
    "gn:dem":1094,
    "gn:feature_class":"P",
    "gn:feature_code":"PPL",
    "gn:name":"Mandalt Sum",
    "gn:population":0,
    "gn:timezone":"Asia/Shanghai",
    "iso:country":"CN",
    "name:und_x_variant":[
        "Man-ta-la-t\u2019u-miao",
        "Mandalt Sum"
    ],
    "wof:name":"Mandalt Sum",
    "wof:placetype":"locality"
},
  "geometry": {"coordinates":[112.75,44.15],"type":"Point"}
}