{
  "type": "Feature",
  "properties": {
    "gn:admin1_code":"4.0",
    "gn:asciiname":"Caiguancun",
    "gn:country_code":"CN",
    "gn:dem":8,
    "gn:feature_class":"P",
    "gn:feature_code":"PPL",
    "gn:name":"Caiguancun",
    "gn:population":0,
    "gn:timezone":"Asia/Shanghai",
    "iso:country":"CN",
    "name:und_x_variant":[
        "Caiguan",
        "Caiguancun"
    ],
    "name:zho_x_preferred":[
        "\u8521\u5b98"
    ],
    "name:zho_x_variant":[
        "\u8521\u5b98\u6751"
    ],
    "wof:name":"Caiguancun",
    "wof:placetype":"locality"
},
  "geometry": {"coordinates":[120.04871,32.44812],"type":"Point"}
}