{
  "type": "Feature",
  "properties": {
    "gn:admin1_code":"19.0",
    "gn:asciiname":"Dapipacun",
    "gn:country_code":"CN",
    "gn:dem":450,
    "gn:feature_class":"P",
    "gn:feature_code":"PPL",
    "gn:name":"Dapipacun",
    "gn:population":0,
    "gn:timezone":"Asia/Shanghai",
    "iso:country":"CN",
    "name:zho_x_preferred":[
        "\u5927\u7435\u7436\u6751"
    ],
    "wof:name":"Dapipacun",
    "wof:placetype":"locality"
},
  "geometry": {"coordinates":[124.82108999999998,41.40308],"type":"Point"}
}