{
  "type": "Feature",
  "properties": {
    "gn:admin1_code":"16.0",
    "gn:asciiname":"Gu Zhen",
    "gn:country_code":"CN",
    "gn:dem":488,
    "gn:feature_class":"P",
    "gn:feature_code":"PPL",
    "gn:name":"Gu Zhen",
    "gn:population":0,
    "gn:timezone":"Asia/Shanghai",
    "iso:country":"CN",
    "name:zho_x_preferred":[
        "\u53e4\u9547"
    ],
    "wof:name":"Gu Zhen",
    "wof:placetype":"locality"
},
  "geometry": {"coordinates":[110.35899999999999,24.1129],"type":"Point"}
}