{
  "type": "Feature",
  "properties": {
    "gn:admin1_code":"30.0",
    "gn:asciiname":"Pingxicun",
    "gn:country_code":"CN",
    "gn:dem":44,
    "gn:feature_class":"P",
    "gn:feature_code":"PPL",
    "gn:name":"Pingxicun",
    "gn:population":0,
    "gn:timezone":"Asia/Shanghai",
    "iso:country":"CN",
    "name:zho_x_preferred":[
        "\u576a\u6eaa\u6751"
    ],
    "wof:name":"Pingxicun",
    "wof:placetype":"locality"
},
  "geometry": {"coordinates":[116.62212,24.20965],"type":"Point"}
}