{
  "type": "Feature",
  "properties": {
    "gn:admin1_code":"19.0",
    "gn:asciiname":"Dashandixia",
    "gn:country_code":"CN",
    "gn:dem":123,
    "gn:feature_class":"P",
    "gn:feature_code":"PPL",
    "gn:name":"Dashandixia",
    "gn:population":0,
    "gn:timezone":"Asia/Shanghai",
    "iso:country":"CN",
    "name:zho_x_preferred":[
        "\u5927\u5c71\u5e95\u4e0b"
    ],
    "wof:name":"Dashandixia",
    "wof:placetype":"locality"
},
  "geometry": {"coordinates":[122.934,42.6978],"type":"Point"}
}