{
  "type": "Feature",
  "properties": {
    "gn:admin1_code":"8.0",
    "gn:asciiname":"Qinggangcun",
    "gn:country_code":"CN",
    "gn:dem":178,
    "gn:feature_class":"P",
    "gn:feature_code":"PPL",
    "gn:name":"Qinggangcun",
    "gn:population":0,
    "gn:timezone":"Asia/Shanghai",
    "iso:country":"CN",
    "name:zho_x_preferred":[
        "\u5e86\u7eb2\u6751"
    ],
    "wof:name":"Qinggangcun",
    "wof:placetype":"locality"
},
  "geometry": {"coordinates":[126.59948,45.42834000000001],"type":"Point"}
}