{
  "type": "Feature",
  "properties": {
    "gn:admin1_code":"15.0",
    "gn:asciiname":"Shanggoumen",
    "gn:country_code":"CN",
    "gn:dem":2650,
    "gn:feature_class":"P",
    "gn:feature_code":"PPL",
    "gn:name":"Shanggoumen",
    "gn:population":0,
    "gn:timezone":"Asia/Shanghai",
    "iso:country":"CN",
    "name:und_x_variant":[
        "\u4e0a\u6c9f\u95e8"
    ],
    "wof:name":"Shanggoumen",
    "wof:placetype":"locality"
},
  "geometry": {"coordinates":[103.82153,34.62819],"type":"Point"}
}