{
  "type": "Feature",
  "properties": {
    "gn:admin1_code":"4.0",
    "gn:asciiname":"Lichangbang",
    "gn:country_code":"CN",
    "gn:dem":5,
    "gn:feature_class":"P",
    "gn:feature_code":"PPL",
    "gn:name":"Lichangbang",
    "gn:population":0,
    "gn:timezone":"Asia/Shanghai",
    "iso:country":"CN",
    "name:zho_x_preferred":[
        "\u91cc\u957f\u6d5c"
    ],
    "wof:name":"Lichangbang",
    "wof:placetype":"locality"
},
  "geometry": {"coordinates":[120.67442,31.08186],"type":"Point"}
}