{
  "type": "Feature",
  "properties": {
    "gn:admin1_code":"16.0",
    "gn:asciiname":"Banyao",
    "gn:country_code":"CN",
    "gn:dem":263,
    "gn:feature_class":"P",
    "gn:feature_code":"PPL",
    "gn:name":"Banyao",
    "gn:population":0,
    "gn:timezone":"Asia/Shanghai",
    "iso:country":"CN",
    "name:zho_x_preferred":[
        "\u677f\u7476"
    ],
    "wof:name":"Banyao",
    "wof:placetype":"locality"
},
  "geometry": {"coordinates":[110.44,23.972],"type":"Point"}
}