{
  "type": "Feature",
  "properties": {
    "gn:admin1_code":"18",
    "gn:asciiname":"Biji",
    "gn:country_code":"CN",
    "gn:dem":2083,
    "gn:feature_class":"P",
    "gn:feature_code":"PPL",
    "gn:name":"Biji",
    "gn:population":0,
    "gn:timezone":"Asia/Shanghai",
    "iso:country":"CN",
    "name:ceb_x_preferred":[
        "Biji"
    ],
    "name:zho_x_preferred":[
        "\u6bd4\u9e21"
    ],
    "wof:name":"Biji",
    "wof:placetype":"locality"
},
  "geometry": {"coordinates":[104.099,27.2778],"type":"Point"}
}