{
  "type": "Feature",
  "properties": {
    "gn:admin1_code":"9.0",
    "gn:asciiname":"Yeli",
    "gn:country_code":"CN",
    "gn:dem":93,
    "gn:feature_class":"P",
    "gn:feature_code":"PPL",
    "gn:name":"Yeli",
    "gn:population":0,
    "gn:timezone":"Asia/Shanghai",
    "iso:country":"CN",
    "name:ceb_x_preferred":[
        "Yeli"
    ],
    "name:swe_x_preferred":[
        "Yeli"
    ],
    "name:zho_x_preferred":[
        "\u53f6\u674e"
    ],
    "wof:name":"Yeli",
    "wof:placetype":"locality"
},
  "geometry": {"coordinates":[112.61245,32.48873],"type":"Point"}
}