{
  "type": "Feature",
  "properties": {
    "gn:admin1_code":"26.0",
    "gn:asciiname":"Lenggou",
    "gn:country_code":"CN",
    "gn:dem":1325,
    "gn:feature_class":"P",
    "gn:feature_code":"PPL",
    "gn:name":"Lenggou",
    "gn:population":0,
    "gn:timezone":"Asia/Shanghai",
    "iso:country":"CN",
    "name:zho_x_preferred":[
        "\u51b7\u6c9f"
    ],
    "wof:name":"Lenggou",
    "wof:placetype":"locality"
},
  "geometry": {"coordinates":[109.52043999999999,33.88464],"type":"Point"}
}