{
  "type": "Feature",
  "properties": {
    "gn:admin1_code":"12.0",
    "gn:asciiname":"Fengjiapu",
    "gn:country_code":"CN",
    "gn:dem":22,
    "gn:feature_class":"P",
    "gn:feature_code":"PPL",
    "gn:name":"Fengjiapu",
    "gn:population":0,
    "gn:timezone":"Asia/Shanghai",
    "iso:country":"CN",
    "name:und_x_variant":[
        "\u51af\u5bb6\u94fa"
    ],
    "wof:name":"Fengjiapu",
    "wof:placetype":"locality"
},
  "geometry": {"coordinates":[114.70028000000001,30.75224],"type":"Point"}
}