{
  "type": "Feature",
  "properties": {
    "gn:admin1_code":"5.0",
    "gn:asciiname":"Xigouli",
    "gn:country_code":"CN",
    "gn:dem":821,
    "gn:feature_class":"P",
    "gn:feature_code":"PPL",
    "gn:name":"Xigouli",
    "gn:population":0,
    "gn:timezone":"Asia/Shanghai",
    "iso:country":"CN",
    "name:und_x_variant":[
        "\u897f\u6c9f\u91cc"
    ],
    "wof:name":"Xigouli",
    "wof:placetype":"locality"
},
  "geometry": {"coordinates":[127.15233000000001,41.99361],"type":"Point"}
}