{
  "type": "Feature",
  "properties": {
    "gn:admin1_code":"11.0",
    "gn:asciiname":"Huangshawan",
    "gn:country_code":"CN",
    "gn:dem":26,
    "gn:feature_class":"P",
    "gn:feature_code":"PPL",
    "gn:name":"Huangshawan",
    "gn:population":0,
    "gn:timezone":"Asia/Shanghai",
    "iso:country":"CN",
    "name:zho_x_preferred":[
        "\u9ec4\u6c99\u6e7e"
    ],
    "name:zho_x_variant":[
        "\u9ec4\u6c99\u6e7e\u8857\u9053"
    ],
    "wof:name":"Huangshawan",
    "wof:placetype":"locality"
},
  "geometry": {"coordinates":[113.06808999999998,29.33108],"type":"Point"}
}