{
  "type": "Feature",
  "properties": {
    "gn:admin1_code":"30",
    "gn:asciiname":"Sandong",
    "gn:country_code":"CN",
    "gn:dem":74,
    "gn:feature_class":"P",
    "gn:feature_code":"PPLA4",
    "gn:name":"Sandong",
    "gn:population":0,
    "gn:timezone":"Asia/Shanghai",
    "iso:country":"CN",
    "name:und_x_variant":[
        "Sandong Zhen",
        "\u4e09\u680b\u9547"
    ],
    "name:zho_x_preferred":[
        "\u4e09\u680b"
    ],
    "wof:name":"Sandong",
    "wof:placetype":"locality"
},
  "geometry": {"coordinates":[114.44781999999999,22.99604],"type":"Point"}
}