{
  "type": "Feature",
  "properties": {
    "gn:admin1_code":"1.0",
    "gn:asciiname":"Guantangyangcun",
    "gn:country_code":"CN",
    "gn:dem":51,
    "gn:feature_class":"P",
    "gn:feature_code":"PPL",
    "gn:name":"Guantangyangcun",
    "gn:population":0,
    "gn:timezone":"Asia/Shanghai",
    "iso:country":"CN",
    "name:zho_x_preferred":[
        "\u5b98\u5858\u6768\u6751"
    ],
    "wof:name":"Guantangyangcun",
    "wof:placetype":"locality"
},
  "geometry": {"coordinates":[117.59657,32.31330999999999],"type":"Point"}
}