{
  "type": "Feature",
  "properties": {
    "gn:admin1_code":"14.0",
    "gn:asciiname":"Retong",
    "gn:country_code":"CN",
    "gn:dem":4087,
    "gn:feature_class":"P",
    "gn:feature_code":"PPL",
    "gn:name":"Retong",
    "gn:population":0,
    "gn:timezone":"Asia/Urumqi",
    "iso:country":"CN",
    "name:zho_x_preferred":[
        "\u70ed\u7b52"
    ],
    "wof:name":"Retong",
    "wof:placetype":"locality"
},
  "geometry": {"coordinates":[96.54376999999999,31.61889],"type":"Point"}
}