{
  "type": "Feature",
  "properties": {
    "gn:admin1_code":"5.0",
    "gn:asciiname":"Shuangshancun",
    "gn:country_code":"CN",
    "gn:dem":356,
    "gn:feature_class":"P",
    "gn:feature_code":"PPL",
    "gn:name":"Shuangshancun",
    "gn:population":0,
    "gn:timezone":"Asia/Shanghai",
    "iso:country":"CN",
    "name:zho_x_preferred":[
        "\u53cc\u5c71\u6751"
    ],
    "wof:name":"Shuangshancun",
    "wof:placetype":"locality"
},
  "geometry": {"coordinates":[125.65009000000001,42.64212],"type":"Point"}
}