{
  "type": "Feature",
  "properties": {
    "gn:admin1_code":"24.0",
    "gn:asciiname":"Nianbangshui",
    "gn:country_code":"CN",
    "gn:dem":1291,
    "gn:feature_class":"P",
    "gn:feature_code":"PPL",
    "gn:name":"Nianbangshui",
    "gn:population":0,
    "gn:timezone":"Asia/Shanghai",
    "iso:country":"CN",
    "name:zho_x_preferred":[
        "\u78be\u5e2e\u6c34"
    ],
    "wof:name":"Nianbangshui",
    "wof:placetype":"locality"
},
  "geometry": {"coordinates":[113.20287999999999,35.56273],"type":"Point"}
}