{
  "type": "Feature",
  "properties": {
    "gn:admin1_code":"32.0",
    "gn:asciiname":"Dalongtang",
    "gn:country_code":"CN",
    "gn:dem":2345,
    "gn:feature_class":"P",
    "gn:feature_code":"PPL",
    "gn:name":"Dalongtang",
    "gn:population":0,
    "gn:timezone":"Asia/Shanghai",
    "iso:country":"CN",
    "name:zho_x_preferred":[
        "\u5927\u9f99\u5858"
    ],
    "wof:name":"Dalongtang",
    "wof:placetype":"locality"
},
  "geometry": {"coordinates":[102.536,28.831],"type":"Point"}
}