{
  "type": "Feature",
  "properties": {
    "gn:admin1_code":"19.0",
    "gn:asciiname":"Qijiafangcun",
    "gn:country_code":"CN",
    "gn:dem":30,
    "gn:feature_class":"P",
    "gn:feature_code":"PPL",
    "gn:name":"Qijiafangcun",
    "gn:population":0,
    "gn:timezone":"Asia/Shanghai",
    "iso:country":"CN",
    "name:zho_x_preferred":[
        "\u9f50\u5bb6\u623f\u6751"
    ],
    "wof:name":"Qijiafangcun",
    "wof:placetype":"locality"
},
  "geometry": {"coordinates":[121.98242999999999,40.02628],"type":"Point"}
}