{
  "type": "Feature",
  "properties": {
    "gn:admin1_code":"26.0",
    "gn:asciiname":"Baitu Gangzicun",
    "gn:country_code":"CN",
    "gn:dem":1358,
    "gn:feature_class":"P",
    "gn:feature_code":"PPL",
    "gn:name":"Baitu Gangzicun",
    "gn:population":0,
    "gn:timezone":"Asia/Shanghai",
    "iso:country":"CN",
    "name:zho_x_preferred":[
        "\u767d\u571f\u5c97\u5b50\u6751"
    ],
    "wof:name":"Baitu Gangzicun",
    "wof:placetype":"locality"
},
  "geometry": {"coordinates":[108.22499999999999,37.57],"type":"Point"}
}