{
  "type": "Feature",
  "properties": {
    "gn:admin1_code":"12.0",
    "gn:asciiname":"Xiaoyujiatai",
    "gn:country_code":"CN",
    "gn:dem":27,
    "gn:feature_class":"P",
    "gn:feature_code":"PPL",
    "gn:name":"Xiaoyujiatai",
    "gn:population":0,
    "gn:timezone":"Asia/Shanghai",
    "iso:country":"CN",
    "name:zho_x_preferred":[
        "\u5c0f\u4f59\u5bb6\u53f0"
    ],
    "wof:name":"Xiaoyujiatai",
    "wof:placetype":"locality"
},
  "geometry": {"coordinates":[112.79647,30.02656],"type":"Point"}
}