{
  "type": "Feature",
  "properties": {
    "gn:admin1_code":"11.0",
    "gn:asciiname":"Hutian",
    "gn:country_code":"CN",
    "gn:dem":147,
    "gn:feature_class":"P",
    "gn:feature_code":"PPL",
    "gn:name":"Hutian",
    "gn:population":0,
    "gn:timezone":"Asia/Shanghai",
    "iso:country":"CN",
    "name:zho_x_preferred":[
        "\u547c\u7530"
    ],
    "wof:name":"Hutian",
    "wof:placetype":"locality"
},
  "geometry": {"coordinates":[113.87417000000001,28.41746],"type":"Point"}
}