{
  "type": "Feature",
  "properties": {
    "gn:admin1_code":"7.0",
    "gn:asciiname":"Huangshikeng",
    "gn:country_code":"CN",
    "gn:dem":360,
    "gn:feature_class":"P",
    "gn:feature_code":"PPL",
    "gn:name":"Huangshikeng",
    "gn:population":0,
    "gn:timezone":"Asia/Shanghai",
    "iso:country":"CN",
    "name:zho_x_preferred":[
        "\u9ec4\u4ed5\u5751"
    ],
    "wof:name":"Huangshikeng",
    "wof:placetype":"locality"
},
  "geometry": {"coordinates":[116.92124,24.64872],"type":"Point"}
}