{
  "type": "Feature",
  "properties": {
    "gn:admin1_code":"7",
    "gn:asciiname":"Shanbing",
    "gn:country_code":"CN",
    "gn:dem":17,
    "gn:feature_class":"P",
    "gn:feature_code":"PPL",
    "gn:name":"Shanbing",
    "gn:population":0,
    "gn:timezone":"Asia/Shanghai",
    "iso:country":"CN",
    "name:und_x_variant":[
        "Shan-ping",
        "Shanbing"
    ],
    "name:zho_x_preferred":[
        "\u5c71\u67c4"
    ],
    "wof:name":"Shanbing",
    "wof:placetype":"locality"
},
  "geometry": {"coordinates":[119.10323,25.12342],"type":"Point"}
}