{
  "type": "Feature",
  "properties": {
    "gn:admin1_code":"14.0",
    "gn:asciiname":"Yang'annong",
    "gn:country_code":"CN",
    "gn:dem":4695,
    "gn:feature_class":"P",
    "gn:feature_code":"PPL",
    "gn:name":"Yang\u2019annong",
    "gn:population":0,
    "gn:timezone":"Asia/Urumqi",
    "iso:country":"CN",
    "name:und_x_variant":[
        "Yang\u2019annong"
    ],
    "name:zho_x_preferred":[
        "\u7f8a\u5b89\u5f04"
    ],
    "wof:name":"Yang'annong",
    "wof:placetype":"locality"
},
  "geometry": {"coordinates":[95.02222999999999,31.35832000000001],"type":"Point"}
}