{
  "type": "Feature",
  "properties": {
    "gn:admin1_code":"8.0",
    "gn:asciiname":"Sanbucun",
    "gn:country_code":"CN",
    "gn:dem":218,
    "gn:feature_class":"P",
    "gn:feature_code":"PPL",
    "gn:name":"Sanbucun",
    "gn:population":0,
    "gn:timezone":"Asia/Shanghai",
    "iso:country":"CN",
    "name:zho_x_preferred":[
        "\u4e09\u90e8\u6751"
    ],
    "wof:name":"Sanbucun",
    "wof:placetype":"locality"
},
  "geometry": {"coordinates":[127.41701,47.21202],"type":"Point"}
}