{
  "type": "Feature",
  "properties": {
    "gn:admin1_code":"8.0",
    "gn:asciiname":"Qunlincun",
    "gn:country_code":"CN",
    "gn:dem":174,
    "gn:feature_class":"P",
    "gn:feature_code":"PPL",
    "gn:name":"Qunlincun",
    "gn:population":0,
    "gn:timezone":"Asia/Shanghai",
    "iso:country":"CN",
    "name:zho_x_preferred":[
        "\u7fa4\u6797\u6751"
    ],
    "wof:name":"Qunlincun",
    "wof:placetype":"locality"
},
  "geometry": {"coordinates":[130.26868999999999,46.6327],"type":"Point"}
}