{
  "type": "Feature",
  "properties": {
    "gn:admin1_code":"18",
    "gn:asciiname":"Jiantouya",
    "gn:country_code":"CN",
    "gn:dem":1072,
    "gn:feature_class":"P",
    "gn:feature_code":"PPL",
    "gn:name":"Jiantouya",
    "gn:population":0,
    "gn:timezone":"Asia/Shanghai",
    "iso:country":"CN",
    "name:zho_x_preferred":[
        "\u7bad\u5934\u57ad"
    ],
    "wof:name":"Jiantouya",
    "wof:placetype":"locality"
},
  "geometry": {"coordinates":[106.752,28.5603],"type":"Point"}
}