{
  "type": "Feature",
  "properties": {
    "gn:admin1_code":"30",
    "gn:asciiname":"Bayi Linchang",
    "gn:country_code":"CN",
    "gn:dem":283,
    "gn:feature_class":"P",
    "gn:feature_code":"PPLF",
    "gn:name":"Bayi Linchang",
    "gn:population":0,
    "gn:timezone":"Asia/Urumqi",
    "iso:country":"CN",
    "name:zho_x_preferred":[
        "\u516b\u4e00\u6797\u573a"
    ],
    "wof:name":"Bayi Linchang",
    "wof:placetype":"locality"
},
  "geometry": {"coordinates":[111.61806,22.42722],"type":"Point"}
}