{
  "type": "Feature",
  "properties": {
    "gn:admin1_code":"32.0",
    "gn:asciiname":"Guandaliang",
    "gn:country_code":"CN",
    "gn:dem":493,
    "gn:feature_class":"P",
    "gn:feature_code":"PPL",
    "gn:name":"Guandaliang",
    "gn:population":0,
    "gn:timezone":"Asia/Shanghai",
    "iso:country":"CN",
    "name:zho_x_preferred":[
        "\u5173\u5927\u6881"
    ],
    "wof:name":"Guandaliang",
    "wof:placetype":"locality"
},
  "geometry": {"coordinates":[105.90000999999999,31.82977],"type":"Point"}
}