{
  "type": "Feature",
  "properties": {
    "gn:admin1_code":"15.0",
    "gn:asciiname":"Wuxing",
    "gn:country_code":"CN",
    "gn:dem":2173,
    "gn:feature_class":"P",
    "gn:feature_code":"PPL",
    "gn:name":"Wuxing",
    "gn:population":0,
    "gn:timezone":"Asia/Shanghai",
    "iso:country":"CN",
    "name:ceb_x_preferred":[
        "Wuxing"
    ],
    "name:deu_x_preferred":[
        "Wuxing"
    ],
    "name:fra_x_preferred":[
        "Wuxing"
    ],
    "name:zho_x_preferred":[
        "\u4e94\u661f"
    ],
    "wof:name":"Wuxing",
    "wof:placetype":"locality"
},
  "geometry": {"coordinates":[103.19799999999999,35.5439],"type":"Point"}
}