{
  "type": "Feature",
  "properties": {
    "gn:admin1_code":"16.0",
    "gn:asciiname":"Xinshanjiao",
    "gn:country_code":"CN",
    "gn:dem":82,
    "gn:feature_class":"P",
    "gn:feature_code":"PPL",
    "gn:name":"Xinshanjiao",
    "gn:population":0,
    "gn:timezone":"Asia/Shanghai",
    "iso:country":"CN",
    "name:zho_x_preferred":[
        "\u65b0\u5c71\u811a"
    ],
    "wof:name":"Xinshanjiao",
    "wof:placetype":"locality"
},
  "geometry": {"coordinates":[109.34099999999999,23.7181],"type":"Point"}
}