{
  "type": "Feature",
  "properties": {
    "gn:admin1_code":"2.0",
    "gn:asciiname":"Dantoushan",
    "gn:country_code":"CN",
    "gn:dem":526,
    "gn:feature_class":"P",
    "gn:feature_code":"PPL",
    "gn:name":"Dantoushan",
    "gn:population":0,
    "gn:timezone":"Asia/Shanghai",
    "iso:country":"CN",
    "name:zho_x_preferred":[
        "\u65e6\u5934\u5c71"
    ],
    "wof:name":"Dantoushan",
    "wof:placetype":"locality"
},
  "geometry": {"coordinates":[120.27703,28.37912],"type":"Point"}
}