{
  "type": "Feature",
  "properties": {
    "gn:admin1_code":"02",
    "gn:asciiname":"Guandi",
    "gn:cc2":"CN",
    "gn:country_code":"CN",
    "gn:dem":26,
    "gn:feature_class":"P",
    "gn:feature_code":"PPL",
    "gn:name":"Guandi",
    "gn:population":0,
    "gn:timezone":"Asia/Shanghai",
    "iso:country":"CN",
    "name:und_x_variant":[
        "Kuan-ti",
        "Guandi",
        "\u5b98\u5730"
    ],
    "name:zho_x_preferred":[
        "\u5b98\u5730"
    ],
    "wof:name":"Guandi",
    "wof:placetype":"locality"
},
  "geometry": {"coordinates":[121.35805999999999,29.23778],"type":"Point"}
}