{
  "type": "Feature",
  "properties": {
    "gn:admin1_code":"4.0",
    "gn:asciiname":"Wuzong",
    "gn:country_code":"CN",
    "gn:dem":5,
    "gn:feature_class":"P",
    "gn:feature_code":"PPL",
    "gn:name":"Wuzong",
    "gn:population":0,
    "gn:timezone":"Asia/Shanghai",
    "iso:country":"CN",
    "name:deu_x_preferred":[
        "Wuzong"
    ],
    "name:nld_x_preferred":[
        "Wuzong"
    ],
    "name:pol_x_preferred":[
        "Wuzong"
    ],
    "name:ukr_x_preferred":[
        "\u0423\u0446\u0437\u0443\u043d"
    ],
    "name:vie_x_preferred":[
        "V\u0169 T\u00f4ng"
    ],
    "name:zho_x_preferred":[
        "\u4e94\u603b"
    ],
    "wof:name":"Wuzong",
    "wof:placetype":"locality"
},
  "geometry": {"coordinates":[121.31332,32.08588],"type":"Point"}
}