{
  "type": "Feature",
  "properties": {
    "gn:admin1_code":"8.0",
    "gn:asciiname":"Puyang Shidui",
    "gn:country_code":"CN",
    "gn:dem":66,
    "gn:feature_class":"P",
    "gn:feature_code":"PPLF",
    "gn:name":"Puyang Shidui",
    "gn:population":0,
    "gn:timezone":"Asia/Shanghai",
    "iso:country":"CN",
    "name:zho_x_preferred":[
        "\u97f3\u9633\u5341\u961f"
    ],
    "wof:name":"Puyang Shidui",
    "wof:placetype":"locality"
},
  "geometry": {"coordinates":[131.14072999999999,47.25532000000001],"type":"Point"}
}