{
  "type": "Feature",
  "properties": {
    "gn:admin1_code":"3.0",
    "gn:asciiname":"Taoshanwo",
    "gn:country_code":"CN",
    "gn:dem":406,
    "gn:feature_class":"P",
    "gn:feature_code":"PPL",
    "gn:name":"Taoshanwo",
    "gn:population":0,
    "gn:timezone":"Asia/Shanghai",
    "iso:country":"CN",
    "name:und_x_variant":[
        "\u6843\u5c71\u7a9d"
    ],
    "wof:name":"Taoshanwo",
    "wof:placetype":"locality"
},
  "geometry": {"coordinates":[115.60227999999999,26.44428],"type":"Point"}
}