{
  "type": "Feature",
  "properties": {
    "gn:admin1_code":"29.0",
    "gn:asciiname":"Shifoshan",
    "gn:country_code":"CN",
    "gn:dem":3186,
    "gn:feature_class":"P",
    "gn:feature_code":"PPL",
    "gn:name":"Shifoshan",
    "gn:population":0,
    "gn:timezone":"Asia/Shanghai",
    "iso:country":"CN",
    "name:zho_x_preferred":[
        "\u77f3\u4f5b\u5c71"
    ],
    "wof:name":"Shifoshan",
    "wof:placetype":"locality"
},
  "geometry": {"coordinates":[100.72,27.55],"type":"Point"}
}