{
  "type": "Feature",
  "properties": {
    "gn:admin1_code":"1.0",
    "gn:asciiname":"Nangaoloucun",
    "gn:country_code":"CN",
    "gn:dem":41,
    "gn:feature_class":"P",
    "gn:feature_code":"PPL",
    "gn:name":"Nangaoloucun",
    "gn:population":0,
    "gn:timezone":"Asia/Shanghai",
    "iso:country":"CN",
    "name:zho_x_preferred":[
        "\u5357\u9ad8\u697c\u6751"
    ],
    "wof:name":"Nangaoloucun",
    "wof:placetype":"locality"
},
  "geometry": {"coordinates":[115.70047,33.87894],"type":"Point"}
}