{
  "type": "Feature",
  "properties": {
    "gn:admin1_code":"15.0",
    "gn:asciiname":"Gaxia",
    "gn:country_code":"CN",
    "gn:dem":2225,
    "gn:feature_class":"P",
    "gn:feature_code":"PPL",
    "gn:name":"Gaxia",
    "gn:population":0,
    "gn:timezone":"Asia/Shanghai",
    "iso:country":"CN",
    "name:und_x_variant":[
        "\u560e\u4e0b"
    ],
    "name:zho_x_preferred":[
        "\u560e\u4e0b"
    ],
    "wof:name":"Gaxia",
    "wof:placetype":"locality"
},
  "geometry": {"coordinates":[104.32939,33.62644],"type":"Point"}
}