{
  "type": "Feature",
  "properties": {
    "gn:admin1_code":"02",
    "gn:asciiname":"Waiyangqing",
    "gn:country_code":"CN",
    "gn:dem":7,
    "gn:feature_class":"P",
    "gn:feature_code":"PPL",
    "gn:name":"Waiyangqing",
    "gn:population":0,
    "gn:timezone":"Asia/Shanghai",
    "iso:country":"CN",
    "name:zho_x_preferred":[
        "\u5916\u579f\u9752"
    ],
    "name:zho_x_variant":[
        "Wai-yang-ch\u2019ing"
    ],
    "wof:name":"Waiyangqing",
    "wof:placetype":"locality"
},
  "geometry": {"coordinates":[121.04206000000001,27.98474],"type":"Point"}
}