{
  "type": "Feature",
  "properties": {
    "gn:admin1_code":"3",
    "gn:asciiname":"Yantang",
    "gn:country_code":"CN",
    "gn:dem":31,
    "gn:feature_class":"P",
    "gn:feature_code":"PPL",
    "gn:name":"Yantang",
    "gn:population":0,
    "gn:timezone":"Asia/Shanghai",
    "iso:country":"CN",
    "name:ceb_x_preferred":[
        "Yantang"
    ],
    "name:deu_x_preferred":[
        "Yantang"
    ],
    "name:swe_x_preferred":[
        "Yantang"
    ],
    "name:und_x_variant":[
        "\u96c1\u5858"
    ],
    "wof:name":"Yantang",
    "wof:placetype":"locality"
},
  "geometry": {"coordinates":[116.38658,28.34364],"type":"Point"}
}