{
  "type": "Feature",
  "properties": {
    "gn:admin1_code":"8.0",
    "gn:asciiname":"Qianyicun",
    "gn:country_code":"CN",
    "gn:dem":239,
    "gn:feature_class":"P",
    "gn:feature_code":"PPL",
    "gn:name":"Qianyicun",
    "gn:population":0,
    "gn:timezone":"Asia/Shanghai",
    "iso:country":"CN",
    "name:zho_x_preferred":[
        "\u8c26\u76ca\u6751"
    ],
    "wof:name":"Qianyicun",
    "wof:placetype":"locality"
},
  "geometry": {"coordinates":[125.48721,48.46439],"type":"Point"}
}