{
  "type": "Feature",
  "properties": {
    "gn:admin1_code":"32.0",
    "gn:asciiname":"Waqulewa",
    "gn:country_code":"CN",
    "gn:dem":1205,
    "gn:feature_class":"P",
    "gn:feature_code":"PPL",
    "gn:name":"Waqulewa",
    "gn:population":0,
    "gn:timezone":"Asia/Shanghai",
    "iso:country":"CN",
    "name:zho_x_preferred":[
        "\u6316\u53d6\u52d2\u74e6"
    ],
    "wof:name":"Waqulewa",
    "wof:placetype":"locality"
},
  "geometry": {"coordinates":[103.43300000000001,28.7852],"type":"Point"}
}