{
  "type": "Feature",
  "properties": {
    "gn:admin1_code":"19.0",
    "gn:asciiname":"Xiaokangtuncun",
    "gn:country_code":"CN",
    "gn:dem":71,
    "gn:feature_class":"P",
    "gn:feature_code":"PPL",
    "gn:name":"Xiaokangtuncun",
    "gn:population":0,
    "gn:timezone":"Asia/Shanghai",
    "iso:country":"CN",
    "name:zho_x_preferred":[
        "\u5c0f\u5eb7\u5c6f\u6751"
    ],
    "wof:name":"Xiaokangtuncun",
    "wof:placetype":"locality"
},
  "geometry": {"coordinates":[123.602,42.2078],"type":"Point"}
}