{
  "type": "Feature",
  "properties": {
    "gn:admin1_code":"15.0",
    "gn:asciiname":"Xigouzi",
    "gn:country_code":"CN",
    "gn:dem":1186,
    "gn:feature_class":"P",
    "gn:feature_code":"PPL",
    "gn:name":"Xigouzi",
    "gn:population":0,
    "gn:timezone":"Asia/Shanghai",
    "iso:country":"CN",
    "name:zho_x_preferred":[
        "\u897f\u6c9f\u5b50"
    ],
    "wof:name":"Xigouzi",
    "wof:placetype":"locality"
},
  "geometry": {"coordinates":[107.914,35.4355],"type":"Point"}
}