{
  "type": "Feature",
  "properties": {
    "gn:admin1_code":"18",
    "gn:asciiname":"Linwan",
    "gn:country_code":"CN",
    "gn:dem":1022,
    "gn:feature_class":"P",
    "gn:feature_code":"PPL",
    "gn:name":"Linwan",
    "gn:population":0,
    "gn:timezone":"Asia/Shanghai",
    "iso:country":"CN",
    "name:zho_x_preferred":[
        "\u6797\u6e7e"
    ],
    "wof:name":"Linwan",
    "wof:placetype":"locality"
},
  "geometry": {"coordinates":[106.994,27.2352],"type":"Point"}
}