{
  "type": "Feature",
  "properties": {
    "gn:admin1_code":"26.0",
    "gn:asciiname":"Caogouquan",
    "gn:country_code":"CN",
    "gn:dem":1335,
    "gn:feature_class":"P",
    "gn:feature_code":"PPL",
    "gn:name":"Caogouquan",
    "gn:population":0,
    "gn:timezone":"Asia/Shanghai",
    "iso:country":"CN",
    "name:und_x_variant":[
        "\u8349\u6c9f\u5708"
    ],
    "wof:name":"Caogouquan",
    "wof:placetype":"locality"
},
  "geometry": {"coordinates":[107.85277000000001,34.94783],"type":"Point"}
}