{
  "type": "Feature",
  "properties": {
    "gn:admin1_code":"11.0",
    "gn:asciiname":"Huangjinyu",
    "gn:country_code":"CN",
    "gn:dem":354,
    "gn:feature_class":"P",
    "gn:feature_code":"PPL",
    "gn:name":"Huangjinyu",
    "gn:population":0,
    "gn:timezone":"Asia/Shanghai",
    "iso:country":"CN",
    "name:zho_x_preferred":[
        "Huangjinyu"
    ],
    "name:zho_x_variant":[
        "\u9ec4\u91d1\u5cea"
    ],
    "wof:name":"Huangjinyu",
    "wof:placetype":"locality"
},
  "geometry": {"coordinates":[111.22244000000001,29.43113],"type":"Point"}
}