{
  "type": "Feature",
  "properties": {
    "gn:admin1_code":"25.0",
    "gn:asciiname":"Dugezhuangcun",
    "gn:country_code":"CN",
    "gn:dem":24,
    "gn:feature_class":"P",
    "gn:feature_code":"PPL",
    "gn:name":"Dugezhuangcun",
    "gn:population":0,
    "gn:timezone":"Asia/Shanghai",
    "iso:country":"CN",
    "name:zho_x_preferred":[
        "\u675c\u6208\u5e84\u6751"
    ],
    "wof:name":"Dugezhuangcun",
    "wof:placetype":"locality"
},
  "geometry": {"coordinates":[120.0829,36.57721],"type":"Point"}
}