{
  "type": "Feature",
  "properties": {
    "gn:admin1_code":"3.0",
    "gn:asciiname":"Luoshan Zonghe Kenzhichang",
    "gn:country_code":"CN",
    "gn:dem":135,
    "gn:feature_class":"P",
    "gn:feature_code":"PPLF",
    "gn:name":"Luoshan Zonghe Kenzhichang",
    "gn:population":0,
    "gn:timezone":"Asia/Shanghai",
    "iso:country":"CN",
    "name:und_x_variant":[
        "\u7f57\u5c71\u7efc\u5408\u57a6\u6b96\u573a"
    ],
    "wof:name":"Luoshan Zonghe Kenzhichang",
    "wof:placetype":"locality"
},
  "geometry": {"coordinates":[115.92699,27.85349],"type":"Point"}
}