{
  "type": "Feature",
  "properties": {
    "gn:admin1_code":"26",
    "gn:asciiname":"Laoguanmiao",
    "gn:country_code":"CN",
    "gn:dem":624,
    "gn:feature_class":"P",
    "gn:feature_code":"PPL",
    "gn:name":"Laoguanmiao",
    "gn:population":0,
    "gn:timezone":"Asia/Shanghai",
    "iso:country":"CN",
    "name:und_x_variant":[
        "Lao-kuan-miao",
        "Laoguanmiao",
        "\u8001\u5173\u5e99"
    ],
    "wof:name":"Laoguanmiao",
    "wof:placetype":"locality"
},
  "geometry": {"coordinates":[105.93361000000002,32.91147],"type":"Point"}
}