{
  "type": "Feature",
  "properties": {
    "gn:admin1_code":"25",
    "gn:asciiname":"Nuomiwan",
    "gn:country_code":"CN",
    "gn:dem":197,
    "gn:feature_class":"P",
    "gn:feature_code":"PPL",
    "gn:name":"Nuomiwan",
    "gn:population":0,
    "gn:timezone":"Asia/Shanghai",
    "iso:country":"CN",
    "name:zho_x_preferred":[
        "\u7cef\u7c73\u6e7e"
    ],
    "wof:name":"Nuomiwan",
    "wof:placetype":"locality"
},
  "geometry": {"coordinates":[117.846,35.213],"type":"Point"}
}