{
  "type": "Feature",
  "properties": {
    "gn:admin1_code":"32.0",
    "gn:asciiname":"Kongxinzhai",
    "gn:country_code":"CN",
    "gn:dem":3332,
    "gn:feature_class":"P",
    "gn:feature_code":"PPL",
    "gn:name":"Kongxinzhai",
    "gn:population":0,
    "gn:timezone":"Asia/Shanghai",
    "iso:country":"CN",
    "name:zho_x_preferred":[
        "\u7a7a\u5fc3\u5be8"
    ],
    "wof:name":"Kongxinzhai",
    "wof:placetype":"locality"
},
  "geometry": {"coordinates":[103.64721,32.43855],"type":"Point"}
}