{
  "type": "Feature",
  "properties": {
    "gn:admin1_code":"09",
    "gn:asciiname":"Panlong",
    "gn:country_code":"CN",
    "gn:dem":99,
    "gn:feature_class":"P",
    "gn:feature_code":"PPLA3",
    "gn:name":"Panlong",
    "gn:population":0,
    "gn:timezone":"Asia/Shanghai",
    "iso:country":"CN",
    "name:und_x_variant":[
        "Kioshan-hsien",
        "Ch\u2019\u00fceh-shan-hsien",
        "Kioshan",
        "Ch\u2019\u00fceh-shan",
        "Chiu-shan",
        "Queshan",
        "Panlong"
    ],
    "name:zho_x_preferred":[
        "\u76d8\u9f99"
    ],
    "wof:name":"Panlong",
    "wof:placetype":"locality"
},
  "geometry": {"coordinates":[114.01917,32.80222],"type":"Point"}
}