{
  "type": "Feature",
  "properties": {
    "gn:admin1_code":"09",
    "gn:asciiname":"Panlong",
    "gn:country_code":"CN",
    "gn:dem":99,
    "gn:feature_class":"P",
    "gn:feature_code":"PPLA3",
    "gn:name":"Panlong",
    "gn:population":0,
    "gn:timezone":"Asia/Shanghai",
    "iso:country":"CN",
    "name:deu_x_preferred":[
        "Queshan"
    ],
    "name:fas_x_preferred":[
        "\u0634\u0647\u0631\u0633\u062a\u0627\u0646 \u0686\u0648\u0634\u0627\u0646"
    ],
    "name:jpn_x_preferred":[
        "\u78ba\u5c71\u770c"
    ],
    "name:kor_x_preferred":[
        "\ucdcc\uc0b0\ud604"
    ],
    "name:nor_x_preferred":[
        "Queshan"
    ],
    "name:rus_x_preferred":[
        "\u0426\u044e\u044d\u0448\u0430\u043d\u044c"
    ],
    "name:swe_x_preferred":[
        "Queshan"
    ],
    "name:und_x_variant":[
        "Kioshan-hsien",
        "Ch\u2019\u00fceh-shan-hsien",
        "Kioshan",
        "Ch\u2019\u00fceh-shan",
        "Chiu-shan",
        "Panlong"
    ],
    "name:vie_x_preferred":[
        "X\u00e1c S\u01a1n"
    ],
    "name:zho_x_preferred":[
        "\u76d8\u9f99"
    ],
    "name:zho_x_variant":[
        "\u786e\u5c71\u53bf"
    ],
    "wof:name":"Panlong",
    "wof:placetype":"locality"
},
  "geometry": {"coordinates":[114.01917,32.80222],"type":"Point"}
}