{
  "type": "Feature",
  "properties": {
    "gn:admin1_code":"3.0",
    "gn:asciiname":"Kejialing",
    "gn:country_code":"CN",
    "gn:dem":31,
    "gn:feature_class":"P",
    "gn:feature_code":"PPL",
    "gn:name":"Kejialing",
    "gn:population":0,
    "gn:timezone":"Asia/Shanghai",
    "iso:country":"CN",
    "name:und_x_variant":[
        "\u67ef\u5bb6\u5cad"
    ],
    "wof:name":"Kejialing",
    "wof:placetype":"locality"
},
  "geometry": {"coordinates":[116.86948999999998,28.44658],"type":"Point"}
}