{
  "type": "Feature",
  "properties": {
    "gn:admin1_code":"29",
    "gn:asciiname":"Jinguan",
    "gn:country_code":"CN",
    "gn:dem":1599,
    "gn:feature_class":"P",
    "gn:feature_code":"PPL",
    "gn:name":"Jinguan",
    "gn:population":0,
    "gn:timezone":"Asia/Shanghai",
    "iso:country":"CN",
    "name:und_x_variant":[
        "Chin-kuan",
        "Jinguan"
    ],
    "wof:name":"Jinguan",
    "wof:placetype":"locality"
},
  "geometry": {"coordinates":[100.66621000000001,26.75803],"type":"Point"}
}