{
  "type": "Feature",
  "properties": {
    "gn:admin1_code":"3",
    "gn:asciiname":"Zhangmukeng",
    "gn:country_code":"CN",
    "gn:dem":73,
    "gn:feature_class":"P",
    "gn:feature_code":"PPL",
    "gn:name":"Zhangmukeng",
    "gn:population":0,
    "gn:timezone":"Asia/Shanghai",
    "iso:country":"CN",
    "name:zho_x_preferred":[
        "\u6a1f\u6728\u5751"
    ],
    "wof:name":"Zhangmukeng",
    "wof:placetype":"locality"
},
  "geometry": {"coordinates":[115.133,27.1137],"type":"Point"}
}