{
  "type": "Feature",
  "properties": {
    "gn:admin1_code":"5.0",
    "gn:asciiname":"Ming'ancun",
    "gn:country_code":"CN",
    "gn:dem":138,
    "gn:feature_class":"P",
    "gn:feature_code":"PPL",
    "gn:name":"Ming\u2019ancun",
    "gn:population":0,
    "gn:timezone":"Asia/Shanghai",
    "iso:country":"CN",
    "name:und_x_variant":[
        "Ming\u2019ancun"
    ],
    "name:zho_x_preferred":[
        "\u660e\u5b89\u6751"
    ],
    "wof:name":"Ming'ancun",
    "wof:placetype":"locality"
},
  "geometry": {"coordinates":[125.22620000000001,45.36543],"type":"Point"}
}