{
  "type": "Feature",
  "properties": {
    "gn:admin1_code":"11.0",
    "gn:asciiname":"Chengjiangkou",
    "gn:country_code":"CN",
    "gn:dem":116,
    "gn:feature_class":"P",
    "gn:feature_code":"PPL",
    "gn:name":"Chengjiangkou",
    "gn:population":0,
    "gn:timezone":"Asia/Shanghai",
    "iso:country":"CN",
    "name:zho_x_preferred":[
        "\u7a0b\u6c5f\u53e3"
    ],
    "wof:name":"Chengjiangkou",
    "wof:placetype":"locality"
},
  "geometry": {"coordinates":[113.15505,26.04036],"type":"Point"}
}