{
  "type": "Feature",
  "properties": {
    "gn:admin1_code":"30.0",
    "gn:asciiname":"Sanyahu",
    "gn:country_code":"CN",
    "gn:dem":168,
    "gn:feature_class":"P",
    "gn:feature_code":"PPL",
    "gn:name":"Sanyahu",
    "gn:population":0,
    "gn:timezone":"Asia/Shanghai",
    "iso:country":"CN",
    "name:zho_x_preferred":[
        "\u4e09\u4e2b\u6e56"
    ],
    "wof:name":"Sanyahu",
    "wof:placetype":"locality"
},
  "geometry": {"coordinates":[113.00187,21.94277],"type":"Point"}
}