{
  "type": "Feature",
  "properties": {
    "gn:admin1_code":"16.0",
    "gn:asciiname":"Yunlin",
    "gn:country_code":"CN",
    "gn:dem":221,
    "gn:feature_class":"P",
    "gn:feature_code":"PPL",
    "gn:name":"Yunlin",
    "gn:population":0,
    "gn:timezone":"Asia/Shanghai",
    "iso:country":"CN",
    "name:zho_x_preferred":[
        "\u4e91\u6797"
    ],
    "wof:name":"Yunlin",
    "wof:placetype":"locality"
},
  "geometry": {"coordinates":[107.20699999999999,23.3861],"type":"Point"}
}