{
  "type": "Feature",
  "properties": {
    "gn:admin1_code":"31.0",
    "gn:asciiname":"Rufeng",
    "gn:country_code":"CN",
    "gn:dem":17,
    "gn:feature_class":"P",
    "gn:feature_code":"PPL",
    "gn:name":"Rufeng",
    "gn:population":0,
    "gn:timezone":"Asia/Shanghai",
    "iso:country":"CN",
    "name:zho_x_preferred":[
        "\u5112\u9022"
    ],
    "wof:name":"Rufeng",
    "wof:placetype":"locality"
},
  "geometry": {"coordinates":[110.37406,19.9536],"type":"Point"}
}