{
  "type": "Feature",
  "properties": {
    "gn:admin1_code":"29.0",
    "gn:asciiname":"Qincaitang",
    "gn:country_code":"CN",
    "gn:dem":2151,
    "gn:feature_class":"P",
    "gn:feature_code":"PPL",
    "gn:name":"Qincaitang",
    "gn:population":0,
    "gn:timezone":"Asia/Shanghai",
    "iso:country":"CN",
    "name:zho_x_preferred":[
        "\u82b9\u83dc\u5858"
    ],
    "wof:name":"Qincaitang",
    "wof:placetype":"locality"
},
  "geometry": {"coordinates":[102.55,25.1079],"type":"Point"}
}