{
  "type": "Feature",
  "properties": {
    "gn:admin1_code":"26.0",
    "gn:asciiname":"Manjianghongcun",
    "gn:country_code":"CN",
    "gn:dem":504,
    "gn:feature_class":"P",
    "gn:feature_code":"PPL",
    "gn:name":"Manjianghongcun",
    "gn:population":0,
    "gn:timezone":"Asia/Shanghai",
    "iso:country":"CN",
    "name:zho_x_preferred":[
        "\u6ee1\u6c5f\u7ea2\u6751"
    ],
    "wof:name":"Manjianghongcun",
    "wof:placetype":"locality"
},
  "geometry": {"coordinates":[108.94962,34.05349],"type":"Point"}
}