{
  "type": "Feature",
  "properties": {
    "gn:admin1_code":"3.0",
    "gn:asciiname":"Zankou",
    "gn:country_code":"CN",
    "gn:dem":251,
    "gn:feature_class":"P",
    "gn:feature_code":"PPL",
    "gn:name":"Zankou",
    "gn:population":0,
    "gn:timezone":"Asia/Shanghai",
    "iso:country":"CN",
    "name:ita_x_preferred":[
        "Zankou"
    ],
    "name:nld_x_preferred":[
        "Zankou"
    ],
    "name:und_x_variant":[
        "\u8d5e\u53e3"
    ],
    "wof:name":"Zankou",
    "wof:placetype":"locality"
},
  "geometry": {"coordinates":[116.16672,26.29451],"type":"Point"}
}