{
  "type": "Feature",
  "properties": {
    "gn:admin1_code":"12.0",
    "gn:asciiname":"Huajiagang",
    "gn:country_code":"CN",
    "gn:dem":108,
    "gn:feature_class":"P",
    "gn:feature_code":"PPL",
    "gn:name":"Huajiagang",
    "gn:population":0,
    "gn:timezone":"Asia/Shanghai",
    "iso:country":"CN",
    "name:zho_x_preferred":[
        "\u534e\u5bb6\u5c97"
    ],
    "wof:name":"Huajiagang",
    "wof:placetype":"locality"
},
  "geometry": {"coordinates":[111.92522,32.04658],"type":"Point"}
}