{
  "type": "Feature",
  "properties": {
    "gn:admin1_code":"5.0",
    "gn:asciiname":"Bijiamu Hekou",
    "gn:country_code":"CN",
    "gn:dem":514,
    "gn:feature_class":"P",
    "gn:feature_code":"PPL",
    "gn:name":"Bijiamu Hekou",
    "gn:population":0,
    "gn:timezone":"Asia/Shanghai",
    "iso:country":"CN",
    "name:und_x_variant":[
        "\u6bd5\u5bb6\u6728\u6cb3\u53e3"
    ],
    "wof:name":"Bijiamu Hekou",
    "wof:placetype":"locality"
},
  "geometry": {"coordinates":[127.15161000000001,41.84662],"type":"Point"}
}