{
  "type": "Feature",
  "properties": {
    "gn:admin1_code":"32.0",
    "gn:asciiname":"Mujiagou",
    "gn:country_code":"CN",
    "gn:dem":343,
    "gn:feature_class":"P",
    "gn:feature_code":"PPL",
    "gn:name":"Mujiagou",
    "gn:population":0,
    "gn:timezone":"Asia/Shanghai",
    "iso:country":"CN",
    "name:zho_x_preferred":[
        "\u7a46\u5bb6\u6c9f"
    ],
    "wof:name":"Mujiagou",
    "wof:placetype":"locality"
},
  "geometry": {"coordinates":[106.25490000000001,30.87449],"type":"Point"}
}