{
  "type": "Feature",
  "properties": {
    "gn:admin1_code":"12.0",
    "gn:asciiname":"Hefuyuan",
    "gn:country_code":"CN",
    "gn:dem":26,
    "gn:feature_class":"P",
    "gn:feature_code":"PPL",
    "gn:name":"Hefuyuan",
    "gn:population":0,
    "gn:timezone":"Asia/Shanghai",
    "iso:country":"CN",
    "name:zho_x_preferred":[
        "\u5408\u798f\u57b8"
    ],
    "wof:name":"Hefuyuan",
    "wof:placetype":"locality"
},
  "geometry": {"coordinates":[113.30624,30.25736],"type":"Point"}
}