{
  "type": "Feature",
  "properties": {
    "gn:admin1_code":"4.0",
    "gn:asciiname":"Banqiaotoudai",
    "gn:country_code":"CN",
    "gn:dem":3,
    "gn:feature_class":"P",
    "gn:feature_code":"PPL",
    "gn:name":"Banqiaotoudai",
    "gn:population":0,
    "gn:timezone":"Asia/Shanghai",
    "iso:country":"CN",
    "name:zho_x_preferred":[
        "\u677f\u6865\u5934\u5788"
    ],
    "wof:name":"Banqiaotoudai",
    "wof:placetype":"locality"
},
  "geometry": {"coordinates":[120.27933,32.06092],"type":"Point"}
}