{
  "type": "Feature",
  "properties": {
    "gn:admin1_code":"13.0",
    "gn:asciiname":"Kax",
    "gn:country_code":"CN",
    "gn:dem":704,
    "gn:feature_class":"P",
    "gn:feature_code":"PPLA4",
    "gn:name":"Kax",
    "gn:population":0,
    "gn:timezone":"Asia/Shanghai",
    "iso:country":"CN",
    "name:uig_x_preferred":[
        "K\u0329ax"
    ],
    "name:uig_x_variant":[
        "Qash",
        "\u0642\u0627\u0634",
        "\u049a\u0430\u0448"
    ],
    "name:und_x_variant":[
        "Kax Xiang",
        "Kax",
        "Kashen",
        "Kashen Xiang"
    ],
    "name:zho_x_preferred":[
        "\u5580\u4ec0"
    ],
    "name:zho_x_variant":[
        "\u5580\u4ec0\u4e61"
    ],
    "wof:name":"Kax",
    "wof:placetype":"locality"
},
  "geometry": {"coordinates":[81.87,43.64111],"type":"Point"}
}