{
  "type": "Feature",
  "properties": {
    "gn:admin1_code":"7",
    "gn:asciiname":"Qian'an",
    "gn:country_code":"CN",
    "gn:dem":173,
    "gn:feature_class":"P",
    "gn:feature_code":"PPL",
    "gn:name":"Qian\u2019an",
    "gn:population":0,
    "gn:timezone":"Asia/Shanghai",
    "iso:country":"CN",
    "name:deu_x_preferred":[
        "Qian\u2019an"
    ],
    "name:fra_x_preferred":[
        "Qian'an"
    ],
    "name:nor_x_preferred":[
        "Qian'an"
    ],
    "name:swe_x_preferred":[
        "Qian'an"
    ],
    "name:und_x_variant":[
        "Qian\u2019an"
    ],
    "name:zho_x_preferred":[
        "\u524d\u5b89"
    ],
    "wof:name":"Qian'an",
    "wof:placetype":"locality"
},
  "geometry": {"coordinates":[119.07167,25.55667],"type":"Point"}
}