{
  "type": "Feature",
  "properties": {
    "gn:admin1_code":"16.0",
    "gn:asciiname":"Dapokan",
    "gn:country_code":"CN",
    "gn:dem":1159,
    "gn:feature_class":"P",
    "gn:feature_code":"PPL",
    "gn:name":"Dapokan",
    "gn:population":0,
    "gn:timezone":"Asia/Shanghai",
    "iso:country":"CN",
    "name:zho_x_preferred":[
        "\u5927\u5761\u574e"
    ],
    "wof:name":"Dapokan",
    "wof:placetype":"locality"
},
  "geometry": {"coordinates":[105.181,24.9228],"type":"Point"}
}