{
  "type": "Feature",
  "properties": {
    "gn:admin1_code":"25",
    "gn:asciiname":"Chiping",
    "gn:cc2":"CN",
    "gn:country_code":"CN",
    "gn:dem":31,
    "gn:feature_class":"P",
    "gn:feature_code":"PPL",
    "gn:name":"Chiping",
    "gn:population":0,
    "gn:timezone":"Asia/Shanghai",
    "iso:country":"CN",
    "name:und_x_variant":[
        "Shin-p\u2019ing",
        "Ch\u2019ih-p\u2019ing",
        "Shih-p\u2019ing",
        "Ch\u2019ih-p\u2019ing-hsien",
        "Chiping"
    ],
    "wof:name":"Chiping",
    "wof:placetype":"locality"
},
  "geometry": {"coordinates":[116.24194,36.59417],"type":"Point"}
}