{
  "type": "Feature",
  "properties": {
    "gn:admin1_code":"4.0",
    "gn:asciiname":"Ma'ancun",
    "gn:country_code":"CN",
    "gn:dem":49,
    "gn:feature_class":"P",
    "gn:feature_code":"PPL",
    "gn:name":"Ma\u2019ancun",
    "gn:population":0,
    "gn:timezone":"Asia/Shanghai",
    "iso:country":"CN",
    "name:und_x_variant":[
        "Ma\u2019ancun"
    ],
    "name:zho_x_preferred":[
        "\u9a6c\u5b89\u6751"
    ],
    "wof:name":"Ma'ancun",
    "wof:placetype":"locality"
},
  "geometry": {"coordinates":[117.40582000000001,34.52935],"type":"Point"}
}