{
  "type": "Feature",
  "properties": {
    "gn:admin1_code":"12.0",
    "gn:asciiname":"Tuanbei",
    "gn:country_code":"CN",
    "gn:dem":67,
    "gn:feature_class":"P",
    "gn:feature_code":"PPLA4",
    "gn:name":"Tuanbei",
    "gn:population":0,
    "gn:timezone":"Asia/Shanghai",
    "iso:country":"CN",
    "name:und_x_variant":[
        "\u56e2\u9642"
    ],
    "name:zho_x_preferred":[
        "Tuanbei Zhen"
    ],
    "name:zho_x_variant":[
        "\u56e2\u9642\u9547"
    ],
    "wof:name":"Tuanbei",
    "wof:placetype":"locality"
},
  "geometry": {"coordinates":[115.22768000000001,30.72869],"type":"Point"}
}