{
  "type": "Feature",
  "properties": {
    "gn:admin1_code":"26.0",
    "gn:asciiname":"Lianfengcun",
    "gn:country_code":"CN",
    "gn:dem":326,
    "gn:feature_class":"P",
    "gn:feature_code":"PPL",
    "gn:name":"Lianfengcun",
    "gn:population":0,
    "gn:timezone":"Asia/Shanghai",
    "iso:country":"CN",
    "name:zho_x_preferred":[
        "\u8054\u4e30\u6751"
    ],
    "wof:name":"Lianfengcun",
    "wof:placetype":"locality"
},
  "geometry": {"coordinates":[108.59936,32.46258],"type":"Point"}
}