{
  "type": "Feature",
  "properties": {
    "gn:admin1_code":"2.0",
    "gn:asciiname":"Shabuye",
    "gn:country_code":"CN",
    "gn:dem":597,
    "gn:feature_class":"P",
    "gn:feature_code":"PPL",
    "gn:name":"Shabuye",
    "gn:population":0,
    "gn:timezone":"Asia/Shanghai",
    "iso:country":"CN",
    "name:zho_x_preferred":[
        "\u6c99\u57e0\u53f6"
    ],
    "wof:name":"Shabuye",
    "wof:placetype":"locality"
},
  "geometry": {"coordinates":[120.03694,27.43754],"type":"Point"}
}