{
  "type": "Feature",
  "properties": {
    "gn:admin1_code":"1.0",
    "gn:asciiname":"Songwancun",
    "gn:country_code":"CN",
    "gn:dem":60,
    "gn:feature_class":"P",
    "gn:feature_code":"PPL",
    "gn:name":"Songwancun",
    "gn:population":0,
    "gn:timezone":"Asia/Shanghai",
    "iso:country":"CN",
    "name:zho_x_preferred":[
        "\u677e\u6e7e\u6751"
    ],
    "wof:name":"Songwancun",
    "wof:placetype":"locality"
},
  "geometry": {"coordinates":[116.63397000000001,31.42869],"type":"Point"}
}