{
  "type": "Feature",
  "properties": {
    "gn:admin1_code":"1.0",
    "gn:asciiname":"Chendu Nongchangcun",
    "gn:country_code":"CN",
    "gn:dem":23,
    "gn:feature_class":"P",
    "gn:feature_code":"PPLF",
    "gn:name":"Chendu Nongchangcun",
    "gn:population":0,
    "gn:timezone":"Asia/Shanghai",
    "iso:country":"CN",
    "name:zho_x_preferred":[
        "\u9648\u6e21\u519c\u573a\u6751"
    ],
    "wof:name":"Chendu Nongchangcun",
    "wof:placetype":"locality"
},
  "geometry": {"coordinates":[117.46804,33.13056],"type":"Point"}
}