{
  "type": "Feature",
  "properties": {
    "gn:admin1_code":"7.0",
    "gn:asciiname":"Honghu",
    "gn:country_code":"CN",
    "gn:dem":336,
    "gn:feature_class":"P",
    "gn:feature_code":"PPL",
    "gn:name":"Honghu",
    "gn:population":0,
    "gn:timezone":"Asia/Shanghai",
    "iso:country":"CN",
    "name:und_x_variant":[
        "\u7ea2\u6e56"
    ],
    "name:zho_x_preferred":[
        "\u7ea2\u6e56"
    ],
    "wof:name":"Honghu",
    "wof:placetype":"locality"
},
  "geometry": {"coordinates":[116.35635000000001,25.86874],"type":"Point"}
}