{
  "type": "Feature",
  "properties": {
    "gn:admin1_code":"32.0",
    "gn:asciiname":"Liangshui",
    "gn:country_code":"CN",
    "gn:dem":422,
    "gn:feature_class":"P",
    "gn:feature_code":"PPL",
    "gn:name":"Liangshui",
    "gn:population":0,
    "gn:timezone":"Asia/Shanghai",
    "iso:country":"CN",
    "name:zho_x_preferred":[
        "\u51c9\u6c34"
    ],
    "wof:name":"Liangshui",
    "wof:placetype":"locality"
},
  "geometry": {"coordinates":[104.86199999999999,30.2609],"type":"Point"}
}