{
  "type": "Feature",
  "properties": {
    "gn:admin1_code":"19.0",
    "gn:asciiname":"Mojiacun",
    "gn:country_code":"CN",
    "gn:dem":37,
    "gn:feature_class":"P",
    "gn:feature_code":"PPL",
    "gn:name":"Mojiacun",
    "gn:population":0,
    "gn:timezone":"Asia/Shanghai",
    "iso:country":"CN",
    "name:zho_x_preferred":[
        "\u8c1f\u5bb6\u6751"
    ],
    "wof:name":"Mojiacun",
    "wof:placetype":"locality"
},
  "geometry": {"coordinates":[123.295,41.7157],"type":"Point"}
}