{
  "type": "Feature",
  "properties": {
    "gn:admin1_code":"07",
    "gn:asciiname":"Qingtan",
    "gn:country_code":"CN",
    "gn:dem":445,
    "gn:feature_class":"P",
    "gn:feature_code":"PPL",
    "gn:name":"Qingtan",
    "gn:population":0,
    "gn:timezone":"Asia/Shanghai",
    "iso:country":"CN",
    "name:ast_x_preferred":[
        "Qingtan"
    ],
    "name:deu_x_preferred":[
        "Qingtan"
    ],
    "name:fra_x_preferred":[
        "Qingtan"
    ],
    "name:nor_x_preferred":[
        "Qingtan"
    ],
    "name:pol_x_preferred":[
        "Qingtan"
    ],
    "name:spa_x_preferred":[
        "Qingtan"
    ],
    "name:swe_x_preferred":[
        "Qingtan"
    ],
    "name:zho_x_preferred":[
        "\u9752\u6f6d"
    ],
    "wof:name":"Qingtan",
    "wof:placetype":"locality"
},
  "geometry": {"coordinates":[117.38533,25.40161],"type":"Point"}
}