{
  "type": "Feature",
  "properties": {
    "gn:admin1_code":"26.0",
    "gn:asciiname":"Huoshenmiao",
    "gn:country_code":"CN",
    "gn:dem":541,
    "gn:feature_class":"P",
    "gn:feature_code":"PPL",
    "gn:name":"Huoshenmiao",
    "gn:population":0,
    "gn:timezone":"Asia/Shanghai",
    "iso:country":"CN",
    "name:zho_x_preferred":[
        "\u706b\u795e\u5e99"
    ],
    "wof:name":"Huoshenmiao",
    "wof:placetype":"locality"
},
  "geometry": {"coordinates":[109.92681,32.73795],"type":"Point"}
}