{
  "type": "Feature",
  "properties": {
    "gn:admin1_code":"28",
    "gn:asciiname":"Huanghuadian",
    "gn:cc2":"CN",
    "gn:country_code":"CN",
    "gn:dem":13,
    "gn:feature_class":"P",
    "gn:feature_code":"PPL",
    "gn:name":"Huanghuadian",
    "gn:population":0,
    "gn:timezone":"Asia/Shanghai",
    "iso:country":"CN",
    "name:und_x_variant":[
        "Huang-hua-tien",
        "Huang-hou-tien-chen",
        "Huang-hou-tien",
        "Huanghuadian"
    ],
    "wof:name":"Huanghuadian",
    "wof:placetype":"locality"
},
  "geometry": {"coordinates":[116.89111,39.365],"type":"Point"}
}