{
  "type": "Feature",
  "properties": {
    "gn:admin1_code":"30.0",
    "gn:asciiname":"Xizeng",
    "gn:country_code":"CN",
    "gn:dem":652,
    "gn:feature_class":"P",
    "gn:feature_code":"PPL",
    "gn:name":"Xizeng",
    "gn:population":0,
    "gn:timezone":"Asia/Shanghai",
    "iso:country":"CN",
    "name:zho_x_preferred":[
        "Xizeng"
    ],
    "name:zho_x_variant":[
        "\u7ec6\u66fe"
    ],
    "wof:name":"Xizeng",
    "wof:placetype":"locality"
},
  "geometry": {"coordinates":[113.14812000000001,24.52744],"type":"Point"}
}