{
  "type": "Feature",
  "properties": {
    "gn:admin1_code":"18",
    "gn:asciiname":"Panjiashan",
    "gn:country_code":"CN",
    "gn:dem":834,
    "gn:feature_class":"P",
    "gn:feature_code":"PPL",
    "gn:name":"Panjiashan",
    "gn:population":0,
    "gn:timezone":"Asia/Shanghai",
    "iso:country":"CN",
    "name:zho_x_preferred":[
        "\u6f58\u5bb6\u5c71"
    ],
    "wof:name":"Panjiashan",
    "wof:placetype":"locality"
},
  "geometry": {"coordinates":[107.59399999999999,27.4103],"type":"Point"}
}