{
  "type": "Feature",
  "properties": {
    "gn:admin1_code":"16.0",
    "gn:asciiname":"Mayao",
    "gn:country_code":"CN",
    "gn:dem":567,
    "gn:feature_class":"P",
    "gn:feature_code":"PPL",
    "gn:name":"Mayao",
    "gn:population":0,
    "gn:timezone":"Asia/Shanghai",
    "iso:country":"CN",
    "name:zho_x_preferred":[
        "\u9a6c\u8170"
    ],
    "wof:name":"Mayao",
    "wof:placetype":"locality"
},
  "geometry": {"coordinates":[107.575,24.5825],"type":"Point"}
}