{
  "type": "Feature",
  "properties": {
    "gn:admin1_code":"32.0",
    "gn:asciiname":"Pujia Huofang",
    "gn:country_code":"CN",
    "gn:dem":2407,
    "gn:feature_class":"P",
    "gn:feature_code":"PPL",
    "gn:name":"Pujia Huofang",
    "gn:population":0,
    "gn:timezone":"Asia/Shanghai",
    "iso:country":"CN",
    "name:zho_x_preferred":[
        "\u6d66\u5bb6\u706b\u623f"
    ],
    "wof:name":"Pujia Huofang",
    "wof:placetype":"locality"
},
  "geometry": {"coordinates":[102.85899999999999,26.6982],"type":"Point"}
}