{
  "type": "Feature",
  "properties": {
    "gn:admin1_code":"8.0",
    "gn:asciiname":"Xinfuyaotun",
    "gn:country_code":"CN",
    "gn:dem":184,
    "gn:feature_class":"P",
    "gn:feature_code":"PPL",
    "gn:name":"Xinfuyaotun",
    "gn:population":0,
    "gn:timezone":"Asia/Shanghai",
    "iso:country":"CN",
    "name:zho_x_preferred":[
        "\u65b0\u798f\u8170\u5c6f"
    ],
    "wof:name":"Xinfuyaotun",
    "wof:placetype":"locality"
},
  "geometry": {"coordinates":[127.84963999999999,46.45149],"type":"Point"}
}