{
  "type": "Feature",
  "properties": {
    "gn:admin1_code":"1.0",
    "gn:asciiname":"Langcun",
    "gn:country_code":"CN",
    "gn:dem":109,
    "gn:feature_class":"P",
    "gn:feature_code":"PPL",
    "gn:name":"Langcun",
    "gn:population":0,
    "gn:timezone":"Asia/Shanghai",
    "iso:country":"CN",
    "name:zho_x_preferred":[
        "Langcun"
    ],
    "name:zho_x_variant":[
        "\u90ce\u6751"
    ],
    "wof:name":"Langcun",
    "wof:placetype":"locality"
},
  "geometry": {"coordinates":[119.40588,30.82196],"type":"Point"}
}