{
  "type": "Feature",
  "properties": {
    "gn:admin1_code":"30.0",
    "gn:asciiname":"Guiling",
    "gn:country_code":"CN",
    "gn:dem":56,
    "gn:feature_class":"P",
    "gn:feature_code":"PPL",
    "gn:name":"Guiling",
    "gn:population":0,
    "gn:timezone":"Asia/Shanghai",
    "iso:country":"CN",
    "name:zho_x_preferred":[
        "Guiling"
    ],
    "name:zho_x_variant":[
        "\u6842\u5cad"
    ],
    "wof:name":"Guiling",
    "wof:placetype":"locality"
},
  "geometry": {"coordinates":[112.89778,23.94278],"type":"Point"}
}