{
  "type": "Feature",
  "properties": {
    "gn:admin1_code":"8.0",
    "gn:asciiname":"Zengchancun",
    "gn:country_code":"CN",
    "gn:dem":161,
    "gn:feature_class":"P",
    "gn:feature_code":"PPL",
    "gn:name":"Zengchancun",
    "gn:population":0,
    "gn:timezone":"Asia/Shanghai",
    "iso:country":"CN",
    "name:zho_x_preferred":[
        "\u589e\u4ea7\u6751"
    ],
    "wof:name":"Zengchancun",
    "wof:placetype":"locality"
},
  "geometry": {"coordinates":[125.46952,46.63395],"type":"Point"}
}