{
  "type": "Feature",
  "properties": {
    "gn:admin1_code":"3.0",
    "gn:asciiname":"Woli",
    "gn:country_code":"CN",
    "gn:dem":72,
    "gn:feature_class":"P",
    "gn:feature_code":"PPL",
    "gn:name":"Woli",
    "gn:population":0,
    "gn:timezone":"Asia/Shanghai",
    "iso:country":"CN",
    "name:und_x_variant":[
        "\u7a9d\u91cc"
    ],
    "wof:name":"Woli",
    "wof:placetype":"locality"
},
  "geometry": {"coordinates":[116.68084,27.47965],"type":"Point"}
}