{
  "type": "Feature",
  "properties": {
    "gn:admin1_code":"26.0",
    "gn:asciiname":"Ganxigou",
    "gn:country_code":"CN",
    "gn:dem":1008,
    "gn:feature_class":"P",
    "gn:feature_code":"PPL",
    "gn:name":"Ganxigou",
    "gn:population":0,
    "gn:timezone":"Asia/Shanghai",
    "iso:country":"CN",
    "name:und_x_variant":[
        "\u5e72\u6eaa\u6c9f"
    ],
    "wof:name":"Ganxigou",
    "wof:placetype":"locality"
},
  "geometry": {"coordinates":[106.28609,32.99062],"type":"Point"}
}