{
  "type": "Feature",
  "properties": {
    "gn:admin1_code":"14.0",
    "gn:asciiname":"Bangqian",
    "gn:country_code":"CN",
    "gn:dem":4845,
    "gn:feature_class":"P",
    "gn:feature_code":"PPL",
    "gn:name":"Bangqian",
    "gn:population":0,
    "gn:timezone":"Asia/Urumqi",
    "iso:country":"CN",
    "name:zho_x_preferred":[
        "\u5e2e\u8fc1"
    ],
    "wof:name":"Bangqian",
    "wof:placetype":"locality"
},
  "geometry": {"coordinates":[87.42,30.9032],"type":"Point"}
}