{
  "type": "Feature",
  "properties": {
    "gn:admin1_code":"7.0",
    "gn:asciiname":"Longtou",
    "gn:country_code":"CN",
    "gn:dem":500,
    "gn:feature_class":"P",
    "gn:feature_code":"PPL",
    "gn:name":"Longtou",
    "gn:population":0,
    "gn:timezone":"Asia/Shanghai",
    "iso:country":"CN",
    "name:und_x_variant":[
        "\u9647\u5934"
    ],
    "name:zho_x_preferred":[
        "\u9647\u5934"
    ],
    "wof:name":"Longtou",
    "wof:placetype":"locality"
},
  "geometry": {"coordinates":[118.11962,26.44312],"type":"Point"}
}