{
  "type": "Feature",
  "properties": {
    "gn:admin1_code":"20.0",
    "gn:asciiname":"Qingshuihe",
    "gn:country_code":"CN",
    "gn:dem":1628,
    "gn:feature_class":"P",
    "gn:feature_code":"PPL",
    "gn:name":"Qingshuihe",
    "gn:population":0,
    "gn:timezone":"Asia/Shanghai",
    "iso:country":"CN",
    "name:und_x_variant":[
        "\u6e05\u6c34\u6cb3"
    ],
    "wof:name":"Qingshuihe",
    "wof:placetype":"locality"
},
  "geometry": {"coordinates":[111.60184,41.1186],"type":"Point"}
}