{
  "type": "Feature",
  "properties": {
    "gn:admin1_code":"1.0",
    "gn:asciiname":"Haoxucun",
    "gn:country_code":"CN",
    "gn:dem":29,
    "gn:feature_class":"P",
    "gn:feature_code":"PPL",
    "gn:name":"Haoxucun",
    "gn:population":0,
    "gn:timezone":"Asia/Shanghai",
    "iso:country":"CN",
    "name:und_x_variant":[
        "Haoxu"
    ],
    "name:zho_x_preferred":[
        "\u90dd\u5729\u6751"
    ],
    "wof:name":"Haoxucun",
    "wof:placetype":"locality"
},
  "geometry": {"coordinates":[116.75845,32.63974],"type":"Point"}
}