{
  "type": "Feature",
  "properties": {
    "gn:admin1_code":"30.0",
    "gn:asciiname":"Liangjia",
    "gn:country_code":"CN",
    "gn:dem":257,
    "gn:feature_class":"P",
    "gn:feature_code":"PPL",
    "gn:name":"Liangjia",
    "gn:population":0,
    "gn:timezone":"Asia/Shanghai",
    "iso:country":"CN",
    "name:zho_x_preferred":[
        "Liangjia"
    ],
    "name:zho_x_variant":[
        "\u6881\u5bb6",
        "\u6881\u5bb6\u9547"
    ],
    "wof:name":"Liangjia",
    "wof:placetype":"locality"
},
  "geometry": {"coordinates":[112.29277999999999,25.06972],"type":"Point"}
}