{
  "type": "Feature",
  "properties": {
    "gn:admin1_code":"19.0",
    "gn:asciiname":"Dalitun",
    "gn:country_code":"CN",
    "gn:dem":22,
    "gn:feature_class":"P",
    "gn:feature_code":"PPL",
    "gn:name":"Dalitun",
    "gn:population":0,
    "gn:timezone":"Asia/Shanghai",
    "iso:country":"CN",
    "name:und_x_variant":[
        "\u5927\u674e\u5c6f"
    ],
    "name:zho_x_preferred":[
        "\u5927\u674e\u5c6f"
    ],
    "wof:name":"Dalitun",
    "wof:placetype":"locality"
},
  "geometry": {"coordinates":[122.75951999999999,39.64042],"type":"Point"}
}