{
  "type": "Feature",
  "properties": {
    "gn:admin1_code":"3.0",
    "gn:asciiname":"Jiangjia",
    "gn:country_code":"CN",
    "gn:dem":52,
    "gn:feature_class":"P",
    "gn:feature_code":"PPL",
    "gn:name":"Jiangjia",
    "gn:population":0,
    "gn:timezone":"Asia/Shanghai",
    "iso:country":"CN",
    "name:zho_x_preferred":[
        "\u848b\u5bb6"
    ],
    "wof:name":"Jiangjia",
    "wof:placetype":"locality"
},
  "geometry": {"coordinates":[117.4713,28.72424],"type":"Point"}
}