{
  "type": "Feature",
  "properties": {
    "gn:admin1_code":"29.0",
    "gn:asciiname":"Shidemu",
    "gn:country_code":"CN",
    "gn:dem":1715,
    "gn:feature_class":"P",
    "gn:feature_code":"PPL",
    "gn:name":"Shidemu",
    "gn:population":0,
    "gn:timezone":"Asia/Shanghai",
    "iso:country":"CN",
    "name:zho_x_preferred":[
        "\u77f3\u5f97\u6728"
    ],
    "wof:name":"Shidemu",
    "wof:placetype":"locality"
},
  "geometry": {"coordinates":[98.8516,26.9554],"type":"Point"}
}