{
  "type": "Feature",
  "properties": {
    "gn:admin1_code":"13.0",
    "gn:asciiname":"Aykol",
    "gn:country_code":"CN",
    "gn:dem":1075,
    "gn:feature_class":"P",
    "gn:feature_code":"PPL",
    "gn:name":"Aykol",
    "gn:population":11260,
    "gn:timezone":"Asia/Shanghai",
    "iso:country":"CN",
    "name:ceb_x_preferred":[
        "Aykol"
    ],
    "name:fas_x_preferred":[
        "\u0627\u06cc\u06a9\u0648\u0644"
    ],
    "name:mlg_x_preferred":[
        "Aykol"
    ],
    "name:swe_x_preferred":[
        "Aykol"
    ],
    "name:uig_x_preferred":[
        "Ayk\u0275l"
    ],
    "name:uig_x_variant":[
        "Ayk\u00f6l",
        "\u0626\u0627\u064a\u0643\u06c6\u0644",
        "\u0410\u0439\u043a\u04e9\u043b",
        "\u0626\u0627\u064a\u0643\u06c6\u0644 \u064a\u06d0\u0632\u0649\u0633\u0649"
    ],
    "name:und_x_variant":[
        "A-yin-k\u2019o",
        "Aykol"
    ],
    "name:zho_x_preferred":[
        "\u963f\u4f9d\u5e93\u52d2\u4e61"
    ],
    "wof:name":"Aykol",
    "wof:placetype":"locality",
    "wof:population":11260
},
  "geometry": {"coordinates":[80.13574,40.95759],"type":"Point"}
}