{
  "type": "Feature",
  "properties": {
    "gn:admin1_code":"1.0",
    "gn:asciiname":"Ranzhoucun",
    "gn:country_code":"CN",
    "gn:dem":34,
    "gn:feature_class":"P",
    "gn:feature_code":"PPL",
    "gn:name":"Ranzhoucun",
    "gn:population":0,
    "gn:timezone":"Asia/Shanghai",
    "iso:country":"CN",
    "name:zho_x_preferred":[
        "\u5189\u5468\u6751"
    ],
    "wof:name":"Ranzhoucun",
    "wof:placetype":"locality"
},
  "geometry": {"coordinates":[117.89205,32.38693],"type":"Point"}
}