{
  "type": "Feature",
  "properties": {
    "gn:admin1_code":"18",
    "gn:asciiname":"Zimuzhuang",
    "gn:country_code":"CN",
    "gn:dem":1063,
    "gn:feature_class":"P",
    "gn:feature_code":"PPL",
    "gn:name":"Zimuzhuang",
    "gn:population":0,
    "gn:timezone":"Asia/Shanghai",
    "iso:country":"CN",
    "name:zho_x_preferred":[
        "\u6893\u6728\u5e84"
    ],
    "wof:name":"Zimuzhuang",
    "wof:placetype":"locality"
},
  "geometry": {"coordinates":[107.07899999999999,26.3169],"type":"Point"}
}