{
  "type": "Feature",
  "properties": {
    "gn:admin1_code":"4.0",
    "gn:asciiname":"Dongtianqimiao",
    "gn:country_code":"CN",
    "gn:dem":35,
    "gn:feature_class":"P",
    "gn:feature_code":"PPL",
    "gn:name":"Dongtianqimiao",
    "gn:population":0,
    "gn:timezone":"Asia/Shanghai",
    "iso:country":"CN",
    "name:zho_x_preferred":[
        "\u4e1c\u5929\u9f50\u5e99"
    ],
    "wof:name":"Dongtianqimiao",
    "wof:placetype":"locality"
},
  "geometry": {"coordinates":[117.155,34.3139],"type":"Point"}
}