{
  "type": "Feature",
  "properties": {
    "gn:admin1_code":"19.0",
    "gn:asciiname":"Xiaobiangou",
    "gn:country_code":"CN",
    "gn:dem":335,
    "gn:feature_class":"P",
    "gn:feature_code":"PPL",
    "gn:name":"Xiaobiangou",
    "gn:population":0,
    "gn:timezone":"Asia/Shanghai",
    "iso:country":"CN",
    "name:und_x_variant":[
        "\u5c0f\u8fb9\u6c9f"
    ],
    "wof:name":"Xiaobiangou",
    "wof:placetype":"locality"
},
  "geometry": {"coordinates":[124.54194,41.02294000000001],"type":"Point"}
}