{
  "type": "Feature",
  "properties": {
    "gn:admin1_code":"10",
    "gn:asciiname":"Hezhangzi",
    "gn:country_code":"CN",
    "gn:dem":603,
    "gn:feature_class":"P",
    "gn:feature_code":"PPL",
    "gn:name":"Hezhangzi",
    "gn:population":0,
    "gn:timezone":"Asia/Shanghai",
    "iso:country":"CN",
    "name:zho_x_preferred":[
        "\u4f55\u6756\u5b50"
    ],
    "wof:name":"Hezhangzi",
    "wof:placetype":"locality"
},
  "geometry": {"coordinates":[118.71720999999999,40.97618],"type":"Point"}
}