{
  "type": "Feature",
  "properties": {
    "gn:admin1_code":"5.0",
    "gn:asciiname":"Niuxin Dingzi",
    "gn:country_code":"CN",
    "gn:dem":256,
    "gn:feature_class":"P",
    "gn:feature_code":"PPL",
    "gn:name":"Niuxin Dingzi",
    "gn:population":0,
    "gn:timezone":"Asia/Shanghai",
    "iso:country":"CN",
    "name:zho_x_preferred":[
        "\u725b\u5fc3\u9876\u5b50"
    ],
    "wof:name":"Niuxin Dingzi",
    "wof:placetype":"locality"
},
  "geometry": {"coordinates":[127.30415000000001,44.50194000000001],"type":"Point"}
}