{
  "type": "Feature",
  "properties": {
    "gn:admin1_code":"5.0",
    "gn:asciiname":"Changchuancun",
    "gn:country_code":"CN",
    "gn:dem":201,
    "gn:feature_class":"P",
    "gn:feature_code":"PPL",
    "gn:name":"Changchuancun",
    "gn:population":0,
    "gn:timezone":"Asia/Shanghai",
    "iso:country":"CN",
    "name:zho_x_preferred":[
        "\u957f\u5ddd\u6751"
    ],
    "wof:name":"Changchuancun",
    "wof:placetype":"locality"
},
  "geometry": {"coordinates":[126.3382,41.24198],"type":"Point"}
}