{
  "type": "Feature",
  "properties": {
    "gn:admin1_code":"7",
    "gn:asciiname":"Xiapu",
    "gn:country_code":"CN",
    "gn:dem":37,
    "gn:feature_class":"P",
    "gn:feature_code":"PPL",
    "gn:name":"Xiapu",
    "gn:population":0,
    "gn:timezone":"Asia/Shanghai",
    "iso:country":"CN",
    "name:zho_x_preferred":[
        "\u4e0b\u57d4"
    ],
    "wof:name":"Xiapu",
    "wof:placetype":"locality"
},
  "geometry": {"coordinates":[117.04968999999998,23.77217000000001],"type":"Point"}
}