{
  "type": "Feature",
  "properties": {
    "gn:admin1_code":"32.0",
    "gn:asciiname":"Xixiang",
    "gn:country_code":"CN",
    "gn:dem":1520,
    "gn:feature_class":"P",
    "gn:feature_code":"PPL",
    "gn:name":"Xixiang",
    "gn:population":0,
    "gn:timezone":"Asia/Shanghai",
    "iso:country":"CN",
    "name:zho_x_preferred":[
        "\u897f\u4e61"
    ],
    "wof:name":"Xixiang",
    "wof:placetype":"locality"
},
  "geometry": {"coordinates":[102.19638999999999,27.93594],"type":"Point"}
}