{
  "type": "Feature",
  "properties": {
    "gn:admin1_code":"2.0",
    "gn:asciiname":"Shuang'ao",
    "gn:country_code":"CN",
    "gn:dem":132,
    "gn:feature_class":"P",
    "gn:feature_code":"PPL",
    "gn:name":"Shuang\u2019ao",
    "gn:population":0,
    "gn:timezone":"Asia/Shanghai",
    "iso:country":"CN",
    "name:und_x_variant":[
        "Shuang\u2019ao"
    ],
    "name:zho_x_preferred":[
        "\u53cc\u5c99"
    ],
    "wof:name":"Shuang'ao",
    "wof:placetype":"locality"
},
  "geometry": {"coordinates":[119.58784,29.79266],"type":"Point"}
}