{
  "type": "Feature",
  "properties": {
    "gn:admin1_code":"26.0",
    "gn:asciiname":"Heigouhe",
    "gn:country_code":"CN",
    "gn:dem":964,
    "gn:feature_class":"P",
    "gn:feature_code":"PPL",
    "gn:name":"Heigouhe",
    "gn:population":0,
    "gn:timezone":"Asia/Shanghai",
    "iso:country":"CN",
    "name:und_x_variant":[
        "\u9ed1\u6c9f\u6cb3"
    ],
    "wof:name":"Heigouhe",
    "wof:placetype":"locality"
},
  "geometry": {"coordinates":[107.60911000000002,34.1837],"type":"Point"}
}