{
  "type": "Feature",
  "properties": {
    "gn:admin1_code":"4.0",
    "gn:asciiname":"Shixinzhuang",
    "gn:country_code":"CN",
    "gn:dem":15,
    "gn:feature_class":"P",
    "gn:feature_code":"PPL",
    "gn:name":"Shixinzhuang",
    "gn:population":0,
    "gn:timezone":"Asia/Shanghai",
    "iso:country":"CN",
    "name:zho_x_preferred":[
        "\u53f2\u65b0\u5e84"
    ],
    "wof:name":"Shixinzhuang",
    "wof:placetype":"locality"
},
  "geometry": {"coordinates":[118.63200000000001,33.801],"type":"Point"}
}