{
  "type": "Feature",
  "properties": {
    "gn:admin1_code":"29.0",
    "gn:asciiname":"Bainijing",
    "gn:country_code":"CN",
    "gn:dem":2342,
    "gn:feature_class":"P",
    "gn:feature_code":"PPL",
    "gn:name":"Bainijing",
    "gn:population":0,
    "gn:timezone":"Asia/Shanghai",
    "iso:country":"CN",
    "name:zho_x_preferred":[
        "\u767d\u6ce5\u4e95"
    ],
    "wof:name":"Bainijing",
    "wof:placetype":"locality"
},
  "geometry": {"coordinates":[103.89400000000001,27.5339],"type":"Point"}
}