{
  "type": "Feature",
  "properties": {
    "gn:admin1_code":"11.0",
    "gn:asciiname":"Yanhechang",
    "gn:country_code":"CN",
    "gn:dem":31,
    "gn:feature_class":"P",
    "gn:feature_code":"PPL",
    "gn:name":"Yanhechang",
    "gn:population":0,
    "gn:timezone":"Asia/Shanghai",
    "iso:country":"CN",
    "name:zho_x_preferred":[
        "\u5ca9\u79be\u573a"
    ],
    "wof:name":"Yanhechang",
    "wof:placetype":"locality"
},
  "geometry": {"coordinates":[111.87196000000002,28.86365],"type":"Point"}
}