{
  "type": "Feature",
  "properties": {
    "gn:admin1_code":"16",
    "gn:asciiname":"Taojiaying",
    "gn:country_code":"CN",
    "gn:dem":321,
    "gn:feature_class":"P",
    "gn:feature_code":"PPL",
    "gn:name":"Taojiaying",
    "gn:population":0,
    "gn:timezone":"Asia/Shanghai",
    "iso:country":"CN",
    "name:zho_x_preferred":[
        "\u9676\u5bb6\u8425"
    ],
    "wof:name":"Taojiaying",
    "wof:placetype":"locality"
},
  "geometry": {"coordinates":[110.792,25.4481],"type":"Point"}
}