{
  "type": "Feature",
  "properties": {
    "gn:admin1_code":"1.0",
    "gn:asciiname":"Guazhencun",
    "gn:country_code":"CN",
    "gn:dem":64,
    "gn:feature_class":"P",
    "gn:feature_code":"PPL",
    "gn:name":"Guazhencun",
    "gn:population":0,
    "gn:timezone":"Asia/Shanghai",
    "iso:country":"CN",
    "name:und_x_variant":[
        "Guazhen"
    ],
    "name:zho_x_preferred":[
        "\u6302\u9547\u6751"
    ],
    "wof:name":"Guazhencun",
    "wof:placetype":"locality"
},
  "geometry": {"coordinates":[116.85053000000001,30.99029],"type":"Point"}
}