{
  "type": "Feature",
  "properties": {
    "gn:admin1_code":"29.0",
    "gn:asciiname":"Nikubu Xinzhai",
    "gn:country_code":"CN",
    "gn:dem":1607,
    "gn:feature_class":"P",
    "gn:feature_code":"PPL",
    "gn:name":"Nikubu Xinzhai",
    "gn:population":0,
    "gn:timezone":"Asia/Shanghai",
    "iso:country":"CN",
    "name:zho_x_preferred":[
        "\u5c3c\u67af\u8865\u65b0\u5be8"
    ],
    "wof:name":"Nikubu Xinzhai",
    "wof:placetype":"locality"
},
  "geometry": {"coordinates":[103.093,22.9883],"type":"Point"}
}