{
  "type": "Feature",
  "properties": {
    "gn:admin1_code":"4.0",
    "gn:asciiname":"Zhoubafang",
    "gn:country_code":"CN",
    "gn:dem":3,
    "gn:feature_class":"P",
    "gn:feature_code":"PPL",
    "gn:name":"Zhoubafang",
    "gn:population":0,
    "gn:timezone":"Asia/Shanghai",
    "iso:country":"CN",
    "name:zho_x_preferred":[
        "\u5468\u516b\u623f"
    ],
    "wof:name":"Zhoubafang",
    "wof:placetype":"locality"
},
  "geometry": {"coordinates":[119.63218999999999,32.31667],"type":"Point"}
}