{
  "type": "Feature",
  "properties": {
    "gn:admin1_code":"15.0",
    "gn:asciiname":"Shangzhuangli",
    "gn:country_code":"CN",
    "gn:dem":1894,
    "gn:feature_class":"P",
    "gn:feature_code":"PPL",
    "gn:name":"Shangzhuangli",
    "gn:population":0,
    "gn:timezone":"Asia/Shanghai",
    "iso:country":"CN",
    "name:und_x_variant":[
        "\u4e0a\u5e84\u91cc"
    ],
    "wof:name":"Shangzhuangli",
    "wof:placetype":"locality"
},
  "geometry": {"coordinates":[105.00566000000001,35.10854],"type":"Point"}
}