{
  "type": "Feature",
  "properties": {
    "gn:admin1_code":"12",
    "gn:asciiname":"Gaoleshan",
    "gn:country_code":"CN",
    "gn:dem":739,
    "gn:feature_class":"P",
    "gn:feature_code":"PPLA3",
    "gn:name":"Gaoleshan",
    "gn:population":0,
    "gn:timezone":"Asia/Shanghai",
    "iso:country":"CN",
    "name:und_x_variant":[
        "Sienfenghsien",
        "Xianfeng",
        "Hsien-feng-hsien",
        "Hsien-feng",
        "Gaoleshan Zhen",
        "Gaoleshan",
        "Chengfeng Xian",
        "\u6210\u4e30\u53bf"
    ],
    "name:zho_x_preferred":[
        "\u9ad8\u4e50\u5c71"
    ],
    "name:zho_x_variant":[
        "\u9ad8\u4e50\u5c71\u9547"
    ],
    "wof:name":"Gaoleshan",
    "wof:placetype":"locality"
},
  "geometry": {"coordinates":[109.14453,29.67825],"type":"Point"}
}