{
  "type": "Feature",
  "properties": {
    "gn:admin1_code":"2.0",
    "gn:asciiname":"Danankeng",
    "gn:country_code":"CN",
    "gn:dem":925,
    "gn:feature_class":"P",
    "gn:feature_code":"PPL",
    "gn:name":"Danankeng",
    "gn:population":0,
    "gn:timezone":"Asia/Shanghai",
    "iso:country":"CN",
    "name:zho_x_preferred":[
        "\u5927\u5357\u5751"
    ],
    "wof:name":"Danankeng",
    "wof:placetype":"locality"
},
  "geometry": {"coordinates":[118.95023,28.16002000000001],"type":"Point"}
}