{
  "type": "Feature",
  "properties": {
    "iso:country":"CN",
    "qs:name":"\u4f59\u59da\u5e02",
    "qs:name_adm0":"\u4e2d\u570b",
    "qs:name_adm1":"\u6d59\u6c5f\u7701",
    "qs:photos":2,
    "qs:photos_1k":1,
    "qs:photos_9k":1,
    "qs:photos_9r":3,
    "qs:photos_all":105,
    "qs:photos_sr":1,
    "qs:placetype":"LocalAdmin",
    "qs:pop_sr":"0",
    "wof:name":"\u4f59\u59da\u5e02",
    "wof:placetype":"localadmin"
},
  "geometry": {"coordinates":[121.15070299999999,30.0475],"type":"Point"}
}