{
  "type": "Feature",
  "properties": {
    "gn:admin1_code":"11.0",
    "gn:asciiname":"Fenghuoli",
    "gn:country_code":"CN",
    "gn:dem":403,
    "gn:feature_class":"P",
    "gn:feature_code":"PPL",
    "gn:name":"Fenghuoli",
    "gn:population":0,
    "gn:timezone":"Asia/Shanghai",
    "iso:country":"CN",
    "name:zho_x_preferred":[
        "\u98ce\u6d3b\u91cc"
    ],
    "wof:name":"Fenghuoli",
    "wof:placetype":"locality"
},
  "geometry": {"coordinates":[113.83951999999999,26.6518],"type":"Point"}
}