{
  "type": "Feature",
  "properties": {
    "gn:admin1_code":"16.0",
    "gn:asciiname":"Yuanjiang",
    "gn:country_code":"CN",
    "gn:dem":213,
    "gn:feature_class":"P",
    "gn:feature_code":"PPL",
    "gn:name":"Yuanjiang",
    "gn:population":0,
    "gn:timezone":"Asia/Shanghai",
    "iso:country":"CN",
    "name:zho_x_preferred":[
        "\u5143\u6c5f"
    ],
    "wof:name":"Yuanjiang",
    "wof:placetype":"locality"
},
  "geometry": {"coordinates":[108.429,24.4351],"type":"Point"}
}