{
  "type": "Feature",
  "properties": {
    "gn:admin1_code":"16.0",
    "gn:asciiname":"Yuanjiang",
    "gn:country_code":"CN",
    "gn:dem":213,
    "gn:feature_class":"P",
    "gn:feature_code":"PPL",
    "gn:name":"Yuanjiang",
    "gn:population":0,
    "gn:timezone":"Asia/Shanghai",
    "iso:country":"CN",
    "name:ceb_x_preferred":[
        "Yuanjiang Shi"
    ],
    "name:deu_x_preferred":[
        "Yuanjiang"
    ],
    "name:fra_x_preferred":[
        "Yuanjiang"
    ],
    "name:hak_x_preferred":[
        "Ngi\u00ean-k\u00f4ng-s\u1e73"
    ],
    "name:ita_x_preferred":[
        "Yuanjiang"
    ],
    "name:jpn_x_preferred":[
        "\u30b2\u30f3\u6c5f\u5e02"
    ],
    "name:kik_x_preferred":[
        "Yuanjiang"
    ],
    "name:kor_x_preferred":[
        "\uc704\uc548\uc7a5\uc2dc"
    ],
    "name:nor_x_preferred":[
        "Yuanjiang"
    ],
    "name:pam_x_preferred":[
        "Yuanjiang"
    ],
    "name:swe_x_preferred":[
        "Yuanjiang"
    ],
    "name:vie_x_preferred":[
        "Nguy\u00ean Giang"
    ],
    "name:war_x_preferred":[
        "Yuanjiang"
    ],
    "name:zho_x_preferred":[
        "\u5143\u6c5f"
    ],
    "name:zho_x_variant":[
        "\u6c85\u6c5f\u5e02"
    ],
    "wof:name":"Yuanjiang",
    "wof:placetype":"locality"
},
  "geometry": {"coordinates":[108.429,24.4351],"type":"Point"}
}