{
  "type": "Feature",
  "properties": {
    "gn:admin1_code":"1.0",
    "gn:asciiname":"Qiutangcun",
    "gn:country_code":"CN",
    "gn:dem":43,
    "gn:feature_class":"P",
    "gn:feature_code":"PPL",
    "gn:name":"Qiutangcun",
    "gn:population":0,
    "gn:timezone":"Asia/Shanghai",
    "iso:country":"CN",
    "name:zho_x_preferred":[
        "\u90b1\u5858\u6751"
    ],
    "wof:name":"Qiutangcun",
    "wof:placetype":"locality"
},
  "geometry": {"coordinates":[117.9935,33.08558],"type":"Point"}
}