{
  "type": "Feature",
  "properties": {
    "gn:admin1_code":"29.0",
    "gn:asciiname":"Da'aozi",
    "gn:country_code":"CN",
    "gn:dem":2217,
    "gn:feature_class":"P",
    "gn:feature_code":"PPL",
    "gn:name":"Da\u2019aozi",
    "gn:population":0,
    "gn:timezone":"Asia/Shanghai",
    "iso:country":"CN",
    "name:und_x_variant":[
        "Da\u2019aozi"
    ],
    "name:zho_x_preferred":[
        "\u5927\u51f9\u5b50"
    ],
    "wof:name":"Da'aozi",
    "wof:placetype":"locality"
},
  "geometry": {"coordinates":[100.303,24.4252],"type":"Point"}
}