{
  "type": "Feature",
  "properties": {
    "gn:admin1_code":"25",
    "gn:asciiname":"Tiefoxi",
    "gn:country_code":"CN",
    "gn:dem":49,
    "gn:feature_class":"P",
    "gn:feature_code":"PPL",
    "gn:name":"Tiefoxi",
    "gn:population":0,
    "gn:timezone":"Asia/Shanghai",
    "iso:country":"CN",
    "name:zho_x_preferred":[
        "\u94c1\u4f5b\u897f"
    ],
    "wof:name":"Tiefoxi",
    "wof:placetype":"locality"
},
  "geometry": {"coordinates":[117.41800000000001,34.6532],"type":"Point"}
}