{
  "type": "Feature",
  "properties": {
    "gn:admin1_code":"12.0",
    "gn:asciiname":"Shangxigou",
    "gn:country_code":"CN",
    "gn:dem":313,
    "gn:feature_class":"P",
    "gn:feature_code":"PPL",
    "gn:name":"Shangxigou",
    "gn:population":0,
    "gn:timezone":"Asia/Shanghai",
    "iso:country":"CN",
    "name:zho_x_preferred":[
        "\u4e0a\u897f\u6c9f"
    ],
    "wof:name":"Shangxigou",
    "wof:placetype":"locality"
},
  "geometry": {"coordinates":[113.44803,32.20185],"type":"Point"}
}