{
  "type": "Feature",
  "properties": {
    "gn:admin1_code":"4.0",
    "gn:asciiname":"Jinhaicun",
    "gn:country_code":"CN",
    "gn:dem":-3,
    "gn:feature_class":"P",
    "gn:feature_code":"PPL",
    "gn:name":"Jinhaicun",
    "gn:population":0,
    "gn:timezone":"Asia/Shanghai",
    "iso:country":"CN",
    "name:zho_x_preferred":[
        "\u91d1\u6d77\u6751"
    ],
    "wof:name":"Jinhaicun",
    "wof:placetype":"locality"
},
  "geometry": {"coordinates":[120.32532,34.01813],"type":"Point"}
}