{
  "type": "Feature",
  "properties": {
    "gn:admin1_code":"16",
    "gn:asciiname":"Liuli",
    "gn:country_code":"CN",
    "gn:dem":158,
    "gn:feature_class":"P",
    "gn:feature_code":"PPL",
    "gn:name":"Liuli",
    "gn:population":0,
    "gn:timezone":"Asia/Shanghai",
    "iso:country":"CN",
    "name:zho_x_preferred":[
        "\u69b4\u5229"
    ],
    "wof:name":"Liuli",
    "wof:placetype":"locality"
},
  "geometry": {"coordinates":[106.965,22.0938],"type":"Point"}
}