{
  "type": "Feature",
  "properties": {
    "gn:admin1_code":"24",
    "gn:asciiname":"Moli",
    "gn:cc2":"CN",
    "gn:country_code":"CN",
    "gn:dem":753,
    "gn:feature_class":"P",
    "gn:feature_code":"PPL",
    "gn:name":"Moli",
    "gn:population":0,
    "gn:timezone":"Asia/Shanghai",
    "iso:country":"CN",
    "name:bih_x_preferred":[
        "\u092e\u094b\u0932\u0940"
    ],
    "name:ceb_x_preferred":[
        "Moli"
    ],
    "name:fra_x_preferred":[
        "Moli"
    ],
    "name:hin_x_preferred":[
        "\u092e\u094b\u0932\u0940"
    ],
    "name:mai_x_preferred":[
        "\u092e\u094b\u0932\u0940"
    ],
    "name:msa_x_preferred":[
        "Moli"
    ],
    "name:nep_x_preferred":[
        "\u092e\u094b\u0932\u0940"
    ],
    "name:new_x_preferred":[
        "\u092e\u094b\u0932\u0940"
    ],
    "name:pol_x_preferred":[
        "Moli"
    ],
    "name:und_x_variant":[
        "Mo-li-ts\u2019un"
    ],
    "wof:name":"Moli",
    "wof:placetype":"locality"
},
  "geometry": {"coordinates":[111.69,35.52472],"type":"Point"}
}