{
  "type": "Feature",
  "properties": {
    "gn:admin1_code":"24",
    "gn:asciiname":"Moli",
    "gn:cc2":"CN",
    "gn:country_code":"CN",
    "gn:dem":753,
    "gn:feature_class":"P",
    "gn:feature_code":"PPL",
    "gn:name":"Moli",
    "gn:population":0,
    "gn:timezone":"Asia/Shanghai",
    "iso:country":"CN",
    "name:und_x_variant":[
        "Mo-li-ts\u2019un",
        "Moli"
    ],
    "wof:name":"Moli",
    "wof:placetype":"locality"
},
  "geometry": {"coordinates":[111.69,35.52472],"type":"Point"}
}