{
  "type": "Feature",
  "properties": {
    "gn:admin1_code":"02",
    "gn:asciiname":"Shangfucun",
    "gn:country_code":"CN",
    "gn:dem":10,
    "gn:feature_class":"P",
    "gn:feature_code":"PPL",
    "gn:name":"Shangfucun",
    "gn:population":0,
    "gn:timezone":"Asia/Shanghai",
    "iso:country":"CN",
    "name:und_x_variant":[
        "Shang-p\u2019u-hsiang",
        "Shangfu",
        "Shangfucun"
    ],
    "name:zho_x_preferred":[
        "\u4e0a\u5085"
    ],
    "name:zho_x_variant":[
        "\u4e0a\u5085\u6751"
    ],
    "wof:name":"Shangfucun",
    "wof:placetype":"locality"
},
  "geometry": {"coordinates":[121.86951000000001,29.86951],"type":"Point"}
}