{
  "type": "Feature",
  "properties": {
    "gn:admin1_code":"29.0",
    "gn:asciiname":"Guida",
    "gn:country_code":"CN",
    "gn:dem":2315,
    "gn:feature_class":"P",
    "gn:feature_code":"PPL",
    "gn:name":"Guida",
    "gn:population":0,
    "gn:timezone":"Asia/Shanghai",
    "iso:country":"CN",
    "name:zho_x_preferred":[
        "\u5f52\u8fbe"
    ],
    "wof:name":"Guida",
    "wof:placetype":"locality"
},
  "geometry": {"coordinates":[99.39919999999999,27.9685],"type":"Point"}
}