{
  "type": "Feature",
  "properties": {
    "gn:admin1_code":"9.0",
    "gn:asciiname":"Xisizhuang",
    "gn:country_code":"CN",
    "gn:dem":208,
    "gn:feature_class":"P",
    "gn:feature_code":"PPL",
    "gn:name":"Xisizhuang",
    "gn:population":0,
    "gn:timezone":"Asia/Shanghai",
    "iso:country":"CN",
    "name:zho_x_preferred":[
        "\u897f\u5bfa\u5e84"
    ],
    "wof:name":"Xisizhuang",
    "wof:placetype":"locality"
},
  "geometry": {"coordinates":[113.97323,35.53508],"type":"Point"}
}