{
  "type": "Feature",
  "properties": {
    "gn:admin1_code":"4.0",
    "gn:asciiname":"Yongchang",
    "gn:country_code":"CN",
    "gn:dem":15,
    "gn:feature_class":"P",
    "gn:feature_code":"PPL",
    "gn:name":"Yongchang",
    "gn:population":0,
    "gn:timezone":"Asia/Shanghai",
    "iso:country":"CN",
    "name:ceb_x_preferred":[
        "Yongchang"
    ],
    "name:deu_x_preferred":[
        "Yongchang"
    ],
    "name:zho_x_preferred":[
        "\u6c38\u660c"
    ],
    "wof:name":"Yongchang",
    "wof:placetype":"locality"
},
  "geometry": {"coordinates":[119.68926,31.2796],"type":"Point"}
}