{
  "type": "Feature",
  "properties": {
    "gn:admin1_code":"33.0",
    "gn:asciiname":"Yongzhongcun",
    "gn:country_code":"CN",
    "gn:dem":665,
    "gn:feature_class":"P",
    "gn:feature_code":"PPL",
    "gn:name":"Yongzhongcun",
    "gn:population":0,
    "gn:timezone":"Asia/Shanghai",
    "iso:country":"CN",
    "name:zho_x_preferred":[
        "\u6c38\u4e2d\u6751"
    ],
    "wof:name":"Yongzhongcun",
    "wof:placetype":"locality"
},
  "geometry": {"coordinates":[107.128,29.2749],"type":"Point"}
}