{
  "type": "Feature",
  "properties": {
    "gn:admin1_code":"29.0",
    "gn:asciiname":"Xiaoguishan",
    "gn:country_code":"CN",
    "gn:dem":1876,
    "gn:feature_class":"P",
    "gn:feature_code":"PPL",
    "gn:name":"Xiaoguishan",
    "gn:population":0,
    "gn:timezone":"Asia/Shanghai",
    "iso:country":"CN",
    "name:zho_x_preferred":[
        "\u5c0f\u572d\u5c71"
    ],
    "wof:name":"Xiaoguishan",
    "wof:placetype":"locality"
},
  "geometry": {"coordinates":[103.527,24.592],"type":"Point"}
}