{
  "type": "Feature",
  "properties": {
    "gn:admin1_code":"5.0",
    "gn:asciiname":"Wuzhancun",
    "gn:country_code":"CN",
    "gn:dem":254,
    "gn:feature_class":"P",
    "gn:feature_code":"PPL",
    "gn:name":"Wuzhancun",
    "gn:population":0,
    "gn:timezone":"Asia/Shanghai",
    "iso:country":"CN",
    "name:zho_x_preferred":[
        "\u4e94\u7ad9\u6751"
    ],
    "wof:name":"Wuzhancun",
    "wof:placetype":"locality"
},
  "geometry": {"coordinates":[129.54521,43.42239],"type":"Point"}
}