{
  "type": "Feature",
  "properties": {
    "gn:admin1_code":"9.0",
    "gn:asciiname":"Cuijingzhuang",
    "gn:country_code":"CN",
    "gn:dem":65,
    "gn:feature_class":"P",
    "gn:feature_code":"PPL",
    "gn:name":"Cuijingzhuang",
    "gn:population":0,
    "gn:timezone":"Asia/Shanghai",
    "iso:country":"CN",
    "name:zho_x_preferred":[
        "\u5d14\u656c\u5e84"
    ],
    "wof:name":"Cuijingzhuang",
    "wof:placetype":"locality"
},
  "geometry": {"coordinates":[113.95214,33.46457],"type":"Point"}
}