{
  "type": "Feature",
  "properties": {
    "gn:admin1_code":"20.0",
    "gn:asciiname":"Beijingba",
    "gn:country_code":"CN",
    "gn:dem":1384,
    "gn:feature_class":"P",
    "gn:feature_code":"PPL",
    "gn:name":"Beijingba",
    "gn:population":0,
    "gn:timezone":"Asia/Shanghai",
    "iso:country":"CN",
    "name:und_x_variant":[
        "\u5317\u4eac\u575d"
    ],
    "wof:name":"Beijingba",
    "wof:placetype":"locality"
},
  "geometry": {"coordinates":[113.97911000000001,40.72223],"type":"Point"}
}