{
  "type": "Feature",
  "properties": {
    "gn:admin1_code":"2.0",
    "gn:asciiname":"Limin",
    "gn:country_code":"CN",
    "gn:dem":13,
    "gn:feature_class":"P",
    "gn:feature_code":"PPL",
    "gn:name":"Limin",
    "gn:population":0,
    "gn:timezone":"Asia/Shanghai",
    "iso:country":"CN",
    "name:zho_x_preferred":[
        "\u91cc\u6c11"
    ],
    "wof:name":"Limin",
    "wof:placetype":"locality"
},
  "geometry": {"coordinates":[120.86365000000001,29.78747000000001],"type":"Point"}
}