{
  "type": "Feature",
  "properties": {
    "gn:admin1_code":"15.0",
    "gn:asciiname":"Changziwan",
    "gn:country_code":"CN",
    "gn:dem":1081,
    "gn:feature_class":"P",
    "gn:feature_code":"PPL",
    "gn:name":"Changziwan",
    "gn:population":0,
    "gn:timezone":"Asia/Shanghai",
    "iso:country":"CN",
    "name:und_x_variant":[
        "\u573a\u5b50\u6e7e"
    ],
    "wof:name":"Changziwan",
    "wof:placetype":"locality"
},
  "geometry": {"coordinates":[105.74034,33.05862],"type":"Point"}
}