{
  "type": "Feature",
  "properties": {
    "gn:admin1_code":"16.0",
    "gn:asciiname":"Zhenbei",
    "gn:country_code":"CN",
    "gn:dem":148,
    "gn:feature_class":"P",
    "gn:feature_code":"PPL",
    "gn:name":"Zhenbei",
    "gn:population":0,
    "gn:timezone":"Asia/Shanghai",
    "iso:country":"CN",
    "name:zho_x_preferred":[
        "\u9547\u80cc"
    ],
    "wof:name":"Zhenbei",
    "wof:placetype":"locality"
},
  "geometry": {"coordinates":[109.31399999999999,24.8423],"type":"Point"}
}