{
  "type": "Feature",
  "properties": {
    "gn:admin1_code":"15.0",
    "gn:asciiname":"Sha'e",
    "gn:country_code":"CN",
    "gn:dem":2915,
    "gn:feature_class":"P",
    "gn:feature_code":"PPL",
    "gn:name":"Sha\u2019e",
    "gn:population":0,
    "gn:timezone":"Asia/Shanghai",
    "iso:country":"CN",
    "name:und_x_variant":[
        "Sha\u2019e",
        "\u6c99\u4fc4"
    ],
    "wof:name":"Sha'e",
    "wof:placetype":"locality"
},
  "geometry": {"coordinates":[103.42214,34.62374000000001],"type":"Point"}
}