{
  "type": "Feature",
  "properties": {
    "gn:admin1_code":"16.0",
    "gn:asciiname":"Dalu",
    "gn:country_code":"CN",
    "gn:dem":130,
    "gn:feature_class":"P",
    "gn:feature_code":"PPL",
    "gn:name":"Dalu",
    "gn:population":0,
    "gn:timezone":"Asia/Shanghai",
    "iso:country":"CN",
    "name:ceb_x_preferred":[
        "Dalu"
    ],
    "name:deu_x_preferred":[
        "Dalu"
    ],
    "name:zho_x_preferred":[
        "\u5927\u9646"
    ],
    "wof:name":"Dalu",
    "wof:placetype":"locality"
},
  "geometry": {"coordinates":[108.21899999999999,23.3469],"type":"Point"}
}