{
  "type": "Feature",
  "properties": {
    "gn:admin1_code":"16",
    "gn:asciiname":"Ping'aotou",
    "gn:country_code":"CN",
    "gn:dem":989,
    "gn:feature_class":"P",
    "gn:feature_code":"PPL",
    "gn:name":"Ping\u2019aotou",
    "gn:population":0,
    "gn:timezone":"Asia/Shanghai",
    "iso:country":"CN",
    "name:und_x_variant":[
        "Ping\u2019aotou"
    ],
    "name:zho_x_preferred":[
        "\u5e73\u5773\u5934"
    ],
    "wof:name":"Ping'aotou",
    "wof:placetype":"locality"
},
  "geometry": {"coordinates":[110.10599999999999,25.9704],"type":"Point"}
}