{
  "type": "Feature",
  "properties": {
    "gn:admin1_code":"1.0",
    "gn:asciiname":"Dunxu",
    "gn:country_code":"CN",
    "gn:dem":6,
    "gn:feature_class":"P",
    "gn:feature_code":"PPL",
    "gn:name":"Dunxu",
    "gn:population":0,
    "gn:timezone":"Asia/Shanghai",
    "iso:country":"CN",
    "name:msa_x_preferred":[
        "Dunxu"
    ],
    "name:zho_x_preferred":[
        "\u58a9\u5729"
    ],
    "wof:name":"Dunxu",
    "wof:placetype":"locality"
},
  "geometry": {"coordinates":[119.08853000000001,32.78052],"type":"Point"}
}