{
  "type": "Feature",
  "properties": {
    "gn:gn_country":"CN",
    "gn:gn_fcode":"PPLA3",
    "gn:gn_pop":421283,
    "gn:population":421283,
    "iso:country":"CN",
    "name:afr_x_preferred":[
        "Sjaoxing"
    ],
    "name:ara_x_preferred":[
        "\u0634\u0627\u0648\u0643\u0633\u064a\u0646\u062c"
    ],
    "name:cdo_x_preferred":[
        "Si\u00eau-h\u012dng"
    ],
    "name:ces_x_preferred":[
        "\u0160ao-sing"
    ],
    "name:deu_x_preferred":[
        "Shaoxing"
    ],
    "name:eng_x_preferred":[
        "Shaoxing"
    ],
    "name:epo_x_preferred":[
        "\u015caosing"
    ],
    "name:fas_x_preferred":[
        "\u0634\u0627\u0648\u0634\u06cc\u0646\u06af"
    ],
    "name:fra_x_preferred":[
        "Shaoxing"
    ],
    "name:jpn_x_preferred":[
        "\u7d39\u8208\u5e02"
    ],
    "name:kor_x_preferred":[
        "\uc18c\ud765"
    ],
    "name:kor_x_variant":[
        "\uc0ac\uc624\uc2f1 \uc2dc"
    ],
    "name:lzh_x_preferred":[
        "\u7d39\u8208\u5e02"
    ],
    "name:nan_x_preferred":[
        "Si\u0101u-heng-chh\u012b"
    ],
    "name:nno_x_preferred":[
        "Shaoxing"
    ],
    "name:nor_x_preferred":[
        "Shaoxing"
    ],
    "name:pol_x_preferred":[
        "Shaoxing"
    ],
    "name:rus_x_preferred":[
        "\u0428\u0430\u043e\u0441\u0438\u043d"
    ],
    "name:srp_x_preferred":[
        "\u0428\u0430\u043e\u0441\u0438\u043d\u0433"
    ],
    "name:uig_x_preferred":[
        "Shawshin shehiri"
    ],
    "name:unk_x_variant":[
        "Shao-hsing"
    ],
    "name:urd_x_preferred":[
        "\u0634\u0627\u0648\u0634\u0646\u06af"
    ],
    "name:vie_x_preferred":[
        "Thi\u1ec7u H\u01b0ng"
    ],
    "name:wuu_x_preferred":[
        "\u7ecd\u5174\u5e02"
    ],
    "name:yue_x_preferred":[
        "\u7d39\u8208"
    ],
    "name:zho_x_preferred":[
        "\u7ecd\u5174\u5e02"
    ],
    "qs_pg:aaroncc":"CN",
    "qs_pg:gn_country":"CN",
    "qs_pg:gn_fcode":"PPLA3",
    "qs_pg:gn_pop":421283,
    "qs_pg:name":"\u7ecd\u5174\u53bf",
    "qs_pg:name_adm0":"\u4e2d\u570b",
    "qs_pg:name_adm1":"\u6d59\u6c5f\u7701",
    "qs_pg:photos":4,
    "qs_pg:photos_1k":1,
    "qs_pg:photos_9k":10,
    "qs_pg:photos_9r":9,
    "qs_pg:photos_all":2289,
    "qs_pg:photos_sr":1,
    "qs_pg:pop_sr":11,
    "qs_pg:qs_pg_placetype":"localadmin",
    "qs_pg:qs_pg_placetype_gp":"LocalAdmin",
    "qs_pg:woe_adm0":23424781,
    "woe:adm0_id":23424781,
    "woe:name_adm0":"\u4e2d\u570b",
    "woe:name_adm1":"\u6d59\u6c5f\u7701",
    "woe:placetype":"LocalAdmin",
    "wof:name":"\u7ecd\u5174\u53bf",
    "wof:placetype":"localadmin",
    "wof:population":421283
},
  "geometry": {"coordinates":[120.57153,30.01102],"type":"Point"}
}