{
  "type": "Feature",
  "properties": {
    "gn:admin1_code":"26.0",
    "gn:asciiname":"Podihecun",
    "gn:country_code":"CN",
    "gn:dem":1027,
    "gn:feature_class":"P",
    "gn:feature_code":"PPL",
    "gn:name":"Podihecun",
    "gn:population":0,
    "gn:timezone":"Asia/Shanghai",
    "iso:country":"CN",
    "name:zho_x_preferred":[
        "\u5761\u5e95\u6cb3\u6751"
    ],
    "wof:name":"Podihecun",
    "wof:placetype":"locality"
},
  "geometry": {"coordinates":[110.20301000000001,37.10632],"type":"Point"}
}