{
  "type": "Feature",
  "properties": {
    "gn:admin1_code":"18.0",
    "gn:asciiname":"Lingshangzhai",
    "gn:country_code":"CN",
    "gn:dem":736,
    "gn:feature_class":"P",
    "gn:feature_code":"PPL",
    "gn:name":"Lingshangzhai",
    "gn:population":0,
    "gn:timezone":"Asia/Shanghai",
    "iso:country":"CN",
    "name:zho_x_preferred":[
        "\u5cad\u4e0a\u5be8"
    ],
    "wof:name":"Lingshangzhai",
    "wof:placetype":"locality"
},
  "geometry": {"coordinates":[108.797,25.8441],"type":"Point"}
}