{
  "type": "Feature",
  "properties": {
    "gn:admin1_code":"29.0",
    "gn:asciiname":"Chayuan",
    "gn:country_code":"CN",
    "gn:dem":1166,
    "gn:feature_class":"P",
    "gn:feature_code":"PPL",
    "gn:name":"Chayuan",
    "gn:population":0,
    "gn:timezone":"Asia/Shanghai",
    "iso:country":"CN",
    "name:und_x_variant":[
        "\u8336\u56ed"
    ],
    "wof:name":"Chayuan",
    "wof:placetype":"locality"
},
  "geometry": {"coordinates":[104.024,27.9602],"type":"Point"}
}