{
  "type": "Feature",
  "properties": {
    "gn:admin1_code":"5.0",
    "gn:asciiname":"Xiaoqing Gouli",
    "gn:country_code":"CN",
    "gn:dem":709,
    "gn:feature_class":"P",
    "gn:feature_code":"PPL",
    "gn:name":"Xiaoqing Gouli",
    "gn:population":0,
    "gn:timezone":"Asia/Shanghai",
    "iso:country":"CN",
    "name:zho_x_preferred":[
        "\u5c0f\u6e05\u6c9f\u91cc"
    ],
    "wof:name":"Xiaoqing Gouli",
    "wof:placetype":"locality"
},
  "geometry": {"coordinates":[126.48591999999999,41.78046],"type":"Point"}
}