{
  "type": "Feature",
  "properties": {
    "gn:admin1_code":"11.0",
    "gn:asciiname":"Shenzhouhe",
    "gn:country_code":"CN",
    "gn:dem":112,
    "gn:feature_class":"P",
    "gn:feature_code":"PPL",
    "gn:name":"Shenzhouhe",
    "gn:population":0,
    "gn:timezone":"Asia/Shanghai",
    "iso:country":"CN",
    "name:zho_x_preferred":[
        "\u795e\u6d32\u6cb3"
    ],
    "wof:name":"Shenzhouhe",
    "wof:placetype":"locality"
},
  "geometry": {"coordinates":[113.34466,26.60369],"type":"Point"}
}