{
  "type": "Feature",
  "properties": {
    "gn:admin1_code":"26",
    "gn:asciiname":"Lingkou",
    "gn:country_code":"CN",
    "gn:dem":392,
    "gn:feature_class":"P",
    "gn:feature_code":"PPLA4",
    "gn:name":"Lingkou",
    "gn:population":0,
    "gn:timezone":"Asia/Shanghai",
    "iso:country":"CN",
    "name:und_x_variant":[
        "Lingkou Zhen"
    ],
    "name:zho_x_preferred":[
        "\u96f6\u53e3"
    ],
    "wof:name":"Lingkou",
    "wof:placetype":"locality"
},
  "geometry": {"coordinates":[109.36098,34.47749],"type":"Point"}
}