{
  "type": "Feature",
  "properties": {
    "gn:admin1_code":"30.0",
    "gn:asciiname":"Sifangjing",
    "gn:country_code":"CN",
    "gn:dem":115,
    "gn:feature_class":"P",
    "gn:feature_code":"PPL",
    "gn:name":"Sifangjing",
    "gn:population":0,
    "gn:timezone":"Asia/Shanghai",
    "iso:country":"CN",
    "name:zho_x_preferred":[
        "Sifangjing"
    ],
    "name:zho_x_variant":[
        "\u56db\u65b9\u4e95"
    ],
    "wof:name":"Sifangjing",
    "wof:placetype":"locality"
},
  "geometry": {"coordinates":[112.36111,24.82639],"type":"Point"}
}