{
  "type": "Feature",
  "properties": {
    "gn:admin1_code":"1.0",
    "gn:asciiname":"Zhetangcun",
    "gn:country_code":"CN",
    "gn:dem":64,
    "gn:feature_class":"P",
    "gn:feature_code":"PPL",
    "gn:name":"Zhetangcun",
    "gn:population":0,
    "gn:timezone":"Asia/Shanghai",
    "iso:country":"CN",
    "name:zho_x_preferred":[
        "\u67d8\u5858\u6751"
    ],
    "wof:name":"Zhetangcun",
    "wof:placetype":"locality"
},
  "geometry": {"coordinates":[117.27177,32.3255],"type":"Point"}
}