{
  "type": "Feature",
  "properties": {
    "gn:admin1_code":"32.0",
    "gn:asciiname":"Chenghuang",
    "gn:country_code":"CN",
    "gn:dem":371,
    "gn:feature_class":"P",
    "gn:feature_code":"PPL",
    "gn:name":"Chenghuang",
    "gn:population":0,
    "gn:timezone":"Asia/Shanghai",
    "iso:country":"CN",
    "name:zho_x_preferred":[
        "\u7a0b\u9ec4"
    ],
    "wof:name":"Chenghuang",
    "wof:placetype":"locality"
},
  "geometry": {"coordinates":[103.71299999999999,29.5208],"type":"Point"}
}