{
  "type": "Feature",
  "properties": {
    "gn:admin1_code":"24.0",
    "gn:asciiname":"Hongchengcun",
    "gn:country_code":"CN",
    "gn:dem":763,
    "gn:feature_class":"P",
    "gn:feature_code":"PPL",
    "gn:name":"Hongchengcun",
    "gn:population":0,
    "gn:timezone":"Asia/Shanghai",
    "iso:country":"CN",
    "name:zho_x_preferred":[
        "\u7ea2\u57ce\u6751"
    ],
    "wof:name":"Hongchengcun",
    "wof:placetype":"locality"
},
  "geometry": {"coordinates":[112.44316000000001,37.58679],"type":"Point"}
}