{
  "type": "Feature",
  "properties": {
    "gn:admin1_code":"26",
    "gn:asciiname":"Dongjiawang",
    "gn:country_code":"CN",
    "gn:dem":451,
    "gn:feature_class":"P",
    "gn:feature_code":"PPL",
    "gn:name":"Dongjiawang",
    "gn:population":0,
    "gn:timezone":"Asia/Shanghai",
    "iso:country":"CN",
    "name:und_x_variant":[
        "\u4e1c\u67b6\u738b"
    ],
    "name:zho_x_preferred":[
        "\u4e1c\u67b6\u738b"
    ],
    "wof:name":"Dongjiawang",
    "wof:placetype":"locality"
},
  "geometry": {"coordinates":[108.78583,34.63306],"type":"Point"}
}