{
  "type": "Feature",
  "properties": {
    "gn:admin1_code":"8.0",
    "gn:asciiname":"Lianxing Yi'erdui",
    "gn:country_code":"CN",
    "gn:dem":255,
    "gn:feature_class":"P",
    "gn:feature_code":"PPLF",
    "gn:name":"Lianxing Yi\u2019erdui",
    "gn:population":0,
    "gn:timezone":"Asia/Shanghai",
    "iso:country":"CN",
    "name:und_x_variant":[
        "Lianxing Yi\u2019erdui"
    ],
    "name:zho_x_preferred":[
        "\u8054\u5174\u4e00\u4e8c\u961f"
    ],
    "wof:name":"Lianxing Yi'erdui",
    "wof:placetype":"locality"
},
  "geometry": {"coordinates":[125.64230000000001,48.11393],"type":"Point"}
}