{
  "type": "Feature",
  "properties": {
    "gn:admin1_code":"1.0",
    "gn:asciiname":"Ligaocun",
    "gn:country_code":"CN",
    "gn:dem":24,
    "gn:feature_class":"P",
    "gn:feature_code":"PPL",
    "gn:name":"Ligaocun",
    "gn:population":0,
    "gn:timezone":"Asia/Shanghai",
    "iso:country":"CN",
    "name:zho_x_preferred":[
        "\u674e\u9ad8\u6751"
    ],
    "wof:name":"Ligaocun",
    "wof:placetype":"locality"
},
  "geometry": {"coordinates":[117.2099,33.12573],"type":"Point"}
}