{
  "type": "Feature",
  "properties": {
    "gn:admin1_code":"29.0",
    "gn:asciiname":"Duanjia Pingzi",
    "gn:country_code":"CN",
    "gn:dem":2658,
    "gn:feature_class":"P",
    "gn:feature_code":"PPL",
    "gn:name":"Duanjia Pingzi",
    "gn:population":0,
    "gn:timezone":"Asia/Shanghai",
    "iso:country":"CN",
    "name:zho_x_preferred":[
        "\u6bb5\u5bb6\u576a\u5b50"
    ],
    "wof:name":"Duanjia Pingzi",
    "wof:placetype":"locality"
},
  "geometry": {"coordinates":[103.858,27.3614],"type":"Point"}
}