{
  "type": "Feature",
  "properties": {
    "gn:admin1_code":"19.0",
    "gn:asciiname":"Heishancun",
    "gn:country_code":"CN",
    "gn:dem":44,
    "gn:feature_class":"P",
    "gn:feature_code":"PPL",
    "gn:name":"Heishancun",
    "gn:population":0,
    "gn:timezone":"Asia/Shanghai",
    "iso:country":"CN",
    "name:zho_x_preferred":[
        "\u9ed1\u5c71\u6751"
    ],
    "wof:name":"Heishancun",
    "wof:placetype":"locality"
},
  "geometry": {"coordinates":[121.767,39.0585],"type":"Point"}
}