{
  "type": "Feature",
  "properties": {
    "gn:admin1_code":"25.0",
    "gn:asciiname":"Zhangjia Aotou",
    "gn:country_code":"CN",
    "gn:dem":2,
    "gn:feature_class":"P",
    "gn:feature_code":"PPL",
    "gn:name":"Zhangjia Aotou",
    "gn:population":0,
    "gn:timezone":"Asia/Shanghai",
    "iso:country":"CN",
    "name:zho_x_preferred":[
        "\u5f20\u5bb6\u5ed2\u5934"
    ],
    "wof:name":"Zhangjia Aotou",
    "wof:placetype":"locality"
},
  "geometry": {"coordinates":[119.39693,35.31077],"type":"Point"}
}