{
  "type": "Feature",
  "properties": {
    "gn:admin1_code":"1.0",
    "gn:asciiname":"Lituloucun",
    "gn:country_code":"CN",
    "gn:dem":31,
    "gn:feature_class":"P",
    "gn:feature_code":"PPL",
    "gn:name":"Lituloucun",
    "gn:population":0,
    "gn:timezone":"Asia/Shanghai",
    "iso:country":"CN",
    "name:zho_x_preferred":[
        "\u6817\u571f\u697c\u6751"
    ],
    "wof:name":"Lituloucun",
    "wof:placetype":"locality"
},
  "geometry": {"coordinates":[116.05627,33.28607],"type":"Point"}
}