{
  "type": "Feature",
  "properties": {
    "gn:admin1_code":"08",
    "gn:asciiname":"Changchun",
    "gn:country_code":"CN",
    "gn:dem":265,
    "gn:feature_class":"P",
    "gn:feature_code":"PPLA4",
    "gn:name":"Changchun",
    "gn:population":0,
    "gn:timezone":"Asia/Shanghai",
    "iso:country":"CN",
    "name:rus_x_preferred":[
        "\u0427\u0430\u043d\u0447\u0443\u043d\u044c"
    ],
    "name:und_x_variant":[
        "Ch\u2019ang-ch\u2019un-chen",
        "Changchun",
        "Changchun Zhen"
    ],
    "name:zho_x_preferred":[
        "\u957f\u6625"
    ],
    "name:zho_x_variant":[
        "\u957f\u6625\u9547"
    ],
    "wof:name":"Changchun",
    "wof:placetype":"locality"
},
  "geometry": {"coordinates":[125.65863,47.73186],"type":"Point"}
}