{
  "type": "Feature",
  "properties": {
    "gn:admin1_code":"02",
    "gn:asciiname":"Xinshichang",
    "gn:country_code":"CN",
    "gn:dem":428,
    "gn:feature_class":"P",
    "gn:feature_code":"PPLA4",
    "gn:name":"Xinshichang",
    "gn:population":0,
    "gn:timezone":"Asia/Shanghai",
    "iso:country":"CN",
    "name:und_x_variant":[
        "Huishan Zhen",
        "Huishan",
        "Xinshichang",
        "\u65b0\u5e02\u573a",
        "Shuangcai"
    ],
    "name:zho_x_preferred":[
        "\u56de\u5c71\u9547"
    ],
    "name:zho_x_variant":[
        "\u65b0\u5e02\u573a",
        "\u53cc\u5f69"
    ],
    "wof:name":"Xinshichang",
    "wof:placetype":"locality"
},
  "geometry": {"coordinates":[120.80674,29.27986],"type":"Point"}
}