{
  "type": "Feature",
  "properties": {
    "gn:admin1_code":"5.0",
    "gn:asciiname":"Wanzhongcun",
    "gn:country_code":"CN",
    "gn:dem":159,
    "gn:feature_class":"P",
    "gn:feature_code":"PPL",
    "gn:name":"Wanzhongcun",
    "gn:population":0,
    "gn:timezone":"Asia/Shanghai",
    "iso:country":"CN",
    "name:zho_x_preferred":[
        "\u4e07\u4f17\u6751"
    ],
    "wof:name":"Wanzhongcun",
    "wof:placetype":"locality"
},
  "geometry": {"coordinates":[125.44807,45.19772],"type":"Point"}
}