{
  "type": "Feature",
  "properties": {
    "gn:admin1_code":"19",
    "gn:asciiname":"Qiujia",
    "gn:country_code":"CN",
    "gn:dem":154,
    "gn:feature_class":"P",
    "gn:feature_code":"PPLA4",
    "gn:name":"Qiujia",
    "gn:population":0,
    "gn:timezone":"Asia/Shanghai",
    "iso:country":"CN",
    "name:und_x_variant":[
        "Chaoyang Zhen",
        "Chaoyang",
        "Qiujia"
    ],
    "name:zho_x_preferred":[
        "\u90b1\u5bb6"
    ],
    "name:zho_x_variant":[
        "\u671d\u9633\u9547",
        "\u671d\u9633"
    ],
    "wof:name":"Qiujia",
    "wof:placetype":"locality"
},
  "geometry": {"coordinates":[124.07263,43.11736],"type":"Point"}
}