{
  "type": "Feature",
  "properties": {
    "gn:admin1_code":"9",
    "gn:asciiname":"Cuijia",
    "gn:country_code":"CN",
    "gn:dem":52,
    "gn:feature_class":"P",
    "gn:feature_code":"PPL",
    "gn:name":"Cuijia",
    "gn:population":0,
    "gn:timezone":"Asia/Shanghai",
    "iso:country":"CN",
    "name:ceb_x_preferred":[
        "Dijia"
    ],
    "name:swe_x_preferred":[
        "Dijia"
    ],
    "name:zho_x_preferred":[
        "\u5d14\u5bb6"
    ],
    "name:zho_x_variant":[
        "\u7fdf\u5bb6\u9547"
    ],
    "wof:name":"Cuijia",
    "wof:placetype":"locality"
},
  "geometry": {"coordinates":[115.334,35.9521],"type":"Point"}
}