{
  "type": "Feature",
  "properties": {
    "gn:admin1_code":"16.0",
    "gn:asciiname":"Xilan",
    "gn:country_code":"CN",
    "gn:dem":116,
    "gn:feature_class":"P",
    "gn:feature_code":"PPL",
    "gn:name":"Xilan",
    "gn:population":0,
    "gn:timezone":"Asia/Shanghai",
    "iso:country":"CN",
    "name:zho_x_preferred":[
        "\u897f\u6f9c"
    ],
    "wof:name":"Xilan",
    "wof:placetype":"locality"
},
  "geometry": {"coordinates":[110.821,22.825],"type":"Point"}
}