{
  "type": "Feature",
  "properties": {
    "gn:admin1_code":"30.0",
    "gn:asciiname":"Zhuanpanling",
    "gn:country_code":"CN",
    "gn:dem":624,
    "gn:feature_class":"P",
    "gn:feature_code":"PPL",
    "gn:name":"Zhuanpanling",
    "gn:population":0,
    "gn:timezone":"Asia/Shanghai",
    "iso:country":"CN",
    "name:zho_x_preferred":[
        "Zhuanpanling"
    ],
    "name:zho_x_variant":[
        "\u7bc6\u76d8\u5cad"
    ],
    "wof:name":"Zhuanpanling",
    "wof:placetype":"locality"
},
  "geometry": {"coordinates":[112.49028,25.08556],"type":"Point"}
}