{
  "type": "Feature",
  "properties": {
    "gn:admin1_code":"5.0",
    "gn:asciiname":"Xiaoyaojie",
    "gn:country_code":"CN",
    "gn:dem":212,
    "gn:feature_class":"P",
    "gn:feature_code":"PPL",
    "gn:name":"Xiaoyaojie",
    "gn:population":0,
    "gn:timezone":"Asia/Shanghai",
    "iso:country":"CN",
    "name:zho_x_preferred":[
        "\u5c0f\u8170\u8857"
    ],
    "wof:name":"Xiaoyaojie",
    "wof:placetype":"locality"
},
  "geometry": {"coordinates":[124.66105,43.37434],"type":"Point"}
}