{
  "type": "Feature",
  "properties": {
    "gn:admin1_code":"1.0",
    "gn:asciiname":"Lufangloucun",
    "gn:country_code":"CN",
    "gn:dem":38,
    "gn:feature_class":"P",
    "gn:feature_code":"PPL",
    "gn:name":"Lufangloucun",
    "gn:population":0,
    "gn:timezone":"Asia/Shanghai",
    "iso:country":"CN",
    "name:zho_x_preferred":[
        "\u9c81\u623f\u697c\u6751"
    ],
    "wof:name":"Lufangloucun",
    "wof:placetype":"locality"
},
  "geometry": {"coordinates":[116.00302000000001,33.8905],"type":"Point"}
}