{
  "type": "Feature",
  "properties": {
    "gn:admin1_code":"14.0",
    "gn:asciiname":"Rangmagecun",
    "gn:country_code":"CN",
    "gn:dem":3983,
    "gn:feature_class":"P",
    "gn:feature_code":"PPL",
    "gn:name":"Rangmagecun",
    "gn:population":0,
    "gn:timezone":"Asia/Urumqi",
    "iso:country":"CN",
    "name:zho_x_preferred":[
        "\u8ba9\u739b\u683c\u6751"
    ],
    "wof:name":"Rangmagecun",
    "wof:placetype":"locality"
},
  "geometry": {"coordinates":[94.79867,30.85198],"type":"Point"}
}