{
  "type": "Feature",
  "properties": {
    "gn:admin1_code":"3",
    "gn:asciiname":"Shebei",
    "gn:country_code":"CN",
    "gn:dem":198,
    "gn:feature_class":"P",
    "gn:feature_code":"PPL",
    "gn:name":"Shebei",
    "gn:population":0,
    "gn:timezone":"Asia/Shanghai",
    "iso:country":"CN",
    "name:zho_x_preferred":[
        "\u86c7\u80cc"
    ],
    "wof:name":"Shebei",
    "wof:placetype":"locality"
},
  "geometry": {"coordinates":[114.81999999999999,25.5877],"type":"Point"}
}