{
  "type": "Feature",
  "properties": {
    "gn:admin1_code":"19.0",
    "gn:asciiname":"Shatuozi",
    "gn:country_code":"CN",
    "gn:dem":35,
    "gn:feature_class":"P",
    "gn:feature_code":"PPL",
    "gn:name":"Shatuozi",
    "gn:population":0,
    "gn:timezone":"Asia/Shanghai",
    "iso:country":"CN",
    "name:und_x_variant":[
        "\u6c99\u5768\u5b50"
    ],
    "name:zho_x_preferred":[
        "\u6c99\u5768\u5b50"
    ],
    "wof:name":"Shatuozi",
    "wof:placetype":"locality"
},
  "geometry": {"coordinates":[123.18553,41.83597],"type":"Point"}
}