{
  "type": "Feature",
  "properties": {
    "gn:admin1_code":"16.0",
    "gn:asciiname":"Sanjiang",
    "gn:country_code":"CN",
    "gn:dem":80,
    "gn:feature_class":"P",
    "gn:feature_code":"PPL",
    "gn:name":"Sanjiang",
    "gn:population":0,
    "gn:timezone":"Asia/Shanghai",
    "iso:country":"CN",
    "name:ceb_x_preferred":[
        "Sanjiang"
    ],
    "name:deu_x_preferred":[
        "Sanjiang"
    ],
    "name:zho_x_preferred":[
        "\u4e09\u6c5f"
    ],
    "wof:name":"Sanjiang",
    "wof:placetype":"locality"
},
  "geometry": {"coordinates":[109.789,23.5578],"type":"Point"}
}