{
  "type": "Feature",
  "properties": {
    "gn:admin1_code":"14.0",
    "gn:asciiname":"Chuka",
    "gn:country_code":"CN",
    "gn:dem":4137,
    "gn:feature_class":"P",
    "gn:feature_code":"PPLF",
    "gn:name":"Chuka",
    "gn:population":0,
    "gn:timezone":"Asia/Urumqi",
    "iso:country":"CN",
    "name:bod_x_preferred":[
        "Chuka"
    ],
    "name:msa_x_preferred":[
        "Chuka"
    ],
    "name:und_x_variant":[
        "Mang-k\u2019ang",
        "Chuka"
    ],
    "name:zho_x_preferred":[
        "Zhuka"
    ],
    "name:zho_x_variant":[
        "\u7af9\u5361"
    ],
    "wof:name":"Chuka",
    "wof:placetype":"locality"
},
  "geometry": {"coordinates":[98.46666999999999,29.63333],"type":"Point"}
}