{
  "type": "Feature",
  "properties": {
    "gn:admin1_code":"3.0",
    "gn:asciiname":"Likeng",
    "gn:country_code":"CN",
    "gn:dem":87,
    "gn:feature_class":"P",
    "gn:feature_code":"PPL",
    "gn:name":"Likeng",
    "gn:population":0,
    "gn:timezone":"Asia/Shanghai",
    "iso:country":"CN",
    "name:und_x_variant":[
        "\u67a5\u5751"
    ],
    "wof:name":"Likeng",
    "wof:placetype":"locality"
},
  "geometry": {"coordinates":[115.17644,27.7329],"type":"Point"}
}