{
  "type": "Feature",
  "properties": {
    "gn:admin1_code":"4.0",
    "gn:asciiname":"Zhongjiaxia",
    "gn:country_code":"CN",
    "gn:dem":6,
    "gn:feature_class":"P",
    "gn:feature_code":"PPL",
    "gn:name":"Zhongjiaxia",
    "gn:population":0,
    "gn:timezone":"Asia/Shanghai",
    "iso:country":"CN",
    "name:zho_x_preferred":[
        "\u4ef2\u5bb6\u53a6"
    ],
    "wof:name":"Zhongjiaxia",
    "wof:placetype":"locality"
},
  "geometry": {"coordinates":[119.66518000000001,32.78895],"type":"Point"}
}