{
  "type": "Feature",
  "properties": {
    "gn:admin1_code":"26",
    "gn:asciiname":"Xijing",
    "gn:country_code":"CN",
    "gn:dem":909,
    "gn:feature_class":"P",
    "gn:feature_code":"PPLA4",
    "gn:name":"Xijing",
    "gn:population":0,
    "gn:timezone":"Asia/Shanghai",
    "iso:country":"CN",
    "name:und_x_variant":[
        "\u897f\u8346",
        "Xijing"
    ],
    "wof:name":"Xijing",
    "wof:placetype":"locality"
},
  "geometry": {"coordinates":[109.81816000000001,34.04857],"type":"Point"}
}