{
  "type": "Feature",
  "properties": {
    "gn:admin1_code":"11.0",
    "gn:asciiname":"Niumudong",
    "gn:country_code":"CN",
    "gn:dem":766,
    "gn:feature_class":"P",
    "gn:feature_code":"PPL",
    "gn:name":"Niumudong",
    "gn:population":0,
    "gn:timezone":"Asia/Shanghai",
    "iso:country":"CN",
    "name:zho_x_preferred":[
        "\u725b\u6728\u6d1e"
    ],
    "wof:name":"Niumudong",
    "wof:placetype":"locality"
},
  "geometry": {"coordinates":[113.72837,25.64667],"type":"Point"}
}