{
  "type": "Feature",
  "properties": {
    "gn:admin1_code":"12.0",
    "gn:asciiname":"Yemenfan",
    "gn:country_code":"CN",
    "gn:dem":86,
    "gn:feature_class":"P",
    "gn:feature_code":"PPL",
    "gn:name":"Yemenfan",
    "gn:population":0,
    "gn:timezone":"Asia/Shanghai",
    "iso:country":"CN",
    "name:zho_x_preferred":[
        "\u53f6\u95e8\u7548"
    ],
    "wof:name":"Yemenfan",
    "wof:placetype":"locality"
},
  "geometry": {"coordinates":[113.90076000000001,29.50032],"type":"Point"}
}