{
  "type": "Feature",
  "properties": {
    "gn:admin1_code":"26.0",
    "gn:asciiname":"Shaojiagou",
    "gn:country_code":"CN",
    "gn:dem":979,
    "gn:feature_class":"P",
    "gn:feature_code":"PPL",
    "gn:name":"Shaojiagou",
    "gn:population":0,
    "gn:timezone":"Asia/Shanghai",
    "iso:country":"CN",
    "name:und_x_variant":[
        "\u90b5\u5bb6\u6c9f"
    ],
    "wof:name":"Shaojiagou",
    "wof:placetype":"locality"
},
  "geometry": {"coordinates":[107.67677999999999,33.53077],"type":"Point"}
}