{
  "type": "Feature",
  "properties": {
    "gn:admin1_code":"21.0",
    "gn:asciiname":"Huanggu",
    "gn:country_code":"CN",
    "gn:dem":1531,
    "gn:feature_class":"P",
    "gn:feature_code":"PPL",
    "gn:name":"Huanggu",
    "gn:population":0,
    "gn:timezone":"Asia/Shanghai",
    "iso:country":"CN",
    "name:zho_x_preferred":[
        "\u9ec4\u8c37"
    ],
    "wof:name":"Huanggu",
    "wof:placetype":"locality"
},
  "geometry": {"coordinates":[105.78700000000001,36.8888],"type":"Point"}
}