{
  "type": "Feature",
  "properties": {
    "gn:admin1_code":"7.0",
    "gn:asciiname":"Lisuxi",
    "gn:country_code":"CN",
    "gn:dem":306,
    "gn:feature_class":"P",
    "gn:feature_code":"PPL",
    "gn:name":"Lisuxi",
    "gn:population":0,
    "gn:timezone":"Asia/Shanghai",
    "iso:country":"CN",
    "name:zho_x_preferred":[
        "\u91cc\u82cf\u6eaa"
    ],
    "wof:name":"Lisuxi",
    "wof:placetype":"locality"
},
  "geometry": {"coordinates":[117.74403,27.14998],"type":"Point"}
}