{
  "type": "Feature",
  "properties": {
    "gn:admin1_code":"33.0",
    "gn:asciiname":"Yandongwan",
    "gn:country_code":"CN",
    "gn:dem":1558,
    "gn:feature_class":"P",
    "gn:feature_code":"PPL",
    "gn:name":"Yandongwan",
    "gn:population":0,
    "gn:timezone":"Asia/Shanghai",
    "iso:country":"CN",
    "name:zho_x_preferred":[
        "\u5ca9\u6d1e\u6e7e"
    ],
    "wof:name":"Yandongwan",
    "wof:placetype":"locality"
},
  "geometry": {"coordinates":[109.21066,31.76627],"type":"Point"}
}