{
  "type": "Feature",
  "properties": {
    "gn:admin1_code":"25",
    "gn:asciiname":"Dachenjia Junzi",
    "gn:country_code":"CN",
    "gn:dem":134,
    "gn:feature_class":"P",
    "gn:feature_code":"PPL",
    "gn:name":"Dachenjia Junzi",
    "gn:population":0,
    "gn:timezone":"Asia/Shanghai",
    "iso:country":"CN",
    "name:und_x_variant":[
        "\u5927\u9648\u5bb6\u519b\u5b50"
    ],
    "wof:name":"Dachenjia Junzi",
    "wof:placetype":"locality"
},
  "geometry": {"coordinates":[119.00594,35.4021],"type":"Point"}
}