{
  "type": "Feature",
  "properties": {
    "gn:admin1_code":"29",
    "gn:asciiname":"Xizai",
    "gn:country_code":"CN",
    "gn:dem":1154,
    "gn:feature_class":"P",
    "gn:feature_code":"PPL",
    "gn:name":"Xizai",
    "gn:population":0,
    "gn:timezone":"Asia/Shanghai",
    "iso:country":"CN",
    "name:zho_x_preferred":[
        "\u606f\u5bb0"
    ],
    "wof:name":"Xizai",
    "wof:placetype":"locality"
},
  "geometry": {"coordinates":[103.372,24.0235],"type":"Point"}
}