{
  "type": "Feature",
  "properties": {
    "gn:admin1_code":"11.0",
    "gn:asciiname":"Niulianchong",
    "gn:country_code":"CN",
    "gn:dem":401,
    "gn:feature_class":"P",
    "gn:feature_code":"PPL",
    "gn:name":"Niulianchong",
    "gn:population":0,
    "gn:timezone":"Asia/Shanghai",
    "iso:country":"CN",
    "name:zho_x_preferred":[
        "\u725b\u604b\u51b2"
    ],
    "wof:name":"Niulianchong",
    "wof:placetype":"locality"
},
  "geometry": {"coordinates":[110.32916000000002,27.39964],"type":"Point"}
}