{
  "type": "Feature",
  "properties": {
    "gn:admin1_code":"14.0",
    "gn:asciiname":"Qumaduo",
    "gn:country_code":"CN",
    "gn:dem":4283,
    "gn:feature_class":"P",
    "gn:feature_code":"PPL",
    "gn:name":"Qumaduo",
    "gn:population":0,
    "gn:timezone":"Asia/Urumqi",
    "iso:country":"CN",
    "name:zho_x_preferred":[
        "\u66f2\u739b\u591a"
    ],
    "wof:name":"Qumaduo",
    "wof:placetype":"locality"
},
  "geometry": {"coordinates":[91.20679,30.56757],"type":"Point"}
}