{
  "type": "Feature",
  "properties": {
    "gn:admin1_code":"1.0",
    "gn:asciiname":"Hailiancun",
    "gn:country_code":"CN",
    "gn:dem":137,
    "gn:feature_class":"P",
    "gn:feature_code":"PPL",
    "gn:name":"Hailiancun",
    "gn:population":0,
    "gn:timezone":"Asia/Shanghai",
    "iso:country":"CN",
    "name:zho_x_preferred":[
        "\u6d77\u83b2\u6751"
    ],
    "wof:name":"Hailiancun",
    "wof:placetype":"locality"
},
  "geometry": {"coordinates":[115.97445,31.46321],"type":"Point"}
}