{
  "type": "Feature",
  "properties": {
    "gn:admin1_code":"26.0",
    "gn:asciiname":"Zhou'ao",
    "gn:country_code":"CN",
    "gn:dem":623,
    "gn:feature_class":"P",
    "gn:feature_code":"PPL",
    "gn:name":"Zhou\u2019ao",
    "gn:population":0,
    "gn:timezone":"Asia/Shanghai",
    "iso:country":"CN",
    "name:und_x_variant":[
        "Zhou\u2019ao"
    ],
    "name:zho_x_preferred":[
        "\u5468\u51f9"
    ],
    "wof:name":"Zhou'ao",
    "wof:placetype":"locality"
},
  "geometry": {"coordinates":[109.94329,33.26688],"type":"Point"}
}