{
  "type": "Feature",
  "properties": {
    "gn:admin1_code":"25",
    "gn:asciiname":"Zhaoguzhuang Xicun",
    "gn:country_code":"CN",
    "gn:dem":84,
    "gn:feature_class":"P",
    "gn:feature_code":"PPL",
    "gn:name":"Zhaoguzhuang Xicun",
    "gn:population":0,
    "gn:timezone":"Asia/Shanghai",
    "iso:country":"CN",
    "name:zho_x_preferred":[
        "\u8d75\u53e4\u5e84\u897f\u6751"
    ],
    "wof:name":"Zhaoguzhuang Xicun",
    "wof:placetype":"locality"
},
  "geometry": {"coordinates":[119.19799999999999,36.0704],"type":"Point"}
}