{
  "type": "Feature",
  "properties": {
    "gn:admin1_code":"11.0",
    "gn:asciiname":"Doujiaolong",
    "gn:country_code":"CN",
    "gn:dem":360,
    "gn:feature_class":"P",
    "gn:feature_code":"PPL",
    "gn:name":"Doujiaolong",
    "gn:population":0,
    "gn:timezone":"Asia/Shanghai",
    "iso:country":"CN",
    "name:zho_x_preferred":[
        "\u8c46\u89d2\u5785"
    ],
    "wof:name":"Doujiaolong",
    "wof:placetype":"locality"
},
  "geometry": {"coordinates":[114.20195,26.16131],"type":"Point"}
}