{
  "type": "Feature",
  "properties": {
    "gn:admin1_code":"8.0",
    "gn:asciiname":"Duifengli Yiduidi Wobu",
    "gn:country_code":"CN",
    "gn:dem":73,
    "gn:feature_class":"P",
    "gn:feature_code":"PPLF",
    "gn:name":"Duifengli Yiduidi Wobu",
    "gn:population":0,
    "gn:timezone":"Asia/Shanghai",
    "iso:country":"CN",
    "name:zho_x_preferred":[
        "\u5806\u5cf0\u91cc\u4e00\u961f\u5730\u7a9d\u5821"
    ],
    "wof:name":"Duifengli Yiduidi Wobu",
    "wof:placetype":"locality"
},
  "geometry": {"coordinates":[130.57831000000002,46.97783],"type":"Point"}
}