{
  "type": "Feature",
  "properties": {
    "gn:admin1_code":"3",
    "gn:asciiname":"Yuanlong",
    "gn:country_code":"CN",
    "gn:dem":79,
    "gn:feature_class":"P",
    "gn:feature_code":"PPL",
    "gn:name":"Yuanlong",
    "gn:population":0,
    "gn:timezone":"Asia/Shanghai",
    "iso:country":"CN",
    "name:zho_x_preferred":[
        "\u9662\u5784"
    ],
    "wof:name":"Yuanlong",
    "wof:placetype":"locality"
},
  "geometry": {"coordinates":[114.70446,26.85211],"type":"Point"}
}