{
  "type": "Feature",
  "properties": {
    "gn:admin1_code":"12.0",
    "gn:asciiname":"Ganheling",
    "gn:country_code":"CN",
    "gn:dem":28,
    "gn:feature_class":"P",
    "gn:feature_code":"PPL",
    "gn:name":"Ganheling",
    "gn:population":0,
    "gn:timezone":"Asia/Shanghai",
    "iso:country":"CN",
    "name:zho_x_preferred":[
        "\u5e72\u6cb3\u5cad"
    ],
    "wof:name":"Ganheling",
    "wof:placetype":"locality"
},
  "geometry": {"coordinates":[113.07265,30.63989],"type":"Point"}
}