{
  "type": "Feature",
  "properties": {
    "gn:admin1_code":"18",
    "gn:asciiname":"Pingdiying",
    "gn:country_code":"CN",
    "gn:dem":1935,
    "gn:feature_class":"P",
    "gn:feature_code":"PPL",
    "gn:name":"Pingdiying",
    "gn:population":0,
    "gn:timezone":"Asia/Shanghai",
    "iso:country":"CN",
    "name:zho_x_preferred":[
        "\u576a\u5730\u8425"
    ],
    "wof:name":"Pingdiying",
    "wof:placetype":"locality"
},
  "geometry": {"coordinates":[103.77,27.0159],"type":"Point"}
}