{
  "type": "Feature",
  "properties": {
    "gn:admin1_code":"32.0",
    "gn:asciiname":"Luding",
    "gn:country_code":"CN",
    "gn:dem":2118,
    "gn:feature_class":"P",
    "gn:feature_code":"PPL",
    "gn:name":"L\u00fcding",
    "gn:population":0,
    "gn:timezone":"Asia/Shanghai",
    "iso:country":"CN",
    "name:deu_x_preferred":[
        "Luding"
    ],
    "name:fra_x_preferred":[
        "Luding"
    ],
    "name:und_x_variant":[
        "L\u00fcding"
    ],
    "name:zho_x_preferred":[
        "\u7eff\u5b9a"
    ],
    "wof:name":"Luding",
    "wof:placetype":"locality"
},
  "geometry": {"coordinates":[100.527,28.1068],"type":"Point"}
}