{
  "type": "Feature",
  "properties": {
    "gn:admin1_code":"18.0",
    "gn:asciiname":"Quezui'ao",
    "gn:country_code":"CN",
    "gn:dem":665,
    "gn:feature_class":"P",
    "gn:feature_code":"PPL",
    "gn:name":"Quezui\u2019ao",
    "gn:population":0,
    "gn:timezone":"Asia/Shanghai",
    "iso:country":"CN",
    "name:und_x_variant":[
        "Quezui\u2019ao"
    ],
    "name:zho_x_preferred":[
        "\u9e4a\u5480\u5773"
    ],
    "wof:name":"Quezui'ao",
    "wof:placetype":"locality"
},
  "geometry": {"coordinates":[109.11199999999999,28.2043],"type":"Point"}
}