{
  "type": "Feature",
  "properties": {
    "gn:admin1_code":"19.0",
    "gn:asciiname":"Feituncun",
    "gn:country_code":"CN",
    "gn:dem":112,
    "gn:feature_class":"P",
    "gn:feature_code":"PPL",
    "gn:name":"Feituncun",
    "gn:population":0,
    "gn:timezone":"Asia/Shanghai",
    "iso:country":"CN",
    "name:zho_x_preferred":[
        "\u8d39\u5c6f\u6751"
    ],
    "wof:name":"Feituncun",
    "wof:placetype":"locality"
},
  "geometry": {"coordinates":[122.12255999999999,39.76939],"type":"Point"}
}