{
  "type": "Feature",
  "properties": {
    "gn:admin1_code":"3.0",
    "gn:asciiname":"Jiangfangcun",
    "gn:country_code":"CN",
    "gn:dem":46,
    "gn:feature_class":"P",
    "gn:feature_code":"PPL",
    "gn:name":"Jiangfangcun",
    "gn:population":0,
    "gn:timezone":"Asia/Shanghai",
    "iso:country":"CN",
    "name:und_x_variant":[
        "\u848b\u574a\u6751"
    ],
    "wof:name":"Jiangfangcun",
    "wof:placetype":"locality"
},
  "geometry": {"coordinates":[116.10896,28.22954],"type":"Point"}
}