{
  "type": "Feature",
  "properties": {
    "gn:admin1_code":"16",
    "gn:asciiname":"Pantian",
    "gn:country_code":"CN",
    "gn:dem":230,
    "gn:feature_class":"P",
    "gn:feature_code":"PPL",
    "gn:name":"Pantian",
    "gn:population":0,
    "gn:timezone":"Asia/Shanghai",
    "iso:country":"CN",
    "name:zho_x_preferred":[
        "\u7554\u7530"
    ],
    "wof:name":"Pantian",
    "wof:placetype":"locality"
},
  "geometry": {"coordinates":[111.11499999999999,25.7037],"type":"Point"}
}