{
  "type": "Feature",
  "properties": {
    "gn:admin1_code":"11.0",
    "gn:asciiname":"Erchagang",
    "gn:country_code":"CN",
    "gn:dem":127,
    "gn:feature_class":"P",
    "gn:feature_code":"PPL",
    "gn:name":"Erchagang",
    "gn:population":0,
    "gn:timezone":"Asia/Shanghai",
    "iso:country":"CN",
    "name:zho_x_preferred":[
        "Erchagang"
    ],
    "name:zho_x_variant":[
        "\u4e8c\u53c9\u5c97"
    ],
    "wof:name":"Erchagang",
    "wof:placetype":"locality"
},
  "geometry": {"coordinates":[111.35209999999999,29.0331],"type":"Point"}
}