{
  "type": "Feature",
  "properties": {
    "gn:admin1_code":"13",
    "gn:asciiname":"Bolakalake",
    "gn:country_code":"CN",
    "gn:dem":1392,
    "gn:feature_class":"P",
    "gn:feature_code":"PPL",
    "gn:name":"Bolakalake",
    "gn:population":0,
    "gn:timezone":"Asia/Shanghai",
    "iso:country":"CN",
    "name:und_x_variant":[
        "\u535a\u62c9\u5580\u62c9\u514b"
    ],
    "wof:name":"Bolakalake",
    "wof:placetype":"locality"
},
  "geometry": {"coordinates":[77.00582,38.06281],"type":"Point"}
}