{
  "type": "Feature",
  "properties": {
    "gn:admin1_code":"15.0",
    "gn:asciiname":"Weijiatai",
    "gn:country_code":"CN",
    "gn:dem":2076,
    "gn:feature_class":"P",
    "gn:feature_code":"PPL",
    "gn:name":"Weijiatai",
    "gn:population":0,
    "gn:timezone":"Asia/Shanghai",
    "iso:country":"CN",
    "name:zho_x_preferred":[
        "\u9b4f\u5bb6\u53f0"
    ],
    "wof:name":"Weijiatai",
    "wof:placetype":"locality"
},
  "geometry": {"coordinates":[104.45699999999999,36.3769],"type":"Point"}
}