{
  "type": "Feature",
  "properties": {
    "gn:admin1_code":"22.0",
    "gn:asciiname":"Xiangyangcun",
    "gn:country_code":"CN",
    "gn:dem":175,
    "gn:feature_class":"P",
    "gn:feature_code":"PPL",
    "gn:name":"Xiangyangcun",
    "gn:population":0,
    "gn:timezone":"Asia/Shanghai",
    "iso:country":"CN",
    "name:zho_x_preferred":[
        "\u5411\u9633\u6751"
    ],
    "wof:name":"Xiangyangcun",
    "wof:placetype":"locality"
},
  "geometry": {"coordinates":[117.28491,40.14326],"type":"Point"}
}