{
  "type": "Feature",
  "properties": {
    "gn:admin1_code":"11.0",
    "gn:asciiname":"Luoziping",
    "gn:country_code":"CN",
    "gn:dem":80,
    "gn:feature_class":"P",
    "gn:feature_code":"PPL",
    "gn:name":"Luoziping",
    "gn:population":0,
    "gn:timezone":"Asia/Shanghai",
    "iso:country":"CN",
    "name:zho_x_preferred":[
        "\u9a86\u5b50\u576a"
    ],
    "wof:name":"Luoziping",
    "wof:placetype":"locality"
},
  "geometry": {"coordinates":[112.40449,27.07829000000001],"type":"Point"}
}