{
  "type": "Feature",
  "properties": {
    "gn:admin1_code":"29.0",
    "gn:asciiname":"Yangbule",
    "gn:country_code":"CN",
    "gn:dem":1630,
    "gn:feature_class":"P",
    "gn:feature_code":"PPL",
    "gn:name":"Yangbule",
    "gn:population":0,
    "gn:timezone":"Asia/Shanghai",
    "iso:country":"CN",
    "name:zho_x_preferred":[
        "\u7f8a\u4e0d\u52d2"
    ],
    "wof:name":"Yangbule",
    "wof:placetype":"locality"
},
  "geometry": {"coordinates":[99.5266,23.117],"type":"Point"}
}