{
  "type": "Feature",
  "properties": {
    "gn:admin1_code":"8.0",
    "gn:asciiname":"Zhong'ancun",
    "gn:country_code":"CN",
    "gn:dem":117,
    "gn:feature_class":"P",
    "gn:feature_code":"PPL",
    "gn:name":"Zhong\u2019ancun",
    "gn:population":0,
    "gn:timezone":"Asia/Shanghai",
    "iso:country":"CN",
    "name:und_x_variant":[
        "Zhong\u2019ancun"
    ],
    "name:zho_x_preferred":[
        "\u5fe0\u5b89\u6751"
    ],
    "wof:name":"Zhong'ancun",
    "wof:placetype":"locality"
},
  "geometry": {"coordinates":[131.37333000000001,46.70613],"type":"Point"}
}