{
  "type": "Feature",
  "properties": {
    "gn:admin1_code":"14.0",
    "gn:asciiname":"Shengge",
    "gn:country_code":"CN",
    "gn:dem":4358,
    "gn:feature_class":"P",
    "gn:feature_code":"PPL",
    "gn:name":"Shengge",
    "gn:population":0,
    "gn:timezone":"Asia/Urumqi",
    "iso:country":"CN",
    "name:zho_x_preferred":[
        "\u751f\u4e2a"
    ],
    "wof:name":"Shengge",
    "wof:placetype":"locality"
},
  "geometry": {"coordinates":[94.16215,31.90263],"type":"Point"}
}