{
  "type": "Feature",
  "properties": {
    "gn:admin1_code":"11.0",
    "gn:asciiname":"Yijiali",
    "gn:country_code":"CN",
    "gn:dem":407,
    "gn:feature_class":"P",
    "gn:feature_code":"PPL",
    "gn:name":"Yijiali",
    "gn:population":0,
    "gn:timezone":"Asia/Shanghai",
    "iso:country":"CN",
    "name:zho_x_preferred":[
        "\u6613\u5bb6\u91cc"
    ],
    "wof:name":"Yijiali",
    "wof:placetype":"locality"
},
  "geometry": {"coordinates":[111.58477000000001,28.09174],"type":"Point"}
}