{
  "type": "Feature",
  "properties": {
    "gn:admin1_code":"26.0",
    "gn:asciiname":"Qiaogoucun",
    "gn:country_code":"CN",
    "gn:dem":1195,
    "gn:feature_class":"P",
    "gn:feature_code":"PPL",
    "gn:name":"Qiaogoucun",
    "gn:population":0,
    "gn:timezone":"Asia/Shanghai",
    "iso:country":"CN",
    "name:zho_x_preferred":[
        "\u6865\u6c9f\u6751"
    ],
    "wof:name":"Qiaogoucun",
    "wof:placetype":"locality"
},
  "geometry": {"coordinates":[109.61089,37.23825],"type":"Point"}
}