{
  "type": "Feature",
  "properties": {
    "gn:admin1_code":"32.0",
    "gn:asciiname":"Yanggongsi",
    "gn:country_code":"CN",
    "gn:dem":655,
    "gn:feature_class":"P",
    "gn:feature_code":"PPL",
    "gn:name":"Yanggongsi",
    "gn:population":0,
    "gn:timezone":"Asia/Shanghai",
    "iso:country":"CN",
    "name:zho_x_preferred":[
        "\u6768\u516c\u5bfa"
    ],
    "wof:name":"Yanggongsi",
    "wof:placetype":"locality"
},
  "geometry": {"coordinates":[104.866,28.2915],"type":"Point"}
}