{
  "type": "Feature",
  "properties": {
    "gn:admin1_code":"5.0",
    "gn:asciiname":"Xihangnaihuoshao",
    "gn:country_code":"CN",
    "gn:dem":134,
    "gn:feature_class":"P",
    "gn:feature_code":"PPL",
    "gn:name":"Xihangnaihuoshao",
    "gn:population":0,
    "gn:timezone":"Asia/Shanghai",
    "iso:country":"CN",
    "name:zho_x_preferred":[
        "\u897f\u676d\u4e43\u706b\u70e7"
    ],
    "wof:name":"Xihangnaihuoshao",
    "wof:placetype":"locality"
},
  "geometry": {"coordinates":[123.53265,46.07001],"type":"Point"}
}