{
  "type": "Feature",
  "properties": {
    "gn:admin1_code":"4.0",
    "gn:asciiname":"Shunan",
    "gn:country_code":"CN",
    "gn:dem":3,
    "gn:feature_class":"P",
    "gn:feature_code":"PPL",
    "gn:name":"Shunan",
    "gn:population":0,
    "gn:timezone":"Asia/Shanghai",
    "iso:country":"CN",
    "name:zho_x_preferred":[
        "\u7ad6\u5357"
    ],
    "wof:name":"Shunan",
    "wof:placetype":"locality"
},
  "geometry": {"coordinates":[119.68844,31.48841],"type":"Point"}
}