{
  "type": "Feature",
  "properties": {
    "gn:admin1_code":"19.0",
    "gn:asciiname":"Shilingzicun",
    "gn:country_code":"CN",
    "gn:dem":79,
    "gn:feature_class":"P",
    "gn:feature_code":"PPL",
    "gn:name":"Shilingzicun",
    "gn:population":0,
    "gn:timezone":"Asia/Shanghai",
    "iso:country":"CN",
    "name:zho_x_preferred":[
        "\u77f3\u5cad\u5b50\u6751"
    ],
    "wof:name":"Shilingzicun",
    "wof:placetype":"locality"
},
  "geometry": {"coordinates":[122.514,42.2863],"type":"Point"}
}