{
  "type": "Feature",
  "properties": {
    "gn:admin1_code":"07",
    "gn:asciiname":"Xiaqi",
    "gn:country_code":"CN",
    "gn:dem":608,
    "gn:feature_class":"P",
    "gn:feature_code":"PPL",
    "gn:name":"Xiaqi",
    "gn:population":0,
    "gn:timezone":"Asia/Shanghai",
    "iso:country":"CN",
    "name:zho_x_preferred":[
        "\u4e0b\u78dc"
    ],
    "wof:name":"Xiaqi",
    "wof:placetype":"locality"
},
  "geometry": {"coordinates":[117.86144,25.16001],"type":"Point"}
}