{
  "type": "Feature",
  "properties": {
    "gn:admin1_code":"19.0",
    "gn:asciiname":"Xintun",
    "gn:country_code":"CN",
    "gn:dem":64,
    "gn:feature_class":"P",
    "gn:feature_code":"PPL",
    "gn:name":"Xintun",
    "gn:population":0,
    "gn:timezone":"Asia/Shanghai",
    "iso:country":"CN",
    "name:und_x_variant":[
        "\u65b0\u5c6f"
    ],
    "name:zho_x_preferred":[
        "\u65b0\u5c6f"
    ],
    "wof:name":"Xintun",
    "wof:placetype":"locality"
},
  "geometry": {"coordinates":[123.73652,42.19171],"type":"Point"}
}