{
  "type": "Feature",
  "properties": {
    "gn:admin1_code":"16.0",
    "gn:asciiname":"Longjue",
    "gn:country_code":"CN",
    "gn:dem":262,
    "gn:feature_class":"P",
    "gn:feature_code":"PPL",
    "gn:name":"Longjue",
    "gn:population":0,
    "gn:timezone":"Asia/Shanghai",
    "iso:country":"CN",
    "name:zho_x_preferred":[
        "\u9647\u8568"
    ],
    "wof:name":"Longjue",
    "wof:placetype":"locality"
},
  "geometry": {"coordinates":[107.002,22.6352],"type":"Point"}
}