{
  "type": "Feature",
  "properties": {
    "gn:admin1_code":"26.0",
    "gn:asciiname":"Yaodiancun",
    "gn:country_code":"CN",
    "gn:dem":558,
    "gn:feature_class":"P",
    "gn:feature_code":"PPL",
    "gn:name":"Yaodiancun",
    "gn:population":0,
    "gn:timezone":"Asia/Shanghai",
    "iso:country":"CN",
    "name:zho_x_preferred":[
        "\u8170\u5e97\u6751"
    ],
    "wof:name":"Yaodiancun",
    "wof:placetype":"locality"
},
  "geometry": {"coordinates":[108.34914000000001,32.80723],"type":"Point"}
}