{
  "type": "Feature",
  "properties": {
    "gn:admin1_code":"7.0",
    "gn:asciiname":"Jiangkeng",
    "gn:country_code":"CN",
    "gn:dem":345,
    "gn:feature_class":"P",
    "gn:feature_code":"PPL",
    "gn:name":"Jiangkeng",
    "gn:population":0,
    "gn:timezone":"Asia/Shanghai",
    "iso:country":"CN",
    "name:und_x_variant":[
        "\u5c06\u5751"
    ],
    "name:zho_x_preferred":[
        "\u5c06\u5751"
    ],
    "wof:name":"Jiangkeng",
    "wof:placetype":"locality"
},
  "geometry": {"coordinates":[116.49432,25.56899],"type":"Point"}
}