{
  "type": "Feature",
  "properties": {
    "gn:admin1_code":"30.0",
    "gn:asciiname":"Liangjiang",
    "gn:country_code":"CN",
    "gn:dem":98,
    "gn:feature_class":"P",
    "gn:feature_code":"PPL",
    "gn:name":"Liangjiang",
    "gn:population":0,
    "gn:timezone":"Asia/Shanghai",
    "iso:country":"CN",
    "name:zho_x_preferred":[
        "Liangjiang"
    ],
    "name:zho_x_variant":[
        "\u826f\u6c5f"
    ],
    "wof:name":"Liangjiang",
    "wof:placetype":"locality"
},
  "geometry": {"coordinates":[112.38388999999999,24.80556],"type":"Point"}
}