{
  "type": "Feature",
  "properties": {
    "gn:admin1_code":"12.0",
    "gn:asciiname":"Dacaojiazui",
    "gn:country_code":"CN",
    "gn:dem":78,
    "gn:feature_class":"P",
    "gn:feature_code":"PPL",
    "gn:name":"Dacaojiazui",
    "gn:population":0,
    "gn:timezone":"Asia/Shanghai",
    "iso:country":"CN",
    "name:zho_x_preferred":[
        "\u5927\u66f9\u5bb6\u5480"
    ],
    "wof:name":"Dacaojiazui",
    "wof:placetype":"locality"
},
  "geometry": {"coordinates":[112.18470000000001,31.34563],"type":"Point"}
}