{
  "type": "Feature",
  "properties": {
    "gn:admin1_code":"2.0",
    "gn:asciiname":"Long'ertou",
    "gn:country_code":"CN",
    "gn:dem":559,
    "gn:feature_class":"P",
    "gn:feature_code":"PPL",
    "gn:name":"Long\u2019ertou",
    "gn:population":0,
    "gn:timezone":"Asia/Shanghai",
    "iso:country":"CN",
    "name:und_x_variant":[
        "Long\u2019ertou"
    ],
    "name:zho_x_preferred":[
        "\u9f99\u513f\u5934"
    ],
    "wof:name":"Long'ertou",
    "wof:placetype":"locality"
},
  "geometry": {"coordinates":[120.08514,27.81411],"type":"Point"}
}