{
  "type": "Feature",
  "properties": {
    "gn:admin1_code":"15.0",
    "gn:asciiname":"Yuantanzi",
    "gn:country_code":"CN",
    "gn:dem":1848,
    "gn:feature_class":"P",
    "gn:feature_code":"PPL",
    "gn:name":"Yuantanzi",
    "gn:population":0,
    "gn:timezone":"Asia/Shanghai",
    "iso:country":"CN",
    "name:und_x_variant":[
        "\u56ed\u6ee9\u5b50"
    ],
    "wof:name":"Yuantanzi",
    "wof:placetype":"locality"
},
  "geometry": {"coordinates":[105.34625,33.36251],"type":"Point"}
}