{
  "type": "Feature",
  "properties": {
    "gn:admin1_code":"30.0",
    "gn:asciiname":"Huaidongcun",
    "gn:country_code":"CN",
    "gn:dem":177,
    "gn:feature_class":"P",
    "gn:feature_code":"PPL",
    "gn:name":"Huaidongcun",
    "gn:population":0,
    "gn:timezone":"Asia/Shanghai",
    "iso:country":"CN",
    "name:zho_x_preferred":[
        "\u6dee\u6d1e\u6751"
    ],
    "wof:name":"Huaidongcun",
    "wof:placetype":"locality"
},
  "geometry": {"coordinates":[116.05192,24.05018],"type":"Point"}
}