{
  "type": "Feature",
  "properties": {
    "gn:admin1_code":"20.0",
    "gn:asciiname":"Guangmingdui Nongyedian",
    "gn:country_code":"CN",
    "gn:dem":634,
    "gn:feature_class":"P",
    "gn:feature_code":"PPL",
    "gn:name":"Guangmingdui Nongyedian",
    "gn:population":0,
    "gn:timezone":"Asia/Shanghai",
    "iso:country":"CN",
    "name:zho_x_preferred":[
        "\u5149\u660e\u961f\u519c\u4e1a\u70b9"
    ],
    "wof:name":"Guangmingdui Nongyedian",
    "wof:placetype":"locality"
},
  "geometry": {"coordinates":[119.93136,49.18494000000001],"type":"Point"}
}