{
  "type": "Feature",
  "properties": {
    "gn:admin1_code":"2.0",
    "gn:asciiname":"Cheng`ao",
    "gn:country_code":"CN",
    "gn:dem":24,
    "gn:feature_class":"P",
    "gn:feature_code":"PPL",
    "gn:name":"Cheng\u2018ao",
    "gn:population":0,
    "gn:timezone":"Asia/Shanghai",
    "iso:country":"CN",
    "name:zho_x_preferred":[
        "Cheng\u2018ao"
    ],
    "wof:name":"Cheng`ao",
    "wof:placetype":"locality"
},
  "geometry": {"coordinates":[120.87381999999999,29.74476],"type":"Point"}
}