{
  "type": "Feature",
  "properties": {
    "gn:admin1_code":"11.0",
    "gn:asciiname":"Baiyinzhang",
    "gn:country_code":"CN",
    "gn:dem":29,
    "gn:feature_class":"P",
    "gn:feature_code":"PPL",
    "gn:name":"Baiyinzhang",
    "gn:population":0,
    "gn:timezone":"Asia/Shanghai",
    "iso:country":"CN",
    "name:zho_x_preferred":[
        "\u767e\u5f15\u969c"
    ],
    "wof:name":"Baiyinzhang",
    "wof:placetype":"locality"
},
  "geometry": {"coordinates":[112.04275,28.81622],"type":"Point"}
}