{
  "type": "Feature",
  "properties": {
    "gn:admin1_code":"30",
    "gn:asciiname":"Shiluo",
    "gn:country_code":"CN",
    "gn:dem":77,
    "gn:feature_class":"P",
    "gn:feature_code":"PPL",
    "gn:name":"Shiluo",
    "gn:population":0,
    "gn:timezone":"Asia/Shanghai",
    "iso:country":"CN",
    "name:und_x_variant":[
        "\u77f3\u87ba"
    ],
    "wof:name":"Shiluo",
    "wof:placetype":"locality"
},
  "geometry": {"coordinates":[112.54125000000001,24.60397],"type":"Point"}
}