{
  "type": "Feature",
  "properties": {
    "gn:admin1_code":"11.0",
    "gn:asciiname":"Dazujiao",
    "gn:country_code":"CN",
    "gn:dem":272,
    "gn:feature_class":"P",
    "gn:feature_code":"PPL",
    "gn:name":"Dazujiao",
    "gn:population":0,
    "gn:timezone":"Asia/Shanghai",
    "iso:country":"CN",
    "name:zho_x_preferred":[
        "\u5927\u7956\u811a"
    ],
    "wof:name":"Dazujiao",
    "wof:placetype":"locality"
},
  "geometry": {"coordinates":[111.5004,24.89049],"type":"Point"}
}