{
  "type": "Feature",
  "properties": {
    "gn:admin1_code":"11",
    "gn:asciiname":"Xiangjiang",
    "gn:country_code":"CN",
    "gn:dem":774,
    "gn:feature_class":"P",
    "gn:feature_code":"PPLA4",
    "gn:name":"Xiangjiang",
    "gn:population":0,
    "gn:timezone":"Asia/Shanghai",
    "iso:country":"CN",
    "name:und_x_variant":[
        "Xiangjiang Xiang",
        "\u6e58\u6c5f\u4e61",
        "Xiangjiang"
    ],
    "name:zho_x_preferred":[
        "\u6e58\u6c5f"
    ],
    "wof:name":"Xiangjiang",
    "wof:placetype":"locality"
},
  "geometry": {"coordinates":[111.81917,25.06917],"type":"Point"}
}