{
  "type": "Feature",
  "properties": {
    "gn:admin1_code":"1.0",
    "gn:asciiname":"Chuyuancun",
    "gn:country_code":"CN",
    "gn:dem":39,
    "gn:feature_class":"P",
    "gn:feature_code":"PPL",
    "gn:name":"Chuyuancun",
    "gn:population":0,
    "gn:timezone":"Asia/Shanghai",
    "iso:country":"CN",
    "name:zho_x_preferred":[
        "\u695a\u56ed\u6751"
    ],
    "wof:name":"Chuyuancun",
    "wof:placetype":"locality"
},
  "geometry": {"coordinates":[115.89909,33.78535],"type":"Point"}
}