{
  "type": "Feature",
  "properties": {
    "gn:admin1_code":"32.0",
    "gn:asciiname":"Xiaojingtang",
    "gn:country_code":"CN",
    "gn:dem":2833,
    "gn:feature_class":"P",
    "gn:feature_code":"PPL",
    "gn:name":"Xiaojingtang",
    "gn:population":0,
    "gn:timezone":"Asia/Shanghai",
    "iso:country":"CN",
    "name:zho_x_preferred":[
        "\u5c0f\u7ecf\u5802"
    ],
    "wof:name":"Xiaojingtang",
    "wof:placetype":"locality"
},
  "geometry": {"coordinates":[101.247,27.8311],"type":"Point"}
}