{
  "type": "Feature",
  "properties": {
    "gn:admin1_code":"33.0",
    "gn:asciiname":"Xinxi",
    "gn:country_code":"CN",
    "gn:dem":571,
    "gn:feature_class":"P",
    "gn:feature_code":"PPL",
    "gn:name":"Xinxi",
    "gn:population":0,
    "gn:timezone":"Asia/Shanghai",
    "iso:country":"CN",
    "name:zho_x_preferred":[
        "\u65b0\u6eaa"
    ],
    "wof:name":"Xinxi",
    "wof:placetype":"locality"
},
  "geometry": {"coordinates":[107.68273000000001,29.73716],"type":"Point"}
}