{
  "type": "Feature",
  "properties": {
    "gn:admin1_code":"21",
    "gn:asciiname":"Qiying",
    "gn:country_code":"CN",
    "gn:dem":1468,
    "gn:feature_class":"P",
    "gn:feature_code":"PPLA4",
    "gn:name":"Qiying",
    "gn:population":0,
    "gn:timezone":"Asia/Shanghai",
    "iso:country":"CN",
    "name:und_x_variant":[
        "Ch\u2019i-ying",
        "Qiying",
        "\u4e03\u8425",
        "Qiying Zhen",
        "\u4e03\u8425\u9547"
    ],
    "wof:name":"Qiying",
    "wof:placetype":"locality"
},
  "geometry": {"coordinates":[106.14861999999999,36.50324000000001],"type":"Point"}
}