{
  "type": "Feature",
  "properties": {
    "gn:admin1_code":"8.0",
    "gn:asciiname":"Duilijia",
    "gn:country_code":"CN",
    "gn:dem":187,
    "gn:feature_class":"P",
    "gn:feature_code":"PPL",
    "gn:name":"Duilijia",
    "gn:population":0,
    "gn:timezone":"Asia/Shanghai",
    "iso:country":"CN",
    "name:zho_x_preferred":[
        "\u5bf9\u674e\u5bb6"
    ],
    "wof:name":"Duilijia",
    "wof:placetype":"locality"
},
  "geometry": {"coordinates":[127.10127,45.01675],"type":"Point"}
}