{
  "type": "Feature",
  "properties": {
    "gn:admin1_code":"18",
    "gn:asciiname":"Jichangping",
    "gn:country_code":"CN",
    "gn:dem":1003,
    "gn:feature_class":"P",
    "gn:feature_code":"PPL",
    "gn:name":"Jichangping",
    "gn:population":0,
    "gn:timezone":"Asia/Shanghai",
    "iso:country":"CN",
    "name:zho_x_preferred":[
        "\u9e21\u573a\u576a"
    ],
    "wof:name":"Jichangping",
    "wof:placetype":"locality"
},
  "geometry": {"coordinates":[107.101,26.1196],"type":"Point"}
}