{
  "type": "Feature",
  "properties": {
    "gn:admin1_code":"4.0",
    "gn:asciiname":"Qiujiabu",
    "gn:country_code":"CN",
    "gn:dem":3,
    "gn:feature_class":"P",
    "gn:feature_code":"PPL",
    "gn:name":"Qiujiabu",
    "gn:population":0,
    "gn:timezone":"Asia/Shanghai",
    "iso:country":"CN",
    "name:zho_x_preferred":[
        "\u4ec7\u5bb6\u5821"
    ],
    "wof:name":"Qiujiabu",
    "wof:placetype":"locality"
},
  "geometry": {"coordinates":[120.22019,32.81003],"type":"Point"}
}