{
  "type": "Feature",
  "properties": {
    "gn:admin1_code":"5.0",
    "gn:asciiname":"Daxiao Dingzi",
    "gn:country_code":"CN",
    "gn:dem":467,
    "gn:feature_class":"P",
    "gn:feature_code":"PPL",
    "gn:name":"Daxiao Dingzi",
    "gn:population":0,
    "gn:timezone":"Asia/Shanghai",
    "iso:country":"CN",
    "name:zho_x_preferred":[
        "\u5927\u5c0f\u9876\u5b50"
    ],
    "wof:name":"Daxiao Dingzi",
    "wof:placetype":"locality"
},
  "geometry": {"coordinates":[126.5141,42.55111],"type":"Point"}
}