{
  "type": "Feature",
  "properties": {
    "gn:admin1_code":"7.0",
    "gn:asciiname":"Tongzhong",
    "gn:country_code":"CN",
    "gn:dem":32,
    "gn:feature_class":"P",
    "gn:feature_code":"PPL",
    "gn:name":"Tongzhong",
    "gn:population":0,
    "gn:timezone":"Asia/Shanghai",
    "iso:country":"CN",
    "name:zho_x_preferred":[
        "\u94dc\u4e2d"
    ],
    "wof:name":"Tongzhong",
    "wof:placetype":"locality"
},
  "geometry": {"coordinates":[117.35568000000001,24.39282],"type":"Point"}
}