{
  "type": "Feature",
  "properties": {
    "gn:admin1_code":"9.0",
    "gn:asciiname":"Mahu",
    "gn:country_code":"CN",
    "gn:dem":48,
    "gn:feature_class":"P",
    "gn:feature_code":"PPL",
    "gn:name":"Mahu",
    "gn:population":0,
    "gn:timezone":"Asia/Shanghai",
    "iso:country":"CN",
    "name:ceb_x_preferred":[
        "Mahu"
    ],
    "name:deu_x_preferred":[
        "Mahu"
    ],
    "name:rus_x_preferred":[
        "\u041c\u0430\u0445\u0443"
    ],
    "name:spa_x_preferred":[
        "Mahu"
    ],
    "name:swe_x_preferred":[
        "Mahu"
    ],
    "name:zho_x_preferred":[
        "\u9a6c\u6e56"
    ],
    "wof:name":"Mahu",
    "wof:placetype":"locality"
},
  "geometry": {"coordinates":[114.99173999999999,32.03084],"type":"Point"}
}