{
  "type": "Feature",
  "properties": {
    "gn:admin1_code":"32.0",
    "gn:asciiname":"Gongse",
    "gn:country_code":"CN",
    "gn:dem":3193,
    "gn:feature_class":"P",
    "gn:feature_code":"PPL",
    "gn:name":"Gongse",
    "gn:population":0,
    "gn:timezone":"Asia/Shanghai",
    "iso:country":"CN",
    "name:zho_x_preferred":[
        "\u5171\u8272"
    ],
    "wof:name":"Gongse",
    "wof:placetype":"locality"
},
  "geometry": {"coordinates":[101.807,32.6349],"type":"Point"}
}