{
  "type": "Feature",
  "properties": {
    "gn:admin1_code":"12.0",
    "gn:asciiname":"Tangzichong",
    "gn:country_code":"CN",
    "gn:dem":112,
    "gn:feature_class":"P",
    "gn:feature_code":"PPL",
    "gn:name":"Tangzichong",
    "gn:population":0,
    "gn:timezone":"Asia/Shanghai",
    "iso:country":"CN",
    "name:zho_x_preferred":[
        "\u5858\u6893\u51b2"
    ],
    "wof:name":"Tangzichong",
    "wof:placetype":"locality"
},
  "geometry": {"coordinates":[113.79598,29.2229],"type":"Point"}
}