{
  "type": "Feature",
  "properties": {
    "gn:admin1_code":"2.0",
    "gn:asciiname":"Tanlingtou",
    "gn:country_code":"CN",
    "gn:dem":42,
    "gn:feature_class":"P",
    "gn:feature_code":"PPL",
    "gn:name":"Tanlingtou",
    "gn:population":0,
    "gn:timezone":"Asia/Shanghai",
    "iso:country":"CN",
    "name:zho_x_preferred":[
        "\u6ee9\u5cad\u5934"
    ],
    "wof:name":"Tanlingtou",
    "wof:placetype":"locality"
},
  "geometry": {"coordinates":[121.06223,29.06949],"type":"Point"}
}