{
  "type": "Feature",
  "properties": {
    "gn:admin1_code":"29.0",
    "gn:asciiname":"Naban",
    "gn:country_code":"CN",
    "gn:dem":921,
    "gn:feature_class":"P",
    "gn:feature_code":"PPL",
    "gn:name":"Naban",
    "gn:population":0,
    "gn:timezone":"Asia/Shanghai",
    "iso:country":"CN",
    "name:zho_x_preferred":[
        "\u7eb3\u677f"
    ],
    "wof:name":"Naban",
    "wof:placetype":"locality"
},
  "geometry": {"coordinates":[100.93000000000001,22.1761],"type":"Point"}
}