{
  "type": "Feature",
  "properties": {
    "gn:admin1_code":"24",
    "gn:asciiname":"Huangniuti",
    "gn:cc2":"CN",
    "gn:country_code":"CN",
    "gn:dem":764,
    "gn:feature_class":"P",
    "gn:feature_code":"PPL",
    "gn:name":"Huangniuti",
    "gn:population":0,
    "gn:timezone":"Asia/Shanghai",
    "iso:country":"CN",
    "name:und_x_variant":[
        "Huang-niu-t\u2019i-ts\u2019un",
        "Huangniuti"
    ],
    "wof:name":"Huangniuti",
    "wof:placetype":"locality"
},
  "geometry": {"coordinates":[113.36667,36.31667],"type":"Point"}
}