{
  "type": "Feature",
  "properties": {
    "gn:admin1_code":"8.0",
    "gn:asciiname":"Gangtiecun",
    "gn:country_code":"CN",
    "gn:dem":252,
    "gn:feature_class":"P",
    "gn:feature_code":"PPL",
    "gn:name":"Gangtiecun",
    "gn:population":0,
    "gn:timezone":"Asia/Shanghai",
    "iso:country":"CN",
    "name:zho_x_preferred":[
        "\u94a2\u94c1\u6751"
    ],
    "wof:name":"Gangtiecun",
    "wof:placetype":"locality"
},
  "geometry": {"coordinates":[126.28766,47.86182],"type":"Point"}
}