{
  "type": "Feature",
  "properties": {
    "gn:admin1_code":"11",
    "gn:asciiname":"Xinpanzhang",
    "gn:country_code":"CN",
    "gn:dem":406,
    "gn:feature_class":"P",
    "gn:feature_code":"PPL",
    "gn:name":"Xinpanzhang",
    "gn:population":0,
    "gn:timezone":"Asia/Shanghai",
    "iso:country":"CN",
    "name:und_x_variant":[
        "\u65b0\u6cee\u6f33",
        "Xinpanzhang"
    ],
    "wof:name":"Xinpanzhang",
    "wof:placetype":"locality"
},
  "geometry": {"coordinates":[111.84193999999999,25.71472],"type":"Point"}
}