{
  "type": "Feature",
  "properties": {
    "gn:admin1_code":"07",
    "gn:asciiname":"Jiangtian",
    "gn:country_code":"CN",
    "gn:dem":13,
    "gn:feature_class":"P",
    "gn:feature_code":"PPLA4",
    "gn:name":"Jiangtian",
    "gn:population":0,
    "gn:timezone":"Asia/Shanghai",
    "iso:country":"CN",
    "name:und_x_variant":[
        "Kengtien",
        "Chiang-t\u2019ien",
        "Jiangtian",
        "Jiangtian Zhen"
    ],
    "name:zho_x_preferred":[
        "\u6c5f\u7530"
    ],
    "name:zho_x_variant":[
        "\u6c5f\u7530\u9547"
    ],
    "wof:name":"Jiangtian",
    "wof:placetype":"locality"
},
  "geometry": {"coordinates":[119.57518,25.81947000000001],"type":"Point"}
}