{
  "type": "Feature",
  "properties": {
    "gn:admin1_code":"14.0",
    "gn:asciiname":"Sharencun",
    "gn:country_code":"CN",
    "gn:dem":3023,
    "gn:feature_class":"P",
    "gn:feature_code":"PPL",
    "gn:name":"Sharencun",
    "gn:population":0,
    "gn:timezone":"Asia/Urumqi",
    "iso:country":"CN",
    "name:zho_x_preferred":[
        "\u6c99\u4ec1\u6751"
    ],
    "wof:name":"Sharencun",
    "wof:placetype":"locality"
},
  "geometry": {"coordinates":[95.38299000000001,30.24069],"type":"Point"}
}