{
  "type": "Feature",
  "properties": {
    "gn:admin1_code":"13",
    "gn:asciiname":"Ahetaqi",
    "gn:country_code":"CN",
    "gn:dem":1312,
    "gn:feature_class":"P",
    "gn:feature_code":"PPL",
    "gn:name":"Ahetaqi",
    "gn:population":0,
    "gn:timezone":"Asia/Shanghai",
    "iso:country":"CN",
    "name:und_x_variant":[
        "\u963f\u5408\u5854\u5176"
    ],
    "wof:name":"Ahetaqi",
    "wof:placetype":"locality"
},
  "geometry": {"coordinates":[77.16718,38.15947],"type":"Point"}
}