{
  "type": "Feature",
  "properties": {
    "gn:admin1_code":"12.0",
    "gn:asciiname":"Dunzigang",
    "gn:country_code":"CN",
    "gn:dem":72,
    "gn:feature_class":"P",
    "gn:feature_code":"PPL",
    "gn:name":"Dunzigang",
    "gn:population":0,
    "gn:timezone":"Asia/Shanghai",
    "iso:country":"CN",
    "name:zho_x_preferred":[
        "\u58a9\u5b50\u5c97"
    ],
    "wof:name":"Dunzigang",
    "wof:placetype":"locality"
},
  "geometry": {"coordinates":[114.28842,31.17259],"type":"Point"}
}