{
  "type": "Feature",
  "properties": {
    "gn:admin1_code":"25",
    "gn:asciiname":"Litang",
    "gn:country_code":"CN",
    "gn:dem":40,
    "gn:feature_class":"P",
    "gn:feature_code":"PPL",
    "gn:name":"Litang",
    "gn:population":0,
    "gn:timezone":"Asia/Shanghai",
    "iso:country":"CN",
    "name:ceb_x_preferred":[
        "Litang"
    ],
    "name:nld_x_preferred":[
        "Litang"
    ],
    "name:zho_x_preferred":[
        "\u674e\u5802"
    ],
    "wof:name":"Litang",
    "wof:placetype":"locality"
},
  "geometry": {"coordinates":[116.282,35.1624],"type":"Point"}
}