{
  "type": "Feature",
  "properties": {
    "gn:admin1_code":"30.0",
    "gn:asciiname":"Dacun",
    "gn:country_code":"CN",
    "gn:dem":102,
    "gn:feature_class":"P",
    "gn:feature_code":"PPL",
    "gn:name":"Dacun",
    "gn:population":0,
    "gn:timezone":"Asia/Shanghai",
    "iso:country":"CN",
    "name:zho_x_preferred":[
        "Dacun"
    ],
    "name:zho_x_variant":[
        "\u5927\u6751"
    ],
    "wof:name":"Dacun",
    "wof:placetype":"locality"
},
  "geometry": {"coordinates":[112.39444,24.58194],"type":"Point"}
}