{
  "type": "Feature",
  "properties": {
    "gn:admin1_code":"30.0",
    "gn:asciiname":"Dacun",
    "gn:country_code":"CN",
    "gn:dem":102,
    "gn:feature_class":"P",
    "gn:feature_code":"PPL",
    "gn:name":"Dacun",
    "gn:population":0,
    "gn:timezone":"Asia/Shanghai",
    "iso:country":"CN",
    "name:ceb_x_preferred":[
        "Dacun Xiang"
    ],
    "name:hak_x_preferred":[
        "Thai-tsh\u00fbn-hi\u00f4ng"
    ],
    "name:ita_x_preferred":[
        "Dacun"
    ],
    "name:jpn_x_preferred":[
        "\u5927\u6751\u90f7"
    ],
    "name:kor_x_preferred":[
        "\ub2e4\ucd98\ud5a5"
    ],
    "name:pol_x_preferred":[
        "Dacun"
    ],
    "name:vie_x_preferred":[
        "\u0110\u1ea1i Th\u00f4n"
    ],
    "name:zho_x_preferred":[
        "Dacun"
    ],
    "name:zho_x_variant":[
        "\u5927\u6751",
        "\u5927\u6751\u9109"
    ],
    "wof:name":"Dacun",
    "wof:placetype":"locality"
},
  "geometry": {"coordinates":[112.39444,24.58194],"type":"Point"}
}