{
  "type": "Feature",
  "properties": {
    "gn:admin1_code":"11.0",
    "gn:asciiname":"Yijiachong",
    "gn:country_code":"CN",
    "gn:dem":224,
    "gn:feature_class":"P",
    "gn:feature_code":"PPL",
    "gn:name":"Yijiachong",
    "gn:population":0,
    "gn:timezone":"Asia/Shanghai",
    "iso:country":"CN",
    "name:zho_x_preferred":[
        "\u4e59\u5bb6\u51b2"
    ],
    "wof:name":"Yijiachong",
    "wof:placetype":"locality"
},
  "geometry": {"coordinates":[110.89688,28.14963],"type":"Point"}
}