{
  "type": "Feature",
  "properties": {
    "gn:admin1_code":"32.0",
    "gn:asciiname":"Lihuo'amo",
    "gn:country_code":"CN",
    "gn:dem":3025,
    "gn:feature_class":"P",
    "gn:feature_code":"PPL",
    "gn:name":"Lihuo\u2019amo",
    "gn:population":0,
    "gn:timezone":"Asia/Shanghai",
    "iso:country":"CN",
    "name:und_x_variant":[
        "Lihuo\u2019amo"
    ],
    "name:zho_x_preferred":[
        "\u529b\u970d\u963f\u83ab"
    ],
    "wof:name":"Lihuo'amo",
    "wof:placetype":"locality"
},
  "geometry": {"coordinates":[102.029,27.8803],"type":"Point"}
}