{
  "type": "Feature",
  "properties": {
    "gn:admin1_code":"26.0",
    "gn:asciiname":"Zhaojiayahuo",
    "gn:country_code":"CN",
    "gn:dem":1511,
    "gn:feature_class":"P",
    "gn:feature_code":"PPL",
    "gn:name":"Zhaojiayahuo",
    "gn:population":0,
    "gn:timezone":"Asia/Shanghai",
    "iso:country":"CN",
    "name:und_x_variant":[
        "\u8d75\u5bb6\u57ad\u8c41"
    ],
    "wof:name":"Zhaojiayahuo",
    "wof:placetype":"locality"
},
  "geometry": {"coordinates":[106.55074999999999,33.96536],"type":"Point"}
}