{
  "type": "Feature",
  "properties": {
    "gn:admin1_code":"1.0",
    "gn:asciiname":"Hongmiaocun",
    "gn:country_code":"CN",
    "gn:dem":63,
    "gn:feature_class":"P",
    "gn:feature_code":"PPL",
    "gn:name":"Hongmiaocun",
    "gn:population":0,
    "gn:timezone":"Asia/Shanghai",
    "iso:country":"CN",
    "name:und_x_variant":[
        "Hongmiao",
        "Hongmiaocun"
    ],
    "name:zho_x_preferred":[
        "\u7ea2\u5e99"
    ],
    "name:zho_x_variant":[
        "\u7ea2\u5e99\u6751"
    ],
    "wof:name":"Hongmiaocun",
    "wof:placetype":"locality"
},
  "geometry": {"coordinates":[118.90942,31.04026],"type":"Point"}
}