{
  "type": "Feature",
  "properties": {
    "gn:admin1_code":"9.0",
    "gn:asciiname":"Xiejiazhuang",
    "gn:country_code":"CN",
    "gn:dem":987,
    "gn:feature_class":"P",
    "gn:feature_code":"PPL",
    "gn:name":"Xiejiazhuang",
    "gn:population":0,
    "gn:timezone":"Asia/Shanghai",
    "iso:country":"CN",
    "name:zho_x_preferred":[
        "\u8c22\u5bb6\u5e84"
    ],
    "wof:name":"Xiejiazhuang",
    "wof:placetype":"locality"
},
  "geometry": {"coordinates":[111.85133,33.55535],"type":"Point"}
}