{
  "type": "Feature",
  "properties": {
    "gn:admin1_code":"15",
    "gn:asciiname":"Maya",
    "gn:country_code":"CN",
    "gn:dem":2384,
    "gn:feature_class":"P",
    "gn:feature_code":"PPL",
    "gn:name":"Maya",
    "gn:population":0,
    "gn:timezone":"Asia/Shanghai",
    "iso:country":"CN",
    "name:ara_x_preferred":[
        "\u0645\u0627\u064a\u0627"
    ],
    "name:ast_x_preferred":[
        "Maya"
    ],
    "name:cdo_x_preferred":[
        "Maya"
    ],
    "name:ceb_x_preferred":[
        "Maya"
    ],
    "name:ces_x_preferred":[
        "Maya"
    ],
    "name:deu_x_preferred":[
        "Maya"
    ],
    "name:ell_x_preferred":[
        "\u039c\u03b1\u03af\u03b1"
    ],
    "name:fas_x_preferred":[
        "\u0645\u0627\u06cc\u0627"
    ],
    "name:fin_x_preferred":[
        "Maya"
    ],
    "name:fra_x_preferred":[
        "Maya"
    ],
    "name:heb_x_preferred":[
        "\u05de\u05d0\u05d9\u05d0\u05d1\u05e7"
    ],
    "name:heb_x_variant":[
        "\u05de\u05d0\u05d9\u05d4"
    ],
    "name:hin_x_preferred":[
        "\u092e\u093e\u092f\u093e"
    ],
    "name:ind_x_preferred":[
        "Maya"
    ],
    "name:ita_x_preferred":[
        "Maya"
    ],
    "name:jpn_x_preferred":[
        "\u30de\u30e4"
    ],
    "name:lav_x_preferred":[
        "Maya"
    ],
    "name:nds_x_preferred":[
        "Maya"
    ],
    "name:nld_x_preferred":[
        "Maya"
    ],
    "name:nno_x_preferred":[
        "Maya"
    ],
    "name:pol_x_preferred":[
        "Maya"
    ],
    "name:por_x_preferred":[
        "Maya"
    ],
    "name:que_x_preferred":[
        "Maya"
    ],
    "name:ron_x_preferred":[
        "Maya"
    ],
    "name:rus_x_preferred":[
        "Maya"
    ],
    "name:sin_x_preferred":[
        "\u0db8\u0dcf\u0dba\u0dcf"
    ],
    "name:spa_x_preferred":[
        "Maya"
    ],
    "name:swe_x_preferred":[
        "Mayafloden"
    ],
    "name:swe_x_variant":[
        "Maya"
    ],
    "name:tat_x_preferred":[
        "\u041c\u0430\u0439\u044f\u043b\u0430\u0440"
    ],
    "name:tgl_x_preferred":[
        "Maya"
    ],
    "name:tur_x_preferred":[
        "Maya"
    ],
    "name:urd_x_preferred":[
        "\u0645\u0627\u06cc\u0627"
    ],
    "name:vie_x_preferred":[
        "S\u00f4ng Maya"
    ],
    "name:vie_x_variant":[
        "Maya"
    ],
    "wof:name":"Maya",
    "wof:placetype":"locality"
},
  "geometry": {"coordinates":[103.75,33.91667],"type":"Point"}
}