{
  "type": "Feature",
  "properties": {
    "gn:admin1_code":"15",
    "gn:asciiname":"Maya",
    "gn:country_code":"CN",
    "gn:dem":2384,
    "gn:feature_class":"P",
    "gn:feature_code":"PPL",
    "gn:name":"Maya",
    "gn:population":0,
    "gn:timezone":"Asia/Shanghai",
    "iso:country":"CN",
    "wof:name":"Maya",
    "wof:placetype":"locality"
},
  "geometry": {"coordinates":[103.75,33.91667],"type":"Point"}
}