{
  "type": "Feature",
  "properties": {
    "gn:admin1_code":"30.0",
    "gn:asciiname":"Yutengcun",
    "gn:country_code":"CN",
    "gn:dem":350,
    "gn:feature_class":"P",
    "gn:feature_code":"PPL",
    "gn:name":"Yutengcun",
    "gn:population":0,
    "gn:timezone":"Asia/Shanghai",
    "iso:country":"CN",
    "name:zho_x_preferred":[
        "\u9c7c\u817e\u6751"
    ],
    "wof:name":"Yutengcun",
    "wof:placetype":"locality"
},
  "geometry": {"coordinates":[112.22516,24.14559],"type":"Point"}
}