{
  "type": "Feature",
  "properties": {
    "gn:admin1_code":"1.0",
    "gn:asciiname":"Shengjia Dazhuang",
    "gn:country_code":"CN",
    "gn:dem":31,
    "gn:feature_class":"P",
    "gn:feature_code":"PPL",
    "gn:name":"Shengjia Dazhuang",
    "gn:population":0,
    "gn:timezone":"Asia/Shanghai",
    "iso:country":"CN",
    "name:zho_x_preferred":[
        "\u76db\u5bb6\u5927\u5e84"
    ],
    "wof:name":"Shengjia Dazhuang",
    "wof:placetype":"locality"
},
  "geometry": {"coordinates":[119.03179,32.65123],"type":"Point"}
}