{
  "type": "Feature",
  "properties": {
    "gn:admin1_code":"30.0",
    "gn:asciiname":"Chixincun",
    "gn:country_code":"CN",
    "gn:dem":12,
    "gn:feature_class":"P",
    "gn:feature_code":"PPL",
    "gn:name":"Chixincun",
    "gn:population":0,
    "gn:timezone":"Asia/Shanghai",
    "iso:country":"CN",
    "name:zho_x_preferred":[
        "\u8d64\u65b0\u6751"
    ],
    "wof:name":"Chixincun",
    "wof:placetype":"locality"
},
  "geometry": {"coordinates":[114.74093999999999,22.70674],"type":"Point"}
}