{
  "type": "Feature",
  "properties": {
    "gn:admin1_code":"25",
    "gn:asciiname":"Chengshan",
    "gn:country_code":"CN",
    "gn:dem":29,
    "gn:feature_class":"P",
    "gn:feature_code":"PPLA4",
    "gn:name":"Chengshan",
    "gn:population":0,
    "gn:timezone":"Asia/Shanghai",
    "iso:country":"CN",
    "name:und_x_variant":[
        "Chengshanwei",
        "Chengshan Zhen"
    ],
    "name:zho_x_preferred":[
        "\u6210\u5c71"
    ],
    "name:zho_x_variant":[
        "\u6210\u5c71\u9547"
    ],
    "wof:name":"Chengshan",
    "wof:placetype":"locality"
},
  "geometry": {"coordinates":[122.55198,37.36716],"type":"Point"}
}