{
  "type": "Feature",
  "properties": {
    "gn:admin1_code":"30",
    "gn:asciiname":"Dinggong",
    "gn:country_code":"CN",
    "gn:dem":63,
    "gn:feature_class":"P",
    "gn:feature_code":"PPL",
    "gn:name":"Dinggong",
    "gn:population":0,
    "gn:timezone":"Asia/Urumqi",
    "iso:country":"CN",
    "name:zho_x_preferred":[
        "\u4e01\u516c"
    ],
    "wof:name":"Dinggong",
    "wof:placetype":"locality"
},
  "geometry": {"coordinates":[110.65253,22.20967000000001],"type":"Point"}
}