{
  "type": "Feature",
  "properties": {
    "gn:admin1_code":"29.0",
    "gn:asciiname":"Manhele",
    "gn:country_code":"CN",
    "gn:dem":1218,
    "gn:feature_class":"P",
    "gn:feature_code":"PPL",
    "gn:name":"Manhele",
    "gn:population":0,
    "gn:timezone":"Asia/Shanghai",
    "iso:country":"CN",
    "name:zho_x_preferred":[
        "\u66fc\u8d3a\u52d2"
    ],
    "wof:name":"Manhele",
    "wof:placetype":"locality"
},
  "geometry": {"coordinates":[100.511,21.9498],"type":"Point"}
}