{
  "type": "Feature",
  "properties": {
    "gn:admin1_code":"16",
    "gn:asciiname":"Jinya",
    "gn:cc2":"CN",
    "gn:country_code":"CN",
    "gn:dem":920,
    "gn:feature_class":"P",
    "gn:feature_code":"PPL",
    "gn:name":"Jinya",
    "gn:population":0,
    "gn:timezone":"Asia/Shanghai",
    "iso:country":"CN",
    "name:und_x_variant":[
        "Chin-ya",
        "Jinya"
    ],
    "wof:name":"Jinya",
    "wof:placetype":"locality"
},
  "geometry": {"coordinates":[106.90000000000001,24.58333],"type":"Point"}
}