{
  "type": "Feature",
  "properties": {
    "gn:admin1_code":"29.0",
    "gn:asciiname":"Qideng",
    "gn:country_code":"CN",
    "gn:dem":2027,
    "gn:feature_class":"P",
    "gn:feature_code":"PPL",
    "gn:name":"Qideng",
    "gn:population":0,
    "gn:timezone":"Asia/Shanghai",
    "iso:country":"CN",
    "name:zho_x_preferred":[
        "\u4e03\u767b"
    ],
    "wof:name":"Qideng",
    "wof:placetype":"locality"
},
  "geometry": {"coordinates":[99.4323,26.1683],"type":"Point"}
}