{
  "type": "Feature",
  "properties": {
    "gn:admin1_code":"16.0",
    "gn:asciiname":"Nengyachong",
    "gn:country_code":"CN",
    "gn:dem":159,
    "gn:feature_class":"P",
    "gn:feature_code":"PPL",
    "gn:name":"Nengyachong",
    "gn:population":0,
    "gn:timezone":"Asia/Shanghai",
    "iso:country":"CN",
    "name:zho_x_preferred":[
        "\u80fd\u7259\u51b2"
    ],
    "wof:name":"Nengyachong",
    "wof:placetype":"locality"
},
  "geometry": {"coordinates":[110.71299999999999,23.7656],"type":"Point"}
}