{
  "type": "Feature",
  "properties": {
    "gn:admin1_code":"15.0",
    "gn:asciiname":"Songliang",
    "gn:country_code":"CN",
    "gn:dem":1660,
    "gn:feature_class":"P",
    "gn:feature_code":"PPL",
    "gn:name":"Songliang",
    "gn:population":0,
    "gn:timezone":"Asia/Shanghai",
    "iso:country":"CN",
    "name:zho_x_preferred":[
        "\u5b8b\u6881"
    ],
    "wof:name":"Songliang",
    "wof:placetype":"locality"
},
  "geometry": {"coordinates":[104.03100000000001,37.1215],"type":"Point"}
}