{
  "type": "Feature",
  "properties": {
    "gn:admin1_code":"24.0",
    "gn:asciiname":"Jingyang",
    "gn:country_code":"CN",
    "gn:dem":692,
    "gn:feature_class":"P",
    "gn:feature_code":"PPL",
    "gn:name":"Jingyang",
    "gn:population":0,
    "gn:timezone":"Asia/Shanghai",
    "iso:country":"CN",
    "name:ceb_x_preferred":[
        "Jingyang"
    ],
    "name:deu_x_preferred":[
        "Jingyang"
    ],
    "name:fra_x_preferred":[
        "Jingyang"
    ],
    "name:nor_x_preferred":[
        "Jingyang"
    ],
    "name:swe_x_preferred":[
        "Jingyang"
    ],
    "name:zho_x_preferred":[
        "\u9759\u9633"
    ],
    "wof:name":"Jingyang",
    "wof:placetype":"locality"
},
  "geometry": {"coordinates":[113.94898000000001,37.62853],"type":"Point"}
}