{
  "type": "Feature",
  "properties": {
    "gn:admin1_code":"32.0",
    "gn:asciiname":"Huoluo",
    "gn:country_code":"CN",
    "gn:dem":2031,
    "gn:feature_class":"P",
    "gn:feature_code":"PPL",
    "gn:name":"Huoluo",
    "gn:population":0,
    "gn:timezone":"Asia/Shanghai",
    "iso:country":"CN",
    "name:zho_x_preferred":[
        "\u706b\u6d1b"
    ],
    "wof:name":"Huoluo",
    "wof:placetype":"locality"
},
  "geometry": {"coordinates":[102.90900000000001,28.0856],"type":"Point"}
}