{
  "type": "Feature",
  "properties": {
    "gn:admin1_code":"4.0",
    "gn:asciiname":"Shuangduncun",
    "gn:country_code":"CN",
    "gn:dem":37,
    "gn:feature_class":"P",
    "gn:feature_code":"PPL",
    "gn:name":"Shuangduncun",
    "gn:population":0,
    "gn:timezone":"Asia/Shanghai",
    "iso:country":"CN",
    "name:zho_x_preferred":[
        "\u53cc\u58a9\u6751"
    ],
    "wof:name":"Shuangduncun",
    "wof:placetype":"locality"
},
  "geometry": {"coordinates":[118.89507999999999,32.48328],"type":"Point"}
}