{
  "type": "Feature",
  "properties": {
    "gn:admin1_code":"15.0",
    "gn:asciiname":"Xintianle",
    "gn:country_code":"CN",
    "gn:dem":2163,
    "gn:feature_class":"P",
    "gn:feature_code":"PPL",
    "gn:name":"Xintianle",
    "gn:population":0,
    "gn:timezone":"Asia/Shanghai",
    "iso:country":"CN",
    "name:zho_x_preferred":[
        "\u65b0\u5929\u4e50"
    ],
    "wof:name":"Xintianle",
    "wof:placetype":"locality"
},
  "geometry": {"coordinates":[100.73099999999999,38.512],"type":"Point"}
}