{
  "type": "Feature",
  "properties": {
    "gn:admin1_code":"26.0",
    "gn:asciiname":"Gaojia Goukou",
    "gn:country_code":"CN",
    "gn:dem":1063,
    "gn:feature_class":"P",
    "gn:feature_code":"PPL",
    "gn:name":"Gaojia Goukou",
    "gn:population":0,
    "gn:timezone":"Asia/Shanghai",
    "iso:country":"CN",
    "name:zho_x_preferred":[
        "\u9ad8\u5bb6\u6c9f\u53e3"
    ],
    "wof:name":"Gaojia Goukou",
    "wof:placetype":"locality"
},
  "geometry": {"coordinates":[109.1138,36.41654000000001],"type":"Point"}
}