{
  "type": "Feature",
  "properties": {
    "gn:admin1_code":"26.0",
    "gn:asciiname":"Liyukoucun",
    "gn:country_code":"CN",
    "gn:dem":748,
    "gn:feature_class":"P",
    "gn:feature_code":"PPL",
    "gn:name":"Liyukoucun",
    "gn:population":0,
    "gn:timezone":"Asia/Shanghai",
    "iso:country":"CN",
    "name:und_x_variant":[
        "\u91cc\u5cea\u53e3\u6751"
    ],
    "wof:name":"Liyukoucun",
    "wof:placetype":"locality"
},
  "geometry": {"coordinates":[109.69034000000001,34.38225],"type":"Point"}
}