{
  "type": "Feature",
  "properties": {
    "gn:admin1_code":"33.0",
    "gn:asciiname":"Changyuanba",
    "gn:country_code":"CN",
    "gn:dem":313,
    "gn:feature_class":"P",
    "gn:feature_code":"PPL",
    "gn:name":"Changyuanba",
    "gn:population":0,
    "gn:timezone":"Asia/Shanghai",
    "iso:country":"CN",
    "name:zho_x_preferred":[
        "\u957f\u5143\u575d"
    ],
    "wof:name":"Changyuanba",
    "wof:placetype":"locality"
},
  "geometry": {"coordinates":[109.11565,28.97796],"type":"Point"}
}