{
  "type": "Feature",
  "properties": {
    "gn:admin1_code":"3.0",
    "gn:asciiname":"Huaqiao Yujia",
    "gn:country_code":"CN",
    "gn:dem":103,
    "gn:feature_class":"P",
    "gn:feature_code":"PPL",
    "gn:name":"Huaqiao Yujia",
    "gn:population":0,
    "gn:timezone":"Asia/Shanghai",
    "iso:country":"CN",
    "name:zho_x_preferred":[
        "\u82b1\u6865\u4f59\u5bb6"
    ],
    "wof:name":"Huaqiao Yujia",
    "wof:placetype":"locality"
},
  "geometry": {"coordinates":[117.53754000000001,28.06911],"type":"Point"}
}