{
  "type": "Feature",
  "properties": {
    "gn:admin1_code":"32.0",
    "gn:asciiname":"Guloushan",
    "gn:country_code":"CN",
    "gn:dem":932,
    "gn:feature_class":"P",
    "gn:feature_code":"PPL",
    "gn:name":"Guloushan",
    "gn:population":0,
    "gn:timezone":"Asia/Shanghai",
    "iso:country":"CN",
    "name:zho_x_preferred":[
        "\u53e4\u697c\u5c71"
    ],
    "wof:name":"Guloushan",
    "wof:placetype":"locality"
},
  "geometry": {"coordinates":[106.83,31.9526],"type":"Point"}
}