{
  "type": "Feature",
  "properties": {
    "gn:admin1_code":"1.0",
    "gn:asciiname":"Fanggouyacun",
    "gn:country_code":"CN",
    "gn:dem":44,
    "gn:feature_class":"P",
    "gn:feature_code":"PPL",
    "gn:name":"Fanggouyacun",
    "gn:population":0,
    "gn:timezone":"Asia/Shanghai",
    "iso:country":"CN",
    "name:zho_x_preferred":[
        "\u623f\u6c9f\u6daf\u6751"
    ],
    "wof:name":"Fanggouyacun",
    "wof:placetype":"locality"
},
  "geometry": {"coordinates":[116.51357,34.33722],"type":"Point"}
}