{
  "type": "Feature",
  "properties": {
    "gn:admin1_code":"12.0",
    "gn:asciiname":"Zhengjiatai",
    "gn:country_code":"CN",
    "gn:dem":37,
    "gn:feature_class":"P",
    "gn:feature_code":"PPL",
    "gn:name":"Zhengjiatai",
    "gn:population":0,
    "gn:timezone":"Asia/Shanghai",
    "iso:country":"CN",
    "name:eng_x_historical":[
        "Chin tan"
    ],
    "name:eng_x_preferred":[
        "Chin tan"
    ],
    "name:zho_x_preferred":[
        "\u90d1\u5bb6\u53f0"
    ],
    "wof:name":"Zhengjiatai",
    "wof:placetype":"locality"
},
  "geometry": {"coordinates":[112.62247000000001,30.6691],"type":"Point"}
}