{
  "type": "Feature",
  "properties": {
    "gn:admin1_code":"11.0",
    "gn:asciiname":"Buyunping",
    "gn:country_code":"CN",
    "gn:dem":165,
    "gn:feature_class":"P",
    "gn:feature_code":"PPL",
    "gn:name":"Buyunping",
    "gn:population":0,
    "gn:timezone":"Asia/Shanghai",
    "iso:country":"CN",
    "name:zho_x_preferred":[
        "\u6b65\u4e91\u576a"
    ],
    "wof:name":"Buyunping",
    "wof:placetype":"locality"
},
  "geometry": {"coordinates":[109.76985999999999,27.79245],"type":"Point"}
}