{
  "type": "Feature",
  "properties": {
    "gn:admin1_code":"30.0",
    "gn:asciiname":"Taiyucun",
    "gn:country_code":"CN",
    "gn:dem":84,
    "gn:feature_class":"P",
    "gn:feature_code":"PPL",
    "gn:name":"Taiyucun",
    "gn:population":0,
    "gn:timezone":"Asia/Shanghai",
    "iso:country":"CN",
    "name:zho_x_preferred":[
        "\u592a\u5b87\u6751"
    ],
    "wof:name":"Taiyucun",
    "wof:placetype":"locality"
},
  "geometry": {"coordinates":[116.70985,24.55577000000001],"type":"Point"}
}