{
  "type": "Feature",
  "properties": {
    "gn:admin1_code":"30",
    "gn:asciiname":"Dazhou",
    "gn:country_code":"CN",
    "gn:dem":40,
    "gn:feature_class":"P",
    "gn:feature_code":"PPLA4",
    "gn:name":"Dazhou",
    "gn:population":0,
    "gn:timezone":"Asia/Shanghai",
    "iso:country":"CN",
    "name:und_x_variant":[
        "Dazhou Zhen",
        "\u5927\u6d32\u9547"
    ],
    "name:zho_x_preferred":[
        "\u5927\u6d32"
    ],
    "wof:name":"Dazhou",
    "wof:placetype":"locality"
},
  "geometry": {"coordinates":[111.53917,23.51676],"type":"Point"}
}