{
  "type": "Feature",
  "properties": {
    "gn:admin1_code":"29.0",
    "gn:asciiname":"Shansongqing",
    "gn:country_code":"CN",
    "gn:dem":2700,
    "gn:feature_class":"P",
    "gn:feature_code":"PPL",
    "gn:name":"Shansongqing",
    "gn:population":0,
    "gn:timezone":"Asia/Shanghai",
    "iso:country":"CN",
    "name:zho_x_preferred":[
        "\u6749\u677e\u7b90"
    ],
    "wof:name":"Shansongqing",
    "wof:placetype":"locality"
},
  "geometry": {"coordinates":[103.339,27.2157],"type":"Point"}
}