{
  "type": "Feature",
  "properties": {
    "gn:admin1_code":"10",
    "gn:asciiname":"Tiejianggou",
    "gn:country_code":"CN",
    "gn:dem":727,
    "gn:feature_class":"P",
    "gn:feature_code":"PPL",
    "gn:name":"Tiejianggou",
    "gn:population":0,
    "gn:timezone":"Asia/Shanghai",
    "iso:country":"CN",
    "name:zho_x_preferred":[
        "\u94c1\u5320\u6c9f"
    ],
    "wof:name":"Tiejianggou",
    "wof:placetype":"locality"
},
  "geometry": {"coordinates":[118.71183000000001,41.22317],"type":"Point"}
}