{
  "type": "Feature",
  "properties": {
    "gn:admin1_code":"19.0",
    "gn:asciiname":"Houchangheyan",
    "gn:country_code":"CN",
    "gn:dem":48,
    "gn:feature_class":"P",
    "gn:feature_code":"PPL",
    "gn:name":"Houchangheyan",
    "gn:population":0,
    "gn:timezone":"Asia/Shanghai",
    "iso:country":"CN",
    "name:zho_x_preferred":[
        "\u540e\u957f\u6cb3\u6cbf"
    ],
    "wof:name":"Houchangheyan",
    "wof:placetype":"locality"
},
  "geometry": {"coordinates":[123.482,42.1553],"type":"Point"}
}