{
  "type": "Feature",
  "properties": {
    "gn:admin1_code":"03",
    "gn:asciiname":"Huangbi",
    "gn:cc2":"CN",
    "gn:country_code":"CN",
    "gn:dem":1385,
    "gn:feature_class":"P",
    "gn:feature_code":"PPL",
    "gn:name":"Huangbi",
    "gn:population":0,
    "gn:timezone":"Asia/Shanghai",
    "iso:country":"CN",
    "name:und_x_variant":[
        "Huang-pi",
        "Huangbi"
    ],
    "wof:name":"Huangbi",
    "wof:placetype":"locality"
},
  "geometry": {"coordinates":[117.68333,27.88333],"type":"Point"}
}