{
  "type": "Feature",
  "properties": {
    "gn:admin1_code":"22.0",
    "gn:asciiname":"Hongshimencun",
    "gn:country_code":"CN",
    "gn:dem":201,
    "gn:feature_class":"P",
    "gn:feature_code":"PPL",
    "gn:name":"Hongshimencun",
    "gn:population":0,
    "gn:timezone":"Asia/Shanghai",
    "iso:country":"CN",
    "name:zho_x_preferred":[
        "\u7ea2\u77f3\u95e8\u6751"
    ],
    "wof:name":"Hongshimencun",
    "wof:placetype":"locality"
},
  "geometry": {"coordinates":[117.35746,40.21771],"type":"Point"}
}