{
  "type": "Feature",
  "properties": {
    "gn:admin1_code":"25",
    "gn:asciiname":"Dongmanzi",
    "gn:country_code":"CN",
    "gn:dem":137,
    "gn:feature_class":"P",
    "gn:feature_code":"PPL",
    "gn:name":"Dongmanzi",
    "gn:population":0,
    "gn:timezone":"Asia/Shanghai",
    "iso:country":"CN",
    "name:zho_x_preferred":[
        "\u4e1c\u86ee\u5b50"
    ],
    "wof:name":"Dongmanzi",
    "wof:placetype":"locality"
},
  "geometry": {"coordinates":[116.492,36.2513],"type":"Point"}
}