{
  "type": "Feature",
  "properties": {
    "gn:admin1_code":"2.0",
    "gn:asciiname":"Heshan",
    "gn:country_code":"CN",
    "gn:dem":306,
    "gn:feature_class":"P",
    "gn:feature_code":"PPL",
    "gn:name":"Heshan",
    "gn:population":0,
    "gn:timezone":"Asia/Shanghai",
    "iso:country":"CN",
    "name:ceb_x_preferred":[
        "Heshan"
    ],
    "name:deu_x_preferred":[
        "Heshan"
    ],
    "name:fra_x_preferred":[
        "Heshan"
    ],
    "name:kor_x_preferred":[
        "\ud5c8\uc0b0\uc2dc"
    ],
    "name:nor_x_preferred":[
        "Heshan"
    ],
    "name:rus_x_preferred":[
        "\u0425\u044d\u0448\u0430\u043d\u044c"
    ],
    "name:swe_x_preferred":[
        "Heshan"
    ],
    "name:zho_x_preferred":[
        "\u8377\u5c71"
    ],
    "wof:name":"Heshan",
    "wof:placetype":"locality"
},
  "geometry": {"coordinates":[121.12555,28.94706],"type":"Point"}
}