{
  "type": "Feature",
  "properties": {
    "gn:admin1_code":"4.0",
    "gn:asciiname":"Daxuezhuang",
    "gn:country_code":"CN",
    "gn:dem":2,
    "gn:feature_class":"P",
    "gn:feature_code":"PPL",
    "gn:name":"Daxuezhuang",
    "gn:population":0,
    "gn:timezone":"Asia/Shanghai",
    "iso:country":"CN",
    "name:zho_x_preferred":[
        "\u5927\u96ea\u5e84"
    ],
    "wof:name":"Daxuezhuang",
    "wof:placetype":"locality"
},
  "geometry": {"coordinates":[119.46177,32.71313],"type":"Point"}
}