{
  "type": "Feature",
  "properties": {
    "gn:admin1_code":"29.0",
    "gn:asciiname":"Damuwan",
    "gn:country_code":"CN",
    "gn:dem":1099,
    "gn:feature_class":"P",
    "gn:feature_code":"PPL",
    "gn:name":"Damuwan",
    "gn:population":0,
    "gn:timezone":"Asia/Shanghai",
    "iso:country":"CN",
    "name:zho_x_preferred":[
        "\u5927\u6728\u6e7e"
    ],
    "wof:name":"Damuwan",
    "wof:placetype":"locality"
},
  "geometry": {"coordinates":[104.57899999999999,27.674],"type":"Point"}
}