{
  "type": "Feature",
  "properties": {
    "gn:admin1_code":"32.0",
    "gn:asciiname":"Mayiduo",
    "gn:country_code":"CN",
    "gn:dem":4087,
    "gn:feature_class":"P",
    "gn:feature_code":"PPL",
    "gn:name":"Mayiduo",
    "gn:population":0,
    "gn:timezone":"Asia/Shanghai",
    "iso:country":"CN",
    "name:zho_x_preferred":[
        "\u9a6c\u8863\u591a"
    ],
    "wof:name":"Mayiduo",
    "wof:placetype":"locality"
},
  "geometry": {"coordinates":[99.44999,32.23809],"type":"Point"}
}