{
  "type": "Feature",
  "properties": {
    "gn:admin1_code":"19.0",
    "gn:asciiname":"Jigou",
    "gn:country_code":"CN",
    "gn:dem":137,
    "gn:feature_class":"P",
    "gn:feature_code":"PPL",
    "gn:name":"Jigou",
    "gn:population":0,
    "gn:timezone":"Asia/Shanghai",
    "iso:country":"CN",
    "name:zho_x_preferred":[
        "\u5d47\u6c9f"
    ],
    "wof:name":"Jigou",
    "wof:placetype":"locality"
},
  "geometry": {"coordinates":[122.18000000000001,39.8146],"type":"Point"}
}