{
  "type": "Feature",
  "properties": {
    "gn:admin1_code":"10",
    "gn:asciiname":"Xiao'ertai",
    "gn:country_code":"CN",
    "gn:dem":1409,
    "gn:feature_class":"P",
    "gn:feature_code":"PPL",
    "gn:name":"Xiao\u2019ertai",
    "gn:population":0,
    "gn:timezone":"Asia/Shanghai",
    "iso:country":"CN",
    "wof:name":"Xiao'ertai",
    "wof:placetype":"locality"
},
  "geometry": {"coordinates":[114.84083,41.17917],"type":"Point"}
}