{
  "type": "Feature",
  "properties": {
    "gn:admin1_code":"29.0",
    "gn:asciiname":"Xiataiping",
    "gn:country_code":"CN",
    "gn:dem":2381,
    "gn:feature_class":"P",
    "gn:feature_code":"PPL",
    "gn:name":"Xiataiping",
    "gn:population":0,
    "gn:timezone":"Asia/Shanghai",
    "iso:country":"CN",
    "name:zho_x_preferred":[
        "\u4e0b\u592a\u576a"
    ],
    "wof:name":"Xiataiping",
    "wof:placetype":"locality"
},
  "geometry": {"coordinates":[99.61020000000001,26.4623],"type":"Point"}
}