{
  "type": "Feature",
  "properties": {
    "gn:admin1_code":"30.0",
    "gn:asciiname":"Dongqianxicun",
    "gn:country_code":"CN",
    "gn:dem":12,
    "gn:feature_class":"P",
    "gn:feature_code":"PPL",
    "gn:name":"Dongqianxicun",
    "gn:population":0,
    "gn:timezone":"Asia/Shanghai",
    "iso:country":"CN",
    "name:zho_x_preferred":[
        "\u4e1c\u524d\u6eaa\u6751"
    ],
    "wof:name":"Dongqianxicun",
    "wof:placetype":"locality"
},
  "geometry": {"coordinates":[116.68982,23.56817],"type":"Point"}
}