{
  "type": "Feature",
  "properties": {
    "gn:admin1_code":"29.0",
    "gn:asciiname":"Biehashidi",
    "gn:country_code":"CN",
    "gn:dem":2352,
    "gn:feature_class":"P",
    "gn:feature_code":"PPL",
    "gn:name":"Biehashidi",
    "gn:population":0,
    "gn:timezone":"Asia/Shanghai",
    "iso:country":"CN",
    "name:zho_x_preferred":[
        "\u522b\u54c8\u65bd\u5e95"
    ],
    "wof:name":"Biehashidi",
    "wof:placetype":"locality"
},
  "geometry": {"coordinates":[99.2457,27.2093],"type":"Point"}
}