{
  "type": "Feature",
  "properties": {
    "gn:admin1_code":"19.0",
    "gn:asciiname":"Gaizhoudao",
    "gn:country_code":"CN",
    "gn:dem":49,
    "gn:feature_class":"P",
    "gn:feature_code":"PPL",
    "gn:name":"Gaizhoudao",
    "gn:population":0,
    "gn:timezone":"Asia/Shanghai",
    "iso:country":"CN",
    "name:zho_x_preferred":[
        "\u76d6\u5dde\u9053"
    ],
    "wof:name":"Gaizhoudao",
    "wof:placetype":"locality"
},
  "geometry": {"coordinates":[122.98099999999999,39.8162],"type":"Point"}
}