{
  "type": "Feature",
  "properties": {
    "gn:admin1_code":"7.0",
    "gn:asciiname":"Hengyang",
    "gn:country_code":"CN",
    "gn:dem":563,
    "gn:feature_class":"P",
    "gn:feature_code":"PPL",
    "gn:name":"Hengyang",
    "gn:population":0,
    "gn:timezone":"Asia/Shanghai",
    "iso:country":"CN",
    "name:afr_x_preferred":[
        "Hengyang"
    ],
    "name:ara_x_preferred":[
        "\u0647\u0646\u063a\u064a\u0627\u0646\u063a"
    ],
    "name:bre_x_preferred":[
        "Hengyang"
    ],
    "name:bul_x_preferred":[
        "\u0425\u044a\u043d\u044f\u043d"
    ],
    "name:cdo_x_preferred":[
        "H\u00e8ng-i\u00f2ng"
    ],
    "name:ceb_x_preferred":[
        "Hengyang"
    ],
    "name:ces_x_preferred":[
        "Cheng-jang"
    ],
    "name:dan_x_preferred":[
        "Hengyang"
    ],
    "name:deu_x_preferred":[
        "Hengyang"
    ],
    "name:epo_x_preferred":[
        "Hengjang"
    ],
    "name:eus_x_preferred":[
        "Hengyang"
    ],
    "name:fas_x_preferred":[
        "\u0647\u0646\u06af\u06cc\u0627\u0646\u06af"
    ],
    "name:fin_x_preferred":[
        "Hengyang"
    ],
    "name:fra_x_preferred":[
        "Hengyang"
    ],
    "name:hak_x_preferred":[
        "F\u00ean-y\u00f2ng-s\u1e73"
    ],
    "name:ind_x_preferred":[
        "Hengyang"
    ],
    "name:ita_x_preferred":[
        "Hengyang"
    ],
    "name:jpn_x_preferred":[
        "\u8861\u967d\u5e02"
    ],
    "name:kik_x_preferred":[
        "Hengyang"
    ],
    "name:kor_x_preferred":[
        "\ud5dd\uc591\uc2dc"
    ],
    "name:lit_x_preferred":[
        "Hengjangas"
    ],
    "name:mlg_x_preferred":[
        "Hengyang"
    ],
    "name:nld_x_preferred":[
        "Hengyang"
    ],
    "name:nno_x_preferred":[
        "Hengyang"
    ],
    "name:nor_x_preferred":[
        "Hengyang"
    ],
    "name:pam_x_preferred":[
        "Hengyang"
    ],
    "name:pol_x_preferred":[
        "Hengyang"
    ],
    "name:por_x_preferred":[
        "Hengyang"
    ],
    "name:rus_x_preferred":[
        "\u0425\u044d\u043d\u044a\u044f\u043d"
    ],
    "name:spa_x_preferred":[
        "Hengyang"
    ],
    "name:srp_x_preferred":[
        "\u0425\u0435\u043d\u0433\u0458\u0430\u043d\u0433"
    ],
    "name:swe_x_preferred":[
        "Hengyang"
    ],
    "name:tgl_x_preferred":[
        "Hengyang"
    ],
    "name:tur_x_preferred":[
        "Hengyang"
    ],
    "name:uig_x_preferred":[
        "X\u00e9ngyang shehiri"
    ],
    "name:urd_x_preferred":[
        "\u06c1\u06cc\u0646\u06af\u06cc\u0627\u0646\u06af"
    ],
    "name:vie_x_preferred":[
        "H\u00e0nh D\u01b0\u01a1ng"
    ],
    "name:war_x_preferred":[
        "Hengyang"
    ],
    "name:zho_x_preferred":[
        "\u8861\u6d0b"
    ],
    "name:zho_x_variant":[
        "\u8861\u9633\u5e02"
    ],
    "wof:name":"Hengyang",
    "wof:placetype":"locality"
},
  "geometry": {"coordinates":[118.49460000000001,25.77819],"type":"Point"}
}