{
  "type": "Feature",
  "properties": {
    "gn:admin1_code":"7.0",
    "gn:asciiname":"Hengyang",
    "gn:country_code":"CN",
    "gn:dem":563,
    "gn:feature_class":"P",
    "gn:feature_code":"PPL",
    "gn:name":"Hengyang",
    "gn:population":0,
    "gn:timezone":"Asia/Shanghai",
    "iso:country":"CN",
    "name:zho_x_preferred":[
        "\u8861\u6d0b"
    ],
    "wof:name":"Hengyang",
    "wof:placetype":"locality"
},
  "geometry": {"coordinates":[118.49460000000001,25.77819],"type":"Point"}
}