{
  "type": "Feature",
  "properties": {
    "gn:admin1_code":"29.0",
    "gn:asciiname":"Enjiao",
    "gn:country_code":"CN",
    "gn:dem":1764,
    "gn:feature_class":"P",
    "gn:feature_code":"PPL",
    "gn:name":"Enjiao",
    "gn:population":0,
    "gn:timezone":"Asia/Shanghai",
    "iso:country":"CN",
    "name:zho_x_preferred":[
        "\u6069\u811a"
    ],
    "wof:name":"Enjiao",
    "wof:placetype":"locality"
},
  "geometry": {"coordinates":[103.29000000000001,25.1159],"type":"Point"}
}