{
  "type": "Feature",
  "properties": {
    "gn:admin1_code":"13.0",
    "gn:asciiname":"Tuonuqi",
    "gn:country_code":"CN",
    "gn:dem":1337,
    "gn:feature_class":"P",
    "gn:feature_code":"PPL",
    "gn:name":"Tuonuqi",
    "gn:population":0,
    "gn:timezone":"Asia/Shanghai",
    "iso:country":"CN",
    "name:und_x_variant":[
        "\u6258\u52aa\u5176"
    ],
    "wof:name":"Tuonuqi",
    "wof:placetype":"locality"
},
  "geometry": {"coordinates":[76.38063000000002,38.72802],"type":"Point"}
}