{
  "type": "Feature",
  "properties": {
    "gn:admin1_code":"25",
    "gn:asciiname":"Nanhuozhai",
    "gn:country_code":"CN",
    "gn:dem":63,
    "gn:feature_class":"P",
    "gn:feature_code":"PPL",
    "gn:name":"Nanhuozhai",
    "gn:population":0,
    "gn:timezone":"Asia/Shanghai",
    "iso:country":"CN",
    "name:zho_x_preferred":[
        "\u5357\u970d\u5be8"
    ],
    "wof:name":"Nanhuozhai",
    "wof:placetype":"locality"
},
  "geometry": {"coordinates":[114.974,35.2417],"type":"Point"}
}