{
  "type": "Feature",
  "properties": {
    "gn:admin1_code":"32.0",
    "gn:asciiname":"Xiucaigou",
    "gn:country_code":"CN",
    "gn:dem":426,
    "gn:feature_class":"P",
    "gn:feature_code":"PPL",
    "gn:name":"Xiucaigou",
    "gn:population":0,
    "gn:timezone":"Asia/Shanghai",
    "iso:country":"CN",
    "name:zho_x_preferred":[
        "\u79c0\u624d\u6c9f"
    ],
    "wof:name":"Xiucaigou",
    "wof:placetype":"locality"
},
  "geometry": {"coordinates":[104.37779999999999,30.36164],"type":"Point"}
}