{
  "type": "Feature",
  "properties": {
    "gn:admin1_code":"29.0",
    "gn:asciiname":"Huodi",
    "gn:country_code":"CN",
    "gn:dem":2245,
    "gn:feature_class":"P",
    "gn:feature_code":"PPL",
    "gn:name":"Huodi",
    "gn:population":0,
    "gn:timezone":"Asia/Shanghai",
    "iso:country":"CN",
    "name:und_x_variant":[
        "\u706b\u5730"
    ],
    "wof:name":"Huodi",
    "wof:placetype":"locality"
},
  "geometry": {"coordinates":[103.932,27.6105],"type":"Point"}
}