{
  "type": "Feature",
  "properties": {
    "gn:admin1_code":"2.0",
    "gn:asciiname":"Kexili",
    "gn:country_code":"CN",
    "gn:dem":120,
    "gn:feature_class":"P",
    "gn:feature_code":"PPL",
    "gn:name":"Kexili",
    "gn:population":0,
    "gn:timezone":"Asia/Shanghai",
    "iso:country":"CN",
    "name:zho_x_preferred":[
        "\u5cc7\u6eaa\u91cc"
    ],
    "wof:name":"Kexili",
    "wof:placetype":"locality"
},
  "geometry": {"coordinates":[120.80239,29.16151],"type":"Point"}
}