{
  "type": "Feature",
  "properties": {
    "gn:admin1_code":"06",
    "gn:asciiname":"Dalung",
    "gn:country_code":"CN",
    "gn:dem":3286,
    "gn:feature_class":"P",
    "gn:feature_code":"PPL",
    "gn:name":"Dalung",
    "gn:population":0,
    "gn:timezone":"Asia/Shanghai",
    "iso:country":"CN",
    "name:bod_x_preferred":[
        "Dalung"
    ],
    "name:und_x_variant":[
        "Dalong",
        "\u8fbe\u9f99"
    ],
    "name:zho_x_preferred":[
        "\u8fbe\u9f99"
    ],
    "wof:name":"Dalung",
    "wof:placetype":"locality"
},
  "geometry": {"coordinates":[100.50973999999999,35.57169000000001],"type":"Point"}
}