{
  "type": "Feature",
  "properties": {
    "gn:admin1_code":"09",
    "gn:asciiname":"Fangcheng Chengguanzhen",
    "gn:country_code":"CN",
    "gn:dem":158,
    "gn:feature_class":"P",
    "gn:feature_code":"PPLA3",
    "gn:name":"Fangcheng Chengguanzhen",
    "gn:population":0,
    "gn:timezone":"Asia/Shanghai",
    "iso:country":"CN",
    "name:und_x_variant":[
        "Y\u00fc-chou",
        "Fang-ch\u2019eng-hsien",
        "Y\u00fcchow",
        "Fangcheng",
        "Fangcheng Chengguanzhen"
    ],
    "name:zho_x_preferred":[
        "\u65b9\u57ce\u57ce\u5173\u9547"
    ],
    "wof:name":"Fangcheng Chengguanzhen",
    "wof:placetype":"locality"
},
  "geometry": {"coordinates":[113.0012,33.25322],"type":"Point"}
}