{
  "type": "Feature",
  "properties": {
    "gn:admin1_code":"18",
    "gn:asciiname":"Xiaotianba",
    "gn:country_code":"CN",
    "gn:dem":906,
    "gn:feature_class":"P",
    "gn:feature_code":"PPL",
    "gn:name":"Xiaotianba",
    "gn:population":0,
    "gn:timezone":"Asia/Shanghai",
    "iso:country":"CN",
    "name:zho_x_preferred":[
        "\u5c0f\u7530\u575d"
    ],
    "wof:name":"Xiaotianba",
    "wof:placetype":"locality"
},
  "geometry": {"coordinates":[105.128,26.2856],"type":"Point"}
}