{
  "type": "Feature",
  "properties": {
    "gn:admin1_code":"30.0",
    "gn:asciiname":"Xiaoxicun",
    "gn:country_code":"CN",
    "gn:dem":147,
    "gn:feature_class":"P",
    "gn:feature_code":"PPL",
    "gn:name":"Xiaoxicun",
    "gn:population":0,
    "gn:timezone":"Asia/Shanghai",
    "iso:country":"CN",
    "name:zho_x_preferred":[
        "Xiaoxicun"
    ],
    "name:zho_x_variant":[
        "\u5c0f\u6eaa\u6751"
    ],
    "wof:name":"Xiaoxicun",
    "wof:placetype":"locality"
},
  "geometry": {"coordinates":[114.68306,24.23505],"type":"Point"}
}