{
  "type": "Feature",
  "properties": {
    "gn:admin1_code":"16.0",
    "gn:asciiname":"Waipoluo",
    "gn:country_code":"CN",
    "gn:dem":210,
    "gn:feature_class":"P",
    "gn:feature_code":"PPL",
    "gn:name":"Waipoluo",
    "gn:population":0,
    "gn:timezone":"Asia/Shanghai",
    "iso:country":"CN",
    "name:zho_x_preferred":[
        "\u5916\u5761\u7f57"
    ],
    "wof:name":"Waipoluo",
    "wof:placetype":"locality"
},
  "geometry": {"coordinates":[108.482,24.6219],"type":"Point"}
}