{
  "type": "Feature",
  "properties": {
    "gn:admin1_code":"16.0",
    "gn:asciiname":"Zhuqin",
    "gn:country_code":"CN",
    "gn:dem":333,
    "gn:feature_class":"P",
    "gn:feature_code":"PPL",
    "gn:name":"Zhuqin",
    "gn:population":0,
    "gn:timezone":"Asia/Shanghai",
    "iso:country":"CN",
    "name:zho_x_preferred":[
        "\u9010\u94a6"
    ],
    "wof:name":"Zhuqin",
    "wof:placetype":"locality"
},
  "geometry": {"coordinates":[106.93899999999999,22.794],"type":"Point"}
}