{
  "type": "Feature",
  "properties": {
    "gn:admin1_code":"24.0",
    "gn:asciiname":"Linghou",
    "gn:country_code":"CN",
    "gn:dem":1010,
    "gn:feature_class":"P",
    "gn:feature_code":"PPL",
    "gn:name":"Linghou",
    "gn:population":0,
    "gn:timezone":"Asia/Shanghai",
    "iso:country":"CN",
    "name:zho_x_preferred":[
        "\u5cad\u540e"
    ],
    "wof:name":"Linghou",
    "wof:placetype":"locality"
},
  "geometry": {"coordinates":[113.1994,36.35813],"type":"Point"}
}