{
  "type": "Feature",
  "properties": {
    "gn:admin1_code":"8.0",
    "gn:asciiname":"Dafangtun",
    "gn:country_code":"CN",
    "gn:dem":155,
    "gn:feature_class":"P",
    "gn:feature_code":"PPL",
    "gn:name":"Dafangtun",
    "gn:population":0,
    "gn:timezone":"Asia/Shanghai",
    "iso:country":"CN",
    "name:zho_x_preferred":[
        "\u5927\u623f\u5c6f"
    ],
    "wof:name":"Dafangtun",
    "wof:placetype":"locality"
},
  "geometry": {"coordinates":[127.42221000000001,45.83179000000001],"type":"Point"}
}