{
  "type": "Feature",
  "properties": {
    "gn:admin1_code":"19.0",
    "gn:asciiname":"Wuliwazi",
    "gn:country_code":"CN",
    "gn:dem":121,
    "gn:feature_class":"P",
    "gn:feature_code":"PPL",
    "gn:name":"Wuliwazi",
    "gn:population":0,
    "gn:timezone":"Asia/Shanghai",
    "iso:country":"CN",
    "name:zho_x_preferred":[
        "\u4e94\u91cc\u6d3c\u5b50"
    ],
    "wof:name":"Wuliwazi",
    "wof:placetype":"locality"
},
  "geometry": {"coordinates":[123.74299999999999,43.2299],"type":"Point"}
}