{
  "type": "Feature",
  "properties": {
    "gn:admin1_code":"19.0",
    "gn:asciiname":"Jianganhu",
    "gn:country_code":"CN",
    "gn:dem":56,
    "gn:feature_class":"P",
    "gn:feature_code":"PPL",
    "gn:name":"Jianganhu",
    "gn:population":0,
    "gn:timezone":"Asia/Shanghai",
    "iso:country":"CN",
    "name:zho_x_preferred":[
        "\u7bad\u6746\u6e56"
    ],
    "wof:name":"Jianganhu",
    "wof:placetype":"locality"
},
  "geometry": {"coordinates":[123.685,42.2952],"type":"Point"}
}