{
  "type": "Feature",
  "properties": {
    "gn:admin1_code":"26.0",
    "gn:asciiname":"Xiajiadian",
    "gn:country_code":"CN",
    "gn:dem":1225,
    "gn:feature_class":"P",
    "gn:feature_code":"PPL",
    "gn:name":"Xiajiadian",
    "gn:population":0,
    "gn:timezone":"Asia/Shanghai",
    "iso:country":"CN",
    "name:zho_x_preferred":[
        "\u590f\u5bb6\u5e97"
    ],
    "wof:name":"Xiajiadian",
    "wof:placetype":"locality"
},
  "geometry": {"coordinates":[109.30456,33.70644],"type":"Point"}
}