{
  "type": "Feature",
  "properties": {
    "gn:admin1_code":"9.0",
    "gn:asciiname":"Xiwuzhuang",
    "gn:country_code":"CN",
    "gn:dem":131,
    "gn:feature_class":"P",
    "gn:feature_code":"PPL",
    "gn:name":"Xiwuzhuang",
    "gn:population":0,
    "gn:timezone":"Asia/Shanghai",
    "iso:country":"CN",
    "name:zho_x_preferred":[
        "\u897f\u5434\u5e84"
    ],
    "wof:name":"Xiwuzhuang",
    "wof:placetype":"locality"
},
  "geometry": {"coordinates":[113.21272,33.80037],"type":"Point"}
}