{
  "type": "Feature",
  "properties": {
    "gn:admin1_code":"32.0",
    "gn:asciiname":"Shuangbaishu",
    "gn:country_code":"CN",
    "gn:dem":332,
    "gn:feature_class":"P",
    "gn:feature_code":"PPL",
    "gn:name":"Shuangbaishu",
    "gn:population":0,
    "gn:timezone":"Asia/Shanghai",
    "iso:country":"CN",
    "name:zho_x_preferred":[
        "\u53cc\u67cf\u6811"
    ],
    "wof:name":"Shuangbaishu",
    "wof:placetype":"locality"
},
  "geometry": {"coordinates":[105.449,30.7561],"type":"Point"}
}