{
  "type": "Feature",
  "properties": {
    "gn:admin1_code":"12.0",
    "gn:asciiname":"Hongwawu",
    "gn:country_code":"CN",
    "gn:dem":729,
    "gn:feature_class":"P",
    "gn:feature_code":"PPL",
    "gn:name":"Hongwawu",
    "gn:population":0,
    "gn:timezone":"Asia/Shanghai",
    "iso:country":"CN",
    "name:zho_x_preferred":[
        "\u7ea2\u74e6\u5c4b"
    ],
    "wof:name":"Hongwawu",
    "wof:placetype":"locality"
},
  "geometry": {"coordinates":[109.86033999999999,32.22116],"type":"Point"}
}