{
  "type": "Feature",
  "properties": {
    "gn:admin1_code":"02",
    "gn:asciiname":"Zhaojia'ao",
    "gn:country_code":"CN",
    "gn:dem":24,
    "gn:feature_class":"P",
    "gn:feature_code":"PPL",
    "gn:name":"Zhaojia\u2019ao",
    "gn:population":0,
    "gn:timezone":"Asia/Shanghai",
    "iso:country":"CN",
    "name:und_x_variant":[
        "Chao-chia-ao",
        "Zhaojia\u2019ao"
    ],
    "wof:name":"Zhaojia'ao",
    "wof:placetype":"locality"
},
  "geometry": {"coordinates":[122.28749999999999,29.99778],"type":"Point"}
}