{
  "type": "Feature",
  "properties": {
    "gn:admin1_code":"4.0",
    "gn:asciiname":"Zhuyaozhuang",
    "gn:country_code":"CN",
    "gn:dem":6,
    "gn:feature_class":"P",
    "gn:feature_code":"PPL",
    "gn:name":"Zhuyaozhuang",
    "gn:population":0,
    "gn:timezone":"Asia/Shanghai",
    "iso:country":"CN",
    "name:zho_x_preferred":[
        "Zhuyaozhuang"
    ],
    "name:zho_x_variant":[
        "\u6731\u59da\u5e84"
    ],
    "wof:name":"Zhuyaozhuang",
    "wof:placetype":"locality"
},
  "geometry": {"coordinates":[119.07438999999999,33.1519],"type":"Point"}
}