{
  "type": "Feature",
  "properties": {
    "gn:admin1_code":"1.0",
    "gn:asciiname":"Tanqiaocun",
    "gn:country_code":"CN",
    "gn:dem":18,
    "gn:feature_class":"P",
    "gn:feature_code":"PPL",
    "gn:name":"Tanqiaocun",
    "gn:population":0,
    "gn:timezone":"Asia/Shanghai",
    "iso:country":"CN",
    "name:zho_x_preferred":[
        "\u8c2d\u6865\u6751"
    ],
    "wof:name":"Tanqiaocun",
    "wof:placetype":"locality"
},
  "geometry": {"coordinates":[116.89915000000001,30.68424000000001],"type":"Point"}
}