{
  "type": "Feature",
  "properties": {
    "gn:admin1_code":"29.0",
    "gn:asciiname":"Liyuantian",
    "gn:country_code":"CN",
    "gn:dem":1679,
    "gn:feature_class":"P",
    "gn:feature_code":"PPL",
    "gn:name":"Liyuantian",
    "gn:population":0,
    "gn:timezone":"Asia/Shanghai",
    "iso:country":"CN",
    "name:zho_x_preferred":[
        "\u674e\u56ed\u7530"
    ],
    "wof:name":"Liyuantian",
    "wof:placetype":"locality"
},
  "geometry": {"coordinates":[100.985,25.9078],"type":"Point"}
}