{
  "type": "Feature",
  "properties": {
    "gn:admin1_code":"25.0",
    "gn:asciiname":"Zhanghaicun",
    "gn:country_code":"CN",
    "gn:dem":43,
    "gn:feature_class":"P",
    "gn:feature_code":"PPL",
    "gn:name":"Zhanghaicun",
    "gn:population":0,
    "gn:timezone":"Asia/Shanghai",
    "iso:country":"CN",
    "name:und_x_variant":[
        "Luohai"
    ],
    "name:zho_x_preferred":[
        "\u5f20\u6d77\u6751"
    ],
    "name:zho_x_variant":[
        "\u7f57\u6d77"
    ],
    "wof:name":"Zhanghaicun",
    "wof:placetype":"locality"
},
  "geometry": {"coordinates":[115.82984,36.16203],"type":"Point"}
}