{
  "type": "Feature",
  "properties": {
    "gn:admin1_code":"29",
    "gn:asciiname":"Xiananshan",
    "gn:country_code":"CN",
    "gn:dem":1934,
    "gn:feature_class":"P",
    "gn:feature_code":"PPL",
    "gn:name":"Xiananshan",
    "gn:population":0,
    "gn:timezone":"Asia/Shanghai",
    "iso:country":"CN",
    "name:zho_x_preferred":[
        "\u4e0b\u5357\u5c71"
    ],
    "wof:name":"Xiananshan",
    "wof:placetype":"locality"
},
  "geometry": {"coordinates":[102.758,24.636],"type":"Point"}
}