{
  "type": "Feature",
  "properties": {
    "gn:admin1_code":"26.0",
    "gn:asciiname":"Xinxingcun",
    "gn:country_code":"CN",
    "gn:dem":541,
    "gn:feature_class":"P",
    "gn:feature_code":"PPL",
    "gn:name":"Xinxingcun",
    "gn:population":0,
    "gn:timezone":"Asia/Shanghai",
    "iso:country":"CN",
    "name:zho_x_preferred":[
        "\u65b0\u661f\u6751"
    ],
    "wof:name":"Xinxingcun",
    "wof:placetype":"locality"
},
  "geometry": {"coordinates":[108.69754,32.73875],"type":"Point"}
}