{
  "type": "Feature",
  "properties": {
    "gn:admin1_code":"8.0",
    "gn:asciiname":"Caoyoufang",
    "gn:country_code":"CN",
    "gn:dem":197,
    "gn:feature_class":"P",
    "gn:feature_code":"PPL",
    "gn:name":"Caoyoufang",
    "gn:population":0,
    "gn:timezone":"Asia/Shanghai",
    "iso:country":"CN",
    "name:zho_x_preferred":[
        "\u66f9\u6cb9\u574a"
    ],
    "wof:name":"Caoyoufang",
    "wof:placetype":"locality"
},
  "geometry": {"coordinates":[127.12099000000001,44.72395],"type":"Point"}
}