{
  "type": "Feature",
  "properties": {
    "gn:admin1_code":"32.0",
    "gn:asciiname":"Baishidui",
    "gn:country_code":"CN",
    "gn:dem":2193,
    "gn:feature_class":"P",
    "gn:feature_code":"PPL",
    "gn:name":"Baishidui",
    "gn:population":0,
    "gn:timezone":"Asia/Shanghai",
    "iso:country":"CN",
    "name:zho_x_preferred":[
        "\u767d\u77f3\u5806"
    ],
    "wof:name":"Baishidui",
    "wof:placetype":"locality"
},
  "geometry": {"coordinates":[102.098,27.1133],"type":"Point"}
}