{
  "type": "Feature",
  "properties": {
    "gn:admin1_code":"15",
    "gn:asciiname":"Tuwopu",
    "gn:country_code":"CN",
    "gn:dem":1346,
    "gn:feature_class":"P",
    "gn:feature_code":"PPL",
    "gn:name":"Tuwopu",
    "gn:population":0,
    "gn:timezone":"Asia/Shanghai",
    "iso:country":"CN",
    "name:zho_x_preferred":[
        "\u571f\u7a9d\u94fa"
    ],
    "wof:name":"Tuwopu",
    "wof:placetype":"locality"
},
  "geometry": {"coordinates":[102.148,38.8531],"type":"Point"}
}