{
  "type": "Feature",
  "properties": {
    "gn:admin1_code":"19.0",
    "gn:asciiname":"Qianhaodianzi",
    "gn:country_code":"CN",
    "gn:dem":107,
    "gn:feature_class":"P",
    "gn:feature_code":"PPL",
    "gn:name":"Qianhaodianzi",
    "gn:population":0,
    "gn:timezone":"Asia/Shanghai",
    "iso:country":"CN",
    "name:zho_x_preferred":[
        "\u524d\u84bf\u7538\u5b50"
    ],
    "wof:name":"Qianhaodianzi",
    "wof:placetype":"locality"
},
  "geometry": {"coordinates":[123.58938000000001,41.17557],"type":"Point"}
}