{
  "type": "Feature",
  "properties": {
    "gn:admin1_code":"22",
    "gn:asciiname":"Beixinzhuang",
    "gn:country_code":"CN",
    "gn:dem":22,
    "gn:feature_class":"P",
    "gn:feature_code":"PPL",
    "gn:name":"Beixinzhuang",
    "gn:population":0,
    "gn:timezone":"Asia/Shanghai",
    "iso:country":"CN",
    "name:zho_x_preferred":[
        "\u5317\u8f9b\u5e84"
    ],
    "wof:name":"Beixinzhuang",
    "wof:placetype":"locality"
},
  "geometry": {"coordinates":[116.62805,39.70148],"type":"Point"}
}