{
  "type": "Feature",
  "properties": {
    "gn:admin1_code":"12.0",
    "gn:asciiname":"Dongzhang Jiatai",
    "gn:country_code":"CN",
    "gn:dem":28,
    "gn:feature_class":"P",
    "gn:feature_code":"PPL",
    "gn:name":"Dongzhang Jiatai",
    "gn:population":0,
    "gn:timezone":"Asia/Shanghai",
    "iso:country":"CN",
    "name:zho_x_preferred":[
        "\u4e1c\u5f20\u5bb6\u53f0"
    ],
    "wof:name":"Dongzhang Jiatai",
    "wof:placetype":"locality"
},
  "geometry": {"coordinates":[112.45690999999999,30.35599],"type":"Point"}
}