{
  "type": "Feature",
  "properties": {
    "gn:admin1_code":"15.0",
    "gn:asciiname":"Sijiawan",
    "gn:country_code":"CN",
    "gn:dem":1930,
    "gn:feature_class":"P",
    "gn:feature_code":"PPL",
    "gn:name":"Sijiawan",
    "gn:population":0,
    "gn:timezone":"Asia/Shanghai",
    "iso:country":"CN",
    "name:und_x_variant":[
        "\u53f8\u5bb6\u6e7e"
    ],
    "wof:name":"Sijiawan",
    "wof:placetype":"locality"
},
  "geometry": {"coordinates":[105.13115000000001,35.82141],"type":"Point"}
}