{
  "type": "Feature",
  "properties": {
    "gn:admin1_code":"31.0",
    "gn:asciiname":"Yalu",
    "gn:country_code":"CN",
    "gn:dem":29,
    "gn:feature_class":"P",
    "gn:feature_code":"PPL",
    "gn:name":"Yal\u00fc",
    "gn:population":0,
    "gn:timezone":"Asia/Shanghai",
    "iso:country":"CN",
    "name:und_x_variant":[
        "Yal\u00fc"
    ],
    "name:zho_x_preferred":[
        "\u9e2d\u7eff"
    ],
    "wof:name":"Yalu",
    "wof:placetype":"locality"
},
  "geometry": {"coordinates":[110.73782,19.83309],"type":"Point"}
}