{
  "type": "Feature",
  "properties": {
    "gn:admin1_code":"8.0",
    "gn:asciiname":"Zhangmenggutun",
    "gn:country_code":"CN",
    "gn:dem":301,
    "gn:feature_class":"P",
    "gn:feature_code":"PPL",
    "gn:name":"Zhangmenggutun",
    "gn:population":0,
    "gn:timezone":"Asia/Shanghai",
    "iso:country":"CN",
    "name:zho_x_preferred":[
        "\u5f20\u8499\u53e4\u5c6f"
    ],
    "wof:name":"Zhangmenggutun",
    "wof:placetype":"locality"
},
  "geometry": {"coordinates":[125.49518999999999,48.40598],"type":"Point"}
}