{
  "type": "Feature",
  "properties": {
    "gn:admin1_code":"3.0",
    "gn:asciiname":"Jiashang",
    "gn:country_code":"CN",
    "gn:dem":385,
    "gn:feature_class":"P",
    "gn:feature_code":"PPL",
    "gn:name":"Jiashang",
    "gn:population":0,
    "gn:timezone":"Asia/Shanghai",
    "iso:country":"CN",
    "name:und_x_variant":[
        "\u67b6\u4e0a"
    ],
    "wof:name":"Jiashang",
    "wof:placetype":"locality"
},
  "geometry": {"coordinates":[116.88293,27.6235],"type":"Point"}
}