{
  "type": "Feature",
  "properties": {
    "gn:admin1_code":"8.0",
    "gn:asciiname":"Xinfucun",
    "gn:country_code":"CN",
    "gn:dem":377,
    "gn:feature_class":"P",
    "gn:feature_code":"PPL",
    "gn:name":"Xinfucun",
    "gn:population":0,
    "gn:timezone":"Asia/Shanghai",
    "iso:country":"CN",
    "name:zho_x_preferred":[
        "\u65b0\u5bcc\u6751"
    ],
    "wof:name":"Xinfucun",
    "wof:placetype":"locality"
},
  "geometry": {"coordinates":[130.51840000000001,45.29548],"type":"Point"}
}