{
  "type": "Feature",
  "properties": {
    "gn:admin1_code":"19.0",
    "gn:asciiname":"Liudaogou",
    "gn:country_code":"CN",
    "gn:dem":124,
    "gn:feature_class":"P",
    "gn:feature_code":"PPL",
    "gn:name":"Liudaogou",
    "gn:population":0,
    "gn:timezone":"Asia/Shanghai",
    "iso:country":"CN",
    "name:und_x_variant":[
        "\u516d\u9053\u6c9f"
    ],
    "wof:name":"Liudaogou",
    "wof:placetype":"locality"
},
  "geometry": {"coordinates":[122.67950999999999,40.49191],"type":"Point"}
}