{
  "type": "Feature",
  "properties": {
    "gn:admin1_code":"33.0",
    "gn:asciiname":"Caiyuanjiao",
    "gn:country_code":"CN",
    "gn:dem":381,
    "gn:feature_class":"P",
    "gn:feature_code":"PPL",
    "gn:name":"Caiyuanjiao",
    "gn:population":0,
    "gn:timezone":"Asia/Shanghai",
    "iso:country":"CN",
    "name:zho_x_preferred":[
        "\u83dc\u56ed\u89d2"
    ],
    "wof:name":"Caiyuanjiao",
    "wof:placetype":"locality"
},
  "geometry": {"coordinates":[105.86802,28.95219],"type":"Point"}
}