{
  "type": "Feature",
  "properties": {
    "gn:admin1_code":"30",
    "gn:asciiname":"Shanying",
    "gn:country_code":"CN",
    "gn:dem":22,
    "gn:feature_class":"P",
    "gn:feature_code":"PPL",
    "gn:name":"Shanying",
    "gn:population":0,
    "gn:timezone":"Asia/Urumqi",
    "iso:country":"CN",
    "name:zho_x_preferred":[
        "\u5c71\u8425"
    ],
    "wof:name":"Shanying",
    "wof:placetype":"locality"
},
  "geometry": {"coordinates":[110.01775000000001,21.67049],"type":"Point"}
}