{
  "type": "Feature",
  "properties": {
    "gn:admin1_code":"25",
    "gn:asciiname":"Guanshuai",
    "gn:cc2":"CN",
    "gn:country_code":"CN",
    "gn:dem":144,
    "gn:feature_class":"P",
    "gn:feature_code":"PPL",
    "gn:name":"Guanshuai",
    "gn:population":0,
    "gn:timezone":"Asia/Shanghai",
    "iso:country":"CN",
    "name:und_x_variant":[
        "Kuan-shuai-chen",
        "Kuan-shuai",
        "Guanshuai"
    ],
    "wof:name":"Guanshuai",
    "wof:placetype":"locality"
},
  "geometry": {"coordinates":[118.98333,35.91667],"type":"Point"}
}