{
  "type": "Feature",
  "properties": {
    "gn:admin1_code":"31.0",
    "gn:asciiname":"Shatian",
    "gn:country_code":"CN",
    "gn:dem":69,
    "gn:feature_class":"P",
    "gn:feature_code":"PPL",
    "gn:name":"Shatian",
    "gn:population":0,
    "gn:timezone":"Asia/Shanghai",
    "iso:country":"CN",
    "name:ceb_x_preferred":[
        "Shatian"
    ],
    "name:deu_x_preferred":[
        "Shatian"
    ],
    "name:jpn_x_preferred":[
        "\u6c99\u7530"
    ],
    "name:swe_x_preferred":[
        "Shatian"
    ],
    "name:zho_x_preferred":[
        "\u6c99\u7530"
    ],
    "wof:name":"Shatian",
    "wof:placetype":"locality"
},
  "geometry": {"coordinates":[108.98223,19.36442000000001],"type":"Point"}
}