{
  "type": "Feature",
  "properties": {
    "gn:admin1_code":"18",
    "gn:asciiname":"Maichong",
    "gn:country_code":"CN",
    "gn:dem":1147,
    "gn:feature_class":"P",
    "gn:feature_code":"PPL",
    "gn:name":"Maichong",
    "gn:population":0,
    "gn:timezone":"Asia/Shanghai",
    "iso:country":"CN",
    "name:zho_x_preferred":[
        "\u9ea6\u51b2"
    ],
    "wof:name":"Maichong",
    "wof:placetype":"locality"
},
  "geometry": {"coordinates":[107.017,26.4928],"type":"Point"}
}