{
  "type": "Feature",
  "properties": {
    "gn:admin1_code":"3.0",
    "gn:asciiname":"Wangjiacao",
    "gn:country_code":"CN",
    "gn:dem":329,
    "gn:feature_class":"P",
    "gn:feature_code":"PPL",
    "gn:name":"Wangjiacao",
    "gn:population":0,
    "gn:timezone":"Asia/Shanghai",
    "iso:country":"CN",
    "name:und_x_variant":[
        "\u6c6a\u5bb6\u69fd"
    ],
    "wof:name":"Wangjiacao",
    "wof:placetype":"locality"
},
  "geometry": {"coordinates":[114.47322,28.46937],"type":"Point"}
}