{
  "type": "Feature",
  "properties": {
    "gn:admin1_code":"7.0",
    "gn:asciiname":"Wulongshan",
    "gn:country_code":"CN",
    "gn:dem":417,
    "gn:feature_class":"P",
    "gn:feature_code":"PPL",
    "gn:name":"Wulongshan",
    "gn:population":0,
    "gn:timezone":"Asia/Shanghai",
    "iso:country":"CN",
    "name:zho_x_preferred":[
        "\u4e94\u9f99\u5c71"
    ],
    "wof:name":"Wulongshan",
    "wof:placetype":"locality"
},
  "geometry": {"coordinates":[117.96253,25.30463],"type":"Point"}
}