{
  "type": "Feature",
  "properties": {
    "gn:admin1_code":"16.0",
    "gn:asciiname":"Liuwei",
    "gn:country_code":"CN",
    "gn:dem":678,
    "gn:feature_class":"P",
    "gn:feature_code":"PPL",
    "gn:name":"Liuwei",
    "gn:population":0,
    "gn:timezone":"Asia/Shanghai",
    "iso:country":"CN",
    "name:zho_x_preferred":[
        "\u516d\u4e3a"
    ],
    "wof:name":"Liuwei",
    "wof:placetype":"locality"
},
  "geometry": {"coordinates":[106.31699999999999,24.254],"type":"Point"}
}