{
  "type": "Feature",
  "properties": {
    "gn:admin1_code":"4.0",
    "gn:asciiname":"Dahuangcun",
    "gn:country_code":"CN",
    "gn:dem":15,
    "gn:feature_class":"P",
    "gn:feature_code":"PPL",
    "gn:name":"Dahuangcun",
    "gn:population":0,
    "gn:timezone":"Asia/Shanghai",
    "iso:country":"CN",
    "name:zho_x_preferred":[
        "\u5927\u9ec4\u6751"
    ],
    "wof:name":"Dahuangcun",
    "wof:placetype":"locality"
},
  "geometry": {"coordinates":[118.54053,32.00671],"type":"Point"}
}