{
  "type": "Feature",
  "properties": {
    "gn:admin1_code":"14.0",
    "gn:asciiname":"Babacun",
    "gn:country_code":"CN",
    "gn:dem":4200,
    "gn:feature_class":"P",
    "gn:feature_code":"PPL",
    "gn:name":"Babacun",
    "gn:population":0,
    "gn:timezone":"Asia/Urumqi",
    "iso:country":"CN",
    "name:zho_x_preferred":[
        "\u5df4\u5df4\u6751"
    ],
    "wof:name":"Babacun",
    "wof:placetype":"locality"
},
  "geometry": {"coordinates":[94.80835,31.6704],"type":"Point"}
}