{
  "type": "Feature",
  "properties": {
    "gn:admin1_code":"30.0",
    "gn:asciiname":"Tongpacun",
    "gn:country_code":"CN",
    "gn:dem":64,
    "gn:feature_class":"P",
    "gn:feature_code":"PPL",
    "gn:name":"Tongpacun",
    "gn:population":0,
    "gn:timezone":"Asia/Shanghai",
    "iso:country":"CN",
    "name:zho_x_preferred":[
        "\u94dc\u7436\u6751"
    ],
    "wof:name":"Tongpacun",
    "wof:placetype":"locality"
},
  "geometry": {"coordinates":[116.42807999999999,24.50868],"type":"Point"}
}