{
  "type": "Feature",
  "properties": {
    "gn:admin1_code":"32.0",
    "gn:asciiname":"Qishuwan",
    "gn:country_code":"CN",
    "gn:dem":816,
    "gn:feature_class":"P",
    "gn:feature_code":"PPL",
    "gn:name":"Qishuwan",
    "gn:population":0,
    "gn:timezone":"Asia/Shanghai",
    "iso:country":"CN",
    "name:zho_x_preferred":[
        "\u6f06\u6811\u6e7e"
    ],
    "wof:name":"Qishuwan",
    "wof:placetype":"locality"
},
  "geometry": {"coordinates":[105.24165000000001,28.07818],"type":"Point"}
}