{
  "type": "Feature",
  "properties": {
    "gn:admin1_code":"16.0",
    "gn:asciiname":"Guoma",
    "gn:country_code":"CN",
    "gn:dem":335,
    "gn:feature_class":"P",
    "gn:feature_code":"PPL",
    "gn:name":"Guoma",
    "gn:population":0,
    "gn:timezone":"Asia/Shanghai",
    "iso:country":"CN",
    "name:zho_x_preferred":[
        "\u679c\u9ebb"
    ],
    "wof:name":"Guoma",
    "wof:placetype":"locality"
},
  "geometry": {"coordinates":[108.03100000000001,24.2999],"type":"Point"}
}