{
  "type": "Feature",
  "properties": {
    "gn:admin1_code":"8.0",
    "gn:asciiname":"Gouliucun",
    "gn:country_code":"CN",
    "gn:dem":199,
    "gn:feature_class":"P",
    "gn:feature_code":"PPL",
    "gn:name":"Gouliucun",
    "gn:population":0,
    "gn:timezone":"Asia/Shanghai",
    "iso:country":"CN",
    "name:zho_x_preferred":[
        "\u6c9f\u5218\u6751"
    ],
    "wof:name":"Gouliucun",
    "wof:placetype":"locality"
},
  "geometry": {"coordinates":[127.32344999999999,47.03495],"type":"Point"}
}