{
  "type": "Feature",
  "properties": {
    "gn:admin1_code":"26.0",
    "gn:asciiname":"Tianjiawuchang",
    "gn:country_code":"CN",
    "gn:dem":670,
    "gn:feature_class":"P",
    "gn:feature_code":"PPL",
    "gn:name":"Tianjiawuchang",
    "gn:population":0,
    "gn:timezone":"Asia/Shanghai",
    "iso:country":"CN",
    "name:zho_x_preferred":[
        "\u7530\u5bb6\u5c4b\u573a"
    ],
    "wof:name":"Tianjiawuchang",
    "wof:placetype":"locality"
},
  "geometry": {"coordinates":[108.92097,32.39104],"type":"Point"}
}