{
  "type": "Feature",
  "properties": {
    "gn:admin1_code":"1.0",
    "gn:asciiname":"Sangshuxingcun",
    "gn:country_code":"CN",
    "gn:dem":39,
    "gn:feature_class":"P",
    "gn:feature_code":"PPL",
    "gn:name":"Sangshuxingcun",
    "gn:population":0,
    "gn:timezone":"Asia/Shanghai",
    "iso:country":"CN",
    "name:zho_x_preferred":[
        "\u6851\u6811\u884c\u6751"
    ],
    "wof:name":"Sangshuxingcun",
    "wof:placetype":"locality"
},
  "geometry": {"coordinates":[115.70873,33.50302],"type":"Point"}
}