{
  "type": "Feature",
  "properties": {
    "gn:admin1_code":"32.0",
    "gn:asciiname":"Baxue",
    "gn:country_code":"CN",
    "gn:dem":3594,
    "gn:feature_class":"P",
    "gn:feature_code":"PPL",
    "gn:name":"Baxue",
    "gn:population":0,
    "gn:timezone":"Asia/Shanghai",
    "iso:country":"CN",
    "name:zho_x_preferred":[
        "\u516b\u5b66"
    ],
    "wof:name":"Baxue",
    "wof:placetype":"locality"
},
  "geometry": {"coordinates":[98.9849,30.6227],"type":"Point"}
}