{
  "type": "Feature",
  "properties": {
    "gn:admin1_code":"11.0",
    "gn:asciiname":"Hongqiao",
    "gn:country_code":"CN",
    "gn:dem":66,
    "gn:feature_class":"P",
    "gn:feature_code":"PPL",
    "gn:name":"Hongqiao",
    "gn:population":0,
    "gn:timezone":"Asia/Shanghai",
    "iso:country":"CN",
    "name:ceb_x_preferred":[
        "Hongqiao"
    ],
    "name:deu_x_preferred":[
        "Hongqiao"
    ],
    "name:fra_x_preferred":[
        "Hongqiao"
    ],
    "name:kor_x_preferred":[
        "\ud6d9\ucc28\uc624"
    ],
    "name:mlg_x_preferred":[
        "Hongqiao"
    ],
    "name:zho_x_preferred":[
        "\u8679\u6865"
    ],
    "wof:name":"Hongqiao",
    "wof:placetype":"locality"
},
  "geometry": {"coordinates":[113.5971,27.70783],"type":"Point"}
}