{
  "type": "Feature",
  "properties": {
    "gn:admin1_code":"07",
    "gn:asciiname":"Huangdankeng",
    "gn:country_code":"CN",
    "gn:dem":615,
    "gn:feature_class":"P",
    "gn:feature_code":"PPL",
    "gn:name":"Huangdankeng",
    "gn:population":0,
    "gn:timezone":"Asia/Shanghai",
    "iso:country":"CN",
    "name:und_x_variant":[
        "Huangtankeng"
    ],
    "name:zho_x_preferred":[
        "\u9ec4\u6de1\u5751"
    ],
    "wof:name":"Huangdankeng",
    "wof:placetype":"locality"
},
  "geometry": {"coordinates":[117.29111,25.95194],"type":"Point"}
}