{
  "type": "Feature",
  "properties": {
    "gn:admin1_code":"21.0",
    "gn:asciiname":"Tong'erzhuang",
    "gn:country_code":"CN",
    "gn:dem":1540,
    "gn:feature_class":"P",
    "gn:feature_code":"PPL",
    "gn:name":"Tong\u2019erzhuang",
    "gn:population":0,
    "gn:timezone":"Asia/Shanghai",
    "iso:country":"CN",
    "name:und_x_variant":[
        "Tong\u2019erzhuang"
    ],
    "name:zho_x_preferred":[
        "\u7ae5\u513f\u5e84"
    ],
    "wof:name":"Tong'erzhuang",
    "wof:placetype":"locality"
},
  "geometry": {"coordinates":[106.54000000000001,37.1337],"type":"Point"}
}