{
  "type": "Feature",
  "properties": {
    "gn:admin1_code":"4.0",
    "gn:asciiname":"Jiangyuan",
    "gn:country_code":"CN",
    "gn:dem":10,
    "gn:feature_class":"P",
    "gn:feature_code":"PPL",
    "gn:name":"Jiangyuan",
    "gn:population":0,
    "gn:timezone":"Asia/Shanghai",
    "iso:country":"CN",
    "name:ceb_x_preferred":[
        "Jiangyuan"
    ],
    "name:fra_x_preferred":[
        "Jiangyuan"
    ],
    "name:kor_x_preferred":[
        "\uc7a5\uc704\uc548"
    ],
    "name:zho_x_preferred":[
        "\u848b\u56ed"
    ],
    "wof:name":"Jiangyuan",
    "wof:placetype":"locality"
},
  "geometry": {"coordinates":[118.76288,34.2417],"type":"Point"}
}