{
  "type": "Feature",
  "properties": {
    "gn:admin1_code":"32",
    "gn:asciiname":"Chaotian",
    "gn:country_code":"CN",
    "gn:dem":513,
    "gn:feature_class":"P",
    "gn:feature_code":"PPLA3",
    "gn:name":"Chaotian",
    "gn:population":0,
    "gn:timezone":"Asia/Shanghai",
    "iso:country":"CN",
    "name:und_x_variant":[
        "Chaotianyi",
        "Chaotian"
    ],
    "name:zho_x_preferred":[
        "Chzhaotyan\u2019"
    ],
    "name:zho_x_variant":[
        "Ch\u2019ao-t\u2019ien",
        "Ch\u2019ao-t\u2019ien-kuan",
        "Ch\u2019ao-t\u2019ien-i",
        "\u671d\u5929"
    ],
    "wof:name":"Chaotian",
    "wof:placetype":"locality"
},
  "geometry": {"coordinates":[105.88500999999999,32.64462],"type":"Point"}
}