{
  "type": "Feature",
  "properties": {
    "gn:admin1_code":"4.0",
    "gn:asciiname":"Banyu Liuzu",
    "gn:country_code":"CN",
    "gn:dem":2,
    "gn:feature_class":"P",
    "gn:feature_code":"PPLF",
    "gn:name":"Banyu Liuzu",
    "gn:population":0,
    "gn:timezone":"Asia/Shanghai",
    "iso:country":"CN",
    "name:und_x_variant":[
        "\u677f\u9c7c\u516d\u7ec4"
    ],
    "name:zho_x_preferred":[
        "\u677f\u9c7c\u516d\u7ec4"
    ],
    "wof:name":"Banyu Liuzu",
    "wof:placetype":"locality"
},
  "geometry": {"coordinates":[121.00686,31.40216],"type":"Point"}
}