{
  "type": "Feature",
  "properties": {
    "gn:admin1_code":"12.0",
    "gn:asciiname":"Wanjiashan",
    "gn:country_code":"CN",
    "gn:dem":478,
    "gn:feature_class":"P",
    "gn:feature_code":"PPL",
    "gn:name":"Wanjiashan",
    "gn:population":0,
    "gn:timezone":"Asia/Shanghai",
    "iso:country":"CN",
    "name:zho_x_preferred":[
        "\u4e07\u5bb6\u5c71"
    ],
    "wof:name":"Wanjiashan",
    "wof:placetype":"locality"
},
  "geometry": {"coordinates":[115.28707,31.09347],"type":"Point"}
}