{
  "type": "Feature",
  "properties": {
    "gn:admin1_code":"32.0",
    "gn:asciiname":"Tianya",
    "gn:country_code":"CN",
    "gn:dem":989,
    "gn:feature_class":"P",
    "gn:feature_code":"PPL",
    "gn:name":"Tianya",
    "gn:population":0,
    "gn:timezone":"Asia/Shanghai",
    "iso:country":"CN",
    "name:und_x_variant":[
        "\u7530\u57ad"
    ],
    "wof:name":"Tianya",
    "wof:placetype":"locality"
},
  "geometry": {"coordinates":[106.14091000000001,32.14929],"type":"Point"}
}