{
  "type": "Feature",
  "properties": {
    "gn:admin1_code":"2.0",
    "gn:asciiname":"Dongshantou",
    "gn:country_code":"CN",
    "gn:dem":389,
    "gn:feature_class":"P",
    "gn:feature_code":"PPL",
    "gn:name":"Dongshantou",
    "gn:population":0,
    "gn:timezone":"Asia/Shanghai",
    "iso:country":"CN",
    "name:zho_x_preferred":[
        "\u4e1c\u5c71\u5934"
    ],
    "wof:name":"Dongshantou",
    "wof:placetype":"locality"
},
  "geometry": {"coordinates":[120.16103,27.68492],"type":"Point"}
}