{
  "type": "Feature",
  "properties": {
    "gn:admin1_code":"3.0",
    "gn:asciiname":"Xinjie",
    "gn:country_code":"CN",
    "gn:dem":192,
    "gn:feature_class":"P",
    "gn:feature_code":"PPL",
    "gn:name":"Xinjie",
    "gn:population":0,
    "gn:timezone":"Asia/Shanghai",
    "iso:country":"CN",
    "name:und_x_variant":[
        "\u65b0\u8857"
    ],
    "wof:name":"Xinjie",
    "wof:placetype":"locality"
},
  "geometry": {"coordinates":[115.96630999999999,26.20069],"type":"Point"}
}