{
  "type": "Feature",
  "properties": {
    "gn:admin1_code":"30.0",
    "gn:asciiname":"Yuzhoucun",
    "gn:country_code":"CN",
    "gn:dem":59,
    "gn:feature_class":"P",
    "gn:feature_code":"PPL",
    "gn:name":"Yuzhoucun",
    "gn:population":0,
    "gn:timezone":"Asia/Shanghai",
    "iso:country":"CN",
    "name:zho_x_preferred":[
        "\u88d5\u6d32\u6751"
    ],
    "wof:name":"Yuzhoucun",
    "wof:placetype":"locality"
},
  "geometry": {"coordinates":[116.53534999999999,24.31628],"type":"Point"}
}