{
  "type": "Feature",
  "properties": {
    "gn:admin1_code":"25.0",
    "gn:asciiname":"Nanma",
    "gn:country_code":"CN",
    "gn:dem":53,
    "gn:feature_class":"P",
    "gn:feature_code":"PPL",
    "gn:name":"Nanma",
    "gn:population":0,
    "gn:timezone":"Asia/Shanghai",
    "iso:country":"CN",
    "name:mlg_x_preferred":[
        "Nanma"
    ],
    "name:zho_x_preferred":[
        "\u5357\u9a6c"
    ],
    "wof:name":"Nanma",
    "wof:placetype":"locality"
},
  "geometry": {"coordinates":[122.00884000000001,37.13712],"type":"Point"}
}