{
  "type": "Feature",
  "properties": {
    "gn:admin1_code":"15.0",
    "gn:asciiname":"Nuanhewan",
    "gn:country_code":"CN",
    "gn:dem":1208,
    "gn:feature_class":"P",
    "gn:feature_code":"PPL",
    "gn:name":"Nuanhewan",
    "gn:population":0,
    "gn:timezone":"Asia/Shanghai",
    "iso:country":"CN",
    "name:zho_x_preferred":[
        "\u6696\u548c\u6e7e"
    ],
    "wof:name":"Nuanhewan",
    "wof:placetype":"locality"
},
  "geometry": {"coordinates":[105.681,34.5569],"type":"Point"}
}