{
  "type": "Feature",
  "properties": {
    "gn:admin1_code":"19.0",
    "gn:asciiname":"Guangdong Caigou",
    "gn:country_code":"CN",
    "gn:dem":66,
    "gn:feature_class":"P",
    "gn:feature_code":"PPL",
    "gn:name":"Guangdong Caigou",
    "gn:population":0,
    "gn:timezone":"Asia/Shanghai",
    "iso:country":"CN",
    "name:und_x_variant":[
        "\u5e7f\u4e1c\u83dc\u6c9f"
    ],
    "wof:name":"Guangdong Caigou",
    "wof:placetype":"locality"
},
  "geometry": {"coordinates":[123.75329000000001,40.20049],"type":"Point"}
}