{
  "type": "Feature",
  "properties": {
    "gn:admin1_code":"14.0",
    "gn:asciiname":"Guojiangma",
    "gn:country_code":"CN",
    "gn:dem":4491,
    "gn:feature_class":"P",
    "gn:feature_code":"PPL",
    "gn:name":"Guojiangma",
    "gn:population":0,
    "gn:timezone":"Asia/Shanghai",
    "iso:country":"CN",
    "name:zho_x_preferred":[
        "\u679c\u6c5f\u739b"
    ],
    "wof:name":"Guojiangma",
    "wof:placetype":"locality"
},
  "geometry": {"coordinates":[81.91901999999997,32.88861],"type":"Point"}
}