{
  "type": "Feature",
  "properties": {
    "gn:admin1_code":"30.0",
    "gn:asciiname":"Jilongwei",
    "gn:country_code":"CN",
    "gn:dem":388,
    "gn:feature_class":"P",
    "gn:feature_code":"PPL",
    "gn:name":"Jilongwei",
    "gn:population":0,
    "gn:timezone":"Asia/Shanghai",
    "iso:country":"CN",
    "name:zho_x_preferred":[
        "\u9e21\u9f99\u5c3e"
    ],
    "wof:name":"Jilongwei",
    "wof:placetype":"locality"
},
  "geometry": {"coordinates":[112.64797,23.65582],"type":"Point"}
}