{
  "type": "Feature",
  "properties": {
    "gn:admin1_code":"16.0",
    "gn:asciiname":"Guotao",
    "gn:country_code":"CN",
    "gn:dem":852,
    "gn:feature_class":"P",
    "gn:feature_code":"PPL",
    "gn:name":"Guotao",
    "gn:population":0,
    "gn:timezone":"Asia/Shanghai",
    "iso:country":"CN",
    "name:zho_x_preferred":[
        "\u679c\u6843"
    ],
    "wof:name":"Guotao",
    "wof:placetype":"locality"
},
  "geometry": {"coordinates":[105.962,23.4299],"type":"Point"}
}