{
  "type": "Feature",
  "properties": {
    "gn:admin1_code":"4.0",
    "gn:asciiname":"Yangao",
    "gn:country_code":"CN",
    "gn:dem":8,
    "gn:feature_class":"P",
    "gn:feature_code":"PPL",
    "gn:name":"Yangao",
    "gn:population":0,
    "gn:timezone":"Asia/Shanghai",
    "iso:country":"CN",
    "name:zho_x_preferred":[
        "Yangao"
    ],
    "name:zho_x_variant":[
        "\u4e25\u9ad8"
    ],
    "wof:name":"Yangao",
    "wof:placetype":"locality"
},
  "geometry": {"coordinates":[119.19484,33.63205],"type":"Point"}
}