{
  "type": "Feature",
  "properties": {
    "gn:admin1_code":"30.0",
    "gn:asciiname":"Chenjiang Xincun",
    "gn:country_code":"CN",
    "gn:dem":14,
    "gn:feature_class":"P",
    "gn:feature_code":"PPL",
    "gn:name":"Chenjiang Xincun",
    "gn:population":0,
    "gn:timezone":"Asia/Shanghai",
    "iso:country":"CN",
    "name:zho_x_preferred":[
        "\u9648\u6c5f\u65b0\u6751"
    ],
    "wof:name":"Chenjiang Xincun",
    "wof:placetype":"locality"
},
  "geometry": {"coordinates":[114.32057,23.00719],"type":"Point"}
}