{
  "type": "Feature",
  "properties": {
    "gn:admin1_code":"26",
    "gn:asciiname":"Liushudian",
    "gn:cc2":"CN",
    "gn:country_code":"CN",
    "gn:dem":745,
    "gn:feature_class":"P",
    "gn:feature_code":"PPL",
    "gn:name":"Liushudian",
    "gn:population":0,
    "gn:timezone":"Asia/Shanghai",
    "iso:country":"CN",
    "name:und_x_variant":[
        "Liu-shu-tien",
        "Liushudian"
    ],
    "wof:name":"Liushudian",
    "wof:placetype":"locality"
},
  "geometry": {"coordinates":[107.12667,33.48083],"type":"Point"}
}