{
  "type": "Feature",
  "properties": {
    "gn:admin1_code":"9.0",
    "gn:asciiname":"Gongmazhuang",
    "gn:country_code":"CN",
    "gn:dem":100,
    "gn:feature_class":"P",
    "gn:feature_code":"PPL",
    "gn:name":"Gongmazhuang",
    "gn:population":0,
    "gn:timezone":"Asia/Shanghai",
    "iso:country":"CN",
    "name:zho_x_preferred":[
        "\u5f13\u9a6c\u5e84"
    ],
    "wof:name":"Gongmazhuang",
    "wof:placetype":"locality"
},
  "geometry": {"coordinates":[113.81726,34.69042],"type":"Point"}
}