{
  "type": "Feature",
  "properties": {
    "gn:admin1_code":"24.0",
    "gn:asciiname":"Liujiashan",
    "gn:country_code":"CN",
    "gn:dem":990,
    "gn:feature_class":"P",
    "gn:feature_code":"PPL",
    "gn:name":"Liujiashan",
    "gn:population":0,
    "gn:timezone":"Asia/Shanghai",
    "iso:country":"CN",
    "name:zho_x_preferred":[
        "\u5218\u5bb6\u5c71"
    ],
    "wof:name":"Liujiashan",
    "wof:placetype":"locality"
},
  "geometry": {"coordinates":[111.88046,36.55242],"type":"Point"}
}