{
  "type": "Feature",
  "properties": {
    "gn:admin1_code":"4.0",
    "gn:asciiname":"Guyancun",
    "gn:country_code":"CN",
    "gn:dem":5,
    "gn:feature_class":"P",
    "gn:feature_code":"PPL",
    "gn:name":"Guyancun",
    "gn:population":0,
    "gn:timezone":"Asia/Shanghai",
    "iso:country":"CN",
    "name:zho_x_preferred":[
        "\u53e4\u989c\u6751"
    ],
    "wof:name":"Guyancun",
    "wof:placetype":"locality"
},
  "geometry": {"coordinates":[119.50293000000001,33.6189],"type":"Point"}
}