{
  "type": "Feature",
  "properties": {
    "gn:admin1_code":"12.0",
    "gn:asciiname":"Pengsanwan",
    "gn:country_code":"CN",
    "gn:dem":113,
    "gn:feature_class":"P",
    "gn:feature_code":"PPL",
    "gn:name":"Pengsanwan",
    "gn:population":0,
    "gn:timezone":"Asia/Shanghai",
    "iso:country":"CN",
    "name:und_x_variant":[
        "\u68da\u4e09\u5846"
    ],
    "wof:name":"Pengsanwan",
    "wof:placetype":"locality"
},
  "geometry": {"coordinates":[115.24301,30.8252],"type":"Point"}
}