{
  "type": "Feature",
  "properties": {
    "gn:admin1_code":"8.0",
    "gn:asciiname":"Dongliangcun",
    "gn:country_code":"CN",
    "gn:dem":149,
    "gn:feature_class":"P",
    "gn:feature_code":"PPL",
    "gn:name":"Dongliangcun",
    "gn:population":0,
    "gn:timezone":"Asia/Shanghai",
    "iso:country":"CN",
    "name:zho_x_preferred":[
        "\u4e1c\u4eae\u6751"
    ],
    "wof:name":"Dongliangcun",
    "wof:placetype":"locality"
},
  "geometry": {"coordinates":[131.04093999999998,46.705],"type":"Point"}
}