{
  "type": "Feature",
  "properties": {
    "gn:admin1_code":"24.0",
    "gn:asciiname":"Xiagaoshicun",
    "gn:country_code":"CN",
    "gn:dem":361,
    "gn:feature_class":"P",
    "gn:feature_code":"PPL",
    "gn:name":"Xiagaoshicun",
    "gn:population":0,
    "gn:timezone":"Asia/Shanghai",
    "iso:country":"CN",
    "name:zho_x_preferred":[
        "\u4e0b\u9ad8\u5e02\u6751"
    ],
    "wof:name":"Xiagaoshicun",
    "wof:placetype":"locality"
},
  "geometry": {"coordinates":[110.44731000000002,34.93265],"type":"Point"}
}