{
  "type": "Feature",
  "properties": {
    "gn:admin1_code":"24.0",
    "gn:asciiname":"Zhijiaocun",
    "gn:country_code":"CN",
    "gn:dem":1065,
    "gn:feature_class":"P",
    "gn:feature_code":"PPL",
    "gn:name":"Zhijiaocun",
    "gn:population":0,
    "gn:timezone":"Asia/Shanghai",
    "iso:country":"CN",
    "name:und_x_variant":[
        "Chih-chiao",
        "Chih-chiao-ts\u2019un",
        "Zhijiao",
        "Zhijiaocun"
    ],
    "name:zho_x_preferred":[
        "\u652f\u89d2\u6751"
    ],
    "wof:name":"Zhijiaocun",
    "wof:placetype":"locality"
},
  "geometry": {"coordinates":[114.17842,39.39993],"type":"Point"}
}