{
  "type": "Feature",
  "properties": {
    "gn:admin1_code":"4.0",
    "gn:asciiname":"Sheyang",
    "gn:country_code":"CN",
    "gn:dem":4,
    "gn:feature_class":"P",
    "gn:feature_code":"PPL",
    "gn:name":"Sheyang",
    "gn:population":0,
    "gn:timezone":"Asia/Shanghai",
    "iso:country":"CN",
    "name:zho_x_preferred":[
        "\u5c04\u9633"
    ],
    "wof:name":"Sheyang",
    "wof:placetype":"locality"
},
  "geometry": {"coordinates":[119.66674999999999,31.58969],"type":"Point"}
}