{
  "type": "Feature",
  "properties": {
    "gn:admin1_code":"11.0",
    "gn:asciiname":"Laren",
    "gn:country_code":"CN",
    "gn:dem":947,
    "gn:feature_class":"P",
    "gn:feature_code":"PPL",
    "gn:name":"Laren",
    "gn:population":0,
    "gn:timezone":"Asia/Shanghai",
    "iso:country":"CN",
    "name:zho_x_preferred":[
        "\u62c9\u5fcd"
    ],
    "wof:name":"Laren",
    "wof:placetype":"locality"
},
  "geometry": {"coordinates":[109.31416000000002,28.10525],"type":"Point"}
}