{
  "type": "Feature",
  "properties": {
    "gn:admin1_code":"4.0",
    "gn:asciiname":"Zhongdaying",
    "gn:country_code":"CN",
    "gn:dem":6,
    "gn:feature_class":"P",
    "gn:feature_code":"PPL",
    "gn:name":"Zhongdaying",
    "gn:population":0,
    "gn:timezone":"Asia/Shanghai",
    "iso:country":"CN",
    "name:zho_x_preferred":[
        "Zhongdaying"
    ],
    "name:zho_x_variant":[
        "\u4e2d\u5927\u8425"
    ],
    "wof:name":"Zhongdaying",
    "wof:placetype":"locality"
},
  "geometry": {"coordinates":[119.09282,34.58699],"type":"Point"}
}