{
  "type": "Feature",
  "properties": {
    "gn:admin1_code":"20.0",
    "gn:asciiname":"Shifenzi",
    "gn:country_code":"CN",
    "gn:dem":1606,
    "gn:feature_class":"P",
    "gn:feature_code":"PPL",
    "gn:name":"Shifenzi",
    "gn:population":0,
    "gn:timezone":"Asia/Shanghai",
    "iso:country":"CN",
    "name:und_x_variant":[
        "\u5341\u5206\u5b50"
    ],
    "wof:name":"Shifenzi",
    "wof:placetype":"locality"
},
  "geometry": {"coordinates":[109.74813,41.37716],"type":"Point"}
}