{
  "type": "Feature",
  "properties": {
    "gn:admin1_code":"5.0",
    "gn:asciiname":"Lianshancun",
    "gn:country_code":"CN",
    "gn:dem":197,
    "gn:feature_class":"P",
    "gn:feature_code":"PPL",
    "gn:name":"Lianshancun",
    "gn:population":0,
    "gn:timezone":"Asia/Shanghai",
    "iso:country":"CN",
    "name:zho_x_preferred":[
        "\u83b2\u5c71\u6751"
    ],
    "wof:name":"Lianshancun",
    "wof:placetype":"locality"
},
  "geometry": {"coordinates":[126.59399000000001,45.20637],"type":"Point"}
}