{
  "type": "Feature",
  "properties": {
    "gn:admin1_code":"29.0",
    "gn:asciiname":"Mihuadong",
    "gn:country_code":"CN",
    "gn:dem":1461,
    "gn:feature_class":"P",
    "gn:feature_code":"PPL",
    "gn:name":"Mihuadong",
    "gn:population":0,
    "gn:timezone":"Asia/Shanghai",
    "iso:country":"CN",
    "name:zho_x_preferred":[
        "\u5bc6\u82b1\u6d1e"
    ],
    "wof:name":"Mihuadong",
    "wof:placetype":"locality"
},
  "geometry": {"coordinates":[103.703,23.8995],"type":"Point"}
}