{
  "type": "Feature",
  "properties": {
    "gn:admin1_code":"29.0",
    "gn:asciiname":"Pacun",
    "gn:country_code":"CN",
    "gn:dem":2022,
    "gn:feature_class":"P",
    "gn:feature_code":"PPL",
    "gn:name":"Pacun",
    "gn:population":0,
    "gn:timezone":"Asia/Shanghai",
    "iso:country":"CN",
    "name:zho_x_preferred":[
        "\u5e15\u6751"
    ],
    "wof:name":"Pacun",
    "wof:placetype":"locality"
},
  "geometry": {"coordinates":[100.127,25.2665],"type":"Point"}
}