{
  "type": "Feature",
  "properties": {
    "gn:admin1_code":"30",
    "gn:asciiname":"Nating",
    "gn:country_code":"CN",
    "gn:dem":108,
    "gn:feature_class":"P",
    "gn:feature_code":"PPL",
    "gn:name":"Nating",
    "gn:population":0,
    "gn:timezone":"Asia/Urumqi",
    "iso:country":"CN",
    "name:und_x_variant":[
        "\u90a3\u505c"
    ],
    "name:zho_x_preferred":[
        "\u90a3\u505c"
    ],
    "wof:name":"Nating",
    "wof:placetype":"locality"
},
  "geometry": {"coordinates":[110.06417,20.5925],"type":"Point"}
}