{
  "type": "Feature",
  "properties": {
    "gn:admin1_code":"25",
    "gn:asciiname":"Dongyihe",
    "gn:country_code":"CN",
    "gn:dem":5,
    "gn:feature_class":"P",
    "gn:feature_code":"PPL",
    "gn:name":"Dongyihe",
    "gn:population":0,
    "gn:timezone":"Asia/Shanghai",
    "iso:country":"CN",
    "name:zho_x_preferred":[
        "\u4e1c\u4e49\u548c"
    ],
    "wof:name":"Dongyihe",
    "wof:placetype":"locality"
},
  "geometry": {"coordinates":[118.83499999999999,37.5619],"type":"Point"}
}