{
  "type": "Feature",
  "properties": {
    "gn:admin1_code":"12.0",
    "gn:asciiname":"Anzui",
    "gn:country_code":"CN",
    "gn:dem":29,
    "gn:feature_class":"P",
    "gn:feature_code":"PPL",
    "gn:name":"Anzui",
    "gn:population":0,
    "gn:timezone":"Asia/Shanghai",
    "iso:country":"CN",
    "name:zho_x_preferred":[
        "\u978d\u5480"
    ],
    "wof:name":"Anzui",
    "wof:placetype":"locality"
},
  "geometry": {"coordinates":[113.5547,29.69553],"type":"Point"}
}