{
  "type": "Feature",
  "properties": {
    "gn:admin1_code":"3.0",
    "gn:asciiname":"Huakengkou",
    "gn:country_code":"CN",
    "gn:dem":236,
    "gn:feature_class":"P",
    "gn:feature_code":"PPL",
    "gn:name":"Huakengkou",
    "gn:population":0,
    "gn:timezone":"Asia/Shanghai",
    "iso:country":"CN",
    "name:und_x_variant":[
        "\u6ed1\u5751\u53e3"
    ],
    "wof:name":"Huakengkou",
    "wof:placetype":"locality"
},
  "geometry": {"coordinates":[114.20321,29.04767],"type":"Point"}
}