{
  "type": "Feature",
  "properties": {
    "gn:admin1_code":"32.0",
    "gn:asciiname":"Walang",
    "gn:country_code":"CN",
    "gn:dem":2890,
    "gn:feature_class":"P",
    "gn:feature_code":"PPL",
    "gn:name":"Walang",
    "gn:population":0,
    "gn:timezone":"Asia/Shanghai",
    "iso:country":"CN",
    "name:zho_x_preferred":[
        "\u74e6\u90ce"
    ],
    "wof:name":"Walang",
    "wof:placetype":"locality"
},
  "geometry": {"coordinates":[100.922,28.6691],"type":"Point"}
}