{
  "type": "Feature",
  "properties": {
    "gn:admin1_code":"4.0",
    "gn:asciiname":"Zushimiao",
    "gn:country_code":"CN",
    "gn:dem":5,
    "gn:feature_class":"P",
    "gn:feature_code":"PPL",
    "gn:name":"Zushimiao",
    "gn:population":0,
    "gn:timezone":"Asia/Shanghai",
    "iso:country":"CN",
    "name:zho_x_preferred":[
        "\u7956\u5e08\u5e99"
    ],
    "wof:name":"Zushimiao",
    "wof:placetype":"locality"
},
  "geometry": {"coordinates":[120.44268999999998,32.47333],"type":"Point"}
}