{
  "type": "Feature",
  "properties": {
    "gn:admin1_code":"24.0",
    "gn:asciiname":"Zhangyanggoucun",
    "gn:country_code":"CN",
    "gn:dem":1168,
    "gn:feature_class":"P",
    "gn:feature_code":"PPL",
    "gn:name":"Zhangyanggoucun",
    "gn:population":0,
    "gn:timezone":"Asia/Shanghai",
    "iso:country":"CN",
    "name:zho_x_preferred":[
        "\u5f20\u9633\u6c9f\u6751"
    ],
    "wof:name":"Zhangyanggoucun",
    "wof:placetype":"locality"
},
  "geometry": {"coordinates":[110.79649999999999,38.10427],"type":"Point"}
}