{
  "type": "Feature",
  "properties": {
    "gn:admin1_code":"4.0",
    "gn:asciiname":"Jinjiaying",
    "gn:country_code":"CN",
    "gn:dem":22,
    "gn:feature_class":"P",
    "gn:feature_code":"PPL",
    "gn:name":"Jinjiaying",
    "gn:population":0,
    "gn:timezone":"Asia/Shanghai",
    "iso:country":"CN",
    "name:zho_x_preferred":[
        "\u91d1\u5bb6\u8425"
    ],
    "wof:name":"Jinjiaying",
    "wof:placetype":"locality"
},
  "geometry": {"coordinates":[119.18804,32.33819],"type":"Point"}
}