{
  "type": "Feature",
  "properties": {
    "gn:admin1_code":"16.0",
    "gn:asciiname":"Mipai",
    "gn:country_code":"CN",
    "gn:dem":33,
    "gn:feature_class":"P",
    "gn:feature_code":"PPL",
    "gn:name":"Mipai",
    "gn:population":0,
    "gn:timezone":"Asia/Shanghai",
    "iso:country":"CN",
    "name:zho_x_preferred":[
        "\u7c73\u6d3e"
    ],
    "wof:name":"Mipai",
    "wof:placetype":"locality"
},
  "geometry": {"coordinates":[108.22499999999999,21.6888],"type":"Point"}
}