{
  "type": "Feature",
  "properties": {
    "gn:admin1_code":"6.0",
    "gn:asciiname":"Bieri",
    "gn:country_code":"CN",
    "gn:dem":3770,
    "gn:feature_class":"P",
    "gn:feature_code":"PPL",
    "gn:name":"Bieri",
    "gn:population":0,
    "gn:timezone":"Asia/Urumqi",
    "iso:country":"CN",
    "name:zho_x_preferred":[
        "\u522b\u65e5"
    ],
    "wof:name":"Bieri",
    "wof:placetype":"locality"
},
  "geometry": {"coordinates":[97.24258,32.995],"type":"Point"}
}