{
  "type": "Feature",
  "properties": {
    "gn:admin1_code":"2",
    "gn:asciiname":"Zhanglong",
    "gn:country_code":"CN",
    "gn:dem":883,
    "gn:feature_class":"P",
    "gn:feature_code":"PPL",
    "gn:name":"Zhanglong",
    "gn:population":0,
    "gn:timezone":"Asia/Shanghai",
    "iso:country":"CN",
    "name:zho_x_preferred":[
        "\u5f20\u783b"
    ],
    "wof:name":"Zhanglong",
    "wof:placetype":"locality"
},
  "geometry": {"coordinates":[119.14833,27.87694],"type":"Point"}
}