{
  "type": "Feature",
  "properties": {
    "gn:admin1_code":"30",
    "gn:asciiname":"Lizhu",
    "gn:country_code":"CN",
    "gn:dem":12,
    "gn:feature_class":"P",
    "gn:feature_code":"PPL",
    "gn:name":"Lizhu",
    "gn:population":0,
    "gn:timezone":"Asia/Urumqi",
    "iso:country":"CN",
    "name:zho_x_preferred":[
        "\u529b\u7af9"
    ],
    "wof:name":"Lizhu",
    "wof:placetype":"locality"
},
  "geometry": {"coordinates":[110.53498999999999,21.26861],"type":"Point"}
}