{
  "type": "Feature",
  "properties": {
    "gn:admin1_code":"30.0",
    "gn:asciiname":"Zhangmu Touwei",
    "gn:country_code":"CN",
    "gn:dem":21,
    "gn:feature_class":"P",
    "gn:feature_code":"PPL",
    "gn:name":"Zhangmu Touwei",
    "gn:population":0,
    "gn:timezone":"Asia/Shanghai",
    "iso:country":"CN",
    "name:zho_x_preferred":[
        "\u6a1f\u6728\u5934\u56f4"
    ],
    "wof:name":"Zhangmu Touwei",
    "wof:placetype":"locality"
},
  "geometry": {"coordinates":[114.07498,22.89558],"type":"Point"}
}