{
  "type": "Feature",
  "properties": {
    "gn:admin1_code":"20.0",
    "gn:asciiname":"Qingshiya",
    "gn:country_code":"CN",
    "gn:dem":1706,
    "gn:feature_class":"P",
    "gn:feature_code":"PPL",
    "gn:name":"Qingshiya",
    "gn:population":0,
    "gn:timezone":"Asia/Shanghai",
    "iso:country":"CN",
    "name:und_x_variant":[
        "\u9752\u77f3\u5d16"
    ],
    "wof:name":"Qingshiya",
    "wof:placetype":"locality"
},
  "geometry": {"coordinates":[112.83308,41.35018],"type":"Point"}
}