{
  "type": "Feature",
  "properties": {
    "gn:admin1_code":"24.0",
    "gn:asciiname":"Sanyi",
    "gn:country_code":"CN",
    "gn:dem":1297,
    "gn:feature_class":"P",
    "gn:feature_code":"PPL",
    "gn:name":"Sanyi",
    "gn:population":0,
    "gn:timezone":"Asia/Shanghai",
    "iso:country":"CN",
    "name:zho_x_preferred":[
        "\u4e09\u4e49"
    ],
    "name:zho_x_variant":[
        "\u5357\u756a\u987a"
    ],
    "wof:name":"Sanyi",
    "wof:placetype":"locality"
},
  "geometry": {"coordinates":[112.25023,36.77999000000001],"type":"Point"}
}