{
  "type": "Feature",
  "properties": {
    "gn:admin1_code":"32.0",
    "gn:asciiname":"Dashuicun",
    "gn:country_code":"CN",
    "gn:dem":1768,
    "gn:feature_class":"P",
    "gn:feature_code":"PPL",
    "gn:name":"Dashuicun",
    "gn:population":0,
    "gn:timezone":"Asia/Shanghai",
    "iso:country":"CN",
    "name:zho_x_preferred":[
        "\u5927\u6c34\u6751"
    ],
    "wof:name":"Dashuicun",
    "wof:placetype":"locality"
},
  "geometry": {"coordinates":[102.04309000000001,28.09725],"type":"Point"}
}