{
  "type": "Feature",
  "properties": {
    "gn:admin1_code":"14.0",
    "gn:asciiname":"Dasakacun",
    "gn:country_code":"CN",
    "gn:dem":4288,
    "gn:feature_class":"P",
    "gn:feature_code":"PPL",
    "gn:name":"Dasakacun",
    "gn:population":0,
    "gn:timezone":"Asia/Urumqi",
    "iso:country":"CN",
    "name:zho_x_preferred":[
        "\u8fbe\u8428\u5494\u6751"
    ],
    "wof:name":"Dasakacun",
    "wof:placetype":"locality"
},
  "geometry": {"coordinates":[94.13011,31.81971],"type":"Point"}
}