{
  "type": "Feature",
  "properties": {
    "gn:admin1_code":"20.0",
    "gn:asciiname":"Yaleng Kemao",
    "gn:country_code":"CN",
    "gn:dem":353,
    "gn:feature_class":"P",
    "gn:feature_code":"PPL",
    "gn:name":"Yaleng Kemao",
    "gn:population":0,
    "gn:timezone":"Asia/Shanghai",
    "iso:country":"CN",
    "name:zho_x_preferred":[
        "\u4e9a\u51b7\u523b\u6bdb"
    ],
    "wof:name":"Yaleng Kemao",
    "wof:placetype":"locality"
},
  "geometry": {"coordinates":[123.74121,48.74592],"type":"Point"}
}