{
  "type": "Feature",
  "properties": {
    "gn:admin1_code":"21.0",
    "gn:asciiname":"Yaodujia",
    "gn:country_code":"CN",
    "gn:dem":1808,
    "gn:feature_class":"P",
    "gn:feature_code":"PPL",
    "gn:name":"Yaodujia",
    "gn:population":0,
    "gn:timezone":"Asia/Shanghai",
    "iso:country":"CN",
    "name:und_x_variant":[
        "\u59da\u675c\u5bb6"
    ],
    "name:zho_x_preferred":[
        "\u59da\u675c\u5bb6"
    ],
    "wof:name":"Yaodujia",
    "wof:placetype":"locality"
},
  "geometry": {"coordinates":[105.9117,35.70425],"type":"Point"}
}