{
  "type": "Feature",
  "properties": {
    "gn:admin1_code":"7.0",
    "gn:asciiname":"Fucun",
    "gn:country_code":"CN",
    "gn:dem":986,
    "gn:feature_class":"P",
    "gn:feature_code":"PPL",
    "gn:name":"Fucun",
    "gn:population":0,
    "gn:timezone":"Asia/Shanghai",
    "iso:country":"CN",
    "name:zho_x_preferred":[
        "\u5bcc\u6751"
    ],
    "wof:name":"Fucun",
    "wof:placetype":"locality"
},
  "geometry": {"coordinates":[119.12846,27.29685],"type":"Point"}
}