{
  "type": "Feature",
  "properties": {
    "gn:admin1_code":"22.0",
    "gn:asciiname":"Tujingcun",
    "gn:country_code":"CN",
    "gn:dem":48,
    "gn:feature_class":"P",
    "gn:feature_code":"PPL",
    "gn:name":"Tujingcun",
    "gn:population":0,
    "gn:timezone":"Asia/Shanghai",
    "iso:country":"CN",
    "name:zho_x_preferred":[
        "\u571f\u4e95\u6751"
    ],
    "wof:name":"Tujingcun",
    "wof:placetype":"locality"
},
  "geometry": {"coordinates":[116.26139999999999,40.05813],"type":"Point"}
}