{
  "type": "Feature",
  "properties": {
    "gn:admin1_code":"32.0",
    "gn:asciiname":"Xiongjiaqiao",
    "gn:country_code":"CN",
    "gn:dem":329,
    "gn:feature_class":"P",
    "gn:feature_code":"PPL",
    "gn:name":"Xiongjiaqiao",
    "gn:population":0,
    "gn:timezone":"Asia/Shanghai",
    "iso:country":"CN",
    "name:zho_x_preferred":[
        "\u718a\u5bb6\u6865"
    ],
    "wof:name":"Xiongjiaqiao",
    "wof:placetype":"locality"
},
  "geometry": {"coordinates":[103.95816000000001,29.18039000000001],"type":"Point"}
}