{
  "type": "Feature",
  "properties": {
    "gn:admin1_code":"1.0",
    "gn:asciiname":"Puhuangcun",
    "gn:country_code":"CN",
    "gn:dem":21,
    "gn:feature_class":"P",
    "gn:feature_code":"PPL",
    "gn:name":"Puhuangcun",
    "gn:population":0,
    "gn:timezone":"Asia/Shanghai",
    "iso:country":"CN",
    "name:zho_x_preferred":[
        "\u84b2\u9ec4\u6751"
    ],
    "wof:name":"Puhuangcun",
    "wof:placetype":"locality"
},
  "geometry": {"coordinates":[117.22735,32.80365],"type":"Point"}
}