{
  "type": "Feature",
  "properties": {
    "gn:admin1_code":"22.0",
    "gn:asciiname":"Beiniantoucun",
    "gn:country_code":"CN",
    "gn:dem":37,
    "gn:feature_class":"P",
    "gn:feature_code":"PPL",
    "gn:name":"Beiniantoucun",
    "gn:population":0,
    "gn:timezone":"Asia/Shanghai",
    "iso:country":"CN",
    "name:zho_x_preferred":[
        "\u5317\u57dd\u5934\u6751"
    ],
    "wof:name":"Beiniantoucun",
    "wof:placetype":"locality"
},
  "geometry": {"coordinates":[117.05025000000001,40.17081],"type":"Point"}
}