{
  "type": "Feature",
  "properties": {
    "gn:admin1_code":"7.0",
    "gn:asciiname":"Chenbucun",
    "gn:country_code":"CN",
    "gn:dem":148,
    "gn:feature_class":"P",
    "gn:feature_code":"PPL",
    "gn:name":"Chenbucun",
    "gn:population":0,
    "gn:timezone":"Asia/Shanghai",
    "iso:country":"CN",
    "name:zho_x_preferred":[
        "\u9648\u5e03\u6751"
    ],
    "wof:name":"Chenbucun",
    "wof:placetype":"locality"
},
  "geometry": {"coordinates":[117.75287,26.80269],"type":"Point"}
}