{
  "type": "Feature",
  "properties": {
    "gn:admin1_code":"2.0",
    "gn:asciiname":"Hongnan",
    "gn:country_code":"CN",
    "gn:dem":3,
    "gn:feature_class":"P",
    "gn:feature_code":"PPL",
    "gn:name":"Hongnan",
    "gn:population":0,
    "gn:timezone":"Asia/Shanghai",
    "iso:country":"CN",
    "name:zho_x_preferred":[
        "\u6cd3\u5357"
    ],
    "wof:name":"Hongnan",
    "wof:placetype":"locality"
},
  "geometry": {"coordinates":[121.64657,29.98929],"type":"Point"}
}