{
  "type": "Feature",
  "properties": {
    "gn:admin1_code":"33.0",
    "gn:asciiname":"Zhupodong",
    "gn:country_code":"CN",
    "gn:dem":412,
    "gn:feature_class":"P",
    "gn:feature_code":"PPL",
    "gn:name":"Zhupodong",
    "gn:population":0,
    "gn:timezone":"Asia/Shanghai",
    "iso:country":"CN",
    "name:zho_x_preferred":[
        "\u6731\u5a46\u6d1e"
    ],
    "wof:name":"Zhupodong",
    "wof:placetype":"locality"
},
  "geometry": {"coordinates":[107.30826,30.08162],"type":"Point"}
}