{
  "type": "Feature",
  "properties": {
    "gn:admin1_code":"2",
    "gn:asciiname":"Chimaoshe",
    "gn:country_code":"CN",
    "gn:dem":634,
    "gn:feature_class":"P",
    "gn:feature_code":"PPL",
    "gn:name":"Chimaoshe",
    "gn:population":0,
    "gn:timezone":"Asia/Shanghai",
    "iso:country":"CN",
    "name:zho_x_preferred":[
        "\u8d64\u6bdb\u7572"
    ],
    "wof:name":"Chimaoshe",
    "wof:placetype":"locality"
},
  "geometry": {"coordinates":[118.9375,27.69222],"type":"Point"}
}