{
  "type": "Feature",
  "properties": {
    "gn:admin1_code":"3.0",
    "gn:asciiname":"Changlun",
    "gn:country_code":"CN",
    "gn:dem":145,
    "gn:feature_class":"P",
    "gn:feature_code":"PPL",
    "gn:name":"Changlun",
    "gn:population":0,
    "gn:timezone":"Asia/Shanghai",
    "iso:country":"CN",
    "name:ind_x_preferred":[
        "Changlun"
    ],
    "name:msa_x_preferred":[
        "Changlun"
    ],
    "name:tha_x_preferred":[
        "\u0e0a\u0e31\u0e07\u0e25\u0e38\u0e19"
    ],
    "name:und_x_variant":[
        "\u957f\u4ed1"
    ],
    "name:wuu_x_preferred":[
        "\u8c61\u9686"
    ],
    "wof:name":"Changlun",
    "wof:placetype":"locality"
},
  "geometry": {"coordinates":[115.05395,29.20149],"type":"Point"}
}