{
  "type": "Feature",
  "properties": {
    "gn:admin1_code":"3.0",
    "gn:asciiname":"Changlun",
    "gn:country_code":"CN",
    "gn:dem":145,
    "gn:feature_class":"P",
    "gn:feature_code":"PPL",
    "gn:name":"Changlun",
    "gn:population":0,
    "gn:timezone":"Asia/Shanghai",
    "iso:country":"CN",
    "name:und_x_variant":[
        "\u957f\u4ed1"
    ],
    "wof:name":"Changlun",
    "wof:placetype":"locality"
},
  "geometry": {"coordinates":[115.05395,29.20149],"type":"Point"}
}