{
  "type": "Feature",
  "properties": {
    "gn:admin1_code":"32.0",
    "gn:asciiname":"Kangqiao",
    "gn:country_code":"CN",
    "gn:dem":444,
    "gn:feature_class":"P",
    "gn:feature_code":"PPL",
    "gn:name":"Kangqiao",
    "gn:population":0,
    "gn:timezone":"Asia/Shanghai",
    "iso:country":"CN",
    "name:zho_x_preferred":[
        "\u5eb7\u6865"
    ],
    "name:zho_x_variant":[
        "\u5eb7\u6865\u9547"
    ],
    "wof:name":"Kangqiao",
    "wof:placetype":"locality"
},
  "geometry": {"coordinates":[105.075,31.3498],"type":"Point"}
}