{
  "type": "Feature",
  "properties": {
    "gn:admin1_code":"29.0",
    "gn:asciiname":"Xiabinglong",
    "gn:country_code":"CN",
    "gn:dem":1610,
    "gn:feature_class":"P",
    "gn:feature_code":"PPL",
    "gn:name":"Xiabinglong",
    "gn:population":0,
    "gn:timezone":"Asia/Shanghai",
    "iso:country":"CN",
    "name:zho_x_preferred":[
        "\u4e0b\u4e19\u9f99"
    ],
    "wof:name":"Xiabinglong",
    "wof:placetype":"locality"
},
  "geometry": {"coordinates":[99.6619,25.0894],"type":"Point"}
}