{
  "type": "Feature",
  "properties": {
    "gn:admin1_code":"11.0",
    "gn:asciiname":"Dayu",
    "gn:country_code":"CN",
    "gn:dem":84,
    "gn:feature_class":"P",
    "gn:feature_code":"PPL",
    "gn:name":"Dayu",
    "gn:population":0,
    "gn:timezone":"Asia/Shanghai",
    "iso:country":"CN",
    "name:ceb_x_preferred":[
        "Dayu"
    ],
    "name:deu_x_preferred":[
        "Dayu"
    ],
    "name:ind_x_preferred":[
        "Dayu"
    ],
    "name:nld_x_preferred":[
        "Dayu"
    ],
    "name:swe_x_preferred":[
        "Dayu"
    ],
    "name:zho_x_preferred":[
        "\u5927\u9c7c"
    ],
    "wof:name":"Dayu",
    "wof:placetype":"locality"
},
  "geometry": {"coordinates":[113.27424000000001,28.32351],"type":"Point"}
}