{
  "type": "Feature",
  "properties": {
    "gn:admin1_code":"19.0",
    "gn:asciiname":"Jiajiajie",
    "gn:country_code":"CN",
    "gn:dem":337,
    "gn:feature_class":"P",
    "gn:feature_code":"PPL",
    "gn:name":"Jiajiajie",
    "gn:population":0,
    "gn:timezone":"Asia/Shanghai",
    "iso:country":"CN",
    "name:und_x_variant":[
        "\u8d3e\u5bb6\u8857"
    ],
    "wof:name":"Jiajiajie",
    "wof:placetype":"locality"
},
  "geometry": {"coordinates":[122.79192,40.36876],"type":"Point"}
}