{
  "type": "Feature",
  "properties": {
    "gn:admin1_code":"07",
    "gn:asciiname":"Zhuangduzi",
    "gn:country_code":"CN",
    "gn:dem":699,
    "gn:feature_class":"P",
    "gn:feature_code":"PPL",
    "gn:name":"Zhuangduzi",
    "gn:population":0,
    "gn:timezone":"Asia/Shanghai",
    "iso:country":"CN",
    "name:zho_x_preferred":[
        "\u58ee\u809a\u5b50"
    ],
    "wof:name":"Zhuangduzi",
    "wof:placetype":"locality"
},
  "geometry": {"coordinates":[116.24503,24.81463],"type":"Point"}
}