{
  "type": "Feature",
  "properties": {
    "gn:admin1_code":"16",
    "gn:asciiname":"Qidong",
    "gn:cc2":"CN",
    "gn:country_code":"CN",
    "gn:dem":235,
    "gn:feature_class":"P",
    "gn:feature_code":"PPL",
    "gn:name":"Qidong",
    "gn:population":0,
    "gn:timezone":"Asia/Shanghai",
    "iso:country":"CN",
    "name:ceb_x_preferred":[
        "Qidong"
    ],
    "name:deu_x_preferred":[
        "Qidong"
    ],
    "name:fra_x_preferred":[
        "Qidong"
    ],
    "name:nor_x_preferred":[
        "Qidong"
    ],
    "name:rus_x_preferred":[
        "\u0426\u0438\u0434\u0443\u043d"
    ],
    "name:swe_x_preferred":[
        "Qidong"
    ],
    "name:und_x_variant":[
        "Ch\u2019i-tung",
        "Qidong"
    ],
    "wof:name":"Qidong",
    "wof:placetype":"locality"
},
  "geometry": {"coordinates":[109.09999999999999,24.01667],"type":"Point"}
}