{
  "type": "Feature",
  "properties": {
    "gn:admin1_code":"32.0",
    "gn:asciiname":"Zhoutun",
    "gn:country_code":"CN",
    "gn:dem":1497,
    "gn:feature_class":"P",
    "gn:feature_code":"PPL",
    "gn:name":"Zhoutun",
    "gn:population":0,
    "gn:timezone":"Asia/Shanghai",
    "iso:country":"CN",
    "name:zho_x_preferred":[
        "\u5468\u5c6f"
    ],
    "wof:name":"Zhoutun",
    "wof:placetype":"locality"
},
  "geometry": {"coordinates":[102.20699999999999,27.7868],"type":"Point"}
}