{
  "type": "Feature",
  "properties": {
    "gn:admin1_code":"19.0",
    "gn:asciiname":"Balipucun",
    "gn:country_code":"CN",
    "gn:dem":74,
    "gn:feature_class":"P",
    "gn:feature_code":"PPL",
    "gn:name":"Balipucun",
    "gn:population":0,
    "gn:timezone":"Asia/Shanghai",
    "iso:country":"CN",
    "name:zho_x_preferred":[
        "\u516b\u91cc\u94fa\u6751"
    ],
    "wof:name":"Balipucun",
    "wof:placetype":"locality"
},
  "geometry": {"coordinates":[121.169,41.5504],"type":"Point"}
}