{
  "type": "Feature",
  "properties": {
    "gn:admin1_code":"19.0",
    "gn:asciiname":"Hounihezi",
    "gn:country_code":"CN",
    "gn:dem":80,
    "gn:feature_class":"P",
    "gn:feature_code":"PPL",
    "gn:name":"Hounihezi",
    "gn:population":0,
    "gn:timezone":"Asia/Shanghai",
    "iso:country":"CN",
    "name:und_x_variant":[
        "\u540e\u6ce5\u6cb3\u5b50"
    ],
    "name:zho_x_preferred":[
        "\u540e\u6ce5\u6cb3\u5b50"
    ],
    "wof:name":"Hounihezi",
    "wof:placetype":"locality"
},
  "geometry": {"coordinates":[121.22833,41.47823],"type":"Point"}
}