{
  "type": "Feature",
  "properties": {
    "gn:admin1_code":"08",
    "gn:asciiname":"Yung-fa-t'un",
    "gn:country_code":"CN",
    "gn:dem":291,
    "gn:feature_class":"P",
    "gn:feature_code":"PPL",
    "gn:name":"Yung-fa-t\u2019un",
    "gn:population":0,
    "gn:timezone":"Asia/Shanghai",
    "iso:country":"CN",
    "wof:name":"Yung-fa-t'un",
    "wof:placetype":"locality"
},
  "geometry": {"coordinates":[126.37724,48.3344],"type":"Point"}
}