{
  "type": "Feature",
  "properties": {
    "gn:admin1_code":"16",
    "gn:asciiname":"Tiantoushanchong",
    "gn:country_code":"CN",
    "gn:dem":465,
    "gn:feature_class":"P",
    "gn:feature_code":"PPL",
    "gn:name":"Tiantoushanchong",
    "gn:population":0,
    "gn:timezone":"Asia/Shanghai",
    "iso:country":"CN",
    "name:zho_x_preferred":[
        "\u7530\u5934\u5c71\u51b2"
    ],
    "wof:name":"Tiantoushanchong",
    "wof:placetype":"locality"
},
  "geometry": {"coordinates":[109.548,25.5421],"type":"Point"}
}