{
  "type": "Feature",
  "properties": {
    "gn:admin1_code":"11.0",
    "gn:asciiname":"Liulichong",
    "gn:country_code":"CN",
    "gn:dem":377,
    "gn:feature_class":"P",
    "gn:feature_code":"PPL",
    "gn:name":"Liulichong",
    "gn:population":0,
    "gn:timezone":"Asia/Shanghai",
    "iso:country":"CN",
    "name:zho_x_preferred":[
        "\u516d\u91cc\u51b2"
    ],
    "wof:name":"Liulichong",
    "wof:placetype":"locality"
},
  "geometry": {"coordinates":[110.00313,27.48842],"type":"Point"}
}