{
  "type": "Feature",
  "properties": {
    "gn:admin1_code":"8.0",
    "gn:asciiname":"Xiaolingtun",
    "gn:country_code":"CN",
    "gn:dem":253,
    "gn:feature_class":"P",
    "gn:feature_code":"PPL",
    "gn:name":"Xiaolingtun",
    "gn:population":0,
    "gn:timezone":"Asia/Shanghai",
    "iso:country":"CN",
    "name:zho_x_preferred":[
        "\u5c0f\u5cad\u5c6f"
    ],
    "wof:name":"Xiaolingtun",
    "wof:placetype":"locality"
},
  "geometry": {"coordinates":[127.35274,45.62599],"type":"Point"}
}