{
  "type": "Feature",
  "properties": {
    "gn:admin1_code":"31",
    "gn:asciiname":"Fumen",
    "gn:country_code":"CN",
    "gn:dem":216,
    "gn:feature_class":"P",
    "gn:feature_code":"PPL",
    "gn:name":"Fumen",
    "gn:population":0,
    "gn:timezone":"Asia/Shanghai",
    "iso:country":"CN",
    "name:und_x_variant":[
        "\u798f\u95e8",
        "Fuma"
    ],
    "wof:name":"Fumen",
    "wof:placetype":"locality"
},
  "geometry": {"coordinates":[109.542,19.2009],"type":"Point"}
}