{
  "type": "Feature",
  "properties": {
    "gn:admin1_code":"31.0",
    "gn:asciiname":"Shitong",
    "gn:country_code":"CN",
    "gn:dem":59,
    "gn:feature_class":"P",
    "gn:feature_code":"PPL",
    "gn:name":"Shitong",
    "gn:population":0,
    "gn:timezone":"Asia/Shanghai",
    "iso:country":"CN",
    "name:und_x_variant":[
        "\u77f3\u5cdd"
    ],
    "name:vie_x_preferred":[
        "S\u1eed th\u00f4ng"
    ],
    "wof:name":"Shitong",
    "wof:placetype":"locality"
},
  "geometry": {"coordinates":[109.7623,18.62774],"type":"Point"}
}