{
  "type": "Feature",
  "properties": {
    "gn:admin1_code":"32.0",
    "gn:asciiname":"Laba",
    "gn:country_code":"CN",
    "gn:dem":1536,
    "gn:feature_class":"P",
    "gn:feature_code":"PPL",
    "gn:name":"Laba",
    "gn:population":0,
    "gn:timezone":"Asia/Shanghai",
    "iso:country":"CN",
    "name:zho_x_preferred":[
        "\u62c9\u5df4"
    ],
    "wof:name":"Laba",
    "wof:placetype":"locality"
},
  "geometry": {"coordinates":[103.45099999999999,28.2429],"type":"Point"}
}