{
  "type": "Feature",
  "properties": {
    "gn:admin1_code":"26",
    "gn:asciiname":"Xiwanli",
    "gn:country_code":"CN",
    "gn:dem":1483,
    "gn:feature_class":"P",
    "gn:feature_code":"PPL",
    "gn:name":"Xiwanli",
    "gn:population":0,
    "gn:timezone":"Asia/Shanghai",
    "iso:country":"CN",
    "name:und_x_variant":[
        "\u897f\u6e7e\u91cc"
    ],
    "wof:name":"Xiwanli",
    "wof:placetype":"locality"
},
  "geometry": {"coordinates":[107.645,34.79139],"type":"Point"}
}