{
  "type": "Feature",
  "properties": {
    "gn:admin1_code":"18.0",
    "gn:asciiname":"Laoyazhai",
    "gn:country_code":"CN",
    "gn:dem":1007,
    "gn:feature_class":"P",
    "gn:feature_code":"PPL",
    "gn:name":"Laoyazhai",
    "gn:population":0,
    "gn:timezone":"Asia/Shanghai",
    "iso:country":"CN",
    "name:zho_x_preferred":[
        "\u8001\u9e26\u5be8"
    ],
    "wof:name":"Laoyazhai",
    "wof:placetype":"locality"
},
  "geometry": {"coordinates":[107.67700000000001,26.2813],"type":"Point"}
}