{
  "type": "Feature",
  "properties": {
    "gn:admin1_code":"9",
    "gn:asciiname":"Xizi'an",
    "gn:country_code":"CN",
    "gn:dem":54,
    "gn:feature_class":"P",
    "gn:feature_code":"PPL",
    "gn:name":"Xizi\u2019an",
    "gn:population":0,
    "gn:timezone":"Asia/Shanghai",
    "iso:country":"CN",
    "name:und_x_variant":[
        "Xizi\u2019an"
    ],
    "name:zho_x_preferred":[
        "\u897f\u5b50\u5cb8"
    ],
    "wof:name":"Xizi'an",
    "wof:placetype":"locality"
},
  "geometry": {"coordinates":[114.98,35.6117],"type":"Point"}
}