{
  "type": "Feature",
  "properties": {
    "gn:admin1_code":"18.0",
    "gn:asciiname":"Xiluo",
    "gn:country_code":"CN",
    "gn:dem":965,
    "gn:feature_class":"P",
    "gn:feature_code":"PPL",
    "gn:name":"Xiluo",
    "gn:population":0,
    "gn:timezone":"Asia/Shanghai",
    "iso:country":"CN",
    "name:hak_x_preferred":[
        "S\u00ee-l\u00f4-ts\u1e73\u0301n"
    ],
    "name:jpn_x_preferred":[
        "\u897f\u87ba\u93ae"
    ],
    "name:kor_x_preferred":[
        "\uc2dc\ub904\uc9c4"
    ],
    "name:vie_x_preferred":[
        "T\u00e2y Loa"
    ],
    "name:zho_x_preferred":[
        "\u897f\u87ba\u93ae"
    ],
    "wof:name":"Xiluo",
    "wof:placetype":"locality"
},
  "geometry": {"coordinates":[106.18056,27.49833],"type":"Point"}
}