{
  "type": "Feature",
  "properties": {
    "gn:admin1_code":"2.0",
    "gn:asciiname":"Xiachaxi",
    "gn:country_code":"CN",
    "gn:dem":932,
    "gn:feature_class":"P",
    "gn:feature_code":"PPL",
    "gn:name":"Xiachaxi",
    "gn:population":0,
    "gn:timezone":"Asia/Shanghai",
    "iso:country":"CN",
    "name:zho_x_preferred":[
        "\u4e0b\u5bdf\u6eaa"
    ],
    "wof:name":"Xiachaxi",
    "wof:placetype":"locality"
},
  "geometry": {"coordinates":[119.65356,27.74514000000001],"type":"Point"}
}