{
  "type": "Feature",
  "properties": {
    "gn:admin1_code":"8.0",
    "gn:asciiname":"Jingtaicun",
    "gn:country_code":"CN",
    "gn:dem":147,
    "gn:feature_class":"P",
    "gn:feature_code":"PPL",
    "gn:name":"Jingtaicun",
    "gn:population":0,
    "gn:timezone":"Asia/Shanghai",
    "iso:country":"CN",
    "name:zho_x_preferred":[
        "\u666f\u592a\u6751"
    ],
    "wof:name":"Jingtaicun",
    "wof:placetype":"locality"
},
  "geometry": {"coordinates":[130.22484,46.03093],"type":"Point"}
}