{
  "type": "Feature",
  "properties": {
    "gn:admin1_code":"8.0",
    "gn:asciiname":"Tongshancun",
    "gn:country_code":"CN",
    "gn:dem":220,
    "gn:feature_class":"P",
    "gn:feature_code":"PPL",
    "gn:name":"Tongshancun",
    "gn:population":0,
    "gn:timezone":"Asia/Shanghai",
    "iso:country":"CN",
    "name:zho_x_preferred":[
        "\u901a\u5c71\u6751"
    ],
    "wof:name":"Tongshancun",
    "wof:placetype":"locality"
},
  "geometry": {"coordinates":[125.07707000000001,48.1493],"type":"Point"}
}