{
  "type": "Feature",
  "properties": {
    "gn:admin1_code":"29.0",
    "gn:asciiname":"Jiucheng",
    "gn:country_code":"CN",
    "gn:dem":1676,
    "gn:feature_class":"P",
    "gn:feature_code":"PPL",
    "gn:name":"Jiucheng",
    "gn:population":0,
    "gn:timezone":"Asia/Shanghai",
    "iso:country":"CN",
    "name:zho_x_preferred":[
        "\u81fc\u57ce"
    ],
    "wof:name":"Jiucheng",
    "wof:placetype":"locality"
},
  "geometry": {"coordinates":[104.239,23.5457],"type":"Point"}
}