{
  "type": "Feature",
  "properties": {
    "gn:admin1_code":"9",
    "gn:asciiname":"Nanziyang",
    "gn:country_code":"CN",
    "gn:dem":47,
    "gn:feature_class":"P",
    "gn:feature_code":"PPL",
    "gn:name":"Nanziyang",
    "gn:population":0,
    "gn:timezone":"Asia/Shanghai",
    "iso:country":"CN",
    "name:zho_x_preferred":[
        "\u5357\u5b50\u9633"
    ],
    "wof:name":"Nanziyang",
    "wof:placetype":"locality"
},
  "geometry": {"coordinates":[115.3837,36.00364000000001],"type":"Point"}
}