{
  "type": "Feature",
  "properties": {
    "gn:admin1_code":"29.0",
    "gn:asciiname":"Fushan",
    "gn:country_code":"CN",
    "gn:dem":2468,
    "gn:feature_class":"P",
    "gn:feature_code":"PPL",
    "gn:name":"Fushan",
    "gn:population":0,
    "gn:timezone":"Asia/Shanghai",
    "iso:country":"CN",
    "name:ceb_x_preferred":[
        "Fushan"
    ],
    "name:deu_x_preferred":[
        "Fushan"
    ],
    "name:fra_x_preferred":[
        "Fushan"
    ],
    "name:nor_x_preferred":[
        "Fushan"
    ],
    "name:rus_x_preferred":[
        "\u0424\u0443\u0448\u0430\u043d\u044c"
    ],
    "name:swe_x_preferred":[
        "Fushan"
    ],
    "name:zho_x_preferred":[
        "\u798f\u6247"
    ],
    "wof:name":"Fushan",
    "wof:placetype":"locality"
},
  "geometry": {"coordinates":[99.977,26.4219],"type":"Point"}
}