{
  "type": "Feature",
  "properties": {
    "gn:admin1_code":"32.0",
    "gn:asciiname":"Zhangda",
    "gn:country_code":"CN",
    "gn:dem":3201,
    "gn:feature_class":"P",
    "gn:feature_code":"PPL",
    "gn:name":"Zhangda",
    "gn:population":0,
    "gn:timezone":"Asia/Shanghai",
    "iso:country":"CN",
    "name:zho_x_preferred":[
        "\u7ae0\u8fbe"
    ],
    "wof:name":"Zhangda",
    "wof:placetype":"locality"
},
  "geometry": {"coordinates":[100.74256,31.33035],"type":"Point"}
}