{
  "type": "Feature",
  "properties": {
    "gn:admin1_code":"9",
    "gn:asciiname":"Hezhuang",
    "gn:country_code":"CN",
    "gn:dem":35,
    "gn:feature_class":"P",
    "gn:feature_code":"PPL",
    "gn:name":"Hezhuang",
    "gn:population":0,
    "gn:timezone":"Asia/Shanghai",
    "iso:country":"CN",
    "name:ceb_x_preferred":[
        "Hezhuang"
    ],
    "name:swe_x_preferred":[
        "Hezhuang"
    ],
    "name:zho_x_preferred":[
        "\u8d3a\u5e84"
    ],
    "wof:name":"Hezhuang",
    "wof:placetype":"locality"
},
  "geometry": {"coordinates":[116.04600000000001,33.943],"type":"Point"}
}