{
  "type": "Feature",
  "properties": {
    "gn:admin1_code":"19.0",
    "gn:asciiname":"Lujiayingzi",
    "gn:country_code":"CN",
    "gn:dem":387,
    "gn:feature_class":"P",
    "gn:feature_code":"PPL",
    "gn:name":"L\u00fcjiayingzi",
    "gn:population":0,
    "gn:timezone":"Asia/Shanghai",
    "iso:country":"CN",
    "name:und_x_variant":[
        "L\u00fcjiayingzi"
    ],
    "name:zho_x_preferred":[
        "\u5415\u5bb6\u8425\u5b50"
    ],
    "wof:name":"Lujiayingzi",
    "wof:placetype":"locality"
},
  "geometry": {"coordinates":[120.462,41.8778],"type":"Point"}
}