{
  "type": "Feature",
  "properties": {
    "gn:admin1_code":"3.0",
    "gn:asciiname":"Shankou",
    "gn:country_code":"CN",
    "gn:dem":90,
    "gn:feature_class":"P",
    "gn:feature_code":"PPL",
    "gn:name":"Shankou",
    "gn:population":0,
    "gn:timezone":"Asia/Shanghai",
    "iso:country":"CN",
    "name:deu_x_preferred":[
        "Shankou"
    ],
    "name:und_x_variant":[
        "\u5c71\u53e3"
    ],
    "wof:name":"Shankou",
    "wof:placetype":"locality"
},
  "geometry": {"coordinates":[115.10138000000001,29.31836],"type":"Point"}
}