{
  "type": "Feature",
  "properties": {
    "gn:admin1_code":"32.0",
    "gn:asciiname":"Chengfeng",
    "gn:country_code":"CN",
    "gn:dem":290,
    "gn:feature_class":"P",
    "gn:feature_code":"PPL",
    "gn:name":"Chengfeng",
    "gn:population":0,
    "gn:timezone":"Asia/Shanghai",
    "iso:country":"CN",
    "name:zho_x_preferred":[
        "\u6210\u51e4"
    ],
    "wof:name":"Chengfeng",
    "wof:placetype":"locality"
},
  "geometry": {"coordinates":[105.666,29.9154],"type":"Point"}
}