{
  "type": "Feature",
  "properties": {
    "gn:admin1_code":"05",
    "gn:asciiname":"Linshengcun",
    "gn:country_code":"CN",
    "gn:dem":424,
    "gn:feature_class":"P",
    "gn:feature_code":"PPL",
    "gn:name":"Linshengcun",
    "gn:population":0,
    "gn:timezone":"Asia/Shanghai",
    "iso:country":"CN",
    "name:und_x_variant":[
        "Linsheng"
    ],
    "name:zho_x_preferred":[
        "\u6797\u80dc\u6751"
    ],
    "wof:name":"Linshengcun",
    "wof:placetype":"locality"
},
  "geometry": {"coordinates":[128.48979,43.6066],"type":"Point"}
}