{
  "type": "Feature",
  "properties": {
    "gn:admin1_code":"8.0",
    "gn:asciiname":"Xiuhecun",
    "gn:country_code":"CN",
    "gn:dem":315,
    "gn:feature_class":"P",
    "gn:feature_code":"PPL",
    "gn:name":"Xiuhecun",
    "gn:population":0,
    "gn:timezone":"Asia/Shanghai",
    "iso:country":"CN",
    "name:zho_x_preferred":[
        "\u9508\u6cb3\u6751"
    ],
    "wof:name":"Xiuhecun",
    "wof:placetype":"locality"
},
  "geometry": {"coordinates":[127.47471000000002,49.08135],"type":"Point"}
}