{
  "type": "Feature",
  "properties": {
    "gn:admin1_code":"32.0",
    "gn:asciiname":"Taihe",
    "gn:country_code":"CN",
    "gn:dem":497,
    "gn:feature_class":"P",
    "gn:feature_code":"PPL",
    "gn:name":"Taihe",
    "gn:population":0,
    "gn:timezone":"Asia/Shanghai",
    "iso:country":"CN",
    "name:ceb_x_preferred":[
        "Taihe"
    ],
    "name:deu_x_preferred":[
        "Taihe"
    ],
    "name:eus_x_preferred":[
        "Taihe konderria"
    ],
    "name:fra_x_preferred":[
        "Taihe"
    ],
    "name:kor_x_preferred":[
        "\ud0c0\uc774\ud5c8"
    ],
    "name:nor_x_preferred":[
        "Taihe"
    ],
    "name:rus_x_preferred":[
        "\u0422\u0430\u0439\u0445\u044d"
    ],
    "name:swe_x_preferred":[
        "Taihe"
    ],
    "name:zho_x_preferred":[
        "\u592a\u548c"
    ],
    "wof:name":"Taihe",
    "wof:placetype":"locality"
},
  "geometry": {"coordinates":[104.416,29.5543],"type":"Point"}
}