{
  "type": "Feature",
  "properties": {
    "gn:admin1_code":"19.0",
    "gn:asciiname":"Guomuyuancun",
    "gn:country_code":"CN",
    "gn:dem":26,
    "gn:feature_class":"P",
    "gn:feature_code":"PPL",
    "gn:name":"Guomuyuancun",
    "gn:population":0,
    "gn:timezone":"Asia/Shanghai",
    "iso:country":"CN",
    "name:zho_x_preferred":[
        "\u679c\u6728\u56ed\u6751"
    ],
    "wof:name":"Guomuyuancun",
    "wof:placetype":"locality"
},
  "geometry": {"coordinates":[122.28637999999999,39.48609],"type":"Point"}
}