{
  "type": "Feature",
  "properties": {
    "gn:admin1_code":"21.0",
    "gn:asciiname":"Duantugou",
    "gn:country_code":"CN",
    "gn:dem":1602,
    "gn:feature_class":"P",
    "gn:feature_code":"PPL",
    "gn:name":"Duantugou",
    "gn:population":0,
    "gn:timezone":"Asia/Shanghai",
    "iso:country":"CN",
    "name:zho_x_preferred":[
        "\u65ad\u5154\u6c9f"
    ],
    "wof:name":"Duantugou",
    "wof:placetype":"locality"
},
  "geometry": {"coordinates":[107.012,37.3586],"type":"Point"}
}