{
  "type": "Feature",
  "properties": {
    "gn:admin1_code":"25",
    "gn:asciiname":"Tingshui Dongcun",
    "gn:country_code":"CN",
    "gn:dem":110,
    "gn:feature_class":"P",
    "gn:feature_code":"PPL",
    "gn:name":"Tingshui Dongcun",
    "gn:population":0,
    "gn:timezone":"Asia/Shanghai",
    "iso:country":"CN",
    "name:zho_x_preferred":[
        "\u6c40\u6c34\u4e1c\u6751"
    ],
    "wof:name":"Tingshui Dongcun",
    "wof:placetype":"locality"
},
  "geometry": {"coordinates":[118.60899999999999,35.3808],"type":"Point"}
}