{
  "type": "Feature",
  "properties": {
    "gn:admin1_code":"3.0",
    "gn:asciiname":"Huoxing",
    "gn:country_code":"CN",
    "gn:dem":210,
    "gn:feature_class":"P",
    "gn:feature_code":"PPL",
    "gn:name":"Huoxing",
    "gn:population":0,
    "gn:timezone":"Asia/Shanghai",
    "iso:country":"CN",
    "name:und_x_variant":[
        "\u706b\u661f"
    ],
    "wof:name":"Huoxing",
    "wof:placetype":"locality"
},
  "geometry": {"coordinates":[115.78521000000001,25.81181],"type":"Point"}
}