{
  "type": "Feature",
  "properties": {
    "gn:admin1_code":"32.0",
    "gn:asciiname":"Dafang",
    "gn:country_code":"CN",
    "gn:dem":926,
    "gn:feature_class":"P",
    "gn:feature_code":"PPL",
    "gn:name":"Dafang",
    "gn:population":0,
    "gn:timezone":"Asia/Shanghai",
    "iso:country":"CN",
    "name:zho_x_preferred":[
        "\u5927\u623f"
    ],
    "wof:name":"Dafang",
    "wof:placetype":"locality"
},
  "geometry": {"coordinates":[105.066,32.3464],"type":"Point"}
}