{
  "type": "Feature",
  "properties": {
    "gn:admin1_code":"1.0",
    "gn:asciiname":"Yuba",
    "gn:country_code":"CN",
    "gn:dem":24,
    "gn:feature_class":"P",
    "gn:feature_code":"PPL",
    "gn:name":"Yuba",
    "gn:population":0,
    "gn:timezone":"Asia/Shanghai",
    "iso:country":"CN",
    "name:ara_x_preferred":[
        "\u064a\u0648\u0628\u0627"
    ],
    "name:bel_x_preferred":[
        "\u042e\u0431\u0430"
    ],
    "name:deu_x_preferred":[
        "Yuba"
    ],
    "name:fra_x_preferred":[
        "Yuba"
    ],
    "name:ita_x_preferred":[
        "Yuba"
    ],
    "name:nld_x_preferred":[
        "Yuba"
    ],
    "name:pol_x_preferred":[
        "Yuba"
    ],
    "name:por_x_preferred":[
        "Yuba"
    ],
    "name:rus_x_preferred":[
        "\u042e\u0431\u0430"
    ],
    "name:spa_x_preferred":[
        "Yuba"
    ],
    "name:ukr_x_preferred":[
        "\u042e\u0431\u0430"
    ],
    "name:zho_x_preferred":[
        "\u4fde\u575d"
    ],
    "wof:name":"Yuba",
    "wof:placetype":"locality"
},
  "geometry": {"coordinates":[118.07635999999999,31.75655],"type":"Point"}
}