{
  "type": "Feature",
  "properties": {
    "gn:admin1_code":"02",
    "gn:asciiname":"Fanzhoucun",
    "gn:country_code":"CN",
    "gn:dem":6,
    "gn:feature_class":"P",
    "gn:feature_code":"PPL",
    "gn:name":"Fanzhoucun",
    "gn:population":0,
    "gn:timezone":"Asia/Shanghai",
    "iso:country":"CN",
    "name:und_x_variant":[
        "Fanzhou",
        "\u7548\u5468",
        "Fan-chou-ts\u2019un",
        "Fanzhoucun"
    ],
    "name:zho_x_preferred":[
        "\u7548\u5468\u6751"
    ],
    "wof:name":"Fanzhoucun",
    "wof:placetype":"locality"
},
  "geometry": {"coordinates":[121.12188999999999,30.07428],"type":"Point"}
}