{
  "type": "Feature",
  "properties": {
    "gn:admin1_code":"4.0",
    "gn:asciiname":"Zhangdongcun",
    "gn:country_code":"CN",
    "gn:dem":3,
    "gn:feature_class":"P",
    "gn:feature_code":"PPL",
    "gn:name":"Zhangdongcun",
    "gn:population":0,
    "gn:timezone":"Asia/Shanghai",
    "iso:country":"CN",
    "name:zho_x_preferred":[
        "\u5f20\u4e1c\u6751"
    ],
    "wof:name":"Zhangdongcun",
    "wof:placetype":"locality"
},
  "geometry": {"coordinates":[119.881,32.92],"type":"Point"}
}