{
  "type": "Feature",
  "properties": {
    "gn:admin1_code":"29.0",
    "gn:asciiname":"Mengpengqing",
    "gn:country_code":"CN",
    "gn:dem":1241,
    "gn:feature_class":"P",
    "gn:feature_code":"PPL",
    "gn:name":"Mengpengqing",
    "gn:population":0,
    "gn:timezone":"Asia/Shanghai",
    "iso:country":"CN",
    "name:zho_x_preferred":[
        "\u731b\u68da\u7b90"
    ],
    "wof:name":"Mengpengqing",
    "wof:placetype":"locality"
},
  "geometry": {"coordinates":[100.685,22.7533],"type":"Point"}
}