{
  "type": "Feature",
  "properties": {
    "gn:admin1_code":"16.0",
    "gn:asciiname":"Buzhai",
    "gn:country_code":"CN",
    "gn:dem":122,
    "gn:feature_class":"P",
    "gn:feature_code":"PPL",
    "gn:name":"Buzhai",
    "gn:population":0,
    "gn:timezone":"Asia/Shanghai",
    "iso:country":"CN",
    "name:zho_x_preferred":[
        "\u535c\u5be8"
    ],
    "wof:name":"Buzhai",
    "wof:placetype":"locality"
},
  "geometry": {"coordinates":[107.595,22.7506],"type":"Point"}
}