{
  "type": "Feature",
  "properties": {
    "gn:admin1_code":"30.0",
    "gn:asciiname":"Wangtang",
    "gn:country_code":"CN",
    "gn:dem":466,
    "gn:feature_class":"P",
    "gn:feature_code":"PPL",
    "gn:name":"Wangtang",
    "gn:population":0,
    "gn:timezone":"Asia/Shanghai",
    "iso:country":"CN",
    "name:und_x_variant":[
        "\u65fa\u5858"
    ],
    "name:zho_x_preferred":[
        "\u65fa\u5858"
    ],
    "wof:name":"Wangtang",
    "wof:placetype":"locality"
},
  "geometry": {"coordinates":[115.30343999999999,23.96215],"type":"Point"}
}