{
  "type": "Feature",
  "properties": {
    "gn:admin1_code":"5.0",
    "gn:asciiname":"Changjiatun",
    "gn:country_code":"CN",
    "gn:dem":327,
    "gn:feature_class":"P",
    "gn:feature_code":"PPL",
    "gn:name":"Changjiatun",
    "gn:population":0,
    "gn:timezone":"Asia/Shanghai",
    "iso:country":"CN",
    "name:zho_x_preferred":[
        "\u5e38\u5bb6\u5c6f"
    ],
    "wof:name":"Changjiatun",
    "wof:placetype":"locality"
},
  "geometry": {"coordinates":[126.04514,42.98378],"type":"Point"}
}