{
  "type": "Feature",
  "properties": {
    "gn:admin1_code":"30",
    "gn:asciiname":"Jianghai",
    "gn:country_code":"CN",
    "gn:dem":5,
    "gn:feature_class":"P",
    "gn:feature_code":"PPLA3",
    "gn:name":"Jianghai",
    "gn:population":0,
    "gn:timezone":"Asia/Shanghai",
    "iso:country":"CN",
    "name:deu_x_preferred":[
        "Jianghai"
    ],
    "name:fas_x_preferred":[
        "\u0698\u06cc\u0627\u0646\u06af\u0647\u0627\u06cc"
    ],
    "name:hak_x_preferred":[
        "K\u00f4ng-h\u00f3i-kh\u00ee"
    ],
    "name:jpn_x_preferred":[
        "\u6c5f\u6d77\u533a"
    ],
    "name:kor_x_preferred":[
        "\uc7a5\ud558\uc774\uad6c"
    ],
    "name:mwl_x_preferred":[
        "Jianghai"
    ],
    "name:nor_x_preferred":[
        "Jianghai"
    ],
    "name:swe_x_preferred":[
        "Jianghai"
    ],
    "name:und_x_variant":[
        "Jianghai Qu"
    ],
    "name:vie_x_preferred":[
        "Giang H\u1ea3i"
    ],
    "name:zho_x_preferred":[
        "\u6c5f\u6d77"
    ],
    "name:zho_x_variant":[
        "\u6c5f\u6d77\u533a"
    ],
    "wof:name":"Jianghai",
    "wof:placetype":"locality"
},
  "geometry": {"coordinates":[113.11903999999998,22.57518],"type":"Point"}
}