{
  "type": "Feature",
  "properties": {
    "gn:admin1_code":"5.0",
    "gn:asciiname":"Xiaoxigou",
    "gn:country_code":"CN",
    "gn:dem":602,
    "gn:feature_class":"P",
    "gn:feature_code":"PPL",
    "gn:name":"Xiaoxigou",
    "gn:population":0,
    "gn:timezone":"Asia/Shanghai",
    "iso:country":"CN",
    "name:und_x_variant":[
        "\u5c0f\u897f\u6c9f"
    ],
    "wof:name":"Xiaoxigou",
    "wof:placetype":"locality"
},
  "geometry": {"coordinates":[126.89539000000001,42.30233],"type":"Point"}
}