{
  "type": "Feature",
  "properties": {
    "gn:admin1_code":"14.0",
    "gn:asciiname":"Larong",
    "gn:country_code":"CN",
    "gn:dem":3348,
    "gn:feature_class":"P",
    "gn:feature_code":"PPL",
    "gn:name":"Larong",
    "gn:population":0,
    "gn:timezone":"Asia/Urumqi",
    "iso:country":"CN",
    "name:zho_x_preferred":[
        "\u62c9\u8363"
    ],
    "wof:name":"Larong",
    "wof:placetype":"locality"
},
  "geometry": {"coordinates":[98.75716,29.77914],"type":"Point"}
}