{
  "type": "Feature",
  "properties": {
    "gn:admin1_code":"14",
    "gn:asciiname":"Nganggar",
    "gn:country_code":"CN",
    "gn:dem":4075,
    "gn:feature_class":"P",
    "gn:feature_code":"PPL",
    "gn:name":"Nganggar",
    "gn:population":0,
    "gn:timezone":"Asia/Urumqi",
    "iso:country":"CN",
    "name:bod_x_preferred":[
        "\u0f44\u0f44\u0f0b\u0f51\u0f40\u0f62"
    ],
    "wof:name":"Nganggar",
    "wof:placetype":"locality"
},
  "geometry": {"coordinates":[90.66759,29.98802],"type":"Point"}
}