{
  "type": "Feature",
  "properties": {
    "gn:admin1_code":"15.0",
    "gn:asciiname":"Heshangwan",
    "gn:country_code":"CN",
    "gn:dem":2039,
    "gn:feature_class":"P",
    "gn:feature_code":"PPL",
    "gn:name":"Heshangwan",
    "gn:population":0,
    "gn:timezone":"Asia/Shanghai",
    "iso:country":"CN",
    "name:und_x_variant":[
        "\u548c\u5c1a\u6e7e"
    ],
    "wof:name":"Heshangwan",
    "wof:placetype":"locality"
},
  "geometry": {"coordinates":[105.25421,35.37121],"type":"Point"}
}