{
  "type": "Feature",
  "properties": {
    "gn:admin1_code":"26.0",
    "gn:asciiname":"Dishuiya Goukou",
    "gn:country_code":"CN",
    "gn:dem":1411,
    "gn:feature_class":"P",
    "gn:feature_code":"PPL",
    "gn:name":"Dishuiya Goukou",
    "gn:population":0,
    "gn:timezone":"Asia/Shanghai",
    "iso:country":"CN",
    "name:zho_x_preferred":[
        "\u6ef4\u6c34\u5d16\u6c9f\u53e3"
    ],
    "wof:name":"Dishuiya Goukou",
    "wof:placetype":"locality"
},
  "geometry": {"coordinates":[109.11524,33.82032],"type":"Point"}
}