{
  "type": "Feature",
  "properties": {
    "gn:admin1_code":"11.0",
    "gn:asciiname":"Diemaqiao",
    "gn:country_code":"CN",
    "gn:dem":84,
    "gn:feature_class":"P",
    "gn:feature_code":"PPL",
    "gn:name":"Diemaqiao",
    "gn:population":0,
    "gn:timezone":"Asia/Shanghai",
    "iso:country":"CN",
    "name:zho_x_preferred":[
        "\u8dcc\u9a6c\u6865"
    ],
    "wof:name":"Diemaqiao",
    "wof:placetype":"locality"
},
  "geometry": {"coordinates":[111.84168,28.55498],"type":"Point"}
}