{
  "type": "Feature",
  "properties": {
    "gn:admin1_code":"2.0",
    "gn:asciiname":"Shangqian",
    "gn:country_code":"CN",
    "gn:dem":73,
    "gn:feature_class":"P",
    "gn:feature_code":"PPL",
    "gn:name":"Shangqian",
    "gn:population":0,
    "gn:timezone":"Asia/Shanghai",
    "iso:country":"CN",
    "name:und_x_variant":[
        "\u4e0a\u94b1"
    ],
    "name:zho_x_preferred":[
        "Shangqian"
    ],
    "wof:name":"Shangqian",
    "wof:placetype":"locality"
},
  "geometry": {"coordinates":[119.72601,30.10997],"type":"Point"}
}