{
  "type": "Feature",
  "properties": {
    "gn:admin1_code":"32.0",
    "gn:asciiname":"Jiejie",
    "gn:country_code":"CN",
    "gn:dem":2217,
    "gn:feature_class":"P",
    "gn:feature_code":"PPL",
    "gn:name":"Jiejie",
    "gn:population":0,
    "gn:timezone":"Asia/Shanghai",
    "iso:country":"CN",
    "name:zho_x_preferred":[
        "\u8857\u8857"
    ],
    "wof:name":"Jiejie",
    "wof:placetype":"locality"
},
  "geometry": {"coordinates":[102.09739999999999,28.77352],"type":"Point"}
}