{
  "type": "Feature",
  "properties": {
    "gn:admin1_code":"19.0",
    "gn:asciiname":"Shibadian",
    "gn:country_code":"CN",
    "gn:dem":11,
    "gn:feature_class":"P",
    "gn:feature_code":"PPL",
    "gn:name":"Shibadian",
    "gn:population":0,
    "gn:timezone":"Asia/Shanghai",
    "iso:country":"CN",
    "name:zho_x_preferred":[
        "\u5341\u516b\u70b9"
    ],
    "wof:name":"Shibadian",
    "wof:placetype":"locality"
},
  "geometry": {"coordinates":[123.09399999999999,39.6947],"type":"Point"}
}