{
  "type": "Feature",
  "properties": {
    "gn:admin1_code":"9.0",
    "gn:asciiname":"Wodanchen",
    "gn:country_code":"CN",
    "gn:dem":56,
    "gn:feature_class":"P",
    "gn:feature_code":"PPL",
    "gn:name":"Wodanchen",
    "gn:population":0,
    "gn:timezone":"Asia/Shanghai",
    "iso:country":"CN",
    "name:zho_x_preferred":[
        "\u5367\u4e39\u9648"
    ],
    "wof:name":"Wodanchen",
    "wof:placetype":"locality"
},
  "geometry": {"coordinates":[114.74462,33.88372],"type":"Point"}
}