{
  "type": "Feature",
  "properties": {
    "gn:admin1_code":"3",
    "gn:asciiname":"Liancheng",
    "gn:country_code":"CN",
    "gn:dem":49,
    "gn:feature_class":"P",
    "gn:feature_code":"PPLA4",
    "gn:name":"Liancheng",
    "gn:population":0,
    "gn:timezone":"Asia/Shanghai",
    "iso:country":"CN",
    "name:ceb_x_preferred":[
        "Liancheng"
    ],
    "name:deu_x_preferred":[
        "Liancheng"
    ],
    "name:und_x_variant":[
        "\u8fde\u57ce",
        "Liancheng Xiang",
        "\u8fde\u57ce\u4e61"
    ],
    "wof:name":"Liancheng",
    "wof:placetype":"locality"
},
  "geometry": {"coordinates":[116.30714999999999,27.89256],"type":"Point"}
}