{
  "type": "Feature",
  "properties": {
    "gn:admin1_code":"12",
    "gn:asciiname":"Longzhong",
    "gn:country_code":"CN",
    "gn:dem":71,
    "gn:feature_class":"P",
    "gn:feature_code":"PPLA4",
    "gn:name":"Longzhong",
    "gn:population":0,
    "gn:timezone":"Asia/Shanghai",
    "iso:country":"CN",
    "name:nor_x_preferred":[
        "Longzhong"
    ],
    "name:ukr_x_preferred":[
        "\u041b\u0443\u043d\u0447\u0436\u0443\u043d"
    ],
    "name:und_x_variant":[
        "Lung-chung",
        "Longzhong Jiedao"
    ],
    "name:zho_x_preferred":[
        "\u9686\u4e2d"
    ],
    "name:zho_x_variant":[
        "\u9686\u4e2d\u8857\u9053"
    ],
    "wof:name":"Longzhong",
    "wof:placetype":"locality"
},
  "geometry": {"coordinates":[112.08141999999999,32.01036],"type":"Point"}
}