{
  "type": "Feature",
  "properties": {
    "gn:admin1_code":"11.0",
    "gn:asciiname":"Yijiangxu",
    "gn:cc2":"CN",
    "gn:country_code":"CN",
    "gn:dem":364,
    "gn:feature_class":"P",
    "gn:feature_code":"PPL",
    "gn:name":"Yijiangxu",
    "gn:population":0,
    "gn:timezone":"Asia/Shanghai",
    "iso:country":"CN",
    "name:und_x_variant":[
        "Yijiang",
        "Yijiangxu"
    ],
    "wof:name":"Yijiangxu",
    "wof:placetype":"locality"
},
  "geometry": {"coordinates":[113.86583,25.56972],"type":"Point"}
}