{
  "type": "Feature",
  "properties": {
    "gn:admin1_code":"9.0",
    "gn:asciiname":"Xizhangzhai",
    "gn:country_code":"CN",
    "gn:dem":78,
    "gn:feature_class":"P",
    "gn:feature_code":"PPL",
    "gn:name":"Xizhangzhai",
    "gn:population":0,
    "gn:timezone":"Asia/Shanghai",
    "iso:country":"CN",
    "name:zho_x_preferred":[
        "\u897f\u5f20\u5be8"
    ],
    "wof:name":"Xizhangzhai",
    "wof:placetype":"locality"
},
  "geometry": {"coordinates":[114.83727,32.0155],"type":"Point"}
}