{
  "type": "Feature",
  "properties": {
    "gn:admin1_code":"18",
    "gn:asciiname":"Qilihe",
    "gn:country_code":"CN",
    "gn:dem":2290,
    "gn:feature_class":"P",
    "gn:feature_code":"PPL",
    "gn:name":"Qilihe",
    "gn:population":0,
    "gn:timezone":"Asia/Shanghai",
    "iso:country":"CN",
    "name:zho_x_preferred":[
        "\u4e03\u91cc\u6cb3"
    ],
    "wof:name":"Qilihe",
    "wof:placetype":"locality"
},
  "geometry": {"coordinates":[104.13200000000001,26.9918],"type":"Point"}
}