{
  "type": "Feature",
  "properties": {
    "gn:admin1_code":"25",
    "gn:asciiname":"Zhongpu",
    "gn:country_code":"CN",
    "gn:dem":41,
    "gn:feature_class":"P",
    "gn:feature_code":"PPL",
    "gn:name":"Zhongpu",
    "gn:population":0,
    "gn:timezone":"Asia/Shanghai",
    "iso:country":"CN",
    "name:zho_x_preferred":[
        "\u4e2d\u94fa"
    ],
    "wof:name":"Zhongpu",
    "wof:placetype":"locality"
},
  "geometry": {"coordinates":[116.086,36.1195],"type":"Point"}
}