{
  "type": "Feature",
  "properties": {
    "gn:admin1_code":"18",
    "gn:asciiname":"Dongshang",
    "gn:country_code":"CN",
    "gn:dem":978,
    "gn:feature_class":"P",
    "gn:feature_code":"PPL",
    "gn:name":"Dongshang",
    "gn:population":0,
    "gn:timezone":"Asia/Shanghai",
    "iso:country":"CN",
    "name:zho_x_preferred":[
        "\u7850\u4e0a"
    ],
    "wof:name":"Dongshang",
    "wof:placetype":"locality"
},
  "geometry": {"coordinates":[106.254,28.0491],"type":"Point"}
}