{
  "type": "Feature",
  "properties": {
    "gn:admin1_code":"3.0",
    "gn:asciiname":"Naitou",
    "gn:country_code":"CN",
    "gn:dem":276,
    "gn:feature_class":"P",
    "gn:feature_code":"PPL",
    "gn:name":"Naitou",
    "gn:population":0,
    "gn:timezone":"Asia/Shanghai",
    "iso:country":"CN",
    "name:und_x_variant":[
        "\u4e43\u5934"
    ],
    "wof:name":"Naitou",
    "wof:placetype":"locality"
},
  "geometry": {"coordinates":[115.92898,26.84228],"type":"Point"}
}