{
  "type": "Feature",
  "properties": {
    "gn:admin1_code":"1.0",
    "gn:asciiname":"Chenluzhuangcun",
    "gn:country_code":"CN",
    "gn:dem":30,
    "gn:feature_class":"P",
    "gn:feature_code":"PPL",
    "gn:name":"Chenluzhuangcun",
    "gn:population":0,
    "gn:timezone":"Asia/Shanghai",
    "iso:country":"CN",
    "name:zho_x_preferred":[
        "\u9648\u7089\u5e84\u6751"
    ],
    "wof:name":"Chenluzhuangcun",
    "wof:placetype":"locality"
},
  "geometry": {"coordinates":[116.17418000000001,32.8625],"type":"Point"}
}