{
  "type": "Feature",
  "properties": {
    "gn:admin1_code":"18",
    "gn:asciiname":"Digu",
    "gn:country_code":"CN",
    "gn:dem":1584,
    "gn:feature_class":"P",
    "gn:feature_code":"PPL",
    "gn:name":"Digu",
    "gn:population":0,
    "gn:timezone":"Asia/Shanghai",
    "iso:country":"CN",
    "name:zho_x_preferred":[
        "\u4f4e\u53e4"
    ],
    "wof:name":"Digu",
    "wof:placetype":"locality"
},
  "geometry": {"coordinates":[105.116,25.3027],"type":"Point"}
}