{
  "type": "Feature",
  "properties": {
    "gn:admin1_code":"20.0",
    "gn:asciiname":"Xingsheng",
    "gn:country_code":"CN",
    "gn:dem":280,
    "gn:feature_class":"P",
    "gn:feature_code":"PPL",
    "gn:name":"Xingsheng",
    "gn:population":0,
    "gn:timezone":"Asia/Shanghai",
    "iso:country":"CN",
    "name:zho_x_preferred":[
        "\u5174\u80dc"
    ],
    "wof:name":"Xingsheng",
    "wof:placetype":"locality"
},
  "geometry": {"coordinates":[123.60767,48.49884],"type":"Point"}
}