{
  "type": "Feature",
  "properties": {
    "gn:admin1_code":"4.0",
    "gn:asciiname":"Xinqiao",
    "gn:country_code":"CN",
    "gn:dem":2,
    "gn:feature_class":"P",
    "gn:feature_code":"PPLA4",
    "gn:name":"Xinqiao",
    "gn:population":0,
    "gn:timezone":"Asia/Shanghai",
    "iso:country":"CN",
    "name:ceb_x_preferred":[
        "Xinqiao"
    ],
    "name:deu_x_preferred":[
        "Xinqiao"
    ],
    "name:swe_x_preferred":[
        "Xinqiao"
    ],
    "name:und_x_variant":[
        "\u65b0\u6865",
        "Xinqiao Zhen",
        "\u65b0\u6865\u9547"
    ],
    "name:zho_x_preferred":[
        "\u65b0\u6865\u9547"
    ],
    "wof:name":"Xinqiao",
    "wof:placetype":"locality"
},
  "geometry": {"coordinates":[120.79336000000001,32.9457],"type":"Point"}
}