{
  "type": "Feature",
  "properties": {
    "gn:admin1_code":"19.0",
    "gn:asciiname":"Guoshucun",
    "gn:country_code":"CN",
    "gn:dem":461,
    "gn:feature_class":"P",
    "gn:feature_code":"PPL",
    "gn:name":"Guoshucun",
    "gn:population":0,
    "gn:timezone":"Asia/Shanghai",
    "iso:country":"CN",
    "name:zho_x_preferred":[
        "\u679c\u6811\u6751"
    ],
    "wof:name":"Guoshucun",
    "wof:placetype":"locality"
},
  "geometry": {"coordinates":[121.471,42.3065],"type":"Point"}
}