{
  "type": "Feature",
  "properties": {
    "gn:admin1_code":"31.0",
    "gn:asciiname":"Changfu",
    "gn:country_code":"CN",
    "gn:dem":24,
    "gn:feature_class":"P",
    "gn:feature_code":"PPL",
    "gn:name":"Changfu",
    "gn:population":0,
    "gn:timezone":"Asia/Shanghai",
    "iso:country":"CN",
    "name:zho_x_preferred":[
        "Changfu"
    ],
    "name:zho_x_variant":[
        "\u660c\u798f"
    ],
    "wof:name":"Changfu",
    "wof:placetype":"locality"
},
  "geometry": {"coordinates":[110.91701,19.77938],"type":"Point"}
}