{
  "type": "Feature",
  "properties": {
    "gn:admin1_code":"22.0",
    "gn:asciiname":"Nannxinzhuangcun",
    "gn:country_code":"CN",
    "gn:dem":65,
    "gn:feature_class":"P",
    "gn:feature_code":"PPL",
    "gn:name":"Nannxinzhuangcun",
    "gn:population":0,
    "gn:timezone":"Asia/Shanghai",
    "iso:country":"CN",
    "name:zho_x_preferred":[
        "\u5357\u8f9b\u5e84\u6751"
    ],
    "wof:name":"Nannxinzhuangcun",
    "wof:placetype":"locality"
},
  "geometry": {"coordinates":[116.20292000000001,39.95322],"type":"Point"}
}