{
  "type": "Feature",
  "properties": {
    "gn:admin1_code":"9.0",
    "gn:asciiname":"Dachewang",
    "gn:country_code":"CN",
    "gn:dem":72,
    "gn:feature_class":"P",
    "gn:feature_code":"PPL",
    "gn:name":"Dachewang",
    "gn:population":0,
    "gn:timezone":"Asia/Shanghai",
    "iso:country":"CN",
    "name:und_x_variant":[
        "\u6253\u8f66\u738b"
    ],
    "name:zho_x_preferred":[
        "\u6253\u8f66\u738b"
    ],
    "wof:name":"Dachewang",
    "wof:placetype":"locality"
},
  "geometry": {"coordinates":[113.87056,33.80077],"type":"Point"}
}