{
  "type": "Feature",
  "properties": {
    "gn:admin1_code":"4.0",
    "gn:asciiname":"Zhuchawangcun",
    "gn:country_code":"CN",
    "gn:dem":9,
    "gn:feature_class":"P",
    "gn:feature_code":"PPL",
    "gn:name":"Zhuchawangcun",
    "gn:population":0,
    "gn:timezone":"Asia/Shanghai",
    "iso:country":"CN",
    "name:zho_x_preferred":[
        "\u6731\u5c94\u6c6a\u6751"
    ],
    "wof:name":"Zhuchawangcun",
    "wof:placetype":"locality"
},
  "geometry": {"coordinates":[119.01349,34.83508],"type":"Point"}
}