{
  "type": "Feature",
  "properties": {
    "gn:admin1_code":"8.0",
    "gn:asciiname":"Xinanshan",
    "gn:country_code":"CN",
    "gn:dem":131,
    "gn:feature_class":"P",
    "gn:feature_code":"PPL",
    "gn:name":"Xinanshan",
    "gn:population":0,
    "gn:timezone":"Asia/Shanghai",
    "iso:country":"CN",
    "name:zho_x_preferred":[
        "\u897f\u5357\u5c71"
    ],
    "wof:name":"Xinanshan",
    "wof:placetype":"locality"
},
  "geometry": {"coordinates":[124.62394999999999,45.88145],"type":"Point"}
}