{
  "type": "Feature",
  "properties": {
    "gn:admin1_code":"32.0",
    "gn:asciiname":"Tongkuzi",
    "gn:country_code":"CN",
    "gn:dem":390,
    "gn:feature_class":"P",
    "gn:feature_code":"PPL",
    "gn:name":"Tongkuzi",
    "gn:population":0,
    "gn:timezone":"Asia/Shanghai",
    "iso:country":"CN",
    "name:zho_x_preferred":[
        "\u94dc\u5e93\u5b50"
    ],
    "wof:name":"Tongkuzi",
    "wof:placetype":"locality"
},
  "geometry": {"coordinates":[103.72512,29.5445],"type":"Point"}
}