{
  "type": "Feature",
  "properties": {
    "gn:admin1_code":"14.0",
    "gn:asciiname":"Gyungcang",
    "gn:country_code":"CN",
    "gn:dem":4848,
    "gn:feature_class":"P",
    "gn:feature_code":"PPLF",
    "gn:name":"Gyungcang",
    "gn:population":0,
    "gn:timezone":"Asia/Urumqi",
    "iso:country":"CN",
    "name:bod_x_preferred":[
        "Gyungcang"
    ],
    "name:msa_x_preferred":[
        "Gyungcang"
    ],
    "name:zho_x_preferred":[
        "Juncang"
    ],
    "name:zho_x_variant":[
        "\u519b\u4ed3",
        "Lumanarong",
        "\u9c81\u739b\u90a3\u7ed2"
    ],
    "wof:name":"Gyungcang",
    "wof:placetype":"locality"
},
  "geometry": {"coordinates":[85.83333,31.35],"type":"Point"}
}