{
  "type": "Feature",
  "properties": {
    "gn:admin1_code":"8.0",
    "gn:asciiname":"Damen Yujiatun",
    "gn:country_code":"CN",
    "gn:dem":222,
    "gn:feature_class":"P",
    "gn:feature_code":"PPL",
    "gn:name":"Damen Yujiatun",
    "gn:population":0,
    "gn:timezone":"Asia/Shanghai",
    "iso:country":"CN",
    "name:zho_x_preferred":[
        "\u5927\u95e8\u4e8e\u5bb6\u5c6f"
    ],
    "wof:name":"Damen Yujiatun",
    "wof:placetype":"locality"
},
  "geometry": {"coordinates":[127.92959999999999,45.6525],"type":"Point"}
}