{
  "type": "Feature",
  "properties": {
    "gn:admin1_code":"7",
    "gn:asciiname":"Hujiao",
    "gn:country_code":"CN",
    "gn:dem":23,
    "gn:feature_class":"P",
    "gn:feature_code":"PPL",
    "gn:name":"Hujiao",
    "gn:population":0,
    "gn:timezone":"Asia/Shanghai",
    "iso:country":"CN",
    "name:zho_x_preferred":[
        "\u6e56\u4ea4"
    ],
    "wof:name":"Hujiao",
    "wof:placetype":"locality"
},
  "geometry": {"coordinates":[117.85646,24.15226],"type":"Point"}
}