{
  "type": "Feature",
  "properties": {
    "gn:admin1_code":"22",
    "gn:asciiname":"Banjiehe",
    "gn:country_code":"CN",
    "gn:dem":17,
    "gn:feature_class":"P",
    "gn:feature_code":"PPL",
    "gn:name":"Banjiehe",
    "gn:population":0,
    "gn:timezone":"Asia/Shanghai",
    "iso:country":"CN",
    "name:zho_x_preferred":[
        "\u534a\u622a\u6cb3"
    ],
    "wof:name":"Banjiehe",
    "wof:placetype":"locality"
},
  "geometry": {"coordinates":[116.79638,39.63986],"type":"Point"}
}