{
  "type": "Feature",
  "properties": {
    "gn:admin1_code":"18.0",
    "gn:asciiname":"Shiziting",
    "gn:country_code":"CN",
    "gn:dem":596,
    "gn:feature_class":"P",
    "gn:feature_code":"PPL",
    "gn:name":"Shiziting",
    "gn:population":0,
    "gn:timezone":"Asia/Shanghai",
    "iso:country":"CN",
    "name:zho_x_preferred":[
        "\u72ee\u5b50\u5385"
    ],
    "wof:name":"Shiziting",
    "wof:placetype":"locality"
},
  "geometry": {"coordinates":[108.51900000000001,27.2795],"type":"Point"}
}