{
  "type": "Feature",
  "properties": {
    "gn:admin1_code":"10",
    "gn:asciiname":"Huaying",
    "gn:country_code":"CN",
    "gn:dem":59,
    "gn:feature_class":"P",
    "gn:feature_code":"PPL",
    "gn:name":"Huaying",
    "gn:population":0,
    "gn:timezone":"Asia/Shanghai",
    "iso:country":"CN",
    "name:ara_x_preferred":[
        "\u0647\u0648\u0627\u064a\u0646\u063a"
    ],
    "name:dan_x_preferred":[
        "Huaying"
    ],
    "name:deu_x_preferred":[
        "Huaying"
    ],
    "name:fas_x_preferred":[
        "\u0647\u0648\u0627\u06cc\u06cc\u0646\u06af"
    ],
    "name:fra_x_preferred":[
        "Huaying"
    ],
    "name:hak_x_preferred":[
        "F\u00e0-y\u00ecn-s\u1e73"
    ],
    "name:ita_x_preferred":[
        "Huaying"
    ],
    "name:jpn_x_preferred":[
        "\u83ef\u30a8\u30a4\u5e02"
    ],
    "name:kik_x_preferred":[
        "Huaying"
    ],
    "name:kor_x_preferred":[
        "\ud654\uc789\uc2dc"
    ],
    "name:nor_x_preferred":[
        "Huaying"
    ],
    "name:rus_x_preferred":[
        "\u0425\u0443\u0430\u0438\u043d"
    ],
    "name:swe_x_preferred":[
        "Huaying"
    ],
    "name:vie_x_preferred":[
        "Hoa Dinh"
    ],
    "name:war_x_preferred":[
        "Huaying"
    ],
    "name:zho_x_preferred":[
        "\u534e\u8425"
    ],
    "name:zho_x_variant":[
        "\u534e\u84e5\u5e02"
    ],
    "wof:name":"Huaying",
    "wof:placetype":"locality"
},
  "geometry": {"coordinates":[114.85899999999999,36.1815],"type":"Point"}
}