{
  "type": "Feature",
  "properties": {
    "gn:admin1_code":"32.0",
    "gn:asciiname":"Yaozhailin",
    "gn:country_code":"CN",
    "gn:dem":878,
    "gn:feature_class":"P",
    "gn:feature_code":"PPL",
    "gn:name":"Yaozhailin",
    "gn:population":0,
    "gn:timezone":"Asia/Shanghai",
    "iso:country":"CN",
    "name:zho_x_preferred":[
        "\u59da\u5be8\u6797"
    ],
    "wof:name":"Yaozhailin",
    "wof:placetype":"locality"
},
  "geometry": {"coordinates":[104.273,28.75],"type":"Point"}
}