{
  "type": "Feature",
  "properties": {
    "gn:admin1_code":"15.0",
    "gn:asciiname":"Mayaozi",
    "gn:country_code":"CN",
    "gn:dem":1853,
    "gn:feature_class":"P",
    "gn:feature_code":"PPL",
    "gn:name":"Mayaozi",
    "gn:population":0,
    "gn:timezone":"Asia/Shanghai",
    "iso:country":"CN",
    "name:zho_x_preferred":[
        "\u9ebb\u7a91\u5b50"
    ],
    "wof:name":"Mayaozi",
    "wof:placetype":"locality"
},
  "geometry": {"coordinates":[104.97433999999998,33.93769],"type":"Point"}
}