{
  "type": "Feature",
  "properties": {
    "gn:admin1_code":"14.0",
    "gn:asciiname":"Bengkang",
    "gn:country_code":"CN",
    "gn:dem":4528,
    "gn:feature_class":"P",
    "gn:feature_code":"PPL",
    "gn:name":"Bengkang",
    "gn:population":0,
    "gn:timezone":"Asia/Urumqi",
    "iso:country":"CN",
    "name:zho_x_preferred":[
        "\u5d29\u5eb7"
    ],
    "wof:name":"Bengkang",
    "wof:placetype":"locality"
},
  "geometry": {"coordinates":[94.29687,31.11032],"type":"Point"}
}