{
  "type": "Feature",
  "properties": {
    "gn:admin1_code":"30",
    "gn:asciiname":"Shijing",
    "gn:country_code":"CN",
    "gn:dem":36,
    "gn:feature_class":"P",
    "gn:feature_code":"PPLA4",
    "gn:name":"Shijing",
    "gn:population":0,
    "gn:timezone":"Asia/Urumqi",
    "iso:country":"CN",
    "name:und_x_variant":[
        "Shijing Zhen",
        "\u77f3\u9888\u9547"
    ],
    "name:zho_x_preferred":[
        "\u77f3\u9888"
    ],
    "wof:name":"Shijing",
    "wof:placetype":"locality"
},
  "geometry": {"coordinates":[110.02330000000001,21.69851],"type":"Point"}
}