{
  "type": "Feature",
  "properties": {
    "gn:admin1_code":"12.0",
    "gn:asciiname":"Yanqiao",
    "gn:country_code":"CN",
    "gn:dem":77,
    "gn:feature_class":"P",
    "gn:feature_code":"PPL",
    "gn:name":"Yanqiao",
    "gn:population":0,
    "gn:timezone":"Asia/Shanghai",
    "iso:country":"CN",
    "name:und_x_variant":[
        "\u5830\u6865"
    ],
    "wof:name":"Yanqiao",
    "wof:placetype":"locality"
},
  "geometry": {"coordinates":[115.39234,30.41179],"type":"Point"}
}