{
  "type": "Feature",
  "properties": {
    "gn:admin1_code":"9.0",
    "gn:asciiname":"Shanzhang",
    "gn:country_code":"CN",
    "gn:dem":175,
    "gn:feature_class":"P",
    "gn:feature_code":"PPL",
    "gn:name":"Shanzhang",
    "gn:population":0,
    "gn:timezone":"Asia/Shanghai",
    "iso:country":"CN",
    "name:und_x_variant":[
        "\u5c71\u5f20",
        "Shanzhang"
    ],
    "wof:name":"Shanzhang",
    "wof:placetype":"locality"
},
  "geometry": {"coordinates":[112.98285,33.87251],"type":"Point"}
}