{
  "type": "Feature",
  "properties": {
    "gn:admin1_code":"24.0",
    "gn:asciiname":"Baidaoyucun",
    "gn:country_code":"CN",
    "gn:dem":730,
    "gn:feature_class":"P",
    "gn:feature_code":"PPL",
    "gn:name":"Baidaoyucun",
    "gn:population":0,
    "gn:timezone":"Asia/Shanghai",
    "iso:country":"CN",
    "name:zho_x_preferred":[
        "\u767d\u9053\u5cea\u6751"
    ],
    "wof:name":"Baidaoyucun",
    "wof:placetype":"locality"
},
  "geometry": {"coordinates":[110.65325,37.83563],"type":"Point"}
}