{
  "type": "Feature",
  "properties": {
    "gn:admin1_code":"3.0",
    "gn:asciiname":"Pengtian",
    "gn:country_code":"CN",
    "gn:dem":136,
    "gn:feature_class":"P",
    "gn:feature_code":"PPL",
    "gn:name":"Pengtian",
    "gn:population":0,
    "gn:timezone":"Asia/Shanghai",
    "iso:country":"CN",
    "name:und_x_variant":[
        "\u5f6d\u7530"
    ],
    "wof:name":"Pengtian",
    "wof:placetype":"locality"
},
  "geometry": {"coordinates":[116.88630000000001,27.69991],"type":"Point"}
}