{
  "type": "Feature",
  "properties": {
    "gn:admin1_code":"7.0",
    "gn:asciiname":"Hutoushan",
    "gn:country_code":"CN",
    "gn:dem":571,
    "gn:feature_class":"P",
    "gn:feature_code":"PPL",
    "gn:name":"Hutoushan",
    "gn:population":0,
    "gn:timezone":"Asia/Shanghai",
    "iso:country":"CN",
    "name:zho_x_preferred":[
        "\u864e\u5934\u5c71"
    ],
    "wof:name":"Hutoushan",
    "wof:placetype":"locality"
},
  "geometry": {"coordinates":[117.66513999999999,26.24974000000001],"type":"Point"}
}