{
  "type": "Feature",
  "properties": {
    "gn:admin1_code":"29.0",
    "gn:asciiname":"Dong'an",
    "gn:country_code":"CN",
    "gn:dem":1941,
    "gn:feature_class":"P",
    "gn:feature_code":"PPL",
    "gn:name":"Dong\u2019an",
    "gn:population":0,
    "gn:timezone":"Asia/Shanghai",
    "iso:country":"CN",
    "name:und_x_variant":[
        "Dong\u2019an"
    ],
    "name:zho_x_preferred":[
        "\u4e1c\u5b89"
    ],
    "wof:name":"Dong'an",
    "wof:placetype":"locality"
},
  "geometry": {"coordinates":[99.10980000000001,24.5937],"type":"Point"}
}