{
  "type": "Feature",
  "properties": {
    "gn:admin1_code":"32.0",
    "gn:asciiname":"Laoshuikong",
    "gn:country_code":"CN",
    "gn:dem":1038,
    "gn:feature_class":"P",
    "gn:feature_code":"PPL",
    "gn:name":"Laoshuikong",
    "gn:population":0,
    "gn:timezone":"Asia/Shanghai",
    "iso:country":"CN",
    "name:zho_x_preferred":[
        "\u8001\u6c34\u5b54"
    ],
    "wof:name":"Laoshuikong",
    "wof:placetype":"locality"
},
  "geometry": {"coordinates":[103.9485,28.8024],"type":"Point"}
}