{
  "type": "Feature",
  "properties": {
    "gn:admin1_code":"32.0",
    "gn:asciiname":"Fenggongci",
    "gn:country_code":"CN",
    "gn:dem":464,
    "gn:feature_class":"P",
    "gn:feature_code":"PPL",
    "gn:name":"Fenggongci",
    "gn:population":0,
    "gn:timezone":"Asia/Shanghai",
    "iso:country":"CN",
    "name:zho_x_preferred":[
        "\u73a2\u516c\u7960"
    ],
    "wof:name":"Fenggongci",
    "wof:placetype":"locality"
},
  "geometry": {"coordinates":[104.63936,30.66889],"type":"Point"}
}