{
  "type": "Feature",
  "properties": {
    "gn:admin1_code":"19",
    "gn:asciiname":"Liulonggoumanzuxiang",
    "gn:cc2":"CN",
    "gn:country_code":"CN",
    "gn:dem":205,
    "gn:feature_class":"P",
    "gn:feature_code":"PPL",
    "gn:name":"Liulonggoumanzuxiang",
    "gn:population":0,
    "gn:timezone":"Asia/Shanghai",
    "iso:country":"CN",
    "name:und_x_variant":[
        "Liulonggou",
        "Liulonggoumanzuxiang"
    ],
    "wof:name":"Liulonggoumanzuxiang",
    "wof:placetype":"locality"
},
  "geometry": {"coordinates":[121.05833,41.39417],"type":"Point"}
}