{
  "type": "Feature",
  "properties": {
    "gn:admin1_code":"24.0",
    "gn:asciiname":"Shangmaigou",
    "gn:country_code":"CN",
    "gn:dem":658,
    "gn:feature_class":"P",
    "gn:feature_code":"PPL",
    "gn:name":"Shangmaigou",
    "gn:population":0,
    "gn:timezone":"Asia/Shanghai",
    "iso:country":"CN",
    "name:und_x_variant":[
        "\u4e0a\u9ea6\u6c9f"
    ],
    "name:zho_x_preferred":[
        "\u4e0a\u9ea6\u6c9f"
    ],
    "wof:name":"Shangmaigou",
    "wof:placetype":"locality"
},
  "geometry": {"coordinates":[111.52802,35.79759],"type":"Point"}
}