{
  "type": "Feature",
  "properties": {
    "gn:admin1_code":"16.0",
    "gn:asciiname":"Lansha",
    "gn:country_code":"CN",
    "gn:dem":577,
    "gn:feature_class":"P",
    "gn:feature_code":"PPL",
    "gn:name":"Lansha",
    "gn:population":0,
    "gn:timezone":"Asia/Shanghai",
    "iso:country":"CN",
    "name:zho_x_preferred":[
        "\u89c8\u6c99"
    ],
    "wof:name":"Lansha",
    "wof:placetype":"locality"
},
  "geometry": {"coordinates":[106.515,24.3758],"type":"Point"}
}