{
  "type": "Feature",
  "properties": {
    "gn:admin1_code":"10",
    "gn:asciiname":"Laonituo Shangying",
    "gn:country_code":"CN",
    "gn:dem":1514,
    "gn:feature_class":"P",
    "gn:feature_code":"PPL",
    "gn:name":"Laonituo Shangying",
    "gn:population":0,
    "gn:timezone":"Asia/Shanghai",
    "iso:country":"CN",
    "name:zho_x_preferred":[
        "\u6d9d\u6ce5\u6cb1\u4e0a\u8425"
    ],
    "wof:name":"Laonituo Shangying",
    "wof:placetype":"locality"
},
  "geometry": {"coordinates":[116.56467000000001,41.72545],"type":"Point"}
}