{
  "type": "Feature",
  "properties": {
    "gn:admin1_code":"25.0",
    "gn:asciiname":"Gaojialoucun",
    "gn:country_code":"CN",
    "gn:dem":15,
    "gn:feature_class":"P",
    "gn:feature_code":"PPL",
    "gn:name":"Gaojialoucun",
    "gn:population":0,
    "gn:timezone":"Asia/Shanghai",
    "iso:country":"CN",
    "name:zho_x_preferred":[
        "\u9ad8\u5bb6\u697c\u6751"
    ],
    "wof:name":"Gaojialoucun",
    "wof:placetype":"locality"
},
  "geometry": {"coordinates":[119.64261999999999,36.40491],"type":"Point"}
}