{
  "type": "Feature",
  "properties": {
    "gn:admin1_code":"32.0",
    "gn:asciiname":"Yaoshishan",
    "gn:country_code":"CN",
    "gn:dem":525,
    "gn:feature_class":"P",
    "gn:feature_code":"PPL",
    "gn:name":"Yaoshishan",
    "gn:population":0,
    "gn:timezone":"Asia/Shanghai",
    "iso:country":"CN",
    "name:zho_x_preferred":[
        "\u6447\u77f3\u5c71"
    ],
    "wof:name":"Yaoshishan",
    "wof:placetype":"locality"
},
  "geometry": {"coordinates":[106.786,31.5273],"type":"Point"}
}