{
  "type": "Feature",
  "properties": {
    "gn:admin1_code":"29.0",
    "gn:asciiname":"Xiabolu",
    "gn:country_code":"CN",
    "gn:dem":1104,
    "gn:feature_class":"P",
    "gn:feature_code":"PPL",
    "gn:name":"Xiabolu",
    "gn:population":0,
    "gn:timezone":"Asia/Shanghai",
    "iso:country":"CN",
    "name:zho_x_preferred":[
        "\u4e0b\u6ce2\u8def"
    ],
    "wof:name":"Xiabolu",
    "wof:placetype":"locality"
},
  "geometry": {"coordinates":[100.34,22.3142],"type":"Point"}
}