{
  "type": "Feature",
  "properties": {
    "gn:admin1_code":"9.0",
    "gn:asciiname":"Huli",
    "gn:country_code":"CN",
    "gn:dem":76,
    "gn:feature_class":"P",
    "gn:feature_code":"PPL",
    "gn:name":"Huli",
    "gn:population":0,
    "gn:timezone":"Asia/Shanghai",
    "iso:country":"CN",
    "name:ceb_x_preferred":[
        "Huli"
    ],
    "name:deu_x_preferred":[
        "Huli"
    ],
    "name:fra_x_preferred":[
        "Huli"
    ],
    "name:rus_x_preferred":[
        "\u0425\u0443\u043b\u0438"
    ],
    "name:swe_x_preferred":[
        "Huli"
    ],
    "name:tur_x_preferred":[
        "Huli"
    ],
    "name:zho_x_preferred":[
        "\u6e56\u674e"
    ],
    "wof:name":"Huli",
    "wof:placetype":"locality"
},
  "geometry": {"coordinates":[113.67752,33.67383],"type":"Point"}
}