{
  "type": "Feature",
  "properties": {
    "gn:admin1_code":"22.0",
    "gn:asciiname":"Qiyuancun",
    "gn:country_code":"CN",
    "gn:dem":214,
    "gn:feature_class":"P",
    "gn:feature_code":"PPL",
    "gn:name":"Qiyuancun",
    "gn:population":0,
    "gn:timezone":"Asia/Shanghai",
    "iso:country":"CN",
    "name:zho_x_preferred":[
        "\u6f06\u56ed\u6751"
    ],
    "wof:name":"Qiyuancun",
    "wof:placetype":"locality"
},
  "geometry": {"coordinates":[116.02966000000001,40.13001],"type":"Point"}
}