{
  "type": "Feature",
  "properties": {
    "gn:admin1_code":"8.0",
    "gn:asciiname":"Daobaocun",
    "gn:country_code":"CN",
    "gn:dem":136,
    "gn:feature_class":"P",
    "gn:feature_code":"PPL",
    "gn:name":"Daobaocun",
    "gn:population":0,
    "gn:timezone":"Asia/Shanghai",
    "iso:country":"CN",
    "name:zho_x_preferred":[
        "\u9053\u5b9d\u6751"
    ],
    "wof:name":"Daobaocun",
    "wof:placetype":"locality"
},
  "geometry": {"coordinates":[124.21482,45.79967],"type":"Point"}
}