{
  "type": "Feature",
  "properties": {
    "gn:admin1_code":"14.0",
    "gn:asciiname":"Guoluo",
    "gn:country_code":"CN",
    "gn:dem":3919,
    "gn:feature_class":"P",
    "gn:feature_code":"PPL",
    "gn:name":"Guoluo",
    "gn:population":0,
    "gn:timezone":"Asia/Urumqi",
    "iso:country":"CN",
    "name:zho_x_preferred":[
        "\u679c\u6d1b"
    ],
    "wof:name":"Guoluo",
    "wof:placetype":"locality"
},
  "geometry": {"coordinates":[96.77616999999999,29.4958],"type":"Point"}
}