{
  "type": "Feature",
  "properties": {
    "gn:admin1_code":"10",
    "gn:asciiname":"Beisongjia",
    "gn:country_code":"CN",
    "gn:dem":24,
    "gn:feature_class":"P",
    "gn:feature_code":"PPL",
    "gn:name":"Beisongjia",
    "gn:population":0,
    "gn:timezone":"Asia/Shanghai",
    "iso:country":"CN",
    "name:zho_x_preferred":[
        "\u5317\u5b8b\u5bb6"
    ],
    "wof:name":"Beisongjia",
    "wof:placetype":"locality"
},
  "geometry": {"coordinates":[115.657,37.7857],"type":"Point"}
}