{
  "type": "Feature",
  "properties": {
    "gn:admin1_code":"4.0",
    "gn:asciiname":"Matai",
    "gn:country_code":"CN",
    "gn:dem":18,
    "gn:feature_class":"P",
    "gn:feature_code":"PPL",
    "gn:name":"Matai",
    "gn:population":0,
    "gn:timezone":"Asia/Shanghai",
    "iso:country":"CN",
    "name:ceb_x_preferred":[
        "Matai"
    ],
    "name:deu_x_preferred":[
        "Matai"
    ],
    "name:swe_x_preferred":[
        "Matai"
    ],
    "name:zho_x_preferred":[
        "\u9a6c\u53f0"
    ],
    "wof:name":"Matai",
    "wof:placetype":"locality"
},
  "geometry": {"coordinates":[118.08799999999999,33.1789],"type":"Point"}
}