{
  "type": "Feature",
  "properties": {
    "gn:admin1_code":"9.0",
    "gn:asciiname":"Wangjixiang",
    "gn:country_code":"CN",
    "gn:dem":105,
    "gn:feature_class":"P",
    "gn:feature_code":"PPL",
    "gn:name":"Wangjixiang",
    "gn:population":0,
    "gn:timezone":"Asia/Shanghai",
    "iso:country":"CN",
    "name:und_x_variant":[
        "\u738b\u96c6\u4e61"
    ],
    "name:zho_x_preferred":[
        "\u738b\u96c6\u4e61"
    ],
    "wof:name":"Wangjixiang",
    "wof:placetype":"locality"
},
  "geometry": {"coordinates":[113.27986,33.96409],"type":"Point"}
}