{
  "type": "Feature",
  "properties": {
    "gn:admin1_code":"29.0",
    "gn:asciiname":"Baopingcun",
    "gn:country_code":"CN",
    "gn:dem":1117,
    "gn:feature_class":"P",
    "gn:feature_code":"PPL",
    "gn:name":"Baopingcun",
    "gn:population":0,
    "gn:timezone":"Asia/Shanghai",
    "iso:country":"CN",
    "name:zho_x_preferred":[
        "\u4fdd\u576a\u6751"
    ],
    "wof:name":"Baopingcun",
    "wof:placetype":"locality"
},
  "geometry": {"coordinates":[103.16500000000001,27.3805],"type":"Point"}
}