{
  "type": "Feature",
  "properties": {
    "gn:admin1_code":"11.0",
    "gn:asciiname":"Fangzishan",
    "gn:country_code":"CN",
    "gn:dem":462,
    "gn:feature_class":"P",
    "gn:feature_code":"PPL",
    "gn:name":"Fangzishan",
    "gn:population":0,
    "gn:timezone":"Asia/Shanghai",
    "iso:country":"CN",
    "name:zho_x_preferred":[
        "\u65b9\u5b50\u5c71"
    ],
    "wof:name":"Fangzishan",
    "wof:placetype":"locality"
},
  "geometry": {"coordinates":[110.18250999999999,27.80167],"type":"Point"}
}