{
  "type": "Feature",
  "properties": {
    "gn:admin1_code":"8.0",
    "gn:asciiname":"Qixincun",
    "gn:country_code":"CN",
    "gn:dem":145,
    "gn:feature_class":"P",
    "gn:feature_code":"PPL",
    "gn:name":"Qixincun",
    "gn:population":0,
    "gn:timezone":"Asia/Shanghai",
    "iso:country":"CN",
    "name:zho_x_preferred":[
        "\u542f\u65b0\u6751"
    ],
    "wof:name":"Qixincun",
    "wof:placetype":"locality"
},
  "geometry": {"coordinates":[127.58853999999999,45.98224],"type":"Point"}
}