{
  "type": "Feature",
  "properties": {
    "gn:admin1_code":"26",
    "gn:asciiname":"Tangzang",
    "gn:country_code":"CN",
    "gn:dem":1238,
    "gn:feature_class":"P",
    "gn:feature_code":"PPLA4",
    "gn:name":"Tangzang",
    "gn:population":0,
    "gn:timezone":"Asia/Shanghai",
    "iso:country":"CN",
    "name:und_x_variant":[
        "T\u2019ang-tsang",
        "Tangzang",
        "\u5510\u85cf",
        "Tangzang Zhen",
        "\u5510\u85cf\u9547"
    ],
    "wof:name":"Tangzang",
    "wof:placetype":"locality"
},
  "geometry": {"coordinates":[106.58360999999999,34.09056],"type":"Point"}
}