{
  "type": "Feature",
  "properties": {
    "gn:admin1_code":"11.0",
    "gn:asciiname":"Sunjiaqiao",
    "gn:country_code":"CN",
    "gn:dem":31,
    "gn:feature_class":"P",
    "gn:feature_code":"PPL",
    "gn:name":"Sunjiaqiao",
    "gn:population":0,
    "gn:timezone":"Asia/Shanghai",
    "iso:country":"CN",
    "name:zho_x_preferred":[
        "Sunjiaqiao"
    ],
    "name:zho_x_variant":[
        "\u5b59\u5bb6\u6865"
    ],
    "wof:name":"Sunjiaqiao",
    "wof:placetype":"locality"
},
  "geometry": {"coordinates":[111.77012999999999,28.93215],"type":"Point"}
}