{
  "type": "Feature",
  "properties": {
    "gn:admin1_code":"29.0",
    "gn:asciiname":"Laoyuanzhai",
    "gn:country_code":"CN",
    "gn:dem":1738,
    "gn:feature_class":"P",
    "gn:feature_code":"PPL",
    "gn:name":"Laoyuanzhai",
    "gn:population":0,
    "gn:timezone":"Asia/Shanghai",
    "iso:country":"CN",
    "name:zho_x_preferred":[
        "\u8001\u5458\u5be8"
    ],
    "wof:name":"Laoyuanzhai",
    "wof:placetype":"locality"
},
  "geometry": {"coordinates":[104.081,23.2722],"type":"Point"}
}