{
  "type": "Feature",
  "properties": {
    "gn:admin1_code":"12.0",
    "gn:asciiname":"Lujiahe",
    "gn:country_code":"CN",
    "gn:dem":369,
    "gn:feature_class":"P",
    "gn:feature_code":"PPL",
    "gn:name":"L\u00fcjiahe",
    "gn:population":0,
    "gn:timezone":"Asia/Shanghai",
    "iso:country":"CN",
    "name:und_x_variant":[
        "L\u00fcjiahe"
    ],
    "name:zho_x_preferred":[
        "\u5415\u5bb6\u6cb3"
    ],
    "wof:name":"Lujiahe",
    "wof:placetype":"locality"
},
  "geometry": {"coordinates":[110.88582,32.3612],"type":"Point"}
}