{
  "type": "Feature",
  "properties": {
    "gn:admin1_code":"18.0",
    "gn:asciiname":"Nongzikou",
    "gn:country_code":"CN",
    "gn:dem":423,
    "gn:feature_class":"P",
    "gn:feature_code":"PPL",
    "gn:name":"Nongzikou",
    "gn:population":0,
    "gn:timezone":"Asia/Shanghai",
    "iso:country":"CN",
    "name:zho_x_preferred":[
        "\u5f04\u5b50\u53e3"
    ],
    "wof:name":"Nongzikou",
    "wof:placetype":"locality"
},
  "geometry": {"coordinates":[108.383,26.0587],"type":"Point"}
}