{
  "type": "Feature",
  "properties": {
    "gn:admin1_code":"10",
    "gn:asciiname":"Aizi",
    "gn:country_code":"CN",
    "gn:dem":9,
    "gn:feature_class":"P",
    "gn:feature_code":"PPL",
    "gn:name":"Aizi",
    "gn:population":0,
    "gn:timezone":"Asia/Shanghai",
    "iso:country":"CN",
    "name:fra_x_preferred":[
        "A\u00efzi"
    ],
    "name:zho_x_preferred":[
        "\u827e\u5b50"
    ],
    "wof:name":"Aizi",
    "wof:placetype":"locality"
},
  "geometry": {"coordinates":[116.565,38.7832],"type":"Point"}
}