{
  "type": "Feature",
  "properties": {
    "gn:admin1_code":"11.0",
    "gn:asciiname":"Daobeishan",
    "gn:country_code":"CN",
    "gn:dem":723,
    "gn:feature_class":"P",
    "gn:feature_code":"PPL",
    "gn:name":"Daobeishan",
    "gn:population":0,
    "gn:timezone":"Asia/Shanghai",
    "iso:country":"CN",
    "name:zho_x_preferred":[
        "\u5200\u80cc\u5c71"
    ],
    "wof:name":"Daobeishan",
    "wof:placetype":"locality"
},
  "geometry": {"coordinates":[114.14134,26.12785],"type":"Point"}
}