{
  "type": "Feature",
  "properties": {
    "gn:admin1_code":"1.0",
    "gn:asciiname":"Qindacun",
    "gn:country_code":"CN",
    "gn:dem":32,
    "gn:feature_class":"P",
    "gn:feature_code":"PPL",
    "gn:name":"Qindacun",
    "gn:population":0,
    "gn:timezone":"Asia/Shanghai",
    "iso:country":"CN",
    "name:zho_x_preferred":[
        "\u79e6\u5927\u6751"
    ],
    "wof:name":"Qindacun",
    "wof:placetype":"locality"
},
  "geometry": {"coordinates":[115.65260000000001,32.77849000000001],"type":"Point"}
}