{
  "type": "Feature",
  "properties": {
    "gn:admin1_code":"9.0",
    "gn:asciiname":"Yugouya",
    "gn:country_code":"CN",
    "gn:dem":43,
    "gn:feature_class":"P",
    "gn:feature_code":"PPL",
    "gn:name":"Yugouya",
    "gn:population":0,
    "gn:timezone":"Asia/Shanghai",
    "iso:country":"CN",
    "name:zho_x_preferred":[
        "\u4e8e\u6c9f\u6daf"
    ],
    "wof:name":"Yugouya",
    "wof:placetype":"locality"
},
  "geometry": {"coordinates":[115.24764,33.45601],"type":"Point"}
}