{
  "type": "Feature",
  "properties": {
    "gn:admin1_code":"7.0",
    "gn:asciiname":"Fangqian",
    "gn:country_code":"CN",
    "gn:dem":358,
    "gn:feature_class":"P",
    "gn:feature_code":"PPL",
    "gn:name":"Fangqian",
    "gn:population":0,
    "gn:timezone":"Asia/Shanghai",
    "iso:country":"CN",
    "name:zho_x_preferred":[
        "\u574a\u524d"
    ],
    "wof:name":"Fangqian",
    "wof:placetype":"locality"
},
  "geometry": {"coordinates":[117.26271,27.14703],"type":"Point"}
}