{
  "type": "Feature",
  "properties": {
    "gn:admin1_code":"10",
    "gn:asciiname":"Dayanzhangzi",
    "gn:country_code":"CN",
    "gn:dem":318,
    "gn:feature_class":"P",
    "gn:feature_code":"PPL",
    "gn:name":"Dayanzhangzi",
    "gn:population":0,
    "gn:timezone":"Asia/Shanghai",
    "iso:country":"CN",
    "name:zho_x_preferred":[
        "\u5927\u960e\u6756\u5b50"
    ],
    "wof:name":"Dayanzhangzi",
    "wof:placetype":"locality"
},
  "geometry": {"coordinates":[119.03198999999999,40.61517],"type":"Point"}
}