{
  "type": "Feature",
  "properties": {
    "gn:admin1_code":"16.0",
    "gn:asciiname":"Huaqun",
    "gn:country_code":"CN",
    "gn:dem":139,
    "gn:feature_class":"P",
    "gn:feature_code":"PPL",
    "gn:name":"Huaqun",
    "gn:population":0,
    "gn:timezone":"Asia/Shanghai",
    "iso:country":"CN",
    "name:zho_x_preferred":[
        "\u534e\u7fa4"
    ],
    "wof:name":"Huaqun",
    "wof:placetype":"locality"
},
  "geometry": {"coordinates":[108.20999999999999,22.4239],"type":"Point"}
}