{
  "type": "Feature",
  "properties": {
    "gn:admin1_code":"7.0",
    "gn:asciiname":"Lijiang",
    "gn:country_code":"CN",
    "gn:dem":408,
    "gn:feature_class":"P",
    "gn:feature_code":"PPL",
    "gn:name":"Lijiang",
    "gn:population":0,
    "gn:timezone":"Asia/Shanghai",
    "iso:country":"CN",
    "name:und_x_variant":[
        "\u9ca4\u6c5f"
    ],
    "name:zho_x_preferred":[
        "\u9ca4\u6c5f"
    ],
    "wof:name":"Lijiang",
    "wof:placetype":"locality"
},
  "geometry": {"coordinates":[116.76124,25.60675],"type":"Point"}
}