{
  "type": "Feature",
  "properties": {
    "gn:admin1_code":"32.0",
    "gn:asciiname":"Goudi",
    "gn:country_code":"CN",
    "gn:dem":2648,
    "gn:feature_class":"P",
    "gn:feature_code":"PPL",
    "gn:name":"Goudi",
    "gn:population":0,
    "gn:timezone":"Asia/Shanghai",
    "iso:country":"CN",
    "name:zho_x_preferred":[
        "\u82df\u5e95"
    ],
    "wof:name":"Goudi",
    "wof:placetype":"locality"
},
  "geometry": {"coordinates":[103.001,34.1377],"type":"Point"}
}