{
  "type": "Feature",
  "properties": {
    "gn:admin1_code":"12.0",
    "gn:asciiname":"Xijiapai",
    "gn:country_code":"CN",
    "gn:dem":113,
    "gn:feature_class":"P",
    "gn:feature_code":"PPL",
    "gn:name":"Xijiapai",
    "gn:population":0,
    "gn:timezone":"Asia/Shanghai",
    "iso:country":"CN",
    "name:zho_x_preferred":[
        "\u4e60\u5bb6\u6392"
    ],
    "wof:name":"Xijiapai",
    "wof:placetype":"locality"
},
  "geometry": {"coordinates":[113.84278999999999,29.22039],"type":"Point"}
}