{
  "type": "Feature",
  "properties": {
    "gn:admin1_code":"16.0",
    "gn:asciiname":"Badi",
    "gn:country_code":"CN",
    "gn:dem":144,
    "gn:feature_class":"P",
    "gn:feature_code":"PPL",
    "gn:name":"Badi",
    "gn:population":0,
    "gn:timezone":"Asia/Shanghai",
    "iso:country":"CN",
    "name:ceb_x_preferred":[
        "Badi"
    ],
    "name:deu_x_preferred":[
        "Badi"
    ],
    "name:ita_x_preferred":[
        "Badi"
    ],
    "name:rus_x_preferred":[
        "\u0411\u0430\u0434\u0438"
    ],
    "name:swe_x_preferred":[
        "Badi"
    ],
    "name:tur_x_preferred":[
        "Badi"
    ],
    "name:zho_x_preferred":[
        "\u5df4\u7b1b"
    ],
    "wof:name":"Badi",
    "wof:placetype":"locality"
},
  "geometry": {"coordinates":[107.218,22.1442],"type":"Point"}
}