{
  "type": "Feature",
  "properties": {
    "gn:admin1_code":"8.0",
    "gn:asciiname":"Dong'ancun",
    "gn:country_code":"CN",
    "gn:dem":409,
    "gn:feature_class":"P",
    "gn:feature_code":"PPL",
    "gn:name":"Dong\u2019ancun",
    "gn:population":0,
    "gn:timezone":"Asia/Shanghai",
    "iso:country":"CN",
    "name:und_x_variant":[
        "Dong\u2019ancun"
    ],
    "name:zho_x_preferred":[
        "\u4e1c\u5b89\u6751"
    ],
    "wof:name":"Dong'ancun",
    "wof:placetype":"locality"
},
  "geometry": {"coordinates":[129.57378,44.28498],"type":"Point"}
}