{
  "type": "Feature",
  "properties": {
    "gn:admin1_code":"3",
    "gn:asciiname":"Yandongkeng",
    "gn:country_code":"CN",
    "gn:dem":500,
    "gn:feature_class":"P",
    "gn:feature_code":"PPL",
    "gn:name":"Yandongkeng",
    "gn:population":0,
    "gn:timezone":"Asia/Shanghai",
    "iso:country":"CN",
    "name:zho_x_preferred":[
        "\u76d0\u4e1c\u5751"
    ],
    "wof:name":"Yandongkeng",
    "wof:placetype":"locality"
},
  "geometry": {"coordinates":[113.988,25.725],"type":"Point"}
}