{
  "type": "Feature",
  "properties": {
    "gn:admin1_code":"10",
    "gn:asciiname":"Nidong",
    "gn:country_code":"CN",
    "gn:dem":13,
    "gn:feature_class":"P",
    "gn:feature_code":"PPL",
    "gn:name":"Nidong",
    "gn:population":0,
    "gn:timezone":"Asia/Shanghai",
    "iso:country":"CN",
    "name:und_x_variant":[
        "Ni-tung",
        "Nidong"
    ],
    "name:zho_x_preferred":[
        "\u6ce5\u6d1e"
    ],
    "wof:name":"Nidong",
    "wof:placetype":"locality"
},
  "geometry": {"coordinates":[115.974,38.4672],"type":"Point"}
}