{
  "type": "Feature",
  "properties": {
    "gn:admin1_code":"12.0",
    "gn:asciiname":"Bao'erchang",
    "gn:country_code":"CN",
    "gn:dem":883,
    "gn:feature_class":"P",
    "gn:feature_code":"PPL",
    "gn:name":"Bao\u2019erchang",
    "gn:population":0,
    "gn:timezone":"Asia/Shanghai",
    "iso:country":"CN",
    "name:und_x_variant":[
        "Bao\u2019erchang"
    ],
    "name:zho_x_preferred":[
        "\u5305\u8033\u573a"
    ],
    "wof:name":"Bao'erchang",
    "wof:placetype":"locality"
},
  "geometry": {"coordinates":[109.74457,33.1981],"type":"Point"}
}