{
  "type": "Feature",
  "properties": {
    "gn:admin1_code":"26",
    "gn:asciiname":"Zhongying",
    "gn:country_code":"CN",
    "gn:dem":374,
    "gn:feature_class":"P",
    "gn:feature_code":"PPL",
    "gn:name":"Zhongying",
    "gn:population":0,
    "gn:timezone":"Asia/Shanghai",
    "iso:country":"CN",
    "name:und_x_variant":[
        "\u4e2d\u8425"
    ],
    "name:zho_x_preferred":[
        "\u4e2d\u8425"
    ],
    "wof:name":"Zhongying",
    "wof:placetype":"locality"
},
  "geometry": {"coordinates":[108.87555999999999,34.35472],"type":"Point"}
}