{
  "type": "Feature",
  "properties": {
    "gn:admin1_code":"32.0",
    "gn:asciiname":"Kuji",
    "gn:country_code":"CN",
    "gn:dem":2399,
    "gn:feature_class":"P",
    "gn:feature_code":"PPL",
    "gn:name":"Kuji",
    "gn:population":0,
    "gn:timezone":"Asia/Shanghai",
    "iso:country":"CN",
    "name:zho_x_preferred":[
        "\u5e93\u5409"
    ],
    "wof:name":"Kuji",
    "wof:placetype":"locality"
},
  "geometry": {"coordinates":[103.02800000000001,27.8295],"type":"Point"}
}