{
  "type": "Feature",
  "properties": {
    "gn:admin1_code":"8.0",
    "gn:asciiname":"Tongli",
    "gn:country_code":"CN",
    "gn:dem":209,
    "gn:feature_class":"P",
    "gn:feature_code":"PPL",
    "gn:name":"Tongli",
    "gn:population":0,
    "gn:timezone":"Asia/Shanghai",
    "iso:country":"CN",
    "name:ara_x_preferred":[
        "\u062a\u0648\u0646\u063a\u0644\u064a"
    ],
    "name:deu_x_preferred":[
        "Tongli"
    ],
    "name:fra_x_preferred":[
        "Tongli"
    ],
    "name:hun_x_preferred":[
        "Tungli"
    ],
    "name:kor_x_preferred":[
        "\ud241\ub9ac \uc9c4"
    ],
    "name:nor_x_preferred":[
        "Tongli"
    ],
    "name:tha_x_preferred":[
        "\u0e16\u0e07\u0e2b\u0e25\u0e35\u0e48"
    ],
    "name:vie_x_preferred":[
        "\u0110\u1ed3ng L\u00fd"
    ],
    "name:wuu_x_preferred":[
        "\u540c\u91cc\u9547"
    ],
    "name:zho_x_preferred":[
        "\u540c\u5229"
    ],
    "name:zho_x_variant":[
        "\u540c\u91cc\u9547"
    ],
    "wof:name":"Tongli",
    "wof:placetype":"locality"
},
  "geometry": {"coordinates":[123.29068999999998,47.77147],"type":"Point"}
}