{
  "type": "Feature",
  "properties": {
    "gn:admin1_code":"12.0",
    "gn:asciiname":"Taosifangkou",
    "gn:country_code":"CN",
    "gn:dem":690,
    "gn:feature_class":"P",
    "gn:feature_code":"PPL",
    "gn:name":"Taosifangkou",
    "gn:population":0,
    "gn:timezone":"Asia/Shanghai",
    "iso:country":"CN",
    "name:zho_x_preferred":[
        "\u6843\u5bfa\u65b9\u53e3"
    ],
    "wof:name":"Taosifangkou",
    "wof:placetype":"locality"
},
  "geometry": {"coordinates":[110.68956,32.24763],"type":"Point"}
}