{
  "type": "Feature",
  "properties": {
    "gn:admin1_code":"26.0",
    "gn:asciiname":"Yanbucun",
    "gn:country_code":"CN",
    "gn:dem":472,
    "gn:feature_class":"P",
    "gn:feature_code":"PPL",
    "gn:name":"Yanbucun",
    "gn:population":0,
    "gn:timezone":"Asia/Shanghai",
    "iso:country":"CN",
    "name:und_x_variant":[
        "\u95eb\u5821\u6751"
    ],
    "wof:name":"Yanbucun",
    "wof:placetype":"locality"
},
  "geometry": {"coordinates":[107.59262,33.19343],"type":"Point"}
}