{
  "type": "Feature",
  "properties": {
    "gn:admin1_code":"9.0",
    "gn:asciiname":"Wangshengtun",
    "gn:country_code":"CN",
    "gn:dem":89,
    "gn:feature_class":"P",
    "gn:feature_code":"PPL",
    "gn:name":"Wangshengtun",
    "gn:population":0,
    "gn:timezone":"Asia/Shanghai",
    "iso:country":"CN",
    "name:zho_x_preferred":[
        "\u738b\u5347\u5c6f"
    ],
    "wof:name":"Wangshengtun",
    "wof:placetype":"locality"
},
  "geometry": {"coordinates":[114.29798,35.74512],"type":"Point"}
}