{
  "type": "Feature",
  "properties": {
    "gn:admin1_code":"11.0",
    "gn:asciiname":"Shibitou",
    "gn:country_code":"CN",
    "gn:dem":149,
    "gn:feature_class":"P",
    "gn:feature_code":"PPL",
    "gn:name":"Shibitou",
    "gn:population":0,
    "gn:timezone":"Asia/Shanghai",
    "iso:country":"CN",
    "name:zho_x_preferred":[
        "\u77f3\u9f3b\u5934"
    ],
    "wof:name":"Shibitou",
    "wof:placetype":"locality"
},
  "geometry": {"coordinates":[113.22646,26.55538],"type":"Point"}
}