{
  "type": "Feature",
  "properties": {
    "gn:admin1_code":"16.0",
    "gn:asciiname":"Rongshuikou",
    "gn:country_code":"CN",
    "gn:dem":122,
    "gn:feature_class":"P",
    "gn:feature_code":"PPL",
    "gn:name":"Rongshuikou",
    "gn:population":0,
    "gn:timezone":"Asia/Shanghai",
    "iso:country":"CN",
    "name:zho_x_preferred":[
        "\u5bb9\u6c34\u53e3"
    ],
    "wof:name":"Rongshuikou",
    "wof:placetype":"locality"
},
  "geometry": {"coordinates":[111.809,23.9726],"type":"Point"}
}