{
  "type": "Feature",
  "properties": {
    "gn:admin1_code":"29",
    "gn:asciiname":"Gulinqing",
    "gn:cc2":"CN",
    "gn:country_code":"CN",
    "gn:dem":1473,
    "gn:feature_class":"P",
    "gn:feature_code":"PPL",
    "gn:name":"Gulinqing",
    "gn:population":0,
    "gn:timezone":"Asia/Shanghai",
    "iso:country":"CN",
    "name:und_x_variant":[
        "Ku-lin-ching",
        "Gulinqing"
    ],
    "wof:name":"Gulinqing",
    "wof:placetype":"locality"
},
  "geometry": {"coordinates":[103.96472,22.80694],"type":"Point"}
}