{
  "type": "Feature",
  "properties": {
    "gn:admin1_code":"19.0",
    "gn:asciiname":"Songjiatun",
    "gn:country_code":"CN",
    "gn:dem":6,
    "gn:feature_class":"P",
    "gn:feature_code":"PPL",
    "gn:name":"Songjiatun",
    "gn:population":0,
    "gn:timezone":"Asia/Shanghai",
    "iso:country":"CN",
    "name:und_x_variant":[
        "\u5b8b\u5bb6\u5c6f"
    ],
    "name:zho_x_preferred":[
        "\u5b8b\u5bb6\u5c6f"
    ],
    "wof:name":"Songjiatun",
    "wof:placetype":"locality"
},
  "geometry": {"coordinates":[123.67440999999999,39.87947],"type":"Point"}
}