{
  "type": "Feature",
  "properties": {
    "gn:admin1_code":"29",
    "gn:asciiname":"Longtan",
    "gn:country_code":"CN",
    "gn:dem":1712,
    "gn:feature_class":"P",
    "gn:feature_code":"PPL",
    "gn:name":"Longtan",
    "gn:population":0,
    "gn:timezone":"Asia/Shanghai",
    "iso:country":"CN",
    "name:zho_x_preferred":[
        "\u9f99\u6f6d"
    ],
    "wof:name":"Longtan",
    "wof:placetype":"locality"
},
  "geometry": {"coordinates":[103.23180000000001,24.72578],"type":"Point"}
}