{
  "type": "Feature",
  "properties": {
    "gn:admin1_code":"4.0",
    "gn:asciiname":"Chaduitou",
    "gn:country_code":"CN",
    "gn:dem":17,
    "gn:feature_class":"P",
    "gn:feature_code":"PPL",
    "gn:name":"Chaduitou",
    "gn:population":0,
    "gn:timezone":"Asia/Shanghai",
    "iso:country":"CN",
    "name:zho_x_preferred":[
        "\u5c94\u5806\u5934"
    ],
    "wof:name":"Chaduitou",
    "wof:placetype":"locality"
},
  "geometry": {"coordinates":[118.98,33.5988],"type":"Point"}
}