{
  "type": "Feature",
  "properties": {
    "gn:admin1_code":"06",
    "gn:asciiname":"Zhenqin",
    "gn:country_code":"CN",
    "gn:dem":4271,
    "gn:feature_class":"P",
    "gn:feature_code":"PPL",
    "gn:name":"Zhenqin",
    "gn:population":0,
    "gn:timezone":"Asia/Urumqi",
    "iso:country":"CN",
    "name:bod_x_preferred":[
        "\u0f66\u0f92\u0fb2\u0f74\u0f56\u0f0b\u0f56\u0f62\u0f92\u0fb1\u0f74\u0f51\u0f0b\u0f51\u0f42\u0f7c\u0f53"
    ],
    "name:und_x_variant":[
        "Zhubgy\u00fcgoin"
    ],
    "name:zho_x_preferred":[
        "\u73cd\u79e6"
    ],
    "wof:name":"Zhenqin",
    "wof:placetype":"locality"
},
  "geometry": {"coordinates":[97.29783999999999,33.41504],"type":"Point"}
}