{
  "type": "Feature",
  "properties": {
    "gn:admin1_code":"24",
    "gn:asciiname":"Langzhuang",
    "gn:country_code":"CN",
    "gn:dem":1407,
    "gn:feature_class":"P",
    "gn:feature_code":"PPL",
    "gn:name":"Langzhuang",
    "gn:population":0,
    "gn:timezone":"Asia/Shanghai",
    "iso:country":"CN",
    "name:und_x_variant":[
        "Lang-chia-chuang",
        "Langjiazhuang",
        "Langzhuang",
        "\u90ce\u5e84"
    ],
    "wof:name":"Langzhuang",
    "wof:placetype":"locality"
},
  "geometry": {"coordinates":[113.38199,39.04511],"type":"Point"}
}