{
  "type": "Feature",
  "properties": {
    "gn:admin1_code":"12.0",
    "gn:asciiname":"Shangshuikou",
    "gn:country_code":"CN",
    "gn:dem":37,
    "gn:feature_class":"P",
    "gn:feature_code":"PPL",
    "gn:name":"Shangshuikou",
    "gn:population":0,
    "gn:timezone":"Asia/Shanghai",
    "iso:country":"CN",
    "name:zho_x_preferred":[
        "\u4e0a\u6c34\u53e3"
    ],
    "wof:name":"Shangshuikou",
    "wof:placetype":"locality"
},
  "geometry": {"coordinates":[114.58557,30.02647],"type":"Point"}
}