{
  "type": "Feature",
  "properties": {
    "gn:admin1_code":"29.0",
    "gn:asciiname":"Shibi",
    "gn:country_code":"CN",
    "gn:dem":2040,
    "gn:feature_class":"P",
    "gn:feature_code":"PPL",
    "gn:name":"Shibi",
    "gn:population":0,
    "gn:timezone":"Asia/Shanghai",
    "iso:country":"CN",
    "name:ceb_x_preferred":[
        "Shibi"
    ],
    "name:deu_x_preferred":[
        "Shibi"
    ],
    "name:swe_x_preferred":[
        "Shibi"
    ],
    "name:zho_x_preferred":[
        "\u77f3\u58c1"
    ],
    "wof:name":"Shibi",
    "wof:placetype":"locality"
},
  "geometry": {"coordinates":[100.295,25.6062],"type":"Point"}
}