{
  "type": "Feature",
  "properties": {
    "gn:admin1_code":"4.0",
    "gn:asciiname":"Lengjia",
    "gn:country_code":"CN",
    "gn:dem":7,
    "gn:feature_class":"P",
    "gn:feature_code":"PPL",
    "gn:name":"Lengjia",
    "gn:population":0,
    "gn:timezone":"Asia/Shanghai",
    "iso:country":"CN",
    "name:zho_x_preferred":[
        "\u51b7\u5bb6"
    ],
    "wof:name":"Lengjia",
    "wof:placetype":"locality"
},
  "geometry": {"coordinates":[119.77956,32.05552],"type":"Point"}
}