{
  "type": "Feature",
  "properties": {
    "gn:admin1_code":"5.0",
    "gn:asciiname":"Qianhuanzidong",
    "gn:country_code":"CN",
    "gn:dem":193,
    "gn:feature_class":"P",
    "gn:feature_code":"PPL",
    "gn:name":"Qianhuanzidong",
    "gn:population":0,
    "gn:timezone":"Asia/Shanghai",
    "iso:country":"CN",
    "name:zho_x_preferred":[
        "\u524d\u737e\u5b50\u6d1e"
    ],
    "wof:name":"Qianhuanzidong",
    "wof:placetype":"locality"
},
  "geometry": {"coordinates":[124.11429,43.94129],"type":"Point"}
}