{
  "type": "Feature",
  "properties": {
    "gn:admin1_code":"4.0",
    "gn:asciiname":"Shangzhuangcun",
    "gn:country_code":"CN",
    "gn:dem":10,
    "gn:feature_class":"P",
    "gn:feature_code":"PPL",
    "gn:name":"Shangzhuangcun",
    "gn:population":0,
    "gn:timezone":"Asia/Shanghai",
    "iso:country":"CN",
    "name:zho_x_preferred":[
        "\u5c1a\u5e84\u6751"
    ],
    "wof:name":"Shangzhuangcun",
    "wof:placetype":"locality"
},
  "geometry": {"coordinates":[118.86388999999998,34.13953],"type":"Point"}
}