{
  "type": "Feature",
  "properties": {
    "gn:admin1_code":"3.0",
    "gn:asciiname":"Qiaotou Wangjia",
    "gn:country_code":"CN",
    "gn:dem":73,
    "gn:feature_class":"P",
    "gn:feature_code":"PPL",
    "gn:name":"Qiaotou Wangjia",
    "gn:population":0,
    "gn:timezone":"Asia/Shanghai",
    "iso:country":"CN",
    "name:zho_x_preferred":[
        "\u6865\u5934\u738b\u5bb6"
    ],
    "wof:name":"Qiaotou Wangjia",
    "wof:placetype":"locality"
},
  "geometry": {"coordinates":[117.04576000000002,28.10581],"type":"Point"}
}