{
  "type": "Feature",
  "properties": {
    "gn:admin1_code":"12.0",
    "gn:asciiname":"Matangjiao",
    "gn:country_code":"CN",
    "gn:dem":36,
    "gn:feature_class":"P",
    "gn:feature_code":"PPL",
    "gn:name":"Matangjiao",
    "gn:population":0,
    "gn:timezone":"Asia/Shanghai",
    "iso:country":"CN",
    "name:zho_x_preferred":[
        "Matangjiao"
    ],
    "name:zho_x_variant":[
        "\u9a6c\u5858\u89d2"
    ],
    "wof:name":"Matangjiao",
    "wof:placetype":"locality"
},
  "geometry": {"coordinates":[115.04828000000001,29.87345],"type":"Point"}
}