{
  "type": "Feature",
  "properties": {
    "gn:admin1_code":"14.0",
    "gn:asciiname":"Jiesong",
    "gn:country_code":"CN",
    "gn:dem":4586,
    "gn:feature_class":"P",
    "gn:feature_code":"PPL",
    "gn:name":"Jiesong",
    "gn:population":0,
    "gn:timezone":"Asia/Urumqi",
    "iso:country":"CN",
    "name:zho_x_preferred":[
        "\u6770\u677e"
    ],
    "wof:name":"Jiesong",
    "wof:placetype":"locality"
},
  "geometry": {"coordinates":[92.58804000000001,31.40353],"type":"Point"}
}