{
  "type": "Feature",
  "properties": {
    "gn:admin1_code":"8.0",
    "gn:asciiname":"Shuangxincun",
    "gn:country_code":"CN",
    "gn:dem":169,
    "gn:feature_class":"P",
    "gn:feature_code":"PPL",
    "gn:name":"Shuangxincun",
    "gn:population":0,
    "gn:timezone":"Asia/Shanghai",
    "iso:country":"CN",
    "name:zho_x_preferred":[
        "\u53cc\u65b0\u6751"
    ],
    "wof:name":"Shuangxincun",
    "wof:placetype":"locality"
},
  "geometry": {"coordinates":[130.00282000000001,45.80361],"type":"Point"}
}