{
  "type": "Feature",
  "properties": {
    "gn:admin1_code":"6.0",
    "gn:asciiname":"Re'aige",
    "gn:country_code":"CN",
    "gn:dem":3968,
    "gn:feature_class":"P",
    "gn:feature_code":"PPL",
    "gn:name":"Re\u2019aige",
    "gn:population":0,
    "gn:timezone":"Asia/Urumqi",
    "iso:country":"CN",
    "name:und_x_variant":[
        "Re\u2019aige"
    ],
    "name:zho_x_preferred":[
        "\u70ed\u57c3\u683c"
    ],
    "wof:name":"Re'aige",
    "wof:placetype":"locality"
},
  "geometry": {"coordinates":[97.2449,32.2055],"type":"Point"}
}