{
  "type": "Feature",
  "properties": {
    "gn:admin1_code":"15.0",
    "gn:asciiname":"Xiaoqingyang",
    "gn:country_code":"CN",
    "gn:dem":2887,
    "gn:feature_class":"P",
    "gn:feature_code":"PPL",
    "gn:name":"Xiaoqingyang",
    "gn:population":0,
    "gn:timezone":"Asia/Shanghai",
    "iso:country":"CN",
    "name:zho_x_preferred":[
        "\u5c0f\u9752\u7f8a"
    ],
    "wof:name":"Xiaoqingyang",
    "wof:placetype":"locality"
},
  "geometry": {"coordinates":[97.9529,39.58],"type":"Point"}
}