{
  "type": "Feature",
  "properties": {
    "gn:admin1_code":"29.0",
    "gn:asciiname":"Laoyaozhai",
    "gn:country_code":"CN",
    "gn:dem":1368,
    "gn:feature_class":"P",
    "gn:feature_code":"PPL",
    "gn:name":"Laoyaozhai",
    "gn:population":0,
    "gn:timezone":"Asia/Shanghai",
    "iso:country":"CN",
    "name:zho_x_preferred":[
        "\u8001\u59da\u5be8"
    ],
    "wof:name":"Laoyaozhai",
    "wof:placetype":"locality"
},
  "geometry": {"coordinates":[101.09399999999999,23.0411],"type":"Point"}
}