{
  "type": "Feature",
  "properties": {
    "gn:admin1_code":"33.0",
    "gn:asciiname":"Zijin",
    "gn:country_code":"CN",
    "gn:dem":648,
    "gn:feature_class":"P",
    "gn:feature_code":"PPL",
    "gn:name":"Zijin",
    "gn:population":0,
    "gn:timezone":"Asia/Shanghai",
    "iso:country":"CN",
    "name:zho_x_preferred":[
        "\u7d2b\u91d1"
    ],
    "wof:name":"Zijin",
    "wof:placetype":"locality"
},
  "geometry": {"coordinates":[109.42906000000001,31.23243],"type":"Point"}
}