{
  "type": "Feature",
  "properties": {
    "gn:admin1_code":"18",
    "gn:asciiname":"Xishui",
    "gn:country_code":"CN",
    "gn:dem":758,
    "gn:feature_class":"P",
    "gn:feature_code":"PPL",
    "gn:name":"Xishui",
    "gn:population":0,
    "gn:timezone":"Asia/Shanghai",
    "iso:country":"CN",
    "name:deu_x_preferred":[
        "Xishui"
    ],
    "name:fra_x_preferred":[
        "Xishui"
    ],
    "name:kor_x_preferred":[
        "\uc2dc\uc218\uc774\ud604"
    ],
    "name:nor_x_preferred":[
        "Xishui"
    ],
    "name:rus_x_preferred":[
        "\u0421\u0438\u0448\u0443\u0439"
    ],
    "name:swe_x_preferred":[
        "Xishui"
    ],
    "name:zho_x_preferred":[
        "\u6eaa\u6c34"
    ],
    "wof:name":"Xishui",
    "wof:placetype":"locality"
},
  "geometry": {"coordinates":[107.167,27.7008],"type":"Point"}
}