{
  "type": "Feature",
  "properties": {
    "gn:country":"CN",
    "gn:fcode":"PPLX",
    "gn:pop":123,
    "iso:country":"CN",
    "qs:name":"Htunstar",
    "qs:photos_9r":0,
    "qs:photos_sr":0,
    "qs:pop_sr":"1",
    "wof:name":"Htunstar",
    "wof:placetype":"neighbourhood",
    "wof:population":123
},
  "geometry": {"coordinates":[108.30837,22.81764],"type":"Point"}
}