{
  "type": "Feature",
  "properties": {
    "gn:admin1_code":"8.0",
    "gn:asciiname":"Sandao Linchang",
    "gn:country_code":"CN",
    "gn:dem":239,
    "gn:feature_class":"P",
    "gn:feature_code":"PPLF",
    "gn:name":"Sandao Linchang",
    "gn:population":0,
    "gn:timezone":"Asia/Shanghai",
    "iso:country":"CN",
    "name:zho_x_preferred":[
        "\u4e09\u9053\u6797\u573a"
    ],
    "wof:name":"Sandao Linchang",
    "wof:placetype":"locality"
},
  "geometry": {"coordinates":[129.98658999999998,47.31093],"type":"Point"}
}