{
  "type": "Feature",
  "properties": {
    "gn:admin1_code":"10",
    "gn:asciiname":"Sanbozi",
    "gn:country_code":"CN",
    "gn:dem":249,
    "gn:feature_class":"P",
    "gn:feature_code":"PPL",
    "gn:name":"Sanbozi",
    "gn:population":0,
    "gn:timezone":"Asia/Shanghai",
    "iso:country":"CN",
    "name:und_x_variant":[
        "San-po-tzu",
        "Sanbozi"
    ],
    "name:zho_x_preferred":[
        "\u4e09\u62e8\u5b50"
    ],
    "wof:name":"Sanbozi",
    "wof:placetype":"locality"
},
  "geometry": {"coordinates":[117.58651,40.22371],"type":"Point"}
}