{
  "type": "Feature",
  "properties": {
    "gn:admin1_code":"8.0",
    "gn:asciiname":"Baisicun",
    "gn:country_code":"CN",
    "gn:dem":152,
    "gn:feature_class":"P",
    "gn:feature_code":"PPL",
    "gn:name":"Baisicun",
    "gn:population":0,
    "gn:timezone":"Asia/Shanghai",
    "iso:country":"CN",
    "name:zho_x_preferred":[
        "\u767d\u56db\u6751"
    ],
    "wof:name":"Baisicun",
    "wof:placetype":"locality"
},
  "geometry": {"coordinates":[126.41273,46.78422],"type":"Point"}
}