{
  "type": "Feature",
  "properties": {
    "gn:admin1_code":"29",
    "gn:asciiname":"Changshang",
    "gn:country_code":"CN",
    "gn:dem":1714,
    "gn:feature_class":"P",
    "gn:feature_code":"PPL",
    "gn:name":"Changshang",
    "gn:population":0,
    "gn:timezone":"Asia/Shanghai",
    "iso:country":"CN",
    "name:zho_x_preferred":[
        "\u5382\u4e0a"
    ],
    "wof:name":"Changshang",
    "wof:placetype":"locality"
},
  "geometry": {"coordinates":[102.301,24.1239],"type":"Point"}
}