{
  "type": "Feature",
  "properties": {
    "gn:admin1_code":"32.0",
    "gn:asciiname":"Sijia Dayuanzi",
    "gn:country_code":"CN",
    "gn:dem":658,
    "gn:feature_class":"P",
    "gn:feature_code":"PPL",
    "gn:name":"Sijia Dayuanzi",
    "gn:population":0,
    "gn:timezone":"Asia/Shanghai",
    "iso:country":"CN",
    "name:zho_x_preferred":[
        "\u53f8\u5bb6\u5927\u9662\u5b50"
    ],
    "wof:name":"Sijia Dayuanzi",
    "wof:placetype":"locality"
},
  "geometry": {"coordinates":[104.819,31.8478],"type":"Point"}
}