{
  "type": "Feature",
  "properties": {
    "gn:admin1_code":"3.0",
    "gn:asciiname":"Suoyitang",
    "gn:country_code":"CN",
    "gn:dem":300,
    "gn:feature_class":"P",
    "gn:feature_code":"PPL",
    "gn:name":"Suoyitang",
    "gn:population":0,
    "gn:timezone":"Asia/Shanghai",
    "iso:country":"CN",
    "name:zho_x_preferred":[
        "\u84d1\u8863\u5858"
    ],
    "wof:name":"Suoyitang",
    "wof:placetype":"locality"
},
  "geometry": {"coordinates":[115.324,24.9537],"type":"Point"}
}