{
  "type": "Feature",
  "properties": {
    "gn:admin1_code":"10.0",
    "gn:asciiname":"Songshutai",
    "gn:country_code":"CN",
    "gn:dem":326,
    "gn:feature_class":"P",
    "gn:feature_code":"PPL",
    "gn:name":"Songshutai",
    "gn:population":0,
    "gn:timezone":"Asia/Shanghai",
    "iso:country":"CN",
    "name:zho_x_preferred":[
        "\u677e\u6811\u53f0"
    ],
    "wof:name":"Songshutai",
    "wof:placetype":"locality"
},
  "geometry": {"coordinates":[114.94244999999999,39.05295],"type":"Point"}
}