{
  "type": "Feature",
  "properties": {
    "gn:admin1_code":"2.0",
    "gn:asciiname":"Xinmeizhou",
    "gn:country_code":"CN",
    "gn:dem":42,
    "gn:feature_class":"P",
    "gn:feature_code":"PPL",
    "gn:name":"Xinmeizhou",
    "gn:population":0,
    "gn:timezone":"Asia/Shanghai",
    "iso:country":"CN",
    "name:zho_x_preferred":[
        "\u65b0\u7f8e\u5dde"
    ],
    "wof:name":"Xinmeizhou",
    "wof:placetype":"locality"
},
  "geometry": {"coordinates":[120.29297,27.82937],"type":"Point"}
}