{
  "type": "Feature",
  "properties": {
    "gn:admin1_code":"5.0",
    "gn:asciiname":"Xinsandui",
    "gn:country_code":"CN",
    "gn:dem":666,
    "gn:feature_class":"P",
    "gn:feature_code":"PPLF",
    "gn:name":"Xinsandui",
    "gn:population":0,
    "gn:timezone":"Asia/Shanghai",
    "iso:country":"CN",
    "name:und_x_variant":[
        "\u65b0\u4e09\u961f"
    ],
    "wof:name":"Xinsandui",
    "wof:placetype":"locality"
},
  "geometry": {"coordinates":[126.78175,41.9197],"type":"Point"}
}