{
  "type": "Feature",
  "properties": {
    "gn:admin1_code":"16.0",
    "gn:asciiname":"Zhushatang",
    "gn:country_code":"CN",
    "gn:dem":81,
    "gn:feature_class":"P",
    "gn:feature_code":"PPL",
    "gn:name":"Zhushatang",
    "gn:population":0,
    "gn:timezone":"Asia/Shanghai",
    "iso:country":"CN",
    "name:zho_x_preferred":[
        "\u6731\u6c99\u5858"
    ],
    "wof:name":"Zhushatang",
    "wof:placetype":"locality"
},
  "geometry": {"coordinates":[110.23699999999999,22.1406],"type":"Point"}
}