{
  "type": "Feature",
  "properties": {
    "gn:admin1_code":"25.0",
    "gn:asciiname":"Dawu",
    "gn:country_code":"CN",
    "gn:dem":16,
    "gn:feature_class":"P",
    "gn:feature_code":"PPL",
    "gn:name":"Dawu",
    "gn:population":0,
    "gn:timezone":"Asia/Shanghai",
    "iso:country":"CN",
    "name:ceb_x_preferred":[
        "Dawu"
    ],
    "name:deu_x_preferred":[
        "Dawu"
    ],
    "name:eus_x_preferred":[
        "Dawu"
    ],
    "name:fra_x_preferred":[
        "Dawu"
    ],
    "name:nor_x_preferred":[
        "Dawu"
    ],
    "name:swe_x_preferred":[
        "Dawu"
    ],
    "name:zho_x_preferred":[
        "\u5927\u5c4b"
    ],
    "wof:name":"Dawu",
    "wof:placetype":"locality"
},
  "geometry": {"coordinates":[121.23667,37.42731],"type":"Point"}
}