{
  "type": "Feature",
  "properties": {
    "gn:admin1_code":"20.0",
    "gn:asciiname":"Kaoxian",
    "gn:country_code":"CN",
    "gn:dem":200,
    "gn:feature_class":"P",
    "gn:feature_code":"PPL",
    "gn:name":"Kaoxian",
    "gn:population":0,
    "gn:timezone":"Asia/Shanghai",
    "iso:country":"CN",
    "name:zho_x_preferred":[
        "\u9760\u9c9c"
    ],
    "wof:name":"Kaoxian",
    "wof:placetype":"locality"
},
  "geometry": {"coordinates":[123.58438999999998,48.06197],"type":"Point"}
}