{
  "type": "Feature",
  "properties": {
    "gn:admin1_code":"1.0",
    "gn:asciiname":"Laozhuangcun",
    "gn:country_code":"CN",
    "gn:dem":59,
    "gn:feature_class":"P",
    "gn:feature_code":"PPL",
    "gn:name":"Laozhuangcun",
    "gn:population":0,
    "gn:timezone":"Asia/Shanghai",
    "iso:country":"CN",
    "name:zho_x_preferred":[
        "\u8001\u5e84\u6751"
    ],
    "wof:name":"Laozhuangcun",
    "wof:placetype":"locality"
},
  "geometry": {"coordinates":[117.127,32.15099],"type":"Point"}
}