{
  "type": "Feature",
  "properties": {
    "gn:admin1_code":"5.0",
    "gn:asciiname":"Yanpao",
    "gn:country_code":"CN",
    "gn:dem":274,
    "gn:feature_class":"P",
    "gn:feature_code":"PPL",
    "gn:name":"Yanpao",
    "gn:population":0,
    "gn:timezone":"Asia/Shanghai",
    "iso:country":"CN",
    "name:und_x_variant":[
        "\u6cbf\u6ce1"
    ],
    "wof:name":"Yanpao",
    "wof:placetype":"locality"
},
  "geometry": {"coordinates":[126.46299,41.36437],"type":"Point"}
}