{
  "type": "Feature",
  "properties": {
    "gn:admin1_code":"25",
    "gn:asciiname":"Nanzhouzhuang",
    "gn:country_code":"CN",
    "gn:dem":58,
    "gn:feature_class":"P",
    "gn:feature_code":"PPL",
    "gn:name":"Nanzhouzhuang",
    "gn:population":0,
    "gn:timezone":"Asia/Shanghai",
    "iso:country":"CN",
    "name:zho_x_preferred":[
        "\u5357\u5468\u5e84"
    ],
    "wof:name":"Nanzhouzhuang",
    "wof:placetype":"locality"
},
  "geometry": {"coordinates":[115.32899999999999,35.1548],"type":"Point"}
}