{
  "type": "Feature",
  "properties": {
    "gn:admin1_code":"12.0",
    "gn:asciiname":"Payangdong",
    "gn:country_code":"CN",
    "gn:dem":1422,
    "gn:feature_class":"P",
    "gn:feature_code":"PPL",
    "gn:name":"Payangdong",
    "gn:population":0,
    "gn:timezone":"Asia/Shanghai",
    "iso:country":"CN",
    "name:zho_x_preferred":[
        "\u722c\u7f8a\u6d1e"
    ],
    "wof:name":"Payangdong",
    "wof:placetype":"locality"
},
  "geometry": {"coordinates":[110.16410999999999,31.59812],"type":"Point"}
}