{
  "type": "Feature",
  "properties": {
    "gn:admin1_code":"15.0",
    "gn:asciiname":"Wangwan",
    "gn:country_code":"CN",
    "gn:dem":1366,
    "gn:feature_class":"P",
    "gn:feature_code":"PPL",
    "gn:name":"Wangwan",
    "gn:population":0,
    "gn:timezone":"Asia/Shanghai",
    "iso:country":"CN",
    "name:zho_x_preferred":[
        "\u738b\u6e7e"
    ],
    "wof:name":"Wangwan",
    "wof:placetype":"locality"
},
  "geometry": {"coordinates":[107.285,35.9364],"type":"Point"}
}