{
  "type": "Feature",
  "properties": {
    "gn:admin1_code":"13.0",
    "gn:asciiname":"Shuimogou",
    "gn:country_code":"CN",
    "gn:dem":867,
    "gn:feature_class":"P",
    "gn:feature_code":"PPLA3",
    "gn:name":"Shuimogou",
    "gn:population":0,
    "gn:timezone":"Asia/Urumqi",
    "iso:country":"CN",
    "name:und_x_variant":[
        "Shui-mo-kou",
        "Shuimogou",
        "Shuimogoucun",
        "\u6c34\u78e8\u6c9f\u6751",
        "Shuimogou Qu"
    ],
    "name:zho_x_preferred":[
        "\u6c34\u78e8\u6c9f"
    ],
    "name:zho_x_variant":[
        "\u6c34\u78e8\u6c9f\u533a"
    ],
    "wof:name":"Shuimogou",
    "wof:placetype":"locality"
},
  "geometry": {"coordinates":[87.6382,43.82856],"type":"Point"}
}