{
  "type": "Feature",
  "properties": {
    "gn:admin1_code":"15.0",
    "gn:asciiname":"Houjiangtai",
    "gn:country_code":"CN",
    "gn:dem":2472,
    "gn:feature_class":"P",
    "gn:feature_code":"PPL",
    "gn:name":"Houjiangtai",
    "gn:population":0,
    "gn:timezone":"Asia/Shanghai",
    "iso:country":"CN",
    "name:zho_x_preferred":[
        "\u540e\u5c06\u53f0"
    ],
    "wof:name":"Houjiangtai",
    "wof:placetype":"locality"
},
  "geometry": {"coordinates":[103.34399999999999,35.3502],"type":"Point"}
}