{
  "type": "Feature",
  "properties": {
    "gn:admin1_code":"5.0",
    "gn:asciiname":"Dabahao",
    "gn:country_code":"CN",
    "gn:dem":165,
    "gn:feature_class":"P",
    "gn:feature_code":"PPL",
    "gn:name":"Dabahao",
    "gn:population":0,
    "gn:timezone":"Asia/Shanghai",
    "iso:country":"CN",
    "name:zho_x_preferred":[
        "\u5927\u516b\u53f7"
    ],
    "wof:name":"Dabahao",
    "wof:placetype":"locality"
},
  "geometry": {"coordinates":[123.66426,44.18653],"type":"Point"}
}