{
  "type": "Feature",
  "properties": {
    "gn:admin1_code":"12.0",
    "gn:asciiname":"Maluchi",
    "gn:country_code":"CN",
    "gn:dem":960,
    "gn:feature_class":"P",
    "gn:feature_code":"PPL",
    "gn:name":"Maluchi",
    "gn:population":0,
    "gn:timezone":"Asia/Shanghai",
    "iso:country":"CN",
    "name:zho_x_preferred":[
        "\u9a6c\u9e7f\u6c60"
    ],
    "wof:name":"Maluchi",
    "wof:placetype":"locality"
},
  "geometry": {"coordinates":[109.02502,30.08042],"type":"Point"}
}