{
  "type": "Feature",
  "properties": {
    "gn:admin1_code":"33.0",
    "gn:asciiname":"Qiaotou Shizui",
    "gn:country_code":"CN",
    "gn:dem":484,
    "gn:feature_class":"P",
    "gn:feature_code":"PPL",
    "gn:name":"Qiaotou Shizui",
    "gn:population":0,
    "gn:timezone":"Asia/Shanghai",
    "iso:country":"CN",
    "name:zho_x_preferred":[
        "\u6865\u5934\u77f3\u5480"
    ],
    "wof:name":"Qiaotou Shizui",
    "wof:placetype":"locality"
},
  "geometry": {"coordinates":[107.71925,30.45511],"type":"Point"}
}