{
  "type": "Feature",
  "properties": {
    "gn:admin1_code":"16.0",
    "gn:asciiname":"Nongheng",
    "gn:country_code":"CN",
    "gn:dem":1097,
    "gn:feature_class":"P",
    "gn:feature_code":"PPL",
    "gn:name":"Nongheng",
    "gn:population":0,
    "gn:timezone":"Asia/Shanghai",
    "iso:country":"CN",
    "name:zho_x_preferred":[
        "\u5f04\u6052"
    ],
    "wof:name":"Nongheng",
    "wof:placetype":"locality"
},
  "geometry": {"coordinates":[104.944,24.5632],"type":"Point"}
}