{
  "type": "Feature",
  "properties": {
    "gn:admin1_code":"11",
    "gn:asciiname":"Jiangya",
    "gn:country_code":"CN",
    "gn:dem":153,
    "gn:feature_class":"P",
    "gn:feature_code":"PPLA4",
    "gn:name":"Jiangya",
    "gn:population":0,
    "gn:timezone":"Asia/Shanghai",
    "iso:country":"CN",
    "name:und_x_variant":[
        "Chiang-ya",
        "Jiangya Zhen",
        "Jiangya"
    ],
    "name:zho_x_preferred":[
        "\u6c5f\u57ad"
    ],
    "name:zho_x_variant":[
        "\u6c5f\u57ad\u9547"
    ],
    "wof:name":"Jiangya",
    "wof:placetype":"locality"
},
  "geometry": {"coordinates":[110.76382,29.50428],"type":"Point"}
}