{
  "type": "Feature",
  "properties": {
    "gn:admin1_code":"04",
    "gn:asciiname":"Gaotangcun",
    "gn:country_code":"CN",
    "gn:dem":30,
    "gn:feature_class":"P",
    "gn:feature_code":"PPL",
    "gn:name":"Gaotangcun",
    "gn:population":0,
    "gn:timezone":"Asia/Shanghai",
    "iso:country":"CN",
    "name:und_x_variant":[
        "Kao-t\u2019an-kou",
        "Gaotanggou",
        "Kao-t\u2019ang-kou",
        "Gaotang",
        "Gaotangcun"
    ],
    "name:zho_x_preferred":[
        "\u9ad8\u5858"
    ],
    "name:zho_x_variant":[
        "\u9ad8\u5858\u6751"
    ],
    "wof:name":"Gaotangcun",
    "wof:placetype":"locality"
},
  "geometry": {"coordinates":[118.47113,34.3689],"type":"Point"}
}