{
  "type": "Feature",
  "properties": {
    "gn:admin1_code":"29.0",
    "gn:asciiname":"Pula",
    "gn:country_code":"CN",
    "gn:dem":1975,
    "gn:feature_class":"P",
    "gn:feature_code":"PPL",
    "gn:name":"Pula",
    "gn:population":0,
    "gn:timezone":"Asia/Shanghai",
    "iso:country":"CN",
    "name:zho_x_preferred":[
        "\u666e\u62c9"
    ],
    "wof:name":"Pula",
    "wof:placetype":"locality"
},
  "geometry": {"coordinates":[98.5911,27.7936],"type":"Point"}
}