{
  "type": "Feature",
  "properties": {
    "gn:admin1_code":"5.0",
    "gn:asciiname":"Mijiazi",
    "gn:country_code":"CN",
    "gn:dem":445,
    "gn:feature_class":"P",
    "gn:feature_code":"PPL",
    "gn:name":"Mijiazi",
    "gn:population":0,
    "gn:timezone":"Asia/Shanghai",
    "iso:country":"CN",
    "name:und_x_variant":[
        "\u7c73\u67b6\u5b50"
    ],
    "wof:name":"Mijiazi",
    "wof:placetype":"locality"
},
  "geometry": {"coordinates":[125.96738000000001,41.50929],"type":"Point"}
}