{
  "type": "Feature",
  "properties": {
    "gn:admin1_code":"3.0",
    "gn:asciiname":"Shangfenglin",
    "gn:country_code":"CN",
    "gn:dem":96,
    "gn:feature_class":"P",
    "gn:feature_code":"PPL",
    "gn:name":"Shangfenglin",
    "gn:population":0,
    "gn:timezone":"Asia/Shanghai",
    "iso:country":"CN",
    "name:und_x_variant":[
        "\u4e0a\u67ab\u6797"
    ],
    "wof:name":"Shangfenglin",
    "wof:placetype":"locality"
},
  "geometry": {"coordinates":[115.59077000000001,29.04847],"type":"Point"}
}