{
  "type": "Feature",
  "properties": {
    "gn:admin1_code":"19.0",
    "gn:asciiname":"Wudaolingzicun",
    "gn:country_code":"CN",
    "gn:dem":295,
    "gn:feature_class":"P",
    "gn:feature_code":"PPL",
    "gn:name":"Wudaolingzicun",
    "gn:population":0,
    "gn:timezone":"Asia/Shanghai",
    "iso:country":"CN",
    "name:zho_x_preferred":[
        "\u4e94\u9053\u5cad\u5b50\u6751"
    ],
    "wof:name":"Wudaolingzicun",
    "wof:placetype":"locality"
},
  "geometry": {"coordinates":[124.961,40.9496],"type":"Point"}
}