{
  "type": "Feature",
  "properties": {
    "gn:admin1_code":"30",
    "gn:asciiname":"Houhongcun",
    "gn:country_code":"CN",
    "gn:dem":11,
    "gn:feature_class":"P",
    "gn:feature_code":"PPL",
    "gn:name":"Houhongcun",
    "gn:population":0,
    "gn:timezone":"Asia/Urumqi",
    "iso:country":"CN",
    "name:und_x_variant":[
        "Hou-hung",
        "Houhongcun",
        "\u540e\u6d2a\u6751"
    ],
    "name:zho_x_preferred":[
        "\u540e\u6d2a\u6751"
    ],
    "wof:name":"Houhongcun",
    "wof:placetype":"locality"
},
  "geometry": {"coordinates":[109.90917,20.49861],"type":"Point"}
}