{
  "type": "Feature",
  "properties": {
    "gn:admin1_code":"16.0",
    "gn:asciiname":"Pengping",
    "gn:country_code":"CN",
    "gn:dem":812,
    "gn:feature_class":"P",
    "gn:feature_code":"PPL",
    "gn:name":"Pengping",
    "gn:population":0,
    "gn:timezone":"Asia/Shanghai",
    "iso:country":"CN",
    "name:zho_x_preferred":[
        "\u670b\u5e73"
    ],
    "wof:name":"Pengping",
    "wof:placetype":"locality"
},
  "geometry": {"coordinates":[108.729,25.3406],"type":"Point"}
}