{
  "type": "Feature",
  "properties": {
    "gn:admin1_code":"11.0",
    "gn:asciiname":"Luogushi",
    "gn:country_code":"CN",
    "gn:dem":404,
    "gn:feature_class":"P",
    "gn:feature_code":"PPL",
    "gn:name":"Luogushi",
    "gn:population":0,
    "gn:timezone":"Asia/Shanghai",
    "iso:country":"CN",
    "name:zho_x_preferred":[
        "\u7f57\u53e4\u77f3"
    ],
    "wof:name":"Luogushi",
    "wof:placetype":"locality"
},
  "geometry": {"coordinates":[110.95399,27.48122],"type":"Point"}
}