{
  "type": "Feature",
  "properties": {
    "gn:admin1_code":"32.0",
    "gn:asciiname":"Ruiwa",
    "gn:country_code":"CN",
    "gn:dem":2579,
    "gn:feature_class":"P",
    "gn:feature_code":"PPL",
    "gn:name":"Ruiwa",
    "gn:population":0,
    "gn:timezone":"Asia/Shanghai",
    "iso:country":"CN",
    "name:swa_x_preferred":[
        "Ruiwa"
    ],
    "name:zho_x_preferred":[
        "\u9510\u54c7"
    ],
    "wof:name":"Ruiwa",
    "wof:placetype":"locality"
},
  "geometry": {"coordinates":[99.14190000000001,29.2751],"type":"Point"}
}