{
  "type": "Feature",
  "properties": {
    "gn:admin1_code":"30.0",
    "gn:asciiname":"Huangzhu'an",
    "gn:country_code":"CN",
    "gn:dem":678,
    "gn:feature_class":"P",
    "gn:feature_code":"PPL",
    "gn:name":"Huangzhu\u2019an",
    "gn:population":0,
    "gn:timezone":"Asia/Shanghai",
    "iso:country":"CN",
    "name:zho_x_preferred":[
        "Huangzhu\u2019an"
    ],
    "name:zho_x_variant":[
        "\u9ec4\u7af9\u5eb5"
    ],
    "wof:name":"Huangzhu'an",
    "wof:placetype":"locality"
},
  "geometry": {"coordinates":[113.53583,25.17],"type":"Point"}
}