{
  "type": "Feature",
  "properties": {
    "gn:admin1_code":"30.0",
    "gn:asciiname":"Hudi",
    "gn:country_code":"CN",
    "gn:dem":5,
    "gn:feature_class":"P",
    "gn:feature_code":"PPL",
    "gn:name":"Hudi",
    "gn:population":0,
    "gn:timezone":"Asia/Shanghai",
    "iso:country":"CN",
    "name:fas_x_preferred":[
        "\u0647\u0648\u062f\u06cc"
    ],
    "name:msa_x_preferred":[
        "Hudi"
    ],
    "name:ukr_x_preferred":[
        "\u0413\u0443\u0434\u0456"
    ],
    "name:zho_x_preferred":[
        "\u7b0f\u5e95"
    ],
    "wof:name":"Hudi",
    "wof:placetype":"locality"
},
  "geometry": {"coordinates":[115.59815999999999,22.92671],"type":"Point"}
}