{
  "type": "Feature",
  "properties": {
    "gn:admin1_code":"30",
    "gn:asciiname":"Daxingshan",
    "gn:country_code":"CN",
    "gn:dem":369,
    "gn:feature_class":"P",
    "gn:feature_code":"PPL",
    "gn:name":"Daxingshan",
    "gn:population":0,
    "gn:timezone":"Asia/Shanghai",
    "iso:country":"CN",
    "name:und_x_variant":[
        "\u5927\u884c\u5c71",
        "Daxingshan"
    ],
    "name:zho_x_preferred":[
        "\u5927\u884c\u5c71"
    ],
    "wof:name":"Daxingshan",
    "wof:placetype":"locality"
},
  "geometry": {"coordinates":[115.85164,24.27352],"type":"Point"}
}