{
  "type": "Feature",
  "properties": {
    "gn:admin1_code":"1.0",
    "gn:asciiname":"Dangshan Linchang",
    "gn:country_code":"CN",
    "gn:dem":46,
    "gn:feature_class":"P",
    "gn:feature_code":"PPLF",
    "gn:name":"Dangshan Linchang",
    "gn:population":0,
    "gn:timezone":"Asia/Shanghai",
    "iso:country":"CN",
    "wof:name":"Dangshan Linchang",
    "wof:placetype":"locality"
},
  "geometry": {"coordinates":[116.40000000000001,34.61667],"type":"Point"}
}