{
  "type": "Feature",
  "properties": {
    "gn:admin1_code":"3.0",
    "gn:asciiname":"Paishangcun",
    "gn:country_code":"CN",
    "gn:dem":242,
    "gn:feature_class":"P",
    "gn:feature_code":"PPL",
    "gn:name":"Paishangcun",
    "gn:population":0,
    "gn:timezone":"Asia/Shanghai",
    "iso:country":"CN",
    "name:zho_x_preferred":[
        "\u6392\u4e0a\u6751"
    ],
    "wof:name":"Paishangcun",
    "wof:placetype":"locality"
},
  "geometry": {"coordinates":[117.10899999999999,27.719],"type":"Point"}
}