{
  "type": "Feature",
  "properties": {
    "gn:admin1_code":"25",
    "gn:asciiname":"Hongxingqianjie",
    "gn:country_code":"CN",
    "gn:dem":26,
    "gn:feature_class":"P",
    "gn:feature_code":"PPL",
    "gn:name":"Hongxingqianjie",
    "gn:population":0,
    "gn:timezone":"Asia/Shanghai",
    "iso:country":"CN",
    "name:zho_x_preferred":[
        "\u7ea2\u661f\u524d\u8857"
    ],
    "wof:name":"Hongxingqianjie",
    "wof:placetype":"locality"
},
  "geometry": {"coordinates":[116.47199999999999,36.9928],"type":"Point"}
}