{
  "type": "Feature",
  "properties": {
    "gn:admin1_code":"18",
    "gn:asciiname":"Duobukuai",
    "gn:country_code":"CN",
    "gn:dem":2054,
    "gn:feature_class":"P",
    "gn:feature_code":"PPL",
    "gn:name":"Duobukuai",
    "gn:population":0,
    "gn:timezone":"Asia/Shanghai",
    "iso:country":"CN",
    "name:zho_x_preferred":[
        "\u8eb2\u5e03\u5757"
    ],
    "wof:name":"Duobukuai",
    "wof:placetype":"locality"
},
  "geometry": {"coordinates":[104.374,27.169],"type":"Point"}
}