{
  "type": "Feature",
  "properties": {
    "gn:admin1_code":"05",
    "gn:asciiname":"Shidaohe",
    "gn:cc2":"CN",
    "gn:country_code":"CN",
    "gn:dem":387,
    "gn:feature_class":"P",
    "gn:feature_code":"PPL",
    "gn:name":"Shidaohe",
    "gn:population":0,
    "gn:timezone":"Asia/Shanghai",
    "iso:country":"CN",
    "name:und_x_variant":[
        "Shih-tao-ho",
        "Shidaohe"
    ],
    "wof:name":"Shidaohe",
    "wof:placetype":"locality"
},
  "geometry": {"coordinates":[126.52556,42.63639000000001],"type":"Point"}
}