{
  "type": "Feature",
  "properties": {
    "gn:admin1_code":"2.0",
    "gn:asciiname":"Weituobang",
    "gn:country_code":"CN",
    "gn:dem":7,
    "gn:feature_class":"P",
    "gn:feature_code":"PPL",
    "gn:name":"Weituobang",
    "gn:population":0,
    "gn:timezone":"Asia/Shanghai",
    "iso:country":"CN",
    "name:und_x_variant":[
        "\u97e6\u9640\u6d5c"
    ],
    "wof:name":"Weituobang",
    "wof:placetype":"locality"
},
  "geometry": {"coordinates":[120.80513000000001,30.76094],"type":"Point"}
}