{
  "type": "Feature",
  "properties": {
    "gn:admin1_code":"18",
    "gn:asciiname":"Tuozheshangba",
    "gn:country_code":"CN",
    "gn:dem":2038,
    "gn:feature_class":"P",
    "gn:feature_code":"PPL",
    "gn:name":"Tuozheshangba",
    "gn:population":0,
    "gn:timezone":"Asia/Shanghai",
    "iso:country":"CN",
    "name:zho_x_preferred":[
        "\u6258\u7740\u4e0a\u575d"
    ],
    "wof:name":"Tuozheshangba",
    "wof:placetype":"locality"
},
  "geometry": {"coordinates":[104.661,27.2858],"type":"Point"}
}