{
  "type": "Feature",
  "properties": {
    "gn:admin1_code":"5.0",
    "gn:asciiname":"Xiaowenzi Goumen",
    "gn:country_code":"CN",
    "gn:dem":611,
    "gn:feature_class":"P",
    "gn:feature_code":"PPL",
    "gn:name":"Xiaowenzi Goumen",
    "gn:population":0,
    "gn:timezone":"Asia/Shanghai",
    "iso:country":"CN",
    "name:und_x_variant":[
        "\u5c0f\u6587\u5b57\u6c9f\u95e8"
    ],
    "wof:name":"Xiaowenzi Goumen",
    "wof:placetype":"locality"
},
  "geometry": {"coordinates":[126.01873999999999,41.39899000000001],"type":"Point"}
}