{
  "type": "Feature",
  "properties": {
    "gn:admin1_code":"4.0",
    "gn:asciiname":"Dixiang",
    "gn:country_code":"CN",
    "gn:dem":8,
    "gn:feature_class":"P",
    "gn:feature_code":"PPL",
    "gn:name":"Dixiang",
    "gn:population":0,
    "gn:timezone":"Asia/Shanghai",
    "iso:country":"CN",
    "name:zho_x_preferred":[
        "Dixiang"
    ],
    "name:zho_x_variant":[
        "\u7fdf\u5df7"
    ],
    "wof:name":"Dixiang",
    "wof:placetype":"locality"
},
  "geometry": {"coordinates":[119.20541,33.56585],"type":"Point"}
}