{
  "type": "Feature",
  "properties": {
    "gn:admin1_code":"11.0",
    "gn:asciiname":"Zaoxi",
    "gn:country_code":"CN",
    "gn:dem":479,
    "gn:feature_class":"P",
    "gn:feature_code":"PPL",
    "gn:name":"Zaoxi",
    "gn:population":0,
    "gn:timezone":"Asia/Shanghai",
    "iso:country":"CN",
    "name:zho_x_preferred":[
        "\u7682\u6eaa"
    ],
    "wof:name":"Zaoxi",
    "wof:placetype":"locality"
},
  "geometry": {"coordinates":[109.15181,27.16753],"type":"Point"}
}