{
  "type": "Feature",
  "properties": {
    "gn:admin1_code":"32.0",
    "gn:asciiname":"Piankou",
    "gn:country_code":"CN",
    "gn:dem":1029,
    "gn:feature_class":"P",
    "gn:feature_code":"PPL",
    "gn:name":"Piankou",
    "gn:population":0,
    "gn:timezone":"Asia/Shanghai",
    "iso:country":"CN",
    "name:zho_x_preferred":[
        "\u7247\u53e3"
    ],
    "wof:name":"Piankou",
    "wof:placetype":"locality"
},
  "geometry": {"coordinates":[104.14926,32.11299],"type":"Point"}
}