{
  "type": "Feature",
  "properties": {
    "gn:admin1_code":"19.0",
    "gn:asciiname":"Yanwujie",
    "gn:country_code":"CN",
    "gn:dem":103,
    "gn:feature_class":"P",
    "gn:feature_code":"PPL",
    "gn:name":"Yanwujie",
    "gn:population":0,
    "gn:timezone":"Asia/Shanghai",
    "iso:country":"CN",
    "name:zho_x_preferred":[
        "\u6f14\u6b66\u8857"
    ],
    "wof:name":"Yanwujie",
    "wof:placetype":"locality"
},
  "geometry": {"coordinates":[123.822,41.8206],"type":"Point"}
}