{
  "type": "Feature",
  "properties": {
    "gn:admin1_code":"19.0",
    "gn:asciiname":"Erzhaizi",
    "gn:country_code":"CN",
    "gn:dem":85,
    "gn:feature_class":"P",
    "gn:feature_code":"PPL",
    "gn:name":"Erzhaizi",
    "gn:population":0,
    "gn:timezone":"Asia/Shanghai",
    "iso:country":"CN",
    "name:und_x_variant":[
        "\u4e8c\u5be8\u5b50"
    ],
    "name:zho_x_preferred":[
        "\u4e8c\u5be8\u5b50"
    ],
    "wof:name":"Erzhaizi",
    "wof:placetype":"locality"
},
  "geometry": {"coordinates":[123.97461,42.53426],"type":"Point"}
}