{
  "type": "Feature",
  "properties": {
    "gn:admin1_code":"18.0",
    "gn:asciiname":"Shangfengxi",
    "gn:country_code":"CN",
    "gn:dem":479,
    "gn:feature_class":"P",
    "gn:feature_code":"PPL",
    "gn:name":"Shangfengxi",
    "gn:population":0,
    "gn:timezone":"Asia/Shanghai",
    "iso:country":"CN",
    "name:zho_x_preferred":[
        "\u4e0a\u51e4\u6eaa"
    ],
    "wof:name":"Shangfengxi",
    "wof:placetype":"locality"
},
  "geometry": {"coordinates":[108.601,27.2976],"type":"Point"}
}