{
  "type": "Feature",
  "properties": {
    "gn:admin1_code":"4.0",
    "gn:asciiname":"Mingxing",
    "gn:country_code":"CN",
    "gn:dem":10,
    "gn:feature_class":"P",
    "gn:feature_code":"PPL",
    "gn:name":"Mingxing",
    "gn:population":0,
    "gn:timezone":"Asia/Shanghai",
    "iso:country":"CN",
    "name:deu_x_preferred":[
        "Mingxing-Filmgesellschaft"
    ],
    "name:kaz_x_preferred":[
        "\u041c\u0438\u043d\u0441\u0438\u043d \u043a\u0438\u043d\u043e\u043a\u043e\u043c\u043f\u0430\u043d\u0438\u044f\u0441\u044b"
    ],
    "name:nor_x_preferred":[
        "Mingxing"
    ],
    "name:rus_x_preferred":[
        "\u041c\u0438\u043d\u0441\u0438\u043d"
    ],
    "name:swe_x_preferred":[
        "Mingxing"
    ],
    "name:zho_x_preferred":[
        "\u660e\u661f"
    ],
    "name:zho_x_variant":[
        "\u660e\u661f\u7535\u5f71\u516c\u53f8"
    ],
    "wof:name":"Mingxing",
    "wof:placetype":"locality"
},
  "geometry": {"coordinates":[119.47233,32.01413],"type":"Point"}
}