{
  "type": "Feature",
  "properties": {
    "gn:admin1_code":"15.0",
    "gn:asciiname":"Hujia Yaoxian",
    "gn:country_code":"CN",
    "gn:dem":1354,
    "gn:feature_class":"P",
    "gn:feature_code":"PPL",
    "gn:name":"Hujia Yaoxian",
    "gn:population":0,
    "gn:timezone":"Asia/Shanghai",
    "iso:country":"CN",
    "name:und_x_variant":[
        "\u80e1\u5bb6\u5d3e\u5c98"
    ],
    "wof:name":"Hujia Yaoxian",
    "wof:placetype":"locality"
},
  "geometry": {"coordinates":[107.986,36.2361],"type":"Point"}
}