{
  "type": "Feature",
  "properties": {
    "gn:admin1_code":"3.0",
    "gn:asciiname":"Beixi Huangjia",
    "gn:country_code":"CN",
    "gn:dem":63,
    "gn:feature_class":"P",
    "gn:feature_code":"PPL",
    "gn:name":"Beixi Huangjia",
    "gn:population":0,
    "gn:timezone":"Asia/Shanghai",
    "iso:country":"CN",
    "name:und_x_variant":[
        "\u5317\u6eaa\u9ec4\u5bb6"
    ],
    "wof:name":"Beixi Huangjia",
    "wof:placetype":"locality"
},
  "geometry": {"coordinates":[116.40763,27.84121],"type":"Point"}
}