{
  "type": "Feature",
  "properties": {
    "gn:admin1_code":"15.0",
    "gn:asciiname":"Laofangzi",
    "gn:country_code":"CN",
    "gn:dem":1731,
    "gn:feature_class":"P",
    "gn:feature_code":"PPL",
    "gn:name":"Laofangzi",
    "gn:population":0,
    "gn:timezone":"Asia/Shanghai",
    "iso:country":"CN",
    "name:zho_x_preferred":[
        "\u8001\u623f\u5b50"
    ],
    "wof:name":"Laofangzi",
    "wof:placetype":"locality"
},
  "geometry": {"coordinates":[104.751,32.7706],"type":"Point"}
}