{
  "type": "Feature",
  "properties": {
    "gn:admin1_code":"9.0",
    "gn:asciiname":"Sifuchang",
    "gn:country_code":"CN",
    "gn:dem":60,
    "gn:feature_class":"P",
    "gn:feature_code":"PPL",
    "gn:name":"Sifuchang",
    "gn:population":0,
    "gn:timezone":"Asia/Shanghai",
    "iso:country":"CN",
    "name:zho_x_preferred":[
        "\u56db\u4f0f\u5382"
    ],
    "wof:name":"Sifuchang",
    "wof:placetype":"locality"
},
  "geometry": {"coordinates":[114.59795,36.00308],"type":"Point"}
}