{
  "type": "Feature",
  "properties": {
    "gn:admin1_code":"29.0",
    "gn:asciiname":"Bangeshan",
    "gn:country_code":"CN",
    "gn:dem":2124,
    "gn:feature_class":"P",
    "gn:feature_code":"PPL",
    "gn:name":"Bangeshan",
    "gn:population":0,
    "gn:timezone":"Asia/Shanghai",
    "iso:country":"CN",
    "name:zho_x_preferred":[
        "\u534a\u4e2a\u5c71"
    ],
    "wof:name":"Bangeshan",
    "wof:placetype":"locality"
},
  "geometry": {"coordinates":[103.598,25.3158],"type":"Point"}
}