{
  "type": "Feature",
  "properties": {
    "gn:admin1_code":"29.0",
    "gn:asciiname":"Mideka",
    "gn:country_code":"CN",
    "gn:dem":1937,
    "gn:feature_class":"P",
    "gn:feature_code":"PPL",
    "gn:name":"Mideka",
    "gn:population":0,
    "gn:timezone":"Asia/Shanghai",
    "iso:country":"CN",
    "name:zho_x_preferred":[
        "\u7c73\u5fb7\u5361"
    ],
    "wof:name":"Mideka",
    "wof:placetype":"locality"
},
  "geometry": {"coordinates":[103.47799999999999,25.6039],"type":"Point"}
}