{
  "type": "Feature",
  "properties": {
    "gn:admin1_code":"6.0",
    "gn:asciiname":"Gashari",
    "gn:country_code":"CN",
    "gn:dem":2371,
    "gn:feature_class":"P",
    "gn:feature_code":"PPL",
    "gn:name":"Gashari",
    "gn:population":0,
    "gn:timezone":"Asia/Shanghai",
    "iso:country":"CN",
    "name:und_x_variant":[
        "\u5c15\u6c99\u65e5"
    ],
    "wof:name":"Gashari",
    "wof:placetype":"locality"
},
  "geometry": {"coordinates":[102.04407,35.61169],"type":"Point"}
}