{
  "type": "Feature",
  "properties": {
    "gn:admin1_code":"8.0",
    "gn:asciiname":"Wangfuguang",
    "gn:country_code":"CN",
    "gn:dem":185,
    "gn:feature_class":"P",
    "gn:feature_code":"PPL",
    "gn:name":"Wangfuguang",
    "gn:population":0,
    "gn:timezone":"Asia/Shanghai",
    "iso:country":"CN",
    "name:zho_x_preferred":[
        "\u738b\u798f\u5e7f"
    ],
    "wof:name":"Wangfuguang",
    "wof:placetype":"locality"
},
  "geometry": {"coordinates":[127.24621999999999,47.12858],"type":"Point"}
}