{
  "type": "Feature",
  "properties": {
    "gn:admin1_code":"24",
    "gn:asciiname":"Caocun",
    "gn:country_code":"CN",
    "gn:dem":1303,
    "gn:feature_class":"P",
    "gn:feature_code":"PPL",
    "gn:name":"Caocun",
    "gn:population":0,
    "gn:timezone":"Asia/Shanghai",
    "iso:country":"CN",
    "name:und_x_variant":[
        "Ts\u2019ao-ts\u2019un",
        "Caocun"
    ],
    "name:zho_x_preferred":[
        "\u66f9\u6751"
    ],
    "wof:name":"Caocun",
    "wof:placetype":"locality"
},
  "geometry": {"coordinates":[111.09208999999998,36.56365],"type":"Point"}
}