{
  "type": "Feature",
  "properties": {
    "gn:admin1_code":"2.0",
    "gn:asciiname":"Qiaoli",
    "gn:country_code":"CN",
    "gn:dem":131,
    "gn:feature_class":"P",
    "gn:feature_code":"PPL",
    "gn:name":"Qiaoli",
    "gn:population":0,
    "gn:timezone":"Asia/Shanghai",
    "iso:country":"CN",
    "name:und_x_variant":[
        "\u6865\u91cc",
        "Qiaoli"
    ],
    "wof:name":"Qiaoli",
    "wof:placetype":"locality"
},
  "geometry": {"coordinates":[119.70283999999999,29.88185],"type":"Point"}
}