{
  "type": "Feature",
  "properties": {
    "gn:admin1_code":"32.0",
    "gn:asciiname":"Gongcun",
    "gn:country_code":"CN",
    "gn:dem":3619,
    "gn:feature_class":"P",
    "gn:feature_code":"PPL",
    "gn:name":"Gongcun",
    "gn:population":0,
    "gn:timezone":"Asia/Shanghai",
    "iso:country":"CN",
    "name:zho_x_preferred":[
        "\u8d21\u6751"
    ],
    "wof:name":"Gongcun",
    "wof:placetype":"locality"
},
  "geometry": {"coordinates":[98.7062,31.976],"type":"Point"}
}