{
  "type": "Feature",
  "properties": {
    "gn:admin1_code":"15.0",
    "gn:asciiname":"Chengliang",
    "gn:country_code":"CN",
    "gn:dem":1896,
    "gn:feature_class":"P",
    "gn:feature_code":"PPL",
    "gn:name":"Chengliang",
    "gn:population":0,
    "gn:timezone":"Asia/Shanghai",
    "iso:country":"CN",
    "name:und_x_variant":[
        "\u7a0b\u6881"
    ],
    "wof:name":"Chengliang",
    "wof:placetype":"locality"
},
  "geometry": {"coordinates":[105.88694,35.46832],"type":"Point"}
}