{
  "type": "Feature",
  "properties": {
    "gn:admin1_code":"26.0",
    "gn:asciiname":"Heyicun",
    "gn:country_code":"CN",
    "gn:dem":646,
    "gn:feature_class":"P",
    "gn:feature_code":"PPL",
    "gn:name":"Heyicun",
    "gn:population":0,
    "gn:timezone":"Asia/Shanghai",
    "iso:country":"CN",
    "name:zho_x_preferred":[
        "\u5408\u4e49\u6751"
    ],
    "wof:name":"Heyicun",
    "wof:placetype":"locality"
},
  "geometry": {"coordinates":[110.29080999999999,35.29639],"type":"Point"}
}