{
  "type": "Feature",
  "properties": {
    "gn:admin1_code":"4.0",
    "gn:asciiname":"Xizhouxu",
    "gn:country_code":"CN",
    "gn:dem":1,
    "gn:feature_class":"P",
    "gn:feature_code":"PPL",
    "gn:name":"Xizhouxu",
    "gn:population":0,
    "gn:timezone":"Asia/Shanghai",
    "iso:country":"CN",
    "name:zho_x_preferred":[
        "Xizhouxu"
    ],
    "name:zho_x_variant":[
        "\u897f\u5468\u5729"
    ],
    "wof:name":"Xizhouxu",
    "wof:placetype":"locality"
},
  "geometry": {"coordinates":[119.36417,34.48034000000001],"type":"Point"}
}