{
  "type": "Feature",
  "properties": {
    "gn:admin1_code":"18.0",
    "gn:asciiname":"Jiaoliu",
    "gn:country_code":"CN",
    "gn:dem":851,
    "gn:feature_class":"P",
    "gn:feature_code":"PPL",
    "gn:name":"Jiaoliu",
    "gn:population":0,
    "gn:timezone":"Asia/Shanghai",
    "iso:country":"CN",
    "name:zho_x_preferred":[
        "\u7ede\u67f3"
    ],
    "wof:name":"Jiaoliu",
    "wof:placetype":"locality"
},
  "geometry": {"coordinates":[108.949,27.0195],"type":"Point"}
}