{
  "type": "Feature",
  "properties": {
    "gn:admin1_code":"12.0",
    "gn:asciiname":"Xinqiao",
    "gn:country_code":"CN",
    "gn:dem":18,
    "gn:feature_class":"P",
    "gn:feature_code":"PPL",
    "gn:name":"Xinqiao",
    "gn:population":0,
    "gn:timezone":"Asia/Shanghai",
    "iso:country":"CN",
    "name:ceb_x_preferred":[
        "Xinqiao"
    ],
    "name:deu_x_preferred":[
        "Xinqiao"
    ],
    "name:swe_x_preferred":[
        "Xinqiao"
    ],
    "name:zho_x_preferred":[
        "Xinqiao"
    ],
    "name:zho_x_variant":[
        "\u65b0\u6865"
    ],
    "wof:name":"Xinqiao",
    "wof:placetype":"locality"
},
  "geometry": {"coordinates":[115.33887,30.10597000000001],"type":"Point"}
}