{
  "type": "Feature",
  "properties": {
    "gn:admin1_code":"2.0",
    "gn:asciiname":"Yiting",
    "gn:country_code":"CN",
    "gn:dem":67,
    "gn:feature_class":"P",
    "gn:feature_code":"PPLA4",
    "gn:name":"Yiting",
    "gn:population":0,
    "gn:timezone":"Asia/Shanghai",
    "iso:country":"CN",
    "name:und_x_variant":[
        "I-ting-shih",
        "I-t\u2019ing",
        "\u4e49\u4ead",
        "Yiting",
        "Yiting Zhen"
    ],
    "name:zho_x_preferred":[
        "\u4e49\u4ead\u9547"
    ],
    "wof:name":"Yiting",
    "wof:placetype":"locality"
},
  "geometry": {"coordinates":[119.96089000000001,29.23597],"type":"Point"}
}