{
  "type": "Feature",
  "properties": {
    "gn:admin1_code":"19.0",
    "gn:asciiname":"Jiantaizi",
    "gn:country_code":"CN",
    "gn:dem":4,
    "gn:feature_class":"P",
    "gn:feature_code":"PPL",
    "gn:name":"Jiantaizi",
    "gn:population":0,
    "gn:timezone":"Asia/Shanghai",
    "iso:country":"CN",
    "name:zho_x_preferred":[
        "\u5c16\u53f0\u5b50"
    ],
    "wof:name":"Jiantaizi",
    "wof:placetype":"locality"
},
  "geometry": {"coordinates":[122.38254000000001,41.10507],"type":"Point"}
}