{
  "type": "Feature",
  "properties": {
    "gn:admin1_code":"20.0",
    "gn:asciiname":"Sishiba Gongli",
    "gn:country_code":"CN",
    "gn:dem":790,
    "gn:feature_class":"P",
    "gn:feature_code":"PPL",
    "gn:name":"Sishiba Gongli",
    "gn:population":0,
    "gn:timezone":"Asia/Shanghai",
    "iso:country":"CN",
    "name:zho_x_preferred":[
        "\u56db\u5341\u516b\u516c\u91cc"
    ],
    "wof:name":"Sishiba Gongli",
    "wof:placetype":"locality"
},
  "geometry": {"coordinates":[121.60111000000001,49.0898],"type":"Point"}
}