{
  "type": "Feature",
  "properties": {
    "gn:admin1_code":"29.0",
    "gn:asciiname":"Dugulu",
    "gn:country_code":"CN",
    "gn:dem":1695,
    "gn:feature_class":"P",
    "gn:feature_code":"PPL",
    "gn:name":"Dugulu",
    "gn:population":0,
    "gn:timezone":"Asia/Shanghai",
    "iso:country":"CN",
    "name:zho_x_preferred":[
        "\u5ea6\u56fa\u8def"
    ],
    "wof:name":"Dugulu",
    "wof:placetype":"locality"
},
  "geometry": {"coordinates":[100.20399999999999,24.7646],"type":"Point"}
}