{
  "type": "Feature",
  "properties": {
    "gn:admin1_code":"18",
    "gn:asciiname":"Longdongkan",
    "gn:country_code":"CN",
    "gn:dem":659,
    "gn:feature_class":"P",
    "gn:feature_code":"PPL",
    "gn:name":"Longdongkan",
    "gn:population":0,
    "gn:timezone":"Asia/Shanghai",
    "iso:country":"CN",
    "name:zho_x_preferred":[
        "\u9f99\u6d1e\u574e"
    ],
    "wof:name":"Longdongkan",
    "wof:placetype":"locality"
},
  "geometry": {"coordinates":[107.55200000000001,27.4384],"type":"Point"}
}