{
  "type": "Feature",
  "properties": {
    "gn:admin1_code":"9.0",
    "gn:asciiname":"Luodong",
    "gn:country_code":"CN",
    "gn:dem":140,
    "gn:feature_class":"P",
    "gn:feature_code":"PPL",
    "gn:name":"Luodong",
    "gn:population":0,
    "gn:timezone":"Asia/Shanghai",
    "iso:country":"CN",
    "name:ceb_x_preferred":[
        "Luodong Zhen"
    ],
    "name:deu_x_preferred":[
        "Luodong"
    ],
    "name:hak_x_preferred":[
        "L\u00f2-t\u00fbng-ts\u1e73\u0301n"
    ],
    "name:ita_x_preferred":[
        "Luodong"
    ],
    "name:jpn_x_preferred":[
        "\u7f85\u6771\u93ae"
    ],
    "name:kor_x_preferred":[
        "\ub904\ub465\uc9c4"
    ],
    "name:spa_x_preferred":[
        "Luodong"
    ],
    "name:vie_x_preferred":[
        "La \u0110\u00f4ng"
    ],
    "name:zho_x_preferred":[
        "\u7f57\u578c"
    ],
    "name:zho_x_variant":[
        "\u7f85\u6771\u93ae"
    ],
    "wof:name":"Luodong",
    "wof:placetype":"locality"
},
  "geometry": {"coordinates":[113.43804,34.78449000000001],"type":"Point"}
}