{
  "type": "Feature",
  "properties": {
    "gn:admin1_code":"3",
    "gn:asciiname":"Longxi",
    "gn:country_code":"CN",
    "gn:dem":62,
    "gn:feature_class":"P",
    "gn:feature_code":"PPLA4",
    "gn:name":"Longxi",
    "gn:population":0,
    "gn:timezone":"Asia/Shanghai",
    "iso:country":"CN",
    "name:und_x_variant":[
        "\u9f99\u6eaa",
        "Longxi Zhen",
        "\u9f99\u6eaa\u9547"
    ],
    "wof:name":"Longxi",
    "wof:placetype":"locality"
},
  "geometry": {"coordinates":[116.28787,27.71399000000001],"type":"Point"}
}