{
  "type": "Feature",
  "properties": {
    "gn:admin1_code":"26.0",
    "gn:asciiname":"Xiqingtuncun",
    "gn:country_code":"CN",
    "gn:dem":346,
    "gn:feature_class":"P",
    "gn:feature_code":"PPL",
    "gn:name":"Xiqingtuncun",
    "gn:population":0,
    "gn:timezone":"Asia/Shanghai",
    "iso:country":"CN",
    "name:und_x_variant":[
        "Xiqingtun"
    ],
    "name:zho_x_preferred":[
        "\u897f\u5e86\u5c6f\u6751"
    ],
    "name:zho_x_variant":[
        "\u897f\u5e86\u5c6f"
    ],
    "wof:name":"Xiqingtuncun",
    "wof:placetype":"locality"
},
  "geometry": {"coordinates":[109.42518,34.54121],"type":"Point"}
}