{
  "type": "Feature",
  "properties": {
    "gn:admin1_code":"20.0",
    "gn:asciiname":"Ya'ergenchu",
    "gn:country_code":"CN",
    "gn:dem":315,
    "gn:feature_class":"P",
    "gn:feature_code":"PPLA4",
    "gn:name":"Ya\u2019ergenchu",
    "gn:population":0,
    "gn:timezone":"Asia/Shanghai",
    "iso:country":"CN",
    "name:und_x_variant":[
        "Ya\u2019ergenchu",
        "Ya\u2019ergenchu Zhen"
    ],
    "name:zho_x_preferred":[
        "\u96c5\u5c14\u6839\u695a"
    ],
    "name:zho_x_variant":[
        "\u96c5\u5c14\u6839\u695a\u9547"
    ],
    "wof:name":"Ya'ergenchu",
    "wof:placetype":"locality"
},
  "geometry": {"coordinates":[122.60809,47.74603],"type":"Point"}
}