{
  "type": "Feature",
  "properties": {
    "gn:admin1_code":"12.0",
    "gn:asciiname":"Yakoutian",
    "gn:country_code":"CN",
    "gn:dem":774,
    "gn:feature_class":"P",
    "gn:feature_code":"PPL",
    "gn:name":"Yakoutian",
    "gn:population":0,
    "gn:timezone":"Asia/Shanghai",
    "iso:country":"CN",
    "name:zho_x_preferred":[
        "\u57ad\u53e3\u7530"
    ],
    "wof:name":"Yakoutian",
    "wof:placetype":"locality"
},
  "geometry": {"coordinates":[109.11035,29.64934],"type":"Point"}
}