{
  "type": "Feature",
  "properties": {
    "gn:admin1_code":"16.0",
    "gn:asciiname":"Penxia",
    "gn:country_code":"CN",
    "gn:dem":217,
    "gn:feature_class":"P",
    "gn:feature_code":"PPL",
    "gn:name":"Penxia",
    "gn:population":0,
    "gn:timezone":"Asia/Shanghai",
    "iso:country":"CN",
    "name:zho_x_preferred":[
        "\u76c6\u4e0b"
    ],
    "wof:name":"Penxia",
    "wof:placetype":"locality"
},
  "geometry": {"coordinates":[107.92400000000001,23.9195],"type":"Point"}
}