{
  "type": "Feature",
  "properties": {
    "gn:admin1_code":"2.0",
    "gn:asciiname":"Luoqiubang",
    "gn:country_code":"CN",
    "gn:dem":5,
    "gn:feature_class":"P",
    "gn:feature_code":"PPL",
    "gn:name":"Luoqiubang",
    "gn:population":0,
    "gn:timezone":"Asia/Shanghai",
    "iso:country":"CN",
    "name:und_x_variant":[
        "\u7f57\u79cb\u6d5c"
    ],
    "wof:name":"Luoqiubang",
    "wof:placetype":"locality"
},
  "geometry": {"coordinates":[120.60476,30.63141],"type":"Point"}
}