{
  "type": "Feature",
  "properties": {
    "gn:admin1_code":"25.0",
    "gn:asciiname":"Shuangshiwucun",
    "gn:country_code":"CN",
    "gn:dem":296,
    "gn:feature_class":"P",
    "gn:feature_code":"PPL",
    "gn:name":"Shuangshiwucun",
    "gn:population":0,
    "gn:timezone":"Asia/Shanghai",
    "iso:country":"CN",
    "name:zho_x_preferred":[
        "\u53cc\u77f3\u5c4b\u6751"
    ],
    "wof:name":"Shuangshiwucun",
    "wof:placetype":"locality"
},
  "geometry": {"coordinates":[120.5958,36.21163],"type":"Point"}
}