{
  "type": "Feature",
  "properties": {
    "gn:admin1_code":"15.0",
    "gn:asciiname":"Huanghe",
    "gn:country_code":"CN",
    "gn:dem":1720,
    "gn:feature_class":"P",
    "gn:feature_code":"PPL",
    "gn:name":"Huanghe",
    "gn:population":0,
    "gn:timezone":"Asia/Shanghai",
    "iso:country":"CN",
    "name:zho_x_preferred":[
        "\u9ec4\u9e64"
    ],
    "wof:name":"Huanghe",
    "wof:placetype":"locality"
},
  "geometry": {"coordinates":[105.325,34.9416],"type":"Point"}
}