{
  "type": "Feature",
  "properties": {
    "gn:admin1_code":"18",
    "gn:asciiname":"Anzishan",
    "gn:country_code":"CN",
    "gn:dem":761,
    "gn:feature_class":"P",
    "gn:feature_code":"PPL",
    "gn:name":"Anzishan",
    "gn:population":0,
    "gn:timezone":"Asia/Shanghai",
    "iso:country":"CN",
    "name:zho_x_preferred":[
        "\u5b89\u5b50\u5c71"
    ],
    "wof:name":"Anzishan",
    "wof:placetype":"locality"
},
  "geometry": {"coordinates":[107.407,27.4142],"type":"Point"}
}