{
  "type": "Feature",
  "properties": {
    "gn:admin1_code":"32.0",
    "gn:asciiname":"Taojing",
    "gn:country_code":"CN",
    "gn:dem":343,
    "gn:feature_class":"P",
    "gn:feature_code":"PPL",
    "gn:name":"Taojing",
    "gn:population":0,
    "gn:timezone":"Asia/Shanghai",
    "iso:country":"CN",
    "name:zho_x_preferred":[
        "\u6dd8\u4e95"
    ],
    "wof:name":"Taojing",
    "wof:placetype":"locality"
},
  "geometry": {"coordinates":[105.51000000000001,29.9482],"type":"Point"}
}