{
  "type": "Feature",
  "properties": {
    "gn:admin1_code":"29.0",
    "gn:asciiname":"Laowuzhai",
    "gn:country_code":"CN",
    "gn:dem":1264,
    "gn:feature_class":"P",
    "gn:feature_code":"PPL",
    "gn:name":"Laowuzhai",
    "gn:population":0,
    "gn:timezone":"Asia/Shanghai",
    "iso:country":"CN",
    "name:zho_x_preferred":[
        "\u8001\u4e4c\u5be8"
    ],
    "wof:name":"Laowuzhai",
    "wof:placetype":"locality"
},
  "geometry": {"coordinates":[101.44,22.8989],"type":"Point"}
}