{
  "type": "Feature",
  "properties": {
    "gn:admin1_code":"3.0",
    "gn:asciiname":"Guyuan",
    "gn:country_code":"CN",
    "gn:dem":101,
    "gn:feature_class":"P",
    "gn:feature_code":"PPL",
    "gn:name":"Guyuan",
    "gn:population":0,
    "gn:timezone":"Asia/Shanghai",
    "iso:country":"CN",
    "name:zho_x_preferred":[
        "\u53e4\u6e90"
    ],
    "wof:name":"Guyuan",
    "wof:placetype":"locality"
},
  "geometry": {"coordinates":[117.107,28.6632],"type":"Point"}
}