{
  "type": "Feature",
  "properties": {
    "gn:admin1_code":"02",
    "gn:asciiname":"Hsia-t'ang-ao-ti-ts'un",
    "gn:country_code":"CN",
    "gn:dem":17,
    "gn:feature_class":"P",
    "gn:feature_code":"PPL",
    "gn:name":"Hsia-t\u2019ang-ao-ti-ts\u2019un",
    "gn:population":0,
    "gn:timezone":"Asia/Shanghai",
    "iso:country":"CN",
    "wof:name":"Hsia-t'ang-ao-ti-ts'un",
    "wof:placetype":"locality"
},
  "geometry": {"coordinates":[120.66278,28.12556],"type":"Point"}
}