{
  "type": "Feature",
  "properties": {
    "gn:admin1_code":"18",
    "gn:asciiname":"Rangba",
    "gn:country_code":"CN",
    "gn:dem":1158,
    "gn:feature_class":"P",
    "gn:feature_code":"PPL",
    "gn:name":"Rangba",
    "gn:population":0,
    "gn:timezone":"Asia/Shanghai",
    "iso:country":"CN",
    "name:zho_x_preferred":[
        "\u8ba9\u575d"
    ],
    "wof:name":"Rangba",
    "wof:placetype":"locality"
},
  "geometry": {"coordinates":[107.43000000000001,28.9611],"type":"Point"}
}