{
  "type": "Feature",
  "properties": {
    "gn:admin1_code":"8.0",
    "gn:asciiname":"Xi'ancun",
    "gn:country_code":"CN",
    "gn:dem":293,
    "gn:feature_class":"P",
    "gn:feature_code":"PPL",
    "gn:name":"Xi\u2019ancun",
    "gn:population":0,
    "gn:timezone":"Asia/Shanghai",
    "iso:country":"CN",
    "name:und_x_variant":[
        "Xi\u2019ancun"
    ],
    "name:zho_x_preferred":[
        "\u897f\u5b89\u6751"
    ],
    "wof:name":"Xi'ancun",
    "wof:placetype":"locality"
},
  "geometry": {"coordinates":[129.05686,44.13881],"type":"Point"}
}