{
  "type": "Feature",
  "properties": {
    "gn:admin1_code":"9",
    "gn:asciiname":"Dadailou",
    "gn:country_code":"CN",
    "gn:dem":46,
    "gn:feature_class":"P",
    "gn:feature_code":"PPL",
    "gn:name":"Dadailou",
    "gn:population":0,
    "gn:timezone":"Asia/Shanghai",
    "iso:country":"CN",
    "name:zho_x_preferred":[
        "\u5927\u4ee3\u697c"
    ],
    "wof:name":"Dadailou",
    "wof:placetype":"locality"
},
  "geometry": {"coordinates":[115.974,34.2439],"type":"Point"}
}