{
  "type": "Feature",
  "properties": {
    "gn:admin1_code":"25",
    "gn:asciiname":"Sunjiapuwang",
    "gn:country_code":"CN",
    "gn:dem":179,
    "gn:feature_class":"P",
    "gn:feature_code":"PPL",
    "gn:name":"Sunjiapuwang",
    "gn:population":0,
    "gn:timezone":"Asia/Shanghai",
    "iso:country":"CN",
    "name:und_x_variant":[
        "\u5b59\u5bb6\u84b2\u6c6a"
    ],
    "wof:name":"Sunjiapuwang",
    "wof:placetype":"locality"
},
  "geometry": {"coordinates":[119.09649,35.34916],"type":"Point"}
}