{
  "type": "Feature",
  "properties": {
    "gn:admin1_code":"18",
    "gn:asciiname":"Changtian",
    "gn:country_code":"CN",
    "gn:dem":1572,
    "gn:feature_class":"P",
    "gn:feature_code":"PPL",
    "gn:name":"Changtian",
    "gn:population":0,
    "gn:timezone":"Asia/Shanghai",
    "iso:country":"CN",
    "name:zho_x_preferred":[
        "\u957f\u7530"
    ],
    "wof:name":"Changtian",
    "wof:placetype":"locality"
},
  "geometry": {"coordinates":[105.14100000000001,25.3012],"type":"Point"}
}