{
  "type": "Feature",
  "properties": {
    "gn:admin1_code":"25",
    "gn:asciiname":"Qianyujiazhuang",
    "gn:country_code":"CN",
    "gn:dem":103,
    "gn:feature_class":"P",
    "gn:feature_code":"PPL",
    "gn:name":"Qianyujiazhuang",
    "gn:population":0,
    "gn:timezone":"Asia/Shanghai",
    "iso:country":"CN",
    "name:zho_x_preferred":[
        "\u524d\u4e8e\u5bb6\u5e84"
    ],
    "wof:name":"Qianyujiazhuang",
    "wof:placetype":"locality"
},
  "geometry": {"coordinates":[118.815,35.5372],"type":"Point"}
}