{
  "type": "Feature",
  "properties": {
    "gn:admin1_code":"26.0",
    "gn:asciiname":"Shaqucun",
    "gn:country_code":"CN",
    "gn:dem":1436,
    "gn:feature_class":"P",
    "gn:feature_code":"PPL",
    "gn:name":"Shaqucun",
    "gn:population":0,
    "gn:timezone":"Asia/Shanghai",
    "iso:country":"CN",
    "name:zho_x_preferred":[
        "\u6c99\u6e20\u6751"
    ],
    "wof:name":"Shaqucun",
    "wof:placetype":"locality"
},
  "geometry": {"coordinates":[108.54298,37.52774],"type":"Point"}
}