{
  "type": "Feature",
  "properties": {
    "gn:admin1_code":"14.0",
    "gn:asciiname":"Bidongcun",
    "gn:country_code":"CN",
    "gn:dem":3246,
    "gn:feature_class":"P",
    "gn:feature_code":"PPL",
    "gn:name":"Bidongcun",
    "gn:population":0,
    "gn:timezone":"Asia/Urumqi",
    "iso:country":"CN",
    "name:zho_x_preferred":[
        "\u6bd4\u4e1c\u6751"
    ],
    "wof:name":"Bidongcun",
    "wof:placetype":"locality"
},
  "geometry": {"coordinates":[94.66434,29.5155],"type":"Point"}
}