{
  "type": "Feature",
  "properties": {
    "gn:admin1_code":"14.0",
    "gn:asciiname":"Bakang",
    "gn:country_code":"CN",
    "gn:dem":4583,
    "gn:feature_class":"P",
    "gn:feature_code":"PPL",
    "gn:name":"Bakang",
    "gn:population":0,
    "gn:timezone":"Asia/Urumqi",
    "iso:country":"CN",
    "name:zho_x_preferred":[
        "\u5df4\u5eb7"
    ],
    "wof:name":"Bakang",
    "wof:placetype":"locality"
},
  "geometry": {"coordinates":[96.34881,29.51648],"type":"Point"}
}