{
  "type": "Feature",
  "properties": {
    "gn:admin1_code":"5.0",
    "gn:asciiname":"Dong'ershihao",
    "gn:country_code":"CN",
    "gn:dem":156,
    "gn:feature_class":"P",
    "gn:feature_code":"PPL",
    "gn:name":"Dong\u2019ershihao",
    "gn:population":0,
    "gn:timezone":"Asia/Shanghai",
    "iso:country":"CN",
    "name:und_x_variant":[
        "Dong\u2019ershihao"
    ],
    "name:zho_x_preferred":[
        "\u4e1c\u4e8c\u5341\u53f7"
    ],
    "wof:name":"Dong'ershihao",
    "wof:placetype":"locality"
},
  "geometry": {"coordinates":[123.61852,44.2742],"type":"Point"}
}