{
  "type": "Feature",
  "properties": {
    "gn:admin1_code":"16.0",
    "gn:asciiname":"Chongbiaotang",
    "gn:country_code":"CN",
    "gn:dem":132,
    "gn:feature_class":"P",
    "gn:feature_code":"PPL",
    "gn:name":"Chongbiaotang",
    "gn:population":0,
    "gn:timezone":"Asia/Shanghai",
    "iso:country":"CN",
    "name:zho_x_preferred":[
        "\u51b2\u8868\u5858"
    ],
    "wof:name":"Chongbiaotang",
    "wof:placetype":"locality"
},
  "geometry": {"coordinates":[110.30500000000001,23.2309],"type":"Point"}
}