{
  "type": "Feature",
  "properties": {
    "gn:admin1_code":"8.0",
    "gn:asciiname":"Dongxing Erdui",
    "gn:country_code":"CN",
    "gn:dem":352,
    "gn:feature_class":"P",
    "gn:feature_code":"PPLF",
    "gn:name":"Dongxing Erdui",
    "gn:population":0,
    "gn:timezone":"Asia/Shanghai",
    "iso:country":"CN",
    "name:zho_x_preferred":[
        "\u4e1c\u5174\u4e8c\u961f"
    ],
    "wof:name":"Dongxing Erdui",
    "wof:placetype":"locality"
},
  "geometry": {"coordinates":[126.33758,49.16992],"type":"Point"}
}