{
  "type": "Feature",
  "properties": {
    "gn:admin1_code":"24",
    "gn:asciiname":"Duanjiazhuang",
    "gn:country_code":"CN",
    "gn:dem":1138,
    "gn:feature_class":"P",
    "gn:feature_code":"PPL",
    "gn:name":"Duanjiazhuang",
    "gn:population":0,
    "gn:timezone":"Asia/Shanghai",
    "iso:country":"CN",
    "name:zho_x_preferred":[
        "\u6bb5\u5bb6\u5e84"
    ],
    "wof:name":"Duanjiazhuang",
    "wof:placetype":"locality"
},
  "geometry": {"coordinates":[111.19821,37.30759000000001],"type":"Point"}
}