{
  "type": "Feature",
  "properties": {
    "gn:admin1_code":"25.0",
    "gn:asciiname":"Dongliujia",
    "gn:country_code":"CN",
    "gn:dem":119,
    "gn:feature_class":"P",
    "gn:feature_code":"PPL",
    "gn:name":"Dongliujia",
    "gn:population":0,
    "gn:timezone":"Asia/Shanghai",
    "iso:country":"CN",
    "name:zho_x_preferred":[
        "\u4e1c\u5218\u5bb6"
    ],
    "wof:name":"Dongliujia",
    "wof:placetype":"locality"
},
  "geometry": {"coordinates":[121.14755,37.07127],"type":"Point"}
}