{
  "type": "Feature",
  "properties": {
    "gn:admin1_code":"24",
    "gn:asciiname":"Guozhuang",
    "gn:cc2":"CN",
    "gn:country_code":"CN",
    "gn:dem":990,
    "gn:feature_class":"P",
    "gn:feature_code":"PPL",
    "gn:name":"Guozhuang",
    "gn:population":0,
    "gn:timezone":"Asia/Shanghai",
    "iso:country":"CN",
    "name:und_x_variant":[
        "Kuo-chuang",
        "Guozhuang"
    ],
    "wof:name":"Guozhuang",
    "wof:placetype":"locality"
},
  "geometry": {"coordinates":[112.59999999999999,36.58333],"type":"Point"}
}