{
  "type": "Feature",
  "properties": {
    "gn:admin1_code":"7.0",
    "gn:asciiname":"Shizhushan",
    "gn:country_code":"CN",
    "gn:dem":529,
    "gn:feature_class":"P",
    "gn:feature_code":"PPL",
    "gn:name":"Shizhushan",
    "gn:population":0,
    "gn:timezone":"Asia/Shanghai",
    "iso:country":"CN",
    "name:zho_x_preferred":[
        "\u77f3\u7af9\u5c71"
    ],
    "wof:name":"Shizhushan",
    "wof:placetype":"locality"
},
  "geometry": {"coordinates":[116.69755000000001,26.10847],"type":"Point"}
}