{
  "type": "Feature",
  "properties": {
    "gn:admin1_code":"05",
    "gn:asciiname":"Zixing",
    "gn:country_code":"CN",
    "gn:dem":351,
    "gn:feature_class":"P",
    "gn:feature_code":"PPL",
    "gn:name":"Zixing",
    "gn:population":0,
    "gn:timezone":"Asia/Shanghai",
    "iso:country":"CN",
    "name:und_x_variant":[
        "\u81ea\u5174",
        "Zixingcun"
    ],
    "wof:name":"Zixing",
    "wof:placetype":"locality"
},
  "geometry": {"coordinates":[126.05492,41.1003],"type":"Point"}
}