{
  "type": "Feature",
  "properties": {
    "gn:admin1_code":"05",
    "gn:asciiname":"Zixing",
    "gn:country_code":"CN",
    "gn:dem":351,
    "gn:feature_class":"P",
    "gn:feature_code":"PPL",
    "gn:name":"Zixing",
    "gn:population":0,
    "gn:timezone":"Asia/Shanghai",
    "iso:country":"CN",
    "name:ceb_x_preferred":[
        "Zixing Shi"
    ],
    "name:deu_x_preferred":[
        "Zixing"
    ],
    "name:fra_x_preferred":[
        "Zixing"
    ],
    "name:hak_x_preferred":[
        "Ch\u1e73\u0302-h\u00een-s\u1e73"
    ],
    "name:ita_x_preferred":[
        "Zixing"
    ],
    "name:jpn_x_preferred":[
        "\u8cc7\u8208\u5e02"
    ],
    "name:kik_x_preferred":[
        "Zixing"
    ],
    "name:kor_x_preferred":[
        "\ucbd4\uc2f1\uc2dc"
    ],
    "name:mlg_x_preferred":[
        "Zixing"
    ],
    "name:nld_x_preferred":[
        "Zixing"
    ],
    "name:nor_x_preferred":[
        "Zixing"
    ],
    "name:pam_x_preferred":[
        "Zixing"
    ],
    "name:pol_x_preferred":[
        "Zixing"
    ],
    "name:swe_x_preferred":[
        "Zixing"
    ],
    "name:und_x_variant":[
        "\u81ea\u5174",
        "Zixingcun"
    ],
    "name:vie_x_preferred":[
        "T\u01b0 H\u01b0ng"
    ],
    "name:war_x_preferred":[
        "Zixing"
    ],
    "name:zho_x_preferred":[
        "\u8d44\u5174\u5e02"
    ],
    "wof:name":"Zixing",
    "wof:placetype":"locality"
},
  "geometry": {"coordinates":[126.05492,41.1003],"type":"Point"}
}