{
  "type": "Feature",
  "properties": {
    "gn:admin1_code":"30",
    "gn:asciiname":"Shanhua",
    "gn:country_code":"CN",
    "gn:dem":60,
    "gn:feature_class":"P",
    "gn:feature_code":"PPL",
    "gn:name":"Shanhua",
    "gn:population":0,
    "gn:timezone":"Asia/Urumqi",
    "iso:country":"CN",
    "name:zho_x_preferred":[
        "\u5c71\u534e"
    ],
    "wof:name":"Shanhua",
    "wof:placetype":"locality"
},
  "geometry": {"coordinates":[110.14467,21.71114],"type":"Point"}
}