{
  "type": "Feature",
  "properties": {
    "gn:admin1_code":"9.0",
    "gn:asciiname":"Shanzhuang",
    "gn:country_code":"CN",
    "gn:dem":103,
    "gn:feature_class":"P",
    "gn:feature_code":"PPL",
    "gn:name":"Shanzhuang",
    "gn:population":0,
    "gn:timezone":"Asia/Shanghai",
    "iso:country":"CN",
    "name:zho_x_preferred":[
        "\u5c71\u5e84"
    ],
    "wof:name":"Shanzhuang",
    "wof:placetype":"locality"
},
  "geometry": {"coordinates":[113.96679,35.44005999999999],"type":"Point"}
}