{
  "type": "Feature",
  "properties": {
    "gn:admin1_code":"16.0",
    "gn:asciiname":"Qinhou",
    "gn:country_code":"CN",
    "gn:dem":227,
    "gn:feature_class":"P",
    "gn:feature_code":"PPL",
    "gn:name":"Qinhou",
    "gn:population":0,
    "gn:timezone":"Asia/Shanghai",
    "iso:country":"CN",
    "name:zho_x_preferred":[
        "\u7434\u539a"
    ],
    "wof:name":"Qinhou",
    "wof:placetype":"locality"
},
  "geometry": {"coordinates":[107.383,22.2241],"type":"Point"}
}