{
  "type": "Feature",
  "properties": {
    "gn:admin1_code":"16.0",
    "gn:asciiname":"Guhe",
    "gn:country_code":"CN",
    "gn:dem":235,
    "gn:feature_class":"P",
    "gn:feature_code":"PPL",
    "gn:name":"Guhe",
    "gn:population":0,
    "gn:timezone":"Asia/Shanghai",
    "iso:country":"CN",
    "name:ceb_x_preferred":[
        "Guhe"
    ],
    "name:swe_x_preferred":[
        "Guhe"
    ],
    "name:zho_x_preferred":[
        "\u53e4\u6cb3"
    ],
    "wof:name":"Guhe",
    "wof:placetype":"locality"
},
  "geometry": {"coordinates":[108.71599999999999,23.8033],"type":"Point"}
}