{
  "type": "Feature",
  "properties": {
    "gn:admin1_code":"11.0",
    "gn:asciiname":"Yongfanghu",
    "gn:country_code":"CN",
    "gn:dem":921,
    "gn:feature_class":"P",
    "gn:feature_code":"PPL",
    "gn:name":"Yongfanghu",
    "gn:population":0,
    "gn:timezone":"Asia/Shanghai",
    "iso:country":"CN",
    "name:zho_x_preferred":[
        "\u6c38\u574a\u6e56"
    ],
    "name:zho_x_variant":[
        "\u6c38\u65b9\u6e56"
    ],
    "wof:name":"Yongfanghu",
    "wof:placetype":"locality"
},
  "geometry": {"coordinates":[113.83368,26.82592],"type":"Point"}
}