{
  "type": "Feature",
  "properties": {
    "gn:admin1_code":"12",
    "gn:asciiname":"Guanqiaopu",
    "gn:country_code":"CN",
    "gn:dem":137,
    "gn:feature_class":"P",
    "gn:feature_code":"PPL",
    "gn:name":"Guanqiaopu",
    "gn:population":0,
    "gn:timezone":"Asia/Shanghai",
    "iso:country":"CN",
    "name:und_x_variant":[
        "Kuan-ch\u2019iao-p\u2019u",
        "Guanqiao",
        "Guanqiaopu",
        "\u5b98\u6865\u94fa"
    ],
    "wof:name":"Guanqiaopu",
    "wof:placetype":"locality"
},
  "geometry": {"coordinates":[112.93882000000001,31.11169000000001],"type":"Point"}
}