{
  "type": "Feature",
  "properties": {
    "gn:admin1_code":"18",
    "gn:asciiname":"Maziba",
    "gn:country_code":"CN",
    "gn:dem":1057,
    "gn:feature_class":"P",
    "gn:feature_code":"PPL",
    "gn:name":"Maziba",
    "gn:population":0,
    "gn:timezone":"Asia/Shanghai",
    "iso:country":"CN",
    "name:zho_x_preferred":[
        "\u9ebb\u5b50\u575d"
    ],
    "wof:name":"Maziba",
    "wof:placetype":"locality"
},
  "geometry": {"coordinates":[106.337,27.6874],"type":"Point"}
}