{
  "type": "Feature",
  "properties": {
    "gn:admin1_code":"12.0",
    "gn:asciiname":"Youfangjiao",
    "gn:country_code":"CN",
    "gn:dem":638,
    "gn:feature_class":"P",
    "gn:feature_code":"PPL",
    "gn:name":"Youfangjiao",
    "gn:population":0,
    "gn:timezone":"Asia/Shanghai",
    "iso:country":"CN",
    "name:zho_x_preferred":[
        "\u6cb9\u574a\u89d2"
    ],
    "wof:name":"Youfangjiao",
    "wof:placetype":"locality"
},
  "geometry": {"coordinates":[109.18098999999999,29.35666],"type":"Point"}
}