{
  "type": "Feature",
  "properties": {
    "gn:admin1_code":"11.0",
    "gn:asciiname":"Beiliping",
    "gn:country_code":"CN",
    "gn:dem":474,
    "gn:feature_class":"P",
    "gn:feature_code":"PPL",
    "gn:name":"Beiliping",
    "gn:population":0,
    "gn:timezone":"Asia/Shanghai",
    "iso:country":"CN",
    "name:zho_x_preferred":[
        "\u5351\u7acb\u576a"
    ],
    "wof:name":"Beiliping",
    "wof:placetype":"locality"
},
  "geometry": {"coordinates":[109.83978,29.24806],"type":"Point"}
}