{
  "type": "Feature",
  "properties": {
    "gn:admin1_code":"26.0",
    "gn:asciiname":"Liuzhuocun",
    "gn:country_code":"CN",
    "gn:dem":749,
    "gn:feature_class":"P",
    "gn:feature_code":"PPL",
    "gn:name":"Liuzhuocun",
    "gn:population":0,
    "gn:timezone":"Asia/Shanghai",
    "iso:country":"CN",
    "name:zho_x_preferred":[
        "\u5218\u5353\u6751"
    ],
    "wof:name":"Liuzhuocun",
    "wof:placetype":"locality"
},
  "geometry": {"coordinates":[109.84032000000001,35.23377],"type":"Point"}
}