{
  "type": "Feature",
  "properties": {
    "gn:admin1_code":"04",
    "gn:asciiname":"Wangxiangcun",
    "gn:country_code":"CN",
    "gn:dem":5,
    "gn:feature_class":"P",
    "gn:feature_code":"PPL",
    "gn:name":"Wangxiangcun",
    "gn:population":0,
    "gn:timezone":"Asia/Shanghai",
    "iso:country":"CN",
    "name:und_x_variant":[
        "Wang-hsiang",
        "Wangxiang",
        "Wangxiangcun"
    ],
    "name:zho_x_preferred":[
        "\u65fa\u5df7\u6751"
    ],
    "wof:name":"Wangxiangcun",
    "wof:placetype":"locality"
},
  "geometry": {"coordinates":[120.71008,31.43231],"type":"Point"}
}