{
  "type": "Feature",
  "properties": {
    "gn:admin1_code":"33",
    "gn:asciiname":"Hepingchang",
    "gn:country_code":"CN",
    "gn:dem":262,
    "gn:feature_class":"P",
    "gn:feature_code":"PPL",
    "gn:name":"Hepingchang",
    "gn:population":0,
    "gn:timezone":"Asia/Shanghai",
    "iso:country":"CN",
    "name:zho_x_preferred":[
        "\u548c\u5e73\u573a"
    ],
    "wof:name":"Hepingchang",
    "wof:placetype":"locality"
},
  "geometry": {"coordinates":[106.46593,29.22453],"type":"Point"}
}