{
  "type": "Feature",
  "properties": {
    "gn:admin1_code":"2.0",
    "gn:asciiname":"Wangdui",
    "gn:country_code":"CN",
    "gn:dem":51,
    "gn:feature_class":"P",
    "gn:feature_code":"PPL",
    "gn:name":"Wangdui",
    "gn:population":0,
    "gn:timezone":"Asia/Shanghai",
    "iso:country":"CN",
    "name:zho_x_preferred":[
        "\u6c6a\u5bf9"
    ],
    "wof:name":"Wangdui",
    "wof:placetype":"locality"
},
  "geometry": {"coordinates":[119.83566999999999,31.10167],"type":"Point"}
}