{
  "type": "Feature",
  "properties": {
    "gn:admin1_code":"15.0",
    "gn:asciiname":"Chejiasi",
    "gn:country_code":"CN",
    "gn:dem":2205,
    "gn:feature_class":"P",
    "gn:feature_code":"PPL",
    "gn:name":"Chejiasi",
    "gn:population":0,
    "gn:timezone":"Asia/Shanghai",
    "iso:country":"CN",
    "name:zho_x_preferred":[
        "\u8f66\u5bb6\u5bfa"
    ],
    "wof:name":"Chejiasi",
    "wof:placetype":"locality"
},
  "geometry": {"coordinates":[103.024,35.9544],"type":"Point"}
}