{
  "type": "Feature",
  "properties": {
    "gn:admin1_code":"9.0",
    "gn:asciiname":"Huayanggong",
    "gn:country_code":"CN",
    "gn:dem":323,
    "gn:feature_class":"P",
    "gn:feature_code":"PPL",
    "gn:name":"Huayanggong",
    "gn:population":0,
    "gn:timezone":"Asia/Shanghai",
    "iso:country":"CN",
    "name:und_x_variant":[
        "\u534e\u9633\u5bab",
        "Huayanggong"
    ],
    "wof:name":"Huayanggong",
    "wof:placetype":"locality"
},
  "geometry": {"coordinates":[112.23558,33.43492],"type":"Point"}
}