{
  "type": "Feature",
  "properties": {
    "gn:admin1_code":"32.0",
    "gn:asciiname":"Guzhongcun",
    "gn:country_code":"CN",
    "gn:dem":3799,
    "gn:feature_class":"P",
    "gn:feature_code":"PPL",
    "gn:name":"Guzhongcun",
    "gn:population":0,
    "gn:timezone":"Asia/Shanghai",
    "iso:country":"CN",
    "name:zho_x_preferred":[
        "\u56fa\u4e2d\u6751"
    ],
    "wof:name":"Guzhongcun",
    "wof:placetype":"locality"
},
  "geometry": {"coordinates":[100.462,29.6137],"type":"Point"}
}