{
  "type": "Feature",
  "properties": {
    "gn:admin1_code":"3",
    "gn:asciiname":"Shengbei",
    "gn:country_code":"CN",
    "gn:dem":189,
    "gn:feature_class":"P",
    "gn:feature_code":"PPL",
    "gn:name":"Shengbei",
    "gn:population":0,
    "gn:timezone":"Asia/Shanghai",
    "iso:country":"CN",
    "name:zho_x_preferred":[
        "\u5d4a\u80cc"
    ],
    "wof:name":"Shengbei",
    "wof:placetype":"locality"
},
  "geometry": {"coordinates":[114.947,25.2426],"type":"Point"}
}