{
  "type": "Feature",
  "properties": {
    "gn:admin1_code":"14.0",
    "gn:asciiname":"Gangzi",
    "gn:country_code":"CN",
    "gn:dem":3845,
    "gn:feature_class":"P",
    "gn:feature_code":"PPL",
    "gn:name":"Gangzi",
    "gn:population":0,
    "gn:timezone":"Asia/Shanghai",
    "iso:country":"CN",
    "name:und_x_variant":[
        "Gangzhi",
        "Gangzi"
    ],
    "name:zho_x_preferred":[
        "\u5c97\u829d"
    ],
    "name:zho_x_variant":[
        "\u5c97\u5b5c"
    ],
    "wof:name":"Gangzi",
    "wof:placetype":"locality"
},
  "geometry": {"coordinates":[81.2153,30.22],"type":"Point"}
}