{
  "type": "Feature",
  "properties": {
    "gn:admin1_code":"8.0",
    "gn:asciiname":"Zhongxiancun",
    "gn:country_code":"CN",
    "gn:dem":161,
    "gn:feature_class":"P",
    "gn:feature_code":"PPL",
    "gn:name":"Zhongxiancun",
    "gn:population":0,
    "gn:timezone":"Asia/Shanghai",
    "iso:country":"CN",
    "name:zho_x_preferred":[
        "\u4e2d\u9c9c\u6751"
    ],
    "wof:name":"Zhongxiancun",
    "wof:placetype":"locality"
},
  "geometry": {"coordinates":[130.81372999999999,45.85935],"type":"Point"}
}