{
  "type": "Feature",
  "properties": {
    "gn:admin1_code":"14.0",
    "gn:asciiname":"Dagdong",
    "gn:country_code":"CN",
    "gn:dem":3816,
    "gn:feature_class":"P",
    "gn:feature_code":"PPL",
    "gn:name":"Dagdong",
    "gn:population":0,
    "gn:timezone":"Asia/Urumqi",
    "iso:country":"CN",
    "name:bod_x_preferred":[
        "Dagdong"
    ],
    "name:und_x_variant":[
        "Dadong"
    ],
    "name:zho_x_preferred":[
        "\u8fbe\u4e1c"
    ],
    "name:zho_x_variant":[
        "\u5927\u4e1c"
    ],
    "wof:name":"Dagdong",
    "wof:placetype":"locality"
},
  "geometry": {"coordinates":[91.04395,29.50866],"type":"Point"}
}