{
  "type": "Feature",
  "properties": {
    "gn:admin1_code":"29.0",
    "gn:asciiname":"Wujiayao",
    "gn:country_code":"CN",
    "gn:dem":1861,
    "gn:feature_class":"P",
    "gn:feature_code":"PPL",
    "gn:name":"Wujiayao",
    "gn:population":0,
    "gn:timezone":"Asia/Shanghai",
    "iso:country":"CN",
    "name:zho_x_preferred":[
        "\u4f0d\u5bb6\u7a91"
    ],
    "wof:name":"Wujiayao",
    "wof:placetype":"locality"
},
  "geometry": {"coordinates":[101.46899999999999,25.3327],"type":"Point"}
}