{
  "type": "Feature",
  "properties": {
    "gn:admin1_code":"16.0",
    "gn:asciiname":"Doudiling",
    "gn:country_code":"CN",
    "gn:dem":152,
    "gn:feature_class":"P",
    "gn:feature_code":"PPL",
    "gn:name":"Doudiling",
    "gn:population":0,
    "gn:timezone":"Asia/Shanghai",
    "iso:country":"CN",
    "name:zho_x_preferred":[
        "\u8c46\u5730\u5cad"
    ],
    "wof:name":"Doudiling",
    "wof:placetype":"locality"
},
  "geometry": {"coordinates":[110.852,24.5025],"type":"Point"}
}