{
  "type": "Feature",
  "properties": {
    "gn:admin1_code":"32.0",
    "gn:asciiname":"Qinglin",
    "gn:country_code":"CN",
    "gn:dem":1641,
    "gn:feature_class":"P",
    "gn:feature_code":"PPL",
    "gn:name":"Qinglin",
    "gn:population":0,
    "gn:timezone":"Asia/Shanghai",
    "iso:country":"CN",
    "name:und_x_variant":[
        "\u9752\u6797"
    ],
    "wof:name":"Qinglin",
    "wof:placetype":"locality"
},
  "geometry": {"coordinates":[106.20256999999999,32.58934],"type":"Point"}
}