{
  "type": "Feature",
  "properties": {
    "gn:admin1_code":"12.0",
    "gn:asciiname":"Sidugang",
    "gn:country_code":"CN",
    "gn:dem":555,
    "gn:feature_class":"P",
    "gn:feature_code":"PPL",
    "gn:name":"Sidugang",
    "gn:population":0,
    "gn:timezone":"Asia/Shanghai",
    "iso:country":"CN",
    "name:zho_x_preferred":[
        "Sidugang"
    ],
    "name:zho_x_variant":[
        "\u56db\u90fd\u6e2f"
    ],
    "wof:name":"Sidugang",
    "wof:placetype":"locality"
},
  "geometry": {"coordinates":[114.35169999999999,29.34971],"type":"Point"}
}