{
  "type": "Feature",
  "properties": {
    "gn:admin1_code":"21.0",
    "gn:asciiname":"Zhangyaoxian",
    "gn:country_code":"CN",
    "gn:dem":1784,
    "gn:feature_class":"P",
    "gn:feature_code":"PPL",
    "gn:name":"Zhangyaoxian",
    "gn:population":0,
    "gn:timezone":"Asia/Shanghai",
    "iso:country":"CN",
    "name:zho_x_preferred":[
        "\u5f20\u5d3e\u5c98"
    ],
    "wof:name":"Zhangyaoxian",
    "wof:placetype":"locality"
},
  "geometry": {"coordinates":[106.61993,36.06948],"type":"Point"}
}