{
  "type": "Feature",
  "properties": {
    "gn:admin1_code":"32.0",
    "gn:asciiname":"Ranfangwan",
    "gn:country_code":"CN",
    "gn:dem":492,
    "gn:feature_class":"P",
    "gn:feature_code":"PPL",
    "gn:name":"Ranfangwan",
    "gn:population":0,
    "gn:timezone":"Asia/Shanghai",
    "iso:country":"CN",
    "name:zho_x_preferred":[
        "\u67d3\u623f\u5846"
    ],
    "wof:name":"Ranfangwan",
    "wof:placetype":"locality"
},
  "geometry": {"coordinates":[105.85299999999999,30.6709],"type":"Point"}
}