{
  "type": "Feature",
  "properties": {
    "gn:admin1_code":"33.0",
    "gn:asciiname":"Wuqiao",
    "gn:country_code":"CN",
    "gn:dem":228,
    "gn:feature_class":"P",
    "gn:feature_code":"PPLA4",
    "gn:name":"Wuqiao",
    "gn:population":0,
    "gn:timezone":"Asia/Shanghai",
    "iso:country":"CN",
    "name:und_x_variant":[
        "Wuqiao Jiedao"
    ],
    "name:zho_x_preferred":[
        "\u4e94\u6865"
    ],
    "name:zho_x_variant":[
        "\u4e94\u6865\u8857\u9053"
    ],
    "wof:name":"Wuqiao",
    "wof:placetype":"locality"
},
  "geometry": {"coordinates":[108.45506,30.77967],"type":"Point"}
}