{
  "type": "Feature",
  "properties": {
    "gn:admin1_code":"30",
    "gn:asciiname":"Fengtianzhang",
    "gn:country_code":"CN",
    "gn:dem":724,
    "gn:feature_class":"P",
    "gn:feature_code":"PPL",
    "gn:name":"Fengtianzhang",
    "gn:population":0,
    "gn:timezone":"Asia/Shanghai",
    "iso:country":"CN",
    "name:zho_x_preferred":[
        "\u4e30\u7530\u5d82"
    ],
    "wof:name":"Fengtianzhang",
    "wof:placetype":"locality"
},
  "geometry": {"coordinates":[116.13892,23.89716],"type":"Point"}
}