{
  "type": "Feature",
  "properties": {
    "gn:admin1_code":"19.0",
    "gn:asciiname":"Lamadong",
    "gn:country_code":"CN",
    "gn:dem":280,
    "gn:feature_class":"P",
    "gn:feature_code":"PPL",
    "gn:name":"Lamadong",
    "gn:population":0,
    "gn:timezone":"Asia/Shanghai",
    "iso:country":"CN",
    "name:zho_x_preferred":[
        "\u5587\u561b\u6d1e"
    ],
    "wof:name":"Lamadong",
    "wof:placetype":"locality"
},
  "geometry": {"coordinates":[121.087,41.9869],"type":"Point"}
}