{
  "type": "Feature",
  "properties": {
    "gn:admin1_code":"7",
    "gn:asciiname":"Shanlian",
    "gn:country_code":"CN",
    "gn:dem":238,
    "gn:feature_class":"P",
    "gn:feature_code":"PPL",
    "gn:name":"Shanlian",
    "gn:population":0,
    "gn:timezone":"Asia/Shanghai",
    "iso:country":"CN",
    "name:mlg_x_preferred":[
        "Shanlian"
    ],
    "name:und_x_variant":[
        "\u5c71\u8fde"
    ],
    "name:zho_x_preferred":[
        "\u5584\u740f\u9547"
    ],
    "wof:name":"Shanlian",
    "wof:placetype":"locality"
},
  "geometry": {"coordinates":[118.05486000000001,26.21249],"type":"Point"}
}