{
  "type": "Feature",
  "properties": {
    "gn:admin1_code":"14.0",
    "gn:asciiname":"Gaibanang",
    "gn:country_code":"CN",
    "gn:dem":4420,
    "gn:feature_class":"P",
    "gn:feature_code":"PPL",
    "gn:name":"Gaibanang",
    "gn:population":0,
    "gn:timezone":"Asia/Urumqi",
    "iso:country":"CN",
    "name:zho_x_preferred":[
        "\u6539\u5df4\u56ca"
    ],
    "wof:name":"Gaibanang",
    "wof:placetype":"locality"
},
  "geometry": {"coordinates":[94.95285,30.89006],"type":"Point"}
}