{
  "type": "Feature",
  "properties": {
    "gn:admin1_code":"25",
    "gn:asciiname":"Donghetou",
    "gn:country_code":"CN",
    "gn:dem":38,
    "gn:feature_class":"P",
    "gn:feature_code":"PPL",
    "gn:name":"Donghetou",
    "gn:population":0,
    "gn:timezone":"Asia/Shanghai",
    "iso:country":"CN",
    "name:zho_x_preferred":[
        "\u4e1c\u6cb3\u5934"
    ],
    "wof:name":"Donghetou",
    "wof:placetype":"locality"
},
  "geometry": {"coordinates":[118.083,34.7072],"type":"Point"}
}