{
  "type": "Feature",
  "properties": {
    "gn:admin1_code":"29.0",
    "gn:asciiname":"Longbeng",
    "gn:country_code":"CN",
    "gn:dem":1284,
    "gn:feature_class":"P",
    "gn:feature_code":"PPL",
    "gn:name":"Longbeng",
    "gn:population":0,
    "gn:timezone":"Asia/Shanghai",
    "iso:country":"CN",
    "name:zho_x_preferred":[
        "\u9f99\u868c"
    ],
    "wof:name":"Longbeng",
    "wof:placetype":"locality"
},
  "geometry": {"coordinates":[99.9854,22.2425],"type":"Point"}
}