{
  "type": "Feature",
  "properties": {
    "gn:admin1_code":"3.0",
    "gn:asciiname":"Zhelingxia",
    "gn:country_code":"CN",
    "gn:dem":78,
    "gn:feature_class":"P",
    "gn:feature_code":"PPL",
    "gn:name":"Zhelingxia",
    "gn:population":0,
    "gn:timezone":"Asia/Shanghai",
    "iso:country":"CN",
    "name:zho_x_preferred":[
        "\u54f2\u5cad\u4e0b"
    ],
    "wof:name":"Zhelingxia",
    "wof:placetype":"locality"
},
  "geometry": {"coordinates":[114.833,27.9111],"type":"Point"}
}