{
  "type": "Feature",
  "properties": {
    "gn:admin1_code":"29.0",
    "gn:asciiname":"Zhanniu",
    "gn:country_code":"CN",
    "gn:dem":1600,
    "gn:feature_class":"P",
    "gn:feature_code":"PPL",
    "gn:name":"Zhanniu",
    "gn:population":0,
    "gn:timezone":"Asia/Shanghai",
    "iso:country":"CN",
    "name:zho_x_preferred":[
        "\u6cbe\u725b"
    ],
    "wof:name":"Zhanniu",
    "wof:placetype":"locality"
},
  "geometry": {"coordinates":[101.009,24.42],"type":"Point"}
}