{
  "type": "Feature",
  "properties": {
    "gn:admin1_code":"5.0",
    "gn:asciiname":"Renjia Weizi",
    "gn:country_code":"CN",
    "gn:dem":133,
    "gn:feature_class":"P",
    "gn:feature_code":"PPL",
    "gn:name":"Renjia Weizi",
    "gn:population":0,
    "gn:timezone":"Asia/Shanghai",
    "iso:country":"CN",
    "name:zho_x_preferred":[
        "\u4efb\u5bb6\u56f4\u5b50"
    ],
    "wof:name":"Renjia Weizi",
    "wof:placetype":"locality"
},
  "geometry": {"coordinates":[123.38993000000001,46.08127],"type":"Point"}
}