{
  "type": "Feature",
  "properties": {
    "gn:admin1_code":"7",
    "gn:asciiname":"Tadou",
    "gn:country_code":"CN",
    "gn:dem":335,
    "gn:feature_class":"P",
    "gn:feature_code":"PPL",
    "gn:name":"Tadou",
    "gn:population":0,
    "gn:timezone":"Asia/Shanghai",
    "iso:country":"CN",
    "name:zho_x_preferred":[
        "\u5854\u515c"
    ],
    "wof:name":"Tadou",
    "wof:placetype":"locality"
},
  "geometry": {"coordinates":[118.39779,25.59735],"type":"Point"}
}