{
  "type": "Feature",
  "properties": {
    "gn:admin1_code":"31.0",
    "gn:asciiname":"Tankangzai",
    "gn:country_code":"CN",
    "gn:dem":25,
    "gn:feature_class":"P",
    "gn:feature_code":"PPL",
    "gn:name":"Tankangzai",
    "gn:population":0,
    "gn:timezone":"Asia/Shanghai",
    "iso:country":"CN",
    "name:zho_x_preferred":[
        "\u8c2d\u5eb7\u4ed4"
    ],
    "wof:name":"Tankangzai",
    "wof:placetype":"locality"
},
  "geometry": {"coordinates":[110.50136000000001,19.93066],"type":"Point"}
}