{
  "type": "Feature",
  "properties": {
    "gn:admin1_code":"32.0",
    "gn:asciiname":"Zhuwo",
    "gn:country_code":"CN",
    "gn:dem":3602,
    "gn:feature_class":"P",
    "gn:feature_code":"PPL",
    "gn:name":"Zhuwo",
    "gn:population":0,
    "gn:timezone":"Asia/Shanghai",
    "iso:country":"CN",
    "name:zho_x_preferred":[
        "\u6731\u7a9d"
    ],
    "wof:name":"Zhuwo",
    "wof:placetype":"locality"
},
  "geometry": {"coordinates":[100.68899999999999,31.892],"type":"Point"}
}