{
  "type": "Feature",
  "properties": {
    "gn:admin1_code":"3.0",
    "gn:asciiname":"Niaoling",
    "gn:country_code":"CN",
    "gn:dem":110,
    "gn:feature_class":"P",
    "gn:feature_code":"PPL",
    "gn:name":"Niaoling",
    "gn:population":0,
    "gn:timezone":"Asia/Shanghai",
    "iso:country":"CN",
    "name:und_x_variant":[
        "\u9e1f\u5cad"
    ],
    "wof:name":"Niaoling",
    "wof:placetype":"locality"
},
  "geometry": {"coordinates":[116.17010000000001,27.3871],"type":"Point"}
}