{
  "type": "Feature",
  "properties": {
    "gn:admin1_code":"19.0",
    "gn:asciiname":"Rongjiakanzi",
    "gn:country_code":"CN",
    "gn:dem":183,
    "gn:feature_class":"P",
    "gn:feature_code":"PPL",
    "gn:name":"Rongjiakanzi",
    "gn:population":0,
    "gn:timezone":"Asia/Shanghai",
    "iso:country":"CN",
    "name:und_x_variant":[
        "\u69ae\u5bb6\u574e\u5b50"
    ],
    "name:zho_x_preferred":[
        "\u69ae\u5bb6\u574e\u5b50"
    ],
    "wof:name":"Rongjiakanzi",
    "wof:placetype":"locality"
},
  "geometry": {"coordinates":[124.47575000000001,40.77566],"type":"Point"}
}