{
  "type": "Feature",
  "properties": {
    "gn:admin1_code":"12.0",
    "gn:asciiname":"Tujialing",
    "gn:country_code":"CN",
    "gn:dem":1488,
    "gn:feature_class":"P",
    "gn:feature_code":"PPL",
    "gn:name":"Tujialing",
    "gn:population":0,
    "gn:timezone":"Asia/Shanghai",
    "iso:country":"CN",
    "name:zho_x_preferred":[
        "\u6d82\u5bb6\u5cad"
    ],
    "wof:name":"Tujialing",
    "wof:placetype":"locality"
},
  "geometry": {"coordinates":[110.50418000000001,30.47518],"type":"Point"}
}