{
  "type": "Feature",
  "properties": {
    "gn:admin1_code":"9.0",
    "gn:asciiname":"Dafeng",
    "gn:country_code":"CN",
    "gn:dem":61,
    "gn:feature_class":"P",
    "gn:feature_code":"PPL",
    "gn:name":"Dafeng",
    "gn:population":0,
    "gn:timezone":"Asia/Shanghai",
    "iso:country":"CN",
    "name:zho_x_preferred":[
        "\u5927\u51af"
    ],
    "wof:name":"Dafeng",
    "wof:placetype":"locality"
},
  "geometry": {"coordinates":[114.69052000000001,35.80314],"type":"Point"}
}