{
  "type": "Feature",
  "properties": {
    "gn:admin1_code":"30",
    "gn:asciiname":"Shishan",
    "gn:country_code":"CN",
    "gn:dem":35,
    "gn:feature_class":"P",
    "gn:feature_code":"PPL",
    "gn:name":"Shishan",
    "gn:population":0,
    "gn:timezone":"Asia/Shanghai",
    "iso:country":"CN",
    "name:zho_x_preferred":[
        "\u72ee\u5c71"
    ],
    "wof:name":"Shishan",
    "wof:placetype":"locality"
},
  "geometry": {"coordinates":[112.91441,22.00723],"type":"Point"}
}