{
  "type": "Feature",
  "properties": {
    "gn:admin1_code":"24",
    "gn:asciiname":"Hangcun",
    "gn:cc2":"CN",
    "gn:country_code":"CN",
    "gn:dem":1245,
    "gn:feature_class":"P",
    "gn:feature_code":"PPL",
    "gn:name":"Hangcun",
    "gn:population":0,
    "gn:timezone":"Asia/Shanghai",
    "iso:country":"CN",
    "name:und_x_variant":[
        "Hang-ts\u2019un",
        "Hangcun"
    ],
    "wof:name":"Hangcun",
    "wof:placetype":"locality"
},
  "geometry": {"coordinates":[112.21666999999999,36.66667],"type":"Point"}
}