{
  "type": "Feature",
  "properties": {
    "gn:admin1_code":"9.0",
    "gn:asciiname":"Liulindun",
    "gn:country_code":"CN",
    "gn:dem":79,
    "gn:feature_class":"P",
    "gn:feature_code":"PPL",
    "gn:name":"Liulindun",
    "gn:population":0,
    "gn:timezone":"Asia/Shanghai",
    "iso:country":"CN",
    "name:zho_x_preferred":[
        "\u67f3\u6797\u58a9"
    ],
    "wof:name":"Liulindun",
    "wof:placetype":"locality"
},
  "geometry": {"coordinates":[114.43470000000001,31.81701],"type":"Point"}
}