{
  "type": "Feature",
  "properties": {
    "gn:admin1_code":"19.0",
    "gn:asciiname":"Houhuafang",
    "gn:country_code":"CN",
    "gn:dem":16,
    "gn:feature_class":"P",
    "gn:feature_code":"PPL",
    "gn:name":"Houhuafang",
    "gn:population":0,
    "gn:timezone":"Asia/Shanghai",
    "iso:country":"CN",
    "name:und_x_variant":[
        "\u540e\u82b1\u623f"
    ],
    "name:zho_x_preferred":[
        "\u540e\u82b1\u623f"
    ],
    "wof:name":"Houhuafang",
    "wof:placetype":"locality"
},
  "geometry": {"coordinates":[122.14979,39.36592],"type":"Point"}
}