{
  "type": "Feature",
  "properties": {
    "gn:admin1_code":"16.0",
    "gn:asciiname":"Shangshiqiao",
    "gn:country_code":"CN",
    "gn:dem":56,
    "gn:feature_class":"P",
    "gn:feature_code":"PPL",
    "gn:name":"Shangshiqiao",
    "gn:population":0,
    "gn:timezone":"Asia/Shanghai",
    "iso:country":"CN",
    "name:zho_x_preferred":[
        "\u4e0a\u77f3\u6865"
    ],
    "wof:name":"Shangshiqiao",
    "wof:placetype":"locality"
},
  "geometry": {"coordinates":[108.92,22.1704],"type":"Point"}
}