{
  "type": "Feature",
  "properties": {
    "gn:admin1_code":"4.0",
    "gn:asciiname":"Xiyuxutou",
    "gn:country_code":"CN",
    "gn:dem":6,
    "gn:feature_class":"P",
    "gn:feature_code":"PPL",
    "gn:name":"Xiyuxutou",
    "gn:population":0,
    "gn:timezone":"Asia/Shanghai",
    "iso:country":"CN",
    "name:zho_x_preferred":[
        "Xiyuxutou"
    ],
    "name:zho_x_variant":[
        "\u897f\u4e8e\u5729\u5934"
    ],
    "wof:name":"Xiyuxutou",
    "wof:placetype":"locality"
},
  "geometry": {"coordinates":[119.27148,33.59298],"type":"Point"}
}