{
  "type": "Feature",
  "properties": {
    "gn:admin1_code":"30.0",
    "gn:asciiname":"Sanbencun",
    "gn:country_code":"CN",
    "gn:dem":464,
    "gn:feature_class":"P",
    "gn:feature_code":"PPL",
    "gn:name":"Sanbencun",
    "gn:population":0,
    "gn:timezone":"Asia/Shanghai",
    "iso:country":"CN",
    "name:zho_x_preferred":[
        "Sanbencun"
    ],
    "name:zho_x_variant":[
        "\u4e09\u574c\u6751"
    ],
    "wof:name":"Sanbencun",
    "wof:placetype":"locality"
},
  "geometry": {"coordinates":[114.18221,24.18052],"type":"Point"}
}