{
  "type": "Feature",
  "properties": {
    "gn:admin1_code":"19.0",
    "gn:asciiname":"Daomugou",
    "gn:country_code":"CN",
    "gn:dem":108,
    "gn:feature_class":"P",
    "gn:feature_code":"PPL",
    "gn:name":"Daomugou",
    "gn:population":0,
    "gn:timezone":"Asia/Shanghai",
    "iso:country":"CN",
    "name:zho_x_preferred":[
        "\u53e8\u6728\u6c9f"
    ],
    "wof:name":"Daomugou",
    "wof:placetype":"locality"
},
  "geometry": {"coordinates":[124.19499999999999,40.3799],"type":"Point"}
}