{
  "type": "Feature",
  "properties": {
    "gn:admin1_code":"16",
    "gn:asciiname":"Bajiashan",
    "gn:country_code":"CN",
    "gn:dem":645,
    "gn:feature_class":"P",
    "gn:feature_code":"PPL",
    "gn:name":"Bajiashan",
    "gn:population":0,
    "gn:timezone":"Asia/Shanghai",
    "iso:country":"CN",
    "name:zho_x_preferred":[
        "\u516b\u7532\u5c71"
    ],
    "wof:name":"Bajiashan",
    "wof:placetype":"locality"
},
  "geometry": {"coordinates":[110.967,25.6762],"type":"Point"}
}