{
  "type": "Feature",
  "properties": {
    "gn:admin1_code":"5.0",
    "gn:asciiname":"Heisha Tuozi",
    "gn:country_code":"CN",
    "gn:dem":150,
    "gn:feature_class":"P",
    "gn:feature_code":"PPL",
    "gn:name":"Heisha Tuozi",
    "gn:population":0,
    "gn:timezone":"Asia/Shanghai",
    "iso:country":"CN",
    "name:zho_x_preferred":[
        "\u9ed1\u6c99\u5768\u5b50"
    ],
    "wof:name":"Heisha Tuozi",
    "wof:placetype":"locality"
},
  "geometry": {"coordinates":[125.09947,45.27725],"type":"Point"}
}