{
  "type": "Feature",
  "properties": {
    "gn:admin1_code":"9",
    "gn:asciiname":"Shawo",
    "gn:country_code":"CN",
    "gn:dem":55,
    "gn:feature_class":"P",
    "gn:feature_code":"PPL",
    "gn:name":"Shawo",
    "gn:population":0,
    "gn:timezone":"Asia/Shanghai",
    "iso:country":"CN",
    "name:ceb_x_preferred":[
        "Shawo"
    ],
    "name:zho_x_preferred":[
        "\u6c99\u7a9d"
    ],
    "wof:name":"Shawo",
    "wof:placetype":"locality"
},
  "geometry": {"coordinates":[115.19801,35.85059000000001],"type":"Point"}
}