{
  "type": "Feature",
  "properties": {
    "gn:admin1_code":"7.0",
    "gn:asciiname":"Hengkui",
    "gn:country_code":"CN",
    "gn:dem":667,
    "gn:feature_class":"P",
    "gn:feature_code":"PPL",
    "gn:name":"Hengkui",
    "gn:population":0,
    "gn:timezone":"Asia/Shanghai",
    "iso:country":"CN",
    "name:zho_x_preferred":[
        "\u6a2a\u594e"
    ],
    "wof:name":"Hengkui",
    "wof:placetype":"locality"
},
  "geometry": {"coordinates":[117.51506000000001,25.08513],"type":"Point"}
}