{
  "type": "Feature",
  "properties": {
    "gn:admin1_code":"29.0",
    "gn:asciiname":"Luowuyao",
    "gn:country_code":"CN",
    "gn:dem":1957,
    "gn:feature_class":"P",
    "gn:feature_code":"PPL",
    "gn:name":"Luowuyao",
    "gn:population":0,
    "gn:timezone":"Asia/Shanghai",
    "iso:country":"CN",
    "name:und_x_variant":[
        "Luowume",
        "Luowuyao"
    ],
    "name:zho_x_preferred":[
        "\u7f57\u575e\u4e48"
    ],
    "wof:name":"Luowuyao",
    "wof:placetype":"locality"
},
  "geometry": {"coordinates":[100.377,25.1254],"type":"Point"}
}