{
  "type": "Feature",
  "properties": {
    "gn:admin1_code":"29",
    "gn:asciiname":"Najiaying",
    "gn:country_code":"CN",
    "gn:dem":1797,
    "gn:feature_class":"P",
    "gn:feature_code":"PPLA4",
    "gn:name":"Najiaying",
    "gn:population":0,
    "gn:timezone":"Asia/Shanghai",
    "iso:country":"CN",
    "name:und_x_variant":[
        "Nagu",
        "Nagu Zhen",
        "\u7eb3\u53e4\u9547",
        "Najiaying"
    ],
    "name:zho_x_preferred":[
        "\u7eb3\u5bb6\u8425"
    ],
    "name:zho_x_variant":[
        "\u7eb3\u53e4"
    ],
    "wof:name":"Najiaying",
    "wof:placetype":"locality"
},
  "geometry": {"coordinates":[102.73886,24.18252],"type":"Point"}
}