{
  "type": "Feature",
  "properties": {
    "gn:admin1_code":"32.0",
    "gn:asciiname":"Zaojueshu",
    "gn:country_code":"CN",
    "gn:dem":750,
    "gn:feature_class":"P",
    "gn:feature_code":"PPL",
    "gn:name":"Zaojueshu",
    "gn:population":0,
    "gn:timezone":"Asia/Shanghai",
    "iso:country":"CN",
    "name:zho_x_preferred":[
        "\u7682\u6877\u6811"
    ],
    "wof:name":"Zaojueshu",
    "wof:placetype":"locality"
},
  "geometry": {"coordinates":[104.30574,31.88033],"type":"Point"}
}