{
  "type": "Feature",
  "properties": {
    "gn:admin1_code":"32.0",
    "gn:asciiname":"Macaoxi",
    "gn:country_code":"CN",
    "gn:dem":603,
    "gn:feature_class":"P",
    "gn:feature_code":"PPL",
    "gn:name":"Macaoxi",
    "gn:population":0,
    "gn:timezone":"Asia/Shanghai",
    "iso:country":"CN",
    "name:zho_x_preferred":[
        "\u9a6c\u69fd\u6eaa"
    ],
    "wof:name":"Macaoxi",
    "wof:placetype":"locality"
},
  "geometry": {"coordinates":[106.85899999999999,31.4235],"type":"Point"}
}