{
  "type": "Feature",
  "properties": {
    "gn:admin1_code":"3.0",
    "gn:asciiname":"Wanjiaxiang",
    "gn:country_code":"CN",
    "gn:dem":38,
    "gn:feature_class":"P",
    "gn:feature_code":"PPL",
    "gn:name":"Wanjiaxiang",
    "gn:population":0,
    "gn:timezone":"Asia/Shanghai",
    "iso:country":"CN",
    "name:und_x_variant":[
        "\u4e07\u5bb6\u5df7"
    ],
    "wof:name":"Wanjiaxiang",
    "wof:placetype":"locality"
},
  "geometry": {"coordinates":[116.30117,28.01409],"type":"Point"}
}