{
  "type": "Feature",
  "properties": {
    "gn:admin1_code":"02",
    "gn:asciiname":"Linjiacun",
    "gn:country_code":"CN",
    "gn:dem":56,
    "gn:feature_class":"P",
    "gn:feature_code":"PPL",
    "gn:name":"Linjiacun",
    "gn:population":0,
    "gn:timezone":"Asia/Shanghai",
    "iso:country":"CN",
    "name:und_x_variant":[
        "Linjia",
        "\u6797\u5bb6",
        "Linjiacun"
    ],
    "name:zho_x_preferred":[
        "\u6797\u5bb6"
    ],
    "name:zho_x_variant":[
        "\u6797\u5bb6\u6751"
    ],
    "wof:name":"Linjiacun",
    "wof:placetype":"locality"
},
  "geometry": {"coordinates":[121.3424,29.67517],"type":"Point"}
}