{
  "type": "Feature",
  "properties": {
    "gn:admin1_code":"5.0",
    "gn:asciiname":"Jiangjiadiancun",
    "gn:country_code":"CN",
    "gn:dem":173,
    "gn:feature_class":"P",
    "gn:feature_code":"PPL",
    "gn:name":"Jiangjiadiancun",
    "gn:population":0,
    "gn:timezone":"Asia/Shanghai",
    "iso:country":"CN",
    "name:zho_x_preferred":[
        "\u59dc\u5bb6\u5e97\u6751"
    ],
    "wof:name":"Jiangjiadiancun",
    "wof:placetype":"locality"
},
  "geometry": {"coordinates":[125.96996,44.50204],"type":"Point"}
}