{
  "type": "Feature",
  "properties": {
    "gn:admin1_code":"3.0",
    "gn:asciiname":"Yanwosun",
    "gn:country_code":"CN",
    "gn:dem":28,
    "gn:feature_class":"P",
    "gn:feature_code":"PPL",
    "gn:name":"Yanwosun",
    "gn:population":0,
    "gn:timezone":"Asia/Shanghai",
    "iso:country":"CN",
    "name:und_x_variant":[
        "\u71d5\u7a9d\u5b59"
    ],
    "wof:name":"Yanwosun",
    "wof:placetype":"locality"
},
  "geometry": {"coordinates":[115.88120000000001,28.82607],"type":"Point"}
}