{
  "type": "Feature",
  "properties": {
    "gn:admin1_code":"15.0",
    "gn:asciiname":"Erlangshanxiang",
    "gn:country_code":"CN",
    "gn:dem":1305,
    "gn:feature_class":"P",
    "gn:feature_code":"PPL",
    "gn:name":"Erlangshanxiang",
    "gn:population":0,
    "gn:timezone":"Asia/Shanghai",
    "iso:country":"CN",
    "name:zho_x_preferred":[
        "\u4e8c\u6717\u5c71\u4e61"
    ],
    "wof:name":"Erlangshanxiang",
    "wof:placetype":"locality"
},
  "geometry": {"coordinates":[107.66,35.9879],"type":"Point"}
}