{
  "type": "Feature",
  "properties": {
    "gn:admin1_code":"30",
    "gn:asciiname":"Shitoutan",
    "gn:country_code":"CN",
    "gn:dem":61,
    "gn:feature_class":"P",
    "gn:feature_code":"PPL",
    "gn:name":"Shitoutan",
    "gn:population":0,
    "gn:timezone":"Asia/Shanghai",
    "iso:country":"CN",
    "name:und_x_variant":[
        "\u77f3\u5934\u6f6d",
        "Shitoutan"
    ],
    "wof:name":"Shitoutan",
    "wof:placetype":"locality"
},
  "geometry": {"coordinates":[114.78924000000001,23.32648],"type":"Point"}
}