{
  "type": "Feature",
  "properties": {
    "gn:admin1_code":"14.0",
    "gn:asciiname":"Jiaduicun",
    "gn:country_code":"CN",
    "gn:dem":3182,
    "gn:feature_class":"P",
    "gn:feature_code":"PPL",
    "gn:name":"Jiaduicun",
    "gn:population":0,
    "gn:timezone":"Asia/Urumqi",
    "iso:country":"CN",
    "name:zho_x_preferred":[
        "\u52a0\u5806\u6751"
    ],
    "wof:name":"Jiaduicun",
    "wof:placetype":"locality"
},
  "geometry": {"coordinates":[97.47953,29.75913],"type":"Point"}
}