{
  "type": "Feature",
  "properties": {
    "gn:admin1_code":"32.0",
    "gn:asciiname":"Yurong",
    "gn:country_code":"CN",
    "gn:dem":3610,
    "gn:feature_class":"P",
    "gn:feature_code":"PPL",
    "gn:name":"Yurong",
    "gn:population":0,
    "gn:timezone":"Asia/Shanghai",
    "iso:country":"CN",
    "name:zho_x_preferred":[
        "\u7389\u7ed2"
    ],
    "wof:name":"Yurong",
    "wof:placetype":"locality"
},
  "geometry": {"coordinates":[99.38079999999999,30.3368],"type":"Point"}
}