{
  "type": "Feature",
  "properties": {
    "gn:admin1_code":"5.0",
    "gn:asciiname":"Miaojiajiecun",
    "gn:country_code":"CN",
    "gn:dem":316,
    "gn:feature_class":"P",
    "gn:feature_code":"PPL",
    "gn:name":"Miaojiajiecun",
    "gn:population":0,
    "gn:timezone":"Asia/Shanghai",
    "iso:country":"CN",
    "name:zho_x_preferred":[
        "\u82d7\u5bb6\u8857\u6751"
    ],
    "wof:name":"Miaojiajiecun",
    "wof:placetype":"locality"
},
  "geometry": {"coordinates":[126.10697999999999,42.52268],"type":"Point"}
}