{
  "type": "Feature",
  "properties": {
    "gn:admin1_code":"10",
    "gn:asciiname":"Hou'enguan",
    "gn:country_code":"CN",
    "gn:dem":27,
    "gn:feature_class":"P",
    "gn:feature_code":"PPL",
    "gn:name":"Hou\u2019enguan",
    "gn:population":0,
    "gn:timezone":"Asia/Shanghai",
    "iso:country":"CN",
    "name:und_x_variant":[
        "Hou\u2019enguan"
    ],
    "name:zho_x_preferred":[
        "\u540e\u6069\u5173"
    ],
    "wof:name":"Hou'enguan",
    "wof:placetype":"locality"
},
  "geometry": {"coordinates":[115.483,37.4685],"type":"Point"}
}