{
  "type": "Feature",
  "properties": {
    "gn:admin1_code":"24",
    "gn:asciiname":"Huabeitun",
    "gn:country_code":"CN",
    "gn:dem":1456,
    "gn:feature_class":"P",
    "gn:feature_code":"PPLA4",
    "gn:name":"Huabeitun",
    "gn:population":0,
    "gn:timezone":"Asia/Shanghai",
    "iso:country":"CN",
    "name:und_x_variant":[
        "Hua-pei-ts\u2019un",
        "Hua-pei-t\u2019un",
        "Huabeitun",
        "\u5316\u5317\u5c6f",
        "Huabeitun Xiang",
        "\u5316\u5317\u5c6f\u4e61"
    ],
    "wof:name":"Huabeitun",
    "wof:placetype":"locality"
},
  "geometry": {"coordinates":[112.10052,38.69885],"type":"Point"}
}