{
  "type": "Feature",
  "properties": {
    "gn:admin1_code":"14.0",
    "gn:asciiname":"Yasha",
    "gn:country_code":"CN",
    "gn:dem":4507,
    "gn:feature_class":"P",
    "gn:feature_code":"PPL",
    "gn:name":"Yasha",
    "gn:population":0,
    "gn:timezone":"Asia/Urumqi",
    "iso:country":"CN",
    "name:ceb_x_preferred":[
        "Yasha"
    ],
    "name:swe_x_preferred":[
        "Yasha"
    ],
    "name:zho_x_preferred":[
        "\u4e9a\u838e"
    ],
    "wof:name":"Yasha",
    "wof:placetype":"locality"
},
  "geometry": {"coordinates":[90.81356,28.98565],"type":"Point"}
}