{
  "type": "Feature",
  "properties": {
    "gn:admin1_code":"29.0",
    "gn:asciiname":"Bahong",
    "gn:country_code":"CN",
    "gn:dem":2229,
    "gn:feature_class":"P",
    "gn:feature_code":"PPL",
    "gn:name":"Bahong",
    "gn:population":0,
    "gn:timezone":"Asia/Shanghai",
    "iso:country":"CN",
    "name:und_x_variant":[
        "\u5df4\u6d2a"
    ],
    "wof:name":"Bahong",
    "wof:placetype":"locality"
},
  "geometry": {"coordinates":[102.61524,25.83622],"type":"Point"}
}