{
  "type": "Feature",
  "properties": {
    "gn:admin1_code":"32.0",
    "gn:asciiname":"Danzhamu",
    "gn:country_code":"CN",
    "gn:dem":2282,
    "gn:feature_class":"P",
    "gn:feature_code":"PPL",
    "gn:name":"Danzhamu",
    "gn:population":0,
    "gn:timezone":"Asia/Shanghai",
    "iso:country":"CN",
    "name:zho_x_preferred":[
        "\u4e39\u624e\u6728"
    ],
    "wof:name":"Danzhamu",
    "wof:placetype":"locality"
},
  "geometry": {"coordinates":[102.05500000000001,31.511],"type":"Point"}
}