{
  "type": "Feature",
  "properties": {
    "gn:admin1_code":"02",
    "gn:asciiname":"Wanliang",
    "gn:country_code":"CN",
    "gn:dem":38,
    "gn:feature_class":"P",
    "gn:feature_code":"PPL",
    "gn:name":"Wanliang",
    "gn:population":0,
    "gn:timezone":"Asia/Shanghai",
    "iso:country":"CN",
    "name:und_x_variant":[
        "\u4e07\u826f"
    ],
    "wof:name":"Wanliang",
    "wof:placetype":"locality"
},
  "geometry": {"coordinates":[122.40313,30.43523],"type":"Point"}
}