{
  "type": "Feature",
  "properties": {
    "gn:admin1_code":"11.0",
    "gn:asciiname":"Shuimanxi",
    "gn:country_code":"CN",
    "gn:dem":180,
    "gn:feature_class":"P",
    "gn:feature_code":"PPL",
    "gn:name":"Shuimanxi",
    "gn:population":0,
    "gn:timezone":"Asia/Shanghai",
    "iso:country":"CN",
    "name:zho_x_preferred":[
        "\u6c34\u6f2b\u6eaa"
    ],
    "wof:name":"Shuimanxi",
    "wof:placetype":"locality"
},
  "geometry": {"coordinates":[109.86362,27.88421],"type":"Point"}
}