{
  "type": "Feature",
  "properties": {
    "gn:admin1_code":"15.0",
    "gn:asciiname":"Xiadonggou",
    "gn:country_code":"CN",
    "gn:dem":1232,
    "gn:feature_class":"P",
    "gn:feature_code":"PPL",
    "gn:name":"Xiadonggou",
    "gn:population":0,
    "gn:timezone":"Asia/Shanghai",
    "iso:country":"CN",
    "name:zho_x_preferred":[
        "\u4e0b\u4e1c\u6c9f"
    ],
    "wof:name":"Xiadonggou",
    "wof:placetype":"locality"
},
  "geometry": {"coordinates":[98.91719999999999,40.22],"type":"Point"}
}