{
  "type": "Feature",
  "properties": {
    "gn:admin1_code":"22.0",
    "gn:asciiname":"Xiying Ercun",
    "gn:country_code":"CN",
    "gn:dem":24,
    "gn:feature_class":"P",
    "gn:feature_code":"PPL",
    "gn:name":"Xiying Ercun",
    "gn:population":0,
    "gn:timezone":"Asia/Shanghai",
    "iso:country":"CN",
    "name:zho_x_preferred":[
        "\u897f\u8425\u4e8c\u6751"
    ],
    "wof:name":"Xiying Ercun",
    "wof:placetype":"locality"
},
  "geometry": {"coordinates":[116.61624999999999,39.65845],"type":"Point"}
}