{
  "type": "Feature",
  "properties": {
    "gn:admin1_code":"1.0",
    "gn:asciiname":"Jiaozhuang",
    "gn:country_code":"CN",
    "gn:dem":9,
    "gn:feature_class":"P",
    "gn:feature_code":"PPL",
    "gn:name":"Jiaozhuang",
    "gn:population":0,
    "gn:timezone":"Asia/Shanghai",
    "iso:country":"CN",
    "name:zho_x_preferred":[
        "\u7126\u5e84"
    ],
    "wof:name":"Jiaozhuang",
    "wof:placetype":"locality"
},
  "geometry": {"coordinates":[118.41964,31.44024000000001],"type":"Point"}
}