{
  "type": "Feature",
  "properties": {
    "gn:admin1_code":"1.0",
    "gn:asciiname":"Songfancun",
    "gn:country_code":"CN",
    "gn:dem":187,
    "gn:feature_class":"P",
    "gn:feature_code":"PPL",
    "gn:name":"Songfancun",
    "gn:population":0,
    "gn:timezone":"Asia/Shanghai",
    "iso:country":"CN",
    "name:zho_x_preferred":[
        "\u5b8b\u7548\u6751"
    ],
    "wof:name":"Songfancun",
    "wof:placetype":"locality"
},
  "geometry": {"coordinates":[115.75906999999999,31.46947],"type":"Point"}
}