{
  "type": "Feature",
  "properties": {
    "gn:admin1_code":"10.0",
    "gn:asciiname":"Muzhuang",
    "gn:country_code":"CN",
    "gn:dem":77,
    "gn:feature_class":"P",
    "gn:feature_code":"PPL",
    "gn:name":"Muzhuang",
    "gn:population":0,
    "gn:timezone":"Asia/Shanghai",
    "iso:country":"CN",
    "name:und_x_variant":[
        "\u6728\u5e84"
    ],
    "wof:name":"Muzhuang",
    "wof:placetype":"locality"
},
  "geometry": {"coordinates":[114.60137,38.20268],"type":"Point"}
}