{
  "type": "Feature",
  "properties": {
    "gn:admin1_code":"12.0",
    "gn:asciiname":"Jiangjiafan",
    "gn:country_code":"CN",
    "gn:dem":55,
    "gn:feature_class":"P",
    "gn:feature_code":"PPL",
    "gn:name":"Jiangjiafan",
    "gn:population":0,
    "gn:timezone":"Asia/Shanghai",
    "iso:country":"CN",
    "name:zho_x_preferred":[
        "\u6c5f\u5bb6\u7548"
    ],
    "wof:name":"Jiangjiafan",
    "wof:placetype":"locality"
},
  "geometry": {"coordinates":[114.06263,31.3654],"type":"Point"}
}