{
  "type": "Feature",
  "properties": {
    "gn:admin1_code":"10.0",
    "gn:asciiname":"Xujiazhuang",
    "gn:country_code":"CN",
    "gn:dem":693,
    "gn:feature_class":"P",
    "gn:feature_code":"PPL",
    "gn:name":"Xujiazhuang",
    "gn:population":0,
    "gn:timezone":"Asia/Shanghai",
    "iso:country":"CN",
    "name:zho_x_preferred":[
        "\u8bb8\u5bb6\u5e84"
    ],
    "wof:name":"Xujiazhuang",
    "wof:placetype":"locality"
},
  "geometry": {"coordinates":[114.82290999999999,40.74526],"type":"Point"}
}