{
  "type": "Feature",
  "properties": {
    "gn:admin1_code":"3",
    "gn:asciiname":"Xinlimen",
    "gn:country_code":"CN",
    "gn:dem":139,
    "gn:feature_class":"P",
    "gn:feature_code":"PPL",
    "gn:name":"Xinlimen",
    "gn:population":0,
    "gn:timezone":"Asia/Shanghai",
    "iso:country":"CN",
    "name:zho_x_preferred":[
        "\u65b0\u793c\u95e8"
    ],
    "wof:name":"Xinlimen",
    "wof:placetype":"locality"
},
  "geometry": {"coordinates":[114.646,26.8844],"type":"Point"}
}