{
  "type": "Feature",
  "properties": {
    "gn:admin1_code":"8.0",
    "gn:asciiname":"Sunbucun",
    "gn:country_code":"CN",
    "gn:dem":136,
    "gn:feature_class":"P",
    "gn:feature_code":"PPL",
    "gn:name":"Sunbucun",
    "gn:population":0,
    "gn:timezone":"Asia/Shanghai",
    "iso:country":"CN",
    "name:zho_x_preferred":[
        "\u5b59\u5821\u6751"
    ],
    "wof:name":"Sunbucun",
    "wof:placetype":"locality"
},
  "geometry": {"coordinates":[126.70910000000001,46.1888],"type":"Point"}
}