{
  "type": "Feature",
  "properties": {
    "gn:admin1_code":"30.0",
    "gn:asciiname":"Nanhua",
    "gn:country_code":"CN",
    "gn:dem":20,
    "gn:feature_class":"P",
    "gn:feature_code":"PPL",
    "gn:name":"Nanhua",
    "gn:population":0,
    "gn:timezone":"Asia/Shanghai",
    "iso:country":"CN",
    "name:deu_x_preferred":[
        "Nanhua"
    ],
    "name:zho_x_preferred":[
        "\u5357\u534e"
    ],
    "wof:name":"Nanhua",
    "wof:placetype":"locality"
},
  "geometry": {"coordinates":[112.82653999999999,22.29953],"type":"Point"}
}