{
  "type": "Feature",
  "properties": {
    "gn:admin1_code":"15.0",
    "gn:asciiname":"Huanglatan",
    "gn:country_code":"CN",
    "gn:dem":2902,
    "gn:feature_class":"P",
    "gn:feature_code":"PPL",
    "gn:name":"Huanglatan",
    "gn:population":0,
    "gn:timezone":"Asia/Shanghai",
    "iso:country":"CN",
    "name:und_x_variant":[
        "\u9ec4\u524c\u6ee9"
    ],
    "wof:name":"Huanglatan",
    "wof:placetype":"locality"
},
  "geometry": {"coordinates":[102.57801000000001,35.19535],"type":"Point"}
}