{
  "type": "Feature",
  "properties": {
    "gn:admin1_code":"33.0",
    "gn:asciiname":"Jianlong",
    "gn:country_code":"CN",
    "gn:dem":276,
    "gn:feature_class":"P",
    "gn:feature_code":"PPLA4",
    "gn:name":"Jianlong",
    "gn:population":0,
    "gn:timezone":"Asia/Shanghai",
    "iso:country":"CN",
    "name:und_x_variant":[
        "Jianlong Xiang"
    ],
    "name:zho_x_preferred":[
        "\u5065\u9f99"
    ],
    "name:zho_x_variant":[
        "\u5065\u9f99\u4e61"
    ],
    "wof:name":"Jianlong",
    "wof:placetype":"locality"
},
  "geometry": {"coordinates":[106.18522,29.3586],"type":"Point"}
}