{
  "type": "Feature",
  "properties": {
    "gn:admin1_code":"30",
    "gn:asciiname":"Maichen",
    "gn:country_code":"CN",
    "gn:dem":24,
    "gn:feature_class":"P",
    "gn:feature_code":"PPLA4",
    "gn:name":"Maichen",
    "gn:population":0,
    "gn:timezone":"Asia/Urumqi",
    "iso:country":"CN",
    "name:und_x_variant":[
        "\u8fc8\u9648",
        "Maichen Zhen",
        "\u8fc8\u9648\u9547"
    ],
    "name:zho_x_preferred":[
        "Mai-ch\u2019en-hs\u00fc"
    ],
    "name:zho_x_variant":[
        "\u8fc8\u9648"
    ],
    "wof:name":"Maichen",
    "wof:placetype":"locality"
},
  "geometry": {"coordinates":[109.99481000000002,20.335],"type":"Point"}
}