{
  "type": "Feature",
  "properties": {
    "gn:admin1_code":"21.0",
    "gn:asciiname":"Huolonggou",
    "gn:country_code":"CN",
    "gn:dem":1917,
    "gn:feature_class":"P",
    "gn:feature_code":"PPL",
    "gn:name":"Huolonggou",
    "gn:population":0,
    "gn:timezone":"Asia/Shanghai",
    "iso:country":"CN",
    "name:zho_x_preferred":[
        "\u706b\u9f99\u6c9f"
    ],
    "wof:name":"Huolonggou",
    "wof:placetype":"locality"
},
  "geometry": {"coordinates":[106.30800000000001,35.8557],"type":"Point"}
}