{
  "type": "Feature",
  "properties": {
    "gn:admin1_code":"29.0",
    "gn:asciiname":"Sichuandi",
    "gn:country_code":"CN",
    "gn:dem":2030,
    "gn:feature_class":"P",
    "gn:feature_code":"PPL",
    "gn:name":"Sichuandi",
    "gn:population":0,
    "gn:timezone":"Asia/Shanghai",
    "iso:country":"CN",
    "name:zho_x_preferred":[
        "\u56db\u5ddd\u5730"
    ],
    "wof:name":"Sichuandi",
    "wof:placetype":"locality"
},
  "geometry": {"coordinates":[99.3347,25.2305],"type":"Point"}
}