{
  "type": "Feature",
  "properties": {
    "gn:admin1_code":"11.0",
    "gn:asciiname":"Pujialing",
    "gn:country_code":"CN",
    "gn:dem":545,
    "gn:feature_class":"P",
    "gn:feature_code":"PPL",
    "gn:name":"Pujialing",
    "gn:population":0,
    "gn:timezone":"Asia/Shanghai",
    "iso:country":"CN",
    "name:zho_x_preferred":[
        "\u84b2\u5bb6\u5cad"
    ],
    "wof:name":"Pujialing",
    "wof:placetype":"locality"
},
  "geometry": {"coordinates":[110.51073,27.71655],"type":"Point"}
}