{
  "type": "Feature",
  "properties": {
    "gn:admin1_code":"26",
    "gn:asciiname":"Longguo",
    "gn:country_code":"CN",
    "gn:dem":414,
    "gn:feature_class":"P",
    "gn:feature_code":"PPL",
    "gn:name":"Longguo",
    "gn:population":0,
    "gn:timezone":"Asia/Shanghai",
    "iso:country":"CN",
    "name:zho_x_preferred":[
        "\u9f99\u8fc7"
    ],
    "wof:name":"Longguo",
    "wof:placetype":"locality"
},
  "geometry": {"coordinates":[108.32832999999999,34.20333],"type":"Point"}
}