{
  "type": "Feature",
  "properties": {
    "gn:admin1_code":"32.0",
    "gn:asciiname":"Teluoze",
    "gn:country_code":"CN",
    "gn:dem":2426,
    "gn:feature_class":"P",
    "gn:feature_code":"PPL",
    "gn:name":"Teluoze",
    "gn:population":0,
    "gn:timezone":"Asia/Shanghai",
    "iso:country":"CN",
    "name:zho_x_preferred":[
        "\u7279\u843d\u5219"
    ],
    "wof:name":"Teluoze",
    "wof:placetype":"locality"
},
  "geometry": {"coordinates":[102.58499999999999,27.7648],"type":"Point"}
}