{
  "type": "Feature",
  "properties": {
    "gn:admin1_code":"10",
    "gn:asciiname":"Chejiaying",
    "gn:country_code":"CN",
    "gn:dem":990,
    "gn:feature_class":"P",
    "gn:feature_code":"PPL",
    "gn:name":"Chejiaying",
    "gn:population":0,
    "gn:timezone":"Asia/Shanghai",
    "iso:country":"CN",
    "name:zho_x_preferred":[
        "\u8f66\u5bb6\u8425"
    ],
    "wof:name":"Chejiaying",
    "wof:placetype":"locality"
},
  "geometry": {"coordinates":[118.06395999999999,42.14286],"type":"Point"}
}