{
  "type": "Feature",
  "properties": {
    "gn:admin1_code":"14.0",
    "gn:asciiname":"Qiaogui",
    "gn:country_code":"CN",
    "gn:dem":4873,
    "gn:feature_class":"P",
    "gn:feature_code":"PPL",
    "gn:name":"Qiaogui",
    "gn:population":0,
    "gn:timezone":"Asia/Urumqi",
    "iso:country":"CN",
    "name:zho_x_preferred":[
        "\u5de7\u5f52"
    ],
    "wof:name":"Qiaogui",
    "wof:placetype":"locality"
},
  "geometry": {"coordinates":[87.6682,28.6848],"type":"Point"}
}