{
  "type": "Feature",
  "properties": {
    "gn:admin1_code":"15.0",
    "gn:asciiname":"Xichuan",
    "gn:country_code":"CN",
    "gn:dem":1592,
    "gn:feature_class":"P",
    "gn:feature_code":"PPL",
    "gn:name":"Xichuan",
    "gn:population":0,
    "gn:timezone":"Asia/Shanghai",
    "iso:country":"CN",
    "name:zho_x_preferred":[
        "\u897f\u5ddd"
    ],
    "wof:name":"Xichuan",
    "wof:placetype":"locality"
},
  "geometry": {"coordinates":[104.94799999999999,36.0743],"type":"Point"}
}