{
  "type": "Feature",
  "properties": {
    "gn:admin1_code":"26.0",
    "gn:asciiname":"Dataigou",
    "gn:country_code":"CN",
    "gn:dem":1331,
    "gn:feature_class":"P",
    "gn:feature_code":"PPL",
    "gn:name":"Dataigou",
    "gn:population":0,
    "gn:timezone":"Asia/Shanghai",
    "iso:country":"CN",
    "name:zho_x_preferred":[
        "\u5927\u53f0\u6c9f"
    ],
    "wof:name":"Dataigou",
    "wof:placetype":"locality"
},
  "geometry": {"coordinates":[109.56319999999999,36.43699],"type":"Point"}
}