{
  "type": "Feature",
  "properties": {
    "gn:admin1_code":"25",
    "gn:asciiname":"Lengjiacun",
    "gn:cc2":"CN",
    "gn:country_code":"CN",
    "gn:dem":23,
    "gn:feature_class":"P",
    "gn:feature_code":"PPL",
    "gn:name":"Lengjiacun",
    "gn:population":0,
    "gn:timezone":"Asia/Shanghai",
    "iso:country":"CN",
    "name:und_x_variant":[
        "Leng-chia-ts\u2019un",
        "Lengjiacun"
    ],
    "wof:name":"Lengjiacun",
    "wof:placetype":"locality"
},
  "geometry": {"coordinates":[119.90667000000001,36.1375],"type":"Point"}
}