{
  "type": "Feature",
  "properties": {
    "gn:admin1_code":"11.0",
    "gn:asciiname":"Shishantou",
    "gn:country_code":"CN",
    "gn:dem":209,
    "gn:feature_class":"P",
    "gn:feature_code":"PPL",
    "gn:name":"Shishantou",
    "gn:population":0,
    "gn:timezone":"Asia/Shanghai",
    "iso:country":"CN",
    "name:zho_x_preferred":[
        "\u77f3\u5c71\u5934"
    ],
    "wof:name":"Shishantou",
    "wof:placetype":"locality"
},
  "geometry": {"coordinates":[112.81672,25.72857],"type":"Point"}
}