{
  "type": "Feature",
  "properties": {
    "gn:admin1_code":"32.0",
    "gn:asciiname":"Mingxinsi",
    "gn:country_code":"CN",
    "gn:dem":363,
    "gn:feature_class":"P",
    "gn:feature_code":"PPL",
    "gn:name":"Mingxinsi",
    "gn:population":0,
    "gn:timezone":"Asia/Shanghai",
    "iso:country":"CN",
    "name:zho_x_preferred":[
        "\u660e\u5fc3\u5bfa"
    ],
    "wof:name":"Mingxinsi",
    "wof:placetype":"locality"
},
  "geometry": {"coordinates":[104.90431,29.73791],"type":"Point"}
}