{
  "type": "Feature",
  "properties": {
    "gn:admin1_code":"29.0",
    "gn:asciiname":"Shangtaizi",
    "gn:country_code":"CN",
    "gn:dem":1671,
    "gn:feature_class":"P",
    "gn:feature_code":"PPL",
    "gn:name":"Shangtaizi",
    "gn:population":0,
    "gn:timezone":"Asia/Shanghai",
    "iso:country":"CN",
    "name:zho_x_preferred":[
        "\u4e0a\u53f0\u5b50"
    ],
    "wof:name":"Shangtaizi",
    "wof:placetype":"locality"
},
  "geometry": {"coordinates":[102.748,26.0878],"type":"Point"}
}