{
  "type": "Feature",
  "properties": {
    "gn:admin1_code":"3",
    "gn:asciiname":"Huamaitu",
    "gn:country_code":"CN",
    "gn:dem":590,
    "gn:feature_class":"P",
    "gn:feature_code":"PPL",
    "gn:name":"Huamaitu",
    "gn:population":0,
    "gn:timezone":"Asia/Shanghai",
    "iso:country":"CN",
    "name:zho_x_preferred":[
        "\u82b1\u9ea6\u571f"
    ],
    "wof:name":"Huamaitu",
    "wof:placetype":"locality"
},
  "geometry": {"coordinates":[114.404,25.7543],"type":"Point"}
}