{
  "type": "Feature",
  "properties": {
    "gn:admin1_code":"25",
    "gn:asciiname":"Mayingliucun",
    "gn:country_code":"CN",
    "gn:dem":9,
    "gn:feature_class":"P",
    "gn:feature_code":"PPL",
    "gn:name":"Mayingliucun",
    "gn:population":0,
    "gn:timezone":"Asia/Shanghai",
    "iso:country":"CN",
    "name:zho_x_preferred":[
        "\u9a6c\u8425\u516d\u6751"
    ],
    "wof:name":"Mayingliucun",
    "wof:placetype":"locality"
},
  "geometry": {"coordinates":[118.32599999999999,37.7558],"type":"Point"}
}