{
  "type": "Feature",
  "properties": {
    "gn:admin1_code":"8.0",
    "gn:asciiname":"Jiangbing Shiwudui",
    "gn:country_code":"CN",
    "gn:dem":64,
    "gn:feature_class":"P",
    "gn:feature_code":"PPLF",
    "gn:name":"Jiangbing Shiwudui",
    "gn:population":0,
    "gn:timezone":"Asia/Shanghai",
    "iso:country":"CN",
    "name:zho_x_preferred":[
        "\u6c5f\u6ee8\u5341\u4e94\u961f"
    ],
    "wof:name":"Jiangbing Shiwudui",
    "wof:placetype":"locality"
},
  "geometry": {"coordinates":[131.31927999999999,47.57561],"type":"Point"}
}