{
  "type": "Feature",
  "properties": {
    "gn:admin1_code":"5.0",
    "gn:asciiname":"Houbalicun",
    "gn:country_code":"CN",
    "gn:dem":205,
    "gn:feature_class":"P",
    "gn:feature_code":"PPL",
    "gn:name":"Houbalicun",
    "gn:population":0,
    "gn:timezone":"Asia/Shanghai",
    "iso:country":"CN",
    "name:zho_x_preferred":[
        "\u540e\u516b\u91cc\u6751"
    ],
    "wof:name":"Houbalicun",
    "wof:placetype":"locality"
},
  "geometry": {"coordinates":[125.93342,43.71058],"type":"Point"}
}