{
  "type": "Feature",
  "properties": {
    "gn:admin1_code":"29.0",
    "gn:asciiname":"Laiyuanpu",
    "gn:country_code":"CN",
    "gn:dem":2125,
    "gn:feature_class":"P",
    "gn:feature_code":"PPL",
    "gn:name":"Laiyuanpu",
    "gn:population":0,
    "gn:timezone":"Asia/Shanghai",
    "iso:country":"CN",
    "name:zho_x_preferred":[
        "\u6765\u8fdc\u94fa"
    ],
    "wof:name":"Laiyuanpu",
    "wof:placetype":"locality"
},
  "geometry": {"coordinates":[103.999,25.8713],"type":"Point"}
}