{
  "type": "Feature",
  "properties": {
    "gn:admin1_code":"16.0",
    "gn:asciiname":"Longbaocun",
    "gn:country_code":"CN",
    "gn:dem":907,
    "gn:feature_class":"P",
    "gn:feature_code":"PPL",
    "gn:name":"Longbaocun",
    "gn:population":0,
    "gn:timezone":"Asia/Shanghai",
    "iso:country":"CN",
    "name:zho_x_preferred":[
        "\u9647\u4fdd\u5b58"
    ],
    "wof:name":"Longbaocun",
    "wof:placetype":"locality"
},
  "geometry": {"coordinates":[106.678,24.4876],"type":"Point"}
}