{
  "type": "Feature",
  "properties": {
    "gn:admin1_code":"5.0",
    "gn:asciiname":"Shijiancun",
    "gn:country_code":"CN",
    "gn:dem":123,
    "gn:feature_class":"P",
    "gn:feature_code":"PPL",
    "gn:name":"Shijiancun",
    "gn:population":0,
    "gn:timezone":"Asia/Shanghai",
    "iso:country":"CN",
    "name:zho_x_preferred":[
        "\u77f3\u5efa\u6751"
    ],
    "wof:name":"Shijiancun",
    "wof:placetype":"locality"
},
  "geometry": {"coordinates":[129.80351000000002,42.83725],"type":"Point"}
}