{
  "type": "Feature",
  "properties": {
    "gn:admin1_code":"2.0",
    "gn:asciiname":"Maocaoshan",
    "gn:country_code":"CN",
    "gn:dem":58,
    "gn:feature_class":"P",
    "gn:feature_code":"PPL",
    "gn:name":"Maocaoshan",
    "gn:population":0,
    "gn:timezone":"Asia/Shanghai",
    "iso:country":"CN",
    "name:zho_x_preferred":[
        "\u6bdb\u8349\u5c71"
    ],
    "wof:name":"Maocaoshan",
    "wof:placetype":"locality"
},
  "geometry": {"coordinates":[119.69257,29.07062],"type":"Point"}
}