{
  "type": "Feature",
  "properties": {
    "gn:admin1_code":"32.0",
    "gn:asciiname":"Heboluo",
    "gn:country_code":"CN",
    "gn:dem":2023,
    "gn:feature_class":"P",
    "gn:feature_code":"PPL",
    "gn:name":"Heboluo",
    "gn:population":0,
    "gn:timezone":"Asia/Shanghai",
    "iso:country":"CN",
    "name:zho_x_preferred":[
        "\u8d3a\u6ce2\u6d1b"
    ],
    "wof:name":"Heboluo",
    "wof:placetype":"locality"
},
  "geometry": {"coordinates":[102.45533,28.33861],"type":"Point"}
}