{
  "type": "Feature",
  "properties": {
    "gn:admin1_code":"15.0",
    "gn:asciiname":"Hongqiling",
    "gn:country_code":"CN",
    "gn:dem":864,
    "gn:feature_class":"P",
    "gn:feature_code":"PPL",
    "gn:name":"Hongqiling",
    "gn:population":0,
    "gn:timezone":"Asia/Shanghai",
    "iso:country":"CN",
    "name:und_x_variant":[
        "\u7ea2\u65d7\u5cad"
    ],
    "wof:name":"Hongqiling",
    "wof:placetype":"locality"
},
  "geometry": {"coordinates":[105.76327000000001,33.1295],"type":"Point"}
}