{
  "type": "Feature",
  "properties": {
    "gn:admin1_code":"33.0",
    "gn:asciiname":"Guanghua",
    "gn:country_code":"CN",
    "gn:dem":634,
    "gn:feature_class":"P",
    "gn:feature_code":"PPL",
    "gn:name":"Guanghua",
    "gn:population":0,
    "gn:timezone":"Asia/Shanghai",
    "iso:country":"CN",
    "name:ceb_x_preferred":[
        "Guanghua"
    ],
    "name:deu_x_preferred":[
        "Guanghua"
    ],
    "name:pol_x_preferred":[
        "Guanghua"
    ],
    "name:swe_x_preferred":[
        "Guanghua"
    ],
    "name:zho_x_preferred":[
        "\u5149\u534e"
    ],
    "wof:name":"Guanghua",
    "wof:placetype":"locality"
},
  "geometry": {"coordinates":[107.50671,29.71242],"type":"Point"}
}