{
  "type": "Feature",
  "properties": {
    "gn:admin1_code":"30",
    "gn:asciiname":"Qingdong",
    "gn:country_code":"CN",
    "gn:dem":67,
    "gn:feature_class":"P",
    "gn:feature_code":"PPL",
    "gn:name":"Qingdong",
    "gn:population":0,
    "gn:timezone":"Asia/Urumqi",
    "iso:country":"CN",
    "name:zho_x_preferred":[
        "\u6e05\u578c"
    ],
    "wof:name":"Qingdong",
    "wof:placetype":"locality"
},
  "geometry": {"coordinates":[110.84048,22.11399],"type":"Point"}
}