{
  "type": "Feature",
  "properties": {
    "gn:admin1_code":"30",
    "gn:asciiname":"Nanhongcun",
    "gn:country_code":"CN",
    "gn:dem":9,
    "gn:feature_class":"P",
    "gn:feature_code":"PPL",
    "gn:name":"Nanhongcun",
    "gn:population":0,
    "gn:timezone":"Asia/Urumqi",
    "iso:country":"CN",
    "name:zho_x_preferred":[
        "\u5357\u6d2a\u6751"
    ],
    "wof:name":"Nanhongcun",
    "wof:placetype":"locality"
},
  "geometry": {"coordinates":[109.81314,21.34938],"type":"Point"}
}