{
  "type": "Feature",
  "properties": {
    "gn:admin1_code":"19.0",
    "gn:asciiname":"Xiaobalicun",
    "gn:country_code":"CN",
    "gn:dem":223,
    "gn:feature_class":"P",
    "gn:feature_code":"PPL",
    "gn:name":"Xiaobalicun",
    "gn:population":0,
    "gn:timezone":"Asia/Shanghai",
    "iso:country":"CN",
    "name:zho_x_preferred":[
        "\u5c0f\u5df4\u91cc\u6751"
    ],
    "wof:name":"Xiaobalicun",
    "wof:placetype":"locality"
},
  "geometry": {"coordinates":[120.60616,41.82386],"type":"Point"}
}