{
  "type": "Feature",
  "properties": {
    "gn:admin1_code":"25.0",
    "gn:asciiname":"Qianpanjiacun",
    "gn:country_code":"CN",
    "gn:dem":115,
    "gn:feature_class":"P",
    "gn:feature_code":"PPL",
    "gn:name":"Qianpanjiacun",
    "gn:population":0,
    "gn:timezone":"Asia/Shanghai",
    "iso:country":"CN",
    "name:zho_x_preferred":[
        "\u524d\u6f58\u5bb6\u6751"
    ],
    "wof:name":"Qianpanjiacun",
    "wof:placetype":"locality"
},
  "geometry": {"coordinates":[120.15313999999999,36.95304],"type":"Point"}
}