{
  "type": "Feature",
  "properties": {
    "gn:admin1_code":"16",
    "gn:asciiname":"Zongshuping",
    "gn:country_code":"CN",
    "gn:dem":504,
    "gn:feature_class":"P",
    "gn:feature_code":"PPL",
    "gn:name":"Zongshuping",
    "gn:population":0,
    "gn:timezone":"Asia/Shanghai",
    "iso:country":"CN",
    "name:zho_x_preferred":[
        "\u68d5\u6811\u576a"
    ],
    "wof:name":"Zongshuping",
    "wof:placetype":"locality"
},
  "geometry": {"coordinates":[110.679,25.062],"type":"Point"}
}