{
  "type": "Feature",
  "properties": {
    "gn:admin1_code":"16",
    "gn:asciiname":"Qingshanpeng",
    "gn:country_code":"CN",
    "gn:dem":508,
    "gn:feature_class":"P",
    "gn:feature_code":"PPL",
    "gn:name":"Qingshanpeng",
    "gn:population":0,
    "gn:timezone":"Asia/Shanghai",
    "iso:country":"CN",
    "name:zho_x_preferred":[
        "\u9752\u5c71\u68da"
    ],
    "wof:name":"Qingshanpeng",
    "wof:placetype":"locality"
},
  "geometry": {"coordinates":[111.202,25.4832],"type":"Point"}
}