{
  "type": "Feature",
  "properties": {
    "gn:admin1_code":"2.0",
    "gn:asciiname":"Minhe",
    "gn:country_code":"CN",
    "gn:dem":6,
    "gn:feature_class":"P",
    "gn:feature_code":"PPL",
    "gn:name":"Minhe",
    "gn:population":0,
    "gn:timezone":"Asia/Shanghai",
    "iso:country":"CN",
    "name:ceb_x_preferred":[
        "Minhe"
    ],
    "name:deu_x_preferred":[
        "Minhe"
    ],
    "name:und_x_variant":[
        "\u6c11\u548c"
    ],
    "wof:name":"Minhe",
    "wof:placetype":"locality"
},
  "geometry": {"coordinates":[120.65719,30.50931],"type":"Point"}
}