{
  "type": "Feature",
  "properties": {
    "gn:admin1_code":"11.0",
    "gn:asciiname":"Luojiachong",
    "gn:country_code":"CN",
    "gn:dem":174,
    "gn:feature_class":"P",
    "gn:feature_code":"PPL",
    "gn:name":"Luojiachong",
    "gn:population":0,
    "gn:timezone":"Asia/Shanghai",
    "iso:country":"CN",
    "name:zho_x_preferred":[
        "\u7f57\u5bb6\u51b2"
    ],
    "wof:name":"Luojiachong",
    "wof:placetype":"locality"
},
  "geometry": {"coordinates":[111.62823,28.42977],"type":"Point"}
}