{
  "type": "Feature",
  "properties": {
    "gn:admin1_code":"32.0",
    "gn:asciiname":"Futian",
    "gn:country_code":"CN",
    "gn:dem":1151,
    "gn:feature_class":"P",
    "gn:feature_code":"PPL",
    "gn:name":"Futian",
    "gn:population":0,
    "gn:timezone":"Asia/Shanghai",
    "iso:country":"CN",
    "name:zho_x_preferred":[
        "\u798f\u7530"
    ],
    "wof:name":"Futian",
    "wof:placetype":"locality"
},
  "geometry": {"coordinates":[101.41461,26.57729],"type":"Point"}
}