{
  "type": "Feature",
  "properties": {
    "gn:admin1_code":"16.0",
    "gn:asciiname":"Qukun",
    "gn:country_code":"CN",
    "gn:dem":161,
    "gn:feature_class":"P",
    "gn:feature_code":"PPL",
    "gn:name":"Qukun",
    "gn:population":0,
    "gn:timezone":"Asia/Shanghai",
    "iso:country":"CN",
    "name:zho_x_preferred":[
        "\u6e20\u5764"
    ],
    "wof:name":"Qukun",
    "wof:placetype":"locality"
},
  "geometry": {"coordinates":[107.95099999999999,22.4324],"type":"Point"}
}