{
  "type": "Feature",
  "properties": {
    "gn:admin1_code":"15.0",
    "gn:asciiname":"Sheke",
    "gn:country_code":"CN",
    "gn:dem":2274,
    "gn:feature_class":"P",
    "gn:feature_code":"PPL",
    "gn:name":"Sheke",
    "gn:population":0,
    "gn:timezone":"Asia/Shanghai",
    "iso:country":"CN",
    "name:und_x_variant":[
        "\u820d\u79d1"
    ],
    "wof:name":"Sheke",
    "wof:placetype":"locality"
},
  "geometry": {"coordinates":[103.77885999999999,34.85436],"type":"Point"}
}