{
  "type": "Feature",
  "properties": {
    "gn:admin1_code":"19",
    "gn:asciiname":"Yizhou",
    "gn:cc2":"CN",
    "gn:country_code":"CN",
    "gn:dem":67,
    "gn:feature_class":"P",
    "gn:feature_code":"PPL",
    "gn:name":"Yizhou",
    "gn:population":0,
    "gn:timezone":"Asia/Shanghai",
    "iso:country":"CN",
    "name:und_x_variant":[
        "I-chou-chen",
        "Yixian",
        "I-chou",
        "I-hsien",
        "Yizhou"
    ],
    "wof:name":"Yizhou",
    "wof:placetype":"locality"
},
  "geometry": {"coordinates":[121.24806,41.53361],"type":"Point"}
}