{
  "type": "Feature",
  "properties": {
    "gn:admin1_code":"29.0",
    "gn:asciiname":"Nuokao Laozhai",
    "gn:country_code":"CN",
    "gn:dem":1494,
    "gn:feature_class":"P",
    "gn:feature_code":"PPL",
    "gn:name":"Nuokao Laozhai",
    "gn:population":0,
    "gn:timezone":"Asia/Shanghai",
    "iso:country":"CN",
    "name:zho_x_preferred":[
        "\u7cef\u8003\u8001\u5be8"
    ],
    "wof:name":"Nuokao Laozhai",
    "wof:placetype":"locality"
},
  "geometry": {"coordinates":[99.8573,22.559],"type":"Point"}
}