{
  "type": "Feature",
  "properties": {
    "gn:admin1_code":"11.0",
    "gn:asciiname":"Heimudui",
    "gn:country_code":"CN",
    "gn:dem":976,
    "gn:feature_class":"P",
    "gn:feature_code":"PPL",
    "gn:name":"Heimudui",
    "gn:population":0,
    "gn:timezone":"Asia/Shanghai",
    "iso:country":"CN",
    "name:zho_x_preferred":[
        "\u9ed1\u6728\u5806"
    ],
    "wof:name":"Heimudui",
    "wof:placetype":"locality"
},
  "geometry": {"coordinates":[110.3276,26.03823],"type":"Point"}
}