{
  "type": "Feature",
  "properties": {
    "gn:admin1_code":"26.0",
    "gn:asciiname":"Yujiayuan",
    "gn:country_code":"CN",
    "gn:dem":1082,
    "gn:feature_class":"P",
    "gn:feature_code":"PPL",
    "gn:name":"Yujiayuan",
    "gn:population":0,
    "gn:timezone":"Asia/Shanghai",
    "iso:country":"CN",
    "name:zho_x_preferred":[
        "\u8fc2\u5bb6\u586c"
    ],
    "wof:name":"Yujiayuan",
    "wof:placetype":"locality"
},
  "geometry": {"coordinates":[109.20218,35.6573],"type":"Point"}
}