{
  "type": "Feature",
  "properties": {
    "gn:admin1_code":"1.0",
    "gn:asciiname":"Wanzhuangcun",
    "gn:country_code":"CN",
    "gn:dem":54,
    "gn:feature_class":"P",
    "gn:feature_code":"PPL",
    "gn:name":"Wanzhuangcun",
    "gn:population":0,
    "gn:timezone":"Asia/Shanghai",
    "iso:country":"CN",
    "name:zho_x_preferred":[
        "\u4e07\u5e84\u6751"
    ],
    "wof:name":"Wanzhuangcun",
    "wof:placetype":"locality"
},
  "geometry": {"coordinates":[117.59205,32.21939],"type":"Point"}
}