{
  "type": "Feature",
  "properties": {
    "gn:admin1_code":"24.0",
    "gn:asciiname":"Liyan",
    "gn:country_code":"CN",
    "gn:dem":736,
    "gn:feature_class":"P",
    "gn:feature_code":"PPL",
    "gn:name":"Liyan",
    "gn:population":0,
    "gn:timezone":"Asia/Shanghai",
    "iso:country":"CN",
    "name:ara_x_preferred":[
        "\u0644\u064a\u0627\u0646"
    ],
    "name:fas_x_preferred":[
        "\u0644\u06cc\u0627\u0646"
    ],
    "name:zho_x_preferred":[
        "\u674e\u5895"
    ],
    "wof:name":"Liyan",
    "wof:placetype":"locality"
},
  "geometry": {"coordinates":[112.61673999999999,35.45576],"type":"Point"}
}