{
  "type": "Feature",
  "properties": {
    "gn:admin1_code":"11.0",
    "gn:asciiname":"Jinlanxi",
    "gn:country_code":"CN",
    "gn:dem":370,
    "gn:feature_class":"P",
    "gn:feature_code":"PPL",
    "gn:name":"Jinlanxi",
    "gn:population":0,
    "gn:timezone":"Asia/Shanghai",
    "iso:country":"CN",
    "name:zho_x_preferred":[
        "Jinlanxi"
    ],
    "name:zho_x_variant":[
        "\u91d1\u62e6\u6eaa"
    ],
    "wof:name":"Jinlanxi",
    "wof:placetype":"locality"
},
  "geometry": {"coordinates":[114.08496,28.30138],"type":"Point"}
}