{
  "type": "Feature",
  "properties": {
    "gn:admin1_code":"32.0",
    "gn:asciiname":"Niutoupo",
    "gn:country_code":"CN",
    "gn:dem":304,
    "gn:feature_class":"P",
    "gn:feature_code":"PPL",
    "gn:name":"Niutoupo",
    "gn:population":0,
    "gn:timezone":"Asia/Shanghai",
    "iso:country":"CN",
    "name:zho_x_preferred":[
        "\u725b\u5934\u5761"
    ],
    "wof:name":"Niutoupo",
    "wof:placetype":"locality"
},
  "geometry": {"coordinates":[105.50631,30.22337000000001],"type":"Point"}
}