{
  "type": "Feature",
  "properties": {
    "gn:admin1_code":"30.0",
    "gn:asciiname":"Hemugang",
    "gn:country_code":"CN",
    "gn:dem":97,
    "gn:feature_class":"P",
    "gn:feature_code":"PPL",
    "gn:name":"Hemugang",
    "gn:population":0,
    "gn:timezone":"Asia/Shanghai",
    "iso:country":"CN",
    "name:zho_x_preferred":[
        "\u4f55\u6728\u5c97"
    ],
    "wof:name":"Hemugang",
    "wof:placetype":"locality"
},
  "geometry": {"coordinates":[113.72577,24.05224],"type":"Point"}
}