{
  "type": "Feature",
  "properties": {
    "gn:admin1_code":"10",
    "gn:asciiname":"Nangoumen",
    "gn:country_code":"CN",
    "gn:dem":354,
    "gn:feature_class":"P",
    "gn:feature_code":"PPL",
    "gn:name":"Nangoumen",
    "gn:population":0,
    "gn:timezone":"Asia/Shanghai",
    "iso:country":"CN",
    "name:zho_x_preferred":[
        "\u5357\u6c9f\u95e8"
    ],
    "wof:name":"Nangoumen",
    "wof:placetype":"locality"
},
  "geometry": {"coordinates":[117.22811000000002,40.83149],"type":"Point"}
}