{
  "type": "Feature",
  "properties": {
    "gn:admin1_code":"29.0",
    "gn:asciiname":"Duoyichang Xincun",
    "gn:country_code":"CN",
    "gn:dem":1879,
    "gn:feature_class":"P",
    "gn:feature_code":"PPL",
    "gn:name":"Duoyichang Xincun",
    "gn:population":0,
    "gn:timezone":"Asia/Shanghai",
    "iso:country":"CN",
    "name:zho_x_preferred":[
        "\u591a\u4f9d\u5382\u65b0\u6751"
    ],
    "wof:name":"Duoyichang Xincun",
    "wof:placetype":"locality"
},
  "geometry": {"coordinates":[100.684,25.0718],"type":"Point"}
}