{
  "type": "Feature",
  "properties": {
    "gn:admin1_code":"30.0",
    "gn:asciiname":"Huangmaotang",
    "gn:country_code":"CN",
    "gn:dem":111,
    "gn:feature_class":"P",
    "gn:feature_code":"PPL",
    "gn:name":"Huangmaotang",
    "gn:population":0,
    "gn:timezone":"Asia/Shanghai",
    "iso:country":"CN",
    "name:zho_x_preferred":[
        "Huangmaotang"
    ],
    "name:zho_x_variant":[
        "\u9ec4\u8305\u5858"
    ],
    "wof:name":"Huangmaotang",
    "wof:placetype":"locality"
},
  "geometry": {"coordinates":[114.99056000000002,24.34667],"type":"Point"}
}