{
  "type": "Feature",
  "properties": {
    "gn:admin1_code":"3.0",
    "gn:asciiname":"Huangyuanshan",
    "gn:country_code":"CN",
    "gn:dem":68,
    "gn:feature_class":"P",
    "gn:feature_code":"PPL",
    "gn:name":"Huangyuanshan",
    "gn:population":0,
    "gn:timezone":"Asia/Shanghai",
    "iso:country":"CN",
    "name:zho_x_preferred":[
        "\u9ec4\u6e90\u5c71"
    ],
    "wof:name":"Huangyuanshan",
    "wof:placetype":"locality"
},
  "geometry": {"coordinates":[117.36315,28.51743],"type":"Point"}
}