{
  "type": "Feature",
  "properties": {
    "gn:admin1_code":"16.0",
    "gn:asciiname":"Baigedong",
    "gn:country_code":"CN",
    "gn:dem":85,
    "gn:feature_class":"P",
    "gn:feature_code":"PPL",
    "gn:name":"Baigedong",
    "gn:population":0,
    "gn:timezone":"Asia/Shanghai",
    "iso:country":"CN",
    "name:zho_x_preferred":[
        "\u767d\u9e3d\u578c"
    ],
    "wof:name":"Baigedong",
    "wof:placetype":"locality"
},
  "geometry": {"coordinates":[109.642,22.191],"type":"Point"}
}