{
  "type": "Feature",
  "properties": {
    "gn:admin1_code":"29.0",
    "gn:asciiname":"Luguan",
    "gn:country_code":"CN",
    "gn:dem":1578,
    "gn:feature_class":"P",
    "gn:feature_code":"PPL",
    "gn:name":"L\u00fcguan",
    "gn:population":0,
    "gn:timezone":"Asia/Shanghai",
    "iso:country":"CN",
    "name:und_x_variant":[
        "L\u00fcguan"
    ],
    "name:zho_x_preferred":[
        "\u5415\u5b98"
    ],
    "wof:name":"Luguan",
    "wof:placetype":"locality"
},
  "geometry": {"coordinates":[100.627,26.7583],"type":"Point"}
}