{
  "type": "Feature",
  "properties": {
    "gn:admin1_code":"18",
    "gn:asciiname":"Huangnishang",
    "gn:country_code":"CN",
    "gn:dem":641,
    "gn:feature_class":"P",
    "gn:feature_code":"PPL",
    "gn:name":"Huangnishang",
    "gn:population":0,
    "gn:timezone":"Asia/Shanghai",
    "iso:country":"CN",
    "name:zho_x_preferred":[
        "\u9ec4\u6ce5\u5c1a"
    ],
    "wof:name":"Huangnishang",
    "wof:placetype":"locality"
},
  "geometry": {"coordinates":[107.419,28.7308],"type":"Point"}
}