{
  "type": "Feature",
  "properties": {
    "gn:admin1_code":"14.0",
    "gn:asciiname":"Bangmaicun",
    "gn:country_code":"CN",
    "gn:dem":3809,
    "gn:feature_class":"P",
    "gn:feature_code":"PPL",
    "gn:name":"Bangmaicun",
    "gn:population":0,
    "gn:timezone":"Asia/Urumqi",
    "iso:country":"CN",
    "name:zho_x_preferred":[
        "\u5e2e\u9ea6\u6751"
    ],
    "wof:name":"Bangmaicun",
    "wof:placetype":"locality"
},
  "geometry": {"coordinates":[92.71905,28.99422],"type":"Point"}
}