{
  "type": "Feature",
  "properties": {
    "gn:admin1_code":"8.0",
    "gn:asciiname":"Wuying Xumuchang",
    "gn:country_code":"CN",
    "gn:dem":274,
    "gn:feature_class":"P",
    "gn:feature_code":"PPLF",
    "gn:name":"Wuying Xumuchang",
    "gn:population":0,
    "gn:timezone":"Asia/Shanghai",
    "iso:country":"CN",
    "name:zho_x_preferred":[
        "\u4e94\u8425\u755c\u7267\u573a"
    ],
    "wof:name":"Wuying Xumuchang",
    "wof:placetype":"locality"
},
  "geometry": {"coordinates":[129.16228000000001,48.08254],"type":"Point"}
}