{
  "type": "Feature",
  "properties": {
    "gn:admin1_code":"11.0",
    "gn:asciiname":"Houwangdong",
    "gn:country_code":"CN",
    "gn:dem":447,
    "gn:feature_class":"P",
    "gn:feature_code":"PPL",
    "gn:name":"Houwangdong",
    "gn:population":0,
    "gn:timezone":"Asia/Shanghai",
    "iso:country":"CN",
    "name:zho_x_preferred":[
        "\u7334\u738b\u6d1e"
    ],
    "wof:name":"Houwangdong",
    "wof:placetype":"locality"
},
  "geometry": {"coordinates":[109.49151000000001,27.84023],"type":"Point"}
}