{
  "type": "Feature",
  "properties": {
    "gn:admin1_code":"11.0",
    "gn:asciiname":"Tongmuping",
    "gn:country_code":"CN",
    "gn:dem":631,
    "gn:feature_class":"P",
    "gn:feature_code":"PPL",
    "gn:name":"Tongmuping",
    "gn:population":0,
    "gn:timezone":"Asia/Shanghai",
    "iso:country":"CN",
    "name:zho_x_preferred":[
        "\u6850\u6728\u576a"
    ],
    "wof:name":"Tongmuping",
    "wof:placetype":"locality"
},
  "geometry": {"coordinates":[109.3272,27.96744],"type":"Point"}
}