{
  "type": "Feature",
  "properties": {
    "gn:admin1_code":"16.0",
    "gn:asciiname":"Qiandong",
    "gn:country_code":"CN",
    "gn:dem":252,
    "gn:feature_class":"P",
    "gn:feature_code":"PPL",
    "gn:name":"Qiandong",
    "gn:population":0,
    "gn:timezone":"Asia/Shanghai",
    "iso:country":"CN",
    "name:zho_x_preferred":[
        "\u94b1\u6d1e"
    ],
    "wof:name":"Qiandong",
    "wof:placetype":"locality"
},
  "geometry": {"coordinates":[109.429,25.1574],"type":"Point"}
}