{
  "type": "Feature",
  "properties": {
    "gn:admin1_code":"20.0",
    "gn:asciiname":"Fushengwang",
    "gn:country_code":"CN",
    "gn:dem":1521,
    "gn:feature_class":"P",
    "gn:feature_code":"PPL",
    "gn:name":"Fushengwang",
    "gn:population":0,
    "gn:timezone":"Asia/Shanghai",
    "iso:country":"CN",
    "name:und_x_variant":[
        "\u798f\u751f\u65fa"
    ],
    "wof:name":"Fushengwang",
    "wof:placetype":"locality"
},
  "geometry": {"coordinates":[110.23397,41.048],"type":"Point"}
}