{
  "type": "Feature",
  "properties": {
    "gn:admin1_code":"24",
    "gn:asciiname":"Zhangxiao",
    "gn:cc2":"CN",
    "gn:country_code":"CN",
    "gn:dem":1126,
    "gn:feature_class":"P",
    "gn:feature_code":"PPL",
    "gn:name":"Zhangxiao",
    "gn:population":0,
    "gn:timezone":"Asia/Shanghai",
    "iso:country":"CN",
    "name:und_x_variant":[
        "Chang-hsiao-ts\u2019un",
        "Zhangxiaocun",
        "Zhangxiao"
    ],
    "wof:name":"Zhangxiao",
    "wof:placetype":"locality"
},
  "geometry": {"coordinates":[113.68722,40.38889],"type":"Point"}
}