{
  "type": "Feature",
  "properties": {
    "gn:admin1_code":"02",
    "gn:asciiname":"Nanmu",
    "gn:cc2":"CN",
    "gn:country_code":"CN",
    "gn:dem":7,
    "gn:feature_class":"P",
    "gn:feature_code":"PPL",
    "gn:name":"Nanmu",
    "gn:population":0,
    "gn:timezone":"Asia/Shanghai",
    "iso:country":"CN",
    "name:und_x_variant":[
        "Nan-chai",
        "Nanmu"
    ],
    "wof:name":"Nanmu",
    "wof:placetype":"locality"
},
  "geometry": {"coordinates":[120.95638999999998,27.99972],"type":"Point"}
}