{
  "type": "Feature",
  "properties": {
    "gn:admin1_code":"2.0",
    "gn:asciiname":"Xialiao",
    "gn:country_code":"CN",
    "gn:dem":372,
    "gn:feature_class":"P",
    "gn:feature_code":"PPL",
    "gn:name":"Xialiao",
    "gn:population":0,
    "gn:timezone":"Asia/Shanghai",
    "iso:country":"CN",
    "name:zho_x_preferred":[
        "\u4e0b\u5bee"
    ],
    "wof:name":"Xialiao",
    "wof:placetype":"locality"
},
  "geometry": {"coordinates":[120.61261,28.98229000000001],"type":"Point"}
}