{
  "type": "Feature",
  "properties": {
    "gn:admin1_code":"29.0",
    "gn:asciiname":"Dasheyao",
    "gn:country_code":"CN",
    "gn:dem":1752,
    "gn:feature_class":"P",
    "gn:feature_code":"PPL",
    "gn:name":"Dasheyao",
    "gn:population":0,
    "gn:timezone":"Asia/Shanghai",
    "iso:country":"CN",
    "name:zho_x_preferred":[
        "\u5927\u86c7\u8170"
    ],
    "wof:name":"Dasheyao",
    "wof:placetype":"locality"
},
  "geometry": {"coordinates":[99.7114,24.9643],"type":"Point"}
}