{
  "type": "Feature",
  "properties": {
    "gn:admin1_code":"11.0",
    "gn:asciiname":"Gongmushu",
    "gn:country_code":"CN",
    "gn:dem":50,
    "gn:feature_class":"P",
    "gn:feature_code":"PPL",
    "gn:name":"Gongmushu",
    "gn:population":0,
    "gn:timezone":"Asia/Shanghai",
    "iso:country":"CN",
    "name:zho_x_preferred":[
        "\u516c\u6bcd\u6811"
    ],
    "wof:name":"Gongmushu",
    "wof:placetype":"locality"
},
  "geometry": {"coordinates":[112.84399999999999,29.72745],"type":"Point"}
}