{
  "type": "Feature",
  "properties": {
    "gn:admin1_code":"2.0",
    "gn:asciiname":"Lingxi",
    "gn:country_code":"CN",
    "gn:dem":18,
    "gn:feature_class":"P",
    "gn:feature_code":"PPL",
    "gn:name":"Lingxi",
    "gn:population":0,
    "gn:timezone":"Asia/Shanghai",
    "iso:country":"CN",
    "name:zho_x_preferred":[
        "\u5cad\u6eaa"
    ],
    "name:zho_x_variant":[
        "\u7075\u6eaa\u9547"
    ],
    "wof:name":"Lingxi",
    "wof:placetype":"locality"
},
  "geometry": {"coordinates":[120.95449000000001,28.86436],"type":"Point"}
}