{
  "type": "Feature",
  "properties": {
    "gn:admin1_code":"4.0",
    "gn:asciiname":"Houfan",
    "gn:country_code":"CN",
    "gn:dem":6,
    "gn:feature_class":"P",
    "gn:feature_code":"PPL",
    "gn:name":"Houfan",
    "gn:population":0,
    "gn:timezone":"Asia/Shanghai",
    "iso:country":"CN",
    "name:zho_x_preferred":[
        "Houfan"
    ],
    "name:zho_x_variant":[
        "\u540e\u8303"
    ],
    "wof:name":"Houfan",
    "wof:placetype":"locality"
},
  "geometry": {"coordinates":[119.05826,33.30448],"type":"Point"}
}