{
  "type": "Feature",
  "properties": {
    "gn:admin1_code":"1.0",
    "gn:asciiname":"Houhecun",
    "gn:country_code":"CN",
    "gn:dem":36,
    "gn:feature_class":"P",
    "gn:feature_code":"PPL",
    "gn:name":"Houhecun",
    "gn:population":0,
    "gn:timezone":"Asia/Shanghai",
    "iso:country":"CN",
    "name:zho_x_preferred":[
        "\u540e\u4f55\u6751"
    ],
    "wof:name":"Houhecun",
    "wof:placetype":"locality"
},
  "geometry": {"coordinates":[115.48908,32.66226],"type":"Point"}
}