{
  "type": "Feature",
  "properties": {
    "gn:admin1_code":"19.0",
    "gn:asciiname":"Heiwozi",
    "gn:country_code":"CN",
    "gn:dem":249,
    "gn:feature_class":"P",
    "gn:feature_code":"PPL",
    "gn:name":"Heiwozi",
    "gn:population":0,
    "gn:timezone":"Asia/Shanghai",
    "iso:country":"CN",
    "name:zho_x_preferred":[
        "\u9ed1\u5367\u5b50"
    ],
    "wof:name":"Heiwozi",
    "wof:placetype":"locality"
},
  "geometry": {"coordinates":[124.199,40.7813],"type":"Point"}
}