{
  "type": "Feature",
  "properties": {
    "gn:admin1_code":"09",
    "gn:asciiname":"Qiliping",
    "gn:cc2":"CN",
    "gn:country_code":"CN",
    "gn:dem":256,
    "gn:feature_class":"P",
    "gn:feature_code":"PPL",
    "gn:name":"Qiliping",
    "gn:population":0,
    "gn:timezone":"Asia/Shanghai",
    "iso:country":"CN",
    "name:und_x_variant":[
        "Ch\u2019i-li-p\u2019ing",
        "Qiliping"
    ],
    "wof:name":"Qiliping",
    "wof:placetype":"locality"
},
  "geometry": {"coordinates":[111.82333,33.32639],"type":"Point"}
}