{
  "type": "Feature",
  "properties": {
    "gn:admin1_code":"18",
    "gn:asciiname":"Bangeshan",
    "gn:country_code":"CN",
    "gn:dem":1461,
    "gn:feature_class":"P",
    "gn:feature_code":"PPL",
    "gn:name":"Bangeshan",
    "gn:population":0,
    "gn:timezone":"Asia/Shanghai",
    "iso:country":"CN",
    "name:zho_x_preferred":[
        "\u534a\u4e2a\u5c71"
    ],
    "wof:name":"Bangeshan",
    "wof:placetype":"locality"
},
  "geometry": {"coordinates":[104.81999999999999,25.7871],"type":"Point"}
}