{
  "type": "Feature",
  "properties": {
    "gn:admin1_code":"24.0",
    "gn:asciiname":"Qingzhong",
    "gn:country_code":"CN",
    "gn:dem":1067,
    "gn:feature_class":"P",
    "gn:feature_code":"PPL",
    "gn:name":"Qingzhong",
    "gn:population":0,
    "gn:timezone":"Asia/Shanghai",
    "iso:country":"CN",
    "name:und_x_variant":[
        "\u9752\u949f"
    ],
    "name:zho_x_preferred":[
        "\u9752\u949f"
    ],
    "wof:name":"Qingzhong",
    "wof:placetype":"locality"
},
  "geometry": {"coordinates":[112.58954,39.2048],"type":"Point"}
}