{
  "type": "Feature",
  "properties": {
    "gn:admin1_code":"29.0",
    "gn:asciiname":"Mangmianhe",
    "gn:country_code":"CN",
    "gn:dem":855,
    "gn:feature_class":"P",
    "gn:feature_code":"PPL",
    "gn:name":"Mangmianhe",
    "gn:population":0,
    "gn:timezone":"Asia/Shanghai",
    "iso:country":"CN",
    "name:zho_x_preferred":[
        "\u8292\u7f05\u6cb3"
    ],
    "wof:name":"Mangmianhe",
    "wof:placetype":"locality"
},
  "geometry": {"coordinates":[97.86709999999999,24.5742],"type":"Point"}
}