{
  "type": "Feature",
  "properties": {
    "gn:admin1_code":"16.0",
    "gn:asciiname":"Naliudong",
    "gn:country_code":"CN",
    "gn:dem":68,
    "gn:feature_class":"P",
    "gn:feature_code":"PPL",
    "gn:name":"Naliudong",
    "gn:population":0,
    "gn:timezone":"Asia/Shanghai",
    "iso:country":"CN",
    "name:zho_x_preferred":[
        "\u90a3\u516d\u6d1e"
    ],
    "wof:name":"Naliudong",
    "wof:placetype":"locality"
},
  "geometry": {"coordinates":[108.681,22.2874],"type":"Point"}
}