{
  "type": "Feature",
  "properties": {
    "gn:admin1_code":"7.0",
    "gn:asciiname":"Wulikeng",
    "gn:country_code":"CN",
    "gn:dem":460,
    "gn:feature_class":"P",
    "gn:feature_code":"PPL",
    "gn:name":"Wulikeng",
    "gn:population":0,
    "gn:timezone":"Asia/Shanghai",
    "iso:country":"CN",
    "name:zho_x_preferred":[
        "\u65e0\u529b\u5751"
    ],
    "wof:name":"Wulikeng",
    "wof:placetype":"locality"
},
  "geometry": {"coordinates":[117.33462,26.3672],"type":"Point"}
}