{
  "type": "Feature",
  "properties": {
    "gn:admin1_code":"30.0",
    "gn:asciiname":"Weili",
    "gn:country_code":"CN",
    "gn:dem":163,
    "gn:feature_class":"P",
    "gn:feature_code":"PPL",
    "gn:name":"Weili",
    "gn:population":0,
    "gn:timezone":"Asia/Shanghai",
    "iso:country":"CN",
    "name:zho_x_preferred":[
        "\u56f4\u4fda"
    ],
    "wof:name":"Weili",
    "wof:placetype":"locality"
},
  "geometry": {"coordinates":[114.56144999999999,25.16055],"type":"Point"}
}