{
  "type": "Feature",
  "properties": {
    "gn:admin1_code":"15.0",
    "gn:asciiname":"Zhewan",
    "gn:country_code":"CN",
    "gn:dem":1715,
    "gn:feature_class":"P",
    "gn:feature_code":"PPL",
    "gn:name":"Zhewan",
    "gn:population":0,
    "gn:timezone":"Asia/Shanghai",
    "iso:country":"CN",
    "name:zho_x_preferred":[
        "\u6298\u6e7e"
    ],
    "wof:name":"Zhewan",
    "wof:placetype":"locality"
},
  "geometry": {"coordinates":[106.057,34.816],"type":"Point"}
}