{
  "type": "Feature",
  "properties": {
    "gn:admin1_code":"25",
    "gn:asciiname":"Beitanpo",
    "gn:country_code":"CN",
    "gn:dem":36,
    "gn:feature_class":"P",
    "gn:feature_code":"PPL",
    "gn:name":"Beitanpo",
    "gn:population":0,
    "gn:timezone":"Asia/Shanghai",
    "iso:country":"CN",
    "name:zho_x_preferred":[
        "\u5317\u5766\u5761"
    ],
    "wof:name":"Beitanpo",
    "wof:placetype":"locality"
},
  "geometry": {"coordinates":[119.673,36.8684],"type":"Point"}
}