{
  "type": "Feature",
  "properties": {
    "gn:admin1_code":"29.0",
    "gn:asciiname":"Haicaitang",
    "gn:country_code":"CN",
    "gn:dem":2048,
    "gn:feature_class":"P",
    "gn:feature_code":"PPL",
    "gn:name":"Haicaitang",
    "gn:population":0,
    "gn:timezone":"Asia/Shanghai",
    "iso:country":"CN",
    "name:zho_x_preferred":[
        "\u6d77\u83dc\u5858"
    ],
    "wof:name":"Haicaitang",
    "wof:placetype":"locality"
},
  "geometry": {"coordinates":[99.1681,24.9641],"type":"Point"}
}