{
  "type": "Feature",
  "properties": {
    "gn:admin1_code":"19.0",
    "gn:asciiname":"Tongzigou",
    "gn:country_code":"CN",
    "gn:dem":490,
    "gn:feature_class":"P",
    "gn:feature_code":"PPL",
    "gn:name":"Tongzigou",
    "gn:population":0,
    "gn:timezone":"Asia/Shanghai",
    "iso:country":"CN",
    "name:zho_x_preferred":[
        "\u901a\u5b50\u6c9f"
    ],
    "wof:name":"Tongzigou",
    "wof:placetype":"locality"
},
  "geometry": {"coordinates":[124.48011,41.53467],"type":"Point"}
}