{
  "type": "Feature",
  "properties": {
    "gn:admin1_code":"9.0",
    "gn:asciiname":"Shangligou",
    "gn:country_code":"CN",
    "gn:dem":190,
    "gn:feature_class":"P",
    "gn:feature_code":"PPL",
    "gn:name":"Shangligou",
    "gn:population":0,
    "gn:timezone":"Asia/Shanghai",
    "iso:country":"CN",
    "name:und_x_variant":[
        "\u4e0a\u674e\u6c9f",
        "Shangligou"
    ],
    "wof:name":"Shangligou",
    "wof:placetype":"locality"
},
  "geometry": {"coordinates":[112.32767,33.14272],"type":"Point"}
}