{
  "type": "Feature",
  "properties": {
    "gn:admin1_code":"30",
    "gn:asciiname":"Qingkeng Linchang",
    "gn:country_code":"CN",
    "gn:dem":34,
    "gn:feature_class":"P",
    "gn:feature_code":"PPLF",
    "gn:name":"Qingkeng Linchang",
    "gn:population":0,
    "gn:timezone":"Asia/Shanghai",
    "iso:country":"CN",
    "name:zho_x_preferred":[
        "\u9752\u5751\u6797\u573a"
    ],
    "wof:name":"Qingkeng Linchang",
    "wof:placetype":"locality"
},
  "geometry": {"coordinates":[116.06977000000001,23.1239],"type":"Point"}
}