{
  "type": "Feature",
  "properties": {
    "gn:admin1_code":"6.0",
    "gn:asciiname":"Xianggu",
    "gn:country_code":"CN",
    "gn:dem":3505,
    "gn:feature_class":"P",
    "gn:feature_code":"PPL",
    "gn:name":"Xianggu",
    "gn:population":0,
    "gn:timezone":"Asia/Urumqi",
    "iso:country":"CN",
    "name:zho_x_preferred":[
        "\u76f8\u53e4"
    ],
    "wof:name":"Xianggu",
    "wof:placetype":"locality"
},
  "geometry": {"coordinates":[97.41354,32.71585],"type":"Point"}
}