{
  "type": "Feature",
  "properties": {
    "gn:admin1_code":"4.0",
    "gn:asciiname":"Guancang",
    "gn:country_code":"CN",
    "gn:dem":22,
    "gn:feature_class":"P",
    "gn:feature_code":"PPL",
    "gn:name":"Guancang",
    "gn:population":0,
    "gn:timezone":"Asia/Shanghai",
    "iso:country":"CN",
    "name:zho_x_preferred":[
        "\u7ba1\u4ed3"
    ],
    "wof:name":"Guancang",
    "wof:placetype":"locality"
},
  "geometry": {"coordinates":[119.23499,32.40147],"type":"Point"}
}