{
  "type": "Feature",
  "properties": {
    "gn:admin1_code":"30",
    "gn:asciiname":"Kuzhukeng",
    "gn:country_code":"CN",
    "gn:dem":587,
    "gn:feature_class":"P",
    "gn:feature_code":"PPL",
    "gn:name":"Kuzhukeng",
    "gn:population":0,
    "gn:timezone":"Asia/Shanghai",
    "iso:country":"CN",
    "name:zho_x_preferred":[
        "\u82e6\u7af9\u5751"
    ],
    "wof:name":"Kuzhukeng",
    "wof:placetype":"locality"
},
  "geometry": {"coordinates":[116.63124000000001,23.94396],"type":"Point"}
}