{
  "type": "Feature",
  "properties": {
    "gn:admin1_code":"29.0",
    "gn:asciiname":"Lawan",
    "gn:country_code":"CN",
    "gn:dem":900,
    "gn:feature_class":"P",
    "gn:feature_code":"PPL",
    "gn:name":"Lawan",
    "gn:population":0,
    "gn:timezone":"Asia/Shanghai",
    "iso:country":"CN",
    "name:ceb_x_preferred":[
        "Lawan"
    ],
    "name:jpn_x_preferred":[
        "\u30e9\u30ef\u30f3"
    ],
    "name:swe_x_preferred":[
        "Lawan"
    ],
    "name:zho_x_preferred":[
        "\u62c9\u6e7e"
    ],
    "wof:name":"Lawan",
    "wof:placetype":"locality"
},
  "geometry": {"coordinates":[98.0565,24.7953],"type":"Point"}
}