{
  "type": "Feature",
  "properties": {
    "gn:admin1_code":"5.0",
    "gn:asciiname":"Qianshangou",
    "gn:country_code":"CN",
    "gn:dem":211,
    "gn:feature_class":"P",
    "gn:feature_code":"PPL",
    "gn:name":"Qianshangou",
    "gn:population":0,
    "gn:timezone":"Asia/Shanghai",
    "iso:country":"CN",
    "name:zho_x_preferred":[
        "\u8fc1\u5584\u6c9f"
    ],
    "wof:name":"Qianshangou",
    "wof:placetype":"locality"
},
  "geometry": {"coordinates":[126.51002,44.98292],"type":"Point"}
}