{
  "type": "Feature",
  "properties": {
    "gn:admin1_code":"5.0",
    "gn:asciiname":"Houbaoletai",
    "gn:country_code":"CN",
    "gn:dem":136,
    "gn:feature_class":"P",
    "gn:feature_code":"PPL",
    "gn:name":"Houbaoletai",
    "gn:population":0,
    "gn:timezone":"Asia/Shanghai",
    "iso:country":"CN",
    "name:zho_x_preferred":[
        "\u540e\u5b9d\u52d2\u592a"
    ],
    "wof:name":"Houbaoletai",
    "wof:placetype":"locality"
},
  "geometry": {"coordinates":[124.37309999999999,45.17542],"type":"Point"}
}