{
  "type": "Feature",
  "properties": {
    "gn:admin1_code":"29.0",
    "gn:asciiname":"Beile'en",
    "gn:country_code":"CN",
    "gn:dem":2058,
    "gn:feature_class":"P",
    "gn:feature_code":"PPL",
    "gn:name":"Beile\u2019en",
    "gn:population":0,
    "gn:timezone":"Asia/Shanghai",
    "iso:country":"CN",
    "name:und_x_variant":[
        "Beile\u2019en"
    ],
    "name:zho_x_preferred":[
        "\u5317\u4e50\u6069"
    ],
    "wof:name":"Beile'en",
    "wof:placetype":"locality"
},
  "geometry": {"coordinates":[100.261,26.4399],"type":"Point"}
}