{
  "type": "Feature",
  "properties": {
    "gn:admin1_code":"16.0",
    "gn:asciiname":"Zhu'ergen",
    "gn:country_code":"CN",
    "gn:dem":35,
    "gn:feature_class":"P",
    "gn:feature_code":"PPL",
    "gn:name":"Zhu\u2019ergen",
    "gn:population":0,
    "gn:timezone":"Asia/Shanghai",
    "iso:country":"CN",
    "name:und_x_variant":[
        "Zhu\u2019ergen"
    ],
    "name:zho_x_preferred":[
        "\u7af9\u513f\u6839"
    ],
    "wof:name":"Zhu'ergen",
    "wof:placetype":"locality"
},
  "geometry": {"coordinates":[110.33199999999999,23.5679],"type":"Point"}
}