{
  "type": "Feature",
  "properties": {
    "gn:admin1_code":"14.0",
    "gn:asciiname":"Rengong Nongchang",
    "gn:country_code":"CN",
    "gn:dem":4117,
    "gn:feature_class":"P",
    "gn:feature_code":"PPLF",
    "gn:name":"Rengong Nongchang",
    "gn:population":0,
    "gn:timezone":"Asia/Shanghai",
    "iso:country":"CN",
    "name:zho_x_preferred":[
        "\u4ec1\u8d21\u519c\u573a"
    ],
    "wof:name":"Rengong Nongchang",
    "wof:placetype":"locality"
},
  "geometry": {"coordinates":[81.08839999999999,30.4844],"type":"Point"}
}