{
  "type": "Feature",
  "properties": {
    "gn:admin1_code":"24.0",
    "gn:asciiname":"Taoshangcun",
    "gn:country_code":"CN",
    "gn:dem":390,
    "gn:feature_class":"P",
    "gn:feature_code":"PPL",
    "gn:name":"Taoshangcun",
    "gn:population":0,
    "gn:timezone":"Asia/Shanghai",
    "iso:country":"CN",
    "name:zho_x_preferred":[
        "\u9676\u4e0a\u6751"
    ],
    "wof:name":"Taoshangcun",
    "wof:placetype":"locality"
},
  "geometry": {"coordinates":[110.97529,35.09636],"type":"Point"}
}