{
  "type": "Feature",
  "properties": {
    "gn:admin1_code":"3.0",
    "gn:asciiname":"Shanglingtian",
    "gn:country_code":"CN",
    "gn:dem":112,
    "gn:feature_class":"P",
    "gn:feature_code":"PPL",
    "gn:name":"Shanglingtian",
    "gn:population":0,
    "gn:timezone":"Asia/Shanghai",
    "iso:country":"CN",
    "name:und_x_variant":[
        "\u4e0a\u94c3\u7530"
    ],
    "wof:name":"Shanglingtian",
    "wof:placetype":"locality"
},
  "geometry": {"coordinates":[114.27538,28.14772],"type":"Point"}
}