{
  "type": "Feature",
  "properties": {
    "gn:admin1_code":"30.0",
    "gn:asciiname":"Sanhetang",
    "gn:country_code":"CN",
    "gn:dem":190,
    "gn:feature_class":"P",
    "gn:feature_code":"PPL",
    "gn:name":"Sanhetang",
    "gn:population":0,
    "gn:timezone":"Asia/Shanghai",
    "iso:country":"CN",
    "name:zho_x_preferred":[
        "Sanhetang"
    ],
    "name:zho_x_variant":[
        "\u4e09\u5408\u5858"
    ],
    "wof:name":"Sanhetang",
    "wof:placetype":"locality"
},
  "geometry": {"coordinates":[115.45972,24.25361],"type":"Point"}
}