{
  "type": "Feature",
  "properties": {
    "gn:admin1_code":"1.0",
    "gn:asciiname":"Nongfeng",
    "gn:country_code":"CN",
    "gn:dem":460,
    "gn:feature_class":"P",
    "gn:feature_code":"PPL",
    "gn:name":"Nongfeng",
    "gn:population":0,
    "gn:timezone":"Asia/Shanghai",
    "iso:country":"CN",
    "name:und_x_variant":[
        "\u519c\u4e30",
        "Nongfeng"
    ],
    "wof:name":"Nongfeng",
    "wof:placetype":"locality"
},
  "geometry": {"coordinates":[118.70929,29.90985],"type":"Point"}
}