{
  "type": "Feature",
  "properties": {
    "gn:admin1_code":"29",
    "gn:asciiname":"Tuguodong",
    "gn:country_code":"CN",
    "gn:dem":1334,
    "gn:feature_class":"P",
    "gn:feature_code":"PPL",
    "gn:name":"Tuguodong",
    "gn:population":0,
    "gn:timezone":"Asia/Shanghai",
    "iso:country":"CN",
    "name:zho_x_preferred":[
        "\u571f\u9505\u6d1e"
    ],
    "wof:name":"Tuguodong",
    "wof:placetype":"locality"
},
  "geometry": {"coordinates":[104.70399999999999,23.4767],"type":"Point"}
}