{
  "type": "Feature",
  "properties": {
    "gn:admin1_code":"5.0",
    "gn:asciiname":"Yangquanzi",
    "gn:country_code":"CN",
    "gn:dem":559,
    "gn:feature_class":"P",
    "gn:feature_code":"PPL",
    "gn:name":"Yangquanzi",
    "gn:population":0,
    "gn:timezone":"Asia/Shanghai",
    "iso:country":"CN",
    "name:und_x_variant":[
        "\u7f8a\u5708\u5b50"
    ],
    "wof:name":"Yangquanzi",
    "wof:placetype":"locality"
},
  "geometry": {"coordinates":[125.47955,41.68718],"type":"Point"}
}