{
  "type": "Feature",
  "properties": {
    "gn:admin1_code":"29.0",
    "gn:asciiname":"Ma'anshan",
    "gn:country_code":"CN",
    "gn:dem":2375,
    "gn:feature_class":"P",
    "gn:feature_code":"PPL",
    "gn:name":"Ma\u2019anshan",
    "gn:population":0,
    "gn:timezone":"Asia/Shanghai",
    "iso:country":"CN",
    "name:und_x_variant":[
        "Ma\u2019anshan"
    ],
    "name:zho_x_preferred":[
        "\u9a6c\u978d\u5c71"
    ],
    "wof:name":"Ma'anshan",
    "wof:placetype":"locality"
},
  "geometry": {"coordinates":[103.003,25.6262],"type":"Point"}
}