{
  "type": "Feature",
  "properties": {
    "gn:admin1_code":"16.0",
    "gn:asciiname":"Shangchangman",
    "gn:country_code":"CN",
    "gn:dem":171,
    "gn:feature_class":"P",
    "gn:feature_code":"PPL",
    "gn:name":"Shangchangman",
    "gn:population":0,
    "gn:timezone":"Asia/Shanghai",
    "iso:country":"CN",
    "name:zho_x_preferred":[
        "\u4e0a\u957f\u6ee1"
    ],
    "wof:name":"Shangchangman",
    "wof:placetype":"locality"
},
  "geometry": {"coordinates":[109.992,24.075],"type":"Point"}
}