{
  "type": "Feature",
  "properties": {
    "gn:admin1_code":"16.0",
    "gn:asciiname":"Laigeng",
    "gn:country_code":"CN",
    "gn:dem":738,
    "gn:feature_class":"P",
    "gn:feature_code":"PPL",
    "gn:name":"Laigeng",
    "gn:population":0,
    "gn:timezone":"Asia/Shanghai",
    "iso:country":"CN",
    "name:zho_x_preferred":[
        "\u8d56\u66f4"
    ],
    "wof:name":"Laigeng",
    "wof:placetype":"locality"
},
  "geometry": {"coordinates":[107.18899999999999,24.7443],"type":"Point"}
}