{
  "type": "Feature",
  "properties": {
    "gn:admin1_code":"19.0",
    "gn:asciiname":"Houhuangshanzi",
    "gn:country_code":"CN",
    "gn:dem":37,
    "gn:feature_class":"P",
    "gn:feature_code":"PPL",
    "gn:name":"Houhuangshanzi",
    "gn:population":0,
    "gn:timezone":"Asia/Shanghai",
    "iso:country":"CN",
    "name:und_x_variant":[
        "\u540e\u8352\u5c71\u5b50"
    ],
    "name:zho_x_preferred":[
        "\u540e\u8352\u5c71\u5b50"
    ],
    "wof:name":"Houhuangshanzi",
    "wof:placetype":"locality"
},
  "geometry": {"coordinates":[122.26361,41.91171],"type":"Point"}
}