{
  "type": "Feature",
  "properties": {
    "iso:country":"CN",
    "name:eng_x_preferred":[
        "Dongguan"
    ],
    "name:zho_x_preferred":[
        "\u4e1c\u839e\u5e02"
    ],
    "qs:name":"\u4e1c\u839e\u5e02",
    "qs:name_adm0":"\u4e2d\u570b",
    "qs:name_adm1":"\u5e7f\u4e1c\u7701",
    "qs:photos":3543,
    "qs:photos_1k":718,
    "qs:photos_9k":16,
    "qs:photos_9r":12,
    "qs:photos_all":3543,
    "qs:photos_sr":21,
    "qs:placetype":"Town",
    "qs:pop_sr":"0",
    "wof:name":"Dongguan",
    "wof:placetype":"locality"
},
  "geometry": {"coordinates":[113.734588,23.047511],"type":"Point"}
}