{
  "type": "Feature",
  "properties": {
    "gn:admin1_code":"2.0",
    "gn:asciiname":"Laodaokeng",
    "gn:country_code":"CN",
    "gn:dem":716,
    "gn:feature_class":"P",
    "gn:feature_code":"PPL",
    "gn:name":"Laodaokeng",
    "gn:population":0,
    "gn:timezone":"Asia/Shanghai",
    "iso:country":"CN",
    "name:zho_x_preferred":[
        "\u635e\u5200\u5751"
    ],
    "wof:name":"Laodaokeng",
    "wof:placetype":"locality"
},
  "geometry": {"coordinates":[119.58279,29.2292],"type":"Point"}
}