{
  "type": "Feature",
  "properties": {
    "gn:admin1_code":"33.0",
    "gn:asciiname":"Shunxi",
    "gn:country_code":"CN",
    "gn:dem":186,
    "gn:feature_class":"P",
    "gn:feature_code":"PPL",
    "gn:name":"Shunxi",
    "gn:population":0,
    "gn:timezone":"Asia/Shanghai",
    "iso:country":"CN",
    "name:zho_x_preferred":[
        "\u987a\u6eaa"
    ],
    "wof:name":"Shunxi",
    "wof:placetype":"locality"
},
  "geometry": {"coordinates":[108.07379,30.34526],"type":"Point"}
}