{
  "type": "Feature",
  "properties": {
    "gn:admin1_code":"1.0",
    "gn:asciiname":"Chayuancun",
    "gn:country_code":"CN",
    "gn:dem":67,
    "gn:feature_class":"P",
    "gn:feature_code":"PPL",
    "gn:name":"Chayuancun",
    "gn:population":0,
    "gn:timezone":"Asia/Shanghai",
    "iso:country":"CN",
    "name:zho_x_preferred":[
        "\u8336\u56ed\u6751"
    ],
    "wof:name":"Chayuancun",
    "wof:placetype":"locality"
},
  "geometry": {"coordinates":[117.02451000000001,31.30444],"type":"Point"}
}