{
  "type": "Feature",
  "properties": {
    "gn:admin1_code":"11",
    "gn:asciiname":"Baima",
    "gn:country_code":"CN",
    "gn:dem":218,
    "gn:feature_class":"P",
    "gn:feature_code":"PPL",
    "gn:name":"Baima",
    "gn:population":0,
    "gn:timezone":"Asia/Shanghai",
    "iso:country":"CN",
    "name:ceb_x_preferred":[
        "Baima"
    ],
    "name:deu_x_preferred":[
        "Baima"
    ],
    "name:nor_x_preferred":[
        "Baima"
    ],
    "wof:name":"Baima",
    "wof:placetype":"locality"
},
  "geometry": {"coordinates":[111.48389,27.20833],"type":"Point"}
}