{
  "type": "Feature",
  "properties": {
    "gn:admin1_code":"32.0",
    "gn:asciiname":"Yonghu",
    "gn:country_code":"CN",
    "gn:dem":506,
    "gn:feature_class":"P",
    "gn:feature_code":"PPL",
    "gn:name":"Yonghu",
    "gn:population":0,
    "gn:timezone":"Asia/Shanghai",
    "iso:country":"CN",
    "name:zho_x_preferred":[
        "\u62e5\u62a4"
    ],
    "wof:name":"Yonghu",
    "wof:placetype":"locality"
},
  "geometry": {"coordinates":[104.20699999999999,30.61],"type":"Point"}
}