{
  "type": "Feature",
  "properties": {
    "gn:admin1_code":"15.0",
    "gn:asciiname":"Lianwan",
    "gn:country_code":"CN",
    "gn:dem":1847,
    "gn:feature_class":"P",
    "gn:feature_code":"PPL",
    "gn:name":"Lianwan",
    "gn:population":0,
    "gn:timezone":"Asia/Shanghai",
    "iso:country":"CN",
    "name:und_x_variant":[
        "\u8fde\u6e7e"
    ],
    "wof:name":"Lianwan",
    "wof:placetype":"locality"
},
  "geometry": {"coordinates":[105.84443,35.38954000000001],"type":"Point"}
}