{
  "type": "Feature",
  "properties": {
    "gn:admin1_code":"11.0",
    "gn:asciiname":"Yaji'ao",
    "gn:country_code":"CN",
    "gn:dem":189,
    "gn:feature_class":"P",
    "gn:feature_code":"PPL",
    "gn:name":"Yaji\u2019ao",
    "gn:population":0,
    "gn:timezone":"Asia/Shanghai",
    "iso:country":"CN",
    "name:und_x_variant":[
        "Yaji\u2019ao"
    ],
    "name:zho_x_preferred":[
        "\u96c5\u5409\u5773"
    ],
    "wof:name":"Yaji'ao",
    "wof:placetype":"locality"
},
  "geometry": {"coordinates":[112.05719000000001,27.19041],"type":"Point"}
}