{
  "type": "Feature",
  "properties": {
    "gn:admin1_code":"16",
    "gn:asciiname":"Dongjiang",
    "gn:country_code":"CN",
    "gn:dem":146,
    "gn:feature_class":"P",
    "gn:feature_code":"PPL",
    "gn:name":"Dongjiang",
    "gn:population":0,
    "gn:timezone":"Asia/Shanghai",
    "iso:country":"CN",
    "name:und_x_variant":[
        "Tung-chiang",
        "Dongjiang"
    ],
    "name:zho_x_preferred":[
        "\u4e1c\u6c5f"
    ],
    "wof:name":"Dongjiang",
    "wof:placetype":"locality"
},
  "geometry": {"coordinates":[109.336,25.0387],"type":"Point"}
}