{
  "type": "Feature",
  "properties": {
    "gn:admin1_code":"29.0",
    "gn:asciiname":"Dayuanzi",
    "gn:country_code":"CN",
    "gn:dem":1434,
    "gn:feature_class":"P",
    "gn:feature_code":"PPL",
    "gn:name":"Dayuanzi",
    "gn:population":0,
    "gn:timezone":"Asia/Shanghai",
    "iso:country":"CN",
    "name:zho_x_preferred":[
        "\u5927\u56ed\u5b50"
    ],
    "wof:name":"Dayuanzi",
    "wof:placetype":"locality"
},
  "geometry": {"coordinates":[99.1915,24.2295],"type":"Point"}
}