{
  "type": "Feature",
  "properties": {
    "gn:admin1_code":"14.0",
    "gn:asciiname":"Gangduo",
    "gn:country_code":"CN",
    "gn:dem":4231,
    "gn:feature_class":"P",
    "gn:feature_code":"PPL",
    "gn:name":"Gangduo",
    "gn:population":0,
    "gn:timezone":"Asia/Urumqi",
    "iso:country":"CN",
    "name:zho_x_preferred":[
        "\u5c97\u591a"
    ],
    "wof:name":"Gangduo",
    "wof:placetype":"locality"
},
  "geometry": {"coordinates":[91.53672,29.4996],"type":"Point"}
}