{
  "type": "Feature",
  "properties": {
    "gn:admin1_code":"32.0",
    "gn:asciiname":"Ziyu",
    "gn:country_code":"CN",
    "gn:dem":2234,
    "gn:feature_class":"P",
    "gn:feature_code":"PPL",
    "gn:name":"Ziyu",
    "gn:population":0,
    "gn:timezone":"Asia/Shanghai",
    "iso:country":"CN",
    "name:zho_x_preferred":[
        "\u81ea\u7389"
    ],
    "wof:name":"Ziyu",
    "wof:placetype":"locality"
},
  "geometry": {"coordinates":[104.048,33.5199],"type":"Point"}
}