{
  "type": "Feature",
  "properties": {
    "gn:admin1_code":"3.0",
    "gn:asciiname":"Xindian",
    "gn:cc2":"CN",
    "gn:country_code":"CN",
    "gn:dem":425,
    "gn:feature_class":"P",
    "gn:feature_code":"PPL",
    "gn:name":"Xindian",
    "gn:population":0,
    "gn:timezone":"Asia/Shanghai",
    "iso:country":"CN",
    "name:ceb_x_preferred":[
        "Xindian"
    ],
    "name:deu_x_preferred":[
        "Xindian"
    ],
    "name:swe_x_preferred":[
        "Xindian"
    ],
    "name:und_x_variant":[
        "Hsin-tien"
    ],
    "wof:name":"Xindian",
    "wof:placetype":"locality"
},
  "geometry": {"coordinates":[114.09999999999999,27.53333],"type":"Point"}
}