{
  "type": "Feature",
  "properties": {
    "gn:admin1_code":"11",
    "gn:asciiname":"Xiangjiatian",
    "gn:country_code":"CN",
    "gn:dem":490,
    "gn:feature_class":"P",
    "gn:feature_code":"PPL",
    "gn:name":"Xiangjiatian",
    "gn:population":0,
    "gn:timezone":"Asia/Shanghai",
    "iso:country":"CN",
    "name:zho_x_preferred":[
        "\u5411\u5bb6\u7530"
    ],
    "wof:name":"Xiangjiatian",
    "wof:placetype":"locality"
},
  "geometry": {"coordinates":[110.31646000000001,27.22422000000001],"type":"Point"}
}