{
  "type": "Feature",
  "properties": {
    "gn:admin1_code":"3.0",
    "gn:asciiname":"Heyuan Weixiaojia",
    "gn:country_code":"CN",
    "gn:dem":61,
    "gn:feature_class":"P",
    "gn:feature_code":"PPL",
    "gn:name":"Heyuan Weixiaojia",
    "gn:population":0,
    "gn:timezone":"Asia/Shanghai",
    "iso:country":"CN",
    "name:und_x_variant":[
        "\u6cb3\u6e90\u6e2d\u8096\u5bb6"
    ],
    "wof:name":"Heyuan Weixiaojia",
    "wof:placetype":"locality"
},
  "geometry": {"coordinates":[115.21835,28.06015],"type":"Point"}
}