{
  "type": "Feature",
  "properties": {
    "gn:admin1_code":"8.0",
    "gn:asciiname":"Gengtiancun",
    "gn:country_code":"CN",
    "gn:dem":187,
    "gn:feature_class":"P",
    "gn:feature_code":"PPL",
    "gn:name":"Gengtiancun",
    "gn:population":0,
    "gn:timezone":"Asia/Shanghai",
    "iso:country":"CN",
    "name:zho_x_preferred":[
        "\u8015\u7530\u6751"
    ],
    "wof:name":"Gengtiancun",
    "wof:placetype":"locality"
},
  "geometry": {"coordinates":[127.24573999999998,46.58009000000001],"type":"Point"}
}