{
  "type": "Feature",
  "properties": {
    "gn:admin1_code":"29.0",
    "gn:asciiname":"Shulong Xinzhai",
    "gn:country_code":"CN",
    "gn:dem":1291,
    "gn:feature_class":"P",
    "gn:feature_code":"PPL",
    "gn:name":"Shulong Xinzhai",
    "gn:population":0,
    "gn:timezone":"Asia/Shanghai",
    "iso:country":"CN",
    "name:zho_x_preferred":[
        "\u6811\u9f99\u65b0\u5be8"
    ],
    "wof:name":"Shulong Xinzhai",
    "wof:placetype":"locality"
},
  "geometry": {"coordinates":[104.413,24.1601],"type":"Point"}
}