{
  "type": "Feature",
  "properties": {
    "gn:admin1_code":"3",
    "gn:asciiname":"Xiashantian",
    "gn:country_code":"CN",
    "gn:dem":149,
    "gn:feature_class":"P",
    "gn:feature_code":"PPL",
    "gn:name":"Xiashantian",
    "gn:population":0,
    "gn:timezone":"Asia/Shanghai",
    "iso:country":"CN",
    "name:zho_x_preferred":[
        "\u4e0b\u5c71\u7530"
    ],
    "wof:name":"Xiashantian",
    "wof:placetype":"locality"
},
  "geometry": {"coordinates":[114.764,25.6337],"type":"Point"}
}