{
  "type": "Feature",
  "properties": {
    "gn:admin1_code":"7.0",
    "gn:asciiname":"Yukeng",
    "gn:country_code":"CN",
    "gn:dem":386,
    "gn:feature_class":"P",
    "gn:feature_code":"PPL",
    "gn:name":"Yukeng",
    "gn:population":0,
    "gn:timezone":"Asia/Shanghai",
    "iso:country":"CN",
    "name:zho_x_preferred":[
        "\u828b\u5751"
    ],
    "wof:name":"Yukeng",
    "wof:placetype":"locality"
},
  "geometry": {"coordinates":[118.97396999999999,25.8897],"type":"Point"}
}