{
  "type": "Feature",
  "properties": {
    "gn:admin1_code":"29.0",
    "gn:asciiname":"Tuopu",
    "gn:country_code":"CN",
    "gn:dem":1490,
    "gn:feature_class":"P",
    "gn:feature_code":"PPL",
    "gn:name":"Tuopu",
    "gn:population":0,
    "gn:timezone":"Asia/Shanghai",
    "iso:country":"CN",
    "name:zho_x_preferred":[
        "\u59a5\u6d66"
    ],
    "wof:name":"Tuopu",
    "wof:placetype":"locality"
},
  "geometry": {"coordinates":[102.163,23.3429],"type":"Point"}
}