{
  "type": "Feature",
  "properties": {
    "gn:admin1_code":"29.0",
    "gn:asciiname":"Guozhe",
    "gn:country_code":"CN",
    "gn:dem":1133,
    "gn:feature_class":"P",
    "gn:feature_code":"PPL",
    "gn:name":"Guozhe",
    "gn:population":0,
    "gn:timezone":"Asia/Shanghai",
    "iso:country":"CN",
    "name:zho_x_preferred":[
        "\u8fc7\u8005"
    ],
    "wof:name":"Guozhe",
    "wof:placetype":"locality"
},
  "geometry": {"coordinates":[101.43000000000001,23.4408],"type":"Point"}
}