{
  "type": "Feature",
  "properties": {
    "gn:admin1_code":"2.0",
    "gn:asciiname":"Lingshan",
    "gn:country_code":"CN",
    "gn:dem":128,
    "gn:feature_class":"P",
    "gn:feature_code":"PPL",
    "gn:name":"Lingshan",
    "gn:population":0,
    "gn:timezone":"Asia/Shanghai",
    "iso:country":"CN",
    "name:ceb_x_preferred":[
        "Lingshan"
    ],
    "name:deu_x_preferred":[
        "Lingshan"
    ],
    "name:swe_x_preferred":[
        "Lingshan"
    ],
    "name:zho_x_preferred":[
        "\u7075\u5c71"
    ],
    "wof:name":"Lingshan",
    "wof:placetype":"locality"
},
  "geometry": {"coordinates":[118.58882,28.63476],"type":"Point"}
}