{
  "type": "Feature",
  "properties": {
    "gn:admin1_code":"11",
    "gn:asciiname":"Longyuanchong",
    "gn:country_code":"CN",
    "gn:dem":119,
    "gn:feature_class":"P",
    "gn:feature_code":"PPL",
    "gn:name":"Longyuanchong",
    "gn:population":0,
    "gn:timezone":"Asia/Shanghai",
    "iso:country":"CN",
    "name:zho_x_preferred":[
        "\u9f99\u5143\u51b2"
    ],
    "wof:name":"Longyuanchong",
    "wof:placetype":"locality"
},
  "geometry": {"coordinates":[112.30709,26.44954],"type":"Point"}
}