{
  "type": "Feature",
  "properties": {
    "gn:admin1_code":"10",
    "gn:asciiname":"Qinjia Yingzi",
    "gn:country_code":"CN",
    "gn:dem":1484,
    "gn:feature_class":"P",
    "gn:feature_code":"PPL",
    "gn:name":"Qinjia Yingzi",
    "gn:population":0,
    "gn:timezone":"Asia/Shanghai",
    "iso:country":"CN",
    "name:zho_x_preferred":[
        "\u79e6\u5bb6\u8425\u5b50"
    ],
    "wof:name":"Qinjia Yingzi",
    "wof:placetype":"locality"
},
  "geometry": {"coordinates":[115.5847,41.5372],"type":"Point"}
}