{
  "type": "Feature",
  "properties": {
    "gn:admin1_code":"8.0",
    "gn:asciiname":"Jinzhancun",
    "gn:country_code":"CN",
    "gn:dem":271,
    "gn:feature_class":"P",
    "gn:feature_code":"PPL",
    "gn:name":"Jinzhancun",
    "gn:population":0,
    "gn:timezone":"Asia/Shanghai",
    "iso:country":"CN",
    "name:zho_x_preferred":[
        "\u8fdb\u5c55\u6751"
    ],
    "wof:name":"Jinzhancun",
    "wof:placetype":"locality"
},
  "geometry": {"coordinates":[125.95143,47.71562],"type":"Point"}
}