{
  "type": "Feature",
  "properties": {
    "gn:admin1_code":"11.0",
    "gn:asciiname":"Wufanggong",
    "gn:country_code":"CN",
    "gn:dem":51,
    "gn:feature_class":"P",
    "gn:feature_code":"PPL",
    "gn:name":"Wufanggong",
    "gn:population":0,
    "gn:timezone":"Asia/Shanghai",
    "iso:country":"CN",
    "name:zho_x_preferred":[
        "\u4e94\u623f\u516c"
    ],
    "wof:name":"Wufanggong",
    "wof:placetype":"locality"
},
  "geometry": {"coordinates":[112.28964999999999,28.50023],"type":"Point"}
}