{
  "type": "Feature",
  "properties": {
    "gn:admin1_code":"3",
    "gn:asciiname":"Xiaorui",
    "gn:country_code":"CN",
    "gn:dem":76,
    "gn:feature_class":"P",
    "gn:feature_code":"PPL",
    "gn:name":"Xiaorui",
    "gn:population":0,
    "gn:timezone":"Asia/Shanghai",
    "iso:country":"CN",
    "name:zho_x_preferred":[
        "\u6653\u745e"
    ],
    "wof:name":"Xiaorui",
    "wof:placetype":"locality"
},
  "geometry": {"coordinates":[114.68300000000001,26.4857],"type":"Point"}
}