{
  "type": "Feature",
  "properties": {
    "gn:admin1_code":"30.0",
    "gn:asciiname":"Fengchaocun",
    "gn:country_code":"CN",
    "gn:dem":7,
    "gn:feature_class":"P",
    "gn:feature_code":"PPL",
    "gn:name":"Fengchaocun",
    "gn:population":0,
    "gn:timezone":"Asia/Shanghai",
    "iso:country":"CN",
    "name:zho_x_preferred":[
        "\u51e4\u6f6e\u6751"
    ],
    "wof:name":"Fengchaocun",
    "wof:placetype":"locality"
},
  "geometry": {"coordinates":[116.34147,23.5539],"type":"Point"}
}