{
  "type": "Feature",
  "properties": {
    "gn:admin1_code":"02",
    "gn:asciiname":"Libeiyangcun",
    "gn:country_code":"CN",
    "gn:dem":8,
    "gn:feature_class":"P",
    "gn:feature_code":"PPL",
    "gn:name":"Libeiyangcun",
    "gn:population":0,
    "gn:timezone":"Asia/Shanghai",
    "iso:country":"CN",
    "name:und_x_variant":[
        "Li-pei-yang",
        "Libeiyang",
        "Libeiyangcun"
    ],
    "name:zho_x_preferred":[
        "\u91cc\u5317\u579f\u6751"
    ],
    "wof:name":"Libeiyangcun",
    "wof:placetype":"locality"
},
  "geometry": {"coordinates":[120.66228999999998,27.83752],"type":"Point"}
}