{
  "type": "Feature",
  "properties": {
    "gn:admin1_code":"3.0",
    "gn:asciiname":"Heshanggang",
    "gn:country_code":"CN",
    "gn:dem":295,
    "gn:feature_class":"P",
    "gn:feature_code":"PPL",
    "gn:name":"Heshanggang",
    "gn:population":0,
    "gn:timezone":"Asia/Shanghai",
    "iso:country":"CN",
    "name:zho_x_preferred":[
        "\u548c\u5c1a\u5c97"
    ],
    "wof:name":"Heshanggang",
    "wof:placetype":"locality"
},
  "geometry": {"coordinates":[115.389,25.5579],"type":"Point"}
}