{
  "type": "Feature",
  "properties": {
    "gn:admin1_code":"18.0",
    "gn:asciiname":"Sansui",
    "gn:country_code":"CN",
    "gn:dem":1018,
    "gn:feature_class":"P",
    "gn:feature_code":"PPL",
    "gn:name":"Sansui",
    "gn:population":0,
    "gn:timezone":"Asia/Shanghai",
    "iso:country":"CN",
    "name:ceb_x_preferred":[
        "Sansui"
    ],
    "name:deu_x_preferred":[
        "Sansui"
    ],
    "name:zho_x_preferred":[
        "\u4e09\u7a57"
    ],
    "wof:name":"Sansui",
    "wof:placetype":"locality"
},
  "geometry": {"coordinates":[107.12139000000001,28.72694000000001],"type":"Point"}
}