{
  "type": "Feature",
  "properties": {
    "gn:admin1_code":"24.0",
    "gn:asciiname":"Dongwangjiagou",
    "gn:country_code":"CN",
    "gn:dem":1681,
    "gn:feature_class":"P",
    "gn:feature_code":"PPL",
    "gn:name":"Dongwangjiagou",
    "gn:population":0,
    "gn:timezone":"Asia/Shanghai",
    "iso:country":"CN",
    "name:und_x_variant":[
        "\u4e1c\u738b\u5bb6\u6c9f"
    ],
    "name:zho_x_preferred":[
        "\u4e1c\u738b\u5bb6\u6c9f"
    ],
    "wof:name":"Dongwangjiagou",
    "wof:placetype":"locality"
},
  "geometry": {"coordinates":[112.07398000000001,38.76493],"type":"Point"}
}