{
  "type": "Feature",
  "properties": {
    "gn:admin1_code":"02",
    "gn:asciiname":"Xiyuan",
    "gn:country_code":"CN",
    "gn:dem":457,
    "gn:feature_class":"P",
    "gn:feature_code":"PPL",
    "gn:name":"Xiyuan",
    "gn:population":0,
    "gn:timezone":"Asia/Shanghai",
    "iso:country":"CN",
    "name:deu_x_preferred":[
        "Xiyuan"
    ],
    "name:und_x_variant":[
        "\u6eaa\u6e90"
    ],
    "wof:name":"Xiyuan",
    "wof:placetype":"locality"
},
  "geometry": {"coordinates":[120.00203999999999,27.50107],"type":"Point"}
}