{
  "type": "Feature",
  "properties": {
    "gn:admin1_code":"12.0",
    "gn:asciiname":"Tujiawan",
    "gn:country_code":"CN",
    "gn:dem":88,
    "gn:feature_class":"P",
    "gn:feature_code":"PPL",
    "gn:name":"Tujiawan",
    "gn:population":0,
    "gn:timezone":"Asia/Shanghai",
    "iso:country":"CN",
    "name:zho_x_preferred":[
        "\u6d82\u5bb6\u6e7e"
    ],
    "wof:name":"Tujiawan",
    "wof:placetype":"locality"
},
  "geometry": {"coordinates":[112.41956999999999,31.77453],"type":"Point"}
}