{
  "type": "Feature",
  "properties": {
    "gn:admin1_code":"29.0",
    "gn:asciiname":"Wangduoluo",
    "gn:country_code":"CN",
    "gn:dem":1814,
    "gn:feature_class":"P",
    "gn:feature_code":"PPL",
    "gn:name":"Wangduoluo",
    "gn:population":0,
    "gn:timezone":"Asia/Shanghai",
    "iso:country":"CN",
    "name:zho_x_preferred":[
        "\u738b\u591a\u6d1b"
    ],
    "wof:name":"Wangduoluo",
    "wof:placetype":"locality"
},
  "geometry": {"coordinates":[98.89360000000001,25.7922],"type":"Point"}
}