{
  "type": "Feature",
  "properties": {
    "gn:admin1_code":"16.0",
    "gn:asciiname":"Longbian",
    "gn:country_code":"CN",
    "gn:dem":327,
    "gn:feature_class":"P",
    "gn:feature_code":"PPL",
    "gn:name":"Longbian",
    "gn:population":0,
    "gn:timezone":"Asia/Shanghai",
    "iso:country":"CN",
    "name:zho_x_preferred":[
        "\u9f99\u8fb9"
    ],
    "wof:name":"Longbian",
    "wof:placetype":"locality"
},
  "geometry": {"coordinates":[106.926,22.2078],"type":"Point"}
}