{
  "type": "Feature",
  "properties": {
    "gn:admin1_code":"29.0",
    "gn:asciiname":"Bizechang",
    "gn:country_code":"CN",
    "gn:dem":1978,
    "gn:feature_class":"P",
    "gn:feature_code":"PPL",
    "gn:name":"Bizechang",
    "gn:population":0,
    "gn:timezone":"Asia/Shanghai",
    "iso:country":"CN",
    "name:zho_x_preferred":[
        "\u6bd4\u5219\u5382"
    ],
    "wof:name":"Bizechang",
    "wof:placetype":"locality"
},
  "geometry": {"coordinates":[103.461,26.4934],"type":"Point"}
}