{
  "type": "Feature",
  "properties": {
    "gn:admin1_code":"19.0",
    "gn:asciiname":"Shangtao Huatucun",
    "gn:country_code":"CN",
    "gn:dem":216,
    "gn:feature_class":"P",
    "gn:feature_code":"PPL",
    "gn:name":"Shangtao Huatucun",
    "gn:population":0,
    "gn:timezone":"Asia/Shanghai",
    "iso:country":"CN",
    "name:und_x_variant":[
        "Shangtaohuatucun",
        "Shangtao Huatucun"
    ],
    "name:zho_x_preferred":[
        "\u4e0a\u6843\u82b1\u5410\u6751"
    ],
    "wof:name":"Shangtao Huatucun",
    "wof:placetype":"locality"
},
  "geometry": {"coordinates":[120.59633999999998,41.73031],"type":"Point"}
}