{
  "type": "Feature",
  "properties": {
    "gn:admin1_code":"30",
    "gn:asciiname":"Baikengwei",
    "gn:country_code":"CN",
    "gn:dem":507,
    "gn:feature_class":"P",
    "gn:feature_code":"PPL",
    "gn:name":"Baikengwei",
    "gn:population":0,
    "gn:timezone":"Asia/Urumqi",
    "iso:country":"CN",
    "name:zho_x_preferred":[
        "\u67cf\u5751\u5c3e"
    ],
    "wof:name":"Baikengwei",
    "wof:placetype":"locality"
},
  "geometry": {"coordinates":[111.15940000000001,22.21161],"type":"Point"}
}