{
  "type": "Feature",
  "properties": {
    "gn:admin1_code":"5.0",
    "gn:asciiname":"Wulongcun",
    "gn:country_code":"CN",
    "gn:dem":343,
    "gn:feature_class":"P",
    "gn:feature_code":"PPL",
    "gn:name":"Wulongcun",
    "gn:population":0,
    "gn:timezone":"Asia/Shanghai",
    "iso:country":"CN",
    "name:zho_x_preferred":[
        "\u4e4c\u9f99\u6751"
    ],
    "wof:name":"Wulongcun",
    "wof:placetype":"locality"
},
  "geometry": {"coordinates":[124.98922,42.8007],"type":"Point"}
}