{
  "type": "Feature",
  "properties": {
    "gn:admin1_code":"3.0",
    "gn:asciiname":"Guanhu",
    "gn:country_code":"CN",
    "gn:dem":19,
    "gn:feature_class":"P",
    "gn:feature_code":"PPL",
    "gn:name":"Guanhu",
    "gn:population":0,
    "gn:timezone":"Asia/Shanghai",
    "iso:country":"CN",
    "name:und_x_variant":[
        "\u5b98\u6e56"
    ],
    "wof:name":"Guanhu",
    "wof:placetype":"locality"
},
  "geometry": {"coordinates":[115.87139999999999,29.72687],"type":"Point"}
}