{
  "type": "Feature",
  "properties": {
    "gn:admin1_code":"2.0",
    "gn:asciiname":"Mihuyan",
    "gn:country_code":"CN",
    "gn:dem":425,
    "gn:feature_class":"P",
    "gn:feature_code":"PPL",
    "gn:name":"Mihuyan",
    "gn:population":0,
    "gn:timezone":"Asia/Shanghai",
    "iso:country":"CN",
    "name:zho_x_preferred":[
        "\u7c73\u864e\u5ca9"
    ],
    "wof:name":"Mihuyan",
    "wof:placetype":"locality"
},
  "geometry": {"coordinates":[121.32208,29.44818],"type":"Point"}
}