{
  "type": "Feature",
  "properties": {
    "gn:admin1_code":"05",
    "gn:asciiname":"Zhongxingcun",
    "gn:country_code":"CN",
    "gn:dem":268,
    "gn:feature_class":"P",
    "gn:feature_code":"PPL",
    "gn:name":"Zhongxingcun",
    "gn:population":0,
    "gn:timezone":"Asia/Shanghai",
    "iso:country":"CN",
    "name:und_x_variant":[
        "Zhongxingtun"
    ],
    "name:zho_x_preferred":[
        "\u4e2d\u5174\u6751"
    ],
    "wof:name":"Zhongxingcun",
    "wof:placetype":"locality"
},
  "geometry": {"coordinates":[126.88864,43.78513],"type":"Point"}
}