{
  "type": "Feature",
  "properties": {
    "gn:admin1_code":"26.0",
    "gn:asciiname":"Houjiagoucun",
    "gn:country_code":"CN",
    "gn:dem":1091,
    "gn:feature_class":"P",
    "gn:feature_code":"PPL",
    "gn:name":"Houjiagoucun",
    "gn:population":0,
    "gn:timezone":"Asia/Shanghai",
    "iso:country":"CN",
    "name:zho_x_preferred":[
        "\u4faf\u5bb6\u6c9f\u6751"
    ],
    "wof:name":"Houjiagoucun",
    "wof:placetype":"locality"
},
  "geometry": {"coordinates":[109.41392999999999,36.62124],"type":"Point"}
}