{
  "type": "Feature",
  "properties": {
    "gn:admin1_code":"11.0",
    "gn:asciiname":"Daxuantang",
    "gn:country_code":"CN",
    "gn:dem":125,
    "gn:feature_class":"P",
    "gn:feature_code":"PPL",
    "gn:name":"Daxuantang",
    "gn:population":0,
    "gn:timezone":"Asia/Shanghai",
    "iso:country":"CN",
    "name:zho_x_preferred":[
        "\u5927\u7384\u5858"
    ],
    "wof:name":"Daxuantang",
    "wof:placetype":"locality"
},
  "geometry": {"coordinates":[112.50338000000001,26.36558],"type":"Point"}
}