{
  "type": "Feature",
  "properties": {
    "gn:admin1_code":"16.0",
    "gn:asciiname":"Guansuoying",
    "gn:country_code":"CN",
    "gn:dem":72,
    "gn:feature_class":"P",
    "gn:feature_code":"PPL",
    "gn:name":"Guansuoying",
    "gn:population":0,
    "gn:timezone":"Asia/Shanghai",
    "iso:country":"CN",
    "name:zho_x_preferred":[
        "\u5173\u6240\u8425"
    ],
    "wof:name":"Guansuoying",
    "wof:placetype":"locality"
},
  "geometry": {"coordinates":[109.51000000000001,21.7808],"type":"Point"}
}