{
  "type": "Feature",
  "properties": {
    "gn:admin1_code":"32.0",
    "gn:asciiname":"Anziping",
    "gn:country_code":"CN",
    "gn:dem":1016,
    "gn:feature_class":"P",
    "gn:feature_code":"PPL",
    "gn:name":"Anziping",
    "gn:population":0,
    "gn:timezone":"Asia/Shanghai",
    "iso:country":"CN",
    "name:und_x_variant":[
        "\u978d\u5b50\u576a"
    ],
    "wof:name":"Anziping",
    "wof:placetype":"locality"
},
  "geometry": {"coordinates":[106.61886,32.64073],"type":"Point"}
}