{
  "type": "Feature",
  "properties": {
    "gn:admin1_code":"15.0",
    "gn:asciiname":"Nanpo",
    "gn:country_code":"CN",
    "gn:dem":1916,
    "gn:feature_class":"P",
    "gn:feature_code":"PPL",
    "gn:name":"Nanpo",
    "gn:population":0,
    "gn:timezone":"Asia/Shanghai",
    "iso:country":"CN",
    "name:und_x_variant":[
        "\u5357\u5761"
    ],
    "wof:name":"Nanpo",
    "wof:placetype":"locality"
},
  "geometry": {"coordinates":[105.06931000000002,35.72623],"type":"Point"}
}