{
  "type": "Feature",
  "properties": {
    "gn:admin1_code":"29.0",
    "gn:asciiname":"Dachuma",
    "gn:country_code":"CN",
    "gn:dem":1404,
    "gn:feature_class":"P",
    "gn:feature_code":"PPL",
    "gn:name":"Dachuma",
    "gn:population":0,
    "gn:timezone":"Asia/Shanghai",
    "iso:country":"CN",
    "name:zho_x_preferred":[
        "\u5927\u51fa\u9a6c"
    ],
    "wof:name":"Dachuma",
    "wof:placetype":"locality"
},
  "geometry": {"coordinates":[102.01600000000001,23.0153],"type":"Point"}
}