{
  "type": "Feature",
  "properties": {
    "gn:admin1_code":"14.0",
    "gn:asciiname":"Gaya",
    "gn:country_code":"CN",
    "gn:dem":3806,
    "gn:feature_class":"P",
    "gn:feature_code":"PPL",
    "gn:name":"Gaya",
    "gn:population":0,
    "gn:timezone":"Asia/Urumqi",
    "iso:country":"CN",
    "name:ara_x_preferred":[
        "\u062c\u0627\u064a\u0627"
    ],
    "name:aze_x_preferred":[
        "Qaya"
    ],
    "name:cat_x_preferred":[
        "Gaya"
    ],
    "name:ceb_x_preferred":[
        "Gaya"
    ],
    "name:ces_x_preferred":[
        "Gaya"
    ],
    "name:deu_x_preferred":[
        "Gaya"
    ],
    "name:fra_x_preferred":[
        "Gaya"
    ],
    "name:heb_x_preferred":[
        "\u05d2\u05d0\u05d9\u05d4"
    ],
    "name:hif_x_preferred":[
        "Gaya"
    ],
    "name:hye_x_preferred":[
        "\u0533\u0561\u0575\u0561"
    ],
    "name:ind_x_preferred":[
        "Gaya"
    ],
    "name:ita_x_preferred":[
        "Gaya"
    ],
    "name:kor_x_preferred":[
        "\uac00\uc57c"
    ],
    "name:lit_x_preferred":[
        "Gaja"
    ],
    "name:msa_x_preferred":[
        "Gaya"
    ],
    "name:nld_x_preferred":[
        "Gaya"
    ],
    "name:nor_x_preferred":[
        "Gaya"
    ],
    "name:pol_x_preferred":[
        "Gaya"
    ],
    "name:por_x_preferred":[
        "Gaya"
    ],
    "name:pus_x_preferred":[
        "\u06af\u0627\u064a\u0627"
    ],
    "name:rus_x_preferred":[
        "\u0413\u0430\u044f"
    ],
    "name:spa_x_preferred":[
        "Gaya"
    ],
    "name:swe_x_preferred":[
        "Gaya"
    ],
    "name:ukr_x_preferred":[
        "\u0413\u0430\u044f"
    ],
    "name:zho_x_preferred":[
        "\u560e\u5440"
    ],
    "wof:name":"Gaya",
    "wof:placetype":"locality"
},
  "geometry": {"coordinates":[94.27528,30.69977],"type":"Point"}
}