{
  "type": "Feature",
  "properties": {
    "gn:admin1_code":"19.0",
    "gn:asciiname":"Yangjia Wopu",
    "gn:country_code":"CN",
    "gn:dem":432,
    "gn:feature_class":"P",
    "gn:feature_code":"PPL",
    "gn:name":"Yangjia Wopu",
    "gn:population":0,
    "gn:timezone":"Asia/Shanghai",
    "iso:country":"CN",
    "name:zho_x_preferred":[
        "\u6768\u5bb6\u7a9d\u94fa"
    ],
    "wof:name":"Yangjia Wopu",
    "wof:placetype":"locality"
},
  "geometry": {"coordinates":[119.646,40.7791],"type":"Point"}
}