{
  "type": "Feature",
  "properties": {
    "gn:admin1_code":"18",
    "gn:asciiname":"Bingba",
    "gn:country_code":"CN",
    "gn:dem":990,
    "gn:feature_class":"P",
    "gn:feature_code":"PPL",
    "gn:name":"Bingba",
    "gn:population":0,
    "gn:timezone":"Asia/Shanghai",
    "iso:country":"CN",
    "name:zho_x_preferred":[
        "\u70b3\u575d"
    ],
    "wof:name":"Bingba",
    "wof:placetype":"locality"
},
  "geometry": {"coordinates":[105.84399999999999,25.6606],"type":"Point"}
}