{
  "type": "Feature",
  "properties": {
    "gn:admin1_code":"29.0",
    "gn:asciiname":"Hui'ai",
    "gn:country_code":"CN",
    "gn:dem":1244,
    "gn:feature_class":"P",
    "gn:feature_code":"PPL",
    "gn:name":"Hui\u2019ai",
    "gn:population":0,
    "gn:timezone":"Asia/Shanghai",
    "iso:country":"CN",
    "name:und_x_variant":[
        "Hui\u2019ai"
    ],
    "name:zho_x_preferred":[
        "\u56de\u7231"
    ],
    "wof:name":"Hui'ai",
    "wof:placetype":"locality"
},
  "geometry": {"coordinates":[99.36799999999999,23.437],"type":"Point"}
}