{
  "type": "Feature",
  "properties": {
    "gn:admin1_code":"16.0",
    "gn:asciiname":"Chidong",
    "gn:country_code":"CN",
    "gn:dem":656,
    "gn:feature_class":"P",
    "gn:feature_code":"PPL",
    "gn:name":"Chidong",
    "gn:population":0,
    "gn:timezone":"Asia/Shanghai",
    "iso:country":"CN",
    "name:zho_x_preferred":[
        "\u6c60\u6d1e"
    ],
    "wof:name":"Chidong",
    "wof:placetype":"locality"
},
  "geometry": {"coordinates":[108.715,25.1287],"type":"Point"}
}