{
  "type": "Feature",
  "properties": {
    "gn:admin1_code":"21.0",
    "gn:asciiname":"Xiabuxiang",
    "gn:country_code":"CN",
    "gn:dem":1933,
    "gn:feature_class":"P",
    "gn:feature_code":"PPL",
    "gn:name":"Xiabuxiang",
    "gn:population":0,
    "gn:timezone":"Asia/Shanghai",
    "iso:country":"CN",
    "name:und_x_variant":[
        "\u4e0b\u5821\u4e61"
    ],
    "name:zho_x_preferred":[
        "\u4e0b\u5821\u4e61"
    ],
    "wof:name":"Xiabuxiang",
    "wof:placetype":"locality"
},
  "geometry": {"coordinates":[105.90475000000001,36.00088],"type":"Point"}
}