{
  "type": "Feature",
  "properties": {
    "gn:admin1_code":"26.0",
    "gn:asciiname":"Shangguandimiao",
    "gn:country_code":"CN",
    "gn:dem":672,
    "gn:feature_class":"P",
    "gn:feature_code":"PPL",
    "gn:name":"Shangguandimiao",
    "gn:population":0,
    "gn:timezone":"Asia/Shanghai",
    "iso:country":"CN",
    "name:zho_x_preferred":[
        "\u4e0a\u5173\u5e1d\u5e99"
    ],
    "wof:name":"Shangguandimiao",
    "wof:placetype":"locality"
},
  "geometry": {"coordinates":[109.85623,32.62354000000001],"type":"Point"}
}