{
  "type": "Feature",
  "properties": {
    "gn:admin1_code":"16.0",
    "gn:asciiname":"Xiaowen",
    "gn:country_code":"CN",
    "gn:dem":44,
    "gn:feature_class":"P",
    "gn:feature_code":"PPL",
    "gn:name":"Xiaowen",
    "gn:population":0,
    "gn:timezone":"Asia/Shanghai",
    "iso:country":"CN",
    "name:fra_x_preferred":[
        "Xiaowen"
    ],
    "name:zho_x_preferred":[
        "\u5c0f\u6c76"
    ],
    "wof:name":"Xiaowen",
    "wof:placetype":"locality"
},
  "geometry": {"coordinates":[110.133,23.4297],"type":"Point"}
}