{
  "type": "Feature",
  "properties": {
    "gn:admin1_code":"03",
    "gn:asciiname":"Lutian",
    "gn:cc2":"CN",
    "gn:country_code":"CN",
    "gn:dem":20,
    "gn:feature_class":"P",
    "gn:feature_code":"PPL",
    "gn:name":"Lutian",
    "gn:population":0,
    "gn:timezone":"Asia/Shanghai",
    "iso:country":"CN",
    "name:und_x_variant":[
        "Lu-t\u2019ien",
        "Lutian"
    ],
    "wof:name":"Lutian",
    "wof:placetype":"locality"
},
  "geometry": {"coordinates":[116.83333,28.95],"type":"Point"}
}