{
  "type": "Feature",
  "properties": {
    "gn:admin1_code":"6.0",
    "gn:asciiname":"Mucao Liangzhong Fanzhichang",
    "gn:country_code":"CN",
    "gn:dem":3289,
    "gn:feature_class":"P",
    "gn:feature_code":"PPLF",
    "gn:name":"Mucao Liangzhong Fanzhichang",
    "gn:population":0,
    "gn:timezone":"Asia/Shanghai",
    "iso:country":"CN",
    "name:und_x_variant":[
        "\u7267\u8349\u826f\u79cd\u7e41\u6b96\u573a"
    ],
    "wof:name":"Mucao Liangzhong Fanzhichang",
    "wof:placetype":"locality"
},
  "geometry": {"coordinates":[100.65116,35.26076],"type":"Point"}
}