{
  "type": "Feature",
  "properties": {
    "gn:admin1_code":"19.0",
    "gn:asciiname":"Yanghuandong",
    "gn:country_code":"CN",
    "gn:dem":41,
    "gn:feature_class":"P",
    "gn:feature_code":"PPL",
    "gn:name":"Yanghuandong",
    "gn:population":0,
    "gn:timezone":"Asia/Shanghai",
    "iso:country":"CN",
    "name:zho_x_preferred":[
        "\u6768\u737e\u6d1e"
    ],
    "wof:name":"Yanghuandong",
    "wof:placetype":"locality"
},
  "geometry": {"coordinates":[122.786,42.0944],"type":"Point"}
}