{
  "type": "Feature",
  "properties": {
    "gn:admin1_code":"29.0",
    "gn:asciiname":"Shangshuipanpu",
    "gn:country_code":"CN",
    "gn:dem":1926,
    "gn:feature_class":"P",
    "gn:feature_code":"PPL",
    "gn:name":"Shangshuipanpu",
    "gn:population":0,
    "gn:timezone":"Asia/Shanghai",
    "iso:country":"CN",
    "name:zho_x_preferred":[
        "\u4e0a\u6c34\u76d8\u94fa"
    ],
    "wof:name":"Shangshuipanpu",
    "wof:placetype":"locality"
},
  "geometry": {"coordinates":[101.211,25.2187],"type":"Point"}
}