{
  "type": "Feature",
  "properties": {
    "gn:admin1_code":"12.0",
    "gn:asciiname":"Xinfanchang",
    "gn:country_code":"CN",
    "gn:dem":29,
    "gn:feature_class":"P",
    "gn:feature_code":"PPL",
    "gn:name":"Xinfanchang",
    "gn:population":0,
    "gn:timezone":"Asia/Shanghai",
    "iso:country":"CN",
    "name:zho_x_preferred":[
        "Xinfanchang"
    ],
    "name:zho_x_variant":[
        "\u65b0\u6a0a\u573a"
    ],
    "wof:name":"Xinfanchang",
    "wof:placetype":"locality"
},
  "geometry": {"coordinates":[112.55674999999999,30.40022],"type":"Point"}
}