{
  "type": "Feature",
  "properties": {
    "gn:admin1_code":"3.0",
    "gn:asciiname":"Guoluli",
    "gn:country_code":"CN",
    "gn:dem":208,
    "gn:feature_class":"P",
    "gn:feature_code":"PPL",
    "gn:name":"Guoluli",
    "gn:population":0,
    "gn:timezone":"Asia/Shanghai",
    "iso:country":"CN",
    "name:zho_x_preferred":[
        "\u9505\u7089\u91cc"
    ],
    "wof:name":"Guoluli",
    "wof:placetype":"locality"
},
  "geometry": {"coordinates":[117.15300000000001,29.6702],"type":"Point"}
}