{
  "type": "Feature",
  "properties": {
    "gn:admin1_code":"15.0",
    "gn:asciiname":"Sixiachuan",
    "gn:country_code":"CN",
    "gn:dem":2174,
    "gn:feature_class":"P",
    "gn:feature_code":"PPL",
    "gn:name":"Sixiachuan",
    "gn:population":0,
    "gn:timezone":"Asia/Shanghai",
    "iso:country":"CN",
    "name:und_x_variant":[
        "\u5bfa\u4e0b\u5ddd"
    ],
    "wof:name":"Sixiachuan",
    "wof:placetype":"locality"
},
  "geometry": {"coordinates":[103.8279,34.87696],"type":"Point"}
}