{
  "type": "Feature",
  "properties": {
    "gn:admin1_code":"11.0",
    "gn:asciiname":"Shangdongmaoping",
    "gn:country_code":"CN",
    "gn:dem":728,
    "gn:feature_class":"P",
    "gn:feature_code":"PPL",
    "gn:name":"Shangdongmaoping",
    "gn:population":0,
    "gn:timezone":"Asia/Shanghai",
    "iso:country":"CN",
    "name:zho_x_preferred":[
        "\u4e0a\u4e1c\u6bdb\u576a"
    ],
    "wof:name":"Shangdongmaoping",
    "wof:placetype":"locality"
},
  "geometry": {"coordinates":[110.23308,26.04713],"type":"Point"}
}