{
  "type": "Feature",
  "properties": {
    "gn:admin1_code":"26.0",
    "gn:asciiname":"Shichuanhe",
    "gn:country_code":"CN",
    "gn:dem":914,
    "gn:feature_class":"P",
    "gn:feature_code":"PPL",
    "gn:name":"Shichuanhe",
    "gn:population":0,
    "gn:timezone":"Asia/Shanghai",
    "iso:country":"CN",
    "name:zho_x_preferred":[
        "\u77f3\u5ddd\u6cb3"
    ],
    "wof:name":"Shichuanhe",
    "wof:placetype":"locality"
},
  "geometry": {"coordinates":[109.34593999999998,35.38287000000001],"type":"Point"}
}