{
  "type": "Feature",
  "properties": {
    "gn:admin1_code":"14.0",
    "gn:asciiname":"Longqingtong",
    "gn:country_code":"CN",
    "gn:dem":4402,
    "gn:feature_class":"P",
    "gn:feature_code":"PPL",
    "gn:name":"Longqingtong",
    "gn:population":0,
    "gn:timezone":"Asia/Urumqi",
    "iso:country":"CN",
    "name:zho_x_preferred":[
        "\u9f99\u9752\u901a"
    ],
    "wof:name":"Longqingtong",
    "wof:placetype":"locality"
},
  "geometry": {"coordinates":[95.35548,31.51011],"type":"Point"}
}