{
  "type": "Feature",
  "properties": {
    "gn:admin1_code":"3.0",
    "gn:asciiname":"Zhangwuchang",
    "gn:country_code":"CN",
    "gn:dem":194,
    "gn:feature_class":"P",
    "gn:feature_code":"PPL",
    "gn:name":"Zhangwuchang",
    "gn:population":0,
    "gn:timezone":"Asia/Shanghai",
    "iso:country":"CN",
    "name:zho_x_preferred":[
        "\u5f20\u5c4b\u573a"
    ],
    "wof:name":"Zhangwuchang",
    "wof:placetype":"locality"
},
  "geometry": {"coordinates":[115.08499999999999,25.7568],"type":"Point"}
}