{
  "type": "Feature",
  "properties": {
    "gn:admin1_code":"32",
    "gn:asciiname":"Guifu",
    "gn:country_code":"CN",
    "gn:dem":388,
    "gn:feature_class":"P",
    "gn:feature_code":"PPL",
    "gn:name":"Guifu",
    "gn:population":0,
    "gn:timezone":"Asia/Shanghai",
    "iso:country":"CN",
    "name:und_x_variant":[
        "Kuei-fu-i",
        "Kuei-fu",
        "Guifu"
    ],
    "name:zho_x_preferred":[
        "\u8d35\u798f"
    ],
    "wof:name":"Guifu",
    "wof:placetype":"locality"
},
  "geometry": {"coordinates":[106.98275,31.13126],"type":"Point"}
}