{
  "type": "Feature",
  "properties": {
    "gn:admin1_code":"16.0",
    "gn:asciiname":"Dima",
    "gn:country_code":"CN",
    "gn:dem":39,
    "gn:feature_class":"P",
    "gn:feature_code":"PPL",
    "gn:name":"Dima",
    "gn:population":0,
    "gn:timezone":"Asia/Shanghai",
    "iso:country":"CN",
    "name:ceb_x_preferred":[
        "Dima"
    ],
    "name:deu_x_preferred":[
        "Dima"
    ],
    "name:fra_x_preferred":[
        "Dima"
    ],
    "name:hun_x_preferred":[
        "Dima"
    ],
    "name:ita_x_preferred":[
        "Dima"
    ],
    "name:nld_x_preferred":[
        "Dima"
    ],
    "name:rus_x_preferred":[
        "\u0414\u0438\u043c\u0430"
    ],
    "name:sco_x_preferred":[
        "Dima"
    ],
    "name:swe_x_preferred":[
        "Dima"
    ],
    "name:ukr_x_preferred":[
        "\u0414\u0456\u043c\u0430"
    ],
    "name:vie_x_preferred":[
        "Dima"
    ],
    "name:zho_x_preferred":[
        "\u4f4e\u9a6c"
    ],
    "wof:name":"Dima",
    "wof:placetype":"locality"
},
  "geometry": {"coordinates":[109.45,21.8022],"type":"Point"}
}