{
  "type": "Feature",
  "properties": {
    "gn:admin1_code":"4.0",
    "gn:asciiname":"Nancunbacun",
    "gn:country_code":"CN",
    "gn:dem":5,
    "gn:feature_class":"P",
    "gn:feature_code":"PPL",
    "gn:name":"Nancunbacun",
    "gn:population":0,
    "gn:timezone":"Asia/Shanghai",
    "iso:country":"CN",
    "name:und_x_variant":[
        "\u5357\u6751\u575d\u6751"
    ],
    "name:zho_x_preferred":[
        "\u5357\u6751\u575d\u6751"
    ],
    "wof:name":"Nancunbacun",
    "wof:placetype":"locality"
},
  "geometry": {"coordinates":[120.58148,31.73029],"type":"Point"}
}