{
  "type": "Feature",
  "properties": {
    "gn:admin1_code":"3.0",
    "gn:asciiname":"Tangshanzhen",
    "gn:country_code":"CN",
    "gn:dem":26,
    "gn:feature_class":"P",
    "gn:feature_code":"PPL",
    "gn:name":"Tangshanzhen",
    "gn:population":0,
    "gn:timezone":"Asia/Shanghai",
    "iso:country":"CN",
    "name:und_x_variant":[
        "\u5858\u5c71\u9547"
    ],
    "wof:name":"Tangshanzhen",
    "wof:placetype":"locality"
},
  "geometry": {"coordinates":[115.93716000000001,28.72274],"type":"Point"}
}