{
  "type": "Feature",
  "properties": {
    "gn:admin1_code":"15.0",
    "gn:asciiname":"Jinjiaping",
    "gn:country_code":"CN",
    "gn:dem":1157,
    "gn:feature_class":"P",
    "gn:feature_code":"PPL",
    "gn:name":"Jinjiaping",
    "gn:population":0,
    "gn:timezone":"Asia/Shanghai",
    "iso:country":"CN",
    "name:und_x_variant":[
        "\u91d1\u5bb6\u576a"
    ],
    "wof:name":"Jinjiaping",
    "wof:placetype":"locality"
},
  "geometry": {"coordinates":[105.86844000000001,33.6316],"type":"Point"}
}