{
  "type": "Feature",
  "properties": {
    "gn:admin1_code":"24.0",
    "gn:asciiname":"Hedongyao",
    "gn:country_code":"CN",
    "gn:dem":1160,
    "gn:feature_class":"P",
    "gn:feature_code":"PPL",
    "gn:name":"Hedongyao",
    "gn:population":0,
    "gn:timezone":"Asia/Shanghai",
    "iso:country":"CN",
    "name:zho_x_preferred":[
        "\u6cb3\u4e1c\u7a91"
    ],
    "wof:name":"Hedongyao",
    "wof:placetype":"locality"
},
  "geometry": {"coordinates":[113.27358999999998,40.36384],"type":"Point"}
}