{
  "type": "Feature",
  "properties": {
    "gn:admin1_code":"26.0",
    "gn:asciiname":"Tang'an",
    "gn:country_code":"CN",
    "gn:dem":974,
    "gn:feature_class":"P",
    "gn:feature_code":"PPL",
    "gn:name":"Tang\u2019an",
    "gn:population":0,
    "gn:timezone":"Asia/Shanghai",
    "iso:country":"CN",
    "name:und_x_variant":[
        "Tang\u2019an",
        "\u6c64\u5eb5"
    ],
    "wof:name":"Tang'an",
    "wof:placetype":"locality"
},
  "geometry": {"coordinates":[107.65767,33.37742],"type":"Point"}
}