{
  "type": "Feature",
  "properties": {
    "gn:admin1_code":"8.0",
    "gn:asciiname":"Chaoyangtun",
    "gn:country_code":"CN",
    "gn:dem":145,
    "gn:feature_class":"P",
    "gn:feature_code":"PPL",
    "gn:name":"Chaoyangtun",
    "gn:population":0,
    "gn:timezone":"Asia/Shanghai",
    "iso:country":"CN",
    "name:zho_x_preferred":[
        "\u671d\u9633\u5c6f"
    ],
    "wof:name":"Chaoyangtun",
    "wof:placetype":"locality"
},
  "geometry": {"coordinates":[125.75366,46.11829],"type":"Point"}
}