{
  "type": "Feature",
  "properties": {
    "gn:admin1_code":"10",
    "gn:asciiname":"Beibate",
    "gn:country_code":"CN",
    "gn:dem":284,
    "gn:feature_class":"P",
    "gn:feature_code":"PPL",
    "gn:name":"Beibate",
    "gn:population":0,
    "gn:timezone":"Asia/Shanghai",
    "iso:country":"CN",
    "name:zho_x_preferred":[
        "\u5317\u516b\u7279"
    ],
    "wof:name":"Beibate",
    "wof:placetype":"locality"
},
  "geometry": {"coordinates":[114.09,36.5599],"type":"Point"}
}