{
  "type": "Feature",
  "properties": {
    "gn:admin1_code":"32.0",
    "gn:asciiname":"Yue'erqiu",
    "gn:country_code":"CN",
    "gn:dem":457,
    "gn:feature_class":"P",
    "gn:feature_code":"PPL",
    "gn:name":"Yue\u2019erqiu",
    "gn:population":0,
    "gn:timezone":"Asia/Shanghai",
    "iso:country":"CN",
    "name:und_x_variant":[
        "Yue\u2019erqiu"
    ],
    "name:zho_x_preferred":[
        "\u6708\u513f\u4e18"
    ],
    "wof:name":"Yue'erqiu",
    "wof:placetype":"locality"
},
  "geometry": {"coordinates":[107.895,30.9295],"type":"Point"}
}