{
  "type": "Feature",
  "properties": {
    "gn:admin1_code":"9.0",
    "gn:asciiname":"Zhangnainaimiao",
    "gn:country_code":"CN",
    "gn:dem":50,
    "gn:feature_class":"P",
    "gn:feature_code":"PPL",
    "gn:name":"Zhangnainaimiao",
    "gn:population":0,
    "gn:timezone":"Asia/Shanghai",
    "iso:country":"CN",
    "name:zho_x_preferred":[
        "\u5f20\u5976\u5976\u5e99"
    ],
    "wof:name":"Zhangnainaimiao",
    "wof:placetype":"locality"
},
  "geometry": {"coordinates":[114.69696,32.97311],"type":"Point"}
}