{
  "type": "Feature",
  "properties": {
    "gn:admin1_code":"30.0",
    "gn:asciiname":"Makeng",
    "gn:country_code":"CN",
    "gn:dem":198,
    "gn:feature_class":"P",
    "gn:feature_code":"PPL",
    "gn:name":"Makeng",
    "gn:population":0,
    "gn:timezone":"Asia/Shanghai",
    "iso:country":"CN",
    "name:zho_x_preferred":[
        "Makeng"
    ],
    "name:zho_x_variant":[
        "\u9ebb\u5751"
    ],
    "wof:name":"Makeng",
    "wof:placetype":"locality"
},
  "geometry": {"coordinates":[114.48412999999999,24.13719],"type":"Point"}
}