{
  "type": "Feature",
  "properties": {
    "gn:admin1_code":"12.0",
    "gn:asciiname":"Changmaosi",
    "gn:country_code":"CN",
    "gn:dem":603,
    "gn:feature_class":"P",
    "gn:feature_code":"PPL",
    "gn:name":"Changmaosi",
    "gn:population":0,
    "gn:timezone":"Asia/Shanghai",
    "iso:country":"CN",
    "name:zho_x_preferred":[
        "\u957f\u8302\u53f8"
    ],
    "wof:name":"Changmaosi",
    "wof:placetype":"locality"
},
  "geometry": {"coordinates":[110.44752,30.21276],"type":"Point"}
}