{
  "type": "Feature",
  "properties": {
    "gn:admin1_code":"7.0",
    "gn:asciiname":"Baishakeng",
    "gn:country_code":"CN",
    "gn:dem":527,
    "gn:feature_class":"P",
    "gn:feature_code":"PPL",
    "gn:name":"Baishakeng",
    "gn:population":0,
    "gn:timezone":"Asia/Shanghai",
    "iso:country":"CN",
    "name:und_x_variant":[
        "\u767d\u6c99\u5751"
    ],
    "wof:name":"Baishakeng",
    "wof:placetype":"locality"
},
  "geometry": {"coordinates":[116.87945000000001,27.0142],"type":"Point"}
}