{
  "type": "Feature",
  "properties": {
    "gn:admin1_code":"29.0",
    "gn:asciiname":"Masangping Shangcun",
    "gn:country_code":"CN",
    "gn:dem":2184,
    "gn:feature_class":"P",
    "gn:feature_code":"PPL",
    "gn:name":"Masangping Shangcun",
    "gn:population":0,
    "gn:timezone":"Asia/Shanghai",
    "iso:country":"CN",
    "name:zho_x_preferred":[
        "\u9a6c\u6851\u5e73\u4e0a\u6751"
    ],
    "wof:name":"Masangping Shangcun",
    "wof:placetype":"locality"
},
  "geometry": {"coordinates":[102.04600000000001,25.8389],"type":"Point"}
}