{
  "type": "Feature",
  "properties": {
    "gn:admin1_code":"16",
    "gn:asciiname":"Sunshantou",
    "gn:country_code":"CN",
    "gn:dem":1085,
    "gn:feature_class":"P",
    "gn:feature_code":"PPL",
    "gn:name":"Sunshantou",
    "gn:population":0,
    "gn:timezone":"Asia/Shanghai",
    "iso:country":"CN",
    "name:zho_x_preferred":[
        "\u7b0b\u5c71\u5934"
    ],
    "wof:name":"Sunshantou",
    "wof:placetype":"locality"
},
  "geometry": {"coordinates":[110.52500000000001,26.0293],"type":"Point"}
}