{
  "type": "Feature",
  "properties": {
    "gn:admin1_code":"13.0",
    "gn:asciiname":"Qiakeleke",
    "gn:country_code":"CN",
    "gn:dem":1226,
    "gn:feature_class":"P",
    "gn:feature_code":"PPL",
    "gn:name":"Qiakeleke",
    "gn:population":0,
    "gn:timezone":"Asia/Shanghai",
    "iso:country":"CN",
    "name:zho_x_preferred":[
        "\u6070\u514b\u52d2\u514b"
    ],
    "wof:name":"Qiakeleke",
    "wof:placetype":"locality"
},
  "geometry": {"coordinates":[76.5287,39.29559],"type":"Point"}
}