{
  "type": "Feature",
  "properties": {
    "gn:admin1_code":"30.0",
    "gn:asciiname":"Shegongbian",
    "gn:country_code":"CN",
    "gn:dem":18,
    "gn:feature_class":"P",
    "gn:feature_code":"PPL",
    "gn:name":"Shegongbian",
    "gn:population":0,
    "gn:timezone":"Asia/Shanghai",
    "iso:country":"CN",
    "name:zho_x_preferred":[
        "\u793e\u516c\u8fb9"
    ],
    "wof:name":"Shegongbian",
    "wof:placetype":"locality"
},
  "geometry": {"coordinates":[111.8805,23.12816],"type":"Point"}
}