{
  "type": "Feature",
  "properties": {
    "gn:admin1_code":"30",
    "gn:asciiname":"Fengshuke",
    "gn:country_code":"CN",
    "gn:dem":267,
    "gn:feature_class":"P",
    "gn:feature_code":"PPL",
    "gn:name":"Fengshuke",
    "gn:population":0,
    "gn:timezone":"Asia/Shanghai",
    "iso:country":"CN",
    "name:zho_x_preferred":[
        "\u98ce\u6811\u79d1"
    ],
    "wof:name":"Fengshuke",
    "wof:placetype":"locality"
},
  "geometry": {"coordinates":[116.64269,24.56915],"type":"Point"}
}