{
  "type": "Feature",
  "properties": {
    "gn:admin1_code":"11",
    "gn:asciiname":"Yanjiawan",
    "gn:country_code":"CN",
    "gn:dem":84,
    "gn:feature_class":"P",
    "gn:feature_code":"PPL",
    "gn:name":"Yanjiawan",
    "gn:population":0,
    "gn:timezone":"Asia/Shanghai",
    "iso:country":"CN",
    "name:zho_x_preferred":[
        "\u989c\u5bb6\u6e7e"
    ],
    "wof:name":"Yanjiawan",
    "wof:placetype":"locality"
},
  "geometry": {"coordinates":[112.47443,26.77269],"type":"Point"}
}