{
  "type": "Feature",
  "properties": {
    "gn:admin1_code":"3.0",
    "gn:asciiname":"Xishang",
    "gn:country_code":"CN",
    "gn:dem":103,
    "gn:feature_class":"P",
    "gn:feature_code":"PPL",
    "gn:name":"Xishang",
    "gn:population":0,
    "gn:timezone":"Asia/Shanghai",
    "iso:country":"CN",
    "name:und_x_variant":[
        "\u6eaa\u4e0a"
    ],
    "wof:name":"Xishang",
    "wof:placetype":"locality"
},
  "geometry": {"coordinates":[114.86857999999999,27.82023],"type":"Point"}
}