{
  "type": "Feature",
  "properties": {
    "gn:admin1_code":"16.0",
    "gn:asciiname":"Chajiang",
    "gn:country_code":"CN",
    "gn:dem":103,
    "gn:feature_class":"P",
    "gn:feature_code":"PPL",
    "gn:name":"Chajiang",
    "gn:population":0,
    "gn:timezone":"Asia/Shanghai",
    "iso:country":"CN",
    "name:zho_x_preferred":[
        "\u69ce\u6c5f"
    ],
    "wof:name":"Chajiang",
    "wof:placetype":"locality"
},
  "geometry": {"coordinates":[108.79600000000001,22.4574],"type":"Point"}
}