{
  "type": "Feature",
  "properties": {
    "gn:admin1_code":"2.0",
    "gn:asciiname":"Dalangkeng",
    "gn:country_code":"CN",
    "gn:dem":712,
    "gn:feature_class":"P",
    "gn:feature_code":"PPL",
    "gn:name":"Dalangkeng",
    "gn:population":0,
    "gn:timezone":"Asia/Shanghai",
    "iso:country":"CN",
    "name:zho_x_preferred":[
        "\u5927\u7405\u5751"
    ],
    "wof:name":"Dalangkeng",
    "wof:placetype":"locality"
},
  "geometry": {"coordinates":[118.59923000000001,29.2237],"type":"Point"}
}