{
  "type": "Feature",
  "properties": {
    "gn:admin1_code":"11.0",
    "gn:asciiname":"Jiaodaopo",
    "gn:country_code":"CN",
    "gn:dem":792,
    "gn:feature_class":"P",
    "gn:feature_code":"PPL",
    "gn:name":"Jiaodaopo",
    "gn:population":0,
    "gn:timezone":"Asia/Shanghai",
    "iso:country":"CN",
    "name:zho_x_preferred":[
        "\u7ede\u9053\u5761"
    ],
    "wof:name":"Jiaodaopo",
    "wof:placetype":"locality"
},
  "geometry": {"coordinates":[108.85241000000001,27.09001],"type":"Point"}
}