{
  "type": "Feature",
  "properties": {
    "gn:admin1_code":"12.0",
    "gn:asciiname":"Baziyan",
    "gn:country_code":"CN",
    "gn:dem":967,
    "gn:feature_class":"P",
    "gn:feature_code":"PPL",
    "gn:name":"Baziyan",
    "gn:population":0,
    "gn:timezone":"Asia/Shanghai",
    "iso:country":"CN",
    "name:zho_x_preferred":[
        "\u516b\u5b57\u5ca9"
    ],
    "wof:name":"Baziyan",
    "wof:placetype":"locality"
},
  "geometry": {"coordinates":[110.24406999999999,30.54832],"type":"Point"}
}