{
  "type": "Feature",
  "properties": {
    "gn:admin1_code":"02",
    "gn:asciiname":"Xiasanzao",
    "gn:country_code":"CN",
    "gn:dem":6,
    "gn:feature_class":"P",
    "gn:feature_code":"PPL",
    "gn:name":"Xiasanzao",
    "gn:population":0,
    "gn:timezone":"Asia/Shanghai",
    "iso:country":"CN",
    "name:und_x_variant":[
        "\u4e0b\u4e09\u7076"
    ],
    "wof:name":"Xiasanzao",
    "wof:placetype":"locality"
},
  "geometry": {"coordinates":[121.32193999999998,30.28833],"type":"Point"}
}