{
  "type": "Feature",
  "properties": {
    "gn:admin1_code":"29.0",
    "gn:asciiname":"Geyading",
    "gn:country_code":"CN",
    "gn:dem":2575,
    "gn:feature_class":"P",
    "gn:feature_code":"PPL",
    "gn:name":"Geyading",
    "gn:population":0,
    "gn:timezone":"Asia/Shanghai",
    "iso:country":"CN",
    "name:zho_x_preferred":[
        "\u683c\u4e9a\u9876"
    ],
    "wof:name":"Geyading",
    "wof:placetype":"locality"
},
  "geometry": {"coordinates":[99.102,28.7721],"type":"Point"}
}