{
  "type": "Feature",
  "properties": {
    "gn:admin1_code":"30",
    "gn:asciiname":"Liuge",
    "gn:country_code":"CN",
    "gn:dem":25,
    "gn:feature_class":"P",
    "gn:feature_code":"PPL",
    "gn:name":"Liuge",
    "gn:population":0,
    "gn:timezone":"Asia/Urumqi",
    "iso:country":"CN",
    "name:zho_x_preferred":[
        "\u516d\u683c"
    ],
    "wof:name":"Liuge",
    "wof:placetype":"locality"
},
  "geometry": {"coordinates":[110.08857,21.49735],"type":"Point"}
}