{
  "type": "Feature",
  "properties": {
    "gn:admin1_code":"1.0",
    "gn:asciiname":"Yaochencun",
    "gn:country_code":"CN",
    "gn:dem":26,
    "gn:feature_class":"P",
    "gn:feature_code":"PPL",
    "gn:name":"Yaochencun",
    "gn:population":0,
    "gn:timezone":"Asia/Shanghai",
    "iso:country":"CN",
    "name:zho_x_preferred":[
        "\u59da\u9648\u6751"
    ],
    "wof:name":"Yaochencun",
    "wof:placetype":"locality"
},
  "geometry": {"coordinates":[118.02267999999999,32.94304],"type":"Point"}
}