{
  "type": "Feature",
  "properties": {
    "gn:admin1_code":"07",
    "gn:asciiname":"Maolin",
    "gn:country_code":"CN",
    "gn:dem":557,
    "gn:feature_class":"P",
    "gn:feature_code":"PPL",
    "gn:name":"Maolin",
    "gn:population":0,
    "gn:timezone":"Asia/Shanghai",
    "iso:country":"CN",
    "name:zho_x_preferred":[
        "\u8302\u6797"
    ],
    "wof:name":"Maolin",
    "wof:placetype":"locality"
},
  "geometry": {"coordinates":[118.02306000000002,25.48861],"type":"Point"}
}