{
  "type": "Feature",
  "properties": {
    "gn:admin1_code":"15.0",
    "gn:asciiname":"Chenjiazui",
    "gn:country_code":"CN",
    "gn:dem":2163,
    "gn:feature_class":"P",
    "gn:feature_code":"PPL",
    "gn:name":"Chenjiazui",
    "gn:population":0,
    "gn:timezone":"Asia/Shanghai",
    "iso:country":"CN",
    "name:und_x_variant":[
        "\u9648\u5bb6\u5480"
    ],
    "wof:name":"Chenjiazui",
    "wof:placetype":"locality"
},
  "geometry": {"coordinates":[104.52709,34.72336],"type":"Point"}
}