{
  "type": "Feature",
  "properties": {
    "gn:admin1_code":"29",
    "gn:asciiname":"Xiaba'ai",
    "gn:country_code":"CN",
    "gn:dem":1119,
    "gn:feature_class":"P",
    "gn:feature_code":"PPL",
    "gn:name":"Xiaba\u2019ai",
    "gn:population":0,
    "gn:timezone":"Asia/Shanghai",
    "iso:country":"CN",
    "name:und_x_variant":[
        "Xiaba\u2019ai"
    ],
    "name:zho_x_preferred":[
        "\u4e0b\u516b\u7231"
    ],
    "wof:name":"Xiaba'ai",
    "wof:placetype":"locality"
},
  "geometry": {"coordinates":[104.697,23.018],"type":"Point"}
}