{
  "type": "Feature",
  "properties": {
    "gn:admin1_code":"7",
    "gn:asciiname":"Xishan",
    "gn:country_code":"CN",
    "gn:dem":589,
    "gn:feature_class":"P",
    "gn:feature_code":"PPL",
    "gn:name":"Xishan",
    "gn:population":0,
    "gn:timezone":"Asia/Shanghai",
    "iso:country":"CN",
    "name:und_x_variant":[
        "\u897f\u5c71",
        "Xishan"
    ],
    "wof:name":"Xishan",
    "wof:placetype":"locality"
},
  "geometry": {"coordinates":[119.33834,27.39824],"type":"Point"}
}