{
  "type": "Feature",
  "properties": {
    "gn:admin1_code":"7",
    "gn:asciiname":"Xishan",
    "gn:country_code":"CN",
    "gn:dem":589,
    "gn:feature_class":"P",
    "gn:feature_code":"PPL",
    "gn:name":"Xishan",
    "gn:population":0,
    "gn:timezone":"Asia/Shanghai",
    "iso:country":"CN",
    "name:ceb_x_preferred":[
        "Xishan"
    ],
    "name:deu_x_preferred":[
        "Xishan"
    ],
    "name:fra_x_preferred":[
        "Xishan"
    ],
    "name:kor_x_preferred":[
        "\uc2dc\uc0b0\uad6c"
    ],
    "name:mlg_x_preferred":[
        "Xishan"
    ],
    "name:nor_x_preferred":[
        "Xishan"
    ],
    "name:rus_x_preferred":[
        "\u0421\u0438\u0448\u0430\u043d\u044c"
    ],
    "name:swe_x_preferred":[
        "Xishan"
    ],
    "name:und_x_variant":[
        "\u897f\u5c71"
    ],
    "wof:name":"Xishan",
    "wof:placetype":"locality"
},
  "geometry": {"coordinates":[119.33834,27.39824],"type":"Point"}
}