{
  "type": "Feature",
  "properties": {
    "gn:admin1_code":"29.0",
    "gn:asciiname":"Fulong",
    "gn:country_code":"CN",
    "gn:dem":2281,
    "gn:feature_class":"P",
    "gn:feature_code":"PPL",
    "gn:name":"Fulong",
    "gn:population":0,
    "gn:timezone":"Asia/Shanghai",
    "iso:country":"CN",
    "name:zho_x_preferred":[
        "\u4f0f\u9f99"
    ],
    "wof:name":"Fulong",
    "wof:placetype":"locality"
},
  "geometry": {"coordinates":[100.32899999999999,25.2986],"type":"Point"}
}