{
  "type": "Feature",
  "properties": {
    "gn:admin1_code":"5.0",
    "gn:asciiname":"Xiaoqing",
    "gn:country_code":"CN",
    "gn:dem":153,
    "gn:feature_class":"P",
    "gn:feature_code":"PPL",
    "gn:name":"Xiaoqing",
    "gn:population":0,
    "gn:timezone":"Asia/Shanghai",
    "iso:country":"CN",
    "name:zho_x_preferred":[
        "\u5c0f\u9752"
    ],
    "wof:name":"Xiaoqing",
    "wof:placetype":"locality"
},
  "geometry": {"coordinates":[123.75535000000001,44.47253],"type":"Point"}
}