{
  "type": "Feature",
  "properties": {
    "gn:admin1_code":"7",
    "gn:asciiname":"Liuxi",
    "gn:country_code":"CN",
    "gn:dem":345,
    "gn:feature_class":"P",
    "gn:feature_code":"PPL",
    "gn:name":"Liuxi",
    "gn:population":0,
    "gn:timezone":"Asia/Shanghai",
    "iso:country":"CN",
    "name:zho_x_preferred":[
        "\u67f3\u6eaa"
    ],
    "wof:name":"Liuxi",
    "wof:placetype":"locality"
},
  "geometry": {"coordinates":[118.65227,25.51626],"type":"Point"}
}