{
  "type": "Feature",
  "properties": {
    "gn:admin1_code":"5.0",
    "gn:asciiname":"Daguangningwa",
    "gn:country_code":"CN",
    "gn:dem":166,
    "gn:feature_class":"P",
    "gn:feature_code":"PPL",
    "gn:name":"Daguangningwa",
    "gn:population":0,
    "gn:timezone":"Asia/Shanghai",
    "iso:country":"CN",
    "name:zho_x_preferred":[
        "\u5927\u5e7f\u5b81\u6d3c"
    ],
    "wof:name":"Daguangningwa",
    "wof:placetype":"locality"
},
  "geometry": {"coordinates":[125.73887999999999,44.41877],"type":"Point"}
}