{
  "type": "Feature",
  "properties": {
    "gn:admin1_code":"18",
    "gn:asciiname":"Bandengpo",
    "gn:country_code":"CN",
    "gn:dem":1061,
    "gn:feature_class":"P",
    "gn:feature_code":"PPL",
    "gn:name":"Bandengpo",
    "gn:population":0,
    "gn:timezone":"Asia/Shanghai",
    "iso:country":"CN",
    "name:zho_x_preferred":[
        "\u677f\u51f3\u5761"
    ],
    "wof:name":"Bandengpo",
    "wof:placetype":"locality"
},
  "geometry": {"coordinates":[108.15000000000001,27.2595],"type":"Point"}
}