{
  "type": "Feature",
  "properties": {
    "gn:admin1_code":"9.0",
    "gn:asciiname":"Sike",
    "gn:country_code":"CN",
    "gn:dem":441,
    "gn:feature_class":"P",
    "gn:feature_code":"PPL",
    "gn:name":"Sike",
    "gn:population":0,
    "gn:timezone":"Asia/Shanghai",
    "iso:country":"CN",
    "name:und_x_variant":[
        "\u56db\u68f5",
        "Sike"
    ],
    "wof:name":"Sike",
    "wof:placetype":"locality"
},
  "geometry": {"coordinates":[112.18961000000002,33.26633],"type":"Point"}
}