{
  "type": "Feature",
  "properties": {
    "gn:admin1_code":"10.0",
    "gn:asciiname":"Donglangyue",
    "gn:country_code":"CN",
    "gn:dem":36,
    "gn:feature_class":"P",
    "gn:feature_code":"PPL",
    "gn:name":"Donglangyue",
    "gn:population":0,
    "gn:timezone":"Asia/Shanghai",
    "iso:country":"CN",
    "name:zho_x_preferred":[
        "\u4e1c\u90ce\u6708"
    ],
    "wof:name":"Donglangyue",
    "wof:placetype":"locality"
},
  "geometry": {"coordinates":[115.383,38.0329],"type":"Point"}
}