{
  "type": "Feature",
  "properties": {
    "gn:admin1_code":"04",
    "gn:asciiname":"Longdong Dadui",
    "gn:country_code":"CN",
    "gn:dem":0,
    "gn:feature_class":"P",
    "gn:feature_code":"PPLF",
    "gn:name":"Longdong Dadui",
    "gn:population":0,
    "gn:timezone":"Asia/Shanghai",
    "iso:country":"CN",
    "name:und_x_variant":[
        "\u9f99\u4e1c\u5927\u961f"
    ],
    "wof:name":"Longdong Dadui",
    "wof:placetype":"locality"
},
  "geometry": {"coordinates":[120.52916999999999,33.435],"type":"Point"}
}