{
  "type": "Feature",
  "properties": {
    "gn:admin1_code":"18",
    "gn:asciiname":"Zhangjiazhai",
    "gn:country_code":"CN",
    "gn:dem":1670,
    "gn:feature_class":"P",
    "gn:feature_code":"PPL",
    "gn:name":"Zhangjiazhai",
    "gn:population":0,
    "gn:timezone":"Asia/Shanghai",
    "iso:country":"CN",
    "name:zho_x_preferred":[
        "\u5f20\u5bb6\u5be8"
    ],
    "wof:name":"Zhangjiazhai",
    "wof:placetype":"locality"
},
  "geometry": {"coordinates":[105.08199999999999,26.6839],"type":"Point"}
}