{
  "type": "Feature",
  "properties": {
    "gn:admin1_code":"2.0",
    "gn:asciiname":"Houyang",
    "gn:country_code":"CN",
    "gn:dem":634,
    "gn:feature_class":"P",
    "gn:feature_code":"PPL",
    "gn:name":"Houyang",
    "gn:population":0,
    "gn:timezone":"Asia/Shanghai",
    "iso:country":"CN",
    "name:zho_x_preferred":[
        "\u540e\u6d0b"
    ],
    "wof:name":"Houyang",
    "wof:placetype":"locality"
},
  "geometry": {"coordinates":[118.77845000000001,28.59089],"type":"Point"}
}