{
  "type": "Feature",
  "properties": {
    "gn:admin1_code":"5.0",
    "gn:asciiname":"Laopianpo",
    "gn:country_code":"CN",
    "gn:dem":642,
    "gn:feature_class":"P",
    "gn:feature_code":"PPL",
    "gn:name":"Laopianpo",
    "gn:population":0,
    "gn:timezone":"Asia/Shanghai",
    "iso:country":"CN",
    "name:und_x_variant":[
        "\u8001\u504f\u5761"
    ],
    "wof:name":"Laopianpo",
    "wof:placetype":"locality"
},
  "geometry": {"coordinates":[128.31826999999998,42.61943],"type":"Point"}
}