{
  "type": "Feature",
  "properties": {
    "gn:admin1_code":"3.0",
    "gn:asciiname":"Shashanxia",
    "gn:country_code":"CN",
    "gn:dem":30,
    "gn:feature_class":"P",
    "gn:feature_code":"PPL",
    "gn:name":"Shashanxia",
    "gn:population":0,
    "gn:timezone":"Asia/Shanghai",
    "iso:country":"CN",
    "name:und_x_variant":[
        "\u6749\u5c71\u4e0b"
    ],
    "wof:name":"Shashanxia",
    "wof:placetype":"locality"
},
  "geometry": {"coordinates":[115.65940000000001,29.77544],"type":"Point"}
}