{
  "type": "Feature",
  "properties": {
    "gn:admin1_code":"16.0",
    "gn:asciiname":"Shuliangping",
    "gn:country_code":"CN",
    "gn:dem":171,
    "gn:feature_class":"P",
    "gn:feature_code":"PPL",
    "gn:name":"Shuliangping",
    "gn:population":0,
    "gn:timezone":"Asia/Shanghai",
    "iso:country":"CN",
    "name:zho_x_preferred":[
        "\u85af\u826f\u576a"
    ],
    "wof:name":"Shuliangping",
    "wof:placetype":"locality"
},
  "geometry": {"coordinates":[110.767,24.1467],"type":"Point"}
}