{
  "type": "Feature",
  "properties": {
    "gn:admin1_code":"7",
    "gn:asciiname":"Baiye",
    "gn:country_code":"CN",
    "gn:dem":331,
    "gn:feature_class":"P",
    "gn:feature_code":"PPL",
    "gn:name":"Baiye",
    "gn:population":0,
    "gn:timezone":"Asia/Shanghai",
    "iso:country":"CN",
    "name:und_x_variant":[
        "\u767d\u53f6"
    ],
    "name:zho_x_preferred":[
        "\u767d\u53f6"
    ],
    "wof:name":"Baiye",
    "wof:placetype":"locality"
},
  "geometry": {"coordinates":[117.09827,26.55009],"type":"Point"}
}