{
  "type": "Feature",
  "properties": {
    "gn:admin1_code":"8.0",
    "gn:asciiname":"Wanghada",
    "gn:country_code":"CN",
    "gn:dem":182,
    "gn:feature_class":"P",
    "gn:feature_code":"PPL",
    "gn:name":"Wanghada",
    "gn:population":0,
    "gn:timezone":"Asia/Shanghai",
    "iso:country":"CN",
    "name:zho_x_preferred":[
        "\u65fa\u54c8\u8fbe"
    ],
    "wof:name":"Wanghada",
    "wof:placetype":"locality"
},
  "geometry": {"coordinates":[126.44546,51.95565],"type":"Point"}
}