{
  "type": "Feature",
  "properties": {
    "gn:admin1_code":"1.0",
    "gn:asciiname":"Lishuangloucun",
    "gn:country_code":"CN",
    "gn:dem":40,
    "gn:feature_class":"P",
    "gn:feature_code":"PPL",
    "gn:name":"Lishuangloucun",
    "gn:population":0,
    "gn:timezone":"Asia/Shanghai",
    "iso:country":"CN",
    "name:zho_x_preferred":[
        "\u674e\u53cc\u697c\u6751"
    ],
    "wof:name":"Lishuangloucun",
    "wof:placetype":"locality"
},
  "geometry": {"coordinates":[115.84225000000001,33.86356],"type":"Point"}
}