{
  "type": "Feature",
  "properties": {
    "gn:admin1_code":"29",
    "gn:asciiname":"Yueliangdi",
    "gn:country_code":"CN",
    "gn:dem":1889,
    "gn:feature_class":"P",
    "gn:feature_code":"PPL",
    "gn:name":"Yueliangdi",
    "gn:population":0,
    "gn:timezone":"Asia/Shanghai",
    "iso:country":"CN",
    "name:zho_x_preferred":[
        "\u6708\u4eae\u5730"
    ],
    "wof:name":"Yueliangdi",
    "wof:placetype":"locality"
},
  "geometry": {"coordinates":[101.30500000000001,24.7648],"type":"Point"}
}