{
  "type": "Feature",
  "properties": {
    "gn:admin1_code":"30",
    "gn:asciiname":"Lishutang",
    "gn:country_code":"CN",
    "gn:dem":449,
    "gn:feature_class":"P",
    "gn:feature_code":"PPL",
    "gn:name":"Lishutang",
    "gn:population":0,
    "gn:timezone":"Asia/Shanghai",
    "iso:country":"CN",
    "name:zho_x_preferred":[
        "\u68a8\u6811\u5858"
    ],
    "wof:name":"Lishutang",
    "wof:placetype":"locality"
},
  "geometry": {"coordinates":[115.72553000000001,23.57779],"type":"Point"}
}