{
  "type": "Feature",
  "properties": {
    "gn:admin1_code":"26",
    "gn:asciiname":"Huangjiagui",
    "gn:country_code":"CN",
    "gn:dem":898,
    "gn:feature_class":"P",
    "gn:feature_code":"PPL",
    "gn:name":"Huangjiagui",
    "gn:population":0,
    "gn:timezone":"Asia/Shanghai",
    "iso:country":"CN",
    "name:zho_x_preferred":[
        "\u9ec4\u5bb6\u9b3c"
    ],
    "wof:name":"Huangjiagui",
    "wof:placetype":"locality"
},
  "geometry": {"coordinates":[108.03722,34.64111],"type":"Point"}
}