{
  "type": "Feature",
  "properties": {
    "gn:admin1_code":"2.0",
    "gn:asciiname":"Xiaxitan",
    "gn:country_code":"CN",
    "gn:dem":207,
    "gn:feature_class":"P",
    "gn:feature_code":"PPL",
    "gn:name":"Xiaxitan",
    "gn:population":0,
    "gn:timezone":"Asia/Shanghai",
    "iso:country":"CN",
    "name:zho_x_preferred":[
        "\u4e0b\u6eaa\u6ee9"
    ],
    "wof:name":"Xiaxitan",
    "wof:placetype":"locality"
},
  "geometry": {"coordinates":[119.21673,28.868],"type":"Point"}
}