{
  "type": "Feature",
  "properties": {
    "gn:admin1_code":"16.0",
    "gn:asciiname":"Nongyou",
    "gn:country_code":"CN",
    "gn:dem":476,
    "gn:feature_class":"P",
    "gn:feature_code":"PPL",
    "gn:name":"Nongyou",
    "gn:population":0,
    "gn:timezone":"Asia/Shanghai",
    "iso:country":"CN",
    "name:zho_x_preferred":[
        "\u5f04\u72b9"
    ],
    "wof:name":"Nongyou",
    "wof:placetype":"locality"
},
  "geometry": {"coordinates":[107.33799999999999,24.31],"type":"Point"}
}