{
  "type": "Feature",
  "properties": {
    "gn:admin1_code":"04",
    "gn:asciiname":"Qiaotoujie",
    "gn:country_code":"CN",
    "gn:dem":6,
    "gn:feature_class":"P",
    "gn:feature_code":"PPL",
    "gn:name":"Qiaotoujie",
    "gn:population":0,
    "gn:timezone":"Asia/Shanghai",
    "iso:country":"CN",
    "name:und_x_variant":[
        "\u6865\u5934\u8857"
    ],
    "wof:name":"Qiaotoujie",
    "wof:placetype":"locality"
},
  "geometry": {"coordinates":[120.51600999999999,31.96187],"type":"Point"}
}