{
  "type": "Feature",
  "properties": {
    "gn:admin1_code":"11.0",
    "gn:asciiname":"Xinpuya",
    "gn:country_code":"CN",
    "gn:dem":254,
    "gn:feature_class":"P",
    "gn:feature_code":"PPL",
    "gn:name":"Xinpuya",
    "gn:population":0,
    "gn:timezone":"Asia/Shanghai",
    "iso:country":"CN",
    "name:zho_x_preferred":[
        "Xinpuya"
    ],
    "name:zho_x_variant":[
        "\u65b0\u94fa\u57ad"
    ],
    "wof:name":"Xinpuya",
    "wof:placetype":"locality"
},
  "geometry": {"coordinates":[111.04031999999999,29.5309],"type":"Point"}
}