{
  "type": "Feature",
  "properties": {
    "gn:admin1_code":"2.0",
    "gn:asciiname":"Qinghe",
    "gn:country_code":"CN",
    "gn:dem":53,
    "gn:feature_class":"P",
    "gn:feature_code":"PPL",
    "gn:name":"Qinghe",
    "gn:population":0,
    "gn:timezone":"Asia/Shanghai",
    "iso:country":"CN",
    "name:ceb_x_preferred":[
        "Qinghe"
    ],
    "name:deu_x_preferred":[
        "Qinghe"
    ],
    "name:fra_x_preferred":[
        "Qinghe"
    ],
    "name:nor_x_preferred":[
        "Qinghe"
    ],
    "name:rus_x_preferred":[
        "\u0426\u0438\u043d\u0445\u044d"
    ],
    "name:swe_x_preferred":[
        "Qinghe"
    ],
    "name:und_x_variant":[
        "\u9752\u4f55"
    ],
    "wof:name":"Qinghe",
    "wof:placetype":"locality"
},
  "geometry": {"coordinates":[119.74007,30.06877],"type":"Point"}
}