{
  "type": "Feature",
  "properties": {
    "gn:admin1_code":"15.0",
    "gn:asciiname":"Daliugou",
    "gn:country_code":"CN",
    "gn:dem":2530,
    "gn:feature_class":"P",
    "gn:feature_code":"PPL",
    "gn:name":"Daliugou",
    "gn:population":0,
    "gn:timezone":"Asia/Shanghai",
    "iso:country":"CN",
    "name:zho_x_preferred":[
        "\u5927\u67f3\u6c9f"
    ],
    "wof:name":"Daliugou",
    "wof:placetype":"locality"
},
  "geometry": {"coordinates":[101.352,38.2851],"type":"Point"}
}