{
  "type": "Feature",
  "properties": {
    "gn:admin1_code":"12.0",
    "gn:asciiname":"Leshicai",
    "gn:country_code":"CN",
    "gn:dem":44,
    "gn:feature_class":"P",
    "gn:feature_code":"PPL",
    "gn:name":"Leshicai",
    "gn:population":0,
    "gn:timezone":"Asia/Shanghai",
    "iso:country":"CN",
    "name:zho_x_preferred":[
        "Leshicai"
    ],
    "name:zho_x_variant":[
        "\u4e50\u4e16\u624d"
    ],
    "wof:name":"Leshicai",
    "wof:placetype":"locality"
},
  "geometry": {"coordinates":[114.97011999999999,29.81132],"type":"Point"}
}