{
  "type": "Feature",
  "properties": {
    "gn:admin1_code":"14.0",
    "gn:asciiname":"Buke",
    "gn:country_code":"CN",
    "gn:dem":3672,
    "gn:feature_class":"P",
    "gn:feature_code":"PPL",
    "gn:name":"Buke",
    "gn:population":0,
    "gn:timezone":"Asia/Urumqi",
    "iso:country":"CN",
    "name:zho_x_preferred":[
        "\u5e03\u67ef"
    ],
    "wof:name":"Buke",
    "wof:placetype":"locality"
},
  "geometry": {"coordinates":[97.25438,31.19804],"type":"Point"}
}