{
  "type": "Feature",
  "properties": {
    "gn:admin1_code":"11.0",
    "gn:asciiname":"Chenjiawan",
    "gn:country_code":"CN",
    "gn:dem":990,
    "gn:feature_class":"P",
    "gn:feature_code":"PPL",
    "gn:name":"Chenjiawan",
    "gn:population":0,
    "gn:timezone":"Asia/Shanghai",
    "iso:country":"CN",
    "name:zho_x_preferred":[
        "\u9648\u5bb6\u6e7e"
    ],
    "wof:name":"Chenjiawan",
    "wof:placetype":"locality"
},
  "geometry": {"coordinates":[109.50442,29.26307000000001],"type":"Point"}
}