{
  "type": "Feature",
  "properties": {
    "gn:admin1_code":"3.0",
    "gn:asciiname":"Duannao",
    "gn:country_code":"CN",
    "gn:dem":193,
    "gn:feature_class":"P",
    "gn:feature_code":"PPL",
    "gn:name":"Duannao",
    "gn:population":0,
    "gn:timezone":"Asia/Shanghai",
    "iso:country":"CN",
    "name:und_x_variant":[
        "\u5845\u8111"
    ],
    "wof:name":"Duannao",
    "wof:placetype":"locality"
},
  "geometry": {"coordinates":[115.80676,25.85674],"type":"Point"}
}