{
  "type": "Feature",
  "properties": {
    "gn:admin1_code":"32.0",
    "gn:asciiname":"Tiekuang",
    "gn:country_code":"CN",
    "gn:dem":732,
    "gn:feature_class":"P",
    "gn:feature_code":"PPL",
    "gn:name":"Tiekuang",
    "gn:population":0,
    "gn:timezone":"Asia/Shanghai",
    "iso:country":"CN",
    "name:zho_x_preferred":[
        "\u94c1\u77ff"
    ],
    "wof:name":"Tiekuang",
    "wof:placetype":"locality"
},
  "geometry": {"coordinates":[108.03434,31.82106],"type":"Point"}
}