{
  "type": "Feature",
  "properties": {
    "gn:admin1_code":"18",
    "gn:asciiname":"Heixigou",
    "gn:country_code":"CN",
    "gn:dem":833,
    "gn:feature_class":"P",
    "gn:feature_code":"PPL",
    "gn:name":"Heixigou",
    "gn:population":0,
    "gn:timezone":"Asia/Shanghai",
    "iso:country":"CN",
    "name:zho_x_preferred":[
        "\u9ed1\u6eaa\u6c9f"
    ],
    "wof:name":"Heixigou",
    "wof:placetype":"locality"
},
  "geometry": {"coordinates":[107.717,28.2732],"type":"Point"}
}