{
  "type": "Feature",
  "properties": {
    "gn:admin1_code":"24.0",
    "gn:asciiname":"Zhouguanglu",
    "gn:country_code":"CN",
    "gn:dem":1325,
    "gn:feature_class":"P",
    "gn:feature_code":"PPL",
    "gn:name":"Zhouguanglu",
    "gn:population":0,
    "gn:timezone":"Asia/Shanghai",
    "iso:country":"CN",
    "name:zho_x_preferred":[
        "\u5468\u5149\u5f55"
    ],
    "wof:name":"Zhouguanglu",
    "wof:placetype":"locality"
},
  "geometry": {"coordinates":[112.41445,40.1813],"type":"Point"}
}