{
  "type": "Feature",
  "properties": {
    "gn:admin1_code":"11.0",
    "gn:asciiname":"Guanxia",
    "gn:country_code":"CN",
    "gn:dem":182,
    "gn:feature_class":"P",
    "gn:feature_code":"PPL",
    "gn:name":"Guanxia",
    "gn:population":0,
    "gn:timezone":"Asia/Shanghai",
    "iso:country":"CN",
    "name:zho_x_preferred":[
        "\u89c2\u4e0b"
    ],
    "wof:name":"Guanxia",
    "wof:placetype":"locality"
},
  "geometry": {"coordinates":[113.31189000000001,27.21082],"type":"Point"}
}