{
  "type": "Feature",
  "properties": {
    "gn:admin1_code":"16.0",
    "gn:asciiname":"Chenghe",
    "gn:country_code":"CN",
    "gn:dem":56,
    "gn:feature_class":"P",
    "gn:feature_code":"PPL",
    "gn:name":"Chenghe",
    "gn:population":0,
    "gn:timezone":"Asia/Shanghai",
    "iso:country":"CN",
    "name:zho_x_preferred":[
        "\u6210\u548c"
    ],
    "wof:name":"Chenghe",
    "wof:placetype":"locality"
},
  "geometry": {"coordinates":[110.124,23.6559],"type":"Point"}
}