{
  "type": "Feature",
  "properties": {
    "gn:admin1_code":"12.0",
    "gn:asciiname":"Zaoshuya",
    "gn:country_code":"CN",
    "gn:dem":269,
    "gn:feature_class":"P",
    "gn:feature_code":"PPL",
    "gn:name":"Zaoshuya",
    "gn:population":0,
    "gn:timezone":"Asia/Shanghai",
    "iso:country":"CN",
    "name:zho_x_preferred":[
        "\u67a3\u6811\u57ad"
    ],
    "wof:name":"Zaoshuya",
    "wof:placetype":"locality"
},
  "geometry": {"coordinates":[111.46159,32.62617],"type":"Point"}
}