{
  "type": "Feature",
  "properties": {
    "gn:admin1_code":"19.0",
    "gn:asciiname":"Dudalianpao",
    "gn:country_code":"CN",
    "gn:dem":8,
    "gn:feature_class":"P",
    "gn:feature_code":"PPL",
    "gn:name":"Dudalianpao",
    "gn:population":0,
    "gn:timezone":"Asia/Shanghai",
    "iso:country":"CN",
    "name:und_x_variant":[
        "\u675c\u8fbe\u8fde\u6ce1"
    ],
    "name:zho_x_preferred":[
        "\u675c\u8fbe\u8fde\u6ce1"
    ],
    "wof:name":"Dudalianpao",
    "wof:placetype":"locality"
},
  "geometry": {"coordinates":[122.40891000000001,41.31311],"type":"Point"}
}