{
  "type": "Feature",
  "properties": {
    "gn:admin1_code":"32.0",
    "gn:asciiname":"Mengjia",
    "gn:country_code":"CN",
    "gn:dem":486,
    "gn:feature_class":"P",
    "gn:feature_code":"PPL",
    "gn:name":"Mengjia",
    "gn:population":0,
    "gn:timezone":"Asia/Shanghai",
    "iso:country":"CN",
    "name:deu_x_preferred":[
        "Mengjia"
    ],
    "name:zho_x_preferred":[
        "\u5b5f\u5bb6"
    ],
    "wof:name":"Mengjia",
    "wof:placetype":"locality"
},
  "geometry": {"coordinates":[106.76300000000001,31.7922],"type":"Point"}
}