{
  "type": "Feature",
  "properties": {
    "gn:admin1_code":"26.0",
    "gn:asciiname":"Yandixia",
    "gn:country_code":"CN",
    "gn:dem":973,
    "gn:feature_class":"P",
    "gn:feature_code":"PPL",
    "gn:name":"Yandixia",
    "gn:population":0,
    "gn:timezone":"Asia/Shanghai",
    "iso:country":"CN",
    "name:und_x_variant":[
        "\u5ca9\u5e95\u4e0b"
    ],
    "wof:name":"Yandixia",
    "wof:placetype":"locality"
},
  "geometry": {"coordinates":[106.36769,32.84299],"type":"Point"}
}