{
  "type": "Feature",
  "properties": {
    "gn:admin1_code":"7",
    "gn:asciiname":"Baicheng",
    "gn:country_code":"CN",
    "gn:dem":146,
    "gn:feature_class":"P",
    "gn:feature_code":"PPL",
    "gn:name":"Baicheng",
    "gn:population":0,
    "gn:timezone":"Asia/Shanghai",
    "iso:country":"CN",
    "name:ara_x_preferred":[
        "\u0628\u0627\u064a\u062a\u0634\u0646\u063a"
    ],
    "name:bak_x_preferred":[
        "\u0411\u0430\u0439\u0447\u044d\u043d"
    ],
    "name:cdo_x_preferred":[
        "B\u0103h-si\u00e0ng"
    ],
    "name:ceb_x_preferred":[
        "Baicheng"
    ],
    "name:ces_x_preferred":[
        "Paj-\u010dcheng"
    ],
    "name:dan_x_preferred":[
        "Baicheng"
    ],
    "name:deu_x_preferred":[
        "Baicheng"
    ],
    "name:eus_x_preferred":[
        "Baicheng"
    ],
    "name:fas_x_preferred":[
        "\u0628\u0627\u06cc\u0686\u0646\u06af"
    ],
    "name:fin_x_preferred":[
        "Baicheng"
    ],
    "name:fra_x_preferred":[
        "Baicheng"
    ],
    "name:heb_x_preferred":[
        "\u05d1\u05d0\u05d9\u05e6'\u05e0\u05d2"
    ],
    "name:hun_x_preferred":[
        "Baicheng"
    ],
    "name:ind_x_preferred":[
        "Baicheng"
    ],
    "name:ita_x_preferred":[
        "Baicheng"
    ],
    "name:jpn_x_preferred":[
        "\u767d\u57ce\u5e02"
    ],
    "name:kik_x_preferred":[
        "Baicheng"
    ],
    "name:kor_x_preferred":[
        "\ubc14\uc774\uccad\uc2dc"
    ],
    "name:lit_x_preferred":[
        "Bai\u010dengas"
    ],
    "name:mlg_x_preferred":[
        "Baicheng"
    ],
    "name:nld_x_preferred":[
        "Baicheng"
    ],
    "name:nno_x_preferred":[
        "Baicheng"
    ],
    "name:nor_x_preferred":[
        "Baicheng"
    ],
    "name:pol_x_preferred":[
        "Baicheng"
    ],
    "name:por_x_preferred":[
        "Baicheng"
    ],
    "name:rus_x_preferred":[
        "\u0411\u0430\u0439\u0447\u044d\u043d"
    ],
    "name:spa_x_preferred":[
        "Baicheng"
    ],
    "name:srp_x_preferred":[
        "\u0411\u0430\u0458\u0447\u0435\u043d\u0433"
    ],
    "name:swe_x_preferred":[
        "Baicheng"
    ],
    "name:tur_x_preferred":[
        "Baicheng"
    ],
    "name:urd_x_preferred":[
        "\u0628\u0627\u0626\u0686\u06cc\u0646\u06af"
    ],
    "name:vie_x_preferred":[
        "B\u1ea1ch Th\u00e0nh"
    ],
    "name:war_x_preferred":[
        "Baicheng"
    ],
    "name:wuu_x_preferred":[
        "\u767d\u57ce\u5e02"
    ],
    "name:zho_x_preferred":[
        "\u767d\u5448"
    ],
    "name:zho_x_variant":[
        "\u767d\u57ce\u5e02"
    ],
    "wof:name":"Baicheng",
    "wof:placetype":"locality"
},
  "geometry": {"coordinates":[118.76642,25.29694],"type":"Point"}
}