{
  "type": "Feature",
  "properties": {
    "gn:admin1_code":"9",
    "gn:asciiname":"Xiaoxiying",
    "gn:country_code":"CN",
    "gn:dem":164,
    "gn:feature_class":"P",
    "gn:feature_code":"PPL",
    "gn:name":"Xiaoxiying",
    "gn:population":0,
    "gn:timezone":"Asia/Shanghai",
    "iso:country":"CN",
    "name:und_x_variant":[
        "\u5c0f\u897f\u8425",
        "Xiaoxiying"
    ],
    "wof:name":"Xiaoxiying",
    "wof:placetype":"locality"
},
  "geometry": {"coordinates":[112.27504999999999,33.00777],"type":"Point"}
}