{
  "type": "Feature",
  "properties": {
    "gn:admin1_code":"9",
    "gn:asciiname":"Wangfuma",
    "gn:country_code":"CN",
    "gn:dem":49,
    "gn:feature_class":"P",
    "gn:feature_code":"PPL",
    "gn:name":"Wangfuma",
    "gn:population":0,
    "gn:timezone":"Asia/Shanghai",
    "iso:country":"CN",
    "name:zho_x_preferred":[
        "\u738b\u9644\u9a6c"
    ],
    "wof:name":"Wangfuma",
    "wof:placetype":"locality"
},
  "geometry": {"coordinates":[115.616,34.2856],"type":"Point"}
}