{
  "type": "Feature",
  "properties": {
    "gn:admin1_code":"9",
    "gn:asciiname":"Anqiu",
    "gn:country_code":"CN",
    "gn:dem":58,
    "gn:feature_class":"P",
    "gn:feature_code":"PPL",
    "gn:name":"Anqiu",
    "gn:population":0,
    "gn:timezone":"Asia/Shanghai",
    "iso:country":"CN",
    "name:ara_x_preferred":[
        "\u0622\u0646\u0643\u0648\u064a"
    ],
    "name:bxr_x_preferred":[
        "\u0410\u043d\u044c\u0446\u044e"
    ],
    "name:ceb_x_preferred":[
        "Anqiu Shi"
    ],
    "name:deu_x_preferred":[
        "Anqiu"
    ],
    "name:fas_x_preferred":[
        "\u0622\u0646\u06a9\u06cc\u0648"
    ],
    "name:fra_x_preferred":[
        "Anqiu"
    ],
    "name:ita_x_preferred":[
        "Anqiu"
    ],
    "name:jpn_x_preferred":[
        "\u5b89\u4e18\u5e02"
    ],
    "name:kik_x_preferred":[
        "Anqiu"
    ],
    "name:kor_x_preferred":[
        "\uc548\ucd94\uc2dc"
    ],
    "name:mlg_x_preferred":[
        "Anqiu"
    ],
    "name:nld_x_preferred":[
        "Anqiu"
    ],
    "name:nor_x_preferred":[
        "Anqiu"
    ],
    "name:rus_x_preferred":[
        "\u0410\u043d\u044c\u0446\u044e"
    ],
    "name:swe_x_preferred":[
        "Anqiu"
    ],
    "name:vie_x_preferred":[
        "An Kh\u00e2u"
    ],
    "name:zho_x_preferred":[
        "\u5b89\u90b1"
    ],
    "name:zho_x_variant":[
        "\u5b89\u4e18\u5e02"
    ],
    "wof:name":"Anqiu",
    "wof:placetype":"locality"
},
  "geometry": {"coordinates":[115.01300000000001,35.4091],"type":"Point"}
}