{
  "type": "Feature",
  "properties": {
    "gn:admin1_code":"9",
    "gn:asciiname":"Anqiu",
    "gn:country_code":"CN",
    "gn:dem":58,
    "gn:feature_class":"P",
    "gn:feature_code":"PPL",
    "gn:name":"Anqiu",
    "gn:population":0,
    "gn:timezone":"Asia/Shanghai",
    "iso:country":"CN",
    "name:zho_x_preferred":[
        "\u5b89\u90b1"
    ],
    "wof:name":"Anqiu",
    "wof:placetype":"locality"
},
  "geometry": {"coordinates":[115.01300000000001,35.4091],"type":"Point"}
}