{
  "type": "Feature",
  "properties": {
    "gn:admin1_code":"5.0",
    "gn:asciiname":"Yangmugou",
    "gn:country_code":"CN",
    "gn:dem":283,
    "gn:feature_class":"P",
    "gn:feature_code":"PPL",
    "gn:name":"Yangmugou",
    "gn:population":0,
    "gn:timezone":"Asia/Shanghai",
    "iso:country":"CN",
    "name:zho_x_preferred":[
        "\u517b\u6728\u6c9f"
    ],
    "wof:name":"Yangmugou",
    "wof:placetype":"locality"
},
  "geometry": {"coordinates":[124.95519,42.94034],"type":"Point"}
}