{
  "type": "Feature",
  "properties": {
    "gn:admin1_code":"10.0",
    "gn:asciiname":"Doumen",
    "gn:country_code":"CN",
    "gn:dem":50,
    "gn:feature_class":"P",
    "gn:feature_code":"PPL",
    "gn:name":"Doumen",
    "gn:population":0,
    "gn:timezone":"Asia/Shanghai",
    "iso:country":"CN",
    "name:ceb_x_preferred":[
        "Doumen"
    ],
    "name:deu_x_preferred":[
        "Doumen"
    ],
    "name:zho_x_preferred":[
        "\u6597\u95e8"
    ],
    "wof:name":"Doumen",
    "wof:placetype":"locality"
},
  "geometry": {"coordinates":[115.03758000000001,36.31691],"type":"Point"}
}