{
  "type": "Feature",
  "properties": {
    "gn:admin1_code":"5.0",
    "gn:asciiname":"Shangjian",
    "gn:country_code":"CN",
    "gn:dem":387,
    "gn:feature_class":"P",
    "gn:feature_code":"PPL",
    "gn:name":"Shangjian",
    "gn:population":0,
    "gn:timezone":"Asia/Shanghai",
    "iso:country":"CN",
    "name:und_x_variant":[
        "\u4e0a\u78b1",
        "Shangjiancun",
        "\u4e0a\u78b1\u6751"
    ],
    "wof:name":"Shangjian",
    "wof:placetype":"locality"
},
  "geometry": {"coordinates":[130.33005,43.70429],"type":"Point"}
}