{
  "type": "Feature",
  "properties": {
    "gn:admin1_code":"10",
    "gn:asciiname":"Shaoguoying",
    "gn:country_code":"CN",
    "gn:dem":609,
    "gn:feature_class":"P",
    "gn:feature_code":"PPL",
    "gn:name":"Shaoguoying",
    "gn:population":0,
    "gn:timezone":"Asia/Shanghai",
    "iso:country":"CN",
    "name:zho_x_preferred":[
        "\u70e7\u9505\u8425"
    ],
    "wof:name":"Shaoguoying",
    "wof:placetype":"locality"
},
  "geometry": {"coordinates":[117.44338,40.92439],"type":"Point"}
}