{
  "type": "Feature",
  "properties": {
    "gn:admin1_code":"4.0",
    "gn:asciiname":"Linianlinchang Yifenchang",
    "gn:country_code":"CN",
    "gn:dem":82,
    "gn:feature_class":"P",
    "gn:feature_code":"PPLF",
    "gn:name":"Linianlinchang Yifenchang",
    "gn:population":0,
    "gn:timezone":"Asia/Shanghai",
    "iso:country":"CN",
    "name:und_x_variant":[
        "\u674e\u57dd\u6797\u573a\u4e00\u5206\u573a"
    ],
    "wof:name":"Linianlinchang Yifenchang",
    "wof:placetype":"locality"
},
  "geometry": {"coordinates":[118.63799,34.66728],"type":"Point"}
}