{
  "type": "Feature",
  "properties": {
    "gn:admin1_code":"10",
    "gn:asciiname":"Xinhuaying",
    "gn:country_code":"CN",
    "gn:dem":49,
    "gn:feature_class":"P",
    "gn:feature_code":"PPL",
    "gn:name":"Xinhuaying",
    "gn:population":0,
    "gn:timezone":"Asia/Shanghai",
    "iso:country":"CN",
    "name:zho_x_preferred":[
        "\u65b0\u534e\u8425"
    ],
    "wof:name":"Xinhuaying",
    "wof:placetype":"locality"
},
  "geometry": {"coordinates":[115.02316999999999,36.50322],"type":"Point"}
}