{
  "type": "Feature",
  "properties": {
    "gn:admin1_code":"16.0",
    "gn:asciiname":"Lizhi",
    "gn:country_code":"CN",
    "gn:dem":90,
    "gn:feature_class":"P",
    "gn:feature_code":"PPL",
    "gn:name":"Lizhi",
    "gn:population":0,
    "gn:timezone":"Asia/Shanghai",
    "iso:country":"CN",
    "name:zho_x_preferred":[
        "\u52b1\u5fd7"
    ],
    "wof:name":"Lizhi",
    "wof:placetype":"locality"
},
  "geometry": {"coordinates":[110.58799999999999,22.8425],"type":"Point"}
}