{
  "type": "Feature",
  "properties": {
    "gn:admin1_code":"32.0",
    "gn:asciiname":"Taiyigou",
    "gn:country_code":"CN",
    "gn:dem":418,
    "gn:feature_class":"P",
    "gn:feature_code":"PPL",
    "gn:name":"Taiyigou",
    "gn:population":0,
    "gn:timezone":"Asia/Shanghai",
    "iso:country":"CN",
    "name:zho_x_preferred":[
        "\u592a\u533b\u6c9f"
    ],
    "wof:name":"Taiyigou",
    "wof:placetype":"locality"
},
  "geometry": {"coordinates":[104.456,30.207],"type":"Point"}
}