{
  "type": "Feature",
  "properties": {
    "gn:admin1_code":"15.0",
    "gn:asciiname":"Si'ershan Yuanpan",
    "gn:country_code":"CN",
    "gn:dem":1252,
    "gn:feature_class":"P",
    "gn:feature_code":"PPL",
    "gn:name":"Si\u2019ershan Yuanpan",
    "gn:population":0,
    "gn:timezone":"Asia/Shanghai",
    "iso:country":"CN",
    "name:und_x_variant":[
        "Si\u2019ershan Yuanpan",
        "\u5bfa\u513f\u5c71\u586c\u7554"
    ],
    "wof:name":"Si'ershan Yuanpan",
    "wof:placetype":"locality"
},
  "geometry": {"coordinates":[107.90437,36.08991],"type":"Point"}
}