{
  "type": "Feature",
  "properties": {
    "gn:admin1_code":"30",
    "gn:asciiname":"Maoqifeng",
    "gn:country_code":"CN",
    "gn:dem":457,
    "gn:feature_class":"P",
    "gn:feature_code":"PPL",
    "gn:name":"Maoqifeng",
    "gn:population":0,
    "gn:timezone":"Asia/Shanghai",
    "iso:country":"CN",
    "name:zho_x_preferred":[
        "\u8305\u78dc\u5cf0"
    ],
    "wof:name":"Maoqifeng",
    "wof:placetype":"locality"
},
  "geometry": {"coordinates":[116.3201,24.81929],"type":"Point"}
}