{
  "type": "Feature",
  "properties": {
    "gn:admin1_code":"30.0",
    "gn:asciiname":"Yingshancun",
    "gn:country_code":"CN",
    "gn:dem":46,
    "gn:feature_class":"P",
    "gn:feature_code":"PPL",
    "gn:name":"Yingshancun",
    "gn:population":0,
    "gn:timezone":"Asia/Shanghai",
    "iso:country":"CN",
    "name:zho_x_preferred":[
        "\u82f1\u5c71\u6751"
    ],
    "wof:name":"Yingshancun",
    "wof:placetype":"locality"
},
  "geometry": {"coordinates":[116.72818999999998,23.68174],"type":"Point"}
}