{
  "type": "Feature",
  "properties": {
    "gn:admin1_code":"18.0",
    "gn:asciiname":"Long'erping",
    "gn:country_code":"CN",
    "gn:dem":637,
    "gn:feature_class":"P",
    "gn:feature_code":"PPL",
    "gn:name":"Long\u2019erping",
    "gn:population":0,
    "gn:timezone":"Asia/Shanghai",
    "iso:country":"CN",
    "name:und_x_variant":[
        "Long\u2019erping"
    ],
    "name:zho_x_preferred":[
        "\u9f99\u4e8c\u576a"
    ],
    "wof:name":"Long'erping",
    "wof:placetype":"locality"
},
  "geometry": {"coordinates":[109.218,27.8991],"type":"Point"}
}