{
  "type": "Feature",
  "properties": {
    "gn:admin1_code":"10",
    "gn:asciiname":"Beijingmeng",
    "gn:country_code":"CN",
    "gn:dem":28,
    "gn:feature_class":"P",
    "gn:feature_code":"PPL",
    "gn:name":"Beijingmeng",
    "gn:population":0,
    "gn:timezone":"Asia/Shanghai",
    "iso:country":"CN",
    "name:zho_x_preferred":[
        "\u5317\u666f\u840c"
    ],
    "wof:name":"Beijingmeng",
    "wof:placetype":"locality"
},
  "geometry": {"coordinates":[115.583,37.9557],"type":"Point"}
}