{
  "type": "Feature",
  "properties": {
    "gn:admin1_code":"7.0",
    "gn:asciiname":"Daoshi",
    "gn:country_code":"CN",
    "gn:dem":337,
    "gn:feature_class":"P",
    "gn:feature_code":"PPL",
    "gn:name":"Daoshi",
    "gn:population":0,
    "gn:timezone":"Asia/Shanghai",
    "iso:country":"CN",
    "name:zho_x_preferred":[
        "\u5c9b\u77f3"
    ],
    "wof:name":"Daoshi",
    "wof:placetype":"locality"
},
  "geometry": {"coordinates":[117.15963000000001,27.50346],"type":"Point"}
}