{
  "type": "Feature",
  "properties": {
    "gn:admin1_code":"19.0",
    "gn:asciiname":"Zhanggangzi",
    "gn:country_code":"CN",
    "gn:dem":24,
    "gn:feature_class":"P",
    "gn:feature_code":"PPL",
    "gn:name":"Zhanggangzi",
    "gn:population":0,
    "gn:timezone":"Asia/Shanghai",
    "iso:country":"CN",
    "name:und_x_variant":[
        "\u5f20\u5c97\u5b50"
    ],
    "name:zho_x_preferred":[
        "\u5f20\u5c97\u5b50"
    ],
    "wof:name":"Zhanggangzi",
    "wof:placetype":"locality"
},
  "geometry": {"coordinates":[122.29931999999999,41.78649],"type":"Point"}
}