{
  "type": "Feature",
  "properties": {
    "gn:admin1_code":"1.0",
    "gn:asciiname":"Gaohuangcun",
    "gn:country_code":"CN",
    "gn:dem":15,
    "gn:feature_class":"P",
    "gn:feature_code":"PPL",
    "gn:name":"Gaohuangcun",
    "gn:population":0,
    "gn:timezone":"Asia/Shanghai",
    "iso:country":"CN",
    "name:zho_x_preferred":[
        "\u9ad8\u9ec4\u6751"
    ],
    "wof:name":"Gaohuangcun",
    "wof:placetype":"locality"
},
  "geometry": {"coordinates":[117.26939,30.68874000000001],"type":"Point"}
}