{
  "type": "Feature",
  "properties": {
    "gn:admin1_code":"25.0",
    "gn:asciiname":"Dayulincun",
    "gn:country_code":"CN",
    "gn:dem":52,
    "gn:feature_class":"P",
    "gn:feature_code":"PPL",
    "gn:name":"Dayulincun",
    "gn:population":0,
    "gn:timezone":"Asia/Shanghai",
    "iso:country":"CN",
    "name:zho_x_preferred":[
        "\u5927\u6986\u6797\u6751"
    ],
    "wof:name":"Dayulincun",
    "wof:placetype":"locality"
},
  "geometry": {"coordinates":[119.41092,35.69161],"type":"Point"}
}