{
  "type": "Feature",
  "properties": {
    "gn:admin1_code":"7",
    "gn:asciiname":"Huziling",
    "gn:country_code":"CN",
    "gn:dem":266,
    "gn:feature_class":"P",
    "gn:feature_code":"PPL",
    "gn:name":"Huziling",
    "gn:population":0,
    "gn:timezone":"Asia/Shanghai",
    "iso:country":"CN",
    "name:zho_x_preferred":[
        "\u6e56\u5b50\u5cad"
    ],
    "wof:name":"Huziling",
    "wof:placetype":"locality"
},
  "geometry": {"coordinates":[117.09121,24.10173],"type":"Point"}
}