{
  "type": "Feature",
  "properties": {
    "gn:admin1_code":"25.0",
    "gn:asciiname":"Zhujidiancun",
    "gn:country_code":"CN",
    "gn:dem":37,
    "gn:feature_class":"P",
    "gn:feature_code":"PPL",
    "gn:name":"Zhujidiancun",
    "gn:population":0,
    "gn:timezone":"Asia/Shanghai",
    "iso:country":"CN",
    "name:zho_x_preferred":[
        "\u73e0\u7391\u5e97\u6751"
    ],
    "wof:name":"Zhujidiancun",
    "wof:placetype":"locality"
},
  "geometry": {"coordinates":[122.25967,37.0935],"type":"Point"}
}