{
  "type": "Feature",
  "properties": {
    "gn:admin1_code":"18",
    "gn:asciiname":"Yinhe",
    "gn:country_code":"CN",
    "gn:dem":1351,
    "gn:feature_class":"P",
    "gn:feature_code":"PPL",
    "gn:name":"Yinhe",
    "gn:population":0,
    "gn:timezone":"Asia/Shanghai",
    "iso:country":"CN",
    "name:zho_x_preferred":[
        "\u9634\u6cb3"
    ],
    "wof:name":"Yinhe",
    "wof:placetype":"locality"
},
  "geometry": {"coordinates":[105.14400000000001,25.1878],"type":"Point"}
}