{
  "type": "Feature",
  "properties": {
    "gn:admin1_code":"16",
    "gn:asciiname":"Dong'an",
    "gn:country_code":"CN",
    "gn:dem":128,
    "gn:feature_class":"P",
    "gn:feature_code":"PPL",
    "gn:name":"Dong\u2019an",
    "gn:population":0,
    "gn:timezone":"Asia/Shanghai",
    "iso:country":"CN",
    "name:und_x_variant":[
        "Tung-an-hsiang",
        "Dong\u2019an"
    ],
    "wof:name":"Dong'an",
    "wof:placetype":"locality"
},
  "geometry": {"coordinates":[107.20332999999999,22.11611],"type":"Point"}
}