{
  "type": "Feature",
  "properties": {
    "gn:admin1_code":"29.0",
    "gn:asciiname":"Laosutian",
    "gn:country_code":"CN",
    "gn:dem":1804,
    "gn:feature_class":"P",
    "gn:feature_code":"PPL",
    "gn:name":"Laosutian",
    "gn:population":0,
    "gn:timezone":"Asia/Shanghai",
    "iso:country":"CN",
    "name:zho_x_preferred":[
        "\u8001\u82cf\u7530"
    ],
    "wof:name":"Laosutian",
    "wof:placetype":"locality"
},
  "geometry": {"coordinates":[101.075,25.8964],"type":"Point"}
}