{
  "type": "Feature",
  "properties": {
    "gn:admin1_code":"11.0",
    "gn:asciiname":"Diyaoshan",
    "gn:country_code":"CN",
    "gn:dem":563,
    "gn:feature_class":"P",
    "gn:feature_code":"PPL",
    "gn:name":"Diyaoshan",
    "gn:population":0,
    "gn:timezone":"Asia/Shanghai",
    "iso:country":"CN",
    "name:zho_x_preferred":[
        "\u5730\u836f\u5c71"
    ],
    "wof:name":"Diyaoshan",
    "wof:placetype":"locality"
},
  "geometry": {"coordinates":[109.73165,26.37013],"type":"Point"}
}