{
  "type": "Feature",
  "properties": {
    "gn:admin1_code":"19.0",
    "gn:asciiname":"Qijiatun",
    "gn:country_code":"CN",
    "gn:dem":80,
    "gn:feature_class":"P",
    "gn:feature_code":"PPL",
    "gn:name":"Qijiatun",
    "gn:population":0,
    "gn:timezone":"Asia/Shanghai",
    "iso:country":"CN",
    "name:zho_x_preferred":[
        "\u9f50\u5bb6\u5c6f"
    ],
    "wof:name":"Qijiatun",
    "wof:placetype":"locality"
},
  "geometry": {"coordinates":[123.54053,42.66759],"type":"Point"}
}