{
  "type": "Feature",
  "properties": {
    "gn:admin1_code":"19.0",
    "gn:asciiname":"Guangfucun",
    "gn:country_code":"CN",
    "gn:dem":1,
    "gn:feature_class":"P",
    "gn:feature_code":"PPL",
    "gn:name":"Guangfucun",
    "gn:population":0,
    "gn:timezone":"Asia/Shanghai",
    "iso:country":"CN",
    "name:zho_x_preferred":[
        "\u5149\u590d\u6751"
    ],
    "wof:name":"Guangfucun",
    "wof:placetype":"locality"
},
  "geometry": {"coordinates":[124.05240999999999,39.85017],"type":"Point"}
}