{
  "type": "Feature",
  "properties": {
    "gn:admin1_code":"13",
    "gn:asciiname":"Shihuiyao",
    "gn:country_code":"CN",
    "gn:dem":1385,
    "gn:feature_class":"P",
    "gn:feature_code":"PPL",
    "gn:name":"Shihuiyao",
    "gn:population":0,
    "gn:timezone":"Asia/Urumqi",
    "iso:country":"CN",
    "name:und_x_variant":[
        "\u77f3\u7070\u7a91"
    ],
    "wof:name":"Shihuiyao",
    "wof:placetype":"locality"
},
  "geometry": {"coordinates":[86.2561,42.50012],"type":"Point"}
}