{
  "type": "Feature",
  "properties": {
    "gn:admin1_code":"3.0",
    "gn:asciiname":"Zhengcun",
    "gn:country_code":"CN",
    "gn:dem":109,
    "gn:feature_class":"P",
    "gn:feature_code":"PPLA4",
    "gn:name":"Zhengcun",
    "gn:population":0,
    "gn:timezone":"Asia/Shanghai",
    "iso:country":"CN",
    "name:und_x_variant":[
        "Cheng-ts\u2019un",
        "Zhengcun",
        "\u5f81\u6751",
        "Zhengcun Xiang",
        "\u5f81\u6751\u4e61"
    ],
    "wof:name":"Zhengcun",
    "wof:placetype":"locality"
},
  "geometry": {"coordinates":[114.52934,28.95454],"type":"Point"}
}