{
  "type": "Feature",
  "properties": {
    "gn:admin1_code":"30",
    "gn:asciiname":"Meitang",
    "gn:country_code":"CN",
    "gn:dem":18,
    "gn:feature_class":"P",
    "gn:feature_code":"PPLA4",
    "gn:name":"Meitang",
    "gn:population":0,
    "gn:timezone":"Asia/Shanghai",
    "iso:country":"CN",
    "name:und_x_variant":[
        "Meitang Zhen",
        "\u6885\u5858\u9547"
    ],
    "name:zho_x_preferred":[
        "\u6885\u5858"
    ],
    "wof:name":"Meitang",
    "wof:placetype":"locality"
},
  "geometry": {"coordinates":[116.08314,23.34747],"type":"Point"}
}