{
  "type": "Feature",
  "properties": {
    "gn:admin1_code":"7.0",
    "gn:asciiname":"Yangmeikeng",
    "gn:country_code":"CN",
    "gn:dem":373,
    "gn:feature_class":"P",
    "gn:feature_code":"PPL",
    "gn:name":"Yangmeikeng",
    "gn:population":0,
    "gn:timezone":"Asia/Shanghai",
    "iso:country":"CN",
    "name:und_x_variant":[
        "\u6768\u6885\u5751"
    ],
    "name:zho_x_preferred":[
        "\u6768\u6885\u5751"
    ],
    "wof:name":"Yangmeikeng",
    "wof:placetype":"locality"
},
  "geometry": {"coordinates":[117.15488000000001,26.8467],"type":"Point"}
}