{
  "type": "Feature",
  "properties": {
    "gn:admin1_code":"3.0",
    "gn:asciiname":"Xingshan",
    "gn:country_code":"CN",
    "gn:dem":103,
    "gn:feature_class":"P",
    "gn:feature_code":"PPL",
    "gn:name":"Xingshan",
    "gn:population":0,
    "gn:timezone":"Asia/Shanghai",
    "iso:country":"CN",
    "name:und_x_variant":[
        "\u884c\u5c71"
    ],
    "wof:name":"Xingshan",
    "wof:placetype":"locality"
},
  "geometry": {"coordinates":[114.72648999999998,27.67056],"type":"Point"}
}