{
  "type": "Feature",
  "properties": {
    "gn:admin1_code":"2.0",
    "gn:asciiname":"Huangwuling",
    "gn:country_code":"CN",
    "gn:dem":129,
    "gn:feature_class":"P",
    "gn:feature_code":"PPL",
    "gn:name":"Huangwuling",
    "gn:population":0,
    "gn:timezone":"Asia/Shanghai",
    "iso:country":"CN",
    "name:zho_x_preferred":[
        "\u9ec4\u575e\u5cad"
    ],
    "wof:name":"Huangwuling",
    "wof:placetype":"locality"
},
  "geometry": {"coordinates":[118.5654,29.01323],"type":"Point"}
}