{
  "type": "Feature",
  "properties": {
    "gn:admin1_code":"19.0",
    "gn:asciiname":"Yanghugoucun",
    "gn:country_code":"CN",
    "gn:dem":514,
    "gn:feature_class":"P",
    "gn:feature_code":"PPL",
    "gn:name":"Yanghugoucun",
    "gn:population":0,
    "gn:timezone":"Asia/Shanghai",
    "iso:country":"CN",
    "name:zho_x_preferred":[
        "\u6d0b\u6e56\u6c9f\u6751"
    ],
    "wof:name":"Yanghugoucun",
    "wof:placetype":"locality"
},
  "geometry": {"coordinates":[124.66057000000001,41.2041],"type":"Point"}
}