{
  "type": "Feature",
  "properties": {
    "gn:admin1_code":"29.0",
    "gn:asciiname":"Laofuzhai",
    "gn:country_code":"CN",
    "gn:dem":1132,
    "gn:feature_class":"P",
    "gn:feature_code":"PPL",
    "gn:name":"Laofuzhai",
    "gn:population":0,
    "gn:timezone":"Asia/Shanghai",
    "iso:country":"CN",
    "name:zho_x_preferred":[
        "\u8001\u5bcc\u5be8"
    ],
    "wof:name":"Laofuzhai",
    "wof:placetype":"locality"
},
  "geometry": {"coordinates":[101.881,22.6266],"type":"Point"}
}