{
  "type": "Feature",
  "properties": {
    "gn:admin1_code":"7",
    "gn:asciiname":"Denglong",
    "gn:country_code":"CN",
    "gn:dem":390,
    "gn:feature_class":"P",
    "gn:feature_code":"PPL",
    "gn:name":"Denglong",
    "gn:population":0,
    "gn:timezone":"Asia/Shanghai",
    "iso:country":"CN",
    "name:jpn_x_preferred":[
        "\u30b3\u30a6"
    ],
    "name:kor_x_preferred":[
        "\uc870\ucc9c\ud6c4"
    ],
    "name:und_x_variant":[
        "\u706f\u7b3c"
    ],
    "wof:name":"Denglong",
    "wof:placetype":"locality"
},
  "geometry": {"coordinates":[118.72638999999999,27.26667],"type":"Point"}
}