{
  "type": "Feature",
  "properties": {
    "gn:admin1_code":"8.0",
    "gn:asciiname":"Huadongcun",
    "gn:country_code":"CN",
    "gn:dem":70,
    "gn:feature_class":"P",
    "gn:feature_code":"PPL",
    "gn:name":"Huadongcun",
    "gn:population":0,
    "gn:timezone":"Asia/Shanghai",
    "iso:country":"CN",
    "name:zho_x_preferred":[
        "\u6866\u4e1c\u6751"
    ],
    "wof:name":"Huadongcun",
    "wof:placetype":"locality"
},
  "geometry": {"coordinates":[133.00261,45.737],"type":"Point"}
}