{
  "type": "Feature",
  "properties": {
    "gn:admin1_code":"02",
    "gn:asciiname":"Dahengcun",
    "gn:country_code":"CN",
    "gn:dem":65,
    "gn:feature_class":"P",
    "gn:feature_code":"PPL",
    "gn:name":"Dahengcun",
    "gn:population":0,
    "gn:timezone":"Asia/Shanghai",
    "iso:country":"CN",
    "name:und_x_variant":[
        "Ta-k\u2019eng-ts\u2019un",
        "Daheng",
        "Dahengcun"
    ],
    "name:zho_x_preferred":[
        "\u5927\u4ea8"
    ],
    "name:zho_x_variant":[
        "\u5927\u4ea8\u6751"
    ],
    "wof:name":"Dahengcun",
    "wof:placetype":"locality"
},
  "geometry": {"coordinates":[120.64704,28.19197],"type":"Point"}
}