{
  "type": "Feature",
  "properties": {
    "gn:admin1_code":"8.0",
    "gn:asciiname":"Zhanshengcun",
    "gn:country_code":"CN",
    "gn:dem":514,
    "gn:feature_class":"P",
    "gn:feature_code":"PPL",
    "gn:name":"Zhanshengcun",
    "gn:population":0,
    "gn:timezone":"Asia/Shanghai",
    "iso:country":"CN",
    "name:zho_x_preferred":[
        "\u6218\u80dc\u6751"
    ],
    "wof:name":"Zhanshengcun",
    "wof:placetype":"locality"
},
  "geometry": {"coordinates":[130.62267,44.71932],"type":"Point"}
}