{
  "type": "Feature",
  "properties": {
    "gn:admin1_code":"8.0",
    "gn:asciiname":"Qiangong Nongchang",
    "gn:country_code":"CN",
    "gn:dem":270,
    "gn:feature_class":"P",
    "gn:feature_code":"PPLF",
    "gn:name":"Qiangong Nongchang",
    "gn:population":0,
    "gn:timezone":"Asia/Shanghai",
    "iso:country":"CN",
    "name:zho_x_preferred":[
        "\u524d\u5de5\u519c\u573a"
    ],
    "wof:name":"Qiangong Nongchang",
    "wof:placetype":"locality"
},
  "geometry": {"coordinates":[129.57012,49.04651],"type":"Point"}
}