{
  "type": "Feature",
  "properties": {
    "gn:admin1_code":"1.0",
    "gn:asciiname":"Hulizhangcun",
    "gn:country_code":"CN",
    "gn:dem":25,
    "gn:feature_class":"P",
    "gn:feature_code":"PPL",
    "gn:name":"Hulizhangcun",
    "gn:population":0,
    "gn:timezone":"Asia/Shanghai",
    "iso:country":"CN",
    "name:zho_x_preferred":[
        "\u6e56\u91cc\u5f20\u6751"
    ],
    "wof:name":"Hulizhangcun",
    "wof:placetype":"locality"
},
  "geometry": {"coordinates":[117.23987,32.58597],"type":"Point"}
}