{
  "type": "Feature",
  "properties": {
    "gn:admin1_code":"15.0",
    "gn:asciiname":"Zhangjia Zuizui",
    "gn:country_code":"CN",
    "gn:dem":2224,
    "gn:feature_class":"P",
    "gn:feature_code":"PPL",
    "gn:name":"Zhangjia Zuizui",
    "gn:population":0,
    "gn:timezone":"Asia/Shanghai",
    "iso:country":"CN",
    "name:zho_x_preferred":[
        "\u5f20\u5bb6\u5634\u5634"
    ],
    "wof:name":"Zhangjia Zuizui",
    "wof:placetype":"locality"
},
  "geometry": {"coordinates":[103.88500000000001,35.2914],"type":"Point"}
}