{
  "type": "Feature",
  "properties": {
    "gn:admin1_code":"14",
    "gn:asciiname":"Zhaba",
    "gn:country_code":"CN",
    "gn:dem":4580,
    "gn:feature_class":"P",
    "gn:feature_code":"PPL",
    "gn:name":"Zhaba",
    "gn:population":0,
    "gn:timezone":"Asia/Urumqi",
    "iso:country":"CN",
    "name:zho_x_preferred":[
        "\u624e\u5df4"
    ],
    "wof:name":"Zhaba",
    "wof:placetype":"locality"
},
  "geometry": {"coordinates":[89.80070000000001,29.1866],"type":"Point"}
}