{
  "type": "Feature",
  "properties": {
    "gn:admin1_code":"25",
    "gn:asciiname":"Woshiling",
    "gn:country_code":"CN",
    "gn:dem":207,
    "gn:feature_class":"P",
    "gn:feature_code":"PPL",
    "gn:name":"Woshiling",
    "gn:population":0,
    "gn:timezone":"Asia/Shanghai",
    "iso:country":"CN",
    "name:zho_x_preferred":[
        "\u5367\u77f3\u5cad"
    ],
    "wof:name":"Woshiling",
    "wof:placetype":"locality"
},
  "geometry": {"coordinates":[118.848,35.2827],"type":"Point"}
}