{
  "type": "Feature",
  "properties": {
    "gn:admin1_code":"19.0",
    "gn:asciiname":"Jiangjiatun",
    "gn:country_code":"CN",
    "gn:dem":139,
    "gn:feature_class":"P",
    "gn:feature_code":"PPL",
    "gn:name":"Jiangjiatun",
    "gn:population":0,
    "gn:timezone":"Asia/Shanghai",
    "iso:country":"CN",
    "name:und_x_variant":[
        "Jiangtun",
        "Jiangjiatun",
        "\u848b\u5bb6\u5c6f"
    ],
    "name:zho_x_preferred":[
        "\u848b\u5c6f"
    ],
    "wof:name":"Jiangjiatun",
    "wof:placetype":"locality"
},
  "geometry": {"coordinates":[122.62237,40.00651],"type":"Point"}
}