{
  "type": "Feature",
  "properties": {
    "gn:admin1_code":"4.0",
    "gn:asciiname":"Touchangcun",
    "gn:country_code":"CN",
    "gn:dem":-2,
    "gn:feature_class":"P",
    "gn:feature_code":"PPL",
    "gn:name":"Touchangcun",
    "gn:population":0,
    "gn:timezone":"Asia/Shanghai",
    "iso:country":"CN",
    "name:zho_x_preferred":[
        "\u5934\u5382\u6751"
    ],
    "wof:name":"Touchangcun",
    "wof:placetype":"locality"
},
  "geometry": {"coordinates":[120.30969,34.04272],"type":"Point"}
}