{
  "type": "Feature",
  "properties": {
    "gn:admin1_code":"14.0",
    "gn:asciiname":"Bunuseri",
    "gn:country_code":"CN",
    "gn:dem":4445,
    "gn:feature_class":"P",
    "gn:feature_code":"PPL",
    "gn:name":"Bunuseri",
    "gn:population":0,
    "gn:timezone":"Asia/Urumqi",
    "iso:country":"CN",
    "name:zho_x_preferred":[
        "\u5e03\u52aa\u8272\u65e5"
    ],
    "wof:name":"Bunuseri",
    "wof:placetype":"locality"
},
  "geometry": {"coordinates":[94.04737,31.21927],"type":"Point"}
}