{
  "type": "Feature",
  "properties": {
    "gn:admin1_code":"29.0",
    "gn:asciiname":"Pinggoutang",
    "gn:country_code":"CN",
    "gn:dem":2223,
    "gn:feature_class":"P",
    "gn:feature_code":"PPL",
    "gn:name":"Pinggoutang",
    "gn:population":0,
    "gn:timezone":"Asia/Shanghai",
    "iso:country":"CN",
    "name:zho_x_preferred":[
        "\u5e73\u6c9f\u5858"
    ],
    "wof:name":"Pinggoutang",
    "wof:placetype":"locality"
},
  "geometry": {"coordinates":[99.97880000000001,24.7001],"type":"Point"}
}