{
  "type": "Feature",
  "properties": {
    "gn:admin1_code":"10",
    "gn:asciiname":"Lanyang",
    "gn:country_code":"CN",
    "gn:dem":87,
    "gn:feature_class":"P",
    "gn:feature_code":"PPL",
    "gn:name":"Lanyang",
    "gn:population":0,
    "gn:timezone":"Asia/Shanghai",
    "iso:country":"CN",
    "name:zho_x_preferred":[
        "\u5170\u7f8a"
    ],
    "wof:name":"Lanyang",
    "wof:placetype":"locality"
},
  "geometry": {"coordinates":[114.485,37.1633],"type":"Point"}
}