{
  "type": "Feature",
  "properties": {
    "gn:admin1_code":"14",
    "gn:asciiname":"Buede",
    "gn:country_code":"CN",
    "gn:dem":3614,
    "gn:feature_class":"P",
    "gn:feature_code":"PPL",
    "gn:name":"B\u00fcd\u00ea",
    "gn:population":0,
    "gn:timezone":"Asia/Urumqi",
    "iso:country":"CN",
    "name:bod_x_preferred":[
        "\u0f60\u0f56\u0f74\u0f51\u0f0b\u0f56\u0f51\u0f7a"
    ],
    "wof:name":"Buede",
    "wof:placetype":"locality"
},
  "geometry": {"coordinates":[90.95564,29.48373],"type":"Point"}
}