{
  "type": "Feature",
  "properties": {
    "gn:admin1_code":"2.0",
    "gn:asciiname":"Jidai",
    "gn:country_code":"CN",
    "gn:dem":38,
    "gn:feature_class":"P",
    "gn:feature_code":"PPL",
    "gn:name":"Jidai",
    "gn:population":0,
    "gn:timezone":"Asia/Shanghai",
    "iso:country":"CN",
    "name:jpn_x_preferred":[
        "\u6642\u4ee3"
    ],
    "name:kor_x_preferred":[
        "\uc9c0\ub2e4\uc774"
    ],
    "name:spa_x_preferred":[
        "Jidai"
    ],
    "name:zho_x_preferred":[
        "\u5b63\u5cb1"
    ],
    "wof:name":"Jidai",
    "wof:placetype":"locality"
},
  "geometry": {"coordinates":[121.6386,29.34257],"type":"Point"}
}