{
  "type": "Feature",
  "properties": {
    "gn:admin1_code":"18",
    "gn:asciiname":"Jiaobu",
    "gn:country_code":"CN",
    "gn:dem":1079,
    "gn:feature_class":"P",
    "gn:feature_code":"PPL",
    "gn:name":"Jiaobu",
    "gn:population":0,
    "gn:timezone":"Asia/Shanghai",
    "iso:country":"CN",
    "name:zho_x_preferred":[
        "\u7ede\u535c"
    ],
    "wof:name":"Jiaobu",
    "wof:placetype":"locality"
},
  "geometry": {"coordinates":[106.102,25.5421],"type":"Point"}
}