{
  "type": "Feature",
  "properties": {
    "gn:admin1_code":"1.0",
    "gn:asciiname":"Zhonglingjiao",
    "gn:country_code":"CN",
    "gn:dem":334,
    "gn:feature_class":"P",
    "gn:feature_code":"PPL",
    "gn:name":"Zhonglingjiao",
    "gn:population":0,
    "gn:timezone":"Asia/Shanghai",
    "iso:country":"CN",
    "name:zho_x_preferred":[
        "\u4e2d\u5cad\u811a"
    ],
    "wof:name":"Zhonglingjiao",
    "wof:placetype":"locality"
},
  "geometry": {"coordinates":[118.76258,30.01647],"type":"Point"}
}