{
  "type": "Feature",
  "properties": {
    "gn:admin1_code":"30",
    "gn:asciiname":"Shilangxu",
    "gn:country_code":"CN",
    "gn:dem":20,
    "gn:feature_class":"P",
    "gn:feature_code":"PPL",
    "gn:name":"Shilangxu",
    "gn:population":0,
    "gn:timezone":"Asia/Urumqi",
    "iso:country":"CN",
    "name:zho_x_preferred":[
        "\u77f3\u6d6a\u5729"
    ],
    "wof:name":"Shilangxu",
    "wof:placetype":"locality"
},
  "geometry": {"coordinates":[110.92685,21.6202],"type":"Point"}
}