{
  "type": "Feature",
  "properties": {
    "gn:admin1_code":"15.0",
    "gn:asciiname":"Xiacha",
    "gn:country_code":"CN",
    "gn:dem":1699,
    "gn:feature_class":"P",
    "gn:feature_code":"PPL",
    "gn:name":"Xiacha",
    "gn:population":0,
    "gn:timezone":"Asia/Shanghai",
    "iso:country":"CN",
    "name:und_x_variant":[
        "\u4e0b\u5c94"
    ],
    "wof:name":"Xiacha",
    "wof:placetype":"locality"
},
  "geometry": {"coordinates":[105.99827999999999,35.28962999999999],"type":"Point"}
}