{
  "type": "Feature",
  "properties": {
    "gn:admin1_code":"12",
    "gn:asciiname":"Qunli",
    "gn:country_code":"CN",
    "gn:dem":648,
    "gn:feature_class":"P",
    "gn:feature_code":"PPL",
    "gn:name":"Qunli",
    "gn:population":0,
    "gn:timezone":"Asia/Shanghai",
    "iso:country":"CN",
    "wof:name":"Qunli",
    "wof:placetype":"locality"
},
  "geometry": {"coordinates":[110.76667,30.83333],"type":"Point"}
}