{
  "type": "Feature",
  "properties": {
    "gn:admin1_code":"10",
    "gn:asciiname":"Guantao",
    "gn:cc2":"CN",
    "gn:country_code":"CN",
    "gn:dem":625,
    "gn:feature_class":"P",
    "gn:feature_code":"PPL",
    "gn:name":"Guantao",
    "gn:population":0,
    "gn:timezone":"Asia/Shanghai",
    "iso:country":"CN",
    "name:und_x_variant":[
        "Kuan-t\u2019ao",
        "Ying-t\u2019ao",
        "Guantao"
    ],
    "wof:name":"Guantao",
    "wof:placetype":"locality"
},
  "geometry": {"coordinates":[113.84361,36.81639000000001],"type":"Point"}
}