{
  "type": "Feature",
  "properties": {
    "gn:admin1_code":"33.0",
    "gn:asciiname":"Jianshanmiao",
    "gn:country_code":"CN",
    "gn:dem":296,
    "gn:feature_class":"P",
    "gn:feature_code":"PPL",
    "gn:name":"Jianshanmiao",
    "gn:population":0,
    "gn:timezone":"Asia/Shanghai",
    "iso:country":"CN",
    "name:zho_x_preferred":[
        "\u5c16\u5c71\u5e99"
    ],
    "wof:name":"Jianshanmiao",
    "wof:placetype":"locality"
},
  "geometry": {"coordinates":[106.56638,29.64005],"type":"Point"}
}