{
  "type": "Feature",
  "properties": {
    "gn:admin1_code":"19.0",
    "gn:asciiname":"Xinjiatuncun",
    "gn:country_code":"CN",
    "gn:dem":51,
    "gn:feature_class":"P",
    "gn:feature_code":"PPL",
    "gn:name":"Xinjiatuncun",
    "gn:population":0,
    "gn:timezone":"Asia/Shanghai",
    "iso:country":"CN",
    "name:zho_x_preferred":[
        "\u4fe1\u5bb6\u5c6f\u6751"
    ],
    "wof:name":"Xinjiatuncun",
    "wof:placetype":"locality"
},
  "geometry": {"coordinates":[120.84871,40.83977],"type":"Point"}
}