{
  "type": "Feature",
  "properties": {
    "gn:admin1_code":"12.0",
    "gn:asciiname":"Shepanxi",
    "gn:country_code":"CN",
    "gn:dem":686,
    "gn:feature_class":"P",
    "gn:feature_code":"PPL",
    "gn:name":"Shepanxi",
    "gn:population":0,
    "gn:timezone":"Asia/Shanghai",
    "iso:country":"CN",
    "name:zho_x_preferred":[
        "\u86c7\u76d8\u6eaa"
    ],
    "wof:name":"Shepanxi",
    "wof:placetype":"locality"
},
  "geometry": {"coordinates":[108.71272,29.71515],"type":"Point"}
}