{
  "type": "Feature",
  "properties": {
    "gn:admin1_code":"32",
    "gn:asciiname":"Jijia",
    "gn:country_code":"CN",
    "gn:dem":383,
    "gn:feature_class":"P",
    "gn:feature_code":"PPL",
    "gn:name":"Jijia",
    "gn:population":0,
    "gn:timezone":"Asia/Shanghai",
    "iso:country":"CN",
    "name:und_x_variant":[
        "Chi-chia-miao",
        "Jijiamiao",
        "Jijia"
    ],
    "name:zho_x_preferred":[
        "\u7eaa\u5bb6"
    ],
    "wof:name":"Jijia",
    "wof:placetype":"locality"
},
  "geometry": {"coordinates":[104.10420999999999,29.30735],"type":"Point"}
}