{
  "type": "Feature",
  "properties": {
    "gn:admin1_code":"7.0",
    "gn:asciiname":"Chaliao",
    "gn:country_code":"CN",
    "gn:dem":716,
    "gn:feature_class":"P",
    "gn:feature_code":"PPL",
    "gn:name":"Chaliao",
    "gn:population":0,
    "gn:timezone":"Asia/Shanghai",
    "iso:country":"CN",
    "name:zho_x_preferred":[
        "\u8336\u5bee"
    ],
    "wof:name":"Chaliao",
    "wof:placetype":"locality"
},
  "geometry": {"coordinates":[116.98086000000001,25.15787000000001],"type":"Point"}
}