{
  "type": "Feature",
  "properties": {
    "gn:admin1_code":"30.0",
    "gn:asciiname":"Dajiancun",
    "gn:country_code":"CN",
    "gn:dem":68,
    "gn:feature_class":"P",
    "gn:feature_code":"PPL",
    "gn:name":"Dajiancun",
    "gn:population":0,
    "gn:timezone":"Asia/Shanghai",
    "iso:country":"CN",
    "name:zho_x_preferred":[
        "\u5927\u6da7\u6751"
    ],
    "wof:name":"Dajiancun",
    "wof:placetype":"locality"
},
  "geometry": {"coordinates":[116.42270000000001,24.52358],"type":"Point"}
}