{
  "type": "Feature",
  "properties": {
    "gn:admin1_code":"24.0",
    "gn:asciiname":"Lidianpucun",
    "gn:country_code":"CN",
    "gn:dem":356,
    "gn:feature_class":"P",
    "gn:feature_code":"PPL",
    "gn:name":"Lidianpucun",
    "gn:population":0,
    "gn:timezone":"Asia/Shanghai",
    "iso:country":"CN",
    "name:zho_x_preferred":[
        "\u674e\u5e97\u94fa\u6751"
    ],
    "wof:name":"Lidianpucun",
    "wof:placetype":"locality"
},
  "geometry": {"coordinates":[110.95602,34.99466],"type":"Point"}
}