{
  "type": "Feature",
  "properties": {
    "gn:admin1_code":"4.0",
    "gn:asciiname":"Chaoyang Yizu",
    "gn:country_code":"CN",
    "gn:dem":-2,
    "gn:feature_class":"P",
    "gn:feature_code":"PPLF",
    "gn:name":"Chaoyang Yizu",
    "gn:population":0,
    "gn:timezone":"Asia/Shanghai",
    "iso:country":"CN",
    "name:zho_x_preferred":[
        "\u671d\u9633\u4e00\u7ec4"
    ],
    "wof:name":"Chaoyang Yizu",
    "wof:placetype":"locality"
},
  "geometry": {"coordinates":[120.11799999999999,33.933],"type":"Point"}
}