{
  "type": "Feature",
  "properties": {
    "gn:admin1_code":"31",
    "gn:asciiname":"Limushan Caifachang",
    "gn:country_code":"CN",
    "gn:dem":635,
    "gn:feature_class":"P",
    "gn:feature_code":"PPLF",
    "gn:name":"Limushan Caifachang",
    "gn:population":0,
    "gn:timezone":"Asia/Shanghai",
    "iso:country":"CN",
    "name:und_x_variant":[
        "Limushan Linchang",
        "\u9ece\u6bcd\u5c71\u6797\u573a",
        "Limushan Caifachang",
        "\u9ece\u6bcd\u5c71\u91c7\u4f10\u573a"
    ],
    "wof:name":"Limushan Caifachang",
    "wof:placetype":"locality"
},
  "geometry": {"coordinates":[109.74368,19.17566],"type":"Point"}
}