{
  "type": "Feature",
  "properties": {
    "gn:admin1_code":"33.0",
    "gn:asciiname":"Xiahanjiagou",
    "gn:country_code":"CN",
    "gn:dem":315,
    "gn:feature_class":"P",
    "gn:feature_code":"PPL",
    "gn:name":"Xiahanjiagou",
    "gn:population":0,
    "gn:timezone":"Asia/Shanghai",
    "iso:country":"CN",
    "name:zho_x_preferred":[
        "\u4e0b\u97e9\u5bb6\u6c9f"
    ],
    "wof:name":"Xiahanjiagou",
    "wof:placetype":"locality"
},
  "geometry": {"coordinates":[107.96284,30.27692],"type":"Point"}
}