{
  "type": "Feature",
  "properties": {
    "gn:admin1_code":"7.0",
    "gn:asciiname":"Huyang",
    "gn:country_code":"CN",
    "gn:dem":300,
    "gn:feature_class":"P",
    "gn:feature_code":"PPL",
    "gn:name":"Huyang",
    "gn:population":0,
    "gn:timezone":"Asia/Shanghai",
    "iso:country":"CN",
    "name:zho_x_preferred":[
        "\u864e\u6d0b"
    ],
    "wof:name":"Huyang",
    "wof:placetype":"locality"
},
  "geometry": {"coordinates":[118.87963999999999,27.6631],"type":"Point"}
}