{
  "type": "Feature",
  "properties": {
    "gn:admin1_code":"11",
    "gn:asciiname":"Chaxi",
    "gn:country_code":"CN",
    "gn:dem":473,
    "gn:feature_class":"P",
    "gn:feature_code":"PPL",
    "gn:name":"Chaxi",
    "gn:population":0,
    "gn:timezone":"Asia/Shanghai",
    "iso:country":"CN",
    "name:zho_x_preferred":[
        "\u69ce\u6eaa\u9547"
    ],
    "wof:name":"Chaxi",
    "wof:placetype":"locality"
},
  "geometry": {"coordinates":[111.58111,27.96139],"type":"Point"}
}