{
  "type": "Feature",
  "properties": {
    "gn:admin1_code":"8.0",
    "gn:asciiname":"Loushangcun",
    "gn:country_code":"CN",
    "gn:dem":137,
    "gn:feature_class":"P",
    "gn:feature_code":"PPL",
    "gn:name":"Loushangcun",
    "gn:population":0,
    "gn:timezone":"Asia/Shanghai",
    "iso:country":"CN",
    "name:zho_x_preferred":[
        "\u697c\u4e0a\u6751"
    ],
    "wof:name":"Loushangcun",
    "wof:placetype":"locality"
},
  "geometry": {"coordinates":[125.73860999999999,45.33555],"type":"Point"}
}