{
  "type": "Feature",
  "properties": {
    "gn:admin1_code":"16.0",
    "gn:asciiname":"Kendu",
    "gn:country_code":"CN",
    "gn:dem":664,
    "gn:feature_class":"P",
    "gn:feature_code":"PPL",
    "gn:name":"Kendu",
    "gn:population":0,
    "gn:timezone":"Asia/Shanghai",
    "iso:country":"CN",
    "name:zho_x_preferred":[
        "\u80af\u8bfb"
    ],
    "wof:name":"Kendu",
    "wof:placetype":"locality"
},
  "geometry": {"coordinates":[108.496,25.402],"type":"Point"}
}