{
  "type": "Feature",
  "properties": {
    "gn:admin1_code":"8.0",
    "gn:asciiname":"Changshuihe Nongchang Yifenchang",
    "gn:country_code":"CN",
    "gn:dem":341,
    "gn:feature_class":"P",
    "gn:feature_code":"PPLF",
    "gn:name":"Changshuihe Nongchang Yifenchang",
    "gn:population":0,
    "gn:timezone":"Asia/Shanghai",
    "iso:country":"CN",
    "name:zho_x_preferred":[
        "\u957f\u6c34\u6cb3\u519c\u573a\u4e00\u5206\u573a"
    ],
    "wof:name":"Changshuihe Nongchang Yifenchang",
    "wof:placetype":"locality"
},
  "geometry": {"coordinates":[126.92364999999999,48.3961],"type":"Point"}
}