{
  "type": "Feature",
  "properties": {
    "gn:admin1_code":"32.0",
    "gn:asciiname":"Fengminggang",
    "gn:country_code":"CN",
    "gn:dem":572,
    "gn:feature_class":"P",
    "gn:feature_code":"PPL",
    "gn:name":"Fengminggang",
    "gn:population":0,
    "gn:timezone":"Asia/Shanghai",
    "iso:country":"CN",
    "name:zho_x_preferred":[
        "\u51e4\u9e23\u5c97"
    ],
    "wof:name":"Fengminggang",
    "wof:placetype":"locality"
},
  "geometry": {"coordinates":[105.2722,28.17235],"type":"Point"}
}