{
  "type": "Feature",
  "properties": {
    "gn:admin1_code":"14.0",
    "gn:asciiname":"Da'ngaigai",
    "gn:country_code":"CN",
    "gn:dem":4763,
    "gn:feature_class":"P",
    "gn:feature_code":"PPL",
    "gn:name":"Da\u2019ngaigai",
    "gn:population":0,
    "gn:timezone":"Asia/Urumqi",
    "iso:country":"CN",
    "name:bod_x_preferred":[
        "Da\u2019ngaigai"
    ],
    "name:zho_x_preferred":[
        "Da\u2019aige"
    ],
    "name:zho_x_variant":[
        "\u6253\u7231\u683c"
    ],
    "wof:name":"Da'ngaigai",
    "wof:placetype":"locality"
},
  "geometry": {"coordinates":[97.202,32.102],"type":"Point"}
}