{
  "type": "Feature",
  "properties": {
    "gn:admin1_code":"05",
    "gn:asciiname":"Gangouzi",
    "gn:cc2":"CN",
    "gn:country_code":"CN",
    "gn:dem":640,
    "gn:feature_class":"P",
    "gn:feature_code":"PPL",
    "gn:name":"Gangouzi",
    "gn:population":0,
    "gn:timezone":"Asia/Shanghai",
    "iso:country":"CN",
    "name:und_x_variant":[
        "Tung-kan-kou-tzu",
        "Gangouzi",
        "\u5e72\u6c9f\u5b50"
    ],
    "wof:name":"Gangouzi",
    "wof:placetype":"locality"
},
  "geometry": {"coordinates":[127.96167,41.445],"type":"Point"}
}