{
  "type": "Feature",
  "properties": {
    "gn:admin1_code":"29.0",
    "gn:asciiname":"Daganchong",
    "gn:country_code":"CN",
    "gn:dem":1192,
    "gn:feature_class":"P",
    "gn:feature_code":"PPL",
    "gn:name":"Daganchong",
    "gn:population":0,
    "gn:timezone":"Asia/Shanghai",
    "iso:country":"CN",
    "name:zho_x_preferred":[
        "\u5927\u5e72\u51b2"
    ],
    "wof:name":"Daganchong",
    "wof:placetype":"locality"
},
  "geometry": {"coordinates":[103.051,26.6559],"type":"Point"}
}