{
  "type": "Feature",
  "properties": {
    "gn:admin1_code":"5.0",
    "gn:asciiname":"Houdi Wopeng",
    "gn:country_code":"CN",
    "gn:dem":141,
    "gn:feature_class":"P",
    "gn:feature_code":"PPL",
    "gn:name":"Houdi Wopeng",
    "gn:population":0,
    "gn:timezone":"Asia/Shanghai",
    "iso:country":"CN",
    "name:zho_x_preferred":[
        "\u540e\u5730\u7a9d\u68da"
    ],
    "wof:name":"Houdi Wopeng",
    "wof:placetype":"locality"
},
  "geometry": {"coordinates":[123.95331000000002,45.70888],"type":"Point"}
}