{
  "type": "Feature",
  "properties": {
    "gn:admin1_code":"1.0",
    "gn:asciiname":"Xianlincun",
    "gn:country_code":"CN",
    "gn:dem":159,
    "gn:feature_class":"P",
    "gn:feature_code":"PPL",
    "gn:name":"Xianlincun",
    "gn:population":0,
    "gn:timezone":"Asia/Shanghai",
    "iso:country":"CN",
    "name:zho_x_preferred":[
        "\u4ed9\u6797\u6751"
    ],
    "wof:name":"Xianlincun",
    "wof:placetype":"locality"
},
  "geometry": {"coordinates":[118.28412,29.75549],"type":"Point"}
}