{
  "type": "Feature",
  "properties": {
    "gn:admin1_code":"32.0",
    "gn:asciiname":"Wanbaishan",
    "gn:country_code":"CN",
    "gn:dem":416,
    "gn:feature_class":"P",
    "gn:feature_code":"PPL",
    "gn:name":"Wanbaishan",
    "gn:population":0,
    "gn:timezone":"Asia/Shanghai",
    "iso:country":"CN",
    "name:zho_x_preferred":[
        "\u4e07\u67cf\u5c71"
    ],
    "wof:name":"Wanbaishan",
    "wof:placetype":"locality"
},
  "geometry": {"coordinates":[105.28654,30.7771],"type":"Point"}
}