{
  "type": "Feature",
  "properties": {
    "gn:admin1_code":"32.0",
    "gn:asciiname":"Shangshilong",
    "gn:country_code":"CN",
    "gn:dem":1872,
    "gn:feature_class":"P",
    "gn:feature_code":"PPL",
    "gn:name":"Shangshilong",
    "gn:population":0,
    "gn:timezone":"Asia/Shanghai",
    "iso:country":"CN",
    "name:zho_x_preferred":[
        "\u4e0a\u77f3\u9f99"
    ],
    "wof:name":"Shangshilong",
    "wof:placetype":"locality"
},
  "geometry": {"coordinates":[101.97799999999999,26.1887],"type":"Point"}
}