{
  "type": "Feature",
  "properties": {
    "gn:admin1_code":"29",
    "gn:asciiname":"Pangxiedi",
    "gn:country_code":"CN",
    "gn:dem":1906,
    "gn:feature_class":"P",
    "gn:feature_code":"PPL",
    "gn:name":"Pangxiedi",
    "gn:population":0,
    "gn:timezone":"Asia/Shanghai",
    "iso:country":"CN",
    "name:zho_x_preferred":[
        "\u8783\u87f9\u5730"
    ],
    "wof:name":"Pangxiedi",
    "wof:placetype":"locality"
},
  "geometry": {"coordinates":[101.599,24.616],"type":"Point"}
}