{
  "type": "Feature",
  "properties": {
    "gn:admin1_code":"11.0",
    "gn:asciiname":"Xialaoposhan",
    "gn:country_code":"CN",
    "gn:dem":169,
    "gn:feature_class":"P",
    "gn:feature_code":"PPL",
    "gn:name":"Xialaoposhan",
    "gn:population":0,
    "gn:timezone":"Asia/Shanghai",
    "iso:country":"CN",
    "name:zho_x_preferred":[
        "\u4e0b\u8001\u5a46\u5c71"
    ],
    "wof:name":"Xialaoposhan",
    "wof:placetype":"locality"
},
  "geometry": {"coordinates":[110.07247,27.81237],"type":"Point"}
}