{
  "type": "Feature",
  "properties": {
    "gn:admin1_code":"3.0",
    "gn:asciiname":"Zheyuan",
    "gn:country_code":"CN",
    "gn:dem":151,
    "gn:feature_class":"P",
    "gn:feature_code":"PPL",
    "gn:name":"Zheyuan",
    "gn:population":0,
    "gn:timezone":"Asia/Shanghai",
    "iso:country":"CN",
    "name:und_x_variant":[
        "\u67d8\u6e90"
    ],
    "wof:name":"Zheyuan",
    "wof:placetype":"locality"
},
  "geometry": {"coordinates":[116.69721,27.12009],"type":"Point"}
}