{
  "type": "Feature",
  "properties": {
    "gn:admin1_code":"25",
    "gn:asciiname":"Xichahe Yicun",
    "gn:country_code":"CN",
    "gn:dem":5,
    "gn:feature_class":"P",
    "gn:feature_code":"PPL",
    "gn:name":"Xichahe Yicun",
    "gn:population":0,
    "gn:timezone":"Asia/Shanghai",
    "iso:country":"CN",
    "name:zho_x_preferred":[
        "\u897f\u5c94\u6cb3\u4e00\u6751"
    ],
    "wof:name":"Xichahe Yicun",
    "wof:placetype":"locality"
},
  "geometry": {"coordinates":[118.97808999999999,37.0257],"type":"Point"}
}