{
  "type": "Feature",
  "properties": {
    "gn:admin1_code":"4.0",
    "gn:asciiname":"Dingdaying",
    "gn:country_code":"CN",
    "gn:dem":39,
    "gn:feature_class":"P",
    "gn:feature_code":"PPL",
    "gn:name":"Dingdaying",
    "gn:population":0,
    "gn:timezone":"Asia/Shanghai",
    "iso:country":"CN",
    "name:zho_x_preferred":[
        "\u4e01\u5927\u8425"
    ],
    "wof:name":"Dingdaying",
    "wof:placetype":"locality"
},
  "geometry": {"coordinates":[118.55152,32.87644],"type":"Point"}
}