{
  "type": "Feature",
  "properties": {
    "gn:admin1_code":"11.0",
    "gn:asciiname":"Caigouyan",
    "gn:country_code":"CN",
    "gn:dem":527,
    "gn:feature_class":"P",
    "gn:feature_code":"PPL",
    "gn:name":"Caigouyan",
    "gn:population":0,
    "gn:timezone":"Asia/Shanghai",
    "iso:country":"CN",
    "name:zho_x_preferred":[
        "\u8d22\u72d7\u5ca9"
    ],
    "wof:name":"Caigouyan",
    "wof:placetype":"locality"
},
  "geometry": {"coordinates":[110.87894,26.62953],"type":"Point"}
}