{
  "type": "Feature",
  "properties": {
    "gn:admin1_code":"25",
    "gn:asciiname":"Yangjiachengzi",
    "gn:country_code":"CN",
    "gn:dem":202,
    "gn:feature_class":"P",
    "gn:feature_code":"PPL",
    "gn:name":"Yangjiachengzi",
    "gn:population":0,
    "gn:timezone":"Asia/Shanghai",
    "iso:country":"CN",
    "name:zho_x_preferred":[
        "\u6768\u5bb6\u57ce\u5b50"
    ],
    "wof:name":"Yangjiachengzi",
    "wof:placetype":"locality"
},
  "geometry": {"coordinates":[118.746,36.0513],"type":"Point"}
}