{
  "type": "Feature",
  "properties": {
    "gn:admin1_code":"29.0",
    "gn:asciiname":"Xiaojunsai",
    "gn:country_code":"CN",
    "gn:dem":580,
    "gn:feature_class":"P",
    "gn:feature_code":"PPL",
    "gn:name":"Xiaojunsai",
    "gn:population":0,
    "gn:timezone":"Asia/Shanghai",
    "iso:country":"CN",
    "name:zho_x_preferred":[
        "\u5c0f\u519b\u8d5b"
    ],
    "wof:name":"Xiaojunsai",
    "wof:placetype":"locality"
},
  "geometry": {"coordinates":[99.2757,23.6808],"type":"Point"}
}