{
  "type": "Feature",
  "properties": {
    "gn:admin1_code":"7",
    "gn:asciiname":"Humeiping",
    "gn:country_code":"CN",
    "gn:dem":224,
    "gn:feature_class":"P",
    "gn:feature_code":"PPL",
    "gn:name":"Humeiping",
    "gn:population":0,
    "gn:timezone":"Asia/Shanghai",
    "iso:country":"CN",
    "name:zho_x_preferred":[
        "\u864e\u6885\u576a"
    ],
    "wof:name":"Humeiping",
    "wof:placetype":"locality"
},
  "geometry": {"coordinates":[118.09475,24.81014],"type":"Point"}
}