{
  "type": "Feature",
  "properties": {
    "gn:admin1_code":"29.0",
    "gn:asciiname":"Taoshuqing",
    "gn:country_code":"CN",
    "gn:dem":2379,
    "gn:feature_class":"P",
    "gn:feature_code":"PPL",
    "gn:name":"Taoshuqing",
    "gn:population":0,
    "gn:timezone":"Asia/Shanghai",
    "iso:country":"CN",
    "name:zho_x_preferred":[
        "\u6843\u6811\u7b90"
    ],
    "wof:name":"Taoshuqing",
    "wof:placetype":"locality"
},
  "geometry": {"coordinates":[102.11,25.6598],"type":"Point"}
}