{
  "type": "Feature",
  "properties": {
    "gn:admin1_code":"15.0",
    "gn:asciiname":"Fengjiashan",
    "gn:country_code":"CN",
    "gn:dem":1235,
    "gn:feature_class":"P",
    "gn:feature_code":"PPL",
    "gn:name":"Fengjiashan",
    "gn:population":0,
    "gn:timezone":"Asia/Shanghai",
    "iso:country":"CN",
    "name:zho_x_preferred":[
        "\u51af\u5bb6\u5c71"
    ],
    "wof:name":"Fengjiashan",
    "wof:placetype":"locality"
},
  "geometry": {"coordinates":[107.672,35.0551],"type":"Point"}
}