{
  "type": "Feature",
  "properties": {
    "gn:admin1_code":"24.0",
    "gn:asciiname":"Beitangcheng",
    "gn:country_code":"CN",
    "gn:dem":544,
    "gn:feature_class":"P",
    "gn:feature_code":"PPL",
    "gn:name":"Beitangcheng",
    "gn:population":0,
    "gn:timezone":"Asia/Shanghai",
    "iso:country":"CN",
    "name:zho_x_preferred":[
        "\u5317\u5510\u57ce"
    ],
    "wof:name":"Beitangcheng",
    "wof:placetype":"locality"
},
  "geometry": {"coordinates":[111.60693000000001,35.73631],"type":"Point"}
}