{
  "type": "Feature",
  "properties": {
    "gn:admin1_code":"32.0",
    "gn:asciiname":"Shibaoling",
    "gn:country_code":"CN",
    "gn:dem":1248,
    "gn:feature_class":"P",
    "gn:feature_code":"PPL",
    "gn:name":"Shibaoling",
    "gn:population":0,
    "gn:timezone":"Asia/Shanghai",
    "iso:country":"CN",
    "name:zho_x_preferred":[
        "\u77f3\u5305\u5cad"
    ],
    "wof:name":"Shibaoling",
    "wof:placetype":"locality"
},
  "geometry": {"coordinates":[108.1583,31.89174],"type":"Point"}
}