{
  "type": "Feature",
  "properties": {
    "gn:admin1_code":"29.0",
    "gn:asciiname":"Miaojiazhai",
    "gn:country_code":"CN",
    "gn:dem":2150,
    "gn:feature_class":"P",
    "gn:feature_code":"PPL",
    "gn:name":"Miaojiazhai",
    "gn:population":0,
    "gn:timezone":"Asia/Shanghai",
    "iso:country":"CN",
    "name:zho_x_preferred":[
        "\u82d7\u5bb6\u5be8"
    ],
    "wof:name":"Miaojiazhai",
    "wof:placetype":"locality"
},
  "geometry": {"coordinates":[99.58240000000001,24.018],"type":"Point"}
}