{
  "type": "Feature",
  "properties": {
    "gn:admin1_code":"7.0",
    "gn:asciiname":"Gaogang",
    "gn:country_code":"CN",
    "gn:dem":870,
    "gn:feature_class":"P",
    "gn:feature_code":"PPL",
    "gn:name":"Gaogang",
    "gn:population":0,
    "gn:timezone":"Asia/Shanghai",
    "iso:country":"CN",
    "name:zho_x_preferred":[
        "\u9ad8\u6e2f"
    ],
    "wof:name":"Gaogang",
    "wof:placetype":"locality"
},
  "geometry": {"coordinates":[118.87884,26.45641],"type":"Point"}
}