{
  "type": "Feature",
  "properties": {
    "gn:admin1_code":"11.0",
    "gn:asciiname":"Huotanchong",
    "gn:country_code":"CN",
    "gn:dem":657,
    "gn:feature_class":"P",
    "gn:feature_code":"PPL",
    "gn:name":"Huotanchong",
    "gn:population":0,
    "gn:timezone":"Asia/Shanghai",
    "iso:country":"CN",
    "name:zho_x_preferred":[
        "\u706b\u70ad\u51b2"
    ],
    "wof:name":"Huotanchong",
    "wof:placetype":"locality"
},
  "geometry": {"coordinates":[110.20435999999999,27.6169],"type":"Point"}
}