{
  "type": "Feature",
  "properties": {
    "gn:admin1_code":"30",
    "gn:asciiname":"Huangbaokeng",
    "gn:country_code":"CN",
    "gn:dem":15,
    "gn:feature_class":"P",
    "gn:feature_code":"PPL",
    "gn:name":"Huangbaokeng",
    "gn:population":0,
    "gn:timezone":"Asia/Shanghai",
    "iso:country":"CN",
    "name:und_x_variant":[
        "\u9ec3\u5bf6\u5751"
    ],
    "wof:name":"Huangbaokeng",
    "wof:placetype":"locality"
},
  "geometry": {"coordinates":[113.00636000000002,22.78365],"type":"Point"}
}