{
  "type": "Feature",
  "properties": {
    "gn:admin1_code":"19.0",
    "gn:asciiname":"Pianpoyingzi",
    "gn:country_code":"CN",
    "gn:dem":173,
    "gn:feature_class":"P",
    "gn:feature_code":"PPL",
    "gn:name":"Pianpoyingzi",
    "gn:population":0,
    "gn:timezone":"Asia/Shanghai",
    "iso:country":"CN",
    "name:und_x_variant":[
        "\u504f\u5761\u8425\u5b50"
    ],
    "name:zho_x_preferred":[
        "\u504f\u5761\u8425\u5b50"
    ],
    "wof:name":"Pianpoyingzi",
    "wof:placetype":"locality"
},
  "geometry": {"coordinates":[122.077,42.6184],"type":"Point"}
}