{
  "type": "Feature",
  "properties": {
    "gn:admin1_code":"32.0",
    "gn:asciiname":"Guoqiao",
    "gn:country_code":"CN",
    "gn:dem":390,
    "gn:feature_class":"P",
    "gn:feature_code":"PPL",
    "gn:name":"Guoqiao",
    "gn:population":0,
    "gn:timezone":"Asia/Shanghai",
    "iso:country":"CN",
    "name:zho_x_preferred":[
        "\u56fd\u6865"
    ],
    "wof:name":"Guoqiao",
    "wof:placetype":"locality"
},
  "geometry": {"coordinates":[106.54000000000001,31.5627],"type":"Point"}
}