{
  "type": "Feature",
  "properties": {
    "gn:admin1_code":"32.0",
    "gn:asciiname":"Lubanji",
    "gn:country_code":"CN",
    "gn:dem":442,
    "gn:feature_class":"P",
    "gn:feature_code":"PPL",
    "gn:name":"Lubanji",
    "gn:population":0,
    "gn:timezone":"Asia/Shanghai",
    "iso:country":"CN",
    "name:zho_x_preferred":[
        "\u9c81\u73ed\u8ff9"
    ],
    "wof:name":"Lubanji",
    "wof:placetype":"locality"
},
  "geometry": {"coordinates":[106.36499999999999,30.5938],"type":"Point"}
}