{
  "type": "Feature",
  "properties": {
    "gn:admin1_code":"8.0",
    "gn:asciiname":"Xinmiaocun",
    "gn:country_code":"CN",
    "gn:dem":75,
    "gn:feature_class":"P",
    "gn:feature_code":"PPL",
    "gn:name":"Xinmiaocun",
    "gn:population":0,
    "gn:timezone":"Asia/Shanghai",
    "iso:country":"CN",
    "name:zho_x_preferred":[
        "\u65b0\u82d7\u6751"
    ],
    "wof:name":"Xinmiaocun",
    "wof:placetype":"locality"
},
  "geometry": {"coordinates":[130.93081000000001,47.5095],"type":"Point"}
}