{
  "type": "Feature",
  "properties": {
    "gn:admin1_code":"19.0",
    "gn:asciiname":"Zhangjia Buzixigou",
    "gn:country_code":"CN",
    "gn:dem":338,
    "gn:feature_class":"P",
    "gn:feature_code":"PPL",
    "gn:name":"Zhangjia Buzixigou",
    "gn:population":0,
    "gn:timezone":"Asia/Shanghai",
    "iso:country":"CN",
    "name:zho_x_preferred":[
        "\u5f20\u5bb6\u5821\u5b50\u897f\u6c9f"
    ],
    "wof:name":"Zhangjia Buzixigou",
    "wof:placetype":"locality"
},
  "geometry": {"coordinates":[124.44,42.243],"type":"Point"}
}