{
  "type": "Feature",
  "properties": {
    "gn:admin1_code":"8.0",
    "gn:asciiname":"Kejia Wobu",
    "gn:country_code":"CN",
    "gn:dem":182,
    "gn:feature_class":"P",
    "gn:feature_code":"PPL",
    "gn:name":"Kejia Wobu",
    "gn:population":0,
    "gn:timezone":"Asia/Shanghai",
    "iso:country":"CN",
    "name:zho_x_preferred":[
        "\u5ba2\u5bb6\u7a9d\u5821"
    ],
    "wof:name":"Kejia Wobu",
    "wof:placetype":"locality"
},
  "geometry": {"coordinates":[126.18368999999998,46.13801],"type":"Point"}
}