{
  "type": "Feature",
  "properties": {
    "gn:admin1_code":"19.0",
    "gn:asciiname":"Laoyemiao",
    "gn:country_code":"CN",
    "gn:dem":77,
    "gn:feature_class":"P",
    "gn:feature_code":"PPL",
    "gn:name":"Laoyemiao",
    "gn:population":0,
    "gn:timezone":"Asia/Shanghai",
    "iso:country":"CN",
    "name:zho_x_preferred":[
        "\u8001\u7237\u5e99"
    ],
    "wof:name":"Laoyemiao",
    "wof:placetype":"locality"
},
  "geometry": {"coordinates":[124.05289999999999,40.35548],"type":"Point"}
}