{
  "type": "Feature",
  "properties": {
    "gn:admin1_code":"32.0",
    "gn:asciiname":"Wangdatang",
    "gn:country_code":"CN",
    "gn:dem":441,
    "gn:feature_class":"P",
    "gn:feature_code":"PPL",
    "gn:name":"Wangdatang",
    "gn:population":0,
    "gn:timezone":"Asia/Shanghai",
    "iso:country":"CN",
    "name:zho_x_preferred":[
        "\u738b\u5927\u5858"
    ],
    "wof:name":"Wangdatang",
    "wof:placetype":"locality"
},
  "geometry": {"coordinates":[103.76600000000001,30.061],"type":"Point"}
}