{
  "type": "Feature",
  "properties": {
    "gn:admin1_code":"7.0",
    "gn:asciiname":"Hanjing",
    "gn:country_code":"CN",
    "gn:dem":77,
    "gn:feature_class":"P",
    "gn:feature_code":"PPL",
    "gn:name":"Hanjing",
    "gn:population":0,
    "gn:timezone":"Asia/Shanghai",
    "iso:country":"CN",
    "name:zho_x_preferred":[
        "\u6db5\u4e95"
    ],
    "wof:name":"Hanjing",
    "wof:placetype":"locality"
},
  "geometry": {"coordinates":[118.7453,25.37187],"type":"Point"}
}