{
  "type": "Feature",
  "properties": {
    "gn:admin1_code":"26.0",
    "gn:asciiname":"Zhuyuanzi",
    "gn:country_code":"CN",
    "gn:dem":1174,
    "gn:feature_class":"P",
    "gn:feature_code":"PPL",
    "gn:name":"Zhuyuanzi",
    "gn:population":0,
    "gn:timezone":"Asia/Shanghai",
    "iso:country":"CN",
    "name:zho_x_preferred":[
        "\u7af9\u56ed\u5b50"
    ],
    "wof:name":"Zhuyuanzi",
    "wof:placetype":"locality"
},
  "geometry": {"coordinates":[109.52573999999998,33.59034],"type":"Point"}
}