{
  "type": "Feature",
  "properties": {
    "gn:admin1_code":"7.0",
    "gn:asciiname":"Linyang",
    "gn:country_code":"CN",
    "gn:dem":833,
    "gn:feature_class":"P",
    "gn:feature_code":"PPL",
    "gn:name":"Linyang",
    "gn:population":0,
    "gn:timezone":"Asia/Shanghai",
    "iso:country":"CN",
    "name:zho_x_preferred":[
        "Linyang"
    ],
    "name:zho_x_variant":[
        "\u6797\u6d0b"
    ],
    "wof:name":"Linyang",
    "wof:placetype":"locality"
},
  "geometry": {"coordinates":[119.11778,26.7175],"type":"Point"}
}