{
  "type": "Feature",
  "properties": {
    "gn:admin1_code":"4.0",
    "gn:asciiname":"Xiqianzhuang",
    "gn:country_code":"CN",
    "gn:dem":5,
    "gn:feature_class":"P",
    "gn:feature_code":"PPL",
    "gn:name":"Xiqianzhuang",
    "gn:population":0,
    "gn:timezone":"Asia/Shanghai",
    "iso:country":"CN",
    "name:zho_x_preferred":[
        "\u897f\u94b1\u5e84"
    ],
    "wof:name":"Xiqianzhuang",
    "wof:placetype":"locality"
},
  "geometry": {"coordinates":[119.72992000000001,32.85658],"type":"Point"}
}