{
  "type": "Feature",
  "properties": {
    "gn:admin1_code":"8.0",
    "gn:asciiname":"Fuyucun",
    "gn:country_code":"CN",
    "gn:dem":353,
    "gn:feature_class":"P",
    "gn:feature_code":"PPL",
    "gn:name":"Fuyucun",
    "gn:population":0,
    "gn:timezone":"Asia/Shanghai",
    "iso:country":"CN",
    "name:zho_x_preferred":[
        "\u5bcc\u88d5\u6751"
    ],
    "wof:name":"Fuyucun",
    "wof:placetype":"locality"
},
  "geometry": {"coordinates":[129.17411999999999,43.98268],"type":"Point"}
}