{
  "type": "Feature",
  "properties": {
    "gn:admin1_code":"8.0",
    "gn:asciiname":"Chenjiagangzi",
    "gn:country_code":"CN",
    "gn:dem":238,
    "gn:feature_class":"P",
    "gn:feature_code":"PPL",
    "gn:name":"Chenjiagangzi",
    "gn:population":0,
    "gn:timezone":"Asia/Shanghai",
    "iso:country":"CN",
    "name:zho_x_preferred":[
        "\u9648\u5bb6\u5c97\u5b50"
    ],
    "wof:name":"Chenjiagangzi",
    "wof:placetype":"locality"
},
  "geometry": {"coordinates":[125.0406,48.04212],"type":"Point"}
}