{
  "type": "Feature",
  "properties": {
    "gn:admin1_code":"32.0",
    "gn:asciiname":"Changqiao",
    "gn:country_code":"CN",
    "gn:dem":407,
    "gn:feature_class":"P",
    "gn:feature_code":"PPL",
    "gn:name":"Changqiao",
    "gn:population":0,
    "gn:timezone":"Asia/Shanghai",
    "iso:country":"CN",
    "name:zho_x_preferred":[
        "\u957f\u6865"
    ],
    "wof:name":"Changqiao",
    "wof:placetype":"locality"
},
  "geometry": {"coordinates":[105.10299999999999,30.8811],"type":"Point"}
}