{
  "type": "Feature",
  "properties": {
    "gn:admin1_code":"1.0",
    "gn:asciiname":"Haiqingcun",
    "gn:country_code":"CN",
    "gn:dem":40,
    "gn:feature_class":"P",
    "gn:feature_code":"PPL",
    "gn:name":"Haiqingcun",
    "gn:population":0,
    "gn:timezone":"Asia/Shanghai",
    "iso:country":"CN",
    "name:zho_x_preferred":[
        "\u6d77\u9752\u6751"
    ],
    "wof:name":"Haiqingcun",
    "wof:placetype":"locality"
},
  "geometry": {"coordinates":[116.58938999999999,34.15617],"type":"Point"}
}