{
  "type": "Feature",
  "properties": {
    "gn:admin1_code":"13.0",
    "gn:asciiname":"Yengimahalla",
    "gn:country_code":"CN",
    "gn:dem":923,
    "gn:feature_class":"P",
    "gn:feature_code":"PPL",
    "gn:name":"Yengimahalla",
    "gn:population":0,
    "gn:timezone":"Asia/Urumqi",
    "iso:country":"CN",
    "name:uig_x_preferred":[
        "Yengim\u0259h\u0328\u0259ll\u0259"
    ],
    "name:uig_x_variant":[
        "Y\u00e9ngimehelle",
        "\u064a\u06d0\u06ad\u0649\u0645\u06d5\u06be\u06d5\u0644\u0644\u06d5",
        "\u0415\u04a3\u0438\u043c\u04d9\u04bb\u04d9\u043b\u043b\u04d9"
    ],
    "wof:name":"Yengimahalla",
    "wof:placetype":"locality"
},
  "geometry": {"coordinates":[84.68333,41.21667],"type":"Point"}
}