{
  "type": "Feature",
  "properties": {
    "gn:admin1_code":"32.0",
    "gn:asciiname":"Nawo",
    "gn:country_code":"CN",
    "gn:dem":2759,
    "gn:feature_class":"P",
    "gn:feature_code":"PPL",
    "gn:name":"Nawo",
    "gn:population":0,
    "gn:timezone":"Asia/Shanghai",
    "iso:country":"CN",
    "name:zho_x_preferred":[
        "\u7eb3\u7a9d"
    ],
    "wof:name":"Nawo",
    "wof:placetype":"locality"
},
  "geometry": {"coordinates":[103.164,32.2625],"type":"Point"}
}