{
  "type": "Feature",
  "properties": {
    "gn:admin1_code":"19.0",
    "gn:asciiname":"Damintun",
    "gn:country_code":"CN",
    "gn:dem":31,
    "gn:feature_class":"P",
    "gn:feature_code":"PPL",
    "gn:name":"Damintun",
    "gn:population":0,
    "gn:timezone":"Asia/Shanghai",
    "iso:country":"CN",
    "name:zho_x_preferred":[
        "\u5927\u6c11\u5c6f"
    ],
    "wof:name":"Damintun",
    "wof:placetype":"locality"
},
  "geometry": {"coordinates":[122.27898,41.84034000000001],"type":"Point"}
}