{
  "type": "Feature",
  "properties": {
    "gn:admin1_code":"10",
    "gn:asciiname":"Madayu",
    "gn:country_code":"CN",
    "gn:dem":166,
    "gn:feature_class":"P",
    "gn:feature_code":"PPL",
    "gn:name":"Madayu",
    "gn:population":0,
    "gn:timezone":"Asia/Shanghai",
    "iso:country":"CN",
    "name:zho_x_preferred":[
        "\u9ebb\u8fbe\u5cea"
    ],
    "wof:name":"Madayu",
    "wof:placetype":"locality"
},
  "geometry": {"coordinates":[118.44225,40.26828],"type":"Point"}
}