{
  "type": "Feature",
  "properties": {
    "gn:admin1_code":"2.0",
    "gn:asciiname":"Dahezhao",
    "gn:country_code":"CN",
    "gn:dem":6,
    "gn:feature_class":"P",
    "gn:feature_code":"PPL",
    "gn:name":"Dahezhao",
    "gn:population":0,
    "gn:timezone":"Asia/Shanghai",
    "iso:country":"CN",
    "name:zho_x_preferred":[
        "\u5927\u6cb3\u6cbc"
    ],
    "wof:name":"Dahezhao",
    "wof:placetype":"locality"
},
  "geometry": {"coordinates":[121.15340999999999,30.72859],"type":"Point"}
}