{
  "type": "Feature",
  "properties": {
    "gn:admin1_code":"1.0",
    "gn:asciiname":"Chonglingshan",
    "gn:country_code":"CN",
    "gn:dem":42,
    "gn:feature_class":"P",
    "gn:feature_code":"PPL",
    "gn:name":"Chonglingshan",
    "gn:population":0,
    "gn:timezone":"Asia/Shanghai",
    "iso:country":"CN",
    "name:und_x_variant":[
        "\u5d07\u5cad\u5c71"
    ],
    "wof:name":"Chonglingshan",
    "wof:placetype":"locality"
},
  "geometry": {"coordinates":[118.30833,30.86667000000001],"type":"Point"}
}