{
  "type": "Feature",
  "properties": {
    "gn:admin1_code":"8.0",
    "gn:asciiname":"Jixiehua",
    "gn:country_code":"CN",
    "gn:dem":207,
    "gn:feature_class":"P",
    "gn:feature_code":"PPL",
    "gn:name":"Jixiehua",
    "gn:population":0,
    "gn:timezone":"Asia/Shanghai",
    "iso:country":"CN",
    "name:zho_x_preferred":[
        "\u673a\u68b0\u5316"
    ],
    "wof:name":"Jixiehua",
    "wof:placetype":"locality"
},
  "geometry": {"coordinates":[127.61591,45.06903],"type":"Point"}
}