{
  "type": "Feature",
  "properties": {
    "gn:admin1_code":"8.0",
    "gn:asciiname":"Liangzhongcun",
    "gn:country_code":"CN",
    "gn:dem":172,
    "gn:feature_class":"P",
    "gn:feature_code":"PPL",
    "gn:name":"Liangzhongcun",
    "gn:population":0,
    "gn:timezone":"Asia/Shanghai",
    "iso:country":"CN",
    "name:zho_x_preferred":[
        "\u826f\u79cd\u6751"
    ],
    "wof:name":"Liangzhongcun",
    "wof:placetype":"locality"
},
  "geometry": {"coordinates":[127.65576,46.36876],"type":"Point"}
}