{
  "type": "Feature",
  "properties": {
    "gn:admin1_code":"29",
    "gn:asciiname":"Dazongduo",
    "gn:country_code":"CN",
    "gn:dem":1814,
    "gn:feature_class":"P",
    "gn:feature_code":"PPL",
    "gn:name":"Dazongduo",
    "gn:population":0,
    "gn:timezone":"Asia/Shanghai",
    "iso:country":"CN",
    "name:zho_x_preferred":[
        "\u5927\u603b\u591a"
    ],
    "wof:name":"Dazongduo",
    "wof:placetype":"locality"
},
  "geometry": {"coordinates":[102.95004,24.09136],"type":"Point"}
}