{
  "type": "Feature",
  "properties": {
    "gn:admin1_code":"9.0",
    "gn:asciiname":"Jiuluzhuang",
    "gn:country_code":"CN",
    "gn:dem":87,
    "gn:feature_class":"P",
    "gn:feature_code":"PPL",
    "gn:name":"Jiuluzhuang",
    "gn:population":0,
    "gn:timezone":"Asia/Shanghai",
    "iso:country":"CN",
    "name:zho_x_preferred":[
        "\u4e5d\u82a6\u5e84"
    ],
    "wof:name":"Jiuluzhuang",
    "wof:placetype":"locality"
},
  "geometry": {"coordinates":[112.34828,32.39254],"type":"Point"}
}