{
  "type": "Feature",
  "properties": {
    "gn:admin1_code":"31.0",
    "gn:asciiname":"Xinxing Liuqu Wudui",
    "gn:country_code":"CN",
    "gn:dem":108,
    "gn:feature_class":"P",
    "gn:feature_code":"PPLF",
    "gn:name":"Xinxing Liuqu Wudui",
    "gn:population":0,
    "gn:timezone":"Asia/Shanghai",
    "iso:country":"CN",
    "name:und_x_variant":[
        "\u65b0\u661f\u516d\u533a\u4e94\u961f"
    ],
    "wof:name":"Xinxing Liuqu Wudui",
    "wof:placetype":"locality"
},
  "geometry": {"coordinates":[109.66509000000001,18.6958],"type":"Point"}
}