{
  "type": "Feature",
  "properties": {
    "gn:admin1_code":"24.0",
    "gn:asciiname":"Jiancun",
    "gn:country_code":"CN",
    "gn:dem":791,
    "gn:feature_class":"P",
    "gn:feature_code":"PPL",
    "gn:name":"Jiancun",
    "gn:population":0,
    "gn:timezone":"Asia/Shanghai",
    "iso:country":"CN",
    "name:zho_x_preferred":[
        "\u6da7\u6751"
    ],
    "wof:name":"Jiancun",
    "wof:placetype":"locality"
},
  "geometry": {"coordinates":[112.41673,37.3273],"type":"Point"}
}