{
  "type": "Feature",
  "properties": {
    "gn:admin1_code":"13",
    "gn:asciiname":"Fengshousanchang Yi'erlian",
    "gn:country_code":"CN",
    "gn:dem":1041,
    "gn:feature_class":"P",
    "gn:feature_code":"PPL",
    "gn:name":"Fengshousanchang Yi\u2019erlian",
    "gn:population":0,
    "gn:timezone":"Asia/Shanghai",
    "iso:country":"CN",
    "name:und_x_variant":[
        "Fengshousanchang Yi\u2019erlian",
        "\u4e30\u6536\u4e09\u573a\u4e00\u4e8c\u8fde"
    ],
    "wof:name":"Fengshousanchang Yi'erlian",
    "wof:placetype":"locality"
},
  "geometry": {"coordinates":[80.27015,40.42966],"type":"Point"}
}