{
  "type": "Feature",
  "properties": {
    "gn:admin1_code":"24",
    "gn:asciiname":"Fangchicun",
    "gn:country_code":"CN",
    "gn:dem":393,
    "gn:feature_class":"P",
    "gn:feature_code":"PPL",
    "gn:name":"Fangchicun",
    "gn:population":0,
    "gn:timezone":"Asia/Shanghai",
    "iso:country":"CN",
    "name:und_x_variant":[
        "Fang-ch\u2019ih",
        "Fang-ch\u2019ih-ts\u2019un",
        "Fangchi",
        "Fangchicun"
    ],
    "name:zho_x_preferred":[
        "\u65b9\u6c60\u6751"
    ],
    "wof:name":"Fangchicun",
    "wof:placetype":"locality"
},
  "geometry": {"coordinates":[110.34650000000001,34.95576],"type":"Point"}
}