{
  "type": "Feature",
  "properties": {
    "gn:admin1_code":"4.0",
    "gn:asciiname":"Yujiajing",
    "gn:country_code":"CN",
    "gn:dem":5,
    "gn:feature_class":"P",
    "gn:feature_code":"PPL",
    "gn:name":"Yujiajing",
    "gn:population":0,
    "gn:timezone":"Asia/Shanghai",
    "iso:country":"CN",
    "name:zho_x_preferred":[
        "\u90c1\u5bb6\u6cfe"
    ],
    "wof:name":"Yujiajing",
    "wof:placetype":"locality"
},
  "geometry": {"coordinates":[120.84338,31.45469000000001],"type":"Point"}
}