{
  "type": "Feature",
  "properties": {
    "gn:admin1_code":"3.0",
    "gn:asciiname":"Xiaowuli",
    "gn:country_code":"CN",
    "gn:dem":357,
    "gn:feature_class":"P",
    "gn:feature_code":"PPL",
    "gn:name":"Xiaowuli",
    "gn:population":0,
    "gn:timezone":"Asia/Shanghai",
    "iso:country":"CN",
    "name:und_x_variant":[
        "\u5c0f\u575e\u91cc"
    ],
    "wof:name":"Xiaowuli",
    "wof:placetype":"locality"
},
  "geometry": {"coordinates":[117.58006,29.56985],"type":"Point"}
}