{
  "type": "Feature",
  "properties": {
    "gn:admin1_code":"25",
    "gn:asciiname":"Wenjiapozi",
    "gn:country_code":"CN",
    "gn:dem":53,
    "gn:feature_class":"P",
    "gn:feature_code":"PPL",
    "gn:name":"Wenjiapozi",
    "gn:population":0,
    "gn:timezone":"Asia/Shanghai",
    "iso:country":"CN",
    "name:zho_x_preferred":[
        "\u6e29\u5bb6\u5761\u5b50"
    ],
    "wof:name":"Wenjiapozi",
    "wof:placetype":"locality"
},
  "geometry": {"coordinates":[119.224,36.4895],"type":"Point"}
}