{
  "type": "Feature",
  "properties": {
    "gn:admin1_code":"30",
    "gn:asciiname":"Cangcheng",
    "gn:country_code":"CN",
    "gn:dem":11,
    "gn:feature_class":"P",
    "gn:feature_code":"PPLA4",
    "gn:name":"Cangcheng",
    "gn:population":0,
    "gn:timezone":"Asia/Shanghai",
    "iso:country":"CN",
    "name:und_x_variant":[
        "K\u2019ai-p\u2019ing-hsien",
        "Chiu-k\u2019ai-p\u2019ing",
        "Ts\u2019ang-ch\u2019eng",
        "Hoiping",
        "K\u2019ai-p\u2019ing",
        "Hoiping-hsien",
        "Cangcheng",
        "Cangcheng Zhen",
        "\u82cd\u57ce\u9547"
    ],
    "name:zho_x_preferred":[
        "\u82cd\u57ce"
    ],
    "wof:name":"Cangcheng",
    "wof:placetype":"locality"
},
  "geometry": {"coordinates":[112.54810000000001,22.47805],"type":"Point"}
}