{
  "type": "Feature",
  "properties": {
    "gn:admin1_code":"8.0",
    "gn:asciiname":"Laotoushe",
    "gn:country_code":"CN",
    "gn:dem":147,
    "gn:feature_class":"P",
    "gn:feature_code":"PPL",
    "gn:name":"Laotoushe",
    "gn:population":0,
    "gn:timezone":"Asia/Shanghai",
    "iso:country":"CN",
    "name:zho_x_preferred":[
        "\u8001\u5934\u793e"
    ],
    "wof:name":"Laotoushe",
    "wof:placetype":"locality"
},
  "geometry": {"coordinates":[124.04563,47.3258],"type":"Point"}
}