{
  "type": "Feature",
  "properties": {
    "gn:admin1_code":"29.0",
    "gn:asciiname":"Shantoutian",
    "gn:country_code":"CN",
    "gn:dem":1845,
    "gn:feature_class":"P",
    "gn:feature_code":"PPL",
    "gn:name":"Shantoutian",
    "gn:population":0,
    "gn:timezone":"Asia/Shanghai",
    "iso:country":"CN",
    "name:zho_x_preferred":[
        "\u5c71\u5934\u7530"
    ],
    "wof:name":"Shantoutian",
    "wof:placetype":"locality"
},
  "geometry": {"coordinates":[99.8326,24.3523],"type":"Point"}
}