{
  "type": "Feature",
  "properties": {
    "gn:admin1_code":"24.0",
    "gn:asciiname":"Beilecun",
    "gn:country_code":"CN",
    "gn:dem":1243,
    "gn:feature_class":"P",
    "gn:feature_code":"PPL",
    "gn:name":"Beilecun",
    "gn:population":0,
    "gn:timezone":"Asia/Shanghai",
    "iso:country":"CN",
    "name:zho_x_preferred":[
        "\u5317\u4e50\u6751"
    ],
    "wof:name":"Beilecun",
    "wof:placetype":"locality"
},
  "geometry": {"coordinates":[110.76167,36.05856],"type":"Point"}
}