{
  "type": "Feature",
  "properties": {
    "gn:admin1_code":"15.0",
    "gn:asciiname":"Dayantai",
    "gn:country_code":"CN",
    "gn:dem":1447,
    "gn:feature_class":"P",
    "gn:feature_code":"PPL",
    "gn:name":"Dayantai",
    "gn:population":0,
    "gn:timezone":"Asia/Shanghai",
    "iso:country":"CN",
    "name:und_x_variant":[
        "\u5927\u96c1\u53f0"
    ],
    "wof:name":"Dayantai",
    "wof:placetype":"locality"
},
  "geometry": {"coordinates":[107.25109999999999,36.9395],"type":"Point"}
}