{
  "type": "Feature",
  "properties": {
    "gn:admin1_code":"24.0",
    "gn:asciiname":"Dongxinguan",
    "gn:country_code":"CN",
    "gn:dem":596,
    "gn:feature_class":"P",
    "gn:feature_code":"PPL",
    "gn:name":"Dongxinguan",
    "gn:population":0,
    "gn:timezone":"Asia/Shanghai",
    "iso:country":"CN",
    "name:zho_x_preferred":[
        "\u4e1c\u8f9b\u5173"
    ],
    "wof:name":"Dongxinguan",
    "wof:placetype":"locality"
},
  "geometry": {"coordinates":[110.46845,37.0578],"type":"Point"}
}