{
  "type": "Feature",
  "properties": {
    "gn:admin1_code":"29.0",
    "gn:asciiname":"Tianxing",
    "gn:country_code":"CN",
    "gn:dem":646,
    "gn:feature_class":"P",
    "gn:feature_code":"PPL",
    "gn:name":"Tianxing",
    "gn:population":0,
    "gn:timezone":"Asia/Shanghai",
    "iso:country":"CN",
    "name:ceb_x_preferred":[
        "Tianxing"
    ],
    "name:deu_x_preferred":[
        "Tianxing"
    ],
    "name:swe_x_preferred":[
        "Tianxing"
    ],
    "name:zho_x_preferred":[
        "\u5929\u661f"
    ],
    "wof:name":"Tianxing",
    "wof:placetype":"locality"
},
  "geometry": {"coordinates":[104.21749,28.21694],"type":"Point"}
}