{
  "type": "Feature",
  "properties": {
    "gn:admin1_code":"33.0",
    "gn:asciiname":"Huaqiansi",
    "gn:country_code":"CN",
    "gn:dem":353,
    "gn:feature_class":"P",
    "gn:feature_code":"PPL",
    "gn:name":"Huaqiansi",
    "gn:population":0,
    "gn:timezone":"Asia/Shanghai",
    "iso:country":"CN",
    "name:zho_x_preferred":[
        "\u5316\u94b1\u5bfa"
    ],
    "wof:name":"Huaqiansi",
    "wof:placetype":"locality"
},
  "geometry": {"coordinates":[105.65765,30.24246],"type":"Point"}
}