{
  "type": "Feature",
  "properties": {
    "gn:admin1_code":"14",
    "gn:asciiname":"Pudui",
    "gn:country_code":"CN",
    "gn:dem":4801,
    "gn:feature_class":"P",
    "gn:feature_code":"PPL",
    "gn:name":"Pudui",
    "gn:population":0,
    "gn:timezone":"Asia/Urumqi",
    "iso:country":"CN",
    "name:zho_x_preferred":[
        "\u666e\u5806"
    ],
    "wof:name":"Pudui",
    "wof:placetype":"locality"
},
  "geometry": {"coordinates":[89.72750000000001,29.1862],"type":"Point"}
}