{
  "type": "Feature",
  "properties": {
    "gn:admin1_code":"16.0",
    "gn:asciiname":"Bancha",
    "gn:country_code":"CN",
    "gn:dem":239,
    "gn:feature_class":"P",
    "gn:feature_code":"PPL",
    "gn:name":"Bancha",
    "gn:population":0,
    "gn:timezone":"Asia/Shanghai",
    "iso:country":"CN",
    "name:bre_x_preferred":[
        "Bancha"
    ],
    "name:cat_x_preferred":[
        "Bancha"
    ],
    "name:ces_x_preferred":[
        "Ban\u010da"
    ],
    "name:deu_x_preferred":[
        "Bancha"
    ],
    "name:fin_x_preferred":[
        "Bancha"
    ],
    "name:fra_x_preferred":[
        "Bancha"
    ],
    "name:hun_x_preferred":[
        "Bancsa tea"
    ],
    "name:hye_x_preferred":[
        "\u0532\u0561\u0576\u057f\u0575\u0561"
    ],
    "name:por_x_preferred":[
        "Bancha"
    ],
    "name:rus_x_preferred":[
        "\u0411\u0430\u043d\u0442\u044f"
    ],
    "name:spa_x_preferred":[
        "Bancha"
    ],
    "name:swe_x_preferred":[
        "Bancha"
    ],
    "name:tur_x_preferred":[
        "Bancha"
    ],
    "name:ukr_x_preferred":[
        "\u0411\u0430\u043d\u0442\u044f"
    ],
    "name:vie_x_preferred":[
        "Bancha"
    ],
    "name:zho_x_preferred":[
        "\u73ed\u8336"
    ],
    "wof:name":"Bancha",
    "wof:placetype":"locality"
},
  "geometry": {"coordinates":[110.357,23.8012],"type":"Point"}
}