{
  "type": "Feature",
  "properties": {
    "gn:admin1_code":"16.0",
    "gn:asciiname":"Bancha",
    "gn:country_code":"CN",
    "gn:dem":239,
    "gn:feature_class":"P",
    "gn:feature_code":"PPL",
    "gn:name":"Bancha",
    "gn:population":0,
    "gn:timezone":"Asia/Shanghai",
    "iso:country":"CN",
    "name:zho_x_preferred":[
        "\u73ed\u8336"
    ],
    "wof:name":"Bancha",
    "wof:placetype":"locality"
},
  "geometry": {"coordinates":[110.357,23.8012],"type":"Point"}
}