{
  "type": "Feature",
  "properties": {
    "gn:admin1_code":"15.0",
    "gn:asciiname":"Xindezhuang",
    "gn:country_code":"CN",
    "gn:dem":1622,
    "gn:feature_class":"P",
    "gn:feature_code":"PPL",
    "gn:name":"Xindezhuang",
    "gn:population":0,
    "gn:timezone":"Asia/Shanghai",
    "iso:country":"CN",
    "name:und_x_variant":[
        "\u65b0\u5fb7\u5e84"
    ],
    "name:zho_x_preferred":[
        "\u65b0\u5fb7\u5e84"
    ],
    "wof:name":"Xindezhuang",
    "wof:placetype":"locality"
},
  "geometry": {"coordinates":[104.75149,33.1964],"type":"Point"}
}