{
  "type": "Feature",
  "properties": {
    "gn:admin1_code":"11.0",
    "gn:asciiname":"Pengjiadong",
    "gn:country_code":"CN",
    "gn:dem":789,
    "gn:feature_class":"P",
    "gn:feature_code":"PPL",
    "gn:name":"Pengjiadong",
    "gn:population":0,
    "gn:timezone":"Asia/Shanghai",
    "iso:country":"CN",
    "name:zho_x_preferred":[
        "\u5f6d\u5bb6\u6d1e"
    ],
    "wof:name":"Pengjiadong",
    "wof:placetype":"locality"
},
  "geometry": {"coordinates":[110.85303999999999,27.56865],"type":"Point"}
}