{
  "type": "Feature",
  "properties": {
    "gn:admin1_code":"26.0",
    "gn:asciiname":"Xujiazhuang",
    "gn:country_code":"CN",
    "gn:dem":1637,
    "gn:feature_class":"P",
    "gn:feature_code":"PPL",
    "gn:name":"Xujiazhuang",
    "gn:population":0,
    "gn:timezone":"Asia/Shanghai",
    "iso:country":"CN",
    "name:und_x_variant":[
        "\u8bb8\u5bb6\u5e84"
    ],
    "wof:name":"Xujiazhuang",
    "wof:placetype":"locality"
},
  "geometry": {"coordinates":[106.5724,33.74391],"type":"Point"}
}