{
  "type": "Feature",
  "properties": {
    "gn:admin1_code":"7.0",
    "gn:asciiname":"Huangtuzhai",
    "gn:country_code":"CN",
    "gn:dem":648,
    "gn:feature_class":"P",
    "gn:feature_code":"PPL",
    "gn:name":"Huangtuzhai",
    "gn:population":0,
    "gn:timezone":"Asia/Shanghai",
    "iso:country":"CN",
    "name:zho_x_preferred":[
        "\u9ec4\u571f\u5be8"
    ],
    "wof:name":"Huangtuzhai",
    "wof:placetype":"locality"
},
  "geometry": {"coordinates":[118.78051000000001,25.94267],"type":"Point"}
}