{
  "type": "Feature",
  "properties": {
    "gn:admin1_code":"33.0",
    "gn:asciiname":"Anping",
    "gn:country_code":"CN",
    "gn:dem":266,
    "gn:feature_class":"P",
    "gn:feature_code":"PPL",
    "gn:name":"Anping",
    "gn:population":0,
    "gn:timezone":"Asia/Shanghai",
    "iso:country":"CN",
    "name:zho_x_preferred":[
        "\u5b89\u5e73"
    ],
    "wof:name":"Anping",
    "wof:placetype":"locality"
},
  "geometry": {"coordinates":[107.97521999999999,30.82498],"type":"Point"}
}