{
  "type": "Feature",
  "properties": {
    "gn:admin1_code":"14.0",
    "gn:asciiname":"Zaxoi",
    "gn:country_code":"CN",
    "gn:dem":3926,
    "gn:feature_class":"P",
    "gn:feature_code":"PPL",
    "gn:name":"Zaxoi",
    "gn:population":0,
    "gn:timezone":"Asia/Urumqi",
    "iso:country":"CN",
    "name:bod_x_preferred":[
        "\u0f62\u0fa9\u0f0b\u0f5e\u0f7c\u0f63"
    ],
    "name:msa_x_preferred":[
        "Zaxoi"
    ],
    "name:und_x_variant":[
        "Zhaxue"
    ],
    "name:zho_x_preferred":[
        "\u624e\u96ea"
    ],
    "name:zho_x_variant":[
        "\u624e\u96ea\u4e61"
    ],
    "wof:name":"Zaxoi",
    "wof:placetype":"locality"
},
  "geometry": {"coordinates":[91.81804,30.04755],"type":"Point"}
}