{
  "type": "Feature",
  "properties": {
    "gn:admin1_code":"14.0",
    "gn:asciiname":"Maintang",
    "gn:country_code":"CN",
    "gn:dem":4617,
    "gn:feature_class":"P",
    "gn:feature_code":"PPLA4",
    "gn:name":"Maintang",
    "gn:population":0,
    "gn:timezone":"Asia/Urumqi",
    "iso:country":"CN",
    "name:bod_x_preferred":[
        "Maintang"
    ],
    "name:und_x_variant":[
        "Mendang Xiang"
    ],
    "name:zho_x_preferred":[
        "Mendang"
    ],
    "name:zho_x_variant":[
        "\u95e8\u5f53",
        "Mendangrezi",
        "\u95e8\u5f53\u60f9\u5b5c",
        "\u95e8\u5f53\u4e61"
    ],
    "wof:name":"Maintang",
    "wof:placetype":"locality"
},
  "geometry": {"coordinates":[89.75582,31.41328],"type":"Point"}
}