{
  "type": "Feature",
  "properties": {
    "gn:admin1_code":"9.0",
    "gn:asciiname":"Xitanggou",
    "gn:country_code":"CN",
    "gn:dem":296,
    "gn:feature_class":"P",
    "gn:feature_code":"PPL",
    "gn:name":"Xitanggou",
    "gn:population":0,
    "gn:timezone":"Asia/Shanghai",
    "iso:country":"CN",
    "name:zho_x_preferred":[
        "\u897f\u5510\u6c9f"
    ],
    "wof:name":"Xitanggou",
    "wof:placetype":"locality"
},
  "geometry": {"coordinates":[112.60511,34.20769],"type":"Point"}
}