{
  "type": "Feature",
  "properties": {
    "gn:admin1_code":"24.0",
    "gn:asciiname":"Beiluozhuang",
    "gn:country_code":"CN",
    "gn:dem":1495,
    "gn:feature_class":"P",
    "gn:feature_code":"PPL",
    "gn:name":"Beiluozhuang",
    "gn:population":0,
    "gn:timezone":"Asia/Shanghai",
    "iso:country":"CN",
    "name:und_x_variant":[
        "\u5317\u7f57\u5e84"
    ],
    "wof:name":"Beiluozhuang",
    "wof:placetype":"locality"
},
  "geometry": {"coordinates":[112.69614,39.59932],"type":"Point"}
}