{
  "type": "Feature",
  "properties": {
    "gn:admin1_code":"05",
    "gn:asciiname":"Shuangchacun",
    "gn:country_code":"CN",
    "gn:dem":504,
    "gn:feature_class":"P",
    "gn:feature_code":"PPL",
    "gn:name":"Shuangchacun",
    "gn:population":0,
    "gn:timezone":"Asia/Shanghai",
    "iso:country":"CN",
    "name:und_x_variant":[
        "Shuangcha",
        "Shuang-ch\u2019a-ho",
        "Shuangchahe",
        "\u53cc\u53c9",
        "Shuangchacun"
    ],
    "name:zho_x_preferred":[
        "\u53cc\u5c94\u6751"
    ],
    "wof:name":"Shuangchacun",
    "wof:placetype":"locality"
},
  "geometry": {"coordinates":[125.92285,41.16671],"type":"Point"}
}