{
  "type": "Feature",
  "properties": {
    "gn:admin1_code":"2.0",
    "gn:asciiname":"Hongyanjiao",
    "gn:country_code":"CN",
    "gn:dem":12,
    "gn:feature_class":"P",
    "gn:feature_code":"PPL",
    "gn:name":"Hongyanjiao",
    "gn:population":0,
    "gn:timezone":"Asia/Shanghai",
    "iso:country":"CN",
    "name:zho_x_preferred":[
        "\u7ea2\u5ca9\u811a"
    ],
    "wof:name":"Hongyanjiao",
    "wof:placetype":"locality"
},
  "geometry": {"coordinates":[121.61332,28.95004],"type":"Point"}
}