{
  "type": "Feature",
  "properties": {
    "gn:admin1_code":"8.0",
    "gn:asciiname":"Xingfacun",
    "gn:country_code":"CN",
    "gn:dem":230,
    "gn:feature_class":"P",
    "gn:feature_code":"PPL",
    "gn:name":"Xingfacun",
    "gn:population":0,
    "gn:timezone":"Asia/Shanghai",
    "iso:country":"CN",
    "name:zho_x_preferred":[
        "\u5174\u53d1\u6751"
    ],
    "wof:name":"Xingfacun",
    "wof:placetype":"locality"
},
  "geometry": {"coordinates":[127.64388,46.64237],"type":"Point"}
}