{
  "type": "Feature",
  "properties": {
    "gn:admin1_code":"29.0",
    "gn:asciiname":"Masangshu",
    "gn:country_code":"CN",
    "gn:dem":1857,
    "gn:feature_class":"P",
    "gn:feature_code":"PPL",
    "gn:name":"Masangshu",
    "gn:population":0,
    "gn:timezone":"Asia/Shanghai",
    "iso:country":"CN",
    "name:zho_x_preferred":[
        "\u9a6c\u6851\u6811"
    ],
    "wof:name":"Masangshu",
    "wof:placetype":"locality"
},
  "geometry": {"coordinates":[99.9346,25.5145],"type":"Point"}
}