{
  "type": "Feature",
  "properties": {
    "gn:admin1_code":"2.0",
    "gn:asciiname":"Neixikeng",
    "gn:country_code":"CN",
    "gn:dem":210,
    "gn:feature_class":"P",
    "gn:feature_code":"PPL",
    "gn:name":"Neixikeng",
    "gn:population":0,
    "gn:timezone":"Asia/Shanghai",
    "iso:country":"CN",
    "name:zho_x_preferred":[
        "\u5185\u897f\u5751"
    ],
    "wof:name":"Neixikeng",
    "wof:placetype":"locality"
},
  "geometry": {"coordinates":[118.41578,28.98849],"type":"Point"}
}