{
  "type": "Feature",
  "properties": {
    "gn:admin1_code":"33",
    "gn:asciiname":"Gongtan",
    "gn:country_code":"CN",
    "gn:dem":298,
    "gn:feature_class":"P",
    "gn:feature_code":"PPLA4",
    "gn:name":"Gongtan",
    "gn:population":0,
    "gn:timezone":"Asia/Shanghai",
    "iso:country":"CN",
    "name:und_x_variant":[
        "Kiangtan",
        "Kung-t\u2019an",
        "Kung-t\u2019an-hs\u00fcn",
        "Gongtan",
        "Gongtan Zhen"
    ],
    "name:zho_x_preferred":[
        "\u9f9a\u6ee9"
    ],
    "name:zho_x_variant":[
        "\u9f9a\u6ee9\u9547"
    ],
    "wof:name":"Gongtan",
    "wof:placetype":"locality"
},
  "geometry": {"coordinates":[108.34856000000001,28.90772],"type":"Point"}
}