{
  "type": "Feature",
  "properties": {
    "gn:admin1_code":"14.0",
    "gn:asciiname":"Lagongcun",
    "gn:country_code":"CN",
    "gn:dem":1721,
    "gn:feature_class":"P",
    "gn:feature_code":"PPL",
    "gn:name":"Lagongcun",
    "gn:population":0,
    "gn:timezone":"Asia/Urumqi",
    "iso:country":"CN",
    "name:zho_x_preferred":[
        "\u62c9\u8d21\u6751"
    ],
    "wof:name":"Lagongcun",
    "wof:placetype":"locality"
},
  "geometry": {"coordinates":[95.377,29.69223],"type":"Point"}
}