{
  "type": "Feature",
  "properties": {
    "gn:country":"CN",
    "gn:fcode":"PPLA3",
    "gn:pop":75347,
    "iso:country":"CN",
    "name:ceb_x_preferred":[
        "Chaoyang"
    ],
    "name:ces_x_preferred":[
        "\u010cchao-jang"
    ],
    "name:deu_x_preferred":[
        "Chaoyang"
    ],
    "name:eus_x_preferred":[
        "Chaoyang"
    ],
    "name:fra_x_preferred":[
        "Chaoyang"
    ],
    "name:mlg_x_preferred":[
        "Chaoyang"
    ],
    "name:nld_x_preferred":[
        "Chaoyang"
    ],
    "name:nor_x_preferred":[
        "Chaoyang"
    ],
    "name:pol_x_preferred":[
        "Chaoyang"
    ],
    "name:rus_x_preferred":[
        "\u0427\u0430\u043e\u044f\u043d"
    ],
    "name:spa_x_preferred":[
        "Chaoyang"
    ],
    "name:swe_x_preferred":[
        "Chaoyang"
    ],
    "name:tur_x_preferred":[
        "Chaoyang"
    ],
    "name:unk_x_variant":[
        "Huinan"
    ],
    "name:zho_x_preferred":[
        "Ch\u2019ao-yang-chen"
    ],
    "name:zho_x_variant":[
        "Ch\u2019ao-yang-shen",
        "\u671d\u9633"
    ],
    "qs:name":"Chaoyang",
    "qs:photos_9r":0,
    "qs:photos_sr":0,
    "qs:pop_sr":"8",
    "wd:wordcount":95,
    "wof:name":"Chaoyang",
    "wof:placetype":"locality",
    "wof:population":75347
},
  "geometry": {"coordinates":[126.02630000000001,42.66223],"type":"Point"}
}