{
  "type": "Feature",
  "properties": {
    "gn:admin1_code":"26.0",
    "gn:asciiname":"Yangwacun",
    "gn:country_code":"CN",
    "gn:dem":981,
    "gn:feature_class":"P",
    "gn:feature_code":"PPL",
    "gn:name":"Yangwacun",
    "gn:population":0,
    "gn:timezone":"Asia/Shanghai",
    "iso:country":"CN",
    "name:zho_x_preferred":[
        "\u9633\u6d3c\u6751"
    ],
    "wof:name":"Yangwacun",
    "wof:placetype":"locality"
},
  "geometry": {"coordinates":[109.62291999999999,36.65526],"type":"Point"}
}