{
  "type": "Feature",
  "properties": {
    "gn:admin1_code":"15.0",
    "gn:asciiname":"Zhanglianzhuang",
    "gn:country_code":"CN",
    "gn:dem":2689,
    "gn:feature_class":"P",
    "gn:feature_code":"PPL",
    "gn:name":"Zhanglianzhuang",
    "gn:population":0,
    "gn:timezone":"Asia/Shanghai",
    "iso:country":"CN",
    "name:zho_x_preferred":[
        "\u5f20\u8fde\u5e84"
    ],
    "wof:name":"Zhanglianzhuang",
    "wof:placetype":"locality"
},
  "geometry": {"coordinates":[100.901,38.2774],"type":"Point"}
}