{
  "type": "Feature",
  "properties": {
    "gn:admin1_code":"26.0",
    "gn:asciiname":"Dongjiajiawan",
    "gn:country_code":"CN",
    "gn:dem":989,
    "gn:feature_class":"P",
    "gn:feature_code":"PPL",
    "gn:name":"Dongjiajiawan",
    "gn:population":0,
    "gn:timezone":"Asia/Shanghai",
    "iso:country":"CN",
    "name:zho_x_preferred":[
        "\u4e1c\u8d3e\u5bb6\u6e7e"
    ],
    "wof:name":"Dongjiajiawan",
    "wof:placetype":"locality"
},
  "geometry": {"coordinates":[111.09228,39.3216],"type":"Point"}
}