{
  "type": "Feature",
  "properties": {
    "gn:admin1_code":"26.0",
    "gn:asciiname":"Daochen Xicun",
    "gn:country_code":"CN",
    "gn:dem":785,
    "gn:feature_class":"P",
    "gn:feature_code":"PPL",
    "gn:name":"Daochen Xicun",
    "gn:population":0,
    "gn:timezone":"Asia/Shanghai",
    "iso:country":"CN",
    "name:und_x_variant":[
        "Daochencun",
        "Daochen"
    ],
    "name:zho_x_preferred":[
        "\u5200\u9648\u897f\u6751"
    ],
    "name:zho_x_variant":[
        "\u5200\u9648"
    ],
    "wof:name":"Daochen Xicun",
    "wof:placetype":"locality"
},
  "geometry": {"coordinates":[108.33946,34.5966],"type":"Point"}
}