{
  "type": "Feature",
  "properties": {
    "gn:admin1_code":"11",
    "gn:asciiname":"Reshi",
    "gn:country_code":"CN",
    "gn:dem":94,
    "gn:feature_class":"P",
    "gn:feature_code":"PPLA4",
    "gn:name":"Reshi",
    "gn:population":0,
    "gn:timezone":"Asia/Shanghai",
    "iso:country":"CN",
    "name:und_x_variant":[
        "Je-Shih",
        "Reshi",
        "\u70ed\u5e02",
        "Reshuikeng",
        "Reshi Zhen",
        "\u70ed\u5e02\u9547",
        "\u70ed\u6c34\u5751"
    ],
    "wof:name":"Reshi",
    "wof:placetype":"locality"
},
  "geometry": {"coordinates":[111.32248,29.32137],"type":"Point"}
}