{
  "type": "Feature",
  "properties": {
    "gn:admin1_code":"2.0",
    "gn:asciiname":"Shijiaokeng",
    "gn:country_code":"CN",
    "gn:dem":304,
    "gn:feature_class":"P",
    "gn:feature_code":"PPL",
    "gn:name":"Shijiaokeng",
    "gn:population":0,
    "gn:timezone":"Asia/Shanghai",
    "iso:country":"CN",
    "name:und_x_variant":[
        "\u77f3\u89d2\u5751"
    ],
    "wof:name":"Shijiaokeng",
    "wof:placetype":"locality"
},
  "geometry": {"coordinates":[119.56158000000001,29.97875],"type":"Point"}
}