{
  "type": "Feature",
  "properties": {
    "gn:admin1_code":"25",
    "gn:asciiname":"Nangongzhuang",
    "gn:country_code":"CN",
    "gn:dem":23,
    "gn:feature_class":"P",
    "gn:feature_code":"PPL",
    "gn:name":"Nangongzhuang",
    "gn:population":0,
    "gn:timezone":"Asia/Shanghai",
    "iso:country":"CN",
    "name:zho_x_preferred":[
        "\u5357\u5bab\u5e84"
    ],
    "wof:name":"Nangongzhuang",
    "wof:placetype":"locality"
},
  "geometry": {"coordinates":[116.492,37.1287],"type":"Point"}
}