{
  "type": "Feature",
  "properties": {
    "gn:admin1_code":"19.0",
    "gn:asciiname":"Gongtun",
    "gn:country_code":"CN",
    "gn:dem":10,
    "gn:feature_class":"P",
    "gn:feature_code":"PPL",
    "gn:name":"Gongtun",
    "gn:population":0,
    "gn:timezone":"Asia/Shanghai",
    "iso:country":"CN",
    "name:zho_x_preferred":[
        "\u8d21\u5c6f"
    ],
    "wof:name":"Gongtun",
    "wof:placetype":"locality"
},
  "geometry": {"coordinates":[120.92552999999999,40.80617],"type":"Point"}
}