{
  "type": "Feature",
  "properties": {
    "gn:admin1_code":"33",
    "gn:asciiname":"Shantuo",
    "gn:country_code":"CN",
    "gn:dem":196,
    "gn:feature_class":"P",
    "gn:feature_code":"PPL",
    "gn:name":"Shantuo",
    "gn:population":0,
    "gn:timezone":"Asia/Shanghai",
    "iso:country":"CN",
    "name:und_x_variant":[
        "Shan-t\u2019o-ch\u2019ang",
        "Shang-t\u2019o-ch\u2019ang",
        "Shan-t\u2019o",
        "Shantuo"
    ],
    "name:zho_x_preferred":[
        "\u6247\u6cb1"
    ],
    "wof:name":"Shantuo",
    "wof:placetype":"locality"
},
  "geometry": {"coordinates":[106.99500999999999,29.76875],"type":"Point"}
}