{
  "type": "Feature",
  "properties": {
    "gn:admin1_code":"24",
    "gn:asciiname":"Duanjia",
    "gn:cc2":"CN",
    "gn:country_code":"CN",
    "gn:dem":1547,
    "gn:feature_class":"P",
    "gn:feature_code":"PPL",
    "gn:name":"Duanjia",
    "gn:population":0,
    "gn:timezone":"Asia/Shanghai",
    "iso:country":"CN",
    "name:und_x_variant":[
        "Tuan-chia",
        "Tuan-chia-ling",
        "Duanjia"
    ],
    "wof:name":"Duanjia",
    "wof:placetype":"locality"
},
  "geometry": {"coordinates":[112.34166999999999,38.95556],"type":"Point"}
}