{
  "type": "Feature",
  "properties": {
    "gn:admin1_code":"6.0",
    "gn:asciiname":"Yuangao",
    "gn:country_code":"CN",
    "gn:dem":3673,
    "gn:feature_class":"P",
    "gn:feature_code":"PPL",
    "gn:name":"Yuangao",
    "gn:population":0,
    "gn:timezone":"Asia/Urumqi",
    "iso:country":"CN",
    "name:zho_x_preferred":[
        "\u8fdc\u9ad8"
    ],
    "wof:name":"Yuangao",
    "wof:placetype":"locality"
},
  "geometry": {"coordinates":[96.53277,32.17224],"type":"Point"}
}