{
  "type": "Feature",
  "properties": {
    "gn:admin1_code":"18",
    "gn:asciiname":"Yuechitou",
    "gn:country_code":"CN",
    "gn:dem":1519,
    "gn:feature_class":"P",
    "gn:feature_code":"PPL",
    "gn:name":"Yuechitou",
    "gn:population":0,
    "gn:timezone":"Asia/Shanghai",
    "iso:country":"CN",
    "name:zho_x_preferred":[
        "\u94a5\u5319\u5934"
    ],
    "wof:name":"Yuechitou",
    "wof:placetype":"locality"
},
  "geometry": {"coordinates":[104.825,25.0875],"type":"Point"}
}