{
  "type": "Feature",
  "properties": {
    "gn:admin1_code":"32.0",
    "gn:asciiname":"Shengliping",
    "gn:country_code":"CN",
    "gn:dem":2276,
    "gn:feature_class":"P",
    "gn:feature_code":"PPL",
    "gn:name":"Shengliping",
    "gn:population":0,
    "gn:timezone":"Asia/Shanghai",
    "iso:country":"CN",
    "name:zho_x_preferred":[
        "\u80dc\u5229\u576a"
    ],
    "wof:name":"Shengliping",
    "wof:placetype":"locality"
},
  "geometry": {"coordinates":[103.05002,28.73694],"type":"Point"}
}