{
  "type": "Feature",
  "properties": {
    "gn:admin1_code":"29.0",
    "gn:asciiname":"Huafang",
    "gn:country_code":"CN",
    "gn:dem":2096,
    "gn:feature_class":"P",
    "gn:feature_code":"PPL",
    "gn:name":"Huafang",
    "gn:population":0,
    "gn:timezone":"Asia/Shanghai",
    "iso:country":"CN",
    "name:und_x_variant":[
        "\u82b1\u623f"
    ],
    "wof:name":"Huafang",
    "wof:placetype":"locality"
},
  "geometry": {"coordinates":[103.426,26.7897],"type":"Point"}
}