{
  "type": "Feature",
  "properties": {
    "gn:admin1_code":"29.0",
    "gn:asciiname":"Zhangdaoshan",
    "gn:country_code":"CN",
    "gn:dem":2101,
    "gn:feature_class":"P",
    "gn:feature_code":"PPL",
    "gn:name":"Zhangdaoshan",
    "gn:population":0,
    "gn:timezone":"Asia/Shanghai",
    "iso:country":"CN",
    "name:zho_x_preferred":[
        "\u5f20\u5230\u5c71"
    ],
    "wof:name":"Zhangdaoshan",
    "wof:placetype":"locality"
},
  "geometry": {"coordinates":[100.408,24.24],"type":"Point"}
}