{
  "type": "Feature",
  "properties": {
    "gn:admin1_code":"6.0",
    "gn:asciiname":"Yangrika",
    "gn:country_code":"CN",
    "gn:dem":3823,
    "gn:feature_class":"P",
    "gn:feature_code":"PPL",
    "gn:name":"Yangrika",
    "gn:population":0,
    "gn:timezone":"Asia/Urumqi",
    "iso:country":"CN",
    "name:zho_x_preferred":[
        "\u7f8a\u65e5\u5361"
    ],
    "wof:name":"Yangrika",
    "wof:placetype":"locality"
},
  "geometry": {"coordinates":[96.8028,32.43945],"type":"Point"}
}