{
  "type": "Feature",
  "properties": {
    "gn:admin1_code":"24.0",
    "gn:asciiname":"Yaotoucun",
    "gn:country_code":"CN",
    "gn:dem":1018,
    "gn:feature_class":"P",
    "gn:feature_code":"PPL",
    "gn:name":"Yaotoucun",
    "gn:population":0,
    "gn:timezone":"Asia/Shanghai",
    "iso:country":"CN",
    "name:und_x_variant":[
        "Yao-t\u2019ou-ts\u2019un",
        "Yaotou",
        "Yaotoucun"
    ],
    "name:zho_x_preferred":[
        "\u7a91\u5934\u6751"
    ],
    "wof:name":"Yaotoucun",
    "wof:placetype":"locality"
},
  "geometry": {"coordinates":[110.79088,36.26427],"type":"Point"}
}