{
  "type": "Feature",
  "properties": {
    "gn:admin1_code":"25",
    "gn:asciiname":"Laowa",
    "gn:country_code":"CN",
    "gn:dem":379,
    "gn:feature_class":"P",
    "gn:feature_code":"PPL",
    "gn:name":"Laowa",
    "gn:population":0,
    "gn:timezone":"Asia/Shanghai",
    "iso:country":"CN",
    "name:zho_x_preferred":[
        "\u6d9d\u6d3c"
    ],
    "wof:name":"Laowa",
    "wof:placetype":"locality"
},
  "geometry": {"coordinates":[117.97499999999999,36.5086],"type":"Point"}
}