{
  "type": "Feature",
  "properties": {
    "gn:admin1_code":"30",
    "gn:asciiname":"Xinwuzai",
    "gn:country_code":"CN",
    "gn:dem":12,
    "gn:feature_class":"P",
    "gn:feature_code":"PPL",
    "gn:name":"Xinwuzai",
    "gn:population":0,
    "gn:timezone":"Asia/Urumqi",
    "iso:country":"CN",
    "name:zho_x_preferred":[
        "\u65b0\u5c4b\u4ed4"
    ],
    "wof:name":"Xinwuzai",
    "wof:placetype":"locality"
},
  "geometry": {"coordinates":[110.94428000000001,21.55782],"type":"Point"}
}