{
  "type": "Feature",
  "properties": {
    "gn:admin1_code":"12.0",
    "gn:asciiname":"Dawu",
    "gn:country_code":"CN",
    "gn:dem":227,
    "gn:feature_class":"P",
    "gn:feature_code":"PPL",
    "gn:name":"Dawu",
    "gn:population":0,
    "gn:timezone":"Asia/Shanghai",
    "iso:country":"CN",
    "name:zho_x_preferred":[
        "Dawu"
    ],
    "name:zho_x_variant":[
        "\u5927\u5c4b"
    ],
    "wof:name":"Dawu",
    "wof:placetype":"locality"
},
  "geometry": {"coordinates":[114.92865999999999,29.55114],"type":"Point"}
}