{
  "type": "Feature",
  "properties": {
    "gn:admin1_code":"29.0",
    "gn:asciiname":"Keluopu",
    "gn:country_code":"CN",
    "gn:dem":1485,
    "gn:feature_class":"P",
    "gn:feature_code":"PPL",
    "gn:name":"Keluopu",
    "gn:population":0,
    "gn:timezone":"Asia/Shanghai",
    "iso:country":"CN",
    "name:zho_x_preferred":[
        "\u514b\u6d1b\u57d4"
    ],
    "wof:name":"Keluopu",
    "wof:placetype":"locality"
},
  "geometry": {"coordinates":[101.67700000000001,23.5326],"type":"Point"}
}