{
  "type": "Feature",
  "properties": {
    "iso:country":"CN",
    "name:eng_x_preferred":[
        "Chuxiong"
    ],
    "name:zho_x_preferred":[
        "\u695a\u96c4\u5e02"
    ],
    "qs:name":"\u695a\u96c4\u5e02",
    "qs:name_adm0":"\u4e2d\u570b",
    "qs:name_adm1":"\u4e91\u5357\u7701",
    "qs:photos":1,
    "qs:photos_1k":1,
    "qs:photos_9k":1,
    "qs:photos_9r":2,
    "qs:photos_all":58,
    "qs:photos_sr":1,
    "qs:placetype":"LocalAdmin",
    "qs:pop_sr":"0",
    "wof:name":"Chuxiong",
    "wof:placetype":"localadmin"
},
  "geometry": {"coordinates":[101.54113700000001,25.04237],"type":"Point"}
}