{
  "type": "Feature",
  "properties": {
    "gn:admin1_code":"19.0",
    "gn:asciiname":"Qiangzilingcun",
    "gn:country_code":"CN",
    "gn:dem":647,
    "gn:feature_class":"P",
    "gn:feature_code":"PPL",
    "gn:name":"Qiangzilingcun",
    "gn:population":0,
    "gn:timezone":"Asia/Shanghai",
    "iso:country":"CN",
    "name:zho_x_preferred":[
        "\u5899\u5b50\u5cad\u6751"
    ],
    "wof:name":"Qiangzilingcun",
    "wof:placetype":"locality"
},
  "geometry": {"coordinates":[119.705,40.48],"type":"Point"}
}