{
  "type": "Feature",
  "properties": {
    "gn:admin1_code":"16.0",
    "gn:asciiname":"Huishuang",
    "gn:country_code":"CN",
    "gn:dem":339,
    "gn:feature_class":"P",
    "gn:feature_code":"PPL",
    "gn:name":"Huishuang",
    "gn:population":0,
    "gn:timezone":"Asia/Shanghai",
    "iso:country":"CN",
    "name:zho_x_preferred":[
        "\u4f1a\u53cc"
    ],
    "wof:name":"Huishuang",
    "wof:placetype":"locality"
},
  "geometry": {"coordinates":[108.40900000000001,23.8078],"type":"Point"}
}