{
  "type": "Feature",
  "properties": {
    "gn:admin1_code":"16.0",
    "gn:asciiname":"Junziling",
    "gn:country_code":"CN",
    "gn:dem":62,
    "gn:feature_class":"P",
    "gn:feature_code":"PPL",
    "gn:name":"Junziling",
    "gn:population":0,
    "gn:timezone":"Asia/Shanghai",
    "iso:country":"CN",
    "name:zho_x_preferred":[
        "\u541b\u5b50\u5cad"
    ],
    "wof:name":"Junziling",
    "wof:placetype":"locality"
},
  "geometry": {"coordinates":[109.73099999999999,22.9063],"type":"Point"}
}