{
  "type": "Feature",
  "properties": {
    "gn:admin1_code":"18",
    "gn:asciiname":"Waitoupo",
    "gn:country_code":"CN",
    "gn:dem":1261,
    "gn:feature_class":"P",
    "gn:feature_code":"PPL",
    "gn:name":"Waitoupo",
    "gn:population":0,
    "gn:timezone":"Asia/Shanghai",
    "iso:country":"CN",
    "name:zho_x_preferred":[
        "\u6b6a\u5934\u5761"
    ],
    "wof:name":"Waitoupo",
    "wof:placetype":"locality"
},
  "geometry": {"coordinates":[106.279,26.698],"type":"Point"}
}