{
  "type": "Feature",
  "properties": {
    "gn:admin1_code":"23.0",
    "gn:asciiname":"Zhuqiao",
    "gn:country_code":"CN",
    "gn:dem":4,
    "gn:feature_class":"P",
    "gn:feature_code":"PPL",
    "gn:name":"Zhuqiao",
    "gn:population":0,
    "gn:timezone":"Asia/Shanghai",
    "iso:country":"CN",
    "name:und_x_variant":[
        "\u6d19\u6865"
    ],
    "wof:name":"Zhuqiao",
    "wof:placetype":"locality"
},
  "geometry": {"coordinates":[121.10787999999999,30.96738],"type":"Point"}
}