{
  "type": "Feature",
  "properties": {
    "gn:admin1_code":"32.0",
    "gn:asciiname":"Shuangjingwan",
    "gn:country_code":"CN",
    "gn:dem":559,
    "gn:feature_class":"P",
    "gn:feature_code":"PPL",
    "gn:name":"Shuangjingwan",
    "gn:population":0,
    "gn:timezone":"Asia/Shanghai",
    "iso:country":"CN",
    "name:zho_x_preferred":[
        "\u53cc\u4e95\u6e7e"
    ],
    "wof:name":"Shuangjingwan",
    "wof:placetype":"locality"
},
  "geometry": {"coordinates":[106.955,31.1702],"type":"Point"}
}