{
  "type": "Feature",
  "properties": {
    "gn:admin1_code":"9.0",
    "gn:asciiname":"Liqu",
    "gn:country_code":"CN",
    "gn:dem":239,
    "gn:feature_class":"P",
    "gn:feature_code":"PPL",
    "gn:name":"Liqu",
    "gn:population":0,
    "gn:timezone":"Asia/Shanghai",
    "iso:country":"CN",
    "name:zho_x_preferred":[
        "\u793c\u6e20"
    ],
    "wof:name":"Liqu",
    "wof:placetype":"locality"
},
  "geometry": {"coordinates":[112.00675,34.49624],"type":"Point"}
}