{
  "type": "Feature",
  "properties": {
    "gn:admin1_code":"32.0",
    "gn:asciiname":"Huangguazui",
    "gn:country_code":"CN",
    "gn:dem":628,
    "gn:feature_class":"P",
    "gn:feature_code":"PPL",
    "gn:name":"Huangguazui",
    "gn:population":0,
    "gn:timezone":"Asia/Shanghai",
    "iso:country":"CN",
    "name:zho_x_preferred":[
        "\u9ec4\u74dc\u5480"
    ],
    "wof:name":"Huangguazui",
    "wof:placetype":"locality"
},
  "geometry": {"coordinates":[104.96299999999999,31.8488],"type":"Point"}
}