{
  "type": "Feature",
  "properties": {
    "gn:admin1_code":"20.0",
    "gn:asciiname":"Zuoshantun",
    "gn:country_code":"CN",
    "gn:dem":292,
    "gn:feature_class":"P",
    "gn:feature_code":"PPL",
    "gn:name":"Zuoshantun",
    "gn:population":0,
    "gn:timezone":"Asia/Shanghai",
    "iso:country":"CN",
    "name:zho_x_preferred":[
        "\u67de\u5c71\u5c6f"
    ],
    "wof:name":"Zuoshantun",
    "wof:placetype":"locality"
},
  "geometry": {"coordinates":[124.96241999999999,50.06348],"type":"Point"}
}