{
  "type": "Feature",
  "properties": {
    "gn:admin1_code":"18",
    "gn:asciiname":"Tuanyan",
    "gn:country_code":"CN",
    "gn:dem":819,
    "gn:feature_class":"P",
    "gn:feature_code":"PPL",
    "gn:name":"Tuanyan",
    "gn:population":0,
    "gn:timezone":"Asia/Shanghai",
    "iso:country":"CN",
    "name:zho_x_preferred":[
        "\u56e2\u5ca9"
    ],
    "wof:name":"Tuanyan",
    "wof:placetype":"locality"
},
  "geometry": {"coordinates":[108.15000000000001,27.2886],"type":"Point"}
}