{
  "type": "Feature",
  "properties": {
    "gn:admin1_code":"5.0",
    "gn:asciiname":"Qingduizi",
    "gn:country_code":"CN",
    "gn:dem":209,
    "gn:feature_class":"P",
    "gn:feature_code":"PPL",
    "gn:name":"Qingduizi",
    "gn:population":0,
    "gn:timezone":"Asia/Shanghai",
    "iso:country":"CN",
    "name:zho_x_preferred":[
        "\u9752\u5806\u5b50"
    ],
    "wof:name":"Qingduizi",
    "wof:placetype":"locality"
},
  "geometry": {"coordinates":[124.55065999999999,43.42142],"type":"Point"}
}