{
  "type": "Feature",
  "properties": {
    "gn:admin1_code":"3.0",
    "gn:asciiname":"Wushijie",
    "gn:cc2":"CN",
    "gn:country_code":"CN",
    "gn:dem":77,
    "gn:feature_class":"P",
    "gn:feature_code":"PPL",
    "gn:name":"Wushijie",
    "gn:population":0,
    "gn:timezone":"Asia/Shanghai",
    "iso:country":"CN",
    "name:und_x_variant":[
        "Wu-shih-chieh",
        "Wushijie"
    ],
    "wof:name":"Wushijie",
    "wof:placetype":"locality"
},
  "geometry": {"coordinates":[115.55,29.65],"type":"Point"}
}