{
  "type": "Feature",
  "properties": {
    "gn:admin1_code":"8.0",
    "gn:asciiname":"Sanyongcun",
    "gn:country_code":"CN",
    "gn:dem":144,
    "gn:feature_class":"P",
    "gn:feature_code":"PPL",
    "gn:name":"Sanyongcun",
    "gn:population":0,
    "gn:timezone":"Asia/Shanghai",
    "iso:country":"CN",
    "name:zho_x_preferred":[
        "\u4e09\u6c38\u6751"
    ],
    "wof:name":"Sanyongcun",
    "wof:placetype":"locality"
},
  "geometry": {"coordinates":[125.12414,46.57413],"type":"Point"}
}