{
  "type": "Feature",
  "properties": {
    "gn:admin1_code":"16",
    "gn:asciiname":"Weiguo",
    "gn:country_code":"CN",
    "gn:dem":184,
    "gn:feature_class":"P",
    "gn:feature_code":"PPL",
    "gn:name":"Weiguo",
    "gn:population":0,
    "gn:timezone":"Asia/Shanghai",
    "iso:country":"CN",
    "name:und_x_variant":[
        "Wei-kuo-ts\u2019un",
        "Weiguo"
    ],
    "name:zho_x_preferred":[
        "\u536b\u56fd"
    ],
    "wof:name":"Weiguo",
    "wof:placetype":"locality"
},
  "geometry": {"coordinates":[106.997,22.5421],"type":"Point"}
}