{
  "type": "Feature",
  "properties": {
    "gn:admin1_code":"1.0",
    "gn:asciiname":"Huangzhuangcun",
    "gn:country_code":"CN",
    "gn:dem":36,
    "gn:feature_class":"P",
    "gn:feature_code":"PPL",
    "gn:name":"Huangzhuangcun",
    "gn:population":0,
    "gn:timezone":"Asia/Shanghai",
    "iso:country":"CN",
    "name:zho_x_preferred":[
        "\u9ec4\u5e84\u6751"
    ],
    "wof:name":"Huangzhuangcun",
    "wof:placetype":"locality"
},
  "geometry": {"coordinates":[115.98542999999999,33.74373],"type":"Point"}
}