{
  "type": "Feature",
  "properties": {
    "gn:admin1_code":"32.0",
    "gn:asciiname":"Zhuqing",
    "gn:country_code":"CN",
    "gn:dem":1734,
    "gn:feature_class":"P",
    "gn:feature_code":"PPL",
    "gn:name":"Zhuqing",
    "gn:population":0,
    "gn:timezone":"Asia/Shanghai",
    "iso:country":"CN",
    "name:zho_x_preferred":[
        "\u7af9\u7b90"
    ],
    "wof:name":"Zhuqing",
    "wof:placetype":"locality"
},
  "geometry": {"coordinates":[102.36372,26.35254],"type":"Point"}
}