{
  "type": "Feature",
  "properties": {
    "gn:admin1_code":"24.0",
    "gn:asciiname":"Wazhaping",
    "gn:country_code":"CN",
    "gn:dem":1239,
    "gn:feature_class":"P",
    "gn:feature_code":"PPL",
    "gn:name":"Wazhaping",
    "gn:population":0,
    "gn:timezone":"Asia/Shanghai",
    "iso:country":"CN",
    "name:zho_x_preferred":[
        "\u74e6\u624e\u576a"
    ],
    "wof:name":"Wazhaping",
    "wof:placetype":"locality"
},
  "geometry": {"coordinates":[113.1431,38.50823],"type":"Point"}
}