{
  "type": "Feature",
  "properties": {
    "gn:admin1_code":"9.0",
    "gn:asciiname":"Tiancicheng",
    "gn:country_code":"CN",
    "gn:dem":50,
    "gn:feature_class":"P",
    "gn:feature_code":"PPL",
    "gn:name":"Tiancicheng",
    "gn:population":0,
    "gn:timezone":"Asia/Shanghai",
    "iso:country":"CN",
    "name:zho_x_preferred":[
        "\u5929\u8d50\u57ce"
    ],
    "wof:name":"Tiancicheng",
    "wof:placetype":"locality"
},
  "geometry": {"coordinates":[114.97237,32.0206],"type":"Point"}
}