{
  "type": "Feature",
  "properties": {
    "gn:admin1_code":"8.0",
    "gn:asciiname":"Baidifangzi",
    "gn:country_code":"CN",
    "gn:dem":139,
    "gn:feature_class":"P",
    "gn:feature_code":"PPL",
    "gn:name":"Baidifangzi",
    "gn:population":0,
    "gn:timezone":"Asia/Shanghai",
    "iso:country":"CN",
    "name:zho_x_preferred":[
        "\u767d\u5730\u623f\u5b50"
    ],
    "wof:name":"Baidifangzi",
    "wof:placetype":"locality"
},
  "geometry": {"coordinates":[124.30943000000001,46.88726],"type":"Point"}
}