{
  "type": "Feature",
  "properties": {
    "gn:admin1_code":"20.0",
    "gn:asciiname":"Wunegetu",
    "gn:country_code":"CN",
    "gn:dem":757,
    "gn:feature_class":"P",
    "gn:feature_code":"PPL",
    "gn:name":"Wunegetu",
    "gn:population":0,
    "gn:timezone":"Asia/Shanghai",
    "iso:country":"CN",
    "name:zho_x_preferred":[
        "\u4e4c\u8bb7\u683c\u56fe"
    ],
    "wof:name":"Wunegetu",
    "wof:placetype":"locality"
},
  "geometry": {"coordinates":[117.26488000000001,49.43235],"type":"Point"}
}