{
  "type": "Feature",
  "properties": {
    "gn:admin1_code":"24",
    "gn:asciiname":"Shangguan",
    "gn:country_code":"CN",
    "gn:dem":878,
    "gn:feature_class":"P",
    "gn:feature_code":"PPLA3",
    "gn:name":"Shangguan",
    "gn:population":0,
    "gn:timezone":"Asia/Shanghai",
    "iso:country":"CN",
    "name:deu_x_preferred":[
        "Shangguan"
    ],
    "name:und_x_variant":[
        "Tai",
        "Tai-hsien",
        "Taichow",
        "Daixian",
        "Dai Xian",
        "Shangguan Zhen",
        "\u4ee3\u53bf",
        "\u4e0a\u9986\u9547"
    ],
    "name:zho_x_preferred":[
        "Tai-hsien-ch\u2019eng"
    ],
    "name:zho_x_variant":[
        "Tai-ch\u2019eng",
        "Daysyan\u2019"
    ],
    "wof:name":"Shangguan",
    "wof:placetype":"locality"
},
  "geometry": {"coordinates":[112.92913,39.06901],"type":"Point"}
}