{
  "type": "Feature",
  "properties": {
    "gn:admin1_code":"12",
    "gn:asciiname":"Sanlifan",
    "gn:country_code":"CN",
    "gn:dem":57,
    "gn:feature_class":"P",
    "gn:feature_code":"PPLA4",
    "gn:name":"Sanlifan",
    "gn:population":0,
    "gn:timezone":"Asia/Shanghai",
    "iso:country":"CN",
    "name:und_x_variant":[
        "\u4e09\u91cc\u7548",
        "Sanlifan Zhen",
        "\u4e09\u91cc\u7548\u9547"
    ],
    "wof:name":"Sanlifan",
    "wof:placetype":"locality"
},
  "geometry": {"coordinates":[115.26658999999999,30.83553],"type":"Point"}
}