{
  "type": "Feature",
  "properties": {
    "gn:admin1_code":"12.0",
    "gn:asciiname":"Watanggang",
    "gn:country_code":"CN",
    "gn:dem":469,
    "gn:feature_class":"P",
    "gn:feature_code":"PPL",
    "gn:name":"Watanggang",
    "gn:population":0,
    "gn:timezone":"Asia/Shanghai",
    "iso:country":"CN",
    "name:zho_x_preferred":[
        "\u6316\u5858\u5c97"
    ],
    "wof:name":"Watanggang",
    "wof:placetype":"locality"
},
  "geometry": {"coordinates":[110.87223,32.71029],"type":"Point"}
}