{
  "type": "Feature",
  "properties": {
    "gn:admin1_code":"2.0",
    "gn:asciiname":"Fangjiawu",
    "gn:country_code":"CN",
    "gn:dem":213,
    "gn:feature_class":"P",
    "gn:feature_code":"PPL",
    "gn:name":"Fangjiawu",
    "gn:population":0,
    "gn:timezone":"Asia/Shanghai",
    "iso:country":"CN",
    "name:und_x_variant":[
        "\u65b9\u5bb6\u575e"
    ],
    "wof:name":"Fangjiawu",
    "wof:placetype":"locality"
},
  "geometry": {"coordinates":[119.41498,30.28312],"type":"Point"}
}