{
  "type": "Feature",
  "properties": {
    "gn:admin1_code":"23",
    "gn:asciiname":"Bangzhen",
    "gn:country_code":"CN",
    "gn:dem":4,
    "gn:feature_class":"P",
    "gn:feature_code":"PPL",
    "gn:name":"Bangzhen",
    "gn:population":0,
    "gn:timezone":"Asia/Shanghai",
    "iso:country":"CN",
    "name:und_x_variant":[
        "Pin-chen",
        "Peng-chen",
        "Pang-chen",
        "Bangzhen",
        "\u6d5c\u9547"
    ],
    "wof:name":"Bangzhen",
    "wof:placetype":"locality"
},
  "geometry": {"coordinates":[121.48644,31.65071],"type":"Point"}
}