{
  "type": "Feature",
  "properties": {
    "gn:admin1_code":"14",
    "gn:asciiname":"Nongfeng",
    "gn:country_code":"CN",
    "gn:dem":4537,
    "gn:feature_class":"P",
    "gn:feature_code":"PPL",
    "gn:name":"Nongfeng",
    "gn:population":0,
    "gn:timezone":"Asia/Urumqi",
    "iso:country":"CN",
    "name:zho_x_preferred":[
        "\u5f04\u5cf0"
    ],
    "wof:name":"Nongfeng",
    "wof:placetype":"locality"
},
  "geometry": {"coordinates":[88.4667,29.527],"type":"Point"}
}