{
  "type": "Feature",
  "properties": {
    "gn:admin1_code":"9",
    "gn:asciiname":"Goutouzhangzhuang",
    "gn:country_code":"CN",
    "gn:dem":50,
    "gn:feature_class":"P",
    "gn:feature_code":"PPL",
    "gn:name":"Goutouzhangzhuang",
    "gn:population":0,
    "gn:timezone":"Asia/Shanghai",
    "iso:country":"CN",
    "name:zho_x_preferred":[
        "\u6c9f\u5934\u5f20\u5e84"
    ],
    "wof:name":"Goutouzhangzhuang",
    "wof:placetype":"locality"
},
  "geometry": {"coordinates":[115.83,34.4854],"type":"Point"}
}