{
  "type": "Feature",
  "properties": {
    "gn:admin1_code":"7.0",
    "gn:asciiname":"Jiaokeng",
    "gn:country_code":"CN",
    "gn:dem":372,
    "gn:feature_class":"P",
    "gn:feature_code":"PPL",
    "gn:name":"Jiaokeng",
    "gn:population":0,
    "gn:timezone":"Asia/Shanghai",
    "iso:country":"CN",
    "name:und_x_variant":[
        "\u8549\u5751"
    ],
    "name:zho_x_preferred":[
        "\u8549\u5751"
    ],
    "wof:name":"Jiaokeng",
    "wof:placetype":"locality"
},
  "geometry": {"coordinates":[118.18953999999999,26.27164],"type":"Point"}
}