{
  "type": "Feature",
  "properties": {
    "gn:admin1_code":"32.0",
    "gn:asciiname":"Er'erwatuo",
    "gn:country_code":"CN",
    "gn:dem":2167,
    "gn:feature_class":"P",
    "gn:feature_code":"PPL",
    "gn:name":"Er\u2019erwatuo",
    "gn:population":0,
    "gn:timezone":"Asia/Shanghai",
    "iso:country":"CN",
    "name:und_x_variant":[
        "Er\u2019erwatuo"
    ],
    "name:zho_x_preferred":[
        "\u4fc4\u5c14\u6d3c\u59a5"
    ],
    "wof:name":"Er'erwatuo",
    "wof:placetype":"locality"
},
  "geometry": {"coordinates":[102.86799999999999,28.0086],"type":"Point"}
}