{
  "type": "Feature",
  "properties": {
    "gn:admin1_code":"7",
    "gn:asciiname":"Chatou",
    "gn:country_code":"CN",
    "gn:dem":1068,
    "gn:feature_class":"P",
    "gn:feature_code":"PPL",
    "gn:name":"Chatou",
    "gn:population":0,
    "gn:timezone":"Asia/Shanghai",
    "iso:country":"CN",
    "name:und_x_variant":[
        "\u5c94\u5934"
    ],
    "wof:name":"Chatou",
    "wof:placetype":"locality"
},
  "geometry": {"coordinates":[119.20972,27.21139],"type":"Point"}
}