{
  "type": "Feature",
  "properties": {
    "gn:admin1_code":"7",
    "gn:asciiname":"Chatou",
    "gn:country_code":"CN",
    "gn:dem":1068,
    "gn:feature_class":"P",
    "gn:feature_code":"PPL",
    "gn:name":"Chatou",
    "gn:population":0,
    "gn:timezone":"Asia/Shanghai",
    "iso:country":"CN",
    "name:azb_x_preferred":[
        "\u0634\u062a\u0648"
    ],
    "name:bug_x_preferred":[
        "Chatou"
    ],
    "name:cat_x_preferred":[
        "Chatou"
    ],
    "name:ceb_x_preferred":[
        "Chatou"
    ],
    "name:ces_x_preferred":[
        "Chatou"
    ],
    "name:deu_x_preferred":[
        "Chatou"
    ],
    "name:epo_x_preferred":[
        "Chatou"
    ],
    "name:eus_x_preferred":[
        "Chatou"
    ],
    "name:fas_x_preferred":[
        "\u0634\u062a\u0648"
    ],
    "name:fin_x_preferred":[
        "Chatou"
    ],
    "name:fra_x_preferred":[
        "Chatou"
    ],
    "name:hun_x_preferred":[
        "Chatou"
    ],
    "name:ind_x_preferred":[
        "Chatou"
    ],
    "name:ita_x_preferred":[
        "Chatou"
    ],
    "name:jpn_x_preferred":[
        "\u30b7\u30e3\u30c8\u30a5\u30fc"
    ],
    "name:kaz_x_preferred":[
        "\u0428\u0430\u0442\u0443"
    ],
    "name:lat_x_preferred":[
        "Chatou"
    ],
    "name:msa_x_preferred":[
        "Chatou"
    ],
    "name:mzn_x_preferred":[
        "\u0634\u062a\u0648"
    ],
    "name:nld_x_preferred":[
        "Chatou"
    ],
    "name:nor_x_preferred":[
        "Chatou"
    ],
    "name:oci_x_preferred":[
        "Chatou"
    ],
    "name:pms_x_preferred":[
        "Chatou"
    ],
    "name:pol_x_preferred":[
        "Chatou"
    ],
    "name:por_x_preferred":[
        "Chatou"
    ],
    "name:ron_x_preferred":[
        "Chatou"
    ],
    "name:rus_x_preferred":[
        "\u0428\u0430\u0442\u0443"
    ],
    "name:slk_x_preferred":[
        "Chatou"
    ],
    "name:slv_x_preferred":[
        "Chatou"
    ],
    "name:spa_x_preferred":[
        "Chatou"
    ],
    "name:srp_x_preferred":[
        "\u0428\u0430\u0442\u0443"
    ],
    "name:swa_x_preferred":[
        "Chatou"
    ],
    "name:swe_x_preferred":[
        "Chatou"
    ],
    "name:tur_x_preferred":[
        "Chatou"
    ],
    "name:ukr_x_preferred":[
        "\u0428\u0430\u0442\u0443"
    ],
    "name:und_x_variant":[
        "\u5c94\u5934"
    ],
    "name:vie_x_preferred":[
        "Chatou"
    ],
    "name:vol_x_preferred":[
        "Chatou"
    ],
    "name:war_x_preferred":[
        "Chatou"
    ],
    "wof:name":"Chatou",
    "wof:placetype":"locality"
},
  "geometry": {"coordinates":[119.20972,27.21139],"type":"Point"}
}