{
  "type": "Feature",
  "properties": {
    "gn:admin1_code":"3.0",
    "gn:asciiname":"Kengkou",
    "gn:country_code":"CN",
    "gn:dem":201,
    "gn:feature_class":"P",
    "gn:feature_code":"PPL",
    "gn:name":"Kengkou",
    "gn:population":0,
    "gn:timezone":"Asia/Shanghai",
    "iso:country":"CN",
    "name:und_x_variant":[
        "\u5751\u53e3"
    ],
    "wof:name":"Kengkou",
    "wof:placetype":"locality"
},
  "geometry": {"coordinates":[114.29642,27.31311],"type":"Point"}
}