{
  "type": "Feature",
  "properties": {
    "gn:admin1_code":"11.0",
    "gn:asciiname":"Yanjiali",
    "gn:country_code":"CN",
    "gn:dem":228,
    "gn:feature_class":"P",
    "gn:feature_code":"PPL",
    "gn:name":"Yanjiali",
    "gn:population":0,
    "gn:timezone":"Asia/Shanghai",
    "iso:country":"CN",
    "name:zho_x_preferred":[
        "\u989c\u5bb6\u91cc"
    ],
    "wof:name":"Yanjiali",
    "wof:placetype":"locality"
},
  "geometry": {"coordinates":[113.53552000000001,26.95483],"type":"Point"}
}