{
  "type": "Feature",
  "properties": {
    "gn:admin1_code":"11.0",
    "gn:asciiname":"Tuhuangtan",
    "gn:country_code":"CN",
    "gn:dem":232,
    "gn:feature_class":"P",
    "gn:feature_code":"PPL",
    "gn:name":"Tuhuangtan",
    "gn:population":0,
    "gn:timezone":"Asia/Shanghai",
    "iso:country":"CN",
    "name:zho_x_preferred":[
        "\u571f\u9ec4\u6f6d"
    ],
    "wof:name":"Tuhuangtan",
    "wof:placetype":"locality"
},
  "geometry": {"coordinates":[109.57621,27.86998],"type":"Point"}
}