{
  "type": "Feature",
  "properties": {
    "gn:admin1_code":"4.0",
    "gn:asciiname":"Yuxi",
    "gn:country_code":"CN",
    "gn:dem":4,
    "gn:feature_class":"P",
    "gn:feature_code":"PPLA4",
    "gn:name":"Yuxi",
    "gn:population":0,
    "gn:timezone":"Asia/Shanghai",
    "iso:country":"CN",
    "name:und_x_variant":[
        "Y\u00fc-ch\u2019i",
        "Y\u00fc-hsi",
        "Yuxi",
        "Yuxi Zhen"
    ],
    "name:zho_x_preferred":[
        "\u6de4\u6eaa"
    ],
    "name:zho_x_variant":[
        "\u6de4\u6eaa\u9547"
    ],
    "wof:name":"Yuxi",
    "wof:placetype":"locality"
},
  "geometry": {"coordinates":[119.99926000000001,32.58231],"type":"Point"}
}