{
  "type": "Feature",
  "properties": {
    "gn:admin1_code":"3.0",
    "gn:asciiname":"Ma'anshan",
    "gn:country_code":"CN",
    "gn:dem":239,
    "gn:feature_class":"P",
    "gn:feature_code":"PPL",
    "gn:name":"Ma\u2019anshan",
    "gn:population":0,
    "gn:timezone":"Asia/Shanghai",
    "iso:country":"CN",
    "name:afr_x_preferred":[
        "Ma'anshan"
    ],
    "name:ara_x_preferred":[
        "\u0645\u0627\u0646\u0634\u0627\u0646"
    ],
    "name:bul_x_preferred":[
        "\u041c\u0430\u0430\u043d\u0448\u0430\u043d"
    ],
    "name:cdo_x_preferred":[
        "M\u0101-\u0103ng-s\u0103ng"
    ],
    "name:ces_x_preferred":[
        "Ma-an-\u0161an"
    ],
    "name:cym_x_preferred":[
        "Ma'anshan"
    ],
    "name:dan_x_preferred":[
        "Ma'anshan"
    ],
    "name:deu_x_preferred":[
        "Ma\u2019anshan"
    ],
    "name:epo_x_preferred":[
        "Maan\u015dan"
    ],
    "name:eus_x_preferred":[
        "Ma'anshan"
    ],
    "name:fas_x_preferred":[
        "\u0645\u0627\u0646\u0634\u0627\u0646"
    ],
    "name:fin_x_preferred":[
        "Ma\u2019anshan"
    ],
    "name:fra_x_preferred":[
        "Ma'anshan"
    ],
    "name:hye_x_preferred":[
        "\u0544\u0561\u0561\u0576\u0577\u0561\u0576"
    ],
    "name:ind_x_preferred":[
        "Ma'anshan"
    ],
    "name:ita_x_preferred":[
        "Ma'anshan"
    ],
    "name:jpn_x_preferred":[
        "\u99ac\u978d\u5c71\u5e02"
    ],
    "name:kik_x_preferred":[
        "Ma'anshan"
    ],
    "name:kor_x_preferred":[
        "\ub9c8\uc548\uc0b0\uc2dc"
    ],
    "name:mlg_x_preferred":[
        "Ma'anshan"
    ],
    "name:nld_x_preferred":[
        "Ma'anshan"
    ],
    "name:nno_x_preferred":[
        "Ma'anshan"
    ],
    "name:nor_x_preferred":[
        "Ma'anshan"
    ],
    "name:pam_x_preferred":[
        "Ma'anshan"
    ],
    "name:pnb_x_preferred":[
        "\u0645\u0622\u0646\u0634\u0627\u0646"
    ],
    "name:pol_x_preferred":[
        "Ma\u2019anshan"
    ],
    "name:por_x_preferred":[
        "Maanshan"
    ],
    "name:rus_x_preferred":[
        "\u041c\u0430\u0430\u043d\u044c\u0448\u0430\u043d\u044c"
    ],
    "name:sco_x_preferred":[
        "Ma'anshan"
    ],
    "name:spa_x_preferred":[
        "Maanshan"
    ],
    "name:srp_x_preferred":[
        "\u041c\u0430'\u0430\u043d\u0448\u0430\u043d"
    ],
    "name:swe_x_preferred":[
        "Ma'anshan"
    ],
    "name:tgl_x_preferred":[
        "Ma'anshan"
    ],
    "name:tur_x_preferred":[
        "Ma'anshan"
    ],
    "name:uig_x_preferred":[
        "\u0645\u0627\u0626\u06d5\u0646\u0634\u06d5\u0646 \u0634\u06d5\u06be\u0649\u0631\u0649"
    ],
    "name:ukr_x_preferred":[
        "\u041c\u0430\u0430\u043d\u044c\u0448\u0430\u043d\u044c"
    ],
    "name:und_x_variant":[
        "Ma\u2019anshan"
    ],
    "name:urd_x_preferred":[
        "\u0645\u0622\u0646\u0634\u0627\u0646"
    ],
    "name:war_x_preferred":[
        "Maanshan"
    ],
    "name:wuu_x_preferred":[
        "\u9a6c\u978d\u5c71\u5e02"
    ],
    "name:zho_x_preferred":[
        "\u9a6c\u978d\u5c71"
    ],
    "name:zho_x_variant":[
        "\u9a6c\u978d\u5c71\u5e02"
    ],
    "wof:name":"Ma'anshan",
    "wof:placetype":"locality"
},
  "geometry": {"coordinates":[114.592,28.469],"type":"Point"}
}