{
  "type": "Feature",
  "properties": {
    "gn:admin1_code":"18",
    "gn:asciiname":"Wengzhao",
    "gn:country_code":"CN",
    "gn:dem":926,
    "gn:feature_class":"P",
    "gn:feature_code":"PPL",
    "gn:name":"Wengzhao",
    "gn:population":0,
    "gn:timezone":"Asia/Shanghai",
    "iso:country":"CN",
    "wof:name":"Wengzhao",
    "wof:placetype":"locality"
},
  "geometry": {"coordinates":[107.09028000000001,25.61806],"type":"Point"}
}