{
  "type": "Feature",
  "properties": {
    "gn:admin1_code":"21.0",
    "gn:asciiname":"Liubazhuang",
    "gn:country_code":"CN",
    "gn:dem":1399,
    "gn:feature_class":"P",
    "gn:feature_code":"PPL",
    "gn:name":"Liubazhuang",
    "gn:population":0,
    "gn:timezone":"Asia/Shanghai",
    "iso:country":"CN",
    "name:zho_x_preferred":[
        "\u5218\u516b\u5e84"
    ],
    "wof:name":"Liubazhuang",
    "wof:placetype":"locality"
},
  "geometry": {"coordinates":[107.327,37.8194],"type":"Point"}
}