{
  "type": "Feature",
  "properties": {
    "gn:admin1_code":"10",
    "gn:asciiname":"Houshuiquan",
    "gn:country_code":"CN",
    "gn:dem":1386,
    "gn:feature_class":"P",
    "gn:feature_code":"PPL",
    "gn:name":"Houshuiquan",
    "gn:population":0,
    "gn:timezone":"Asia/Shanghai",
    "iso:country":"CN",
    "name:zho_x_preferred":[
        "\u540e\u6c34\u6cc9"
    ],
    "wof:name":"Houshuiquan",
    "wof:placetype":"locality"
},
  "geometry": {"coordinates":[115.73674,41.78628],"type":"Point"}
}