{
  "type": "Feature",
  "properties": {
    "iso:country":"CN",
    "qs:name":"\u9547\u6c5f",
    "qs:name_adm0":"\u4e2d\u570b",
    "qs:name_adm1":"\u6c5f\u82cf\u7701",
    "qs:photos":1162,
    "qs:photos_1k":235,
    "qs:photos_9k":5,
    "qs:photos_9r":7,
    "qs:photos_all":1162,
    "qs:photos_sr":11,
    "qs:placetype":"Town",
    "qs:pop_sr":"0",
    "wof:name":"\u9547\u6c5f",
    "wof:placetype":"locality"
},
  "geometry": {"coordinates":[119.428596,32.214253],"type":"Point"}
}