{
  "type": "Feature",
  "properties": {
    "gn:admin1_code":"32.0",
    "gn:asciiname":"Kuiyong",
    "gn:country_code":"CN",
    "gn:dem":3462,
    "gn:feature_class":"P",
    "gn:feature_code":"PPL",
    "gn:name":"Kuiyong",
    "gn:population":0,
    "gn:timezone":"Asia/Shanghai",
    "iso:country":"CN",
    "name:zho_x_preferred":[
        "\u594e\u62e5"
    ],
    "wof:name":"Kuiyong",
    "wof:placetype":"locality"
},
  "geometry": {"coordinates":[101.76688,30.53748],"type":"Point"}
}