{
  "type": "Feature",
  "properties": {
    "gn:admin1_code":"11.0",
    "gn:asciiname":"Huomaping",
    "gn:country_code":"CN",
    "gn:dem":238,
    "gn:feature_class":"P",
    "gn:feature_code":"PPL",
    "gn:name":"Huomaping",
    "gn:population":0,
    "gn:timezone":"Asia/Shanghai",
    "iso:country":"CN",
    "name:zho_x_preferred":[
        "\u706b\u9ebb\u576a"
    ],
    "wof:name":"Huomaping",
    "wof:placetype":"locality"
},
  "geometry": {"coordinates":[109.7869,27.50436],"type":"Point"}
}