{
  "type": "Feature",
  "properties": {
    "gn:admin1_code":"16.0",
    "gn:asciiname":"Sanqishan",
    "gn:country_code":"CN",
    "gn:dem":706,
    "gn:feature_class":"P",
    "gn:feature_code":"PPL",
    "gn:name":"Sanqishan",
    "gn:population":0,
    "gn:timezone":"Asia/Shanghai",
    "iso:country":"CN",
    "name:zho_x_preferred":[
        "\u4e09\u4e03\u5c71"
    ],
    "wof:name":"Sanqishan",
    "wof:placetype":"locality"
},
  "geometry": {"coordinates":[106.34,24.1385],"type":"Point"}
}