{
  "type": "Feature",
  "properties": {
    "gn:admin1_code":"14.0",
    "gn:asciiname":"Najiagangcun",
    "gn:country_code":"CN",
    "gn:dem":4629,
    "gn:feature_class":"P",
    "gn:feature_code":"PPL",
    "gn:name":"Najiagangcun",
    "gn:population":0,
    "gn:timezone":"Asia/Urumqi",
    "iso:country":"CN",
    "name:zho_x_preferred":[
        "\u7eb3\u52a0\u5c97\u6751"
    ],
    "wof:name":"Najiagangcun",
    "wof:placetype":"locality"
},
  "geometry": {"coordinates":[91.05569,31.99],"type":"Point"}
}