{
  "type": "Feature",
  "properties": {
    "gn:admin1_code":"19.0",
    "gn:asciiname":"Fengjialing",
    "gn:country_code":"CN",
    "gn:dem":327,
    "gn:feature_class":"P",
    "gn:feature_code":"PPL",
    "gn:name":"Fengjialing",
    "gn:population":0,
    "gn:timezone":"Asia/Shanghai",
    "iso:country":"CN",
    "name:und_x_variant":[
        "\u51af\u5bb6\u5cad"
    ],
    "name:zho_x_preferred":[
        "\u51af\u5bb6\u5cad"
    ],
    "wof:name":"Fengjialing",
    "wof:placetype":"locality"
},
  "geometry": {"coordinates":[120.97452,41.4521],"type":"Point"}
}