{
  "type": "Feature",
  "properties": {
    "gn:admin1_code":"11.0",
    "gn:asciiname":"Changshachong",
    "gn:country_code":"CN",
    "gn:dem":97,
    "gn:feature_class":"P",
    "gn:feature_code":"PPL",
    "gn:name":"Changshachong",
    "gn:population":0,
    "gn:timezone":"Asia/Shanghai",
    "iso:country":"CN",
    "name:zho_x_preferred":[
        "\u957f\u6c99\u51b2"
    ],
    "wof:name":"Changshachong",
    "wof:placetype":"locality"
},
  "geometry": {"coordinates":[112.39341,28.20974],"type":"Point"}
}