{
  "type": "Feature",
  "properties": {
    "gn:admin1_code":"07",
    "gn:asciiname":"Daqiu",
    "gn:country_code":"CN",
    "gn:dem":769,
    "gn:feature_class":"P",
    "gn:feature_code":"PPL",
    "gn:name":"Daqiu",
    "gn:population":0,
    "gn:timezone":"Asia/Shanghai",
    "iso:country":"CN",
    "name:zho_x_preferred":[
        "\u5927\u4e18"
    ],
    "wof:name":"Daqiu",
    "wof:placetype":"locality"
},
  "geometry": {"coordinates":[117.62542999999999,25.94636],"type":"Point"}
}