{
  "type": "Feature",
  "properties": {
    "gn:admin1_code":"19.0",
    "gn:asciiname":"Houjiumencun",
    "gn:country_code":"CN",
    "gn:dem":96,
    "gn:feature_class":"P",
    "gn:feature_code":"PPL",
    "gn:name":"Houjiumencun",
    "gn:population":0,
    "gn:timezone":"Asia/Shanghai",
    "iso:country":"CN",
    "name:zho_x_preferred":[
        "\u540e\u65e7\u95e8\u6751"
    ],
    "wof:name":"Houjiumencun",
    "wof:placetype":"locality"
},
  "geometry": {"coordinates":[123.30891,42.6207],"type":"Point"}
}