{
  "type": "Feature",
  "properties": {
    "gn:admin1_code":"14.0",
    "gn:asciiname":"Quechiku",
    "gn:country_code":"CN",
    "gn:dem":3584,
    "gn:feature_class":"P",
    "gn:feature_code":"PPL",
    "gn:name":"Quechiku",
    "gn:population":0,
    "gn:timezone":"Asia/Urumqi",
    "iso:country":"CN",
    "name:zho_x_preferred":[
        "\u786e\u6301\u5e93"
    ],
    "wof:name":"Quechiku",
    "wof:placetype":"locality"
},
  "geometry": {"coordinates":[98.88114,30.45256],"type":"Point"}
}