{
  "type": "Feature",
  "properties": {
    "gn:admin1_code":"10",
    "gn:asciiname":"Tanhua",
    "gn:country_code":"CN",
    "gn:dem":205,
    "gn:feature_class":"P",
    "gn:feature_code":"PPL",
    "gn:name":"Tanhua",
    "gn:population":0,
    "gn:timezone":"Asia/Shanghai",
    "iso:country":"CN",
    "name:zho_x_preferred":[
        "\u8c08\u8bdd"
    ],
    "wof:name":"Tanhua",
    "wof:placetype":"locality"
},
  "geometry": {"coordinates":[114.303,37.1771],"type":"Point"}
}