{
  "type": "Feature",
  "properties": {
    "gn:admin1_code":"18.0",
    "gn:asciiname":"Nanyao Shangzhai",
    "gn:country_code":"CN",
    "gn:dem":828,
    "gn:feature_class":"P",
    "gn:feature_code":"PPL",
    "gn:name":"Nanyao Shangzhai",
    "gn:population":0,
    "gn:timezone":"Asia/Shanghai",
    "iso:country":"CN",
    "name:zho_x_preferred":[
        "\u5357\u5c27\u4e0a\u5be8"
    ],
    "wof:name":"Nanyao Shangzhai",
    "wof:placetype":"locality"
},
  "geometry": {"coordinates":[108.137,26.4652],"type":"Point"}
}