{
  "type": "Feature",
  "properties": {
    "gn:admin1_code":"18",
    "gn:asciiname":"Lishizhai",
    "gn:country_code":"CN",
    "gn:dem":825,
    "gn:feature_class":"P",
    "gn:feature_code":"PPL",
    "gn:name":"Lishizhai",
    "gn:population":0,
    "gn:timezone":"Asia/Shanghai",
    "iso:country":"CN",
    "name:zho_x_preferred":[
        "\u674e\u77f3\u5b85"
    ],
    "wof:name":"Lishizhai",
    "wof:placetype":"locality"
},
  "geometry": {"coordinates":[107.419,28.9203],"type":"Point"}
}