{
  "type": "Feature",
  "properties": {
    "gn:admin1_code":"02",
    "gn:asciiname":"Jintang",
    "gn:country_code":"CN",
    "gn:dem":7,
    "gn:feature_class":"P",
    "gn:feature_code":"PPLA4",
    "gn:name":"Jintang",
    "gn:population":0,
    "gn:timezone":"Asia/Shanghai",
    "iso:country":"CN",
    "name:ceb_x_preferred":[
        "Jintang"
    ],
    "name:deu_x_preferred":[
        "Jintang"
    ],
    "name:rus_x_preferred":[
        "\u0426\u0437\u0438\u043d\u044c\u0442\u0430\u043d"
    ],
    "name:und_x_variant":[
        "\u91d1\u5858",
        "Jintang Zhen",
        "\u91d1\u5858\u9547"
    ],
    "wof:name":"Jintang",
    "wof:placetype":"locality"
},
  "geometry": {"coordinates":[121.86621,30.00579],"type":"Point"}
}