{
  "type": "Feature",
  "properties": {
    "gn:admin1_code":"3.0",
    "gn:asciiname":"Chishi",
    "gn:country_code":"CN",
    "gn:dem":46,
    "gn:feature_class":"P",
    "gn:feature_code":"PPL",
    "gn:name":"Chishi",
    "gn:population":0,
    "gn:timezone":"Asia/Shanghai",
    "iso:country":"CN",
    "name:zho_x_preferred":[
        "\u8d64\u77f3"
    ],
    "wof:name":"Chishi",
    "wof:placetype":"locality"
},
  "geometry": {"coordinates":[117.223,28.4426],"type":"Point"}
}