{
  "type": "Feature",
  "properties": {
    "gn:admin1_code":"25.0",
    "gn:asciiname":"Quanlihujia",
    "gn:country_code":"CN",
    "gn:dem":13,
    "gn:feature_class":"P",
    "gn:feature_code":"PPL",
    "gn:name":"Quanlihujia",
    "gn:population":0,
    "gn:timezone":"Asia/Shanghai",
    "iso:country":"CN",
    "name:zho_x_preferred":[
        "\u5708\u91cc\u80e1\u5bb6"
    ],
    "wof:name":"Quanlihujia",
    "wof:placetype":"locality"
},
  "geometry": {"coordinates":[119.77063,36.7038],"type":"Point"}
}