{
  "type": "Feature",
  "properties": {
    "gn:admin1_code":"30",
    "gn:asciiname":"Xiaoling",
    "gn:country_code":"CN",
    "gn:dem":267,
    "gn:feature_class":"P",
    "gn:feature_code":"PPL",
    "gn:name":"Xiaoling",
    "gn:population":0,
    "gn:timezone":"Asia/Shanghai",
    "iso:country":"CN",
    "name:swe_x_preferred":[
        "Xiaoling"
    ],
    "name:zho_x_preferred":[
        "\u5c0f\u4ee4"
    ],
    "wof:name":"Xiaoling",
    "wof:placetype":"locality"
},
  "geometry": {"coordinates":[116.34398,24.78548],"type":"Point"}
}