{
  "type": "Feature",
  "properties": {
    "gn:admin1_code":"5.0",
    "gn:asciiname":"Bafucun",
    "gn:country_code":"CN",
    "gn:dem":160,
    "gn:feature_class":"P",
    "gn:feature_code":"PPL",
    "gn:name":"Bafucun",
    "gn:population":0,
    "gn:timezone":"Asia/Shanghai",
    "iso:country":"CN",
    "name:zho_x_preferred":[
        "\u516b\u4ed8\u6751"
    ],
    "wof:name":"Bafucun",
    "wof:placetype":"locality"
},
  "geometry": {"coordinates":[123.52245000000001,44.2073],"type":"Point"}
}