{
  "type": "Feature",
  "properties": {
    "gn:admin1_code":"29.0",
    "gn:asciiname":"Mingzhuang",
    "gn:country_code":"CN",
    "gn:dem":2001,
    "gn:feature_class":"P",
    "gn:feature_code":"PPL",
    "gn:name":"Mingzhuang",
    "gn:population":0,
    "gn:timezone":"Asia/Shanghai",
    "iso:country":"CN",
    "name:zho_x_preferred":[
        "\u540d\u5e84"
    ],
    "wof:name":"Mingzhuang",
    "wof:placetype":"locality"
},
  "geometry": {"coordinates":[100.268,25.7292],"type":"Point"}
}