{
  "type": "Feature",
  "properties": {
    "gn:admin1_code":"16.0",
    "gn:asciiname":"Tianzhuchong",
    "gn:country_code":"CN",
    "gn:dem":237,
    "gn:feature_class":"P",
    "gn:feature_code":"PPL",
    "gn:name":"Tianzhuchong",
    "gn:population":0,
    "gn:timezone":"Asia/Shanghai",
    "iso:country":"CN",
    "name:zho_x_preferred":[
        "\u5929\u67f1\u51b2"
    ],
    "wof:name":"Tianzhuchong",
    "wof:placetype":"locality"
},
  "geometry": {"coordinates":[111.34099999999999,24.3602],"type":"Point"}
}