{
  "type": "Feature",
  "properties": {
    "gn:admin1_code":"11.0",
    "gn:asciiname":"Jiemulong",
    "gn:country_code":"CN",
    "gn:dem":963,
    "gn:feature_class":"P",
    "gn:feature_code":"PPL",
    "gn:name":"Jiemulong",
    "gn:population":0,
    "gn:timezone":"Asia/Shanghai",
    "iso:country":"CN",
    "name:zho_x_preferred":[
        "\u754c\u6728\u5785"
    ],
    "wof:name":"Jiemulong",
    "wof:placetype":"locality"
},
  "geometry": {"coordinates":[113.76746,25.53061],"type":"Point"}
}