{
  "type": "Feature",
  "properties": {
    "gn:admin1_code":"32.0",
    "gn:asciiname":"Weike",
    "gn:country_code":"CN",
    "gn:dem":3658,
    "gn:feature_class":"P",
    "gn:feature_code":"PPL",
    "gn:name":"Weike",
    "gn:population":0,
    "gn:timezone":"Asia/Shanghai",
    "iso:country":"CN",
    "name:zho_x_preferred":[
        "\u7ef4\u67ef"
    ],
    "wof:name":"Weike",
    "wof:placetype":"locality"
},
  "geometry": {"coordinates":[101.14,31.3252],"type":"Point"}
}