{
  "type": "Feature",
  "properties": {
    "gn:admin1_code":"32.0",
    "gn:asciiname":"Yituo",
    "gn:country_code":"CN",
    "gn:dem":3409,
    "gn:feature_class":"P",
    "gn:feature_code":"PPL",
    "gn:name":"Yituo",
    "gn:population":0,
    "gn:timezone":"Asia/Shanghai",
    "iso:country":"CN",
    "name:zho_x_preferred":[
        "\u4e00\u62d6"
    ],
    "wof:name":"Yituo",
    "wof:placetype":"locality"
},
  "geometry": {"coordinates":[101.13500000000001,30.9491],"type":"Point"}
}