{
  "type": "Feature",
  "properties": {
    "gn:admin1_code":"10",
    "gn:asciiname":"Laoyacha",
    "gn:country_code":"CN",
    "gn:dem":1284,
    "gn:feature_class":"P",
    "gn:feature_code":"PPL",
    "gn:name":"Laoyacha",
    "gn:population":0,
    "gn:timezone":"Asia/Shanghai",
    "iso:country":"CN",
    "name:zho_x_preferred":[
        "\u8001\u82bd\u832c"
    ],
    "wof:name":"Laoyacha",
    "wof:placetype":"locality"
},
  "geometry": {"coordinates":[115.19627,41.04962],"type":"Point"}
}