{
  "type": "Feature",
  "properties": {
    "gn:admin1_code":"19.0",
    "gn:asciiname":"Taigou",
    "gn:country_code":"CN",
    "gn:dem":287,
    "gn:feature_class":"P",
    "gn:feature_code":"PPL",
    "gn:name":"Taigou",
    "gn:population":0,
    "gn:timezone":"Asia/Shanghai",
    "iso:country":"CN",
    "name:und_x_variant":[
        "\u53f0\u6c9f"
    ],
    "name:zho_x_preferred":[
        "\u53f0\u6c9f"
    ],
    "wof:name":"Taigou",
    "wof:placetype":"locality"
},
  "geometry": {"coordinates":[123.93676000000001,41.56999],"type":"Point"}
}