{
  "type": "Feature",
  "properties": {
    "gn:admin1_code":"16.0",
    "gn:asciiname":"Nandiantang",
    "gn:country_code":"CN",
    "gn:dem":932,
    "gn:feature_class":"P",
    "gn:feature_code":"PPL",
    "gn:name":"Nandiantang",
    "gn:population":0,
    "gn:timezone":"Asia/Shanghai",
    "iso:country":"CN",
    "name:zho_x_preferred":[
        "\u5357\u5e97\u5858"
    ],
    "wof:name":"Nandiantang",
    "wof:placetype":"locality"
},
  "geometry": {"coordinates":[107.515,24.9502],"type":"Point"}
}