{
  "type": "Feature",
  "properties": {
    "gn:admin1_code":"11.0",
    "gn:asciiname":"Shangye Jiaping",
    "gn:country_code":"CN",
    "gn:dem":53,
    "gn:feature_class":"P",
    "gn:feature_code":"PPL",
    "gn:name":"Shangye Jiaping",
    "gn:population":0,
    "gn:timezone":"Asia/Shanghai",
    "iso:country":"CN",
    "name:zho_x_preferred":[
        "Shangye Jiaping"
    ],
    "name:zho_x_variant":[
        "\u4e0a\u53f6\u5bb6\u576a"
    ],
    "wof:name":"Shangye Jiaping",
    "wof:placetype":"locality"
},
  "geometry": {"coordinates":[111.48985,29.59557],"type":"Point"}
}