{
  "type": "Feature",
  "properties": {
    "gn:admin1_code":"16.0",
    "gn:asciiname":"Keyi",
    "gn:country_code":"CN",
    "gn:dem":365,
    "gn:feature_class":"P",
    "gn:feature_code":"PPL",
    "gn:name":"Keyi",
    "gn:population":0,
    "gn:timezone":"Asia/Shanghai",
    "iso:country":"CN",
    "name:zho_x_preferred":[
        "\u53ef\u76ca"
    ],
    "wof:name":"Keyi",
    "wof:placetype":"locality"
},
  "geometry": {"coordinates":[108.515,25.2522],"type":"Point"}
}