{
  "type": "Feature",
  "properties": {
    "gn:admin1_code":"3.0",
    "gn:asciiname":"Neijingzi",
    "gn:country_code":"CN",
    "gn:dem":440,
    "gn:feature_class":"P",
    "gn:feature_code":"PPL",
    "gn:name":"Neijingzi",
    "gn:population":0,
    "gn:timezone":"Asia/Shanghai",
    "iso:country":"CN",
    "name:und_x_variant":[
        "\u5185\u8ff3\u5b50"
    ],
    "wof:name":"Neijingzi",
    "wof:placetype":"locality"
},
  "geometry": {"coordinates":[115.53257000000001,26.25755],"type":"Point"}
}