{
  "type": "Feature",
  "properties": {
    "gn:admin1_code":"9",
    "gn:asciiname":"Handayuan",
    "gn:country_code":"CN",
    "gn:dem":48,
    "gn:feature_class":"P",
    "gn:feature_code":"PPL",
    "gn:name":"Handayuan",
    "gn:population":0,
    "gn:timezone":"Asia/Shanghai",
    "iso:country":"CN",
    "name:zho_x_preferred":[
        "\u97e9\u5927\u5143"
    ],
    "wof:name":"Handayuan",
    "wof:placetype":"locality"
},
  "geometry": {"coordinates":[115.34128,35.99057],"type":"Point"}
}