{
  "type": "Feature",
  "properties": {
    "gn:admin1_code":"26.0",
    "gn:asciiname":"Fotanggou",
    "gn:country_code":"CN",
    "gn:dem":627,
    "gn:feature_class":"P",
    "gn:feature_code":"PPL",
    "gn:name":"Fotanggou",
    "gn:population":0,
    "gn:timezone":"Asia/Shanghai",
    "iso:country":"CN",
    "name:zho_x_preferred":[
        "\u4f5b\u5802\u6c9f"
    ],
    "wof:name":"Fotanggou",
    "wof:placetype":"locality"
},
  "geometry": {"coordinates":[108.82577999999999,33.49463],"type":"Point"}
}