{
  "type": "Feature",
  "properties": {
    "gn:admin1_code":"30.0",
    "gn:asciiname":"Taojuntang",
    "gn:country_code":"CN",
    "gn:dem":308,
    "gn:feature_class":"P",
    "gn:feature_code":"PPL",
    "gn:name":"Taojuntang",
    "gn:population":0,
    "gn:timezone":"Asia/Shanghai",
    "iso:country":"CN",
    "name:zho_x_preferred":[
        "\u6843\u519b\u5858"
    ],
    "wof:name":"Taojuntang",
    "wof:placetype":"locality"
},
  "geometry": {"coordinates":[115.42613,23.77249],"type":"Point"}
}