{
  "type": "Feature",
  "properties": {
    "gn:admin1_code":"15.0",
    "gn:asciiname":"Shijiazui",
    "gn:country_code":"CN",
    "gn:dem":1500,
    "gn:feature_class":"P",
    "gn:feature_code":"PPL",
    "gn:name":"Shijiazui",
    "gn:population":0,
    "gn:timezone":"Asia/Shanghai",
    "iso:country":"CN",
    "name:und_x_variant":[
        "\u53f2\u5bb6\u5480"
    ],
    "wof:name":"Shijiazui",
    "wof:placetype":"locality"
},
  "geometry": {"coordinates":[107.62138,36.59011],"type":"Point"}
}