{
  "type": "Feature",
  "properties": {
    "gn:admin1_code":"26",
    "gn:asciiname":"Baishachuancun",
    "gn:country_code":"CN",
    "gn:dem":1371,
    "gn:feature_class":"P",
    "gn:feature_code":"PPL",
    "gn:name":"Baishachuancun",
    "gn:population":0,
    "gn:timezone":"Asia/Shanghai",
    "iso:country":"CN",
    "name:und_x_variant":[
        "Pai-sha-ch\u2019uan",
        "Baishachuan",
        "Baishachuancun"
    ],
    "name:zho_x_preferred":[
        "\u767d\u6c99\u5ddd\u6751"
    ],
    "wof:name":"Baishachuancun",
    "wof:placetype":"locality"
},
  "geometry": {"coordinates":[108.59863,36.49437],"type":"Point"}
}