{
  "type": "Feature",
  "properties": {
    "gn:admin1_code":"3.0",
    "gn:asciiname":"Dongtang Wujia",
    "gn:country_code":"CN",
    "gn:dem":39,
    "gn:feature_class":"P",
    "gn:feature_code":"PPL",
    "gn:name":"Dongtang Wujia",
    "gn:population":0,
    "gn:timezone":"Asia/Shanghai",
    "iso:country":"CN",
    "name:und_x_variant":[
        "\u4e1c\u5858\u5434\u5bb6"
    ],
    "wof:name":"Dongtang Wujia",
    "wof:placetype":"locality"
},
  "geometry": {"coordinates":[115.73822,28.59968],"type":"Point"}
}