{
  "type": "Feature",
  "properties": {
    "gn:admin1_code":"7",
    "gn:asciiname":"Louzaiding",
    "gn:country_code":"CN",
    "gn:dem":269,
    "gn:feature_class":"P",
    "gn:feature_code":"PPL",
    "gn:name":"Louzaiding",
    "gn:population":0,
    "gn:timezone":"Asia/Shanghai",
    "iso:country":"CN",
    "name:zho_x_preferred":[
        "\u697c\u4ed4\u9876"
    ],
    "wof:name":"Louzaiding",
    "wof:placetype":"locality"
},
  "geometry": {"coordinates":[119.27769000000001,25.79023],"type":"Point"}
}