{
  "type": "Feature",
  "properties": {
    "gn:admin1_code":"6.0",
    "gn:asciiname":"Zhuge",
    "gn:country_code":"CN",
    "gn:dem":2290,
    "gn:feature_class":"P",
    "gn:feature_code":"PPL",
    "gn:name":"Zhuge",
    "gn:population":0,
    "gn:timezone":"Asia/Shanghai",
    "iso:country":"CN",
    "name:deu_x_preferred":[
        "Zhuge"
    ],
    "name:ita_x_preferred":[
        "Zhuge"
    ],
    "name:nld_x_preferred":[
        "Zhuge"
    ],
    "name:nor_x_preferred":[
        "Zhuge"
    ],
    "name:rus_x_preferred":[
        "\u0427\u0436\u0443\u0433\u044d"
    ],
    "name:tha_x_preferred":[
        "\u0e08\u0e39\u0e40\u0e01\u0e48\u0e2d"
    ],
    "name:und_x_variant":[
        "\u6731\u683c"
    ],
    "name:vie_x_preferred":[
        "Gia C\u00e1t"
    ],
    "name:zho_x_preferred":[
        "\u8af8\u845b\u59d3"
    ],
    "wof:name":"Zhuge",
    "wof:placetype":"locality"
},
  "geometry": {"coordinates":[102.54367999999999,35.72461],"type":"Point"}
}