{
  "type": "Feature",
  "properties": {
    "gn:admin1_code":"20.0",
    "gn:asciiname":"Geliaopo",
    "gn:country_code":"CN",
    "gn:dem":1741,
    "gn:feature_class":"P",
    "gn:feature_code":"PPL",
    "gn:name":"Geliaopo",
    "gn:population":0,
    "gn:timezone":"Asia/Shanghai",
    "iso:country":"CN",
    "name:und_x_variant":[
        "\u572a\u6599\u5761"
    ],
    "wof:name":"Geliaopo",
    "wof:placetype":"locality"
},
  "geometry": {"coordinates":[112.43347,41.42813],"type":"Point"}
}