{
  "type": "Feature",
  "properties": {
    "gn:admin1_code":"16.0",
    "gn:asciiname":"Tiemujiang",
    "gn:country_code":"CN",
    "gn:dem":39,
    "gn:feature_class":"P",
    "gn:feature_code":"PPL",
    "gn:name":"Tiemujiang",
    "gn:population":0,
    "gn:timezone":"Asia/Shanghai",
    "iso:country":"CN",
    "name:zho_x_preferred":[
        "\u94c1\u6728\u6c5f"
    ],
    "wof:name":"Tiemujiang",
    "wof:placetype":"locality"
},
  "geometry": {"coordinates":[108.964,22.0659],"type":"Point"}
}