{
  "type": "Feature",
  "properties": {
    "gn:admin1_code":"2.0",
    "gn:asciiname":"Xiaohoutao",
    "gn:country_code":"CN",
    "gn:dem":183,
    "gn:feature_class":"P",
    "gn:feature_code":"PPL",
    "gn:name":"Xiaohoutao",
    "gn:population":0,
    "gn:timezone":"Asia/Shanghai",
    "iso:country":"CN",
    "name:zho_x_preferred":[
        "\u5c0f\u540e\u9676"
    ],
    "wof:name":"Xiaohoutao",
    "wof:placetype":"locality"
},
  "geometry": {"coordinates":[119.64337999999999,28.78913],"type":"Point"}
}