{
  "type": "Feature",
  "properties": {
    "gn:admin1_code":"04",
    "gn:asciiname":"Gujiaxiang",
    "gn:cc2":"CN",
    "gn:country_code":"CN",
    "gn:dem":5,
    "gn:feature_class":"P",
    "gn:feature_code":"PPL",
    "gn:name":"Gujiaxiang",
    "gn:population":0,
    "gn:timezone":"Asia/Shanghai",
    "iso:country":"CN",
    "name:und_x_variant":[
        "Ku-chia-hsiang",
        "Gujiaxiang"
    ],
    "wof:name":"Gujiaxiang",
    "wof:placetype":"locality"
},
  "geometry": {"coordinates":[121.10417,31.56611],"type":"Point"}
}