{
  "type": "Feature",
  "properties": {
    "gn:admin1_code":"29.0",
    "gn:asciiname":"Shuanglongtan",
    "gn:country_code":"CN",
    "gn:dem":1625,
    "gn:feature_class":"P",
    "gn:feature_code":"PPL",
    "gn:name":"Shuanglongtan",
    "gn:population":0,
    "gn:timezone":"Asia/Shanghai",
    "iso:country":"CN",
    "name:zho_x_preferred":[
        "\u53cc\u9f99\u6f6d"
    ],
    "wof:name":"Shuanglongtan",
    "wof:placetype":"locality"
},
  "geometry": {"coordinates":[103.65900000000001,26.2783],"type":"Point"}
}