{
  "type": "Feature",
  "properties": {
    "gn:admin1_code":"25",
    "gn:asciiname":"Sinushu",
    "gn:country_code":"CN",
    "gn:dem":43,
    "gn:feature_class":"P",
    "gn:feature_code":"PPL",
    "gn:name":"Sin\u00fcshu",
    "gn:population":0,
    "gn:timezone":"Asia/Shanghai",
    "iso:country":"CN",
    "name:und_x_variant":[
        "Sin\u00fcshu"
    ],
    "name:zho_x_preferred":[
        "\u56db\u5973\u6811"
    ],
    "wof:name":"Sinushu",
    "wof:placetype":"locality"
},
  "geometry": {"coordinates":[115.66768,36.30103],"type":"Point"}
}