{
  "type": "Feature",
  "properties": {
    "gn:admin1_code":"15.0",
    "gn:asciiname":"Caopozi",
    "gn:country_code":"CN",
    "gn:dem":1522,
    "gn:feature_class":"P",
    "gn:feature_code":"PPL",
    "gn:name":"Caopozi",
    "gn:population":0,
    "gn:timezone":"Asia/Shanghai",
    "iso:country":"CN",
    "name:zho_x_preferred":[
        "\u8349\u5761\u5b50"
    ],
    "wof:name":"Caopozi",
    "wof:placetype":"locality"
},
  "geometry": {"coordinates":[105.06063,33.23558],"type":"Point"}
}