{
  "type": "Feature",
  "properties": {
    "gn:admin1_code":"8.0",
    "gn:asciiname":"Jianbian Nongchang Shisandui",
    "gn:country_code":"CN",
    "gn:dem":279,
    "gn:feature_class":"P",
    "gn:feature_code":"PPLF",
    "gn:name":"Jianbian Nongchang Shisandui",
    "gn:population":0,
    "gn:timezone":"Asia/Shanghai",
    "iso:country":"CN",
    "name:zho_x_preferred":[
        "\u5efa\u8fb9\u519c\u573a\u5341\u4e09\u961f"
    ],
    "wof:name":"Jianbian Nongchang Shisandui",
    "wof:placetype":"locality"
},
  "geometry": {"coordinates":[125.29671999999999,50.02352],"type":"Point"}
}