{
  "type": "Feature",
  "properties": {
    "gn:admin1_code":"30.0",
    "gn:asciiname":"Wenlu",
    "gn:country_code":"CN",
    "gn:dem":686,
    "gn:feature_class":"P",
    "gn:feature_code":"PPL",
    "gn:name":"Wenlu",
    "gn:population":0,
    "gn:timezone":"Asia/Shanghai",
    "iso:country":"CN",
    "name:zho_x_preferred":[
        "\u6587\u8def"
    ],
    "wof:name":"Wenlu",
    "wof:placetype":"locality"
},
  "geometry": {"coordinates":[114.13393000000001,25.12788],"type":"Point"}
}