{
  "type": "Feature",
  "properties": {
    "gn:admin1_code":"29.0",
    "gn:asciiname":"Hebianzhai",
    "gn:country_code":"CN",
    "gn:dem":1454,
    "gn:feature_class":"P",
    "gn:feature_code":"PPL",
    "gn:name":"Hebianzhai",
    "gn:population":0,
    "gn:timezone":"Asia/Shanghai",
    "iso:country":"CN",
    "name:zho_x_preferred":[
        "\u6cb3\u8fb9\u5be8"
    ],
    "wof:name":"Hebianzhai",
    "wof:placetype":"locality"
},
  "geometry": {"coordinates":[99.2744,24.2233],"type":"Point"}
}