{
  "type": "Feature",
  "properties": {
    "gn:admin1_code":"26.0",
    "gn:asciiname":"Huangnibao",
    "gn:country_code":"CN",
    "gn:dem":759,
    "gn:feature_class":"P",
    "gn:feature_code":"PPL",
    "gn:name":"Huangnibao",
    "gn:population":0,
    "gn:timezone":"Asia/Shanghai",
    "iso:country":"CN",
    "name:und_x_variant":[
        "\u9ec4\u6ce5\u5305"
    ],
    "wof:name":"Huangnibao",
    "wof:placetype":"locality"
},
  "geometry": {"coordinates":[106.38768,32.88119],"type":"Point"}
}