{
  "type": "Feature",
  "properties": {
    "gn:admin1_code":"30.0",
    "gn:asciiname":"Liangmixia",
    "gn:country_code":"CN",
    "gn:dem":118,
    "gn:feature_class":"P",
    "gn:feature_code":"PPL",
    "gn:name":"Liangmixia",
    "gn:population":0,
    "gn:timezone":"Asia/Shanghai",
    "iso:country":"CN",
    "name:zho_x_preferred":[
        "\u7cae\u7c73\u4e0b"
    ],
    "wof:name":"Liangmixia",
    "wof:placetype":"locality"
},
  "geometry": {"coordinates":[115.04467,23.27971],"type":"Point"}
}