{
  "type": "Feature",
  "properties": {
    "gn:admin1_code":"30.0",
    "gn:asciiname":"Damianling",
    "gn:country_code":"CN",
    "gn:dem":657,
    "gn:feature_class":"P",
    "gn:feature_code":"PPL",
    "gn:name":"Damianling",
    "gn:population":0,
    "gn:timezone":"Asia/Shanghai",
    "iso:country":"CN",
    "name:zho_x_preferred":[
        "\u5927\u9762\u5cad"
    ],
    "wof:name":"Damianling",
    "wof:placetype":"locality"
},
  "geometry": {"coordinates":[115.32841999999999,23.74529],"type":"Point"}
}