{
  "type": "Feature",
  "properties": {
    "gn:admin1_code":"29.0",
    "gn:asciiname":"Piaochang",
    "gn:country_code":"CN",
    "gn:dem":1724,
    "gn:feature_class":"P",
    "gn:feature_code":"PPL",
    "gn:name":"Piaochang",
    "gn:population":0,
    "gn:timezone":"Asia/Shanghai",
    "iso:country":"CN",
    "name:zho_x_preferred":[
        "\u74e2\u5382"
    ],
    "wof:name":"Piaochang",
    "wof:placetype":"locality"
},
  "geometry": {"coordinates":[103.989,22.8624],"type":"Point"}
}