{
  "type": "Feature",
  "properties": {
    "gn:admin1_code":"25.0",
    "gn:asciiname":"Shanxitou",
    "gn:country_code":"CN",
    "gn:dem":66,
    "gn:feature_class":"P",
    "gn:feature_code":"PPL",
    "gn:name":"Shanxitou",
    "gn:population":0,
    "gn:timezone":"Asia/Shanghai",
    "iso:country":"CN",
    "name:zho_x_preferred":[
        "\u5c71\u897f\u5934"
    ],
    "wof:name":"Shanxitou",
    "wof:placetype":"locality"
},
  "geometry": {"coordinates":[119.17162,35.2237],"type":"Point"}
}