{
  "type": "Feature",
  "properties": {
    "gn:admin1_code":"3.0",
    "gn:asciiname":"Yeqiao",
    "gn:country_code":"CN",
    "gn:dem":169,
    "gn:feature_class":"P",
    "gn:feature_code":"PPL",
    "gn:name":"Yeqiao",
    "gn:population":0,
    "gn:timezone":"Asia/Shanghai",
    "iso:country":"CN",
    "name:zho_x_preferred":[
        "\u53f6\u6865"
    ],
    "wof:name":"Yeqiao",
    "wof:placetype":"locality"
},
  "geometry": {"coordinates":[117.99299999999999,28.7011],"type":"Point"}
}