{
  "type": "Feature",
  "properties": {
    "gn:admin1_code":"29.0",
    "gn:asciiname":"Pingdi",
    "gn:country_code":"CN",
    "gn:dem":1367,
    "gn:feature_class":"P",
    "gn:feature_code":"PPL",
    "gn:name":"Pingdi",
    "gn:population":0,
    "gn:timezone":"Asia/Shanghai",
    "iso:country":"CN",
    "name:zho_x_preferred":[
        "\u5e73\u5730"
    ],
    "wof:name":"Pingdi",
    "wof:placetype":"locality"
},
  "geometry": {"coordinates":[98.9417,25.004],"type":"Point"}
}