{
  "type": "Feature",
  "properties": {
    "gn:admin1_code":"19.0",
    "gn:asciiname":"Ximinzhucun",
    "gn:country_code":"CN",
    "gn:dem":49,
    "gn:feature_class":"P",
    "gn:feature_code":"PPL",
    "gn:name":"Ximinzhucun",
    "gn:population":0,
    "gn:timezone":"Asia/Shanghai",
    "iso:country":"CN",
    "name:zho_x_preferred":[
        "\u897f\u6c11\u4e3b\u6751"
    ],
    "wof:name":"Ximinzhucun",
    "wof:placetype":"locality"
},
  "geometry": {"coordinates":[124.367,40.2955],"type":"Point"}
}