{
  "type": "Feature",
  "properties": {
    "gn:admin1_code":"3.0",
    "gn:asciiname":"Jingtangli",
    "gn:country_code":"CN",
    "gn:dem":85,
    "gn:feature_class":"P",
    "gn:feature_code":"PPL",
    "gn:name":"Jingtangli",
    "gn:population":0,
    "gn:timezone":"Asia/Shanghai",
    "iso:country":"CN",
    "name:zho_x_preferred":[
        "\u4e95\u5858\u91cc"
    ],
    "wof:name":"Jingtangli",
    "wof:placetype":"locality"
},
  "geometry": {"coordinates":[114.816,27.9921],"type":"Point"}
}