{
  "type": "Feature",
  "properties": {
    "gn:admin1_code":"4.0",
    "gn:asciiname":"Taozhuangcun",
    "gn:country_code":"CN",
    "gn:dem":32,
    "gn:feature_class":"P",
    "gn:feature_code":"PPL",
    "gn:name":"Taozhuangcun",
    "gn:population":0,
    "gn:timezone":"Asia/Shanghai",
    "iso:country":"CN",
    "name:zho_x_preferred":[
        "\u9676\u5e84\u6751"
    ],
    "wof:name":"Taozhuangcun",
    "wof:placetype":"locality"
},
  "geometry": {"coordinates":[119.32092,31.62207],"type":"Point"}
}