{
  "type": "Feature",
  "properties": {
    "gn:admin1_code":"25",
    "gn:asciiname":"Boyicun",
    "gn:country_code":"CN",
    "gn:dem":12,
    "gn:feature_class":"P",
    "gn:feature_code":"PPL",
    "gn:name":"Boyicun",
    "gn:population":0,
    "gn:timezone":"Asia/Shanghai",
    "iso:country":"CN",
    "name:zho_x_preferred":[
        "\u535a\u4e00\u6751"
    ],
    "wof:name":"Boyicun",
    "wof:placetype":"locality"
},
  "geometry": {"coordinates":[118.02500000000001,37.2698],"type":"Point"}
}