{
  "type": "Feature",
  "properties": {
    "gn:admin1_code":"30",
    "gn:asciiname":"Fengxiangkeng",
    "gn:country_code":"CN",
    "gn:dem":143,
    "gn:feature_class":"P",
    "gn:feature_code":"PPL",
    "gn:name":"Fengxiangkeng",
    "gn:population":0,
    "gn:timezone":"Asia/Shanghai",
    "iso:country":"CN",
    "name:zho_x_preferred":[
        "\u9022\u76f8\u5751"
    ],
    "wof:name":"Fengxiangkeng",
    "wof:placetype":"locality"
},
  "geometry": {"coordinates":[111.67592999999999,22.37629],"type":"Point"}
}