{
  "type": "Feature",
  "properties": {
    "gn:admin1_code":"0.0",
    "gn:asciiname":"Meng-wen",
    "gn:country_code":"CN",
    "gn:dem":787,
    "gn:feature_class":"P",
    "gn:feature_code":"PPL",
    "gn:name":"Meng-wen",
    "gn:population":0,
    "gn:timezone":"Asia/Shanghai",
    "iso:country":"CN",
    "wof:name":"Meng-wen",
    "wof:placetype":"locality"
},
  "geometry": {"coordinates":[101.3839,21.7162],"type":"Point"}
}