{
  "type": "Feature",
  "properties": {
    "gn:admin1_code":"1.0",
    "gn:asciiname":"Hongyancun",
    "gn:country_code":"CN",
    "gn:dem":54,
    "gn:feature_class":"P",
    "gn:feature_code":"PPL",
    "gn:name":"Hongyancun",
    "gn:population":0,
    "gn:timezone":"Asia/Shanghai",
    "iso:country":"CN",
    "name:zho_x_preferred":[
        "\u7ea2\u5830\u6751"
    ],
    "wof:name":"Hongyancun",
    "wof:placetype":"locality"
},
  "geometry": {"coordinates":[116.63233,31.62753],"type":"Point"}
}