{
  "type": "Feature",
  "properties": {
    "gn:admin1_code":"3.0",
    "gn:asciiname":"Chakou",
    "gn:country_code":"CN",
    "gn:dem":126,
    "gn:feature_class":"P",
    "gn:feature_code":"PPL",
    "gn:name":"Chakou",
    "gn:population":0,
    "gn:timezone":"Asia/Shanghai",
    "iso:country":"CN",
    "name:und_x_variant":[
        "\u8336\u53e3"
    ],
    "wof:name":"Chakou",
    "wof:placetype":"locality"
},
  "geometry": {"coordinates":[114.05595,27.79341],"type":"Point"}
}