{
  "type": "Feature",
  "properties": {
    "gn:admin1_code":"11.0",
    "gn:asciiname":"Yangjia Laowu",
    "gn:country_code":"CN",
    "gn:dem":26,
    "gn:feature_class":"P",
    "gn:feature_code":"PPL",
    "gn:name":"Yangjia Laowu",
    "gn:population":0,
    "gn:timezone":"Asia/Shanghai",
    "iso:country":"CN",
    "name:zho_x_preferred":[
        "\u6768\u5bb6\u8001\u5c4b"
    ],
    "wof:name":"Yangjia Laowu",
    "wof:placetype":"locality"
},
  "geometry": {"coordinates":[112.69114,28.59276],"type":"Point"}
}