{
  "type": "Feature",
  "properties": {
    "gn:admin1_code":"2.0",
    "gn:asciiname":"Xianxi",
    "gn:country_code":"CN",
    "gn:dem":61,
    "gn:feature_class":"P",
    "gn:feature_code":"PPLA4",
    "gn:name":"Xianxi",
    "gn:population":0,
    "gn:timezone":"Asia/Shanghai",
    "iso:country":"CN",
    "name:und_x_variant":[
        "Xianxi Zhen"
    ],
    "name:zho_x_preferred":[
        "\u4ed9\u6eaa"
    ],
    "name:zho_x_variant":[
        "\u4ed9\u6eaa\u9547"
    ],
    "wof:name":"Xianxi",
    "wof:placetype":"locality"
},
  "geometry": {"coordinates":[121.0663,28.41754],"type":"Point"}
}