{
  "type": "Feature",
  "properties": {
    "gn:admin1_code":"9.0",
    "gn:asciiname":"Miaopo",
    "gn:country_code":"CN",
    "gn:dem":189,
    "gn:feature_class":"P",
    "gn:feature_code":"PPL",
    "gn:name":"Miaopo",
    "gn:population":0,
    "gn:timezone":"Asia/Shanghai",
    "iso:country":"CN",
    "name:und_x_variant":[
        "\u5e99\u5761",
        "Miaopo"
    ],
    "wof:name":"Miaopo",
    "wof:placetype":"locality"
},
  "geometry": {"coordinates":[112.47436999999999,33.42361],"type":"Point"}
}