{
  "type": "Feature",
  "properties": {
    "gn:admin1_code":"26.0",
    "gn:asciiname":"Dijiahecun",
    "gn:country_code":"CN",
    "gn:dem":856,
    "gn:feature_class":"P",
    "gn:feature_code":"PPL",
    "gn:name":"Dijiahecun",
    "gn:population":0,
    "gn:timezone":"Asia/Shanghai",
    "iso:country":"CN",
    "name:zho_x_preferred":[
        "\u8fea\u5bb6\u6cb3\u6751"
    ],
    "wof:name":"Dijiahecun",
    "wof:placetype":"locality"
},
  "geometry": {"coordinates":[109.82285,35.36273],"type":"Point"}
}