{
  "type": "Feature",
  "properties": {
    "gn:admin1_code":"11.0",
    "gn:asciiname":"Shangzhoujia",
    "gn:country_code":"CN",
    "gn:dem":131,
    "gn:feature_class":"P",
    "gn:feature_code":"PPL",
    "gn:name":"Shangzhoujia",
    "gn:population":0,
    "gn:timezone":"Asia/Shanghai",
    "iso:country":"CN",
    "name:zho_x_preferred":[
        "\u4e0a\u5468\u5bb6"
    ],
    "wof:name":"Shangzhoujia",
    "wof:placetype":"locality"
},
  "geometry": {"coordinates":[113.00514,26.21193],"type":"Point"}
}