{
  "type": "Feature",
  "properties": {
    "gn:admin1_code":"26.0",
    "gn:asciiname":"Shixialiang",
    "gn:country_code":"CN",
    "gn:dem":1201,
    "gn:feature_class":"P",
    "gn:feature_code":"PPL",
    "gn:name":"Shixialiang",
    "gn:population":0,
    "gn:timezone":"Asia/Shanghai",
    "iso:country":"CN",
    "name:zho_x_preferred":[
        "\u77f3\u5ce1\u6881"
    ],
    "wof:name":"Shixialiang",
    "wof:placetype":"locality"
},
  "geometry": {"coordinates":[110.79658999999999,39.34996],"type":"Point"}
}