{
  "type": "Feature",
  "properties": {
    "gn:admin1_code":"3.0",
    "gn:asciiname":"Xiaoxiyuan",
    "gn:country_code":"CN",
    "gn:dem":481,
    "gn:feature_class":"P",
    "gn:feature_code":"PPL",
    "gn:name":"Xiaoxiyuan",
    "gn:population":0,
    "gn:timezone":"Asia/Shanghai",
    "iso:country":"CN",
    "name:und_x_variant":[
        "\u5c0f\u6eaa\u6e90"
    ],
    "wof:name":"Xiaoxiyuan",
    "wof:placetype":"locality"
},
  "geometry": {"coordinates":[116.27663,26.51428],"type":"Point"}
}