{
  "type": "Feature",
  "properties": {
    "gn:admin1_code":"15.0",
    "gn:asciiname":"Madaliang",
    "gn:country_code":"CN",
    "gn:dem":1492,
    "gn:feature_class":"P",
    "gn:feature_code":"PPL",
    "gn:name":"Madaliang",
    "gn:population":0,
    "gn:timezone":"Asia/Shanghai",
    "iso:country":"CN",
    "name:zho_x_preferred":[
        "\u9a6c\u5927\u6881"
    ],
    "wof:name":"Madaliang",
    "wof:placetype":"locality"
},
  "geometry": {"coordinates":[108.19799999999999,36.306],"type":"Point"}
}