{
  "type": "Feature",
  "properties": {
    "gn:admin1_code":"29.0",
    "gn:asciiname":"Bidi Xinzhai",
    "gn:country_code":"CN",
    "gn:dem":1738,
    "gn:feature_class":"P",
    "gn:feature_code":"PPL",
    "gn:name":"Bidi Xinzhai",
    "gn:population":0,
    "gn:timezone":"Asia/Shanghai",
    "iso:country":"CN",
    "name:zho_x_preferred":[
        "\u5fc5\u4f4e\u65b0\u5be8"
    ],
    "wof:name":"Bidi Xinzhai",
    "wof:placetype":"locality"
},
  "geometry": {"coordinates":[99.74250000000001,23.0083],"type":"Point"}
}