{
  "type": "Feature",
  "properties": {
    "gn:admin1_code":"1.0",
    "gn:asciiname":"Yinhecun",
    "gn:country_code":"CN",
    "gn:dem":429,
    "gn:feature_class":"P",
    "gn:feature_code":"PPL",
    "gn:name":"Yinhecun",
    "gn:population":0,
    "gn:timezone":"Asia/Shanghai",
    "iso:country":"CN",
    "name:zho_x_preferred":[
        "\u94f6\u6cb3\u6751"
    ],
    "wof:name":"Yinhecun",
    "wof:placetype":"locality"
},
  "geometry": {"coordinates":[116.29053,31.07849],"type":"Point"}
}