{
  "type": "Feature",
  "properties": {
    "gn:admin1_code":"30.0",
    "gn:asciiname":"Changgeng",
    "gn:country_code":"CN",
    "gn:dem":615,
    "gn:feature_class":"P",
    "gn:feature_code":"PPL",
    "gn:name":"Changgeng",
    "gn:population":0,
    "gn:timezone":"Asia/Shanghai",
    "iso:country":"CN",
    "name:zho_x_preferred":[
        "Changgeng"
    ],
    "name:zho_x_variant":[
        "\u957f\u57c2"
    ],
    "wof:name":"Changgeng",
    "wof:placetype":"locality"
},
  "geometry": {"coordinates":[113.25534,25.03924],"type":"Point"}
}