{
  "type": "Feature",
  "properties": {
    "gn:admin1_code":"32.0",
    "gn:asciiname":"Longmenya",
    "gn:country_code":"CN",
    "gn:dem":459,
    "gn:feature_class":"P",
    "gn:feature_code":"PPL",
    "gn:name":"Longmenya",
    "gn:population":0,
    "gn:timezone":"Asia/Shanghai",
    "iso:country":"CN",
    "name:zho_x_preferred":[
        "\u9f99\u95e8\u57ad"
    ],
    "wof:name":"Longmenya",
    "wof:placetype":"locality"
},
  "geometry": {"coordinates":[105.26000000000001,30.7222],"type":"Point"}
}