{
  "type": "Feature",
  "properties": {
    "gn:admin1_code":"7",
    "gn:asciiname":"Xiping",
    "gn:country_code":"CN",
    "gn:dem":89,
    "gn:feature_class":"P",
    "gn:feature_code":"PPL",
    "gn:name":"Xiping",
    "gn:population":0,
    "gn:timezone":"Asia/Shanghai",
    "iso:country":"CN",
    "name:zho_x_preferred":[
        "\u6eaa\u576a"
    ],
    "wof:name":"Xiping",
    "wof:placetype":"locality"
},
  "geometry": {"coordinates":[117.42306000000001,24.03167],"type":"Point"}
}