{
  "type": "Feature",
  "properties": {
    "gn:admin1_code":"7.0",
    "gn:asciiname":"Guankeng",
    "gn:country_code":"CN",
    "gn:dem":362,
    "gn:feature_class":"P",
    "gn:feature_code":"PPL",
    "gn:name":"Guankeng",
    "gn:population":0,
    "gn:timezone":"Asia/Shanghai",
    "iso:country":"CN",
    "name:und_x_variant":[
        "\u5b98\u5751"
    ],
    "name:zho_x_preferred":[
        "\u5b98\u5751"
    ],
    "wof:name":"Guankeng",
    "wof:placetype":"locality"
},
  "geometry": {"coordinates":[116.50543999999999,26.26577],"type":"Point"}
}