{
  "type": "Feature",
  "properties": {
    "gn:admin1_code":"13",
    "gn:asciiname":"Aotula Maili",
    "gn:country_code":"CN",
    "gn:dem":1302,
    "gn:feature_class":"P",
    "gn:feature_code":"PPL",
    "gn:name":"Aotula Maili",
    "gn:population":0,
    "gn:timezone":"Asia/Shanghai",
    "iso:country":"CN",
    "name:und_x_variant":[
        "\u5965\u5410\u62c9\u4e70\u91cc"
    ],
    "wof:name":"Aotula Maili",
    "wof:placetype":"locality"
},
  "geometry": {"coordinates":[76.11946999999998,39.581],"type":"Point"}
}