{
  "type": "Feature",
  "properties": {
    "gn:admin1_code":"29.0",
    "gn:asciiname":"Changshui",
    "gn:country_code":"CN",
    "gn:dem":2412,
    "gn:feature_class":"P",
    "gn:feature_code":"PPL",
    "gn:name":"Changshui",
    "gn:population":0,
    "gn:timezone":"Asia/Shanghai",
    "iso:country":"CN",
    "name:zho_x_preferred":[
        "\u957f\u6c34"
    ],
    "wof:name":"Changshui",
    "wof:placetype":"locality"
},
  "geometry": {"coordinates":[100.18600000000001,26.8632],"type":"Point"}
}