{
  "type": "Feature",
  "properties": {
    "gn:admin1_code":"10.0",
    "gn:asciiname":"Senluozhai",
    "gn:country_code":"CN",
    "gn:dem":67,
    "gn:feature_class":"P",
    "gn:feature_code":"PPL",
    "gn:name":"Senluozhai",
    "gn:population":0,
    "gn:timezone":"Asia/Shanghai",
    "iso:country":"CN",
    "name:zho_x_preferred":[
        "\u68ee\u7f57\u5be8"
    ],
    "wof:name":"Senluozhai",
    "wof:placetype":"locality"
},
  "geometry": {"coordinates":[118.87199,40.1043],"type":"Point"}
}