{
  "type": "Feature",
  "properties": {
    "gn:admin1_code":"16.0",
    "gn:asciiname":"Nongmei",
    "gn:country_code":"CN",
    "gn:dem":970,
    "gn:feature_class":"P",
    "gn:feature_code":"PPL",
    "gn:name":"Nongmei",
    "gn:population":0,
    "gn:timezone":"Asia/Shanghai",
    "iso:country":"CN",
    "name:zho_x_preferred":[
        "\u5f04\u7f8e"
    ],
    "wof:name":"Nongmei",
    "wof:placetype":"locality"
},
  "geometry": {"coordinates":[106.02800000000001,23.3583],"type":"Point"}
}