{
  "type": "Feature",
  "properties": {
    "gn:admin1_code":"8.0",
    "gn:asciiname":"Fuhuacun",
    "gn:country_code":"CN",
    "gn:dem":48,
    "gn:feature_class":"P",
    "gn:feature_code":"PPL",
    "gn:name":"Fuhuacun",
    "gn:population":0,
    "gn:timezone":"Asia/Shanghai",
    "iso:country":"CN",
    "name:zho_x_preferred":[
        "\u5bcc\u534e\u6751"
    ],
    "wof:name":"Fuhuacun",
    "wof:placetype":"locality"
},
  "geometry": {"coordinates":[133.51381999999998,48.06423],"type":"Point"}
}