{
  "type": "Feature",
  "properties": {
    "gn:admin1_code":"11.0",
    "gn:asciiname":"Liushanping",
    "gn:country_code":"CN",
    "gn:dem":224,
    "gn:feature_class":"P",
    "gn:feature_code":"PPL",
    "gn:name":"Liushanping",
    "gn:population":0,
    "gn:timezone":"Asia/Shanghai",
    "iso:country":"CN",
    "name:zho_x_preferred":[
        "\u67f3\u5c71\u576a"
    ],
    "wof:name":"Liushanping",
    "wof:placetype":"locality"
},
  "geometry": {"coordinates":[110.93171,28.07302],"type":"Point"}
}