{
  "type": "Feature",
  "properties": {
    "gn:admin1_code":"09",
    "gn:asciiname":"Bidian",
    "gn:cc2":"CN",
    "gn:country_code":"CN",
    "gn:dem":143,
    "gn:feature_class":"P",
    "gn:feature_code":"PPL",
    "gn:name":"Bidian",
    "gn:population":0,
    "gn:timezone":"Asia/Shanghai",
    "iso:country":"CN",
    "name:und_x_variant":[
        "Pi-tien",
        "Pi-tien-chen",
        "Bidian"
    ],
    "wof:name":"Bidian",
    "wof:placetype":"locality"
},
  "geometry": {"coordinates":[113.05389,32.63333],"type":"Point"}
}