{
  "type": "Feature",
  "properties": {
    "gn:admin1_code":"4.0",
    "gn:asciiname":"Chengxu",
    "gn:country_code":"CN",
    "gn:dem":2,
    "gn:feature_class":"P",
    "gn:feature_code":"PPL",
    "gn:name":"Chengxu",
    "gn:population":0,
    "gn:timezone":"Asia/Shanghai",
    "iso:country":"CN",
    "name:zho_x_preferred":[
        "Chengxu"
    ],
    "name:zho_x_variant":[
        "\u7a0b\u5729"
    ],
    "wof:name":"Chengxu",
    "wof:placetype":"locality"
},
  "geometry": {"coordinates":[119.37012,34.49012],"type":"Point"}
}