{
  "type": "Feature",
  "properties": {
    "gn:admin1_code":"30",
    "gn:asciiname":"Daba",
    "gn:country_code":"CN",
    "gn:dem":45,
    "gn:feature_class":"P",
    "gn:feature_code":"PPLA4",
    "gn:name":"Daba",
    "gn:population":0,
    "gn:timezone":"Asia/Shanghai",
    "iso:country":"CN",
    "name:ceb_x_preferred":[
        "Daba"
    ],
    "name:fra_x_preferred":[
        "Daba"
    ],
    "name:kat_x_preferred":[
        "\u10d3\u10d0\u10d1\u10d0"
    ],
    "name:rus_x_preferred":[
        "\u0414\u0430\u0431\u0430"
    ],
    "name:swe_x_preferred":[
        "Daba"
    ],
    "name:und_x_variant":[
        "Ta-pa-hs\u00fc",
        "Daba Zhen",
        "\u5927\u516b\u9547"
    ],
    "name:zho_x_preferred":[
        "\u5927\u516b"
    ],
    "wof:name":"Daba",
    "wof:placetype":"locality"
},
  "geometry": {"coordinates":[111.96034,22.07338],"type":"Point"}
}