{
  "type": "Feature",
  "properties": {
    "gn:admin1_code":"30.0",
    "gn:asciiname":"Kengmencun",
    "gn:country_code":"CN",
    "gn:dem":31,
    "gn:feature_class":"P",
    "gn:feature_code":"PPL",
    "gn:name":"Kengmencun",
    "gn:population":0,
    "gn:timezone":"Asia/Shanghai",
    "iso:country":"CN",
    "name:zho_x_preferred":[
        "\u5751\u95e8\u6751"
    ],
    "wof:name":"Kengmencun",
    "wof:placetype":"locality"
},
  "geometry": {"coordinates":[116.79953999999999,23.62882],"type":"Point"}
}