{
  "type": "Feature",
  "properties": {
    "gn:admin1_code":"9.0",
    "gn:asciiname":"Houhouzhuang",
    "gn:country_code":"CN",
    "gn:dem":229,
    "gn:feature_class":"P",
    "gn:feature_code":"PPL",
    "gn:name":"Houhouzhuang",
    "gn:population":0,
    "gn:timezone":"Asia/Shanghai",
    "iso:country":"CN",
    "name:zho_x_preferred":[
        "\u540e\u4faf\u5e84"
    ],
    "wof:name":"Houhouzhuang",
    "wof:placetype":"locality"
},
  "geometry": {"coordinates":[112.75958,33.37866],"type":"Point"}
}