{
  "type": "Feature",
  "properties": {
    "gn:admin1_code":"33.0",
    "gn:asciiname":"Huangbai'ao",
    "gn:country_code":"CN",
    "gn:dem":1120,
    "gn:feature_class":"P",
    "gn:feature_code":"PPL",
    "gn:name":"Huangbai\u2019ao",
    "gn:population":0,
    "gn:timezone":"Asia/Shanghai",
    "iso:country":"CN",
    "name:und_x_variant":[
        "Huangbai\u2019ao"
    ],
    "name:zho_x_preferred":[
        "\u9ec4\u767d\u5773"
    ],
    "wof:name":"Huangbai'ao",
    "wof:placetype":"locality"
},
  "geometry": {"coordinates":[108.7608,28.23005],"type":"Point"}
}