{
  "type": "Feature",
  "properties": {
    "gn:admin1_code":"10.0",
    "gn:asciiname":"Nandawangzhuang",
    "gn:country_code":"CN",
    "gn:dem":9,
    "gn:feature_class":"P",
    "gn:feature_code":"PPL",
    "gn:name":"Nandawangzhuang",
    "gn:population":0,
    "gn:timezone":"Asia/Shanghai",
    "iso:country":"CN",
    "name:zho_x_preferred":[
        "\u5357\u5927\u738b\u5e84"
    ],
    "wof:name":"Nandawangzhuang",
    "wof:placetype":"locality"
},
  "geometry": {"coordinates":[116.57682,39.1751],"type":"Point"}
}