{
  "type": "Feature",
  "properties": {
    "gn:admin1_code":"1.0",
    "gn:asciiname":"Nanhuzhaocun",
    "gn:country_code":"CN",
    "gn:dem":64,
    "gn:feature_class":"P",
    "gn:feature_code":"PPL",
    "gn:name":"Nanhuzhaocun",
    "gn:population":0,
    "gn:timezone":"Asia/Shanghai",
    "iso:country":"CN",
    "name:zho_x_preferred":[
        "\u5357\u6237\u8d75\u6751"
    ],
    "wof:name":"Nanhuzhaocun",
    "wof:placetype":"locality"
},
  "geometry": {"coordinates":[117.61523,32.31248],"type":"Point"}
}