{
  "type": "Feature",
  "properties": {
    "gn:admin1_code":"29.0",
    "gn:asciiname":"Zhonglupi",
    "gn:country_code":"CN",
    "gn:dem":1891,
    "gn:feature_class":"P",
    "gn:feature_code":"PPL",
    "gn:name":"Zhonglupi",
    "gn:population":0,
    "gn:timezone":"Asia/Shanghai",
    "iso:country":"CN",
    "name:zho_x_preferred":[
        "\u4e2d\u9c81\u4e15"
    ],
    "wof:name":"Zhonglupi",
    "wof:placetype":"locality"
},
  "geometry": {"coordinates":[100.113,24.773],"type":"Point"}
}