{
  "type": "Feature",
  "properties": {
    "gn:admin1_code":"32.0",
    "gn:asciiname":"Yaofang",
    "gn:country_code":"CN",
    "gn:dem":466,
    "gn:feature_class":"P",
    "gn:feature_code":"PPL",
    "gn:name":"Yaofang",
    "gn:population":0,
    "gn:timezone":"Asia/Shanghai",
    "iso:country":"CN",
    "name:zho_x_preferred":[
        "\u4e48\u623f"
    ],
    "wof:name":"Yaofang",
    "wof:placetype":"locality"
},
  "geometry": {"coordinates":[104.93344999999999,31.21107],"type":"Point"}
}