{
  "type": "Feature",
  "properties": {
    "gn:admin1_code":"21.0",
    "gn:asciiname":"Xidatan",
    "gn:cc2":"CN",
    "gn:country_code":"CN",
    "gn:dem":1101,
    "gn:feature_class":"P",
    "gn:feature_code":"PPL",
    "gn:name":"Xidatan",
    "gn:population":0,
    "gn:timezone":"Asia/Shanghai",
    "iso:country":"CN",
    "name:und_x_variant":[
        "Hsi-ta-t\u2019an",
        "Xidatan"
    ],
    "wof:name":"Xidatan",
    "wof:placetype":"locality"
},
  "geometry": {"coordinates":[106.3725,38.84667],"type":"Point"}
}