{
  "type": "Feature",
  "properties": {
    "gn:admin1_code":"10",
    "gn:asciiname":"Maoshanzhuang",
    "gn:country_code":"CN",
    "gn:dem":40,
    "gn:feature_class":"P",
    "gn:feature_code":"PPL",
    "gn:name":"Maoshanzhuang",
    "gn:population":0,
    "gn:timezone":"Asia/Shanghai",
    "iso:country":"CN",
    "name:zho_x_preferred":[
        "\u8305\u5c71\u5e84"
    ],
    "wof:name":"Maoshanzhuang",
    "wof:placetype":"locality"
},
  "geometry": {"coordinates":[114.71599999999999,37.4056],"type":"Point"}
}