{
  "type": "Feature",
  "properties": {
    "gn:admin1_code":"19.0",
    "gn:asciiname":"Jiahexin",
    "gn:country_code":"CN",
    "gn:dem":80,
    "gn:feature_class":"P",
    "gn:feature_code":"PPL",
    "gn:name":"Jiahexin",
    "gn:population":0,
    "gn:timezone":"Asia/Shanghai",
    "iso:country":"CN",
    "name:und_x_variant":[
        "\u5939\u6cb3\u5fc3"
    ],
    "name:zho_x_preferred":[
        "\u5939\u6cb3\u5fc3"
    ],
    "wof:name":"Jiahexin",
    "wof:placetype":"locality"
},
  "geometry": {"coordinates":[122.06853999999998,39.80676],"type":"Point"}
}