{
  "type": "Feature",
  "properties": {
    "gn:admin1_code":"29.0",
    "gn:asciiname":"Jingkeng",
    "gn:country_code":"CN",
    "gn:dem":633,
    "gn:feature_class":"P",
    "gn:feature_code":"PPL",
    "gn:name":"Jingkeng",
    "gn:population":0,
    "gn:timezone":"Asia/Shanghai",
    "iso:country":"CN",
    "name:zho_x_preferred":[
        "\u666f\u5751"
    ],
    "wof:name":"Jingkeng",
    "wof:placetype":"locality"
},
  "geometry": {"coordinates":[100.893,21.9306],"type":"Point"}
}