{
  "type": "Feature",
  "properties": {
    "gn:admin1_code":"15.0",
    "gn:asciiname":"Daquan",
    "gn:country_code":"CN",
    "gn:dem":4124,
    "gn:feature_class":"P",
    "gn:feature_code":"PPL",
    "gn:name":"Daquan",
    "gn:population":0,
    "gn:timezone":"Asia/Urumqi",
    "iso:country":"CN",
    "wof:name":"Daquan",
    "wof:placetype":"locality"
},
  "geometry": {"coordinates":[96.31667,39.25],"type":"Point"}
}