{
  "type": "Feature",
  "properties": {
    "gn:admin1_code":"29",
    "gn:asciiname":"Laxida",
    "gn:country_code":"CN",
    "gn:dem":1646,
    "gn:feature_class":"P",
    "gn:feature_code":"PPL",
    "gn:name":"Laxida",
    "gn:population":0,
    "gn:timezone":"Asia/Shanghai",
    "iso:country":"CN",
    "name:zho_x_preferred":[
        "\u62c9\u7ec6\u8fbe"
    ],
    "wof:name":"Laxida",
    "wof:placetype":"locality"
},
  "geometry": {"coordinates":[102.03,24.8215],"type":"Point"}
}