{
  "type": "Feature",
  "properties": {
    "gn:admin1_code":"29.0",
    "gn:asciiname":"Dadaiping",
    "gn:country_code":"CN",
    "gn:dem":1539,
    "gn:feature_class":"P",
    "gn:feature_code":"PPL",
    "gn:name":"Dadaiping",
    "gn:population":0,
    "gn:timezone":"Asia/Shanghai",
    "iso:country":"CN",
    "name:zho_x_preferred":[
        "\u8fbe\u4ee3\u576a"
    ],
    "wof:name":"Dadaiping",
    "wof:placetype":"locality"
},
  "geometry": {"coordinates":[100.928,26.2166],"type":"Point"}
}