{
  "type": "Feature",
  "properties": {
    "gn:admin1_code":"29.0",
    "gn:asciiname":"Xiaoniuchang",
    "gn:country_code":"CN",
    "gn:dem":1872,
    "gn:feature_class":"P",
    "gn:feature_code":"PPL",
    "gn:name":"Xiaoniuchang",
    "gn:population":0,
    "gn:timezone":"Asia/Shanghai",
    "iso:country":"CN",
    "name:zho_x_preferred":[
        "\u5c0f\u725b\u5382"
    ],
    "wof:name":"Xiaoniuchang",
    "wof:placetype":"locality"
},
  "geometry": {"coordinates":[103.21599999999999,26.0562],"type":"Point"}
}