{
  "type": "Feature",
  "properties": {
    "gn:admin1_code":"30.0",
    "gn:asciiname":"Yixicun",
    "gn:country_code":"CN",
    "gn:dem":19,
    "gn:feature_class":"P",
    "gn:feature_code":"PPL",
    "gn:name":"Yixicun",
    "gn:population":0,
    "gn:timezone":"Asia/Shanghai",
    "iso:country":"CN",
    "name:zho_x_preferred":[
        "\u6ea2\u6eaa\u6751"
    ],
    "wof:name":"Yixicun",
    "wof:placetype":"locality"
},
  "geometry": {"coordinates":[116.29136,23.64941],"type":"Point"}
}