{
  "type": "Feature",
  "properties": {
    "gn:admin1_code":"18",
    "gn:asciiname":"Baiyanjiao",
    "gn:country_code":"CN",
    "gn:dem":1770,
    "gn:feature_class":"P",
    "gn:feature_code":"PPL",
    "gn:name":"Baiyanjiao",
    "gn:population":0,
    "gn:timezone":"Asia/Shanghai",
    "iso:country":"CN",
    "name:zho_x_preferred":[
        "\u767d\u5ca9\u811a"
    ],
    "wof:name":"Baiyanjiao",
    "wof:placetype":"locality"
},
  "geometry": {"coordinates":[105.691,27.5029],"type":"Point"}
}