{
  "type": "Feature",
  "properties": {
    "gn:admin1_code":"32.0",
    "gn:asciiname":"Sifuwan",
    "gn:country_code":"CN",
    "gn:dem":948,
    "gn:feature_class":"P",
    "gn:feature_code":"PPL",
    "gn:name":"Sifuwan",
    "gn:population":0,
    "gn:timezone":"Asia/Shanghai",
    "iso:country":"CN",
    "name:zho_x_preferred":[
        "\u56db\u5085\u6e7e"
    ],
    "wof:name":"Sifuwan",
    "wof:placetype":"locality"
},
  "geometry": {"coordinates":[107.422,32.0788],"type":"Point"}
}