{
  "type": "Feature",
  "properties": {
    "gn:admin1_code":"29.0",
    "gn:asciiname":"Mibenghe Xiazhai",
    "gn:country_code":"CN",
    "gn:dem":1326,
    "gn:feature_class":"P",
    "gn:feature_code":"PPL",
    "gn:name":"Mibenghe Xiazhai",
    "gn:population":0,
    "gn:timezone":"Asia/Shanghai",
    "iso:country":"CN",
    "name:zho_x_preferred":[
        "\u5bc6\u868c\u6cb3\u4e0b\u5be8"
    ],
    "wof:name":"Mibenghe Xiazhai",
    "wof:placetype":"locality"
},
  "geometry": {"coordinates":[100.179,22.1247],"type":"Point"}
}