{
  "type": "Feature",
  "properties": {
    "gn:admin1_code":"11.0",
    "gn:asciiname":"Shuibu'ao",
    "gn:country_code":"CN",
    "gn:dem":784,
    "gn:feature_class":"P",
    "gn:feature_code":"PPL",
    "gn:name":"Shuibu\u2019ao",
    "gn:population":0,
    "gn:timezone":"Asia/Shanghai",
    "iso:country":"CN",
    "name:und_x_variant":[
        "Shuibu\u2019ao"
    ],
    "name:zho_x_preferred":[
        "\u6c34\u6b65\u5773"
    ],
    "wof:name":"Shuibu'ao",
    "wof:placetype":"locality"
},
  "geometry": {"coordinates":[110.1626,26.10613],"type":"Point"}
}