{
  "type": "Feature",
  "properties": {
    "gn:admin1_code":"33.0",
    "gn:asciiname":"Qiyuan",
    "gn:country_code":"CN",
    "gn:dem":1250,
    "gn:feature_class":"P",
    "gn:feature_code":"PPL",
    "gn:name":"Qiyuan",
    "gn:population":0,
    "gn:timezone":"Asia/Shanghai",
    "iso:country":"CN",
    "name:zho_x_preferred":[
        "\u6f06\u56ed"
    ],
    "wof:name":"Qiyuan",
    "wof:placetype":"locality"
},
  "geometry": {"coordinates":[108.07496999999999,29.51968],"type":"Point"}
}