{
  "type": "Feature",
  "properties": {
    "gn:admin1_code":"29.0",
    "gn:asciiname":"Longzhuang",
    "gn:country_code":"CN",
    "gn:dem":1926,
    "gn:feature_class":"P",
    "gn:feature_code":"PPL",
    "gn:name":"Longzhuang",
    "gn:population":0,
    "gn:timezone":"Asia/Shanghai",
    "iso:country":"CN",
    "name:und_x_variant":[
        "\u9686\u5e84"
    ],
    "wof:name":"Longzhuang",
    "wof:placetype":"locality"
},
  "geometry": {"coordinates":[104.23251,26.20393],"type":"Point"}
}