{
  "type": "Feature",
  "properties": {
    "gn:admin1_code":"11.0",
    "gn:asciiname":"Leijiapeng",
    "gn:country_code":"CN",
    "gn:dem":221,
    "gn:feature_class":"P",
    "gn:feature_code":"PPL",
    "gn:name":"Leijiapeng",
    "gn:population":0,
    "gn:timezone":"Asia/Shanghai",
    "iso:country":"CN",
    "name:zho_x_preferred":[
        "\u96f7\u5bb6\u68da"
    ],
    "wof:name":"Leijiapeng",
    "wof:placetype":"locality"
},
  "geometry": {"coordinates":[111.08653,28.20801],"type":"Point"}
}