{
  "type": "Feature",
  "properties": {
    "gn:admin1_code":"29.0",
    "gn:asciiname":"Yanpeng",
    "gn:country_code":"CN",
    "gn:dem":1839,
    "gn:feature_class":"P",
    "gn:feature_code":"PPL",
    "gn:name":"Yanpeng",
    "gn:population":0,
    "gn:timezone":"Asia/Shanghai",
    "iso:country":"CN",
    "name:zho_x_preferred":[
        "\u5ca9\u68da"
    ],
    "wof:name":"Yanpeng",
    "wof:placetype":"locality"
},
  "geometry": {"coordinates":[100.38,25.7472],"type":"Point"}
}