{
  "type": "Feature",
  "properties": {
    "gn:admin1_code":"12.0",
    "gn:asciiname":"Caochiping",
    "gn:country_code":"CN",
    "gn:dem":1179,
    "gn:feature_class":"P",
    "gn:feature_code":"PPL",
    "gn:name":"Caochiping",
    "gn:population":0,
    "gn:timezone":"Asia/Shanghai",
    "iso:country":"CN",
    "name:zho_x_preferred":[
        "\u8349\u6c60\u576a"
    ],
    "wof:name":"Caochiping",
    "wof:placetype":"locality"
},
  "geometry": {"coordinates":[110.30457,31.84652],"type":"Point"}
}