{
  "type": "Feature",
  "properties": {
    "gn:admin1_code":"29.0",
    "gn:asciiname":"Taheng",
    "gn:country_code":"CN",
    "gn:dem":2097,
    "gn:feature_class":"P",
    "gn:feature_code":"PPL",
    "gn:name":"Taheng",
    "gn:population":0,
    "gn:timezone":"Asia/Shanghai",
    "iso:country":"CN",
    "name:zho_x_preferred":[
        "\u5b83\u4ea8"
    ],
    "wof:name":"Taheng",
    "wof:placetype":"locality"
},
  "geometry": {"coordinates":[102.209,25.8649],"type":"Point"}
}