{
  "type": "Feature",
  "properties": {
    "gn:admin1_code":"8.0",
    "gn:asciiname":"Rongfacun",
    "gn:country_code":"CN",
    "gn:dem":193,
    "gn:feature_class":"P",
    "gn:feature_code":"PPL",
    "gn:name":"Rongfacun",
    "gn:population":0,
    "gn:timezone":"Asia/Shanghai",
    "iso:country":"CN",
    "name:zho_x_preferred":[
        "\u8363\u53d1\u6751"
    ],
    "wof:name":"Rongfacun",
    "wof:placetype":"locality"
},
  "geometry": {"coordinates":[127.21359,46.46982],"type":"Point"}
}