{
  "type": "Feature",
  "properties": {
    "gn:admin1_code":"4.0",
    "gn:asciiname":"Xiongliucun",
    "gn:country_code":"CN",
    "gn:dem":6,
    "gn:feature_class":"P",
    "gn:feature_code":"PPL",
    "gn:name":"Xiongliucun",
    "gn:population":0,
    "gn:timezone":"Asia/Shanghai",
    "iso:country":"CN",
    "name:zho_x_preferred":[
        "\u718a\u67f3\u6751"
    ],
    "wof:name":"Xiongliucun",
    "wof:placetype":"locality"
},
  "geometry": {"coordinates":[118.96472,32.26569],"type":"Point"}
}