{
  "type": "Feature",
  "properties": {
    "gn:admin1_code":"10.0",
    "gn:asciiname":"Wuguanying",
    "gn:country_code":"CN",
    "gn:dem":101,
    "gn:feature_class":"P",
    "gn:feature_code":"PPL",
    "gn:name":"Wuguanying",
    "gn:population":0,
    "gn:timezone":"Asia/Shanghai",
    "iso:country":"CN",
    "name:zho_x_preferred":[
        "\u5434\u5b98\u8425"
    ],
    "wof:name":"Wuguanying",
    "wof:placetype":"locality"
},
  "geometry": {"coordinates":[118.5735,40.06188],"type":"Point"}
}