{
  "type": "Feature",
  "properties": {
    "gn:admin1_code":"30.0",
    "gn:asciiname":"Xiaoliaoshui",
    "gn:country_code":"CN",
    "gn:dem":348,
    "gn:feature_class":"P",
    "gn:feature_code":"PPL",
    "gn:name":"Xiaoliaoshui",
    "gn:population":0,
    "gn:timezone":"Asia/Shanghai",
    "iso:country":"CN",
    "name:zho_x_preferred":[
        "Xiaoliaoshui"
    ],
    "name:zho_x_variant":[
        "\u5c0f\u8fbd\u6c34"
    ],
    "wof:name":"Xiaoliaoshui",
    "wof:placetype":"locality"
},
  "geometry": {"coordinates":[113.03888999999999,25.20167],"type":"Point"}
}