{
  "type": "Feature",
  "properties": {
    "gn:admin1_code":"4.0",
    "gn:asciiname":"Laoma Jiadai",
    "gn:country_code":"CN",
    "gn:dem":4,
    "gn:feature_class":"P",
    "gn:feature_code":"PPL",
    "gn:name":"Laoma Jiadai",
    "gn:population":0,
    "gn:timezone":"Asia/Shanghai",
    "iso:country":"CN",
    "name:zho_x_preferred":[
        "\u8001\u9a6c\u5bb6\u5788"
    ],
    "wof:name":"Laoma Jiadai",
    "wof:placetype":"locality"
},
  "geometry": {"coordinates":[120.19171,32.0522],"type":"Point"}
}