{
  "type": "Feature",
  "properties": {
    "gn:admin1_code":"26.0",
    "gn:asciiname":"Duiwogou",
    "gn:country_code":"CN",
    "gn:dem":1388,
    "gn:feature_class":"P",
    "gn:feature_code":"PPL",
    "gn:name":"Duiwogou",
    "gn:population":0,
    "gn:timezone":"Asia/Shanghai",
    "iso:country":"CN",
    "name:und_x_variant":[
        "\u7893\u7a9d\u6c9f"
    ],
    "wof:name":"Duiwogou",
    "wof:placetype":"locality"
},
  "geometry": {"coordinates":[106.58078999999999,33.30963],"type":"Point"}
}