{
  "type": "Feature",
  "properties": {
    "gn:admin1_code":"30.0",
    "gn:asciiname":"Yanqian",
    "gn:country_code":"CN",
    "gn:dem":442,
    "gn:feature_class":"P",
    "gn:feature_code":"PPL",
    "gn:name":"Yanqian",
    "gn:population":0,
    "gn:timezone":"Asia/Shanghai",
    "iso:country":"CN",
    "name:zho_x_preferred":[
        "Yanqian"
    ],
    "name:zho_x_variant":[
        "\u5ca9\u524d"
    ],
    "wof:name":"Yanqian",
    "wof:placetype":"locality"
},
  "geometry": {"coordinates":[115.11306,24.13694],"type":"Point"}
}