{
  "type": "Feature",
  "properties": {
    "gn:admin1_code":"18",
    "gn:asciiname":"Gouchangba",
    "gn:country_code":"CN",
    "gn:dem":1683,
    "gn:feature_class":"P",
    "gn:feature_code":"PPL",
    "gn:name":"Gouchangba",
    "gn:population":0,
    "gn:timezone":"Asia/Shanghai",
    "iso:country":"CN",
    "name:zho_x_preferred":[
        "\u72d7\u573a\u575d"
    ],
    "wof:name":"Gouchangba",
    "wof:placetype":"locality"
},
  "geometry": {"coordinates":[104.782,25.4082],"type":"Point"}
}