{
  "type": "Feature",
  "properties": {
    "gn:admin1_code":"32",
    "gn:asciiname":"Daxincun",
    "gn:country_code":"CN",
    "gn:dem":498,
    "gn:feature_class":"P",
    "gn:feature_code":"PPL",
    "gn:name":"Daxincun",
    "gn:population":0,
    "gn:timezone":"Asia/Shanghai",
    "iso:country":"CN",
    "name:zho_x_preferred":[
        "\u5927\u65b0\u6751"
    ],
    "wof:name":"Daxincun",
    "wof:placetype":"locality"
},
  "geometry": {"coordinates":[105.42443,31.49397],"type":"Point"}
}