{
  "type": "Feature",
  "properties": {
    "gn:admin1_code":"5.0",
    "gn:asciiname":"Dadianzi",
    "gn:country_code":"CN",
    "gn:dem":169,
    "gn:feature_class":"P",
    "gn:feature_code":"PPL",
    "gn:name":"Dadianzi",
    "gn:population":0,
    "gn:timezone":"Asia/Shanghai",
    "iso:country":"CN",
    "name:und_x_variant":[
        "\u5927\u7538\u5b50"
    ],
    "wof:name":"Dadianzi",
    "wof:placetype":"locality"
},
  "geometry": {"coordinates":[125.90839,40.96115],"type":"Point"}
}