{
  "type": "Feature",
  "properties": {
    "gn:admin1_code":"3",
    "gn:asciiname":"Huashi",
    "gn:country_code":"CN",
    "gn:dem":210,
    "gn:feature_class":"P",
    "gn:feature_code":"PPL",
    "gn:name":"Huashi",
    "gn:population":0,
    "gn:timezone":"Asia/Shanghai",
    "iso:country":"CN",
    "name:deu_x_preferred":[
        "Huashi"
    ],
    "name:zho_x_preferred":[
        "\u82b1\u77f3"
    ],
    "wof:name":"Huashi",
    "wof:placetype":"locality"
},
  "geometry": {"coordinates":[113.92100000000001,26.9365],"type":"Point"}
}