{
  "type": "Feature",
  "properties": {
    "gn:admin1_code":"02",
    "gn:asciiname":"Hengxi",
    "gn:cc2":"CN",
    "gn:country_code":"CN",
    "gn:dem":151,
    "gn:feature_class":"P",
    "gn:feature_code":"PPL",
    "gn:name":"Hengxi",
    "gn:population":0,
    "gn:timezone":"Asia/Shanghai",
    "iso:country":"CN",
    "name:und_x_variant":[
        "Heng-hsi",
        "Hengxi"
    ],
    "wof:name":"Hengxi",
    "wof:placetype":"locality"
},
  "geometry": {"coordinates":[119.81361,29.36278],"type":"Point"}
}