{
  "type": "Feature",
  "properties": {
    "gn:admin1_code":"14.0",
    "gn:asciiname":"Gamaniangcun",
    "gn:country_code":"CN",
    "gn:dem":4711,
    "gn:feature_class":"P",
    "gn:feature_code":"PPL",
    "gn:name":"Gamaniangcun",
    "gn:population":0,
    "gn:timezone":"Asia/Urumqi",
    "iso:country":"CN",
    "name:zho_x_preferred":[
        "\u560e\u739b\u5a18\u6751"
    ],
    "wof:name":"Gamaniangcun",
    "wof:placetype":"locality"
},
  "geometry": {"coordinates":[92.64579999999999,32.06119],"type":"Point"}
}