{
  "type": "Feature",
  "properties": {
    "gn:admin1_code":"18",
    "gn:asciiname":"Jijia",
    "gn:country_code":"CN",
    "gn:dem":2388,
    "gn:feature_class":"P",
    "gn:feature_code":"PPL",
    "gn:name":"Jijia",
    "gn:population":0,
    "gn:timezone":"Asia/Shanghai",
    "iso:country":"CN",
    "name:zho_x_preferred":[
        "\u59ec\u5bb6"
    ],
    "wof:name":"Jijia",
    "wof:placetype":"locality"
},
  "geometry": {"coordinates":[103.771,26.7683],"type":"Point"}
}