{
  "type": "Feature",
  "properties": {
    "gn:admin1_code":"4.0",
    "gn:asciiname":"Erkancun",
    "gn:country_code":"CN",
    "gn:dem":4,
    "gn:feature_class":"P",
    "gn:feature_code":"PPL",
    "gn:name":"Erkancun",
    "gn:population":0,
    "gn:timezone":"Asia/Shanghai",
    "iso:country":"CN",
    "name:zho_x_preferred":[
        "\u4e8c\u574e\u6751"
    ],
    "wof:name":"Erkancun",
    "wof:placetype":"locality"
},
  "geometry": {"coordinates":[119.83929000000001,34.05353],"type":"Point"}
}