{
  "type": "Feature",
  "properties": {
    "gn:admin1_code":"14",
    "gn:asciiname":"Pinchalong",
    "gn:country_code":"CN",
    "gn:dem":4706,
    "gn:feature_class":"P",
    "gn:feature_code":"PPL",
    "gn:name":"Pinchalong",
    "gn:population":0,
    "gn:timezone":"Asia/Urumqi",
    "iso:country":"CN",
    "name:zho_x_preferred":[
        "\u8d2b\u8336\u9f99"
    ],
    "wof:name":"Pinchalong",
    "wof:placetype":"locality"
},
  "geometry": {"coordinates":[89.6309,29.7215],"type":"Point"}
}