{
  "type": "Feature",
  "properties": {
    "gn:admin1_code":"19.0",
    "gn:asciiname":"Lijia Buzi",
    "gn:country_code":"CN",
    "gn:dem":126,
    "gn:feature_class":"P",
    "gn:feature_code":"PPL",
    "gn:name":"Lijia Buzi",
    "gn:population":0,
    "gn:timezone":"Asia/Shanghai",
    "iso:country":"CN",
    "name:und_x_variant":[
        "Lijia Puzi",
        "Lijia Buzi"
    ],
    "name:zho_x_preferred":[
        "\u674e\u5bb6\u5821\u5b50"
    ],
    "wof:name":"Lijia Buzi",
    "wof:placetype":"locality"
},
  "geometry": {"coordinates":[123.35626000000001,40.18598],"type":"Point"}
}