{
  "type": "Feature",
  "properties": {
    "gn:admin1_code":"29",
    "gn:asciiname":"Shangjiage",
    "gn:country_code":"CN",
    "gn:dem":1827,
    "gn:feature_class":"P",
    "gn:feature_code":"PPL",
    "gn:name":"Shangjiage",
    "gn:population":0,
    "gn:timezone":"Asia/Shanghai",
    "iso:country":"CN",
    "name:zho_x_preferred":[
        "\u4e0a\u67b6\u683c"
    ],
    "wof:name":"Shangjiage",
    "wof:placetype":"locality"
},
  "geometry": {"coordinates":[103.212,24.0618],"type":"Point"}
}