{
  "type": "Feature",
  "properties": {
    "gn:admin1_code":"15.0",
    "gn:asciiname":"Shangyou Dadui",
    "gn:country_code":"CN",
    "gn:dem":2123,
    "gn:feature_class":"P",
    "gn:feature_code":"PPLF",
    "gn:name":"Shangyou Dadui",
    "gn:population":0,
    "gn:timezone":"Asia/Shanghai",
    "iso:country":"CN",
    "name:zho_x_preferred":[
        "\u4e0a\u6e38\u5927\u961f"
    ],
    "wof:name":"Shangyou Dadui",
    "wof:placetype":"locality"
},
  "geometry": {"coordinates":[96.71639999999999,39.836],"type":"Point"}
}