{
  "type": "Feature",
  "properties": {
    "gn:admin1_code":"25",
    "gn:asciiname":"Sunjiashigou",
    "gn:country_code":"CN",
    "gn:dem":106,
    "gn:feature_class":"P",
    "gn:feature_code":"PPL",
    "gn:name":"Sunjiashigou",
    "gn:population":0,
    "gn:timezone":"Asia/Shanghai",
    "iso:country":"CN",
    "name:zho_x_preferred":[
        "\u5b59\u5bb6\u4ed5\u6c9f"
    ],
    "wof:name":"Sunjiashigou",
    "wof:placetype":"locality"
},
  "geometry": {"coordinates":[118.776,35.3005],"type":"Point"}
}