{
  "type": "Feature",
  "properties": {
    "gn:admin1_code":"8.0",
    "gn:asciiname":"Yujia Fenfang",
    "gn:country_code":"CN",
    "gn:dem":316,
    "gn:feature_class":"P",
    "gn:feature_code":"PPL",
    "gn:name":"Yujia Fenfang",
    "gn:population":0,
    "gn:timezone":"Asia/Shanghai",
    "iso:country":"CN",
    "name:zho_x_preferred":[
        "\u4e8e\u5bb6\u7c89\u623f"
    ],
    "wof:name":"Yujia Fenfang",
    "wof:placetype":"locality"
},
  "geometry": {"coordinates":[125.75986,48.43665],"type":"Point"}
}