{
  "type": "Feature",
  "properties": {
    "gn:admin1_code":"26.0",
    "gn:asciiname":"Weijiayaoke",
    "gn:country_code":"CN",
    "gn:dem":1143,
    "gn:feature_class":"P",
    "gn:feature_code":"PPL",
    "gn:name":"Weijiayaoke",
    "gn:population":0,
    "gn:timezone":"Asia/Shanghai",
    "iso:country":"CN",
    "name:zho_x_preferred":[
        "\u9b4f\u5bb6\u7a91\u79d1"
    ],
    "wof:name":"Weijiayaoke",
    "wof:placetype":"locality"
},
  "geometry": {"coordinates":[110.03903,36.38512],"type":"Point"}
}