{
  "type": "Feature",
  "properties": {
    "gn:admin1_code":"20.0",
    "gn:asciiname":"Huangdiliang",
    "gn:country_code":"CN",
    "gn:dem":1197,
    "gn:feature_class":"P",
    "gn:feature_code":"PPL",
    "gn:name":"Huangdiliang",
    "gn:population":0,
    "gn:timezone":"Asia/Shanghai",
    "iso:country":"CN",
    "name:und_x_variant":[
        "\u8352\u5730\u6881"
    ],
    "wof:name":"Huangdiliang",
    "wof:placetype":"locality"
},
  "geometry": {"coordinates":[111.43049999999999,39.70144000000001],"type":"Point"}
}