{
  "type": "Feature",
  "properties": {
    "gn:admin1_code":"11.0",
    "gn:asciiname":"Shitangchong",
    "gn:country_code":"CN",
    "gn:dem":107,
    "gn:feature_class":"P",
    "gn:feature_code":"PPL",
    "gn:name":"Shitangchong",
    "gn:population":0,
    "gn:timezone":"Asia/Shanghai",
    "iso:country":"CN",
    "name:zho_x_preferred":[
        "\u77f3\u5858\u51b2"
    ],
    "wof:name":"Shitangchong",
    "wof:placetype":"locality"
},
  "geometry": {"coordinates":[113.4538,27.1944],"type":"Point"}
}