{
  "type": "Feature",
  "properties": {
    "gn:admin1_code":"5.0",
    "gn:asciiname":"Houdazitun",
    "gn:country_code":"CN",
    "gn:dem":143,
    "gn:feature_class":"P",
    "gn:feature_code":"PPL",
    "gn:name":"Houdazitun",
    "gn:population":0,
    "gn:timezone":"Asia/Shanghai",
    "iso:country":"CN",
    "name:zho_x_preferred":[
        "\u540e\u642d\u5b50\u5c6f"
    ],
    "wof:name":"Houdazitun",
    "wof:placetype":"locality"
},
  "geometry": {"coordinates":[124.87036000000001,45.23776],"type":"Point"}
}