{
  "type": "Feature",
  "properties": {
    "gn:admin1_code":"30.0",
    "gn:asciiname":"Daheshi",
    "gn:country_code":"CN",
    "gn:dem":243,
    "gn:feature_class":"P",
    "gn:feature_code":"PPL",
    "gn:name":"Daheshi",
    "gn:population":0,
    "gn:timezone":"Asia/Shanghai",
    "iso:country":"CN",
    "name:zho_x_preferred":[
        "\u5927\u548c\u77f3"
    ],
    "wof:name":"Daheshi",
    "wof:placetype":"locality"
},
  "geometry": {"coordinates":[115.21928,23.33739],"type":"Point"}
}