{
  "type": "Feature",
  "properties": {
    "gn:admin1_code":"14.0",
    "gn:asciiname":"Dazawa",
    "gn:country_code":"CN",
    "gn:dem":3670,
    "gn:feature_class":"P",
    "gn:feature_code":"PPL",
    "gn:name":"Dazawa",
    "gn:population":0,
    "gn:timezone":"Asia/Urumqi",
    "iso:country":"CN",
    "name:zho_x_preferred":[
        "\u6253\u6742\u5a03"
    ],
    "wof:name":"Dazawa",
    "wof:placetype":"locality"
},
  "geometry": {"coordinates":[97.65989999999999,30.79522],"type":"Point"}
}