{
  "type": "Feature",
  "properties": {
    "gn:admin1_code":"12.0",
    "gn:asciiname":"Xijieling",
    "gn:country_code":"CN",
    "gn:dem":1099,
    "gn:feature_class":"P",
    "gn:feature_code":"PPL",
    "gn:name":"Xijieling",
    "gn:population":0,
    "gn:timezone":"Asia/Shanghai",
    "iso:country":"CN",
    "name:zho_x_preferred":[
        "\u897f\u754c\u5cad"
    ],
    "wof:name":"Xijieling",
    "wof:placetype":"locality"
},
  "geometry": {"coordinates":[110.19539,32.54489],"type":"Point"}
}