{
  "type": "Feature",
  "properties": {
    "gn:admin1_code":"7.0",
    "gn:asciiname":"Qianlu",
    "gn:country_code":"CN",
    "gn:dem":564,
    "gn:feature_class":"P",
    "gn:feature_code":"PPL",
    "gn:name":"Qianlu",
    "gn:population":0,
    "gn:timezone":"Asia/Shanghai",
    "iso:country":"CN",
    "name:zho_x_preferred":[
        "\u524d\u8def"
    ],
    "wof:name":"Qianlu",
    "wof:placetype":"locality"
},
  "geometry": {"coordinates":[119.11696999999999,26.48379000000001],"type":"Point"}
}