{
  "type": "Feature",
  "properties": {
    "gn:admin1_code":"11.0",
    "gn:asciiname":"Zhouyachong",
    "gn:country_code":"CN",
    "gn:dem":148,
    "gn:feature_class":"P",
    "gn:feature_code":"PPL",
    "gn:name":"Zhouyachong",
    "gn:population":0,
    "gn:timezone":"Asia/Shanghai",
    "iso:country":"CN",
    "name:zho_x_preferred":[
        "\u5468\u4e2b\u51b2"
    ],
    "wof:name":"Zhouyachong",
    "wof:placetype":"locality"
},
  "geometry": {"coordinates":[113.47113,26.63799],"type":"Point"}
}