{
  "type": "Feature",
  "properties": {
    "gn:admin1_code":"4.0",
    "gn:asciiname":"Hejiasixu",
    "gn:country_code":"CN",
    "gn:dem":6,
    "gn:feature_class":"P",
    "gn:feature_code":"PPL",
    "gn:name":"Hejiasixu",
    "gn:population":0,
    "gn:timezone":"Asia/Shanghai",
    "iso:country":"CN",
    "name:zho_x_preferred":[
        "\u4f55\u5bb6\u56db\u5729"
    ],
    "wof:name":"Hejiasixu",
    "wof:placetype":"locality"
},
  "geometry": {"coordinates":[120.16073,32.11748],"type":"Point"}
}