{
  "type": "Feature",
  "properties": {
    "gn:admin1_code":"32.0",
    "gn:asciiname":"Lamo",
    "gn:country_code":"CN",
    "gn:dem":2599,
    "gn:feature_class":"P",
    "gn:feature_code":"PPL",
    "gn:name":"Lamo",
    "gn:population":0,
    "gn:timezone":"Asia/Shanghai",
    "iso:country":"CN",
    "name:zho_x_preferred":[
        "\u62c9\u83ab"
    ],
    "wof:name":"Lamo",
    "wof:placetype":"locality"
},
  "geometry": {"coordinates":[102.79217,28.61598],"type":"Point"}
}