{
  "type": "Feature",
  "properties": {
    "gn:admin1_code":"32.0",
    "gn:asciiname":"Yongbiba",
    "gn:country_code":"CN",
    "gn:dem":424,
    "gn:feature_class":"P",
    "gn:feature_code":"PPL",
    "gn:name":"Yongbiba",
    "gn:population":0,
    "gn:timezone":"Asia/Shanghai",
    "iso:country":"CN",
    "name:zho_x_preferred":[
        "\u752c\u58c1\u575d"
    ],
    "wof:name":"Yongbiba",
    "wof:placetype":"locality"
},
  "geometry": {"coordinates":[107.456,30.9506],"type":"Point"}
}