{
  "type": "Feature",
  "properties": {
    "gn:admin1_code":"6.0",
    "gn:asciiname":"Arilong",
    "gn:country_code":"CN",
    "gn:dem":4070,
    "gn:feature_class":"P",
    "gn:feature_code":"PPL",
    "gn:name":"Arilong",
    "gn:population":0,
    "gn:timezone":"Asia/Urumqi",
    "iso:country":"CN",
    "name:zho_x_preferred":[
        "\u963f\u65e5\u9647"
    ],
    "wof:name":"Arilong",
    "wof:placetype":"locality"
},
  "geometry": {"coordinates":[97.35826,33.18376],"type":"Point"}
}