{
  "type": "Feature",
  "properties": {
    "gn:admin1_code":"19.0",
    "gn:asciiname":"Jiulongshan",
    "gn:country_code":"CN",
    "gn:dem":204,
    "gn:feature_class":"P",
    "gn:feature_code":"PPL",
    "gn:name":"Jiulongshan",
    "gn:population":0,
    "gn:timezone":"Asia/Shanghai",
    "iso:country":"CN",
    "name:und_x_variant":[
        "\u4e5d\u9f99\u5c71"
    ],
    "name:zho_x_preferred":[
        "\u4e5d\u9f99\u5c71"
    ],
    "wof:name":"Jiulongshan",
    "wof:placetype":"locality"
},
  "geometry": {"coordinates":[120.79373,41.9262],"type":"Point"}
}