{
  "type": "Feature",
  "properties": {
    "gn:admin1_code":"3.0",
    "gn:asciiname":"Zhoutian",
    "gn:country_code":"CN",
    "gn:dem":212,
    "gn:feature_class":"P",
    "gn:feature_code":"PPLA4",
    "gn:name":"Zhoutian",
    "gn:population":0,
    "gn:timezone":"Asia/Shanghai",
    "iso:country":"CN",
    "name:und_x_variant":[
        "Chou-t\u2019ien",
        "Chou-t\u2019ien-hs\u00fc",
        "Zhoutian",
        "\u5468\u7530",
        "Zhoutian Zhen",
        "\u5468\u7530\u9547"
    ],
    "wof:name":"Zhoutian",
    "wof:placetype":"locality"
},
  "geometry": {"coordinates":[115.72783,25.32882],"type":"Point"}
}