{
  "type": "Feature",
  "properties": {
    "gn:admin1_code":"25",
    "gn:asciiname":"Zhangluji",
    "gn:country_code":"CN",
    "gn:dem":49,
    "gn:feature_class":"P",
    "gn:feature_code":"PPL",
    "gn:name":"Zhangluji",
    "gn:population":0,
    "gn:timezone":"Asia/Shanghai",
    "iso:country":"CN",
    "name:ceb_x_preferred":[
        "Zhangluji"
    ],
    "name:swe_x_preferred":[
        "Zhangluji"
    ],
    "name:zho_x_preferred":[
        "\u5f20\u7089\u96c6\u9547"
    ],
    "wof:name":"Zhangluji",
    "wof:placetype":"locality"
},
  "geometry": {"coordinates":[115.72611000000001,35.68278],"type":"Point"}
}