{
  "type": "Feature",
  "properties": {
    "gn:admin1_code":"30.0",
    "gn:asciiname":"Hehuacun",
    "gn:country_code":"CN",
    "gn:dem":72,
    "gn:feature_class":"P",
    "gn:feature_code":"PPL",
    "gn:name":"Hehuacun",
    "gn:population":0,
    "gn:timezone":"Asia/Urumqi",
    "iso:country":"CN",
    "name:zho_x_preferred":[
        "\u8377\u82b1\u6751"
    ],
    "wof:name":"Hehuacun",
    "wof:placetype":"locality"
},
  "geometry": {"coordinates":[110.71578,22.28651],"type":"Point"}
}