{
  "type": "Feature",
  "properties": {
    "gn:admin1_code":"10",
    "gn:asciiname":"Shibucao",
    "gn:country_code":"CN",
    "gn:dem":579,
    "gn:feature_class":"P",
    "gn:feature_code":"PPL",
    "gn:name":"Shibucao",
    "gn:population":0,
    "gn:timezone":"Asia/Shanghai",
    "iso:country":"CN",
    "name:zho_x_preferred":[
        "\u5341\u6b65\u69fd"
    ],
    "wof:name":"Shibucao",
    "wof:placetype":"locality"
},
  "geometry": {"coordinates":[113.98099999999999,36.4687],"type":"Point"}
}