{
  "type": "Feature",
  "properties": {
    "gn:admin1_code":"11",
    "gn:asciiname":"Jiangjialing",
    "gn:country_code":"CN",
    "gn:dem":699,
    "gn:feature_class":"P",
    "gn:feature_code":"PPL",
    "gn:name":"Jiangjialing",
    "gn:population":0,
    "gn:timezone":"Asia/Shanghai",
    "iso:country":"CN",
    "name:und_x_variant":[
        "\u848b\u5bb6\u5cad",
        "Jiangjialing"
    ],
    "wof:name":"Jiangjialing",
    "wof:placetype":"locality"
},
  "geometry": {"coordinates":[112.02528,25.94028],"type":"Point"}
}