{
  "type": "Feature",
  "properties": {
    "gn:admin1_code":"25",
    "gn:asciiname":"Kongxingsi",
    "gn:country_code":"CN",
    "gn:dem":194,
    "gn:feature_class":"P",
    "gn:feature_code":"PPL",
    "gn:name":"Kongxingsi",
    "gn:population":0,
    "gn:timezone":"Asia/Shanghai",
    "iso:country":"CN",
    "name:zho_x_preferred":[
        "\u7a7a\u674f\u5bfa"
    ],
    "wof:name":"Kongxingsi",
    "wof:placetype":"locality"
},
  "geometry": {"coordinates":[116.831,36.0921],"type":"Point"}
}