{
  "type": "Feature",
  "properties": {
    "gn:admin1_code":"32.0",
    "gn:asciiname":"Luodou",
    "gn:country_code":"CN",
    "gn:dem":2853,
    "gn:feature_class":"P",
    "gn:feature_code":"PPL",
    "gn:name":"Luodou",
    "gn:population":0,
    "gn:timezone":"Asia/Shanghai",
    "iso:country":"CN",
    "name:zho_x_preferred":[
        "\u7f57\u6597"
    ],
    "wof:name":"Luodou",
    "wof:placetype":"locality"
},
  "geometry": {"coordinates":[100.69499999999999,28.2932],"type":"Point"}
}