{
  "type": "Feature",
  "properties": {
    "gn:admin1_code":"32.0",
    "gn:asciiname":"Jin'erguo",
    "gn:country_code":"CN",
    "gn:dem":2806,
    "gn:feature_class":"P",
    "gn:feature_code":"PPL",
    "gn:name":"Jin\u2019erguo",
    "gn:population":0,
    "gn:timezone":"Asia/Shanghai",
    "iso:country":"CN",
    "name:und_x_variant":[
        "Jin\u2019erguo"
    ],
    "name:zho_x_preferred":[
        "\u91d1\u5c14\u679c"
    ],
    "wof:name":"Jin'erguo",
    "wof:placetype":"locality"
},
  "geometry": {"coordinates":[102.42,28.1056],"type":"Point"}
}