{
  "type": "Feature",
  "properties": {
    "gn:admin1_code":"4.0",
    "gn:asciiname":"Tandong Bazu",
    "gn:country_code":"CN",
    "gn:dem":1,
    "gn:feature_class":"P",
    "gn:feature_code":"PPLF",
    "gn:name":"Tandong Bazu",
    "gn:population":0,
    "gn:timezone":"Asia/Shanghai",
    "iso:country":"CN",
    "name:zho_x_preferred":[
        "Tandong Bazu"
    ],
    "name:zho_x_variant":[
        "\u574d\u4e1c\u516b\u7ec4"
    ],
    "wof:name":"Tandong Bazu",
    "wof:placetype":"locality"
},
  "geometry": {"coordinates":[120.15483999999999,34.02937],"type":"Point"}
}