{
  "type": "Feature",
  "properties": {
    "gn:admin1_code":"11",
    "gn:asciiname":"Daishan",
    "gn:country_code":"CN",
    "gn:dem":880,
    "gn:feature_class":"P",
    "gn:feature_code":"PPL",
    "gn:name":"Daishan",
    "gn:population":0,
    "gn:timezone":"Asia/Shanghai",
    "iso:country":"CN",
    "name:und_x_variant":[
        "\u5cb1\u5c71",
        "Daishan"
    ],
    "wof:name":"Daishan",
    "wof:placetype":"locality"
},
  "geometry": {"coordinates":[112.07138999999999,25.12306],"type":"Point"}
}