{
  "type": "Feature",
  "properties": {
    "gn:admin1_code":"32.0",
    "gn:asciiname":"Wutongmiao",
    "gn:country_code":"CN",
    "gn:dem":832,
    "gn:feature_class":"P",
    "gn:feature_code":"PPL",
    "gn:name":"Wutongmiao",
    "gn:population":0,
    "gn:timezone":"Asia/Shanghai",
    "iso:country":"CN",
    "name:zho_x_preferred":[
        "\u4e94\u901a\u5e99"
    ],
    "wof:name":"Wutongmiao",
    "wof:placetype":"locality"
},
  "geometry": {"coordinates":[104.101,28.6534],"type":"Point"}
}