{
  "type": "Feature",
  "properties": {
    "gn:admin1_code":"14.0",
    "gn:asciiname":"Zhaworiwa",
    "gn:country_code":"CN",
    "gn:dem":4099,
    "gn:feature_class":"P",
    "gn:feature_code":"PPL",
    "gn:name":"Zhaworiwa",
    "gn:population":0,
    "gn:timezone":"Asia/Urumqi",
    "iso:country":"CN",
    "name:zho_x_preferred":[
        "\u624e\u5367\u65e5\u74e6"
    ],
    "wof:name":"Zhaworiwa",
    "wof:placetype":"locality"
},
  "geometry": {"coordinates":[95.71999,31.29844000000001],"type":"Point"}
}