{
  "type": "Feature",
  "properties": {
    "gn:admin1_code":"4.0",
    "gn:asciiname":"Zhuyuan",
    "gn:country_code":"CN",
    "gn:dem":4,
    "gn:feature_class":"P",
    "gn:feature_code":"PPL",
    "gn:name":"Zhuyuan",
    "gn:population":0,
    "gn:timezone":"Asia/Shanghai",
    "iso:country":"CN",
    "name:zho_x_preferred":[
        "Zhuyuan"
    ],
    "name:zho_x_variant":[
        "\u6731\u8881"
    ],
    "wof:name":"Zhuyuan",
    "wof:placetype":"locality"
},
  "geometry": {"coordinates":[119.67775,33.01507],"type":"Point"}
}