{
  "type": "Feature",
  "properties": {
    "gn:admin1_code":"16.0",
    "gn:asciiname":"Jieyin",
    "gn:country_code":"CN",
    "gn:dem":173,
    "gn:feature_class":"P",
    "gn:feature_code":"PPL",
    "gn:name":"Jieyin",
    "gn:population":0,
    "gn:timezone":"Asia/Shanghai",
    "iso:country":"CN",
    "name:zho_x_preferred":[
        "\u4ecb\u56e0"
    ],
    "wof:name":"Jieyin",
    "wof:placetype":"locality"
},
  "geometry": {"coordinates":[107.744,22.1463],"type":"Point"}
}