{
  "type": "Feature",
  "properties": {
    "gn:admin1_code":"33.0",
    "gn:asciiname":"Liangfeng",
    "gn:country_code":"CN",
    "gn:dem":1730,
    "gn:feature_class":"P",
    "gn:feature_code":"PPL",
    "gn:name":"Liangfeng",
    "gn:population":0,
    "gn:timezone":"Asia/Shanghai",
    "iso:country":"CN",
    "name:zho_x_preferred":[
        "\u51c9\u98ce"
    ],
    "wof:name":"Liangfeng",
    "wof:placetype":"locality"
},
  "geometry": {"coordinates":[108.47772000000001,31.84802],"type":"Point"}
}