{
  "type": "Feature",
  "properties": {
    "gn:admin1_code":"7",
    "gn:asciiname":"Julang",
    "gn:country_code":"CN",
    "gn:dem":343,
    "gn:feature_class":"P",
    "gn:feature_code":"PPL",
    "gn:name":"Julang",
    "gn:population":0,
    "gn:timezone":"Asia/Shanghai",
    "iso:country":"CN",
    "name:und_x_variant":[
        "\u6989\u6994"
    ],
    "wof:name":"Julang",
    "wof:placetype":"locality"
},
  "geometry": {"coordinates":[118.78667,27.77111],"type":"Point"}
}