{
  "type": "Feature",
  "properties": {
    "gn:admin1_code":"1.0",
    "gn:asciiname":"Huangtugang",
    "gn:country_code":"CN",
    "gn:dem":58,
    "gn:feature_class":"P",
    "gn:feature_code":"PPL",
    "gn:name":"Huangtugang",
    "gn:population":0,
    "gn:timezone":"Asia/Shanghai",
    "iso:country":"CN",
    "name:zho_x_preferred":[
        "Huangtugang"
    ],
    "name:zho_x_variant":[
        "\u9ec4\u571f\u5c97"
    ],
    "wof:name":"Huangtugang",
    "wof:placetype":"locality"
},
  "geometry": {"coordinates":[118.98621,30.70559],"type":"Point"}
}