{
  "type": "Feature",
  "properties": {
    "gn:admin1_code":"15.0",
    "gn:asciiname":"Dianzuizi",
    "gn:country_code":"CN",
    "gn:dem":1343,
    "gn:feature_class":"P",
    "gn:feature_code":"PPL",
    "gn:name":"Dianzuizi",
    "gn:population":0,
    "gn:timezone":"Asia/Shanghai",
    "iso:country":"CN",
    "name:zho_x_preferred":[
        "\u6bbf\u5480\u5b50"
    ],
    "wof:name":"Dianzuizi",
    "wof:placetype":"locality"
},
  "geometry": {"coordinates":[107.345,35.2447],"type":"Point"}
}