{
  "type": "Feature",
  "properties": {
    "gn:admin1_code":"19.0",
    "gn:asciiname":"Jijiajie",
    "gn:country_code":"CN",
    "gn:dem":69,
    "gn:feature_class":"P",
    "gn:feature_code":"PPL",
    "gn:name":"Jijiajie",
    "gn:population":0,
    "gn:timezone":"Asia/Shanghai",
    "iso:country":"CN",
    "name:zho_x_preferred":[
        "\u7eaa\u5bb6\u8857"
    ],
    "wof:name":"Jijiajie",
    "wof:placetype":"locality"
},
  "geometry": {"coordinates":[123.729,42.5359],"type":"Point"}
}