{
  "type": "Feature",
  "properties": {
    "gn:admin1_code":"30.0",
    "gn:asciiname":"Daliaocun",
    "gn:country_code":"CN",
    "gn:dem":12,
    "gn:feature_class":"P",
    "gn:feature_code":"PPL",
    "gn:name":"Daliaocun",
    "gn:population":0,
    "gn:timezone":"Asia/Shanghai",
    "iso:country":"CN",
    "name:und_x_variant":[
        "Daliao"
    ],
    "name:zho_x_preferred":[
        "\u5927\u5bee\u6751"
    ],
    "wof:name":"Daliaocun",
    "wof:placetype":"locality"
},
  "geometry": {"coordinates":[116.31569,23.38055],"type":"Point"}
}