{
  "type": "Feature",
  "properties": {
    "gn:admin1_code":"19.0",
    "gn:asciiname":"Xiaoganhecun",
    "gn:country_code":"CN",
    "gn:dem":307,
    "gn:feature_class":"P",
    "gn:feature_code":"PPL",
    "gn:name":"Xiaoganhecun",
    "gn:population":0,
    "gn:timezone":"Asia/Shanghai",
    "iso:country":"CN",
    "name:zho_x_preferred":[
        "\u5c0f\u7518\u6cb3\u6751"
    ],
    "wof:name":"Xiaoganhecun",
    "wof:placetype":"locality"
},
  "geometry": {"coordinates":[124.94199999999999,42.3273],"type":"Point"}
}