{
  "type": "Feature",
  "properties": {
    "gn:admin1_code":"18.0",
    "gn:asciiname":"Bangqin",
    "gn:country_code":"CN",
    "gn:dem":655,
    "gn:feature_class":"P",
    "gn:feature_code":"PPL",
    "gn:name":"Bangqin",
    "gn:population":0,
    "gn:timezone":"Asia/Shanghai",
    "iso:country":"CN",
    "name:zho_x_preferred":[
        "\u508d\u52e4"
    ],
    "wof:name":"Bangqin",
    "wof:placetype":"locality"
},
  "geometry": {"coordinates":[108.431,26.3632],"type":"Point"}
}