{
  "type": "Feature",
  "properties": {
    "gn:admin1_code":"12",
    "gn:asciiname":"Dongfengluntaichang",
    "gn:country_code":"CN",
    "gn:dem":367,
    "gn:feature_class":"P",
    "gn:feature_code":"PPL",
    "gn:name":"Dongfengluntaichang",
    "gn:population":0,
    "gn:timezone":"Asia/Shanghai",
    "iso:country":"CN",
    "wof:name":"Dongfengluntaichang",
    "wof:placetype":"locality"
},
  "geometry": {"coordinates":[110.75221999999999,32.70194],"type":"Point"}
}