{
  "type": "Feature",
  "properties": {
    "gn:admin1_code":"7.0",
    "gn:asciiname":"Lianxiacun",
    "gn:country_code":"CN",
    "gn:dem":375,
    "gn:feature_class":"P",
    "gn:feature_code":"PPL",
    "gn:name":"Lianxiacun",
    "gn:population":0,
    "gn:timezone":"Asia/Shanghai",
    "iso:country":"CN",
    "name:zho_x_preferred":[
        "\u83b2\u4e0b\u6751"
    ],
    "wof:name":"Lianxiacun",
    "wof:placetype":"locality"
},
  "geometry": {"coordinates":[119.37866,26.69725],"type":"Point"}
}