{
  "type": "Feature",
  "properties": {
    "gn:admin1_code":"9.0",
    "gn:asciiname":"Manliying",
    "gn:country_code":"CN",
    "gn:dem":422,
    "gn:feature_class":"P",
    "gn:feature_code":"PPL",
    "gn:name":"Manliying",
    "gn:population":0,
    "gn:timezone":"Asia/Shanghai",
    "iso:country":"CN",
    "name:zho_x_preferred":[
        "\u5881\u91cc\u8425"
    ],
    "wof:name":"Manliying",
    "wof:placetype":"locality"
},
  "geometry": {"coordinates":[111.15051,33.41763],"type":"Point"}
}