{
  "type": "Feature",
  "properties": {
    "gn:admin1_code":"12",
    "gn:asciiname":"Yinjiaping",
    "gn:country_code":"CN",
    "gn:dem":1257,
    "gn:feature_class":"P",
    "gn:feature_code":"PPL",
    "gn:name":"Yinjiaping",
    "gn:population":0,
    "gn:timezone":"Asia/Shanghai",
    "iso:country":"CN",
    "name:und_x_variant":[
        "Yin-chia-p\u2019ing",
        "Yinjiaping"
    ],
    "name:zho_x_preferred":[
        "\u6bb7\u5bb6\u576a"
    ],
    "wof:name":"Yinjiaping",
    "wof:placetype":"locality"
},
  "geometry": {"coordinates":[111.12872,31.30178],"type":"Point"}
}