{
  "type": "Feature",
  "properties": {
    "gn:admin1_code":"26.0",
    "gn:asciiname":"Sanhezhang",
    "gn:country_code":"CN",
    "gn:dem":1465,
    "gn:feature_class":"P",
    "gn:feature_code":"PPL",
    "gn:name":"Sanhezhang",
    "gn:population":0,
    "gn:timezone":"Asia/Shanghai",
    "iso:country":"CN",
    "name:und_x_variant":[
        "\u4e09\u5408\u638c"
    ],
    "wof:name":"Sanhezhang",
    "wof:placetype":"locality"
},
  "geometry": {"coordinates":[107.77941,36.83065],"type":"Point"}
}