{
  "type": "Feature",
  "properties": {
    "gn:admin1_code":"4.0",
    "gn:asciiname":"Shanglaozhuang",
    "gn:country_code":"CN",
    "gn:dem":11,
    "gn:feature_class":"P",
    "gn:feature_code":"PPL",
    "gn:name":"Shanglaozhuang",
    "gn:population":0,
    "gn:timezone":"Asia/Shanghai",
    "iso:country":"CN",
    "name:zho_x_preferred":[
        "\u5c1a\u8001\u5e84"
    ],
    "wof:name":"Shanglaozhuang",
    "wof:placetype":"locality"
},
  "geometry": {"coordinates":[118.988,33.5613],"type":"Point"}
}