{
  "type": "Feature",
  "properties": {
    "gn:admin1_code":"25",
    "gn:asciiname":"Qianzhangzhuang",
    "gn:country_code":"CN",
    "gn:dem":54,
    "gn:feature_class":"P",
    "gn:feature_code":"PPL",
    "gn:name":"Qianzhangzhuang",
    "gn:population":0,
    "gn:timezone":"Asia/Shanghai",
    "iso:country":"CN",
    "name:zho_x_preferred":[
        "\u524d\u5f20\u5e84"
    ],
    "wof:name":"Qianzhangzhuang",
    "wof:placetype":"locality"
},
  "geometry": {"coordinates":[116.672,35.7225],"type":"Point"}
}