{
  "type": "Feature",
  "properties": {
    "gn:admin1_code":"3",
    "gn:asciiname":"Tushi",
    "gn:country_code":"CN",
    "gn:dem":134,
    "gn:feature_class":"P",
    "gn:feature_code":"PPL",
    "gn:name":"Tushi",
    "gn:population":0,
    "gn:timezone":"Asia/Shanghai",
    "iso:country":"CN",
    "name:ceb_x_preferred":[
        "T\u016bsh\u012b"
    ],
    "name:fas_x_preferred":[
        "\u062a\u0648\u0634\u06cc"
    ],
    "name:msa_x_preferred":[
        "Tushi"
    ],
    "name:swe_x_preferred":[
        "T\u016bsh\u012b"
    ],
    "name:ukr_x_preferred":[
        "\u0422\u0443\u0448\u0456"
    ],
    "name:zho_x_preferred":[
        "\u571f\u77f3"
    ],
    "wof:name":"Tushi",
    "wof:placetype":"locality"
},
  "geometry": {"coordinates":[114.64205,25.78014],"type":"Point"}
}