{
  "type": "Feature",
  "properties": {
    "gn:admin1_code":"21.0",
    "gn:asciiname":"Lucaowan",
    "gn:country_code":"CN",
    "gn:dem":1831,
    "gn:feature_class":"P",
    "gn:feature_code":"PPL",
    "gn:name":"Lucaowan",
    "gn:population":0,
    "gn:timezone":"Asia/Shanghai",
    "iso:country":"CN",
    "name:zho_x_preferred":[
        "\u82a6\u8349\u6e7e"
    ],
    "wof:name":"Lucaowan",
    "wof:placetype":"locality"
},
  "geometry": {"coordinates":[106.57263,36.28432],"type":"Point"}
}