{
  "type": "Feature",
  "properties": {
    "gn:admin1_code":"24.0",
    "gn:asciiname":"Lisanyaocun",
    "gn:country_code":"CN",
    "gn:dem":1230,
    "gn:feature_class":"P",
    "gn:feature_code":"PPL",
    "gn:name":"Lisanyaocun",
    "gn:population":0,
    "gn:timezone":"Asia/Shanghai",
    "iso:country":"CN",
    "name:zho_x_preferred":[
        "\u674e\u4e09\u7a91\u6751"
    ],
    "wof:name":"Lisanyaocun",
    "wof:placetype":"locality"
},
  "geometry": {"coordinates":[113.14319,40.34113],"type":"Point"}
}