{
  "type": "Feature",
  "properties": {
    "gn:admin1_code":"14.0",
    "gn:asciiname":"Songran",
    "gn:country_code":"CN",
    "gn:dem":3650,
    "gn:feature_class":"P",
    "gn:feature_code":"PPL",
    "gn:name":"Songran",
    "gn:population":0,
    "gn:timezone":"Asia/Urumqi",
    "iso:country":"CN",
    "name:zho_x_preferred":[
        "\u5b8b\u7136"
    ],
    "wof:name":"Songran",
    "wof:placetype":"locality"
},
  "geometry": {"coordinates":[96.12976,30.93615],"type":"Point"}
}