{
  "type": "Feature",
  "properties": {
    "gn:admin1_code":"11.0",
    "gn:asciiname":"Miaoyuan",
    "gn:country_code":"CN",
    "gn:dem":244,
    "gn:feature_class":"P",
    "gn:feature_code":"PPL",
    "gn:name":"Miaoyuan",
    "gn:population":0,
    "gn:timezone":"Asia/Shanghai",
    "iso:country":"CN",
    "name:zho_x_preferred":[
        "\u5e99\u5143"
    ],
    "wof:name":"Miaoyuan",
    "wof:placetype":"locality"
},
  "geometry": {"coordinates":[111.33060999999999,27.03739],"type":"Point"}
}