{
  "type": "Feature",
  "properties": {
    "gn:admin1_code":"9.0",
    "gn:asciiname":"Jiaodongcun",
    "gn:country_code":"CN",
    "gn:dem":59,
    "gn:feature_class":"P",
    "gn:feature_code":"PPL",
    "gn:name":"Jiaodongcun",
    "gn:population":0,
    "gn:timezone":"Asia/Shanghai",
    "iso:country":"CN",
    "name:zho_x_preferred":[
        "\u7126\u4e1c\u6751"
    ],
    "wof:name":"Jiaodongcun",
    "wof:placetype":"locality"
},
  "geometry": {"coordinates":[114.20617,33.74079],"type":"Point"}
}