{
  "type": "Feature",
  "properties": {
    "gn:admin1_code":"4.0",
    "gn:asciiname":"Shuanglou",
    "gn:country_code":"CN",
    "gn:dem":38,
    "gn:feature_class":"P",
    "gn:feature_code":"PPL",
    "gn:name":"Shuanglou",
    "gn:population":0,
    "gn:timezone":"Asia/Shanghai",
    "iso:country":"CN",
    "name:zho_x_preferred":[
        "\u53cc\u697c"
    ],
    "wof:name":"Shuanglou",
    "wof:placetype":"locality"
},
  "geometry": {"coordinates":[116.55200000000001,34.76],"type":"Point"}
}