{
  "type": "Feature",
  "properties": {
    "gn:admin1_code":"18.0",
    "gn:asciiname":"Jiasa",
    "gn:country_code":"CN",
    "gn:dem":453,
    "gn:feature_class":"P",
    "gn:feature_code":"PPL",
    "gn:name":"Jiasa",
    "gn:population":0,
    "gn:timezone":"Asia/Shanghai",
    "iso:country":"CN",
    "name:zho_x_preferred":[
        "\u7532\u6d12"
    ],
    "wof:name":"Jiasa",
    "wof:placetype":"locality"
},
  "geometry": {"coordinates":[107.82899999999999,25.9026],"type":"Point"}
}