{
  "type": "Feature",
  "properties": {
    "gn:admin1_code":"25",
    "gn:asciiname":"Liyuanzi",
    "gn:country_code":"CN",
    "gn:dem":44,
    "gn:feature_class":"P",
    "gn:feature_code":"PPL",
    "gn:name":"Liyuanzi",
    "gn:population":0,
    "gn:timezone":"Asia/Shanghai",
    "iso:country":"CN",
    "name:zho_x_preferred":[
        "\u674e\u56ed\u5b50"
    ],
    "wof:name":"Liyuanzi",
    "wof:placetype":"locality"
},
  "geometry": {"coordinates":[115.604,36.2755],"type":"Point"}
}