{
  "type": "Feature",
  "properties": {
    "gn:admin1_code":"7",
    "gn:asciiname":"Lantiancun",
    "gn:country_code":"CN",
    "gn:dem":704,
    "gn:feature_class":"P",
    "gn:feature_code":"PPL",
    "gn:name":"Lantiancun",
    "gn:population":0,
    "gn:timezone":"Asia/Shanghai",
    "iso:country":"CN",
    "name:zho_x_preferred":[
        "\u84dd\u7530\u6751"
    ],
    "wof:name":"Lantiancun",
    "wof:placetype":"locality"
},
  "geometry": {"coordinates":[117.10045,24.93299],"type":"Point"}
}