{
  "type": "Feature",
  "properties": {
    "gn:admin1_code":"2.0",
    "gn:asciiname":"Huashusha",
    "gn:country_code":"CN",
    "gn:dem":12,
    "gn:feature_class":"P",
    "gn:feature_code":"PPL",
    "gn:name":"Huashusha",
    "gn:population":0,
    "gn:timezone":"Asia/Shanghai",
    "iso:country":"CN",
    "name:und_x_variant":[
        "\u534e\u5885\u6c99"
    ],
    "wof:name":"Huashusha",
    "wof:placetype":"locality"
},
  "geometry": {"coordinates":[120.01069,30.07434000000001],"type":"Point"}
}