{
  "type": "Feature",
  "properties": {
    "gn:admin1_code":"26.0",
    "gn:asciiname":"Shaofanggou",
    "gn:country_code":"CN",
    "gn:dem":885,
    "gn:feature_class":"P",
    "gn:feature_code":"PPL",
    "gn:name":"Shaofanggou",
    "gn:population":0,
    "gn:timezone":"Asia/Shanghai",
    "iso:country":"CN",
    "name:und_x_variant":[
        "\u70e7\u623f\u6c9f"
    ],
    "wof:name":"Shaofanggou",
    "wof:placetype":"locality"
},
  "geometry": {"coordinates":[106.15774999999999,32.85266],"type":"Point"}
}