{
  "type": "Feature",
  "properties": {
    "gn:admin1_code":"15.0",
    "gn:asciiname":"Weihe",
    "gn:country_code":"CN",
    "gn:dem":2144,
    "gn:feature_class":"P",
    "gn:feature_code":"PPL",
    "gn:name":"Weihe",
    "gn:population":0,
    "gn:timezone":"Asia/Shanghai",
    "iso:country":"CN",
    "name:deu_x_preferred":[
        "Weihe"
    ],
    "name:nds_x_preferred":[
        "Weihe"
    ],
    "name:und_x_variant":[
        "\u9b4f\u6cb3"
    ],
    "wof:name":"Weihe",
    "wof:placetype":"locality"
},
  "geometry": {"coordinates":[105.21799,35.29544],"type":"Point"}
}