{
  "type": "Feature",
  "properties": {
    "gn:admin1_code":"24.0",
    "gn:asciiname":"Fengjiayu",
    "gn:country_code":"CN",
    "gn:dem":740,
    "gn:feature_class":"P",
    "gn:feature_code":"PPL",
    "gn:name":"Fengjiayu",
    "gn:population":0,
    "gn:timezone":"Asia/Shanghai",
    "iso:country":"CN",
    "name:zho_x_preferred":[
        "\u51af\u5bb6\u5cea"
    ],
    "name:zho_x_variant":[
        "\u51af\u5bb6\u5cea\u9547"
    ],
    "wof:name":"Fengjiayu",
    "wof:placetype":"locality"
},
  "geometry": {"coordinates":[113.73378,37.99184],"type":"Point"}
}