{
  "type": "Feature",
  "properties": {
    "gn:admin1_code":"16.0",
    "gn:asciiname":"Quanlongzha",
    "gn:country_code":"CN",
    "gn:dem":131,
    "gn:feature_class":"P",
    "gn:feature_code":"PPL",
    "gn:name":"Quanlongzha",
    "gn:population":0,
    "gn:timezone":"Asia/Shanghai",
    "iso:country":"CN",
    "name:zho_x_preferred":[
        "\u5168\u9686\u69a8"
    ],
    "wof:name":"Quanlongzha",
    "wof:placetype":"locality"
},
  "geometry": {"coordinates":[110.836,24.6401],"type":"Point"}
}