{
  "type": "Feature",
  "properties": {
    "gn:admin1_code":"4.0",
    "gn:asciiname":"Minzhugang",
    "gn:country_code":"CN",
    "gn:dem":4,
    "gn:feature_class":"P",
    "gn:feature_code":"PPL",
    "gn:name":"Minzhugang",
    "gn:population":0,
    "gn:timezone":"Asia/Shanghai",
    "iso:country":"CN",
    "name:zho_x_preferred":[
        "\u6c11\u4e3b\u6e2f"
    ],
    "wof:name":"Minzhugang",
    "wof:placetype":"locality"
},
  "geometry": {"coordinates":[120.91088999999999,31.94128],"type":"Point"}
}