{
  "type": "Feature",
  "properties": {
    "gn:admin1_code":"32.0",
    "gn:asciiname":"Wutong",
    "gn:country_code":"CN",
    "gn:dem":430,
    "gn:feature_class":"P",
    "gn:feature_code":"PPL",
    "gn:name":"Wutong",
    "gn:population":0,
    "gn:timezone":"Asia/Shanghai",
    "iso:country":"CN",
    "name:deu_x_preferred":[
        "Wutong"
    ],
    "name:zho_x_preferred":[
        "\u68a7\u6850"
    ],
    "wof:name":"Wutong",
    "wof:placetype":"locality"
},
  "geometry": {"coordinates":[104.608,30.6358],"type":"Point"}
}