{
  "type": "Feature",
  "properties": {
    "gn:admin1_code":"3.0",
    "gn:asciiname":"Nanjiajing",
    "gn:country_code":"CN",
    "gn:dem":89,
    "gn:feature_class":"P",
    "gn:feature_code":"PPL",
    "gn:name":"Nanjiajing",
    "gn:population":0,
    "gn:timezone":"Asia/Shanghai",
    "iso:country":"CN",
    "name:zho_x_preferred":[
        "\u5357\u5bb6\u4e95"
    ],
    "wof:name":"Nanjiajing",
    "wof:placetype":"locality"
},
  "geometry": {"coordinates":[117.55488,28.91385],"type":"Point"}
}