{
  "type": "Feature",
  "properties": {
    "gn:admin1_code":"9.0",
    "gn:asciiname":"Housimen",
    "gn:country_code":"CN",
    "gn:dem":98,
    "gn:feature_class":"P",
    "gn:feature_code":"PPL",
    "gn:name":"Housimen",
    "gn:population":0,
    "gn:timezone":"Asia/Shanghai",
    "iso:country":"CN",
    "name:zho_x_preferred":[
        "\u540e\u5bfa\u95e8"
    ],
    "wof:name":"Housimen",
    "wof:placetype":"locality"
},
  "geometry": {"coordinates":[112.39303999999998,32.70652],"type":"Point"}
}