{
  "type": "Feature",
  "properties": {
    "gn:admin1_code":"30.0",
    "gn:asciiname":"Dalingxia",
    "gn:country_code":"CN",
    "gn:dem":151,
    "gn:feature_class":"P",
    "gn:feature_code":"PPL",
    "gn:name":"Dalingxia",
    "gn:population":0,
    "gn:timezone":"Asia/Shanghai",
    "iso:country":"CN",
    "name:zho_x_preferred":[
        "\u5927\u5cad\u4e0b"
    ],
    "wof:name":"Dalingxia",
    "wof:placetype":"locality"
},
  "geometry": {"coordinates":[113.97121,24.92248],"type":"Point"}
}