{
  "type": "Feature",
  "properties": {
    "gn:admin1_code":"30",
    "gn:asciiname":"Xueshixiang",
    "gn:country_code":"CN",
    "gn:dem":88,
    "gn:feature_class":"P",
    "gn:feature_code":"PPL",
    "gn:name":"Xueshixiang",
    "gn:population":0,
    "gn:timezone":"Asia/Shanghai",
    "iso:country":"CN",
    "name:zho_x_preferred":[
        "\u5b66\u4ed5\u4e61"
    ],
    "wof:name":"Xueshixiang",
    "wof:placetype":"locality"
},
  "geometry": {"coordinates":[111.53222,22.15538],"type":"Point"}
}