{
  "type": "Feature",
  "properties": {
    "gn:admin1_code":"31.0",
    "gn:asciiname":"Shuijingshan",
    "gn:country_code":"CN",
    "gn:dem":87,
    "gn:feature_class":"P",
    "gn:feature_code":"PPL",
    "gn:name":"Shuijingshan",
    "gn:population":0,
    "gn:timezone":"Asia/Shanghai",
    "iso:country":"CN",
    "name:zho_x_preferred":[
        "Shuijingshan"
    ],
    "name:zho_x_variant":[
        "\u6c34\u4e95\u5c71"
    ],
    "wof:name":"Shuijingshan",
    "wof:placetype":"locality"
},
  "geometry": {"coordinates":[110.12287000000001,19.62764],"type":"Point"}
}