{
  "type": "Feature",
  "properties": {
    "gn:admin1_code":"29.0",
    "gn:asciiname":"Kongjing",
    "gn:country_code":"CN",
    "gn:dem":1762,
    "gn:feature_class":"P",
    "gn:feature_code":"PPL",
    "gn:name":"Kongjing",
    "gn:population":0,
    "gn:timezone":"Asia/Shanghai",
    "iso:country":"CN",
    "name:zho_x_preferred":[
        "\u63a7\u4e95"
    ],
    "wof:name":"Kongjing",
    "wof:placetype":"locality"
},
  "geometry": {"coordinates":[99.2171,23.2129],"type":"Point"}
}