{
  "type": "Feature",
  "properties": {
    "gn:admin1_code":"29.0",
    "gn:asciiname":"Potouzhai",
    "gn:country_code":"CN",
    "gn:dem":1100,
    "gn:feature_class":"P",
    "gn:feature_code":"PPL",
    "gn:name":"Potouzhai",
    "gn:population":0,
    "gn:timezone":"Asia/Shanghai",
    "iso:country":"CN",
    "name:zho_x_preferred":[
        "\u5761\u5934\u5be8"
    ],
    "wof:name":"Potouzhai",
    "wof:placetype":"locality"
},
  "geometry": {"coordinates":[101.34099999999999,21.8416],"type":"Point"}
}