{
  "type": "Feature",
  "properties": {
    "gn:admin1_code":"19.0",
    "gn:asciiname":"Fangshencun",
    "gn:country_code":"CN",
    "gn:dem":145,
    "gn:feature_class":"P",
    "gn:feature_code":"PPL",
    "gn:name":"Fangshencun",
    "gn:population":0,
    "gn:timezone":"Asia/Shanghai",
    "iso:country":"CN",
    "name:zho_x_preferred":[
        "\u623f\u8eab\u6751"
    ],
    "wof:name":"Fangshencun",
    "wof:placetype":"locality"
},
  "geometry": {"coordinates":[124.11933999999999,42.94595],"type":"Point"}
}