{
  "type": "Feature",
  "properties": {
    "gn:country":"CN",
    "gn:fcode":"PPL",
    "gn:population":0,
    "iso:country":"CN",
    "name:und_x_variant":[
        "Pei-hsin-ching-chen"
    ],
    "qs:name":"\u5317\u65b0\u6cfe\u9547",
    "qs:name_adm0":"\u4e2d\u570b",
    "qs:name_adm1":"\u4e0a\u6d77\u76f4\u8f96\u5e02",
    "qs:photos":1,
    "qs:photos_1k":1,
    "qs:photos_9k":1,
    "qs:photos_9r":1,
    "qs:photos_all":1,
    "qs:photos_sr":1,
    "qs:placetype":"Suburb",
    "qs:pop_sr":"0",
    "wof:name":"\u5317\u65b0\u6cfe\u9547",
    "wof:placetype":"neighbourhood",
    "wof:population":0
},
  "geometry": {"coordinates":[121.36528,31.2225],"type":"Point"}
}