{
  "type": "Feature",
  "properties": {
    "gn:admin1_code":"29.0",
    "gn:asciiname":"Yiwanshui",
    "gn:country_code":"CN",
    "gn:dem":1566,
    "gn:feature_class":"P",
    "gn:feature_code":"PPL",
    "gn:name":"Yiwanshui",
    "gn:population":0,
    "gn:timezone":"Asia/Shanghai",
    "iso:country":"CN",
    "name:zho_x_preferred":[
        "\u4e00\u7897\u6c34"
    ],
    "wof:name":"Yiwanshui",
    "wof:placetype":"locality"
},
  "geometry": {"coordinates":[104.14100000000001,23.1434],"type":"Point"}
}