{
  "type": "Feature",
  "properties": {
    "gn:admin1_code":"3.0",
    "gn:asciiname":"Weishui",
    "gn:country_code":"CN",
    "gn:dem":73,
    "gn:feature_class":"P",
    "gn:feature_code":"PPL",
    "gn:name":"Weishui",
    "gn:population":0,
    "gn:timezone":"Asia/Shanghai",
    "iso:country":"CN",
    "name:und_x_variant":[
        "\u6e2d\u6c34"
    ],
    "wof:name":"Weishui",
    "wof:placetype":"locality"
},
  "geometry": {"coordinates":[114.54152999999999,27.79454],"type":"Point"}
}