{
  "type": "Feature",
  "properties": {
    "gn:admin1_code":"10",
    "gn:asciiname":"Beiwei",
    "gn:cc2":"CN",
    "gn:country_code":"CN",
    "gn:dem":6,
    "gn:feature_class":"P",
    "gn:feature_code":"PPL",
    "gn:name":"Beiwei",
    "gn:population":0,
    "gn:timezone":"Asia/Shanghai",
    "iso:country":"CN",
    "name:und_x_variant":[
        "Pei-wei",
        "Pei-wei-chen",
        "Beiwei"
    ],
    "wof:name":"Beiwei",
    "wof:placetype":"locality"
},
  "geometry": {"coordinates":[116.45,38.65],"type":"Point"}
}