{
  "type": "Feature",
  "properties": {
    "gn:admin1_code":"4.0",
    "gn:asciiname":"Dongguang Sanzu",
    "gn:country_code":"CN",
    "gn:dem":3,
    "gn:feature_class":"P",
    "gn:feature_code":"PPL",
    "gn:name":"Dongguang Sanzu",
    "gn:population":0,
    "gn:timezone":"Asia/Shanghai",
    "iso:country":"CN",
    "name:und_x_variant":[
        "\u4e1c\u5149\u4e09\u7ec4"
    ],
    "name:zho_x_preferred":[
        "\u4e1c\u5149\u4e09\u7ec4"
    ],
    "wof:name":"Dongguang Sanzu",
    "wof:placetype":"locality"
},
  "geometry": {"coordinates":[120.36750000000001,32.73164000000001],"type":"Point"}
}