{
  "type": "Feature",
  "properties": {
    "gn:admin1_code":"1.0",
    "gn:asciiname":"Liangcaocun",
    "gn:country_code":"CN",
    "gn:dem":30,
    "gn:feature_class":"P",
    "gn:feature_code":"PPL",
    "gn:name":"Liangcaocun",
    "gn:population":0,
    "gn:timezone":"Asia/Shanghai",
    "iso:country":"CN",
    "name:zho_x_preferred":[
        "\u6881\u66f9\u6751"
    ],
    "wof:name":"Liangcaocun",
    "wof:placetype":"locality"
},
  "geometry": {"coordinates":[117.17204,32.39530999999999],"type":"Point"}
}