{
  "type": "Feature",
  "properties": {
    "gn:admin1_code":"3.0",
    "gn:asciiname":"Laowujia",
    "gn:country_code":"CN",
    "gn:dem":414,
    "gn:feature_class":"P",
    "gn:feature_code":"PPL",
    "gn:name":"Laowujia",
    "gn:population":0,
    "gn:timezone":"Asia/Shanghai",
    "iso:country":"CN",
    "name:und_x_variant":[
        "\u8001\u5c4b\u5bb6"
    ],
    "wof:name":"Laowujia",
    "wof:placetype":"locality"
},
  "geometry": {"coordinates":[115.43474999999999,26.78733],"type":"Point"}
}