{
  "type": "Feature",
  "properties": {
    "gn:admin1_code":"1.0",
    "gn:asciiname":"Jinzhupingcun",
    "gn:country_code":"CN",
    "gn:dem":633,
    "gn:feature_class":"P",
    "gn:feature_code":"PPL",
    "gn:name":"Jinzhupingcun",
    "gn:population":0,
    "gn:timezone":"Asia/Shanghai",
    "iso:country":"CN",
    "name:zho_x_preferred":[
        "\u91d1\u7af9\u576a\u6751"
    ],
    "wof:name":"Jinzhupingcun",
    "wof:placetype":"locality"
},
  "geometry": {"coordinates":[116.14975,31.13033],"type":"Point"}
}