{
  "type": "Feature",
  "properties": {
    "gn:admin1_code":"25",
    "gn:asciiname":"Xishanjiao",
    "gn:country_code":"CN",
    "gn:dem":170,
    "gn:feature_class":"P",
    "gn:feature_code":"PPL",
    "gn:name":"Xishanjiao",
    "gn:population":0,
    "gn:timezone":"Asia/Shanghai",
    "iso:country":"CN",
    "name:zho_x_preferred":[
        "\u897f\u5c71\u89d2"
    ],
    "wof:name":"Xishanjiao",
    "wof:placetype":"locality"
},
  "geometry": {"coordinates":[118.11499999999999,35.5057],"type":"Point"}
}