{
  "type": "Feature",
  "properties": {
    "gn:admin1_code":"26.0",
    "gn:asciiname":"Hewan Sidui",
    "gn:country_code":"CN",
    "gn:dem":1225,
    "gn:feature_class":"P",
    "gn:feature_code":"PPLF",
    "gn:name":"Hewan Sidui",
    "gn:population":0,
    "gn:timezone":"Asia/Shanghai",
    "iso:country":"CN",
    "name:zho_x_preferred":[
        "\u6cb3\u6e7e\u56db\u961f"
    ],
    "wof:name":"Hewan Sidui",
    "wof:placetype":"locality"
},
  "geometry": {"coordinates":[109.96966999999999,38.96926],"type":"Point"}
}