{
  "type": "Feature",
  "properties": {
    "gn:admin1_code":"2.0",
    "gn:asciiname":"Paimen",
    "gn:country_code":"CN",
    "gn:dem":132,
    "gn:feature_class":"P",
    "gn:feature_code":"PPL",
    "gn:name":"Paimen",
    "gn:population":0,
    "gn:timezone":"Asia/Shanghai",
    "iso:country":"CN",
    "name:und_x_variant":[
        "P\u2019ai-men"
    ],
    "name:zho_x_preferred":[
        "\u724c\u95e8"
    ],
    "wof:name":"Paimen",
    "wof:placetype":"locality"
},
  "geometry": {"coordinates":[120.95173,28.52488],"type":"Point"}
}