{
  "type": "Feature",
  "properties": {
    "gn:admin1_code":"25",
    "gn:asciiname":"Zhangguantun",
    "gn:country_code":"CN",
    "gn:dem":30,
    "gn:feature_class":"P",
    "gn:feature_code":"PPL",
    "gn:name":"Zhangguantun",
    "gn:population":0,
    "gn:timezone":"Asia/Shanghai",
    "iso:country":"CN",
    "name:zho_x_preferred":[
        "\u5f20\u5b98\u5c6f"
    ],
    "wof:name":"Zhangguantun",
    "wof:placetype":"locality"
},
  "geometry": {"coordinates":[116.131,36.9859],"type":"Point"}
}