{
  "type": "Feature",
  "properties": {
    "gn:admin1_code":"1.0",
    "gn:asciiname":"Wangdayingcun",
    "gn:country_code":"CN",
    "gn:dem":26,
    "gn:feature_class":"P",
    "gn:feature_code":"PPL",
    "gn:name":"Wangdayingcun",
    "gn:population":0,
    "gn:timezone":"Asia/Shanghai",
    "iso:country":"CN",
    "name:zho_x_preferred":[
        "\u738b\u5927\u90e2\u6751"
    ],
    "wof:name":"Wangdayingcun",
    "wof:placetype":"locality"
},
  "geometry": {"coordinates":[116.90848,33.11308],"type":"Point"}
}