{
  "type": "Feature",
  "properties": {
    "gn:admin1_code":"13",
    "gn:asciiname":"Kala Wutaike",
    "gn:country_code":"CN",
    "gn:dem":2515,
    "gn:feature_class":"P",
    "gn:feature_code":"PPL",
    "gn:name":"Kala Wutaike",
    "gn:population":0,
    "gn:timezone":"Asia/Urumqi",
    "iso:country":"CN",
    "name:und_x_variant":[
        "\u5580\u62c9\u4e4c\u53f0\u514b"
    ],
    "wof:name":"Kala Wutaike",
    "wof:placetype":"locality"
},
  "geometry": {"coordinates":[94.70353,43.10374],"type":"Point"}
}