{
  "type": "Feature",
  "properties": {
    "gn:admin1_code":"15.0",
    "gn:asciiname":"Shanyangba",
    "gn:country_code":"CN",
    "gn:dem":1799,
    "gn:feature_class":"P",
    "gn:feature_code":"PPL",
    "gn:name":"Shanyangba",
    "gn:population":0,
    "gn:timezone":"Asia/Shanghai",
    "iso:country":"CN",
    "name:und_x_variant":[
        "\u5c71\u7f8a\u575d"
    ],
    "wof:name":"Shanyangba",
    "wof:placetype":"locality"
},
  "geometry": {"coordinates":[105.45341000000001,33.89213],"type":"Point"}
}