{
  "type": "Feature",
  "properties": {
    "gn:admin1_code":"01",
    "gn:asciiname":"Laibanghe",
    "gn:cc2":"CN",
    "gn:country_code":"CN",
    "gn:dem":677,
    "gn:feature_class":"P",
    "gn:feature_code":"PPL",
    "gn:name":"Laibanghe",
    "gn:population":0,
    "gn:timezone":"Asia/Shanghai",
    "iso:country":"CN",
    "name:und_x_variant":[
        "Lai-pang-ho",
        "Lai-pang",
        "Laibang",
        "Laibanghe"
    ],
    "wof:name":"Laibanghe",
    "wof:placetype":"locality"
},
  "geometry": {"coordinates":[116.25,30.93333],"type":"Point"}
}