{
  "type": "Feature",
  "properties": {
    "gn:admin1_code":"19.0",
    "gn:asciiname":"Dongciyu",
    "gn:country_code":"CN",
    "gn:dem":163,
    "gn:feature_class":"P",
    "gn:feature_code":"PPL",
    "gn:name":"Dongciyu",
    "gn:population":0,
    "gn:timezone":"Asia/Shanghai",
    "iso:country":"CN",
    "name:und_x_variant":[
        "\u4e1c\u8328\u5cea"
    ],
    "wof:name":"Dongciyu",
    "wof:placetype":"locality"
},
  "geometry": {"coordinates":[122.5321,40.31466],"type":"Point"}
}