{
  "type": "Feature",
  "properties": {
    "gn:admin1_code":"30.0",
    "gn:asciiname":"Dayukeng",
    "gn:country_code":"CN",
    "gn:dem":324,
    "gn:feature_class":"P",
    "gn:feature_code":"PPL",
    "gn:name":"Dayukeng",
    "gn:population":0,
    "gn:timezone":"Asia/Shanghai",
    "iso:country":"CN",
    "name:zho_x_preferred":[
        "Dayukeng"
    ],
    "name:zho_x_variant":[
        "\u5927\u9c7c\u5751"
    ],
    "wof:name":"Dayukeng",
    "wof:placetype":"locality"
},
  "geometry": {"coordinates":[114.00745999999999,24.60522000000001],"type":"Point"}
}