{
  "type": "Feature",
  "properties": {
    "gn:admin1_code":"7.0",
    "gn:asciiname":"Maikeng",
    "gn:country_code":"CN",
    "gn:dem":510,
    "gn:feature_class":"P",
    "gn:feature_code":"PPL",
    "gn:name":"Maikeng",
    "gn:population":0,
    "gn:timezone":"Asia/Shanghai",
    "iso:country":"CN",
    "name:zho_x_preferred":[
        "\u9ea6\u5751"
    ],
    "wof:name":"Maikeng",
    "wof:placetype":"locality"
},
  "geometry": {"coordinates":[118.29273000000001,27.56044],"type":"Point"}
}