{
  "type": "Feature",
  "properties": {
    "gn:admin1_code":"32.0",
    "gn:asciiname":"Weijiashan",
    "gn:country_code":"CN",
    "gn:dem":1103,
    "gn:feature_class":"P",
    "gn:feature_code":"PPL",
    "gn:name":"Weijiashan",
    "gn:population":0,
    "gn:timezone":"Asia/Shanghai",
    "iso:country":"CN",
    "name:zho_x_preferred":[
        "\u536b\u5bb6\u5c71"
    ],
    "wof:name":"Weijiashan",
    "wof:placetype":"locality"
},
  "geometry": {"coordinates":[102.878,30.1867],"type":"Point"}
}