{
  "type": "Feature",
  "properties": {
    "gn:admin1_code":"9",
    "gn:asciiname":"Qianxulou",
    "gn:country_code":"CN",
    "gn:dem":55,
    "gn:feature_class":"P",
    "gn:feature_code":"PPL",
    "gn:name":"Qianxulou",
    "gn:population":0,
    "gn:timezone":"Asia/Shanghai",
    "iso:country":"CN",
    "name:zho_x_preferred":[
        "\u524d\u8bb8\u697c"
    ],
    "wof:name":"Qianxulou",
    "wof:placetype":"locality"
},
  "geometry": {"coordinates":[115.81211,35.87928],"type":"Point"}
}