{
  "type": "Feature",
  "properties": {
    "gn:admin1_code":"15.0",
    "gn:asciiname":"Majiaotan",
    "gn:country_code":"CN",
    "gn:dem":1559,
    "gn:feature_class":"P",
    "gn:feature_code":"PPL",
    "gn:name":"Majiaotan",
    "gn:population":0,
    "gn:timezone":"Asia/Shanghai",
    "iso:country":"CN",
    "name:und_x_variant":[
        "\u9a6c\u89d2\u6ee9"
    ],
    "wof:name":"Majiaotan",
    "wof:placetype":"locality"
},
  "geometry": {"coordinates":[107.60035999999999,36.73334000000001],"type":"Point"}
}