{
  "type": "Feature",
  "properties": {
    "gn:admin1_code":"10",
    "gn:asciiname":"Hongnitan",
    "gn:country_code":"CN",
    "gn:dem":1435,
    "gn:feature_class":"P",
    "gn:feature_code":"PPL",
    "gn:name":"Hongnitan",
    "gn:population":0,
    "gn:timezone":"Asia/Shanghai",
    "iso:country":"CN",
    "name:zho_x_preferred":[
        "\u7ea2\u6ce5\u6ee9"
    ],
    "wof:name":"Hongnitan",
    "wof:placetype":"locality"
},
  "geometry": {"coordinates":[115.73146,41.37751],"type":"Point"}
}