{
  "type": "Feature",
  "properties": {
    "gn:admin1_code":"32.0",
    "gn:asciiname":"Luogubo",
    "gn:country_code":"CN",
    "gn:dem":1563,
    "gn:feature_class":"P",
    "gn:feature_code":"PPL",
    "gn:name":"Luogubo",
    "gn:population":0,
    "gn:timezone":"Asia/Shanghai",
    "iso:country":"CN",
    "name:zho_x_preferred":[
        "\u6d1b\u53e4\u6ce2"
    ],
    "wof:name":"Luogubo",
    "wof:placetype":"locality"
},
  "geometry": {"coordinates":[102.24285,27.7578],"type":"Point"}
}