{
  "type": "Feature",
  "properties": {
    "gn:admin1_code":"9.0",
    "gn:asciiname":"Beicaotan",
    "gn:country_code":"CN",
    "gn:dem":65,
    "gn:feature_class":"P",
    "gn:feature_code":"PPL",
    "gn:name":"Beicaotan",
    "gn:population":0,
    "gn:timezone":"Asia/Shanghai",
    "iso:country":"CN",
    "name:zho_x_preferred":[
        "\u5317\u8349\u6ee9"
    ],
    "wof:name":"Beicaotan",
    "wof:placetype":"locality"
},
  "geometry": {"coordinates":[114.44099,35.47514],"type":"Point"}
}