{
  "type": "Feature",
  "properties": {
    "gn:admin1_code":"2.0",
    "gn:asciiname":"Miaohou",
    "gn:country_code":"CN",
    "gn:dem":145,
    "gn:feature_class":"P",
    "gn:feature_code":"PPL",
    "gn:name":"Miaohou",
    "gn:population":0,
    "gn:timezone":"Asia/Shanghai",
    "iso:country":"CN",
    "name:zho_x_preferred":[
        "\u5e99\u540e"
    ],
    "wof:name":"Miaohou",
    "wof:placetype":"locality"
},
  "geometry": {"coordinates":[118.60548,29.01486],"type":"Point"}
}