{
  "type": "Feature",
  "properties": {
    "gn:admin1_code":"11.0",
    "gn:asciiname":"Quanmin",
    "gn:country_code":"CN",
    "gn:dem":55,
    "gn:feature_class":"P",
    "gn:feature_code":"PPL",
    "gn:name":"Quanmin",
    "gn:population":0,
    "gn:timezone":"Asia/Shanghai",
    "iso:country":"CN",
    "name:zho_x_preferred":[
        "\u5168\u6c11"
    ],
    "wof:name":"Quanmin",
    "wof:placetype":"locality"
},
  "geometry": {"coordinates":[112.95381999999999,28.69599],"type":"Point"}
}