{
  "type": "Feature",
  "properties": {
    "gn:admin1_code":"18",
    "gn:asciiname":"Heidanzi",
    "gn:country_code":"CN",
    "gn:dem":1176,
    "gn:feature_class":"P",
    "gn:feature_code":"PPL",
    "gn:name":"Heidanzi",
    "gn:population":0,
    "gn:timezone":"Asia/Shanghai",
    "iso:country":"CN",
    "name:zho_x_preferred":[
        "\u9ed1\u65e6\u5b50"
    ],
    "wof:name":"Heidanzi",
    "wof:placetype":"locality"
},
  "geometry": {"coordinates":[106.58199999999999,28.5757],"type":"Point"}
}