{
  "type": "Feature",
  "properties": {
    "gn:admin1_code":"32.0",
    "gn:asciiname":"Mijiagou",
    "gn:country_code":"CN",
    "gn:dem":782,
    "gn:feature_class":"P",
    "gn:feature_code":"PPL",
    "gn:name":"Mijiagou",
    "gn:population":0,
    "gn:timezone":"Asia/Shanghai",
    "iso:country":"CN",
    "name:zho_x_preferred":[
        "\u7c73\u5bb6\u6c9f"
    ],
    "wof:name":"Mijiagou",
    "wof:placetype":"locality"
},
  "geometry": {"coordinates":[107.354,31.7297],"type":"Point"}
}