{
  "type": "Feature",
  "properties": {
    "gn:admin1_code":"9",
    "gn:asciiname":"Wang'erbao",
    "gn:country_code":"CN",
    "gn:dem":54,
    "gn:feature_class":"P",
    "gn:feature_code":"PPL",
    "gn:name":"Wang\u2019erbao",
    "gn:population":0,
    "gn:timezone":"Asia/Shanghai",
    "iso:country":"CN",
    "name:und_x_variant":[
        "Wang\u2019erbao"
    ],
    "name:zho_x_preferred":[
        "\u738b\u4e8c\u4fdd"
    ],
    "wof:name":"Wang'erbao",
    "wof:placetype":"locality"
},
  "geometry": {"coordinates":[115.514,34.4979],"type":"Point"}
}