{
  "type": "Feature",
  "properties": {
    "gn:admin1_code":"5.0",
    "gn:asciiname":"Linjiang Dongcun",
    "gn:country_code":"CN",
    "gn:dem":510,
    "gn:feature_class":"P",
    "gn:feature_code":"PPL",
    "gn:name":"Linjiang Dongcun",
    "gn:population":0,
    "gn:timezone":"Asia/Shanghai",
    "iso:country":"CN",
    "name:zho_x_preferred":[
        "\u4e34\u6c5f\u4e1c\u6751"
    ],
    "wof:name":"Linjiang Dongcun",
    "wof:placetype":"locality"
},
  "geometry": {"coordinates":[128.16492,43.30215],"type":"Point"}
}