{
  "type": "Feature",
  "properties": {
    "gn:admin1_code":"7.0",
    "gn:asciiname":"Songbaijiao",
    "gn:country_code":"CN",
    "gn:dem":339,
    "gn:feature_class":"P",
    "gn:feature_code":"PPL",
    "gn:name":"Songbaijiao",
    "gn:population":0,
    "gn:timezone":"Asia/Shanghai",
    "iso:country":"CN",
    "name:zho_x_preferred":[
        "\u677e\u67cf\u811a"
    ],
    "wof:name":"Songbaijiao",
    "wof:placetype":"locality"
},
  "geometry": {"coordinates":[117.16574,24.36971],"type":"Point"}
}