{
  "type": "Feature",
  "properties": {
    "gn:admin1_code":"26.0",
    "gn:asciiname":"Youfangzhuang",
    "gn:cc2":"CN",
    "gn:country_code":"CN",
    "gn:dem":1659,
    "gn:feature_class":"P",
    "gn:feature_code":"PPL",
    "gn:name":"Youfangzhuang",
    "gn:population":0,
    "gn:timezone":"Asia/Shanghai",
    "iso:country":"CN",
    "name:und_x_variant":[
        "Yu-fang-chuang",
        "Youfangzhuang"
    ],
    "wof:name":"Youfangzhuang",
    "wof:placetype":"locality"
},
  "geometry": {"coordinates":[107.63333,37.35],"type":"Point"}
}