{
  "type": "Feature",
  "properties": {
    "gn:admin1_code":"24.0",
    "gn:asciiname":"Hanweigou",
    "gn:country_code":"CN",
    "gn:dem":1183,
    "gn:feature_class":"P",
    "gn:feature_code":"PPL",
    "gn:name":"Hanweigou",
    "gn:population":0,
    "gn:timezone":"Asia/Shanghai",
    "iso:country":"CN",
    "name:zho_x_preferred":[
        "\u97e9\u5c3e\u6c9f"
    ],
    "wof:name":"Hanweigou",
    "wof:placetype":"locality"
},
  "geometry": {"coordinates":[111.18559999999999,37.31028],"type":"Point"}
}