{
  "type": "Feature",
  "properties": {
    "gn:admin1_code":"10",
    "gn:asciiname":"Beilu",
    "gn:cc2":"CN",
    "gn:country_code":"CN",
    "gn:dem":27,
    "gn:feature_class":"P",
    "gn:feature_code":"PPL",
    "gn:name":"Beilu",
    "gn:population":0,
    "gn:timezone":"Asia/Shanghai",
    "iso:country":"CN",
    "name:und_x_variant":[
        "Pei-y\u00fc-chen",
        "Pei-lu-chen",
        "Pei-lu",
        "Pei-y\u00fc",
        "Beilu"
    ],
    "wof:name":"Beilu",
    "wof:placetype":"locality"
},
  "geometry": {"coordinates":[114.86667,37.46667],"type":"Point"}
}