{
  "type": "Feature",
  "properties": {
    "gn:admin1_code":"4.0",
    "gn:asciiname":"Qixu",
    "gn:country_code":"CN",
    "gn:dem":7,
    "gn:feature_class":"P",
    "gn:feature_code":"PPLA4",
    "gn:name":"Qixu",
    "gn:population":0,
    "gn:timezone":"Asia/Shanghai",
    "iso:country":"CN",
    "name:und_x_variant":[
        "\u4e03\u5729",
        "Qixu Zhen",
        "Dongtouxu",
        "\u4e03\u5729\u9547",
        "\u4e1c\u5934\u5729"
    ],
    "wof:name":"Qixu",
    "wof:placetype":"locality"
},
  "geometry": {"coordinates":[120.01467,32.02739],"type":"Point"}
}