{
  "type": "Feature",
  "properties": {
    "gn:admin1_code":"25",
    "gn:asciiname":"Qianshanbeitou",
    "gn:country_code":"CN",
    "gn:dem":73,
    "gn:feature_class":"P",
    "gn:feature_code":"PPL",
    "gn:name":"Qianshanbeitou",
    "gn:population":0,
    "gn:timezone":"Asia/Shanghai",
    "iso:country":"CN",
    "name:zho_x_preferred":[
        "\u524d\u5c71\u5317\u5934"
    ],
    "wof:name":"Qianshanbeitou",
    "wof:placetype":"locality"
},
  "geometry": {"coordinates":[119.17700000000001,35.3047],"type":"Point"}
}