{
  "type": "Feature",
  "properties": {
    "gn:admin1_code":"7",
    "gn:asciiname":"Yangpingmu",
    "gn:country_code":"CN",
    "gn:dem":975,
    "gn:feature_class":"P",
    "gn:feature_code":"PPL",
    "gn:name":"Yangpingmu",
    "gn:population":0,
    "gn:timezone":"Asia/Shanghai",
    "iso:country":"CN",
    "name:und_x_variant":[
        "\u6768\u576a\u5893",
        "Yangpingmu"
    ],
    "wof:name":"Yangpingmu",
    "wof:placetype":"locality"
},
  "geometry": {"coordinates":[119.36538,27.52421],"type":"Point"}
}