{
  "type": "Feature",
  "properties": {
    "gn:admin1_code":"5.0",
    "gn:asciiname":"Beishan Canchang",
    "gn:country_code":"CN",
    "gn:dem":603,
    "gn:feature_class":"P",
    "gn:feature_code":"PPLF",
    "gn:name":"Beishan Canchang",
    "gn:population":0,
    "gn:timezone":"Asia/Shanghai",
    "iso:country":"CN",
    "name:und_x_variant":[
        "\u5317\u5c71\u53c2\u573a"
    ],
    "wof:name":"Beishan Canchang",
    "wof:placetype":"locality"
},
  "geometry": {"coordinates":[127.23341000000001,42.55274],"type":"Point"}
}