{
  "type": "Feature",
  "properties": {
    "gn:admin1_code":"26.0",
    "gn:asciiname":"Yucuncun",
    "gn:country_code":"CN",
    "gn:dem":1025,
    "gn:feature_class":"P",
    "gn:feature_code":"PPL",
    "gn:name":"Yucuncun",
    "gn:population":0,
    "gn:timezone":"Asia/Shanghai",
    "iso:country":"CN",
    "name:zho_x_preferred":[
        "\u9884\u6751\u6751"
    ],
    "wof:name":"Yucuncun",
    "wof:placetype":"locality"
},
  "geometry": {"coordinates":[106.82899999999999,34.81137],"type":"Point"}
}