{
  "type": "Feature",
  "properties": {
    "gn:admin1_code":"15.0",
    "gn:asciiname":"Baozizhuang",
    "gn:country_code":"CN",
    "gn:dem":1314,
    "gn:feature_class":"P",
    "gn:feature_code":"PPL",
    "gn:name":"Baozizhuang",
    "gn:population":0,
    "gn:timezone":"Asia/Shanghai",
    "iso:country":"CN",
    "name:zho_x_preferred":[
        "\u8c79\u5b50\u5e84"
    ],
    "wof:name":"Baozizhuang",
    "wof:placetype":"locality"
},
  "geometry": {"coordinates":[108.182,36.0184],"type":"Point"}
}