{
  "type": "Feature",
  "properties": {
    "gn:admin1_code":"29.0",
    "gn:asciiname":"Bengdui",
    "gn:country_code":"CN",
    "gn:dem":3253,
    "gn:feature_class":"P",
    "gn:feature_code":"PPL",
    "gn:name":"Bengdui",
    "gn:population":0,
    "gn:timezone":"Asia/Shanghai",
    "iso:country":"CN",
    "name:zho_x_preferred":[
        "\u5d29\u5806"
    ],
    "wof:name":"Bengdui",
    "wof:placetype":"locality"
},
  "geometry": {"coordinates":[99.69672,28.76703],"type":"Point"}
}