{
  "type": "Feature",
  "properties": {
    "gn:admin1_code":"2.0",
    "gn:asciiname":"Jiangwudi",
    "gn:country_code":"CN",
    "gn:dem":56,
    "gn:feature_class":"P",
    "gn:feature_code":"PPL",
    "gn:name":"Jiangwudi",
    "gn:population":0,
    "gn:timezone":"Asia/Shanghai",
    "iso:country":"CN",
    "name:zho_x_preferred":[
        "\u59dc\u575e\u5e95"
    ],
    "wof:name":"Jiangwudi",
    "wof:placetype":"locality"
},
  "geometry": {"coordinates":[119.3036,29.2105],"type":"Point"}
}