{
  "type": "Feature",
  "properties": {
    "gn:admin1_code":"19.0",
    "gn:asciiname":"Dongwafangcun",
    "gn:country_code":"CN",
    "gn:dem":185,
    "gn:feature_class":"P",
    "gn:feature_code":"PPL",
    "gn:name":"Dongwafangcun",
    "gn:population":0,
    "gn:timezone":"Asia/Shanghai",
    "iso:country":"CN",
    "name:zho_x_preferred":[
        "\u4e1c\u74e6\u623f\u6751"
    ],
    "wof:name":"Dongwafangcun",
    "wof:placetype":"locality"
},
  "geometry": {"coordinates":[121.67700000000001,41.9478],"type":"Point"}
}