{
  "type": "Feature",
  "properties": {
    "gn:admin1_code":"18",
    "gn:asciiname":"Dalaodi",
    "gn:country_code":"CN",
    "gn:dem":1772,
    "gn:feature_class":"P",
    "gn:feature_code":"PPL",
    "gn:name":"Dalaodi",
    "gn:population":0,
    "gn:timezone":"Asia/Shanghai",
    "iso:country":"CN",
    "name:zho_x_preferred":[
        "\u5927\u8001\u5730"
    ],
    "wof:name":"Dalaodi",
    "wof:placetype":"locality"
},
  "geometry": {"coordinates":[105.551,26.4691],"type":"Point"}
}