{
  "type": "Feature",
  "properties": {
    "gn:admin1_code":"7.0",
    "gn:asciiname":"Chi'ao",
    "gn:country_code":"CN",
    "gn:dem":22,
    "gn:feature_class":"P",
    "gn:feature_code":"PPL",
    "gn:name":"Chi\u2019ao",
    "gn:population":0,
    "gn:timezone":"Asia/Shanghai",
    "iso:country":"CN",
    "name:und_x_variant":[
        "Chi\u2019ao"
    ],
    "name:zho_x_preferred":[
        "\u8d64\u6fb3"
    ],
    "wof:name":"Chi'ao",
    "wof:placetype":"locality"
},
  "geometry": {"coordinates":[119.8629,26.31512],"type":"Point"}
}