{
  "type": "Feature",
  "properties": {
    "gn:admin1_code":"15.0",
    "gn:asciiname":"Fengshan",
    "gn:country_code":"CN",
    "gn:dem":1864,
    "gn:feature_class":"P",
    "gn:feature_code":"PPL",
    "gn:name":"Fengshan",
    "gn:population":0,
    "gn:timezone":"Asia/Shanghai",
    "iso:country":"CN",
    "name:ceb_x_preferred":[
        "Fengshan"
    ],
    "name:deu_x_preferred":[
        "Fengshan"
    ],
    "name:fra_x_preferred":[
        "Fengshan"
    ],
    "name:nor_x_preferred":[
        "Fengshan"
    ],
    "name:swe_x_preferred":[
        "Fengshan"
    ],
    "name:vie_x_preferred":[
        "Ph\u01b0\u1ee3ng S\u01a1n"
    ],
    "name:zho_x_preferred":[
        "\u51af\u5c71"
    ],
    "wof:name":"Fengshan",
    "wof:placetype":"locality"
},
  "geometry": {"coordinates":[105.04900000000001,34.8791],"type":"Point"}
}