{
  "type": "Feature",
  "properties": {
    "gn:admin1_code":"11.0",
    "gn:asciiname":"Qileishan",
    "gn:country_code":"CN",
    "gn:dem":797,
    "gn:feature_class":"P",
    "gn:feature_code":"PPL",
    "gn:name":"Qileishan",
    "gn:population":0,
    "gn:timezone":"Asia/Shanghai",
    "iso:country":"CN",
    "name:zho_x_preferred":[
        "\u6b67\u5792\u5c71"
    ],
    "wof:name":"Qileishan",
    "wof:placetype":"locality"
},
  "geometry": {"coordinates":[111.89594,26.1594],"type":"Point"}
}