{
  "type": "Feature",
  "properties": {
    "gn:admin1_code":"16.0",
    "gn:asciiname":"Shangbakou",
    "gn:country_code":"CN",
    "gn:dem":488,
    "gn:feature_class":"P",
    "gn:feature_code":"PPL",
    "gn:name":"Shangbakou",
    "gn:population":0,
    "gn:timezone":"Asia/Shanghai",
    "iso:country":"CN",
    "name:zho_x_preferred":[
        "\u4e0a\u8019\u53e3"
    ],
    "wof:name":"Shangbakou",
    "wof:placetype":"locality"
},
  "geometry": {"coordinates":[111.551,24.1783],"type":"Point"}
}