{
  "type": "Feature",
  "properties": {
    "gn:admin1_code":"33.0",
    "gn:asciiname":"Zheyan",
    "gn:country_code":"CN",
    "gn:dem":1022,
    "gn:feature_class":"P",
    "gn:feature_code":"PPL",
    "gn:name":"Zheyan",
    "gn:population":0,
    "gn:timezone":"Asia/Shanghai",
    "iso:country":"CN",
    "name:zho_x_preferred":[
        "\u6298\u5ca9"
    ],
    "wof:name":"Zheyan",
    "wof:placetype":"locality"
},
  "geometry": {"coordinates":[108.62641000000001,30.53508],"type":"Point"}
}