{
  "type": "Feature",
  "properties": {
    "gn:admin1_code":"32.0",
    "gn:asciiname":"Xiabagou",
    "gn:country_code":"CN",
    "gn:dem":2377,
    "gn:feature_class":"P",
    "gn:feature_code":"PPL",
    "gn:name":"Xiabagou",
    "gn:population":0,
    "gn:timezone":"Asia/Shanghai",
    "iso:country":"CN",
    "name:zho_x_preferred":[
        "\u867e\u8019\u6c9f"
    ],
    "wof:name":"Xiabagou",
    "wof:placetype":"locality"
},
  "geometry": {"coordinates":[101.41500000000001,27.4356],"type":"Point"}
}