{
  "type": "Feature",
  "properties": {
    "gn:admin1_code":"19.0",
    "gn:asciiname":"Foyelingliangbei",
    "gn:country_code":"CN",
    "gn:dem":200,
    "gn:feature_class":"P",
    "gn:feature_code":"PPL",
    "gn:name":"Foyelingliangbei",
    "gn:population":0,
    "gn:timezone":"Asia/Shanghai",
    "iso:country":"CN",
    "name:zho_x_preferred":[
        "\u4f5b\u7237\u5cad\u6881\u5317"
    ],
    "wof:name":"Foyelingliangbei",
    "wof:placetype":"locality"
},
  "geometry": {"coordinates":[121.93300000000001,42.0232],"type":"Point"}
}