{
  "type": "Feature",
  "properties": {
    "gn:admin1_code":"26.0",
    "gn:asciiname":"Wuchangcun",
    "gn:country_code":"CN",
    "gn:dem":743,
    "gn:feature_class":"P",
    "gn:feature_code":"PPL",
    "gn:name":"Wuchangcun",
    "gn:population":0,
    "gn:timezone":"Asia/Shanghai",
    "iso:country":"CN",
    "name:zho_x_preferred":[
        "\u5c4b\u573a\u6751"
    ],
    "wof:name":"Wuchangcun",
    "wof:placetype":"locality"
},
  "geometry": {"coordinates":[109.47975,32.59244],"type":"Point"}
}