{
  "type": "Feature",
  "properties": {
    "gn:admin1_code":"4.0",
    "gn:asciiname":"Yuqiaocun",
    "gn:country_code":"CN",
    "gn:dem":1,
    "gn:feature_class":"P",
    "gn:feature_code":"PPL",
    "gn:name":"Yuqiaocun",
    "gn:population":0,
    "gn:timezone":"Asia/Shanghai",
    "iso:country":"CN",
    "name:zho_x_preferred":[
        "\u9c7c\u6865\u6751"
    ],
    "wof:name":"Yuqiaocun",
    "wof:placetype":"locality"
},
  "geometry": {"coordinates":[119.38531999999999,33.30188],"type":"Point"}
}