{
  "type": "Feature",
  "properties": {
    "gn:admin1_code":"26.0",
    "gn:asciiname":"Dadianzi",
    "gn:country_code":"CN",
    "gn:dem":1608,
    "gn:feature_class":"P",
    "gn:feature_code":"PPL",
    "gn:name":"Dadianzi",
    "gn:population":0,
    "gn:timezone":"Asia/Shanghai",
    "iso:country":"CN",
    "name:und_x_variant":[
        "\u5927\u5e97\u5b50"
    ],
    "wof:name":"Dadianzi",
    "wof:placetype":"locality"
},
  "geometry": {"coordinates":[107.96156000000001,33.71382],"type":"Point"}
}