{
  "type": "Feature",
  "properties": {
    "gn:admin1_code":"3",
    "gn:asciiname":"Wulishan",
    "gn:country_code":"CN",
    "gn:dem":364,
    "gn:feature_class":"P",
    "gn:feature_code":"PPL",
    "gn:name":"Wulishan",
    "gn:population":0,
    "gn:timezone":"Asia/Shanghai",
    "iso:country":"CN",
    "name:und_x_variant":[
        "\u4e94\u91cc\u5c71"
    ],
    "name:zho_x_preferred":[
        "\u4e94\u91cc\u5c71"
    ],
    "wof:name":"Wulishan",
    "wof:placetype":"locality"
},
  "geometry": {"coordinates":[117.02333,27.84417],"type":"Point"}
}