{
  "type": "Feature",
  "properties": {
    "gn:admin1_code":"16.0",
    "gn:asciiname":"Laoyuping",
    "gn:country_code":"CN",
    "gn:dem":201,
    "gn:feature_class":"P",
    "gn:feature_code":"PPL",
    "gn:name":"Laoyuping",
    "gn:population":0,
    "gn:timezone":"Asia/Shanghai",
    "iso:country":"CN",
    "name:zho_x_preferred":[
        "\u8001\u4f59\u576a"
    ],
    "wof:name":"Laoyuping",
    "wof:placetype":"locality"
},
  "geometry": {"coordinates":[110.22799999999999,23.8475],"type":"Point"}
}