{
  "type": "Feature",
  "properties": {
    "gn:admin1_code":"32.0",
    "gn:asciiname":"Caokezangzu",
    "gn:country_code":"CN",
    "gn:dem":1498,
    "gn:feature_class":"P",
    "gn:feature_code":"PPL",
    "gn:name":"Caokezangzu",
    "gn:population":0,
    "gn:timezone":"Asia/Shanghai",
    "iso:country":"CN",
    "name:zho_x_preferred":[
        "\u8349\u79d1\u85cf\u65cf"
    ],
    "wof:name":"Caokezangzu",
    "wof:placetype":"locality"
},
  "geometry": {"coordinates":[102.12287999999999,29.39882],"type":"Point"}
}