{
  "type": "Feature",
  "properties": {
    "gn:admin1_code":"6.0",
    "gn:asciiname":"Xireg",
    "gn:country_code":"CN",
    "gn:dem":2950,
    "gn:feature_class":"P",
    "gn:feature_code":"PPLA3",
    "gn:name":"Xireg",
    "gn:population":0,
    "gn:timezone":"Asia/Urumqi",
    "iso:country":"CN",
    "name:und_x_variant":[
        "Hsi-li-kou",
        "Wu-lan",
        "Kukubeli",
        "Ulan",
        "Kokobeli",
        "Tu-lan-hsien",
        "Xiligou",
        "Tu-lan",
        "Xireg",
        "Wulan Xian"
    ],
    "name:zho_x_preferred":[
        "\u5e0c\u91cc\u6c9f"
    ],
    "name:zho_x_variant":[
        "\u4e4c\u5170\u53bf",
        "\u5e0c\u91cc\u6c9f\u9547"
    ],
    "wof:name":"Xireg",
    "wof:placetype":"locality"
},
  "geometry": {"coordinates":[98.44463,36.91866],"type":"Point"}
}