{
  "type": "Feature",
  "properties": {
    "gn:admin1_code":"32.0",
    "gn:asciiname":"Jiguang",
    "gn:country_code":"CN",
    "gn:dem":490,
    "gn:feature_class":"P",
    "gn:feature_code":"PPL",
    "gn:name":"Jiguang",
    "gn:population":0,
    "gn:timezone":"Asia/Shanghai",
    "iso:country":"CN",
    "name:zho_x_preferred":[
        "\u6d4e\u5149"
    ],
    "wof:name":"Jiguang",
    "wof:placetype":"locality"
},
  "geometry": {"coordinates":[103.538,30.0451],"type":"Point"}
}