{
  "type": "Feature",
  "properties": {
    "gn:admin1_code":"3.0",
    "gn:asciiname":"Yexilong",
    "gn:country_code":"CN",
    "gn:dem":34,
    "gn:feature_class":"P",
    "gn:feature_code":"PPL",
    "gn:name":"Yexilong",
    "gn:population":0,
    "gn:timezone":"Asia/Shanghai",
    "iso:country":"CN",
    "name:und_x_variant":[
        "\u91ce\u6eaa\u5784"
    ],
    "wof:name":"Yexilong",
    "wof:placetype":"locality"
},
  "geometry": {"coordinates":[116.37067,29.26218],"type":"Point"}
}