{
  "type": "Feature",
  "properties": {
    "gn:admin1_code":"15.0",
    "gn:asciiname":"Zange",
    "gn:country_code":"CN",
    "gn:dem":3287,
    "gn:feature_class":"P",
    "gn:feature_code":"PPL",
    "gn:name":"Zange",
    "gn:population":0,
    "gn:timezone":"Asia/Shanghai",
    "iso:country":"CN",
    "name:zho_x_preferred":[
        "\u8d5e\u683c"
    ],
    "wof:name":"Zange",
    "wof:placetype":"locality"
},
  "geometry": {"coordinates":[102.215,34.6626],"type":"Point"}
}