{
  "type": "Feature",
  "properties": {
    "gn:admin1_code":"32.0",
    "gn:asciiname":"Sazhong",
    "gn:cc2":"CN",
    "gn:country_code":"CN",
    "gn:dem":3103,
    "gn:feature_class":"P",
    "gn:feature_code":"PPL",
    "gn:name":"Sazhong",
    "gn:population":0,
    "gn:timezone":"Asia/Shanghai",
    "iso:country":"CN",
    "name:bod_x_preferred":[
        "\u0f66\u0f0b\u0f42\u0fb2\u0f7c\u0f44"
    ],
    "name:und_x_variant":[
        "Dagxoi",
        "Shui-wa",
        "Tao-hs\u00fceh",
        "Sowa",
        "Shagong"
    ],
    "name:zho_x_preferred":[
        "\u6c99\u8d21"
    ],
    "wof:name":"Sazhong",
    "wof:placetype":"locality"
},
  "geometry": {"coordinates":[99.90778,29.13192],"type":"Point"}
}