{
  "type": "Feature",
  "properties": {
    "gn:admin1_code":"7.0",
    "gn:asciiname":"Shangfukeng",
    "gn:country_code":"CN",
    "gn:dem":146,
    "gn:feature_class":"P",
    "gn:feature_code":"PPL",
    "gn:name":"Shangfukeng",
    "gn:population":0,
    "gn:timezone":"Asia/Shanghai",
    "iso:country":"CN",
    "name:zho_x_preferred":[
        "\u4e0a\u4f0f\u5751"
    ],
    "wof:name":"Shangfukeng",
    "wof:placetype":"locality"
},
  "geometry": {"coordinates":[117.98466999999999,26.58903],"type":"Point"}
}