{
  "type": "Feature",
  "properties": {
    "gn:admin1_code":"18",
    "gn:asciiname":"Shangkalong",
    "gn:country_code":"CN",
    "gn:dem":1535,
    "gn:feature_class":"P",
    "gn:feature_code":"PPL",
    "gn:name":"Shangkalong",
    "gn:population":0,
    "gn:timezone":"Asia/Shanghai",
    "iso:country":"CN",
    "name:zho_x_preferred":[
        "\u4e0a\u5361\u7b3c"
    ],
    "wof:name":"Shangkalong",
    "wof:placetype":"locality"
},
  "geometry": {"coordinates":[105.03400000000001,25.286],"type":"Point"}
}