{
  "type": "Feature",
  "properties": {
    "gn:admin1_code":"30.0",
    "gn:asciiname":"Guoshuili",
    "gn:country_code":"CN",
    "gn:dem":302,
    "gn:feature_class":"P",
    "gn:feature_code":"PPL",
    "gn:name":"Guoshuili",
    "gn:population":0,
    "gn:timezone":"Asia/Shanghai",
    "iso:country":"CN",
    "name:und_x_variant":[
        "\u8fc7\u6c34\u6ca5"
    ],
    "name:zho_x_preferred":[
        "\u8fc7\u6c34\u6ca5"
    ],
    "wof:name":"Guoshuili",
    "wof:placetype":"locality"
},
  "geometry": {"coordinates":[114.79604999999999,23.44656],"type":"Point"}
}