{
  "type": "Feature",
  "properties": {
    "gn:admin1_code":"5",
    "gn:asciiname":"Xidailuhe",
    "gn:country_code":"CN",
    "gn:dem":360,
    "gn:feature_class":"P",
    "gn:feature_code":"PPL",
    "gn:name":"Xidailuhe",
    "gn:population":0,
    "gn:timezone":"Asia/Shanghai",
    "iso:country":"CN",
    "name:zho_x_preferred":[
        "\u897f\u4ee3\u9732\u6cb3"
    ],
    "wof:name":"Xidailuhe",
    "wof:placetype":"locality"
},
  "geometry": {"coordinates":[127.05445,43.47736],"type":"Point"}
}