{
  "type": "Feature",
  "properties": {
    "gn:admin1_code":"10",
    "gn:asciiname":"Wulagou",
    "gn:country_code":"CN",
    "gn:dem":876,
    "gn:feature_class":"P",
    "gn:feature_code":"PPL",
    "gn:name":"Wulagou",
    "gn:population":0,
    "gn:timezone":"Asia/Shanghai",
    "iso:country":"CN",
    "name:zho_x_preferred":[
        "\u4e4c\u62c9\u6c9f"
    ],
    "wof:name":"Wulagou",
    "wof:placetype":"locality"
},
  "geometry": {"coordinates":[117.83004,41.86684],"type":"Point"}
}