{
  "type": "Feature",
  "properties": {
    "gn:admin1_code":"20.0",
    "gn:asciiname":"Houjia Langgou",
    "gn:country_code":"CN",
    "gn:dem":1201,
    "gn:feature_class":"P",
    "gn:feature_code":"PPL",
    "gn:name":"Houjia Langgou",
    "gn:population":0,
    "gn:timezone":"Asia/Shanghai",
    "iso:country":"CN",
    "name:und_x_variant":[
        "\u540e\u8d3e\u6d6a\u6c9f"
    ],
    "wof:name":"Houjia Langgou",
    "wof:placetype":"locality"
},
  "geometry": {"coordinates":[111.45869999999999,40.10004],"type":"Point"}
}