{
  "type": "Feature",
  "properties": {
    "gn:admin1_code":"9.0",
    "gn:asciiname":"Shangyanke",
    "gn:country_code":"CN",
    "gn:dem":513,
    "gn:feature_class":"P",
    "gn:feature_code":"PPL",
    "gn:name":"Shangyanke",
    "gn:population":0,
    "gn:timezone":"Asia/Shanghai",
    "iso:country":"CN",
    "name:zho_x_preferred":[
        "\u4e0a\u781a\u79d1"
    ],
    "wof:name":"Shangyanke",
    "wof:placetype":"locality"
},
  "geometry": {"coordinates":[113.86172000000001,36.25181],"type":"Point"}
}