{
  "type": "Feature",
  "properties": {
    "gn:admin1_code":"7.0",
    "gn:asciiname":"Huangtudong",
    "gn:country_code":"CN",
    "gn:dem":364,
    "gn:feature_class":"P",
    "gn:feature_code":"PPL",
    "gn:name":"Huangtudong",
    "gn:population":0,
    "gn:timezone":"Asia/Shanghai",
    "iso:country":"CN",
    "name:und_x_variant":[
        "\u9ec4\u571f\u6d1e"
    ],
    "name:zho_x_preferred":[
        "\u9ec4\u571f\u6d1e"
    ],
    "wof:name":"Huangtudong",
    "wof:placetype":"locality"
},
  "geometry": {"coordinates":[117.26967999999999,26.37998],"type":"Point"}
}