{
  "type": "Feature",
  "properties": {
    "gn:admin1_code":"4.0",
    "gn:asciiname":"Xiwang",
    "gn:country_code":"CN",
    "gn:dem":2,
    "gn:feature_class":"P",
    "gn:feature_code":"PPL",
    "gn:name":"Xiwang",
    "gn:population":0,
    "gn:timezone":"Asia/Shanghai",
    "iso:country":"CN",
    "name:zho_x_preferred":[
        "Xiwang"
    ],
    "name:zho_x_variant":[
        "\u897f\u738b"
    ],
    "wof:name":"Xiwang",
    "wof:placetype":"locality"
},
  "geometry": {"coordinates":[119.59180000000001,33.09563],"type":"Point"}
}