{
  "type": "Feature",
  "properties": {
    "gn:admin1_code":"29.0",
    "gn:asciiname":"Fuquma",
    "gn:country_code":"CN",
    "gn:dem":1445,
    "gn:feature_class":"P",
    "gn:feature_code":"PPL",
    "gn:name":"Fuquma",
    "gn:population":0,
    "gn:timezone":"Asia/Shanghai",
    "iso:country":"CN",
    "name:zho_x_preferred":[
        "\u5bcc\u53bb\u5988"
    ],
    "wof:name":"Fuquma",
    "wof:placetype":"locality"
},
  "geometry": {"coordinates":[99.9357,25.2119],"type":"Point"}
}