{
  "type": "Feature",
  "properties": {
    "gn:admin1_code":"3.0",
    "gn:asciiname":"Shuanggangkou",
    "gn:country_code":"CN",
    "gn:dem":499,
    "gn:feature_class":"P",
    "gn:feature_code":"PPL",
    "gn:name":"Shuanggangkou",
    "gn:population":0,
    "gn:timezone":"Asia/Shanghai",
    "iso:country":"CN",
    "name:zho_x_preferred":[
        "\u53cc\u6e2f\u53e3"
    ],
    "wof:name":"Shuanggangkou",
    "wof:placetype":"locality"
},
  "geometry": {"coordinates":[117.1722,27.76504000000001],"type":"Point"}
}