{
  "type": "Feature",
  "properties": {
    "gn:admin1_code":"10.0",
    "gn:asciiname":"Xiaoshan",
    "gn:cc2":"CN",
    "gn:country_code":"CN",
    "gn:dem":5,
    "gn:feature_class":"P",
    "gn:feature_code":"PPL",
    "gn:name":"Xiaoshan",
    "gn:population":0,
    "gn:timezone":"Asia/Shanghai",
    "iso:country":"CN",
    "name:und_x_variant":[
        "Siao shan",
        "Hsiao-shan-chuang",
        "Hsiao-shan",
        "Xiaoshan"
    ],
    "wof:name":"Xiaoshan",
    "wof:placetype":"locality"
},
  "geometry": {"coordinates":[117.57583,38.17083],"type":"Point"}
}