{
  "type": "Feature",
  "properties": {
    "gn:admin1_code":"20",
    "gn:asciiname":"Biqeq",
    "gn:cc2":"CN",
    "gn:country_code":"CN",
    "gn:dem":1043,
    "gn:feature_class":"P",
    "gn:feature_code":"PPL",
    "gn:name":"Biqeq",
    "gn:population":0,
    "gn:timezone":"Asia/Shanghai",
    "iso:country":"CN",
    "name:und_x_variant":[
        "Pi-k\u2019o-ch\u2019i",
        "Biketsi",
        "Pikotsi",
        "Bikeqi",
        "Biqeq"
    ],
    "wof:name":"Biqeq",
    "wof:placetype":"locality"
},
  "geometry": {"coordinates":[111.28917,40.73111],"type":"Point"}
}