{
  "type": "Feature",
  "properties": {
    "gn:admin1_code":"14.0",
    "gn:asciiname":"Bianriwuqie",
    "gn:country_code":"CN",
    "gn:dem":4755,
    "gn:feature_class":"P",
    "gn:feature_code":"PPL",
    "gn:name":"Bianriwuqie",
    "gn:population":0,
    "gn:timezone":"Asia/Urumqi",
    "iso:country":"CN",
    "name:zho_x_preferred":[
        "\u8fb9\u65e5\u543e\u5207"
    ],
    "wof:name":"Bianriwuqie",
    "wof:placetype":"locality"
},
  "geometry": {"coordinates":[90.83324,31.17814000000001],"type":"Point"}
}