{
  "type": "Feature",
  "properties": {
    "gn:admin1_code":"21.0",
    "gn:asciiname":"Dazhanchang",
    "gn:country_code":"CN",
    "gn:dem":1264,
    "gn:feature_class":"P",
    "gn:feature_code":"PPL",
    "gn:name":"Dazhanchang",
    "gn:population":0,
    "gn:timezone":"Asia/Shanghai",
    "iso:country":"CN",
    "name:zho_x_preferred":[
        "\u5927\u6218\u573a"
    ],
    "wof:name":"Dazhanchang",
    "wof:placetype":"locality"
},
  "geometry": {"coordinates":[105.536,37.422],"type":"Point"}
}