{
  "type": "Feature",
  "properties": {
    "gn:admin1_code":"30",
    "gn:asciiname":"Shatang",
    "gn:country_code":"CN",
    "gn:dem":45,
    "gn:feature_class":"P",
    "gn:feature_code":"PPL",
    "gn:name":"Shatang",
    "gn:population":0,
    "gn:timezone":"Asia/Urumqi",
    "iso:country":"CN",
    "name:zho_x_preferred":[
        "\u6c99\u5858"
    ],
    "wof:name":"Shatang",
    "wof:placetype":"locality"
},
  "geometry": {"coordinates":[110.14982000000001,21.64813],"type":"Point"}
}