{
  "type": "Feature",
  "properties": {
    "gn:admin1_code":"32.0",
    "gn:asciiname":"Jiasangka",
    "gn:country_code":"CN",
    "gn:dem":3424,
    "gn:feature_class":"P",
    "gn:feature_code":"PPL",
    "gn:name":"Jiasangka",
    "gn:population":0,
    "gn:timezone":"Asia/Shanghai",
    "iso:country":"CN",
    "name:zho_x_preferred":[
        "\u8d3e\u6851\u5361"
    ],
    "wof:name":"Jiasangka",
    "wof:placetype":"locality"
},
  "geometry": {"coordinates":[98.3918,32.0688],"type":"Point"}
}