{
  "type": "Feature",
  "properties": {
    "gn:admin1_code":"26.0",
    "gn:asciiname":"Jiepaisi",
    "gn:country_code":"CN",
    "gn:dem":729,
    "gn:feature_class":"P",
    "gn:feature_code":"PPL",
    "gn:name":"Jiepaisi",
    "gn:population":0,
    "gn:timezone":"Asia/Shanghai",
    "iso:country":"CN",
    "name:zho_x_preferred":[
        "\u754c\u724c\u5bfa"
    ],
    "wof:name":"Jiepaisi",
    "wof:placetype":"locality"
},
  "geometry": {"coordinates":[107.22879,32.87653],"type":"Point"}
}