{
  "type": "Feature",
  "properties": {
    "gn:admin1_code":"32.0",
    "gn:asciiname":"Huangyangguanzangzu",
    "gn:country_code":"CN",
    "gn:dem":1490,
    "gn:feature_class":"P",
    "gn:feature_code":"PPL",
    "gn:name":"Huangyangguanzangzu",
    "gn:population":0,
    "gn:timezone":"Asia/Shanghai",
    "iso:country":"CN",
    "name:zho_x_preferred":[
        "\u9ec4\u7f8a\u5173\u85cf\u65cf"
    ],
    "wof:name":"Huangyangguanzangzu",
    "wof:placetype":"locality"
},
  "geometry": {"coordinates":[104.22205,32.5488],"type":"Point"}
}