{
  "type": "Feature",
  "properties": {
    "gn:admin1_code":"29.0",
    "gn:asciiname":"Jiefang",
    "gn:country_code":"CN",
    "gn:dem":1368,
    "gn:feature_class":"P",
    "gn:feature_code":"PPL",
    "gn:name":"Jiefang",
    "gn:population":0,
    "gn:timezone":"Asia/Shanghai",
    "iso:country":"CN",
    "name:zho_x_preferred":[
        "\u89e3\u653e"
    ],
    "wof:name":"Jiefang",
    "wof:placetype":"locality"
},
  "geometry": {"coordinates":[102.364,22.8345],"type":"Point"}
}