{
  "type": "Feature",
  "properties": {
    "gn:admin1_code":"18.0",
    "gn:asciiname":"Yingpan",
    "gn:cc2":"CN",
    "gn:country_code":"CN",
    "gn:dem":1114,
    "gn:feature_class":"P",
    "gn:feature_code":"PPL",
    "gn:name":"Yingpan",
    "gn:population":0,
    "gn:timezone":"Asia/Shanghai",
    "iso:country":"CN",
    "name:ceb_x_preferred":[
        "Yingpan"
    ],
    "name:deu_x_preferred":[
        "Yingpan"
    ],
    "name:swe_x_preferred":[
        "Yingpan"
    ],
    "name:und_x_variant":[
        "Yunpan",
        "Yingpan"
    ],
    "name:zho_x_preferred":[
        "\u8425\u76d8\u9547"
    ],
    "wof:name":"Yingpan",
    "wof:placetype":"locality"
},
  "geometry": {"coordinates":[106.31305999999999,25.92972],"type":"Point"}
}