{
  "type": "Feature",
  "properties": {
    "gn:admin1_code":"29.0",
    "gn:asciiname":"Jitongshui",
    "gn:country_code":"CN",
    "gn:dem":2824,
    "gn:feature_class":"P",
    "gn:feature_code":"PPL",
    "gn:name":"Jitongshui",
    "gn:population":0,
    "gn:timezone":"Asia/Shanghai",
    "iso:country":"CN",
    "name:zho_x_preferred":[
        "\u51e0\u901a\u6c34"
    ],
    "wof:name":"Jitongshui",
    "wof:placetype":"locality"
},
  "geometry": {"coordinates":[99.27719999999999,27.9324],"type":"Point"}
}