{
  "type": "Feature",
  "properties": {
    "gn:admin1_code":"30.0",
    "gn:asciiname":"Sijiaolou",
    "gn:country_code":"CN",
    "gn:dem":204,
    "gn:feature_class":"P",
    "gn:feature_code":"PPL",
    "gn:name":"Sijiaolou",
    "gn:population":0,
    "gn:timezone":"Asia/Shanghai",
    "iso:country":"CN",
    "name:zho_x_preferred":[
        "Sijiaolou"
    ],
    "name:zho_x_variant":[
        "\u56db\u89d2\u697c"
    ],
    "wof:name":"Sijiaolou",
    "wof:placetype":"locality"
},
  "geometry": {"coordinates":[115.39028,24.32833],"type":"Point"}
}