{
  "type": "Feature",
  "properties": {
    "gn:admin1_code":"14.0",
    "gn:asciiname":"Nahuoji",
    "gn:country_code":"CN",
    "gn:dem":4111,
    "gn:feature_class":"P",
    "gn:feature_code":"PPL",
    "gn:name":"Nahuoji",
    "gn:population":0,
    "gn:timezone":"Asia/Urumqi",
    "iso:country":"CN",
    "name:zho_x_preferred":[
        "\u90a3\u8d27\u7ed9"
    ],
    "wof:name":"Nahuoji",
    "wof:placetype":"locality"
},
  "geometry": {"coordinates":[96.29040000000001,31.52913],"type":"Point"}
}