{
  "type": "Feature",
  "properties": {
    "gn:admin1_code":"18",
    "gn:asciiname":"Shiyakou",
    "gn:country_code":"CN",
    "gn:dem":1680,
    "gn:feature_class":"P",
    "gn:feature_code":"PPL",
    "gn:name":"Shiyakou",
    "gn:population":0,
    "gn:timezone":"Asia/Shanghai",
    "iso:country":"CN",
    "name:zho_x_preferred":[
        "\u77f3\u57ad\u53e3"
    ],
    "wof:name":"Shiyakou",
    "wof:placetype":"locality"
},
  "geometry": {"coordinates":[104.938,25.6554],"type":"Point"}
}