{
  "type": "Feature",
  "properties": {
    "gn:admin1_code":"29.0",
    "gn:asciiname":"Kaiwen Shangcun",
    "gn:country_code":"CN",
    "gn:dem":2377,
    "gn:feature_class":"P",
    "gn:feature_code":"PPL",
    "gn:name":"Kaiwen Shangcun",
    "gn:population":0,
    "gn:timezone":"Asia/Shanghai",
    "iso:country":"CN",
    "name:zho_x_preferred":[
        "\u5f00\u6587\u4e0a\u6751"
    ],
    "wof:name":"Kaiwen Shangcun",
    "wof:placetype":"locality"
},
  "geometry": {"coordinates":[100.264,26.8705],"type":"Point"}
}