{
  "type": "Feature",
  "properties": {
    "gn:admin1_code":"10",
    "gn:asciiname":"Caowutuan",
    "gn:country_code":"CN",
    "gn:dem":34,
    "gn:feature_class":"P",
    "gn:feature_code":"PPL",
    "gn:name":"Caowutuan",
    "gn:population":0,
    "gn:timezone":"Asia/Shanghai",
    "iso:country":"CN",
    "name:zho_x_preferred":[
        "\u66f9\u4f0d\u7583"
    ],
    "wof:name":"Caowutuan",
    "wof:placetype":"locality"
},
  "geometry": {"coordinates":[114.88500000000001,37.683],"type":"Point"}
}