{
  "type": "Feature",
  "properties": {
    "gn:admin1_code":"7.0",
    "gn:asciiname":"Luxia",
    "gn:country_code":"CN",
    "gn:dem":10,
    "gn:feature_class":"P",
    "gn:feature_code":"PPL",
    "gn:name":"Luxia",
    "gn:population":0,
    "gn:timezone":"Asia/Shanghai",
    "iso:country":"CN",
    "name:zho_x_preferred":[
        "\u80ea\u53a6"
    ],
    "wof:name":"Luxia",
    "wof:placetype":"locality"
},
  "geometry": {"coordinates":[119.33947999999999,26.01016],"type":"Point"}
}