{
  "type": "Feature",
  "properties": {
    "gn:admin1_code":"33.0",
    "gn:asciiname":"Xiangwan",
    "gn:country_code":"CN",
    "gn:dem":1232,
    "gn:feature_class":"P",
    "gn:feature_code":"PPL",
    "gn:name":"Xiangwan",
    "gn:population":0,
    "gn:timezone":"Asia/Shanghai",
    "iso:country":"CN",
    "name:zho_x_preferred":[
        "\u9999\u6e7e"
    ],
    "wof:name":"Xiangwan",
    "wof:placetype":"locality"
},
  "geometry": {"coordinates":[109.18709,31.46685],"type":"Point"}
}