{
  "type": "Feature",
  "properties": {
    "gn:admin1_code":"18.0",
    "gn:asciiname":"Heichongwan",
    "gn:country_code":"CN",
    "gn:dem":539,
    "gn:feature_class":"P",
    "gn:feature_code":"PPL",
    "gn:name":"Heichongwan",
    "gn:population":0,
    "gn:timezone":"Asia/Shanghai",
    "iso:country":"CN",
    "name:zho_x_preferred":[
        "\u9ed1\u51b2\u6e7e"
    ],
    "wof:name":"Heichongwan",
    "wof:placetype":"locality"
},
  "geometry": {"coordinates":[109.02,28.0573],"type":"Point"}
}