{
  "type": "Feature",
  "properties": {
    "gn:admin1_code":"12.0",
    "gn:asciiname":"Dajinjiawan",
    "gn:country_code":"CN",
    "gn:dem":130,
    "gn:feature_class":"P",
    "gn:feature_code":"PPL",
    "gn:name":"Dajinjiawan",
    "gn:population":0,
    "gn:timezone":"Asia/Shanghai",
    "iso:country":"CN",
    "name:zho_x_preferred":[
        "\u5927\u91d1\u5bb6\u6e7e"
    ],
    "wof:name":"Dajinjiawan",
    "wof:placetype":"locality"
},
  "geometry": {"coordinates":[113.57878999999998,31.70796],"type":"Point"}
}