{
  "type": "Feature",
  "properties": {
    "gn:admin1_code":"26.0",
    "gn:asciiname":"Maopingjie",
    "gn:country_code":"CN",
    "gn:dem":461,
    "gn:feature_class":"P",
    "gn:feature_code":"PPL",
    "gn:name":"Maopingjie",
    "gn:population":0,
    "gn:timezone":"Asia/Shanghai",
    "iso:country":"CN",
    "name:zho_x_preferred":[
        "\u8305\u576a\u8857"
    ],
    "wof:name":"Maopingjie",
    "wof:placetype":"locality"
},
  "geometry": {"coordinates":[109.12636999999999,33.14996],"type":"Point"}
}