{
  "type": "Feature",
  "properties": {
    "gn:admin1_code":"24.0",
    "gn:asciiname":"Liuhe",
    "gn:country_code":"CN",
    "gn:dem":1320,
    "gn:feature_class":"P",
    "gn:feature_code":"PPL",
    "gn:name":"Liuhe",
    "gn:population":0,
    "gn:timezone":"Asia/Shanghai",
    "iso:country":"CN",
    "name:zho_x_preferred":[
        "\u67f3\u6cb3"
    ],
    "wof:name":"Liuhe",
    "wof:placetype":"locality"
},
  "geometry": {"coordinates":[111.61790999999999,39.13143],"type":"Point"}
}