{
  "type": "Feature",
  "properties": {
    "gn:admin1_code":"15.0",
    "gn:asciiname":"Heicitai",
    "gn:country_code":"CN",
    "gn:dem":1909,
    "gn:feature_class":"P",
    "gn:feature_code":"PPL",
    "gn:name":"Heicitai",
    "gn:population":0,
    "gn:timezone":"Asia/Shanghai",
    "iso:country":"CN",
    "name:und_x_variant":[
        "\u9ed1\u523a\u53f0"
    ],
    "wof:name":"Heicitai",
    "wof:placetype":"locality"
},
  "geometry": {"coordinates":[106.46448999999998,36.59351],"type":"Point"}
}