{
  "type": "Feature",
  "properties": {
    "gn:admin1_code":"26.0",
    "gn:asciiname":"Haoba",
    "gn:country_code":"CN",
    "gn:dem":1717,
    "gn:feature_class":"P",
    "gn:feature_code":"PPL",
    "gn:name":"Haoba",
    "gn:population":0,
    "gn:timezone":"Asia/Shanghai",
    "iso:country":"CN",
    "name:und_x_variant":[
        "\u84bf\u575d"
    ],
    "wof:name":"Haoba",
    "wof:placetype":"locality"
},
  "geometry": {"coordinates":[106.52261,32.74189000000001],"type":"Point"}
}