{
  "type": "Feature",
  "properties": {
    "gn:admin1_code":"15.0",
    "gn:asciiname":"Taoshuliang",
    "gn:country_code":"CN",
    "gn:dem":1422,
    "gn:feature_class":"P",
    "gn:feature_code":"PPL",
    "gn:name":"Taoshuliang",
    "gn:population":0,
    "gn:timezone":"Asia/Shanghai",
    "iso:country":"CN",
    "name:und_x_variant":[
        "\u6843\u6811\u6881"
    ],
    "wof:name":"Taoshuliang",
    "wof:placetype":"locality"
},
  "geometry": {"coordinates":[107.2719,36.00795],"type":"Point"}
}