{
  "type": "Feature",
  "properties": {
    "gn:admin1_code":"18",
    "gn:asciiname":"Mengzheng",
    "gn:country_code":"CN",
    "gn:dem":1297,
    "gn:feature_class":"P",
    "gn:feature_code":"PPL",
    "gn:name":"Mengzheng",
    "gn:population":0,
    "gn:timezone":"Asia/Shanghai",
    "iso:country":"CN",
    "name:zho_x_preferred":[
        "\u731b\u6b63"
    ],
    "wof:name":"Mengzheng",
    "wof:placetype":"locality"
},
  "geometry": {"coordinates":[105.908,25.9522],"type":"Point"}
}