{
  "type": "Feature",
  "properties": {
    "gn:admin1_code":"14.0",
    "gn:asciiname":"Lari'a",
    "gn:country_code":"CN",
    "gn:dem":3814,
    "gn:feature_class":"P",
    "gn:feature_code":"PPL",
    "gn:name":"Lari\u2019a",
    "gn:population":0,
    "gn:timezone":"Asia/Urumqi",
    "iso:country":"CN",
    "name:und_x_variant":[
        "Lari\u2019a"
    ],
    "name:zho_x_preferred":[
        "\u62c9\u65e5\u963f"
    ],
    "wof:name":"Lari'a",
    "wof:placetype":"locality"
},
  "geometry": {"coordinates":[95.66377,31.36998],"type":"Point"}
}