{
  "type": "Feature",
  "properties": {
    "gn:admin1_code":"7.0",
    "gn:asciiname":"Shantou",
    "gn:country_code":"CN",
    "gn:dem":689,
    "gn:feature_class":"P",
    "gn:feature_code":"PPL",
    "gn:name":"Shantou",
    "gn:population":0,
    "gn:timezone":"Asia/Shanghai",
    "iso:country":"CN",
    "name:zho_x_preferred":[
        "\u5c71\u5934"
    ],
    "wof:name":"Shantou",
    "wof:placetype":"locality"
},
  "geometry": {"coordinates":[116.07999,25.43541],"type":"Point"}
}