{
  "type": "Feature",
  "properties": {
    "gn:admin1_code":"20.0",
    "gn:asciiname":"Hengyilong",
    "gn:country_code":"CN",
    "gn:dem":1517,
    "gn:feature_class":"P",
    "gn:feature_code":"PPL",
    "gn:name":"Hengyilong",
    "gn:population":0,
    "gn:timezone":"Asia/Shanghai",
    "iso:country":"CN",
    "name:und_x_variant":[
        "\u6052\u4e49\u9686"
    ],
    "wof:name":"Hengyilong",
    "wof:placetype":"locality"
},
  "geometry": {"coordinates":[113.32382,41.20555],"type":"Point"}
}