{
  "type": "Feature",
  "properties": {
    "gn:admin1_code":"19.0",
    "gn:asciiname":"Beixiaozhuangzi",
    "gn:country_code":"CN",
    "gn:dem":1,
    "gn:feature_class":"P",
    "gn:feature_code":"PPL",
    "gn:name":"Beixiaozhuangzi",
    "gn:population":0,
    "gn:timezone":"Asia/Shanghai",
    "iso:country":"CN",
    "name:zho_x_preferred":[
        "\u5317\u5c0f\u5e84\u5b50"
    ],
    "wof:name":"Beixiaozhuangzi",
    "wof:placetype":"locality"
},
  "geometry": {"coordinates":[122.12999000000001,40.75819],"type":"Point"}
}