{
  "type": "Feature",
  "properties": {
    "gn:admin1_code":"25",
    "gn:asciiname":"Qianyutun",
    "gn:country_code":"CN",
    "gn:dem":22,
    "gn:feature_class":"P",
    "gn:feature_code":"PPL",
    "gn:name":"Qianyutun",
    "gn:population":0,
    "gn:timezone":"Asia/Shanghai",
    "iso:country":"CN",
    "name:zho_x_preferred":[
        "\u94b1\u7389\u5c6f"
    ],
    "wof:name":"Qianyutun",
    "wof:placetype":"locality"
},
  "geometry": {"coordinates":[116.807,36.9006],"type":"Point"}
}