{
  "type": "Feature",
  "properties": {
    "gn:admin1_code":"7",
    "gn:asciiname":"Qiujiashanxia",
    "gn:country_code":"CN",
    "gn:dem":804,
    "gn:feature_class":"P",
    "gn:feature_code":"PPL",
    "gn:name":"Qiujiashanxia",
    "gn:population":0,
    "gn:timezone":"Asia/Shanghai",
    "iso:country":"CN",
    "name:und_x_variant":[
        "Qiujiashan",
        "Qiujiashanxiacun",
        "Qiujiashanxia",
        "\u90b1\u5bb6\u5c71\u4e0b"
    ],
    "wof:name":"Qiujiashanxia",
    "wof:placetype":"locality"
},
  "geometry": {"coordinates":[117.08163,25.60048],"type":"Point"}
}