{
  "type": "Feature",
  "properties": {
    "gn:admin1_code":"18",
    "gn:asciiname":"Hanjiaba",
    "gn:country_code":"CN",
    "gn:dem":1703,
    "gn:feature_class":"P",
    "gn:feature_code":"PPL",
    "gn:name":"Hanjiaba",
    "gn:population":0,
    "gn:timezone":"Asia/Shanghai",
    "iso:country":"CN",
    "name:zho_x_preferred":[
        "\u97e9\u5bb6\u575d"
    ],
    "wof:name":"Hanjiaba",
    "wof:placetype":"locality"
},
  "geometry": {"coordinates":[105.506,27.0226],"type":"Point"}
}