{
  "type": "Feature",
  "properties": {
    "gn:admin1_code":"4.0",
    "gn:asciiname":"Dongchang",
    "gn:country_code":"CN",
    "gn:dem":4,
    "gn:feature_class":"P",
    "gn:feature_code":"PPL",
    "gn:name":"Dongchang",
    "gn:population":0,
    "gn:timezone":"Asia/Shanghai",
    "iso:country":"CN",
    "name:und_x_variant":[
        "\u4e1c\u660c"
    ],
    "name:zho_x_preferred":[
        "\u4e1c\u660c"
    ],
    "wof:name":"Dongchang",
    "wof:placetype":"locality"
},
  "geometry": {"coordinates":[120.65362,31.44264],"type":"Point"}
}