{
  "type": "Feature",
  "properties": {
    "gn:admin1_code":"11",
    "gn:asciiname":"Dujiangpo",
    "gn:country_code":"CN",
    "gn:dem":141,
    "gn:feature_class":"P",
    "gn:feature_code":"PPL",
    "gn:name":"Dujiangpo",
    "gn:population":0,
    "gn:timezone":"Asia/Shanghai",
    "iso:country":"CN",
    "wof:name":"Dujiangpo",
    "wof:placetype":"locality"
},
  "geometry": {"coordinates":[110.28722,27.5875],"type":"Point"}
}