{
  "type": "Feature",
  "properties": {
    "gn:admin1_code":"32.0",
    "gn:asciiname":"Erlong",
    "gn:country_code":"CN",
    "gn:dem":711,
    "gn:feature_class":"P",
    "gn:feature_code":"PPL",
    "gn:name":"Erlong",
    "gn:population":0,
    "gn:timezone":"Asia/Shanghai",
    "iso:country":"CN",
    "name:zho_x_preferred":[
        "\u4e8c\u9f99"
    ],
    "wof:name":"Erlong",
    "wof:placetype":"locality"
},
  "geometry": {"coordinates":[107.483,31.4269],"type":"Point"}
}