{
  "type": "Feature",
  "properties": {
    "gn:admin1_code":"29.0",
    "gn:asciiname":"Xiaochangkua",
    "gn:country_code":"CN",
    "gn:dem":1848,
    "gn:feature_class":"P",
    "gn:feature_code":"PPL",
    "gn:name":"Xiaochangkua",
    "gn:population":0,
    "gn:timezone":"Asia/Shanghai",
    "iso:country":"CN",
    "name:zho_x_preferred":[
        "\u5c0f\u957f\u8de8"
    ],
    "wof:name":"Xiaochangkua",
    "wof:placetype":"locality"
},
  "geometry": {"coordinates":[103.298,24.9696],"type":"Point"}
}