{
  "type": "Feature",
  "properties": {
    "gn:admin1_code":"31",
    "gn:asciiname":"Xianlai",
    "gn:country_code":"CN",
    "gn:dem":33,
    "gn:feature_class":"P",
    "gn:feature_code":"PPL",
    "gn:name":"Xianlai",
    "gn:population":0,
    "gn:timezone":"Asia/Shanghai",
    "iso:country":"CN",
    "name:und_x_variant":[
        "\u54b8\u6765"
    ],
    "wof:name":"Xianlai",
    "wof:placetype":"locality"
},
  "geometry": {"coordinates":[110.59255,19.80842],"type":"Point"}
}