{
  "type": "Feature",
  "properties": {
    "gn:admin1_code":"11.0",
    "gn:asciiname":"Nanyue",
    "gn:country_code":"CN",
    "gn:dem":68,
    "gn:feature_class":"P",
    "gn:feature_code":"PPL",
    "gn:name":"Nanyue",
    "gn:population":0,
    "gn:timezone":"Asia/Shanghai",
    "iso:country":"CN",
    "name:als_x_preferred":[
        "Nan-Yue"
    ],
    "name:ara_x_preferred":[
        "\u0646\u0627\u0646\u064a\u0627\u0648"
    ],
    "name:ast_x_preferred":[
        "Nanyue"
    ],
    "name:cat_x_preferred":[
        "Nanyue"
    ],
    "name:cdo_x_preferred":[
        "N\u00e0ng-u\u014fk-gu\u00f3k"
    ],
    "name:ces_x_preferred":[
        "Nan-j\u00fce"
    ],
    "name:dan_x_preferred":[
        "Nanyue"
    ],
    "name:deu_x_preferred":[
        "Nan-Yue"
    ],
    "name:epo_x_preferred":[
        "Nanjueo"
    ],
    "name:eus_x_preferred":[
        "Nanyue"
    ],
    "name:fin_x_preferred":[
        "Nam Vi\u1ec7t"
    ],
    "name:fra_x_preferred":[
        "Nanyue"
    ],
    "name:hak_x_preferred":[
        "N\u00e0m-ye\u030dt-koet"
    ],
    "name:ind_x_preferred":[
        "Nanyue"
    ],
    "name:ita_x_preferred":[
        "Nanyue"
    ],
    "name:jpn_x_preferred":[
        "\u5357\u8d8a\u56fd"
    ],
    "name:nor_x_preferred":[
        "Nanyue"
    ],
    "name:pol_x_preferred":[
        "Nanyue"
    ],
    "name:por_x_preferred":[
        "Nanyue"
    ],
    "name:rus_x_preferred":[
        "\u041d\u0430\u043c\u0432\u044c\u0435\u0442"
    ],
    "name:sco_x_preferred":[
        "Nanyue"
    ],
    "name:spa_x_preferred":[
        "Nanyue"
    ],
    "name:swe_x_preferred":[
        "Nanyue"
    ],
    "name:tha_x_preferred":[
        "\u0e2b\u0e19\u0e32\u0e19\u0e40\u0e22\u0e3a\u0e27\u0e48"
    ],
    "name:ukr_x_preferred":[
        "\u041d\u0430\u043c\u0432'\u0454\u0442"
    ],
    "name:vie_x_preferred":[
        "Nam Vi\u1ec7t"
    ],
    "name:wuu_x_preferred":[
        "\u5357\u8d8a\u56fd"
    ],
    "name:zha_x_preferred":[
        "Namzyied"
    ],
    "name:zho_x_preferred":[
        "\u5357\u5cb3"
    ],
    "name:zho_x_variant":[
        "\u5357\u8d8a\u56fd"
    ],
    "wof:name":"Nanyue",
    "wof:placetype":"locality"
},
  "geometry": {"coordinates":[112.88258999999999,26.70741],"type":"Point"}
}