{
  "type": "Feature",
  "properties": {
    "gn:admin1_code":"19.0",
    "gn:asciiname":"Bujia Fenfang",
    "gn:country_code":"CN",
    "gn:dem":207,
    "gn:feature_class":"P",
    "gn:feature_code":"PPL",
    "gn:name":"Bujia Fenfang",
    "gn:population":0,
    "gn:timezone":"Asia/Shanghai",
    "iso:country":"CN",
    "name:und_x_variant":[
        "\u535c\u5bb6\u7c89\u623f"
    ],
    "name:zho_x_preferred":[
        "\u535c\u5bb6\u7c89\u623f"
    ],
    "wof:name":"Bujia Fenfang",
    "wof:placetype":"locality"
},
  "geometry": {"coordinates":[123.58802,40.63631],"type":"Point"}
}