{
  "type": "Feature",
  "properties": {
    "gn:admin1_code":"1.0",
    "gn:asciiname":"Daqincun",
    "gn:country_code":"CN",
    "gn:dem":27,
    "gn:feature_class":"P",
    "gn:feature_code":"PPL",
    "gn:name":"Daqincun",
    "gn:population":0,
    "gn:timezone":"Asia/Shanghai",
    "iso:country":"CN",
    "name:und_x_variant":[
        "Daqin"
    ],
    "name:zho_x_preferred":[
        "\u5927\u79e6\u6751"
    ],
    "wof:name":"Daqincun",
    "wof:placetype":"locality"
},
  "geometry": {"coordinates":[117.21128,33.76627],"type":"Point"}
}