{
  "type": "Feature",
  "properties": {
    "gn:admin1_code":"4.0",
    "gn:asciiname":"Goubangcun",
    "gn:country_code":"CN",
    "gn:dem":2,
    "gn:feature_class":"P",
    "gn:feature_code":"PPL",
    "gn:name":"Goubangcun",
    "gn:population":0,
    "gn:timezone":"Asia/Shanghai",
    "iso:country":"CN",
    "name:zho_x_preferred":[
        "\u6c9f\u90a6\u6751"
    ],
    "wof:name":"Goubangcun",
    "wof:placetype":"locality"
},
  "geometry": {"coordinates":[120.36651999999999,33.80908],"type":"Point"}
}