{
  "type": "Feature",
  "properties": {
    "gn:admin1_code":"7.0",
    "gn:asciiname":"Liujia",
    "gn:country_code":"CN",
    "gn:dem":241,
    "gn:feature_class":"P",
    "gn:feature_code":"PPL",
    "gn:name":"Liujia",
    "gn:population":0,
    "gn:timezone":"Asia/Shanghai",
    "iso:country":"CN",
    "name:ceb_x_preferred":[
        "Liujia"
    ],
    "name:deu_x_preferred":[
        "Liujia"
    ],
    "name:swe_x_preferred":[
        "Liujia"
    ],
    "name:zho_x_preferred":[
        "\u516d\u7532"
    ],
    "wof:name":"Liujia",
    "wof:placetype":"locality"
},
  "geometry": {"coordinates":[116.35933,25.02124],"type":"Point"}
}