{
  "type": "Feature",
  "properties": {
    "gn:admin1_code":"9.0",
    "gn:asciiname":"Tangshangcun",
    "gn:country_code":"CN",
    "gn:dem":1042,
    "gn:feature_class":"P",
    "gn:feature_code":"PPL",
    "gn:name":"Tangshangcun",
    "gn:population":0,
    "gn:timezone":"Asia/Shanghai",
    "iso:country":"CN",
    "name:zho_x_preferred":[
        "\u5802\u4e0a\u6751"
    ],
    "wof:name":"Tangshangcun",
    "wof:placetype":"locality"
},
  "geometry": {"coordinates":[110.58208,34.3396],"type":"Point"}
}