{
  "type": "Feature",
  "properties": {
    "gn:admin1_code":"26.0",
    "gn:asciiname":"Sandiancun",
    "gn:country_code":"CN",
    "gn:dem":546,
    "gn:feature_class":"P",
    "gn:feature_code":"PPL",
    "gn:name":"Sandiancun",
    "gn:population":0,
    "gn:timezone":"Asia/Shanghai",
    "iso:country":"CN",
    "name:zho_x_preferred":[
        "\u4e09\u5e97\u6751"
    ],
    "wof:name":"Sandiancun",
    "wof:placetype":"locality"
},
  "geometry": {"coordinates":[109.0129,34.76494],"type":"Point"}
}