{
  "type": "Feature",
  "properties": {
    "gn:admin1_code":"19",
    "gn:asciiname":"Shui-ch'u-liu-ch'uan",
    "gn:country_code":"CN",
    "gn:dem":405,
    "gn:feature_class":"P",
    "gn:feature_code":"PPL",
    "gn:name":"Shui-ch\u2019\u00fc-liu-ch\u2019uan",
    "gn:population":0,
    "gn:timezone":"Asia/Shanghai",
    "iso:country":"CN",
    "wof:name":"Shui-ch'u-liu-ch'uan",
    "wof:placetype":"locality"
},
  "geometry": {"coordinates":[125.20528,42.16389],"type":"Point"}
}