{
  "type": "Feature",
  "properties": {
    "gn:admin1_code":"7.0",
    "gn:asciiname":"Qiling",
    "gn:country_code":"CN",
    "gn:dem":309,
    "gn:feature_class":"P",
    "gn:feature_code":"PPL",
    "gn:name":"Qiling",
    "gn:population":0,
    "gn:timezone":"Asia/Shanghai",
    "iso:country":"CN",
    "name:zho_x_preferred":[
        "\u5c90\u5cad"
    ],
    "name:zho_x_variant":[
        "\u5c90\u5cad\u9547"
    ],
    "wof:name":"Qiling",
    "wof:placetype":"locality"
},
  "geometry": {"coordinates":[116.36405999999999,25.66985],"type":"Point"}
}