{
  "type": "Feature",
  "properties": {
    "gn:admin1_code":"32.0",
    "gn:asciiname":"Qinggangba",
    "gn:country_code":"CN",
    "gn:dem":662,
    "gn:feature_class":"P",
    "gn:feature_code":"PPL",
    "gn:name":"Qinggangba",
    "gn:population":0,
    "gn:timezone":"Asia/Shanghai",
    "iso:country":"CN",
    "name:zho_x_preferred":[
        "\u9752\u5c97\u575d"
    ],
    "wof:name":"Qinggangba",
    "wof:placetype":"locality"
},
  "geometry": {"coordinates":[104.21525,28.69884],"type":"Point"}
}