{
  "type": "Feature",
  "properties": {
    "gn:admin1_code":"26.0",
    "gn:asciiname":"Qulicun",
    "gn:country_code":"CN",
    "gn:dem":934,
    "gn:feature_class":"P",
    "gn:feature_code":"PPL",
    "gn:name":"Qulicun",
    "gn:population":0,
    "gn:timezone":"Asia/Shanghai",
    "iso:country":"CN",
    "name:zho_x_preferred":[
        "\u66f2\u91cc\u6751"
    ],
    "wof:name":"Qulicun",
    "wof:placetype":"locality"
},
  "geometry": {"coordinates":[110.13531,36.014],"type":"Point"}
}