{
  "type": "Feature",
  "properties": {
    "gn:admin1_code":"1.0",
    "gn:asciiname":"Shangwangcun",
    "gn:country_code":"CN",
    "gn:dem":214,
    "gn:feature_class":"P",
    "gn:feature_code":"PPL",
    "gn:name":"Shangwangcun",
    "gn:population":0,
    "gn:timezone":"Asia/Shanghai",
    "iso:country":"CN",
    "name:zho_x_preferred":[
        "\u4e0a\u6c6a\u6751"
    ],
    "wof:name":"Shangwangcun",
    "wof:placetype":"locality"
},
  "geometry": {"coordinates":[118.27585999999999,29.94903],"type":"Point"}
}