{
  "type": "Feature",
  "properties": {
    "gn:admin1_code":"18.0",
    "gn:asciiname":"Tongniu",
    "gn:country_code":"CN",
    "gn:dem":1012,
    "gn:feature_class":"P",
    "gn:feature_code":"PPL",
    "gn:name":"Tongniu",
    "gn:population":0,
    "gn:timezone":"Asia/Shanghai",
    "iso:country":"CN",
    "name:zho_x_preferred":[
        "\u540c\u725b"
    ],
    "wof:name":"Tongniu",
    "wof:placetype":"locality"
},
  "geometry": {"coordinates":[108.074,26.6205],"type":"Point"}
}