{
  "type": "Feature",
  "properties": {
    "gn:admin1_code":"1.0",
    "gn:asciiname":"Cangwucun",
    "gn:country_code":"CN",
    "gn:dem":26,
    "gn:feature_class":"P",
    "gn:feature_code":"PPL",
    "gn:name":"Cangwucun",
    "gn:population":0,
    "gn:timezone":"Asia/Shanghai",
    "iso:country":"CN",
    "name:zho_x_preferred":[
        "\u4ed3\u5c4b\u6751"
    ],
    "wof:name":"Cangwucun",
    "wof:placetype":"locality"
},
  "geometry": {"coordinates":[117.44112,33.75104],"type":"Point"}
}