{
  "type": "Feature",
  "properties": {
    "gn:admin1_code":"29.0",
    "gn:asciiname":"Yanzitou",
    "gn:country_code":"CN",
    "gn:dem":1558,
    "gn:feature_class":"P",
    "gn:feature_code":"PPL",
    "gn:name":"Yanzitou",
    "gn:population":0,
    "gn:timezone":"Asia/Shanghai",
    "iso:country":"CN",
    "name:zho_x_preferred":[
        "\u5ca9\u5b50\u5934"
    ],
    "wof:name":"Yanzitou",
    "wof:placetype":"locality"
},
  "geometry": {"coordinates":[98.962,23.9859],"type":"Point"}
}