{
  "type": "Feature",
  "properties": {
    "gn:admin1_code":"8.0",
    "gn:asciiname":"Beishihe",
    "gn:country_code":"CN",
    "gn:dem":493,
    "gn:feature_class":"P",
    "gn:feature_code":"PPL",
    "gn:name":"Beishihe",
    "gn:population":0,
    "gn:timezone":"Asia/Shanghai",
    "iso:country":"CN",
    "name:und_x_variant":[
        "\u5317\u5e08\u6cb3"
    ],
    "wof:name":"Beishihe",
    "wof:placetype":"locality"
},
  "geometry": {"coordinates":[126.34591,49.88748],"type":"Point"}
}