{
  "type": "Feature",
  "properties": {
    "gn:admin1_code":"2.0",
    "gn:asciiname":"Xiangjiachang",
    "gn:country_code":"CN",
    "gn:dem":177,
    "gn:feature_class":"P",
    "gn:feature_code":"PPL",
    "gn:name":"Xiangjiachang",
    "gn:population":0,
    "gn:timezone":"Asia/Shanghai",
    "iso:country":"CN",
    "name:zho_x_preferred":[
        "\u9879\u5bb6\u573a"
    ],
    "wof:name":"Xiangjiachang",
    "wof:placetype":"locality"
},
  "geometry": {"coordinates":[120.63042,28.70348],"type":"Point"}
}