{
  "type": "Feature",
  "properties": {
    "gn:admin1_code":"25.0",
    "gn:asciiname":"Shandongtou",
    "gn:cc2":"CN",
    "gn:country_code":"CN",
    "gn:dem":54,
    "gn:feature_class":"P",
    "gn:feature_code":"PPL",
    "gn:name":"Shandongtou",
    "gn:population":0,
    "gn:timezone":"Asia/Shanghai",
    "iso:country":"CN",
    "name:zho_x_preferred":[
        "\u5c71\u4e1c\u5934"
    ],
    "wof:name":"Shandongtou",
    "wof:placetype":"locality"
},
  "geometry": {"coordinates":[119.55678,35.74155],"type":"Point"}
}