{
  "type": "Feature",
  "properties": {
    "gn:admin1_code":"22",
    "gn:asciiname":"Houzhangcun",
    "gn:country_code":"CN",
    "gn:dem":51,
    "gn:feature_class":"P",
    "gn:feature_code":"PPL",
    "gn:name":"Houzhangcun",
    "gn:population":0,
    "gn:timezone":"Asia/Shanghai",
    "iso:country":"CN",
    "name:zho_x_preferred":[
        "\u540e\u7ae0"
    ],
    "wof:name":"Houzhangcun",
    "wof:placetype":"locality"
},
  "geometry": {"coordinates":[116.17726999999999,40.12651],"type":"Point"}
}