{
  "type": "Feature",
  "properties": {
    "gn:admin1_code":"07",
    "gn:asciiname":"Diao'ao",
    "gn:country_code":"CN",
    "gn:dem":94,
    "gn:feature_class":"P",
    "gn:feature_code":"PPL",
    "gn:name":"Diao\u2019ao",
    "gn:population":0,
    "gn:timezone":"Asia/Shanghai",
    "iso:country":"CN",
    "name:zho_x_preferred":[
        "Diao\u2019ao"
    ],
    "name:zho_x_variant":[
        "\u9493\u6fb3"
    ],
    "wof:name":"Diao'ao",
    "wof:placetype":"locality"
},
  "geometry": {"coordinates":[120.39972,27.15556],"type":"Point"}
}