{
  "type": "Feature",
  "properties": {
    "gn:admin1_code":"29",
    "gn:asciiname":"Wuyue",
    "gn:country_code":"CN",
    "gn:dem":2035,
    "gn:feature_class":"P",
    "gn:feature_code":"PPL",
    "gn:name":"Wuyue",
    "gn:population":0,
    "gn:timezone":"Asia/Shanghai",
    "iso:country":"CN",
    "name:ces_x_preferred":[
        "Wu-j\u00fce"
    ],
    "name:deu_x_preferred":[
        "Wuyue-Reich"
    ],
    "name:fra_x_preferred":[
        "Wuyue"
    ],
    "name:hrv_x_preferred":[
        "Wuyue"
    ],
    "name:nor_x_preferred":[
        "Wuyue"
    ],
    "name:pol_x_preferred":[
        "Wuyue"
    ],
    "name:swe_x_preferred":[
        "Wuyue"
    ],
    "name:ukr_x_preferred":[
        "\u0423\u044e\u0435"
    ],
    "name:vie_x_preferred":[
        "Ng\u00f4 Vi\u1ec7t"
    ],
    "name:wuu_x_preferred":[
        "\u5434\u8d8a\u56fd"
    ],
    "name:zho_x_preferred":[
        "\u4e94\u5cb3"
    ],
    "name:zho_x_variant":[
        "\u5434\u8d8a\u56fd"
    ],
    "wof:name":"Wuyue",
    "wof:placetype":"locality"
},
  "geometry": {"coordinates":[102.31985,24.57267],"type":"Point"}
}