{
  "type": "Feature",
  "properties": {
    "gn:admin1_code":"12.0",
    "gn:asciiname":"Huilongge",
    "gn:country_code":"CN",
    "gn:dem":938,
    "gn:feature_class":"P",
    "gn:feature_code":"PPL",
    "gn:name":"Huilongge",
    "gn:population":0,
    "gn:timezone":"Asia/Shanghai",
    "iso:country":"CN",
    "name:zho_x_preferred":[
        "\u56de\u9f99\u9601"
    ],
    "wof:name":"Huilongge",
    "wof:placetype":"locality"
},
  "geometry": {"coordinates":[110.43818,29.84478],"type":"Point"}
}