{
  "type": "Feature",
  "properties": {
    "gn:admin1_code":"06",
    "gn:asciiname":"Ershilipu",
    "gn:country_code":"CN",
    "gn:dem":2310,
    "gn:feature_class":"P",
    "gn:feature_code":"PPLA4",
    "gn:name":"Ershilipu",
    "gn:population":0,
    "gn:timezone":"Asia/Shanghai",
    "iso:country":"CN",
    "name:und_x_variant":[
        "Erh-shih-li-p\u2019u",
        "Ershilipu",
        "Ershilipu Zhen"
    ],
    "name:zho_x_preferred":[
        "\u4e8c\u5341\u91cc\u94fa"
    ],
    "name:zho_x_variant":[
        "\u4e8c\u5341\u91cc\u94fa\u9547"
    ],
    "wof:name":"Ershilipu",
    "wof:placetype":"locality"
},
  "geometry": {"coordinates":[101.7538,36.70866],"type":"Point"}
}