{
  "type": "Feature",
  "properties": {
    "gn:admin1_code":"8.0",
    "gn:asciiname":"Gongquantun",
    "gn:country_code":"CN",
    "gn:dem":208,
    "gn:feature_class":"P",
    "gn:feature_code":"PPL",
    "gn:name":"Gongquantun",
    "gn:population":0,
    "gn:timezone":"Asia/Shanghai",
    "iso:country":"CN",
    "name:zho_x_preferred":[
        "\u5171\u5168\u5c6f"
    ],
    "wof:name":"Gongquantun",
    "wof:placetype":"locality"
},
  "geometry": {"coordinates":[127.4688,45.67587],"type":"Point"}
}