{
  "type": "Feature",
  "properties": {
    "gn:admin1_code":"30.0",
    "gn:asciiname":"Lanpai",
    "gn:country_code":"CN",
    "gn:dem":29,
    "gn:feature_class":"P",
    "gn:feature_code":"PPL",
    "gn:name":"Lanpai",
    "gn:population":0,
    "gn:timezone":"Asia/Shanghai",
    "iso:country":"CN",
    "name:zho_x_preferred":[
        "\u5c9a\u6d3e"
    ],
    "wof:name":"Lanpai",
    "wof:placetype":"locality"
},
  "geometry": {"coordinates":[114.59229999999999,23.38248],"type":"Point"}
}