{
  "type": "Feature",
  "properties": {
    "gn:admin1_code":"5.0",
    "gn:asciiname":"Houlijiatun",
    "gn:country_code":"CN",
    "gn:dem":265,
    "gn:feature_class":"P",
    "gn:feature_code":"PPL",
    "gn:name":"Houlijiatun",
    "gn:population":0,
    "gn:timezone":"Asia/Shanghai",
    "iso:country":"CN",
    "name:zho_x_preferred":[
        "\u540e\u674e\u5bb6\u5c6f"
    ],
    "wof:name":"Houlijiatun",
    "wof:placetype":"locality"
},
  "geometry": {"coordinates":[124.75897000000001,43.10103],"type":"Point"}
}