{
  "type": "Feature",
  "properties": {
    "gn:admin1_code":"29.0",
    "gn:asciiname":"Zhangfeng",
    "gn:country_code":"CN",
    "gn:dem":936,
    "gn:feature_class":"P",
    "gn:feature_code":"PPLA3",
    "gn:name":"Zhangfeng",
    "gn:population":0,
    "gn:timezone":"Asia/Shanghai",
    "iso:country":"CN",
    "name:und_x_variant":[
        "Chang-feng",
        "Chang-Feng-Cheh",
        "Chang-feng-chieh",
        "Changfengkai",
        "Hsanghawng",
        "Zhangfeng"
    ],
    "name:zho_x_preferred":[
        "Lung-ch\u2019uan"
    ],
    "name:zho_x_variant":[
        "\u7ae0\u51e4"
    ],
    "wof:name":"Zhangfeng",
    "wof:placetype":"locality"
},
  "geometry": {"coordinates":[97.78682999999999,24.22085],"type":"Point"}
}