{
  "type": "Feature",
  "properties": {
    "gn:admin1_code":"7.0",
    "gn:asciiname":"Yongxing",
    "gn:country_code":"CN",
    "gn:dem":843,
    "gn:feature_class":"P",
    "gn:feature_code":"PPL",
    "gn:name":"Yongxing",
    "gn:population":0,
    "gn:timezone":"Asia/Shanghai",
    "iso:country":"CN",
    "name:und_x_variant":[
        "\u6c38\u5174"
    ],
    "wof:name":"Yongxing",
    "wof:placetype":"locality"
},
  "geometry": {"coordinates":[116.46083,26.33849],"type":"Point"}
}