{
  "type": "Feature",
  "properties": {
    "gn:admin1_code":"9",
    "gn:asciiname":"Zhangxiaozhuang",
    "gn:country_code":"CN",
    "gn:dem":43,
    "gn:feature_class":"P",
    "gn:feature_code":"PPL",
    "gn:name":"Zhangxiaozhuang",
    "gn:population":0,
    "gn:timezone":"Asia/Shanghai",
    "iso:country":"CN",
    "name:zho_x_preferred":[
        "\u5f20\u5c0f\u5e84"
    ],
    "wof:name":"Zhangxiaozhuang",
    "wof:placetype":"locality"
},
  "geometry": {"coordinates":[115.03700000000001,33.6917],"type":"Point"}
}