{
  "type": "Feature",
  "properties": {
    "gn:admin1_code":"24.0",
    "gn:asciiname":"Lihan",
    "gn:country_code":"CN",
    "gn:dem":975,
    "gn:feature_class":"P",
    "gn:feature_code":"PPL",
    "gn:name":"Lihan",
    "gn:population":0,
    "gn:timezone":"Asia/Shanghai",
    "iso:country":"CN",
    "name:zho_x_preferred":[
        "\u91cc\u95ec"
    ],
    "wof:name":"Lihan",
    "wof:placetype":"locality"
},
  "geometry": {"coordinates":[112.74027,36.5077],"type":"Point"}
}