{
  "type": "Feature",
  "properties": {
    "gn:admin1_code":"19.0",
    "gn:asciiname":"Jiucaigou",
    "gn:country_code":"CN",
    "gn:dem":312,
    "gn:feature_class":"P",
    "gn:feature_code":"PPL",
    "gn:name":"Jiucaigou",
    "gn:population":0,
    "gn:timezone":"Asia/Shanghai",
    "iso:country":"CN",
    "name:zho_x_preferred":[
        "\u97ed\u83dc\u6c9f"
    ],
    "wof:name":"Jiucaigou",
    "wof:placetype":"locality"
},
  "geometry": {"coordinates":[123.62815999999999,40.71939],"type":"Point"}
}