{
  "type": "Feature",
  "properties": {
    "gn:admin1_code":"29.0",
    "gn:asciiname":"Aju'e",
    "gn:country_code":"CN",
    "gn:dem":2489,
    "gn:feature_class":"P",
    "gn:feature_code":"PPL",
    "gn:name":"Aju\u2019e",
    "gn:population":0,
    "gn:timezone":"Asia/Shanghai",
    "iso:country":"CN",
    "name:und_x_variant":[
        "Aju\u2019e"
    ],
    "name:zho_x_preferred":[
        "\u963f\u82f4\u4fc4"
    ],
    "wof:name":"Aju'e",
    "wof:placetype":"locality"
},
  "geometry": {"coordinates":[101.251,26.0009],"type":"Point"}
}