{
  "type": "Feature",
  "properties": {
    "gn:admin1_code":"30.0",
    "gn:asciiname":"Dongqing",
    "gn:country_code":"CN",
    "gn:dem":317,
    "gn:feature_class":"P",
    "gn:feature_code":"PPL",
    "gn:name":"Dongqing",
    "gn:population":0,
    "gn:timezone":"Asia/Shanghai",
    "iso:country":"CN",
    "name:zho_x_preferred":[
        "Dongqing"
    ],
    "name:zho_x_variant":[
        "\u4e1c\u5e86"
    ],
    "wof:name":"Dongqing",
    "wof:placetype":"locality"
},
  "geometry": {"coordinates":[112.10861,24.38889],"type":"Point"}
}