{
  "type": "Feature",
  "properties": {
    "gn:admin1_code":"4.0",
    "gn:asciiname":"Chenyang",
    "gn:country_code":"CN",
    "gn:dem":3,
    "gn:feature_class":"P",
    "gn:feature_code":"PPL",
    "gn:name":"Chenyang",
    "gn:population":0,
    "gn:timezone":"Asia/Shanghai",
    "iso:country":"CN",
    "name:zho_x_preferred":[
        "\u8fb0\u9633\u9547"
    ],
    "wof:name":"Chenyang",
    "wof:placetype":"locality"
},
  "geometry": {"coordinates":[120.49167,32.93889],"type":"Point"}
}