{
  "type": "Feature",
  "properties": {
    "gn:admin1_code":"2.0",
    "gn:asciiname":"Langjia",
    "gn:country_code":"CN",
    "gn:dem":127,
    "gn:feature_class":"P",
    "gn:feature_code":"PPL",
    "gn:name":"Langjia",
    "gn:population":0,
    "gn:timezone":"Asia/Shanghai",
    "iso:country":"CN",
    "name:und_x_variant":[
        "\u90ce\u5bb6"
    ],
    "wof:name":"Langjia",
    "wof:placetype":"locality"
},
  "geometry": {"coordinates":[119.45885,30.01374],"type":"Point"}
}