{
  "type": "Feature",
  "properties": {
    "gn:admin1_code":"18",
    "gn:asciiname":"Heimaojia",
    "gn:country_code":"CN",
    "gn:dem":2249,
    "gn:feature_class":"P",
    "gn:feature_code":"PPL",
    "gn:name":"Heimaojia",
    "gn:population":0,
    "gn:timezone":"Asia/Shanghai",
    "iso:country":"CN",
    "name:zho_x_preferred":[
        "\u9ed1\u6bdb\u621b"
    ],
    "wof:name":"Heimaojia",
    "wof:placetype":"locality"
},
  "geometry": {"coordinates":[104.04000000000001,27.1832],"type":"Point"}
}