{
  "type": "Feature",
  "properties": {
    "gn:admin1_code":"29.0",
    "gn:asciiname":"Sanlianhe",
    "gn:country_code":"CN",
    "gn:dem":2120,
    "gn:feature_class":"P",
    "gn:feature_code":"PPL",
    "gn:name":"Sanlianhe",
    "gn:population":0,
    "gn:timezone":"Asia/Shanghai",
    "iso:country":"CN",
    "name:zho_x_preferred":[
        "\u4e09\u8054\u5408"
    ],
    "wof:name":"Sanlianhe",
    "wof:placetype":"locality"
},
  "geometry": {"coordinates":[100.003,26.2147],"type":"Point"}
}