{
  "type": "Feature",
  "properties": {
    "gn:admin1_code":"5.0",
    "gn:asciiname":"Liumaohe",
    "gn:country_code":"CN",
    "gn:dem":846,
    "gn:feature_class":"P",
    "gn:feature_code":"PPL",
    "gn:name":"Liumaohe",
    "gn:population":0,
    "gn:timezone":"Asia/Shanghai",
    "iso:country":"CN",
    "name:und_x_variant":[
        "\u67f3\u6bdb\u6cb3"
    ],
    "wof:name":"Liumaohe",
    "wof:placetype":"locality"
},
  "geometry": {"coordinates":[127.44062,41.97435],"type":"Point"}
}