{
  "type": "Feature",
  "properties": {
    "gn:admin1_code":"2.0",
    "gn:asciiname":"Xucun",
    "gn:country_code":"CN",
    "gn:dem":95,
    "gn:feature_class":"P",
    "gn:feature_code":"PPL",
    "gn:name":"Xucun",
    "gn:population":0,
    "gn:timezone":"Asia/Shanghai",
    "iso:country":"CN",
    "name:und_x_variant":[
        "\u8bb8\u6751",
        "Xucun"
    ],
    "wof:name":"Xucun",
    "wof:placetype":"locality"
},
  "geometry": {"coordinates":[119.36235000000001,29.59987000000001],"type":"Point"}
}