{
  "type": "Feature",
  "properties": {
    "gn:admin1_code":"10.0",
    "gn:asciiname":"Zhazigou",
    "gn:country_code":"CN",
    "gn:dem":431,
    "gn:feature_class":"P",
    "gn:feature_code":"PPL",
    "gn:name":"Zhazigou",
    "gn:population":0,
    "gn:timezone":"Asia/Shanghai",
    "iso:country":"CN",
    "name:zho_x_preferred":[
        "\u6805\u5b50\u6c9f"
    ],
    "wof:name":"Zhazigou",
    "wof:placetype":"locality"
},
  "geometry": {"coordinates":[117.30568,40.4723],"type":"Point"}
}