{
  "type": "Feature",
  "properties": {
    "gn:admin1_code":"3.0",
    "gn:asciiname":"Yuxi",
    "gn:country_code":"CN",
    "gn:dem":112,
    "gn:feature_class":"P",
    "gn:feature_code":"PPL",
    "gn:name":"Yuxi",
    "gn:population":0,
    "gn:timezone":"Asia/Shanghai",
    "iso:country":"CN",
    "name:und_x_variant":[
        "\u6e14\u6eaa"
    ],
    "wof:name":"Yuxi",
    "wof:placetype":"locality"
},
  "geometry": {"coordinates":[114.49433000000001,28.24488],"type":"Point"}
}