{
  "type": "Feature",
  "properties": {
    "gn:admin1_code":"14.0",
    "gn:asciiname":"Duiricun",
    "gn:country_code":"CN",
    "gn:dem":4221,
    "gn:feature_class":"P",
    "gn:feature_code":"PPL",
    "gn:name":"Duiricun",
    "gn:population":0,
    "gn:timezone":"Asia/Urumqi",
    "iso:country":"CN",
    "name:zho_x_preferred":[
        "\u5806\u65e5\u6751"
    ],
    "wof:name":"Duiricun",
    "wof:placetype":"locality"
},
  "geometry": {"coordinates":[98.28795,30.54218],"type":"Point"}
}