{
  "type": "Feature",
  "properties": {
    "iso:country":"CN",
    "qs:name":"\u57a6\u5229\u53bf",
    "qs:name_adm0":"\u4e2d\u570b",
    "qs:name_adm1":"\u5c71\u4e1c\u7701",
    "qs:photos":2,
    "qs:photos_1k":1,
    "qs:photos_9k":1,
    "qs:photos_9r":4,
    "qs:photos_all":227,
    "qs:photos_sr":1,
    "qs:placetype":"LocalAdmin",
    "qs:pop_sr":"0",
    "wof:name":"\u57a6\u5229\u53bf",
    "wof:placetype":"localadmin"
},
  "geometry": {"coordinates":[118.51570100000001,37.503189],"type":"Point"}
}