{
  "type": "Feature",
  "properties": {
    "gn:admin1_code":"30.0",
    "gn:asciiname":"Yaolicun",
    "gn:country_code":"CN",
    "gn:dem":8,
    "gn:feature_class":"P",
    "gn:feature_code":"PPL",
    "gn:name":"Yaolicun",
    "gn:population":0,
    "gn:timezone":"Asia/Shanghai",
    "iso:country":"CN",
    "name:zho_x_preferred":[
        "\u5c27\u91cc\u6751"
    ],
    "wof:name":"Yaolicun",
    "wof:placetype":"locality"
},
  "geometry": {"coordinates":[116.75071,23.59243],"type":"Point"}
}