{
  "type": "Feature",
  "properties": {
    "gn:admin1_code":"8.0",
    "gn:asciiname":"Minquancun",
    "gn:country_code":"CN",
    "gn:dem":278,
    "gn:feature_class":"P",
    "gn:feature_code":"PPL",
    "gn:name":"Minquancun",
    "gn:population":0,
    "gn:timezone":"Asia/Shanghai",
    "iso:country":"CN",
    "name:zho_x_preferred":[
        "\u6c11\u6743\u6751"
    ],
    "wof:name":"Minquancun",
    "wof:placetype":"locality"
},
  "geometry": {"coordinates":[126.08247,47.5044],"type":"Point"}
}