{
  "type": "Feature",
  "properties": {
    "gn:admin1_code":"14.0",
    "gn:asciiname":"Dahongsha",
    "gn:country_code":"CN",
    "gn:dem":4070,
    "gn:feature_class":"P",
    "gn:feature_code":"PPL",
    "gn:name":"Dahongsha",
    "gn:population":0,
    "gn:timezone":"Asia/Urumqi",
    "iso:country":"CN",
    "name:zho_x_preferred":[
        "\u8fbe\u7ea2\u6c99"
    ],
    "wof:name":"Dahongsha",
    "wof:placetype":"locality"
},
  "geometry": {"coordinates":[97.07896,31.36827000000001],"type":"Point"}
}