{
  "type": "Feature",
  "properties": {
    "gn:admin1_code":"10",
    "gn:asciiname":"Shuangwang",
    "gn:cc2":"CN",
    "gn:country_code":"CN",
    "gn:dem":83,
    "gn:feature_class":"P",
    "gn:feature_code":"PPL",
    "gn:name":"Shuangwang",
    "gn:population":0,
    "gn:timezone":"Asia/Shanghai",
    "iso:country":"CN",
    "name:und_x_variant":[
        "Shang-wang",
        "Shuang-wang-chen",
        "Shuangwang"
    ],
    "wof:name":"Shuangwang",
    "wof:placetype":"locality"
},
  "geometry": {"coordinates":[119.05556,39.905],"type":"Point"}
}