{
  "type": "Feature",
  "properties": {
    "gn:admin1_code":"12.0",
    "gn:asciiname":"Magangxin",
    "gn:country_code":"CN",
    "gn:dem":24,
    "gn:feature_class":"P",
    "gn:feature_code":"PPL",
    "gn:name":"Magangxin",
    "gn:population":0,
    "gn:timezone":"Asia/Shanghai",
    "iso:country":"CN",
    "name:zho_x_preferred":[
        "\u9a6c\u6e2f\u65b0"
    ],
    "wof:name":"Magangxin",
    "wof:placetype":"locality"
},
  "geometry": {"coordinates":[113.55023,30.67271],"type":"Point"}
}