{
  "type": "Feature",
  "properties": {
    "gn:admin1_code":"5.0",
    "gn:asciiname":"Dianhuaju",
    "gn:country_code":"CN",
    "gn:dem":356,
    "gn:feature_class":"P",
    "gn:feature_code":"PPL",
    "gn:name":"Dianhuaju",
    "gn:population":0,
    "gn:timezone":"Asia/Shanghai",
    "iso:country":"CN",
    "name:und_x_variant":[
        "\u7535\u8bdd\u5c40"
    ],
    "wof:name":"Dianhuaju",
    "wof:placetype":"locality"
},
  "geometry": {"coordinates":[125.79886,41.07079],"type":"Point"}
}