{
  "type": "Feature",
  "properties": {
    "gn:admin1_code":"32.0",
    "gn:asciiname":"Yaoqian",
    "gn:country_code":"CN",
    "gn:dem":339,
    "gn:feature_class":"P",
    "gn:feature_code":"PPL",
    "gn:name":"Yaoqian",
    "gn:population":0,
    "gn:timezone":"Asia/Shanghai",
    "iso:country":"CN",
    "name:zho_x_preferred":[
        "\u6447\u94b1"
    ],
    "wof:name":"Yaoqian",
    "wof:placetype":"locality"
},
  "geometry": {"coordinates":[105.349,29.9974],"type":"Point"}
}