{
  "type": "Feature",
  "properties": {
    "gn:admin1_code":"3",
    "gn:asciiname":"Qiutangbu",
    "gn:country_code":"CN",
    "gn:dem":112,
    "gn:feature_class":"P",
    "gn:feature_code":"PPL",
    "gn:name":"Qiutangbu",
    "gn:population":0,
    "gn:timezone":"Asia/Shanghai",
    "iso:country":"CN",
    "name:zho_x_preferred":[
        "\u4e18\u5858\u57e0"
    ],
    "wof:name":"Qiutangbu",
    "wof:placetype":"locality"
},
  "geometry": {"coordinates":[114.629,26.837],"type":"Point"}
}