{
  "type": "Feature",
  "properties": {
    "gn:admin1_code":"12.0",
    "gn:asciiname":"Liuhuiwan",
    "gn:country_code":"CN",
    "gn:dem":236,
    "gn:feature_class":"P",
    "gn:feature_code":"PPL",
    "gn:name":"Liuhuiwan",
    "gn:population":0,
    "gn:timezone":"Asia/Shanghai",
    "iso:country":"CN",
    "name:zho_x_preferred":[
        "Liuhuiwan"
    ],
    "name:zho_x_variant":[
        "\u67f3\u4f1a\u6e7e"
    ],
    "wof:name":"Liuhuiwan",
    "wof:placetype":"locality"
},
  "geometry": {"coordinates":[111.28440999999999,30.95189],"type":"Point"}
}