{
  "type": "Feature",
  "properties": {
    "gn:admin1_code":"10",
    "gn:asciiname":"Dazhangzi",
    "gn:cc2":"CN",
    "gn:country_code":"CN",
    "gn:dem":778,
    "gn:feature_class":"P",
    "gn:feature_code":"PPL",
    "gn:name":"Dazhangzi",
    "gn:population":0,
    "gn:timezone":"Asia/Shanghai",
    "iso:country":"CN",
    "name:und_x_variant":[
        "Ta-chang-tzu",
        "Dazhangzi"
    ],
    "wof:name":"Dazhangzi",
    "wof:placetype":"locality"
},
  "geometry": {"coordinates":[118.76667,40.86667],"type":"Point"}
}