{
  "type": "Feature",
  "properties": {
    "gn:admin1_code":"25",
    "gn:asciiname":"Dachenjia",
    "gn:country_code":"CN",
    "gn:dem":13,
    "gn:feature_class":"P",
    "gn:feature_code":"PPL",
    "gn:name":"Dachenjia",
    "gn:population":0,
    "gn:timezone":"Asia/Shanghai",
    "iso:country":"CN",
    "name:zho_x_preferred":[
        "\u5927\u9648\u5bb6"
    ],
    "wof:name":"Dachenjia",
    "wof:placetype":"locality"
},
  "geometry": {"coordinates":[117.419,37.5951],"type":"Point"}
}