{
  "type": "Feature",
  "properties": {
    "gn:admin1_code":"7.0",
    "gn:asciiname":"Shuinancun",
    "gn:country_code":"CN",
    "gn:dem":198,
    "gn:feature_class":"P",
    "gn:feature_code":"PPL",
    "gn:name":"Shuinancun",
    "gn:population":0,
    "gn:timezone":"Asia/Shanghai",
    "iso:country":"CN",
    "name:zho_x_preferred":[
        "\u6c34\u5357\u6751"
    ],
    "wof:name":"Shuinancun",
    "wof:placetype":"locality"
},
  "geometry": {"coordinates":[118.77261,27.52042],"type":"Point"}
}