{
  "type": "Feature",
  "properties": {
    "gn:admin1_code":"07",
    "gn:asciiname":"Banling",
    "gn:country_code":"CN",
    "gn:dem":620,
    "gn:feature_class":"P",
    "gn:feature_code":"PPL",
    "gn:name":"Banling",
    "gn:population":0,
    "gn:timezone":"Asia/Shanghai",
    "iso:country":"CN",
    "name:zho_x_preferred":[
        "\u534a\u5cad"
    ],
    "wof:name":"Banling",
    "wof:placetype":"locality"
},
  "geometry": {"coordinates":[118.36244000000001,25.62039],"type":"Point"}
}