{
  "type": "Feature",
  "properties": {
    "gn:admin1_code":"3.0",
    "gn:asciiname":"Zhoushang",
    "gn:country_code":"CN",
    "gn:dem":113,
    "gn:feature_class":"P",
    "gn:feature_code":"PPL",
    "gn:name":"Zhoushang",
    "gn:population":0,
    "gn:timezone":"Asia/Shanghai",
    "iso:country":"CN",
    "name:und_x_variant":[
        "\u6d32\u4e0a"
    ],
    "wof:name":"Zhoushang",
    "wof:placetype":"locality"
},
  "geometry": {"coordinates":[115.50233,27.49173],"type":"Point"}
}