{
  "type": "Feature",
  "properties": {
    "gn:admin1_code":"16.0",
    "gn:asciiname":"Nonglong",
    "gn:country_code":"CN",
    "gn:dem":1361,
    "gn:feature_class":"P",
    "gn:feature_code":"PPL",
    "gn:name":"Nonglong",
    "gn:population":0,
    "gn:timezone":"Asia/Shanghai",
    "iso:country":"CN",
    "name:zho_x_preferred":[
        "\u5f04\u9647"
    ],
    "wof:name":"Nonglong",
    "wof:placetype":"locality"
},
  "geometry": {"coordinates":[104.952,24.6489],"type":"Point"}
}