{
  "type": "Feature",
  "properties": {
    "gn:admin1_code":"24",
    "gn:asciiname":"Zhibeizhuang",
    "gn:country_code":"CN",
    "gn:dem":511,
    "gn:feature_class":"P",
    "gn:feature_code":"PPL",
    "gn:name":"Zhibeizhuang",
    "gn:population":0,
    "gn:timezone":"Asia/Shanghai",
    "iso:country":"CN",
    "name:und_x_variant":[
        "\u652f\u5317\u5e84"
    ],
    "wof:name":"Zhibeizhuang",
    "wof:placetype":"locality"
},
  "geometry": {"coordinates":[111.18194,35.51648],"type":"Point"}
}