{
  "type": "Feature",
  "properties": {
    "gn:admin1_code":"12.0",
    "gn:asciiname":"Chenjia",
    "gn:country_code":"CN",
    "gn:dem":213,
    "gn:feature_class":"P",
    "gn:feature_code":"PPL",
    "gn:name":"Chenjia",
    "gn:population":0,
    "gn:timezone":"Asia/Shanghai",
    "iso:country":"CN",
    "name:zho_x_preferred":[
        "Chenjia"
    ],
    "name:zho_x_variant":[
        "\u9648\u5bb6"
    ],
    "wof:name":"Chenjia",
    "wof:placetype":"locality"
},
  "geometry": {"coordinates":[114.50552,29.52669],"type":"Point"}
}