{
  "type": "Feature",
  "properties": {
    "gn:admin1_code":"15.0",
    "gn:asciiname":"Jiaxizhai",
    "gn:country_code":"CN",
    "gn:dem":2253,
    "gn:feature_class":"P",
    "gn:feature_code":"PPL",
    "gn:name":"Jiaxizhai",
    "gn:population":0,
    "gn:timezone":"Asia/Shanghai",
    "iso:country":"CN",
    "name:zho_x_preferred":[
        "\u8d3e\u897f\u5be8"
    ],
    "wof:name":"Jiaxizhai",
    "wof:placetype":"locality"
},
  "geometry": {"coordinates":[100.88500000000001,38.4688],"type":"Point"}
}