{
  "type": "Feature",
  "properties": {
    "gn:admin1_code":"29.0",
    "gn:asciiname":"Ziche Zhongzhai",
    "gn:country_code":"CN",
    "gn:dem":1552,
    "gn:feature_class":"P",
    "gn:feature_code":"PPL",
    "gn:name":"Ziche Zhongzhai",
    "gn:population":0,
    "gn:timezone":"Asia/Shanghai",
    "iso:country":"CN",
    "name:zho_x_preferred":[
        "\u5b50\u8f66\u4e2d\u5be8"
    ],
    "wof:name":"Ziche Zhongzhai",
    "wof:placetype":"locality"
},
  "geometry": {"coordinates":[103.825,23.5981],"type":"Point"}
}