{
  "type": "Feature",
  "properties": {
    "gn:admin1_code":"14.0",
    "gn:asciiname":"Senggekanbab",
    "gn:cc2":"CN",
    "gn:country_code":"CN",
    "gn:dem":5170,
    "gn:feature_class":"P",
    "gn:feature_code":"PPL",
    "gn:name":"S\u00eangg\u00eakanbab",
    "gn:population":0,
    "gn:timezone":"Asia/Shanghai",
    "iso:country":"CN",
    "name:msa_x_preferred":[
        "S\u00eangg\u00eakanbab"
    ],
    "name:und_x_variant":[
        "Sen-ko-k\u2019a-pa-pu"
    ],
    "wof:name":"Senggekanbab",
    "wof:placetype":"locality"
},
  "geometry": {"coordinates":[81.59999999999999,31.43333],"type":"Point"}
}