{
  "type": "Feature",
  "properties": {
    "gn:admin1_code":"11.0",
    "gn:asciiname":"Fuxing",
    "gn:country_code":"CN",
    "gn:dem":27,
    "gn:feature_class":"P",
    "gn:feature_code":"PPL",
    "gn:name":"Fuxing",
    "gn:population":0,
    "gn:timezone":"Asia/Shanghai",
    "iso:country":"CN",
    "name:zho_x_preferred":[
        "\u590d\u5174"
    ],
    "wof:name":"Fuxing",
    "wof:placetype":"locality"
},
  "geometry": {"coordinates":[112.49588,29.0135],"type":"Point"}
}