{
  "type": "Feature",
  "properties": {
    "gn:admin1_code":"3.0",
    "gn:asciiname":"Yangxuzhuang",
    "gn:country_code":"CN",
    "gn:dem":35,
    "gn:feature_class":"P",
    "gn:feature_code":"PPL",
    "gn:name":"Yangxuzhuang",
    "gn:population":0,
    "gn:timezone":"Asia/Shanghai",
    "iso:country":"CN",
    "name:und_x_variant":[
        "\u6768\u5f90\u5e84"
    ],
    "wof:name":"Yangxuzhuang",
    "wof:placetype":"locality"
},
  "geometry": {"coordinates":[116.13502,28.31683],"type":"Point"}
}