{
  "type": "Feature",
  "properties": {
    "gn:admin1_code":"26.0",
    "gn:asciiname":"Wafanggou",
    "gn:country_code":"CN",
    "gn:dem":1150,
    "gn:feature_class":"P",
    "gn:feature_code":"PPL",
    "gn:name":"Wafanggou",
    "gn:population":0,
    "gn:timezone":"Asia/Shanghai",
    "iso:country":"CN",
    "name:und_x_variant":[
        "\u74e6\u623f\u6c9f"
    ],
    "wof:name":"Wafanggou",
    "wof:placetype":"locality"
},
  "geometry": {"coordinates":[107.28576,33.3828],"type":"Point"}
}