{
  "type": "Feature",
  "properties": {
    "gn:admin1_code":"29.0",
    "gn:asciiname":"Aozizhai",
    "gn:country_code":"CN",
    "gn:dem":1516,
    "gn:feature_class":"P",
    "gn:feature_code":"PPL",
    "gn:name":"Aozizhai",
    "gn:population":0,
    "gn:timezone":"Asia/Shanghai",
    "iso:country":"CN",
    "name:zho_x_preferred":[
        "\u51f9\u5b50\u5be8"
    ],
    "wof:name":"Aozizhai",
    "wof:placetype":"locality"
},
  "geometry": {"coordinates":[99.6969,24.5763],"type":"Point"}
}