{
  "type": "Feature",
  "properties": {
    "gn:admin1_code":"10",
    "gn:asciiname":"Dongxiaozhai",
    "gn:country_code":"CN",
    "gn:dem":63,
    "gn:feature_class":"P",
    "gn:feature_code":"PPL",
    "gn:name":"Dongxiaozhai",
    "gn:population":0,
    "gn:timezone":"Asia/Shanghai",
    "iso:country":"CN",
    "name:zho_x_preferred":[
        "\u4e1c\u5c0f\u5be8"
    ],
    "wof:name":"Dongxiaozhai",
    "wof:placetype":"locality"
},
  "geometry": {"coordinates":[118.06993,40.16722],"type":"Point"}
}