{
  "type": "Feature",
  "properties": {
    "gn:admin1_code":"11.0",
    "gn:asciiname":"Jiufeng",
    "gn:country_code":"CN",
    "gn:dem":94,
    "gn:feature_class":"P",
    "gn:feature_code":"PPL",
    "gn:name":"Jiufeng",
    "gn:population":0,
    "gn:timezone":"Asia/Shanghai",
    "iso:country":"CN",
    "name:zho_x_preferred":[
        "\u4e5d\u4e30"
    ],
    "wof:name":"Jiufeng",
    "wof:placetype":"locality"
},
  "geometry": {"coordinates":[113.3884,28.77093],"type":"Point"}
}