{
  "type": "Feature",
  "properties": {
    "gn:admin1_code":"14.0",
    "gn:asciiname":"Zhinda",
    "gn:country_code":"CN",
    "gn:dem":3327,
    "gn:feature_class":"P",
    "gn:feature_code":"PPL",
    "gn:name":"Zhinda",
    "gn:population":0,
    "gn:timezone":"Asia/Urumqi",
    "iso:country":"CN",
    "name:bod_x_preferred":[
        "Zhinda"
    ],
    "name:zho_x_preferred":[
        "Zhaida"
    ],
    "name:zho_x_variant":[
        "\u5be8\u8fbe"
    ],
    "wof:name":"Zhinda",
    "wof:placetype":"locality"
},
  "geometry": {"coordinates":[97.20399999999999,31.404],"type":"Point"}
}