{
  "type": "Feature",
  "properties": {
    "gn:admin1_code":"9.0",
    "gn:asciiname":"Xicun",
    "gn:country_code":"CN",
    "gn:dem":243,
    "gn:feature_class":"P",
    "gn:feature_code":"PPL",
    "gn:name":"Xicun",
    "gn:population":0,
    "gn:timezone":"Asia/Shanghai",
    "iso:country":"CN",
    "wof:name":"Xicun",
    "wof:placetype":"locality"
},
  "geometry": {"coordinates":[113.27972,35.31889],"type":"Point"}
}