{
  "type": "Feature",
  "properties": {
    "gn:admin1_code":"19.0",
    "gn:asciiname":"Baishilang Goucun",
    "gn:country_code":"CN",
    "gn:dem":240,
    "gn:feature_class":"P",
    "gn:feature_code":"PPL",
    "gn:name":"Baishilang Goucun",
    "gn:population":0,
    "gn:timezone":"Asia/Shanghai",
    "iso:country":"CN",
    "name:zho_x_preferred":[
        "\u767d\u4f8d\u90ce\u6c9f\u6751"
    ],
    "wof:name":"Baishilang Goucun",
    "wof:placetype":"locality"
},
  "geometry": {"coordinates":[120.861,41.4321],"type":"Point"}
}