{
  "type": "Feature",
  "properties": {
    "gn:admin1_code":"29.0",
    "gn:asciiname":"Shanglan",
    "gn:country_code":"CN",
    "gn:dem":2636,
    "gn:feature_class":"P",
    "gn:feature_code":"PPL",
    "gn:name":"Shanglan",
    "gn:population":0,
    "gn:timezone":"Asia/Shanghai",
    "iso:country":"CN",
    "wof:name":"Shanglan",
    "wof:placetype":"locality"
},
  "geometry": {"coordinates":[99.55,26.51667],"type":"Point"}
}