{
  "type": "Feature",
  "properties": {
    "gn:admin1_code":"4.0",
    "gn:asciiname":"Yangchengcun",
    "gn:country_code":"CN",
    "gn:dem":6,
    "gn:feature_class":"P",
    "gn:feature_code":"PPL",
    "gn:name":"Yangchengcun",
    "gn:population":0,
    "gn:timezone":"Asia/Shanghai",
    "iso:country":"CN",
    "name:und_x_variant":[
        "Yang-ch\u2019eng-chen",
        "Yang-ch\u2019eng-ts\u2019un",
        "Yangchengcun",
        "\u9633\u6f84\u6751"
    ],
    "wof:name":"Yangchengcun",
    "wof:placetype":"locality"
},
  "geometry": {"coordinates":[120.77518000000001,31.41553],"type":"Point"}
}