{
  "type": "Feature",
  "properties": {
    "gn:admin1_code":"15.0",
    "gn:asciiname":"Gaojiazhuang",
    "gn:country_code":"CN",
    "gn:dem":1379,
    "gn:feature_class":"P",
    "gn:feature_code":"PPL",
    "gn:name":"Gaojiazhuang",
    "gn:population":0,
    "gn:timezone":"Asia/Shanghai",
    "iso:country":"CN",
    "name:und_x_variant":[
        "\u9ad8\u5bb6\u5e84"
    ],
    "wof:name":"Gaojiazhuang",
    "wof:placetype":"locality"
},
  "geometry": {"coordinates":[107.974,36.0299],"type":"Point"}
}