{
  "type": "Feature",
  "properties": {
    "gn:admin1_code":"21.0",
    "gn:asciiname":"Yuejin",
    "gn:country_code":"CN",
    "gn:dem":1142,
    "gn:feature_class":"P",
    "gn:feature_code":"PPL",
    "gn:name":"Yuejin",
    "gn:population":0,
    "gn:timezone":"Asia/Shanghai",
    "iso:country":"CN",
    "name:zho_x_preferred":[
        "\u8dc3\u8fdb"
    ],
    "wof:name":"Yuejin",
    "wof:placetype":"locality"
},
  "geometry": {"coordinates":[106.291,37.8815],"type":"Point"}
}