{
  "type": "Feature",
  "properties": {
    "gn:admin1_code":"32.0",
    "gn:asciiname":"Heye",
    "gn:country_code":"CN",
    "gn:dem":263,
    "gn:feature_class":"P",
    "gn:feature_code":"PPL",
    "gn:name":"Heye",
    "gn:population":0,
    "gn:timezone":"Asia/Shanghai",
    "iso:country":"CN",
    "name:ceb_x_preferred":[
        "Heye"
    ],
    "name:deu_x_preferred":[
        "Heye"
    ],
    "name:swe_x_preferred":[
        "Heye"
    ],
    "name:wln_x_preferred":[
        "Heye"
    ],
    "name:zho_x_preferred":[
        "\u8377\u53f6"
    ],
    "wof:name":"Heye",
    "wof:placetype":"locality"
},
  "geometry": {"coordinates":[105.74541000000001,30.42652],"type":"Point"}
}