{
  "type": "Feature",
  "properties": {
    "gn:admin1_code":"26.0",
    "gn:asciiname":"Dagoumen",
    "gn:country_code":"CN",
    "gn:dem":1461,
    "gn:feature_class":"P",
    "gn:feature_code":"PPL",
    "gn:name":"Dagoumen",
    "gn:population":0,
    "gn:timezone":"Asia/Shanghai",
    "iso:country":"CN",
    "name:zho_x_preferred":[
        "\u5927\u6c9f\u95e8"
    ],
    "wof:name":"Dagoumen",
    "wof:placetype":"locality"
},
  "geometry": {"coordinates":[107.41123,37.42779],"type":"Point"}
}