{
  "type": "Feature",
  "properties": {
    "gn:admin1_code":"12.0",
    "gn:asciiname":"Ganxihe",
    "gn:country_code":"CN",
    "gn:dem":708,
    "gn:feature_class":"P",
    "gn:feature_code":"PPL",
    "gn:name":"Ganxihe",
    "gn:population":0,
    "gn:timezone":"Asia/Shanghai",
    "iso:country":"CN",
    "name:zho_x_preferred":[
        "Ganxihe"
    ],
    "name:zho_x_variant":[
        "\u5e72\u6eaa\u6cb3"
    ],
    "wof:name":"Ganxihe",
    "wof:placetype":"locality"
},
  "geometry": {"coordinates":[109.62685999999999,29.97715],"type":"Point"}
}