{
  "type": "Feature",
  "properties": {
    "gn:admin1_code":"29.0",
    "gn:asciiname":"Xiaoyangpengzi",
    "gn:country_code":"CN",
    "gn:dem":2832,
    "gn:feature_class":"P",
    "gn:feature_code":"PPL",
    "gn:name":"Xiaoyangpengzi",
    "gn:population":0,
    "gn:timezone":"Asia/Shanghai",
    "iso:country":"CN",
    "name:zho_x_preferred":[
        "\u5c0f\u7f8a\u68da\u5b50"
    ],
    "wof:name":"Xiaoyangpengzi",
    "wof:placetype":"locality"
},
  "geometry": {"coordinates":[103.009,27.2812],"type":"Point"}
}