{
  "type": "Feature",
  "properties": {
    "gn:admin1_code":"15.0",
    "gn:asciiname":"Goudixia",
    "gn:country_code":"CN",
    "gn:dem":1391,
    "gn:feature_class":"P",
    "gn:feature_code":"PPL",
    "gn:name":"Goudixia",
    "gn:population":0,
    "gn:timezone":"Asia/Shanghai",
    "iso:country":"CN",
    "name:und_x_variant":[
        "\u6c9f\u5e95\u4e0b"
    ],
    "wof:name":"Goudixia",
    "wof:placetype":"locality"
},
  "geometry": {"coordinates":[105.3026,33.0868],"type":"Point"}
}