{
  "type": "Feature",
  "properties": {
    "gn:admin1_code":"14.0",
    "gn:asciiname":"Bore",
    "gn:country_code":"CN",
    "gn:dem":3329,
    "gn:feature_class":"P",
    "gn:feature_code":"PPL",
    "gn:name":"Bore",
    "gn:population":0,
    "gn:timezone":"Asia/Urumqi",
    "iso:country":"CN",
    "name:ceb_x_preferred":[
        "Bore"
    ],
    "name:deu_x_preferred":[
        "Bore"
    ],
    "name:fin_x_preferred":[
        "Bore"
    ],
    "name:fra_x_preferred":[
        "Bore"
    ],
    "name:hye_x_preferred":[
        "\u0532\u0578\u0580\u0565"
    ],
    "name:nld_x_preferred":[
        "Bore"
    ],
    "name:rus_x_preferred":[
        "\u0411\u043e\u0440\u0435"
    ],
    "name:srp_x_preferred":[
        "\u0411\u043e\u0440\u0435"
    ],
    "name:swe_x_preferred":[
        "Bore"
    ],
    "name:ukr_x_preferred":[
        "\u0411\u043e\u0440\u0435"
    ],
    "name:zho_x_preferred":[
        "\u6ce2\u70ed"
    ],
    "wof:name":"Bore",
    "wof:placetype":"locality"
},
  "geometry": {"coordinates":[98.66123,31.34423],"type":"Point"}
}