{
  "type": "Feature",
  "properties": {
    "gn:admin1_code":"14.0",
    "gn:asciiname":"Naqung",
    "gn:country_code":"CN",
    "gn:dem":4554,
    "gn:feature_class":"P",
    "gn:feature_code":"PPL",
    "gn:name":"Naqung",
    "gn:population":0,
    "gn:timezone":"Asia/Urumqi",
    "iso:country":"CN",
    "name:bod_x_preferred":[
        "Naqung"
    ],
    "name:zho_x_preferred":[
        "Niqiong"
    ],
    "name:zho_x_variant":[
        "\u5c3c\u743c",
        "Namaqiong Gongshe",
        "\u90a3\u739b\u743c\u516c\u793e"
    ],
    "wof:name":"Naqung",
    "wof:placetype":"locality"
},
  "geometry": {"coordinates":[91.31246,31.31715],"type":"Point"}
}