{
  "type": "Feature",
  "properties": {
    "gn:admin1_code":"15.0",
    "gn:asciiname":"Sasuoma",
    "gn:country_code":"CN",
    "gn:dem":2637,
    "gn:feature_class":"P",
    "gn:feature_code":"PPL",
    "gn:name":"Sasuoma",
    "gn:population":0,
    "gn:timezone":"Asia/Shanghai",
    "iso:country":"CN",
    "name:und_x_variant":[
        "\u6d12\u7d22\u739b"
    ],
    "wof:name":"Sasuoma",
    "wof:placetype":"locality"
},
  "geometry": {"coordinates":[102.78625,35.21362],"type":"Point"}
}