{
  "type": "Feature",
  "properties": {
    "gn:admin1_code":"18.0",
    "gn:asciiname":"Jichun",
    "gn:country_code":"CN",
    "gn:dem":425,
    "gn:feature_class":"P",
    "gn:feature_code":"PPL",
    "gn:name":"Jichun",
    "gn:population":0,
    "gn:timezone":"Asia/Shanghai",
    "iso:country":"CN",
    "name:zho_x_preferred":[
        "\u5df1\u7eaf"
    ],
    "wof:name":"Jichun",
    "wof:placetype":"locality"
},
  "geometry": {"coordinates":[108.873,25.9892],"type":"Point"}
}