{
  "type": "Feature",
  "properties": {
    "gn:admin1_code":"25.0",
    "gn:asciiname":"Shipengyanjiacun",
    "gn:country_code":"CN",
    "gn:dem":68,
    "gn:feature_class":"P",
    "gn:feature_code":"PPL",
    "gn:name":"Shipengyanjiacun",
    "gn:population":0,
    "gn:timezone":"Asia/Shanghai",
    "iso:country":"CN",
    "name:zho_x_preferred":[
        "\u77f3\u787c\u95eb\u5bb6\u6751"
    ],
    "wof:name":"Shipengyanjiacun",
    "wof:placetype":"locality"
},
  "geometry": {"coordinates":[122.41368,37.20899],"type":"Point"}
}