{
  "type": "Feature",
  "properties": {
    "gn:admin1_code":"8.0",
    "gn:asciiname":"Aiguocun",
    "gn:country_code":"CN",
    "gn:dem":148,
    "gn:feature_class":"P",
    "gn:feature_code":"PPL",
    "gn:name":"Aiguocun",
    "gn:population":0,
    "gn:timezone":"Asia/Shanghai",
    "iso:country":"CN",
    "name:zho_x_preferred":[
        "\u7231\u56fd\u6751"
    ],
    "wof:name":"Aiguocun",
    "wof:placetype":"locality"
},
  "geometry": {"coordinates":[126.84057,46.42107],"type":"Point"}
}