{
  "type": "Feature",
  "properties": {
    "gn:admin1_code":"24",
    "gn:asciiname":"Pingdicun",
    "gn:country_code":"CN",
    "gn:dem":833,
    "gn:feature_class":"P",
    "gn:feature_code":"PPL",
    "gn:name":"Pingdicun",
    "gn:population":0,
    "gn:timezone":"Asia/Shanghai",
    "iso:country":"CN",
    "name:und_x_variant":[
        "P\u2019ing-ti",
        "Pingdi",
        "Pingdicun"
    ],
    "name:zho_x_preferred":[
        "\u576a\u5e95\u6751"
    ],
    "wof:name":"Pingdicun",
    "wof:placetype":"locality"
},
  "geometry": {"coordinates":[110.79194,37.13088],"type":"Point"}
}