{
  "type": "Feature",
  "properties": {
    "gn:admin1_code":"25",
    "gn:asciiname":"Xiucheng",
    "gn:country_code":"CN",
    "gn:dem":50,
    "gn:feature_class":"P",
    "gn:feature_code":"PPL",
    "gn:name":"Xiucheng",
    "gn:population":0,
    "gn:timezone":"Asia/Shanghai",
    "iso:country":"CN",
    "name:zho_x_preferred":[
        "\u4f11\u57ce"
    ],
    "wof:name":"Xiucheng",
    "wof:placetype":"locality"
},
  "geometry": {"coordinates":[117.01300000000001,35.0991],"type":"Point"}
}