{
  "type": "Feature",
  "properties": {
    "gn:admin1_code":"19.0",
    "gn:asciiname":"Hanjiawazi",
    "gn:country_code":"CN",
    "gn:dem":110,
    "gn:feature_class":"P",
    "gn:feature_code":"PPL",
    "gn:name":"Hanjiawazi",
    "gn:population":0,
    "gn:timezone":"Asia/Shanghai",
    "iso:country":"CN",
    "name:zho_x_preferred":[
        "\u97e9\u5bb6\u6d3c\u5b50"
    ],
    "wof:name":"Hanjiawazi",
    "wof:placetype":"locality"
},
  "geometry": {"coordinates":[123.87,43.1767],"type":"Point"}
}