{
  "type": "Feature",
  "properties": {
    "gn:admin1_code":"19.0",
    "gn:asciiname":"Huangjia Wopu",
    "gn:country_code":"CN",
    "gn:dem":14,
    "gn:feature_class":"P",
    "gn:feature_code":"PPL",
    "gn:name":"Huangjia Wopu",
    "gn:population":0,
    "gn:timezone":"Asia/Shanghai",
    "iso:country":"CN",
    "name:und_x_variant":[
        "\u9ec4\u5bb6\u7a9d\u94fa"
    ],
    "name:zho_x_preferred":[
        "\u9ec4\u5bb6\u7a9d\u94fa"
    ],
    "wof:name":"Huangjia Wopu",
    "wof:placetype":"locality"
},
  "geometry": {"coordinates":[122.584,41.5144],"type":"Point"}
}