{
  "type": "Feature",
  "properties": {
    "gn:admin1_code":"13",
    "gn:asciiname":"Jiaotanchang Caidi",
    "gn:country_code":"CN",
    "gn:dem":436,
    "gn:feature_class":"P",
    "gn:feature_code":"PPL",
    "gn:name":"Jiaotanchang Caidi",
    "gn:population":0,
    "gn:timezone":"Asia/Urumqi",
    "iso:country":"CN",
    "name:zho_x_preferred":[
        "\u7126\u78b3\u5382\u83dc\u5730"
    ],
    "wof:name":"Jiaotanchang Caidi",
    "wof:placetype":"locality"
},
  "geometry": {"coordinates":[87.49699,44.43013],"type":"Point"}
}