{
  "type": "Feature",
  "properties": {
    "gn:admin1_code":"21.0",
    "gn:asciiname":"Tangjiazhuang",
    "gn:country_code":"CN",
    "gn:dem":1093,
    "gn:feature_class":"P",
    "gn:feature_code":"PPL",
    "gn:name":"Tangjiazhuang",
    "gn:population":0,
    "gn:timezone":"Asia/Shanghai",
    "iso:country":"CN",
    "name:zho_x_preferred":[
        "\u5510\u5bb6\u5e84"
    ],
    "wof:name":"Tangjiazhuang",
    "wof:placetype":"locality"
},
  "geometry": {"coordinates":[106.66800000000001,39.0283],"type":"Point"}
}