{
  "type": "Feature",
  "properties": {
    "gn:admin1_code":"25.0",
    "gn:asciiname":"Yuebozhuang",
    "gn:country_code":"CN",
    "gn:dem":47,
    "gn:feature_class":"P",
    "gn:feature_code":"PPL",
    "gn:name":"Yuebozhuang",
    "gn:population":0,
    "gn:timezone":"Asia/Shanghai",
    "iso:country":"CN",
    "name:zho_x_preferred":[
        "\u5cb3\u6cca\u5e84"
    ],
    "wof:name":"Yuebozhuang",
    "wof:placetype":"locality"
},
  "geometry": {"coordinates":[122.29494,37.10381],"type":"Point"}
}