{
  "type": "Feature",
  "properties": {
    "gn:admin1_code":"21.0",
    "gn:asciiname":"Yaogou Zitang",
    "gn:country_code":"CN",
    "gn:dem":1416,
    "gn:feature_class":"P",
    "gn:feature_code":"PPL",
    "gn:name":"Yaogou Zitang",
    "gn:population":0,
    "gn:timezone":"Asia/Shanghai",
    "iso:country":"CN",
    "name:zho_x_preferred":[
        "\u59da\u6c9f\u5b50\u5858"
    ],
    "wof:name":"Yaogou Zitang",
    "wof:placetype":"locality"
},
  "geometry": {"coordinates":[106.73999999999999,37.3461],"type":"Point"}
}