{
  "type": "Feature",
  "properties": {
    "gn:admin1_code":"30.0",
    "gn:asciiname":"Huijiang",
    "gn:country_code":"CN",
    "gn:dem":-2,
    "gn:feature_class":"P",
    "gn:feature_code":"PPL",
    "gn:name":"Huijiang",
    "gn:population":0,
    "gn:timezone":"Asia/Shanghai",
    "iso:country":"CN",
    "name:zho_x_preferred":[
        "\u6703\u6c5f"
    ],
    "wof:name":"Huijiang",
    "wof:placetype":"locality"
},
  "geometry": {"coordinates":[113.28910999999999,23.01639],"type":"Point"}
}