{
  "type": "Feature",
  "properties": {
    "gn:admin1_code":"26.0",
    "gn:asciiname":"Baigou",
    "gn:country_code":"CN",
    "gn:dem":565,
    "gn:feature_class":"P",
    "gn:feature_code":"PPL",
    "gn:name":"Baigou",
    "gn:population":0,
    "gn:timezone":"Asia/Shanghai",
    "iso:country":"CN",
    "name:und_x_variant":[
        "\u767d\u6c9f"
    ],
    "wof:name":"Baigou",
    "wof:placetype":"locality"
},
  "geometry": {"coordinates":[109.3113,34.10838],"type":"Point"}
}