{
  "type": "Feature",
  "properties": {
    "gn:admin1_code":"5.0",
    "gn:asciiname":"Cuyucun",
    "gn:country_code":"CN",
    "gn:dem":371,
    "gn:feature_class":"P",
    "gn:feature_code":"PPL",
    "gn:name":"Cuyucun",
    "gn:population":0,
    "gn:timezone":"Asia/Shanghai",
    "iso:country":"CN",
    "name:zho_x_preferred":[
        "\u7c97\u6986\u6751"
    ],
    "wof:name":"Cuyucun",
    "wof:placetype":"locality"
},
  "geometry": {"coordinates":[126.0956,43.13123],"type":"Point"}
}