{
  "type": "Feature",
  "properties": {
    "gn:admin1_code":"30.0",
    "gn:asciiname":"Muwei",
    "gn:country_code":"CN",
    "gn:dem":-4,
    "gn:feature_class":"P",
    "gn:feature_code":"PPL",
    "gn:name":"Muwei",
    "gn:population":0,
    "gn:timezone":"Asia/Shanghai",
    "iso:country":"CN",
    "name:zho_x_preferred":[
        "\u6728\u56f4"
    ],
    "wof:name":"Muwei",
    "wof:placetype":"locality"
},
  "geometry": {"coordinates":[113.28849,22.43252],"type":"Point"}
}