{
  "type": "Feature",
  "properties": {
    "gn:admin1_code":"18.0",
    "gn:asciiname":"Lingzhen",
    "gn:country_code":"CN",
    "gn:dem":489,
    "gn:feature_class":"P",
    "gn:feature_code":"PPL",
    "gn:name":"Lingzhen",
    "gn:population":0,
    "gn:timezone":"Asia/Shanghai",
    "iso:country":"CN",
    "name:zho_x_preferred":[
        "\u9886\u771f"
    ],
    "wof:name":"Lingzhen",
    "wof:placetype":"locality"
},
  "geometry": {"coordinates":[108.48099999999999,25.9855],"type":"Point"}
}