{
  "type": "Feature",
  "properties": {
    "gn:admin1_code":"4.0",
    "gn:asciiname":"Xiaoshidai",
    "gn:country_code":"CN",
    "gn:dem":5,
    "gn:feature_class":"P",
    "gn:feature_code":"PPL",
    "gn:name":"Xiaoshidai",
    "gn:population":0,
    "gn:timezone":"Asia/Shanghai",
    "iso:country":"CN",
    "name:zho_x_preferred":[
        "\u5c0f\u5e02\u5788"
    ],
    "wof:name":"Xiaoshidai",
    "wof:placetype":"locality"
},
  "geometry": {"coordinates":[120.20129,32.08022],"type":"Point"}
}