{
  "type": "Feature",
  "properties": {
    "gn:admin1_code":"26.0",
    "gn:asciiname":"Santiaogou",
    "gn:country_code":"CN",
    "gn:dem":1123,
    "gn:feature_class":"P",
    "gn:feature_code":"PPL",
    "gn:name":"Santiaogou",
    "gn:population":0,
    "gn:timezone":"Asia/Shanghai",
    "iso:country":"CN",
    "name:zho_x_preferred":[
        "\u4e09\u6761\u6c9f"
    ],
    "wof:name":"Santiaogou",
    "wof:placetype":"locality"
},
  "geometry": {"coordinates":[110.17033000000001,33.4256],"type":"Point"}
}