{
  "type": "Feature",
  "properties": {
    "gn:admin1_code":"12",
    "gn:asciiname":"Yudian",
    "gn:country_code":"CN",
    "gn:dem":102,
    "gn:feature_class":"P",
    "gn:feature_code":"PPLA4",
    "gn:name":"Yudian",
    "gn:population":0,
    "gn:timezone":"Asia/Shanghai",
    "iso:country":"CN",
    "name:und_x_variant":[
        "Y\u00fc-chia-tien",
        "Yudian",
        "\u4f59\u5e97",
        "Yudian Zhen",
        "\u4f59\u5e97\u9547"
    ],
    "wof:name":"Yudian",
    "wof:placetype":"locality"
},
  "geometry": {"coordinates":[113.6347,31.78364],"type":"Point"}
}