{
  "type": "Feature",
  "properties": {
    "gn:admin1_code":"12.0",
    "gn:asciiname":"Duntouliang",
    "gn:country_code":"CN",
    "gn:dem":53,
    "gn:feature_class":"P",
    "gn:feature_code":"PPL",
    "gn:name":"Duntouliang",
    "gn:population":0,
    "gn:timezone":"Asia/Shanghai",
    "iso:country":"CN",
    "name:zho_x_preferred":[
        "Duntouliang"
    ],
    "name:zho_x_variant":[
        "\u58a9\u5934\u6881"
    ],
    "wof:name":"Duntouliang",
    "wof:placetype":"locality"
},
  "geometry": {"coordinates":[115.12345000000001,29.61685],"type":"Point"}
}