{
  "type": "Feature",
  "properties": {
    "gn:admin1_code":"29.0",
    "gn:asciiname":"Zhuangfang",
    "gn:country_code":"CN",
    "gn:dem":2206,
    "gn:feature_class":"P",
    "gn:feature_code":"PPL",
    "gn:name":"Zhuangfang",
    "gn:population":0,
    "gn:timezone":"Asia/Shanghai",
    "iso:country":"CN",
    "name:zho_x_preferred":[
        "\u5e84\u623f"
    ],
    "wof:name":"Zhuangfang",
    "wof:placetype":"locality"
},
  "geometry": {"coordinates":[100.69799999999999,26.0752],"type":"Point"}
}