{
  "type": "Feature",
  "properties": {
    "gn:admin1_code":"2.0",
    "gn:asciiname":"Jigaoling",
    "gn:country_code":"CN",
    "gn:dem":453,
    "gn:feature_class":"P",
    "gn:feature_code":"PPL",
    "gn:name":"Jigaoling",
    "gn:population":0,
    "gn:timezone":"Asia/Shanghai",
    "iso:country":"CN",
    "name:zho_x_preferred":[
        "\u9965\u9ad8\u5cad"
    ],
    "wof:name":"Jigaoling",
    "wof:placetype":"locality"
},
  "geometry": {"coordinates":[119.65277,29.56915],"type":"Point"}
}