{
  "type": "Feature",
  "properties": {
    "gn:admin1_code":"32.0",
    "gn:asciiname":"Liangfengya",
    "gn:country_code":"CN",
    "gn:dem":318,
    "gn:feature_class":"P",
    "gn:feature_code":"PPL",
    "gn:name":"Liangfengya",
    "gn:population":0,
    "gn:timezone":"Asia/Shanghai",
    "iso:country":"CN",
    "name:zho_x_preferred":[
        "\u51c9\u98ce\u57ad"
    ],
    "wof:name":"Liangfengya",
    "wof:placetype":"locality"
},
  "geometry": {"coordinates":[105.26541,30.54831],"type":"Point"}
}