{
  "type": "Feature",
  "properties": {
    "gn:admin1_code":"30",
    "gn:asciiname":"Nachu",
    "gn:country_code":"CN",
    "gn:dem":36,
    "gn:feature_class":"P",
    "gn:feature_code":"PPL",
    "gn:name":"Nachu",
    "gn:population":0,
    "gn:timezone":"Asia/Urumqi",
    "iso:country":"CN",
    "name:fas_x_preferred":[
        "\u0646\u0627\u0686\u0648"
    ],
    "name:zho_x_preferred":[
        "\u90a3\u695a"
    ],
    "wof:name":"Nachu",
    "wof:placetype":"locality"
},
  "geometry": {"coordinates":[110.44004,20.53168],"type":"Point"}
}