{
  "type": "Feature",
  "properties": {
    "gn:admin1_code":"21.0",
    "gn:asciiname":"Shagou",
    "gn:country_code":"CN",
    "gn:dem":1252,
    "gn:feature_class":"P",
    "gn:feature_code":"PPL",
    "gn:name":"Shagou",
    "gn:population":0,
    "gn:timezone":"Asia/Shanghai",
    "iso:country":"CN",
    "name:zho_x_preferred":[
        "\u6c99\u6c9f"
    ],
    "wof:name":"Shagou",
    "wof:placetype":"locality"
},
  "geometry": {"coordinates":[106.532,38.2296],"type":"Point"}
}