{
  "type": "Feature",
  "properties": {
    "gn:admin1_code":"24.0",
    "gn:asciiname":"Linyixian Huanghe Nongchang",
    "gn:country_code":"CN",
    "gn:dem":376,
    "gn:feature_class":"P",
    "gn:feature_code":"PPLF",
    "gn:name":"Linyixian Huanghe Nongchang",
    "gn:population":0,
    "gn:timezone":"Asia/Shanghai",
    "iso:country":"CN",
    "name:zho_x_preferred":[
        "\u4e34\u7317\u53bf\u9ec4\u6cb3\u519c\u573a"
    ],
    "wof:name":"Linyixian Huanghe Nongchang",
    "wof:placetype":"locality"
},
  "geometry": {"coordinates":[110.41127,35.25271],"type":"Point"}
}