{
  "type": "Feature",
  "properties": {
    "gn:admin1_code":"14.0",
    "gn:asciiname":"Jielang",
    "gn:country_code":"CN",
    "gn:dem":4716,
    "gn:feature_class":"P",
    "gn:feature_code":"PPL",
    "gn:name":"Jielang",
    "gn:population":0,
    "gn:timezone":"Asia/Urumqi",
    "iso:country":"CN",
    "name:zho_x_preferred":[
        "\u8282\u6717"
    ],
    "wof:name":"Jielang",
    "wof:placetype":"locality"
},
  "geometry": {"coordinates":[91.30856,31.39412],"type":"Point"}
}