{
  "type": "Feature",
  "properties": {
    "gn:admin1_code":"32.0",
    "gn:asciiname":"Qilan",
    "gn:country_code":"CN",
    "gn:dem":576,
    "gn:feature_class":"P",
    "gn:feature_code":"PPL",
    "gn:name":"Qilan",
    "gn:population":0,
    "gn:timezone":"Asia/Shanghai",
    "iso:country":"CN",
    "name:ara_x_preferred":[
        "\u0642\u064a\u0644\u0627\u0646"
    ],
    "name:ceb_x_preferred":[
        "Q\u012bl\u0101n"
    ],
    "name:fas_x_preferred":[
        "\u0642\u06cc\u0644\u0627\u0646"
    ],
    "name:swe_x_preferred":[
        "Q\u012bl\u0101n"
    ],
    "name:zho_x_preferred":[
        "\u9a91\u5170"
    ],
    "wof:name":"Qilan",
    "wof:placetype":"locality"
},
  "geometry": {"coordinates":[104.735,29.7117],"type":"Point"}
}