{
  "type": "Feature",
  "properties": {
    "gn:admin1_code":"16.0",
    "gn:asciiname":"Jiutiantang",
    "gn:country_code":"CN",
    "gn:dem":91,
    "gn:feature_class":"P",
    "gn:feature_code":"PPL",
    "gn:name":"Jiutiantang",
    "gn:population":0,
    "gn:timezone":"Asia/Shanghai",
    "iso:country":"CN",
    "name:zho_x_preferred":[
        "\u65e7\u5929\u5802"
    ],
    "wof:name":"Jiutiantang",
    "wof:placetype":"locality"
},
  "geometry": {"coordinates":[108.711,22.8216],"type":"Point"}
}