{
  "type": "Feature",
  "properties": {
    "gn:admin1_code":"8.0",
    "gn:asciiname":"Daxingcun",
    "gn:country_code":"CN",
    "gn:dem":138,
    "gn:feature_class":"P",
    "gn:feature_code":"PPL",
    "gn:name":"Daxingcun",
    "gn:population":0,
    "gn:timezone":"Asia/Shanghai",
    "iso:country":"CN",
    "name:zho_x_preferred":[
        "\u5927\u5174\u6751"
    ],
    "wof:name":"Daxingcun",
    "wof:placetype":"locality"
},
  "geometry": {"coordinates":[127.87582999999999,45.80616],"type":"Point"}
}