{
  "type": "Feature",
  "properties": {
    "gn:admin1_code":"2.0",
    "gn:asciiname":"Banluqi",
    "gn:country_code":"CN",
    "gn:dem":8,
    "gn:feature_class":"P",
    "gn:feature_code":"PPL",
    "gn:name":"Banluqi",
    "gn:population":0,
    "gn:timezone":"Asia/Shanghai",
    "iso:country":"CN",
    "name:zho_x_preferred":[
        "\u534a\u8def\u9f50"
    ],
    "wof:name":"Banluqi",
    "wof:placetype":"locality"
},
  "geometry": {"coordinates":[120.58862999999999,29.93821],"type":"Point"}
}