{
  "type": "Feature",
  "properties": {
    "gn:admin1_code":"1.0",
    "gn:asciiname":"Jiepaishicun",
    "gn:country_code":"CN",
    "gn:dem":81,
    "gn:feature_class":"P",
    "gn:feature_code":"PPL",
    "gn:name":"Jiepaishicun",
    "gn:population":0,
    "gn:timezone":"Asia/Shanghai",
    "iso:country":"CN",
    "name:und_x_variant":[
        "Jiepaishi"
    ],
    "name:zho_x_preferred":[
        "\u754c\u724c\u77f3\u6751"
    ],
    "wof:name":"Jiepaishicun",
    "wof:placetype":"locality"
},
  "geometry": {"coordinates":[116.27858000000001,31.6841],"type":"Point"}
}