{
  "type": "Feature",
  "properties": {
    "gn:admin1_code":"19.0",
    "gn:asciiname":"Xiaoxigou",
    "gn:country_code":"CN",
    "gn:dem":125,
    "gn:feature_class":"P",
    "gn:feature_code":"PPL",
    "gn:name":"Xiaoxigou",
    "gn:population":0,
    "gn:timezone":"Asia/Shanghai",
    "iso:country":"CN",
    "name:zho_x_preferred":[
        "\u5c0f\u897f\u6c9f"
    ],
    "wof:name":"Xiaoxigou",
    "wof:placetype":"locality"
},
  "geometry": {"coordinates":[120.03400000000001,40.6297],"type":"Point"}
}