{
  "type": "Feature",
  "properties": {
    "gn:admin1_code":"4.0",
    "gn:asciiname":"Xiaying",
    "gn:country_code":"CN",
    "gn:dem":38,
    "gn:feature_class":"P",
    "gn:feature_code":"PPL",
    "gn:name":"Xiaying",
    "gn:population":0,
    "gn:timezone":"Asia/Shanghai",
    "iso:country":"CN",
    "name:zho_x_preferred":[
        "\u4e0b\u90e2"
    ],
    "wof:name":"Xiaying",
    "wof:placetype":"locality"
},
  "geometry": {"coordinates":[118.68300000000001,32.7606],"type":"Point"}
}