{
  "type": "Feature",
  "properties": {
    "gn:admin1_code":"2.0",
    "gn:asciiname":"Yao'ao",
    "gn:country_code":"CN",
    "gn:dem":169,
    "gn:feature_class":"P",
    "gn:feature_code":"PPL",
    "gn:name":"Yao\u2019ao",
    "gn:population":0,
    "gn:timezone":"Asia/Shanghai",
    "iso:country":"CN",
    "name:zho_x_preferred":[
        "\u59da\u5c99"
    ],
    "name:zho_x_variant":[
        "Yao\u2019ao"
    ],
    "wof:name":"Yao'ao",
    "wof:placetype":"locality"
},
  "geometry": {"coordinates":[120.83528,29.72236],"type":"Point"}
}