{
  "type": "Feature",
  "properties": {
    "gn:admin1_code":"10",
    "gn:asciiname":"Sidaoying",
    "gn:country_code":"CN",
    "gn:dem":1391,
    "gn:feature_class":"P",
    "gn:feature_code":"PPL",
    "gn:name":"Sidaoying",
    "gn:population":0,
    "gn:timezone":"Asia/Shanghai",
    "iso:country":"CN",
    "name:zho_x_preferred":[
        "\u56db\u9053\u8425"
    ],
    "wof:name":"Sidaoying",
    "wof:placetype":"locality"
},
  "geometry": {"coordinates":[115.38663,41.64316],"type":"Point"}
}