{
  "type": "Feature",
  "properties": {
    "gn:admin1_code":"18",
    "gn:asciiname":"Sibu",
    "gn:country_code":"CN",
    "gn:dem":2355,
    "gn:feature_class":"P",
    "gn:feature_code":"PPL",
    "gn:name":"Sibu",
    "gn:population":0,
    "gn:timezone":"Asia/Shanghai",
    "iso:country":"CN",
    "name:zho_x_preferred":[
        "\u56db\u5821"
    ],
    "wof:name":"Sibu",
    "wof:placetype":"locality"
},
  "geometry": {"coordinates":[104.417,26.9934],"type":"Point"}
}