{
  "type": "Feature",
  "properties": {
    "gn:admin1_code":"15.0",
    "gn:asciiname":"Haxigou",
    "gn:country_code":"CN",
    "gn:dem":1950,
    "gn:feature_class":"P",
    "gn:feature_code":"PPL",
    "gn:name":"Haxigou",
    "gn:population":0,
    "gn:timezone":"Asia/Shanghai",
    "iso:country":"CN",
    "name:und_x_variant":[
        "\u54c8\u897f\u6c9f"
    ],
    "name:zho_x_preferred":[
        "\u54c8\u897f\u6c9f"
    ],
    "wof:name":"Haxigou",
    "wof:placetype":"locality"
},
  "geometry": {"coordinates":[104.37282999999999,33.24951],"type":"Point"}
}