{
  "type": "Feature",
  "properties": {
    "gn:admin1_code":"11.0",
    "gn:asciiname":"Chunxinwan",
    "gn:country_code":"CN",
    "gn:dem":104,
    "gn:feature_class":"P",
    "gn:feature_code":"PPL",
    "gn:name":"Chunxinwan",
    "gn:population":0,
    "gn:timezone":"Asia/Shanghai",
    "iso:country":"CN",
    "name:zho_x_preferred":[
        "\u6625\u65b0\u4e07"
    ],
    "wof:name":"Chunxinwan",
    "wof:placetype":"locality"
},
  "geometry": {"coordinates":[113.33638999999999,26.88622],"type":"Point"}
}