{
  "type": "Feature",
  "properties": {
    "gn:admin1_code":"25.0",
    "gn:asciiname":"Xilujiakuang",
    "gn:country_code":"CN",
    "gn:dem":113,
    "gn:feature_class":"P",
    "gn:feature_code":"PPL",
    "gn:name":"Xilujiakuang",
    "gn:population":0,
    "gn:timezone":"Asia/Shanghai",
    "iso:country":"CN",
    "name:zho_x_preferred":[
        "\u897f\u9c81\u5bb6\u593c"
    ],
    "wof:name":"Xilujiakuang",
    "wof:placetype":"locality"
},
  "geometry": {"coordinates":[121.11183,37.1001],"type":"Point"}
}