{
  "type": "Feature",
  "properties": {
    "gn:admin1_code":"8.0",
    "gn:asciiname":"Xizhongshanbu",
    "gn:country_code":"CN",
    "gn:dem":201,
    "gn:feature_class":"P",
    "gn:feature_code":"PPL",
    "gn:name":"Xizhongshanbu",
    "gn:population":0,
    "gn:timezone":"Asia/Shanghai",
    "iso:country":"CN",
    "name:zho_x_preferred":[
        "\u897f\u4e2d\u5c71\u5821"
    ],
    "wof:name":"Xizhongshanbu",
    "wof:placetype":"locality"
},
  "geometry": {"coordinates":[124.62092,48.57525],"type":"Point"}
}