{
  "type": "Feature",
  "properties": {
    "gn:admin1_code":"4.0",
    "gn:asciiname":"Nankangyi",
    "gn:country_code":"CN",
    "gn:dem":43,
    "gn:feature_class":"P",
    "gn:feature_code":"PPL",
    "gn:name":"Nankangyi",
    "gn:population":0,
    "gn:timezone":"Asia/Shanghai",
    "iso:country":"CN",
    "name:zho_x_preferred":[
        "\u5357\u5eb7\u9091"
    ],
    "wof:name":"Nankangyi",
    "wof:placetype":"locality"
},
  "geometry": {"coordinates":[118.88800000000001,34.974],"type":"Point"}
}