{
  "type": "Feature",
  "properties": {
    "gn:admin1_code":"3.0",
    "gn:asciiname":"Chishuikeng",
    "gn:country_code":"CN",
    "gn:dem":432,
    "gn:feature_class":"P",
    "gn:feature_code":"PPL",
    "gn:name":"Chishuikeng",
    "gn:population":0,
    "gn:timezone":"Asia/Shanghai",
    "iso:country":"CN",
    "name:und_x_variant":[
        "\u8d64\u6c34\u5751"
    ],
    "wof:name":"Chishuikeng",
    "wof:placetype":"locality"
},
  "geometry": {"coordinates":[115.70799,25.16319],"type":"Point"}
}