{
  "type": "Feature",
  "properties": {
    "gn:admin1_code":"24.0",
    "gn:asciiname":"Yangqianhe",
    "gn:country_code":"CN",
    "gn:dem":1347,
    "gn:feature_class":"P",
    "gn:feature_code":"PPLA4",
    "gn:name":"Yangqianhe",
    "gn:population":0,
    "gn:timezone":"Asia/Shanghai",
    "iso:country":"CN",
    "name:und_x_variant":[
        "\u6768\u5343\u6cb3",
        "Yangqianhe Xiang",
        "\u6768\u5343\u6cb3\u4e61"
    ],
    "name:zho_x_preferred":[
        "\u6768\u5343\u6cb3"
    ],
    "wof:name":"Yangqianhe",
    "wof:placetype":"locality"
},
  "geometry": {"coordinates":[112.30501,40.10129000000001],"type":"Point"}
}