{
  "type": "Feature",
  "properties": {
    "gn:admin1_code":"19.0",
    "gn:asciiname":"Xinglong Gouli",
    "gn:country_code":"CN",
    "gn:dem":322,
    "gn:feature_class":"P",
    "gn:feature_code":"PPL",
    "gn:name":"Xinglong Gouli",
    "gn:population":0,
    "gn:timezone":"Asia/Shanghai",
    "iso:country":"CN",
    "name:zho_x_preferred":[
        "\u5174\u9686\u6c9f\u91cc"
    ],
    "wof:name":"Xinglong Gouli",
    "wof:placetype":"locality"
},
  "geometry": {"coordinates":[120.17400000000001,40.7058],"type":"Point"}
}