{
  "type": "Feature",
  "properties": {
    "gn:admin1_code":"10.0",
    "gn:asciiname":"Xicaizhuang",
    "gn:country_code":"CN",
    "gn:dem":81,
    "gn:feature_class":"P",
    "gn:feature_code":"PPL",
    "gn:name":"Xicaizhuang",
    "gn:population":0,
    "gn:timezone":"Asia/Shanghai",
    "iso:country":"CN",
    "name:zho_x_preferred":[
        "\u897f\u8521\u5e84"
    ],
    "wof:name":"Xicaizhuang",
    "wof:placetype":"locality"
},
  "geometry": {"coordinates":[118.92534999999999,40.05532],"type":"Point"}
}