{
  "type": "Feature",
  "properties": {
    "gn:admin1_code":"7",
    "gn:asciiname":"Hecangkeng",
    "gn:country_code":"CN",
    "gn:dem":189,
    "gn:feature_class":"P",
    "gn:feature_code":"PPL",
    "gn:name":"Hecangkeng",
    "gn:population":0,
    "gn:timezone":"Asia/Shanghai",
    "iso:country":"CN",
    "name:zho_x_preferred":[
        "\u79be\u4ed3\u5751"
    ],
    "wof:name":"Hecangkeng",
    "wof:placetype":"locality"
},
  "geometry": {"coordinates":[117.20783,24.71136],"type":"Point"}
}