{
  "type": "Feature",
  "properties": {
    "gn:admin1_code":"16.0",
    "gn:asciiname":"Daweichong",
    "gn:country_code":"CN",
    "gn:dem":68,
    "gn:feature_class":"P",
    "gn:feature_code":"PPL",
    "gn:name":"Daweichong",
    "gn:population":0,
    "gn:timezone":"Asia/Shanghai",
    "iso:country":"CN",
    "name:zho_x_preferred":[
        "\u5927\u754f\u51b2"
    ],
    "wof:name":"Daweichong",
    "wof:placetype":"locality"
},
  "geometry": {"coordinates":[111.613,23.796],"type":"Point"}
}