{
  "type": "Feature",
  "properties": {
    "gn:admin1_code":"02",
    "gn:asciiname":"Lupu",
    "gn:country_code":"CN",
    "gn:dem":12,
    "gn:feature_class":"P",
    "gn:feature_code":"PPLA4",
    "gn:name":"Lupu",
    "gn:population":0,
    "gn:timezone":"Asia/Shanghai",
    "iso:country":"CN",
    "name:und_x_variant":[
        "Lu-ao",
        "Lupu",
        "Lupu Zhen",
        "Jingtou"
    ],
    "name:zho_x_preferred":[
        "\u82a6\u6d66"
    ],
    "name:zho_x_variant":[
        "\u82a6\u6d66\u9547",
        "\u4e95\u5934"
    ],
    "wof:name":"Lupu",
    "wof:placetype":"locality"
},
  "geometry": {"coordinates":[121.23642,28.1921],"type":"Point"}
}