{
  "type": "Feature",
  "properties": {
    "gn:admin1_code":"24.0",
    "gn:asciiname":"Xuegucun",
    "gn:cc2":"CN",
    "gn:country_code":"CN",
    "gn:dem":848,
    "gn:feature_class":"P",
    "gn:feature_code":"PPL",
    "gn:name":"Xuegucun",
    "gn:population":0,
    "gn:timezone":"Asia/Shanghai",
    "iso:country":"CN",
    "name:und_x_variant":[
        "Hsia-hu-ku",
        "Hs\u00fceh-ku",
        "Hsia-hsieh-ku",
        "Hsia-hs\u00fceh-ku",
        "Xuegucun"
    ],
    "wof:name":"Xuegucun",
    "wof:placetype":"locality"
},
  "geometry": {"coordinates":[112.71056000000002,38.80389],"type":"Point"}
}