{
  "type": "Feature",
  "properties": {
    "gn:admin1_code":"9",
    "gn:asciiname":"Daguolou",
    "gn:country_code":"CN",
    "gn:dem":39,
    "gn:feature_class":"P",
    "gn:feature_code":"PPL",
    "gn:name":"Daguolou",
    "gn:population":0,
    "gn:timezone":"Asia/Shanghai",
    "iso:country":"CN",
    "name:zho_x_preferred":[
        "\u5927\u90ed\u697c"
    ],
    "wof:name":"Daguolou",
    "wof:placetype":"locality"
},
  "geometry": {"coordinates":[116.408,33.9413],"type":"Point"}
}