{
  "type": "Feature",
  "properties": {
    "gn:admin1_code":"29.0",
    "gn:asciiname":"Gaipai",
    "gn:country_code":"CN",
    "gn:dem":2081,
    "gn:feature_class":"P",
    "gn:feature_code":"PPL",
    "gn:name":"Gaipai",
    "gn:population":0,
    "gn:timezone":"Asia/Shanghai",
    "iso:country":"CN",
    "name:zho_x_preferred":[
        "\u76d6\u724c"
    ],
    "wof:name":"Gaipai",
    "wof:placetype":"locality"
},
  "geometry": {"coordinates":[104.08799999999999,25.7946],"type":"Point"}
}