{
  "type": "Feature",
  "properties": {
    "gn:admin1_code":"8.0",
    "gn:asciiname":"Ershigongli",
    "gn:country_code":"CN",
    "gn:dem":544,
    "gn:feature_class":"P",
    "gn:feature_code":"PPL",
    "gn:name":"Ershigongli",
    "gn:population":0,
    "gn:timezone":"Asia/Shanghai",
    "iso:country":"CN",
    "name:zho_x_preferred":[
        "\u4e8c\u5341\u516c\u91cc"
    ],
    "wof:name":"Ershigongli",
    "wof:placetype":"locality"
},
  "geometry": {"coordinates":[128.59527,46.86444],"type":"Point"}
}