{
  "type": "Feature",
  "properties": {
    "gn:admin1_code":"19.0",
    "gn:asciiname":"Xiguchengzi",
    "gn:country_code":"CN",
    "gn:dem":74,
    "gn:feature_class":"P",
    "gn:feature_code":"PPL",
    "gn:name":"Xiguchengzi",
    "gn:population":0,
    "gn:timezone":"Asia/Shanghai",
    "iso:country":"CN",
    "name:und_x_variant":[
        "\u897f\u53e4\u57ce\u5b50"
    ],
    "name:zho_x_preferred":[
        "\u897f\u53e4\u57ce\u5b50"
    ],
    "wof:name":"Xiguchengzi",
    "wof:placetype":"locality"
},
  "geometry": {"coordinates":[123.7598,42.54754000000001],"type":"Point"}
}