{
  "type": "Feature",
  "properties": {
    "gn:admin1_code":"16.0",
    "gn:asciiname":"Jiuwuchong",
    "gn:country_code":"CN",
    "gn:dem":163,
    "gn:feature_class":"P",
    "gn:feature_code":"PPL",
    "gn:name":"Jiuwuchong",
    "gn:population":0,
    "gn:timezone":"Asia/Shanghai",
    "iso:country":"CN",
    "name:zho_x_preferred":[
        "\u65e7\u5c4b\u51b2"
    ],
    "wof:name":"Jiuwuchong",
    "wof:placetype":"locality"
},
  "geometry": {"coordinates":[110.861,23.511],"type":"Point"}
}