{
  "type": "Feature",
  "properties": {
    "gn:admin1_code":"21.0",
    "gn:asciiname":"Taogouwan",
    "gn:country_code":"CN",
    "gn:dem":1659,
    "gn:feature_class":"P",
    "gn:feature_code":"PPL",
    "gn:name":"Taogouwan",
    "gn:population":0,
    "gn:timezone":"Asia/Shanghai",
    "iso:country":"CN",
    "name:und_x_variant":[
        "\u6843\u6c9f\u6e7e"
    ],
    "name:zho_x_preferred":[
        "\u6843\u6c9f\u6e7e"
    ],
    "wof:name":"Taogouwan",
    "wof:placetype":"locality"
},
  "geometry": {"coordinates":[106.83299,36.17388],"type":"Point"}
}