{
  "type": "Feature",
  "properties": {
    "gn:admin1_code":"5.0",
    "gn:asciiname":"Tiandeshen",
    "gn:country_code":"CN",
    "gn:dem":212,
    "gn:feature_class":"P",
    "gn:feature_code":"PPL",
    "gn:name":"Tiandeshen",
    "gn:population":0,
    "gn:timezone":"Asia/Shanghai",
    "iso:country":"CN",
    "name:zho_x_preferred":[
        "\u5929\u5fb7\u6df1"
    ],
    "wof:name":"Tiandeshen",
    "wof:placetype":"locality"
},
  "geometry": {"coordinates":[126.87503999999998,44.55248],"type":"Point"}
}