{
  "type": "Feature",
  "properties": {
    "gn:admin1_code":"26",
    "gn:asciiname":"Qinling Jieban",
    "gn:country_code":"CN",
    "gn:dem":465,
    "gn:feature_class":"P",
    "gn:feature_code":"PPLA4",
    "gn:name":"Qinling Jieban",
    "gn:population":0,
    "gn:timezone":"Asia/Shanghai",
    "iso:country":"CN",
    "name:und_x_variant":[
        "\u79e6\u9675\u8857\u529e",
        "Qinling Jieban",
        "Qinling"
    ],
    "name:zho_x_preferred":[
        "\u79e6\u9675\u8857\u529e"
    ],
    "wof:name":"Qinling Jieban",
    "wof:placetype":"locality"
},
  "geometry": {"coordinates":[109.24928,34.38678],"type":"Point"}
}