{
  "type": "Feature",
  "properties": {
    "gn:admin1_code":"19.0",
    "gn:asciiname":"Kaobiantuncun",
    "gn:country_code":"CN",
    "gn:dem":93,
    "gn:feature_class":"P",
    "gn:feature_code":"PPL",
    "gn:name":"Kaobiantuncun",
    "gn:population":0,
    "gn:timezone":"Asia/Shanghai",
    "iso:country":"CN",
    "name:zho_x_preferred":[
        "\u9760\u8fb9\u5c6f\u6751"
    ],
    "wof:name":"Kaobiantuncun",
    "wof:placetype":"locality"
},
  "geometry": {"coordinates":[123.157,42.4303],"type":"Point"}
}