{
  "type": "Feature",
  "properties": {
    "gn:admin1_code":"32.0",
    "gn:asciiname":"Lanmugan",
    "gn:country_code":"CN",
    "gn:dem":3860,
    "gn:feature_class":"P",
    "gn:feature_code":"PPL",
    "gn:name":"Lanmugan",
    "gn:population":0,
    "gn:timezone":"Asia/Shanghai",
    "iso:country":"CN",
    "name:zho_x_preferred":[
        "\u6ee5\u6728\u5e72"
    ],
    "wof:name":"Lanmugan",
    "wof:placetype":"locality"
},
  "geometry": {"coordinates":[102.70099999999999,31.0867],"type":"Point"}
}