{
  "type": "Feature",
  "properties": {
    "gn:admin1_code":"15.0",
    "gn:asciiname":"Zhongquan",
    "gn:country_code":"CN",
    "gn:dem":2369,
    "gn:feature_class":"P",
    "gn:feature_code":"PPL",
    "gn:name":"Zhongquan",
    "gn:population":0,
    "gn:timezone":"Asia/Shanghai",
    "iso:country":"CN",
    "name:zho_x_preferred":[
        "\u4e2d\u5708"
    ],
    "wof:name":"Zhongquan",
    "wof:placetype":"locality"
},
  "geometry": {"coordinates":[104.38500000000001,36.1874],"type":"Point"}
}