{
  "type": "Feature",
  "properties": {
    "gn:admin1_code":"8.0",
    "gn:asciiname":"Fuxingtun",
    "gn:country_code":"CN",
    "gn:dem":171,
    "gn:feature_class":"P",
    "gn:feature_code":"PPL",
    "gn:name":"Fuxingtun",
    "gn:population":0,
    "gn:timezone":"Asia/Shanghai",
    "iso:country":"CN",
    "name:zho_x_preferred":[
        "\u798f\u5174\u5c6f"
    ],
    "wof:name":"Fuxingtun",
    "wof:placetype":"locality"
},
  "geometry": {"coordinates":[128.33096,45.37546],"type":"Point"}
}