{
  "type": "Feature",
  "properties": {
    "gn:admin1_code":"11",
    "gn:asciiname":"Duangangtou",
    "gn:country_code":"CN",
    "gn:dem":33,
    "gn:feature_class":"P",
    "gn:feature_code":"PPL",
    "gn:name":"Duangangtou",
    "gn:population":0,
    "gn:timezone":"Asia/Shanghai",
    "iso:country":"CN",
    "name:und_x_variant":[
        "\u65ad\u6e2f\u5934"
    ],
    "wof:name":"Duangangtou",
    "wof:placetype":"locality"
},
  "geometry": {"coordinates":[111.90653,29.12918],"type":"Point"}
}