{
  "type": "Feature",
  "properties": {
    "gn:country":"CN",
    "gn:fcode":"PPL",
    "gn:pop":89107,
    "iso:country":"CN",
    "name:ceb_x_preferred":[
        "Hede"
    ],
    "name:deu_x_preferred":[
        "Hede"
    ],
    "name:fin_x_preferred":[
        "Hede"
    ],
    "name:nds_x_preferred":[
        "Hede"
    ],
    "name:nld_x_preferred":[
        "Hede"
    ],
    "name:rus_x_preferred":[
        "\u0425\u0435\u0434\u0435"
    ],
    "name:srp_x_preferred":[
        "\u0425\u0435\u0434\u0435"
    ],
    "name:swe_x_preferred":[
        "Hede"
    ],
    "name:unk_x_variant":[
        "Sheyang"
    ],
    "name:zho_x_preferred":[
        "\u5408\u5fb7"
    ],
    "name:zho_x_variant":[
        "\u5c04\u9633"
    ],
    "qs:name":"Hede",
    "qs:name_adm0":"\u4e2d\u570b",
    "qs:name_adm1":"\u6c5f\u82cf\u7701",
    "qs:photos_9k":1,
    "qs:photos_9r":1,
    "qs:photos_all":9,
    "qs:photos_sr":0,
    "qs:placetype":"Town",
    "qs:pop_sr":"8",
    "wd:wordcount":35,
    "wof:name":"Hede",
    "wof:placetype":"locality",
    "wof:population":89107
},
  "geometry": {"coordinates":[120.25167,33.76806],"type":"Point"}
}