{
  "type": "Feature",
  "properties": {
    "gn:admin1_code":"32.0",
    "gn:asciiname":"Luotian",
    "gn:country_code":"CN",
    "gn:dem":409,
    "gn:feature_class":"P",
    "gn:feature_code":"PPL",
    "gn:name":"Luotian",
    "gn:population":0,
    "gn:timezone":"Asia/Shanghai",
    "iso:country":"CN",
    "name:zho_x_preferred":[
        "\u7f57\u7530"
    ],
    "wof:name":"Luotian",
    "wof:placetype":"locality"
},
  "geometry": {"coordinates":[107.032,31.0891],"type":"Point"}
}