{
  "type": "Feature",
  "properties": {
    "gn:admin1_code":"12.0",
    "gn:asciiname":"Guanyanchong",
    "gn:country_code":"CN",
    "gn:dem":63,
    "gn:feature_class":"P",
    "gn:feature_code":"PPL",
    "gn:name":"Guanyanchong",
    "gn:population":0,
    "gn:timezone":"Asia/Shanghai",
    "iso:country":"CN",
    "name:zho_x_preferred":[
        "\u5b98\u5830\u51b2"
    ],
    "wof:name":"Guanyanchong",
    "wof:placetype":"locality"
},
  "geometry": {"coordinates":[112.64397,31.31066],"type":"Point"}
}