{
  "type": "Feature",
  "properties": {
    "gn:admin1_code":"30.0",
    "gn:asciiname":"Gongwu",
    "gn:country_code":"CN",
    "gn:dem":42,
    "gn:feature_class":"P",
    "gn:feature_code":"PPL",
    "gn:name":"Gongwu",
    "gn:population":0,
    "gn:timezone":"Asia/Shanghai",
    "iso:country":"CN",
    "name:zho_x_preferred":[
        "\u529f\u6b66"
    ],
    "wof:name":"Gongwu",
    "wof:placetype":"locality"
},
  "geometry": {"coordinates":[114.10186000000002,23.57873],"type":"Point"}
}