{
  "type": "Feature",
  "properties": {
    "gn:admin1_code":"4.0",
    "gn:asciiname":"Zhoutanqiao",
    "gn:country_code":"CN",
    "gn:dem":5,
    "gn:feature_class":"P",
    "gn:feature_code":"PPL",
    "gn:name":"Zhoutanqiao",
    "gn:population":0,
    "gn:timezone":"Asia/Shanghai",
    "iso:country":"CN",
    "name:und_x_variant":[
        "\u5468\u6f6d\u6865"
    ],
    "name:zho_x_preferred":[
        "\u5468\u6f6d\u6865"
    ],
    "wof:name":"Zhoutanqiao",
    "wof:placetype":"locality"
},
  "geometry": {"coordinates":[120.30242,31.45295],"type":"Point"}
}