{
  "type": "Feature",
  "properties": {
    "gn:admin1_code":"8.0",
    "gn:asciiname":"Shaojia Wopeng",
    "gn:country_code":"CN",
    "gn:dem":145,
    "gn:feature_class":"P",
    "gn:feature_code":"PPL",
    "gn:name":"Shaojia Wopeng",
    "gn:population":0,
    "gn:timezone":"Asia/Shanghai",
    "iso:country":"CN",
    "name:zho_x_preferred":[
        "\u90b5\u5bb6\u7a9d\u68da"
    ],
    "wof:name":"Shaojia Wopeng",
    "wof:placetype":"locality"
},
  "geometry": {"coordinates":[125.96099,45.87254],"type":"Point"}
}