{
  "type": "Feature",
  "properties": {
    "gn:admin1_code":"19.0",
    "gn:asciiname":"Xinsheng Erdadui",
    "gn:country_code":"CN",
    "gn:dem":2,
    "gn:feature_class":"P",
    "gn:feature_code":"PPLF",
    "gn:name":"Xinsheng Erdadui",
    "gn:population":0,
    "gn:timezone":"Asia/Shanghai",
    "iso:country":"CN",
    "name:zho_x_preferred":[
        "\u65b0\u751f\u4e8c\u5927\u961f"
    ],
    "wof:name":"Xinsheng Erdadui",
    "wof:placetype":"locality"
},
  "geometry": {"coordinates":[121.89100000000001,41.15600000000001],"type":"Point"}
}