{
  "type": "Feature",
  "properties": {
    "gn:admin1_code":"9",
    "gn:asciiname":"Liuge",
    "gn:country_code":"CN",
    "gn:dem":44,
    "gn:feature_class":"P",
    "gn:feature_code":"PPL",
    "gn:name":"Liuge",
    "gn:population":0,
    "gn:timezone":"Asia/Shanghai",
    "iso:country":"CN",
    "name:zho_x_preferred":[
        "\u5218\u9601"
    ],
    "wof:name":"Liuge",
    "wof:placetype":"locality"
},
  "geometry": {"coordinates":[115.93600000000001,34.0765],"type":"Point"}
}