{
  "type": "Feature",
  "properties": {
    "gn:admin1_code":"16.0",
    "gn:asciiname":"Tongmi",
    "gn:country_code":"CN",
    "gn:dem":64,
    "gn:feature_class":"P",
    "gn:feature_code":"PPL",
    "gn:name":"Tongmi",
    "gn:population":0,
    "gn:timezone":"Asia/Shanghai",
    "iso:country":"CN",
    "name:zho_x_preferred":[
        "\u540c\u7c73"
    ],
    "wof:name":"Tongmi",
    "wof:placetype":"locality"
},
  "geometry": {"coordinates":[111.11499999999999,23.6124],"type":"Point"}
}