{
  "type": "Feature",
  "properties": {
    "gn:admin1_code":"11.0",
    "gn:asciiname":"Chizhuping",
    "gn:country_code":"CN",
    "gn:dem":145,
    "gn:feature_class":"P",
    "gn:feature_code":"PPL",
    "gn:name":"Chizhuping",
    "gn:population":0,
    "gn:timezone":"Asia/Shanghai",
    "iso:country":"CN",
    "name:zho_x_preferred":[
        "\u8d64\u7af9\u576a"
    ],
    "wof:name":"Chizhuping",
    "wof:placetype":"locality"
},
  "geometry": {"coordinates":[113.3862,26.43811],"type":"Point"}
}