{
  "type": "Feature",
  "properties": {
    "gn:admin1_code":"30.0",
    "gn:asciiname":"Rongli",
    "gn:country_code":"CN",
    "gn:dem":2,
    "gn:feature_class":"P",
    "gn:feature_code":"PPL",
    "gn:name":"Rongli",
    "gn:population":0,
    "gn:timezone":"Asia/Shanghai",
    "iso:country":"CN",
    "name:zho_x_preferred":[
        "\u5bb9\u88e1"
    ],
    "wof:name":"Rongli",
    "wof:placetype":"locality"
},
  "geometry": {"coordinates":[113.3053,22.7682],"type":"Point"}
}