{
  "type": "Feature",
  "properties": {
    "gn:admin1_code":"10.0",
    "gn:asciiname":"Taoli",
    "gn:country_code":"CN",
    "gn:dem":20,
    "gn:feature_class":"P",
    "gn:feature_code":"PPL",
    "gn:name":"Taoli",
    "gn:population":0,
    "gn:timezone":"Asia/Shanghai",
    "iso:country":"CN",
    "name:zho_x_preferred":[
        "\u5957\u91cc"
    ],
    "wof:name":"Taoli",
    "wof:placetype":"locality"
},
  "geometry": {"coordinates":[115.699,38.3402],"type":"Point"}
}