{
  "type": "Feature",
  "properties": {
    "gn:admin1_code":"10",
    "gn:asciiname":"Yaojiaying",
    "gn:country_code":"CN",
    "gn:dem":1455,
    "gn:feature_class":"P",
    "gn:feature_code":"PPL",
    "gn:name":"Yaojiaying",
    "gn:population":0,
    "gn:timezone":"Asia/Shanghai",
    "iso:country":"CN",
    "name:zho_x_preferred":[
        "\u59da\u5bb6\u8425"
    ],
    "wof:name":"Yaojiaying",
    "wof:placetype":"locality"
},
  "geometry": {"coordinates":[114.79445,41.85031],"type":"Point"}
}