{
  "type": "Feature",
  "properties": {
    "gn:admin1_code":"26",
    "gn:asciiname":"Shiwengzi",
    "gn:country_code":"CN",
    "gn:dem":724,
    "gn:feature_class":"P",
    "gn:feature_code":"PPL",
    "gn:name":"Shiwengzi",
    "gn:population":0,
    "gn:timezone":"Asia/Shanghai",
    "iso:country":"CN",
    "wof:name":"Shiwengzi",
    "wof:placetype":"locality"
},
  "geometry": {"coordinates":[109.16,33.56583],"type":"Point"}
}