{
  "type": "Feature",
  "properties": {
    "gn:admin1_code":"20",
    "gn:asciiname":"Erh-kuan-ying-tzu",
    "gn:country_code":"CN",
    "gn:dem":686,
    "gn:feature_class":"P",
    "gn:feature_code":"PPL",
    "gn:name":"Erh-kuan-ying-tzu",
    "gn:population":0,
    "gn:timezone":"Asia/Shanghai",
    "iso:country":"CN",
    "wof:name":"Erh-kuan-ying-tzu",
    "wof:placetype":"locality"
},
  "geometry": {"coordinates":[119.87111000000002,42.11639],"type":"Point"}
}