{
  "type": "Feature",
  "properties": {
    "gn:admin1_code":"20.0",
    "gn:asciiname":"Shiyihao",
    "gn:country_code":"CN",
    "gn:dem":1073,
    "gn:feature_class":"P",
    "gn:feature_code":"PPL",
    "gn:name":"Shiyihao",
    "gn:population":0,
    "gn:timezone":"Asia/Shanghai",
    "iso:country":"CN",
    "name:zho_x_preferred":[
        "\u5341\u4e00\u53f7"
    ],
    "wof:name":"Shiyihao",
    "wof:placetype":"locality"
},
  "geometry": {"coordinates":[100.2424,40.9848],"type":"Point"}
}