{
  "type": "Feature",
  "properties": {
    "gn:admin1_code":"4.0",
    "gn:asciiname":"Yaogangcun",
    "gn:country_code":"CN",
    "gn:dem":3,
    "gn:feature_class":"P",
    "gn:feature_code":"PPL",
    "gn:name":"Yaogangcun",
    "gn:population":0,
    "gn:timezone":"Asia/Shanghai",
    "iso:country":"CN",
    "name:und_x_variant":[
        "Yaogang"
    ],
    "name:zho_x_preferred":[
        "\u8200\u6e2f\u6751"
    ],
    "wof:name":"Yaogangcun",
    "wof:placetype":"locality"
},
  "geometry": {"coordinates":[119.89252,33.91992],"type":"Point"}
}