{
  "type": "Feature",
  "properties": {
    "gn:admin1_code":"18.0",
    "gn:asciiname":"Mawei",
    "gn:country_code":"CN",
    "gn:dem":825,
    "gn:feature_class":"P",
    "gn:feature_code":"PPL",
    "gn:name":"Mawei",
    "gn:population":0,
    "gn:timezone":"Asia/Shanghai",
    "iso:country":"CN",
    "name:zho_x_preferred":[
        "\u9a6c\u5c3e"
    ],
    "wof:name":"Mawei",
    "wof:placetype":"locality"
},
  "geometry": {"coordinates":[107.512,26.19400000000001],"type":"Point"}
}