{
  "type": "Feature",
  "properties": {
    "gn:admin1_code":"14.0",
    "gn:asciiname":"Qiji",
    "gn:country_code":"CN",
    "gn:dem":4341,
    "gn:feature_class":"P",
    "gn:feature_code":"PPL",
    "gn:name":"Qiji",
    "gn:population":0,
    "gn:timezone":"Asia/Urumqi",
    "iso:country":"CN",
    "name:ceb_x_preferred":[
        "Qiji"
    ],
    "name:swe_x_preferred":[
        "Qiji"
    ],
    "name:zho_x_preferred":[
        "\u4e03\u57fa"
    ],
    "wof:name":"Qiji",
    "wof:placetype":"locality"
},
  "geometry": {"coordinates":[97.84285,30.4653],"type":"Point"}
}