{
  "type": "Feature",
  "properties": {
    "gn:admin1_code":"20.0",
    "gn:asciiname":"Baoyuanhao",
    "gn:country_code":"CN",
    "gn:dem":1567,
    "gn:feature_class":"P",
    "gn:feature_code":"PPL",
    "gn:name":"Baoyuanhao",
    "gn:population":0,
    "gn:timezone":"Asia/Shanghai",
    "iso:country":"CN",
    "name:und_x_variant":[
        "\u4fdd\u5143\u58d5"
    ],
    "wof:name":"Baoyuanhao",
    "wof:placetype":"locality"
},
  "geometry": {"coordinates":[110.17809,41.21818],"type":"Point"}
}