{
  "type": "Feature",
  "properties": {
    "gn:admin1_code":"10.0",
    "gn:asciiname":"Dingwang",
    "gn:country_code":"CN",
    "gn:dem":88,
    "gn:feature_class":"P",
    "gn:feature_code":"PPL",
    "gn:name":"Dingwang",
    "gn:population":0,
    "gn:timezone":"Asia/Shanghai",
    "iso:country":"CN",
    "name:und_x_variant":[
        "\u9876\u6c6a"
    ],
    "wof:name":"Dingwang",
    "wof:placetype":"locality"
},
  "geometry": {"coordinates":[114.53994,38.25988],"type":"Point"}
}