{
  "type": "Feature",
  "properties": {
    "gn:admin1_code":"02",
    "gn:asciiname":"Shangtangcun",
    "gn:country_code":"CN",
    "gn:dem":54,
    "gn:feature_class":"P",
    "gn:feature_code":"PPL",
    "gn:name":"Shangtangcun",
    "gn:population":0,
    "gn:timezone":"Asia/Shanghai",
    "iso:country":"CN",
    "name:und_x_variant":[
        "Shangtang"
    ],
    "name:zho_x_preferred":[
        "\u4e0a\u5858\u6751"
    ],
    "wof:name":"Shangtangcun",
    "wof:placetype":"locality"
},
  "geometry": {"coordinates":[121.41992,28.27148],"type":"Point"}
}