{
  "type": "Feature",
  "properties": {
    "gn:admin1_code":"16.0",
    "gn:asciiname":"Sanxu",
    "gn:country_code":"CN",
    "gn:dem":543,
    "gn:feature_class":"P",
    "gn:feature_code":"PPL",
    "gn:name":"Sanxu",
    "gn:population":0,
    "gn:timezone":"Asia/Shanghai",
    "iso:country":"CN",
    "name:zho_x_preferred":[
        "\u4e09\u5729"
    ],
    "wof:name":"Sanxu",
    "wof:placetype":"locality"
},
  "geometry": {"coordinates":[107.721,24.9013],"type":"Point"}
}