{
  "type": "Feature",
  "properties": {
    "gn:admin1_code":"4.0",
    "gn:asciiname":"You'aicun",
    "gn:country_code":"CN",
    "gn:dem":0,
    "gn:feature_class":"P",
    "gn:feature_code":"PPL",
    "gn:name":"You\u2019aicun",
    "gn:population":0,
    "gn:timezone":"Asia/Shanghai",
    "iso:country":"CN",
    "name:und_x_variant":[
        "You\u2019aicun"
    ],
    "name:zho_x_preferred":[
        "\u53cb\u7231\u6751"
    ],
    "wof:name":"You'aicun",
    "wof:placetype":"locality"
},
  "geometry": {"coordinates":[120.22351,33.86029],"type":"Point"}
}