{
  "type": "Feature",
  "properties": {
    "gn:admin1_code":"1.0",
    "gn:asciiname":"Zouqiaocun",
    "gn:country_code":"CN",
    "gn:dem":38,
    "gn:feature_class":"P",
    "gn:feature_code":"PPL",
    "gn:name":"Zouqiaocun",
    "gn:population":0,
    "gn:timezone":"Asia/Shanghai",
    "iso:country":"CN",
    "name:zho_x_preferred":[
        "\u90b9\u6865\u6751"
    ],
    "wof:name":"Zouqiaocun",
    "wof:placetype":"locality"
},
  "geometry": {"coordinates":[115.48053,33.24127],"type":"Point"}
}