{
  "type": "Feature",
  "properties": {
    "gn:admin1_code":"25",
    "gn:asciiname":"Dahuaya",
    "gn:country_code":"CN",
    "gn:dem":57,
    "gn:feature_class":"P",
    "gn:feature_code":"PPL",
    "gn:name":"Dahuaya",
    "gn:population":0,
    "gn:timezone":"Asia/Shanghai",
    "iso:country":"CN",
    "name:und_x_variant":[
        "\u5927\u82b1\u5d16"
    ],
    "wof:name":"Dahuaya",
    "wof:placetype":"locality"
},
  "geometry": {"coordinates":[119.22578,35.43926],"type":"Point"}
}