{
  "type": "Feature",
  "properties": {
    "gn:admin1_code":"4.0",
    "gn:asciiname":"Xiangfeng Wudui",
    "gn:country_code":"CN",
    "gn:dem":4,
    "gn:feature_class":"P",
    "gn:feature_code":"PPLF",
    "gn:name":"Xiangfeng Wudui",
    "gn:population":0,
    "gn:timezone":"Asia/Shanghai",
    "iso:country":"CN",
    "name:zho_x_preferred":[
        "\u7965\u4e30\u4e94\u961f"
    ],
    "wof:name":"Xiangfeng Wudui",
    "wof:placetype":"locality"
},
  "geometry": {"coordinates":[120.554,33.11],"type":"Point"}
}