{
  "type": "Feature",
  "properties": {
    "gn:admin1_code":"26.0",
    "gn:asciiname":"Wangluogou",
    "gn:country_code":"CN",
    "gn:dem":1082,
    "gn:feature_class":"P",
    "gn:feature_code":"PPL",
    "gn:name":"Wangluogou",
    "gn:population":0,
    "gn:timezone":"Asia/Shanghai",
    "iso:country":"CN",
    "name:zho_x_preferred":[
        "\u738b\u6d1b\u6c9f"
    ],
    "wof:name":"Wangluogou",
    "wof:placetype":"locality"
},
  "geometry": {"coordinates":[110.32628,39.12053],"type":"Point"}
}