{
  "type": "Feature",
  "properties": {
    "gn:admin1_code":"25",
    "gn:asciiname":"Houchengwang",
    "gn:country_code":"CN",
    "gn:dem":48,
    "gn:feature_class":"P",
    "gn:feature_code":"PPL",
    "gn:name":"Houchengwang",
    "gn:population":0,
    "gn:timezone":"Asia/Shanghai",
    "iso:country":"CN",
    "name:zho_x_preferred":[
        "\u540e\u5448\u65fa"
    ],
    "wof:name":"Houchengwang",
    "wof:placetype":"locality"
},
  "geometry": {"coordinates":[115.4679,36.02023],"type":"Point"}
}