{
  "type": "Feature",
  "properties": {
    "gn:admin1_code":"14.0",
    "gn:asciiname":"Exueli",
    "gn:country_code":"CN",
    "gn:dem":4248,
    "gn:feature_class":"P",
    "gn:feature_code":"PPL",
    "gn:name":"Exueli",
    "gn:population":0,
    "gn:timezone":"Asia/Urumqi",
    "iso:country":"CN",
    "name:zho_x_preferred":[
        "\u4fc4\u5b66\u91cc"
    ],
    "wof:name":"Exueli",
    "wof:placetype":"locality"
},
  "geometry": {"coordinates":[95.89679,31.02589],"type":"Point"}
}