{
  "type": "Feature",
  "properties": {
    "gn:admin1_code":"16",
    "gn:asciiname":"Dachongtian",
    "gn:country_code":"CN",
    "gn:dem":773,
    "gn:feature_class":"P",
    "gn:feature_code":"PPL",
    "gn:name":"Dachongtian",
    "gn:population":0,
    "gn:timezone":"Asia/Shanghai",
    "iso:country":"CN",
    "name:zho_x_preferred":[
        "\u5927\u51b2\u7530"
    ],
    "wof:name":"Dachongtian",
    "wof:placetype":"locality"
},
  "geometry": {"coordinates":[110.30500000000001,25.9544],"type":"Point"}
}