{
  "type": "Feature",
  "properties": {
    "gn:admin1_code":"15.0",
    "gn:asciiname":"Guanfangping",
    "gn:country_code":"CN",
    "gn:dem":1898,
    "gn:feature_class":"P",
    "gn:feature_code":"PPL",
    "gn:name":"Guanfangping",
    "gn:population":0,
    "gn:timezone":"Asia/Shanghai",
    "iso:country":"CN",
    "name:und_x_variant":[
        "\u5173\u623f\u576a"
    ],
    "wof:name":"Guanfangping",
    "wof:placetype":"locality"
},
  "geometry": {"coordinates":[106.54482,33.57019],"type":"Point"}
}