{
  "type": "Feature",
  "properties": {
    "gn:admin1_code":"03",
    "gn:asciiname":"Neiliang",
    "gn:cc2":"CN",
    "gn:country_code":"CN",
    "gn:dem":430,
    "gn:feature_class":"P",
    "gn:feature_code":"PPL",
    "gn:name":"Neiliang",
    "gn:population":0,
    "gn:timezone":"Asia/Shanghai",
    "iso:country":"CN",
    "name:und_x_variant":[
        "Nei-liang-hs\u00fc",
        "Neiliang"
    ],
    "wof:name":"Neiliang",
    "wof:placetype":"locality"
},
  "geometry": {"coordinates":[114.08333,25.38333],"type":"Point"}
}