{
  "type": "Feature",
  "properties": {
    "gn:admin1_code":"2.0",
    "gn:asciiname":"Tianqingkeng",
    "gn:country_code":"CN",
    "gn:dem":83,
    "gn:feature_class":"P",
    "gn:feature_code":"PPL",
    "gn:name":"Tianqingkeng",
    "gn:population":0,
    "gn:timezone":"Asia/Shanghai",
    "iso:country":"CN",
    "name:zho_x_preferred":[
        "\u5929\u9752\u5751"
    ],
    "wof:name":"Tianqingkeng",
    "wof:placetype":"locality"
},
  "geometry": {"coordinates":[119.90449,29.14387],"type":"Point"}
}