{
  "type": "Feature",
  "properties": {
    "gn:admin1_code":"29",
    "gn:asciiname":"Luzicun",
    "gn:country_code":"CN",
    "gn:dem":1957,
    "gn:feature_class":"P",
    "gn:feature_code":"PPL",
    "gn:name":"Luzicun",
    "gn:population":0,
    "gn:timezone":"Asia/Shanghai",
    "iso:country":"CN",
    "name:zho_x_preferred":[
        "\u9c81\u8d44\u6751"
    ],
    "wof:name":"Luzicun",
    "wof:placetype":"locality"
},
  "geometry": {"coordinates":[102.39861999999999,24.63932],"type":"Point"}
}