{
  "type": "Feature",
  "properties": {
    "gn:admin1_code":"32.0",
    "gn:asciiname":"Guomilan",
    "gn:country_code":"CN",
    "gn:dem":2676,
    "gn:feature_class":"P",
    "gn:feature_code":"PPL",
    "gn:name":"Guomilan",
    "gn:population":0,
    "gn:timezone":"Asia/Shanghai",
    "iso:country":"CN",
    "name:zho_x_preferred":[
        "\u90ed\u7c73\u5170"
    ],
    "wof:name":"Guomilan",
    "wof:placetype":"locality"
},
  "geometry": {"coordinates":[101.254,27.2911],"type":"Point"}
}