{
  "type": "Feature",
  "properties": {
    "gn:admin1_code":"14.0",
    "gn:asciiname":"Kanqianji",
    "gn:country_code":"CN",
    "gn:dem":4287,
    "gn:feature_class":"P",
    "gn:feature_code":"PPL",
    "gn:name":"Kanqianji",
    "gn:population":0,
    "gn:timezone":"Asia/Urumqi",
    "iso:country":"CN",
    "name:zho_x_preferred":[
        "\u574e\u6b20\u53ca"
    ],
    "wof:name":"Kanqianji",
    "wof:placetype":"locality"
},
  "geometry": {"coordinates":[97.29917,31.76262],"type":"Point"}
}