{
  "type": "Feature",
  "properties": {
    "gn:admin1_code":"11.0",
    "gn:asciiname":"Zhoujiaxiang",
    "gn:country_code":"CN",
    "gn:dem":123,
    "gn:feature_class":"P",
    "gn:feature_code":"PPL",
    "gn:name":"Zhoujiaxiang",
    "gn:population":0,
    "gn:timezone":"Asia/Shanghai",
    "iso:country":"CN",
    "name:zho_x_preferred":[
        "\u5468\u5bb6\u5df7"
    ],
    "wof:name":"Zhoujiaxiang",
    "wof:placetype":"locality"
},
  "geometry": {"coordinates":[111.67298,26.63512],"type":"Point"}
}