{
  "type": "Feature",
  "properties": {
    "gn:admin1_code":"4.0",
    "gn:asciiname":"Haihe",
    "gn:country_code":"CN",
    "gn:dem":4,
    "gn:feature_class":"P",
    "gn:feature_code":"PPL",
    "gn:name":"Haihe",
    "gn:population":0,
    "gn:timezone":"Asia/Shanghai",
    "iso:country":"CN",
    "name:zho_x_preferred":[
        "Haihe"
    ],
    "name:zho_x_variant":[
        "\u4ea5\u6cb3"
    ],
    "wof:name":"Haihe",
    "wof:placetype":"locality"
},
  "geometry": {"coordinates":[120.94483,32.27200999999999],"type":"Point"}
}