{
  "type": "Feature",
  "properties": {
    "gn:admin1_code":"30.0",
    "gn:asciiname":"Xiamankeng",
    "gn:country_code":"CN",
    "gn:dem":57,
    "gn:feature_class":"P",
    "gn:feature_code":"PPL",
    "gn:name":"Xiamankeng",
    "gn:population":0,
    "gn:timezone":"Asia/Shanghai",
    "iso:country":"CN",
    "name:und_x_variant":[
        "\u4e0b\u6ee1\u5751"
    ],
    "name:zho_x_preferred":[
        "\u4e0b\u6ee1\u5751"
    ],
    "wof:name":"Xiamankeng",
    "wof:placetype":"locality"
},
  "geometry": {"coordinates":[114.98959000000001,23.89016],"type":"Point"}
}