{
  "type": "Feature",
  "properties": {
    "gn:admin1_code":"5.0",
    "gn:asciiname":"Zhengcha",
    "gn:country_code":"CN",
    "gn:dem":379,
    "gn:feature_class":"P",
    "gn:feature_code":"PPL",
    "gn:name":"Zhengcha",
    "gn:population":0,
    "gn:timezone":"Asia/Shanghai",
    "iso:country":"CN",
    "name:und_x_variant":[
        "\u6b63\u5c94"
    ],
    "wof:name":"Zhengcha",
    "wof:placetype":"locality"
},
  "geometry": {"coordinates":[126.09161,41.18501],"type":"Point"}
}