{
  "type": "Feature",
  "properties": {
    "gn:admin1_code":"14.0",
    "gn:asciiname":"Bocun",
    "gn:country_code":"CN",
    "gn:dem":4452,
    "gn:feature_class":"P",
    "gn:feature_code":"PPL",
    "gn:name":"Bocun",
    "gn:population":0,
    "gn:timezone":"Asia/Urumqi",
    "iso:country":"CN",
    "name:zho_x_preferred":[
        "\u6ce2\u6751"
    ],
    "wof:name":"Bocun",
    "wof:placetype":"locality"
},
  "geometry": {"coordinates":[87.6379,29.8877],"type":"Point"}
}