{
  "type": "Feature",
  "properties": {
    "gn:admin1_code":"19.0",
    "gn:asciiname":"Luoguowa",
    "gn:country_code":"CN",
    "gn:dem":321,
    "gn:feature_class":"P",
    "gn:feature_code":"PPL",
    "gn:name":"Luoguowa",
    "gn:population":0,
    "gn:timezone":"Asia/Shanghai",
    "iso:country":"CN",
    "name:zho_x_preferred":[
        "\u7f57\u9505\u6d3c"
    ],
    "wof:name":"Luoguowa",
    "wof:placetype":"locality"
},
  "geometry": {"coordinates":[121.532,42.2093],"type":"Point"}
}