{
  "type": "Feature",
  "properties": {
    "gn:admin1_code":"24.0",
    "gn:asciiname":"Sanjiaocun",
    "gn:country_code":"CN",
    "gn:dem":397,
    "gn:feature_class":"P",
    "gn:feature_code":"PPL",
    "gn:name":"Sanjiaocun",
    "gn:population":0,
    "gn:timezone":"Asia/Shanghai",
    "iso:country":"CN",
    "name:zho_x_preferred":[
        "\u4e09\u7126\u6751"
    ],
    "wof:name":"Sanjiaocun",
    "wof:placetype":"locality"
},
  "geometry": {"coordinates":[110.38882,34.64019],"type":"Point"}
}