{
  "type": "Feature",
  "properties": {
    "gn:admin1_code":"32.0",
    "gn:asciiname":"Tingchuan",
    "gn:country_code":"CN",
    "gn:dem":846,
    "gn:feature_class":"P",
    "gn:feature_code":"PPL",
    "gn:name":"Tingchuan",
    "gn:population":0,
    "gn:timezone":"Asia/Shanghai",
    "iso:country":"CN",
    "name:zho_x_preferred":[
        "\u505c\u8239"
    ],
    "wof:name":"Tingchuan",
    "wof:placetype":"locality"
},
  "geometry": {"coordinates":[105.655,31.9581],"type":"Point"}
}