{
  "type": "Feature",
  "properties": {
    "gn:admin1_code":"32.0",
    "gn:asciiname":"Dulong",
    "gn:country_code":"CN",
    "gn:dem":4148,
    "gn:feature_class":"P",
    "gn:feature_code":"PPL",
    "gn:name":"Dulong",
    "gn:population":0,
    "gn:timezone":"Asia/Shanghai",
    "iso:country":"CN",
    "name:deu_x_preferred":[
        "Dulong"
    ],
    "name:fra_x_preferred":[
        "Dulong"
    ],
    "name:zho_x_preferred":[
        "\u675c\u9f99"
    ],
    "wof:name":"Dulong",
    "wof:placetype":"locality"
},
  "geometry": {"coordinates":[98.35039999999999,33.0604],"type":"Point"}
}