{
  "type": "Feature",
  "properties": {
    "gn:admin1_code":"11.0",
    "gn:asciiname":"Xiaojiazhuang",
    "gn:country_code":"CN",
    "gn:dem":469,
    "gn:feature_class":"P",
    "gn:feature_code":"PPL",
    "gn:name":"Xiaojiazhuang",
    "gn:population":0,
    "gn:timezone":"Asia/Shanghai",
    "iso:country":"CN",
    "name:zho_x_preferred":[
        "\u8096\u5bb6\u5e84"
    ],
    "wof:name":"Xiaojiazhuang",
    "wof:placetype":"locality"
},
  "geometry": {"coordinates":[110.29618000000001,26.33998],"type":"Point"}
}