{
  "type": "Feature",
  "properties": {
    "gn:admin1_code":"32.0",
    "gn:asciiname":"Mo'erding",
    "gn:country_code":"CN",
    "gn:dem":575,
    "gn:feature_class":"P",
    "gn:feature_code":"PPL",
    "gn:name":"Mo\u2019erding",
    "gn:population":0,
    "gn:timezone":"Asia/Shanghai",
    "iso:country":"CN",
    "name:zho_x_preferred":[
        "\u78e8\u513f\u9876"
    ],
    "name:zho_x_variant":[
        "Mo\u2019erding"
    ],
    "wof:name":"Mo'erding",
    "wof:placetype":"locality"
},
  "geometry": {"coordinates":[103.52513999999999,29.72951],"type":"Point"}
}