{
  "type": "Feature",
  "properties": {
    "gn:admin1_code":"19.0",
    "gn:asciiname":"Wangfuleigou",
    "gn:country_code":"CN",
    "gn:dem":312,
    "gn:feature_class":"P",
    "gn:feature_code":"PPL",
    "gn:name":"Wangfuleigou",
    "gn:population":0,
    "gn:timezone":"Asia/Shanghai",
    "iso:country":"CN",
    "name:und_x_variant":[
        "Wangfulaigou"
    ],
    "name:zho_x_preferred":[
        "\u738b\u798f\u8012\u6c9f"
    ],
    "name:zho_x_variant":[
        "\u738b\u798f\u6765\u6c9f"
    ],
    "wof:name":"Wangfuleigou",
    "wof:placetype":"locality"
},
  "geometry": {"coordinates":[125.264,40.7794],"type":"Point"}
}