{
  "type": "Feature",
  "properties": {
    "gn:admin1_code":"19.0",
    "gn:asciiname":"Zoudiancun",
    "gn:country_code":"CN",
    "gn:dem":48,
    "gn:feature_class":"P",
    "gn:feature_code":"PPL",
    "gn:name":"Zoudiancun",
    "gn:population":0,
    "gn:timezone":"Asia/Shanghai",
    "iso:country":"CN",
    "name:zho_x_preferred":[
        "\u90b9\u5e97\u6751"
    ],
    "wof:name":"Zoudiancun",
    "wof:placetype":"locality"
},
  "geometry": {"coordinates":[122.25700000000001,39.5798],"type":"Point"}
}