{
  "type": "Feature",
  "properties": {
    "gn:admin1_code":"12.0",
    "gn:asciiname":"Longzuizi",
    "gn:country_code":"CN",
    "gn:dem":354,
    "gn:feature_class":"P",
    "gn:feature_code":"PPL",
    "gn:name":"Longzuizi",
    "gn:population":0,
    "gn:timezone":"Asia/Shanghai",
    "iso:country":"CN",
    "name:zho_x_preferred":[
        "\u9f99\u5480\u5b50"
    ],
    "wof:name":"Longzuizi",
    "wof:placetype":"locality"
},
  "geometry": {"coordinates":[110.93582000000001,30.95573],"type":"Point"}
}