{
  "type": "Feature",
  "properties": {
    "gn:admin1_code":"11",
    "gn:asciiname":"Tongjinpu",
    "gn:country_code":"CN",
    "gn:dem":152,
    "gn:feature_class":"P",
    "gn:feature_code":"PPLA4",
    "gn:name":"Tongjinpu",
    "gn:population":0,
    "gn:timezone":"Asia/Shanghai",
    "iso:country":"CN",
    "name:und_x_variant":[
        "Tongjinpu Zhen",
        "Tongjinpu"
    ],
    "name:zho_x_preferred":[
        "\u901a\u6d25\u94fa"
    ],
    "name:zho_x_variant":[
        "\u901a\u6d25\u94fa\u9547"
    ],
    "wof:name":"Tongjinpu",
    "wof:placetype":"locality"
},
  "geometry": {"coordinates":[110.96684999999999,29.53845],"type":"Point"}
}