{
  "type": "Feature",
  "properties": {
    "gn:admin1_code":"4.0",
    "gn:asciiname":"Pangulingcun",
    "gn:country_code":"CN",
    "gn:dem":5,
    "gn:feature_class":"P",
    "gn:feature_code":"PPL",
    "gn:name":"Pangulingcun",
    "gn:population":0,
    "gn:timezone":"Asia/Shanghai",
    "iso:country":"CN",
    "name:zho_x_preferred":[
        "\u76d8\u53e4\u5cad\u6751"
    ],
    "wof:name":"Pangulingcun",
    "wof:placetype":"locality"
},
  "geometry": {"coordinates":[119.24609,35.09192],"type":"Point"}
}