{
  "type": "Feature",
  "properties": {
    "gn:admin1_code":"25",
    "gn:asciiname":"Lianchang Qiancun",
    "gn:country_code":"CN",
    "gn:dem":43,
    "gn:feature_class":"P",
    "gn:feature_code":"PPL",
    "gn:name":"Lianchang Qiancun",
    "gn:population":0,
    "gn:timezone":"Asia/Shanghai",
    "iso:country":"CN",
    "name:zho_x_preferred":[
        "\u8fde\u5382\u524d\u6751"
    ],
    "wof:name":"Lianchang Qiancun",
    "wof:placetype":"locality"
},
  "geometry": {"coordinates":[118.029,34.8231],"type":"Point"}
}