{
  "type": "Feature",
  "properties": {
    "gn:admin1_code":"14.0",
    "gn:asciiname":"Quzhacun",
    "gn:country_code":"CN",
    "gn:dem":4390,
    "gn:feature_class":"P",
    "gn:feature_code":"PPL",
    "gn:name":"Quzhacun",
    "gn:population":0,
    "gn:timezone":"Asia/Urumqi",
    "iso:country":"CN",
    "name:zho_x_preferred":[
        "\u66f2\u624e\u6751"
    ],
    "wof:name":"Quzhacun",
    "wof:placetype":"locality"
},
  "geometry": {"coordinates":[97.13441,30.50203],"type":"Point"}
}