{
  "type": "Feature",
  "properties": {
    "gn:admin1_code":"07",
    "gn:asciiname":"Nanxi",
    "gn:country_code":"CN",
    "gn:dem":393,
    "gn:feature_class":"P",
    "gn:feature_code":"PPL",
    "gn:name":"Nanxi",
    "gn:population":0,
    "gn:timezone":"Asia/Shanghai",
    "iso:country":"CN",
    "name:ceb_x_preferred":[
        "Nan Xi"
    ],
    "name:ces_x_preferred":[
        "Nan-si"
    ],
    "name:deu_x_preferred":[
        "Nanxi"
    ],
    "name:fra_x_preferred":[
        "Nanxi"
    ],
    "name:kor_x_preferred":[
        "\ub09c\uc2dc"
    ],
    "name:nor_x_preferred":[
        "Nanxi"
    ],
    "name:swe_x_preferred":[
        "Nan Xi"
    ],
    "name:zho_x_preferred":[
        "\u5357\u6eaa"
    ],
    "wof:name":"Nanxi",
    "wof:placetype":"locality"
},
  "geometry": {"coordinates":[118.23333999999998,25.23298],"type":"Point"}
}