{
  "type": "Feature",
  "properties": {
    "gn:admin1_code":"30",
    "gn:asciiname":"Heshun",
    "gn:country_code":"CN",
    "gn:dem":12,
    "gn:feature_class":"P",
    "gn:feature_code":"PPL",
    "gn:name":"Heshun",
    "gn:population":0,
    "gn:timezone":"Asia/Shanghai",
    "iso:country":"CN",
    "name:und_x_variant":[
        "Ho-shun",
        "Heshun"
    ],
    "name:zho_x_preferred":[
        "\u548c\u987a"
    ],
    "wof:name":"Heshun",
    "wof:placetype":"locality"
},
  "geometry": {"coordinates":[113.12806,23.25069],"type":"Point"}
}