{
  "type": "Feature",
  "properties": {
    "gn:admin1_code":"10",
    "gn:asciiname":"Loudazigou",
    "gn:country_code":"CN",
    "gn:dem":183,
    "gn:feature_class":"P",
    "gn:feature_code":"PPL",
    "gn:name":"Loudazigou",
    "gn:population":0,
    "gn:timezone":"Asia/Shanghai",
    "iso:country":"CN",
    "name:zho_x_preferred":[
        "\u697c\u8fbe\u5b50\u6c9f"
    ],
    "wof:name":"Loudazigou",
    "wof:placetype":"locality"
},
  "geometry": {"coordinates":[118.86235000000001,40.3244],"type":"Point"}
}