{
  "type": "Feature",
  "properties": {
    "gn:admin1_code":"5.0",
    "gn:asciiname":"Wangjia Juzi",
    "gn:country_code":"CN",
    "gn:dem":166,
    "gn:feature_class":"P",
    "gn:feature_code":"PPL",
    "gn:name":"Wangjia Juzi",
    "gn:population":0,
    "gn:timezone":"Asia/Shanghai",
    "iso:country":"CN",
    "name:zho_x_preferred":[
        "\u738b\u5bb6\u5c40\u5b50"
    ],
    "wof:name":"Wangjia Juzi",
    "wof:placetype":"locality"
},
  "geometry": {"coordinates":[124.06157,43.4256],"type":"Point"}
}