{
  "type": "Feature",
  "properties": {
    "gn:admin1_code":"11.0",
    "gn:asciiname":"Pingxishan",
    "gn:country_code":"CN",
    "gn:dem":729,
    "gn:feature_class":"P",
    "gn:feature_code":"PPL",
    "gn:name":"Pingxishan",
    "gn:population":0,
    "gn:timezone":"Asia/Shanghai",
    "iso:country":"CN",
    "name:zho_x_preferred":[
        "\u5e73\u6eaa\u5c71"
    ],
    "wof:name":"Pingxishan",
    "wof:placetype":"locality"
},
  "geometry": {"coordinates":[110.27442000000001,26.44677],"type":"Point"}
}