{
  "type": "Feature",
  "properties": {
    "gn:admin1_code":"15.0",
    "gn:asciiname":"Baipogen",
    "gn:country_code":"CN",
    "gn:dem":1759,
    "gn:feature_class":"P",
    "gn:feature_code":"PPL",
    "gn:name":"Baipogen",
    "gn:population":0,
    "gn:timezone":"Asia/Shanghai",
    "iso:country":"CN",
    "name:zho_x_preferred":[
        "\u767d\u5761\u6839"
    ],
    "wof:name":"Baipogen",
    "wof:placetype":"locality"
},
  "geometry": {"coordinates":[103.56699999999999,35.8126],"type":"Point"}
}