{
  "type": "Feature",
  "properties": {
    "gn:admin1_code":"32.0",
    "gn:asciiname":"Xiashaofang",
    "gn:country_code":"CN",
    "gn:dem":624,
    "gn:feature_class":"P",
    "gn:feature_code":"PPL",
    "gn:name":"Xiashaofang",
    "gn:population":0,
    "gn:timezone":"Asia/Shanghai",
    "iso:country":"CN",
    "name:zho_x_preferred":[
        "\u4e0b\u70e7\u623f"
    ],
    "wof:name":"Xiashaofang",
    "wof:placetype":"locality"
},
  "geometry": {"coordinates":[104.627,29.6027],"type":"Point"}
}