{
  "type": "Feature",
  "properties": {
    "gn:admin1_code":"32.0",
    "gn:asciiname":"Yihuoluo",
    "gn:country_code":"CN",
    "gn:dem":2232,
    "gn:feature_class":"P",
    "gn:feature_code":"PPL",
    "gn:name":"Yihuoluo",
    "gn:population":0,
    "gn:timezone":"Asia/Shanghai",
    "iso:country":"CN",
    "name:zho_x_preferred":[
        "\u4f9d\u706b\u6d1b"
    ],
    "wof:name":"Yihuoluo",
    "wof:placetype":"locality"
},
  "geometry": {"coordinates":[102.589,28.6361],"type":"Point"}
}