{
  "type": "Feature",
  "properties": {
    "gn:admin1_code":"4.0",
    "gn:asciiname":"Xietangcun",
    "gn:country_code":"CN",
    "gn:dem":12,
    "gn:feature_class":"P",
    "gn:feature_code":"PPL",
    "gn:name":"Xietangcun",
    "gn:population":0,
    "gn:timezone":"Asia/Shanghai",
    "iso:country":"CN",
    "name:zho_x_preferred":[
        "\u87f9\u5858\u6751"
    ],
    "wof:name":"Xietangcun",
    "wof:placetype":"locality"
},
  "geometry": {"coordinates":[118.9093,31.68048],"type":"Point"}
}