{
  "type": "Feature",
  "properties": {
    "gn:admin1_code":"2.0",
    "gn:asciiname":"Dianmenkou",
    "gn:country_code":"CN",
    "gn:dem":55,
    "gn:feature_class":"P",
    "gn:feature_code":"PPL",
    "gn:name":"Dianmenkou",
    "gn:population":0,
    "gn:timezone":"Asia/Shanghai",
    "iso:country":"CN",
    "name:und_x_variant":[
        "\u6bbf\u95e8\u53e3"
    ],
    "name:zho_x_preferred":[
        "Dianmenkou"
    ],
    "wof:name":"Dianmenkou",
    "wof:placetype":"locality"
},
  "geometry": {"coordinates":[119.75644,29.98923],"type":"Point"}
}