{
  "type": "Feature",
  "properties": {
    "gn:admin1_code":"9.0",
    "gn:asciiname":"Xiangbi",
    "gn:country_code":"CN",
    "gn:dem":537,
    "gn:feature_class":"P",
    "gn:feature_code":"PPL",
    "gn:name":"Xiangbi",
    "gn:population":0,
    "gn:timezone":"Asia/Shanghai",
    "iso:country":"CN",
    "name:und_x_variant":[
        "\u8c61\u9f3b",
        "Xiangbi"
    ],
    "wof:name":"Xiangbi",
    "wof:placetype":"locality"
},
  "geometry": {"coordinates":[112.55083,33.57013],"type":"Point"}
}