{
  "type": "Feature",
  "properties": {
    "gn:admin1_code":"3.0",
    "gn:asciiname":"Cetian",
    "gn:country_code":"CN",
    "gn:dem":494,
    "gn:feature_class":"P",
    "gn:feature_code":"PPL",
    "gn:name":"Cetian",
    "gn:population":0,
    "gn:timezone":"Asia/Shanghai",
    "iso:country":"CN",
    "name:und_x_variant":[
        "\u518c\u7530"
    ],
    "wof:name":"Cetian",
    "wof:placetype":"locality"
},
  "geometry": {"coordinates":[116.21942,26.63826],"type":"Point"}
}