{
  "type": "Feature",
  "properties": {
    "gn:admin1_code":"32.0",
    "gn:asciiname":"Huolonggou Ercun",
    "gn:country_code":"CN",
    "gn:dem":2410,
    "gn:feature_class":"P",
    "gn:feature_code":"PPL",
    "gn:name":"Huolonggou Ercun",
    "gn:population":0,
    "gn:timezone":"Asia/Shanghai",
    "iso:country":"CN",
    "name:zho_x_preferred":[
        "\u706b\u9f99\u6c9f\u4e8c\u6751"
    ],
    "wof:name":"Huolonggou Ercun",
    "wof:placetype":"locality"
},
  "geometry": {"coordinates":[102.09399999999999,31.0226],"type":"Point"}
}