{
  "type": "Feature",
  "properties": {
    "gn:admin1_code":"15.0",
    "gn:asciiname":"Wangjialeng",
    "gn:country_code":"CN",
    "gn:dem":1667,
    "gn:feature_class":"P",
    "gn:feature_code":"PPL",
    "gn:name":"Wangjialeng",
    "gn:population":0,
    "gn:timezone":"Asia/Shanghai",
    "iso:country":"CN",
    "name:und_x_variant":[
        "\u738b\u5bb6\u5844"
    ],
    "wof:name":"Wangjialeng",
    "wof:placetype":"locality"
},
  "geometry": {"coordinates":[104.68491,34.66489],"type":"Point"}
}