{
  "type": "Feature",
  "properties": {
    "gn:admin1_code":"16.0",
    "gn:asciiname":"Huaiqu",
    "gn:country_code":"CN",
    "gn:dem":808,
    "gn:feature_class":"P",
    "gn:feature_code":"PPL",
    "gn:name":"Huaiqu",
    "gn:population":0,
    "gn:timezone":"Asia/Shanghai",
    "iso:country":"CN",
    "name:zho_x_preferred":[
        "\u6000\u6e20"
    ],
    "wof:name":"Huaiqu",
    "wof:placetype":"locality"
},
  "geometry": {"coordinates":[106.376,23.3391],"type":"Point"}
}