{
  "type": "Feature",
  "properties": {
    "gn:admin1_code":"16.0",
    "gn:asciiname":"Jiulongtao",
    "gn:country_code":"CN",
    "gn:dem":98,
    "gn:feature_class":"P",
    "gn:feature_code":"PPL",
    "gn:name":"Jiulongtao",
    "gn:population":0,
    "gn:timezone":"Asia/Shanghai",
    "iso:country":"CN",
    "name:zho_x_preferred":[
        "\u65e7\u9647\u9676"
    ],
    "wof:name":"Jiulongtao",
    "wof:placetype":"locality"
},
  "geometry": {"coordinates":[108.08199999999999,23.1498],"type":"Point"}
}