{
  "type": "Feature",
  "properties": {
    "gn:admin1_code":"11",
    "gn:asciiname":"Yuanjiang",
    "gn:country_code":"CN",
    "gn:dem":459,
    "gn:feature_class":"P",
    "gn:feature_code":"PPL",
    "gn:name":"Yuanjiang",
    "gn:population":0,
    "gn:timezone":"Asia/Shanghai",
    "iso:country":"CN",
    "name:zho_x_preferred":[
        "\u6c85\u6c5f"
    ],
    "wof:name":"Yuanjiang",
    "wof:placetype":"locality"
},
  "geometry": {"coordinates":[110.79277999999999,27.37889],"type":"Point"}
}