{
  "type": "Feature",
  "properties": {
    "gn:admin1_code":"1.0",
    "gn:asciiname":"Xin'ercun",
    "gn:country_code":"CN",
    "gn:dem":10,
    "gn:feature_class":"P",
    "gn:feature_code":"PPL",
    "gn:name":"Xin\u2019ercun",
    "gn:population":0,
    "gn:timezone":"Asia/Shanghai",
    "iso:country":"CN",
    "name:und_x_variant":[
        "Xin\u2019ercun"
    ],
    "name:zho_x_preferred":[
        "\u65b0\u4e8c\u6751"
    ],
    "wof:name":"Xin'ercun",
    "wof:placetype":"locality"
},
  "geometry": {"coordinates":[117.1568,31.55952000000001],"type":"Point"}
}