{
  "type": "Feature",
  "properties": {
    "gn:admin1_code":"32.0",
    "gn:asciiname":"Gangtie",
    "gn:country_code":"CN",
    "gn:dem":2935,
    "gn:feature_class":"P",
    "gn:feature_code":"PPL",
    "gn:name":"Gangtie",
    "gn:population":0,
    "gn:timezone":"Asia/Shanghai",
    "iso:country":"CN",
    "name:zho_x_preferred":[
        "\u94a2\u94c1"
    ],
    "wof:name":"Gangtie",
    "wof:placetype":"locality"
},
  "geometry": {"coordinates":[102.68899999999999,27.7745],"type":"Point"}
}