{
  "type": "Feature",
  "properties": {
    "gn:admin1_code":"24",
    "gn:asciiname":"Guojiatuo",
    "gn:country_code":"CN",
    "gn:dem":1528,
    "gn:feature_class":"P",
    "gn:feature_code":"PPL",
    "gn:name":"Guojiatuo",
    "gn:population":0,
    "gn:timezone":"Asia/Shanghai",
    "iso:country":"CN",
    "name:zho_x_preferred":[
        "\u90ed\u5bb6\u5768"
    ],
    "wof:name":"Guojiatuo",
    "wof:placetype":"locality"
},
  "geometry": {"coordinates":[113.36247,35.98641],"type":"Point"}
}