{
  "type": "Feature",
  "properties": {
    "gn:admin1_code":"8.0",
    "gn:asciiname":"Jiguanlazicun",
    "gn:country_code":"CN",
    "gn:dem":486,
    "gn:feature_class":"P",
    "gn:feature_code":"PPL",
    "gn:name":"Jiguanlazicun",
    "gn:population":0,
    "gn:timezone":"Asia/Shanghai",
    "iso:country":"CN",
    "name:zho_x_preferred":[
        "\u9e21\u51a0\u782c\u5b50\u6751"
    ],
    "wof:name":"Jiguanlazicun",
    "wof:placetype":"locality"
},
  "geometry": {"coordinates":[130.61965000000001,44.49786],"type":"Point"}
}