{
  "type": "Feature",
  "properties": {
    "gn:admin1_code":"01",
    "gn:asciiname":"Caochangcun",
    "gn:country_code":"CN",
    "gn:dem":25,
    "gn:feature_class":"P",
    "gn:feature_code":"PPL",
    "gn:name":"Caochangcun",
    "gn:population":0,
    "gn:timezone":"Asia/Shanghai",
    "iso:country":"CN",
    "name:und_x_variant":[
        "Ts\u2019ao-ch\u2019ang-chi",
        "Ts\u2019ao-ch\u2019ang",
        "Caochang",
        "Caochangcun"
    ],
    "name:zho_x_preferred":[
        "\u66f9\u573a\u6751"
    ],
    "wof:name":"Caochangcun",
    "wof:placetype":"locality"
},
  "geometry": {"coordinates":[117.73029,33.70288],"type":"Point"}
}