{
  "type": "Feature",
  "properties": {
    "gn:admin1_code":"11",
    "gn:asciiname":"Liming",
    "gn:country_code":"CN",
    "gn:dem":925,
    "gn:feature_class":"P",
    "gn:feature_code":"PPL",
    "gn:name":"Liming",
    "gn:population":0,
    "gn:timezone":"Asia/Shanghai",
    "iso:country":"CN",
    "name:ceb_x_preferred":[
        "Liming"
    ],
    "name:deu_x_preferred":[
        "Liming"
    ],
    "name:swe_x_preferred":[
        "Liming"
    ],
    "wof:name":"Liming",
    "wof:placetype":"locality"
},
  "geometry": {"coordinates":[110.17917,27.15222],"type":"Point"}
}