{
  "type": "Feature",
  "properties": {
    "gn:admin1_code":"29.0",
    "gn:asciiname":"Yonggela",
    "gn:country_code":"CN",
    "gn:dem":1552,
    "gn:feature_class":"P",
    "gn:feature_code":"PPL",
    "gn:name":"Yonggela",
    "gn:population":0,
    "gn:timezone":"Asia/Shanghai",
    "iso:country":"CN",
    "name:zho_x_preferred":[
        "\u6c38\u683c\u62c9"
    ],
    "wof:name":"Yonggela",
    "wof:placetype":"locality"
},
  "geometry": {"coordinates":[99.4796,22.885],"type":"Point"}
}