{
  "type": "Feature",
  "properties": {
    "gn:admin1_code":"32.0",
    "gn:asciiname":"Wabuguli",
    "gn:country_code":"CN",
    "gn:dem":2151,
    "gn:feature_class":"P",
    "gn:feature_code":"PPL",
    "gn:name":"Wabuguli",
    "gn:population":0,
    "gn:timezone":"Asia/Shanghai",
    "iso:country":"CN",
    "name:zho_x_preferred":[
        "\u74e6\u8865\u8c37\u7acb"
    ],
    "wof:name":"Wabuguli",
    "wof:placetype":"locality"
},
  "geometry": {"coordinates":[102.78400000000001,27.9501],"type":"Point"}
}