{
  "type": "Feature",
  "properties": {
    "gn:admin1_code":"07",
    "gn:asciiname":"Zhongtian",
    "gn:country_code":"CN",
    "gn:dem":915,
    "gn:feature_class":"P",
    "gn:feature_code":"PPL",
    "gn:name":"Zhongtian",
    "gn:population":0,
    "gn:timezone":"Asia/Shanghai",
    "iso:country":"CN",
    "name:zho_x_preferred":[
        "\u4e2d\u7530"
    ],
    "wof:name":"Zhongtian",
    "wof:placetype":"locality"
},
  "geometry": {"coordinates":[118.57312,26.74543],"type":"Point"}
}