{
  "type": "Feature",
  "properties": {
    "gn:admin1_code":"14",
    "gn:asciiname":"Zhailing",
    "gn:country_code":"CN",
    "gn:dem":3662,
    "gn:feature_class":"P",
    "gn:feature_code":"PPL",
    "gn:name":"Zhailing",
    "gn:population":0,
    "gn:timezone":"Asia/Urumqi",
    "iso:country":"CN",
    "name:bod_x_preferred":[
        "\u0f56\u0f40\u0fb2\u0f66\u0f0b\u0f42\u0fb3\u0f72\u0f44"
    ],
    "wof:name":"Zhailing",
    "wof:placetype":"locality"
},
  "geometry": {"coordinates":[91.71411999999999,29.10073],"type":"Point"}
}