{
  "type": "Feature",
  "properties": {
    "gn:admin1_code":"29.0",
    "gn:asciiname":"Najiazhuang",
    "gn:country_code":"CN",
    "gn:dem":1821,
    "gn:feature_class":"P",
    "gn:feature_code":"PPL",
    "gn:name":"Najiazhuang",
    "gn:population":0,
    "gn:timezone":"Asia/Shanghai",
    "iso:country":"CN",
    "name:zho_x_preferred":[
        "\u7eb3\u5bb6\u5e84"
    ],
    "wof:name":"Najiazhuang",
    "wof:placetype":"locality"
},
  "geometry": {"coordinates":[101.065,25.8904],"type":"Point"}
}