{
  "type": "Feature",
  "properties": {
    "gn:admin1_code":"16.0",
    "gn:asciiname":"Jian'an",
    "gn:country_code":"CN",
    "gn:dem":250,
    "gn:feature_class":"P",
    "gn:feature_code":"PPL",
    "gn:name":"Jian\u2019an",
    "gn:population":0,
    "gn:timezone":"Asia/Shanghai",
    "iso:country":"CN",
    "name:und_x_variant":[
        "Jian\u2019an"
    ],
    "name:zho_x_preferred":[
        "\u5efa\u5b89"
    ],
    "wof:name":"Jian'an",
    "wof:placetype":"locality"
},
  "geometry": {"coordinates":[108.545,24.3814],"type":"Point"}
}