{
  "type": "Feature",
  "properties": {
    "gn:admin1_code":"18",
    "gn:asciiname":"Kuashan",
    "gn:country_code":"CN",
    "gn:dem":1589,
    "gn:feature_class":"P",
    "gn:feature_code":"PPL",
    "gn:name":"Kuashan",
    "gn:population":0,
    "gn:timezone":"Asia/Shanghai",
    "iso:country":"CN",
    "name:zho_x_preferred":[
        "\u57ae\u5c71"
    ],
    "wof:name":"Kuashan",
    "wof:placetype":"locality"
},
  "geometry": {"coordinates":[104.83499999999999,27.3094],"type":"Point"}
}