{
  "type": "Feature",
  "properties": {
    "gn:admin1_code":"19.0",
    "gn:asciiname":"Liaohaituncun",
    "gn:country_code":"CN",
    "gn:dem":71,
    "gn:feature_class":"P",
    "gn:feature_code":"PPL",
    "gn:name":"Liaohaituncun",
    "gn:population":0,
    "gn:timezone":"Asia/Shanghai",
    "iso:country":"CN",
    "name:zho_x_preferred":[
        "\u8fbd\u6d77\u5c6f\u6751"
    ],
    "wof:name":"Liaohaituncun",
    "wof:placetype":"locality"
},
  "geometry": {"coordinates":[123.79900000000001,42.2352],"type":"Point"}
}