{
  "type": "Feature",
  "properties": {
    "gn:admin1_code":"2.0",
    "gn:asciiname":"Jiajueke",
    "gn:country_code":"CN",
    "gn:dem":11,
    "gn:feature_class":"P",
    "gn:feature_code":"PPL",
    "gn:name":"Jiajueke",
    "gn:population":0,
    "gn:timezone":"Asia/Shanghai",
    "iso:country":"CN",
    "name:zho_x_preferred":[
        "\u52a0\u7235\u79d1"
    ],
    "wof:name":"Jiajueke",
    "wof:placetype":"locality"
},
  "geometry": {"coordinates":[121.47673,29.46711],"type":"Point"}
}