{
  "type": "Feature",
  "properties": {
    "gn:admin1_code":"18",
    "gn:asciiname":"Hongyan Dixia",
    "gn:country_code":"CN",
    "gn:dem":458,
    "gn:feature_class":"P",
    "gn:feature_code":"PPL",
    "gn:name":"Hongyan Dixia",
    "gn:population":0,
    "gn:timezone":"Asia/Shanghai",
    "iso:country":"CN",
    "name:zho_x_preferred":[
        "\u7ea2\u5ca9\u5e95\u4e0b"
    ],
    "wof:name":"Hongyan Dixia",
    "wof:placetype":"locality"
},
  "geometry": {"coordinates":[106.18300000000001,28.5088],"type":"Point"}
}