{
  "type": "Feature",
  "properties": {
    "gn:admin1_code":"20.0",
    "gn:asciiname":"Dongdesheng Sandui",
    "gn:country_code":"CN",
    "gn:dem":273,
    "gn:feature_class":"P",
    "gn:feature_code":"PPLF",
    "gn:name":"Dongdesheng Sandui",
    "gn:population":0,
    "gn:timezone":"Asia/Shanghai",
    "iso:country":"CN",
    "name:zho_x_preferred":[
        "\u4e1c\u5fb7\u80dc\u4e09\u961f"
    ],
    "wof:name":"Dongdesheng Sandui",
    "wof:placetype":"locality"
},
  "geometry": {"coordinates":[122.76275,47.81209000000001],"type":"Point"}
}