{
  "type": "Feature",
  "properties": {
    "gn:admin1_code":"18",
    "gn:asciiname":"Duicuoluo",
    "gn:country_code":"CN",
    "gn:dem":1860,
    "gn:feature_class":"P",
    "gn:feature_code":"PPL",
    "gn:name":"Duicuoluo",
    "gn:population":0,
    "gn:timezone":"Asia/Shanghai",
    "iso:country":"CN",
    "name:zho_x_preferred":[
        "\u5bf9\u78cb\u7f57"
    ],
    "wof:name":"Duicuoluo",
    "wof:placetype":"locality"
},
  "geometry": {"coordinates":[105.10599999999999,26.7662],"type":"Point"}
}