{
  "type": "Feature",
  "properties": {
    "gn:admin1_code":"14.0",
    "gn:asciiname":"Ganglangcun",
    "gn:country_code":"CN",
    "gn:dem":4512,
    "gn:feature_class":"P",
    "gn:feature_code":"PPL",
    "gn:name":"Ganglangcun",
    "gn:population":0,
    "gn:timezone":"Asia/Urumqi",
    "iso:country":"CN",
    "name:zho_x_preferred":[
        "\u5c97\u6717\u6751"
    ],
    "wof:name":"Ganglangcun",
    "wof:placetype":"locality"
},
  "geometry": {"coordinates":[92.88171,30.45097],"type":"Point"}
}