{
  "type": "Feature",
  "properties": {
    "gn:admin1_code":"5.0",
    "gn:asciiname":"Daijia Wobu",
    "gn:country_code":"CN",
    "gn:dem":155,
    "gn:feature_class":"P",
    "gn:feature_code":"PPL",
    "gn:name":"Daijia Wobu",
    "gn:population":0,
    "gn:timezone":"Asia/Shanghai",
    "iso:country":"CN",
    "name:zho_x_preferred":[
        "\u6234\u5bb6\u7a9d\u5821"
    ],
    "wof:name":"Daijia Wobu",
    "wof:placetype":"locality"
},
  "geometry": {"coordinates":[125.04089999999999,45.17596],"type":"Point"}
}