{
  "type": "Feature",
  "properties": {
    "gn:admin1_code":"16.0",
    "gn:asciiname":"Baxi",
    "gn:country_code":"CN",
    "gn:dem":98,
    "gn:feature_class":"P",
    "gn:feature_code":"PPL",
    "gn:name":"Baxi",
    "gn:population":0,
    "gn:timezone":"Asia/Shanghai",
    "iso:country":"CN",
    "name:zho_x_preferred":[
        "\u5c9c\u9521"
    ],
    "wof:name":"Baxi",
    "wof:placetype":"locality"
},
  "geometry": {"coordinates":[107.92100000000001,22.7532],"type":"Point"}
}