{
  "type": "Feature",
  "properties": {
    "gn:admin1_code":"29.0",
    "gn:asciiname":"Xiangjia Baobao",
    "gn:country_code":"CN",
    "gn:dem":2029,
    "gn:feature_class":"P",
    "gn:feature_code":"PPL",
    "gn:name":"Xiangjia Baobao",
    "gn:population":0,
    "gn:timezone":"Asia/Shanghai",
    "iso:country":"CN",
    "name:zho_x_preferred":[
        "\u5411\u5bb6\u5305\u5305"
    ],
    "wof:name":"Xiangjia Baobao",
    "wof:placetype":"locality"
},
  "geometry": {"coordinates":[103.53700000000001,27.3944],"type":"Point"}
}