{
  "type": "Feature",
  "properties": {
    "gn:admin1_code":"9.0",
    "gn:asciiname":"Dasong",
    "gn:country_code":"CN",
    "gn:dem":82,
    "gn:feature_class":"P",
    "gn:feature_code":"PPL",
    "gn:name":"Dasong",
    "gn:population":0,
    "gn:timezone":"Asia/Shanghai",
    "iso:country":"CN",
    "name:und_x_variant":[
        "\u5927\u5b8b"
    ],
    "name:zho_x_preferred":[
        "\u5927\u5b8b"
    ],
    "wof:name":"Dasong",
    "wof:placetype":"locality"
},
  "geometry": {"coordinates":[113.74733999999999,33.90238],"type":"Point"}
}