{
  "type": "Feature",
  "properties": {
    "gn:admin1_code":"19.0",
    "gn:asciiname":"Guanjia",
    "gn:country_code":"CN",
    "gn:dem":23,
    "gn:feature_class":"P",
    "gn:feature_code":"PPL",
    "gn:name":"Guanjia",
    "gn:population":0,
    "gn:timezone":"Asia/Shanghai",
    "iso:country":"CN",
    "name:und_x_variant":[
        "\u8d2f\u5bb6"
    ],
    "name:zho_x_preferred":[
        "\u8d2f\u5bb6"
    ],
    "wof:name":"Guanjia",
    "wof:placetype":"locality"
},
  "geometry": {"coordinates":[122.39722999999999,41.77867],"type":"Point"}
}