{
  "type": "Feature",
  "properties": {
    "gn:admin1_code":"2.0",
    "gn:asciiname":"Nanbatou",
    "gn:country_code":"CN",
    "gn:dem":3,
    "gn:feature_class":"P",
    "gn:feature_code":"PPL",
    "gn:name":"Nanbatou",
    "gn:population":0,
    "gn:timezone":"Asia/Shanghai",
    "iso:country":"CN",
    "name:und_x_variant":[
        "\u5357\u575d\u5934"
    ],
    "wof:name":"Nanbatou",
    "wof:placetype":"locality"
},
  "geometry": {"coordinates":[120.17016,30.84166],"type":"Point"}
}