{
  "type": "Feature",
  "properties": {
    "gn:admin1_code":"7.0",
    "gn:asciiname":"Shangfengcun",
    "gn:country_code":"CN",
    "gn:dem":261,
    "gn:feature_class":"P",
    "gn:feature_code":"PPL",
    "gn:name":"Shangfengcun",
    "gn:population":0,
    "gn:timezone":"Asia/Shanghai",
    "iso:country":"CN",
    "name:und_x_variant":[
        "\u4e0a\u5cf0\u6751"
    ],
    "name:zho_x_preferred":[
        "\u4e0a\u5cf0\u6751"
    ],
    "wof:name":"Shangfengcun",
    "wof:placetype":"locality"
},
  "geometry": {"coordinates":[117.27112,26.71043],"type":"Point"}
}