{
  "type": "Feature",
  "properties": {
    "gn:admin1_code":"12.0",
    "gn:asciiname":"Guanjia'ao",
    "gn:country_code":"CN",
    "gn:dem":73,
    "gn:feature_class":"P",
    "gn:feature_code":"PPL",
    "gn:name":"Guanjia\u2019ao",
    "gn:population":0,
    "gn:timezone":"Asia/Shanghai",
    "iso:country":"CN",
    "name:zho_x_preferred":[
        "Guanjia\u2019ao"
    ],
    "name:zho_x_variant":[
        "\u5b98\u5bb6\u51f9"
    ],
    "wof:name":"Guanjia'ao",
    "wof:placetype":"locality"
},
  "geometry": {"coordinates":[112.19888,30.761],"type":"Point"}
}