{
  "type": "Feature",
  "properties": {
    "gn:admin1_code":"5.0",
    "gn:asciiname":"Xiaocai Yuanzi",
    "gn:country_code":"CN",
    "gn:dem":141,
    "gn:feature_class":"P",
    "gn:feature_code":"PPL",
    "gn:name":"Xiaocai Yuanzi",
    "gn:population":0,
    "gn:timezone":"Asia/Shanghai",
    "iso:country":"CN",
    "name:zho_x_preferred":[
        "\u5c0f\u83dc\u56ed\u5b50"
    ],
    "wof:name":"Xiaocai Yuanzi",
    "wof:placetype":"locality"
},
  "geometry": {"coordinates":[125.24278,44.84387],"type":"Point"}
}