{
  "type": "Feature",
  "properties": {
    "gn:admin1_code":"33.0",
    "gn:asciiname":"Xituo",
    "gn:country_code":"CN",
    "gn:dem":248,
    "gn:feature_class":"P",
    "gn:feature_code":"PPLA4",
    "gn:name":"Xituo",
    "gn:population":0,
    "gn:timezone":"Asia/Shanghai",
    "iso:country":"CN",
    "name:und_x_variant":[
        "Hsi-t\u2019o-chen",
        "Xituo",
        "Xituo Zhen"
    ],
    "name:zho_x_preferred":[
        "\u897f\u6cb1"
    ],
    "name:zho_x_variant":[
        "\u897f\u6cb1\u9547"
    ],
    "wof:name":"Xituo",
    "wof:placetype":"locality"
},
  "geometry": {"coordinates":[108.21732,30.40793],"type":"Point"}
}