{
  "type": "Feature",
  "properties": {
    "gn:admin1_code":"4.0",
    "gn:asciiname":"Qilaozhuang",
    "gn:country_code":"CN",
    "gn:dem":11,
    "gn:feature_class":"P",
    "gn:feature_code":"PPL",
    "gn:name":"Qilaozhuang",
    "gn:population":0,
    "gn:timezone":"Asia/Shanghai",
    "iso:country":"CN",
    "name:zho_x_preferred":[
        "Qilaozhuang"
    ],
    "name:zho_x_variant":[
        "\u9f50\u8001\u5e84"
    ],
    "wof:name":"Qilaozhuang",
    "wof:placetype":"locality"
},
  "geometry": {"coordinates":[119.14315000000001,33.7129],"type":"Point"}
}