{
  "type": "Feature",
  "properties": {
    "gn:admin1_code":"29",
    "gn:asciiname":"Bameng",
    "gn:country_code":"CN",
    "gn:dem":1182,
    "gn:feature_class":"P",
    "gn:feature_code":"PPL",
    "gn:name":"Bameng",
    "gn:population":0,
    "gn:timezone":"Asia/Shanghai",
    "iso:country":"CN",
    "name:zho_x_preferred":[
        "\u53ed\u5b5f"
    ],
    "wof:name":"Bameng",
    "wof:placetype":"locality"
},
  "geometry": {"coordinates":[105.566,23.8478],"type":"Point"}
}