{
  "type": "Feature",
  "properties": {
    "gn:admin1_code":"3.0",
    "gn:asciiname":"Tingqian",
    "gn:country_code":"CN",
    "gn:dem":75,
    "gn:feature_class":"P",
    "gn:feature_code":"PPL",
    "gn:name":"Tingqian",
    "gn:population":0,
    "gn:timezone":"Asia/Shanghai",
    "iso:country":"CN",
    "name:und_x_variant":[
        "\u4ead\u524d"
    ],
    "wof:name":"Tingqian",
    "wof:placetype":"locality"
},
  "geometry": {"coordinates":[114.92032,27.36087],"type":"Point"}
}