{
  "type": "Feature",
  "properties": {
    "gn:admin1_code":"8.0",
    "gn:asciiname":"Lidalitun",
    "gn:country_code":"CN",
    "gn:dem":169,
    "gn:feature_class":"P",
    "gn:feature_code":"PPL",
    "gn:name":"Lidalitun",
    "gn:population":0,
    "gn:timezone":"Asia/Shanghai",
    "iso:country":"CN",
    "name:zho_x_preferred":[
        "\u674e\u5927\u68a8\u5c6f"
    ],
    "wof:name":"Lidalitun",
    "wof:placetype":"locality"
},
  "geometry": {"coordinates":[125.22924,47.34097],"type":"Point"}
}