{
  "type": "Feature",
  "properties": {
    "gn:admin1_code":"11.0",
    "gn:asciiname":"Yijiawan",
    "gn:country_code":"CN",
    "gn:dem":1215,
    "gn:feature_class":"P",
    "gn:feature_code":"PPL",
    "gn:name":"Yijiawan",
    "gn:population":0,
    "gn:timezone":"Asia/Shanghai",
    "iso:country":"CN",
    "name:zho_x_preferred":[
        "\u6613\u5bb6\u6e7e"
    ],
    "name:zho_x_variant":[
        "\u6613\u5bb6\u6e7e\u9547"
    ],
    "wof:name":"Yijiawan",
    "wof:placetype":"locality"
},
  "geometry": {"coordinates":[109.66334000000001,29.56312],"type":"Point"}
}