{
  "type": "Feature",
  "properties": {
    "gn:admin1_code":"10.0",
    "gn:asciiname":"Qianwujialantuo",
    "gn:country_code":"CN",
    "gn:dem":6,
    "gn:feature_class":"P",
    "gn:feature_code":"PPL",
    "gn:name":"Qianwujialantuo",
    "gn:population":0,
    "gn:timezone":"Asia/Shanghai",
    "iso:country":"CN",
    "name:zho_x_preferred":[
        "\u524d\u5434\u5bb6\u5170\u5768"
    ],
    "wof:name":"Qianwujialantuo",
    "wof:placetype":"locality"
},
  "geometry": {"coordinates":[118.76593,39.32809],"type":"Point"}
}