{
  "type": "Feature",
  "properties": {
    "gn:admin1_code":"5.0",
    "gn:asciiname":"Xiaojia Tuozi",
    "gn:country_code":"CN",
    "gn:dem":133,
    "gn:feature_class":"P",
    "gn:feature_code":"PPL",
    "gn:name":"Xiaojia Tuozi",
    "gn:population":0,
    "gn:timezone":"Asia/Shanghai",
    "iso:country":"CN",
    "name:zho_x_preferred":[
        "\u8096\u5bb6\u5768\u5b50"
    ],
    "wof:name":"Xiaojia Tuozi",
    "wof:placetype":"locality"
},
  "geometry": {"coordinates":[125.90501,45.18299],"type":"Point"}
}