{
  "type": "Feature",
  "properties": {
    "gn:admin1_code":"19.0",
    "gn:asciiname":"Nanmaozhangzi",
    "gn:country_code":"CN",
    "gn:dem":613,
    "gn:feature_class":"P",
    "gn:feature_code":"PPL",
    "gn:name":"Nanmaozhangzi",
    "gn:population":0,
    "gn:timezone":"Asia/Shanghai",
    "iso:country":"CN",
    "name:zho_x_preferred":[
        "\u5357\u6bdb\u4e08\u5b50"
    ],
    "wof:name":"Nanmaozhangzi",
    "wof:placetype":"locality"
},
  "geometry": {"coordinates":[119.762,40.6053],"type":"Point"}
}