{
  "type": "Feature",
  "properties": {
    "gn:admin1_code":"4.0",
    "gn:asciiname":"Daliu",
    "gn:country_code":"CN",
    "gn:dem":13,
    "gn:feature_class":"P",
    "gn:feature_code":"PPL",
    "gn:name":"Daliu",
    "gn:population":0,
    "gn:timezone":"Asia/Shanghai",
    "iso:country":"CN",
    "name:zho_x_preferred":[
        "\u5927\u5218"
    ],
    "wof:name":"Daliu",
    "wof:placetype":"locality"
},
  "geometry": {"coordinates":[118.896,33.2412],"type":"Point"}
}