{
  "type": "Feature",
  "properties": {
    "gn:admin1_code":"29.0",
    "gn:asciiname":"Alameng",
    "gn:country_code":"CN",
    "gn:dem":2248,
    "gn:feature_class":"P",
    "gn:feature_code":"PPL",
    "gn:name":"Alameng",
    "gn:population":0,
    "gn:timezone":"Asia/Shanghai",
    "iso:country":"CN",
    "name:zho_x_preferred":[
        "\u963f\u814a\u52d0"
    ],
    "wof:name":"Alameng",
    "wof:placetype":"locality"
},
  "geometry": {"coordinates":[98.6664,27.6306],"type":"Point"}
}