{
  "type": "Feature",
  "properties": {
    "gn:admin1_code":"31.0",
    "gn:asciiname":"Yinsheng",
    "gn:country_code":"CN",
    "gn:dem":35,
    "gn:feature_class":"P",
    "gn:feature_code":"PPL",
    "gn:name":"Yinsheng",
    "gn:population":0,
    "gn:timezone":"Asia/Shanghai",
    "iso:country":"CN",
    "name:zho_x_preferred":[
        "Yinsheng"
    ],
    "name:zho_x_variant":[
        "\u836b\u751f"
    ],
    "wof:name":"Yinsheng",
    "wof:placetype":"locality"
},
  "geometry": {"coordinates":[110.52905,19.8497],"type":"Point"}
}