{
  "type": "Feature",
  "properties": {
    "gn:admin1_code":"32.0",
    "gn:asciiname":"Yiti",
    "gn:country_code":"CN",
    "gn:dem":1405,
    "gn:feature_class":"P",
    "gn:feature_code":"PPL",
    "gn:name":"Yiti",
    "gn:population":0,
    "gn:timezone":"Asia/Shanghai",
    "iso:country":"CN",
    "name:ara_x_preferred":[
        "\u064a\u062a\u064a"
    ],
    "name:fas_x_preferred":[
        "\u06cc\u062a\u06cc"
    ],
    "name:nno_x_preferred":[
        "Yiti"
    ],
    "name:urd_x_preferred":[
        "\u06cc\u062a\u06cc"
    ],
    "name:zho_x_preferred":[
        "\u4f9d\u68af"
    ],
    "wof:name":"Yiti",
    "wof:placetype":"locality"
},
  "geometry": {"coordinates":[103.078,28.9589],"type":"Point"}
}