{
  "type": "Feature",
  "properties": {
    "gn:admin1_code":"14.0",
    "gn:asciiname":"Gesemai",
    "gn:country_code":"CN",
    "gn:dem":4438,
    "gn:feature_class":"P",
    "gn:feature_code":"PPLF",
    "gn:name":"Gesemai",
    "gn:population":0,
    "gn:timezone":"Asia/Urumqi",
    "iso:country":"CN",
    "name:bod_x_preferred":[
        "G\u00easibmai"
    ],
    "name:zho_x_preferred":[
        "Gesemai"
    ],
    "name:zho_x_variant":[
        "\u683c\u8272\u9ea6",
        "Liangmei",
        "\u4eae\u7f8e"
    ],
    "wof:name":"Gesemai",
    "wof:placetype":"locality"
},
  "geometry": {"coordinates":[97.70099999999999,31.701],"type":"Point"}
}