{
  "type": "Feature",
  "properties": {
    "gn:admin1_code":"12.0",
    "gn:asciiname":"Xiaoganxi",
    "gn:country_code":"CN",
    "gn:dem":854,
    "gn:feature_class":"P",
    "gn:feature_code":"PPL",
    "gn:name":"Xiaoganxi",
    "gn:population":0,
    "gn:timezone":"Asia/Shanghai",
    "iso:country":"CN",
    "name:zho_x_preferred":[
        "\u5c0f\u5e72\u6eaa"
    ],
    "wof:name":"Xiaoganxi",
    "wof:placetype":"locality"
},
  "geometry": {"coordinates":[110.29545,30.9868],"type":"Point"}
}