{
  "type": "Feature",
  "properties": {
    "gn:admin1_code":"15.0",
    "gn:asciiname":"Shangjiang",
    "gn:country_code":"CN",
    "gn:dem":1917,
    "gn:feature_class":"P",
    "gn:feature_code":"PPL",
    "gn:name":"Shangjiang",
    "gn:population":0,
    "gn:timezone":"Asia/Shanghai",
    "iso:country":"CN",
    "name:zho_x_preferred":[
        "\u4e0a\u848b"
    ],
    "wof:name":"Shangjiang",
    "wof:placetype":"locality"
},
  "geometry": {"coordinates":[106.21599999999999,35.1422],"type":"Point"}
}