{
  "type": "Feature",
  "properties": {
    "gn:admin1_code":"26.0",
    "gn:asciiname":"Yongping",
    "gn:country_code":"CN",
    "gn:dem":933,
    "gn:feature_class":"P",
    "gn:feature_code":"PPL",
    "gn:name":"Yongping",
    "gn:population":0,
    "gn:timezone":"Asia/Shanghai",
    "iso:country":"CN",
    "name:zho_x_preferred":[
        "\u6c38\u5e73"
    ],
    "wof:name":"Yongping",
    "wof:placetype":"locality"
},
  "geometry": {"coordinates":[109.37372999999999,32.26726],"type":"Point"}
}