{
  "type": "Feature",
  "properties": {
    "gn:admin1_code":"19.0",
    "gn:asciiname":"Daxinggou",
    "gn:country_code":"CN",
    "gn:dem":75,
    "gn:feature_class":"P",
    "gn:feature_code":"PPL",
    "gn:name":"Daxinggou",
    "gn:population":0,
    "gn:timezone":"Asia/Shanghai",
    "iso:country":"CN",
    "name:zho_x_preferred":[
        "\u5927\u90a2\u6c9f"
    ],
    "wof:name":"Daxinggou",
    "wof:placetype":"locality"
},
  "geometry": {"coordinates":[122.07599999999999,39.6815],"type":"Point"}
}