{
  "type": "Feature",
  "properties": {
    "gn:admin1_code":"9.0",
    "gn:asciiname":"Yuanying",
    "gn:country_code":"CN",
    "gn:dem":126,
    "gn:feature_class":"P",
    "gn:feature_code":"PPL",
    "gn:name":"Yuanying",
    "gn:population":0,
    "gn:timezone":"Asia/Shanghai",
    "iso:country":"CN",
    "name:zho_x_preferred":[
        "\u8881\u8425"
    ],
    "name:zho_x_variant":[
        "\u91cb\u5713\u745b"
    ],
    "wof:name":"Yuanying",
    "wof:placetype":"locality"
},
  "geometry": {"coordinates":[112.63172,32.9072],"type":"Point"}
}