{
  "type": "Feature",
  "properties": {
    "gn:admin1_code":"2.0",
    "gn:asciiname":"Sitangtou",
    "gn:country_code":"CN",
    "gn:dem":83,
    "gn:feature_class":"P",
    "gn:feature_code":"PPL",
    "gn:name":"Sitangtou",
    "gn:population":0,
    "gn:timezone":"Asia/Shanghai",
    "iso:country":"CN",
    "name:zho_x_preferred":[
        "\u5bfa\u5858\u5934"
    ],
    "wof:name":"Sitangtou",
    "wof:placetype":"locality"
},
  "geometry": {"coordinates":[120.63608000000001,29.45334],"type":"Point"}
}