{
  "type": "Feature",
  "properties": {
    "gn:admin1_code":"29.0",
    "gn:asciiname":"Namadai",
    "gn:country_code":"CN",
    "gn:dem":1384,
    "gn:feature_class":"P",
    "gn:feature_code":"PPL",
    "gn:name":"Namadai",
    "gn:population":0,
    "gn:timezone":"Asia/Shanghai",
    "iso:country":"CN",
    "name:zho_x_preferred":[
        "\u7eb3\u9ebb\u4ee3"
    ],
    "wof:name":"Namadai",
    "wof:placetype":"locality"
},
  "geometry": {"coordinates":[100.953,26.2432],"type":"Point"}
}