{
  "type": "Feature",
  "properties": {
    "gn:admin1_code":"5.0",
    "gn:asciiname":"Liuqiaogou",
    "gn:country_code":"CN",
    "gn:dem":652,
    "gn:feature_class":"P",
    "gn:feature_code":"PPL",
    "gn:name":"Liuqiaogou",
    "gn:population":0,
    "gn:timezone":"Asia/Shanghai",
    "iso:country":"CN",
    "name:zho_x_preferred":[
        "\u67f3\u6865\u6c9f"
    ],
    "wof:name":"Liuqiaogou",
    "wof:placetype":"locality"
},
  "geometry": {"coordinates":[130.42615000000001,43.66587],"type":"Point"}
}