{
  "type": "Feature",
  "properties": {
    "gn:admin1_code":"5.0",
    "gn:asciiname":"Sanhutun",
    "gn:country_code":"CN",
    "gn:dem":232,
    "gn:feature_class":"P",
    "gn:feature_code":"PPL",
    "gn:name":"Sanhutun",
    "gn:population":0,
    "gn:timezone":"Asia/Shanghai",
    "iso:country":"CN",
    "name:zho_x_preferred":[
        "\u4e09\u6237\u5c6f"
    ],
    "wof:name":"Sanhutun",
    "wof:placetype":"locality"
},
  "geometry": {"coordinates":[125.01117000000001,43.62931],"type":"Point"}
}