{
  "type": "Feature",
  "properties": {
    "gn:admin1_code":"22",
    "gn:asciiname":"Dongfeng",
    "gn:country_code":"CN",
    "gn:dem":40,
    "gn:feature_class":"P",
    "gn:feature_code":"PPLA4",
    "gn:name":"Dongfeng",
    "gn:population":0,
    "gn:timezone":"Asia/Shanghai",
    "iso:country":"CN",
    "name:ceb_x_preferred":[
        "Dongfeng"
    ],
    "name:dan_x_preferred":[
        "Dong Feng"
    ],
    "name:deu_x_preferred":[
        "Dongfeng"
    ],
    "name:fra_x_preferred":[
        "Dongfeng"
    ],
    "name:mlg_x_preferred":[
        "Dongfeng"
    ],
    "name:nld_x_preferred":[
        "Dongfeng"
    ],
    "name:nor_x_preferred":[
        "Dongfeng"
    ],
    "name:pol_x_preferred":[
        "Dongfeng"
    ],
    "name:rus_x_preferred":[
        "\u0414\u0443\u043d\u0444\u044d\u043d"
    ],
    "name:swe_x_preferred":[
        "Dongfeng"
    ],
    "name:und_x_variant":[
        "Dongfeng Xiang"
    ],
    "name:vie_x_preferred":[
        "\u0110\u00f4ng Phong"
    ],
    "name:zho_x_preferred":[
        "\u4e1c\u98ce"
    ],
    "name:zho_x_variant":[
        "\u4e1c\u98ce\u4e61"
    ],
    "wof:name":"Dongfeng",
    "wof:placetype":"locality"
},
  "geometry": {"coordinates":[116.49930999999999,39.9365],"type":"Point"}
}