{
  "type": "Feature",
  "properties": {
    "gn:admin1_code":"32.0",
    "gn:asciiname":"Xiejiagou",
    "gn:country_code":"CN",
    "gn:dem":569,
    "gn:feature_class":"P",
    "gn:feature_code":"PPL",
    "gn:name":"Xiejiagou",
    "gn:population":0,
    "gn:timezone":"Asia/Shanghai",
    "iso:country":"CN",
    "name:zho_x_preferred":[
        "\u8c22\u5bb6\u6c9f"
    ],
    "wof:name":"Xiejiagou",
    "wof:placetype":"locality"
},
  "geometry": {"coordinates":[104.358,29.6033],"type":"Point"}
}