{
  "type": "Feature",
  "properties": {
    "gn:admin1_code":"12.0",
    "gn:asciiname":"Houbianxu",
    "gn:country_code":"CN",
    "gn:dem":31,
    "gn:feature_class":"P",
    "gn:feature_code":"PPL",
    "gn:name":"Houbianxu",
    "gn:population":0,
    "gn:timezone":"Asia/Shanghai",
    "iso:country":"CN",
    "name:und_x_variant":[
        "\u540e\u8fb9\u5f90"
    ],
    "wof:name":"Houbianxu",
    "wof:placetype":"locality"
},
  "geometry": {"coordinates":[114.23746,30.16327],"type":"Point"}
}