{
  "type": "Feature",
  "properties": {
    "gn:admin1_code":"19.0",
    "gn:asciiname":"Jiancaogoucun",
    "gn:country_code":"CN",
    "gn:dem":87,
    "gn:feature_class":"P",
    "gn:feature_code":"PPL",
    "gn:name":"Jiancaogoucun",
    "gn:population":0,
    "gn:timezone":"Asia/Shanghai",
    "iso:country":"CN",
    "name:zho_x_preferred":[
        "\u78b1\u8349\u6c9f\u6751"
    ],
    "wof:name":"Jiancaogoucun",
    "wof:placetype":"locality"
},
  "geometry": {"coordinates":[121.44,41.7289],"type":"Point"}
}