{
  "type": "Feature",
  "properties": {
    "gn:admin1_code":"25",
    "gn:asciiname":"Shuangmiao",
    "gn:country_code":"CN",
    "gn:dem":49,
    "gn:feature_class":"P",
    "gn:feature_code":"PPL",
    "gn:name":"Shuangmiao",
    "gn:population":0,
    "gn:timezone":"Asia/Shanghai",
    "iso:country":"CN",
    "name:ceb_x_preferred":[
        "Shuangmiao"
    ],
    "name:swe_x_preferred":[
        "Shuangmiao"
    ],
    "name:zho_x_preferred":[
        "\u53cc\u5e99"
    ],
    "wof:name":"Shuangmiao",
    "wof:placetype":"locality"
},
  "geometry": {"coordinates":[115.782,35.2755],"type":"Point"}
}