{
  "type": "Feature",
  "properties": {
    "gn:admin1_code":"20",
    "gn:asciiname":"Tanjiayingzi",
    "gn:country_code":"CN",
    "gn:dem":1310,
    "gn:feature_class":"P",
    "gn:feature_code":"PPL",
    "gn:name":"Tanjiayingzi",
    "gn:population":0,
    "gn:timezone":"Asia/Shanghai",
    "iso:country":"CN",
    "wof:name":"Tanjiayingzi",
    "wof:placetype":"locality"
},
  "geometry": {"coordinates":[114.18389000000001,41.62139000000001],"type":"Point"}
}