{
  "type": "Feature",
  "properties": {
    "gn:admin1_code":"2.0",
    "gn:asciiname":"Chenjianong",
    "gn:country_code":"CN",
    "gn:dem":10,
    "gn:feature_class":"P",
    "gn:feature_code":"PPL",
    "gn:name":"Chenjianong",
    "gn:population":0,
    "gn:timezone":"Asia/Shanghai",
    "iso:country":"CN",
    "name:und_x_variant":[
        "\u9648\u5bb6\u5f04"
    ],
    "wof:name":"Chenjianong",
    "wof:placetype":"locality"
},
  "geometry": {"coordinates":[119.63298,30.89418],"type":"Point"}
}