{
  "type": "Feature",
  "properties": {
    "gn:admin1_code":"03",
    "gn:asciiname":"Mahuiling",
    "gn:country_code":"CN",
    "gn:dem":39,
    "gn:feature_class":"P",
    "gn:feature_code":"PPLA4",
    "gn:name":"Mahuiling",
    "gn:population":0,
    "gn:timezone":"Asia/Shanghai",
    "iso:country":"CN",
    "name:und_x_variant":[
        "\u9a6c\u8ff4\u5cad",
        "Mahuiling Zhen",
        "\u9a6c\u8ff4\u5cad\u9547"
    ],
    "wof:name":"Mahuiling",
    "wof:placetype":"locality"
},
  "geometry": {"coordinates":[115.80166,29.44614],"type":"Point"}
}