{
  "type": "Feature",
  "properties": {
    "gn:admin1_code":"4.0",
    "gn:asciiname":"Guanmen",
    "gn:country_code":"CN",
    "gn:dem":3,
    "gn:feature_class":"P",
    "gn:feature_code":"PPL",
    "gn:name":"Guanmen",
    "gn:population":0,
    "gn:timezone":"Asia/Shanghai",
    "iso:country":"CN",
    "name:und_x_variant":[
        "Chengbei"
    ],
    "name:zho_x_preferred":[
        "\u5173\u95e8"
    ],
    "name:zho_x_variant":[
        "\u57ce\u5317"
    ],
    "wof:name":"Guanmen",
    "wof:placetype":"locality"
},
  "geometry": {"coordinates":[119.85124999999999,32.96084],"type":"Point"}
}