{
  "type": "Feature",
  "properties": {
    "gn:admin1_code":"11.0",
    "gn:asciiname":"Ziqiangwan",
    "gn:country_code":"CN",
    "gn:dem":41,
    "gn:feature_class":"P",
    "gn:feature_code":"PPL",
    "gn:name":"Ziqiangwan",
    "gn:population":0,
    "gn:timezone":"Asia/Shanghai",
    "iso:country":"CN",
    "name:zho_x_preferred":[
        "\u5b57\u5899\u6e7e"
    ],
    "wof:name":"Ziqiangwan",
    "wof:placetype":"locality"
},
  "geometry": {"coordinates":[112.45741,28.49502],"type":"Point"}
}