{
  "type": "Feature",
  "properties": {
    "gn:admin1_code":"15.0",
    "gn:asciiname":"Bianjiatai",
    "gn:country_code":"CN",
    "gn:dem":1493,
    "gn:feature_class":"P",
    "gn:feature_code":"PPL",
    "gn:name":"Bianjiatai",
    "gn:population":0,
    "gn:timezone":"Asia/Shanghai",
    "iso:country":"CN",
    "name:zho_x_preferred":[
        "\u535e\u5bb6\u53f0"
    ],
    "wof:name":"Bianjiatai",
    "wof:placetype":"locality"
},
  "geometry": {"coordinates":[104.729,36.7746],"type":"Point"}
}