{
  "type": "Feature",
  "properties": {
    "gn:admin1_code":"24",
    "gn:asciiname":"Nancha",
    "gn:country_code":"CN",
    "gn:dem":1517,
    "gn:feature_class":"P",
    "gn:feature_code":"PPL",
    "gn:name":"Nancha",
    "gn:population":0,
    "gn:timezone":"Asia/Shanghai",
    "iso:country":"CN",
    "name:ara_x_preferred":[
        "\u0646\u0627\u0646\u0634\u0627"
    ],
    "name:ben_x_preferred":[
        "\u09a8\u09be\u09a8\u099a\u09be"
    ],
    "name:ell_x_preferred":[
        "\u039d\u03ac\u03bd\u03c4\u03c3\u03b1"
    ],
    "name:fas_x_preferred":[
        "\u0646\u0627\u0646\u0686\u0627"
    ],
    "name:fra_x_preferred":[
        "Nancha"
    ],
    "name:heb_x_preferred":[
        "\u05e0\u05e0\u05e6'\u05d4"
    ],
    "name:hin_x_preferred":[
        "\u0928\u093e\u0902\u091a\u093e"
    ],
    "name:hun_x_preferred":[
        "Nancha"
    ],
    "name:ind_x_preferred":[
        "Nancha"
    ],
    "name:ita_x_preferred":[
        "Nancha"
    ],
    "name:jpn_x_preferred":[
        "\u5357\u5c94"
    ],
    "name:kor_x_preferred":[
        "\ub09c\ucc28"
    ],
    "name:nld_x_preferred":[
        "Nancha"
    ],
    "name:pol_x_preferred":[
        "Nancha"
    ],
    "name:por_x_preferred":[
        "Nancha"
    ],
    "name:rus_x_preferred":[
        "\u041d\u0430\u043d\u044c\u0447\u0430"
    ],
    "name:spa_x_preferred":[
        "Nancha"
    ],
    "name:tur_x_preferred":[
        "Nancha"
    ],
    "name:ukr_x_preferred":[
        "\u041d\u0430\u043d\u044c\u0447\u0430"
    ],
    "name:urd_x_preferred":[
        "\u0646\u0627\u0646\u0686\u0627"
    ],
    "name:vie_x_preferred":[
        "Nam X\u00f3a"
    ],
    "name:zho_x_preferred":[
        "\u5357\u5c94"
    ],
    "wof:name":"Nancha",
    "wof:placetype":"locality"
},
  "geometry": {"coordinates":[111.81663,37.92187],"type":"Point"}
}