{
  "type": "Feature",
  "properties": {
    "gn:admin1_code":"5.0",
    "gn:asciiname":"Putaogoucun",
    "gn:country_code":"CN",
    "gn:dem":279,
    "gn:feature_class":"P",
    "gn:feature_code":"PPL",
    "gn:name":"Putaogoucun",
    "gn:population":0,
    "gn:timezone":"Asia/Shanghai",
    "iso:country":"CN",
    "name:zho_x_preferred":[
        "\u8461\u8404\u6c9f\u6751"
    ],
    "wof:name":"Putaogoucun",
    "wof:placetype":"locality"
},
  "geometry": {"coordinates":[126.92121000000002,43.68268],"type":"Point"}
}