{
  "type": "Feature",
  "properties": {
    "gn:admin1_code":"15.0",
    "gn:asciiname":"Junma Sanchang Sidui",
    "gn:country_code":"CN",
    "gn:dem":2676,
    "gn:feature_class":"P",
    "gn:feature_code":"PPLF",
    "gn:name":"Junma Sanchang Sidui",
    "gn:population":0,
    "gn:timezone":"Asia/Shanghai",
    "iso:country":"CN",
    "name:zho_x_preferred":[
        "\u519b\u9a6c\u4e09\u573a\u56db\u961f"
    ],
    "wof:name":"Junma Sanchang Sidui",
    "wof:placetype":"locality"
},
  "geometry": {"coordinates":[101.045,38.2768],"type":"Point"}
}