{
  "type": "Feature",
  "properties": {
    "gn:admin1_code":"26.0",
    "gn:asciiname":"Fansi",
    "gn:country_code":"CN",
    "gn:dem":1258,
    "gn:feature_class":"P",
    "gn:feature_code":"PPL",
    "gn:name":"Fansi",
    "gn:population":0,
    "gn:timezone":"Asia/Shanghai",
    "iso:country":"CN",
    "name:zho_x_preferred":[
        "\u8303\u5bfa"
    ],
    "wof:name":"Fansi",
    "wof:placetype":"locality"
},
  "geometry": {"coordinates":[109.08665999999999,37.50432],"type":"Point"}
}