{
  "type": "Feature",
  "properties": {
    "gn:admin1_code":"12.0",
    "gn:asciiname":"Nanhu Nongchang Badui",
    "gn:country_code":"CN",
    "gn:dem":20,
    "gn:feature_class":"P",
    "gn:feature_code":"PPLF",
    "gn:name":"Nanhu Nongchang Badui",
    "gn:population":0,
    "gn:timezone":"Asia/Shanghai",
    "iso:country":"CN",
    "name:zho_x_preferred":[
        "\u5357\u6e56\u519c\u573a\u516b\u961f"
    ],
    "wof:name":"Nanhu Nongchang Badui",
    "wof:placetype":"locality"
},
  "geometry": {"coordinates":[114.949,30.43962],"type":"Point"}
}