{
  "type": "Feature",
  "properties": {
    "gn:admin1_code":"25",
    "gn:asciiname":"Fengwo",
    "gn:country_code":"CN",
    "gn:dem":405,
    "gn:feature_class":"P",
    "gn:feature_code":"PPL",
    "gn:name":"Fengwo",
    "gn:population":0,
    "gn:timezone":"Asia/Shanghai",
    "iso:country":"CN",
    "name:zho_x_preferred":[
        "\u8702\u7a9d"
    ],
    "wof:name":"Fengwo",
    "wof:placetype":"locality"
},
  "geometry": {"coordinates":[117.497,36.4805],"type":"Point"}
}