{
  "type": "Feature",
  "properties": {
    "gn:admin1_code":"3.0",
    "gn:asciiname":"Fenglingtou",
    "gn:country_code":"CN",
    "gn:dem":164,
    "gn:feature_class":"P",
    "gn:feature_code":"PPL",
    "gn:name":"Fenglingtou",
    "gn:population":0,
    "gn:timezone":"Asia/Shanghai",
    "iso:country":"CN",
    "name:und_x_variant":[
        "\u67ab\u5cad\u5934"
    ],
    "wof:name":"Fenglingtou",
    "wof:placetype":"locality"
},
  "geometry": {"coordinates":[117.45749000000001,29.67964000000001],"type":"Point"}
}