{
  "type": "Feature",
  "properties": {
    "gn:admin1_code":"7.0",
    "gn:asciiname":"Xiashadi",
    "gn:country_code":"CN",
    "gn:dem":224,
    "gn:feature_class":"P",
    "gn:feature_code":"PPL",
    "gn:name":"Xiashadi",
    "gn:population":0,
    "gn:timezone":"Asia/Shanghai",
    "iso:country":"CN",
    "name:zho_x_preferred":[
        "\u4e0b\u6c99\u5730"
    ],
    "wof:name":"Xiashadi",
    "wof:placetype":"locality"
},
  "geometry": {"coordinates":[117.39331,26.20092],"type":"Point"}
}