{
  "type": "Feature",
  "properties": {
    "gn:admin1_code":"25",
    "gn:asciiname":"Qianzhuyuan",
    "gn:country_code":"CN",
    "gn:dem":111,
    "gn:feature_class":"P",
    "gn:feature_code":"PPL",
    "gn:name":"Qianzhuyuan",
    "gn:population":0,
    "gn:timezone":"Asia/Shanghai",
    "iso:country":"CN",
    "name:zho_x_preferred":[
        "\u524d\u7af9\u56ed"
    ],
    "wof:name":"Qianzhuyuan",
    "wof:placetype":"locality"
},
  "geometry": {"coordinates":[118.715,35.5123],"type":"Point"}
}