{
  "type": "Feature",
  "properties": {
    "gn:admin1_code":"32.0",
    "gn:asciiname":"Gemei",
    "gn:country_code":"CN",
    "gn:dem":3761,
    "gn:feature_class":"P",
    "gn:feature_code":"PPL",
    "gn:name":"Gemei",
    "gn:population":0,
    "gn:timezone":"Asia/Shanghai",
    "iso:country":"CN",
    "name:zho_x_preferred":[
        "\u683c\u7f8e"
    ],
    "wof:name":"Gemei",
    "wof:placetype":"locality"
},
  "geometry": {"coordinates":[99.71444,31.8345],"type":"Point"}
}