{
  "type": "Feature",
  "properties": {
    "gn:admin1_code":"16.0",
    "gn:asciiname":"Nawen",
    "gn:country_code":"CN",
    "gn:dem":390,
    "gn:feature_class":"P",
    "gn:feature_code":"PPL",
    "gn:name":"Nawen",
    "gn:population":0,
    "gn:timezone":"Asia/Shanghai",
    "iso:country":"CN",
    "name:zho_x_preferred":[
        "\u90a3\u6587"
    ],
    "wof:name":"Nawen",
    "wof:placetype":"locality"
},
  "geometry": {"coordinates":[107.31399999999999,24.512],"type":"Point"}
}