{
  "type": "Feature",
  "properties": {
    "gn:admin1_code":"14.0",
    "gn:asciiname":"Duone",
    "gn:country_code":"CN",
    "gn:dem":4694,
    "gn:feature_class":"P",
    "gn:feature_code":"PPL",
    "gn:name":"Duone",
    "gn:population":0,
    "gn:timezone":"Asia/Urumqi",
    "iso:country":"CN",
    "name:zho_x_preferred":[
        "\u591a\u5462"
    ],
    "wof:name":"Duone",
    "wof:placetype":"locality"
},
  "geometry": {"coordinates":[92.70967,31.72181],"type":"Point"}
}