{
  "type": "Feature",
  "properties": {
    "gn:admin1_code":"30.0",
    "gn:asciiname":"Dawei",
    "gn:country_code":"CN",
    "gn:dem":24,
    "gn:feature_class":"P",
    "gn:feature_code":"PPL",
    "gn:name":"Dawei",
    "gn:population":0,
    "gn:timezone":"Asia/Shanghai",
    "iso:country":"CN",
    "name:zho_x_preferred":[
        "\u5927\u56f4"
    ],
    "wof:name":"Dawei",
    "wof:placetype":"locality"
},
  "geometry": {"coordinates":[113.30138999999998,23.92167],"type":"Point"}
}