{
  "type": "Feature",
  "properties": {
    "gn:admin1_code":"11.0",
    "gn:asciiname":"Wangjiachong",
    "gn:country_code":"CN",
    "gn:dem":620,
    "gn:feature_class":"P",
    "gn:feature_code":"PPL",
    "gn:name":"Wangjiachong",
    "gn:population":0,
    "gn:timezone":"Asia/Shanghai",
    "iso:country":"CN",
    "name:zho_x_preferred":[
        "\u738b\u5bb6\u51b2"
    ],
    "wof:name":"Wangjiachong",
    "wof:placetype":"locality"
},
  "geometry": {"coordinates":[110.47635,27.42331],"type":"Point"}
}