{
  "type": "Feature",
  "properties": {
    "gn:admin1_code":"23.0",
    "gn:asciiname":"Yujiaqiao",
    "gn:cc2":"CN",
    "gn:country_code":"CN",
    "gn:dem":5,
    "gn:feature_class":"P",
    "gn:feature_code":"PPL",
    "gn:name":"Yujiaqiao",
    "gn:population":0,
    "gn:timezone":"Asia/Shanghai",
    "iso:country":"CN",
    "name:und_x_variant":[
        "Y\u00fc-chia-chai",
        "Yujiaqiao"
    ],
    "wof:name":"Yujiaqiao",
    "wof:placetype":"locality"
},
  "geometry": {"coordinates":[121.52806,31.10806],"type":"Point"}
}