{
  "type": "Feature",
  "properties": {
    "gn:admin1_code":"11.0",
    "gn:asciiname":"Mao'erchong",
    "gn:country_code":"CN",
    "gn:dem":401,
    "gn:feature_class":"P",
    "gn:feature_code":"PPL",
    "gn:name":"Mao\u2019erchong",
    "gn:population":0,
    "gn:timezone":"Asia/Shanghai",
    "iso:country":"CN",
    "name:und_x_variant":[
        "Mao\u2019erchong"
    ],
    "name:zho_x_preferred":[
        "\u732b\u513f\u51b2"
    ],
    "wof:name":"Mao'erchong",
    "wof:placetype":"locality"
},
  "geometry": {"coordinates":[112.95858,25.62627],"type":"Point"}
}