{
  "type": "Feature",
  "properties": {
    "gn:admin1_code":"12.0",
    "gn:asciiname":"Baisangguan",
    "gn:country_code":"CN",
    "gn:dem":420,
    "gn:feature_class":"P",
    "gn:feature_code":"PPLA4",
    "gn:name":"Baisangguan",
    "gn:population":0,
    "gn:timezone":"Asia/Shanghai",
    "iso:country":"CN",
    "name:und_x_variant":[
        "Baisangguan Zhen"
    ],
    "name:zho_x_preferred":[
        "\u767d\u6851\u5173"
    ],
    "name:zho_x_variant":[
        "\u767d\u6851\u5173\u9547"
    ],
    "wof:name":"Baisangguan",
    "wof:placetype":"locality"
},
  "geometry": {"coordinates":[110.991,32.96261],"type":"Point"}
}