{
  "type": "Feature",
  "properties": {
    "gn:admin1_code":"26",
    "gn:asciiname":"Donggucun",
    "gn:country_code":"CN",
    "gn:dem":736,
    "gn:feature_class":"P",
    "gn:feature_code":"PPL",
    "gn:name":"Donggucun",
    "gn:population":0,
    "gn:timezone":"Asia/Shanghai",
    "iso:country":"CN",
    "name:und_x_variant":[
        "Tung-ku-chen",
        "Dongguzhen",
        "Donggucun"
    ],
    "name:zho_x_preferred":[
        "\u4e1c\u56fa\u6751"
    ],
    "wof:name":"Donggucun",
    "wof:placetype":"locality"
},
  "geometry": {"coordinates":[109.70101,35.1893],"type":"Point"}
}