{
  "type": "Feature",
  "properties": {
    "gn:admin1_code":"10",
    "gn:asciiname":"Yanzhazi",
    "gn:country_code":"CN",
    "gn:dem":1007,
    "gn:feature_class":"P",
    "gn:feature_code":"PPL",
    "gn:name":"Yanzhazi",
    "gn:population":0,
    "gn:timezone":"Asia/Shanghai",
    "iso:country":"CN",
    "name:zho_x_preferred":[
        "\u960e\u6805\u5b50"
    ],
    "wof:name":"Yanzhazi",
    "wof:placetype":"locality"
},
  "geometry": {"coordinates":[116.37631,41.02213],"type":"Point"}
}