{
  "type": "Feature",
  "properties": {
    "gn:admin1_code":"18",
    "gn:asciiname":"Pingdi",
    "gn:country_code":"CN",
    "gn:dem":1764,
    "gn:feature_class":"P",
    "gn:feature_code":"PPL",
    "gn:name":"Pingdi",
    "gn:population":0,
    "gn:timezone":"Asia/Shanghai",
    "iso:country":"CN",
    "name:zho_x_preferred":[
        "\u576a\u5730"
    ],
    "wof:name":"Pingdi",
    "wof:placetype":"locality"
},
  "geometry": {"coordinates":[104.664,25.6561],"type":"Point"}
}