{
  "type": "Feature",
  "properties": {
    "gn:admin1_code":"32.0",
    "gn:asciiname":"Sijijue",
    "gn:country_code":"CN",
    "gn:dem":2006,
    "gn:feature_class":"P",
    "gn:feature_code":"PPL",
    "gn:name":"Sijijue",
    "gn:population":0,
    "gn:timezone":"Asia/Shanghai",
    "iso:country":"CN",
    "name:zho_x_preferred":[
        "\u56db\u57fa\u89c9"
    ],
    "wof:name":"Sijijue",
    "wof:placetype":"locality"
},
  "geometry": {"coordinates":[103.07899999999999,28.4786],"type":"Point"}
}