{
  "type": "Feature",
  "properties": {
    "gn:admin1_code":"21.0",
    "gn:asciiname":"Guyangwan",
    "gn:country_code":"CN",
    "gn:dem":1718,
    "gn:feature_class":"P",
    "gn:feature_code":"PPL",
    "gn:name":"Guyangwan",
    "gn:population":0,
    "gn:timezone":"Asia/Shanghai",
    "iso:country":"CN",
    "name:und_x_variant":[
        "\u53e4\u9633\u6e7e"
    ],
    "name:zho_x_preferred":[
        "\u53e4\u9633\u6e7e"
    ],
    "wof:name":"Guyangwan",
    "wof:placetype":"locality"
},
  "geometry": {"coordinates":[106.13370999999999,36.88477],"type":"Point"}
}