{
  "type": "Feature",
  "properties": {
    "gn:admin1_code":"29.0",
    "gn:asciiname":"Matai",
    "gn:country_code":"CN",
    "gn:dem":1550,
    "gn:feature_class":"P",
    "gn:feature_code":"PPL",
    "gn:name":"Matai",
    "gn:population":0,
    "gn:timezone":"Asia/Shanghai",
    "iso:country":"CN",
    "name:ceb_x_preferred":[
        "Matai"
    ],
    "name:deu_x_preferred":[
        "Matai"
    ],
    "name:swe_x_preferred":[
        "Matai"
    ],
    "name:zho_x_preferred":[
        "\u9a6c\u53f0"
    ],
    "wof:name":"Matai",
    "wof:placetype":"locality"
},
  "geometry": {"coordinates":[100.77500000000001,24.2255],"type":"Point"}
}