{
  "type": "Feature",
  "properties": {
    "gn:admin1_code":"12.0",
    "gn:asciiname":"Sanfomiao",
    "gn:country_code":"CN",
    "gn:dem":829,
    "gn:feature_class":"P",
    "gn:feature_code":"PPL",
    "gn:name":"Sanfomiao",
    "gn:population":0,
    "gn:timezone":"Asia/Shanghai",
    "iso:country":"CN",
    "name:zho_x_preferred":[
        "\u4e09\u4f5b\u5e99"
    ],
    "wof:name":"Sanfomiao",
    "wof:placetype":"locality"
},
  "geometry": {"coordinates":[110.33362,31.86085],"type":"Point"}
}