{
  "type": "Feature",
  "properties": {
    "gn:admin1_code":"26.0",
    "gn:asciiname":"Anjiazhuangcun",
    "gn:country_code":"CN",
    "gn:dem":496,
    "gn:feature_class":"P",
    "gn:feature_code":"PPL",
    "gn:name":"Anjiazhuangcun",
    "gn:population":0,
    "gn:timezone":"Asia/Shanghai",
    "iso:country":"CN",
    "name:zho_x_preferred":[
        "\u5b89\u9a7e\u5e84\u6751"
    ],
    "wof:name":"Anjiazhuangcun",
    "wof:placetype":"locality"
},
  "geometry": {"coordinates":[108.54593,34.55904],"type":"Point"}
}