{
  "type": "Feature",
  "properties": {
    "gn:admin1_code":"2.0",
    "gn:asciiname":"Fanghuangludong",
    "gn:country_code":"CN",
    "gn:dem":6,
    "gn:feature_class":"P",
    "gn:feature_code":"PPL",
    "gn:name":"Fanghuangludong",
    "gn:population":0,
    "gn:timezone":"Asia/Shanghai",
    "iso:country":"CN",
    "name:und_x_variant":[
        "\u623f\u9ec4\u8def\u4e1c"
    ],
    "wof:name":"Fanghuangludong",
    "wof:placetype":"locality"
},
  "geometry": {"coordinates":[121.24772,30.2617],"type":"Point"}
}