{
  "type": "Feature",
  "properties": {
    "gn:admin1_code":"26.0",
    "gn:asciiname":"Yushutai",
    "gn:country_code":"CN",
    "gn:dem":1490,
    "gn:feature_class":"P",
    "gn:feature_code":"PPL",
    "gn:name":"Yushutai",
    "gn:population":0,
    "gn:timezone":"Asia/Shanghai",
    "iso:country":"CN",
    "name:zho_x_preferred":[
        "\u6986\u6811\u53f0"
    ],
    "wof:name":"Yushutai",
    "wof:placetype":"locality"
},
  "geometry": {"coordinates":[108.40921000000002,37.14339],"type":"Point"}
}