{
  "type": "Feature",
  "properties": {
    "gn:admin1_code":"10",
    "gn:asciiname":"Tianqiaogou",
    "gn:country_code":"CN",
    "gn:dem":977,
    "gn:feature_class":"P",
    "gn:feature_code":"PPL",
    "gn:name":"Tianqiaogou",
    "gn:population":0,
    "gn:timezone":"Asia/Shanghai",
    "iso:country":"CN",
    "name:zho_x_preferred":[
        "\u5929\u6865\u6c9f"
    ],
    "wof:name":"Tianqiaogou",
    "wof:placetype":"locality"
},
  "geometry": {"coordinates":[116.65413999999998,41.05849],"type":"Point"}
}