{
  "type": "Feature",
  "properties": {
    "gn:admin1_code":"29",
    "gn:asciiname":"Liwang",
    "gn:country_code":"CN",
    "gn:dem":569,
    "gn:feature_class":"P",
    "gn:feature_code":"PPL",
    "gn:name":"Liwang",
    "gn:population":0,
    "gn:timezone":"Asia/Shanghai",
    "iso:country":"CN",
    "name:ceb_x_preferred":[
        "Liwang"
    ],
    "name:deu_x_preferred":[
        "Liwang"
    ],
    "name:new_x_preferred":[
        "\u0932\u093f\u0935\u093e\u0919"
    ],
    "name:pol_x_preferred":[
        "Liwang"
    ],
    "name:zho_x_preferred":[
        "\u91cc\u5f80"
    ],
    "wof:name":"Liwang",
    "wof:placetype":"locality"
},
  "geometry": {"coordinates":[105.631,24.0635],"type":"Point"}
}