{
  "type": "Feature",
  "properties": {
    "gn:admin1_code":"9.0",
    "gn:asciiname":"Guojun Nancun",
    "gn:country_code":"CN",
    "gn:dem":66,
    "gn:feature_class":"P",
    "gn:feature_code":"PPL",
    "gn:name":"Guojun Nancun",
    "gn:population":0,
    "gn:timezone":"Asia/Shanghai",
    "iso:country":"CN",
    "name:zho_x_preferred":[
        "\u90ed\u541b\u5357\u6751"
    ],
    "wof:name":"Guojun Nancun",
    "wof:placetype":"locality"
},
  "geometry": {"coordinates":[114.66885000000001,34.67861],"type":"Point"}
}