{
  "type": "Feature",
  "properties": {
    "gn:admin1_code":"29.0",
    "gn:asciiname":"Hanjia",
    "gn:country_code":"CN",
    "gn:dem":1979,
    "gn:feature_class":"P",
    "gn:feature_code":"PPL",
    "gn:name":"Hanjia",
    "gn:population":0,
    "gn:timezone":"Asia/Shanghai",
    "iso:country":"CN",
    "name:zho_x_preferred":[
        "\u6c49\u5bb6"
    ],
    "wof:name":"Hanjia",
    "wof:placetype":"locality"
},
  "geometry": {"coordinates":[100.626,24.6763],"type":"Point"}
}