{
  "type": "Feature",
  "properties": {
    "gn:admin1_code":"2.0",
    "gn:asciiname":"Hedayuan",
    "gn:country_code":"CN",
    "gn:dem":246,
    "gn:feature_class":"P",
    "gn:feature_code":"PPL",
    "gn:name":"Hedayuan",
    "gn:population":0,
    "gn:timezone":"Asia/Shanghai",
    "iso:country":"CN",
    "name:zho_x_preferred":[
        "\u6cb3\u5927\u5143"
    ],
    "wof:name":"Hedayuan",
    "wof:placetype":"locality"
},
  "geometry": {"coordinates":[119.98909,29.5932],"type":"Point"}
}