{
  "type": "Feature",
  "properties": {
    "gn:admin1_code":"32",
    "gn:asciiname":"Daiwan",
    "gn:country_code":"CN",
    "gn:dem":897,
    "gn:feature_class":"P",
    "gn:feature_code":"PPL",
    "gn:name":"Daiwan",
    "gn:population":0,
    "gn:timezone":"Asia/Shanghai",
    "iso:country":"CN",
    "wof:name":"Daiwan",
    "wof:placetype":"locality"
},
  "geometry": {"coordinates":[103.45,29.31667],"type":"Point"}
}