{
  "type": "Feature",
  "properties": {
    "gn:admin1_code":"15.0",
    "gn:asciiname":"Xiazengjiazhuang",
    "gn:country_code":"CN",
    "gn:dem":2008,
    "gn:feature_class":"P",
    "gn:feature_code":"PPL",
    "gn:name":"Xiazengjiazhuang",
    "gn:population":0,
    "gn:timezone":"Asia/Shanghai",
    "iso:country":"CN",
    "name:zho_x_preferred":[
        "\u4e0b\u66fe\u5bb6\u5e84"
    ],
    "wof:name":"Xiazengjiazhuang",
    "wof:placetype":"locality"
},
  "geometry": {"coordinates":[104.488,35.5821],"type":"Point"}
}