{
  "type": "Feature",
  "properties": {
    "gn:admin1_code":"16.0",
    "gn:asciiname":"Lanqing",
    "gn:country_code":"CN",
    "gn:dem":295,
    "gn:feature_class":"P",
    "gn:feature_code":"PPL",
    "gn:name":"Lanqing",
    "gn:population":0,
    "gn:timezone":"Asia/Shanghai",
    "iso:country":"CN",
    "name:zho_x_preferred":[
        "\u84dd\u9752"
    ],
    "wof:name":"Lanqing",
    "wof:placetype":"locality"
},
  "geometry": {"coordinates":[111.313,23.8473],"type":"Point"}
}