{
  "type": "Feature",
  "properties": {
    "gn:admin1_code":"30",
    "gn:asciiname":"Pingtian",
    "gn:country_code":"CN",
    "gn:dem":219,
    "gn:feature_class":"P",
    "gn:feature_code":"PPLA4",
    "gn:name":"Pingtian",
    "gn:population":0,
    "gn:timezone":"Asia/Shanghai",
    "iso:country":"CN",
    "name:und_x_variant":[
        "Pingtian Zhen",
        "\u576a\u7530\u9547"
    ],
    "name:zho_x_preferred":[
        "\u576a\u7530"
    ],
    "wof:name":"Pingtian",
    "wof:placetype":"locality"
},
  "geometry": {"coordinates":[114.62445,25.1915],"type":"Point"}
}