{
  "type": "Feature",
  "properties": {
    "gn:admin1_code":"29.0",
    "gn:asciiname":"Pingzishang",
    "gn:country_code":"CN",
    "gn:dem":1603,
    "gn:feature_class":"P",
    "gn:feature_code":"PPL",
    "gn:name":"Pingzishang",
    "gn:population":0,
    "gn:timezone":"Asia/Shanghai",
    "iso:country":"CN",
    "name:zho_x_preferred":[
        "\u576a\u5b50\u4e0a"
    ],
    "wof:name":"Pingzishang",
    "wof:placetype":"locality"
},
  "geometry": {"coordinates":[103.23399999999999,27.3657],"type":"Point"}
}