{
  "type": "Feature",
  "properties": {
    "gn:admin1_code":"32.0",
    "gn:asciiname":"Xieqitai",
    "gn:country_code":"CN",
    "gn:dem":1462,
    "gn:feature_class":"P",
    "gn:feature_code":"PPL",
    "gn:name":"Xieqitai",
    "gn:population":0,
    "gn:timezone":"Asia/Shanghai",
    "iso:country":"CN",
    "name:zho_x_preferred":[
        "\u6b47\u6c14\u53f0"
    ],
    "wof:name":"Xieqitai",
    "wof:placetype":"locality"
},
  "geometry": {"coordinates":[103.14293000000001,29.2272],"type":"Point"}
}