{
  "type": "Feature",
  "properties": {
    "gn:admin1_code":"29.0",
    "gn:asciiname":"Daheshang",
    "gn:country_code":"CN",
    "gn:dem":2575,
    "gn:feature_class":"P",
    "gn:feature_code":"PPL",
    "gn:name":"Daheshang",
    "gn:population":0,
    "gn:timezone":"Asia/Shanghai",
    "iso:country":"CN",
    "name:zho_x_preferred":[
        "\u5927\u6cb3\u4e0a"
    ],
    "wof:name":"Daheshang",
    "wof:placetype":"locality"
},
  "geometry": {"coordinates":[100.89,27.3317],"type":"Point"}
}