{
  "type": "Feature",
  "properties": {
    "gn:admin1_code":"3.0",
    "gn:asciiname":"Hugang",
    "gn:country_code":"CN",
    "gn:dem":81,
    "gn:feature_class":"P",
    "gn:feature_code":"PPL",
    "gn:name":"Hugang",
    "gn:population":0,
    "gn:timezone":"Asia/Shanghai",
    "iso:country":"CN",
    "name:und_x_variant":[
        "\u6d52\u5188"
    ],
    "wof:name":"Hugang",
    "wof:placetype":"locality"
},
  "geometry": {"coordinates":[115.0454,27.06151],"type":"Point"}
}