{
  "type": "Feature",
  "properties": {
    "gn:admin1_code":"02",
    "gn:asciiname":"Shangtian",
    "gn:country_code":"CN",
    "gn:dem":23,
    "gn:feature_class":"P",
    "gn:feature_code":"PPLA4",
    "gn:name":"Shangtian",
    "gn:population":0,
    "gn:timezone":"Asia/Shanghai",
    "iso:country":"CN",
    "name:und_x_variant":[
        "Shang-t\u2019ien-fan",
        "Shang-t\u2019ien-fan-shih",
        "Shangtianfang",
        "Shangtian",
        "\u5c1a\u7530",
        "Shangtian Zhen",
        "\u5c1a\u7530\u9547"
    ],
    "name:zho_x_preferred":[
        "\u5c1a\u7530"
    ],
    "name:zho_x_variant":[
        "\u5c1a\u7530\u9547"
    ],
    "wof:name":"Shangtian",
    "wof:placetype":"locality"
},
  "geometry": {"coordinates":[121.405,29.6175],"type":"Point"}
}