{
  "type": "Feature",
  "properties": {
    "gn:admin1_code":"15.0",
    "gn:asciiname":"Zhoujiamen",
    "gn:country_code":"CN",
    "gn:dem":2390,
    "gn:feature_class":"P",
    "gn:feature_code":"PPL",
    "gn:name":"Zhoujiamen",
    "gn:population":0,
    "gn:timezone":"Asia/Shanghai",
    "iso:country":"CN",
    "name:und_x_variant":[
        "\u5468\u5bb6\u95e8"
    ],
    "wof:name":"Zhoujiamen",
    "wof:placetype":"locality"
},
  "geometry": {"coordinates":[104.32594,34.72142],"type":"Point"}
}