{
  "type": "Feature",
  "properties": {
    "gn:admin1_code":"2",
    "gn:asciiname":"Wanyao",
    "gn:country_code":"CN",
    "gn:dem":118,
    "gn:feature_class":"P",
    "gn:feature_code":"PPL",
    "gn:name":"Wanyao",
    "gn:population":0,
    "gn:timezone":"Asia/Shanghai",
    "iso:country":"CN",
    "name:zho_x_preferred":[
        "\u7897\u7a91"
    ],
    "wof:name":"Wanyao",
    "wof:placetype":"locality"
},
  "geometry": {"coordinates":[118.66052999999999,28.68949000000001],"type":"Point"}
}