{
  "type": "Feature",
  "properties": {
    "gn:admin1_code":"11.0",
    "gn:asciiname":"Fengmujing",
    "gn:country_code":"CN",
    "gn:dem":245,
    "gn:feature_class":"P",
    "gn:feature_code":"PPL",
    "gn:name":"Fengmujing",
    "gn:population":0,
    "gn:timezone":"Asia/Shanghai",
    "iso:country":"CN",
    "name:zho_x_preferred":[
        "\u67ab\u6728\u4e95"
    ],
    "wof:name":"Fengmujing",
    "wof:placetype":"locality"
},
  "geometry": {"coordinates":[111.52451000000001,26.69876],"type":"Point"}
}