{
  "type": "Feature",
  "properties": {
    "gn:admin1_code":"11.0",
    "gn:asciiname":"Chashuxia",
    "gn:country_code":"CN",
    "gn:dem":192,
    "gn:feature_class":"P",
    "gn:feature_code":"PPL",
    "gn:name":"Chashuxia",
    "gn:population":0,
    "gn:timezone":"Asia/Shanghai",
    "iso:country":"CN",
    "name:zho_x_preferred":[
        "\u69ce\u6811\u4e0b"
    ],
    "wof:name":"Chashuxia",
    "wof:placetype":"locality"
},
  "geometry": {"coordinates":[113.27903000000001,26.52265],"type":"Point"}
}