{
  "type": "Feature",
  "properties": {
    "gn:admin1_code":"30.0",
    "gn:asciiname":"Huangshikeng",
    "gn:country_code":"CN",
    "gn:dem":238,
    "gn:feature_class":"P",
    "gn:feature_code":"PPL",
    "gn:name":"Huangshikeng",
    "gn:population":0,
    "gn:timezone":"Asia/Shanghai",
    "iso:country":"CN",
    "name:zho_x_preferred":[
        "Huangshikeng"
    ],
    "name:zho_x_variant":[
        "\u9ec4\u77f3\u5751"
    ],
    "wof:name":"Huangshikeng",
    "wof:placetype":"locality"
},
  "geometry": {"coordinates":[113.84389,25.28778],"type":"Point"}
}