{
  "type": "Feature",
  "properties": {
    "gn:admin1_code":"26.0",
    "gn:asciiname":"Washigou",
    "gn:country_code":"CN",
    "gn:dem":1258,
    "gn:feature_class":"P",
    "gn:feature_code":"PPL",
    "gn:name":"Washigou",
    "gn:population":0,
    "gn:timezone":"Asia/Shanghai",
    "iso:country":"CN",
    "name:zho_x_preferred":[
        "\u74e6\u77f3\u6c9f"
    ],
    "wof:name":"Washigou",
    "wof:placetype":"locality"
},
  "geometry": {"coordinates":[110.62958,39.16466],"type":"Point"}
}