{
  "type": "Feature",
  "properties": {
    "gn:admin1_code":"02",
    "gn:asciiname":"Fuyoucun",
    "gn:country_code":"CN",
    "gn:dem":69,
    "gn:feature_class":"P",
    "gn:feature_code":"PPL",
    "gn:name":"Fuyoucun",
    "gn:population":0,
    "gn:timezone":"Asia/Shanghai",
    "iso:country":"CN",
    "name:und_x_variant":[
        "Fuyou",
        "Fuyoucun"
    ],
    "name:zho_x_preferred":[
        "\u798f\u4f51"
    ],
    "name:zho_x_variant":[
        "\u798f\u4f51\u6751"
    ],
    "wof:name":"Fuyoucun",
    "wof:placetype":"locality"
},
  "geometry": {"coordinates":[120.77046,28.42639],"type":"Point"}
}