{
  "type": "Feature",
  "properties": {
    "gn:admin1_code":"8.0",
    "gn:asciiname":"Fengchan",
    "gn:country_code":"CN",
    "gn:dem":162,
    "gn:feature_class":"P",
    "gn:feature_code":"PPL",
    "gn:name":"Fengchan",
    "gn:population":0,
    "gn:timezone":"Asia/Shanghai",
    "iso:country":"CN",
    "name:zho_x_preferred":[
        "\u4e30\u4ea7"
    ],
    "wof:name":"Fengchan",
    "wof:placetype":"locality"
},
  "geometry": {"coordinates":[125.07335999999999,47.31715],"type":"Point"}
}