{
  "type": "Feature",
  "properties": {
    "gn:admin1_code":"05",
    "gn:asciiname":"Shuanggang",
    "gn:country_code":"CN",
    "gn:dem":146,
    "gn:feature_class":"P",
    "gn:feature_code":"PPLA4",
    "gn:name":"Shuanggang",
    "gn:population":0,
    "gn:timezone":"Asia/Shanghai",
    "iso:country":"CN",
    "name:fas_x_preferred":[
        "\u0634\u0648\u0627\u0646\u06af\u0627\u0646\u06af"
    ],
    "name:und_x_variant":[
        "Shuang-kang-tzu",
        "Shuang-kang",
        "Shuanggang",
        "Shuanggang Zhen"
    ],
    "name:zho_x_preferred":[
        "\u53cc\u5c97"
    ],
    "name:zho_x_variant":[
        "\u53cc\u5c97\u9547"
    ],
    "wof:name":"Shuanggang",
    "wof:placetype":"locality"
},
  "geometry": {"coordinates":[122.92377999999999,45.10583],"type":"Point"}
}