{
  "type": "Feature",
  "properties": {
    "gn:admin1_code":"26.0",
    "gn:asciiname":"Miaobacun",
    "gn:country_code":"CN",
    "gn:dem":1026,
    "gn:feature_class":"P",
    "gn:feature_code":"PPL",
    "gn:name":"Miaobacun",
    "gn:population":0,
    "gn:timezone":"Asia/Shanghai",
    "iso:country":"CN",
    "name:und_x_variant":[
        "\u5e99\u575d\u6751"
    ],
    "wof:name":"Miaobacun",
    "wof:placetype":"locality"
},
  "geometry": {"coordinates":[107.75445999999999,33.52796],"type":"Point"}
}