{
  "type": "Feature",
  "properties": {
    "gn:admin1_code":"8.0",
    "gn:asciiname":"Shiliugongli",
    "gn:country_code":"CN",
    "gn:dem":877,
    "gn:feature_class":"P",
    "gn:feature_code":"PPL",
    "gn:name":"Shiliugongli",
    "gn:population":0,
    "gn:timezone":"Asia/Shanghai",
    "iso:country":"CN",
    "name:zho_x_preferred":[
        "\u5341\u516d\u516c\u91cc"
    ],
    "wof:name":"Shiliugongli",
    "wof:placetype":"locality"
},
  "geometry": {"coordinates":[129.21392,45.31237],"type":"Point"}
}