{
  "type": "Feature",
  "properties": {
    "gn:admin1_code":"19.0",
    "gn:asciiname":"Nangouli",
    "gn:country_code":"CN",
    "gn:dem":89,
    "gn:feature_class":"P",
    "gn:feature_code":"PPL",
    "gn:name":"Nangouli",
    "gn:population":0,
    "gn:timezone":"Asia/Shanghai",
    "iso:country":"CN",
    "name:und_x_variant":[
        "\u5357\u6c9f\u91cc"
    ],
    "wof:name":"Nangouli",
    "wof:placetype":"locality"
},
  "geometry": {"coordinates":[122.986,40.9978],"type":"Point"}
}