{
  "type": "Feature",
  "properties": {
    "gn:admin1_code":"3.0",
    "gn:asciiname":"Longxiyuan",
    "gn:country_code":"CN",
    "gn:dem":374,
    "gn:feature_class":"P",
    "gn:feature_code":"PPL",
    "gn:name":"Longxiyuan",
    "gn:population":0,
    "gn:timezone":"Asia/Shanghai",
    "iso:country":"CN",
    "name:zho_x_preferred":[
        "\u5784\u897f\u6e90"
    ],
    "wof:name":"Longxiyuan",
    "wof:placetype":"locality"
},
  "geometry": {"coordinates":[117.96719,28.11029000000001],"type":"Point"}
}