{
  "type": "Feature",
  "properties": {
    "gn:admin1_code":"29.0",
    "gn:asciiname":"Mandao",
    "gn:country_code":"CN",
    "gn:dem":1209,
    "gn:feature_class":"P",
    "gn:feature_code":"PPL",
    "gn:name":"Mandao",
    "gn:population":0,
    "gn:timezone":"Asia/Shanghai",
    "iso:country":"CN",
    "name:zho_x_preferred":[
        "\u66fc\u5012"
    ],
    "wof:name":"Mandao",
    "wof:placetype":"locality"
},
  "geometry": {"coordinates":[100.345,21.9713],"type":"Point"}
}