{
  "type": "Feature",
  "properties": {
    "gn:admin1_code":"4.0",
    "gn:asciiname":"Hatuogou",
    "gn:country_code":"CN",
    "gn:dem":2,
    "gn:feature_class":"P",
    "gn:feature_code":"PPL",
    "gn:name":"Hatuogou",
    "gn:population":0,
    "gn:timezone":"Asia/Shanghai",
    "iso:country":"CN",
    "name:zho_x_preferred":[
        "\u86e4\u62d6\u6c9f"
    ],
    "wof:name":"Hatuogou",
    "wof:placetype":"locality"
},
  "geometry": {"coordinates":[119.41978,33.26425],"type":"Point"}
}