{
  "type": "Feature",
  "properties": {
    "gn:admin1_code":"25",
    "gn:asciiname":"Chenyu",
    "gn:country_code":"CN",
    "gn:dem":95,
    "gn:feature_class":"P",
    "gn:feature_code":"PPL",
    "gn:name":"Chenyu",
    "gn:population":0,
    "gn:timezone":"Asia/Shanghai",
    "iso:country":"CN",
    "name:zho_x_preferred":[
        "\u9648\u5cea"
    ],
    "wof:name":"Chenyu",
    "wof:placetype":"locality"
},
  "geometry": {"coordinates":[119.15900000000001,35.9431],"type":"Point"}
}