{
  "type": "Feature",
  "properties": {
    "gn:admin1_code":"14.0",
    "gn:asciiname":"Huliguanggua",
    "gn:country_code":"CN",
    "gn:dem":4461,
    "gn:feature_class":"P",
    "gn:feature_code":"PPL",
    "gn:name":"Huliguanggua",
    "gn:population":0,
    "gn:timezone":"Asia/Urumqi",
    "iso:country":"CN",
    "name:zho_x_preferred":[
        "\u80e1\u91cc\u5149\u522e"
    ],
    "wof:name":"Huliguanggua",
    "wof:placetype":"locality"
},
  "geometry": {"coordinates":[93.23546,30.76148],"type":"Point"}
}