{
  "type": "Feature",
  "properties": {
    "gn:admin1_code":"29.0",
    "gn:asciiname":"Wata",
    "gn:country_code":"CN",
    "gn:dem":1963,
    "gn:feature_class":"P",
    "gn:feature_code":"PPL",
    "gn:name":"Wata",
    "gn:population":0,
    "gn:timezone":"Asia/Shanghai",
    "iso:country":"CN",
    "name:zho_x_preferred":[
        "\u74e6\u5854"
    ],
    "wof:name":"Wata",
    "wof:placetype":"locality"
},
  "geometry": {"coordinates":[99.7354,27.1461],"type":"Point"}
}