{
  "type": "Feature",
  "properties": {
    "gn:admin1_code":"02",
    "gn:asciiname":"Lishanjicun",
    "gn:country_code":"CN",
    "gn:dem":265,
    "gn:feature_class":"P",
    "gn:feature_code":"PPL",
    "gn:name":"Lishanjicun",
    "gn:population":0,
    "gn:timezone":"Asia/Shanghai",
    "iso:country":"CN",
    "name:und_x_variant":[
        "Li-shan-chi",
        "Lishanji",
        "\u91cc\u5c71\u5b63",
        "Lishanjicun"
    ],
    "name:zho_x_preferred":[
        "\u91cc\u5c71\u5b63"
    ],
    "name:zho_x_variant":[
        "\u91cc\u5c71\u5b63\u6751"
    ],
    "wof:name":"Lishanjicun",
    "wof:placetype":"locality"
},
  "geometry": {"coordinates":[121.31753999999999,29.12222],"type":"Point"}
}