{
  "type": "Feature",
  "properties": {
    "gn:admin1_code":"8.0",
    "gn:asciiname":"Hexitun",
    "gn:country_code":"CN",
    "gn:dem":266,
    "gn:feature_class":"P",
    "gn:feature_code":"PPL",
    "gn:name":"Hexitun",
    "gn:population":0,
    "gn:timezone":"Asia/Shanghai",
    "iso:country":"CN",
    "name:zho_x_preferred":[
        "\u6cb3\u897f\u5c6f"
    ],
    "wof:name":"Hexitun",
    "wof:placetype":"locality"
},
  "geometry": {"coordinates":[122.67368999999999,47.54275],"type":"Point"}
}