{
  "type": "Feature",
  "properties": {
    "gn:admin1_code":"25",
    "gn:asciiname":"Kouhouwangjia",
    "gn:country_code":"CN",
    "gn:dem":167,
    "gn:feature_class":"P",
    "gn:feature_code":"PPL",
    "gn:name":"Kouhouwangjia",
    "gn:population":0,
    "gn:timezone":"Asia/Shanghai",
    "iso:country":"CN",
    "name:zho_x_preferred":[
        "\u53e3\u540e\u738b\u5bb6"
    ],
    "wof:name":"Kouhouwangjia",
    "wof:placetype":"locality"
},
  "geometry": {"coordinates":[120.428,37.4935],"type":"Point"}
}