{
  "type": "Feature",
  "properties": {
    "gn:admin1_code":"30.0",
    "gn:asciiname":"Huanghua",
    "gn:country_code":"CN",
    "gn:dem":85,
    "gn:feature_class":"P",
    "gn:feature_code":"PPL",
    "gn:name":"Huanghua",
    "gn:population":0,
    "gn:timezone":"Asia/Shanghai",
    "iso:country":"CN",
    "name:ara_x_preferred":[
        "\u0647\u0648\u0627\u0646\u063a\u0648\u0627"
    ],
    "name:deu_x_preferred":[
        "Huanghua"
    ],
    "name:fra_x_preferred":[
        "Huanghua"
    ],
    "name:ita_x_preferred":[
        "Huanghua"
    ],
    "name:jpn_x_preferred":[
        "\u9ec4\u30ab\u5e02"
    ],
    "name:kik_x_preferred":[
        "Huanghua"
    ],
    "name:kor_x_preferred":[
        "\ud669\ud654\uc2dc"
    ],
    "name:nor_x_preferred":[
        "Huanghua"
    ],
    "name:pam_x_preferred":[
        "Huanghua"
    ],
    "name:pol_x_preferred":[
        "Huanghua"
    ],
    "name:rus_x_preferred":[
        "\u0425\u0443\u0430\u043d\u0445\u0443\u0430"
    ],
    "name:swe_x_preferred":[
        "Huanghua"
    ],
    "name:urd_x_preferred":[
        "\u06c1\u0648\u0627\u0646\u06af\u06c1\u0648\u0627"
    ],
    "name:vie_x_preferred":[
        "Ho\u00e0ng Hoa"
    ],
    "name:war_x_preferred":[
        "Huanghua"
    ],
    "name:zho_x_preferred":[
        "\u9ec4\u82b1"
    ],
    "name:zho_x_variant":[
        "\u9ec4\u9a85\u5e02"
    ],
    "wof:name":"Huanghua",
    "wof:placetype":"locality"
},
  "geometry": {"coordinates":[112.06887999999999,24.09287],"type":"Point"}
}