{
  "type": "Feature",
  "properties": {
    "gn:admin1_code":"19.0",
    "gn:asciiname":"Huoshilingzi",
    "gn:country_code":"CN",
    "gn:dem":256,
    "gn:feature_class":"P",
    "gn:feature_code":"PPL",
    "gn:name":"Huoshilingzi",
    "gn:population":0,
    "gn:timezone":"Asia/Shanghai",
    "iso:country":"CN",
    "name:und_x_variant":[
        "\u706b\u77f3\u5cad\u5b50"
    ],
    "name:zho_x_preferred":[
        "\u706b\u77f3\u5cad\u5b50"
    ],
    "wof:name":"Huoshilingzi",
    "wof:placetype":"locality"
},
  "geometry": {"coordinates":[121.414,42.0434],"type":"Point"}
}