{
  "type": "Feature",
  "properties": {
    "gn:admin1_code":"9.0",
    "gn:asciiname":"Ximengzhuang",
    "gn:country_code":"CN",
    "gn:dem":219,
    "gn:feature_class":"P",
    "gn:feature_code":"PPL",
    "gn:name":"Ximengzhuang",
    "gn:population":0,
    "gn:timezone":"Asia/Shanghai",
    "iso:country":"CN",
    "name:zho_x_preferred":[
        "\u897f\u5b5f\u5e84"
    ],
    "wof:name":"Ximengzhuang",
    "wof:placetype":"locality"
},
  "geometry": {"coordinates":[112.66638,34.94045999999999],"type":"Point"}
}