{
  "type": "Feature",
  "properties": {
    "gn:admin1_code":"21.0",
    "gn:asciiname":"Duanjiabu",
    "gn:country_code":"CN",
    "gn:dem":1568,
    "gn:feature_class":"P",
    "gn:feature_code":"PPL",
    "gn:name":"Duanjiabu",
    "gn:population":0,
    "gn:timezone":"Asia/Shanghai",
    "iso:country":"CN",
    "name:zho_x_preferred":[
        "\u6bb5\u5bb6\u5821"
    ],
    "wof:name":"Duanjiabu",
    "wof:placetype":"locality"
},
  "geometry": {"coordinates":[106.21642,36.18816],"type":"Point"}
}