{
  "type": "Feature",
  "properties": {
    "gn:admin1_code":"02",
    "gn:asciiname":"Fatou",
    "gn:country_code":"CN",
    "gn:dem":76,
    "gn:feature_class":"P",
    "gn:feature_code":"PPLA4",
    "gn:name":"Fatou",
    "gn:population":0,
    "gn:timezone":"Asia/Shanghai",
    "iso:country":"CN",
    "name:und_x_variant":[
        "P\u2019ai-t\u2019ou-chen",
        "Fatou Xiang",
        "Paitou",
        "Fatou",
        "\u7b4f\u5934"
    ],
    "wof:name":"Fatou",
    "wof:placetype":"locality"
},
  "geometry": {"coordinates":[119.85167,30.54639],"type":"Point"}
}