{
  "type": "Feature",
  "properties": {
    "gn:admin1_code":"24.0",
    "gn:asciiname":"Chenzhuang",
    "gn:country_code":"CN",
    "gn:dem":549,
    "gn:feature_class":"P",
    "gn:feature_code":"PPL",
    "gn:name":"Chenzhuang",
    "gn:population":0,
    "gn:timezone":"Asia/Shanghai",
    "iso:country":"CN",
    "name:ceb_x_preferred":[
        "Chenzhuang"
    ],
    "name:swe_x_preferred":[
        "Chenzhuang"
    ],
    "name:und_x_variant":[
        "\u9648\u5e84"
    ],
    "wof:name":"Chenzhuang",
    "wof:placetype":"locality"
},
  "geometry": {"coordinates":[111.52428,35.89692],"type":"Point"}
}