{
  "type": "Feature",
  "properties": {
    "gn:admin1_code":"14.0",
    "gn:asciiname":"Quziricun",
    "gn:country_code":"CN",
    "gn:dem":4584,
    "gn:feature_class":"P",
    "gn:feature_code":"PPL",
    "gn:name":"Quziricun",
    "gn:population":0,
    "gn:timezone":"Asia/Urumqi",
    "iso:country":"CN",
    "name:zho_x_preferred":[
        "\u66f2\u5b5c\u65e5\u6751"
    ],
    "wof:name":"Quziricun",
    "wof:placetype":"locality"
},
  "geometry": {"coordinates":[90.84472,32.15029000000001],"type":"Point"}
}