{
  "type": "Feature",
  "properties": {
    "gn:admin1_code":"32.0",
    "gn:asciiname":"Shangchengsi",
    "gn:country_code":"CN",
    "gn:dem":366,
    "gn:feature_class":"P",
    "gn:feature_code":"PPL",
    "gn:name":"Shangchengsi",
    "gn:population":0,
    "gn:timezone":"Asia/Shanghai",
    "iso:country":"CN",
    "name:zho_x_preferred":[
        "\u4e0a\u4e58\u5bfa"
    ],
    "wof:name":"Shangchengsi",
    "wof:placetype":"locality"
},
  "geometry": {"coordinates":[106.093,31.164],"type":"Point"}
}