{
  "type": "Feature",
  "properties": {
    "gn:admin1_code":"20",
    "gn:asciiname":"Hsiao-t'a-tzu-kou",
    "gn:country_code":"CN",
    "gn:dem":771,
    "gn:feature_class":"P",
    "gn:feature_code":"PPL",
    "gn:name":"Hsiao-t\u2019a-tzu-kou",
    "gn:population":0,
    "gn:timezone":"Asia/Shanghai",
    "iso:country":"CN",
    "wof:name":"Hsiao-t'a-tzu-kou",
    "wof:placetype":"locality"
},
  "geometry": {"coordinates":[119.09472,42.0825],"type":"Point"}
}