{
  "type": "Feature",
  "properties": {
    "gn:admin1_code":"12.0",
    "gn:asciiname":"Zhangjiachangchong",
    "gn:country_code":"CN",
    "gn:dem":45,
    "gn:feature_class":"P",
    "gn:feature_code":"PPL",
    "gn:name":"Zhangjiachangchong",
    "gn:population":0,
    "gn:timezone":"Asia/Shanghai",
    "iso:country":"CN",
    "name:zho_x_preferred":[
        "\u5f20\u5bb6\u957f\u51b2"
    ],
    "wof:name":"Zhangjiachangchong",
    "wof:placetype":"locality"
},
  "geometry": {"coordinates":[114.60393999999999,30.99824000000001],"type":"Point"}
}