{
  "type": "Feature",
  "properties": {
    "gn:admin1_code":"28",
    "gn:asciiname":"Liuxiangzhuang",
    "gn:country_code":"CN",
    "gn:dem":6,
    "gn:feature_class":"P",
    "gn:feature_code":"PPL",
    "gn:name":"Liuxiangzhuang",
    "gn:population":0,
    "gn:timezone":"Asia/Shanghai",
    "iso:country":"CN",
    "name:zho_x_preferred":[
        "\u5218\u7965\u5e84"
    ],
    "wof:name":"Liuxiangzhuang",
    "wof:placetype":"locality"
},
  "geometry": {"coordinates":[117.06604,38.74657],"type":"Point"}
}