{
  "type": "Feature",
  "properties": {
    "gn:admin1_code":"30",
    "gn:asciiname":"Guitou",
    "gn:country_code":"CN",
    "gn:dem":6,
    "gn:feature_class":"P",
    "gn:feature_code":"PPL",
    "gn:name":"Guitou",
    "gn:population":0,
    "gn:timezone":"Asia/Urumqi",
    "iso:country":"CN",
    "name:zho_x_preferred":[
        "\u9f9f\u5934"
    ],
    "wof:name":"Guitou",
    "wof:placetype":"locality"
},
  "geometry": {"coordinates":[110.42677999999999,20.99698],"type":"Point"}
}