{
  "type": "Feature",
  "properties": {
    "gn:admin1_code":"1.0",
    "gn:asciiname":"Xikou",
    "gn:country_code":"CN",
    "gn:dem":57,
    "gn:feature_class":"P",
    "gn:feature_code":"PPL",
    "gn:name":"Xikou",
    "gn:population":0,
    "gn:timezone":"Asia/Shanghai",
    "iso:country":"CN",
    "name:fas_x_preferred":[
        "\u0634\u06cc\u06a9\u0648"
    ],
    "name:ita_x_preferred":[
        "Xikou"
    ],
    "name:nor_x_preferred":[
        "Xikou"
    ],
    "name:swe_x_preferred":[
        "Xikou"
    ],
    "name:zho_x_preferred":[
        "\u6eaa\u53e3"
    ],
    "name:zho_x_variant":[
        "\u6eaa\u53e3\u9547"
    ],
    "wof:name":"Xikou",
    "wof:placetype":"locality"
},
  "geometry": {"coordinates":[118.23359000000001,30.53497],"type":"Point"}
}