{
  "type": "Feature",
  "properties": {
    "gn:country":"CN",
    "gn:fcode":"PPL",
    "gn:pop":1180,
    "iso:country":"CN",
    "name:ceb_x_preferred":[
        "Zhongfang Xian"
    ],
    "name:deu_x_preferred":[
        "Zhongfang"
    ],
    "name:fas_x_preferred":[
        "\u0634\u0647\u0631\u0633\u062a\u0627\u0646 \u0698\u0648\u0646\u06af\u0641\u0627\u0646\u06af"
    ],
    "name:jpn_x_preferred":[
        "\u4e2d\u65b9\u770c"
    ],
    "name:kor_x_preferred":[
        "\uc911\ud321\ud604"
    ],
    "name:nor_x_preferred":[
        "Zhongfang"
    ],
    "name:swe_x_preferred":[
        "Zhongfang"
    ],
    "name:unk_x_variant":[
        "Chung-fang"
    ],
    "name:vie_x_preferred":[
        "Trung Ph\u01b0\u01a1ng"
    ],
    "name:zho_x_preferred":[
        "\u4e2d\u65b9\u53bf"
    ],
    "qs:name":"Zhongfang",
    "qs:photos_9r":0,
    "qs:photos_sr":0,
    "qs:pop_sr":"3",
    "wd:wordcount":102,
    "wof:name":"Zhongfang",
    "wof:placetype":"locality",
    "wof:population":1180
},
  "geometry": {"coordinates":[119.42583,26.60083],"type":"Point"}
}