{
  "type": "Feature",
  "properties": {
    "gn:admin1_code":"26",
    "gn:asciiname":"Zhanglizhuang",
    "gn:country_code":"CN",
    "gn:dem":539,
    "gn:feature_class":"P",
    "gn:feature_code":"PPL",
    "gn:name":"Zhanglizhuang",
    "gn:population":0,
    "gn:timezone":"Asia/Shanghai",
    "iso:country":"CN",
    "name:und_x_variant":[
        "\u5f20\u674e\u5e84"
    ],
    "name:zho_x_preferred":[
        "\u5f20\u674e\u5e84"
    ],
    "wof:name":"Zhanglizhuang",
    "wof:placetype":"locality"
},
  "geometry": {"coordinates":[108.69667,34.63222],"type":"Point"}
}