{
  "type": "Feature",
  "properties": {
    "gn:admin1_code":"20",
    "gn:asciiname":"Haladaokou",
    "gn:cc2":"CN",
    "gn:country_code":"CN",
    "gn:dem":461,
    "gn:feature_class":"P",
    "gn:feature_code":"PPL",
    "gn:name":"Haladaokou",
    "gn:population":0,
    "gn:timezone":"Asia/Shanghai",
    "iso:country":"CN",
    "name:und_x_variant":[
        "Ha-la-tao-k\u2019ou",
        "Haladaokou"
    ],
    "wof:name":"Haladaokou",
    "wof:placetype":"locality"
},
  "geometry": {"coordinates":[119.48417000000001,42.57361],"type":"Point"}
}