{
  "type": "Feature",
  "properties": {
    "gn:admin1_code":"10",
    "gn:asciiname":"Xigoumen",
    "gn:country_code":"CN",
    "gn:dem":1157,
    "gn:feature_class":"P",
    "gn:feature_code":"PPL",
    "gn:name":"Xigoumen",
    "gn:population":0,
    "gn:timezone":"Asia/Shanghai",
    "iso:country":"CN",
    "name:zho_x_preferred":[
        "\u897f\u6c9f\u95e8"
    ],
    "wof:name":"Xigoumen",
    "wof:placetype":"locality"
},
  "geometry": {"coordinates":[116.39879999999999,41.49882],"type":"Point"}
}