{
  "type": "Feature",
  "properties": {
    "gn:admin1_code":"26.0",
    "gn:asciiname":"Yuanyanggou",
    "gn:country_code":"CN",
    "gn:dem":375,
    "gn:feature_class":"P",
    "gn:feature_code":"PPL",
    "gn:name":"Yuanyanggou",
    "gn:population":0,
    "gn:timezone":"Asia/Shanghai",
    "iso:country":"CN",
    "name:und_x_variant":[
        "Yuanchanggou"
    ],
    "name:zho_x_preferred":[
        "\u586c\u6768\u6c9f"
    ],
    "name:zho_x_variant":[
        "\u586c\u573a\u6c9f"
    ],
    "wof:name":"Yuanyanggou",
    "wof:placetype":"locality"
},
  "geometry": {"coordinates":[109.17376000000002,34.48963],"type":"Point"}
}