{
  "type": "Feature",
  "properties": {
    "gn:admin1_code":"29.0",
    "gn:asciiname":"Banzai",
    "gn:country_code":"CN",
    "gn:dem":1301,
    "gn:feature_class":"P",
    "gn:feature_code":"PPL",
    "gn:name":"Banzai",
    "gn:population":0,
    "gn:timezone":"Asia/Shanghai",
    "iso:country":"CN",
    "name:ara_x_preferred":[
        "\u0628\u0627\u0646\u0632\u0627\u064a"
    ],
    "name:bre_x_preferred":[
        "Banzai"
    ],
    "name:ces_x_preferred":[
        "Banzai"
    ],
    "name:deu_x_preferred":[
        "Banzai"
    ],
    "name:fin_x_preferred":[
        "Banzai"
    ],
    "name:fra_x_preferred":[
        "Banza\u00ef"
    ],
    "name:ita_x_preferred":[
        "Banzai"
    ],
    "name:jpn_x_preferred":[
        "\u30d0\u30f3\u30b6\u30a4"
    ],
    "name:rus_x_preferred":[
        "\u0411\u0430\u043d\u0437\u0430\u0439"
    ],
    "name:spa_x_preferred":[
        "Banzai"
    ],
    "name:srp_x_preferred":[
        "\u0411\u0430\u043d\u0437\u0430\u0438"
    ],
    "name:ukr_x_preferred":[
        "\u0411\u0430\u043d\u0437\u0430\u0439"
    ],
    "name:zho_x_preferred":[
        "\u677f\u683d"
    ],
    "name:zho_x_variant":[
        "Banzai"
    ],
    "wof:name":"Banzai",
    "wof:placetype":"locality"
},
  "geometry": {"coordinates":[98.1794,24.3467],"type":"Point"}
}