{
  "type": "Feature",
  "properties": {
    "gn:admin1_code":"14.0",
    "gn:asciiname":"Counugang",
    "gn:country_code":"CN",
    "gn:dem":3950,
    "gn:feature_class":"P",
    "gn:feature_code":"PPL",
    "gn:name":"Counugang",
    "gn:population":0,
    "gn:timezone":"Asia/Urumqi",
    "iso:country":"CN",
    "name:zho_x_preferred":[
        "\u51d1\u6012\u5c97"
    ],
    "wof:name":"Counugang",
    "wof:placetype":"locality"
},
  "geometry": {"coordinates":[91.73027999999999,30.06746],"type":"Point"}
}