{
  "type": "Feature",
  "properties": {
    "gn:admin1_code":"30.0",
    "gn:asciiname":"Lulan",
    "gn:country_code":"CN",
    "gn:dem":17,
    "gn:feature_class":"P",
    "gn:feature_code":"PPL",
    "gn:name":"Lulan",
    "gn:population":0,
    "gn:timezone":"Asia/Shanghai",
    "iso:country":"CN",
    "name:zho_x_preferred":[
        "\u797f\u6b04"
    ],
    "wof:name":"Lulan",
    "wof:placetype":"locality"
},
  "geometry": {"coordinates":[112.60666999999999,22.92272],"type":"Point"}
}