{
  "type": "Feature",
  "properties": {
    "gn:admin1_code":"5.0",
    "gn:asciiname":"Chagantumocun",
    "gn:country_code":"CN",
    "gn:dem":137,
    "gn:feature_class":"P",
    "gn:feature_code":"PPL",
    "gn:name":"Chagantumocun",
    "gn:population":0,
    "gn:timezone":"Asia/Shanghai",
    "iso:country":"CN",
    "name:zho_x_preferred":[
        "\u67e5\u5e72\u5410\u83ab\u6751"
    ],
    "wof:name":"Chagantumocun",
    "wof:placetype":"locality"
},
  "geometry": {"coordinates":[124.60747000000001,44.98355],"type":"Point"}
}