{
  "type": "Feature",
  "properties": {
    "gn:admin1_code":"19.0",
    "gn:asciiname":"Guanjiadiancun",
    "gn:country_code":"CN",
    "gn:dem":41,
    "gn:feature_class":"P",
    "gn:feature_code":"PPL",
    "gn:name":"Guanjiadiancun",
    "gn:population":0,
    "gn:timezone":"Asia/Shanghai",
    "iso:country":"CN",
    "name:zho_x_preferred":[
        "\u5173\u5bb6\u5e97\u6751"
    ],
    "wof:name":"Guanjiadiancun",
    "wof:placetype":"locality"
},
  "geometry": {"coordinates":[123.19499999999999,42.1357],"type":"Point"}
}