{
  "type": "Feature",
  "properties": {
    "gn:admin1_code":"13.0",
    "gn:asciiname":"Puluma'a'aizi",
    "gn:country_code":"CN",
    "gn:dem":2578,
    "gn:feature_class":"P",
    "gn:feature_code":"PPL",
    "gn:name":"Puluma\u2019a\u2019aizi",
    "gn:population":0,
    "gn:timezone":"Asia/Shanghai",
    "iso:country":"CN",
    "name:und_x_variant":[
        "Puluma A\u2019aizi"
    ],
    "name:zho_x_preferred":[
        "\u666e\u9c81\u9ebb\u963f\u57c3\u5b5c"
    ],
    "wof:name":"Puluma'a'aizi",
    "wof:placetype":"locality"
},
  "geometry": {"coordinates":[80.07356999999998,36.6268],"type":"Point"}
}