{
  "type": "Feature",
  "properties": {
    "gn:admin1_code":"18.0",
    "gn:asciiname":"Jianbaodiao",
    "gn:country_code":"CN",
    "gn:dem":814,
    "gn:feature_class":"P",
    "gn:feature_code":"PPL",
    "gn:name":"Jianbaodiao",
    "gn:population":0,
    "gn:timezone":"Asia/Shanghai",
    "iso:country":"CN",
    "name:zho_x_preferred":[
        "\u51cf\u4fdd\u6389"
    ],
    "wof:name":"Jianbaodiao",
    "wof:placetype":"locality"
},
  "geometry": {"coordinates":[108.123,26.9046],"type":"Point"}
}