{
  "type": "Feature",
  "properties": {
    "gn:admin1_code":"11.0",
    "gn:asciiname":"Xietaiwan",
    "gn:country_code":"CN",
    "gn:dem":100,
    "gn:feature_class":"P",
    "gn:feature_code":"PPL",
    "gn:name":"Xietaiwan",
    "gn:population":0,
    "gn:timezone":"Asia/Shanghai",
    "iso:country":"CN",
    "name:zho_x_preferred":[
        "\u534f\u53f0\u6e7e"
    ],
    "wof:name":"Xietaiwan",
    "wof:placetype":"locality"
},
  "geometry": {"coordinates":[113.34523,27.84399],"type":"Point"}
}