{
  "type": "Feature",
  "properties": {
    "gn:admin1_code":"29.0",
    "gn:asciiname":"Tuoliu",
    "gn:country_code":"CN",
    "gn:dem":1995,
    "gn:feature_class":"P",
    "gn:feature_code":"PPL",
    "gn:name":"Tuoliu",
    "gn:population":0,
    "gn:timezone":"Asia/Shanghai",
    "iso:country":"CN",
    "name:zho_x_preferred":[
        "\u62d6\u7559"
    ],
    "wof:name":"Tuoliu",
    "wof:placetype":"locality"
},
  "geometry": {"coordinates":[104.37,25.3961],"type":"Point"}
}