{
  "type": "Feature",
  "properties": {
    "gn:admin1_code":"12.0",
    "gn:asciiname":"Maoxizui",
    "gn:country_code":"CN",
    "gn:dem":28,
    "gn:feature_class":"P",
    "gn:feature_code":"PPL",
    "gn:name":"Maoxizui",
    "gn:population":0,
    "gn:timezone":"Asia/Shanghai",
    "iso:country":"CN",
    "name:zho_x_preferred":[
        "\u732b\u6eaa\u5480"
    ],
    "wof:name":"Maoxizui",
    "wof:placetype":"locality"
},
  "geometry": {"coordinates":[113.41240999999999,30.7369],"type":"Point"}
}