{
  "type": "Feature",
  "properties": {
    "gn:admin1_code":"11",
    "gn:asciiname":"Baiyu",
    "gn:country_code":"CN",
    "gn:dem":544,
    "gn:feature_class":"P",
    "gn:feature_code":"PPL",
    "gn:name":"Baiyu",
    "gn:population":0,
    "gn:timezone":"Asia/Shanghai",
    "iso:country":"CN",
    "name:deu_x_preferred":[
        "Baiyu"
    ],
    "wof:name":"Baiyu",
    "wof:placetype":"locality"
},
  "geometry": {"coordinates":[110.39388999999998,26.7175],"type":"Point"}
}