{
  "type": "Feature",
  "properties": {
    "gn:admin1_code":"32.0",
    "gn:asciiname":"Huajing",
    "gn:country_code":"CN",
    "gn:dem":414,
    "gn:feature_class":"P",
    "gn:feature_code":"PPL",
    "gn:name":"Huajing",
    "gn:population":0,
    "gn:timezone":"Asia/Shanghai",
    "iso:country":"CN",
    "name:wuu_x_preferred":[
        "\u534e\u6cfe\u9547"
    ],
    "name:zho_x_preferred":[
        "\u534e\u666f"
    ],
    "name:zho_x_variant":[
        "\u534e\u6cfe\u9547"
    ],
    "wof:name":"Huajing",
    "wof:placetype":"locality"
},
  "geometry": {"coordinates":[108.09958,31.5616],"type":"Point"}
}