{
  "type": "Feature",
  "properties": {
    "gn:admin1_code":"09",
    "gn:asciiname":"Gumiao",
    "gn:cc2":"CN",
    "gn:country_code":"CN",
    "gn:dem":251,
    "gn:feature_class":"P",
    "gn:feature_code":"PPL",
    "gn:name":"Gumiao",
    "gn:population":0,
    "gn:timezone":"Asia/Shanghai",
    "iso:country":"CN",
    "name:und_x_variant":[
        "Ku-miao",
        "Gumiao"
    ],
    "name:zho_x_preferred":[
        "\u56fa\u5e99"
    ],
    "wof:name":"Gumiao",
    "wof:placetype":"locality"
},
  "geometry": {"coordinates":[113.28694,32.41389],"type":"Point"}
}