{
  "type": "Feature",
  "properties": {
    "gn:admin1_code":"10",
    "gn:asciiname":"Bailagou",
    "gn:country_code":"CN",
    "gn:dem":367,
    "gn:feature_class":"P",
    "gn:feature_code":"PPL",
    "gn:name":"Bailagou",
    "gn:population":0,
    "gn:timezone":"Asia/Shanghai",
    "iso:country":"CN",
    "name:zho_x_preferred":[
        "\u67cf\u782c\u6c9f"
    ],
    "wof:name":"Bailagou",
    "wof:placetype":"locality"
},
  "geometry": {"coordinates":[117.14821000000001,40.81383],"type":"Point"}
}