{
  "type": "Feature",
  "properties": {
    "gn:admin1_code":"24.0",
    "gn:asciiname":"Nanxiaobu",
    "gn:country_code":"CN",
    "gn:dem":732,
    "gn:feature_class":"P",
    "gn:feature_code":"PPL",
    "gn:name":"Nanxiaobu",
    "gn:population":0,
    "gn:timezone":"Asia/Shanghai",
    "iso:country":"CN",
    "name:zho_x_preferred":[
        "\u5357\u5c0f\u5821"
    ],
    "wof:name":"Nanxiaobu",
    "wof:placetype":"locality"
},
  "geometry": {"coordinates":[111.89413,37.14623],"type":"Point"}
}