{
  "type": "Feature",
  "properties": {
    "gn:admin1_code":"19.0",
    "gn:asciiname":"Miaolingqian",
    "gn:country_code":"CN",
    "gn:dem":62,
    "gn:feature_class":"P",
    "gn:feature_code":"PPL",
    "gn:name":"Miaolingqian",
    "gn:population":0,
    "gn:timezone":"Asia/Shanghai",
    "iso:country":"CN",
    "name:und_x_variant":[
        "\u5e99\u5cad\u524d"
    ],
    "wof:name":"Miaolingqian",
    "wof:placetype":"locality"
},
  "geometry": {"coordinates":[123.958,40.1569],"type":"Point"}
}