{
  "type": "Feature",
  "properties": {
    "gn:admin1_code":"10",
    "gn:asciiname":"Zhaojialiang",
    "gn:country_code":"CN",
    "gn:dem":869,
    "gn:feature_class":"P",
    "gn:feature_code":"PPL",
    "gn:name":"Zhaojialiang",
    "gn:population":0,
    "gn:timezone":"Asia/Shanghai",
    "iso:country":"CN",
    "name:und_x_variant":[
        "Chao-chia-liang",
        "Zhaojialiang"
    ],
    "name:zho_x_preferred":[
        "\u8d75\u5bb6\u6881"
    ],
    "wof:name":"Zhaojialiang",
    "wof:placetype":"locality"
},
  "geometry": {"coordinates":[114.65146,40.78357000000001],"type":"Point"}
}