{
  "type": "Feature",
  "properties": {
    "gn:admin1_code":"7.0",
    "gn:asciiname":"Dongkenglong",
    "gn:country_code":"CN",
    "gn:dem":817,
    "gn:feature_class":"P",
    "gn:feature_code":"PPL",
    "gn:name":"Dongkenglong",
    "gn:population":0,
    "gn:timezone":"Asia/Shanghai",
    "iso:country":"CN",
    "name:und_x_variant":[
        "\u4e1c\u5751\u5784"
    ],
    "name:zho_x_preferred":[
        "\u4e1c\u5751\u5784"
    ],
    "wof:name":"Dongkenglong",
    "wof:placetype":"locality"
},
  "geometry": {"coordinates":[117.10328,25.60747000000001],"type":"Point"}
}