{
  "type": "Feature",
  "properties": {
    "gn:admin1_code":"12.0",
    "gn:asciiname":"Shangzhai'ao",
    "gn:country_code":"CN",
    "gn:dem":606,
    "gn:feature_class":"P",
    "gn:feature_code":"PPL",
    "gn:name":"Shangzhai\u2019ao",
    "gn:population":0,
    "gn:timezone":"Asia/Shanghai",
    "iso:country":"CN",
    "name:und_x_variant":[
        "Shangzhai\u2019ao"
    ],
    "name:zho_x_preferred":[
        "\u4e0a\u5be8\u51f9"
    ],
    "wof:name":"Shangzhai'ao",
    "wof:placetype":"locality"
},
  "geometry": {"coordinates":[110.00767999999999,31.90427],"type":"Point"}
}