{
  "type": "Feature",
  "properties": {
    "gn:admin1_code":"8.0",
    "gn:asciiname":"Xiaoshaoguo",
    "gn:country_code":"CN",
    "gn:dem":219,
    "gn:feature_class":"P",
    "gn:feature_code":"PPL",
    "gn:name":"Xiaoshaoguo",
    "gn:population":0,
    "gn:timezone":"Asia/Shanghai",
    "iso:country":"CN",
    "name:zho_x_preferred":[
        "\u5c0f\u70e7\u9505"
    ],
    "wof:name":"Xiaoshaoguo",
    "wof:placetype":"locality"
},
  "geometry": {"coordinates":[127.46099,46.54929],"type":"Point"}
}