{
  "type": "Feature",
  "properties": {
    "gn:admin1_code":"11.0",
    "gn:asciiname":"Jicunba",
    "gn:country_code":"CN",
    "gn:dem":32,
    "gn:feature_class":"P",
    "gn:feature_code":"PPL",
    "gn:name":"Jicunba",
    "gn:population":0,
    "gn:timezone":"Asia/Shanghai",
    "iso:country":"CN",
    "name:zho_x_preferred":[
        "\u79ef\u5b58\u575d"
    ],
    "wof:name":"Jicunba",
    "wof:placetype":"locality"
},
  "geometry": {"coordinates":[111.88552,28.87243],"type":"Point"}
}