{
  "type": "Feature",
  "properties": {
    "gn:admin1_code":"1.0",
    "gn:asciiname":"Dalijicun",
    "gn:country_code":"CN",
    "gn:dem":47,
    "gn:feature_class":"P",
    "gn:feature_code":"PPL",
    "gn:name":"Dalijicun",
    "gn:population":0,
    "gn:timezone":"Asia/Shanghai",
    "iso:country":"CN",
    "name:zho_x_preferred":[
        "\u5927\u674e\u96c6\u6751"
    ],
    "wof:name":"Dalijicun",
    "wof:placetype":"locality"
},
  "geometry": {"coordinates":[115.61203999999999,34.00491],"type":"Point"}
}