{
  "type": "Feature",
  "properties": {
    "gn:admin1_code":"20.0",
    "gn:asciiname":"Houwo Erqi",
    "gn:country_code":"CN",
    "gn:dem":246,
    "gn:feature_class":"P",
    "gn:feature_code":"PPL",
    "gn:name":"Houwo Erqi",
    "gn:population":0,
    "gn:timezone":"Asia/Shanghai",
    "iso:country":"CN",
    "name:zho_x_preferred":[
        "\u540e\u6c83\u5c14\u5947"
    ],
    "wof:name":"Houwo Erqi",
    "wof:placetype":"locality"
},
  "geometry": {"coordinates":[123.90156,48.77411],"type":"Point"}
}