{
  "type": "Feature",
  "properties": {
    "gn:admin1_code":"25",
    "gn:asciiname":"Xiaqiulin",
    "gn:country_code":"CN",
    "gn:dem":293,
    "gn:feature_class":"P",
    "gn:feature_code":"PPL",
    "gn:name":"Xiaqiulin",
    "gn:population":0,
    "gn:timezone":"Asia/Shanghai",
    "iso:country":"CN",
    "name:zho_x_preferred":[
        "\u4e0b\u79cb\u6797"
    ],
    "wof:name":"Xiaqiulin",
    "wof:placetype":"locality"
},
  "geometry": {"coordinates":[117.47799999999999,36.5011],"type":"Point"}
}