{
  "type": "Feature",
  "properties": {
    "gn:admin1_code":"29",
    "gn:asciiname":"Muxiang",
    "gn:country_code":"CN",
    "gn:dem":1558,
    "gn:feature_class":"P",
    "gn:feature_code":"PPL",
    "gn:name":"Muxiang",
    "gn:population":0,
    "gn:timezone":"Asia/Shanghai",
    "iso:country":"CN",
    "name:zho_x_preferred":[
        "\u6728\u76f8"
    ],
    "wof:name":"Muxiang",
    "wof:placetype":"locality"
},
  "geometry": {"coordinates":[105.098,23.3734],"type":"Point"}
}