{
  "type": "Feature",
  "properties": {
    "gn:admin1_code":"24.0",
    "gn:asciiname":"Yangjiayao",
    "gn:country_code":"CN",
    "gn:dem":1600,
    "gn:feature_class":"P",
    "gn:feature_code":"PPL",
    "gn:name":"Yangjiayao",
    "gn:population":0,
    "gn:timezone":"Asia/Shanghai",
    "iso:country":"CN",
    "name:und_x_variant":[
        "\u6768\u5bb6\u7a91"
    ],
    "wof:name":"Yangjiayao",
    "wof:placetype":"locality"
},
  "geometry": {"coordinates":[112.14752,39.60524],"type":"Point"}
}