{
  "type": "Feature",
  "properties": {
    "gn:admin1_code":"24.0",
    "gn:asciiname":"Dadadian",
    "gn:country_code":"CN",
    "gn:dem":1892,
    "gn:feature_class":"P",
    "gn:feature_code":"PPL",
    "gn:name":"Dadadian",
    "gn:population":0,
    "gn:timezone":"Asia/Shanghai",
    "iso:country":"CN",
    "name:und_x_variant":[
        "\u8fbe\u8fbe\u5e97"
    ],
    "name:zho_x_preferred":[
        "\u8fbe\u8fbe\u5e97"
    ],
    "wof:name":"Dadadian",
    "wof:placetype":"locality"
},
  "geometry": {"coordinates":[112.39798999999999,38.66225],"type":"Point"}
}