{
  "type": "Feature",
  "properties": {
    "gn:admin1_code":"5.0",
    "gn:asciiname":"Huizu Wobu",
    "gn:country_code":"CN",
    "gn:dem":128,
    "gn:feature_class":"P",
    "gn:feature_code":"PPL",
    "gn:name":"Huizu Wobu",
    "gn:population":0,
    "gn:timezone":"Asia/Shanghai",
    "iso:country":"CN",
    "name:zho_x_preferred":[
        "\u56de\u65cf\u7a9d\u5821"
    ],
    "wof:name":"Huizu Wobu",
    "wof:placetype":"locality"
},
  "geometry": {"coordinates":[124.76613999999999,45.38556],"type":"Point"}
}