{
  "type": "Feature",
  "properties": {
    "gn:admin1_code":"2.0",
    "gn:asciiname":"Yaojiaqiao",
    "gn:country_code":"CN",
    "gn:dem":6,
    "gn:feature_class":"P",
    "gn:feature_code":"PPL",
    "gn:name":"Yaojiaqiao",
    "gn:population":0,
    "gn:timezone":"Asia/Shanghai",
    "iso:country":"CN",
    "name:und_x_variant":[
        "\u59da\u5bb6\u6865"
    ],
    "name:zho_x_preferred":[
        "Yaojiaqiao"
    ],
    "wof:name":"Yaojiaqiao",
    "wof:placetype":"locality"
},
  "geometry": {"coordinates":[119.83704,30.98826],"type":"Point"}
}