{
  "type": "Feature",
  "properties": {
    "gn:admin1_code":"9.0",
    "gn:asciiname":"Baiguoshu",
    "gn:country_code":"CN",
    "gn:dem":1110,
    "gn:feature_class":"P",
    "gn:feature_code":"PPL",
    "gn:name":"Baiguoshu",
    "gn:population":0,
    "gn:timezone":"Asia/Shanghai",
    "iso:country":"CN",
    "name:und_x_variant":[
        "\u767d\u679c\u6811",
        "Baiguoshu"
    ],
    "wof:name":"Baiguoshu",
    "wof:placetype":"locality"
},
  "geometry": {"coordinates":[112.20242,33.74932],"type":"Point"}
}