{
  "type": "Feature",
  "properties": {
    "gn:admin1_code":"01",
    "gn:asciiname":"Baidafan",
    "gn:cc2":"CN",
    "gn:country_code":"CN",
    "gn:dem":114,
    "gn:feature_class":"P",
    "gn:feature_code":"PPL",
    "gn:name":"Baidafan",
    "gn:population":0,
    "gn:timezone":"Asia/Shanghai",
    "iso:country":"CN",
    "name:und_x_variant":[
        "Pai-ta",
        "Pai-f\u2019a-fan",
        "Pai-ta-fan",
        "Baidafan"
    ],
    "wof:name":"Baidafan",
    "wof:placetype":"locality"
},
  "geometry": {"coordinates":[116.03694,31.71556],"type":"Point"}
}