{
  "type": "Feature",
  "properties": {
    "gn:admin1_code":"5.0",
    "gn:asciiname":"Sujiatangzi",
    "gn:country_code":"CN",
    "gn:dem":520,
    "gn:feature_class":"P",
    "gn:feature_code":"PPL",
    "gn:name":"Sujiatangzi",
    "gn:population":0,
    "gn:timezone":"Asia/Shanghai",
    "iso:country":"CN",
    "name:und_x_variant":[
        "\u82cf\u5bb6\u8d9f\u5b50"
    ],
    "wof:name":"Sujiatangzi",
    "wof:placetype":"locality"
},
  "geometry": {"coordinates":[126.03792,41.97952],"type":"Point"}
}