{
  "type": "Feature",
  "properties": {
    "gn:admin1_code":"19",
    "gn:asciiname":"Nandianzi",
    "gn:country_code":"CN",
    "gn:dem":262,
    "gn:feature_class":"P",
    "gn:feature_code":"PPLA4",
    "gn:name":"Nandianzi",
    "gn:population":0,
    "gn:timezone":"Asia/Shanghai",
    "iso:country":"CN",
    "name:und_x_variant":[
        "Nan-tien",
        "Nan-tien-tzu",
        "Nandianzi Zhen",
        "Nandian",
        "Nandianzi",
        "\u5357\u7538\u5b50",
        "Goukou",
        "\u5357\u7538\u5b50\u9547",
        "\u6c9f\u53e3"
    ],
    "wof:name":"Nandianzi",
    "wof:placetype":"locality"
},
  "geometry": {"coordinates":[124.37024,41.28177],"type":"Point"}
}