{
  "type": "Feature",
  "properties": {
    "gn:admin1_code":"18.0",
    "gn:asciiname":"Baishui",
    "gn:country_code":"CN",
    "gn:dem":1132,
    "gn:feature_class":"P",
    "gn:feature_code":"PPL",
    "gn:name":"Baishui",
    "gn:population":0,
    "gn:timezone":"Asia/Shanghai",
    "iso:country":"CN",
    "name:deu_x_preferred":[
        "Baishui"
    ],
    "name:kor_x_preferred":[
        "\ubc14\uc774\uc218\uc774"
    ],
    "name:zho_x_preferred":[
        "\u767d\u6c34"
    ],
    "wof:name":"Baishui",
    "wof:placetype":"locality"
},
  "geometry": {"coordinates":[105.09999999999999,25.9067],"type":"Point"}
}