{
  "type": "Feature",
  "properties": {
    "gn:admin1_code":"5.0",
    "gn:asciiname":"Shaojiayao Erdui Wopeng",
    "gn:country_code":"CN",
    "gn:dem":169,
    "gn:feature_class":"P",
    "gn:feature_code":"PPLF",
    "gn:name":"Shaojiayao Erdui Wopeng",
    "gn:population":0,
    "gn:timezone":"Asia/Shanghai",
    "iso:country":"CN",
    "name:zho_x_preferred":[
        "\u90b5\u5bb6\u7a91\u4e8c\u961f\u7a9d\u68da"
    ],
    "wof:name":"Shaojiayao Erdui Wopeng",
    "wof:placetype":"locality"
},
  "geometry": {"coordinates":[122.1572,44.58303],"type":"Point"}
}