{
  "type": "Feature",
  "properties": {
    "gn:admin1_code":"07",
    "gn:asciiname":"Changlingxia",
    "gn:country_code":"CN",
    "gn:dem":430,
    "gn:feature_class":"P",
    "gn:feature_code":"PPL",
    "gn:name":"Changlingxia",
    "gn:population":0,
    "gn:timezone":"Asia/Shanghai",
    "iso:country":"CN",
    "name:zho_x_preferred":[
        "\u957f\u5cad\u4e0b"
    ],
    "wof:name":"Changlingxia",
    "wof:placetype":"locality"
},
  "geometry": {"coordinates":[116.89276,24.57544],"type":"Point"}
}