{
  "type": "Feature",
  "properties": {
    "gn:admin1_code":"9.0",
    "gn:asciiname":"Nanhe",
    "gn:country_code":"CN",
    "gn:dem":313,
    "gn:feature_class":"P",
    "gn:feature_code":"PPL",
    "gn:name":"Nanhe",
    "gn:population":0,
    "gn:timezone":"Asia/Shanghai",
    "iso:country":"CN",
    "name:deu_x_preferred":[
        "Nanhe"
    ],
    "name:fra_x_preferred":[
        "Nanhe"
    ],
    "name:und_x_variant":[
        "\u5357\u6cb3"
    ],
    "wof:name":"Nanhe",
    "wof:placetype":"locality"
},
  "geometry": {"coordinates":[112.15466000000001,33.43917],"type":"Point"}
}