{
  "type": "Feature",
  "properties": {
    "gn:admin1_code":"11.0",
    "gn:asciiname":"Mashiyu",
    "gn:country_code":"CN",
    "gn:dem":124,
    "gn:feature_class":"P",
    "gn:feature_code":"PPL",
    "gn:name":"Mashiyu",
    "gn:population":0,
    "gn:timezone":"Asia/Shanghai",
    "iso:country":"CN",
    "name:und_x_variant":[
        "\u9a6c\u5e08\u5809"
    ],
    "wof:name":"Mashiyu",
    "wof:placetype":"locality"
},
  "geometry": {"coordinates":[111.06220999999999,29.20279],"type":"Point"}
}