{
  "type": "Feature",
  "properties": {
    "gn:admin1_code":"11.0",
    "gn:asciiname":"Shaoxikou",
    "gn:country_code":"CN",
    "gn:dem":371,
    "gn:feature_class":"P",
    "gn:feature_code":"PPL",
    "gn:name":"Shaoxikou",
    "gn:population":0,
    "gn:timezone":"Asia/Shanghai",
    "iso:country":"CN",
    "name:zho_x_preferred":[
        "\u54e8\u6eaa\u53e3"
    ],
    "wof:name":"Shaoxikou",
    "wof:placetype":"locality"
},
  "geometry": {"coordinates":[110.19685,26.63664],"type":"Point"}
}