{
  "type": "Feature",
  "properties": {
    "gn:admin1_code":"10.0",
    "gn:asciiname":"Haowangli",
    "gn:country_code":"CN",
    "gn:dem":29,
    "gn:feature_class":"P",
    "gn:feature_code":"PPL",
    "gn:name":"Haowangli",
    "gn:population":0,
    "gn:timezone":"Asia/Shanghai",
    "iso:country":"CN",
    "name:zho_x_preferred":[
        "\u90dd\u738b\u529b"
    ],
    "wof:name":"Haowangli",
    "wof:placetype":"locality"
},
  "geometry": {"coordinates":[115.402,38.6254],"type":"Point"}
}