{
  "type": "Feature",
  "properties": {
    "gn:admin1_code":"14.0",
    "gn:asciiname":"Bari'ake",
    "gn:country_code":"CN",
    "gn:dem":4154,
    "gn:feature_class":"P",
    "gn:feature_code":"PPL",
    "gn:name":"Bari\u2019ake",
    "gn:population":0,
    "gn:timezone":"Asia/Urumqi",
    "iso:country":"CN",
    "name:und_x_variant":[
        "Bari\u2019ake"
    ],
    "name:zho_x_preferred":[
        "\u628a\u65e5\u963f\u53ef"
    ],
    "wof:name":"Bari'ake",
    "wof:placetype":"locality"
},
  "geometry": {"coordinates":[97.59542,32.01411],"type":"Point"}
}