{
  "type": "Feature",
  "properties": {
    "gn:admin1_code":"33.0",
    "gn:asciiname":"Qinglong",
    "gn:country_code":"CN",
    "gn:dem":911,
    "gn:feature_class":"P",
    "gn:feature_code":"PPLA4",
    "gn:name":"Qinglong",
    "gn:population":0,
    "gn:timezone":"Asia/Shanghai",
    "iso:country":"CN",
    "name:ceb_x_preferred":[
        "Qinglong"
    ],
    "name:deu_x_preferred":[
        "Qinglong"
    ],
    "name:fra_x_preferred":[
        "Qinglong"
    ],
    "name:jpn_x_preferred":[
        "\u9752\u7adc"
    ],
    "name:kor_x_preferred":[
        "\uccad\ub8e1"
    ],
    "name:nor_x_preferred":[
        "Qinglong"
    ],
    "name:swe_x_preferred":[
        "Qinglong"
    ],
    "name:und_x_variant":[
        "Qinglong Zhen"
    ],
    "name:vie_x_preferred":[
        "Thanh Long"
    ],
    "name:zho_x_preferred":[
        "\u9752\u9f99"
    ],
    "name:zho_x_variant":[
        "\u9752\u9f99\u9547"
    ],
    "wof:name":"Qinglong",
    "wof:placetype":"locality"
},
  "geometry": {"coordinates":[109.25641,30.77977000000001],"type":"Point"}
}