{
  "type": "Feature",
  "properties": {
    "gn:admin1_code":"30.0",
    "gn:asciiname":"Zhongxin",
    "gn:country_code":"CN",
    "gn:dem":179,
    "gn:feature_class":"P",
    "gn:feature_code":"PPL",
    "gn:name":"Zhongxin",
    "gn:population":0,
    "gn:timezone":"Asia/Shanghai",
    "iso:country":"CN",
    "name:zho_x_preferred":[
        "Zhongxin"
    ],
    "name:zho_x_variant":[
        "\u4e2d\u5fc3"
    ],
    "wof:name":"Zhongxin",
    "wof:placetype":"locality"
},
  "geometry": {"coordinates":[115.33360999999999,24.22972],"type":"Point"}
}