{
  "type": "Feature",
  "properties": {
    "gn:admin1_code":"32.0",
    "gn:asciiname":"Zouma",
    "gn:country_code":"CN",
    "gn:dem":297,
    "gn:feature_class":"P",
    "gn:feature_code":"PPL",
    "gn:name":"Zouma",
    "gn:population":0,
    "gn:timezone":"Asia/Shanghai",
    "iso:country":"CN",
    "name:zho_x_preferred":[
        "\u8d70\u9a6c"
    ],
    "wof:name":"Zouma",
    "wof:placetype":"locality"
},
  "geometry": {"coordinates":[106.23632000000001,30.80612],"type":"Point"}
}