{
  "type": "Feature",
  "properties": {
    "gn:admin1_code":"18",
    "gn:asciiname":"Yaotang",
    "gn:country_code":"CN",
    "gn:dem":1417,
    "gn:feature_class":"P",
    "gn:feature_code":"PPL",
    "gn:name":"Yaotang",
    "gn:population":0,
    "gn:timezone":"Asia/Shanghai",
    "iso:country":"CN",
    "name:und_x_variant":[
        "Metang",
        "Yaotang"
    ],
    "name:zho_x_preferred":[
        "\u4e48\u5858"
    ],
    "wof:name":"Yaotang",
    "wof:placetype":"locality"
},
  "geometry": {"coordinates":[105.495,27.2276],"type":"Point"}
}