{
  "type": "Feature",
  "properties": {
    "gn:admin1_code":"1.0",
    "gn:asciiname":"Luwancun",
    "gn:country_code":"CN",
    "gn:dem":32,
    "gn:feature_class":"P",
    "gn:feature_code":"PPL",
    "gn:name":"Luwancun",
    "gn:population":0,
    "gn:timezone":"Asia/Shanghai",
    "iso:country":"CN",
    "name:zho_x_preferred":[
        "\u9646\u6e7e\u6751"
    ],
    "wof:name":"Luwancun",
    "wof:placetype":"locality"
},
  "geometry": {"coordinates":[116.36807,33.69822],"type":"Point"}
}