{
  "type": "Feature",
  "properties": {
    "gn:admin1_code":"32.0",
    "gn:asciiname":"Dangan",
    "gn:country_code":"CN",
    "gn:dem":3228,
    "gn:feature_class":"P",
    "gn:feature_code":"PPL",
    "gn:name":"Dangan",
    "gn:population":0,
    "gn:timezone":"Asia/Shanghai",
    "iso:country":"CN",
    "name:zho_x_preferred":[
        "\u4e39\u5e72"
    ],
    "wof:name":"Dangan",
    "wof:placetype":"locality"
},
  "geometry": {"coordinates":[102.126,31.0741],"type":"Point"}
}