{
  "type": "Feature",
  "properties": {
    "gn:admin1_code":"32.0",
    "gn:asciiname":"Boliege",
    "gn:country_code":"CN",
    "gn:dem":2641,
    "gn:feature_class":"P",
    "gn:feature_code":"PPL",
    "gn:name":"Boliege",
    "gn:population":0,
    "gn:timezone":"Asia/Shanghai",
    "iso:country":"CN",
    "name:zho_x_preferred":[
        "\u535a\u5217\u683c"
    ],
    "wof:name":"Boliege",
    "wof:placetype":"locality"
},
  "geometry": {"coordinates":[102.622,27.9495],"type":"Point"}
}