{
  "type": "Feature",
  "properties": {
    "gn:admin1_code":"3.0",
    "gn:asciiname":"Yaokeng",
    "gn:country_code":"CN",
    "gn:dem":289,
    "gn:feature_class":"P",
    "gn:feature_code":"PPL",
    "gn:name":"Yaokeng",
    "gn:population":0,
    "gn:timezone":"Asia/Shanghai",
    "iso:country":"CN",
    "name:und_x_variant":[
        "\u7476\u5751"
    ],
    "wof:name":"Yaokeng",
    "wof:placetype":"locality"
},
  "geometry": {"coordinates":[116.11002999999999,27.06792],"type":"Point"}
}