{
  "type": "Feature",
  "properties": {
    "gn:admin1_code":"19.0",
    "gn:asciiname":"Housanchazi",
    "gn:country_code":"CN",
    "gn:dem":5,
    "gn:feature_class":"P",
    "gn:feature_code":"PPL",
    "gn:name":"Housanchazi",
    "gn:population":0,
    "gn:timezone":"Asia/Shanghai",
    "iso:country":"CN",
    "name:und_x_variant":[
        "\u540e\u4e09\u5c94\u5b50"
    ],
    "name:zho_x_preferred":[
        "\u540e\u4e09\u5c94\u5b50"
    ],
    "wof:name":"Housanchazi",
    "wof:placetype":"locality"
},
  "geometry": {"coordinates":[122.42095,40.63143],"type":"Point"}
}