{
  "type": "Feature",
  "properties": {
    "gn:admin1_code":"30",
    "gn:asciiname":"Zhangyucun",
    "gn:country_code":"CN",
    "gn:dem":39,
    "gn:feature_class":"P",
    "gn:feature_code":"PPL",
    "gn:name":"Zhangyucun",
    "gn:population":0,
    "gn:timezone":"Asia/Urumqi",
    "iso:country":"CN",
    "wof:name":"Zhangyucun",
    "wof:placetype":"locality"
},
  "geometry": {"coordinates":[111.16056,21.75972],"type":"Point"}
}