{
  "type": "Feature",
  "properties": {
    "gn:admin1_code":"04",
    "gn:asciiname":"Tianfu",
    "gn:country_code":"CN",
    "gn:dem":2,
    "gn:feature_class":"P",
    "gn:feature_code":"PPL",
    "gn:name":"Tianfu",
    "gn:population":0,
    "gn:timezone":"Asia/Shanghai",
    "iso:country":"CN",
    "name:und_x_variant":[
        "T\u2019ien-fu-chen",
        "Tianfu"
    ],
    "name:zho_x_preferred":[
        "\u5929\u798f"
    ],
    "wof:name":"Tianfu",
    "wof:placetype":"locality"
},
  "geometry": {"coordinates":[120.61573,31.9454],"type":"Point"}
}