{
  "type": "Feature",
  "properties": {
    "gn:admin1_code":"18.0",
    "gn:asciiname":"Jida",
    "gn:country_code":"CN",
    "gn:dem":585,
    "gn:feature_class":"P",
    "gn:feature_code":"PPL",
    "gn:name":"Jida",
    "gn:population":0,
    "gn:timezone":"Asia/Shanghai",
    "iso:country":"CN",
    "name:zho_x_preferred":[
        "\u5df1\u6253"
    ],
    "wof:name":"Jida",
    "wof:placetype":"locality"
},
  "geometry": {"coordinates":[109.014,25.8467],"type":"Point"}
}