{
  "type": "Feature",
  "properties": {
    "gn:admin1_code":"14.0",
    "gn:asciiname":"Kangzha",
    "gn:country_code":"CN",
    "gn:dem":4378,
    "gn:feature_class":"P",
    "gn:feature_code":"PPL",
    "gn:name":"Kangzha",
    "gn:population":0,
    "gn:timezone":"Asia/Urumqi",
    "iso:country":"CN",
    "name:zho_x_preferred":[
        "\u5eb7\u70b8"
    ],
    "wof:name":"Kangzha",
    "wof:placetype":"locality"
},
  "geometry": {"coordinates":[92.85029,31.40405],"type":"Point"}
}