{
  "type": "Feature",
  "properties": {
    "gn:admin1_code":"25",
    "gn:asciiname":"Dongguozhongcun",
    "gn:country_code":"CN",
    "gn:dem":45,
    "gn:feature_class":"P",
    "gn:feature_code":"PPL",
    "gn:name":"Dongguozhongcun",
    "gn:population":0,
    "gn:timezone":"Asia/Shanghai",
    "iso:country":"CN",
    "name:zho_x_preferred":[
        "\u4e1c\u90ed\u4e2d\u6751"
    ],
    "wof:name":"Dongguozhongcun",
    "wof:placetype":"locality"
},
  "geometry": {"coordinates":[116.84999999999999,35.2435],"type":"Point"}
}