{
  "type": "Feature",
  "properties": {
    "gn:admin1_code":"11",
    "gn:asciiname":"Taoziyuan",
    "gn:country_code":"CN",
    "gn:dem":598,
    "gn:feature_class":"P",
    "gn:feature_code":"PPL",
    "gn:name":"Taoziyuan",
    "gn:population":0,
    "gn:timezone":"Asia/Shanghai",
    "iso:country":"CN",
    "name:zho_x_preferred":[
        "\u6843\u5b50\u5143"
    ],
    "wof:name":"Taoziyuan",
    "wof:placetype":"locality"
},
  "geometry": {"coordinates":[112.20363999999999,26.23812],"type":"Point"}
}