{
  "type": "Feature",
  "properties": {
    "gn:admin1_code":"5.0",
    "gn:asciiname":"Fanrong",
    "gn:country_code":"CN",
    "gn:dem":364,
    "gn:feature_class":"P",
    "gn:feature_code":"PPL",
    "gn:name":"Fanrong",
    "gn:population":0,
    "gn:timezone":"Asia/Shanghai",
    "iso:country":"CN",
    "name:und_x_variant":[
        "\u7e41\u8363"
    ],
    "wof:name":"Fanrong",
    "wof:placetype":"locality"
},
  "geometry": {"coordinates":[125.78004,41.57116],"type":"Point"}
}