{
  "type": "Feature",
  "properties": {
    "gn:admin1_code":"3.0",
    "gn:asciiname":"Xinchang",
    "gn:cc2":"CN",
    "gn:country_code":"CN",
    "gn:dem":79,
    "gn:feature_class":"P",
    "gn:feature_code":"PPL",
    "gn:name":"Xinchang",
    "gn:population":0,
    "gn:timezone":"Asia/Shanghai",
    "iso:country":"CN",
    "name:und_x_variant":[
        "Hsin-ch\u2019ang",
        "Xinchang"
    ],
    "wof:name":"Xinchang",
    "wof:placetype":"locality"
},
  "geometry": {"coordinates":[117.26667,29.33333],"type":"Point"}
}