{
  "type": "Feature",
  "properties": {
    "gn:admin1_code":"30.0",
    "gn:asciiname":"Rezhe",
    "gn:country_code":"CN",
    "gn:dem":125,
    "gn:feature_class":"P",
    "gn:feature_code":"PPLA4",
    "gn:name":"Rezhe",
    "gn:population":0,
    "gn:timezone":"Asia/Shanghai",
    "iso:country":"CN",
    "name:und_x_variant":[
        "Rezhe Zhen"
    ],
    "name:zho_x_preferred":[
        "\u70ed\u67d8"
    ],
    "name:zho_x_variant":[
        "\u70ed\u67d8\u9547"
    ],
    "wof:name":"Rezhe",
    "wof:placetype":"locality"
},
  "geometry": {"coordinates":[115.98045,24.53553],"type":"Point"}
}