{
  "type": "Feature",
  "properties": {
    "gn:admin1_code":"5.0",
    "gn:asciiname":"Xiaohetian",
    "gn:country_code":"CN",
    "gn:dem":78,
    "gn:feature_class":"P",
    "gn:feature_code":"PPL",
    "gn:name":"Xiaohetian",
    "gn:population":0,
    "gn:timezone":"Asia/Shanghai",
    "iso:country":"CN",
    "name:und_x_variant":[
        "\u5c0f\u6cb3\u7530"
    ],
    "wof:name":"Xiaohetian",
    "wof:placetype":"locality"
},
  "geometry": {"coordinates":[130.34698,42.65357],"type":"Point"}
}