{
  "type": "Feature",
  "properties": {
    "gn:admin1_code":"4.0",
    "gn:asciiname":"Xinfeng",
    "gn:country_code":"CN",
    "gn:dem":2,
    "gn:feature_class":"P",
    "gn:feature_code":"PPLA4",
    "gn:name":"Xinfeng",
    "gn:population":0,
    "gn:timezone":"Asia/Shanghai",
    "iso:country":"CN",
    "name:ceb_x_preferred":[
        "Xinfeng"
    ],
    "name:deu_x_preferred":[
        "Xinfeng"
    ],
    "name:fra_x_preferred":[
        "Xinfeng"
    ],
    "name:kor_x_preferred":[
        "\uc2e0\ud391\ud604"
    ],
    "name:nor_x_preferred":[
        "Xinfeng"
    ],
    "name:swe_x_preferred":[
        "Xinfeng"
    ],
    "name:und_x_variant":[
        "Hsin-feng-chi",
        "Hsin-feng",
        "Hsin-feng-chen",
        "Xinfeng",
        "\u65b0\u4e30",
        "Xinfeng Zhen",
        "\u65b0\u4e30\u9547"
    ],
    "wof:name":"Xinfeng",
    "wof:placetype":"locality"
},
  "geometry": {"coordinates":[120.45356,33.26831],"type":"Point"}
}