{
  "type": "Feature",
  "properties": {
    "gn:admin1_code":"19.0",
    "gn:asciiname":"Hele",
    "gn:country_code":"CN",
    "gn:dem":518,
    "gn:feature_class":"P",
    "gn:feature_code":"PPL",
    "gn:name":"Hele",
    "gn:population":0,
    "gn:timezone":"Asia/Shanghai",
    "iso:country":"CN",
    "name:ceb_x_preferred":[
        "Hele"
    ],
    "name:deu_x_preferred":[
        "Hele"
    ],
    "name:est_x_preferred":[
        "Hele"
    ],
    "name:swe_x_preferred":[
        "Hele"
    ],
    "name:zho_x_preferred":[
        "\u548c\u4e50"
    ],
    "wof:name":"Hele",
    "wof:placetype":"locality"
},
  "geometry": {"coordinates":[119.33307000000001,41.8364],"type":"Point"}
}