{
  "type": "Feature",
  "properties": {
    "gn:admin1_code":"14.0",
    "gn:asciiname":"Lashanong",
    "gn:country_code":"CN",
    "gn:dem":4259,
    "gn:feature_class":"P",
    "gn:feature_code":"PPL",
    "gn:name":"Lashanong",
    "gn:population":0,
    "gn:timezone":"Asia/Urumqi",
    "iso:country":"CN",
    "name:zho_x_preferred":[
        "\u62c9\u6c99\u5f04"
    ],
    "wof:name":"Lashanong",
    "wof:placetype":"locality"
},
  "geometry": {"coordinates":[96.83893,31.78401],"type":"Point"}
}