{
  "type": "Feature",
  "properties": {
    "gn:admin1_code":"5.0",
    "gn:asciiname":"Beigou Tunjihao",
    "gn:country_code":"CN",
    "gn:dem":340,
    "gn:feature_class":"P",
    "gn:feature_code":"PPL",
    "gn:name":"Beigou Tunjihao",
    "gn:population":0,
    "gn:timezone":"Asia/Shanghai",
    "iso:country":"CN",
    "name:zho_x_preferred":[
        "\u5317\u6c9f\u5c6f\u57fa\u53f7"
    ],
    "wof:name":"Beigou Tunjihao",
    "wof:placetype":"locality"
},
  "geometry": {"coordinates":[125.79443000000001,42.74043],"type":"Point"}
}