{
  "type": "Feature",
  "properties": {
    "gn:admin1_code":"26.0",
    "gn:asciiname":"Houjiatai",
    "gn:country_code":"CN",
    "gn:dem":782,
    "gn:feature_class":"P",
    "gn:feature_code":"PPL",
    "gn:name":"Houjiatai",
    "gn:population":0,
    "gn:timezone":"Asia/Shanghai",
    "iso:country":"CN",
    "name:und_x_variant":[
        "\u5019\u5bb6\u53f0"
    ],
    "wof:name":"Houjiatai",
    "wof:placetype":"locality"
},
  "geometry": {"coordinates":[106.30656999999999,32.84541],"type":"Point"}
}