{
  "type": "Feature",
  "properties": {
    "gn:admin1_code":"09",
    "gn:asciiname":"Hancheng",
    "gn:country_code":"CN",
    "gn:dem":251,
    "gn:feature_class":"P",
    "gn:feature_code":"PPL",
    "gn:name":"Hancheng",
    "gn:population":0,
    "gn:timezone":"Asia/Shanghai",
    "iso:country":"CN",
    "name:ara_x_preferred":[
        "\u0647\u0627\u0646\u062a\u0634\u0646\u063a"
    ],
    "name:ceb_x_preferred":[
        "Hancheng"
    ],
    "name:ces_x_preferred":[
        "Chan-\u010dcheng"
    ],
    "name:deu_x_preferred":[
        "Hancheng"
    ],
    "name:fra_x_preferred":[
        "Hancheng"
    ],
    "name:ind_x_preferred":[
        "Hancheng"
    ],
    "name:ita_x_preferred":[
        "Hancheng"
    ],
    "name:jpn_x_preferred":[
        "\u97d3\u57ce"
    ],
    "name:jpn_x_variant":[
        "\u97d3\u57ce\u5e02"
    ],
    "name:kik_x_preferred":[
        "Hancheng"
    ],
    "name:kor_x_preferred":[
        "\ud55c\uccad\uc2dc"
    ],
    "name:lat_x_preferred":[
        "Hancheng"
    ],
    "name:mlg_x_preferred":[
        "Hancheng"
    ],
    "name:nor_x_preferred":[
        "Hancheng"
    ],
    "name:rus_x_preferred":[
        "\u0425\u0430\u043d\u044c\u0447\u044d\u043d"
    ],
    "name:swe_x_preferred":[
        "Hancheng"
    ],
    "name:urd_x_preferred":[
        "\u06c1\u0627\u0646\u0686\u06cc\u0646\u06af"
    ],
    "name:vie_x_preferred":[
        "H\u00e0n Th\u00e0nh"
    ],
    "name:war_x_preferred":[
        "Hancheng"
    ],
    "name:zho_x_preferred":[
        "\u97e9\u57ce\u5e02"
    ],
    "wof:name":"Hancheng",
    "wof:placetype":"locality"
},
  "geometry": {"coordinates":[111.92,34.49111],"type":"Point"}
}