{
  "type": "Feature",
  "properties": {
    "gn:admin1_code":"29.0",
    "gn:asciiname":"Shangbawan",
    "gn:country_code":"CN",
    "gn:dem":2473,
    "gn:feature_class":"P",
    "gn:feature_code":"PPL",
    "gn:name":"Shangbawan",
    "gn:population":0,
    "gn:timezone":"Asia/Shanghai",
    "iso:country":"CN",
    "name:zho_x_preferred":[
        "\u4e0a\u516b\u6e7e"
    ],
    "wof:name":"Shangbawan",
    "wof:placetype":"locality"
},
  "geometry": {"coordinates":[100.636,26.0745],"type":"Point"}
}