{
  "type": "Feature",
  "properties": {
    "gn:admin1_code":"30",
    "gn:asciiname":"Xinkeng",
    "gn:country_code":"CN",
    "gn:dem":311,
    "gn:feature_class":"P",
    "gn:feature_code":"PPL",
    "gn:name":"Xinkeng",
    "gn:population":0,
    "gn:timezone":"Asia/Shanghai",
    "iso:country":"CN",
    "name:zho_x_preferred":[
        "\u65b0\u5751"
    ],
    "wof:name":"Xinkeng",
    "wof:placetype":"locality"
},
  "geometry": {"coordinates":[115.52565,23.26694],"type":"Point"}
}