{
  "type": "Feature",
  "properties": {
    "gn:admin1_code":"26",
    "gn:asciiname":"Hejia",
    "gn:country_code":"CN",
    "gn:dem":382,
    "gn:feature_class":"P",
    "gn:feature_code":"PPL",
    "gn:name":"Hejia",
    "gn:population":0,
    "gn:timezone":"Asia/Shanghai",
    "iso:country":"CN",
    "name:und_x_variant":[
        "Hejiacun"
    ],
    "name:zho_x_preferred":[
        "\u8d3a\u5bb6"
    ],
    "wof:name":"Hejia",
    "wof:placetype":"locality"
},
  "geometry": {"coordinates":[108.80194,34.31667],"type":"Point"}
}