{
  "type": "Feature",
  "properties": {
    "gn:admin1_code":"9.0",
    "gn:asciiname":"Pozhuang",
    "gn:country_code":"CN",
    "gn:dem":215,
    "gn:feature_class":"P",
    "gn:feature_code":"PPL",
    "gn:name":"Pozhuang",
    "gn:population":0,
    "gn:timezone":"Asia/Shanghai",
    "iso:country":"CN",
    "name:zho_x_preferred":[
        "\u7834\u5e84"
    ],
    "wof:name":"Pozhuang",
    "wof:placetype":"locality"
},
  "geometry": {"coordinates":[114.10276,35.63258],"type":"Point"}
}