{
  "type": "Feature",
  "properties": {
    "gn:admin1_code":"32.0",
    "gn:asciiname":"Tongchang",
    "gn:country_code":"CN",
    "gn:dem":1285,
    "gn:feature_class":"P",
    "gn:feature_code":"PPL",
    "gn:name":"Tongchang",
    "gn:population":0,
    "gn:timezone":"Asia/Shanghai",
    "iso:country":"CN",
    "name:zho_x_preferred":[
        "\u94dc\u5382"
    ],
    "wof:name":"Tongchang",
    "wof:placetype":"locality"
},
  "geometry": {"coordinates":[103.36199999999999,28.8079],"type":"Point"}
}