{
  "type": "Feature",
  "properties": {
    "gn:admin1_code":"10.0",
    "gn:asciiname":"Beimazhuang",
    "gn:country_code":"CN",
    "gn:dem":15,
    "gn:feature_class":"P",
    "gn:feature_code":"PPL",
    "gn:name":"Beimazhuang",
    "gn:population":0,
    "gn:timezone":"Asia/Shanghai",
    "iso:country":"CN",
    "name:zho_x_preferred":[
        "\u5317\u9a6c\u5e84"
    ],
    "wof:name":"Beimazhuang",
    "wof:placetype":"locality"
},
  "geometry": {"coordinates":[116.133,38.2437],"type":"Point"}
}