{
  "type": "Feature",
  "properties": {
    "gn:admin1_code":"16.0",
    "gn:asciiname":"Liumayang",
    "gn:country_code":"CN",
    "gn:dem":77,
    "gn:feature_class":"P",
    "gn:feature_code":"PPL",
    "gn:name":"Liumayang",
    "gn:population":0,
    "gn:timezone":"Asia/Shanghai",
    "iso:country":"CN",
    "name:zho_x_preferred":[
        "\u516d\u9ebb\u6d0b"
    ],
    "wof:name":"Liumayang",
    "wof:placetype":"locality"
},
  "geometry": {"coordinates":[107.79600000000001,21.7387],"type":"Point"}
}