{
  "type": "Feature",
  "properties": {
    "gn:admin1_code":"26.0",
    "gn:asciiname":"Huanghuadi",
    "gn:country_code":"CN",
    "gn:dem":1580,
    "gn:feature_class":"P",
    "gn:feature_code":"PPL",
    "gn:name":"Huanghuadi",
    "gn:population":0,
    "gn:timezone":"Asia/Shanghai",
    "iso:country":"CN",
    "name:zho_x_preferred":[
        "\u9ec4\u82b1\u5730"
    ],
    "wof:name":"Huanghuadi",
    "wof:placetype":"locality"
},
  "geometry": {"coordinates":[106.65582999999999,34.18736],"type":"Point"}
}