{
  "type": "Feature",
  "properties": {
    "gn:admin1_code":"11",
    "gn:asciiname":"Qingshanwan",
    "gn:country_code":"CN",
    "gn:dem":290,
    "gn:feature_class":"P",
    "gn:feature_code":"PPL",
    "gn:name":"Qingshanwan",
    "gn:population":0,
    "gn:timezone":"Asia/Shanghai",
    "iso:country":"CN",
    "wof:name":"Qingshanwan",
    "wof:placetype":"locality"
},
  "geometry": {"coordinates":[111.44583,26.98694],"type":"Point"}
}