{
  "type": "Feature",
  "properties": {
    "gn:admin1_code":"16.0",
    "gn:asciiname":"Banhu",
    "gn:country_code":"CN",
    "gn:dem":295,
    "gn:feature_class":"P",
    "gn:feature_code":"PPL",
    "gn:name":"Banhu",
    "gn:population":0,
    "gn:timezone":"Asia/Shanghai",
    "iso:country":"CN",
    "name:ara_x_preferred":[
        "\u0628\u0627\u0646 \u0647\u0648"
    ],
    "name:deu_x_preferred":[
        "Banhu"
    ],
    "name:epo_x_preferred":[
        "Banhuo"
    ],
    "name:fra_x_preferred":[
        "Banhu"
    ],
    "name:hun_x_preferred":[
        "Panhu"
    ],
    "name:hye_x_preferred":[
        "\u0532\u0561\u0576\u0570\u0578\u0582"
    ],
    "name:ind_x_preferred":[
        "Banhu"
    ],
    "name:nor_x_preferred":[
        "Banhu"
    ],
    "name:rus_x_preferred":[
        "\u0411\u0430\u043d\u044c\u0445\u0443"
    ],
    "name:zho_x_preferred":[
        "\u677f\u9e44"
    ],
    "wof:name":"Banhu",
    "wof:placetype":"locality"
},
  "geometry": {"coordinates":[106.896,22.6047],"type":"Point"}
}