{
  "type": "Feature",
  "properties": {
    "gn:admin1_code":"2.0",
    "gn:asciiname":"Anji",
    "gn:country_code":"CN",
    "gn:dem":289,
    "gn:feature_class":"P",
    "gn:feature_code":"PPL",
    "gn:name":"Anji",
    "gn:population":0,
    "gn:timezone":"Asia/Shanghai",
    "iso:country":"CN",
    "name:ceb_x_preferred":[
        "Anji"
    ],
    "name:deu_x_preferred":[
        "Anji"
    ],
    "name:zho_x_preferred":[
        "\u5b89\u57fa"
    ],
    "wof:name":"Anji",
    "wof:placetype":"locality"
},
  "geometry": {"coordinates":[120.4589,27.36374],"type":"Point"}
}