{
  "type": "Feature",
  "properties": {
    "gn:admin1_code":"11.0",
    "gn:asciiname":"Zhouqingzu",
    "gn:country_code":"CN",
    "gn:dem":78,
    "gn:feature_class":"P",
    "gn:feature_code":"PPL",
    "gn:name":"Zhouqingzu",
    "gn:population":0,
    "gn:timezone":"Asia/Shanghai",
    "iso:country":"CN",
    "name:zho_x_preferred":[
        "\u5468\u5e86\u7956"
    ],
    "wof:name":"Zhouqingzu",
    "wof:placetype":"locality"
},
  "geometry": {"coordinates":[113.31399,29.00654],"type":"Point"}
}