{
  "type": "Feature",
  "properties": {
    "gn:admin1_code":"3.0",
    "gn:asciiname":"Shangmiao",
    "gn:country_code":"CN",
    "gn:dem":123,
    "gn:feature_class":"P",
    "gn:feature_code":"PPL",
    "gn:name":"Shangmiao",
    "gn:population":0,
    "gn:timezone":"Asia/Shanghai",
    "iso:country":"CN",
    "name:und_x_variant":[
        "\u4e0a\u5e99"
    ],
    "wof:name":"Shangmiao",
    "wof:placetype":"locality"
},
  "geometry": {"coordinates":[115.00100999999999,25.88502],"type":"Point"}
}