{
  "type": "Feature",
  "properties": {
    "gn:admin1_code":"14.0",
    "gn:asciiname":"Gudong",
    "gn:country_code":"CN",
    "gn:dem":4699,
    "gn:feature_class":"P",
    "gn:feature_code":"PPL",
    "gn:name":"Gudong",
    "gn:population":0,
    "gn:timezone":"Asia/Urumqi",
    "iso:country":"CN",
    "name:zho_x_preferred":[
        "\u8c37\u51ac"
    ],
    "wof:name":"Gudong",
    "wof:placetype":"locality"
},
  "geometry": {"coordinates":[87.6759,28.8866],"type":"Point"}
}