{
  "type": "Feature",
  "properties": {
    "gn:admin1_code":"19.0",
    "gn:asciiname":"Nansanjiacun",
    "gn:country_code":"CN",
    "gn:dem":265,
    "gn:feature_class":"P",
    "gn:feature_code":"PPL",
    "gn:name":"Nansanjiacun",
    "gn:population":0,
    "gn:timezone":"Asia/Shanghai",
    "iso:country":"CN",
    "name:zho_x_preferred":[
        "\u5357\u4e09\u5bb6\u6751"
    ],
    "wof:name":"Nansanjiacun",
    "wof:placetype":"locality"
},
  "geometry": {"coordinates":[124.762,41.9914],"type":"Point"}
}