{
  "type": "Feature",
  "properties": {
    "gn:admin1_code":"7",
    "gn:asciiname":"Tianma Linchang",
    "gn:country_code":"CN",
    "gn:dem":104,
    "gn:feature_class":"P",
    "gn:feature_code":"PPLF",
    "gn:name":"Tianma Linchang",
    "gn:population":0,
    "gn:timezone":"Asia/Shanghai",
    "iso:country":"CN",
    "name:zho_x_preferred":[
        "\u5929\u9a6c\u6797\u573a"
    ],
    "wof:name":"Tianma Linchang",
    "wof:placetype":"locality"
},
  "geometry": {"coordinates":[117.38833,24.35611],"type":"Point"}
}