{
  "type": "Feature",
  "properties": {
    "gn:country":"CN",
    "gn:fcode":"PPL",
    "gn:population":87236,
    "iso:country":"CN",
    "name:eng_x_preferred":[
        "Nenjiang"
    ],
    "name:est_x_preferred":[
        "Nenjiangi suurvald"
    ],
    "name:fas_x_preferred":[
        "\u0646\u0646\u062c\u06cc\u0627\u0646\u06af"
    ],
    "name:gan_x_preferred":[
        "\u5ae9\u6c5f\u9547"
    ],
    "name:jpn_x_preferred":[
        "\u5ae9\u6c5f\u93ae"
    ],
    "name:und_x_variant":[
        "Nen-ch\u2019eng-hsien"
    ],
    "name:wuu_x_preferred":[
        "\u5ae9\u6c5f\u9547"
    ],
    "name:zho_x_preferred":[
        "\u5ae9\u6c5f"
    ],
    "name:zho_x_variant":[
        "\u5ae9\u6c5f\u53bf",
        "\u5ae9\u6c5f\u9547"
    ],
    "ne:ADM0CAP":0.0,
    "ne:ADM0NAME":"China",
    "ne:ADM0_A3":"CHN",
    "ne:ADM1NAME":"Heilongjiang",
    "ne:ADMIN1_COD":8,
    "ne:CAPALT":0,
    "ne:CHANGED":1,
    "ne:CHECKME":2,
    "ne:COMPARE":0,
    "ne:DIFFASCII":0,
    "ne:DIFFNOTE":"Changed scale rank.",
    "ne:ELEVATION":0.0,
    "ne:FEATURECLA":"Populated place",
    "ne:FEATURE_CL":"P",
    "ne:FEATURE_CO":"PPL",
    "ne:GEONAMEID":2035601,
    "ne:GEONAMESNO":"Geonames ascii name + lat.d + long.d matching.",
    "ne:GN_ASCII":"Nenjiang",
    "ne:GN_POP":87236,
    "ne:GTOPO30":223.0,
    "ne:ISO_A2":"CN",
    "ne:LABELRANK":1,
    "ne:LATITUDE":49.179981,
    "ne:LONGITUDE":125.23002,
    "ne:LS_MATCH":1,
    "ne:LS_NAME":"Nenjiang",
    "ne:MAX_AREAKM":29.0,
    "ne:MAX_AREAMI":11.0,
    "ne:MAX_BBXMAX":125.275,
    "ne:MAX_BBXMIN":125.183333,
    "ne:MAX_BBYMAX":49.2,
    "ne:MAX_BBYMIN":49.133333,
    "ne:MAX_NATSCA":20.0,
    "ne:MAX_PERKM":43.0,
    "ne:MAX_PERMI":27.0,
    "ne:MAX_POP10":72134,
    "ne:MAX_POP20":72134,
    "ne:MAX_POP300":0,
    "ne:MAX_POP310":0,
    "ne:MAX_POP50":0,
    "ne:MEAN_BBXC":125.230801,
    "ne:MEAN_BBYC":49.168546,
    "ne:MEGACITY":0,
    "ne:MIN_AREAKM":29.0,
    "ne:MIN_AREAMI":11.0,
    "ne:MIN_BBXMAX":125.275,
    "ne:MIN_BBXMIN":125.183333,
    "ne:MIN_BBYMAX":49.2,
    "ne:MIN_BBYMIN":49.133333,
    "ne:MIN_PERKM":43.0,
    "ne:MIN_PERMI":27.0,
    "ne:NAME":"Nenjiang",
    "ne:NAMEASCII":"Nenjiang",
    "ne:NAMEDIFF":0,
    "ne:NATSCALE":30,
    "ne:POP1950":0,
    "ne:POP1955":0,
    "ne:POP1960":0,
    "ne:POP1965":0,
    "ne:POP1970":0,
    "ne:POP1975":0,
    "ne:POP1980":0,
    "ne:POP1985":0,
    "ne:POP1990":0,
    "ne:POP1995":0,
    "ne:POP2000":0,
    "ne:POP2005":0,
    "ne:POP2010":0,
    "ne:POP2015":0,
    "ne:POP2020":0,
    "ne:POP2025":0,
    "ne:POP2050":0,
    "ne:POP_MAX":87236,
    "ne:POP_MIN":72134,
    "ne:POP_OTHER":71159,
    "ne:RANK_MAX":8,
    "ne:RANK_MIN":8,
    "ne:SCALERANK":6,
    "ne:SOV0NAME":"China",
    "ne:SOV_A3":"CHN",
    "ne:TIMEZONE":"Asia/Harbin",
    "ne:UN_FID":0,
    "ne:UN_LAT":0.0,
    "ne:UN_LONG":0.0,
    "ne:WORLDCITY":0,
    "qs:name":"Nenjiang",
    "qs:photos_9r":0,
    "qs:photos_sr":0,
    "qs:pop_sr":"8",
    "wd:wordcount":44,
    "wof:name":"Nenjiang",
    "wof:placetype":"locality",
    "wof:population":87236
},
  "geometry": {"coordinates":[125.21666999999999,49.18333],"type":"Point"}
}