{
  "type": "Feature",
  "properties": {
    "gn:admin1_code":"25.0",
    "gn:asciiname":"Hebeidabaicun",
    "gn:country_code":"CN",
    "gn:dem":54,
    "gn:feature_class":"P",
    "gn:feature_code":"PPL",
    "gn:name":"Hebeidabaicun",
    "gn:population":0,
    "gn:timezone":"Asia/Shanghai",
    "iso:country":"CN",
    "name:zho_x_preferred":[
        "\u6cb3\u5317\u5927\u767d\u6751"
    ],
    "wof:name":"Hebeidabaicun",
    "wof:placetype":"locality"
},
  "geometry": {"coordinates":[120.13030999999999,36.77582],"type":"Point"}
}