{
  "type": "Feature",
  "properties": {
    "gn:admin1_code":"32.0",
    "gn:asciiname":"Tiefo",
    "gn:country_code":"CN",
    "gn:dem":543,
    "gn:feature_class":"P",
    "gn:feature_code":"PPL",
    "gn:name":"Tiefo",
    "gn:population":0,
    "gn:timezone":"Asia/Shanghai",
    "iso:country":"CN",
    "name:zho_x_preferred":[
        "\u94c1\u4f5b"
    ],
    "wof:name":"Tiefo",
    "wof:placetype":"locality"
},
  "geometry": {"coordinates":[107.30755000000001,31.75894000000001],"type":"Point"}
}