{
  "type": "Feature",
  "properties": {
    "gn:admin1_code":"18",
    "gn:asciiname":"Xiyu'ao",
    "gn:country_code":"CN",
    "gn:dem":1296,
    "gn:feature_class":"P",
    "gn:feature_code":"PPL",
    "gn:name":"Xiyu\u2019ao",
    "gn:population":0,
    "gn:timezone":"Asia/Shanghai",
    "iso:country":"CN",
    "name:und_x_variant":[
        "Xiyu\u2019ao"
    ],
    "name:zho_x_preferred":[
        "\u5c0f\u9c7c\u51f9"
    ],
    "wof:name":"Xiyu'ao",
    "wof:placetype":"locality"
},
  "geometry": {"coordinates":[106.01600000000001,25.9148],"type":"Point"}
}