{
  "type": "Feature",
  "properties": {
    "gn:admin1_code":"02",
    "gn:asciiname":"Yangzhang'ao",
    "gn:country_code":"CN",
    "gn:dem":30,
    "gn:feature_class":"P",
    "gn:feature_code":"PPL",
    "gn:name":"Yangzhang\u2019ao",
    "gn:population":0,
    "gn:timezone":"Asia/Shanghai",
    "iso:country":"CN",
    "name:und_x_variant":[
        "Yang-chiao-ao",
        "Yangzhang\u2019ao"
    ],
    "wof:name":"Yangzhang'ao",
    "wof:placetype":"locality"
},
  "geometry": {"coordinates":[122.11499999999999,29.88361],"type":"Point"}
}