{
  "type": "Feature",
  "properties": {
    "gn:admin1_code":"13.0",
    "gn:asciiname":"Yigaiqi",
    "gn:country_code":"CN",
    "gn:dem":1337,
    "gn:feature_class":"P",
    "gn:feature_code":"PPL",
    "gn:name":"Yigaiqi",
    "gn:population":0,
    "gn:timezone":"Asia/Shanghai",
    "iso:country":"CN",
    "name:zho_x_preferred":[
        "\u4f9d\u76d6\u5176"
    ],
    "wof:name":"Yigaiqi",
    "wof:placetype":"locality"
},
  "geometry": {"coordinates":[79.94261,37.16295],"type":"Point"}
}