{
  "type": "Feature",
  "properties": {
    "gn:admin1_code":"24.0",
    "gn:asciiname":"Pangyao",
    "gn:country_code":"CN",
    "gn:dem":1467,
    "gn:feature_class":"P",
    "gn:feature_code":"PPL",
    "gn:name":"Pangyao",
    "gn:population":0,
    "gn:timezone":"Asia/Shanghai",
    "iso:country":"CN",
    "name:zho_x_preferred":[
        "\u5e9e\u7a91"
    ],
    "wof:name":"Pangyao",
    "wof:placetype":"locality"
},
  "geometry": {"coordinates":[113.59237,40.32808],"type":"Point"}
}