{
  "type": "Feature",
  "properties": {
    "gn:admin1_code":"4.0",
    "gn:asciiname":"Anlong Shizu",
    "gn:country_code":"CN",
    "gn:dem":7,
    "gn:feature_class":"P",
    "gn:feature_code":"PPLF",
    "gn:name":"Anlong Shizu",
    "gn:population":0,
    "gn:timezone":"Asia/Shanghai",
    "iso:country":"CN",
    "name:zho_x_preferred":[
        "\u5b89\u9f99\u5341\u7ec4"
    ],
    "wof:name":"Anlong Shizu",
    "wof:placetype":"locality"
},
  "geometry": {"coordinates":[120.91865,32.03165],"type":"Point"}
}