{
  "type": "Feature",
  "properties": {
    "gn:admin1_code":"12",
    "gn:asciiname":"Wangjiazui",
    "gn:cc2":"CN",
    "gn:country_code":"CN",
    "gn:dem":76,
    "gn:feature_class":"P",
    "gn:feature_code":"PPL",
    "gn:name":"Wangjiazui",
    "gn:population":0,
    "gn:timezone":"Asia/Shanghai",
    "iso:country":"CN",
    "name:und_x_variant":[
        "Wang-chia-tsui",
        "Wangjiazui"
    ],
    "wof:name":"Wangjiazui",
    "wof:placetype":"locality"
},
  "geometry": {"coordinates":[112.53667,31.59528],"type":"Point"}
}