{
  "type": "Feature",
  "properties": {
    "gn:admin1_code":"8.0",
    "gn:asciiname":"Yaoshendi Fangzi",
    "gn:country_code":"CN",
    "gn:dem":152,
    "gn:feature_class":"P",
    "gn:feature_code":"PPL",
    "gn:name":"Yaoshendi Fangzi",
    "gn:population":0,
    "gn:timezone":"Asia/Shanghai",
    "iso:country":"CN",
    "name:zho_x_preferred":[
        "\u8170\u6c88\u5730\u623f\u5b50"
    ],
    "wof:name":"Yaoshendi Fangzi",
    "wof:placetype":"locality"
},
  "geometry": {"coordinates":[124.83454999999999,47.05186],"type":"Point"}
}