{
  "type": "Feature",
  "properties": {
    "gn:admin1_code":"24.0",
    "gn:asciiname":"Shangshuibo",
    "gn:country_code":"CN",
    "gn:dem":1643,
    "gn:feature_class":"P",
    "gn:feature_code":"PPL",
    "gn:name":"Shangshuibo",
    "gn:population":0,
    "gn:timezone":"Asia/Shanghai",
    "iso:country":"CN",
    "name:zho_x_preferred":[
        "\u4e0a\u6c34\u6cca"
    ],
    "wof:name":"Shangshuibo",
    "wof:placetype":"locality"
},
  "geometry": {"coordinates":[112.08441000000001,39.79342000000001],"type":"Point"}
}