{
  "type": "Feature",
  "properties": {
    "gn:admin1_code":"11",
    "gn:asciiname":"Hemuchong",
    "gn:country_code":"CN",
    "gn:dem":153,
    "gn:feature_class":"P",
    "gn:feature_code":"PPL",
    "gn:name":"Hemuchong",
    "gn:population":0,
    "gn:timezone":"Asia/Shanghai",
    "iso:country":"CN",
    "name:zho_x_preferred":[
        "\u548c\u7766\u51b2"
    ],
    "wof:name":"Hemuchong",
    "wof:placetype":"locality"
},
  "geometry": {"coordinates":[112.48828,27.87718],"type":"Point"}
}