{
  "type": "Feature",
  "properties": {
    "gn:admin1_code":"9.0",
    "gn:asciiname":"Huangweihuicun",
    "gn:country_code":"CN",
    "gn:dem":74,
    "gn:feature_class":"P",
    "gn:feature_code":"PPL",
    "gn:name":"Huangweihuicun",
    "gn:population":0,
    "gn:timezone":"Asia/Shanghai",
    "iso:country":"CN",
    "name:zho_x_preferred":[
        "\u9ec4\u59d4\u4f1a\u6751"
    ],
    "wof:name":"Huangweihuicun",
    "wof:placetype":"locality"
},
  "geometry": {"coordinates":[114.29113999999998,34.78176],"type":"Point"}
}