{
  "type": "Feature",
  "properties": {
    "gn:admin1_code":"15.0",
    "gn:asciiname":"Kutian",
    "gn:country_code":"CN",
    "gn:dem":2358,
    "gn:feature_class":"P",
    "gn:feature_code":"PPL",
    "gn:name":"Kutian",
    "gn:population":0,
    "gn:timezone":"Asia/Shanghai",
    "iso:country":"CN",
    "name:zho_x_preferred":[
        "\u82e6\u7530"
    ],
    "wof:name":"Kutian",
    "wof:placetype":"locality"
},
  "geometry": {"coordinates":[103.41200000000001,35.876],"type":"Point"}
}