{
  "type": "Feature",
  "properties": {
    "gn:admin1_code":"12.0",
    "gn:asciiname":"Wujiahekou",
    "gn:country_code":"CN",
    "gn:dem":113,
    "gn:feature_class":"P",
    "gn:feature_code":"PPL",
    "gn:name":"Wujiahekou",
    "gn:population":0,
    "gn:timezone":"Asia/Shanghai",
    "iso:country":"CN",
    "name:zho_x_preferred":[
        "\u5434\u5bb6\u6cb3\u53e3"
    ],
    "wof:name":"Wujiahekou",
    "wof:placetype":"locality"
},
  "geometry": {"coordinates":[114.20646000000001,31.40683],"type":"Point"}
}