{
  "type": "Feature",
  "properties": {
    "gn:admin1_code":"16",
    "gn:asciiname":"Jinyaodai",
    "gn:country_code":"CN",
    "gn:dem":228,
    "gn:feature_class":"P",
    "gn:feature_code":"PPL",
    "gn:name":"Jinyaodai",
    "gn:population":0,
    "gn:timezone":"Asia/Shanghai",
    "iso:country":"CN",
    "name:zho_x_preferred":[
        "\u91d1\u8170\u5e26"
    ],
    "wof:name":"Jinyaodai",
    "wof:placetype":"locality"
},
  "geometry": {"coordinates":[111.01900000000001,26.0514],"type":"Point"}
}