{
  "type": "Feature",
  "properties": {
    "gn:admin1_code":"3.0",
    "gn:asciiname":"Badouling",
    "gn:country_code":"CN",
    "gn:dem":452,
    "gn:feature_class":"P",
    "gn:feature_code":"PPL",
    "gn:name":"Badouling",
    "gn:population":0,
    "gn:timezone":"Asia/Shanghai",
    "iso:country":"CN",
    "name:zho_x_preferred":[
        "\u516b\u6597\u5cad"
    ],
    "wof:name":"Badouling",
    "wof:placetype":"locality"
},
  "geometry": {"coordinates":[113.845,27.1019],"type":"Point"}
}