{
  "type": "Feature",
  "properties": {
    "gn:admin1_code":"15.0",
    "gn:asciiname":"Jiawan",
    "gn:country_code":"CN",
    "gn:dem":1863,
    "gn:feature_class":"P",
    "gn:feature_code":"PPL",
    "gn:name":"Jiawan",
    "gn:population":0,
    "gn:timezone":"Asia/Shanghai",
    "iso:country":"CN",
    "name:und_x_variant":[
        "\u5bb6\u6e7e"
    ],
    "wof:name":"Jiawan",
    "wof:placetype":"locality"
},
  "geometry": {"coordinates":[105.30119000000001,35.78992],"type":"Point"}
}