{
  "type": "Feature",
  "properties": {
    "gn:admin1_code":"15.0",
    "gn:asciiname":"Shiguojia",
    "gn:country_code":"CN",
    "gn:dem":1806,
    "gn:feature_class":"P",
    "gn:feature_code":"PPL",
    "gn:name":"Shiguojia",
    "gn:population":0,
    "gn:timezone":"Asia/Shanghai",
    "iso:country":"CN",
    "name:zho_x_preferred":[
        "\u77f3\u90ed\u5bb6"
    ],
    "wof:name":"Shiguojia",
    "wof:placetype":"locality"
},
  "geometry": {"coordinates":[103.77500000000001,35.6243],"type":"Point"}
}