{
  "type": "Feature",
  "properties": {
    "gn:admin1_code":"14",
    "gn:asciiname":"Radoi",
    "gn:country_code":"CN",
    "gn:dem":3694,
    "gn:feature_class":"P",
    "gn:feature_code":"PPL",
    "gn:name":"Radoi",
    "gn:population":0,
    "gn:timezone":"Asia/Urumqi",
    "iso:country":"CN",
    "name:bod_x_preferred":[
        "\u0f62\u0f0b\u0f66\u0f9f\u0f7c\u0f51"
    ],
    "name:und_x_variant":[
        "Rat\u00f6"
    ],
    "wof:name":"Radoi",
    "wof:placetype":"locality"
},
  "geometry": {"coordinates":[90.91674,29.53282],"type":"Point"}
}