{
  "type": "Feature",
  "properties": {
    "gn:admin1_code":"9.0",
    "gn:asciiname":"Xiaohonggou",
    "gn:country_code":"CN",
    "gn:dem":1061,
    "gn:feature_class":"P",
    "gn:feature_code":"PPL",
    "gn:name":"Xiaohonggou",
    "gn:population":0,
    "gn:timezone":"Asia/Shanghai",
    "iso:country":"CN",
    "name:zho_x_preferred":[
        "\u5c0f\u7ea2\u6c9f"
    ],
    "wof:name":"Xiaohonggou",
    "wof:placetype":"locality"
},
  "geometry": {"coordinates":[110.98072000000001,33.78165],"type":"Point"}
}