{
  "type": "Feature",
  "properties": {
    "gn:admin1_code":"2.0",
    "gn:asciiname":"Shangmatou",
    "gn:country_code":"CN",
    "gn:dem":294,
    "gn:feature_class":"P",
    "gn:feature_code":"PPL",
    "gn:name":"Shangmatou",
    "gn:population":0,
    "gn:timezone":"Asia/Shanghai",
    "iso:country":"CN",
    "name:zho_x_preferred":[
        "\u4e0a\u9a6c\u5934"
    ],
    "wof:name":"Shangmatou",
    "wof:placetype":"locality"
},
  "geometry": {"coordinates":[119.33289000000001,28.69768],"type":"Point"}
}