{
  "type": "Feature",
  "properties": {
    "gn:admin1_code":"12.0",
    "gn:asciiname":"Xiaojiadawan",
    "gn:country_code":"CN",
    "gn:dem":68,
    "gn:feature_class":"P",
    "gn:feature_code":"PPL",
    "gn:name":"Xiaojiadawan",
    "gn:population":0,
    "gn:timezone":"Asia/Shanghai",
    "iso:country":"CN",
    "name:zho_x_preferred":[
        "\u8096\u5bb6\u5927\u6e7e"
    ],
    "wof:name":"Xiaojiadawan",
    "wof:placetype":"locality"
},
  "geometry": {"coordinates":[112.14688,30.6339],"type":"Point"}
}