{
  "type": "Feature",
  "properties": {
    "gn:admin1_code":"16.0",
    "gn:asciiname":"Manwang",
    "gn:country_code":"CN",
    "gn:dem":169,
    "gn:feature_class":"P",
    "gn:feature_code":"PPL",
    "gn:name":"Manwang",
    "gn:population":0,
    "gn:timezone":"Asia/Shanghai",
    "iso:country":"CN",
    "name:zho_x_preferred":[
        "\u6ee1\u5f80"
    ],
    "wof:name":"Manwang",
    "wof:placetype":"locality"
},
  "geometry": {"coordinates":[109.429,24.7214],"type":"Point"}
}