{
  "type": "Feature",
  "properties": {
    "gn:admin1_code":"4.0",
    "gn:asciiname":"Gongnong",
    "gn:country_code":"CN",
    "gn:dem":16,
    "gn:feature_class":"P",
    "gn:feature_code":"PPLF",
    "gn:name":"Gongnong",
    "gn:population":0,
    "gn:timezone":"Asia/Shanghai",
    "iso:country":"CN",
    "name:ceb_x_preferred":[
        "Gongnong"
    ],
    "name:deu_x_preferred":[
        "Gongnong"
    ],
    "name:zho_x_preferred":[
        "\u5de5\u519c"
    ],
    "wof:name":"Gongnong",
    "wof:placetype":"locality"
},
  "geometry": {"coordinates":[118.72968,32.23792],"type":"Point"}
}