{
  "type": "Feature",
  "properties": {
    "gn:admin1_code":"14.0",
    "gn:asciiname":"Jieke",
    "gn:country_code":"CN",
    "gn:dem":5172,
    "gn:feature_class":"P",
    "gn:feature_code":"PPLF",
    "gn:name":"Jieke",
    "gn:population":0,
    "gn:timezone":"Asia/Shanghai",
    "iso:country":"CN",
    "name:ara_x_preferred":[
        "\u063a\u064a\u063a\u0627\u0631"
    ],
    "name:bod_x_preferred":[
        "G\u00eagar"
    ],
    "name:fas_x_preferred":[
        "\u06af\u06af\u0627\u0631"
    ],
    "name:msa_x_preferred":[
        "G\u00eagar"
    ],
    "name:zho_x_preferred":[
        "Jieke"
    ],
    "name:zho_x_variant":[
        "\u7ed3\u514b",
        "Qinagong",
        "\u9f50\u7eb3\u516c"
    ],
    "wof:name":"Jieke",
    "wof:placetype":"locality"
},
  "geometry": {"coordinates":[81.88333,31.53333],"type":"Point"}
}