{
  "type": "Feature",
  "properties": {
    "gn:admin1_code":"11.0",
    "gn:asciiname":"Shanglongwei",
    "gn:country_code":"CN",
    "gn:dem":812,
    "gn:feature_class":"P",
    "gn:feature_code":"PPL",
    "gn:name":"Shanglongwei",
    "gn:population":0,
    "gn:timezone":"Asia/Shanghai",
    "iso:country":"CN",
    "name:zho_x_preferred":[
        "\u4e0a\u9f99\u5c3e"
    ],
    "wof:name":"Shanglongwei",
    "wof:placetype":"locality"
},
  "geometry": {"coordinates":[113.64343,25.7068],"type":"Point"}
}