{
  "type": "Feature",
  "properties": {
    "gn:admin1_code":"11.0",
    "gn:asciiname":"Chengxi",
    "gn:country_code":"CN",
    "gn:dem":448,
    "gn:feature_class":"P",
    "gn:feature_code":"PPL",
    "gn:name":"Chengxi",
    "gn:population":0,
    "gn:timezone":"Asia/Shanghai",
    "iso:country":"CN",
    "name:zho_x_preferred":[
        "\u57ce\u6eaa"
    ],
    "wof:name":"Chengxi",
    "wof:placetype":"locality"
},
  "geometry": {"coordinates":[110.97978999999999,27.57499],"type":"Point"}
}