{
  "type": "Feature",
  "properties": {
    "gn:admin1_code":"32.0",
    "gn:asciiname":"Shijiapai",
    "gn:country_code":"CN",
    "gn:dem":586,
    "gn:feature_class":"P",
    "gn:feature_code":"PPL",
    "gn:name":"Shijiapai",
    "gn:population":0,
    "gn:timezone":"Asia/Shanghai",
    "iso:country":"CN",
    "name:zho_x_preferred":[
        "\u77f3\u5bb6\u724c"
    ],
    "name:zho_x_variant":[
        "\u77f3\u5bb6\u6392"
    ],
    "wof:name":"Shijiapai",
    "wof:placetype":"locality"
},
  "geometry": {"coordinates":[106.76000000000001,31.9359],"type":"Point"}
}