{
  "type": "Feature",
  "properties": {
    "gn:admin1_code":"1.0",
    "gn:asciiname":"Wangjiawawu",
    "gn:country_code":"CN",
    "gn:dem":170,
    "gn:feature_class":"P",
    "gn:feature_code":"PPL",
    "gn:name":"Wangjiawawu",
    "gn:population":0,
    "gn:timezone":"Asia/Shanghai",
    "iso:country":"CN",
    "wof:name":"Wangjiawawu",
    "wof:placetype":"locality"
},
  "geometry": {"coordinates":[116.77500000000001,30.96389000000001],"type":"Point"}
}