{
  "type": "Feature",
  "properties": {
    "gn:admin1_code":"18.0",
    "gn:asciiname":"Changba",
    "gn:cc2":"CN",
    "gn:country_code":"CN",
    "gn:dem":1119,
    "gn:feature_class":"P",
    "gn:feature_code":"PPL",
    "gn:name":"Changba",
    "gn:population":0,
    "gn:timezone":"Asia/Shanghai",
    "iso:country":"CN",
    "name:und_x_variant":[
        "Changba Zhen",
        "Changba"
    ],
    "wof:name":"Changba",
    "wof:placetype":"locality"
},
  "geometry": {"coordinates":[106.46556,27.31694],"type":"Point"}
}