{
  "type": "Feature",
  "properties": {
    "gn:admin1_code":"19.0",
    "gn:asciiname":"Xibianzi",
    "gn:country_code":"CN",
    "gn:dem":12,
    "gn:feature_class":"P",
    "gn:feature_code":"PPL",
    "gn:name":"Xibianzi",
    "gn:population":0,
    "gn:timezone":"Asia/Shanghai",
    "iso:country":"CN",
    "name:zho_x_preferred":[
        "\u897f\u8fb9\u5b50"
    ],
    "wof:name":"Xibianzi",
    "wof:placetype":"locality"
},
  "geometry": {"coordinates":[122.709,39.0265],"type":"Point"}
}