{
  "type": "Feature",
  "properties": {
    "gn:admin1_code":"3.0",
    "gn:asciiname":"Nifuling",
    "gn:country_code":"CN",
    "gn:dem":758,
    "gn:feature_class":"P",
    "gn:feature_code":"PPL",
    "gn:name":"Nifuling",
    "gn:population":0,
    "gn:timezone":"Asia/Shanghai",
    "iso:country":"CN",
    "name:zho_x_preferred":[
        "\u6ce5\u6276\u5cad"
    ],
    "wof:name":"Nifuling",
    "wof:placetype":"locality"
},
  "geometry": {"coordinates":[114.38800000000001,28.4063],"type":"Point"}
}