{
  "type": "Feature",
  "properties": {
    "gn:admin1_code":"1.0",
    "gn:asciiname":"Lieshancun",
    "gn:country_code":"CN",
    "gn:dem":36,
    "gn:feature_class":"P",
    "gn:feature_code":"PPL",
    "gn:name":"Lieshancun",
    "gn:population":0,
    "gn:timezone":"Asia/Shanghai",
    "iso:country":"CN",
    "name:zho_x_preferred":[
        "\u70c8\u5c71\u6751"
    ],
    "wof:name":"Lieshancun",
    "wof:placetype":"locality"
},
  "geometry": {"coordinates":[116.82812,33.89771],"type":"Point"}
}