{
  "type": "Feature",
  "properties": {
    "gn:admin1_code":"5.0",
    "gn:asciiname":"Gangqiantun",
    "gn:country_code":"CN",
    "gn:dem":378,
    "gn:feature_class":"P",
    "gn:feature_code":"PPL",
    "gn:name":"Gangqiantun",
    "gn:population":0,
    "gn:timezone":"Asia/Shanghai",
    "iso:country":"CN",
    "name:zho_x_preferred":[
        "\u5c97\u524d\u5c6f"
    ],
    "wof:name":"Gangqiantun",
    "wof:placetype":"locality"
},
  "geometry": {"coordinates":[126.31682000000001,42.58277],"type":"Point"}
}