{
  "type": "Feature",
  "properties": {
    "gn:admin1_code":"2.0",
    "gn:asciiname":"Tu'ao",
    "gn:country_code":"CN",
    "gn:dem":2,
    "gn:feature_class":"P",
    "gn:feature_code":"PPL",
    "gn:name":"Tu\u2019ao",
    "gn:population":0,
    "gn:timezone":"Asia/Shanghai",
    "iso:country":"CN",
    "name:und_x_variant":[
        "Tu\u2019ao"
    ],
    "name:zho_x_preferred":[
        "\u6d82\u5c99"
    ],
    "wof:name":"Tu'ao",
    "wof:placetype":"locality"
},
  "geometry": {"coordinates":[121.60375000000001,28.7387],"type":"Point"}
}