{
  "type": "Feature",
  "properties": {
    "gn:admin1_code":"26.0",
    "gn:asciiname":"Simicun",
    "gn:country_code":"CN",
    "gn:dem":936,
    "gn:feature_class":"P",
    "gn:feature_code":"PPL",
    "gn:name":"Simicun",
    "gn:population":0,
    "gn:timezone":"Asia/Shanghai",
    "iso:country":"CN",
    "name:zho_x_preferred":[
        "\u601d\u5f25\u6751"
    ],
    "wof:name":"Simicun",
    "wof:placetype":"locality"
},
  "geometry": {"coordinates":[109.42979,35.4186],"type":"Point"}
}