{
  "type": "Feature",
  "properties": {
    "gn:admin1_code":"18",
    "gn:asciiname":"Zhangke",
    "gn:country_code":"CN",
    "gn:dem":1288,
    "gn:feature_class":"P",
    "gn:feature_code":"PPL",
    "gn:name":"Zhangke",
    "gn:population":0,
    "gn:timezone":"Asia/Shanghai",
    "iso:country":"CN",
    "name:zho_x_preferred":[
        "\u638c\u514b"
    ],
    "wof:name":"Zhangke",
    "wof:placetype":"locality"
},
  "geometry": {"coordinates":[106.577,26.3455],"type":"Point"}
}