{
  "type": "Feature",
  "properties": {
    "gn:admin1_code":"3.0",
    "gn:asciiname":"Wuqian Liujia",
    "gn:country_code":"CN",
    "gn:dem":55,
    "gn:feature_class":"P",
    "gn:feature_code":"PPL",
    "gn:name":"Wuqian Liujia",
    "gn:population":0,
    "gn:timezone":"Asia/Shanghai",
    "iso:country":"CN",
    "name:und_x_variant":[
        "\u90ac\u5811\u5218\u5bb6"
    ],
    "wof:name":"Wuqian Liujia",
    "wof:placetype":"locality"
},
  "geometry": {"coordinates":[115.57047,28.66528],"type":"Point"}
}