{
  "type": "Feature",
  "properties": {
    "gn:admin1_code":"1.0",
    "gn:asciiname":"Yanggancun",
    "gn:country_code":"CN",
    "gn:dem":189,
    "gn:feature_class":"P",
    "gn:feature_code":"PPL",
    "gn:name":"Yanggancun",
    "gn:population":0,
    "gn:timezone":"Asia/Shanghai",
    "iso:country":"CN",
    "name:zho_x_preferred":[
        "\u6768\u5e72\u6751"
    ],
    "wof:name":"Yanggancun",
    "wof:placetype":"locality"
},
  "geometry": {"coordinates":[118.27148,29.90673],"type":"Point"}
}