{
  "type": "Feature",
  "properties": {
    "gn:admin1_code":"9.0",
    "gn:asciiname":"Yuan'erzhuang",
    "gn:country_code":"CN",
    "gn:dem":149,
    "gn:feature_class":"P",
    "gn:feature_code":"PPL",
    "gn:name":"Yuan\u2019erzhuang",
    "gn:population":0,
    "gn:timezone":"Asia/Shanghai",
    "iso:country":"CN",
    "name:und_x_variant":[
        "Yuan\u2019erzhuang"
    ],
    "name:zho_x_preferred":[
        "\u5143\u4e8c\u5e84"
    ],
    "wof:name":"Yuan'erzhuang",
    "wof:placetype":"locality"
},
  "geometry": {"coordinates":[114.27558000000001,35.9928],"type":"Point"}
}