{
  "type": "Feature",
  "properties": {
    "gn:admin1_code":"4.0",
    "gn:asciiname":"Dawangjiaxia",
    "gn:country_code":"CN",
    "gn:dem":5,
    "gn:feature_class":"P",
    "gn:feature_code":"PPL",
    "gn:name":"Dawangjiaxia",
    "gn:population":0,
    "gn:timezone":"Asia/Shanghai",
    "iso:country":"CN",
    "name:zho_x_preferred":[
        "\u5927\u738b\u5bb6\u53a6"
    ],
    "wof:name":"Dawangjiaxia",
    "wof:placetype":"locality"
},
  "geometry": {"coordinates":[119.6168,32.73427],"type":"Point"}
}