{
  "type": "Feature",
  "properties": {
    "gn:admin1_code":"07",
    "gn:asciiname":"Longpanqi",
    "gn:country_code":"CN",
    "gn:dem":948,
    "gn:feature_class":"P",
    "gn:feature_code":"PPL",
    "gn:name":"Longpanqi",
    "gn:population":0,
    "gn:timezone":"Asia/Shanghai",
    "iso:country":"CN",
    "wof:name":"Longpanqi",
    "wof:placetype":"locality"
},
  "geometry": {"coordinates":[117.77667,25.53111],"type":"Point"}
}