{
  "type": "Feature",
  "properties": {
    "gn:admin1_code":"4.0",
    "gn:asciiname":"Nuandouzi",
    "gn:country_code":"CN",
    "gn:dem":4,
    "gn:feature_class":"P",
    "gn:feature_code":"PPL",
    "gn:name":"Nuandouzi",
    "gn:population":0,
    "gn:timezone":"Asia/Shanghai",
    "iso:country":"CN",
    "name:zho_x_preferred":[
        "\u6696\u515c\u5b50"
    ],
    "wof:name":"Nuandouzi",
    "wof:placetype":"locality"
},
  "geometry": {"coordinates":[119.51557,32.72555],"type":"Point"}
}