{
  "type": "Feature",
  "properties": {
    "gn:admin1_code":"25",
    "gn:asciiname":"Shilazi",
    "gn:country_code":"CN",
    "gn:dem":235,
    "gn:feature_class":"P",
    "gn:feature_code":"PPL",
    "gn:name":"Shilazi",
    "gn:population":0,
    "gn:timezone":"Asia/Shanghai",
    "iso:country":"CN",
    "name:zho_x_preferred":[
        "\u77f3\u62c9\u5b50"
    ],
    "wof:name":"Shilazi",
    "wof:placetype":"locality"
},
  "geometry": {"coordinates":[118.057,35.5095],"type":"Point"}
}