{
  "type": "Feature",
  "properties": {
    "gn:admin1_code":"18.0",
    "gn:asciiname":"Yanzhaigou",
    "gn:country_code":"CN",
    "gn:dem":547,
    "gn:feature_class":"P",
    "gn:feature_code":"PPL",
    "gn:name":"Yanzhaigou",
    "gn:population":0,
    "gn:timezone":"Asia/Shanghai",
    "iso:country":"CN",
    "name:zho_x_preferred":[
        "\u6cbf\u5be8\u6c9f"
    ],
    "wof:name":"Yanzhaigou",
    "wof:placetype":"locality"
},
  "geometry": {"coordinates":[108.916,28.1561],"type":"Point"}
}