{
  "type": "Feature",
  "properties": {
    "gn:admin1_code":"29.0",
    "gn:asciiname":"Xixiazhong",
    "gn:country_code":"CN",
    "gn:dem":2876,
    "gn:feature_class":"P",
    "gn:feature_code":"PPL",
    "gn:name":"Xixiazhong",
    "gn:population":0,
    "gn:timezone":"Asia/Shanghai",
    "iso:country":"CN",
    "name:zho_x_preferred":[
        "\u897f\u4e0b\u4e2d"
    ],
    "wof:name":"Xixiazhong",
    "wof:placetype":"locality"
},
  "geometry": {"coordinates":[99.0521,29.1352],"type":"Point"}
}