{
  "type": "Feature",
  "properties": {
    "gn:admin1_code":"12.0",
    "gn:asciiname":"Youlian",
    "gn:country_code":"CN",
    "gn:dem":1476,
    "gn:feature_class":"P",
    "gn:feature_code":"PPL",
    "gn:name":"Youlian",
    "gn:population":0,
    "gn:timezone":"Asia/Shanghai",
    "iso:country":"CN",
    "name:zho_x_preferred":[
        "\u53cb\u8054"
    ],
    "wof:name":"Youlian",
    "wof:placetype":"locality"
},
  "geometry": {"coordinates":[108.90791000000002,30.08362],"type":"Point"}
}