{
  "type": "Feature",
  "properties": {
    "gn:admin1_code":"19",
    "gn:asciiname":"Guoying Linchang",
    "gn:country_code":"CN",
    "gn:dem":476,
    "gn:feature_class":"P",
    "gn:feature_code":"PPLF",
    "gn:name":"Guoying Linchang",
    "gn:population":0,
    "gn:timezone":"Asia/Shanghai",
    "iso:country":"CN",
    "wof:name":"Guoying Linchang",
    "wof:placetype":"locality"
},
  "geometry": {"coordinates":[125.06139,41.27917],"type":"Point"}
}