{
  "type": "Feature",
  "properties": {
    "gn:admin1_code":"12.0",
    "gn:asciiname":"Xiaoshaping",
    "gn:country_code":"CN",
    "gn:dem":173,
    "gn:feature_class":"P",
    "gn:feature_code":"PPL",
    "gn:name":"Xiaoshaping",
    "gn:population":0,
    "gn:timezone":"Asia/Shanghai",
    "iso:country":"CN",
    "name:zho_x_preferred":[
        "\u5c0f\u6c99\u576a"
    ],
    "wof:name":"Xiaoshaping",
    "wof:placetype":"locality"
},
  "geometry": {"coordinates":[113.84216000000001,29.5123],"type":"Point"}
}