{
  "type": "Feature",
  "properties": {
    "gn:admin1_code":"26.0",
    "gn:asciiname":"Liangjia Goucun",
    "gn:country_code":"CN",
    "gn:dem":965,
    "gn:feature_class":"P",
    "gn:feature_code":"PPL",
    "gn:name":"Liangjia Goucun",
    "gn:population":0,
    "gn:timezone":"Asia/Shanghai",
    "iso:country":"CN",
    "name:zho_x_preferred":[
        "\u6881\u5bb6\u6c9f\u6751"
    ],
    "wof:name":"Liangjia Goucun",
    "wof:placetype":"locality"
},
  "geometry": {"coordinates":[110.13500000000001,37.7026],"type":"Point"}
}