{
  "type": "Feature",
  "properties": {
    "gn:admin1_code":"15.0",
    "gn:asciiname":"Dingtan",
    "gn:country_code":"CN",
    "gn:dem":2173,
    "gn:feature_class":"P",
    "gn:feature_code":"PPL",
    "gn:name":"Dingtan",
    "gn:population":0,
    "gn:timezone":"Asia/Shanghai",
    "iso:country":"CN",
    "name:zho_x_preferred":[
        "\u4e01\u6ee9"
    ],
    "wof:name":"Dingtan",
    "wof:placetype":"locality"
},
  "geometry": {"coordinates":[103.69,35.154],"type":"Point"}
}