{
  "type": "Feature",
  "properties": {
    "gn:admin1_code":"25",
    "gn:asciiname":"Ranguji",
    "gn:cc2":"CN",
    "gn:country_code":"CN",
    "gn:dem":49,
    "gn:feature_class":"P",
    "gn:feature_code":"PPL",
    "gn:name":"Ranguji",
    "gn:population":0,
    "gn:timezone":"Asia/Shanghai",
    "iso:country":"CN",
    "name:und_x_variant":[
        "Jan-ku-chi",
        "Rangu",
        "Jan-ku",
        "Ranguji"
    ],
    "wof:name":"Ranguji",
    "wof:placetype":"locality"
},
  "geometry": {"coordinates":[115.72556000000002,34.99278],"type":"Point"}
}