{
  "type": "Feature",
  "properties": {
    "gn:admin1_code":"32.0",
    "gn:asciiname":"Qiwu",
    "gn:country_code":"CN",
    "gn:dem":4196,
    "gn:feature_class":"P",
    "gn:feature_code":"PPL",
    "gn:name":"Qiwu",
    "gn:population":0,
    "gn:timezone":"Asia/Shanghai",
    "iso:country":"CN",
    "name:zho_x_preferred":[
        "\u8d77\u575e"
    ],
    "wof:name":"Qiwu",
    "wof:placetype":"locality"
},
  "geometry": {"coordinates":[98.4872,32.6449],"type":"Point"}
}