{
  "type": "Feature",
  "properties": {
    "gn:admin1_code":"7.0",
    "gn:asciiname":"Pingyang",
    "gn:country_code":"CN",
    "gn:dem":680,
    "gn:feature_class":"P",
    "gn:feature_code":"PPL",
    "gn:name":"Pingyang",
    "gn:population":0,
    "gn:timezone":"Asia/Shanghai",
    "iso:country":"CN",
    "name:ceb_x_preferred":[
        "Pingyang"
    ],
    "name:nor_x_preferred":[
        "Pingyang"
    ],
    "name:swe_x_preferred":[
        "Pingyang"
    ],
    "name:zho_x_preferred":[
        "\u576a\u6d0b"
    ],
    "wof:name":"Pingyang",
    "wof:placetype":"locality"
},
  "geometry": {"coordinates":[117.27715999999999,26.83073],"type":"Point"}
}