{
  "type": "Feature",
  "properties": {
    "gn:admin1_code":"32.0",
    "gn:asciiname":"Zuandong",
    "gn:country_code":"CN",
    "gn:dem":1680,
    "gn:feature_class":"P",
    "gn:feature_code":"PPL",
    "gn:name":"Zuandong",
    "gn:population":0,
    "gn:timezone":"Asia/Shanghai",
    "iso:country":"CN",
    "name:zho_x_preferred":[
        "\u94bb\u6d1e"
    ],
    "wof:name":"Zuandong",
    "wof:placetype":"locality"
},
  "geometry": {"coordinates":[102.20207000000001,26.37326],"type":"Point"}
}