{
  "type": "Feature",
  "properties": {
    "gn:admin1_code":"01",
    "gn:asciiname":"Liujiahe",
    "gn:cc2":"CN",
    "gn:country_code":"CN",
    "gn:dem":206,
    "gn:feature_class":"P",
    "gn:feature_code":"PPL",
    "gn:name":"Liujiahe",
    "gn:population":0,
    "gn:timezone":"Asia/Shanghai",
    "iso:country":"CN",
    "name:und_x_variant":[
        "Liu-chia-ho",
        "Liujiahe"
    ],
    "wof:name":"Liujiahe",
    "wof:placetype":"locality"
},
  "geometry": {"coordinates":[116.26667,30.56667],"type":"Point"}
}