{
  "type": "Feature",
  "properties": {
    "gn:admin1_code":"02",
    "gn:asciiname":"Tianshi",
    "gn:country_code":"CN",
    "gn:dem":83,
    "gn:feature_class":"P",
    "gn:feature_code":"PPLA4",
    "gn:name":"Tianshi",
    "gn:population":0,
    "gn:timezone":"Asia/Shanghai",
    "iso:country":"CN",
    "name:und_x_variant":[
        "Tianshi Zhen"
    ],
    "name:zho_x_preferred":[
        "\u7530\u5e02"
    ],
    "name:zho_x_variant":[
        "\u7530\u5e02\u9547"
    ],
    "wof:name":"Tianshi",
    "wof:placetype":"locality"
},
  "geometry": {"coordinates":[120.63129000000001,28.78143],"type":"Point"}
}