{
  "type": "Feature",
  "properties": {
    "gn:admin1_code":"20.0",
    "gn:asciiname":"Cuijiatun",
    "gn:country_code":"CN",
    "gn:dem":254,
    "gn:feature_class":"P",
    "gn:feature_code":"PPL",
    "gn:name":"Cuijiatun",
    "gn:population":0,
    "gn:timezone":"Asia/Shanghai",
    "iso:country":"CN",
    "name:zho_x_preferred":[
        "\u5d14\u5bb6\u5c6f"
    ],
    "wof:name":"Cuijiatun",
    "wof:placetype":"locality"
},
  "geometry": {"coordinates":[124.20075,48.63714],"type":"Point"}
}