{
  "type": "Feature",
  "properties": {
    "gn:admin1_code":"12.0",
    "gn:asciiname":"Wanjiachang",
    "gn:country_code":"CN",
    "gn:dem":31,
    "gn:feature_class":"P",
    "gn:feature_code":"PPL",
    "gn:name":"Wanjiachang",
    "gn:population":0,
    "gn:timezone":"Asia/Shanghai",
    "iso:country":"CN",
    "name:zho_x_preferred":[
        "Wanjiachang"
    ],
    "name:zho_x_variant":[
        "\u4e07\u5bb6\u573a"
    ],
    "wof:name":"Wanjiachang",
    "wof:placetype":"locality"
},
  "geometry": {"coordinates":[112.28436000000001,30.11499],"type":"Point"}
}