{
  "type": "Feature",
  "properties": {
    "gn:admin1_code":"3.0",
    "gn:asciiname":"Zhugaobei",
    "gn:country_code":"CN",
    "gn:dem":109,
    "gn:feature_class":"P",
    "gn:feature_code":"PPL",
    "gn:name":"Zhugaobei",
    "gn:population":0,
    "gn:timezone":"Asia/Shanghai",
    "iso:country":"CN",
    "name:und_x_variant":[
        "\u7af9\u9ad8\u9642"
    ],
    "wof:name":"Zhugaobei",
    "wof:placetype":"locality"
},
  "geometry": {"coordinates":[116.83744,27.33616],"type":"Point"}
}