{
  "type": "Feature",
  "properties": {
    "gn:admin1_code":"29.0",
    "gn:asciiname":"Mandonghui",
    "gn:country_code":"CN",
    "gn:dem":582,
    "gn:feature_class":"P",
    "gn:feature_code":"PPL",
    "gn:name":"Mandonghui",
    "gn:population":0,
    "gn:timezone":"Asia/Shanghai",
    "iso:country":"CN",
    "name:zho_x_preferred":[
        "\u66fc\u680b\u56de"
    ],
    "wof:name":"Mandonghui",
    "wof:placetype":"locality"
},
  "geometry": {"coordinates":[100.753,21.97300000000001],"type":"Point"}
}