{
  "type": "Feature",
  "properties": {
    "gn:admin1_code":"25",
    "gn:asciiname":"Qianmatun",
    "gn:country_code":"CN",
    "gn:dem":43,
    "gn:feature_class":"P",
    "gn:feature_code":"PPL",
    "gn:name":"Qianmatun",
    "gn:population":0,
    "gn:timezone":"Asia/Shanghai",
    "iso:country":"CN",
    "name:zho_x_preferred":[
        "\u524d\u9a6c\u5c6f"
    ],
    "wof:name":"Qianmatun",
    "wof:placetype":"locality"
},
  "geometry": {"coordinates":[115.59098,36.21876],"type":"Point"}
}