{
  "type": "Feature",
  "properties": {
    "gn:admin1_code":"3.0",
    "gn:asciiname":"Zhangjiadi",
    "gn:country_code":"CN",
    "gn:dem":571,
    "gn:feature_class":"P",
    "gn:feature_code":"PPL",
    "gn:name":"Zhangjiadi",
    "gn:population":0,
    "gn:timezone":"Asia/Shanghai",
    "iso:country":"CN",
    "name:und_x_variant":[
        "\u5f20\u5bb6\u5730"
    ],
    "wof:name":"Zhangjiadi",
    "wof:placetype":"locality"
},
  "geometry": {"coordinates":[115.72474,26.55465],"type":"Point"}
}