{
  "type": "Feature",
  "properties": {
    "gn:admin1_code":"3.0",
    "gn:asciiname":"Yan'ershang",
    "gn:country_code":"CN",
    "gn:dem":605,
    "gn:feature_class":"P",
    "gn:feature_code":"PPL",
    "gn:name":"Yan\u2019ershang",
    "gn:population":0,
    "gn:timezone":"Asia/Shanghai",
    "iso:country":"CN",
    "name:und_x_variant":[
        "Yan\u2019ershang",
        "\u6f14\u5c14\u4e0a"
    ],
    "wof:name":"Yan'ershang",
    "wof:placetype":"locality"
},
  "geometry": {"coordinates":[116.40863,27.46438],"type":"Point"}
}