{
  "type": "Feature",
  "properties": {
    "gn:admin1_code":"14.0",
    "gn:asciiname":"Qiurecun",
    "gn:country_code":"CN",
    "gn:dem":4305,
    "gn:feature_class":"P",
    "gn:feature_code":"PPL",
    "gn:name":"Qiurecun",
    "gn:population":0,
    "gn:timezone":"Asia/Urumqi",
    "iso:country":"CN",
    "name:zho_x_preferred":[
        "\u79cb\u70ed\u6751"
    ],
    "wof:name":"Qiurecun",
    "wof:placetype":"locality"
},
  "geometry": {"coordinates":[92.80623,31.67441],"type":"Point"}
}