{
  "type": "Feature",
  "properties": {
    "gn:admin1_code":"9",
    "gn:asciiname":"Lixinlou",
    "gn:country_code":"CN",
    "gn:dem":50,
    "gn:feature_class":"P",
    "gn:feature_code":"PPL",
    "gn:name":"Lixinlou",
    "gn:population":0,
    "gn:timezone":"Asia/Shanghai",
    "iso:country":"CN",
    "name:zho_x_preferred":[
        "\u674e\u65b0\u697c"
    ],
    "wof:name":"Lixinlou",
    "wof:placetype":"locality"
},
  "geometry": {"coordinates":[114.961,33.8187],"type":"Point"}
}