{
  "type": "Feature",
  "properties": {
    "gn:admin1_code":"11",
    "gn:asciiname":"Jiefangyan",
    "gn:country_code":"CN",
    "gn:dem":211,
    "gn:feature_class":"P",
    "gn:feature_code":"PPLA4",
    "gn:name":"Jiefangyan",
    "gn:population":0,
    "gn:timezone":"Asia/Shanghai",
    "iso:country":"CN",
    "name:und_x_variant":[
        "Jiefangyan Xiang"
    ],
    "name:zho_x_preferred":[
        "\u89e3\u653e\u5ca9"
    ],
    "name:zho_x_variant":[
        "\u89e3\u653e\u5ca9\u4e61"
    ],
    "wof:name":"Jiefangyan",
    "wof:placetype":"locality"
},
  "geometry": {"coordinates":[109.73839,28.12896],"type":"Point"}
}