{
  "type": "Feature",
  "properties": {
    "gn:admin1_code":"32.0",
    "gn:asciiname":"Fenggongmiao",
    "gn:country_code":"CN",
    "gn:dem":563,
    "gn:feature_class":"P",
    "gn:feature_code":"PPL",
    "gn:name":"Fenggongmiao",
    "gn:population":0,
    "gn:timezone":"Asia/Shanghai",
    "iso:country":"CN",
    "name:zho_x_preferred":[
        "\u51af\u516c\u5e99"
    ],
    "wof:name":"Fenggongmiao",
    "wof:placetype":"locality"
},
  "geometry": {"coordinates":[106.97920999999999,31.59212],"type":"Point"}
}