{
  "type": "Feature",
  "properties": {
    "gn:admin1_code":"29.0",
    "gn:asciiname":"Caomuliang Shangzhai",
    "gn:country_code":"CN",
    "gn:dem":1603,
    "gn:feature_class":"P",
    "gn:feature_code":"PPL",
    "gn:name":"Caomuliang Shangzhai",
    "gn:population":0,
    "gn:timezone":"Asia/Shanghai",
    "iso:country":"CN",
    "name:zho_x_preferred":[
        "\u66f9\u6728\u4eae\u4e0a\u5be8"
    ],
    "wof:name":"Caomuliang Shangzhai",
    "wof:placetype":"locality"
},
  "geometry": {"coordinates":[97.9725,24.7745],"type":"Point"}
}