{
  "type": "Feature",
  "properties": {
    "gn:admin1_code":"3.0",
    "gn:asciiname":"Chabutan",
    "gn:country_code":"CN",
    "gn:dem":185,
    "gn:feature_class":"P",
    "gn:feature_code":"PPL",
    "gn:name":"Chabutan",
    "gn:population":0,
    "gn:timezone":"Asia/Shanghai",
    "iso:country":"CN",
    "name:zho_x_preferred":[
        "\u8336\u57e0\u6f6d"
    ],
    "wof:name":"Chabutan",
    "wof:placetype":"locality"
},
  "geometry": {"coordinates":[114.179,29.0567],"type":"Point"}
}