{
  "type": "Feature",
  "properties": {
    "gn:admin1_code":"30.0",
    "gn:asciiname":"Tieluoping",
    "gn:country_code":"CN",
    "gn:dem":448,
    "gn:feature_class":"P",
    "gn:feature_code":"PPL",
    "gn:name":"Tieluoping",
    "gn:population":0,
    "gn:timezone":"Asia/Shanghai",
    "iso:country":"CN",
    "name:und_x_variant":[
        "\u94c1\u7f57\u576a"
    ],
    "name:zho_x_preferred":[
        "\u94c1\u7f57\u576a"
    ],
    "wof:name":"Tieluoping",
    "wof:placetype":"locality"
},
  "geometry": {"coordinates":[115.40967000000001,23.89776],"type":"Point"}
}