{
  "type": "Feature",
  "properties": {
    "gn:admin1_code":"04",
    "gn:asciiname":"Gengji",
    "gn:country_code":"CN",
    "gn:dem":27,
    "gn:feature_class":"P",
    "gn:feature_code":"PPL",
    "gn:name":"Gengji",
    "gn:population":0,
    "gn:timezone":"Asia/Shanghai",
    "iso:country":"CN",
    "name:zho_x_preferred":[
        "\u803f\u96c6"
    ],
    "wof:name":"Gengji",
    "wof:placetype":"locality"
},
  "geometry": {"coordinates":[117.65009000000001,34.36591],"type":"Point"}
}