{
  "type": "Feature",
  "properties": {
    "gn:admin1_code":"11.0",
    "gn:asciiname":"Mujiachong",
    "gn:country_code":"CN",
    "gn:dem":287,
    "gn:feature_class":"P",
    "gn:feature_code":"PPL",
    "gn:name":"Mujiachong",
    "gn:population":0,
    "gn:timezone":"Asia/Shanghai",
    "iso:country":"CN",
    "name:zho_x_preferred":[
        "\u6728\u5bb6\u51b2"
    ],
    "wof:name":"Mujiachong",
    "wof:placetype":"locality"
},
  "geometry": {"coordinates":[110.01755,26.80819],"type":"Point"}
}