{
  "type": "Feature",
  "properties": {
    "gn:admin1_code":"32.0",
    "gn:asciiname":"Huaqiu",
    "gn:country_code":"CN",
    "gn:dem":3003,
    "gn:feature_class":"P",
    "gn:feature_code":"PPL",
    "gn:name":"Huaqiu",
    "gn:population":0,
    "gn:timezone":"Asia/Shanghai",
    "iso:country":"CN",
    "name:zho_x_preferred":[
        "\u534e\u4e18"
    ],
    "wof:name":"Huaqiu",
    "wof:placetype":"locality"
},
  "geometry": {"coordinates":[101.52200000000001,28.9554],"type":"Point"}
}