{
  "type": "Feature",
  "properties": {
    "gn:admin1_code":"26.0",
    "gn:asciiname":"Dajiekou",
    "gn:country_code":"CN",
    "gn:dem":1339,
    "gn:feature_class":"P",
    "gn:feature_code":"PPL",
    "gn:name":"Dajiekou",
    "gn:population":0,
    "gn:timezone":"Asia/Shanghai",
    "iso:country":"CN",
    "name:zho_x_preferred":[
        "\u5927\u4ecb\u53e3"
    ],
    "wof:name":"Dajiekou",
    "wof:placetype":"locality"
},
  "geometry": {"coordinates":[109.07408999999998,37.35789000000001],"type":"Point"}
}