{
  "type": "Feature",
  "properties": {
    "gn:admin1_code":"03",
    "gn:asciiname":"Luoping",
    "gn:country_code":"CN",
    "gn:dem":107,
    "gn:feature_class":"P",
    "gn:feature_code":"PPLA4",
    "gn:name":"Luoping",
    "gn:population":0,
    "gn:timezone":"Asia/Shanghai",
    "iso:country":"CN",
    "name:und_x_variant":[
        "\u7f57\u576a",
        "Luoping Zhen",
        "\u7f57\u576a\u9547"
    ],
    "wof:name":"Luoping",
    "wof:placetype":"locality"
},
  "geometry": {"coordinates":[115.25738,29.23182000000001],"type":"Point"}
}