{
  "type": "Feature",
  "properties": {
    "gn:admin1_code":"14.0",
    "gn:asciiname":"Landengka",
    "gn:country_code":"CN",
    "gn:dem":4735,
    "gn:feature_class":"P",
    "gn:feature_code":"PPL",
    "gn:name":"Landengka",
    "gn:population":0,
    "gn:timezone":"Asia/Urumqi",
    "iso:country":"CN",
    "name:zho_x_preferred":[
        "\u6984\u767b\u5361"
    ],
    "wof:name":"Landengka",
    "wof:placetype":"locality"
},
  "geometry": {"coordinates":[95.15533000000001,31.65235],"type":"Point"}
}