{
  "type": "Feature",
  "properties": {
    "gn:admin1_code":"29.0",
    "gn:asciiname":"Biquan",
    "gn:country_code":"CN",
    "gn:dem":1337,
    "gn:feature_class":"P",
    "gn:feature_code":"PPL",
    "gn:name":"Biquan",
    "gn:population":0,
    "gn:timezone":"Asia/Shanghai",
    "iso:country":"CN",
    "name:zho_x_preferred":[
        "\u78a7\u6cc9"
    ],
    "wof:name":"Biquan",
    "wof:placetype":"locality"
},
  "geometry": {"coordinates":[101.029,26.4402],"type":"Point"}
}