{
  "type": "Feature",
  "properties": {
    "gn:admin1_code":"1.0",
    "gn:asciiname":"Yuanxucun",
    "gn:country_code":"CN",
    "gn:dem":59,
    "gn:feature_class":"P",
    "gn:feature_code":"PPL",
    "gn:name":"Yuanxucun",
    "gn:population":0,
    "gn:timezone":"Asia/Shanghai",
    "iso:country":"CN",
    "name:zho_x_preferred":[
        "\u8881\u5729\u6751"
    ],
    "wof:name":"Yuanxucun",
    "wof:placetype":"locality"
},
  "geometry": {"coordinates":[116.13768,31.99146],"type":"Point"}
}