{
  "type": "Feature",
  "properties": {
    "gn:admin1_code":"7",
    "gn:asciiname":"Fengxie",
    "gn:country_code":"CN",
    "gn:dem":550,
    "gn:feature_class":"P",
    "gn:feature_code":"PPL",
    "gn:name":"Fengxie",
    "gn:population":0,
    "gn:timezone":"Asia/Shanghai",
    "iso:country":"CN",
    "wof:name":"Fengxie",
    "wof:placetype":"locality"
},
  "geometry": {"coordinates":[116.82693999999999,25.12667],"type":"Point"}
}