{
  "type": "Feature",
  "properties": {
    "gn:admin1_code":"1.0",
    "gn:asciiname":"Xiaoling",
    "gn:country_code":"CN",
    "gn:dem":214,
    "gn:feature_class":"P",
    "gn:feature_code":"PPL",
    "gn:name":"Xiaoling",
    "gn:population":0,
    "gn:timezone":"Asia/Shanghai",
    "iso:country":"CN",
    "name:swe_x_preferred":[
        "Xiaoling"
    ],
    "name:zho_x_preferred":[
        "\u5c0f\u5cad"
    ],
    "wof:name":"Xiaoling",
    "wof:placetype":"locality"
},
  "geometry": {"coordinates":[118.42167999999999,30.27737],"type":"Point"}
}