{
  "type": "Feature",
  "properties": {
    "gn:admin1_code":"19",
    "gn:asciiname":"Tangtu",
    "gn:country_code":"CN",
    "gn:dem":175,
    "gn:feature_class":"P",
    "gn:feature_code":"PPLA4",
    "gn:name":"Tangtu",
    "gn:population":0,
    "gn:timezone":"Asia/Shanghai",
    "iso:country":"CN",
    "name:und_x_variant":[
        "T\u2019ang-t\u2019u-huo-lo",
        "Tangtu",
        "\u6c64\u56fe",
        "Tangtu Manzu Xiang",
        "\u6c64\u56fe\u6ee1\u65cf\u4e61"
    ],
    "wof:name":"Tangtu",
    "wof:placetype":"locality"
},
  "geometry": {"coordinates":[124.33695,41.82723],"type":"Point"}
}