{
  "type": "Feature",
  "properties": {
    "gn:admin1_code":"11.0",
    "gn:asciiname":"Xiangluwan",
    "gn:country_code":"CN",
    "gn:dem":542,
    "gn:feature_class":"P",
    "gn:feature_code":"PPL",
    "gn:name":"Xiangluwan",
    "gn:population":0,
    "gn:timezone":"Asia/Shanghai",
    "iso:country":"CN",
    "name:zho_x_preferred":[
        "\u9999\u7089\u6e7e"
    ],
    "wof:name":"Xiangluwan",
    "wof:placetype":"locality"
},
  "geometry": {"coordinates":[110.92443,27.62769],"type":"Point"}
}