{
  "type": "Feature",
  "properties": {
    "gn:admin1_code":"11.0",
    "gn:asciiname":"Mishanqiao",
    "gn:country_code":"CN",
    "gn:dem":86,
    "gn:feature_class":"P",
    "gn:feature_code":"PPL",
    "gn:name":"Mishanqiao",
    "gn:population":0,
    "gn:timezone":"Asia/Shanghai",
    "iso:country":"CN",
    "name:zho_x_preferred":[
        "\u7c73\u5c71\u6865"
    ],
    "wof:name":"Mishanqiao",
    "wof:placetype":"locality"
},
  "geometry": {"coordinates":[113.28278,28.56607],"type":"Point"}
}