{
  "type": "Feature",
  "properties": {
    "gn:admin1_code":"4.0",
    "gn:asciiname":"Houshe",
    "gn:country_code":"CN",
    "gn:dem":5,
    "gn:feature_class":"P",
    "gn:feature_code":"PPL",
    "gn:name":"Houshe",
    "gn:population":0,
    "gn:timezone":"Asia/Shanghai",
    "iso:country":"CN",
    "name:zho_x_preferred":[
        "Houshe"
    ],
    "name:zho_x_variant":[
        "\u540e\u820d"
    ],
    "wof:name":"Houshe",
    "wof:placetype":"locality"
},
  "geometry": {"coordinates":[121.45578999999999,32.04077],"type":"Point"}
}