{
  "type": "Feature",
  "properties": {
    "gn:admin1_code":"12.0",
    "gn:asciiname":"Sangshuba",
    "gn:country_code":"CN",
    "gn:dem":631,
    "gn:feature_class":"P",
    "gn:feature_code":"PPL",
    "gn:name":"Sangshuba",
    "gn:population":0,
    "gn:timezone":"Asia/Shanghai",
    "iso:country":"CN",
    "name:zho_x_preferred":[
        "\u6851\u6811\u575d"
    ],
    "wof:name":"Sangshuba",
    "wof:placetype":"locality"
},
  "geometry": {"coordinates":[110.01367,32.23234],"type":"Point"}
}