{
  "type": "Feature",
  "properties": {
    "gn:admin1_code":"16.0",
    "gn:asciiname":"Nongling",
    "gn:country_code":"CN",
    "gn:dem":827,
    "gn:feature_class":"P",
    "gn:feature_code":"PPL",
    "gn:name":"Nongling",
    "gn:population":0,
    "gn:timezone":"Asia/Shanghai",
    "iso:country":"CN",
    "name:zho_x_preferred":[
        "\u5f04\u9886"
    ],
    "wof:name":"Nongling",
    "wof:placetype":"locality"
},
  "geometry": {"coordinates":[107.154,24.4671],"type":"Point"}
}