{
  "type": "Feature",
  "properties": {
    "gn:admin1_code":"14.0",
    "gn:asciiname":"Baige",
    "gn:country_code":"CN",
    "gn:dem":3705,
    "gn:feature_class":"P",
    "gn:feature_code":"PPL",
    "gn:name":"Baige",
    "gn:population":0,
    "gn:timezone":"Asia/Urumqi",
    "iso:country":"CN",
    "name:zho_x_preferred":[
        "\u767d\u683c"
    ],
    "wof:name":"Baige",
    "wof:placetype":"locality"
},
  "geometry": {"coordinates":[98.69999,31.07244],"type":"Point"}
}