{
  "type": "Feature",
  "properties": {
    "gn:admin1_code":"26.0",
    "gn:asciiname":"Haota",
    "gn:country_code":"CN",
    "gn:dem":296,
    "gn:feature_class":"P",
    "gn:feature_code":"PPL",
    "gn:name":"Haota",
    "gn:population":0,
    "gn:timezone":"Asia/Shanghai",
    "iso:country":"CN",
    "name:und_x_variant":[
        "Haotanzi"
    ],
    "name:zho_x_preferred":[
        "\u84bf\u5854"
    ],
    "name:zho_x_variant":[
        "\u84bf\u6ee9\u5b50"
    ],
    "wof:name":"Haota",
    "wof:placetype":"locality"
},
  "geometry": {"coordinates":[109.53972,32.90122],"type":"Point"}
}