{
  "type": "Feature",
  "properties": {
    "gn:admin1_code":"9.0",
    "gn:asciiname":"Dajizhuang",
    "gn:country_code":"CN",
    "gn:dem":184,
    "gn:feature_class":"P",
    "gn:feature_code":"PPL",
    "gn:name":"Dajizhuang",
    "gn:population":0,
    "gn:timezone":"Asia/Shanghai",
    "iso:country":"CN",
    "name:und_x_variant":[
        "\u5927\u5409\u5e84",
        "Dajizhuang"
    ],
    "wof:name":"Dajizhuang",
    "wof:placetype":"locality"
},
  "geometry": {"coordinates":[112.48451,33.2426],"type":"Point"}
}