{
  "type": "Feature",
  "properties": {
    "gn:admin1_code":"15.0",
    "gn:asciiname":"Baitaoban",
    "gn:country_code":"CN",
    "gn:dem":1236,
    "gn:feature_class":"P",
    "gn:feature_code":"PPL",
    "gn:name":"Baitaoban",
    "gn:population":0,
    "gn:timezone":"Asia/Shanghai",
    "iso:country":"CN",
    "name:zho_x_preferred":[
        "\u767d\u6843\u73ed"
    ],
    "wof:name":"Baitaoban",
    "wof:placetype":"locality"
},
  "geometry": {"coordinates":[107.861,35.6604],"type":"Point"}
}