{
  "type": "Feature",
  "properties": {
    "gn:admin1_code":"3.0",
    "gn:asciiname":"Nanyang Houzhang",
    "gn:country_code":"CN",
    "gn:dem":68,
    "gn:feature_class":"P",
    "gn:feature_code":"PPL",
    "gn:name":"Nanyang Houzhang",
    "gn:population":0,
    "gn:timezone":"Asia/Shanghai",
    "iso:country":"CN",
    "name:und_x_variant":[
        "\u5357\u9633\u540e\u5f20"
    ],
    "wof:name":"Nanyang Houzhang",
    "wof:placetype":"locality"
},
  "geometry": {"coordinates":[115.55628,29.32332],"type":"Point"}
}