{
  "type": "Feature",
  "properties": {
    "gn:admin1_code":"29.0",
    "gn:asciiname":"Shangdaqing",
    "gn:country_code":"CN",
    "gn:dem":2129,
    "gn:feature_class":"P",
    "gn:feature_code":"PPL",
    "gn:name":"Shangdaqing",
    "gn:population":0,
    "gn:timezone":"Asia/Shanghai",
    "iso:country":"CN",
    "name:zho_x_preferred":[
        "\u4e0a\u5927\u7b90"
    ],
    "wof:name":"Shangdaqing",
    "wof:placetype":"locality"
},
  "geometry": {"coordinates":[103.70999999999999,27.0143],"type":"Point"}
}