{
  "type": "Feature",
  "properties": {
    "gn:admin1_code":"26.0",
    "gn:asciiname":"Xiaoxulu",
    "gn:country_code":"CN",
    "gn:dem":1237,
    "gn:feature_class":"P",
    "gn:feature_code":"PPL",
    "gn:name":"Xiaoxul\u00fc",
    "gn:population":0,
    "gn:timezone":"Asia/Shanghai",
    "iso:country":"CN",
    "name:und_x_variant":[
        "Xiaoxul\u00fc"
    ],
    "name:zho_x_preferred":[
        "\u5c0f\u65ed\u5415"
    ],
    "wof:name":"Xiaoxulu",
    "wof:placetype":"locality"
},
  "geometry": {"coordinates":[109.22273,38.33443],"type":"Point"}
}