{
  "type": "Feature",
  "properties": {
    "gn:admin1_code":"10",
    "gn:asciiname":"Dongluzhuang",
    "gn:country_code":"CN",
    "gn:dem":18,
    "gn:feature_class":"P",
    "gn:feature_code":"PPL",
    "gn:name":"Dongluzhuang",
    "gn:population":0,
    "gn:timezone":"Asia/Shanghai",
    "iso:country":"CN",
    "name:zho_x_preferred":[
        "\u4e1c\u82a6\u5e84"
    ],
    "wof:name":"Dongluzhuang",
    "wof:placetype":"locality"
},
  "geometry": {"coordinates":[116.29375,37.83175],"type":"Point"}
}