{
  "type": "Feature",
  "properties": {
    "gn:admin1_code":"32.0",
    "gn:asciiname":"Wutongqiao",
    "gn:cc2":"CN",
    "gn:country_code":"CN",
    "gn:dem":373,
    "gn:feature_class":"P",
    "gn:feature_code":"PPL",
    "gn:name":"Wutongqiao",
    "gn:population":0,
    "gn:timezone":"Asia/Shanghai",
    "iso:country":"CN",
    "name:und_x_variant":[
        "Wutungkiao",
        "Wu-t\u2019ung-ch\u2019iao-shih",
        "Wu-t\u2019ung-ch\u2019iao",
        "Wutongqiao"
    ],
    "name:zho_x_preferred":[
        "\u4e94\u901a\u6865"
    ],
    "wof:name":"Wutongqiao",
    "wof:placetype":"locality"
},
  "geometry": {"coordinates":[103.84999999999999,29.35],"type":"Point"}
}