{
  "type": "Feature",
  "properties": {
    "gn:admin1_code":"4.0",
    "gn:asciiname":"Hulou",
    "gn:country_code":"CN",
    "gn:dem":3,
    "gn:feature_class":"P",
    "gn:feature_code":"PPL",
    "gn:name":"Hulou",
    "gn:population":0,
    "gn:timezone":"Asia/Shanghai",
    "iso:country":"CN",
    "name:zho_x_preferred":[
        "Hulou"
    ],
    "name:zho_x_variant":[
        "\u80e1\u697c"
    ],
    "wof:name":"Hulou",
    "wof:placetype":"locality"
},
  "geometry": {"coordinates":[119.93257,33.24032],"type":"Point"}
}