{
  "type": "Feature",
  "properties": {
    "gn:admin1_code":"11",
    "gn:asciiname":"Shimen",
    "gn:country_code":"CN",
    "gn:dem":482,
    "gn:feature_class":"P",
    "gn:feature_code":"PPL",
    "gn:name":"Shimen",
    "gn:population":0,
    "gn:timezone":"Asia/Shanghai",
    "iso:country":"CN",
    "wof:name":"Shimen",
    "wof:placetype":"locality"
},
  "geometry": {"coordinates":[110.67333000000001,26.51167],"type":"Point"}
}