{
  "type": "Feature",
  "properties": {
    "gn:admin1_code":"16.0",
    "gn:asciiname":"Lizhigen",
    "gn:country_code":"CN",
    "gn:dem":56,
    "gn:feature_class":"P",
    "gn:feature_code":"PPL",
    "gn:name":"Lizhigen",
    "gn:population":0,
    "gn:timezone":"Asia/Shanghai",
    "iso:country":"CN",
    "name:zho_x_preferred":[
        "\u8354\u679d\u6839"
    ],
    "wof:name":"Lizhigen",
    "wof:placetype":"locality"
},
  "geometry": {"coordinates":[109.854,22.0097],"type":"Point"}
}