{
  "type": "Feature",
  "properties": {
    "gn:admin1_code":"25",
    "gn:asciiname":"Xishuangjing",
    "gn:country_code":"CN",
    "gn:dem":11,
    "gn:feature_class":"P",
    "gn:feature_code":"PPL",
    "gn:name":"Xishuangjing",
    "gn:population":0,
    "gn:timezone":"Asia/Shanghai",
    "iso:country":"CN",
    "name:zho_x_preferred":[
        "\u897f\u53cc\u4e95"
    ],
    "wof:name":"Xishuangjing",
    "wof:placetype":"locality"
},
  "geometry": {"coordinates":[118.33,37.6184],"type":"Point"}
}