{
  "type": "Feature",
  "properties": {
    "gn:admin1_code":"24.0",
    "gn:asciiname":"Nanyuancun",
    "gn:country_code":"CN",
    "gn:dem":468,
    "gn:feature_class":"P",
    "gn:feature_code":"PPL",
    "gn:name":"Nanyuancun",
    "gn:population":0,
    "gn:timezone":"Asia/Shanghai",
    "iso:country":"CN",
    "name:zho_x_preferred":[
        "\u5357\u539f\u6751"
    ],
    "wof:name":"Nanyuancun",
    "wof:placetype":"locality"
},
  "geometry": {"coordinates":[110.72095,35.52421],"type":"Point"}
}