{
  "type": "Feature",
  "properties": {
    "gn:admin1_code":"14.0",
    "gn:asciiname":"Logtang",
    "gn:country_code":"CN",
    "gn:dem":4250,
    "gn:feature_class":"P",
    "gn:feature_code":"PPL",
    "gn:name":"Logtang",
    "gn:population":0,
    "gn:timezone":"Asia/Urumqi",
    "iso:country":"CN",
    "name:bod_x_preferred":[
        "Logtang"
    ],
    "name:zho_x_preferred":[
        "Luotang"
    ],
    "name:zho_x_variant":[
        "\u6d1b\u5858",
        "Mairi Gongshe",
        "\u9ea6\u65e5\u516c\u793e"
    ],
    "wof:name":"Logtang",
    "wof:placetype":"locality"
},
  "geometry": {"coordinates":[96.18333,31.16667],"type":"Point"}
}