{
  "type": "Feature",
  "properties": {
    "gn:admin1_code":"9.0",
    "gn:asciiname":"Guanziling",
    "gn:country_code":"CN",
    "gn:dem":479,
    "gn:feature_class":"P",
    "gn:feature_code":"PPL",
    "gn:name":"Guanziling",
    "gn:population":0,
    "gn:timezone":"Asia/Shanghai",
    "iso:country":"CN",
    "name:zho_x_preferred":[
        "\u51a0\u5b50\u5cad"
    ],
    "wof:name":"Guanziling",
    "wof:placetype":"locality"
},
  "geometry": {"coordinates":[112.92352,34.40617],"type":"Point"}
}