{
  "type": "Feature",
  "properties": {
    "gn:admin1_code":"2.0",
    "gn:asciiname":"Maowuli",
    "gn:country_code":"CN",
    "gn:dem":70,
    "gn:feature_class":"P",
    "gn:feature_code":"PPL",
    "gn:name":"Maowuli",
    "gn:population":0,
    "gn:timezone":"Asia/Shanghai",
    "iso:country":"CN",
    "name:und_x_variant":[
        "\u6bdb\u575e\u91cc"
    ],
    "name:zho_x_preferred":[
        "Maowuli"
    ],
    "wof:name":"Maowuli",
    "wof:placetype":"locality"
},
  "geometry": {"coordinates":[119.80405,30.0119],"type":"Point"}
}