{
  "type": "Feature",
  "properties": {
    "gn:admin1_code":"24.0",
    "gn:asciiname":"Yuwu",
    "gn:cc2":"CN",
    "gn:country_code":"CN",
    "gn:dem":958,
    "gn:feature_class":"P",
    "gn:feature_code":"PPL",
    "gn:name":"Yuwu",
    "gn:population":0,
    "gn:timezone":"Asia/Shanghai",
    "iso:country":"CN",
    "name:und_x_variant":[
        "Y\u00fc-wu-chen",
        "Yuwu"
    ],
    "wof:name":"Yuwu",
    "wof:placetype":"locality"
},
  "geometry": {"coordinates":[112.83333,36.38333],"type":"Point"}
}