{
  "type": "Feature",
  "properties": {
    "gn:admin1_code":"24.0",
    "gn:asciiname":"Sangli",
    "gn:country_code":"CN",
    "gn:dem":1186,
    "gn:feature_class":"P",
    "gn:feature_code":"PPL",
    "gn:name":"Sangli",
    "gn:population":0,
    "gn:timezone":"Asia/Shanghai",
    "iso:country":"CN",
    "name:zho_x_preferred":[
        "\u6851\u68a8"
    ],
    "wof:name":"Sangli",
    "wof:placetype":"locality"
},
  "geometry": {"coordinates":[111.01264,37.20966],"type":"Point"}
}