{
  "type": "Feature",
  "properties": {
    "gn:admin1_code":"14.0",
    "gn:asciiname":"Quzhongcun",
    "gn:country_code":"CN",
    "gn:dem":4383,
    "gn:feature_class":"P",
    "gn:feature_code":"PPL",
    "gn:name":"Quzhongcun",
    "gn:population":0,
    "gn:timezone":"Asia/Urumqi",
    "iso:country":"CN",
    "name:zho_x_preferred":[
        "\u66f2\u4ef2\u6751"
    ],
    "wof:name":"Quzhongcun",
    "wof:placetype":"locality"
},
  "geometry": {"coordinates":[93.70059999999999,32.22546],"type":"Point"}
}