{
  "type": "Feature",
  "properties": {
    "gn:admin1_code":"11.0",
    "gn:asciiname":"Wosha",
    "gn:country_code":"CN",
    "gn:dem":85,
    "gn:feature_class":"P",
    "gn:feature_code":"PPL",
    "gn:name":"Wosha",
    "gn:population":0,
    "gn:timezone":"Asia/Shanghai",
    "iso:country":"CN",
    "name:zho_x_preferred":[
        "Wosha"
    ],
    "name:zho_x_variant":[
        "\u6c83\u6c99"
    ],
    "wof:name":"Wosha",
    "wof:placetype":"locality"
},
  "geometry": {"coordinates":[111.59116000000002,29.48167],"type":"Point"}
}