{
  "type": "Feature",
  "properties": {
    "gn:admin1_code":"12.0",
    "gn:asciiname":"Pengjiawan",
    "gn:country_code":"CN",
    "gn:dem":153,
    "gn:feature_class":"P",
    "gn:feature_code":"PPL",
    "gn:name":"Pengjiawan",
    "gn:population":0,
    "gn:timezone":"Asia/Shanghai",
    "iso:country":"CN",
    "name:zho_x_preferred":[
        "\u5f6d\u5bb6\u6e7e"
    ],
    "wof:name":"Pengjiawan",
    "wof:placetype":"locality"
},
  "geometry": {"coordinates":[111.84068000000001,31.2829],"type":"Point"}
}