{
  "type": "Feature",
  "properties": {
    "gn:admin1_code":"26.0",
    "gn:asciiname":"Hujiayaozi",
    "gn:country_code":"CN",
    "gn:dem":739,
    "gn:feature_class":"P",
    "gn:feature_code":"PPL",
    "gn:name":"Hujiayaozi",
    "gn:population":0,
    "gn:timezone":"Asia/Shanghai",
    "iso:country":"CN",
    "name:zho_x_preferred":[
        "\u547c\u5bb6\u7a91\u5b50"
    ],
    "wof:name":"Hujiayaozi",
    "wof:placetype":"locality"
},
  "geometry": {"coordinates":[110.32979,36.24494],"type":"Point"}
}