{
  "type": "Feature",
  "properties": {
    "gn:admin1_code":"5",
    "gn:asciiname":"Xianjin",
    "gn:country_code":"CN",
    "gn:dem":272,
    "gn:feature_class":"P",
    "gn:feature_code":"PPL",
    "gn:name":"Xianjin",
    "gn:population":0,
    "gn:timezone":"Asia/Shanghai",
    "iso:country":"CN",
    "name:zho_x_preferred":[
        "\u5148\u8fdb"
    ],
    "wof:name":"Xianjin",
    "wof:placetype":"locality"
},
  "geometry": {"coordinates":[127.283,43.5211],"type":"Point"}
}