{
  "type": "Feature",
  "properties": {
    "gn:admin1_code":"25.0",
    "gn:asciiname":"Dayuwan",
    "gn:country_code":"CN",
    "gn:dem":29,
    "gn:feature_class":"P",
    "gn:feature_code":"PPL",
    "gn:name":"Dayuwan",
    "gn:population":0,
    "gn:timezone":"Asia/Shanghai",
    "iso:country":"CN",
    "name:zho_x_preferred":[
        "\u5927\u7389\u6e7e"
    ],
    "wof:name":"Dayuwan",
    "wof:placetype":"locality"
},
  "geometry": {"coordinates":[120.13415000000001,36.67596],"type":"Point"}
}