{
  "type": "Feature",
  "properties": {
    "gn:admin1_code":"15.0",
    "gn:asciiname":"Niujiazhuang",
    "gn:country_code":"CN",
    "gn:dem":1947,
    "gn:feature_class":"P",
    "gn:feature_code":"PPL",
    "gn:name":"Niujiazhuang",
    "gn:population":0,
    "gn:timezone":"Asia/Shanghai",
    "iso:country":"CN",
    "name:und_x_variant":[
        "\u725b\u5bb6\u5e84"
    ],
    "wof:name":"Niujiazhuang",
    "wof:placetype":"locality"
},
  "geometry": {"coordinates":[105.19647000000001,33.65965],"type":"Point"}
}