{
  "type": "Feature",
  "properties": {
    "gn:admin1_code":"8.0",
    "gn:asciiname":"Yanjun Liudui",
    "gn:country_code":"CN",
    "gn:dem":73,
    "gn:feature_class":"P",
    "gn:feature_code":"PPLF",
    "gn:name":"Yanjun Liudui",
    "gn:population":0,
    "gn:timezone":"Asia/Shanghai",
    "iso:country":"CN",
    "name:zho_x_preferred":[
        "\u5ef6\u519b\u516d\u961f"
    ],
    "wof:name":"Yanjun Liudui",
    "wof:placetype":"locality"
},
  "geometry": {"coordinates":[130.90929,47.78848],"type":"Point"}
}