{
  "type": "Feature",
  "properties": {
    "gn:admin1_code":"9.0",
    "gn:asciiname":"Changling",
    "gn:country_code":"CN",
    "gn:dem":1001,
    "gn:feature_class":"P",
    "gn:feature_code":"PPL",
    "gn:name":"Changling",
    "gn:population":0,
    "gn:timezone":"Asia/Shanghai",
    "iso:country":"CN",
    "name:und_x_variant":[
        "\u957f\u5cad",
        "Changling"
    ],
    "wof:name":"Changling",
    "wof:placetype":"locality"
},
  "geometry": {"coordinates":[112.25776,33.63189000000001],"type":"Point"}
}