{
  "type": "Feature",
  "properties": {
    "gn:admin1_code":"1.0",
    "gn:asciiname":"Duanzhuangcun",
    "gn:country_code":"CN",
    "gn:dem":40,
    "gn:feature_class":"P",
    "gn:feature_code":"PPL",
    "gn:name":"Duanzhuangcun",
    "gn:population":0,
    "gn:timezone":"Asia/Shanghai",
    "iso:country":"CN",
    "name:zho_x_preferred":[
        "\u6bb5\u5e84\u6751"
    ],
    "wof:name":"Duanzhuangcun",
    "wof:placetype":"locality"
},
  "geometry": {"coordinates":[115.26508,32.8349],"type":"Point"}
}