{
  "type": "Feature",
  "properties": {
    "gn:admin1_code":"30.0",
    "gn:asciiname":"Sili",
    "gn:country_code":"CN",
    "gn:dem":-4,
    "gn:feature_class":"P",
    "gn:feature_code":"PPL",
    "gn:name":"Sili",
    "gn:population":0,
    "gn:timezone":"Asia/Shanghai",
    "iso:country":"CN",
    "name:cat_x_preferred":[
        "Sili"
    ],
    "name:ceb_x_preferred":[
        "Sili"
    ],
    "name:swe_x_preferred":[
        "Sili"
    ],
    "name:zho_x_preferred":[
        "\u6cd7\u6ca5"
    ],
    "wof:name":"Sili",
    "wof:placetype":"locality"
},
  "geometry": {"coordinates":[113.14887,23.11549],"type":"Point"}
}