{
  "type": "Feature",
  "properties": {
    "gn:admin1_code":"8.0",
    "gn:asciiname":"Taiqingcun",
    "gn:country_code":"CN",
    "gn:dem":110,
    "gn:feature_class":"P",
    "gn:feature_code":"PPL",
    "gn:name":"Taiqingcun",
    "gn:population":0,
    "gn:timezone":"Asia/Shanghai",
    "iso:country":"CN",
    "name:zho_x_preferred":[
        "\u592a\u5e86\u6751"
    ],
    "wof:name":"Taiqingcun",
    "wof:placetype":"locality"
},
  "geometry": {"coordinates":[130.67136000000002,46.75373],"type":"Point"}
}