{
  "type": "Feature",
  "properties": {
    "gn:admin1_code":"16.0",
    "gn:asciiname":"Huangtangwei",
    "gn:country_code":"CN",
    "gn:dem":50,
    "gn:feature_class":"P",
    "gn:feature_code":"PPL",
    "gn:name":"Huangtangwei",
    "gn:population":0,
    "gn:timezone":"Asia/Shanghai",
    "iso:country":"CN",
    "name:zho_x_preferred":[
        "\u8352\u5858\u5c3e"
    ],
    "wof:name":"Huangtangwei",
    "wof:placetype":"locality"
},
  "geometry": {"coordinates":[109.06699999999999,21.8347],"type":"Point"}
}