{
  "type": "Feature",
  "properties": {
    "gn:admin1_code":"3.0",
    "gn:asciiname":"Hongyan",
    "gn:country_code":"CN",
    "gn:dem":59,
    "gn:feature_class":"P",
    "gn:feature_code":"PPLA4",
    "gn:name":"Hongyan",
    "gn:population":0,
    "gn:timezone":"Asia/Shanghai",
    "iso:country":"CN",
    "name:ceb_x_preferred":[
        "Hongyan"
    ],
    "name:deu_x_preferred":[
        "Hongyan"
    ],
    "name:ita_x_preferred":[
        "Hongyan"
    ],
    "name:swe_x_preferred":[
        "Hongyan"
    ],
    "name:und_x_variant":[
        "\u6d2a\u5ca9",
        "Hongyan Zhen",
        "\u6d2a\u5ca9\u9547"
    ],
    "wof:name":"Hongyan",
    "wof:placetype":"locality"
},
  "geometry": {"coordinates":[117.46299,29.03997],"type":"Point"}
}