{
  "type": "Feature",
  "properties": {
    "gn:admin1_code":"19.0",
    "gn:asciiname":"Pijiagou",
    "gn:country_code":"CN",
    "gn:dem":96,
    "gn:feature_class":"P",
    "gn:feature_code":"PPL",
    "gn:name":"Pijiagou",
    "gn:population":0,
    "gn:timezone":"Asia/Shanghai",
    "iso:country":"CN",
    "name:und_x_variant":[
        "\u76ae\u5bb6\u6c9f"
    ],
    "name:zho_x_preferred":[
        "\u76ae\u5bb6\u6c9f"
    ],
    "wof:name":"Pijiagou",
    "wof:placetype":"locality"
},
  "geometry": {"coordinates":[121.16750999999999,41.51477],"type":"Point"}
}