{
  "type": "Feature",
  "properties": {
    "gn:admin1_code":"11.0",
    "gn:asciiname":"Changjiang",
    "gn:country_code":"CN",
    "gn:dem":171,
    "gn:feature_class":"P",
    "gn:feature_code":"PPL",
    "gn:name":"Changjiang",
    "gn:population":0,
    "gn:timezone":"Asia/Shanghai",
    "iso:country":"CN",
    "name:zho_x_preferred":[
        "\u660c\u6c5f"
    ],
    "wof:name":"Changjiang",
    "wof:placetype":"locality"
},
  "geometry": {"coordinates":[113.74850000000001,28.95269],"type":"Point"}
}