{
  "type": "Feature",
  "properties": {
    "gn:admin1_code":"1.0",
    "gn:asciiname":"Qishancun",
    "gn:country_code":"CN",
    "gn:dem":239,
    "gn:feature_class":"P",
    "gn:feature_code":"PPL",
    "gn:name":"Qishancun",
    "gn:population":0,
    "gn:timezone":"Asia/Shanghai",
    "iso:country":"CN",
    "name:zho_x_preferred":[
        "\u68cb\u5c71\u6751"
    ],
    "wof:name":"Qishancun",
    "wof:placetype":"locality"
},
  "geometry": {"coordinates":[118.67767000000001,29.92688],"type":"Point"}
}