{
  "type": "Feature",
  "properties": {
    "gn:admin1_code":"12.0",
    "gn:asciiname":"Sanfangdun",
    "gn:country_code":"CN",
    "gn:dem":22,
    "gn:feature_class":"P",
    "gn:feature_code":"PPL",
    "gn:name":"Sanfangdun",
    "gn:population":0,
    "gn:timezone":"Asia/Shanghai",
    "iso:country":"CN",
    "name:zho_x_preferred":[
        "\u4e09\u623f\u58a9"
    ],
    "wof:name":"Sanfangdun",
    "wof:placetype":"locality"
},
  "geometry": {"coordinates":[116.01591000000001,29.766],"type":"Point"}
}