{
  "type": "Feature",
  "properties": {
    "gn:admin1_code":"32.0",
    "gn:asciiname":"Haiziping",
    "gn:country_code":"CN",
    "gn:dem":1936,
    "gn:feature_class":"P",
    "gn:feature_code":"PPL",
    "gn:name":"Haiziping",
    "gn:population":0,
    "gn:timezone":"Asia/Shanghai",
    "iso:country":"CN",
    "name:zho_x_preferred":[
        "\u6d77\u5b50\u576a"
    ],
    "wof:name":"Haiziping",
    "wof:placetype":"locality"
},
  "geometry": {"coordinates":[102.211,29.9094],"type":"Point"}
}