{
  "type": "Feature",
  "properties": {
    "gn:admin1_code":"1.0",
    "gn:asciiname":"Sijijie",
    "gn:country_code":"CN",
    "gn:dem":191,
    "gn:feature_class":"P",
    "gn:feature_code":"PPL",
    "gn:name":"Sijijie",
    "gn:population":0,
    "gn:timezone":"Asia/Shanghai",
    "iso:country":"CN",
    "name:zho_x_preferred":[
        "\u56db\u5b63\u5c95"
    ],
    "wof:name":"Sijijie",
    "wof:placetype":"locality"
},
  "geometry": {"coordinates":[119.56992,31.10804000000001],"type":"Point"}
}