{
  "type": "Feature",
  "properties": {
    "gn:admin1_code":"29.0",
    "gn:asciiname":"Leidashi",
    "gn:country_code":"CN",
    "gn:dem":1354,
    "gn:feature_class":"P",
    "gn:feature_code":"PPL",
    "gn:name":"Leidashi",
    "gn:population":0,
    "gn:timezone":"Asia/Shanghai",
    "iso:country":"CN",
    "name:zho_x_preferred":[
        "\u96f7\u6253\u77f3"
    ],
    "wof:name":"Leidashi",
    "wof:placetype":"locality"
},
  "geometry": {"coordinates":[100.64,23.0953],"type":"Point"}
}