{
  "type": "Feature",
  "properties": {
    "gn:admin1_code":"4.0",
    "gn:asciiname":"Sunyinzhuang",
    "gn:country_code":"CN",
    "gn:dem":6,
    "gn:feature_class":"P",
    "gn:feature_code":"PPL",
    "gn:name":"Sunyinzhuang",
    "gn:population":0,
    "gn:timezone":"Asia/Shanghai",
    "iso:country":"CN",
    "name:zho_x_preferred":[
        "Sunyinzhuang"
    ],
    "name:zho_x_variant":[
        "\u5b59\u5c39\u5e84"
    ],
    "wof:name":"Sunyinzhuang",
    "wof:placetype":"locality"
},
  "geometry": {"coordinates":[119.07447999999999,33.24012],"type":"Point"}
}