{
  "type": "Feature",
  "properties": {
    "gn:admin1_code":"14.0",
    "gn:asciiname":"Shenzhenggongka",
    "gn:country_code":"CN",
    "gn:dem":3055,
    "gn:feature_class":"P",
    "gn:feature_code":"PPL",
    "gn:name":"Shenzhenggongka",
    "gn:population":0,
    "gn:timezone":"Asia/Urumqi",
    "iso:country":"CN",
    "name:zho_x_preferred":[
        "\u6df1\u6574\u8d21\u5361"
    ],
    "wof:name":"Shenzhenggongka",
    "wof:placetype":"locality"
},
  "geometry": {"coordinates":[97.95820000000001,28.98028],"type":"Point"}
}