{
  "type": "Feature",
  "properties": {
    "gn:admin1_code":"22",
    "gn:asciiname":"Hou'anling",
    "gn:country_code":"CN",
    "gn:dem":267,
    "gn:feature_class":"P",
    "gn:feature_code":"PPL",
    "gn:name":"Hou\u2019anling",
    "gn:population":0,
    "gn:timezone":"Asia/Shanghai",
    "iso:country":"CN",
    "name:und_x_variant":[
        "Hou\u2019anling"
    ],
    "name:zho_x_preferred":[
        "\u540e\u5b89\u5cad"
    ],
    "wof:name":"Hou'anling",
    "wof:placetype":"locality"
},
  "geometry": {"coordinates":[116.66293,40.67174],"type":"Point"}
}