{
  "type": "Feature",
  "properties": {
    "gn:admin1_code":"29.0",
    "gn:asciiname":"Fuha",
    "gn:country_code":"CN",
    "gn:dem":1729,
    "gn:feature_class":"P",
    "gn:feature_code":"PPL",
    "gn:name":"Fuha",
    "gn:population":0,
    "gn:timezone":"Asia/Shanghai",
    "iso:country":"CN",
    "name:zho_x_preferred":[
        "\u592b\u54c8"
    ],
    "wof:name":"Fuha",
    "wof:placetype":"locality"
},
  "geometry": {"coordinates":[102.187,22.8959],"type":"Point"}
}