{
  "type": "Feature",
  "properties": {
    "gn:admin1_code":"29.0",
    "gn:asciiname":"Dishiju",
    "gn:country_code":"CN",
    "gn:dem":1715,
    "gn:feature_class":"P",
    "gn:feature_code":"PPL",
    "gn:name":"Dishiju",
    "gn:population":0,
    "gn:timezone":"Asia/Shanghai",
    "iso:country":"CN",
    "name:zho_x_preferred":[
        "\u5730\u4ec0\u82f4"
    ],
    "wof:name":"Dishiju",
    "wof:placetype":"locality"
},
  "geometry": {"coordinates":[101.55,25.9513],"type":"Point"}
}