{
  "type": "Feature",
  "properties": {
    "gn:admin1_code":"9",
    "gn:asciiname":"Shanshiwang",
    "gn:country_code":"CN",
    "gn:dem":158,
    "gn:feature_class":"P",
    "gn:feature_code":"PPL",
    "gn:name":"Shanshiwang",
    "gn:population":0,
    "gn:timezone":"Asia/Shanghai",
    "iso:country":"CN",
    "name:zho_x_preferred":[
        "\u5c71\u77f3\u738b"
    ],
    "wof:name":"Shanshiwang",
    "wof:placetype":"locality"
},
  "geometry": {"coordinates":[113.83056000000001,34.54173],"type":"Point"}
}