{
  "type": "Feature",
  "properties": {
    "gn:admin1_code":"18",
    "gn:asciiname":"Zhaojiashan",
    "gn:country_code":"CN",
    "gn:dem":1211,
    "gn:feature_class":"P",
    "gn:feature_code":"PPL",
    "gn:name":"Zhaojiashan",
    "gn:population":0,
    "gn:timezone":"Asia/Shanghai",
    "iso:country":"CN",
    "name:zho_x_preferred":[
        "\u8d75\u5bb6\u5c71"
    ],
    "wof:name":"Zhaojiashan",
    "wof:placetype":"locality"
},
  "geometry": {"coordinates":[107.127,28.4943],"type":"Point"}
}