{
  "type": "Feature",
  "properties": {
    "gn:admin1_code":"26.0",
    "gn:asciiname":"Wangjiaqiao",
    "gn:country_code":"CN",
    "gn:dem":545,
    "gn:feature_class":"P",
    "gn:feature_code":"PPL",
    "gn:name":"Wangjiaqiao",
    "gn:population":0,
    "gn:timezone":"Asia/Shanghai",
    "iso:country":"CN",
    "name:und_x_variant":[
        "\u738b\u5bb6\u6865"
    ],
    "wof:name":"Wangjiaqiao",
    "wof:placetype":"locality"
},
  "geometry": {"coordinates":[106.86263999999998,33.04062],"type":"Point"}
}