{
  "type": "Feature",
  "properties": {
    "gn:admin1_code":"32.0",
    "gn:asciiname":"Dangshan",
    "gn:country_code":"CN",
    "gn:dem":790,
    "gn:feature_class":"P",
    "gn:feature_code":"PPL",
    "gn:name":"Dangshan",
    "gn:population":0,
    "gn:timezone":"Asia/Shanghai",
    "iso:country":"CN",
    "name:zho_x_preferred":[
        "\u6321\u5c71"
    ],
    "wof:name":"Dangshan",
    "wof:placetype":"locality"
},
  "geometry": {"coordinates":[107.56,31.9397],"type":"Point"}
}