{
  "type": "Feature",
  "properties": {
    "gn:admin1_code":"14.0",
    "gn:asciiname":"Yewa",
    "gn:country_code":"CN",
    "gn:dem":3776,
    "gn:feature_class":"P",
    "gn:feature_code":"PPL",
    "gn:name":"Yewa",
    "gn:population":0,
    "gn:timezone":"Asia/Urumqi",
    "iso:country":"CN",
    "name:cat_x_preferred":[
        "Regne d'Egbado"
    ],
    "name:deu_x_preferred":[
        "Yewa"
    ],
    "name:por_x_preferred":[
        "Egbado"
    ],
    "name:spa_x_preferred":[
        "Yew\u00e1"
    ],
    "name:zho_x_preferred":[
        "\u53f6\u54c7"
    ],
    "wof:name":"Yewa",
    "wof:placetype":"locality"
},
  "geometry": {"coordinates":[98.05305,30.55825],"type":"Point"}
}