{
  "type": "Feature",
  "properties": {
    "gn:admin1_code":"15.0",
    "gn:asciiname":"Xiaochengzi",
    "gn:country_code":"CN",
    "gn:dem":1583,
    "gn:feature_class":"P",
    "gn:feature_code":"PPL",
    "gn:name":"Xiaochengzi",
    "gn:population":0,
    "gn:timezone":"Asia/Shanghai",
    "iso:country":"CN",
    "name:und_x_variant":[
        "\u5c0f\u57ce\u5b50"
    ],
    "wof:name":"Xiaochengzi",
    "wof:placetype":"locality"
},
  "geometry": {"coordinates":[107.97239999999999,36.63759],"type":"Point"}
}