{
  "type": "Feature",
  "properties": {
    "gn:admin1_code":"30",
    "gn:asciiname":"Niuwanxu",
    "gn:country_code":"CN",
    "gn:dem":3,
    "gn:feature_class":"P",
    "gn:feature_code":"PPL",
    "gn:name":"Niuwanxu",
    "gn:population":0,
    "gn:timezone":"Asia/Shanghai",
    "iso:country":"CN",
    "name:und_x_variant":[
        "Niuwan",
        "Niuwanxu"
    ],
    "wof:name":"Niuwanxu",
    "wof:placetype":"locality"
},
  "geometry": {"coordinates":[112.84262,22.43885],"type":"Point"}
}