{
  "type": "Feature",
  "properties": {
    "gn:admin1_code":"32.0",
    "gn:asciiname":"Kerizewa",
    "gn:country_code":"CN",
    "gn:dem":4177,
    "gn:feature_class":"P",
    "gn:feature_code":"PPL",
    "gn:name":"Kerizewa",
    "gn:population":0,
    "gn:timezone":"Asia/Shanghai",
    "iso:country":"CN",
    "name:zho_x_preferred":[
        "\u514b\u65e5\u5219\u6d3c"
    ],
    "wof:name":"Kerizewa",
    "wof:placetype":"locality"
},
  "geometry": {"coordinates":[99.9495,29.9102],"type":"Point"}
}