{
  "type": "Feature",
  "properties": {
    "gn:admin1_code":"15.0",
    "gn:asciiname":"Majiakou",
    "gn:country_code":"CN",
    "gn:dem":2212,
    "gn:feature_class":"P",
    "gn:feature_code":"PPL",
    "gn:name":"Majiakou",
    "gn:population":0,
    "gn:timezone":"Asia/Shanghai",
    "iso:country":"CN",
    "name:und_x_variant":[
        "\u9a6c\u5bb6\u53e3"
    ],
    "wof:name":"Majiakou",
    "wof:placetype":"locality"
},
  "geometry": {"coordinates":[102.968,35.76],"type":"Point"}
}