{
  "type": "Feature",
  "properties": {
    "gn:admin1_code":"18",
    "gn:asciiname":"Mawo",
    "gn:country_code":"CN",
    "gn:dem":1567,
    "gn:feature_class":"P",
    "gn:feature_code":"PPL",
    "gn:name":"Mawo",
    "gn:population":0,
    "gn:timezone":"Asia/Shanghai",
    "iso:country":"CN",
    "name:zho_x_preferred":[
        "\u9ebb\u7a9d"
    ],
    "wof:name":"Mawo",
    "wof:placetype":"locality"
},
  "geometry": {"coordinates":[105.309,26.3358],"type":"Point"}
}