{
  "type": "Feature",
  "properties": {
    "gn:admin1_code":"14.0",
    "gn:asciiname":"Gedu",
    "gn:country_code":"CN",
    "gn:dem":4537,
    "gn:feature_class":"P",
    "gn:feature_code":"PPL",
    "gn:name":"Gedu",
    "gn:population":0,
    "gn:timezone":"Asia/Urumqi",
    "iso:country":"CN",
    "name:zho_x_preferred":[
        "\u683c\u90fd"
    ],
    "wof:name":"Gedu",
    "wof:placetype":"locality"
},
  "geometry": {"coordinates":[95.45423,31.3792],"type":"Point"}
}