{
  "type": "Feature",
  "properties": {
    "gn:admin1_code":"29.0",
    "gn:asciiname":"Ajidu",
    "gn:country_code":"CN",
    "gn:dem":1419,
    "gn:feature_class":"P",
    "gn:feature_code":"PPL",
    "gn:name":"Ajidu",
    "gn:population":0,
    "gn:timezone":"Asia/Shanghai",
    "iso:country":"CN",
    "name:zho_x_preferred":[
        "\u963f\u7ed9\u6e21"
    ],
    "wof:name":"Ajidu",
    "wof:placetype":"locality"
},
  "geometry": {"coordinates":[100.10599999999999,24.6799],"type":"Point"}
}