{
  "type": "Feature",
  "properties": {
    "gn:admin1_code":"20",
    "gn:asciiname":"Mo'er Daoga",
    "gn:country_code":"CN",
    "gn:dem":690,
    "gn:feature_class":"P",
    "gn:feature_code":"PPLA4",
    "gn:name":"Mo\u2019er Daoga",
    "gn:population":0,
    "gn:timezone":"Asia/Shanghai",
    "iso:country":"CN",
    "name:eng_x_preferred":[
        "Moridaga"
    ],
    "name:rus_x_preferred":[
        "\u041c\u043e\u0440\u0434\u0430\u0433\u0430"
    ],
    "name:und_x_variant":[
        "Mordaga",
        "Mo-erh-tao-ka",
        "Mo-erh-tao-a",
        "Moridaga Zhen",
        "Mo\u2019er Daoga",
        "Mo\u2019er Daoga Zhen"
    ],
    "name:zho_x_preferred":[
        "\u83ab\u5c14\u9053\u560e"
    ],
    "name:zho_x_variant":[
        "\u83ab\u5c14\u9053\u560e\u9547"
    ],
    "wof:name":"Mo'er Daoga",
    "wof:placetype":"locality"
},
  "geometry": {"coordinates":[120.77084000000001,51.25901],"type":"Point"}
}