{
  "type": "Feature",
  "properties": {
    "gn:admin1_code":"12.0",
    "gn:asciiname":"Zhoujiazhai",
    "gn:country_code":"CN",
    "gn:dem":39,
    "gn:feature_class":"P",
    "gn:feature_code":"PPL",
    "gn:name":"Zhoujiazhai",
    "gn:population":0,
    "gn:timezone":"Asia/Shanghai",
    "iso:country":"CN",
    "name:und_x_variant":[
        "\u5468\u5bb6\u5be8"
    ],
    "wof:name":"Zhoujiazhai",
    "wof:placetype":"locality"
},
  "geometry": {"coordinates":[114.2894,30.93101],"type":"Point"}
}