{
  "type": "Feature",
  "properties": {
    "gn:admin1_code":"1.0",
    "gn:asciiname":"Sunweicun",
    "gn:country_code":"CN",
    "gn:dem":8,
    "gn:feature_class":"P",
    "gn:feature_code":"PPL",
    "gn:name":"Sunweicun",
    "gn:population":0,
    "gn:timezone":"Asia/Shanghai",
    "iso:country":"CN",
    "name:zho_x_preferred":[
        "\u5b59\u5729\u6751"
    ],
    "wof:name":"Sunweicun",
    "wof:placetype":"locality"
},
  "geometry": {"coordinates":[117.20648,31.50971],"type":"Point"}
}