{
  "type": "Feature",
  "properties": {
    "gn:admin1_code":"9.0",
    "gn:asciiname":"Wangxiaogui",
    "gn:country_code":"CN",
    "gn:dem":76,
    "gn:feature_class":"P",
    "gn:feature_code":"PPL",
    "gn:name":"Wangxiaogui",
    "gn:population":0,
    "gn:timezone":"Asia/Shanghai",
    "iso:country":"CN",
    "name:zho_x_preferred":[
        "\u738b\u5c0f\u8d35"
    ],
    "wof:name":"Wangxiaogui",
    "wof:placetype":"locality"
},
  "geometry": {"coordinates":[113.6504,33.69271],"type":"Point"}
}