{
  "type": "Feature",
  "properties": {
    "gn:admin1_code":"13.0",
    "gn:asciiname":"Kalamou",
    "gn:country_code":"CN",
    "gn:dem":3216,
    "gn:feature_class":"P",
    "gn:feature_code":"PPL",
    "gn:name":"Kalamou",
    "gn:population":0,
    "gn:timezone":"Asia/Shanghai",
    "iso:country":"CN",
    "name:zho_x_preferred":[
        "\u5580\u62c9\u67d0"
    ],
    "wof:name":"Kalamou",
    "wof:placetype":"locality"
},
  "geometry": {"coordinates":[78.27018000000002,36.55414],"type":"Point"}
}