{
  "type": "Feature",
  "properties": {
    "gn:admin1_code":"26.0",
    "gn:asciiname":"Shiwanzi",
    "gn:country_code":"CN",
    "gn:dem":1219,
    "gn:feature_class":"P",
    "gn:feature_code":"PPL",
    "gn:name":"Shiwanzi",
    "gn:population":0,
    "gn:timezone":"Asia/Shanghai",
    "iso:country":"CN",
    "name:zho_x_preferred":[
        "\u77f3\u6e7e\u5b50"
    ],
    "wof:name":"Shiwanzi",
    "wof:placetype":"locality"
},
  "geometry": {"coordinates":[108.59032999999999,36.61867],"type":"Point"}
}