{
  "type": "Feature",
  "properties": {
    "gn:admin1_code":"8.0",
    "gn:asciiname":"Wapenyao",
    "gn:country_code":"CN",
    "gn:dem":199,
    "gn:feature_class":"P",
    "gn:feature_code":"PPL",
    "gn:name":"Wapenyao",
    "gn:population":0,
    "gn:timezone":"Asia/Shanghai",
    "iso:country":"CN",
    "name:zho_x_preferred":[
        "\u74e6\u76c6\u7a91"
    ],
    "wof:name":"Wapenyao",
    "wof:placetype":"locality"
},
  "geometry": {"coordinates":[124.76909999999999,48.22863],"type":"Point"}
}