{
  "type": "Feature",
  "properties": {
    "gn:admin1_code":"32.0",
    "gn:asciiname":"Pipawan",
    "gn:country_code":"CN",
    "gn:dem":973,
    "gn:feature_class":"P",
    "gn:feature_code":"PPL",
    "gn:name":"Pipawan",
    "gn:population":0,
    "gn:timezone":"Asia/Shanghai",
    "iso:country":"CN",
    "name:zho_x_preferred":[
        "\u6787\u6777\u6e7e"
    ],
    "wof:name":"Pipawan",
    "wof:placetype":"locality"
},
  "geometry": {"coordinates":[104.985,28.2382],"type":"Point"}
}