{
  "type": "Feature",
  "properties": {
    "gn:admin1_code":"19.0",
    "gn:asciiname":"Pingxianggou",
    "gn:country_code":"CN",
    "gn:dem":268,
    "gn:feature_class":"P",
    "gn:feature_code":"PPL",
    "gn:name":"Pingxianggou",
    "gn:population":0,
    "gn:timezone":"Asia/Shanghai",
    "iso:country":"CN",
    "name:und_x_variant":[
        "\u5e73\u9999\u6c9f"
    ],
    "name:zho_x_preferred":[
        "\u5e73\u9999\u6c9f"
    ],
    "wof:name":"Pingxianggou",
    "wof:placetype":"locality"
},
  "geometry": {"coordinates":[123.239,40.69001],"type":"Point"}
}