{
  "type": "Feature",
  "properties": {
    "gn:admin1_code":"25",
    "gn:asciiname":"Beigejiaquan",
    "gn:country_code":"CN",
    "gn:dem":140,
    "gn:feature_class":"P",
    "gn:feature_code":"PPL",
    "gn:name":"Beigejiaquan",
    "gn:population":0,
    "gn:timezone":"Asia/Shanghai",
    "iso:country":"CN",
    "name:zho_x_preferred":[
        "\u5317\u845b\u5bb6\u5708"
    ],
    "wof:name":"Beigejiaquan",
    "wof:placetype":"locality"
},
  "geometry": {"coordinates":[117.262,35.8145],"type":"Point"}
}