{
  "type": "Feature",
  "properties": {
    "gn:admin1_code":"02",
    "gn:asciiname":"Maguan",
    "gn:country_code":"CN",
    "gn:dem":4,
    "gn:feature_class":"P",
    "gn:feature_code":"PPL",
    "gn:name":"Maguan",
    "gn:population":0,
    "gn:timezone":"Asia/Shanghai",
    "iso:country":"CN",
    "name:und_x_variant":[
        "Maguanzhen",
        "\u9a6c\u5173\u9547"
    ],
    "name:zho_x_preferred":[
        "\u9a6c\u5173"
    ],
    "wof:name":"Maguan",
    "wof:placetype":"locality"
},
  "geometry": {"coordinates":[122.44583,30.70056],"type":"Point"}
}