{
  "type": "Feature",
  "properties": {
    "gn:admin1_code":"10",
    "gn:asciiname":"Wangkou",
    "gn:country_code":"CN",
    "gn:dem":27,
    "gn:feature_class":"P",
    "gn:feature_code":"PPL",
    "gn:name":"Wangkou",
    "gn:population":0,
    "gn:timezone":"Asia/Shanghai",
    "iso:country":"CN",
    "name:zho_x_preferred":[
        "\u738b\u53e3\u9547"
    ],
    "wof:name":"Wangkou",
    "wof:placetype":"locality"
},
  "geometry": {"coordinates":[115.27361000000001,37.65167],"type":"Point"}
}