{
  "type": "Feature",
  "properties": {
    "gn:admin1_code":"18.0",
    "gn:asciiname":"Lannishan",
    "gn:country_code":"CN",
    "gn:dem":1203,
    "gn:feature_class":"P",
    "gn:feature_code":"PPL",
    "gn:name":"Lannishan",
    "gn:population":0,
    "gn:timezone":"Asia/Shanghai",
    "iso:country":"CN",
    "name:zho_x_preferred":[
        "\u6ee5\u6ce5\u5c71"
    ],
    "wof:name":"Lannishan",
    "wof:placetype":"locality"
},
  "geometry": {"coordinates":[107.508,26.5348],"type":"Point"}
}