{
  "type": "Feature",
  "properties": {
    "gn:admin1_code":"4.0",
    "gn:asciiname":"Zhongshe",
    "gn:country_code":"CN",
    "gn:dem":3,
    "gn:feature_class":"P",
    "gn:feature_code":"PPL",
    "gn:name":"Zhongshe",
    "gn:population":0,
    "gn:timezone":"Asia/Shanghai",
    "iso:country":"CN",
    "name:und_x_variant":[
        "\u4e2d\u820d"
    ],
    "name:zho_x_preferred":[
        "\u4e2d\u820d"
    ],
    "wof:name":"Zhongshe",
    "wof:placetype":"locality"
},
  "geometry": {"coordinates":[120.85477,32.98117],"type":"Point"}
}