{
  "type": "Feature",
  "properties": {
    "gn:admin1_code":"3",
    "gn:asciiname":"Bushang",
    "gn:country_code":"CN",
    "gn:dem":135,
    "gn:feature_class":"P",
    "gn:feature_code":"PPL",
    "gn:name":"Bushang",
    "gn:population":0,
    "gn:timezone":"Asia/Shanghai",
    "iso:country":"CN",
    "name:zho_x_preferred":[
        "\u57e0\u4e0a"
    ],
    "wof:name":"Bushang",
    "wof:placetype":"locality"
},
  "geometry": {"coordinates":[114.94101000000001,25.78669],"type":"Point"}
}