{
  "type": "Feature",
  "properties": {
    "gn:admin1_code":"1.0",
    "gn:asciiname":"Fengyangxian Yuanyichang",
    "gn:country_code":"CN",
    "gn:dem":72,
    "gn:feature_class":"P",
    "gn:feature_code":"PPLF",
    "gn:name":"Fengyangxian Yuanyichang",
    "gn:population":0,
    "gn:timezone":"Asia/Shanghai",
    "iso:country":"CN",
    "name:zho_x_preferred":[
        "\u51e4\u9633\u53bf\u56ed\u827a\u573a"
    ],
    "wof:name":"Fengyangxian Yuanyichang",
    "wof:placetype":"locality"
},
  "geometry": {"coordinates":[117.72323,32.73196],"type":"Point"}
}