{
  "type": "Feature",
  "properties": {
    "gn:admin1_code":"19.0",
    "gn:asciiname":"Sanjianfang",
    "gn:country_code":"CN",
    "gn:dem":333,
    "gn:feature_class":"P",
    "gn:feature_code":"PPL",
    "gn:name":"Sanjianfang",
    "gn:population":0,
    "gn:timezone":"Asia/Shanghai",
    "iso:country":"CN",
    "name:zho_x_preferred":[
        "\u4e09\u95f4\u623f"
    ],
    "wof:name":"Sanjianfang",
    "wof:placetype":"locality"
},
  "geometry": {"coordinates":[119.58076,41.11855],"type":"Point"}
}