{
  "type": "Feature",
  "properties": {
    "gn:admin1_code":"30",
    "gn:asciiname":"Dalang",
    "gn:cc2":"CN",
    "gn:country_code":"CN",
    "gn:dem":1,
    "gn:feature_class":"P",
    "gn:feature_code":"PPL",
    "gn:name":"Dalang",
    "gn:population":0,
    "gn:timezone":"Asia/Shanghai",
    "iso:country":"CN",
    "name:ceb_x_preferred":[
        "Dalang"
    ],
    "name:deu_x_preferred":[
        "Dalang"
    ],
    "name:nld_x_preferred":[
        "Dalang"
    ],
    "name:sco_x_preferred":[
        "Dalang"
    ],
    "name:swe_x_preferred":[
        "Dalang"
    ],
    "name:und_x_variant":[
        "Ta-lang",
        "Dalang"
    ],
    "wof:name":"Dalang",
    "wof:placetype":"locality"
},
  "geometry": {"coordinates":[111.98,21.80556],"type":"Point"}
}