{
  "type": "Feature",
  "properties": {
    "gn:admin1_code":"30.0",
    "gn:asciiname":"Zhongxin",
    "gn:country_code":"CN",
    "gn:dem":5,
    "gn:feature_class":"P",
    "gn:feature_code":"PPL",
    "gn:name":"Zhongxin",
    "gn:population":0,
    "gn:timezone":"Asia/Shanghai",
    "iso:country":"CN",
    "name:zho_x_preferred":[
        "\u5fe0\u5fc3"
    ],
    "wof:name":"Zhongxin",
    "wof:placetype":"locality"
},
  "geometry": {"coordinates":[112.71622000000001,22.29414],"type":"Point"}
}