{
  "type": "Feature",
  "properties": {
    "gn:admin1_code":"9",
    "gn:asciiname":"Diwa",
    "gn:country_code":"CN",
    "gn:dem":53,
    "gn:feature_class":"P",
    "gn:feature_code":"PPL",
    "gn:name":"Diwa",
    "gn:population":0,
    "gn:timezone":"Asia/Shanghai",
    "iso:country":"CN",
    "name:ceb_x_preferred":[
        "Diwa"
    ],
    "name:swe_x_preferred":[
        "Diwa"
    ],
    "name:zho_x_preferred":[
        "\u7fdf\u6d3c"
    ],
    "wof:name":"Diwa",
    "wof:placetype":"locality"
},
  "geometry": {"coordinates":[115.172,34.1099],"type":"Point"}
}