{
  "type": "Feature",
  "properties": {
    "gn:admin1_code":"32.0",
    "gn:asciiname":"Wanbaishu",
    "gn:country_code":"CN",
    "gn:dem":843,
    "gn:feature_class":"P",
    "gn:feature_code":"PPL",
    "gn:name":"Wanbaishu",
    "gn:population":0,
    "gn:timezone":"Asia/Shanghai",
    "iso:country":"CN",
    "name:zho_x_preferred":[
        "\u5f2f\u67cf\u6811"
    ],
    "wof:name":"Wanbaishu",
    "wof:placetype":"locality"
},
  "geometry": {"coordinates":[105.17286,31.99493],"type":"Point"}
}