{
  "type": "Feature",
  "properties": {
    "gn:admin1_code":"12.0",
    "gn:asciiname":"Laowuwang",
    "gn:country_code":"CN",
    "gn:dem":92,
    "gn:feature_class":"P",
    "gn:feature_code":"PPL",
    "gn:name":"Laowuwang",
    "gn:population":0,
    "gn:timezone":"Asia/Shanghai",
    "iso:country":"CN",
    "name:zho_x_preferred":[
        "Laowuwang"
    ],
    "name:zho_x_variant":[
        "\u8001\u5c4b\u738b"
    ],
    "wof:name":"Laowuwang",
    "wof:placetype":"locality"
},
  "geometry": {"coordinates":[114.20985,29.74912],"type":"Point"}
}