{
  "type": "Feature",
  "properties": {
    "gn:admin1_code":"32.0",
    "gn:asciiname":"Jinshansi",
    "gn:country_code":"CN",
    "gn:dem":481,
    "gn:feature_class":"P",
    "gn:feature_code":"PPL",
    "gn:name":"Jinshansi",
    "gn:population":0,
    "gn:timezone":"Asia/Shanghai",
    "iso:country":"CN",
    "name:zho_x_preferred":[
        "\u91d1\u5c71\u5bfa"
    ],
    "wof:name":"Jinshansi",
    "wof:placetype":"locality"
},
  "geometry": {"coordinates":[104.24048000000001,30.99206],"type":"Point"}
}