{
  "type": "Feature",
  "properties": {
    "gn:admin1_code":"2.0",
    "gn:asciiname":"Qiaoying",
    "gn:country_code":"CN",
    "gn:dem":239,
    "gn:feature_class":"P",
    "gn:feature_code":"PPL",
    "gn:name":"Qiaoying",
    "gn:population":0,
    "gn:timezone":"Asia/Shanghai",
    "iso:country":"CN",
    "name:zho_x_preferred":[
        "\u5de7\u82f1"
    ],
    "wof:name":"Qiaoying",
    "wof:placetype":"locality"
},
  "geometry": {"coordinates":[121.14738,29.41369000000001],"type":"Point"}
}