{
  "type": "Feature",
  "properties": {
    "gn:admin1_code":"30.0",
    "gn:asciiname":"Zhuluo",
    "gn:country_code":"CN",
    "gn:dem":6,
    "gn:feature_class":"P",
    "gn:feature_code":"PPL",
    "gn:name":"Zhuluo",
    "gn:population":0,
    "gn:timezone":"Asia/Shanghai",
    "iso:country":"CN",
    "name:zho_x_preferred":[
        "\u7af9\u6d1b"
    ],
    "wof:name":"Zhuluo",
    "wof:placetype":"locality"
},
  "geometry": {"coordinates":[112.80517999999999,22.11361],"type":"Point"}
}