{
  "type": "Feature",
  "properties": {
    "gn:admin1_code":"29.0",
    "gn:asciiname":"Huayu",
    "gn:country_code":"CN",
    "gn:dem":2356,
    "gn:feature_class":"P",
    "gn:feature_code":"PPL",
    "gn:name":"Huayu",
    "gn:population":0,
    "gn:timezone":"Asia/Shanghai",
    "iso:country":"CN",
    "name:und_x_variant":[
        "\u82b1\u9c7c"
    ],
    "wof:name":"Huayu",
    "wof:placetype":"locality"
},
  "geometry": {"coordinates":[103.54378,26.45778],"type":"Point"}
}