{
  "type": "Feature",
  "properties": {
    "gn:admin1_code":"25.0",
    "gn:asciiname":"Qianshuishi",
    "gn:cc2":"CN",
    "gn:country_code":"CN",
    "gn:dem":42,
    "gn:feature_class":"P",
    "gn:feature_code":"PPL",
    "gn:name":"Qianshuishi",
    "gn:population":0,
    "gn:timezone":"Asia/Shanghai",
    "iso:country":"CN",
    "name:zho_x_preferred":[
        "\u524d\u6c34\u5e02"
    ],
    "wof:name":"Qianshuishi",
    "wof:placetype":"locality"
},
  "geometry": {"coordinates":[119.5038,36.24549],"type":"Point"}
}