{
  "type": "Feature",
  "properties": {
    "gn:admin1_code":"10.0",
    "gn:asciiname":"Gaojianzhuang",
    "gn:country_code":"CN",
    "gn:dem":8,
    "gn:feature_class":"P",
    "gn:feature_code":"PPL",
    "gn:name":"Gaojianzhuang",
    "gn:population":0,
    "gn:timezone":"Asia/Shanghai",
    "iso:country":"CN",
    "name:zho_x_preferred":[
        "\u9ad8\u5efa\u5e84"
    ],
    "wof:name":"Gaojianzhuang",
    "wof:placetype":"locality"
},
  "geometry": {"coordinates":[119.73224999999999,39.9779],"type":"Point"}
}