{
  "type": "Feature",
  "properties": {
    "gn:admin1_code":"13",
    "gn:asciiname":"Tugemanbeixi",
    "gn:country_code":"CN",
    "gn:dem":1253,
    "gn:feature_class":"P",
    "gn:feature_code":"PPL",
    "gn:name":"Tugemanbeixi",
    "gn:population":0,
    "gn:timezone":"Asia/Shanghai",
    "iso:country":"CN",
    "name:zho_x_preferred":[
        "\u5410\u683c\u66fc\u8d1d\u5e0c"
    ],
    "wof:name":"Tugemanbeixi",
    "wof:placetype":"locality"
},
  "geometry": {"coordinates":[76.20313,39.37896],"type":"Point"}
}