{
  "type": "Feature",
  "properties": {
    "gn:admin1_code":"3.0",
    "gn:asciiname":"Xiaoyutan",
    "gn:country_code":"CN",
    "gn:dem":196,
    "gn:feature_class":"P",
    "gn:feature_code":"PPL",
    "gn:name":"Xiaoyutan",
    "gn:population":0,
    "gn:timezone":"Asia/Shanghai",
    "iso:country":"CN",
    "name:und_x_variant":[
        "\u5c0f\u9c7c\u6f6d"
    ],
    "wof:name":"Xiaoyutan",
    "wof:placetype":"locality"
},
  "geometry": {"coordinates":[115.78821000000001,25.56309],"type":"Point"}
}