{
  "type": "Feature",
  "properties": {
    "gn:admin1_code":"11.0",
    "gn:asciiname":"Binchang",
    "gn:country_code":"CN",
    "gn:dem":447,
    "gn:feature_class":"P",
    "gn:feature_code":"PPL",
    "gn:name":"Binchang",
    "gn:population":0,
    "gn:timezone":"Asia/Shanghai",
    "iso:country":"CN",
    "name:zho_x_preferred":[
        "\u5f6c\u660c"
    ],
    "wof:name":"Binchang",
    "wof:placetype":"locality"
},
  "geometry": {"coordinates":[110.36111,26.48267],"type":"Point"}
}