{
  "type": "Feature",
  "properties": {
    "gn:admin1_code":"24.0",
    "gn:asciiname":"Dabaipo",
    "gn:country_code":"CN",
    "gn:dem":1358,
    "gn:feature_class":"P",
    "gn:feature_code":"PPL",
    "gn:name":"Dabaipo",
    "gn:population":0,
    "gn:timezone":"Asia/Shanghai",
    "iso:country":"CN",
    "name:und_x_variant":[
        "\u5927\u767d\u5761"
    ],
    "wof:name":"Dabaipo",
    "wof:placetype":"locality"
},
  "geometry": {"coordinates":[112.30252,39.38096],"type":"Point"}
}