{
  "type": "Feature",
  "properties": {
    "gn:admin1_code":"20.0",
    "gn:asciiname":"Xiaojiucaigou",
    "gn:country_code":"CN",
    "gn:dem":254,
    "gn:feature_class":"P",
    "gn:feature_code":"PPL",
    "gn:name":"Xiaojiucaigou",
    "gn:population":0,
    "gn:timezone":"Asia/Shanghai",
    "iso:country":"CN",
    "name:zho_x_preferred":[
        "\u5c0f\u97ed\u83dc\u6c9f"
    ],
    "wof:name":"Xiaojiucaigou",
    "wof:placetype":"locality"
},
  "geometry": {"coordinates":[125.20685,49.67962],"type":"Point"}
}