{
  "type": "Feature",
  "properties": {
    "gn:admin1_code":"32.0",
    "gn:asciiname":"Paofangwan",
    "gn:country_code":"CN",
    "gn:dem":433,
    "gn:feature_class":"P",
    "gn:feature_code":"PPL",
    "gn:name":"Paofangwan",
    "gn:population":0,
    "gn:timezone":"Asia/Shanghai",
    "iso:country":"CN",
    "name:zho_x_preferred":[
        "\u70ae\u623f\u6e7e"
    ],
    "wof:name":"Paofangwan",
    "wof:placetype":"locality"
},
  "geometry": {"coordinates":[105.12617,31.38225],"type":"Point"}
}