{
  "type": "Feature",
  "properties": {
    "gn:admin1_code":"12.0",
    "gn:asciiname":"Eping",
    "gn:country_code":"CN",
    "gn:dem":528,
    "gn:feature_class":"P",
    "gn:feature_code":"PPLA4",
    "gn:name":"Eping",
    "gn:population":0,
    "gn:timezone":"Asia/Shanghai",
    "iso:country":"CN",
    "name:und_x_variant":[
        "Eping Xiang"
    ],
    "name:zho_x_preferred":[
        "\u9102\u576a"
    ],
    "name:zho_x_variant":[
        "\u9102\u576a\u4e61"
    ],
    "wof:name":"Eping",
    "wof:placetype":"locality"
},
  "geometry": {"coordinates":[109.67201,32.1976],"type":"Point"}
}