{
  "type": "Feature",
  "properties": {
    "gn:admin1_code":"29.0",
    "gn:asciiname":"Dayangquan",
    "gn:country_code":"CN",
    "gn:dem":2406,
    "gn:feature_class":"P",
    "gn:feature_code":"PPL",
    "gn:name":"Dayangquan",
    "gn:population":0,
    "gn:timezone":"Asia/Shanghai",
    "iso:country":"CN",
    "name:zho_x_preferred":[
        "\u5927\u7f8a\u5708"
    ],
    "wof:name":"Dayangquan",
    "wof:placetype":"locality"
},
  "geometry": {"coordinates":[102.116,25.475],"type":"Point"}
}