{
  "type": "Feature",
  "properties": {
    "gn:admin1_code":"14.0",
    "gn:asciiname":"Naqian",
    "gn:country_code":"CN",
    "gn:dem":4436,
    "gn:feature_class":"P",
    "gn:feature_code":"PPL",
    "gn:name":"Naqian",
    "gn:population":0,
    "gn:timezone":"Asia/Urumqi",
    "iso:country":"CN",
    "name:zho_x_preferred":[
        "\u90a3\u6b20"
    ],
    "wof:name":"Naqian",
    "wof:placetype":"locality"
},
  "geometry": {"coordinates":[93.05894000000001,31.91039],"type":"Point"}
}