{
  "type": "Feature",
  "properties": {
    "gn:admin1_code":"26.0",
    "gn:asciiname":"Mayimiao",
    "gn:country_code":"CN",
    "gn:dem":838,
    "gn:feature_class":"P",
    "gn:feature_code":"PPL",
    "gn:name":"Mayimiao",
    "gn:population":0,
    "gn:timezone":"Asia/Shanghai",
    "iso:country":"CN",
    "name:zho_x_preferred":[
        "\u9ebb\u8863\u5e99"
    ],
    "wof:name":"Mayimiao",
    "wof:placetype":"locality"
},
  "geometry": {"coordinates":[108.7572,33.0909],"type":"Point"}
}