{
  "type": "Feature",
  "properties": {
    "gn:admin1_code":"19",
    "gn:asciiname":"Erdaogou",
    "gn:country_code":"CN",
    "gn:dem":230,
    "gn:feature_class":"P",
    "gn:feature_code":"PPL",
    "gn:name":"Erdaogou",
    "gn:population":0,
    "gn:timezone":"Asia/Shanghai",
    "iso:country":"CN",
    "name:und_x_variant":[
        "Erdaogoucun",
        "Erdaogou"
    ],
    "name:zho_x_preferred":[
        "\u4e8c\u9053\u6c9f\u6751"
    ],
    "wof:name":"Erdaogou",
    "wof:placetype":"locality"
},
  "geometry": {"coordinates":[121.64722,41.62806],"type":"Point"}
}