{
  "type": "Feature",
  "properties": {
    "gn:admin1_code":"32.0",
    "gn:asciiname":"Leiwei",
    "gn:country_code":"CN",
    "gn:dem":2810,
    "gn:feature_class":"P",
    "gn:feature_code":"PPL",
    "gn:name":"Leiwei",
    "gn:population":0,
    "gn:timezone":"Asia/Shanghai",
    "iso:country":"CN",
    "name:zho_x_preferred":[
        "\u5792\u5c3e"
    ],
    "wof:name":"Leiwei",
    "wof:placetype":"locality"
},
  "geometry": {"coordinates":[101.97948,31.13133],"type":"Point"}
}