{
  "type": "Feature",
  "properties": {
    "gn:admin1_code":"13",
    "gn:asciiname":"Xikan'er",
    "gn:country_code":"CN",
    "gn:dem":462,
    "gn:feature_class":"P",
    "gn:feature_code":"PPL",
    "gn:name":"Xikan\u2019er",
    "gn:population":0,
    "gn:timezone":"Asia/Urumqi",
    "iso:country":"CN",
    "name:und_x_variant":[
        "Xikan\u2019er",
        "\u897f\u574e\u5c14"
    ],
    "wof:name":"Xikan'er",
    "wof:placetype":"locality"
},
  "geometry": {"coordinates":[94.94994,43.77432],"type":"Point"}
}