{
  "type": "Feature",
  "properties": {
    "gn:admin1_code":"19.0",
    "gn:asciiname":"Lijia Wobu",
    "gn:country_code":"CN",
    "gn:dem":6,
    "gn:feature_class":"P",
    "gn:feature_code":"PPL",
    "gn:name":"Lijia Wobu",
    "gn:population":0,
    "gn:timezone":"Asia/Shanghai",
    "iso:country":"CN",
    "name:und_x_variant":[
        "Lijiawobao",
        "\u674e\u5bb6\u7a9d\u5821",
        "Lijia Wobu"
    ],
    "name:zho_x_preferred":[
        "\u674e\u5bb6\u7a9d\u5821"
    ],
    "wof:name":"Lijia Wobu",
    "wof:placetype":"locality"
},
  "geometry": {"coordinates":[122.20099999999999,41.4186],"type":"Point"}
}