{
  "type": "Feature",
  "properties": {
    "gn:admin1_code":"19.0",
    "gn:asciiname":"Heishuiyingzi",
    "gn:country_code":"CN",
    "gn:dem":255,
    "gn:feature_class":"P",
    "gn:feature_code":"PPL",
    "gn:name":"Heishuiyingzi",
    "gn:population":0,
    "gn:timezone":"Asia/Shanghai",
    "iso:country":"CN",
    "name:zho_x_preferred":[
        "\u9ed1\u6c34\u8425\u5b50"
    ],
    "wof:name":"Heishuiyingzi",
    "wof:placetype":"locality"
},
  "geometry": {"coordinates":[121.64681000000002,42.41379000000001],"type":"Point"}
}