{
  "type": "Feature",
  "properties": {
    "gn:admin1_code":"12.0",
    "gn:asciiname":"Fangmazhou",
    "gn:country_code":"CN",
    "gn:dem":85,
    "gn:feature_class":"P",
    "gn:feature_code":"PPL",
    "gn:name":"Fangmazhou",
    "gn:population":0,
    "gn:timezone":"Asia/Shanghai",
    "iso:country":"CN",
    "name:zho_x_preferred":[
        "\u653e\u9a6c\u6d32"
    ],
    "wof:name":"Fangmazhou",
    "wof:placetype":"locality"
},
  "geometry": {"coordinates":[111.65288,32.30433],"type":"Point"}
}