{
  "type": "Feature",
  "properties": {
    "gn:admin1_code":"5.0",
    "gn:asciiname":"Fuzhicun",
    "gn:country_code":"CN",
    "gn:dem":137,
    "gn:feature_class":"P",
    "gn:feature_code":"PPL",
    "gn:name":"Fuzhicun",
    "gn:population":0,
    "gn:timezone":"Asia/Shanghai",
    "iso:country":"CN",
    "name:zho_x_preferred":[
        "\u5bcc\u6cbb\u6751"
    ],
    "wof:name":"Fuzhicun",
    "wof:placetype":"locality"
},
  "geometry": {"coordinates":[123.5789,45.63776],"type":"Point"}
}