{
  "type": "Feature",
  "properties": {
    "gn:admin1_code":"12.0",
    "gn:asciiname":"Luzuchong",
    "gn:country_code":"CN",
    "gn:dem":77,
    "gn:feature_class":"P",
    "gn:feature_code":"PPL",
    "gn:name":"Luzuchong",
    "gn:population":0,
    "gn:timezone":"Asia/Shanghai",
    "iso:country":"CN",
    "name:zho_x_preferred":[
        "\u5362\u7956\u51b2"
    ],
    "wof:name":"Luzuchong",
    "wof:placetype":"locality"
},
  "geometry": {"coordinates":[114.69571000000001,31.29484],"type":"Point"}
}