{
  "type": "Feature",
  "properties": {
    "gn:admin1_code":"26.0",
    "gn:asciiname":"Gaojia Goucun",
    "gn:country_code":"CN",
    "gn:dem":968,
    "gn:feature_class":"P",
    "gn:feature_code":"PPL",
    "gn:name":"Gaojia Goucun",
    "gn:population":0,
    "gn:timezone":"Asia/Shanghai",
    "iso:country":"CN",
    "name:zho_x_preferred":[
        "\u9ad8\u5bb6\u6c9f\u6751"
    ],
    "wof:name":"Gaojia Goucun",
    "wof:placetype":"locality"
},
  "geometry": {"coordinates":[110.31399999999999,37.6427],"type":"Point"}
}