{
  "type": "Feature",
  "properties": {
    "gn:admin1_code":"5.0",
    "gn:asciiname":"Shangxiagongzi",
    "gn:country_code":"CN",
    "gn:dem":745,
    "gn:feature_class":"P",
    "gn:feature_code":"PPL",
    "gn:name":"Shangxiagongzi",
    "gn:population":0,
    "gn:timezone":"Asia/Shanghai",
    "iso:country":"CN",
    "name:und_x_variant":[
        "\u4e0a\u4e0b\u5bab\u5b50"
    ],
    "wof:name":"Shangxiagongzi",
    "wof:placetype":"locality"
},
  "geometry": {"coordinates":[127.21503,42.02748],"type":"Point"}
}