{
  "type": "Feature",
  "properties": {
    "gn:admin1_code":"8.0",
    "gn:asciiname":"Wanfa",
    "gn:country_code":"CN",
    "gn:dem":190,
    "gn:feature_class":"P",
    "gn:feature_code":"PPLA4",
    "gn:name":"Wanfa",
    "gn:population":0,
    "gn:timezone":"Asia/Shanghai",
    "iso:country":"CN",
    "name:und_x_variant":[
        "Wanfa Zhen"
    ],
    "name:zho_x_preferred":[
        "\u4e07\u53d1"
    ],
    "name:zho_x_variant":[
        "\u4e07\u53d1\u9547"
    ],
    "wof:name":"Wanfa",
    "wof:placetype":"locality"
},
  "geometry": {"coordinates":[127.12052,46.53452],"type":"Point"}
}