{
  "type": "Feature",
  "properties": {
    "gn:admin1_code":"26.0",
    "gn:asciiname":"Yuandatan",
    "gn:country_code":"CN",
    "gn:dem":1183,
    "gn:feature_class":"P",
    "gn:feature_code":"PPL",
    "gn:name":"Yuandatan",
    "gn:population":0,
    "gn:timezone":"Asia/Shanghai",
    "iso:country":"CN",
    "name:zho_x_preferred":[
        "\u5143\u5927\u6ee9"
    ],
    "wof:name":"Yuandatan",
    "wof:placetype":"locality"
},
  "geometry": {"coordinates":[109.37318,38.21911],"type":"Point"}
}