{
  "type": "Feature",
  "properties": {
    "gn:admin1_code":"19.0",
    "gn:asciiname":"Liutiaobiancun",
    "gn:country_code":"CN",
    "gn:dem":6,
    "gn:feature_class":"P",
    "gn:feature_code":"PPL",
    "gn:name":"Liutiaobiancun",
    "gn:population":0,
    "gn:timezone":"Asia/Shanghai",
    "iso:country":"CN",
    "name:zho_x_preferred":[
        "\u67f3\u6761\u8fb9\u6751"
    ],
    "wof:name":"Liutiaobiancun",
    "wof:placetype":"locality"
},
  "geometry": {"coordinates":[124.006,39.8226],"type":"Point"}
}