{
  "type": "Feature",
  "properties": {
    "gn:admin1_code":"14.0",
    "gn:asciiname":"Gugu",
    "gn:country_code":"CN",
    "gn:dem":4172,
    "gn:feature_class":"P",
    "gn:feature_code":"PPL",
    "gn:name":"Gugu",
    "gn:population":0,
    "gn:timezone":"Asia/Urumqi",
    "iso:country":"CN",
    "name:ceb_x_preferred":[
        "Gugu"
    ],
    "name:deu_x_preferred":[
        "Gugu"
    ],
    "name:por_x_preferred":[
        "Gugu"
    ],
    "name:spa_x_preferred":[
        "Gugu"
    ],
    "name:swe_x_preferred":[
        "Gugu"
    ],
    "name:zho_x_preferred":[
        "\u8c37\u53e4"
    ],
    "wof:name":"Gugu",
    "wof:placetype":"locality"
},
  "geometry": {"coordinates":[94.18522,29.84968],"type":"Point"}
}