{
  "type": "Feature",
  "properties": {
    "gn:admin1_code":"26",
    "gn:asciiname":"Sanguanmiao",
    "gn:country_code":"CN",
    "gn:dem":823,
    "gn:feature_class":"P",
    "gn:feature_code":"PPL",
    "gn:name":"Sanguanmiao",
    "gn:population":0,
    "gn:timezone":"Asia/Shanghai",
    "iso:country":"CN",
    "name:zho_x_preferred":[
        "\u4e09\u5b98\u5e99"
    ],
    "wof:name":"Sanguanmiao",
    "wof:placetype":"locality"
},
  "geometry": {"coordinates":[109.51099000000001,34.29038],"type":"Point"}
}