{
  "type": "Feature",
  "properties": {
    "gn:admin1_code":"12.0",
    "gn:asciiname":"Sunjia Yuangou",
    "gn:country_code":"CN",
    "gn:dem":42,
    "gn:feature_class":"P",
    "gn:feature_code":"PPL",
    "gn:name":"Sunjia Yuangou",
    "gn:population":0,
    "gn:timezone":"Asia/Shanghai",
    "iso:country":"CN",
    "name:zho_x_preferred":[
        "Sunjia Yuangou"
    ],
    "name:zho_x_variant":[
        "\u5b59\u5bb6\u9662\u6c9f"
    ],
    "wof:name":"Sunjia Yuangou",
    "wof:placetype":"locality"
},
  "geometry": {"coordinates":[112.06534000000001,30.4175],"type":"Point"}
}