{
  "type": "Feature",
  "properties": {
    "gn:admin1_code":"2.0",
    "gn:asciiname":"Jiaoshi",
    "gn:country_code":"CN",
    "gn:dem":17,
    "gn:feature_class":"P",
    "gn:feature_code":"PPL",
    "gn:name":"Jiaoshi",
    "gn:population":0,
    "gn:timezone":"Asia/Shanghai",
    "iso:country":"CN",
    "name:zho_x_preferred":[
        "\u7901\u77f3"
    ],
    "wof:name":"Jiaoshi",
    "wof:placetype":"locality"
},
  "geometry": {"coordinates":[121.55737999999999,29.06768],"type":"Point"}
}