{
  "type": "Feature",
  "properties": {
    "gn:admin1_code":"33.0",
    "gn:asciiname":"Nantianhu",
    "gn:country_code":"CN",
    "gn:dem":1131,
    "gn:feature_class":"P",
    "gn:feature_code":"PPLA4",
    "gn:name":"Nantianhu",
    "gn:population":0,
    "gn:timezone":"Asia/Shanghai",
    "iso:country":"CN",
    "name:und_x_variant":[
        "Nantianhu Zhen"
    ],
    "name:zho_x_preferred":[
        "\u5357\u5929\u6e56"
    ],
    "name:zho_x_variant":[
        "\u5357\u5929\u6e56\u9547"
    ],
    "wof:name":"Nantianhu",
    "wof:placetype":"locality"
},
  "geometry": {"coordinates":[107.92053,29.70098],"type":"Point"}
}