{
  "type": "Feature",
  "properties": {
    "gn:admin1_code":"26.0",
    "gn:asciiname":"Gaojiashan",
    "gn:country_code":"CN",
    "gn:dem":949,
    "gn:feature_class":"P",
    "gn:feature_code":"PPL",
    "gn:name":"Gaojiashan",
    "gn:population":0,
    "gn:timezone":"Asia/Shanghai",
    "iso:country":"CN",
    "name:und_x_variant":[
        "\u9ad8\u5bb6\u5c71"
    ],
    "wof:name":"Gaojiashan",
    "wof:placetype":"locality"
},
  "geometry": {"coordinates":[106.46063999999998,32.95484],"type":"Point"}
}