{
  "type": "Feature",
  "properties": {
    "gn:admin1_code":"6.0",
    "gn:asciiname":"Hacang",
    "gn:country_code":"CN",
    "gn:dem":3498,
    "gn:feature_class":"P",
    "gn:feature_code":"PPL",
    "gn:name":"Hacang",
    "gn:population":0,
    "gn:timezone":"Asia/Shanghai",
    "iso:country":"CN",
    "name:zho_x_preferred":[
        "\u54c8\u85cf"
    ],
    "wof:name":"Hacang",
    "wof:placetype":"locality"
},
  "geometry": {"coordinates":[101.75778,35.21182],"type":"Point"}
}