{
  "type": "Feature",
  "properties": {
    "gn:admin1_code":"19.0",
    "gn:asciiname":"Yangbaozhen Zhangzi",
    "gn:country_code":"CN",
    "gn:dem":255,
    "gn:feature_class":"P",
    "gn:feature_code":"PPL",
    "gn:name":"Yangbaozhen Zhangzi",
    "gn:population":0,
    "gn:timezone":"Asia/Shanghai",
    "iso:country":"CN",
    "name:zho_x_preferred":[
        "\u6768\u5b9d\u73cd\u6756\u5b50"
    ],
    "wof:name":"Yangbaozhen Zhangzi",
    "wof:placetype":"locality"
},
  "geometry": {"coordinates":[120.39,41.2669],"type":"Point"}
}