{
  "type": "Feature",
  "properties": {
    "gn:admin1_code":"11.0",
    "gn:asciiname":"Wujialing",
    "gn:country_code":"CN",
    "gn:dem":34,
    "gn:feature_class":"P",
    "gn:feature_code":"PPL",
    "gn:name":"Wujialing",
    "gn:population":0,
    "gn:timezone":"Asia/Shanghai",
    "iso:country":"CN",
    "name:zho_x_preferred":[
        "\u4e94\u5bb6\u5cad"
    ],
    "wof:name":"Wujialing",
    "wof:placetype":"locality"
},
  "geometry": {"coordinates":[112.16387,29.01569000000001],"type":"Point"}
}