{
  "type": "Feature",
  "properties": {
    "gn:admin1_code":"32.0",
    "gn:asciiname":"Liugou",
    "gn:country_code":"CN",
    "gn:dem":1106,
    "gn:feature_class":"P",
    "gn:feature_code":"PPL",
    "gn:name":"Liugou",
    "gn:population":0,
    "gn:timezone":"Asia/Shanghai",
    "iso:country":"CN",
    "name:zho_x_preferred":[
        "\u5218\u6c9f"
    ],
    "wof:name":"Liugou",
    "wof:placetype":"locality"
},
  "geometry": {"coordinates":[103.22872,30.48289],"type":"Point"}
}