{
  "type": "Feature",
  "properties": {
    "gn:admin1_code":"1.0",
    "gn:asciiname":"Guancun",
    "gn:country_code":"CN",
    "gn:dem":18,
    "gn:feature_class":"P",
    "gn:feature_code":"PPL",
    "gn:name":"Guancun",
    "gn:population":0,
    "gn:timezone":"Asia/Shanghai",
    "iso:country":"CN",
    "name:zho_x_preferred":[
        "Guancun"
    ],
    "name:zho_x_variant":[
        "\u7ba1\u6751"
    ],
    "wof:name":"Guancun",
    "wof:placetype":"locality"
},
  "geometry": {"coordinates":[119.25382,31.03317],"type":"Point"}
}