{
  "type": "Feature",
  "properties": {
    "gn:admin1_code":"29",
    "gn:asciiname":"Longtan",
    "gn:country_code":"CN",
    "gn:dem":1281,
    "gn:feature_class":"P",
    "gn:feature_code":"PPL",
    "gn:name":"Longtan",
    "gn:population":0,
    "gn:timezone":"Asia/Shanghai",
    "iso:country":"CN",
    "wof:name":"Longtan",
    "wof:placetype":"locality"
},
  "geometry": {"coordinates":[101.59999999999999,23.11667000000001],"type":"Point"}
}