{
  "type": "Feature",
  "properties": {
    "gn:admin1_code":"9.0",
    "gn:asciiname":"Wafangzhuang",
    "gn:country_code":"CN",
    "gn:dem":1189,
    "gn:feature_class":"P",
    "gn:feature_code":"PPL",
    "gn:name":"Wafangzhuang",
    "gn:population":0,
    "gn:timezone":"Asia/Shanghai",
    "iso:country":"CN",
    "name:zho_x_preferred":[
        "\u74e6\u623f\u5e84"
    ],
    "wof:name":"Wafangzhuang",
    "wof:placetype":"locality"
},
  "geometry": {"coordinates":[111.2966,33.73573],"type":"Point"}
}