{
  "type": "Feature",
  "properties": {
    "gn:admin1_code":"2.0",
    "gn:asciiname":"Shuban Qiaotou",
    "gn:country_code":"CN",
    "gn:dem":168,
    "gn:feature_class":"P",
    "gn:feature_code":"PPL",
    "gn:name":"Shuban Qiaotou",
    "gn:population":0,
    "gn:timezone":"Asia/Shanghai",
    "iso:country":"CN",
    "name:zho_x_preferred":[
        "\u5885\u5742\u6865\u5934"
    ],
    "wof:name":"Shuban Qiaotou",
    "wof:placetype":"locality"
},
  "geometry": {"coordinates":[120.06579000000001,29.61353],"type":"Point"}
}