{
  "type": "Feature",
  "properties": {
    "gn:admin1_code":"12.0",
    "gn:asciiname":"Lannihu",
    "gn:country_code":"CN",
    "gn:dem":699,
    "gn:feature_class":"P",
    "gn:feature_code":"PPL",
    "gn:name":"Lannihu",
    "gn:population":0,
    "gn:timezone":"Asia/Shanghai",
    "iso:country":"CN",
    "name:zho_x_preferred":[
        "\u70c2\u6ce5\u6e56"
    ],
    "wof:name":"Lannihu",
    "wof:placetype":"locality"
},
  "geometry": {"coordinates":[110.43300000000001,32.78117],"type":"Point"}
}