{
  "type": "Feature",
  "properties": {
    "gn:admin1_code":"15.0",
    "gn:asciiname":"Yeshuihe",
    "gn:country_code":"CN",
    "gn:dem":1545,
    "gn:feature_class":"P",
    "gn:feature_code":"PPL",
    "gn:name":"Yeshuihe",
    "gn:population":0,
    "gn:timezone":"Asia/Shanghai",
    "iso:country":"CN",
    "name:und_x_variant":[
        "\u9875\u6c34\u6cb3"
    ],
    "wof:name":"Yeshuihe",
    "wof:placetype":"locality"
},
  "geometry": {"coordinates":[105.36029000000001,33.86107],"type":"Point"}
}