{
  "type": "Feature",
  "properties": {
    "gn:admin1_code":"15.0",
    "gn:asciiname":"Caopo",
    "gn:country_code":"CN",
    "gn:dem":2488,
    "gn:feature_class":"P",
    "gn:feature_code":"PPL",
    "gn:name":"Caopo",
    "gn:population":0,
    "gn:timezone":"Asia/Shanghai",
    "iso:country":"CN",
    "name:zho_x_preferred":[
        "\u8349\u5761"
    ],
    "wof:name":"Caopo",
    "wof:placetype":"locality"
},
  "geometry": {"coordinates":[104.23143,33.73748],"type":"Point"}
}