{
  "type": "Feature",
  "properties": {
    "gn:admin1_code":"25",
    "gn:asciiname":"Shuangmiaoluzhuang",
    "gn:country_code":"CN",
    "gn:dem":36,
    "gn:feature_class":"P",
    "gn:feature_code":"PPL",
    "gn:name":"Shuangmiaol\u00fczhuang",
    "gn:population":0,
    "gn:timezone":"Asia/Shanghai",
    "iso:country":"CN",
    "name:und_x_variant":[
        "Shuangmiaol\u00fczhuang",
        "L\u00fczhuang"
    ],
    "name:zho_x_preferred":[
        "\u53cc\u5e99\u5415\u5e84"
    ],
    "name:zho_x_variant":[
        "\u5415\u5e84"
    ],
    "wof:name":"Shuangmiaoluzhuang",
    "wof:placetype":"locality"
},
  "geometry": {"coordinates":[115.89422,36.57563],"type":"Point"}
}