{
  "type": "Feature",
  "properties": {
    "gn:admin1_code":"29",
    "gn:asciiname":"Shangfayudong",
    "gn:country_code":"CN",
    "gn:dem":1324,
    "gn:feature_class":"P",
    "gn:feature_code":"PPL",
    "gn:name":"Shangfayudong",
    "gn:population":0,
    "gn:timezone":"Asia/Shanghai",
    "iso:country":"CN",
    "name:zho_x_preferred":[
        "\u4e0a\u53d1\u9c7c\u6d1e"
    ],
    "wof:name":"Shangfayudong",
    "wof:placetype":"locality"
},
  "geometry": {"coordinates":[104.67,23.3043],"type":"Point"}
}