{
  "type": "Feature",
  "properties": {
    "gn:admin1_code":"30.0",
    "gn:asciiname":"Shuangqiaocun",
    "gn:country_code":"CN",
    "gn:dem":118,
    "gn:feature_class":"P",
    "gn:feature_code":"PPL",
    "gn:name":"Shuangqiaocun",
    "gn:population":0,
    "gn:timezone":"Asia/Shanghai",
    "iso:country":"CN",
    "name:zho_x_preferred":[
        "\u53cc\u6865\u6751"
    ],
    "wof:name":"Shuangqiaocun",
    "wof:placetype":"locality"
},
  "geometry": {"coordinates":[116.01694999999999,24.25702],"type":"Point"}
}