{
  "type": "Feature",
  "properties": {
    "gn:admin1_code":"15.0",
    "gn:asciiname":"Guohe",
    "gn:country_code":"CN",
    "gn:dem":1588,
    "gn:feature_class":"P",
    "gn:feature_code":"PPLA4",
    "gn:name":"Guohe",
    "gn:population":0,
    "gn:timezone":"Asia/Shanghai",
    "iso:country":"CN",
    "name:und_x_variant":[
        "\u90ed\u6cb3"
    ],
    "wof:name":"Guohe",
    "wof:placetype":"locality"
},
  "geometry": {"coordinates":[105.14870999999999,33.35113],"type":"Point"}
}