{
  "type": "Feature",
  "properties": {
    "gn:admin1_code":"15.0",
    "gn:asciiname":"Caijiayuan",
    "gn:country_code":"CN",
    "gn:dem":1456,
    "gn:feature_class":"P",
    "gn:feature_code":"PPL",
    "gn:name":"Caijiayuan",
    "gn:population":0,
    "gn:timezone":"Asia/Shanghai",
    "iso:country":"CN",
    "name:zho_x_preferred":[
        "\u8521\u5bb6\u586c"
    ],
    "wof:name":"Caijiayuan",
    "wof:placetype":"locality"
},
  "geometry": {"coordinates":[107.27500000000001,35.0636],"type":"Point"}
}