{
  "type": "Feature",
  "properties": {
    "gn:admin1_code":"10.0",
    "gn:asciiname":"Nijiawa",
    "gn:country_code":"CN",
    "gn:dem":222,
    "gn:feature_class":"P",
    "gn:feature_code":"PPL",
    "gn:name":"Nijiawa",
    "gn:population":0,
    "gn:timezone":"Asia/Shanghai",
    "iso:country":"CN",
    "name:und_x_variant":[
        "\u502a\u5bb6\u6d3c"
    ],
    "wof:name":"Nijiawa",
    "wof:placetype":"locality"
},
  "geometry": {"coordinates":[114.35578,38.77965],"type":"Point"}
}