{
  "type": "Feature",
  "properties": {
    "gn:admin1_code":"14.0",
    "gn:asciiname":"Songwaka Meicun",
    "gn:country_code":"CN",
    "gn:dem":4260,
    "gn:feature_class":"P",
    "gn:feature_code":"PPL",
    "gn:name":"Songwaka Meicun",
    "gn:population":0,
    "gn:timezone":"Asia/Urumqi",
    "iso:country":"CN",
    "name:zho_x_preferred":[
        "\u677e\u74e6\u5361\u7f8e\u6751"
    ],
    "wof:name":"Songwaka Meicun",
    "wof:placetype":"locality"
},
  "geometry": {"coordinates":[98.84278999999999,30.01115],"type":"Point"}
}