{
  "type": "Feature",
  "properties": {
    "gn:admin1_code":"16.0",
    "gn:asciiname":"Yalujiang",
    "gn:country_code":"CN",
    "gn:dem":2,
    "gn:feature_class":"P",
    "gn:feature_code":"PPL",
    "gn:name":"Yalujiang",
    "gn:population":0,
    "gn:timezone":"Asia/Shanghai",
    "iso:country":"CN",
    "name:zho_x_preferred":[
        "\u4e9a\u8def\u6c5f"
    ],
    "wof:name":"Yalujiang",
    "wof:placetype":"locality"
},
  "geometry": {"coordinates":[108.605,21.7707],"type":"Point"}
}