{
  "type": "Feature",
  "properties": {
    "gn:admin1_code":"2.0",
    "gn:asciiname":"Daqiao",
    "gn:country_code":"CN",
    "gn:dem":7,
    "gn:feature_class":"P",
    "gn:feature_code":"PPLA4",
    "gn:name":"Daqiao",
    "gn:population":0,
    "gn:timezone":"Asia/Shanghai",
    "iso:country":"CN",
    "name:ceb_x_preferred":[
        "Daqiao"
    ],
    "name:deu_x_preferred":[
        "Daqiao"
    ],
    "name:swe_x_preferred":[
        "Daqiao"
    ],
    "name:und_x_variant":[
        "\u5927\u6865",
        "Daqiao Zhen",
        "\u5927\u6865\u9547"
    ],
    "wof:name":"Daqiao",
    "wof:placetype":"locality"
},
  "geometry": {"coordinates":[120.85684000000001,30.74751],"type":"Point"}
}