{
  "type": "Feature",
  "properties": {
    "gn:admin1_code":"32.0",
    "gn:asciiname":"Sibao",
    "gn:country_code":"CN",
    "gn:dem":2564,
    "gn:feature_class":"P",
    "gn:feature_code":"PPL",
    "gn:name":"Sibao",
    "gn:population":0,
    "gn:timezone":"Asia/Shanghai",
    "iso:country":"CN",
    "name:zho_x_preferred":[
        "\u56db\u5305"
    ],
    "wof:name":"Sibao",
    "wof:placetype":"locality"
},
  "geometry": {"coordinates":[102.01300000000001,31.388],"type":"Point"}
}