{
  "type": "Feature",
  "properties": {
    "gn:admin1_code":"25",
    "gn:asciiname":"Xiwubagang",
    "gn:country_code":"CN",
    "gn:dem":57,
    "gn:feature_class":"P",
    "gn:feature_code":"PPL",
    "gn:name":"Xiwubagang",
    "gn:population":0,
    "gn:timezone":"Asia/Shanghai",
    "iso:country":"CN",
    "name:zho_x_preferred":[
        "\u897f\u4e94\u9738\u5c97"
    ],
    "wof:name":"Xiwubagang",
    "wof:placetype":"locality"
},
  "geometry": {"coordinates":[115.249,35.2193],"type":"Point"}
}