{
  "type": "Feature",
  "properties": {
    "gn:admin1_code":"12.0",
    "gn:asciiname":"Daliuwan",
    "gn:country_code":"CN",
    "gn:dem":119,
    "gn:feature_class":"P",
    "gn:feature_code":"PPL",
    "gn:name":"Daliuwan",
    "gn:population":0,
    "gn:timezone":"Asia/Shanghai",
    "iso:country":"CN",
    "name:zho_x_preferred":[
        "\u5927\u67f3\u6e7e"
    ],
    "wof:name":"Daliuwan",
    "wof:placetype":"locality"
},
  "geometry": {"coordinates":[112.11568,31.42938],"type":"Point"}
}