{
  "type": "Feature",
  "properties": {
    "gn:admin1_code":"14.0",
    "gn:asciiname":"Gemaojidi",
    "gn:country_code":"CN",
    "gn:dem":4057,
    "gn:feature_class":"P",
    "gn:feature_code":"PPL",
    "gn:name":"Gemaojidi",
    "gn:population":0,
    "gn:timezone":"Asia/Urumqi",
    "iso:country":"CN",
    "name:zho_x_preferred":[
        "\u54e5\u6bdb\u7ed9\u5730"
    ],
    "wof:name":"Gemaojidi",
    "wof:placetype":"locality"
},
  "geometry": {"coordinates":[97.45432,30.02528],"type":"Point"}
}