{
  "type": "Feature",
  "properties": {
    "gn:admin1_code":"14.0",
    "gn:asciiname":"Zongcuocun",
    "gn:country_code":"CN",
    "gn:dem":4821,
    "gn:feature_class":"P",
    "gn:feature_code":"PPL",
    "gn:name":"Zongcuocun",
    "gn:population":0,
    "gn:timezone":"Asia/Urumqi",
    "iso:country":"CN",
    "name:zho_x_preferred":[
        "\u5b97\u9519\u6751"
    ],
    "wof:name":"Zongcuocun",
    "wof:placetype":"locality"
},
  "geometry": {"coordinates":[91.74657999999999,28.75529],"type":"Point"}
}