{
  "type": "Feature",
  "properties": {
    "gn:admin1_code":"4.0",
    "gn:asciiname":"Luhe",
    "gn:country_code":"CN",
    "gn:dem":6,
    "gn:feature_class":"P",
    "gn:feature_code":"PPL",
    "gn:name":"Luhe",
    "gn:population":0,
    "gn:timezone":"Asia/Shanghai",
    "iso:country":"CN",
    "name:ceb_x_preferred":[
        "Luhe"
    ],
    "name:dan_x_preferred":[
        "Luhe"
    ],
    "name:deu_x_preferred":[
        "Luhe"
    ],
    "name:fra_x_preferred":[
        "Luhe"
    ],
    "name:nor_x_preferred":[
        "Luhe"
    ],
    "name:pol_x_preferred":[
        "Luhe"
    ],
    "name:swe_x_preferred":[
        "Luhe"
    ],
    "name:zho_x_preferred":[
        "\u9646\u6cb3"
    ],
    "wof:name":"Luhe",
    "wof:placetype":"locality"
},
  "geometry": {"coordinates":[119.36493,33.40332],"type":"Point"}
}