{
  "type": "Feature",
  "properties": {
    "gn:admin1_code":"29",
    "gn:asciiname":"Dalunan",
    "gn:country_code":"CN",
    "gn:dem":1525,
    "gn:feature_class":"P",
    "gn:feature_code":"PPL",
    "gn:name":"Dalunan",
    "gn:population":0,
    "gn:timezone":"Asia/Shanghai",
    "iso:country":"CN",
    "name:zho_x_preferred":[
        "\u5927\u8def\u5357"
    ],
    "wof:name":"Dalunan",
    "wof:placetype":"locality"
},
  "geometry": {"coordinates":[102.661,23.9572],"type":"Point"}
}