{
  "type": "Feature",
  "properties": {
    "gn:admin1_code":"26.0",
    "gn:asciiname":"Shadongcun",
    "gn:country_code":"CN",
    "gn:dem":1061,
    "gn:feature_class":"P",
    "gn:feature_code":"PPL",
    "gn:name":"Shadongcun",
    "gn:population":0,
    "gn:timezone":"Asia/Shanghai",
    "iso:country":"CN",
    "name:zho_x_preferred":[
        "\u6c99\u6d1e\u6751"
    ],
    "wof:name":"Shadongcun",
    "wof:placetype":"locality"
},
  "geometry": {"coordinates":[109.55906,37.97144],"type":"Point"}
}