{
  "type": "Feature",
  "properties": {
    "gn:admin1_code":"16.0",
    "gn:asciiname":"Poliucun",
    "gn:country_code":"CN",
    "gn:dem":656,
    "gn:feature_class":"P",
    "gn:feature_code":"PPL",
    "gn:name":"Poliucun",
    "gn:population":0,
    "gn:timezone":"Asia/Shanghai",
    "iso:country":"CN",
    "name:zho_x_preferred":[
        "\u5761\u516d\u6751"
    ],
    "wof:name":"Poliucun",
    "wof:placetype":"locality"
},
  "geometry": {"coordinates":[105.93000000000001,23.0905],"type":"Point"}
}