{
  "type": "Feature",
  "properties": {
    "gn:admin1_code":"26.0",
    "gn:asciiname":"Caojia Qucun",
    "gn:country_code":"CN",
    "gn:dem":1045,
    "gn:feature_class":"P",
    "gn:feature_code":"PPL",
    "gn:name":"Caojia Qucun",
    "gn:population":0,
    "gn:timezone":"Asia/Shanghai",
    "iso:country":"CN",
    "name:zho_x_preferred":[
        "\u66f9\u5bb6\u6e20\u6751"
    ],
    "wof:name":"Caojia Qucun",
    "wof:placetype":"locality"
},
  "geometry": {"coordinates":[110.56699999999999,37.4745],"type":"Point"}
}