{
  "type": "Feature",
  "properties": {
    "gn:admin1_code":"21.0",
    "gn:asciiname":"Koujiaqiao",
    "gn:country_code":"CN",
    "gn:dem":1092,
    "gn:feature_class":"P",
    "gn:feature_code":"PPL",
    "gn:name":"Koujiaqiao",
    "gn:population":0,
    "gn:timezone":"Asia/Shanghai",
    "iso:country":"CN",
    "name:zho_x_preferred":[
        "\u5bc7\u5bb6\u6865"
    ],
    "wof:name":"Koujiaqiao",
    "wof:placetype":"locality"
},
  "geometry": {"coordinates":[106.767,39.1273],"type":"Point"}
}