{
  "type": "Feature",
  "properties": {
    "gn:admin1_code":"10",
    "gn:asciiname":"Sirenwa",
    "gn:country_code":"CN",
    "gn:dem":1408,
    "gn:feature_class":"P",
    "gn:feature_code":"PPL",
    "gn:name":"Sirenwa",
    "gn:population":0,
    "gn:timezone":"Asia/Shanghai",
    "iso:country":"CN",
    "name:zho_x_preferred":[
        "\u56db\u4eba\u6d3c"
    ],
    "wof:name":"Sirenwa",
    "wof:placetype":"locality"
},
  "geometry": {"coordinates":[115.75109999999999,41.67604],"type":"Point"}
}