{
  "type": "Feature",
  "properties": {
    "gn:admin1_code":"29.0",
    "gn:asciiname":"Pangpin",
    "gn:country_code":"CN",
    "gn:dem":1547,
    "gn:feature_class":"P",
    "gn:feature_code":"PPL",
    "gn:name":"Pangpin",
    "gn:population":0,
    "gn:timezone":"Asia/Shanghai",
    "iso:country":"CN",
    "name:zho_x_preferred":[
        "\u80d6\u54c1"
    ],
    "wof:name":"Pangpin",
    "wof:placetype":"locality"
},
  "geometry": {"coordinates":[99.9727,23.2714],"type":"Point"}
}