{
  "type": "Feature",
  "properties": {
    "gn:admin1_code":"8.0",
    "gn:asciiname":"Yanjiang",
    "gn:country_code":"CN",
    "gn:dem":97,
    "gn:feature_class":"P",
    "gn:feature_code":"PPL",
    "gn:name":"Yanjiang",
    "gn:population":0,
    "gn:timezone":"Asia/Shanghai",
    "iso:country":"CN",
    "name:zho_x_preferred":[
        "\u6cbf\u6c5f"
    ],
    "wof:name":"Yanjiang",
    "wof:placetype":"locality"
},
  "geometry": {"coordinates":[130.07778999999999,48.91488],"type":"Point"}
}