{
  "type": "Feature",
  "properties": {
    "gn:admin1_code":"30",
    "gn:asciiname":"Dongguo",
    "gn:cc2":"CN",
    "gn:country_code":"CN",
    "gn:dem":85,
    "gn:feature_class":"P",
    "gn:feature_code":"PPL",
    "gn:name":"Dongguo",
    "gn:population":0,
    "gn:timezone":"Asia/Urumqi",
    "iso:country":"CN",
    "name:und_x_variant":[
        "Tung-kuo",
        "Dongguo",
        "\u4e1c\u57da"
    ],
    "name:zho_x_preferred":[
        "\u4e1c\u57da"
    ],
    "wof:name":"Dongguo",
    "wof:placetype":"locality"
},
  "geometry": {"coordinates":[110.18222,20.6675],"type":"Point"}
}