{
  "type": "Feature",
  "properties": {
    "gn:admin1_code":"19.0",
    "gn:asciiname":"Jianshuigou",
    "gn:country_code":"CN",
    "gn:dem":172,
    "gn:feature_class":"P",
    "gn:feature_code":"PPL",
    "gn:name":"Jianshuigou",
    "gn:population":0,
    "gn:timezone":"Asia/Shanghai",
    "iso:country":"CN",
    "name:zho_x_preferred":[
        "\u6da7\u6c34\u6c9f"
    ],
    "wof:name":"Jianshuigou",
    "wof:placetype":"locality"
},
  "geometry": {"coordinates":[124.37745,41.81313],"type":"Point"}
}