{
  "type": "Feature",
  "properties": {
    "gn:admin1_code":"26.0",
    "gn:asciiname":"Wanglaohe",
    "gn:country_code":"CN",
    "gn:dem":1275,
    "gn:feature_class":"P",
    "gn:feature_code":"PPL",
    "gn:name":"Wanglaohe",
    "gn:population":0,
    "gn:timezone":"Asia/Shanghai",
    "iso:country":"CN",
    "name:zho_x_preferred":[
        "\u738b\u8001\u6cb3"
    ],
    "wof:name":"Wanglaohe",
    "wof:placetype":"locality"
},
  "geometry": {"coordinates":[109.26822,37.27574],"type":"Point"}
}