{
  "type": "Feature",
  "properties": {
    "gn:admin1_code":"32.0",
    "gn:asciiname":"Suori",
    "gn:country_code":"CN",
    "gn:dem":3460,
    "gn:feature_class":"P",
    "gn:feature_code":"PPL",
    "gn:name":"Suori",
    "gn:population":0,
    "gn:timezone":"Asia/Shanghai",
    "iso:country":"CN",
    "name:zho_x_preferred":[
        "\u6240\u65e5"
    ],
    "wof:name":"Suori",
    "wof:placetype":"locality"
},
  "geometry": {"coordinates":[100.21599999999999,31.7161],"type":"Point"}
}