{
  "type": "Feature",
  "properties": {
    "gn:admin1_code":"29.0",
    "gn:asciiname":"Yinggepu",
    "gn:country_code":"CN",
    "gn:dem":2258,
    "gn:feature_class":"P",
    "gn:feature_code":"PPL",
    "gn:name":"Yinggepu",
    "gn:population":0,
    "gn:timezone":"Asia/Shanghai",
    "iso:country":"CN",
    "name:zho_x_preferred":[
        "\u9e66\u54e5\u94fa"
    ],
    "wof:name":"Yinggepu",
    "wof:placetype":"locality"
},
  "geometry": {"coordinates":[100.31399999999999,26.4897],"type":"Point"}
}