{
  "type": "Feature",
  "properties": {
    "gn:admin1_code":"30",
    "gn:asciiname":"Beijiao",
    "gn:country_code":"CN",
    "gn:dem":239,
    "gn:feature_class":"P",
    "gn:feature_code":"PPL",
    "gn:name":"Beijiao",
    "gn:population":0,
    "gn:timezone":"Asia/Shanghai",
    "iso:country":"CN",
    "name:zho_x_preferred":[
        "\u9642\u89d2"
    ],
    "wof:name":"Beijiao",
    "wof:placetype":"locality"
},
  "geometry": {"coordinates":[116.36133999999998,24.29896],"type":"Point"}
}