{
  "type": "Feature",
  "properties": {
    "gn:admin1_code":"24.0",
    "gn:asciiname":"Beixike",
    "gn:country_code":"CN",
    "gn:dem":1158,
    "gn:feature_class":"P",
    "gn:feature_code":"PPL",
    "gn:name":"Beixike",
    "gn:population":0,
    "gn:timezone":"Asia/Shanghai",
    "iso:country":"CN",
    "name:zho_x_preferred":[
        "\u5317\u897f\u5ca2"
    ],
    "wof:name":"Beixike",
    "wof:placetype":"locality"
},
  "geometry": {"coordinates":[113.05562999999999,38.00865],"type":"Point"}
}