{
  "type": "Feature",
  "properties": {
    "gn:admin1_code":"12.0",
    "gn:asciiname":"Fengjiawan",
    "gn:country_code":"CN",
    "gn:dem":1468,
    "gn:feature_class":"P",
    "gn:feature_code":"PPL",
    "gn:name":"Fengjiawan",
    "gn:population":0,
    "gn:timezone":"Asia/Shanghai",
    "iso:country":"CN",
    "name:zho_x_preferred":[
        "\u51af\u5bb6\u6e7e"
    ],
    "wof:name":"Fengjiawan",
    "wof:placetype":"locality"
},
  "geometry": {"coordinates":[110.21547,30.83551],"type":"Point"}
}