{
  "type": "Feature",
  "properties": {
    "gn:admin1_code":"25",
    "gn:asciiname":"Lizhuang",
    "gn:country_code":"CN",
    "gn:dem":51,
    "gn:feature_class":"P",
    "gn:feature_code":"PPL",
    "gn:name":"Lizhuang",
    "gn:population":0,
    "gn:timezone":"Asia/Shanghai",
    "iso:country":"CN",
    "name:ceb_x_preferred":[
        "Lizhuang"
    ],
    "name:swe_x_preferred":[
        "Lizhuang"
    ],
    "name:zho_x_preferred":[
        "\u674e\u5e84"
    ],
    "wof:name":"Lizhuang",
    "wof:placetype":"locality"
},
  "geometry": {"coordinates":[115.58226999999999,35.50735],"type":"Point"}
}