{
  "type": "Feature",
  "properties": {
    "gn:admin1_code":"30.0",
    "gn:asciiname":"Xialou",
    "gn:country_code":"CN",
    "gn:dem":207,
    "gn:feature_class":"P",
    "gn:feature_code":"PPL",
    "gn:name":"Xialou",
    "gn:population":0,
    "gn:timezone":"Asia/Shanghai",
    "iso:country":"CN",
    "name:und_x_variant":[
        "\u4e0b\u697c"
    ],
    "name:zho_x_preferred":[
        "\u4e0b\u697c"
    ],
    "wof:name":"Xialou",
    "wof:placetype":"locality"
},
  "geometry": {"coordinates":[114.99639000000001,23.65768],"type":"Point"}
}