{
  "type": "Feature",
  "properties": {
    "gn:admin1_code":"24.0",
    "gn:asciiname":"Hanyang Wujing",
    "gn:country_code":"CN",
    "gn:dem":1705,
    "gn:feature_class":"P",
    "gn:feature_code":"PPL",
    "gn:name":"Hanyang Wujing",
    "gn:population":0,
    "gn:timezone":"Asia/Shanghai",
    "iso:country":"CN",
    "name:zho_x_preferred":[
        "\u97e9\u9633\u4e94\u4e95"
    ],
    "wof:name":"Hanyang Wujing",
    "wof:placetype":"locality"
},
  "geometry": {"coordinates":[112.32377,38.08152000000001],"type":"Point"}
}