{
  "type": "Feature",
  "properties": {
    "gn:admin1_code":"5.0",
    "gn:asciiname":"Xingshancun",
    "gn:country_code":"CN",
    "gn:dem":256,
    "gn:feature_class":"P",
    "gn:feature_code":"PPL",
    "gn:name":"Xingshancun",
    "gn:population":0,
    "gn:timezone":"Asia/Shanghai",
    "iso:country":"CN",
    "name:zho_x_preferred":[
        "\u5174\u5c71\u6751"
    ],
    "wof:name":"Xingshancun",
    "wof:placetype":"locality"
},
  "geometry": {"coordinates":[126.95001000000001,44.35497],"type":"Point"}
}