{
  "type": "Feature",
  "properties": {
    "gn:admin1_code":"1.0",
    "gn:asciiname":"Fangtangcun",
    "gn:country_code":"CN",
    "gn:dem":80,
    "gn:feature_class":"P",
    "gn:feature_code":"PPL",
    "gn:name":"Fangtangcun",
    "gn:population":0,
    "gn:timezone":"Asia/Shanghai",
    "iso:country":"CN",
    "name:zho_x_preferred":[
        "\u65b9\u5858\u6751"
    ],
    "wof:name":"Fangtangcun",
    "wof:placetype":"locality"
},
  "geometry": {"coordinates":[117.34896000000001,32.23468],"type":"Point"}
}