{
  "type": "Feature",
  "properties": {
    "gn:admin1_code":"12.0",
    "gn:asciiname":"Wangjiahe",
    "gn:country_code":"CN",
    "gn:dem":238,
    "gn:feature_class":"P",
    "gn:feature_code":"PPL",
    "gn:name":"Wangjiahe",
    "gn:population":0,
    "gn:timezone":"Asia/Shanghai",
    "iso:country":"CN",
    "name:zho_x_preferred":[
        "Wangjiahe"
    ],
    "name:zho_x_variant":[
        "\u738b\u5bb6\u6cb3"
    ],
    "wof:name":"Wangjiahe",
    "wof:placetype":"locality"
},
  "geometry": {"coordinates":[111.19029,30.77886],"type":"Point"}
}