{
  "type": "Feature",
  "properties": {
    "gn:admin1_code":"11.0",
    "gn:asciiname":"Tang'ao",
    "gn:country_code":"CN",
    "gn:dem":837,
    "gn:feature_class":"P",
    "gn:feature_code":"PPL",
    "gn:name":"Tang\u2019ao",
    "gn:population":0,
    "gn:timezone":"Asia/Shanghai",
    "iso:country":"CN",
    "name:und_x_variant":[
        "Tang\u2019ao"
    ],
    "name:zho_x_preferred":[
        "\u5858\u5773"
    ],
    "wof:name":"Tang'ao",
    "wof:placetype":"locality"
},
  "geometry": {"coordinates":[113.47571000000001,25.45318],"type":"Point"}
}