{
  "type": "Feature",
  "properties": {
    "gn:admin1_code":"19.0",
    "gn:asciiname":"Zoujiatuncun",
    "gn:country_code":"CN",
    "gn:dem":92,
    "gn:feature_class":"P",
    "gn:feature_code":"PPL",
    "gn:name":"Zoujiatuncun",
    "gn:population":0,
    "gn:timezone":"Asia/Shanghai",
    "iso:country":"CN",
    "name:zho_x_preferred":[
        "\u90b9\u5bb6\u5c6f\u6751"
    ],
    "wof:name":"Zoujiatuncun",
    "wof:placetype":"locality"
},
  "geometry": {"coordinates":[121.083,41.5765],"type":"Point"}
}