{
  "type": "Feature",
  "properties": {
    "gn:admin1_code":"10",
    "gn:asciiname":"Haoqian",
    "gn:country_code":"CN",
    "gn:dem":1403,
    "gn:feature_class":"P",
    "gn:feature_code":"PPL",
    "gn:name":"Haoqian",
    "gn:population":0,
    "gn:timezone":"Asia/Shanghai",
    "iso:country":"CN",
    "name:zho_x_preferred":[
        "\u58d5\u5811"
    ],
    "wof:name":"Haoqian",
    "wof:placetype":"locality"
},
  "geometry": {"coordinates":[115.15706000000002,41.51012],"type":"Point"}
}