{
  "type": "Feature",
  "properties": {
    "gn:admin1_code":"07",
    "gn:asciiname":"Shangluo",
    "gn:country_code":"CN",
    "gn:dem":396,
    "gn:feature_class":"P",
    "gn:feature_code":"PPL",
    "gn:name":"Shangluo",
    "gn:population":0,
    "gn:timezone":"Asia/Shanghai",
    "iso:country":"CN",
    "name:ara_x_preferred":[
        "\u0634\u0627\u0646\u063a\u0644\u0648"
    ],
    "name:cdo_x_preferred":[
        "Si\u014fng-l\u014fk"
    ],
    "name:ces_x_preferred":[
        "\u0160ang-luo"
    ],
    "name:dan_x_preferred":[
        "Shangluo"
    ],
    "name:deu_x_preferred":[
        "Shangluo"
    ],
    "name:eus_x_preferred":[
        "Shangluo"
    ],
    "name:fas_x_preferred":[
        "\u0634\u0627\u0646\u06af\u0644\u0648"
    ],
    "name:fin_x_preferred":[
        "Shangluo"
    ],
    "name:fra_x_preferred":[
        "Shangluo"
    ],
    "name:ita_x_preferred":[
        "Shangluo"
    ],
    "name:jpn_x_preferred":[
        "\u5546\u6d1b\u5e02"
    ],
    "name:kik_x_preferred":[
        "Shangluo"
    ],
    "name:kor_x_preferred":[
        "\uc0c1\ub904\uc2dc"
    ],
    "name:mlg_x_preferred":[
        "Shangluo"
    ],
    "name:nld_x_preferred":[
        "Shangluo"
    ],
    "name:nno_x_preferred":[
        "Shangluo"
    ],
    "name:nor_x_preferred":[
        "Shangluo"
    ],
    "name:pol_x_preferred":[
        "Shangluo"
    ],
    "name:rus_x_preferred":[
        "\u0428\u0430\u043d\u043b\u043e"
    ],
    "name:spa_x_preferred":[
        "Shangluo"
    ],
    "name:swe_x_preferred":[
        "Shangluo"
    ],
    "name:tur_x_preferred":[
        "Shangluo"
    ],
    "name:ukr_x_preferred":[
        "\u0428\u0430\u043d\u043b\u043e"
    ],
    "name:urd_x_preferred":[
        "\u0634\u0627\u0646\u06af\u0644\u06cc\u0648"
    ],
    "name:vie_x_preferred":[
        "Th\u01b0\u01a1ng L\u1ea1c"
    ],
    "name:war_x_preferred":[
        "Shangluo"
    ],
    "name:zho_x_preferred":[
        "\u4e0a\u87ba"
    ],
    "name:zho_x_variant":[
        "\u5546\u6d1b\u5e02"
    ],
    "wof:name":"Shangluo",
    "wof:placetype":"locality"
},
  "geometry": {"coordinates":[117.39972,25.7925],"type":"Point"}
}