{
  "type": "Feature",
  "properties": {
    "gn:admin1_code":"10",
    "gn:asciiname":"Bieguzhuang",
    "gn:cc2":"CN",
    "gn:country_code":"CN",
    "gn:dem":19,
    "gn:feature_class":"P",
    "gn:feature_code":"PPL",
    "gn:name":"Bieguzhuang",
    "gn:population":0,
    "gn:timezone":"Asia/Shanghai",
    "iso:country":"CN",
    "name:und_x_variant":[
        "Pieh-chuang",
        "Pieh-ku-chuang",
        "Bieguzhuang"
    ],
    "wof:name":"Bieguzhuang",
    "wof:placetype":"locality"
},
  "geometry": {"coordinates":[116.65971999999999,39.31222],"type":"Point"}
}