{
  "type": "Feature",
  "properties": {
    "gn:admin1_code":"19.0",
    "gn:asciiname":"Houlaohuguan",
    "gn:country_code":"CN",
    "gn:dem":108,
    "gn:feature_class":"P",
    "gn:feature_code":"PPL",
    "gn:name":"Houlaohuguan",
    "gn:population":0,
    "gn:timezone":"Asia/Shanghai",
    "iso:country":"CN",
    "name:zho_x_preferred":[
        "\u540e\u8001\u864e\u5173"
    ],
    "wof:name":"Houlaohuguan",
    "wof:placetype":"locality"
},
  "geometry": {"coordinates":[120.83199999999999,41.2257],"type":"Point"}
}