{
  "type": "Feature",
  "properties": {
    "gn:admin1_code":"31.0",
    "gn:asciiname":"Xinlian Yicun",
    "gn:country_code":"CN",
    "gn:dem":251,
    "gn:feature_class":"P",
    "gn:feature_code":"PPL",
    "gn:name":"Xinlian Yicun",
    "gn:population":0,
    "gn:timezone":"Asia/Shanghai",
    "iso:country":"CN",
    "name:und_x_variant":[
        "\u65b0\u8054\u4e00\u6751"
    ],
    "wof:name":"Xinlian Yicun",
    "wof:placetype":"locality"
},
  "geometry": {"coordinates":[109.92925,18.88047000000001],"type":"Point"}
}