{
  "type": "Feature",
  "properties": {
    "gn:admin1_code":"19.0",
    "gn:asciiname":"Zhoujia Buzi",
    "gn:country_code":"CN",
    "gn:dem":222,
    "gn:feature_class":"P",
    "gn:feature_code":"PPL",
    "gn:name":"Zhoujia Buzi",
    "gn:population":0,
    "gn:timezone":"Asia/Shanghai",
    "iso:country":"CN",
    "name:und_x_variant":[
        "Zhoujia Puzi",
        "\u5468\u5bb6\u5821\u5b50",
        "Zhoujia Buzi"
    ],
    "wof:name":"Zhoujia Buzi",
    "wof:placetype":"locality"
},
  "geometry": {"coordinates":[123.12895,40.23636],"type":"Point"}
}