{
  "type": "Feature",
  "properties": {
    "gn:admin1_code":"29.0",
    "gn:asciiname":"Shipenzi",
    "gn:country_code":"CN",
    "gn:dem":2046,
    "gn:feature_class":"P",
    "gn:feature_code":"PPL",
    "gn:name":"Shipenzi",
    "gn:population":0,
    "gn:timezone":"Asia/Shanghai",
    "iso:country":"CN",
    "name:zho_x_preferred":[
        "\u77f3\u76c6\u5b50"
    ],
    "wof:name":"Shipenzi",
    "wof:placetype":"locality"
},
  "geometry": {"coordinates":[103.919,25.09800000000001],"type":"Point"}
}