{
  "type": "Feature",
  "properties": {
    "gn:admin1_code":"5.0",
    "gn:asciiname":"Minlicun",
    "gn:country_code":"CN",
    "gn:dem":190,
    "gn:feature_class":"P",
    "gn:feature_code":"PPL",
    "gn:name":"Minlicun",
    "gn:population":0,
    "gn:timezone":"Asia/Shanghai",
    "iso:country":"CN",
    "name:zho_x_preferred":[
        "\u6c11\u7acb\u6751"
    ],
    "wof:name":"Minlicun",
    "wof:placetype":"locality"
},
  "geometry": {"coordinates":[124.84780000000001,43.92144],"type":"Point"}
}