{
  "type": "Feature",
  "properties": {
    "gn:admin1_code":"26.0",
    "gn:asciiname":"Pingluocun",
    "gn:country_code":"CN",
    "gn:dem":354,
    "gn:feature_class":"P",
    "gn:feature_code":"PPL",
    "gn:name":"Pingluocun",
    "gn:population":0,
    "gn:timezone":"Asia/Shanghai",
    "iso:country":"CN",
    "name:zho_x_preferred":[
        "\u5e73\u7f57\u6751"
    ],
    "wof:name":"Pingluocun",
    "wof:placetype":"locality"
},
  "geometry": {"coordinates":[110.03588999999999,34.80104],"type":"Point"}
}