{
  "type": "Feature",
  "properties": {
    "gn:admin1_code":"14.0",
    "gn:asciiname":"Rusangcun",
    "gn:country_code":"CN",
    "gn:dem":3966,
    "gn:feature_class":"P",
    "gn:feature_code":"PPL",
    "gn:name":"Rusangcun",
    "gn:population":0,
    "gn:timezone":"Asia/Urumqi",
    "iso:country":"CN",
    "name:zho_x_preferred":[
        "\u5982\u6851\u6751"
    ],
    "wof:name":"Rusangcun",
    "wof:placetype":"locality"
},
  "geometry": {"coordinates":[95.06381,31.43655],"type":"Point"}
}