{
  "type": "Feature",
  "properties": {
    "gn:admin1_code":"32.0",
    "gn:asciiname":"Reshuigou",
    "gn:country_code":"CN",
    "gn:dem":3570,
    "gn:feature_class":"P",
    "gn:feature_code":"PPL",
    "gn:name":"Reshuigou",
    "gn:population":0,
    "gn:timezone":"Asia/Shanghai",
    "iso:country":"CN",
    "name:zho_x_preferred":[
        "\u70ed\u6c34\u6c9f"
    ],
    "wof:name":"Reshuigou",
    "wof:placetype":"locality"
},
  "geometry": {"coordinates":[101.13500000000001,29.176],"type":"Point"}
}