{
  "type": "Feature",
  "properties": {
    "gn:admin1_code":"6.0",
    "gn:asciiname":"Daidida",
    "gn:country_code":"CN",
    "gn:dem":3856,
    "gn:feature_class":"P",
    "gn:feature_code":"PPL",
    "gn:name":"Daidida",
    "gn:population":0,
    "gn:timezone":"Asia/Urumqi",
    "iso:country":"CN",
    "name:zho_x_preferred":[
        "\u4ee3\u4f4e\u8fbe"
    ],
    "wof:name":"Daidida",
    "wof:placetype":"locality"
},
  "geometry": {"coordinates":[96.48057,32.04157],"type":"Point"}
}