{
  "type": "Feature",
  "properties": {
    "gn:admin1_code":"11",
    "gn:asciiname":"Dayun",
    "gn:country_code":"CN",
    "gn:dem":874,
    "gn:feature_class":"P",
    "gn:feature_code":"PPL",
    "gn:name":"Dayun",
    "gn:population":0,
    "gn:timezone":"Asia/Shanghai",
    "iso:country":"CN",
    "wof:name":"Dayun",
    "wof:placetype":"locality"
},
  "geometry": {"coordinates":[110.87555999999999,26.35056],"type":"Point"}
}