{
  "type": "Feature",
  "properties": {
    "gn:admin1_code":"26.0",
    "gn:asciiname":"Shanghepei",
    "gn:country_code":"CN",
    "gn:dem":1199,
    "gn:feature_class":"P",
    "gn:feature_code":"PPL",
    "gn:name":"Shanghepei",
    "gn:population":0,
    "gn:timezone":"Asia/Shanghai",
    "iso:country":"CN",
    "name:zho_x_preferred":[
        "\u4e0a\u5408\u914d"
    ],
    "wof:name":"Shanghepei",
    "wof:placetype":"locality"
},
  "geometry": {"coordinates":[109.99664,36.19228],"type":"Point"}
}