{
  "type": "Feature",
  "properties": {
    "gn:admin1_code":"7.0",
    "gn:asciiname":"Zucuo",
    "gn:country_code":"CN",
    "gn:dem":809,
    "gn:feature_class":"P",
    "gn:feature_code":"PPL",
    "gn:name":"Zucuo",
    "gn:population":0,
    "gn:timezone":"Asia/Shanghai",
    "iso:country":"CN",
    "name:zho_x_preferred":[
        "\u7956\u539d"
    ],
    "wof:name":"Zucuo",
    "wof:placetype":"locality"
},
  "geometry": {"coordinates":[117.91551,25.26411],"type":"Point"}
}