{
  "type": "Feature",
  "properties": {
    "gn:admin1_code":"2.0",
    "gn:asciiname":"Zhimatan",
    "gn:country_code":"CN",
    "gn:dem":574,
    "gn:feature_class":"P",
    "gn:feature_code":"PPL",
    "gn:name":"Zhimatan",
    "gn:population":0,
    "gn:timezone":"Asia/Shanghai",
    "iso:country":"CN",
    "name:zho_x_preferred":[
        "\u829d\u9ebb\u5766"
    ],
    "wof:name":"Zhimatan",
    "wof:placetype":"locality"
},
  "geometry": {"coordinates":[119.75311000000001,27.53683],"type":"Point"}
}