{
  "type": "Feature",
  "properties": {
    "gn:admin1_code":"29.0",
    "gn:asciiname":"Misong",
    "gn:country_code":"CN",
    "gn:dem":1753,
    "gn:feature_class":"P",
    "gn:feature_code":"PPL",
    "gn:name":"Misong",
    "gn:population":0,
    "gn:timezone":"Asia/Shanghai",
    "iso:country":"CN",
    "name:zho_x_preferred":[
        "\u5bc6\u677e"
    ],
    "wof:name":"Misong",
    "wof:placetype":"locality"
},
  "geometry": {"coordinates":[98.96850000000001,25.2799],"type":"Point"}
}