{
  "type": "Feature",
  "properties": {
    "gn:admin1_code":"4.0",
    "gn:asciiname":"Xinwo Erzu",
    "gn:country_code":"CN",
    "gn:dem":7,
    "gn:feature_class":"P",
    "gn:feature_code":"PPL",
    "gn:name":"Xinwo Erzu",
    "gn:population":0,
    "gn:timezone":"Asia/Shanghai",
    "iso:country":"CN",
    "name:zho_x_preferred":[
        "\u65b0\u6c83\u4e8c\u7ec4"
    ],
    "wof:name":"Xinwo Erzu",
    "wof:placetype":"locality"
},
  "geometry": {"coordinates":[118.76846999999999,31.36381],"type":"Point"}
}