{
  "type": "Feature",
  "properties": {
    "gn:admin1_code":"2.0",
    "gn:asciiname":"Baiqiangmen",
    "gn:country_code":"CN",
    "gn:dem":18,
    "gn:feature_class":"P",
    "gn:feature_code":"PPL",
    "gn:name":"Baiqiangmen",
    "gn:population":0,
    "gn:timezone":"Asia/Shanghai",
    "iso:country":"CN",
    "name:zho_x_preferred":[
        "\u767d\u5899\u95e8"
    ],
    "wof:name":"Baiqiangmen",
    "wof:placetype":"locality"
},
  "geometry": {"coordinates":[121.2079,30.13766],"type":"Point"}
}