{
  "type": "Feature",
  "properties": {
    "gn:admin1_code":"14.0",
    "gn:asciiname":"Parag",
    "gn:country_code":"CN",
    "gn:dem":4347,
    "gn:feature_class":"P",
    "gn:feature_code":"PPL",
    "gn:name":"Parag",
    "gn:population":0,
    "gn:timezone":"Asia/Urumqi",
    "iso:country":"CN",
    "name:bod_x_preferred":[
        "Parag"
    ],
    "name:zho_x_preferred":[
        "Pare"
    ],
    "name:zho_x_variant":[
        "\u5e15\u70ed",
        "Pabu Gongshe",
        "\u5e15\u5e03\u516c\u793e"
    ],
    "wof:name":"Parag",
    "wof:placetype":"locality"
},
  "geometry": {"coordinates":[87.39279999999999,29.102],"type":"Point"}
}