{
  "type": "Feature",
  "properties": {
    "gn:admin1_code":"32.0",
    "gn:asciiname":"Labagou",
    "gn:country_code":"CN",
    "gn:dem":1128,
    "gn:feature_class":"P",
    "gn:feature_code":"PPL",
    "gn:name":"Labagou",
    "gn:population":0,
    "gn:timezone":"Asia/Shanghai",
    "iso:country":"CN",
    "name:zho_x_preferred":[
        "\u5587\u53ed\u6c9f"
    ],
    "wof:name":"Labagou",
    "wof:placetype":"locality"
},
  "geometry": {"coordinates":[102.241,26.2352],"type":"Point"}
}