{
  "type": "Feature",
  "properties": {
    "gn:admin1_code":"24.0",
    "gn:asciiname":"Lisi",
    "gn:country_code":"CN",
    "gn:dem":1128,
    "gn:feature_class":"P",
    "gn:feature_code":"PPL",
    "gn:name":"Lisi",
    "gn:population":0,
    "gn:timezone":"Asia/Shanghai",
    "iso:country":"CN",
    "name:ceb_x_preferred":[
        "Lisi"
    ],
    "name:deu_x_preferred":[
        "Lisi"
    ],
    "name:fas_x_preferred":[
        "\u0644\u06cc\u0633\u06cc"
    ],
    "name:fra_x_preferred":[
        "Lisi"
    ],
    "name:heb_x_preferred":[
        "\u05dc\u05d9\u05e1\u05d9"
    ],
    "name:ita_x_preferred":[
        "Lisi"
    ],
    "name:kat_x_preferred":[
        "\u10da\u10d8\u10e1\u10d8"
    ],
    "name:rus_x_preferred":[
        "\u041b\u0438\u0441\u0438"
    ],
    "name:swe_x_preferred":[
        "Lisi"
    ],
    "name:zho_x_preferred":[
        "\u91cc\u601d"
    ],
    "wof:name":"Lisi",
    "wof:placetype":"locality"
},
  "geometry": {"coordinates":[113.21623999999998,37.67288],"type":"Point"}
}