{
  "type": "Feature",
  "properties": {
    "gn:admin1_code":"05",
    "gn:asciiname":"Ta-la-tzu-kou (West)",
    "gn:country_code":"CN",
    "gn:dem":624,
    "gn:feature_class":"P",
    "gn:feature_code":"PPL",
    "gn:name":"Ta-la-tzu-kou (West)",
    "gn:population":0,
    "gn:timezone":"Asia/Shanghai",
    "iso:country":"CN",
    "wof:name":"Ta-la-tzu-kou (West)",
    "wof:placetype":"locality"
},
  "geometry": {"coordinates":[126.06083,41.63389],"type":"Point"}
}