{
  "type": "Feature",
  "properties": {
    "gn:admin1_code":"29.0",
    "gn:asciiname":"Xiaopingzi",
    "gn:country_code":"CN",
    "gn:dem":1522,
    "gn:feature_class":"P",
    "gn:feature_code":"PPL",
    "gn:name":"Xiaopingzi",
    "gn:population":0,
    "gn:timezone":"Asia/Shanghai",
    "iso:country":"CN",
    "name:zho_x_preferred":[
        "\u5c0f\u576a\u5b50"
    ],
    "wof:name":"Xiaopingzi",
    "wof:placetype":"locality"
},
  "geometry": {"coordinates":[103.099,22.9121],"type":"Point"}
}