{
  "type": "Feature",
  "properties": {
    "gn:admin1_code":"8.0",
    "gn:asciiname":"Jianshe Sidui",
    "gn:country_code":"CN",
    "gn:dem":298,
    "gn:feature_class":"P",
    "gn:feature_code":"PPLF",
    "gn:name":"Jianshe Sidui",
    "gn:population":0,
    "gn:timezone":"Asia/Shanghai",
    "iso:country":"CN",
    "name:zho_x_preferred":[
        "\u5efa\u8bbe\u56db\u961f"
    ],
    "wof:name":"Jianshe Sidui",
    "wof:placetype":"locality"
},
  "geometry": {"coordinates":[125.68804,48.31084],"type":"Point"}
}