{
  "type": "Feature",
  "properties": {
    "gn:admin1_code":"25.0",
    "gn:asciiname":"Dazhuohe",
    "gn:country_code":"CN",
    "gn:dem":6,
    "gn:feature_class":"P",
    "gn:feature_code":"PPL",
    "gn:name":"Dazhuohe",
    "gn:population":0,
    "gn:timezone":"Asia/Shanghai",
    "iso:country":"CN",
    "name:zho_x_preferred":[
        "\u5927\u6d5e\u6cb3"
    ],
    "wof:name":"Dazhuohe",
    "wof:placetype":"locality"
},
  "geometry": {"coordinates":[119.68291000000001,37.01364],"type":"Point"}
}