{
  "type": "Feature",
  "properties": {
    "gn:admin1_code":"10",
    "gn:asciiname":"Hongtangsi",
    "gn:country_code":"CN",
    "gn:dem":781,
    "gn:feature_class":"P",
    "gn:feature_code":"PPL",
    "gn:name":"Hongtangsi",
    "gn:population":0,
    "gn:timezone":"Asia/Shanghai",
    "iso:country":"CN",
    "name:und_x_variant":[
        "Hung-t\u2019ang-ssu",
        "Hongtangsi"
    ],
    "name:zho_x_preferred":[
        "\u6d2a\u6c64\u5bfa"
    ],
    "wof:name":"Hongtangsi",
    "wof:placetype":"locality"
},
  "geometry": {"coordinates":[116.49302,41.11911],"type":"Point"}
}