{
  "type": "Feature",
  "properties": {
    "gn:admin1_code":"30.0",
    "gn:asciiname":"Xinweizai",
    "gn:country_code":"CN",
    "gn:dem":85,
    "gn:feature_class":"P",
    "gn:feature_code":"PPL",
    "gn:name":"Xinweizai",
    "gn:population":0,
    "gn:timezone":"Asia/Shanghai",
    "iso:country":"CN",
    "name:zho_x_preferred":[
        "\u65b0\u56f4\u4ed4"
    ],
    "wof:name":"Xinweizai",
    "wof:placetype":"locality"
},
  "geometry": {"coordinates":[113.64673000000001,23.71346],"type":"Point"}
}