{
  "type": "Feature",
  "properties": {
    "gn:admin1_code":"15.0",
    "gn:asciiname":"Zuitou Zhaojia",
    "gn:country_code":"CN",
    "gn:dem":1102,
    "gn:feature_class":"P",
    "gn:feature_code":"PPL",
    "gn:name":"Zuitou Zhaojia",
    "gn:population":0,
    "gn:timezone":"Asia/Shanghai",
    "iso:country":"CN",
    "name:zho_x_preferred":[
        "\u5480\u5934\u8d75\u5bb6"
    ],
    "wof:name":"Zuitou Zhaojia",
    "wof:placetype":"locality"
},
  "geometry": {"coordinates":[107.83199999999999,35.2948],"type":"Point"}
}