{
  "type": "Feature",
  "properties": {
    "gn:admin1_code":"29",
    "gn:asciiname":"Bachong",
    "gn:country_code":"CN",
    "gn:dem":2085,
    "gn:feature_class":"P",
    "gn:feature_code":"PPL",
    "gn:name":"Bachong",
    "gn:population":0,
    "gn:timezone":"Asia/Shanghai",
    "iso:country":"CN",
    "name:zho_x_preferred":[
        "\u575d\u51b2"
    ],
    "wof:name":"Bachong",
    "wof:placetype":"locality"
},
  "geometry": {"coordinates":[101.425,25.0328],"type":"Point"}
}