{
  "type": "Feature",
  "properties": {
    "gn:admin1_code":"07",
    "gn:asciiname":"Shanshiliao",
    "gn:country_code":"CN",
    "gn:dem":406,
    "gn:feature_class":"P",
    "gn:feature_code":"PPL",
    "gn:name":"Shanshiliao",
    "gn:population":0,
    "gn:timezone":"Asia/Shanghai",
    "iso:country":"CN",
    "name:zho_x_preferred":[
        "\u5c71\u77f3\u5bee"
    ],
    "wof:name":"Shanshiliao",
    "wof:placetype":"locality"
},
  "geometry": {"coordinates":[117.09361,25.27139],"type":"Point"}
}