{
  "type": "Feature",
  "properties": {
    "gn:admin1_code":"32.0",
    "gn:asciiname":"Zhashi",
    "gn:cc2":"CN",
    "gn:country_code":"CN",
    "gn:dem":1146,
    "gn:feature_class":"P",
    "gn:feature_code":"PPL",
    "gn:name":"Zhashi",
    "gn:population":0,
    "gn:timezone":"Asia/Shanghai",
    "iso:country":"CN",
    "name:und_x_variant":[
        "Hsiao-cha-shih",
        "Cha-shih",
        "Zhashi"
    ],
    "wof:name":"Zhashi",
    "wof:placetype":"locality"
},
  "geometry": {"coordinates":[101.86667,26.58333],"type":"Point"}
}