{
  "type": "Feature",
  "properties": {
    "gn:admin1_code":"04",
    "gn:asciiname":"Dongqiangmen",
    "gn:cc2":"CN",
    "gn:country_code":"CN",
    "gn:dem":7,
    "gn:feature_class":"P",
    "gn:feature_code":"PPL",
    "gn:name":"Dongqiangmen",
    "gn:population":0,
    "gn:timezone":"Asia/Shanghai",
    "iso:country":"CN",
    "name:und_x_variant":[
        "Ta-ch\u2019iang-men",
        "Dongqiangmen"
    ],
    "wof:name":"Dongqiangmen",
    "wof:placetype":"locality"
},
  "geometry": {"coordinates":[120.53556,31.82639],"type":"Point"}
}