{
  "type": "Feature",
  "properties": {
    "gn:admin1_code":"4.0",
    "gn:asciiname":"Dongnanzhuang",
    "gn:country_code":"CN",
    "gn:dem":5,
    "gn:feature_class":"P",
    "gn:feature_code":"PPL",
    "gn:name":"Dongnanzhuang",
    "gn:population":0,
    "gn:timezone":"Asia/Shanghai",
    "iso:country":"CN",
    "name:zho_x_preferred":[
        "Dongnanzhuang"
    ],
    "name:zho_x_variant":[
        "\u4e1c\u5357\u5e84"
    ],
    "wof:name":"Dongnanzhuang",
    "wof:placetype":"locality"
},
  "geometry": {"coordinates":[119.12923000000001,34.82847],"type":"Point"}
}