{
  "type": "Feature",
  "properties": {
    "gn:admin1_code":"8.0",
    "gn:asciiname":"Baoquangou",
    "gn:country_code":"CN",
    "gn:dem":271,
    "gn:feature_class":"P",
    "gn:feature_code":"PPL",
    "gn:name":"Baoquangou",
    "gn:population":0,
    "gn:timezone":"Asia/Shanghai",
    "iso:country":"CN",
    "name:zho_x_preferred":[
        "\u5b9d\u6cc9\u6c9f"
    ],
    "wof:name":"Baoquangou",
    "wof:placetype":"locality"
},
  "geometry": {"coordinates":[125.96303,51.63652],"type":"Point"}
}