{
  "type": "Feature",
  "properties": {
    "gn:admin1_code":"32.0",
    "gn:asciiname":"Shangmuyabu",
    "gn:country_code":"CN",
    "gn:dem":1574,
    "gn:feature_class":"P",
    "gn:feature_code":"PPL",
    "gn:name":"Shangmuyabu",
    "gn:population":0,
    "gn:timezone":"Asia/Shanghai",
    "iso:country":"CN",
    "name:zho_x_preferred":[
        "\u4e0a\u6728\u57ad\u5821"
    ],
    "wof:name":"Shangmuyabu",
    "wof:placetype":"locality"
},
  "geometry": {"coordinates":[102.212,29.3498],"type":"Point"}
}