{
  "type": "Feature",
  "properties": {
    "gn:admin1_code":"14.0",
    "gn:asciiname":"Yeyi",
    "gn:country_code":"CN",
    "gn:dem":3855,
    "gn:feature_class":"P",
    "gn:feature_code":"PPLF",
    "gn:name":"Yeyi",
    "gn:population":0,
    "gn:timezone":"Asia/Urumqi",
    "iso:country":"CN",
    "name:bod_x_preferred":[
        "Y\u00eayai"
    ],
    "name:fra_x_preferred":[
        "Yeyi"
    ],
    "name:zho_x_preferred":[
        "Yeyi"
    ],
    "name:zho_x_variant":[
        "\u4e5f\u4f9d"
    ],
    "wof:name":"Yeyi",
    "wof:placetype":"locality"
},
  "geometry": {"coordinates":[95.45598,30.88978],"type":"Point"}
}