{
  "type": "Feature",
  "properties": {
    "gn:admin1_code":"4.0",
    "gn:asciiname":"Shenji",
    "gn:country_code":"CN",
    "gn:dem":8,
    "gn:feature_class":"P",
    "gn:feature_code":"PPL",
    "gn:name":"Shenji",
    "gn:population":0,
    "gn:timezone":"Asia/Shanghai",
    "iso:country":"CN",
    "name:zho_x_preferred":[
        "Shenji"
    ],
    "name:zho_x_variant":[
        "\u6c88\u96c6"
    ],
    "wof:name":"Shenji",
    "wof:placetype":"locality"
},
  "geometry": {"coordinates":[119.09291,34.02439],"type":"Point"}
}