{
  "type": "Feature",
  "properties": {
    "gn:admin1_code":"30",
    "gn:asciiname":"Xintang",
    "gn:country_code":"CN",
    "gn:dem":116,
    "gn:feature_class":"P",
    "gn:feature_code":"PPL",
    "gn:name":"Xintang",
    "gn:population":0,
    "gn:timezone":"Asia/Shanghai",
    "iso:country":"CN",
    "name:und_x_variant":[
        "\u65b0\u5858",
        "Xintangguan"
    ],
    "wof:name":"Xintang",
    "wof:placetype":"locality"
},
  "geometry": {"coordinates":[112.34860999999999,24.84472],"type":"Point"}
}