{
  "type": "Feature",
  "properties": {
    "gn:admin1_code":"29",
    "gn:asciiname":"Xiagaoguma",
    "gn:country_code":"CN",
    "gn:dem":1555,
    "gn:feature_class":"P",
    "gn:feature_code":"PPL",
    "gn:name":"Xiagaoguma",
    "gn:population":0,
    "gn:timezone":"Asia/Shanghai",
    "iso:country":"CN",
    "name:zho_x_preferred":[
        "\u4e0b\u9ad8\u53e4\u9a6c"
    ],
    "wof:name":"Xiagaoguma",
    "wof:placetype":"locality"
},
  "geometry": {"coordinates":[103.136,24.7763],"type":"Point"}
}