{
  "type": "Feature",
  "properties": {
    "gn:admin1_code":"1.0",
    "gn:asciiname":"Jianguo",
    "gn:country_code":"CN",
    "gn:dem":18,
    "gn:feature_class":"P",
    "gn:feature_code":"PPL",
    "gn:name":"Jianguo",
    "gn:population":0,
    "gn:timezone":"Asia/Shanghai",
    "iso:country":"CN",
    "name:und_x_variant":[
        "\u5efa\u56fd"
    ],
    "wof:name":"Jianguo",
    "wof:placetype":"locality"
},
  "geometry": {"coordinates":[118.88333,30.93333],"type":"Point"}
}