{
  "type": "Feature",
  "properties": {
    "gn:admin1_code":"19.0",
    "gn:asciiname":"Xiaoshentun",
    "gn:country_code":"CN",
    "gn:dem":42,
    "gn:feature_class":"P",
    "gn:feature_code":"PPL",
    "gn:name":"Xiaoshentun",
    "gn:population":0,
    "gn:timezone":"Asia/Shanghai",
    "iso:country":"CN",
    "name:zho_x_preferred":[
        "\u5c0f\u6c88\u5c6f"
    ],
    "wof:name":"Xiaoshentun",
    "wof:placetype":"locality"
},
  "geometry": {"coordinates":[120.93000000000001,40.9634],"type":"Point"}
}