{
  "type": "Feature",
  "properties": {
    "gn:admin1_code":"8.0",
    "gn:asciiname":"Xinglongdiancun",
    "gn:country_code":"CN",
    "gn:dem":336,
    "gn:feature_class":"P",
    "gn:feature_code":"PPL",
    "gn:name":"Xinglongdiancun",
    "gn:population":0,
    "gn:timezone":"Asia/Shanghai",
    "iso:country":"CN",
    "name:zho_x_preferred":[
        "\u5174\u9686\u5e97\u6751"
    ],
    "wof:name":"Xinglongdiancun",
    "wof:placetype":"locality"
},
  "geometry": {"coordinates":[129.14146000000002,44.23864],"type":"Point"}
}