{
  "type": "Feature",
  "properties": {
    "gn:admin1_code":"19.0",
    "gn:asciiname":"Xietuncun",
    "gn:country_code":"CN",
    "gn:dem":2,
    "gn:feature_class":"P",
    "gn:feature_code":"PPL",
    "gn:name":"Xietuncun",
    "gn:population":0,
    "gn:timezone":"Asia/Shanghai",
    "iso:country":"CN",
    "name:und_x_variant":[
        "Hsieh-t\u2019un",
        "Xietun",
        "Xietuncun"
    ],
    "name:zho_x_preferred":[
        "\u8c22\u5c6f\u6751"
    ],
    "wof:name":"Xietuncun",
    "wof:placetype":"locality"
},
  "geometry": {"coordinates":[121.51812,39.44566],"type":"Point"}
}