{
  "type": "Feature",
  "properties": {
    "gn:admin1_code":"7.0",
    "gn:asciiname":"Zhaili",
    "gn:country_code":"CN",
    "gn:dem":276,
    "gn:feature_class":"P",
    "gn:feature_code":"PPL",
    "gn:name":"Zhaili",
    "gn:population":0,
    "gn:timezone":"Asia/Shanghai",
    "iso:country":"CN",
    "name:und_x_variant":[
        "Chai-li",
        "Zhaili"
    ],
    "name:zho_x_preferred":[
        "\u5be8\u91cc"
    ],
    "wof:name":"Zhaili",
    "wof:placetype":"locality"
},
  "geometry": {"coordinates":[117.413,27.69509],"type":"Point"}
}