{
  "type": "Feature",
  "properties": {
    "gn:admin1_code":"16.0",
    "gn:asciiname":"Silu",
    "gn:country_code":"CN",
    "gn:dem":180,
    "gn:feature_class":"P",
    "gn:feature_code":"PPL",
    "gn:name":"Silu",
    "gn:population":0,
    "gn:timezone":"Asia/Shanghai",
    "iso:country":"CN",
    "name:ceb_x_preferred":[
        "Silu"
    ],
    "name:swe_x_preferred":[
        "Silu"
    ],
    "name:zho_x_preferred":[
        "\u56db\u9e93"
    ],
    "wof:name":"Silu",
    "wof:placetype":"locality"
},
  "geometry": {"coordinates":[108.583,23.0058],"type":"Point"}
}