{
  "type": "Feature",
  "properties": {
    "gn:admin1_code":"29.0",
    "gn:asciiname":"Shicaozi",
    "gn:country_code":"CN",
    "gn:dem":2053,
    "gn:feature_class":"P",
    "gn:feature_code":"PPL",
    "gn:name":"Shicaozi",
    "gn:population":0,
    "gn:timezone":"Asia/Shanghai",
    "iso:country":"CN",
    "name:zho_x_preferred":[
        "\u77f3\u69fd\u5b50"
    ],
    "wof:name":"Shicaozi",
    "wof:placetype":"locality"
},
  "geometry": {"coordinates":[103.52500000000001,25.5924],"type":"Point"}
}