{
  "type": "Feature",
  "properties": {
    "gn:admin1_code":"19.0",
    "gn:asciiname":"Xiaoyong'an",
    "gn:country_code":"CN",
    "gn:dem":250,
    "gn:feature_class":"P",
    "gn:feature_code":"PPL",
    "gn:name":"Xiaoyong\u2019an",
    "gn:population":0,
    "gn:timezone":"Asia/Shanghai",
    "iso:country":"CN",
    "name:zho_x_preferred":[
        "Xiaoyong\u2019an"
    ],
    "name:zho_x_variant":[
        "\u5c0f\u6c38\u5b89"
    ],
    "wof:name":"Xiaoyong'an",
    "wof:placetype":"locality"
},
  "geometry": {"coordinates":[124.8338,42.62683],"type":"Point"}
}