{
  "type": "Feature",
  "properties": {
    "gn:admin1_code":"7",
    "gn:asciiname":"Jiulou",
    "gn:country_code":"CN",
    "gn:dem":72,
    "gn:feature_class":"P",
    "gn:feature_code":"PPL",
    "gn:name":"Jiulou",
    "gn:population":0,
    "gn:timezone":"Asia/Shanghai",
    "iso:country":"CN",
    "name:zho_x_preferred":[
        "\u65e7\u697c"
    ],
    "wof:name":"Jiulou",
    "wof:placetype":"locality"
},
  "geometry": {"coordinates":[117.26703999999999,24.38572000000001],"type":"Point"}
}