{
  "type": "Feature",
  "properties": {
    "gn:admin1_code":"29.0",
    "gn:asciiname":"Yinchang",
    "gn:country_code":"CN",
    "gn:dem":1110,
    "gn:feature_class":"P",
    "gn:feature_code":"PPL",
    "gn:name":"Yinchang",
    "gn:population":0,
    "gn:timezone":"Asia/Shanghai",
    "iso:country":"CN",
    "name:deu_x_preferred":[
        "Yin-Chang"
    ],
    "name:jpn_x_preferred":[
        "\u30a4\u30f3\u660c"
    ],
    "name:zho_x_preferred":[
        "\u94f6\u5382"
    ],
    "wof:name":"Yinchang",
    "wof:placetype":"locality"
},
  "geometry": {"coordinates":[101.238,21.9795],"type":"Point"}
}