{
  "type": "Feature",
  "properties": {
    "gn:admin1_code":"33.0",
    "gn:asciiname":"Doukou",
    "gn:country_code":"CN",
    "gn:dem":527,
    "gn:feature_class":"P",
    "gn:feature_code":"PPL",
    "gn:name":"Doukou",
    "gn:population":0,
    "gn:timezone":"Asia/Shanghai",
    "iso:country":"CN",
    "name:zho_x_preferred":[
        "\u6597\u53e3"
    ],
    "wof:name":"Doukou",
    "wof:placetype":"locality"
},
  "geometry": {"coordinates":[108.10102000000001,30.17367],"type":"Point"}
}