{
  "type": "Feature",
  "properties": {
    "gn:admin1_code":"11",
    "gn:asciiname":"Shigongqiao",
    "gn:country_code":"CN",
    "gn:dem":25,
    "gn:feature_class":"P",
    "gn:feature_code":"PPLA4",
    "gn:name":"Shigongqiao",
    "gn:population":0,
    "gn:timezone":"Asia/Shanghai",
    "iso:country":"CN",
    "name:und_x_variant":[
        "Shih-kong-chow",
        "Shihkungkiao",
        "Shigongqiao",
        "\u77f3\u516c\u6865",
        "Shigongqiao Zhen",
        "\u77f3\u516c\u6865\u9547"
    ],
    "wof:name":"Shigongqiao",
    "wof:placetype":"locality"
},
  "geometry": {"coordinates":[111.86667,29.18333],"type":"Point"}
}