{
  "type": "Feature",
  "properties": {
    "gn:admin1_code":"32.0",
    "gn:asciiname":"Wenxingsi",
    "gn:country_code":"CN",
    "gn:dem":568,
    "gn:feature_class":"P",
    "gn:feature_code":"PPL",
    "gn:name":"Wenxingsi",
    "gn:population":0,
    "gn:timezone":"Asia/Shanghai",
    "iso:country":"CN",
    "name:zho_x_preferred":[
        "\u6587\u661f\u5bfa"
    ],
    "wof:name":"Wenxingsi",
    "wof:placetype":"locality"
},
  "geometry": {"coordinates":[103.87612,30.83113],"type":"Point"}
}