{
  "type": "Feature",
  "properties": {
    "gn:admin1_code":"8.0",
    "gn:asciiname":"Hantou",
    "gn:country_code":"CN",
    "gn:dem":155,
    "gn:feature_class":"P",
    "gn:feature_code":"PPL",
    "gn:name":"Hantou",
    "gn:population":0,
    "gn:timezone":"Asia/Shanghai",
    "iso:country":"CN",
    "name:zho_x_preferred":[
        "\u7f55\u5934"
    ],
    "wof:name":"Hantou",
    "wof:placetype":"locality"
},
  "geometry": {"coordinates":[123.39128999999998,47.12843],"type":"Point"}
}