{
  "type": "Feature",
  "properties": {
    "gn:admin1_code":"18",
    "gn:asciiname":"Dengjia Nianfang",
    "gn:country_code":"CN",
    "gn:dem":505,
    "gn:feature_class":"P",
    "gn:feature_code":"PPL",
    "gn:name":"Dengjia Nianfang",
    "gn:population":0,
    "gn:timezone":"Asia/Shanghai",
    "iso:country":"CN",
    "name:zho_x_preferred":[
        "\u9093\u5bb6\u78be\u623f"
    ],
    "wof:name":"Dengjia Nianfang",
    "wof:placetype":"locality"
},
  "geometry": {"coordinates":[108.428,28.0477],"type":"Point"}
}