{
  "type": "Feature",
  "properties": {
    "gn:admin1_code":"29.0",
    "gn:asciiname":"Majunbu",
    "gn:country_code":"CN",
    "gn:dem":1850,
    "gn:feature_class":"P",
    "gn:feature_code":"PPL",
    "gn:name":"Majunbu",
    "gn:population":0,
    "gn:timezone":"Asia/Shanghai",
    "iso:country":"CN",
    "name:zho_x_preferred":[
        "\u9a6c\u519b\u5821"
    ],
    "wof:name":"Majunbu",
    "wof:placetype":"locality"
},
  "geometry": {"coordinates":[103.753,25.1424],"type":"Point"}
}