{
  "type": "Feature",
  "properties": {
    "gn:admin1_code":"29.0",
    "gn:asciiname":"Xianiuchang",
    "gn:country_code":"CN",
    "gn:dem":560,
    "gn:feature_class":"P",
    "gn:feature_code":"PPL",
    "gn:name":"Xianiuchang",
    "gn:population":0,
    "gn:timezone":"Asia/Shanghai",
    "iso:country":"CN",
    "name:zho_x_preferred":[
        "\u4e0b\u725b\u5382"
    ],
    "wof:name":"Xianiuchang",
    "wof:placetype":"locality"
},
  "geometry": {"coordinates":[103.956,22.8794],"type":"Point"}
}