{
  "type": "Feature",
  "properties": {
    "gn:admin1_code":"33.0",
    "gn:asciiname":"Xiangshuixi",
    "gn:country_code":"CN",
    "gn:dem":822,
    "gn:feature_class":"P",
    "gn:feature_code":"PPL",
    "gn:name":"Xiangshuixi",
    "gn:population":0,
    "gn:timezone":"Asia/Shanghai",
    "iso:country":"CN",
    "name:zho_x_preferred":[
        "\u54cd\u6c34\u6eaa"
    ],
    "wof:name":"Xiangshuixi",
    "wof:placetype":"locality"
},
  "geometry": {"coordinates":[108.90237,28.77744],"type":"Point"}
}