{
  "type": "Feature",
  "properties": {
    "gn:admin1_code":"4.0",
    "gn:asciiname":"Hushancun",
    "gn:country_code":"CN",
    "gn:dem":17,
    "gn:feature_class":"P",
    "gn:feature_code":"PPL",
    "gn:name":"Hushancun",
    "gn:population":0,
    "gn:timezone":"Asia/Shanghai",
    "iso:country":"CN",
    "name:zho_x_preferred":[
        "\u864e\u5c71\u6751"
    ],
    "wof:name":"Hushancun",
    "wof:placetype":"locality"
},
  "geometry": {"coordinates":[118.41888,33.88287],"type":"Point"}
}