{
  "type": "Feature",
  "properties": {
    "gn:admin1_code":"8.0",
    "gn:asciiname":"Duanshitong",
    "gn:country_code":"CN",
    "gn:dem":228,
    "gn:feature_class":"P",
    "gn:feature_code":"PPL",
    "gn:name":"Duanshitong",
    "gn:population":0,
    "gn:timezone":"Asia/Shanghai",
    "iso:country":"CN",
    "name:zho_x_preferred":[
        "\u65ad\u77f3\u901a"
    ],
    "wof:name":"Duanshitong",
    "wof:placetype":"locality"
},
  "geometry": {"coordinates":[129.63071000000002,44.9313],"type":"Point"}
}