{
  "type": "Feature",
  "properties": {
    "gn:admin1_code":"32.0",
    "gn:asciiname":"Chenwan",
    "gn:country_code":"CN",
    "gn:dem":332,
    "gn:feature_class":"P",
    "gn:feature_code":"PPL",
    "gn:name":"Chenwan",
    "gn:population":0,
    "gn:timezone":"Asia/Shanghai",
    "iso:country":"CN",
    "name:zho_x_preferred":[
        "\u9648\u6e7e"
    ],
    "wof:name":"Chenwan",
    "wof:placetype":"locality"
},
  "geometry": {"coordinates":[104.76058,29.09755],"type":"Point"}
}