{
  "type": "Feature",
  "properties": {
    "gn:admin1_code":"07",
    "gn:asciiname":"Kenggongli",
    "gn:country_code":"CN",
    "gn:dem":358,
    "gn:feature_class":"P",
    "gn:feature_code":"PPL",
    "gn:name":"Kenggongli",
    "gn:population":0,
    "gn:timezone":"Asia/Shanghai",
    "iso:country":"CN",
    "name:zho_x_preferred":[
        "\u5751\u516c\u91cc"
    ],
    "wof:name":"Kenggongli",
    "wof:placetype":"locality"
},
  "geometry": {"coordinates":[115.9306,25.01588],"type":"Point"}
}