{
  "type": "Feature",
  "properties": {
    "gn:admin1_code":"2.0",
    "gn:asciiname":"Songkengwei",
    "gn:country_code":"CN",
    "gn:dem":377,
    "gn:feature_class":"P",
    "gn:feature_code":"PPL",
    "gn:name":"Songkengwei",
    "gn:population":0,
    "gn:timezone":"Asia/Shanghai",
    "iso:country":"CN",
    "name:zho_x_preferred":[
        "\u677e\u5751\u5729"
    ],
    "wof:name":"Songkengwei",
    "wof:placetype":"locality"
},
  "geometry": {"coordinates":[119.86617,28.33588],"type":"Point"}
}