{
  "type": "Feature",
  "properties": {
    "gn:admin1_code":"25",
    "gn:asciiname":"Dongguanzhuang",
    "gn:country_code":"CN",
    "gn:dem":6,
    "gn:feature_class":"P",
    "gn:feature_code":"PPL",
    "gn:name":"Dongguanzhuang",
    "gn:population":0,
    "gn:timezone":"Asia/Shanghai",
    "iso:country":"CN",
    "name:zho_x_preferred":[
        "\u4e1c\u5b98\u5e84"
    ],
    "wof:name":"Dongguanzhuang",
    "wof:placetype":"locality"
},
  "geometry": {"coordinates":[117.77200000000001,38.1409],"type":"Point"}
}