{
  "type": "Feature",
  "properties": {
    "gn:admin1_code":"5.0",
    "gn:asciiname":"Songjia Linzi",
    "gn:country_code":"CN",
    "gn:dem":296,
    "gn:feature_class":"P",
    "gn:feature_code":"PPL",
    "gn:name":"Songjia Linzi",
    "gn:population":0,
    "gn:timezone":"Asia/Shanghai",
    "iso:country":"CN",
    "name:zho_x_preferred":[
        "\u5b8b\u5bb6\u6797\u5b50"
    ],
    "wof:name":"Songjia Linzi",
    "wof:placetype":"locality"
},
  "geometry": {"coordinates":[125.27257,43.27644],"type":"Point"}
}