{
  "type": "Feature",
  "properties": {
    "gn:admin1_code":"4.0",
    "gn:asciiname":"Baitacun",
    "gn:country_code":"CN",
    "gn:dem":53,
    "gn:feature_class":"P",
    "gn:feature_code":"PPL",
    "gn:name":"Baitacun",
    "gn:population":0,
    "gn:timezone":"Asia/Shanghai",
    "iso:country":"CN",
    "name:zho_x_preferred":[
        "\u767d\u5854\u6751"
    ],
    "wof:name":"Baitacun",
    "wof:placetype":"locality"
},
  "geometry": {"coordinates":[117.52446999999999,34.17908],"type":"Point"}
}