{
  "type": "Feature",
  "properties": {
    "gn:admin1_code":"8.0",
    "gn:asciiname":"Xingbiancun",
    "gn:country_code":"CN",
    "gn:dem":61,
    "gn:feature_class":"P",
    "gn:feature_code":"PPL",
    "gn:name":"Xingbiancun",
    "gn:population":0,
    "gn:timezone":"Asia/Shanghai",
    "iso:country":"CN",
    "name:zho_x_preferred":[
        "\u5174\u8fb9\u6751"
    ],
    "wof:name":"Xingbiancun",
    "wof:placetype":"locality"
},
  "geometry": {"coordinates":[131.80597,47.62557],"type":"Point"}
}