{
  "type": "Feature",
  "properties": {
    "gn:admin1_code":"19.0",
    "gn:asciiname":"Shuangwobu",
    "gn:country_code":"CN",
    "gn:dem":19,
    "gn:feature_class":"P",
    "gn:feature_code":"PPL",
    "gn:name":"Shuangwobu",
    "gn:population":0,
    "gn:timezone":"Asia/Shanghai",
    "iso:country":"CN",
    "name:zho_x_preferred":[
        "\u53cc\u7a9d\u5821"
    ],
    "wof:name":"Shuangwobu",
    "wof:placetype":"locality"
},
  "geometry": {"coordinates":[122.69199999999999,41.6788],"type":"Point"}
}