{
  "type": "Feature",
  "properties": {
    "gn:admin1_code":"26",
    "gn:asciiname":"Kazi",
    "gn:country_code":"CN",
    "gn:dem":670,
    "gn:feature_class":"P",
    "gn:feature_code":"PPL",
    "gn:name":"Kazi",
    "gn:population":0,
    "gn:timezone":"Asia/Shanghai",
    "iso:country":"CN",
    "name:ben_x_preferred":[
        "\u0995\u09be\u099c\u09c0"
    ],
    "name:ceb_x_preferred":[
        "Kazi"
    ],
    "name:deu_x_preferred":[
        "Kazi"
    ],
    "name:ita_x_preferred":[
        "Kazi"
    ],
    "name:swe_x_preferred":[
        "Kazi"
    ],
    "wof:name":"Kazi",
    "wof:placetype":"locality"
},
  "geometry": {"coordinates":[110.00278,32.61917],"type":"Point"}
}