{
  "type": "Feature",
  "properties": {
    "gn:admin1_code":"12.0",
    "gn:asciiname":"Mahuangxi",
    "gn:country_code":"CN",
    "gn:dem":688,
    "gn:feature_class":"P",
    "gn:feature_code":"PPL",
    "gn:name":"Mahuangxi",
    "gn:population":0,
    "gn:timezone":"Asia/Shanghai",
    "iso:country":"CN",
    "name:zho_x_preferred":[
        "Mahuangxi"
    ],
    "name:zho_x_variant":[
        "\u9a6c\u9ec4\u6eaa"
    ],
    "wof:name":"Mahuangxi",
    "wof:placetype":"locality"
},
  "geometry": {"coordinates":[110.37855999999999,29.69645],"type":"Point"}
}