{
  "type": "Feature",
  "properties": {
    "gn:admin1_code":"11.0",
    "gn:asciiname":"Fenshui'ao",
    "gn:country_code":"CN",
    "gn:dem":543,
    "gn:feature_class":"P",
    "gn:feature_code":"PPL",
    "gn:name":"Fenshui\u2019ao",
    "gn:population":0,
    "gn:timezone":"Asia/Shanghai",
    "iso:country":"CN",
    "name:und_x_variant":[
        "Fenshui\u2019ao"
    ],
    "name:zho_x_preferred":[
        "\u5206\u6c34\u5773"
    ],
    "wof:name":"Fenshui'ao",
    "wof:placetype":"locality"
},
  "geometry": {"coordinates":[109.91013,27.0494],"type":"Point"}
}