{
  "type": "Feature",
  "properties": {
    "gn:admin1_code":"20.0",
    "gn:asciiname":"Houzhaogou",
    "gn:country_code":"CN",
    "gn:dem":1689,
    "gn:feature_class":"P",
    "gn:feature_code":"PPL",
    "gn:name":"Houzhaogou",
    "gn:population":0,
    "gn:timezone":"Asia/Shanghai",
    "iso:country":"CN",
    "name:und_x_variant":[
        "\u540e\u53ec\u6c9f"
    ],
    "wof:name":"Houzhaogou",
    "wof:placetype":"locality"
},
  "geometry": {"coordinates":[109.86471,41.12625],"type":"Point"}
}