{
  "type": "Feature",
  "properties": {
    "gn:admin1_code":"9",
    "gn:asciiname":"Jiudian",
    "gn:country_code":"CN",
    "gn:dem":121,
    "gn:feature_class":"P",
    "gn:feature_code":"PPLA4",
    "gn:name":"Jiudian",
    "gn:population":0,
    "gn:timezone":"Asia/Shanghai",
    "iso:country":"CN",
    "name:und_x_variant":[
        "\u9152\u5e97",
        "Jiudian Xiang",
        "\u9152\u5e97\u4e61"
    ],
    "wof:name":"Jiudian",
    "wof:placetype":"locality"
},
  "geometry": {"coordinates":[113.66103,33.25958],"type":"Point"}
}