{
  "type": "Feature",
  "properties": {
    "gn:admin1_code":"1.0",
    "gn:asciiname":"Mingxiaocun",
    "gn:country_code":"CN",
    "gn:dem":57,
    "gn:feature_class":"P",
    "gn:feature_code":"PPL",
    "gn:name":"Mingxiaocun",
    "gn:population":0,
    "gn:timezone":"Asia/Shanghai",
    "iso:country":"CN",
    "name:zho_x_preferred":[
        "\u660e\u8096\u6751"
    ],
    "wof:name":"Mingxiaocun",
    "wof:placetype":"locality"
},
  "geometry": {"coordinates":[117.69670000000001,32.21353],"type":"Point"}
}