{
  "type": "Feature",
  "properties": {
    "gn:admin1_code":"24.0",
    "gn:asciiname":"Yingziwa",
    "gn:country_code":"CN",
    "gn:dem":1392,
    "gn:feature_class":"P",
    "gn:feature_code":"PPL",
    "gn:name":"Yingziwa",
    "gn:population":0,
    "gn:timezone":"Asia/Shanghai",
    "iso:country":"CN",
    "name:zho_x_preferred":[
        "\u5e94\u5b50\u6d3c"
    ],
    "wof:name":"Yingziwa",
    "wof:placetype":"locality"
},
  "geometry": {"coordinates":[111.76461999999999,39.48065],"type":"Point"}
}