{
  "type": "Feature",
  "properties": {
    "gn:admin1_code":"32.0",
    "gn:asciiname":"Hualuping",
    "gn:country_code":"CN",
    "gn:dem":1380,
    "gn:feature_class":"P",
    "gn:feature_code":"PPL",
    "gn:name":"Hualuping",
    "gn:population":0,
    "gn:timezone":"Asia/Shanghai",
    "iso:country":"CN",
    "name:zho_x_preferred":[
        "\u5316\u7089\u576a"
    ],
    "wof:name":"Hualuping",
    "wof:placetype":"locality"
},
  "geometry": {"coordinates":[103.68000000000001,28.4834],"type":"Point"}
}