{
  "type": "Feature",
  "properties": {
    "gn:admin1_code":"29",
    "gn:asciiname":"Shanrenzhai",
    "gn:country_code":"CN",
    "gn:dem":1759,
    "gn:feature_class":"P",
    "gn:feature_code":"PPL",
    "gn:name":"Shanrenzhai",
    "gn:population":0,
    "gn:timezone":"Asia/Shanghai",
    "iso:country":"CN",
    "name:zho_x_preferred":[
        "\u5c71\u4eba\u5be8"
    ],
    "wof:name":"Shanrenzhai",
    "wof:placetype":"locality"
},
  "geometry": {"coordinates":[104.895,23.8072],"type":"Point"}
}