{
  "type": "Feature",
  "properties": {
    "gn:admin1_code":"15.0",
    "gn:asciiname":"Hujiacha",
    "gn:country_code":"CN",
    "gn:dem":2016,
    "gn:feature_class":"P",
    "gn:feature_code":"PPL",
    "gn:name":"Hujiacha",
    "gn:population":0,
    "gn:timezone":"Asia/Shanghai",
    "iso:country":"CN",
    "name:zho_x_preferred":[
        "\u864e\u5bb6\u5c94"
    ],
    "wof:name":"Hujiacha",
    "wof:placetype":"locality"
},
  "geometry": {"coordinates":[104.361,35.6867],"type":"Point"}
}