{
  "type": "Feature",
  "properties": {
    "gn:admin1_code":"5.0",
    "gn:asciiname":"Wojigoucun",
    "gn:country_code":"CN",
    "gn:dem":355,
    "gn:feature_class":"P",
    "gn:feature_code":"PPL",
    "gn:name":"Wojigoucun",
    "gn:population":0,
    "gn:timezone":"Asia/Shanghai",
    "iso:country":"CN",
    "name:zho_x_preferred":[
        "\u7a9d\u96c6\u6c9f\u6751"
    ],
    "wof:name":"Wojigoucun",
    "wof:placetype":"locality"
},
  "geometry": {"coordinates":[126.10836,42.41409],"type":"Point"}
}