{
  "type": "Feature",
  "properties": {
    "gn:admin1_code":"18",
    "gn:asciiname":"Yangmaoshan",
    "gn:country_code":"CN",
    "gn:dem":1334,
    "gn:feature_class":"P",
    "gn:feature_code":"PPL",
    "gn:name":"Yangmaoshan",
    "gn:population":0,
    "gn:timezone":"Asia/Shanghai",
    "iso:country":"CN",
    "name:zho_x_preferred":[
        "\u7f8a\u6bdb\u5c71"
    ],
    "wof:name":"Yangmaoshan",
    "wof:placetype":"locality"
},
  "geometry": {"coordinates":[106.253,26.4822],"type":"Point"}
}