{
  "type": "Feature",
  "properties": {
    "gn:admin1_code":"1.0",
    "gn:asciiname":"Zhaohoucun",
    "gn:country_code":"CN",
    "gn:dem":25,
    "gn:feature_class":"P",
    "gn:feature_code":"PPL",
    "gn:name":"Zhaohoucun",
    "gn:population":0,
    "gn:timezone":"Asia/Shanghai",
    "iso:country":"CN",
    "name:zho_x_preferred":[
        "\u8d75\u540e\u6751"
    ],
    "wof:name":"Zhaohoucun",
    "wof:placetype":"locality"
},
  "geometry": {"coordinates":[116.74454,32.83203],"type":"Point"}
}