{
  "type": "Feature",
  "properties": {
    "gn:admin1_code":"4.0",
    "gn:asciiname":"Beigang Sizu",
    "gn:country_code":"CN",
    "gn:dem":2,
    "gn:feature_class":"P",
    "gn:feature_code":"PPLF",
    "gn:name":"Beigang Sizu",
    "gn:population":0,
    "gn:timezone":"Asia/Shanghai",
    "iso:country":"CN",
    "name:zho_x_preferred":[
        "\u5317\u6e2f\u56db\u7ec4"
    ],
    "wof:name":"Beigang Sizu",
    "wof:placetype":"locality"
},
  "geometry": {"coordinates":[120.145,33.3608],"type":"Point"}
}