{
  "type": "Feature",
  "properties": {
    "gn:admin1_code":"25",
    "gn:asciiname":"Hanjiazhuma",
    "gn:country_code":"CN",
    "gn:dem":11,
    "gn:feature_class":"P",
    "gn:feature_code":"PPL",
    "gn:name":"Hanjiazhuma",
    "gn:population":0,
    "gn:timezone":"Asia/Shanghai",
    "iso:country":"CN",
    "name:zho_x_preferred":[
        "\u97e9\u5bb6\u6731\u9a6c"
    ],
    "wof:name":"Hanjiazhuma",
    "wof:placetype":"locality"
},
  "geometry": {"coordinates":[119.08499999999999,36.828],"type":"Point"}
}