{
  "type": "Feature",
  "properties": {
    "gn:admin1_code":"8.0",
    "gn:asciiname":"Chenliangtun",
    "gn:country_code":"CN",
    "gn:dem":220,
    "gn:feature_class":"P",
    "gn:feature_code":"PPL",
    "gn:name":"Chenliangtun",
    "gn:population":0,
    "gn:timezone":"Asia/Shanghai",
    "iso:country":"CN",
    "name:zho_x_preferred":[
        "\u9648\u826f\u5c6f"
    ],
    "wof:name":"Chenliangtun",
    "wof:placetype":"locality"
},
  "geometry": {"coordinates":[127.63207,46.73264],"type":"Point"}
}