{
  "type": "Feature",
  "properties": {
    "gn:admin1_code":"29.0",
    "gn:asciiname":"Huajiaoying",
    "gn:country_code":"CN",
    "gn:dem":2277,
    "gn:feature_class":"P",
    "gn:feature_code":"PPL",
    "gn:name":"Huajiaoying",
    "gn:population":0,
    "gn:timezone":"Asia/Shanghai",
    "iso:country":"CN",
    "name:zho_x_preferred":[
        "\u82b1\u6912\u8425"
    ],
    "wof:name":"Huajiaoying",
    "wof:placetype":"locality"
},
  "geometry": {"coordinates":[103.33799999999999,26.897],"type":"Point"}
}