{
  "type": "Feature",
  "properties": {
    "gn:admin1_code":"4.0",
    "gn:asciiname":"Zhuzhuang",
    "gn:country_code":"CN",
    "gn:dem":17,
    "gn:feature_class":"P",
    "gn:feature_code":"PPL",
    "gn:name":"Zhuzhuang",
    "gn:population":0,
    "gn:timezone":"Asia/Shanghai",
    "iso:country":"CN",
    "name:zho_x_preferred":[
        "\u73e0\u5e84"
    ],
    "wof:name":"Zhuzhuang",
    "wof:placetype":"locality"
},
  "geometry": {"coordinates":[119.15021000000002,31.77639000000001],"type":"Point"}
}