{
  "type": "Feature",
  "properties": {
    "gn:admin1_code":"3.0",
    "gn:asciiname":"Xuling Linchang",
    "gn:country_code":"CN",
    "gn:dem":100,
    "gn:feature_class":"P",
    "gn:feature_code":"PPLF",
    "gn:name":"Xuling Linchang",
    "gn:population":0,
    "gn:timezone":"Asia/Shanghai",
    "iso:country":"CN",
    "name:und_x_variant":[
        "\u8bb8\u5cad\u6797\u573a"
    ],
    "wof:name":"Xuling Linchang",
    "wof:placetype":"locality"
},
  "geometry": {"coordinates":[115.93232999999999,27.74914],"type":"Point"}
}