{
  "type": "Feature",
  "properties": {
    "gn:admin1_code":"26.0",
    "gn:asciiname":"Shelizhuangcun",
    "gn:country_code":"CN",
    "gn:dem":992,
    "gn:feature_class":"P",
    "gn:feature_code":"PPL",
    "gn:name":"Shelizhuangcun",
    "gn:population":0,
    "gn:timezone":"Asia/Shanghai",
    "iso:country":"CN",
    "name:zho_x_preferred":[
        "\u820d\u5229\u5e84\u6751"
    ],
    "wof:name":"Shelizhuangcun",
    "wof:placetype":"locality"
},
  "geometry": {"coordinates":[109.95338999999998,36.54013],"type":"Point"}
}