{
  "type": "Feature",
  "properties": {
    "gn:admin1_code":"5.0",
    "gn:asciiname":"Dahechuancun",
    "gn:country_code":"CN",
    "gn:dem":275,
    "gn:feature_class":"P",
    "gn:feature_code":"PPL",
    "gn:name":"Dahechuancun",
    "gn:population":0,
    "gn:timezone":"Asia/Shanghai",
    "iso:country":"CN",
    "name:zho_x_preferred":[
        "\u5927\u6cb3\u5ddd\u6751"
    ],
    "wof:name":"Dahechuancun",
    "wof:placetype":"locality"
},
  "geometry": {"coordinates":[126.15662,43.52499],"type":"Point"}
}