{
  "type": "Feature",
  "properties": {
    "gn:admin1_code":"26",
    "gn:asciiname":"Wanlicun",
    "gn:country_code":"CN",
    "gn:dem":651,
    "gn:feature_class":"P",
    "gn:feature_code":"PPL",
    "gn:name":"Wanlicun",
    "gn:population":0,
    "gn:timezone":"Asia/Shanghai",
    "iso:country":"CN",
    "name:zho_x_preferred":[
        "\u6e7e\u91cc\u6751"
    ],
    "wof:name":"Wanlicun",
    "wof:placetype":"locality"
},
  "geometry": {"coordinates":[109.29333,34.98504000000001],"type":"Point"}
}