{
  "type": "Feature",
  "properties": {
    "gn:admin1_code":"30.0",
    "gn:asciiname":"Huaxiecun",
    "gn:country_code":"CN",
    "gn:dem":7,
    "gn:feature_class":"P",
    "gn:feature_code":"PPL",
    "gn:name":"Huaxiecun",
    "gn:population":0,
    "gn:timezone":"Asia/Shanghai",
    "iso:country":"CN",
    "name:zho_x_preferred":[
        "\u534e\u8c22\u6751"
    ],
    "wof:name":"Huaxiecun",
    "wof:placetype":"locality"
},
  "geometry": {"coordinates":[116.30162,23.0263],"type":"Point"}
}