{
  "type": "Feature",
  "properties": {
    "gn:admin1_code":"7",
    "gn:asciiname":"Xicun",
    "gn:country_code":"CN",
    "gn:dem":397,
    "gn:feature_class":"P",
    "gn:feature_code":"PPL",
    "gn:name":"Xicun",
    "gn:population":0,
    "gn:timezone":"Asia/Shanghai",
    "iso:country":"CN",
    "wof:name":"Xicun",
    "wof:placetype":"locality"
},
  "geometry": {"coordinates":[118.14528,27.07583],"type":"Point"}
}