{
  "type": "Feature",
  "properties": {
    "gn:admin1_code":"07",
    "gn:asciiname":"Yazhujiao",
    "gn:country_code":"CN",
    "gn:dem":613,
    "gn:feature_class":"P",
    "gn:feature_code":"PPL",
    "gn:name":"Yazhujiao",
    "gn:population":0,
    "gn:timezone":"Asia/Shanghai",
    "iso:country":"CN",
    "name:zho_x_preferred":[
        "\u96c5\u7af9\u811a"
    ],
    "wof:name":"Yazhujiao",
    "wof:placetype":"locality"
},
  "geometry": {"coordinates":[116.80055,24.64531],"type":"Point"}
}