{
  "type": "Feature",
  "properties": {
    "gn:admin1_code":"1.0",
    "gn:asciiname":"Songyangcun",
    "gn:country_code":"CN",
    "gn:dem":42,
    "gn:feature_class":"P",
    "gn:feature_code":"PPL",
    "gn:name":"Songyangcun",
    "gn:population":0,
    "gn:timezone":"Asia/Shanghai",
    "iso:country":"CN",
    "name:und_x_variant":[
        "Songyang",
        "\u5b8b\u9633",
        "Xiyangpu",
        "Songyangcun"
    ],
    "name:zho_x_preferred":[
        "\u5b8b\u9633\u6751"
    ],
    "wof:name":"Songyangcun",
    "wof:placetype":"locality"
},
  "geometry": {"coordinates":[116.85028,29.75671],"type":"Point"}
}