{
  "type": "Feature",
  "properties": {
    "gn:admin1_code":"26.0",
    "gn:asciiname":"Bao'anwan",
    "gn:country_code":"CN",
    "gn:dem":1360,
    "gn:feature_class":"P",
    "gn:feature_code":"PPL",
    "gn:name":"Bao\u2019anwan",
    "gn:population":0,
    "gn:timezone":"Asia/Shanghai",
    "iso:country":"CN",
    "name:und_x_variant":[
        "Bao\u2019anwan"
    ],
    "name:zho_x_preferred":[
        "\u4fdd\u5b89\u6e7e"
    ],
    "wof:name":"Bao'anwan",
    "wof:placetype":"locality"
},
  "geometry": {"coordinates":[108.95457,36.47887],"type":"Point"}
}