{
  "type": "Feature",
  "properties": {
    "gn:admin1_code":"33.0",
    "gn:asciiname":"Yangbiao",
    "gn:country_code":"CN",
    "gn:dem":263,
    "gn:feature_class":"P",
    "gn:feature_code":"PPL",
    "gn:name":"Yangbiao",
    "gn:population":0,
    "gn:timezone":"Asia/Shanghai",
    "iso:country":"CN",
    "name:zho_x_preferred":[
        "\u9633\u5f6a"
    ],
    "wof:name":"Yangbiao",
    "wof:placetype":"locality"
},
  "geometry": {"coordinates":[106.36214,30.04513],"type":"Point"}
}