{
  "type": "Feature",
  "properties": {
    "gn:admin1_code":"25",
    "gn:asciiname":"Xirulai",
    "gn:country_code":"CN",
    "gn:dem":209,
    "gn:feature_class":"P",
    "gn:feature_code":"PPL",
    "gn:name":"Xirulai",
    "gn:population":0,
    "gn:timezone":"Asia/Shanghai",
    "iso:country":"CN",
    "name:zho_x_preferred":[
        "\u897f\u5112\u6765"
    ],
    "wof:name":"Xirulai",
    "wof:placetype":"locality"
},
  "geometry": {"coordinates":[117.88,35.7282],"type":"Point"}
}