{
  "type": "Feature",
  "properties": {
    "gn:admin1_code":"33.0",
    "gn:asciiname":"Shankeng",
    "gn:country_code":"CN",
    "gn:dem":98,
    "gn:feature_class":"P",
    "gn:feature_code":"PPLA4",
    "gn:name":"Shankeng",
    "gn:population":0,
    "gn:timezone":"Asia/Shanghai",
    "iso:country":"CN",
    "name:und_x_variant":[
        "Shankeng Xiang"
    ],
    "name:zho_x_preferred":[
        "\u5c71\u5751"
    ],
    "name:zho_x_variant":[
        "\u5c71\u5751\u4e61"
    ],
    "wof:name":"Shankeng",
    "wof:placetype":"locality"
},
  "geometry": {"coordinates":[120.51739000000001,28.34861],"type":"Point"}
}