{
  "type": "Feature",
  "properties": {
    "gn:admin1_code":"19",
    "gn:asciiname":"Xi'an",
    "gn:country_code":"CN",
    "gn:dem":5,
    "gn:feature_class":"P",
    "gn:feature_code":"PPLA4",
    "gn:name":"Xi\u2019an",
    "gn:population":0,
    "gn:timezone":"Asia/Shanghai",
    "iso:country":"CN",
    "name:und_x_variant":[
        "Xi\u2019an",
        "\u897f\u5b89",
        "Xi\u2019an Zhen",
        "\u897f\u5b89\u9547"
    ],
    "wof:name":"Xi'an",
    "wof:placetype":"locality"
},
  "geometry": {"coordinates":[122.23481,40.92265],"type":"Point"}
}