{
  "type": "Feature",
  "properties": {
    "gn:admin1_code":"2.0",
    "gn:asciiname":"Xujiadai",
    "gn:country_code":"CN",
    "gn:dem":8,
    "gn:feature_class":"P",
    "gn:feature_code":"PPL",
    "gn:name":"Xujiadai",
    "gn:population":0,
    "gn:timezone":"Asia/Shanghai",
    "iso:country":"CN",
    "name:und_x_variant":[
        "\u5f90\u5bb6\u57ed"
    ],
    "wof:name":"Xujiadai",
    "wof:placetype":"locality"
},
  "geometry": {"coordinates":[120.38736000000002,30.43737],"type":"Point"}
}