{
  "type": "Feature",
  "properties": {
    "gn:admin1_code":"01",
    "gn:asciiname":"Caijiahecun",
    "gn:country_code":"CN",
    "gn:dem":520,
    "gn:feature_class":"P",
    "gn:feature_code":"PPL",
    "gn:name":"Caijiahecun",
    "gn:population":0,
    "gn:timezone":"Asia/Shanghai",
    "iso:country":"CN",
    "name:und_x_variant":[
        "Ts\u2019ai-chia-ho",
        "Caijiahe",
        "Caijiahecun"
    ],
    "name:zho_x_preferred":[
        "\u8521\u5bb6\u6cb3\u6751"
    ],
    "wof:name":"Caijiahecun",
    "wof:placetype":"locality"
},
  "geometry": {"coordinates":[116.03088,31.0849],"type":"Point"}
}