{
  "type": "Feature",
  "properties": {
    "gn:admin1_code":"3.0",
    "gn:asciiname":"Xiaotian",
    "gn:country_code":"CN",
    "gn:dem":265,
    "gn:feature_class":"P",
    "gn:feature_code":"PPLA4",
    "gn:name":"Xiaotian",
    "gn:population":0,
    "gn:timezone":"Asia/Shanghai",
    "iso:country":"CN",
    "name:und_x_variant":[
        "Hsiao-t\u2019ien",
        "Xiaotian",
        "\u8096\u7530",
        "Xiaotian Zhen",
        "Xiaotian Xiang",
        "\u8096\u7530\u4e61",
        "\u8096\u7530\u93ae"
    ],
    "wof:name":"Xiaotian",
    "wof:placetype":"locality"
},
  "geometry": {"coordinates":[116.09251,27.04204],"type":"Point"}
}