{
  "type": "Feature",
  "properties": {
    "gn:admin1_code":"26.0",
    "gn:asciiname":"Wangshangcun",
    "gn:country_code":"CN",
    "gn:dem":545,
    "gn:feature_class":"P",
    "gn:feature_code":"PPL",
    "gn:name":"Wangshangcun",
    "gn:population":0,
    "gn:timezone":"Asia/Shanghai",
    "iso:country":"CN",
    "name:zho_x_preferred":[
        "\u738b\u5c1a\u6751"
    ],
    "wof:name":"Wangshangcun",
    "wof:placetype":"locality"
},
  "geometry": {"coordinates":[108.41658,34.44075],"type":"Point"}
}