{
  "type": "Feature",
  "properties": {
    "gn:admin1_code":"12.0",
    "gn:asciiname":"Wangjia Xinwu",
    "gn:country_code":"CN",
    "gn:dem":66,
    "gn:feature_class":"P",
    "gn:feature_code":"PPL",
    "gn:name":"Wangjia Xinwu",
    "gn:population":0,
    "gn:timezone":"Asia/Shanghai",
    "iso:country":"CN",
    "name:zho_x_preferred":[
        "Wangjia Xinwu"
    ],
    "name:zho_x_variant":[
        "\u738b\u5bb6\u65b0\u5c4b"
    ],
    "wof:name":"Wangjia Xinwu",
    "wof:placetype":"locality"
},
  "geometry": {"coordinates":[115.22557999999999,30.67212],"type":"Point"}
}