{
  "type": "Feature",
  "properties": {
    "gn:admin1_code":"9.0",
    "gn:asciiname":"Xichenzhai",
    "gn:country_code":"CN",
    "gn:dem":69,
    "gn:feature_class":"P",
    "gn:feature_code":"PPL",
    "gn:name":"Xichenzhai",
    "gn:population":0,
    "gn:timezone":"Asia/Shanghai",
    "iso:country":"CN",
    "name:zho_x_preferred":[
        "\u897f\u9648\u5be8"
    ],
    "wof:name":"Xichenzhai",
    "wof:placetype":"locality"
},
  "geometry": {"coordinates":[114.75586,34.79713],"type":"Point"}
}