{
  "type": "Feature",
  "properties": {
    "gn:admin1_code":"12.0",
    "gn:asciiname":"Zhuziqiao",
    "gn:country_code":"CN",
    "gn:dem":28,
    "gn:feature_class":"P",
    "gn:feature_code":"PPL",
    "gn:name":"Zhuziqiao",
    "gn:population":0,
    "gn:timezone":"Asia/Shanghai",
    "iso:country":"CN",
    "name:zho_x_preferred":[
        "\u7af9\u5b50\u6865"
    ],
    "wof:name":"Zhuziqiao",
    "wof:placetype":"locality"
},
  "geometry": {"coordinates":[112.86924999999999,29.87072],"type":"Point"}
}