{
  "type": "Feature",
  "properties": {
    "gn:admin1_code":"18",
    "gn:asciiname":"Dalu",
    "gn:country_code":"CN",
    "gn:dem":1084,
    "gn:feature_class":"P",
    "gn:feature_code":"PPL",
    "gn:name":"Dalu",
    "gn:population":0,
    "gn:timezone":"Asia/Shanghai",
    "iso:country":"CN",
    "name:ceb_x_preferred":[
        "Dalu"
    ],
    "name:deu_x_preferred":[
        "Dalu"
    ],
    "name:zho_x_preferred":[
        "\u6253\u9c81"
    ],
    "wof:name":"Dalu",
    "wof:placetype":"locality"
},
  "geometry": {"coordinates":[106.449,25.6953],"type":"Point"}
}