{
  "type": "Feature",
  "properties": {
    "gn:admin1_code":"32.0",
    "gn:asciiname":"Youbianshan",
    "gn:country_code":"CN",
    "gn:dem":743,
    "gn:feature_class":"P",
    "gn:feature_code":"PPL",
    "gn:name":"Youbianshan",
    "gn:population":0,
    "gn:timezone":"Asia/Shanghai",
    "iso:country":"CN",
    "name:zho_x_preferred":[
        "\u6cb9\u904d\u5c71"
    ],
    "wof:name":"Youbianshan",
    "wof:placetype":"locality"
},
  "geometry": {"coordinates":[104.36698,29.58703],"type":"Point"}
}