{
  "type": "Feature",
  "properties": {
    "gn:admin1_code":"11.0",
    "gn:asciiname":"Yukou",
    "gn:country_code":"CN",
    "gn:dem":31,
    "gn:feature_class":"P",
    "gn:feature_code":"PPL",
    "gn:name":"Yukou",
    "gn:population":0,
    "gn:timezone":"Asia/Shanghai",
    "iso:country":"CN",
    "name:zho_x_preferred":[
        "\u9c7c\u53e3"
    ],
    "name:zho_x_variant":[
        "\u592a\u5b50\u79a6\u5bc7"
    ],
    "wof:name":"Yukou",
    "wof:placetype":"locality"
},
  "geometry": {"coordinates":[112.40781,28.96502000000001],"type":"Point"}
}