{
  "type": "Feature",
  "properties": {
    "gn:admin1_code":"29.0",
    "gn:asciiname":"Laohezhai",
    "gn:country_code":"CN",
    "gn:dem":1566,
    "gn:feature_class":"P",
    "gn:feature_code":"PPL",
    "gn:name":"Laohezhai",
    "gn:population":0,
    "gn:timezone":"Asia/Shanghai",
    "iso:country":"CN",
    "name:zho_x_preferred":[
        "\u8001\u8d3a\u5be8"
    ],
    "wof:name":"Laohezhai",
    "wof:placetype":"locality"
},
  "geometry": {"coordinates":[100.86199999999999,22.6747],"type":"Point"}
}