{
  "type": "Feature",
  "properties": {
    "gn:admin1_code":"9.0",
    "gn:asciiname":"Caolizhuang",
    "gn:country_code":"CN",
    "gn:dem":62,
    "gn:feature_class":"P",
    "gn:feature_code":"PPL",
    "gn:name":"Caolizhuang",
    "gn:population":0,
    "gn:timezone":"Asia/Shanghai",
    "iso:country":"CN",
    "name:zho_x_preferred":[
        "\u66f9\u674e\u5e84"
    ],
    "wof:name":"Caolizhuang",
    "wof:placetype":"locality"
},
  "geometry": {"coordinates":[114.73241000000002,35.70415999999999],"type":"Point"}
}