{
  "type": "Feature",
  "properties": {
    "gn:admin1_code":"14.0",
    "gn:asciiname":"Relie",
    "gn:country_code":"CN",
    "gn:dem":3959,
    "gn:feature_class":"P",
    "gn:feature_code":"PPL",
    "gn:name":"Relie",
    "gn:population":0,
    "gn:timezone":"Asia/Urumqi",
    "iso:country":"CN",
    "name:zho_x_preferred":[
        "\u70ed\u70c8"
    ],
    "wof:name":"Relie",
    "wof:placetype":"locality"
},
  "geometry": {"coordinates":[94.53421,29.97241],"type":"Point"}
}