{
  "type": "Feature",
  "properties": {
    "gn:admin1_code":"24.0",
    "gn:asciiname":"Goujiacun",
    "gn:country_code":"CN",
    "gn:dem":1429,
    "gn:feature_class":"P",
    "gn:feature_code":"PPL",
    "gn:name":"Goujiacun",
    "gn:population":0,
    "gn:timezone":"Asia/Shanghai",
    "iso:country":"CN",
    "name:zho_x_preferred":[
        "\u7f11\u5bb6\u6751"
    ],
    "wof:name":"Goujiacun",
    "wof:placetype":"locality"
},
  "geometry": {"coordinates":[112.57132,40.014],"type":"Point"}
}