{
  "type": "Feature",
  "properties": {
    "gn:admin1_code":"1.0",
    "gn:asciiname":"Nianpancun",
    "gn:country_code":"CN",
    "gn:dem":50,
    "gn:feature_class":"P",
    "gn:feature_code":"PPL",
    "gn:name":"Nianpancun",
    "gn:population":0,
    "gn:timezone":"Asia/Shanghai",
    "iso:country":"CN",
    "name:zho_x_preferred":[
        "\u78be\u76d8\u6751"
    ],
    "wof:name":"Nianpancun",
    "wof:placetype":"locality"
},
  "geometry": {"coordinates":[116.37408000000001,31.65167000000001],"type":"Point"}
}