{
  "type": "Feature",
  "properties": {
    "gn:admin1_code":"4.0",
    "gn:asciiname":"Xiaowangxu",
    "gn:country_code":"CN",
    "gn:dem":3,
    "gn:feature_class":"P",
    "gn:feature_code":"PPL",
    "gn:name":"Xiaowangxu",
    "gn:population":0,
    "gn:timezone":"Asia/Shanghai",
    "iso:country":"CN",
    "name:zho_x_preferred":[
        "Xiaowangxu"
    ],
    "name:zho_x_variant":[
        "\u5c0f\u6c6a\u5729"
    ],
    "wof:name":"Xiaowangxu",
    "wof:placetype":"locality"
},
  "geometry": {"coordinates":[119.51251000000001,34.29693],"type":"Point"}
}