{
  "type": "Feature",
  "properties": {
    "gn:admin1_code":"7.0",
    "gn:asciiname":"Kengtang",
    "gn:country_code":"CN",
    "gn:dem":226,
    "gn:feature_class":"P",
    "gn:feature_code":"PPL",
    "gn:name":"Kengtang",
    "gn:population":0,
    "gn:timezone":"Asia/Shanghai",
    "iso:country":"CN",
    "name:und_x_variant":[
        "\u5751\u5858"
    ],
    "name:zho_x_preferred":[
        "\u5751\u5858"
    ],
    "wof:name":"Kengtang",
    "wof:placetype":"locality"
},
  "geometry": {"coordinates":[117.27867000000001,26.64041],"type":"Point"}
}