{
  "type": "Feature",
  "properties": {
    "gn:admin1_code":"9.0",
    "gn:asciiname":"Guopaiwa",
    "gn:country_code":"CN",
    "gn:dem":544,
    "gn:feature_class":"P",
    "gn:feature_code":"PPL",
    "gn:name":"Guopaiwa",
    "gn:population":0,
    "gn:timezone":"Asia/Shanghai",
    "iso:country":"CN",
    "name:zho_x_preferred":[
        "\u90ed\u724c\u6d3c"
    ],
    "wof:name":"Guopaiwa",
    "wof:placetype":"locality"
},
  "geometry": {"coordinates":[111.58212,34.4055],"type":"Point"}
}