{
  "type": "Feature",
  "properties": {
    "gn:admin1_code":"14.0",
    "gn:asciiname":"Qusadui",
    "gn:country_code":"CN",
    "gn:dem":4726,
    "gn:feature_class":"P",
    "gn:feature_code":"PPL",
    "gn:name":"Qusadui",
    "gn:population":0,
    "gn:timezone":"Asia/Urumqi",
    "iso:country":"CN",
    "name:zho_x_preferred":[
        "\u66f2\u8428\u5806"
    ],
    "wof:name":"Qusadui",
    "wof:placetype":"locality"
},
  "geometry": {"coordinates":[87.12779999999999,31.5166],"type":"Point"}
}