{
  "type": "Feature",
  "properties": {
    "gn:admin1_code":"8.0",
    "gn:asciiname":"Longtou Wudui",
    "gn:country_code":"CN",
    "gn:dem":110,
    "gn:feature_class":"P",
    "gn:feature_code":"PPLF",
    "gn:name":"Longtou Wudui",
    "gn:population":0,
    "gn:timezone":"Asia/Shanghai",
    "iso:country":"CN",
    "name:zho_x_preferred":[
        "\u9f99\u5934\u4e94\u961f"
    ],
    "wof:name":"Longtou Wudui",
    "wof:placetype":"locality"
},
  "geometry": {"coordinates":[131.99206999999998,46.05417],"type":"Point"}
}