{
  "type": "Feature",
  "properties": {
    "gn:admin1_code":"30",
    "gn:asciiname":"Dongwei",
    "gn:country_code":"CN",
    "gn:dem":20,
    "gn:feature_class":"P",
    "gn:feature_code":"PPL",
    "gn:name":"Dongwei",
    "gn:population":0,
    "gn:timezone":"Asia/Urumqi",
    "iso:country":"CN",
    "name:zho_x_preferred":[
        "\u578c\u5c3e"
    ],
    "wof:name":"Dongwei",
    "wof:placetype":"locality"
},
  "geometry": {"coordinates":[110.87053,21.73669],"type":"Point"}
}