{
  "type": "Feature",
  "properties": {
    "gn:admin1_code":"29.0",
    "gn:asciiname":"Nalianqing",
    "gn:country_code":"CN",
    "gn:dem":1229,
    "gn:feature_class":"P",
    "gn:feature_code":"PPL",
    "gn:name":"Nalianqing",
    "gn:population":0,
    "gn:timezone":"Asia/Shanghai",
    "iso:country":"CN",
    "name:zho_x_preferred":[
        "\u90a3\u7ec3\u7b90"
    ],
    "wof:name":"Nalianqing",
    "wof:placetype":"locality"
},
  "geometry": {"coordinates":[100.92400000000001,22.9339],"type":"Point"}
}