{
  "type": "Feature",
  "properties": {
    "gn:admin1_code":"33.0",
    "gn:asciiname":"Yan'er",
    "gn:country_code":"CN",
    "gn:dem":416,
    "gn:feature_class":"P",
    "gn:feature_code":"PPL",
    "gn:name":"Yan\u2019er",
    "gn:population":0,
    "gn:timezone":"Asia/Shanghai",
    "iso:country":"CN",
    "name:und_x_variant":[
        "Yan\u2019er"
    ],
    "name:zho_x_preferred":[
        "\u71d5\u513f"
    ],
    "wof:name":"Yan'er",
    "wof:placetype":"locality"
},
  "geometry": {"coordinates":[105.65380999999999,29.35871],"type":"Point"}
}