{
  "type": "Feature",
  "properties": {
    "gn:admin1_code":"19.0",
    "gn:asciiname":"Xiayou Fanggoucun",
    "gn:country_code":"CN",
    "gn:dem":209,
    "gn:feature_class":"P",
    "gn:feature_code":"PPL",
    "gn:name":"Xiayou Fanggoucun",
    "gn:population":0,
    "gn:timezone":"Asia/Shanghai",
    "iso:country":"CN",
    "name:und_x_variant":[
        "Xiayoufanggoucun",
        "Xiayou Fanggoucun"
    ],
    "name:zho_x_preferred":[
        "\u4e0b\u6cb9\u574a\u6c9f\u6751"
    ],
    "wof:name":"Xiayou Fanggoucun",
    "wof:placetype":"locality"
},
  "geometry": {"coordinates":[120.73506,41.86596],"type":"Point"}
}