{
  "type": "Feature",
  "properties": {
    "gn:admin1_code":"16.0",
    "gn:asciiname":"Lanhe",
    "gn:country_code":"CN",
    "gn:dem":136,
    "gn:feature_class":"P",
    "gn:feature_code":"PPL",
    "gn:name":"Lanhe",
    "gn:population":0,
    "gn:timezone":"Asia/Shanghai",
    "iso:country":"CN",
    "name:zho_x_preferred":[
        "\u5170\u4f55"
    ],
    "wof:name":"Lanhe",
    "wof:placetype":"locality"
},
  "geometry": {"coordinates":[108.29000000000001,23.3638],"type":"Point"}
}