{
  "type": "Feature",
  "properties": {
    "gn:admin1_code":"6.0",
    "gn:asciiname":"Muqin",
    "gn:country_code":"CN",
    "gn:dem":4337,
    "gn:feature_class":"P",
    "gn:feature_code":"PPL",
    "gn:name":"Muqin",
    "gn:population":0,
    "gn:timezone":"Asia/Urumqi",
    "iso:country":"CN",
    "name:zho_x_preferred":[
        "\u6bcd\u94a6"
    ],
    "wof:name":"Muqin",
    "wof:placetype":"locality"
},
  "geometry": {"coordinates":[96.32738000000001,33.55515],"type":"Point"}
}