{
  "type": "Feature",
  "properties": {
    "gn:admin1_code":"9.0",
    "gn:asciiname":"Peijia Laozhuang",
    "gn:country_code":"CN",
    "gn:dem":704,
    "gn:feature_class":"P",
    "gn:feature_code":"PPL",
    "gn:name":"Peijia Laozhuang",
    "gn:population":0,
    "gn:timezone":"Asia/Shanghai",
    "iso:country":"CN",
    "name:zho_x_preferred":[
        "\u88f4\u5bb6\u8001\u5e84"
    ],
    "wof:name":"Peijia Laozhuang",
    "wof:placetype":"locality"
},
  "geometry": {"coordinates":[112.04226,33.55735],"type":"Point"}
}