{
  "type": "Feature",
  "properties": {
    "gn:admin1_code":"11",
    "gn:asciiname":"Jianshanchong",
    "gn:country_code":"CN",
    "gn:dem":206,
    "gn:feature_class":"P",
    "gn:feature_code":"PPL",
    "gn:name":"Jianshanchong",
    "gn:population":0,
    "gn:timezone":"Asia/Shanghai",
    "iso:country":"CN",
    "name:zho_x_preferred":[
        "\u6da7\u5c71\u51b2"
    ],
    "wof:name":"Jianshanchong",
    "wof:placetype":"locality"
},
  "geometry": {"coordinates":[111.74506,26.9651],"type":"Point"}
}