{
  "type": "Feature",
  "properties": {
    "gn:admin1_code":"15.0",
    "gn:asciiname":"Xinbuzi",
    "gn:country_code":"CN",
    "gn:dem":1781,
    "gn:feature_class":"P",
    "gn:feature_code":"PPL",
    "gn:name":"Xinbuzi",
    "gn:population":0,
    "gn:timezone":"Asia/Shanghai",
    "iso:country":"CN",
    "name:und_x_variant":[
        "\u65b0\u5821\u5b50"
    ],
    "wof:name":"Xinbuzi",
    "wof:placetype":"locality"
},
  "geometry": {"coordinates":[105.2094,35.92326],"type":"Point"}
}