{
  "type": "Feature",
  "properties": {
    "gn:admin1_code":"32.0",
    "gn:asciiname":"Cujin",
    "gn:country_code":"CN",
    "gn:dem":429,
    "gn:feature_class":"P",
    "gn:feature_code":"PPL",
    "gn:name":"Cujin",
    "gn:population":0,
    "gn:timezone":"Asia/Shanghai",
    "iso:country":"CN",
    "name:zho_x_preferred":[
        "\u4fc3\u8fdb"
    ],
    "wof:name":"Cujin",
    "wof:placetype":"locality"
},
  "geometry": {"coordinates":[104.23967,29.75853],"type":"Point"}
}