{
  "type": "Feature",
  "properties": {
    "gn:admin1_code":"7",
    "gn:asciiname":"Baimapu",
    "gn:country_code":"CN",
    "gn:dem":70,
    "gn:feature_class":"P",
    "gn:feature_code":"PPL",
    "gn:name":"Baimapu",
    "gn:population":0,
    "gn:timezone":"Asia/Shanghai",
    "iso:country":"CN",
    "name:und_x_variant":[
        "Baimabu"
    ],
    "name:zho_x_preferred":[
        "\u767d\u9a6c\u94fa"
    ],
    "wof:name":"Baimapu",
    "wof:placetype":"locality"
},
  "geometry": {"coordinates":[117.29722,23.94556],"type":"Point"}
}