{
  "type": "Feature",
  "properties": {
    "gn:admin1_code":"4.0",
    "gn:asciiname":"Dabo",
    "gn:country_code":"CN",
    "gn:dem":13,
    "gn:feature_class":"P",
    "gn:feature_code":"PPL",
    "gn:name":"Dabo",
    "gn:population":0,
    "gn:timezone":"Asia/Shanghai",
    "iso:country":"CN",
    "name:fra_x_preferred":[
        "Dabo"
    ],
    "name:zho_x_preferred":[
        "\u5927\u6cca"
    ],
    "wof:name":"Dabo",
    "wof:placetype":"locality"
},
  "geometry": {"coordinates":[119.59054999999999,32.02606],"type":"Point"}
}