{
  "type": "Feature",
  "properties": {
    "gn:admin1_code":"9",
    "gn:asciiname":"Xiaoqiqiu",
    "gn:country_code":"CN",
    "gn:dem":58,
    "gn:feature_class":"P",
    "gn:feature_code":"PPL",
    "gn:name":"Xiaoqiqiu",
    "gn:population":0,
    "gn:timezone":"Asia/Shanghai",
    "iso:country":"CN",
    "name:zho_x_preferred":[
        "\u8096\u9f50\u4e18"
    ],
    "wof:name":"Xiaoqiqiu",
    "wof:placetype":"locality"
},
  "geometry": {"coordinates":[114.92700000000001,35.44300000000001],"type":"Point"}
}