{
  "type": "Feature",
  "properties": {
    "gn:admin1_code":"2.0",
    "gn:asciiname":"Jiudongshan",
    "gn:country_code":"CN",
    "gn:dem":356,
    "gn:feature_class":"P",
    "gn:feature_code":"PPL",
    "gn:name":"Jiudongshan",
    "gn:population":0,
    "gn:timezone":"Asia/Shanghai",
    "iso:country":"CN",
    "name:und_x_variant":[
        "\u4e5d\u4e1c\u5c71"
    ],
    "wof:name":"Jiudongshan",
    "wof:placetype":"locality"
},
  "geometry": {"coordinates":[119.70613,30.48897],"type":"Point"}
}