{
  "type": "Feature",
  "properties": {
    "gn:admin1_code":"11.0",
    "gn:asciiname":"Caikou",
    "gn:country_code":"CN",
    "gn:dem":231,
    "gn:feature_class":"P",
    "gn:feature_code":"PPL",
    "gn:name":"Caikou",
    "gn:population":0,
    "gn:timezone":"Asia/Shanghai",
    "iso:country":"CN",
    "name:zho_x_preferred":[
        "\u624d\u53e3"
    ],
    "wof:name":"Caikou",
    "wof:placetype":"locality"
},
  "geometry": {"coordinates":[112.87812,25.07903],"type":"Point"}
}