{
  "type": "Feature",
  "properties": {
    "gn:admin1_code":"11.0",
    "gn:asciiname":"Shisanwan",
    "gn:country_code":"CN",
    "gn:dem":33,
    "gn:feature_class":"P",
    "gn:feature_code":"PPL",
    "gn:name":"Shisanwan",
    "gn:population":0,
    "gn:timezone":"Asia/Shanghai",
    "iso:country":"CN",
    "name:zho_x_preferred":[
        "\u5341\u4e09\u6e7e"
    ],
    "wof:name":"Shisanwan",
    "wof:placetype":"locality"
},
  "geometry": {"coordinates":[112.23343,29.29979],"type":"Point"}
}