{
  "type": "Feature",
  "properties": {
    "gn:admin1_code":"5.0",
    "gn:asciiname":"Xinkailingtun",
    "gn:country_code":"CN",
    "gn:dem":366,
    "gn:feature_class":"P",
    "gn:feature_code":"PPL",
    "gn:name":"Xinkailingtun",
    "gn:population":0,
    "gn:timezone":"Asia/Shanghai",
    "iso:country":"CN",
    "name:zho_x_preferred":[
        "\u65b0\u5f00\u5cad\u5c6f"
    ],
    "wof:name":"Xinkailingtun",
    "wof:placetype":"locality"
},
  "geometry": {"coordinates":[125.82872999999999,42.98585],"type":"Point"}
}