{
  "type": "Feature",
  "properties": {
    "gn:admin1_code":"3",
    "gn:asciiname":"Yuelong",
    "gn:country_code":"CN",
    "gn:dem":180,
    "gn:feature_class":"P",
    "gn:feature_code":"PPL",
    "gn:name":"Yuelong",
    "gn:population":0,
    "gn:timezone":"Asia/Shanghai",
    "iso:country":"CN",
    "name:zho_x_preferred":[
        "\u8dc3\u9f99"
    ],
    "wof:name":"Yuelong",
    "wof:placetype":"locality"
},
  "geometry": {"coordinates":[114.843,26.2875],"type":"Point"}
}