{
  "type": "Feature",
  "properties": {
    "gn:admin1_code":"7",
    "gn:asciiname":"Qidu",
    "gn:country_code":"CN",
    "gn:dem":644,
    "gn:feature_class":"P",
    "gn:feature_code":"PPL",
    "gn:name":"Qidu",
    "gn:population":0,
    "gn:timezone":"Asia/Shanghai",
    "iso:country":"CN",
    "name:zho_x_preferred":[
        "\u78dc\u90fd"
    ],
    "wof:name":"Qidu",
    "wof:placetype":"locality"
},
  "geometry": {"coordinates":[117.89278,24.93167],"type":"Point"}
}