{
  "type": "Feature",
  "properties": {
    "gn:admin1_code":"29.0",
    "gn:asciiname":"Guanxi",
    "gn:country_code":"CN",
    "gn:dem":2371,
    "gn:feature_class":"P",
    "gn:feature_code":"PPL",
    "gn:name":"Guanxi",
    "gn:population":0,
    "gn:timezone":"Asia/Shanghai",
    "iso:country":"CN",
    "name:zho_x_preferred":[
        "\u5173\u897f"
    ],
    "wof:name":"Guanxi",
    "wof:placetype":"locality"
},
  "geometry": {"coordinates":[100.51000000000001,26.6196],"type":"Point"}
}