{
  "type": "Feature",
  "properties": {
    "gn:admin1_code":"10",
    "gn:asciiname":"Lahaigou",
    "gn:country_code":"CN",
    "gn:dem":454,
    "gn:feature_class":"P",
    "gn:feature_code":"PPL",
    "gn:name":"Lahaigou",
    "gn:population":0,
    "gn:timezone":"Asia/Shanghai",
    "iso:country":"CN",
    "name:und_x_variant":[
        "La-hai-kou",
        "Lahaigou"
    ],
    "name:zho_x_preferred":[
        "\u62c9\u6d77\u6c9f"
    ],
    "wof:name":"Lahaigou",
    "wof:placetype":"locality"
},
  "geometry": {"coordinates":[117.26514,40.84334000000001],"type":"Point"}
}