{
  "type": "Feature",
  "properties": {
    "gn:admin1_code":"24",
    "gn:asciiname":"Haojiagou",
    "gn:country_code":"CN",
    "gn:dem":1274,
    "gn:feature_class":"P",
    "gn:feature_code":"PPL",
    "gn:name":"Haojiagou",
    "gn:population":0,
    "gn:timezone":"Asia/Shanghai",
    "iso:country":"CN",
    "name:und_x_variant":[
        "Hao-chia-kou",
        "Ho-chia-kou",
        "Haojiagou"
    ],
    "name:zho_x_preferred":[
        "\u90dd\u5bb6\u6c9f"
    ],
    "wof:name":"Haojiagou",
    "wof:placetype":"locality"
},
  "geometry": {"coordinates":[111.18303,38.5829],"type":"Point"}
}