{
  "type": "Feature",
  "properties": {
    "gn:admin1_code":"33.0",
    "gn:asciiname":"Yongping",
    "gn:country_code":"CN",
    "gn:dem":997,
    "gn:feature_class":"P",
    "gn:feature_code":"PPL",
    "gn:name":"Yongping",
    "gn:population":0,
    "gn:timezone":"Asia/Shanghai",
    "iso:country":"CN",
    "name:deu_x_preferred":[
        "Yongping"
    ],
    "name:vie_x_preferred":[
        "V\u0129nh B\u00ecnh"
    ],
    "name:zho_x_preferred":[
        "\u7528\u576a"
    ],
    "wof:name":"Yongping",
    "wof:placetype":"locality"
},
  "geometry": {"coordinates":[108.59545,30.5247],"type":"Point"}
}