{
  "type": "Feature",
  "properties": {
    "gn:admin1_code":"18",
    "gn:asciiname":"Qiujiazhuang",
    "gn:country_code":"CN",
    "gn:dem":1462,
    "gn:feature_class":"P",
    "gn:feature_code":"PPL",
    "gn:name":"Qiujiazhuang",
    "gn:population":0,
    "gn:timezone":"Asia/Shanghai",
    "iso:country":"CN",
    "name:zho_x_preferred":[
        "\u4e18\u5bb6\u5e84"
    ],
    "wof:name":"Qiujiazhuang",
    "wof:placetype":"locality"
},
  "geometry": {"coordinates":[107.017,26.4156],"type":"Point"}
}