{
  "type": "Feature",
  "properties": {
    "gn:admin1_code":"2.0",
    "gn:asciiname":"Dongyu",
    "gn:country_code":"CN",
    "gn:dem":747,
    "gn:feature_class":"P",
    "gn:feature_code":"PPL",
    "gn:name":"Dongyu",
    "gn:population":0,
    "gn:timezone":"Asia/Shanghai",
    "iso:country":"CN",
    "name:zho_x_preferred":[
        "\u4e1c\u4fde"
    ],
    "wof:name":"Dongyu",
    "wof:placetype":"locality"
},
  "geometry": {"coordinates":[120.32725000000001,28.71652000000001],"type":"Point"}
}