{
  "type": "Feature",
  "properties": {
    "gn:admin1_code":"1.0",
    "gn:asciiname":"Suyangcun",
    "gn:country_code":"CN",
    "gn:dem":28,
    "gn:feature_class":"P",
    "gn:feature_code":"PPL",
    "gn:name":"Suyangcun",
    "gn:population":0,
    "gn:timezone":"Asia/Shanghai",
    "iso:country":"CN",
    "name:zho_x_preferred":[
        "\u82cf\u6768\u6751"
    ],
    "wof:name":"Suyangcun",
    "wof:placetype":"locality"
},
  "geometry": {"coordinates":[116.84023999999999,32.76037],"type":"Point"}
}