{
  "type": "Feature",
  "properties": {
    "gn:admin1_code":"02",
    "gn:asciiname":"Hengkeng",
    "gn:country_code":"CN",
    "gn:dem":654,
    "gn:feature_class":"P",
    "gn:feature_code":"PPL",
    "gn:name":"Hengkeng",
    "gn:population":0,
    "gn:timezone":"Asia/Shanghai",
    "iso:country":"CN",
    "name:und_x_variant":[
        "Laibian",
        "Hengkeng"
    ],
    "name:zho_x_preferred":[
        "Heng-k\u2019eng-ts\u2019un"
    ],
    "wof:name":"Hengkeng",
    "wof:placetype":"locality"
},
  "geometry": {"coordinates":[120.03958,27.55894],"type":"Point"}
}