{
  "type": "Feature",
  "properties": {
    "gn:admin1_code":"8.0",
    "gn:asciiname":"Guchengzi",
    "gn:country_code":"CN",
    "gn:dem":136,
    "gn:feature_class":"P",
    "gn:feature_code":"PPL",
    "gn:name":"Guchengzi",
    "gn:population":0,
    "gn:timezone":"Asia/Shanghai",
    "iso:country":"CN",
    "name:zho_x_preferred":[
        "\u53e4\u57ce\u5b50"
    ],
    "wof:name":"Guchengzi",
    "wof:placetype":"locality"
},
  "geometry": {"coordinates":[124.84548999999998,46.33147],"type":"Point"}
}