{
  "type": "Feature",
  "properties": {
    "gn:admin1_code":"24",
    "gn:asciiname":"Nanshangzhai",
    "gn:country_code":"CN",
    "gn:dem":1157,
    "gn:feature_class":"P",
    "gn:feature_code":"PPL",
    "gn:name":"Nanshangzhai",
    "gn:population":0,
    "gn:timezone":"Asia/Shanghai",
    "iso:country":"CN",
    "name:und_x_variant":[
        "Nan-shang-chai",
        "Nanshangzhai",
        "\u5357\u4e0a\u5be8"
    ],
    "wof:name":"Nanshangzhai",
    "wof:placetype":"locality"
},
  "geometry": {"coordinates":[113.24626000000001,39.40508],"type":"Point"}
}