{
  "type": "Feature",
  "properties": {
    "gn:admin1_code":"11.0",
    "gn:asciiname":"Qianjiachong",
    "gn:country_code":"CN",
    "gn:dem":196,
    "gn:feature_class":"P",
    "gn:feature_code":"PPL",
    "gn:name":"Qianjiachong",
    "gn:population":0,
    "gn:timezone":"Asia/Shanghai",
    "iso:country":"CN",
    "name:zho_x_preferred":[
        "Qianjiachong"
    ],
    "name:zho_x_variant":[
        "\u94b1\u5bb6\u51b2"
    ],
    "wof:name":"Qianjiachong",
    "wof:placetype":"locality"
},
  "geometry": {"coordinates":[111.20678999999998,29.01208],"type":"Point"}
}