{
  "type": "Feature",
  "properties": {
    "gn:admin1_code":"30.0",
    "gn:asciiname":"Dengwujiao",
    "gn:country_code":"CN",
    "gn:dem":12,
    "gn:feature_class":"P",
    "gn:feature_code":"PPL",
    "gn:name":"Dengwujiao",
    "gn:population":0,
    "gn:timezone":"Asia/Shanghai",
    "iso:country":"CN",
    "name:zho_x_preferred":[
        "\u9093\u5c4b\u89d2"
    ],
    "wof:name":"Dengwujiao",
    "wof:placetype":"locality"
},
  "geometry": {"coordinates":[114.21578999999998,23.11179],"type":"Point"}
}