{
  "type": "Feature",
  "properties": {
    "gn:admin1_code":"32.0",
    "gn:asciiname":"Xiaoquan",
    "gn:country_code":"CN",
    "gn:dem":541,
    "gn:feature_class":"P",
    "gn:feature_code":"PPL",
    "gn:name":"Xiaoquan",
    "gn:population":0,
    "gn:timezone":"Asia/Shanghai",
    "iso:country":"CN",
    "name:und_x_variant":[
        "Hsiao-ch\u2019\u00fcan-chen",
        "Xiaoquanzhen",
        "Xiaoquan"
    ],
    "name:zho_x_preferred":[
        "\u5b5d\u6cc9"
    ],
    "wof:name":"Xiaoquan",
    "wof:placetype":"locality"
},
  "geometry": {"coordinates":[104.27786999999999,31.2505],"type":"Point"}
}