{
  "type": "Feature",
  "properties": {
    "gn:admin1_code":"18",
    "gn:asciiname":"Dangxiang",
    "gn:country_code":"CN",
    "gn:dem":324,
    "gn:feature_class":"P",
    "gn:feature_code":"PPL",
    "gn:name":"Dangxiang",
    "gn:population":0,
    "gn:timezone":"Asia/Shanghai",
    "iso:country":"CN",
    "name:zho_x_preferred":[
        "\u515a\u76f8"
    ],
    "wof:name":"Dangxiang",
    "wof:placetype":"locality"
},
  "geometry": {"coordinates":[106.60599999999999,25.198],"type":"Point"}
}