{
  "type": "Feature",
  "properties": {
    "gn:admin1_code":"4.0",
    "gn:asciiname":"Jiaba Yizu",
    "gn:country_code":"CN",
    "gn:dem":3,
    "gn:feature_class":"P",
    "gn:feature_code":"PPL",
    "gn:name":"Jiaba Yizu",
    "gn:population":0,
    "gn:timezone":"Asia/Shanghai",
    "iso:country":"CN",
    "name:zho_x_preferred":[
        "\u8d3e\u575d\u4e00\u7ec4"
    ],
    "wof:name":"Jiaba Yizu",
    "wof:placetype":"locality"
},
  "geometry": {"coordinates":[120.54985000000001,32.79019],"type":"Point"}
}