{
  "type": "Feature",
  "properties": {
    "gn:admin1_code":"11.0",
    "gn:asciiname":"Dayangtian",
    "gn:country_code":"CN",
    "gn:dem":333,
    "gn:feature_class":"P",
    "gn:feature_code":"PPL",
    "gn:name":"Dayangtian",
    "gn:population":0,
    "gn:timezone":"Asia/Shanghai",
    "iso:country":"CN",
    "name:zho_x_preferred":[
        "\u5927\u79e7\u7530"
    ],
    "wof:name":"Dayangtian",
    "wof:placetype":"locality"
},
  "geometry": {"coordinates":[111.09739999999999,26.50334],"type":"Point"}
}