{
  "type": "Feature",
  "properties": {
    "gn:admin1_code":"4.0",
    "gn:asciiname":"Jixu",
    "gn:country_code":"CN",
    "gn:dem":8,
    "gn:feature_class":"P",
    "gn:feature_code":"PPL",
    "gn:name":"Jixu",
    "gn:population":0,
    "gn:timezone":"Asia/Shanghai",
    "iso:country":"CN",
    "name:zho_x_preferred":[
        "Jixu"
    ],
    "name:zho_x_variant":[
        "\u5d47\u5729"
    ],
    "wof:name":"Jixu",
    "wof:placetype":"locality"
},
  "geometry": {"coordinates":[119.37706,33.83087],"type":"Point"}
}