{
  "type": "Feature",
  "properties": {
    "gn:admin1_code":"14.0",
    "gn:asciiname":"Katuolacuocun",
    "gn:country_code":"CN",
    "gn:dem":4612,
    "gn:feature_class":"P",
    "gn:feature_code":"PPL",
    "gn:name":"Katuolacuocun",
    "gn:population":0,
    "gn:timezone":"Asia/Urumqi",
    "iso:country":"CN",
    "name:zho_x_preferred":[
        "\u5494\u6258\u62c9\u63aa\u6751"
    ],
    "wof:name":"Katuolacuocun",
    "wof:placetype":"locality"
},
  "geometry": {"coordinates":[91.85269,31.69007],"type":"Point"}
}