{
  "type": "Feature",
  "properties": {
    "gn:admin1_code":"23.0",
    "gn:asciiname":"Zhenjiang",
    "gn:country_code":"CN",
    "gn:dem":6,
    "gn:feature_class":"P",
    "gn:feature_code":"PPL",
    "gn:name":"Zhenjiang",
    "gn:population":0,
    "gn:timezone":"Asia/Shanghai",
    "iso:country":"CN",
    "name:und_x_variant":[
        "\u771f\u6c5f"
    ],
    "wof:name":"Zhenjiang",
    "wof:placetype":"locality"
},
  "geometry": {"coordinates":[121.36465,31.25978],"type":"Point"}
}