{
  "type": "Feature",
  "properties": {
    "gn:admin1_code":"18",
    "gn:asciiname":"Fanizhai",
    "gn:country_code":"CN",
    "gn:dem":1439,
    "gn:feature_class":"P",
    "gn:feature_code":"PPL",
    "gn:name":"Fanizhai",
    "gn:population":0,
    "gn:timezone":"Asia/Shanghai",
    "iso:country":"CN",
    "name:zho_x_preferred":[
        "\u6cd5\u6ce5\u5be8"
    ],
    "wof:name":"Fanizhai",
    "wof:placetype":"locality"
},
  "geometry": {"coordinates":[105.131,25.4202],"type":"Point"}
}