{
  "type": "Feature",
  "properties": {
    "gn:admin1_code":"20",
    "gn:asciiname":"Guyuan",
    "gn:country_code":"CN",
    "gn:dem":450,
    "gn:feature_class":"P",
    "gn:feature_code":"PPLA4",
    "gn:name":"Guyuan",
    "gn:population":0,
    "gn:timezone":"Asia/Shanghai",
    "iso:country":"CN",
    "name:und_x_variant":[
        "Ku-y\u00fcan",
        "Guyuan",
        "Guyuan Zhen"
    ],
    "name:zho_x_preferred":[
        "\u53e4\u6e90"
    ],
    "name:zho_x_variant":[
        "\u53e4\u6e90\u9547"
    ],
    "wof:name":"Guyuan",
    "wof:placetype":"locality"
},
  "geometry": {"coordinates":[124.31153999999999,50.93697],"type":"Point"}
}