{
  "type": "Feature",
  "properties": {
    "gn:admin1_code":"25",
    "gn:asciiname":"Chenghouma",
    "gn:country_code":"CN",
    "gn:dem":22,
    "gn:feature_class":"P",
    "gn:feature_code":"PPL",
    "gn:name":"Chenghouma",
    "gn:population":0,
    "gn:timezone":"Asia/Shanghai",
    "iso:country":"CN",
    "name:zho_x_preferred":[
        "\u57ce\u540e\u9a6c"
    ],
    "wof:name":"Chenghouma",
    "wof:placetype":"locality"
},
  "geometry": {"coordinates":[116.57299999999999,37.3684],"type":"Point"}
}