{
  "type": "Feature",
  "properties": {
    "gn:admin1_code":"32.0",
    "gn:asciiname":"Yuhemiaozu",
    "gn:country_code":"CN",
    "gn:dem":884,
    "gn:feature_class":"P",
    "gn:feature_code":"PPL",
    "gn:name":"Yuhemiaozu",
    "gn:population":0,
    "gn:timezone":"Asia/Shanghai",
    "iso:country":"CN",
    "name:zho_x_preferred":[
        "\u7389\u548c\u82d7\u65cf"
    ],
    "wof:name":"Yuhemiaozu",
    "wof:placetype":"locality"
},
  "geometry": {"coordinates":[104.81511,28.21649],"type":"Point"}
}