{
  "type": "Feature",
  "properties": {
    "gn:admin1_code":"8.0",
    "gn:asciiname":"Xixiaotun",
    "gn:country_code":"CN",
    "gn:dem":275,
    "gn:feature_class":"P",
    "gn:feature_code":"PPL",
    "gn:name":"Xixiaotun",
    "gn:population":0,
    "gn:timezone":"Asia/Shanghai",
    "iso:country":"CN",
    "name:zho_x_preferred":[
        "\u897f\u5c0f\u5c6f"
    ],
    "wof:name":"Xixiaotun",
    "wof:placetype":"locality"
},
  "geometry": {"coordinates":[127.58642999999999,44.43937],"type":"Point"}
}