{
  "type": "Feature",
  "properties": {
    "gn:admin1_code":"12.0",
    "gn:asciiname":"Dingjiashan",
    "gn:country_code":"CN",
    "gn:dem":354,
    "gn:feature_class":"P",
    "gn:feature_code":"PPL",
    "gn:name":"Dingjiashan",
    "gn:population":0,
    "gn:timezone":"Asia/Shanghai",
    "iso:country":"CN",
    "name:zho_x_preferred":[
        "Dingjiashan"
    ],
    "name:zho_x_variant":[
        "\u4e01\u5bb6\u5c71"
    ],
    "wof:name":"Dingjiashan",
    "wof:placetype":"locality"
},
  "geometry": {"coordinates":[111.50787,30.00709],"type":"Point"}
}