{
  "type": "Feature",
  "properties": {
    "gn:admin1_code":"3.0",
    "gn:asciiname":"Shiqiaokeng",
    "gn:country_code":"CN",
    "gn:dem":439,
    "gn:feature_class":"P",
    "gn:feature_code":"PPL",
    "gn:name":"Shiqiaokeng",
    "gn:population":0,
    "gn:timezone":"Asia/Shanghai",
    "iso:country":"CN",
    "name:und_x_variant":[
        "\u77f3\u6865\u5751"
    ],
    "wof:name":"Shiqiaokeng",
    "wof:placetype":"locality"
},
  "geometry": {"coordinates":[115.16273,26.42229],"type":"Point"}
}