{
  "type": "Feature",
  "properties": {
    "gn:admin1_code":"33.0",
    "gn:asciiname":"Boxing",
    "gn:country_code":"CN",
    "gn:dem":798,
    "gn:feature_class":"P",
    "gn:feature_code":"PPL",
    "gn:name":"Boxing",
    "gn:population":0,
    "gn:timezone":"Asia/Shanghai",
    "iso:country":"CN",
    "name:zho_x_preferred":[
        "\u52c3\u5174"
    ],
    "wof:name":"Boxing",
    "wof:placetype":"locality"
},
  "geometry": {"coordinates":[108.80915,29.37448],"type":"Point"}
}