{
  "type": "Feature",
  "properties": {
    "gn:admin1_code":"18",
    "gn:asciiname":"Banpoying",
    "gn:country_code":"CN",
    "gn:dem":1745,
    "gn:feature_class":"P",
    "gn:feature_code":"PPL",
    "gn:name":"Banpoying",
    "gn:population":0,
    "gn:timezone":"Asia/Shanghai",
    "iso:country":"CN",
    "name:zho_x_preferred":[
        "\u534a\u5761\u8425"
    ],
    "wof:name":"Banpoying",
    "wof:placetype":"locality"
},
  "geometry": {"coordinates":[104.64400000000001,27.1301],"type":"Point"}
}