{
  "type": "Feature",
  "properties": {
    "gn:admin1_code":"13.0",
    "gn:asciiname":"Burjay",
    "gn:country_code":"CN",
    "gn:dem":870,
    "gn:feature_class":"P",
    "gn:feature_code":"PPL",
    "gn:name":"Burjay",
    "gn:population":0,
    "gn:timezone":"Asia/Urumqi",
    "iso:country":"CN",
    "name:uig_x_preferred":[
        "\u0628\u06c7\u0631\u062c\u0627\u064a"
    ],
    "name:uig_x_variant":[
        "\u0411\u0443\u0440\u0497\u0430\u0439"
    ],
    "name:und_x_variant":[
        "Bu\u2019erjian"
    ],
    "name:zho_x_preferred":[
        "\u5e03\u5c14\u78b1"
    ],
    "wof:name":"Burjay",
    "wof:placetype":"locality"
},
  "geometry": {"coordinates":[87.98472,42.88778],"type":"Point"}
}