{
  "type": "Feature",
  "properties": {
    "gn:admin1_code":"7",
    "gn:asciiname":"Hengkeng",
    "gn:country_code":"CN",
    "gn:dem":17,
    "gn:feature_class":"P",
    "gn:feature_code":"PPL",
    "gn:name":"Hengkeng",
    "gn:population":0,
    "gn:timezone":"Asia/Shanghai",
    "iso:country":"CN",
    "name:zho_x_preferred":[
        "\u73e9\u5751"
    ],
    "wof:name":"Hengkeng",
    "wof:placetype":"locality"
},
  "geometry": {"coordinates":[117.51694000000001,24.56667],"type":"Point"}
}