{
  "type": "Feature",
  "properties": {
    "gn:admin1_code":"3.0",
    "gn:asciiname":"Longgang",
    "gn:country_code":"CN",
    "gn:dem":97,
    "gn:feature_class":"P",
    "gn:feature_code":"PPL",
    "gn:name":"Longgang",
    "gn:population":0,
    "gn:timezone":"Asia/Shanghai",
    "iso:country":"CN",
    "name:ceb_x_preferred":[
        "Longgang"
    ],
    "name:deu_x_preferred":[
        "Longgang"
    ],
    "name:fra_x_preferred":[
        "Longgang"
    ],
    "name:kor_x_preferred":[
        "\ub8fd\uac15\uad6c"
    ],
    "name:mlg_x_preferred":[
        "Longgang"
    ],
    "name:nor_x_preferred":[
        "Longgang"
    ],
    "name:pol_x_preferred":[
        "Longgang"
    ],
    "name:zho_x_preferred":[
        "\u9f99\u6e2f"
    ],
    "wof:name":"Longgang",
    "wof:placetype":"locality"
},
  "geometry": {"coordinates":[117.163,28.6105],"type":"Point"}
}