{
  "type": "Feature",
  "properties": {
    "gn:admin1_code":"26.0",
    "gn:asciiname":"Qinlinggoucun",
    "gn:country_code":"CN",
    "gn:dem":1335,
    "gn:feature_class":"P",
    "gn:feature_code":"PPL",
    "gn:name":"Qinlinggoucun",
    "gn:population":0,
    "gn:timezone":"Asia/Shanghai",
    "iso:country":"CN",
    "name:zho_x_preferred":[
        "\u79e6\u5cad\u6c9f\u6751"
    ],
    "wof:name":"Qinlinggoucun",
    "wof:placetype":"locality"
},
  "geometry": {"coordinates":[109.56403,33.88393],"type":"Point"}
}