{
  "type": "Feature",
  "properties": {
    "gn:admin1_code":"5.0",
    "gn:asciiname":"Taipingqiaocun",
    "gn:country_code":"CN",
    "gn:dem":301,
    "gn:feature_class":"P",
    "gn:feature_code":"PPL",
    "gn:name":"Taipingqiaocun",
    "gn:population":0,
    "gn:timezone":"Asia/Shanghai",
    "iso:country":"CN",
    "name:zho_x_preferred":[
        "\u592a\u5e73\u6865\u6751"
    ],
    "wof:name":"Taipingqiaocun",
    "wof:placetype":"locality"
},
  "geometry": {"coordinates":[125.54510000000001,43.15778],"type":"Point"}
}