{
  "type": "Feature",
  "properties": {
    "gn:admin1_code":"14.0",
    "gn:asciiname":"Bapu",
    "gn:country_code":"CN",
    "gn:dem":3941,
    "gn:feature_class":"P",
    "gn:feature_code":"PPL",
    "gn:name":"Bapu",
    "gn:population":0,
    "gn:timezone":"Asia/Urumqi",
    "iso:country":"CN",
    "name:deu_x_preferred":[
        "Bapu"
    ],
    "name:fra_x_preferred":[
        "Bapu"
    ],
    "name:hin_x_preferred":[
        "\u092c\u093e\u092a\u0942"
    ],
    "name:pol_x_preferred":[
        "Bapu"
    ],
    "name:zho_x_preferred":[
        "\u5df4\u6d66"
    ],
    "wof:name":"Bapu",
    "wof:placetype":"locality"
},
  "geometry": {"coordinates":[94.35234,30.094],"type":"Point"}
}