{
  "type": "Feature",
  "properties": {
    "gn:admin1_code":"3.0",
    "gn:asciiname":"Liubaiyuan",
    "gn:country_code":"CN",
    "gn:dem":296,
    "gn:feature_class":"P",
    "gn:feature_code":"PPL",
    "gn:name":"Liubaiyuan",
    "gn:population":0,
    "gn:timezone":"Asia/Shanghai",
    "iso:country":"CN",
    "name:und_x_variant":[
        "\u5218\u67cf\u6e90"
    ],
    "wof:name":"Liubaiyuan",
    "wof:placetype":"locality"
},
  "geometry": {"coordinates":[115.83461,26.74281],"type":"Point"}
}