{
  "type": "Feature",
  "properties": {
    "gn:admin1_code":"7",
    "gn:asciiname":"Pingnan Niuchang",
    "gn:country_code":"CN",
    "gn:dem":1241,
    "gn:feature_class":"P",
    "gn:feature_code":"PPLF",
    "gn:name":"Pingnan Niuchang",
    "gn:population":0,
    "gn:timezone":"Asia/Shanghai",
    "iso:country":"CN",
    "name:und_x_variant":[
        "\u5c4f\u5357\u725b\u573a"
    ],
    "wof:name":"Pingnan Niuchang",
    "wof:placetype":"locality"
},
  "geometry": {"coordinates":[118.70166999999999,26.89333],"type":"Point"}
}