{
  "type": "Feature",
  "properties": {
    "gn:admin1_code":"8.0",
    "gn:asciiname":"Dongpucun",
    "gn:country_code":"CN",
    "gn:dem":184,
    "gn:feature_class":"P",
    "gn:feature_code":"PPL",
    "gn:name":"Dongpucun",
    "gn:population":0,
    "gn:timezone":"Asia/Shanghai",
    "iso:country":"CN",
    "name:zho_x_preferred":[
        "\u4e1c\u6734\u6751"
    ],
    "wof:name":"Dongpucun",
    "wof:placetype":"locality"
},
  "geometry": {"coordinates":[126.54658999999999,45.50234],"type":"Point"}
}