{
  "type": "Feature",
  "properties": {
    "gn:admin1_code":"26",
    "gn:asciiname":"Zuitou",
    "gn:country_code":"CN",
    "gn:dem":372,
    "gn:feature_class":"P",
    "gn:feature_code":"PPL",
    "gn:name":"Zuitou",
    "gn:population":0,
    "gn:timezone":"Asia/Shanghai",
    "iso:country":"CN",
    "name:zho_x_preferred":[
        "\u5480\u5934\u9547"
    ],
    "wof:name":"Zuitou",
    "wof:placetype":"locality"
},
  "geometry": {"coordinates":[109.16427,34.47914],"type":"Point"}
}