{
  "type": "Feature",
  "properties": {
    "gn:admin1_code":"16.0",
    "gn:asciiname":"Beishi",
    "gn:country_code":"CN",
    "gn:dem":94,
    "gn:feature_class":"P",
    "gn:feature_code":"PPL",
    "gn:name":"Beishi",
    "gn:population":0,
    "gn:timezone":"Asia/Shanghai",
    "iso:country":"CN",
    "name:zho_x_preferred":[
        "\u9642\u77f3"
    ],
    "wof:name":"Beishi",
    "wof:placetype":"locality"
},
  "geometry": {"coordinates":[110.274,22.6855],"type":"Point"}
}