{
  "type": "Feature",
  "properties": {
    "gn:admin1_code":"15.0",
    "gn:asciiname":"Gongjiawan",
    "gn:country_code":"CN",
    "gn:dem":1883,
    "gn:feature_class":"P",
    "gn:feature_code":"PPL",
    "gn:name":"Gongjiawan",
    "gn:population":0,
    "gn:timezone":"Asia/Shanghai",
    "iso:country":"CN",
    "name:zho_x_preferred":[
        "\u9f9a\u5bb6\u6e7e"
    ],
    "wof:name":"Gongjiawan",
    "wof:placetype":"locality"
},
  "geometry": {"coordinates":[103.79300000000001,36.496],"type":"Point"}
}