{
  "type": "Feature",
  "properties": {
    "gn:admin1_code":"9.0",
    "gn:asciiname":"Zhugang",
    "gn:country_code":"CN",
    "gn:dem":170,
    "gn:feature_class":"P",
    "gn:feature_code":"PPL",
    "gn:name":"Zhugang",
    "gn:population":0,
    "gn:timezone":"Asia/Shanghai",
    "iso:country":"CN",
    "name:und_x_variant":[
        "\u6731\u5c97",
        "Zhugang"
    ],
    "wof:name":"Zhugang",
    "wof:placetype":"locality"
},
  "geometry": {"coordinates":[112.38043999999999,33.03145],"type":"Point"}
}