{
  "type": "Feature",
  "properties": {
    "gn:admin1_code":"5.0",
    "gn:asciiname":"Songlin",
    "gn:country_code":"CN",
    "gn:dem":105,
    "gn:feature_class":"P",
    "gn:feature_code":"PPL",
    "gn:name":"Songlin",
    "gn:population":0,
    "gn:timezone":"Asia/Shanghai",
    "iso:country":"CN",
    "name:und_x_variant":[
        "\u677e\u6797"
    ],
    "wof:name":"Songlin",
    "wof:placetype":"locality"
},
  "geometry": {"coordinates":[129.79041999999998,43.03554000000001],"type":"Point"}
}