{
  "type": "Feature",
  "properties": {
    "gn:admin1_code":"01",
    "gn:asciiname":"Sanqiao",
    "gn:cc2":"CN",
    "gn:country_code":"CN",
    "gn:dem":17,
    "gn:feature_class":"P",
    "gn:feature_code":"PPL",
    "gn:name":"Sanqiao",
    "gn:population":0,
    "gn:timezone":"Asia/Shanghai",
    "iso:country":"CN",
    "name:deu_x_preferred":[
        "Sanqiao"
    ],
    "name:und_x_variant":[
        "San-ch\u2019iao-chen",
        "Sankiao",
        "San-ch\u2019iao",
        "San-ch\u2019iao-p\u2019u",
        "Sanqiao"
    ],
    "wof:name":"Sanqiao",
    "wof:placetype":"locality"
},
  "geometry": {"coordinates":[116.70806,30.60417],"type":"Point"}
}