{
  "type": "Feature",
  "properties": {
    "gn:admin1_code":"29.0",
    "gn:asciiname":"Laolongtang",
    "gn:country_code":"CN",
    "gn:dem":2103,
    "gn:feature_class":"P",
    "gn:feature_code":"PPL",
    "gn:name":"Laolongtang",
    "gn:population":0,
    "gn:timezone":"Asia/Shanghai",
    "iso:country":"CN",
    "name:zho_x_preferred":[
        "\u8001\u9f99\u5858"
    ],
    "wof:name":"Laolongtang",
    "wof:placetype":"locality"
},
  "geometry": {"coordinates":[98.3479,24.715],"type":"Point"}
}