{
  "type": "Feature",
  "properties": {
    "gn:admin1_code":"26.0",
    "gn:asciiname":"Dongshizui",
    "gn:country_code":"CN",
    "gn:dem":1036,
    "gn:feature_class":"P",
    "gn:feature_code":"PPL",
    "gn:name":"Dongshizui",
    "gn:population":0,
    "gn:timezone":"Asia/Shanghai",
    "iso:country":"CN",
    "name:zho_x_preferred":[
        "\u4e1c\u77f3\u5480"
    ],
    "wof:name":"Dongshizui",
    "wof:placetype":"locality"
},
  "geometry": {"coordinates":[110.09090999999999,34.19442],"type":"Point"}
}