{
  "type": "Feature",
  "properties": {
    "gn:admin1_code":"2.0",
    "gn:asciiname":"Zhengqiaotou",
    "gn:country_code":"CN",
    "gn:dem":5,
    "gn:feature_class":"P",
    "gn:feature_code":"PPL",
    "gn:name":"Zhengqiaotou",
    "gn:population":0,
    "gn:timezone":"Asia/Shanghai",
    "iso:country":"CN",
    "name:und_x_variant":[
        "\u90d1\u6865\u5934",
        "Zhengjiaqiao"
    ],
    "wof:name":"Zhengqiaotou",
    "wof:placetype":"locality"
},
  "geometry": {"coordinates":[120.24602,30.75578],"type":"Point"}
}