{
  "type": "Feature",
  "properties": {
    "gn:admin1_code":"29.0",
    "gn:asciiname":"Zelaoshang",
    "gn:country_code":"CN",
    "gn:dem":2395,
    "gn:feature_class":"P",
    "gn:feature_code":"PPL",
    "gn:name":"Zelaoshang",
    "gn:population":0,
    "gn:timezone":"Asia/Shanghai",
    "iso:country":"CN",
    "name:und_x_variant":[
        "\u5219\u8001\u4e0a"
    ],
    "wof:name":"Zelaoshang",
    "wof:placetype":"locality"
},
  "geometry": {"coordinates":[102.86284000000001,26.02261],"type":"Point"}
}