{
  "type": "Feature",
  "properties": {
    "gn:admin1_code":"30",
    "gn:asciiname":"Meilang",
    "gn:country_code":"CN",
    "gn:dem":409,
    "gn:feature_class":"P",
    "gn:feature_code":"PPL",
    "gn:name":"Meilang",
    "gn:population":0,
    "gn:timezone":"Asia/Shanghai",
    "iso:country":"CN",
    "wof:name":"Meilang",
    "wof:placetype":"locality"
},
  "geometry": {"coordinates":[115.5133,23.75604],"type":"Point"}
}