{
  "type": "Feature",
  "properties": {
    "gn:admin1_code":"32.0",
    "gn:asciiname":"Chunshui",
    "gn:country_code":"CN",
    "gn:dem":454,
    "gn:feature_class":"P",
    "gn:feature_code":"PPL",
    "gn:name":"Chunshui",
    "gn:population":0,
    "gn:timezone":"Asia/Shanghai",
    "iso:country":"CN",
    "name:zho_x_preferred":[
        "\u6625\u6c34"
    ],
    "wof:name":"Chunshui",
    "wof:placetype":"locality"
},
  "geometry": {"coordinates":[105.36199999999999,31.2425],"type":"Point"}
}