{
  "type": "Feature",
  "properties": {
    "gn:admin1_code":"10",
    "gn:asciiname":"Xingtaiyong",
    "gn:country_code":"CN",
    "gn:dem":1367,
    "gn:feature_class":"P",
    "gn:feature_code":"PPL",
    "gn:name":"Xingtaiyong",
    "gn:population":0,
    "gn:timezone":"Asia/Shanghai",
    "iso:country":"CN",
    "name:zho_x_preferred":[
        "\u5174\u592a\u6c38"
    ],
    "wof:name":"Xingtaiyong",
    "wof:placetype":"locality"
},
  "geometry": {"coordinates":[115.82073,41.82699],"type":"Point"}
}