{
  "type": "Feature",
  "properties": {
    "gn:admin1_code":"9",
    "gn:asciiname":"Chenwafang",
    "gn:country_code":"CN",
    "gn:dem":58,
    "gn:feature_class":"P",
    "gn:feature_code":"PPL",
    "gn:name":"Chenwafang",
    "gn:population":0,
    "gn:timezone":"Asia/Shanghai",
    "iso:country":"CN",
    "name:zho_x_preferred":[
        "\u9648\u74e6\u623f"
    ],
    "wof:name":"Chenwafang",
    "wof:placetype":"locality"
},
  "geometry": {"coordinates":[115.36199999999999,34.4493],"type":"Point"}
}