{
  "type": "Feature",
  "properties": {
    "gn:admin1_code":"30.0",
    "gn:asciiname":"Hewu",
    "gn:country_code":"CN",
    "gn:dem":206,
    "gn:feature_class":"P",
    "gn:feature_code":"PPL",
    "gn:name":"Hewu",
    "gn:population":0,
    "gn:timezone":"Asia/Shanghai",
    "iso:country":"CN",
    "name:zho_x_preferred":[
        "\u8d3a\u5c4b"
    ],
    "wof:name":"Hewu",
    "wof:placetype":"locality"
},
  "geometry": {"coordinates":[114.93243,23.55119],"type":"Point"}
}