{
  "type": "Feature",
  "properties": {
    "gn:admin1_code":"12.0",
    "gn:asciiname":"Liushike",
    "gn:country_code":"CN",
    "gn:dem":80,
    "gn:feature_class":"P",
    "gn:feature_code":"PPL",
    "gn:name":"Liushike",
    "gn:population":0,
    "gn:timezone":"Asia/Shanghai",
    "iso:country":"CN",
    "name:zho_x_preferred":[
        "\u5218\u4e16\u79d1"
    ],
    "wof:name":"Liushike",
    "wof:placetype":"locality"
},
  "geometry": {"coordinates":[114.62967,31.32737],"type":"Point"}
}