{
  "type": "Feature",
  "properties": {
    "gn:admin1_code":"29.0",
    "gn:asciiname":"Apengcun",
    "gn:country_code":"CN",
    "gn:dem":1949,
    "gn:feature_class":"P",
    "gn:feature_code":"PPL",
    "gn:name":"Apengcun",
    "gn:population":0,
    "gn:timezone":"Asia/Shanghai",
    "iso:country":"CN",
    "name:zho_x_preferred":[
        "\u963f\u68da\u6751"
    ],
    "wof:name":"Apengcun",
    "wof:placetype":"locality"
},
  "geometry": {"coordinates":[103.34099999999999,25.0299],"type":"Point"}
}