{
  "type": "Feature",
  "properties": {
    "gn:admin1_code":"11.0",
    "gn:asciiname":"Shuichi",
    "gn:country_code":"CN",
    "gn:dem":563,
    "gn:feature_class":"P",
    "gn:feature_code":"PPL",
    "gn:name":"Shuichi",
    "gn:population":0,
    "gn:timezone":"Asia/Shanghai",
    "iso:country":"CN",
    "name:zho_x_preferred":[
        "\u6c34\u6c60"
    ],
    "wof:name":"Shuichi",
    "wof:placetype":"locality"
},
  "geometry": {"coordinates":[110.11056000000001,29.20314],"type":"Point"}
}