{
  "type": "Feature",
  "properties": {
    "gn:admin1_code":"18.0",
    "gn:asciiname":"Goukanzhai",
    "gn:country_code":"CN",
    "gn:dem":1302,
    "gn:feature_class":"P",
    "gn:feature_code":"PPL",
    "gn:name":"Goukanzhai",
    "gn:population":0,
    "gn:timezone":"Asia/Shanghai",
    "iso:country":"CN",
    "name:zho_x_preferred":[
        "\u6c9f\u574e\u5be8"
    ],
    "wof:name":"Goukanzhai",
    "wof:placetype":"locality"
},
  "geometry": {"coordinates":[107.104,26.4376],"type":"Point"}
}