{
  "type": "Feature",
  "properties": {
    "gn:admin1_code":"29.0",
    "gn:asciiname":"Jiangdeng",
    "gn:country_code":"CN",
    "gn:dem":2138,
    "gn:feature_class":"P",
    "gn:feature_code":"PPL",
    "gn:name":"Jiangdeng",
    "gn:population":0,
    "gn:timezone":"Asia/Shanghai",
    "iso:country":"CN",
    "name:zho_x_preferred":[
        "\u6c5f\u767b"
    ],
    "wof:name":"Jiangdeng",
    "wof:placetype":"locality"
},
  "geometry": {"coordinates":[99.947,25.9929],"type":"Point"}
}