{
  "type": "Feature",
  "properties": {
    "gn:admin1_code":"24.0",
    "gn:asciiname":"Xuejiayao",
    "gn:country_code":"CN",
    "gn:dem":1571,
    "gn:feature_class":"P",
    "gn:feature_code":"PPL",
    "gn:name":"Xuejiayao",
    "gn:population":0,
    "gn:timezone":"Asia/Shanghai",
    "iso:country":"CN",
    "name:zho_x_preferred":[
        "\u859b\u5bb6\u7a91"
    ],
    "wof:name":"Xuejiayao",
    "wof:placetype":"locality"
},
  "geometry": {"coordinates":[112.12678,39.85704000000001],"type":"Point"}
}