{
  "type": "Feature",
  "properties": {
    "gn:admin1_code":"15.0",
    "gn:asciiname":"Shankouzi",
    "gn:country_code":"CN",
    "gn:dem":1414,
    "gn:feature_class":"P",
    "gn:feature_code":"PPL",
    "gn:name":"Shankouzi",
    "gn:population":0,
    "gn:timezone":"Asia/Shanghai",
    "iso:country":"CN",
    "name:zho_x_preferred":[
        "\u5c71\u53e3\u5b50"
    ],
    "wof:name":"Shankouzi",
    "wof:placetype":"locality"
},
  "geometry": {"coordinates":[103.249,39.116],"type":"Point"}
}