{
  "type": "Feature",
  "properties": {
    "gn:admin1_code":"4.0",
    "gn:asciiname":"Sanlizecun",
    "gn:country_code":"CN",
    "gn:dem":2,
    "gn:feature_class":"P",
    "gn:feature_code":"PPL",
    "gn:name":"Sanlizecun",
    "gn:population":0,
    "gn:timezone":"Asia/Shanghai",
    "iso:country":"CN",
    "name:zho_x_preferred":[
        "\u4e09\u91cc\u6cfd\u6751"
    ],
    "wof:name":"Sanlizecun",
    "wof:placetype":"locality"
},
  "geometry": {"coordinates":[120.04248,32.68213],"type":"Point"}
}