{
  "type": "Feature",
  "properties": {
    "gn:admin1_code":"30.0",
    "gn:asciiname":"Huizhaicun",
    "gn:country_code":"CN",
    "gn:dem":7,
    "gn:feature_class":"P",
    "gn:feature_code":"PPL",
    "gn:name":"Huizhaicun",
    "gn:population":0,
    "gn:timezone":"Asia/Shanghai",
    "iso:country":"CN",
    "name:und_x_variant":[
        "Huizhai"
    ],
    "name:zho_x_preferred":[
        "\u7070\u5be8\u6751"
    ],
    "name:zho_x_variant":[
        "\u7070\u5be8"
    ],
    "wof:name":"Huizhaicun",
    "wof:placetype":"locality"
},
  "geometry": {"coordinates":[116.89586,23.6622],"type":"Point"}
}