{
  "type": "Feature",
  "properties": {
    "gn:admin1_code":"24.0",
    "gn:asciiname":"Sanhekou",
    "gn:country_code":"CN",
    "gn:dem":756,
    "gn:feature_class":"P",
    "gn:feature_code":"PPL",
    "gn:name":"Sanhekou",
    "gn:population":0,
    "gn:timezone":"Asia/Shanghai",
    "iso:country":"CN",
    "name:zho_x_preferred":[
        "\u4e09\u6cb3\u53e3"
    ],
    "wof:name":"Sanhekou",
    "wof:placetype":"locality"
},
  "geometry": {"coordinates":[111.47637,35.38290999999999],"type":"Point"}
}