{
  "type": "Feature",
  "properties": {
    "gn:admin1_code":"4.0",
    "gn:asciiname":"Dunmenkou",
    "gn:country_code":"CN",
    "gn:dem":8,
    "gn:feature_class":"P",
    "gn:feature_code":"PPL",
    "gn:name":"Dunmenkou",
    "gn:population":0,
    "gn:timezone":"Asia/Shanghai",
    "iso:country":"CN",
    "name:zho_x_preferred":[
        "\u8e72\u95e8\u53e3"
    ],
    "wof:name":"Dunmenkou",
    "wof:placetype":"locality"
},
  "geometry": {"coordinates":[120.86462,32.96426],"type":"Point"}
}