{
  "type": "Feature",
  "properties": {
    "gn:admin1_code":"25",
    "gn:asciiname":"Gujiya",
    "gn:country_code":"CN",
    "gn:dem":102,
    "gn:feature_class":"P",
    "gn:feature_code":"PPL",
    "gn:name":"Gujiya",
    "gn:population":0,
    "gn:timezone":"Asia/Shanghai",
    "iso:country":"CN",
    "name:zho_x_preferred":[
        "\u53e4\u8ff9\u5d16"
    ],
    "wof:name":"Gujiya",
    "wof:placetype":"locality"
},
  "geometry": {"coordinates":[118.78700000000001,35.4383],"type":"Point"}
}