{
  "type": "Feature",
  "properties": {
    "gn:admin1_code":"30.0",
    "gn:asciiname":"Wenguicun",
    "gn:country_code":"CN",
    "gn:dem":180,
    "gn:feature_class":"P",
    "gn:feature_code":"PPL",
    "gn:name":"Wenguicun",
    "gn:population":0,
    "gn:timezone":"Asia/Shanghai",
    "iso:country":"CN",
    "name:zho_x_preferred":[
        "\u6587\u8d35\u6751"
    ],
    "wof:name":"Wenguicun",
    "wof:placetype":"locality"
},
  "geometry": {"coordinates":[116.04989999999999,24.79392],"type":"Point"}
}