{
  "type": "Feature",
  "properties": {
    "gn:admin1_code":"6.0",
    "gn:asciiname":"Jilonggen Ci'er",
    "gn:country_code":"CN",
    "gn:dem":4441,
    "gn:feature_class":"P",
    "gn:feature_code":"PPL",
    "gn:name":"Jilonggen Ci\u2019er",
    "gn:population":0,
    "gn:timezone":"Asia/Urumqi",
    "iso:country":"CN",
    "name:und_x_variant":[
        "Jilonggen Ci\u2019er"
    ],
    "name:zho_x_preferred":[
        "\u5409\u9f99\u6839\u523a\u513f"
    ],
    "wof:name":"Jilonggen Ci'er",
    "wof:placetype":"locality"
},
  "geometry": {"coordinates":[95.97445,32.25271],"type":"Point"}
}