{
  "type": "Feature",
  "properties": {
    "gn:admin1_code":"16.0",
    "gn:asciiname":"Pozhuang",
    "gn:country_code":"CN",
    "gn:dem":916,
    "gn:feature_class":"P",
    "gn:feature_code":"PPL",
    "gn:name":"Pozhuang",
    "gn:population":0,
    "gn:timezone":"Asia/Shanghai",
    "iso:country":"CN",
    "name:zho_x_preferred":[
        "\u5761\u72b6"
    ],
    "wof:name":"Pozhuang",
    "wof:placetype":"locality"
},
  "geometry": {"coordinates":[105.852,23.0264],"type":"Point"}
}