{
  "type": "Feature",
  "properties": {
    "gn:admin1_code":"1.0",
    "gn:asciiname":"Chengkan",
    "gn:country_code":"CN",
    "gn:dem":191,
    "gn:feature_class":"P",
    "gn:feature_code":"PPLA4",
    "gn:name":"Chengkan",
    "gn:population":0,
    "gn:timezone":"Asia/Shanghai",
    "iso:country":"CN",
    "name:und_x_variant":[
        "Chengkan Zhen",
        "Chengkan"
    ],
    "name:zho_x_preferred":[
        "\u5448\u574e"
    ],
    "name:zho_x_variant":[
        "\u5448\u574e\u9547"
    ],
    "wof:name":"Chengkan",
    "wof:placetype":"locality"
},
  "geometry": {"coordinates":[118.28361,29.92361],"type":"Point"}
}