{
  "type": "Feature",
  "properties": {
    "gn:admin1_code":"18.0",
    "gn:asciiname":"Mengbei",
    "gn:country_code":"CN",
    "gn:dem":388,
    "gn:feature_class":"P",
    "gn:feature_code":"PPL",
    "gn:name":"Mengbei",
    "gn:population":0,
    "gn:timezone":"Asia/Shanghai",
    "iso:country":"CN",
    "name:zho_x_preferred":[
        "\u5b5f\u7891"
    ],
    "wof:name":"Mengbei",
    "wof:placetype":"locality"
},
  "geometry": {"coordinates":[109.057,26.7244],"type":"Point"}
}