{
  "type": "Feature",
  "properties": {
    "gn:admin1_code":"25",
    "gn:asciiname":"Houxumi",
    "gn:country_code":"CN",
    "gn:dem":123,
    "gn:feature_class":"P",
    "gn:feature_code":"PPL",
    "gn:name":"Houxumi",
    "gn:population":0,
    "gn:timezone":"Asia/Shanghai",
    "iso:country":"CN",
    "name:zho_x_preferred":[
        "\u540e\u7eea\u5bc6"
    ],
    "wof:name":"Houxumi",
    "wof:placetype":"locality"
},
  "geometry": {"coordinates":[118.89700000000001,35.6695],"type":"Point"}
}