{
  "type": "Feature",
  "properties": {
    "gn:admin1_code":"25",
    "gn:asciiname":"Shenshupo",
    "gn:country_code":"CN",
    "gn:dem":3,
    "gn:feature_class":"P",
    "gn:feature_code":"PPL",
    "gn:name":"Shenshupo",
    "gn:population":0,
    "gn:timezone":"Asia/Shanghai",
    "iso:country":"CN",
    "name:zho_x_preferred":[
        "\u795e\u6811\u5761"
    ],
    "wof:name":"Shenshupo",
    "wof:placetype":"locality"
},
  "geometry": {"coordinates":[119.017,37.0474],"type":"Point"}
}