{
  "type": "Feature",
  "properties": {
    "gn:admin1_code":"5.0",
    "gn:asciiname":"Dongzhenchaicun",
    "gn:country_code":"CN",
    "gn:dem":249,
    "gn:feature_class":"P",
    "gn:feature_code":"PPL",
    "gn:name":"Dongzhenchaicun",
    "gn:population":0,
    "gn:timezone":"Asia/Shanghai",
    "iso:country":"CN",
    "name:zho_x_preferred":[
        "\u4e1c\u699b\u67f4\u6751"
    ],
    "wof:name":"Dongzhenchaicun",
    "wof:placetype":"locality"
},
  "geometry": {"coordinates":[124.60545999999999,44.4111],"type":"Point"}
}