{
  "type": "Feature",
  "properties": {
    "gn:admin1_code":"29.0",
    "gn:asciiname":"Liutiaolu",
    "gn:country_code":"CN",
    "gn:dem":2096,
    "gn:feature_class":"P",
    "gn:feature_code":"PPL",
    "gn:name":"Liutiaolu",
    "gn:population":0,
    "gn:timezone":"Asia/Shanghai",
    "iso:country":"CN",
    "name:zho_x_preferred":[
        "\u516d\u6761\u8def"
    ],
    "wof:name":"Liutiaolu",
    "wof:placetype":"locality"
},
  "geometry": {"coordinates":[104.033,26.0106],"type":"Point"}
}