{
  "type": "Feature",
  "properties": {
    "gn:admin1_code":"24.0",
    "gn:asciiname":"Yangzhuang",
    "gn:cc2":"CN",
    "gn:country_code":"CN",
    "gn:dem":1168,
    "gn:feature_class":"P",
    "gn:feature_code":"PPL",
    "gn:name":"Yangzhuang",
    "gn:population":0,
    "gn:timezone":"Asia/Shanghai",
    "iso:country":"CN",
    "name:und_x_variant":[
        "Yang-chuang",
        "Yangzhuang"
    ],
    "wof:name":"Yangzhuang",
    "wof:placetype":"locality"
},
  "geometry": {"coordinates":[112.76667,38.18333],"type":"Point"}
}