{
  "type": "Feature",
  "properties": {
    "gn:admin1_code":"14.0",
    "gn:asciiname":"Yougun",
    "gn:country_code":"CN",
    "gn:dem":4070,
    "gn:feature_class":"P",
    "gn:feature_code":"PPL",
    "gn:name":"Yougun",
    "gn:population":0,
    "gn:timezone":"Asia/Urumqi",
    "iso:country":"CN",
    "name:zho_x_preferred":[
        "\u6709\u68cd"
    ],
    "wof:name":"Yougun",
    "wof:placetype":"locality"
},
  "geometry": {"coordinates":[98.27221,30.46704],"type":"Point"}
}