{
  "type": "Feature",
  "properties": {
    "gn:admin1_code":"18",
    "gn:asciiname":"Wuguxi",
    "gn:country_code":"CN",
    "gn:dem":544,
    "gn:feature_class":"P",
    "gn:feature_code":"PPL",
    "gn:name":"Wuguxi",
    "gn:population":0,
    "gn:timezone":"Asia/Shanghai",
    "iso:country":"CN",
    "name:zho_x_preferred":[
        "\u4e94\u8c37\u6eaa"
    ],
    "wof:name":"Wuguxi",
    "wof:placetype":"locality"
},
  "geometry": {"coordinates":[108.27200000000001,28.4059],"type":"Point"}
}