{
  "type": "Feature",
  "properties": {
    "gn:admin1_code":"24.0",
    "gn:asciiname":"Xipoya",
    "gn:country_code":"CN",
    "gn:dem":1262,
    "gn:feature_class":"P",
    "gn:feature_code":"PPL",
    "gn:name":"Xipoya",
    "gn:population":0,
    "gn:timezone":"Asia/Shanghai",
    "iso:country":"CN",
    "name:und_x_variant":[
        "Hsi-p\u2019o-ya",
        "Hsi-p\u2019o-yai",
        "Xipoya"
    ],
    "name:zho_x_preferred":[
        "\u897f\u5761\u5d16"
    ],
    "wof:name":"Xipoya",
    "wof:placetype":"locality"
},
  "geometry": {"coordinates":[111.91107,38.34727],"type":"Point"}
}