{
  "type": "Feature",
  "properties": {
    "gn:admin1_code":"20",
    "gn:asciiname":"Hsi-ta-tao",
    "gn:country_code":"CN",
    "gn:dem":763,
    "gn:feature_class":"P",
    "gn:feature_code":"PPL",
    "gn:name":"Hsi-ta-tao",
    "gn:population":0,
    "gn:timezone":"Asia/Shanghai",
    "iso:country":"CN",
    "wof:name":"Hsi-ta-tao",
    "wof:placetype":"locality"
},
  "geometry": {"coordinates":[118.95944,42.78194000000001],"type":"Point"}
}