{
  "type": "Feature",
  "properties": {
    "gn:admin1_code":"9.0",
    "gn:asciiname":"Wujianfang",
    "gn:country_code":"CN",
    "gn:dem":210,
    "gn:feature_class":"P",
    "gn:feature_code":"PPL",
    "gn:name":"Wujianfang",
    "gn:population":0,
    "gn:timezone":"Asia/Shanghai",
    "iso:country":"CN",
    "name:und_x_variant":[
        "\u4e94\u95f4\u623f",
        "Wujianfang"
    ],
    "wof:name":"Wujianfang",
    "wof:placetype":"locality"
},
  "geometry": {"coordinates":[112.90613,33.59365],"type":"Point"}
}