{
  "type": "Feature",
  "properties": {
    "gn:admin1_code":"19.0",
    "gn:asciiname":"Shangweitaichong",
    "gn:country_code":"CN",
    "gn:dem":125,
    "gn:feature_class":"P",
    "gn:feature_code":"PPL",
    "gn:name":"Shangweitaichong",
    "gn:population":0,
    "gn:timezone":"Asia/Shanghai",
    "iso:country":"CN",
    "name:und_x_variant":[
        "\u4e0a\u672a\u53f0\u51b2"
    ],
    "name:zho_x_preferred":[
        "\u4e0a\u672a\u53f0\u51b2"
    ],
    "wof:name":"Shangweitaichong",
    "wof:placetype":"locality"
},
  "geometry": {"coordinates":[123.79422,42.08558],"type":"Point"}
}