{
  "type": "Feature",
  "properties": {
    "gn:admin1_code":"5.0",
    "gn:asciiname":"Gaoligou",
    "gn:country_code":"CN",
    "gn:dem":451,
    "gn:feature_class":"P",
    "gn:feature_code":"PPL",
    "gn:name":"Gaoligou",
    "gn:population":0,
    "gn:timezone":"Asia/Shanghai",
    "iso:country":"CN",
    "name:zho_x_preferred":[
        "\u9ad8\u4e3d\u6c9f"
    ],
    "wof:name":"Gaoligou",
    "wof:placetype":"locality"
},
  "geometry": {"coordinates":[126.00631,41.7486],"type":"Point"}
}