{
  "type": "Feature",
  "properties": {
    "gn:admin1_code":"2.0",
    "gn:asciiname":"Datang",
    "gn:country_code":"CN",
    "gn:dem":108,
    "gn:feature_class":"P",
    "gn:feature_code":"PPL",
    "gn:name":"Datang",
    "gn:population":0,
    "gn:timezone":"Asia/Shanghai",
    "iso:country":"CN",
    "name:und_x_variant":[
        "\u5927\u5858",
        "Datang"
    ],
    "wof:name":"Datang",
    "wof:placetype":"locality"
},
  "geometry": {"coordinates":[119.62654000000001,29.30752],"type":"Point"}
}