{
  "type": "Feature",
  "properties": {
    "gn:admin1_code":"26.0",
    "gn:asciiname":"Haopingsi",
    "gn:country_code":"CN",
    "gn:dem":914,
    "gn:feature_class":"P",
    "gn:feature_code":"PPL",
    "gn:name":"Haopingsi",
    "gn:population":0,
    "gn:timezone":"Asia/Shanghai",
    "iso:country":"CN",
    "name:zho_x_preferred":[
        "\u84bf\u5e73\u5bfa"
    ],
    "wof:name":"Haopingsi",
    "wof:placetype":"locality"
},
  "geometry": {"coordinates":[108.17865,32.94841],"type":"Point"}
}