{
  "type": "Feature",
  "properties": {
    "gn:admin1_code":"9",
    "gn:asciiname":"Yangcun",
    "gn:country_code":"CN",
    "gn:dem":113,
    "gn:feature_class":"P",
    "gn:feature_code":"PPL",
    "gn:name":"Yangcun",
    "gn:population":0,
    "gn:timezone":"Asia/Shanghai",
    "iso:country":"CN",
    "name:und_x_variant":[
        "\u6768\u6751",
        "Yangcun"
    ],
    "wof:name":"Yangcun",
    "wof:placetype":"locality"
},
  "geometry": {"coordinates":[113.30931,34.00964],"type":"Point"}
}