{
  "type": "Feature",
  "properties": {
    "gn:admin1_code":"19.0",
    "gn:asciiname":"Bijiashancun",
    "gn:country_code":"CN",
    "gn:dem":71,
    "gn:feature_class":"P",
    "gn:feature_code":"PPL",
    "gn:name":"Bijiashancun",
    "gn:population":0,
    "gn:timezone":"Asia/Shanghai",
    "iso:country":"CN",
    "name:zho_x_preferred":[
        "\u7b14\u67b6\u5c71\u6751"
    ],
    "wof:name":"Bijiashancun",
    "wof:placetype":"locality"
},
  "geometry": {"coordinates":[120.77271,41.06464],"type":"Point"}
}