{
  "type": "Feature",
  "properties": {
    "gn:admin1_code":"07",
    "gn:asciiname":"Qingshui Shezuxiang",
    "gn:cc2":"CN",
    "gn:country_code":"CN",
    "gn:dem":776,
    "gn:feature_class":"P",
    "gn:feature_code":"PPL",
    "gn:name":"Qingshui Shezuxiang",
    "gn:population":0,
    "gn:timezone":"Asia/Shanghai",
    "iso:country":"CN",
    "name:und_x_variant":[
        "Ch\u2019ing-shui-ch\u2019ih",
        "Qingshui",
        "Qingshui Shezuxiang"
    ],
    "wof:name":"Qingshui Shezuxiang",
    "wof:placetype":"locality"
},
  "geometry": {"coordinates":[117.62139000000001,25.87722],"type":"Point"}
}