{
  "type": "Feature",
  "properties": {
    "gn:admin1_code":"12.0",
    "gn:asciiname":"Jiangchengjiawan",
    "gn:country_code":"CN",
    "gn:dem":144,
    "gn:feature_class":"P",
    "gn:feature_code":"PPL",
    "gn:name":"Jiangchengjiawan",
    "gn:population":0,
    "gn:timezone":"Asia/Shanghai",
    "iso:country":"CN",
    "name:zho_x_preferred":[
        "\u59dc\u7a0b\u5bb6\u6e7e"
    ],
    "wof:name":"Jiangchengjiawan",
    "wof:placetype":"locality"
},
  "geometry": {"coordinates":[112.45762999999999,31.90751],"type":"Point"}
}