{
  "type": "Feature",
  "properties": {
    "gn:admin1_code":"24.0",
    "gn:asciiname":"Yashang",
    "gn:country_code":"CN",
    "gn:dem":440,
    "gn:feature_class":"P",
    "gn:feature_code":"PPL",
    "gn:name":"Yashang",
    "gn:population":0,
    "gn:timezone":"Asia/Shanghai",
    "iso:country":"CN",
    "name:und_x_variant":[
        "\u5d16\u4e0a"
    ],
    "wof:name":"Yashang",
    "wof:placetype":"locality"
},
  "geometry": {"coordinates":[111.40184000000001,35.59972],"type":"Point"}
}