{
  "type": "Feature",
  "properties": {
    "gn:admin1_code":"18",
    "gn:asciiname":"Guniangtian",
    "gn:country_code":"CN",
    "gn:dem":1542,
    "gn:feature_class":"P",
    "gn:feature_code":"PPL",
    "gn:name":"Guniangtian",
    "gn:population":0,
    "gn:timezone":"Asia/Shanghai",
    "iso:country":"CN",
    "name:zho_x_preferred":[
        "\u59d1\u5a18\u7530"
    ],
    "wof:name":"Guniangtian",
    "wof:placetype":"locality"
},
  "geometry": {"coordinates":[106.11199999999999,26.4345],"type":"Point"}
}