{
  "type": "Feature",
  "properties": {
    "gn:admin1_code":"15.0",
    "gn:asciiname":"Dongjiachuan",
    "gn:country_code":"CN",
    "gn:dem":1646,
    "gn:feature_class":"P",
    "gn:feature_code":"PPL",
    "gn:name":"Dongjiachuan",
    "gn:population":0,
    "gn:timezone":"Asia/Shanghai",
    "iso:country":"CN",
    "name:zho_x_preferred":[
        "\u8463\u5bb6\u5ddd"
    ],
    "wof:name":"Dongjiachuan",
    "wof:placetype":"locality"
},
  "geometry": {"coordinates":[104.71599999999999,36.0331],"type":"Point"}
}