{
  "type": "Feature",
  "properties": {
    "gn:admin1_code":"10.0",
    "gn:asciiname":"Jianzitun",
    "gn:country_code":"CN",
    "gn:dem":15,
    "gn:feature_class":"P",
    "gn:feature_code":"PPL",
    "gn:name":"Jianzitun",
    "gn:population":0,
    "gn:timezone":"Asia/Shanghai",
    "iso:country":"CN",
    "name:zho_x_preferred":[
        "\u526a\u5b50\u5c6f"
    ],
    "wof:name":"Jianzitun",
    "wof:placetype":"locality"
},
  "geometry": {"coordinates":[116.718,38.1615],"type":"Point"}
}