{
  "type": "Feature",
  "properties": {
    "gn:admin1_code":"11.0",
    "gn:asciiname":"Mutongjing",
    "gn:country_code":"CN",
    "gn:dem":555,
    "gn:feature_class":"P",
    "gn:feature_code":"PPL",
    "gn:name":"Mutongjing",
    "gn:population":0,
    "gn:timezone":"Asia/Shanghai",
    "iso:country":"CN",
    "name:zho_x_preferred":[
        "\u6728\u6876\u4e95"
    ],
    "wof:name":"Mutongjing",
    "wof:placetype":"locality"
},
  "geometry": {"coordinates":[109.35145,27.84302000000001],"type":"Point"}
}