{
  "type": "Feature",
  "properties": {
    "gn:admin1_code":"6.0",
    "gn:asciiname":"Eri Qiaoshang",
    "gn:country_code":"CN",
    "gn:dem":4173,
    "gn:feature_class":"P",
    "gn:feature_code":"PPL",
    "gn:name":"Eri Qiaoshang",
    "gn:population":0,
    "gn:timezone":"Asia/Urumqi",
    "iso:country":"CN",
    "name:zho_x_preferred":[
        "\u4fc4\u65e5\u4e54\u4e0a"
    ],
    "wof:name":"Eri Qiaoshang",
    "wof:placetype":"locality"
},
  "geometry": {"coordinates":[95.40138,32.33654],"type":"Point"}
}