{
  "type": "Feature",
  "properties": {
    "gn:admin1_code":"25",
    "gn:asciiname":"Niandong",
    "gn:country_code":"CN",
    "gn:dem":38,
    "gn:feature_class":"P",
    "gn:feature_code":"PPL",
    "gn:name":"Niandong",
    "gn:population":0,
    "gn:timezone":"Asia/Shanghai",
    "iso:country":"CN",
    "name:zho_x_preferred":[
        "\u57dd\u4e1c"
    ],
    "wof:name":"Niandong",
    "wof:placetype":"locality"
},
  "geometry": {"coordinates":[118.158,34.6083],"type":"Point"}
}