{
  "type": "Feature",
  "properties": {
    "gn:admin1_code":"2.0",
    "gn:asciiname":"Ruoxi Aodi",
    "gn:country_code":"CN",
    "gn:dem":93,
    "gn:feature_class":"P",
    "gn:feature_code":"PPL",
    "gn:name":"Ruoxi Aodi",
    "gn:population":0,
    "gn:timezone":"Asia/Shanghai",
    "iso:country":"CN",
    "name:zho_x_preferred":[
        "\u7bac\u6eaa\u5c99\u5e95"
    ],
    "wof:name":"Ruoxi Aodi",
    "wof:placetype":"locality"
},
  "geometry": {"coordinates":[120.7141,28.30451],"type":"Point"}
}