{
  "type": "Feature",
  "properties": {
    "gn:admin1_code":"13",
    "gn:asciiname":"Narede Muchang",
    "gn:country_code":"CN",
    "gn:dem":2481,
    "gn:feature_class":"P",
    "gn:feature_code":"PPLF",
    "gn:name":"Narede Muchang",
    "gn:population":0,
    "gn:timezone":"Asia/Urumqi",
    "iso:country":"CN",
    "name:und_x_variant":[
        "\u90a3\u70ed\u5fb7\u7267\u573a"
    ],
    "wof:name":"Narede Muchang",
    "wof:placetype":"locality"
},
  "geometry": {"coordinates":[84.19271999999999,43.05002],"type":"Point"}
}