{
  "type": "Feature",
  "properties": {
    "gn:admin1_code":"3.0",
    "gn:asciiname":"Jingyuan",
    "gn:country_code":"CN",
    "gn:dem":141,
    "gn:feature_class":"P",
    "gn:feature_code":"PPL",
    "gn:name":"Jingyuan",
    "gn:population":0,
    "gn:timezone":"Asia/Shanghai",
    "iso:country":"CN",
    "name:und_x_variant":[
        "\u8346\u6c85"
    ],
    "wof:name":"Jingyuan",
    "wof:placetype":"locality"
},
  "geometry": {"coordinates":[116.93487,27.31341],"type":"Point"}
}