{
  "type": "Feature",
  "properties": {
    "gn:admin1_code":"12",
    "gn:asciiname":"Chebu",
    "gn:country_code":"CN",
    "gn:dem":31,
    "gn:feature_class":"P",
    "gn:feature_code":"PPLA4",
    "gn:name":"Chebu",
    "gn:population":0,
    "gn:timezone":"Asia/Shanghai",
    "iso:country":"CN",
    "name:und_x_variant":[
        "Chebu Zhen"
    ],
    "name:zho_x_preferred":[
        "\u8f66\u57e0"
    ],
    "name:zho_x_variant":[
        "\u8f66\u57e0\u9547"
    ],
    "wof:name":"Chebu",
    "wof:placetype":"locality"
},
  "geometry": {"coordinates":[113.76063000000001,29.76878],"type":"Point"}
}