{
  "type": "Feature",
  "properties": {
    "gn:admin1_code":"19.0",
    "gn:asciiname":"Yujia Fenfang",
    "gn:country_code":"CN",
    "gn:dem":12,
    "gn:feature_class":"P",
    "gn:feature_code":"PPL",
    "gn:name":"Yujia Fenfang",
    "gn:population":0,
    "gn:timezone":"Asia/Shanghai",
    "iso:country":"CN",
    "name:zho_x_preferred":[
        "\u4e8e\u5bb6\u7c89\u623f"
    ],
    "wof:name":"Yujia Fenfang",
    "wof:placetype":"locality"
},
  "geometry": {"coordinates":[123.73153000000001,39.94861],"type":"Point"}
}