{
  "type": "Feature",
  "properties": {
    "gn:admin1_code":"26.0",
    "gn:asciiname":"Yejiashan",
    "gn:country_code":"CN",
    "gn:dem":1284,
    "gn:feature_class":"P",
    "gn:feature_code":"PPL",
    "gn:name":"Yejiashan",
    "gn:population":0,
    "gn:timezone":"Asia/Shanghai",
    "iso:country":"CN",
    "name:zho_x_preferred":[
        "\u91ce\u5bb6\u5c71"
    ],
    "wof:name":"Yejiashan",
    "wof:placetype":"locality"
},
  "geometry": {"coordinates":[109.18723,36.97056],"type":"Point"}
}