{
  "type": "Feature",
  "properties": {
    "gn:admin1_code":"3.0",
    "gn:asciiname":"Taoshu'an",
    "gn:country_code":"CN",
    "gn:dem":203,
    "gn:feature_class":"P",
    "gn:feature_code":"PPL",
    "gn:name":"Taoshu\u2019an",
    "gn:population":0,
    "gn:timezone":"Asia/Shanghai",
    "iso:country":"CN",
    "name:und_x_variant":[
        "Taoshu\u2019an"
    ],
    "name:zho_x_preferred":[
        "\u6843\u6811\u5eb5"
    ],
    "wof:name":"Taoshu'an",
    "wof:placetype":"locality"
},
  "geometry": {"coordinates":[115.458,27.034],"type":"Point"}
}