{
  "type": "Feature",
  "properties": {
    "gn:admin1_code":"32.0",
    "gn:asciiname":"Shenkengzi",
    "gn:country_code":"CN",
    "gn:dem":760,
    "gn:feature_class":"P",
    "gn:feature_code":"PPL",
    "gn:name":"Shenkengzi",
    "gn:population":0,
    "gn:timezone":"Asia/Shanghai",
    "iso:country":"CN",
    "name:zho_x_preferred":[
        "\u6df1\u5751\u5b50"
    ],
    "wof:name":"Shenkengzi",
    "wof:placetype":"locality"
},
  "geometry": {"coordinates":[104.34603,31.86163],"type":"Point"}
}