{
  "type": "Feature",
  "properties": {
    "gn:admin1_code":"05",
    "gn:asciiname":"Yitong",
    "gn:country_code":"CN",
    "gn:dem":249,
    "gn:feature_class":"P",
    "gn:feature_code":"PPLA3",
    "gn:name":"Yitong",
    "gn:population":0,
    "gn:timezone":"Asia/Shanghai",
    "iso:country":"CN",
    "name:deu_x_preferred":[
        "Yitong"
    ],
    "name:jpn_x_preferred":[
        "\u4f0a\u901a\u6e80\u65cf\u81ea\u6cbb\u770c"
    ],
    "name:nor_x_preferred":[
        "Yitong"
    ],
    "name:pol_x_preferred":[
        "Yitong"
    ],
    "name:swe_x_preferred":[
        "Yitong"
    ],
    "name:vie_x_preferred":[
        "Y Th\u00f4ng"
    ],
    "name:zho_x_preferred":[
        "I-t\u2019ung-chen"
    ],
    "name:zho_x_variant":[
        "I-t\u2019ung",
        "I-t\u2019ung-hsien",
        "\u4f0a\u901a",
        "\u4f0a\u901a\u6ee1\u65cf\u81ea\u6cbb\u53bf"
    ],
    "wof:name":"Yitong",
    "wof:placetype":"locality"
},
  "geometry": {"coordinates":[125.29725999999999,43.32628],"type":"Point"}
}