{
  "type": "Feature",
  "properties": {
    "gn:admin1_code":"15.0",
    "gn:asciiname":"Luotuowan",
    "gn:country_code":"CN",
    "gn:dem":1783,
    "gn:feature_class":"P",
    "gn:feature_code":"PPL",
    "gn:name":"Luotuowan",
    "gn:population":0,
    "gn:timezone":"Asia/Shanghai",
    "iso:country":"CN",
    "name:zho_x_preferred":[
        "\u9a86\u9a7c\u6e7e"
    ],
    "wof:name":"Luotuowan",
    "wof:placetype":"locality"
},
  "geometry": {"coordinates":[106.764,37.0253],"type":"Point"}
}