{
  "type": "Feature",
  "properties": {
    "gn:admin1_code":"1.0",
    "gn:asciiname":"Penglingcun",
    "gn:country_code":"CN",
    "gn:dem":30,
    "gn:feature_class":"P",
    "gn:feature_code":"PPL",
    "gn:name":"Penglingcun",
    "gn:population":0,
    "gn:timezone":"Asia/Shanghai",
    "iso:country":"CN",
    "name:und_x_variant":[
        "Pengling"
    ],
    "name:zho_x_preferred":[
        "\u5f6d\u5cad\u6751"
    ],
    "wof:name":"Penglingcun",
    "wof:placetype":"locality"
},
  "geometry": {"coordinates":[116.57226,30.67535],"type":"Point"}
}