{
  "type": "Feature",
  "properties": {
    "gn:admin1_code":"22",
    "gn:asciiname":"Shaliangzi",
    "gn:country_code":"CN",
    "gn:dem":428,
    "gn:feature_class":"P",
    "gn:feature_code":"PPL",
    "gn:name":"Shaliangzi",
    "gn:population":0,
    "gn:timezone":"Asia/Shanghai",
    "iso:country":"CN",
    "name:und_x_variant":[
        "Sha-liang-tzu",
        "Shaliangzi"
    ],
    "name:zho_x_preferred":[
        "\u6c99\u6881\u5b50"
    ],
    "wof:name":"Shaliangzi",
    "wof:placetype":"locality"
},
  "geometry": {"coordinates":[116.44971,40.70777],"type":"Point"}
}