{
  "type": "Feature",
  "properties": {
    "gn:admin1_code":"3.0",
    "gn:asciiname":"Yanghu",
    "gn:country_code":"CN",
    "gn:dem":430,
    "gn:feature_class":"P",
    "gn:feature_code":"PPL",
    "gn:name":"Yanghu",
    "gn:population":0,
    "gn:timezone":"Asia/Shanghai",
    "iso:country":"CN",
    "name:und_x_variant":[
        "\u4ef0\u6e56"
    ],
    "wof:name":"Yanghu",
    "wof:placetype":"locality"
},
  "geometry": {"coordinates":[115.26212,25.28335],"type":"Point"}
}