{
  "type": "Feature",
  "properties": {
    "gn:admin1_code":"11",
    "gn:asciiname":"Fuxingchang",
    "gn:country_code":"CN",
    "gn:dem":75,
    "gn:feature_class":"P",
    "gn:feature_code":"PPLA4",
    "gn:name":"Fuxingchang",
    "gn:population":0,
    "gn:timezone":"Asia/Shanghai",
    "iso:country":"CN",
    "name:und_x_variant":[
        "\u590d\u5174\u5382",
        "Fuxing",
        "Fuxingchang Zhen",
        "\u590d\u5174\u5382\u9547"
    ],
    "wof:name":"Fuxingchang",
    "wof:placetype":"locality"
},
  "geometry": {"coordinates":[111.8456,29.83438],"type":"Point"}
}