{
  "type": "Feature",
  "properties": {
    "gn:admin1_code":"24.0",
    "gn:asciiname":"Lujiachang",
    "gn:country_code":"CN",
    "gn:dem":697,
    "gn:feature_class":"P",
    "gn:feature_code":"PPL",
    "gn:name":"Lujiachang",
    "gn:population":0,
    "gn:timezone":"Asia/Shanghai",
    "iso:country":"CN",
    "name:zho_x_preferred":[
        "\u82a6\u5bb6\u573a"
    ],
    "wof:name":"Lujiachang",
    "wof:placetype":"locality"
},
  "geometry": {"coordinates":[111.19198,34.94554],"type":"Point"}
}