{
  "type": "Feature",
  "properties": {
    "gn:admin1_code":"14.0",
    "gn:asciiname":"Xixicun",
    "gn:country_code":"CN",
    "gn:dem":2930,
    "gn:feature_class":"P",
    "gn:feature_code":"PPL",
    "gn:name":"Xixicun",
    "gn:population":0,
    "gn:timezone":"Asia/Urumqi",
    "iso:country":"CN",
    "name:zho_x_preferred":[
        "\u897f\u897f\u6751"
    ],
    "wof:name":"Xixicun",
    "wof:placetype":"locality"
},
  "geometry": {"coordinates":[98.83324,30.85632],"type":"Point"}
}