{
  "type": "Feature",
  "properties": {
    "gn:admin1_code":"19.0",
    "gn:asciiname":"Xiaoxintun",
    "gn:country_code":"CN",
    "gn:dem":189,
    "gn:feature_class":"P",
    "gn:feature_code":"PPL",
    "gn:name":"Xiaoxintun",
    "gn:population":0,
    "gn:timezone":"Asia/Shanghai",
    "iso:country":"CN",
    "name:und_x_variant":[
        "\u5c0f\u8f9b\u5c6f"
    ],
    "wof:name":"Xiaoxintun",
    "wof:placetype":"locality"
},
  "geometry": {"coordinates":[122.42565,40.08432],"type":"Point"}
}