{
  "type": "Feature",
  "properties": {
    "gn:admin1_code":"08",
    "gn:asciiname":"Qianshao Nongchang Liu Dui",
    "gn:country_code":"CN",
    "gn:dem":57,
    "gn:feature_class":"P",
    "gn:feature_code":"PPL",
    "gn:name":"Qianshao Nongchang Liu Dui",
    "gn:population":0,
    "gn:timezone":"Asia/Shanghai",
    "iso:country":"CN",
    "wof:name":"Qianshao Nongchang Liu Dui",
    "wof:placetype":"locality"
},
  "geometry": {"coordinates":[134.28861000000001,47.9125],"type":"Point"}
}