{
  "type": "Feature",
  "properties": {
    "gn:admin1_code":"29",
    "gn:asciiname":"Caotianqing",
    "gn:country_code":"CN",
    "gn:dem":1618,
    "gn:feature_class":"P",
    "gn:feature_code":"PPL",
    "gn:name":"Caotianqing",
    "gn:population":0,
    "gn:timezone":"Asia/Shanghai",
    "iso:country":"CN",
    "name:zho_x_preferred":[
        "\u8349\u5929\u7b90"
    ],
    "wof:name":"Caotianqing",
    "wof:placetype":"locality"
},
  "geometry": {"coordinates":[104.447,23.3626],"type":"Point"}
}