{
  "type": "Feature",
  "properties": {
    "gn:admin1_code":"29.0",
    "gn:asciiname":"Jiari",
    "gn:country_code":"CN",
    "gn:dem":2659,
    "gn:feature_class":"P",
    "gn:feature_code":"PPL",
    "gn:name":"Jiari",
    "gn:population":0,
    "gn:timezone":"Asia/Shanghai",
    "iso:country":"CN",
    "name:zho_x_preferred":[
        "\u52a0\u65e5"
    ],
    "wof:name":"Jiari",
    "wof:placetype":"locality"
},
  "geometry": {"coordinates":[100.902,27.1187],"type":"Point"}
}