{
  "type": "Feature",
  "properties": {
    "gn:admin1_code":"1.0",
    "gn:asciiname":"Shenchangcun",
    "gn:country_code":"CN",
    "gn:dem":23,
    "gn:feature_class":"P",
    "gn:feature_code":"PPL",
    "gn:name":"Shenchangcun",
    "gn:population":0,
    "gn:timezone":"Asia/Shanghai",
    "iso:country":"CN",
    "name:und_x_variant":[
        "Shenchang"
    ],
    "name:zho_x_preferred":[
        "\u7533\u573a\u6751"
    ],
    "wof:name":"Shenchangcun",
    "wof:placetype":"locality"
},
  "geometry": {"coordinates":[117.60833,33.84722],"type":"Point"}
}