{
  "type": "Feature",
  "properties": {
    "gn:admin1_code":"31",
    "gn:asciiname":"Dajin",
    "gn:country_code":"CN",
    "gn:dem":146,
    "gn:feature_class":"P",
    "gn:feature_code":"PPL",
    "gn:name":"Dajin",
    "gn:population":0,
    "gn:timezone":"Asia/Shanghai",
    "iso:country":"CN",
    "name:und_x_variant":[
        "\u6253\u91d1"
    ],
    "wof:name":"Dajin",
    "wof:placetype":"locality"
},
  "geometry": {"coordinates":[109.169,19.2986],"type":"Point"}
}