{
  "type": "Feature",
  "properties": {
    "gn:admin1_code":"21.0",
    "gn:asciiname":"Zhaoping",
    "gn:country_code":"CN",
    "gn:dem":1832,
    "gn:feature_class":"P",
    "gn:feature_code":"PPL",
    "gn:name":"Zhaoping",
    "gn:population":0,
    "gn:timezone":"Asia/Shanghai",
    "iso:country":"CN",
    "name:und_x_variant":[
        "\u8d75\u576a"
    ],
    "name:zho_x_preferred":[
        "\u8d75\u576a"
    ],
    "wof:name":"Zhaoping",
    "wof:placetype":"locality"
},
  "geometry": {"coordinates":[105.33971,35.92189000000001],"type":"Point"}
}