{
  "type": "Feature",
  "properties": {
    "gn:admin1_code":"26",
    "gn:asciiname":"Fuxiacun",
    "gn:country_code":"CN",
    "gn:dem":390,
    "gn:feature_class":"P",
    "gn:feature_code":"PPL",
    "gn:name":"Fuxiacun",
    "gn:population":0,
    "gn:timezone":"Asia/Shanghai",
    "iso:country":"CN",
    "name:und_x_variant":[
        "Fuxia",
        "\u961c\u4e0b",
        "Fuxiacun"
    ],
    "name:zho_x_preferred":[
        "\u961c\u4e0b"
    ],
    "name:zho_x_variant":[
        "\u961c\u4e0b\u6751"
    ],
    "wof:name":"Fuxiacun",
    "wof:placetype":"locality"
},
  "geometry": {"coordinates":[108.89412,34.47418],"type":"Point"}
}