{
  "type": "Feature",
  "properties": {
    "gn:admin1_code":"4.0",
    "gn:asciiname":"Shanyou",
    "gn:country_code":"CN",
    "gn:dem":6,
    "gn:feature_class":"P",
    "gn:feature_code":"PPL",
    "gn:name":"Shanyou",
    "gn:population":0,
    "gn:timezone":"Asia/Shanghai",
    "iso:country":"CN",
    "name:zho_x_preferred":[
        "Shanyou"
    ],
    "name:zho_x_variant":[
        "\u5584\u53cb"
    ],
    "wof:name":"Shanyou",
    "wof:placetype":"locality"
},
  "geometry": {"coordinates":[119.77825,34.1478],"type":"Point"}
}