{
  "type": "Feature",
  "properties": {
    "gn:admin1_code":"26.0",
    "gn:asciiname":"Guandaozui",
    "gn:country_code":"CN",
    "gn:dem":1278,
    "gn:feature_class":"P",
    "gn:feature_code":"PPL",
    "gn:name":"Guandaozui",
    "gn:population":0,
    "gn:timezone":"Asia/Shanghai",
    "iso:country":"CN",
    "name:zho_x_preferred":[
        "\u5173\u9053\u5480"
    ],
    "wof:name":"Guandaozui",
    "wof:placetype":"locality"
},
  "geometry": {"coordinates":[108.59125,36.5948],"type":"Point"}
}