{
  "type": "Feature",
  "properties": {
    "gn:admin1_code":"7",
    "gn:asciiname":"Xiananxi",
    "gn:country_code":"CN",
    "gn:dem":721,
    "gn:feature_class":"P",
    "gn:feature_code":"PPL",
    "gn:name":"Xiananxi",
    "gn:population":0,
    "gn:timezone":"Asia/Shanghai",
    "iso:country":"CN",
    "name:und_x_variant":[
        "\u4e0b\u5357\u6eaa",
        "Xiananxi"
    ],
    "wof:name":"Xiananxi",
    "wof:placetype":"locality"
},
  "geometry": {"coordinates":[119.45363999999999,27.15351],"type":"Point"}
}