{
  "type": "Feature",
  "properties": {
    "gn:admin1_code":"9.0",
    "gn:asciiname":"Niulaojia",
    "gn:country_code":"CN",
    "gn:dem":42,
    "gn:feature_class":"P",
    "gn:feature_code":"PPL",
    "gn:name":"Niulaojia",
    "gn:population":0,
    "gn:timezone":"Asia/Shanghai",
    "iso:country":"CN",
    "name:zho_x_preferred":[
        "\u725b\u8001\u5bb6"
    ],
    "wof:name":"Niulaojia",
    "wof:placetype":"locality"
},
  "geometry": {"coordinates":[115.78501,32.02185],"type":"Point"}
}