{
  "type": "Feature",
  "properties": {
    "gn:admin1_code":"3.0",
    "gn:asciiname":"Zaohekeng",
    "gn:country_code":"CN",
    "gn:dem":24,
    "gn:feature_class":"P",
    "gn:feature_code":"PPL",
    "gn:name":"Zaohekeng",
    "gn:population":0,
    "gn:timezone":"Asia/Shanghai",
    "iso:country":"CN",
    "name:und_x_variant":[
        "\u65e9\u79be\u5751"
    ],
    "wof:name":"Zaohekeng",
    "wof:placetype":"locality"
},
  "geometry": {"coordinates":[116.98560999999999,29.13314],"type":"Point"}
}