{
  "type": "Feature",
  "properties": {
    "gn:admin1_code":"29.0",
    "gn:asciiname":"Pojiaocun",
    "gn:country_code":"CN",
    "gn:dem":1928,
    "gn:feature_class":"P",
    "gn:feature_code":"PPL",
    "gn:name":"Pojiaocun",
    "gn:population":0,
    "gn:timezone":"Asia/Shanghai",
    "iso:country":"CN",
    "name:zho_x_preferred":[
        "\u5761\u811a\u6751"
    ],
    "wof:name":"Pojiaocun",
    "wof:placetype":"locality"
},
  "geometry": {"coordinates":[100.92400000000001,25.6296],"type":"Point"}
}