{
  "type": "Feature",
  "properties": {
    "gn:admin1_code":"4.0",
    "gn:asciiname":"Xinmincun",
    "gn:country_code":"CN",
    "gn:dem":4,
    "gn:feature_class":"P",
    "gn:feature_code":"PPL",
    "gn:name":"Xinmincun",
    "gn:population":0,
    "gn:timezone":"Asia/Shanghai",
    "iso:country":"CN",
    "name:und_x_variant":[
        "Xinmingcun",
        "Xinmincun"
    ],
    "name:zho_x_preferred":[
        "\u65b0\u6c11\u6751"
    ],
    "wof:name":"Xinmincun",
    "wof:placetype":"locality"
},
  "geometry": {"coordinates":[119.43231000000002,32.69812],"type":"Point"}
}