{
  "type": "Feature",
  "properties": {
    "gn:admin1_code":"14.0",
    "gn:asciiname":"Danqu Linji",
    "gn:country_code":"CN",
    "gn:dem":4105,
    "gn:feature_class":"P",
    "gn:feature_code":"PPL",
    "gn:name":"Danqu Linji",
    "gn:population":0,
    "gn:timezone":"Asia/Urumqi",
    "iso:country":"CN",
    "name:zho_x_preferred":[
        "\u65e6\u66f2\u6797\u5409"
    ],
    "wof:name":"Danqu Linji",
    "wof:placetype":"locality"
},
  "geometry": {"coordinates":[87.3737,28.1892],"type":"Point"}
}