{
  "type": "Feature",
  "properties": {
    "gn:admin1_code":"10",
    "gn:asciiname":"Xiachangledian",
    "gn:country_code":"CN",
    "gn:dem":1088,
    "gn:feature_class":"P",
    "gn:feature_code":"PPL",
    "gn:name":"Xiachangledian",
    "gn:population":0,
    "gn:timezone":"Asia/Shanghai",
    "iso:country":"CN",
    "name:zho_x_preferred":[
        "\u4e0b\u5e38\u4e50\u5e97"
    ],
    "wof:name":"Xiachangledian",
    "wof:placetype":"locality"
},
  "geometry": {"coordinates":[118.01429,41.98803],"type":"Point"}
}