{
  "type": "Feature",
  "properties": {
    "gn:admin1_code":"3.0",
    "gn:asciiname":"Dongbianling",
    "gn:country_code":"CN",
    "gn:dem":337,
    "gn:feature_class":"P",
    "gn:feature_code":"PPL",
    "gn:name":"Dongbianling",
    "gn:population":0,
    "gn:timezone":"Asia/Shanghai",
    "iso:country":"CN",
    "name:und_x_variant":[
        "\u4e1c\u8fb9\u5cad"
    ],
    "wof:name":"Dongbianling",
    "wof:placetype":"locality"
},
  "geometry": {"coordinates":[116.11087999999999,27.11844],"type":"Point"}
}