{
  "type": "Feature",
  "properties": {
    "gn:admin1_code":"26",
    "gn:asciiname":"Baohe",
    "gn:country_code":"CN",
    "gn:dem":557,
    "gn:feature_class":"P",
    "gn:feature_code":"PPL",
    "gn:name":"Baohe",
    "gn:population":0,
    "gn:timezone":"Asia/Shanghai",
    "iso:country":"CN",
    "name:und_x_variant":[
        "Pao-ch\u2019eng",
        "Baocheng",
        "Pao-ch\u2019eng-hsien",
        "Baochen",
        "Baohe"
    ],
    "wof:name":"Baohe",
    "wof:placetype":"locality"
},
  "geometry": {"coordinates":[106.96056000000002,33.20333],"type":"Point"}
}