{
  "type": "Feature",
  "properties": {
    "gn:admin1_code":"10",
    "gn:asciiname":"Donglizhifang",
    "gn:country_code":"CN",
    "gn:dem":25,
    "gn:feature_class":"P",
    "gn:feature_code":"PPL",
    "gn:name":"Donglizhifang",
    "gn:population":0,
    "gn:timezone":"Asia/Shanghai",
    "iso:country":"CN",
    "name:zho_x_preferred":[
        "\u4e1c\u674e\u7eb8\u623f"
    ],
    "wof:name":"Donglizhifang",
    "wof:placetype":"locality"
},
  "geometry": {"coordinates":[115.75,37.6113],"type":"Point"}
}