{
  "type": "Feature",
  "properties": {
    "gn:admin1_code":"29.0",
    "gn:asciiname":"Xifandi",
    "gn:country_code":"CN",
    "gn:dem":2803,
    "gn:feature_class":"P",
    "gn:feature_code":"PPL",
    "gn:name":"Xifandi",
    "gn:population":0,
    "gn:timezone":"Asia/Shanghai",
    "iso:country":"CN",
    "name:zho_x_preferred":[
        "\u897f\u756a\u5730"
    ],
    "wof:name":"Xifandi",
    "wof:placetype":"locality"
},
  "geometry": {"coordinates":[99.5386,26.596],"type":"Point"}
}