{
  "type": "Feature",
  "properties": {
    "gn:admin1_code":"25",
    "gn:asciiname":"Beiquan",
    "gn:country_code":"CN",
    "gn:dem":106,
    "gn:feature_class":"P",
    "gn:feature_code":"PPL",
    "gn:name":"Beiquan",
    "gn:population":0,
    "gn:timezone":"Asia/Shanghai",
    "iso:country":"CN",
    "name:zho_x_preferred":[
        "\u5317\u6cc9"
    ],
    "wof:name":"Beiquan",
    "wof:placetype":"locality"
},
  "geometry": {"coordinates":[116.42700000000001,36.2069],"type":"Point"}
}