{
  "type": "Feature",
  "properties": {
    "gn:admin1_code":"16.0",
    "gn:asciiname":"Luo'an",
    "gn:country_code":"CN",
    "gn:dem":421,
    "gn:feature_class":"P",
    "gn:feature_code":"PPL",
    "gn:name":"Luo\u2019an",
    "gn:population":0,
    "gn:timezone":"Asia/Shanghai",
    "iso:country":"CN",
    "name:und_x_variant":[
        "Luo\u2019an"
    ],
    "name:zho_x_preferred":[
        "\u843d\u6848"
    ],
    "wof:name":"Luo'an",
    "wof:placetype":"locality"
},
  "geometry": {"coordinates":[107.803,24.442],"type":"Point"}
}