{
  "type": "Feature",
  "properties": {
    "gn:admin1_code":"14.0",
    "gn:asciiname":"Boduo",
    "gn:country_code":"CN",
    "gn:dem":3562,
    "gn:feature_class":"P",
    "gn:feature_code":"PPL",
    "gn:name":"Boduo",
    "gn:population":0,
    "gn:timezone":"Asia/Urumqi",
    "iso:country":"CN",
    "name:zho_x_preferred":[
        "\u52c3\u591a"
    ],
    "wof:name":"Boduo",
    "wof:placetype":"locality"
},
  "geometry": {"coordinates":[97.32675999999999,30.74368],"type":"Point"}
}