{
  "type": "Feature",
  "properties": {
    "gn:admin1_code":"26",
    "gn:asciiname":"Baozi",
    "gn:country_code":"CN",
    "gn:dem":912,
    "gn:feature_class":"P",
    "gn:feature_code":"PPL",
    "gn:name":"Baozi",
    "gn:population":0,
    "gn:timezone":"Asia/Shanghai",
    "iso:country":"CN",
    "name:und_x_variant":[
        "\u5821\u5b50"
    ],
    "name:zho_x_preferred":[
        "\u5821\u5b50"
    ],
    "wof:name":"Baozi",
    "wof:placetype":"locality"
},
  "geometry": {"coordinates":[108.45778,34.81444],"type":"Point"}
}