{
  "type": "Feature",
  "properties": {
    "gn:admin1_code":"29.0",
    "gn:asciiname":"Zuizishang",
    "gn:country_code":"CN",
    "gn:dem":2273,
    "gn:feature_class":"P",
    "gn:feature_code":"PPL",
    "gn:name":"Zuizishang",
    "gn:population":0,
    "gn:timezone":"Asia/Shanghai",
    "iso:country":"CN",
    "name:zho_x_preferred":[
        "\u5634\u5b50\u4e0a"
    ],
    "wof:name":"Zuizishang",
    "wof:placetype":"locality"
},
  "geometry": {"coordinates":[101.372,25.395],"type":"Point"}
}