{
  "type": "Feature",
  "properties": {
    "gn:admin1_code":"26.0",
    "gn:asciiname":"Tuojiayuan",
    "gn:country_code":"CN",
    "gn:dem":1096,
    "gn:feature_class":"P",
    "gn:feature_code":"PPL",
    "gn:name":"Tuojiayuan",
    "gn:population":0,
    "gn:timezone":"Asia/Shanghai",
    "iso:country":"CN",
    "name:zho_x_preferred":[
        "\u62d3\u5bb6\u586c"
    ],
    "wof:name":"Tuojiayuan",
    "wof:placetype":"locality"
},
  "geometry": {"coordinates":[109.95107,36.62009000000001],"type":"Point"}
}