{
  "type": "Feature",
  "properties": {
    "gn:admin1_code":"3.0",
    "gn:asciiname":"Yuantouwu",
    "gn:country_code":"CN",
    "gn:dem":121,
    "gn:feature_class":"P",
    "gn:feature_code":"PPL",
    "gn:name":"Yuantouwu",
    "gn:population":0,
    "gn:timezone":"Asia/Shanghai",
    "iso:country":"CN",
    "name:und_x_variant":[
        "\u6e90\u5934\u575e"
    ],
    "wof:name":"Yuantouwu",
    "wof:placetype":"locality"
},
  "geometry": {"coordinates":[117.10791,29.13646],"type":"Point"}
}