{
  "type": "Feature",
  "properties": {
    "gn:admin1_code":"3.0",
    "gn:asciiname":"Yueliang",
    "gn:country_code":"CN",
    "gn:dem":21,
    "gn:feature_class":"P",
    "gn:feature_code":"PPL",
    "gn:name":"Yueliang",
    "gn:population":0,
    "gn:timezone":"Asia/Shanghai",
    "iso:country":"CN",
    "name:und_x_variant":[
        "\u6708\u4eae"
    ],
    "wof:name":"Yueliang",
    "wof:placetype":"locality"
},
  "geometry": {"coordinates":[116.23478,29.71275],"type":"Point"}
}