{
  "type": "Feature",
  "properties": {
    "iso:country":"CN",
    "ne:ADM0CAP":0.0,
    "ne:ADM0NAME":"China",
    "ne:ADM0_A3":"CHN",
    "ne:ADM1NAME":"Beijing",
    "ne:ADMIN1_COD":0,
    "ne:CAPALT":0,
    "ne:CHANGED":0,
    "ne:CHECKME":1,
    "ne:COMPARE":0,
    "ne:DIFFASCII":0,
    "ne:ELEVATION":0.0,
    "ne:FEATURECLA":"Populated place",
    "ne:GEONAMEID":-1,
    "ne:GEONAMESNO":"No GeoNames match due to small population, not in GeoNames, or poor NEV placement.",
    "ne:GN_POP":0,
    "ne:GTOPO30":0.0,
    "ne:ISO_A2":"CN",
    "ne:LABELRANK":1,
    "ne:LATITUDE":39.540053,
    "ne:LONGITUDE":115.789976,
    "ne:LS_MATCH":1,
    "ne:LS_NAME":"Zuozhou",
    "ne:MAX_AREAKM":20.0,
    "ne:MAX_AREAMI":8.0,
    "ne:MAX_BBXMAX":115.841667,
    "ne:MAX_BBXMIN":115.758333,
    "ne:MAX_BBYMAX":39.591667,
    "ne:MAX_BBYMIN":39.525,
    "ne:MAX_NATSCA":10.0,
    "ne:MAX_PERKM":37.0,
    "ne:MAX_PERMI":23.0,
    "ne:MAX_POP10":24768,
    "ne:MAX_POP20":0,
    "ne:MAX_POP300":0,
    "ne:MAX_POP310":0,
    "ne:MAX_POP50":0,
    "ne:MEAN_BBXC":115.8025,
    "ne:MEAN_BBYC":39.551944,
    "ne:MEGACITY":0,
    "ne:MIN_AREAKM":20.0,
    "ne:MIN_AREAMI":8.0,
    "ne:MIN_BBXMAX":115.841667,
    "ne:MIN_BBXMIN":115.758333,
    "ne:MIN_BBYMAX":39.591667,
    "ne:MIN_BBYMIN":39.525,
    "ne:MIN_PERKM":37.0,
    "ne:MIN_PERMI":23.0,
    "ne:NAME":"Zhuozhou",
    "ne:NAMEASCII":"Zhuozhou",
    "ne:NAMEDIFF":0,
    "ne:NATSCALE":10,
    "ne:POP1950":0,
    "ne:POP1955":0,
    "ne:POP1960":0,
    "ne:POP1965":0,
    "ne:POP1970":0,
    "ne:POP1975":0,
    "ne:POP1980":0,
    "ne:POP1985":0,
    "ne:POP1990":0,
    "ne:POP1995":0,
    "ne:POP2000":0,
    "ne:POP2005":0,
    "ne:POP2010":0,
    "ne:POP2015":0,
    "ne:POP2020":0,
    "ne:POP2025":0,
    "ne:POP2050":0,
    "ne:POP_MAX":628000,
    "ne:POP_MIN":202000,
    "ne:POP_OTHER":2693698,
    "ne:RANK_MAX":11,
    "ne:RANK_MIN":10,
    "ne:SCALERANK":8,
    "ne:SOV0NAME":"China",
    "ne:SOV_A3":"CHN",
    "ne:UN_FID":0,
    "ne:UN_LAT":0.0,
    "ne:UN_LONG":0.0,
    "ne:WORLDCITY":0,
    "ne:min_zoom":7.0,
    "wof:name":"Zhuozhou",
    "wof:placetype":"locality"
},
  "geometry": {"coordinates":[115.78997595119711,39.54005291651578],"type":"Point"}
}