{
  "type": "Feature",
  "properties": {
    "gn:admin1_code":"4.0",
    "gn:asciiname":"Yantou",
    "gn:country_code":"CN",
    "gn:dem":6,
    "gn:feature_class":"P",
    "gn:feature_code":"PPL",
    "gn:name":"Yantou",
    "gn:population":0,
    "gn:timezone":"Asia/Shanghai",
    "iso:country":"CN",
    "name:zho_x_preferred":[
        "Yantou"
    ],
    "name:zho_x_variant":[
        "\u71d5\u5934"
    ],
    "wof:name":"Yantou",
    "wof:placetype":"locality"
},
  "geometry": {"coordinates":[119.0034,34.02822],"type":"Point"}
}