{
  "type": "Feature",
  "properties": {
    "gn:admin1_code":"4.0",
    "gn:asciiname":"Titangcun",
    "gn:country_code":"CN",
    "gn:dem":36,
    "gn:feature_class":"P",
    "gn:feature_code":"PPL",
    "gn:name":"Titangcun",
    "gn:population":0,
    "gn:timezone":"Asia/Shanghai",
    "iso:country":"CN",
    "name:zho_x_preferred":[
        "\u501c\u50a5\u6751"
    ],
    "wof:name":"Titangcun",
    "wof:placetype":"locality"
},
  "geometry": {"coordinates":[118.6781,32.91089],"type":"Point"}
}