{
  "type": "Feature",
  "properties": {
    "gn:admin1_code":"29.0",
    "gn:asciiname":"Datuantian",
    "gn:country_code":"CN",
    "gn:dem":1670,
    "gn:feature_class":"P",
    "gn:feature_code":"PPL",
    "gn:name":"Datuantian",
    "gn:population":0,
    "gn:timezone":"Asia/Shanghai",
    "iso:country":"CN",
    "name:zho_x_preferred":[
        "\u5927\u56e2\u7530"
    ],
    "wof:name":"Datuantian",
    "wof:placetype":"locality"
},
  "geometry": {"coordinates":[102.655,25.5396],"type":"Point"}
}