{
  "type": "Feature",
  "properties": {
    "gn:admin1_code":"26.0",
    "gn:asciiname":"Gaoyaocun",
    "gn:country_code":"CN",
    "gn:dem":1076,
    "gn:feature_class":"P",
    "gn:feature_code":"PPL",
    "gn:name":"Gaoyaocun",
    "gn:population":0,
    "gn:timezone":"Asia/Shanghai",
    "iso:country":"CN",
    "name:zho_x_preferred":[
        "\u9ad8\u5c27\u6751"
    ],
    "wof:name":"Gaoyaocun",
    "wof:placetype":"locality"
},
  "geometry": {"coordinates":[109.59359000000001,36.78229],"type":"Point"}
}