{
  "type": "Feature",
  "properties": {
    "gn:admin1_code":"12.0",
    "gn:asciiname":"Huangmugou",
    "gn:country_code":"CN",
    "gn:dem":263,
    "gn:feature_class":"P",
    "gn:feature_code":"PPL",
    "gn:name":"Huangmugou",
    "gn:population":0,
    "gn:timezone":"Asia/Shanghai",
    "iso:country":"CN",
    "name:zho_x_preferred":[
        "\u9ec4\u6728\u6c9f"
    ],
    "wof:name":"Huangmugou",
    "wof:placetype":"locality"
},
  "geometry": {"coordinates":[110.92749000000001,32.65279],"type":"Point"}
}