{
  "type": "Feature",
  "properties": {
    "gn:admin1_code":"25",
    "gn:asciiname":"Caotun",
    "gn:country_code":"CN",
    "gn:dem":28,
    "gn:feature_class":"P",
    "gn:feature_code":"PPL",
    "gn:name":"Caotun",
    "gn:population":0,
    "gn:timezone":"Asia/Shanghai",
    "iso:country":"CN",
    "name:deu_x_preferred":[
        "Caotun"
    ],
    "name:hak_x_preferred":[
        "Chh\u00f3-th\u00f9n-ts\u1e73\u0301n"
    ],
    "name:ita_x_preferred":[
        "Caotun"
    ],
    "name:jpn_x_preferred":[
        "\u8349\u5c6f\u93ae"
    ],
    "name:kor_x_preferred":[
        "\ucc28\uc624\ud230\uc9c4"
    ],
    "name:pol_x_preferred":[
        "Caotun"
    ],
    "name:vie_x_preferred":[
        "Th\u1ea3o \u0110\u1ed3n"
    ],
    "name:zho_x_preferred":[
        "\u8349\u5c6f"
    ],
    "name:zho_x_variant":[
        "\u8349\u5c6f\u93ae"
    ],
    "wof:name":"Caotun",
    "wof:placetype":"locality"
},
  "geometry": {"coordinates":[116.215,37.2593],"type":"Point"}
}