{
  "type": "Feature",
  "properties": {
    "gn:admin1_code":"9.0",
    "gn:asciiname":"Houshi Mazhuang",
    "gn:country_code":"CN",
    "gn:dem":55,
    "gn:feature_class":"P",
    "gn:feature_code":"PPL",
    "gn:name":"Houshi Mazhuang",
    "gn:population":0,
    "gn:timezone":"Asia/Shanghai",
    "iso:country":"CN",
    "name:zho_x_preferred":[
        "\u540e\u53f2\u9a6c\u5e84"
    ],
    "wof:name":"Houshi Mazhuang",
    "wof:placetype":"locality"
},
  "geometry": {"coordinates":[114.48945999999999,33.87304],"type":"Point"}
}