{
  "type": "Feature",
  "properties": {
    "gn:admin1_code":"29",
    "gn:asciiname":"Houjidong",
    "gn:country_code":"CN",
    "gn:dem":1610,
    "gn:feature_class":"P",
    "gn:feature_code":"PPL",
    "gn:name":"Houjidong",
    "gn:population":0,
    "gn:timezone":"Asia/Shanghai",
    "iso:country":"CN",
    "name:zho_x_preferred":[
        "\u5019\u9e21\u6d1e"
    ],
    "wof:name":"Houjidong",
    "wof:placetype":"locality"
},
  "geometry": {"coordinates":[104.94199999999999,23.8242],"type":"Point"}
}