{
  "type": "Feature",
  "properties": {
    "gn:admin1_code":"1.0",
    "gn:asciiname":"Liupaifang",
    "gn:country_code":"CN",
    "gn:dem":10,
    "gn:feature_class":"P",
    "gn:feature_code":"PPL",
    "gn:name":"Liupaifang",
    "gn:population":0,
    "gn:timezone":"Asia/Shanghai",
    "iso:country":"CN",
    "name:zho_x_preferred":[
        "\u5218\u724c\u574a"
    ],
    "wof:name":"Liupaifang",
    "wof:placetype":"locality"
},
  "geometry": {"coordinates":[118.19249000000001,31.33969],"type":"Point"}
}