{
  "type": "Feature",
  "properties": {
    "gn:admin1_code":"26.0",
    "gn:asciiname":"Huoliangchengcun",
    "gn:country_code":"CN",
    "gn:dem":1068,
    "gn:feature_class":"P",
    "gn:feature_code":"PPL",
    "gn:name":"Huoliangchengcun",
    "gn:population":0,
    "gn:timezone":"Asia/Shanghai",
    "iso:country":"CN",
    "name:zho_x_preferred":[
        "\u4f19\u6881\u57ce\u6751"
    ],
    "wof:name":"Huoliangchengcun",
    "wof:placetype":"locality"
},
  "geometry": {"coordinates":[110.02848,38.01693],"type":"Point"}
}