{
  "type": "Feature",
  "properties": {
    "gn:admin1_code":"29.0",
    "gn:asciiname":"Hongyan",
    "gn:country_code":"CN",
    "gn:dem":2237,
    "gn:feature_class":"P",
    "gn:feature_code":"PPL",
    "gn:name":"Hongyan",
    "gn:population":0,
    "gn:timezone":"Asia/Shanghai",
    "iso:country":"CN",
    "name:ceb_x_preferred":[
        "Hongyan"
    ],
    "name:deu_x_preferred":[
        "Hongyan"
    ],
    "name:ita_x_preferred":[
        "Hongyan"
    ],
    "name:swe_x_preferred":[
        "Hongyan"
    ],
    "wof:name":"Hongyan",
    "wof:placetype":"locality"
},
  "geometry": {"coordinates":[99.91667,26.98333],"type":"Point"}
}