{
  "type": "Feature",
  "properties": {
    "gn:admin1_code":"23.0",
    "gn:asciiname":"Shaochang Zhen",
    "gn:country_code":"CN",
    "gn:dem":5,
    "gn:feature_class":"P",
    "gn:feature_code":"PPLA4",
    "gn:name":"Shaochang Zhen",
    "gn:population":0,
    "gn:timezone":"Asia/Shanghai",
    "iso:country":"CN",
    "name:und_x_variant":[
        "\u90b5\u5382\u9547"
    ],
    "wof:name":"Shaochang Zhen",
    "wof:placetype":"locality"
},
  "geometry": {"coordinates":[121.75294,30.9084],"type":"Point"}
}