{
  "type": "Feature",
  "properties": {
    "gn:admin1_code":"12",
    "gn:asciiname":"Caijiaba",
    "gn:country_code":"CN",
    "gn:dem":483,
    "gn:feature_class":"P",
    "gn:feature_code":"PPL",
    "gn:name":"Caijiaba",
    "gn:population":0,
    "gn:timezone":"Asia/Shanghai",
    "iso:country":"CN",
    "wof:name":"Caijiaba",
    "wof:placetype":"locality"
},
  "geometry": {"coordinates":[109.84556000000001,32.01556],"type":"Point"}
}