{
  "type": "Feature",
  "properties": {
    "gn:admin1_code":"29.0",
    "gn:asciiname":"Qingmenkou",
    "gn:country_code":"CN",
    "gn:dem":2180,
    "gn:feature_class":"P",
    "gn:feature_code":"PPL",
    "gn:name":"Qingmenkou",
    "gn:population":0,
    "gn:timezone":"Asia/Shanghai",
    "iso:country":"CN",
    "name:zho_x_preferred":[
        "\u7b90\u95e8\u53e3"
    ],
    "wof:name":"Qingmenkou",
    "wof:placetype":"locality"
},
  "geometry": {"coordinates":[100.315,24.3935],"type":"Point"}
}