{
  "type": "Feature",
  "properties": {
    "gn:admin1_code":"26.0",
    "gn:asciiname":"Laoyuanzi",
    "gn:country_code":"CN",
    "gn:dem":1256,
    "gn:feature_class":"P",
    "gn:feature_code":"PPL",
    "gn:name":"Laoyuanzi",
    "gn:population":0,
    "gn:timezone":"Asia/Shanghai",
    "iso:country":"CN",
    "name:zho_x_preferred":[
        "\u8001\u57b8\u5b50"
    ],
    "wof:name":"Laoyuanzi",
    "wof:placetype":"locality"
},
  "geometry": {"coordinates":[109.80683999999999,35.58369000000001],"type":"Point"}
}