{
  "type": "Feature",
  "properties": {
    "gn:admin1_code":"26.0",
    "gn:asciiname":"Niejia",
    "gn:country_code":"CN",
    "gn:dem":584,
    "gn:feature_class":"P",
    "gn:feature_code":"PPL",
    "gn:name":"Niejia",
    "gn:population":0,
    "gn:timezone":"Asia/Shanghai",
    "iso:country":"CN",
    "name:und_x_variant":[
        "\u8042\u5bb6"
    ],
    "wof:name":"Niejia",
    "wof:placetype":"locality"
},
  "geometry": {"coordinates":[107.94077,34.40625],"type":"Point"}
}