{
  "type": "Feature",
  "properties": {
    "gn:admin1_code":"32.0",
    "gn:asciiname":"Shang'ezu",
    "gn:country_code":"CN",
    "gn:dem":3315,
    "gn:feature_class":"P",
    "gn:feature_code":"PPL",
    "gn:name":"Shang\u2019ezu",
    "gn:population":0,
    "gn:timezone":"Asia/Shanghai",
    "iso:country":"CN",
    "name:und_x_variant":[
        "Shang\u2019ezu"
    ],
    "name:zho_x_preferred":[
        "\u4e0a\u4fc4\u7956"
    ],
    "wof:name":"Shang'ezu",
    "wof:placetype":"locality"
},
  "geometry": {"coordinates":[102.21899999999999,30.7478],"type":"Point"}
}