{
  "type": "Feature",
  "properties": {
    "gn:admin1_code":"15.0",
    "gn:asciiname":"Zhashuli",
    "gn:country_code":"CN",
    "gn:dem":2354,
    "gn:feature_class":"P",
    "gn:feature_code":"PPL",
    "gn:name":"Zhashuli",
    "gn:population":0,
    "gn:timezone":"Asia/Shanghai",
    "iso:country":"CN",
    "name:und_x_variant":[
        "\u624e\u6811\u91cc"
    ],
    "wof:name":"Zhashuli",
    "wof:placetype":"locality"
},
  "geometry": {"coordinates":[104.18553,34.80322],"type":"Point"}
}