{
  "type": "Feature",
  "properties": {
    "gn:admin1_code":"3.0",
    "gn:asciiname":"Daling Linchang",
    "gn:country_code":"CN",
    "gn:dem":225,
    "gn:feature_class":"P",
    "gn:feature_code":"PPLF",
    "gn:name":"Daling Linchang",
    "gn:population":0,
    "gn:timezone":"Asia/Shanghai",
    "iso:country":"CN",
    "name:und_x_variant":[
        "\u5927\u5cad\u6797\u573a"
    ],
    "wof:name":"Daling Linchang",
    "wof:placetype":"locality"
},
  "geometry": {"coordinates":[117.69206,29.41699],"type":"Point"}
}