{
  "type": "Feature",
  "properties": {
    "gn:admin1_code":"20",
    "gn:asciiname":"Bilige Linchang",
    "gn:country_code":"CN",
    "gn:dem":686,
    "gn:feature_class":"P",
    "gn:feature_code":"PPLF",
    "gn:name":"Bilige Linchang",
    "gn:population":0,
    "gn:timezone":"Asia/Shanghai",
    "iso:country":"CN",
    "wof:name":"Bilige Linchang",
    "wof:placetype":"locality"
},
  "geometry": {"coordinates":[122.17749999999999,50.0475],"type":"Point"}
}