{
  "type": "Feature",
  "properties": {
    "gn:admin1_code":"12.0",
    "gn:asciiname":"Tieyuhe",
    "gn:country_code":"CN",
    "gn:dem":823,
    "gn:feature_class":"P",
    "gn:feature_code":"PPL",
    "gn:name":"Tieyuhe",
    "gn:population":0,
    "gn:timezone":"Asia/Shanghai",
    "iso:country":"CN",
    "name:zho_x_preferred":[
        "\u94c1\u9c7c\u6cb3"
    ],
    "wof:name":"Tieyuhe",
    "wof:placetype":"locality"
},
  "geometry": {"coordinates":[110.89088,32.23699999999999],"type":"Point"}
}