{
  "type": "Feature",
  "properties": {
    "gn:admin1_code":"19.0",
    "gn:asciiname":"Zhengyingzicun",
    "gn:country_code":"CN",
    "gn:dem":710,
    "gn:feature_class":"P",
    "gn:feature_code":"PPL",
    "gn:name":"Zhengyingzicun",
    "gn:population":0,
    "gn:timezone":"Asia/Shanghai",
    "iso:country":"CN",
    "name:zho_x_preferred":[
        "\u90d1\u8425\u5b50\u6751"
    ],
    "wof:name":"Zhengyingzicun",
    "wof:placetype":"locality"
},
  "geometry": {"coordinates":[119.77500000000001,41.9557],"type":"Point"}
}