{
  "type": "Feature",
  "properties": {
    "gn:admin1_code":"4.0",
    "gn:asciiname":"Xuguanyingcun",
    "gn:country_code":"CN",
    "gn:dem":7,
    "gn:feature_class":"P",
    "gn:feature_code":"PPL",
    "gn:name":"Xuguanyingcun",
    "gn:population":0,
    "gn:timezone":"Asia/Shanghai",
    "iso:country":"CN",
    "name:zho_x_preferred":[
        "\u8bb8\u5b98\u8425\u6751"
    ],
    "wof:name":"Xuguanyingcun",
    "wof:placetype":"locality"
},
  "geometry": {"coordinates":[119.36468000000001,33.71270999999999],"type":"Point"}
}