{
  "type": "Feature",
  "properties": {
    "gn:admin1_code":"26.0",
    "gn:asciiname":"Xiaotiantang",
    "gn:country_code":"CN",
    "gn:dem":1693,
    "gn:feature_class":"P",
    "gn:feature_code":"PPL",
    "gn:name":"Xiaotiantang",
    "gn:population":0,
    "gn:timezone":"Asia/Shanghai",
    "iso:country":"CN",
    "name:zho_x_preferred":[
        "\u5c0f\u7530\u5858"
    ],
    "wof:name":"Xiaotiantang",
    "wof:placetype":"locality"
},
  "geometry": {"coordinates":[107.70927,37.2877],"type":"Point"}
}