{
  "type": "Feature",
  "properties": {
    "gn:admin1_code":"29.0",
    "gn:asciiname":"Yangquan",
    "gn:country_code":"CN",
    "gn:dem":1670,
    "gn:feature_class":"P",
    "gn:feature_code":"PPL",
    "gn:name":"Yangquan",
    "gn:population":0,
    "gn:timezone":"Asia/Shanghai",
    "iso:country":"CN",
    "name:zho_x_preferred":[
        "\u7f8a\u5708"
    ],
    "wof:name":"Yangquan",
    "wof:placetype":"locality"
},
  "geometry": {"coordinates":[99.21769999999999,24.067],"type":"Point"}
}