{
  "type": "Feature",
  "properties": {
    "gn:admin1_code":"5.0",
    "gn:asciiname":"Da'ancun",
    "gn:country_code":"CN",
    "gn:dem":254,
    "gn:feature_class":"P",
    "gn:feature_code":"PPL",
    "gn:name":"Da\u2019ancun",
    "gn:population":0,
    "gn:timezone":"Asia/Shanghai",
    "iso:country":"CN",
    "name:und_x_variant":[
        "Da\u2019ancun"
    ],
    "name:zho_x_preferred":[
        "\u5927\u5b89\u6751"
    ],
    "wof:name":"Da'ancun",
    "wof:placetype":"locality"
},
  "geometry": {"coordinates":[127.16915,44.39833],"type":"Point"}
}