{
  "type": "Feature",
  "properties": {
    "gn:admin1_code":"18",
    "gn:asciiname":"Pinggu",
    "gn:country_code":"CN",
    "gn:dem":767,
    "gn:feature_class":"P",
    "gn:feature_code":"PPL",
    "gn:name":"Pinggu",
    "gn:population":0,
    "gn:timezone":"Asia/Shanghai",
    "iso:country":"CN",
    "name:zho_x_preferred":[
        "\u5e73\u8c37"
    ],
    "wof:name":"Pinggu",
    "wof:placetype":"locality"
},
  "geometry": {"coordinates":[105.925,24.8294],"type":"Point"}
}