{
  "type": "Feature",
  "properties": {
    "gn:admin1_code":"30.0",
    "gn:asciiname":"Zenghetang",
    "gn:country_code":"CN",
    "gn:dem":22,
    "gn:feature_class":"P",
    "gn:feature_code":"PPL",
    "gn:name":"Zenghetang",
    "gn:population":0,
    "gn:timezone":"Asia/Shanghai",
    "iso:country":"CN",
    "name:zho_x_preferred":[
        "\u589e\u548c\u5858"
    ],
    "wof:name":"Zenghetang",
    "wof:placetype":"locality"
},
  "geometry": {"coordinates":[115.47485,23.04645],"type":"Point"}
}