{
  "type": "Feature",
  "properties": {
    "gn:admin1_code":"5.0",
    "gn:asciiname":"Beizhangzhi",
    "gn:country_code":"CN",
    "gn:dem":432,
    "gn:feature_class":"P",
    "gn:feature_code":"PPL",
    "gn:name":"Beizhangzhi",
    "gn:population":0,
    "gn:timezone":"Asia/Shanghai",
    "iso:country":"CN",
    "name:und_x_variant":[
        "\u5317\u5f20\u829d"
    ],
    "wof:name":"Beizhangzhi",
    "wof:placetype":"locality"
},
  "geometry": {"coordinates":[129.22205,43.23408],"type":"Point"}
}