{
  "type": "Feature",
  "properties": {
    "gn:admin1_code":"25.0",
    "gn:asciiname":"Henggou",
    "gn:country_code":"CN",
    "gn:dem":56,
    "gn:feature_class":"P",
    "gn:feature_code":"PPL",
    "gn:name":"Henggou",
    "gn:population":0,
    "gn:timezone":"Asia/Shanghai",
    "iso:country":"CN",
    "name:zho_x_preferred":[
        "\u6a2a\u6c9f"
    ],
    "wof:name":"Henggou",
    "wof:placetype":"locality"
},
  "geometry": {"coordinates":[119.14755,35.23520999999999],"type":"Point"}
}