{
  "type": "Feature",
  "properties": {
    "gn:admin1_code":"7.0",
    "gn:asciiname":"Likengyuan",
    "gn:country_code":"CN",
    "gn:dem":86,
    "gn:feature_class":"P",
    "gn:feature_code":"PPL",
    "gn:name":"Likengyuan",
    "gn:population":0,
    "gn:timezone":"Asia/Shanghai",
    "iso:country":"CN",
    "name:zho_x_preferred":[
        "\u91cc\u5751\u6e90"
    ],
    "wof:name":"Likengyuan",
    "wof:placetype":"locality"
},
  "geometry": {"coordinates":[119.75752,26.85804000000001],"type":"Point"}
}