{
  "type": "Feature",
  "properties": {
    "gn:country":"CN",
    "gn:fcode":"PPL",
    "gn:pop":56637,
    "iso:country":"CN",
    "name:ces_x_preferred":[
        "Chua"
    ],
    "name:deu_x_preferred":[
        "Hua"
    ],
    "name:eng_x_preferred":[
        "Hua County"
    ],
    "name:fas_x_preferred":[
        "\u0634\u0647\u0631\u0633\u062a\u0627\u0646 \u0647\u0648\u0627"
    ],
    "name:gan_x_preferred":[
        "\u6ed1\u53bf"
    ],
    "name:jpn_x_preferred":[
        "\u6ed1\u770c"
    ],
    "name:kor_x_preferred":[
        "\ud654\ud604"
    ],
    "name:nan_x_preferred":[
        "Ku\u030dt-ko\u0101n"
    ],
    "name:nld_x_preferred":[
        "Hua"
    ],
    "name:nob_x_preferred":[
        "Hua"
    ],
    "name:rus_x_preferred":[
        "\u0425\u0443\u0430\u0441\u044f\u043d\u044c"
    ],
    "name:swe_x_preferred":[
        "Hua"
    ],
    "name:ukr_x_preferred":[
        "\u0425\u0443\u0430\u0441\u044f\u043d\u044c"
    ],
    "name:unk_x_variant":[
        "Taokow"
    ],
    "name:vie_x_preferred":[
        "Ho\u1ea1t"
    ],
    "name:wuu_x_preferred":[
        "\u6ed1\u53bf"
    ],
    "name:yue_x_preferred":[
        "\u6ed1\u7e23"
    ],
    "name:zho_x_preferred":[
        "\u9053\u53e3"
    ],
    "name:zho_x_variant":[
        "\u6ed1\u53bf"
    ],
    "qs:name":"Huaxian",
    "qs:photos_9r":0,
    "qs:photos_sr":0,
    "qs:pop_sr":"8",
    "wd:wordcount":262,
    "wof:name":"Huaxian",
    "wof:placetype":"locality",
    "wof:population":56637
},
  "geometry": {"coordinates":[114.50583,35.56389],"type":"Point"}
}