{
  "type": "Feature",
  "properties": {
    "gn:country":"CN",
    "gn:fcode":"PPL",
    "gn:pop":56637,
    "iso:country":"CN",
    "name:unk_x_variant":[
        "Taokow"
    ],
    "name:zho_x_preferred":[
        "\u9053\u53e3"
    ],
    "qs:name":"Huaxian",
    "qs:photos_9r":0,
    "qs:photos_sr":0,
    "qs:pop_sr":"8",
    "wd:wordcount":262,
    "wof:name":"Huaxian",
    "wof:placetype":"locality",
    "wof:population":56637
},
  "geometry": {"coordinates":[114.50583,35.56389],"type":"Point"}
}