{
  "type": "Feature",
  "properties": {
    "gn:admin1_code":"22.0",
    "gn:asciiname":"Caishihecun",
    "gn:country_code":"CN",
    "gn:dem":724,
    "gn:feature_class":"P",
    "gn:feature_code":"PPL",
    "gn:name":"Caishihecun",
    "gn:population":0,
    "gn:timezone":"Asia/Shanghai",
    "iso:country":"CN",
    "name:zho_x_preferred":[
        "\u83dc\u98df\u6cb3\u6751"
    ],
    "wof:name":"Caishihecun",
    "wof:placetype":"locality"
},
  "geometry": {"coordinates":[116.39512999999999,40.51437],"type":"Point"}
}