{
  "type": "Feature",
  "properties": {
    "gn:admin1_code":"10.0",
    "gn:asciiname":"Damazhuang",
    "gn:country_code":"CN",
    "gn:dem":12,
    "gn:feature_class":"P",
    "gn:feature_code":"PPL",
    "gn:name":"Damazhuang",
    "gn:population":0,
    "gn:timezone":"Asia/Shanghai",
    "iso:country":"CN",
    "name:zho_x_preferred":[
        "\u5927\u9a6c\u5e84"
    ],
    "wof:name":"Damazhuang",
    "wof:placetype":"locality"
},
  "geometry": {"coordinates":[116.78,38.1846],"type":"Point"}
}