{
  "type": "Feature",
  "properties": {
    "gn:admin1_code":"14.0",
    "gn:asciiname":"Tunsong",
    "gn:country_code":"CN",
    "gn:dem":4456,
    "gn:feature_class":"P",
    "gn:feature_code":"PPL",
    "gn:name":"Tunsong",
    "gn:population":0,
    "gn:timezone":"Asia/Urumqi",
    "iso:country":"CN",
    "name:zho_x_preferred":[
        "\u5c6f\u677e"
    ],
    "wof:name":"Tunsong",
    "wof:placetype":"locality"
},
  "geometry": {"coordinates":[97.31265999999999,29.45257],"type":"Point"}
}