{
  "type": "Feature",
  "properties": {
    "gn:admin1_code":"11.0",
    "gn:asciiname":"Jiwuli",
    "gn:country_code":"CN",
    "gn:dem":456,
    "gn:feature_class":"P",
    "gn:feature_code":"PPL",
    "gn:name":"Jiwuli",
    "gn:population":0,
    "gn:timezone":"Asia/Shanghai",
    "iso:country":"CN",
    "name:zho_x_preferred":[
        "\u9e21\u5c4b\u91cc"
    ],
    "wof:name":"Jiwuli",
    "wof:placetype":"locality"
},
  "geometry": {"coordinates":[111.39261999999999,28.51797],"type":"Point"}
}