{
  "type": "Feature",
  "properties": {
    "gn:admin1_code":"29.0",
    "gn:asciiname":"Wangqing",
    "gn:country_code":"CN",
    "gn:dem":1982,
    "gn:feature_class":"P",
    "gn:feature_code":"PPL",
    "gn:name":"Wangqing",
    "gn:population":0,
    "gn:timezone":"Asia/Shanghai",
    "iso:country":"CN",
    "name:ben_x_preferred":[
        "\u0993\u09df\u09be\u0982\u0995\u09c1\u0987\u0982"
    ],
    "name:deu_x_preferred":[
        "Wangqing"
    ],
    "name:ell_x_preferred":[
        "\u0393\u03bf\u03c5\u03b1\u03bd\u03b3\u03ba\u03af\u03bd\u03b3\u03ba"
    ],
    "name:fas_x_preferred":[
        "\u0648\u0627\u0646\u06af \u06a9\u06cc\u0646\u06af"
    ],
    "name:fra_x_preferred":[
        "Wangqing"
    ],
    "name:heb_x_preferred":[
        "\u05d5\u05d5\u05d0\u05e0\u05e7\u05d5\u05d5\u05d9\u05e0\u05d2"
    ],
    "name:hin_x_preferred":[
        "\u0935\u093e\u0902\u0917\u0915\u093f\u0902\u0917"
    ],
    "name:hun_x_preferred":[
        "Wangqing"
    ],
    "name:ind_x_preferred":[
        "Wangqing"
    ],
    "name:ita_x_preferred":[
        "Wangqing"
    ],
    "name:kor_x_preferred":[
        "\uc655\uce6d"
    ],
    "name:nld_x_preferred":[
        "Wangqing"
    ],
    "name:pol_x_preferred":[
        "Wangqing"
    ],
    "name:rus_x_preferred":[
        "\u0412\u0430\u043d\u0446\u0438\u043d"
    ],
    "name:spa_x_preferred":[
        "Wangqing"
    ],
    "name:swe_x_preferred":[
        "Wangqing"
    ],
    "name:tur_x_preferred":[
        "Wangqing"
    ],
    "name:ukr_x_preferred":[
        "\u0412\u0430\u043d\u0446\u0438\u043d"
    ],
    "name:urd_x_preferred":[
        "\u0648\u0627\u0646\u06af\u0642\u0646\u06af"
    ],
    "name:vie_x_preferred":[
        "U\u00f4ng Thanh"
    ],
    "name:zho_x_preferred":[
        "\u6c6a\u60c5"
    ],
    "wof:name":"Wangqing",
    "wof:placetype":"locality"
},
  "geometry": {"coordinates":[100.691,25.3769],"type":"Point"}
}