{
  "type": "Feature",
  "properties": {
    "gn:admin1_code":"8.0",
    "gn:asciiname":"Delongtun",
    "gn:country_code":"CN",
    "gn:dem":140,
    "gn:feature_class":"P",
    "gn:feature_code":"PPL",
    "gn:name":"Delongtun",
    "gn:population":0,
    "gn:timezone":"Asia/Shanghai",
    "iso:country":"CN",
    "name:zho_x_preferred":[
        "\u5fb7\u9f99\u5c6f"
    ],
    "wof:name":"Delongtun",
    "wof:placetype":"locality"
},
  "geometry": {"coordinates":[124.05278,46.84483],"type":"Point"}
}