{
  "type": "Feature",
  "properties": {
    "gn:admin1_code":"19.0",
    "gn:asciiname":"Dongfengmigou",
    "gn:country_code":"CN",
    "gn:dem":421,
    "gn:feature_class":"P",
    "gn:feature_code":"PPL",
    "gn:name":"Dongfengmigou",
    "gn:population":0,
    "gn:timezone":"Asia/Shanghai",
    "iso:country":"CN",
    "name:zho_x_preferred":[
        "\u4e1c\u8702\u871c\u6c9f"
    ],
    "wof:name":"Dongfengmigou",
    "wof:placetype":"locality"
},
  "geometry": {"coordinates":[125.25812000000001,41.68561],"type":"Point"}
}