{
  "type": "Feature",
  "properties": {
    "gn:admin1_code":"30.0",
    "gn:asciiname":"Quantouling",
    "gn:country_code":"CN",
    "gn:dem":301,
    "gn:feature_class":"P",
    "gn:feature_code":"PPL",
    "gn:name":"Quantouling",
    "gn:population":0,
    "gn:timezone":"Asia/Shanghai",
    "iso:country":"CN",
    "name:zho_x_preferred":[
        "Quantouling"
    ],
    "name:zho_x_variant":[
        "\u62f3\u5934\u5cad"
    ],
    "wof:name":"Quantouling",
    "wof:placetype":"locality"
},
  "geometry": {"coordinates":[112.65167,24.52556],"type":"Point"}
}