{
  "type": "Feature",
  "properties": {
    "gn:admin1_code":"11.0",
    "gn:asciiname":"Jianjiao Daochang",
    "gn:country_code":"CN",
    "gn:dem":459,
    "gn:feature_class":"P",
    "gn:feature_code":"PPLF",
    "gn:name":"Jianjiao Daochang",
    "gn:population":0,
    "gn:timezone":"Asia/Shanghai",
    "iso:country":"CN",
    "name:zho_x_preferred":[
        "\u5c16\u89d2\u7a3b\u573a"
    ],
    "wof:name":"Jianjiao Daochang",
    "wof:placetype":"locality"
},
  "geometry": {"coordinates":[110.97676,29.89437],"type":"Point"}
}