{
  "type": "Feature",
  "properties": {
    "gn:admin1_code":"29.0",
    "gn:asciiname":"Chunhuadi",
    "gn:country_code":"CN",
    "gn:dem":2080,
    "gn:feature_class":"P",
    "gn:feature_code":"PPL",
    "gn:name":"Chunhuadi",
    "gn:population":0,
    "gn:timezone":"Asia/Shanghai",
    "iso:country":"CN",
    "name:zho_x_preferred":[
        "\u6625\u82b1\u5730"
    ],
    "wof:name":"Chunhuadi",
    "wof:placetype":"locality"
},
  "geometry": {"coordinates":[98.1966,24.9782],"type":"Point"}
}