{
  "type": "Feature",
  "properties": {
    "gn:admin1_code":"32.0",
    "gn:asciiname":"Angui",
    "gn:country_code":"CN",
    "gn:dem":3281,
    "gn:feature_class":"P",
    "gn:feature_code":"PPL",
    "gn:name":"Angui",
    "gn:population":0,
    "gn:timezone":"Asia/Shanghai",
    "iso:country":"CN",
    "name:zho_x_preferred":[
        "\u5b89\u6842"
    ],
    "wof:name":"Angui",
    "wof:placetype":"locality"
},
  "geometry": {"coordinates":[101.123,30.381],"type":"Point"}
}