{
  "type": "Feature",
  "properties": {
    "gn:country":"CN",
    "gn:fcode":"ADM3",
    "gn:population":620000,
    "iso:country":"CN",
    "name:ast_x_preferred":[
        "Changning"
    ],
    "name:cdo_x_preferred":[
        "Di\u00f2ng-n\u00ecng-k\u1e73\u0306"
    ],
    "name:ceb_x_preferred":[
        "Changning Qu"
    ],
    "name:ces_x_preferred":[
        "\u010cchang-ning"
    ],
    "name:cym_x_preferred":[
        "Ardal Changning"
    ],
    "name:deu_x_preferred":[
        "Changning"
    ],
    "name:eng_x_preferred":[
        "Changning District"
    ],
    "name:eus_x_preferred":[
        "Changning Barrutia"
    ],
    "name:gan_x_preferred":[
        "\u957f\u5b81\u533a"
    ],
    "name:heb_x_preferred":[
        "\u05e9\u05d0\u05e0\u05d2\u05d7\u05d0\u05d9/\u05e6'\u05d0\u05e0\u05d2\u05e0\u05d9\u05e0\u05d2"
    ],
    "name:hye_x_preferred":[
        "\u0549\u0561\u0576\u056b\u0576"
    ],
    "name:jpn_x_preferred":[
        "\u9577\u5be7\u533a"
    ],
    "name:kor_x_preferred":[
        "\ucc3d\ub2dd\uad6c"
    ],
    "name:lit_x_preferred":[
        "\u010cangningas"
    ],
    "name:nan_x_preferred":[
        "Ti\u00f4ng-l\u00eang-khu"
    ],
    "name:nld_x_preferred":[
        "Changning"
    ],
    "name:nob_x_preferred":[
        "Changning"
    ],
    "name:ron_x_preferred":[
        "Districtul Changning"
    ],
    "name:rus_x_preferred":[
        "\u0427\u0430\u043d\u043d\u0438\u043d"
    ],
    "name:spa_x_preferred":[
        "Changning"
    ],
    "name:swe_x_preferred":[
        "Changning"
    ],
    "name:tur_x_preferred":[
        "Changning"
    ],
    "name:ukr_x_preferred":[
        "\u0420\u0430\u0439\u043e\u043d \u0427\u0430\u043d\u043d\u0456\u043d"
    ],
    "name:ukr_x_variant":[
        "\u0427\u0430\u043d\u043d\u0456\u043d"
    ],
    "name:und_x_variant":[
        "Ch\u2019ang-ning Shih-ch\u2019\u00fc"
    ],
    "name:urd_x_preferred":[
        "\u0686\u0627\u0646\u06af\u0646\u06cc\u0646\u06af \u0636\u0644\u0639"
    ],
    "name:vie_x_preferred":[
        "Tr\u01b0\u1eddng Ninh"
    ],
    "name:wuu_x_preferred":[
        "\u957f\u5b81\u533a"
    ],
    "name:yue_x_preferred":[
        "\u9577\u5be7\u5340"
    ],
    "name:zho_x_preferred":[
        "\u957f\u5b81\u533a"
    ],
    "name:zho_x_variant":[
        "\u957f\u5b81",
        "\u9577\u5be7\u5340"
    ],
    "qs:name":"Changning Qu",
    "qs:photos_9r":0,
    "qs:photos_sr":0,
    "qs:pop_sr":"11",
    "wd:wordcount":724,
    "wof:name":"Changning Qu",
    "wof:placetype":"localadmin",
    "wof:population":620000
},
  "geometry": {"coordinates":[121.38999,31.20927],"type":"Point"}
}