{
  "type": "Feature",
  "properties": {
    "gn:country":"CN",
    "gn:fcode":"ADM3",
    "gn:pop":620000,
    "iso:country":"CN",
    "name:unk_x_variant":[
        "Ch\u2019ang-ning Shih-ch\u2019\u00fc"
    ],
    "name:zho_x_preferred":[
        "\u957f\u5b81\u533a"
    ],
    "name:zho_x_variant":[
        "\u957f\u5b81"
    ],
    "qs:name":"Changning Qu",
    "qs:photos_9r":0,
    "qs:photos_sr":0,
    "qs:pop_sr":"11",
    "wd:wordcount":724,
    "wof:name":"Changning Qu",
    "wof:placetype":"localadmin",
    "wof:population":620000
},
  "geometry": {"coordinates":[121.38999,31.20927],"type":"Point"}
}