{
  "type": "Feature",
  "properties": {
    "gn:admin1_code":"19.0",
    "gn:asciiname":"Banqiaozi",
    "gn:country_code":"CN",
    "gn:dem":15,
    "gn:feature_class":"P",
    "gn:feature_code":"PPL",
    "gn:name":"Banqiaozi",
    "gn:population":0,
    "gn:timezone":"Asia/Shanghai",
    "iso:country":"CN",
    "name:zho_x_preferred":[
        "\u677f\u6865\u5b50"
    ],
    "wof:name":"Banqiaozi",
    "wof:placetype":"locality"
},
  "geometry": {"coordinates":[121.75700000000001,39.6726],"type":"Point"}
}