{
  "type": "Feature",
  "properties": {
    "gn:admin1_code":"18.0",
    "gn:asciiname":"Luqing",
    "gn:country_code":"CN",
    "gn:dem":980,
    "gn:feature_class":"P",
    "gn:feature_code":"PPL",
    "gn:name":"Luqing",
    "gn:population":0,
    "gn:timezone":"Asia/Shanghai",
    "iso:country":"CN",
    "name:zho_x_preferred":[
        "\u8def\u9752"
    ],
    "name:zho_x_variant":[
        "\u9732\u9752"
    ],
    "wof:name":"Luqing",
    "wof:placetype":"locality"
},
  "geometry": {"coordinates":[108.15600000000001,28.1248],"type":"Point"}
}