{
  "type": "Feature",
  "properties": {
    "gn:admin1_code":"11.0",
    "gn:asciiname":"Daoshichong",
    "gn:country_code":"CN",
    "gn:dem":82,
    "gn:feature_class":"P",
    "gn:feature_code":"PPL",
    "gn:name":"Daoshichong",
    "gn:population":0,
    "gn:timezone":"Asia/Shanghai",
    "iso:country":"CN",
    "name:zho_x_preferred":[
        "\u9053\u58eb\u51b2"
    ],
    "wof:name":"Daoshichong",
    "wof:placetype":"locality"
},
  "geometry": {"coordinates":[112.83076,26.88038],"type":"Point"}
}