{
  "type": "Feature",
  "properties": {
    "gn:admin1_code":"15.0",
    "gn:asciiname":"Gaojia Taizi",
    "gn:country_code":"CN",
    "gn:dem":1501,
    "gn:feature_class":"P",
    "gn:feature_code":"PPL",
    "gn:name":"Gaojia Taizi",
    "gn:population":0,
    "gn:timezone":"Asia/Shanghai",
    "iso:country":"CN",
    "name:zho_x_preferred":[
        "\u9ad8\u5bb6\u53f0\u5b50"
    ],
    "wof:name":"Gaojia Taizi",
    "wof:placetype":"locality"
},
  "geometry": {"coordinates":[106.06999999999999,34.2551],"type":"Point"}
}