{
  "type": "Feature",
  "properties": {
    "gn:admin1_code":"5.0",
    "gn:asciiname":"Luozigou",
    "gn:country_code":"CN",
    "gn:dem":419,
    "gn:feature_class":"P",
    "gn:feature_code":"PPL",
    "gn:name":"Luozigou",
    "gn:population":0,
    "gn:timezone":"Asia/Shanghai",
    "iso:country":"CN",
    "name:und_x_variant":[
        "\u7f57\u5b50\u6c9f"
    ],
    "wof:name":"Luozigou",
    "wof:placetype":"locality"
},
  "geometry": {"coordinates":[130.27321000000001,43.73619],"type":"Point"}
}