{
  "type": "Feature",
  "properties": {
    "gn:admin1_code":"13",
    "gn:asciiname":"Daheyan Chalukou",
    "gn:country_code":"CN",
    "gn:dem":387,
    "gn:feature_class":"P",
    "gn:feature_code":"PPL",
    "gn:name":"Daheyan Chalukou",
    "gn:population":0,
    "gn:timezone":"Asia/Urumqi",
    "iso:country":"CN",
    "name:und_x_variant":[
        "\u5927\u6cb3\u6cbf\u5c94\u8def\u53e3"
    ],
    "wof:name":"Daheyan Chalukou",
    "wof:placetype":"locality"
},
  "geometry": {"coordinates":[88.77984000000002,43.05331],"type":"Point"}
}