{
  "type": "Feature",
  "properties": {
    "gn:country":"CN",
    "gn:fcode":"PPL",
    "gn:pop":109636,
    "iso:country":"CN",
    "name:unk_x_variant":[
        "T\u2019ieh-li-chen"
    ],
    "name:zho_x_preferred":[
        "\u94c1\u529b"
    ],
    "name:zho_x_variant":[
        "\u94c1\u529b\u9547",
        "\u94c1\u529b\u5e02"
    ],
    "ne:ADM0CAP":0.0,
    "ne:ADM0NAME":"China",
    "ne:ADM0_A3":"CHN",
    "ne:ADM1NAME":"Heilongjiang",
    "ne:ADMIN1_COD":8,
    "ne:CAPALT":0,
    "ne:CHANGED":0,
    "ne:CHECKME":0,
    "ne:COMPARE":0,
    "ne:DIFFASCII":0,
    "ne:ELEVATION":0.0,
    "ne:FEATURECLA":"Populated place",
    "ne:FEATURE_CL":"P",
    "ne:FEATURE_CO":"PPL",
    "ne:GEONAMEID":2034440,
    "ne:GEONAMESNO":"GeoNames match with ascii name + lat + long whole numbers.",
    "ne:GN_ASCII":"Tieli",
    "ne:GN_POP":109636,
    "ne:GTOPO30":205.0,
    "ne:ISO_A2":"CN",
    "ne:LABELRANK":1,
    "ne:LATITUDE":46.950376,
    "ne:LONGITUDE":128.050003,
    "ne:LS_MATCH":1,
    "ne:LS_NAME":"Tieli",
    "ne:MAX_AREAKM":45.0,
    "ne:MAX_AREAMI":17.0,
    "ne:MAX_BBXMAX":128.108333,
    "ne:MAX_BBXMIN":127.983333,
    "ne:MAX_BBYMAX":47.033333,
    "ne:MAX_BBYMIN":46.941667,
    "ne:MAX_NATSCA":20.0,
    "ne:MAX_PERKM":56.0,
    "ne:MAX_PERMI":34.0,
    "ne:MAX_POP10":108821,
    "ne:MAX_POP20":108821,
    "ne:MAX_POP300":0,
    "ne:MAX_POP310":0,
    "ne:MAX_POP50":0,
    "ne:MEAN_BBXC":128.039232,
    "ne:MEAN_BBYC":46.989665,
    "ne:MEGACITY":0,
    "ne:MIN_AREAKM":45.0,
    "ne:MIN_AREAMI":17.0,
    "ne:MIN_BBXMAX":128.108333,
    "ne:MIN_BBXMIN":127.983333,
    "ne:MIN_BBYMAX":47.033333,
    "ne:MIN_BBYMIN":46.941667,
    "ne:MIN_PERKM":56.0,
    "ne:MIN_PERMI":34.0,
    "ne:NAME":"Tieli",
    "ne:NAMEASCII":"Tieli",
    "ne:NAMEDIFF":0,
    "ne:NATSCALE":20,
    "ne:POP1950":0,
    "ne:POP1955":0,
    "ne:POP1960":0,
    "ne:POP1965":0,
    "ne:POP1970":0,
    "ne:POP1975":0,
    "ne:POP1980":0,
    "ne:POP1985":0,
    "ne:POP1990":0,
    "ne:POP1995":0,
    "ne:POP2000":0,
    "ne:POP2005":0,
    "ne:POP2010":0,
    "ne:POP2015":0,
    "ne:POP2020":0,
    "ne:POP2025":0,
    "ne:POP2050":0,
    "ne:POP_MAX":109636,
    "ne:POP_MIN":108821,
    "ne:POP_OTHER":0,
    "ne:RANK_MAX":9,
    "ne:RANK_MIN":9,
    "ne:SCALERANK":7,
    "ne:SOV0NAME":"China",
    "ne:SOV_A3":"CHN",
    "ne:TIMEZONE":"Asia/Harbin",
    "ne:UN_FID":0,
    "ne:UN_LAT":0.0,
    "ne:UN_LONG":0.0,
    "ne:WORLDCITY":0,
    "qs:name":"Tieli",
    "qs:photos_9r":0,
    "qs:photos_sr":0,
    "qs:pop_sr":"9",
    "wd:wordcount":20,
    "wof:name":"Tieli",
    "wof:placetype":"locality",
    "wof:population":109636
},
  "geometry": {"coordinates":[128.05000000000001,46.95],"type":"Point"}
}