{
  "type": "Feature",
  "properties": {
    "gn:admin1_code":"29.0",
    "gn:asciiname":"Yijiacun",
    "gn:country_code":"CN",
    "gn:dem":1580,
    "gn:feature_class":"P",
    "gn:feature_code":"PPL",
    "gn:name":"Yijiacun",
    "gn:population":0,
    "gn:timezone":"Asia/Shanghai",
    "iso:country":"CN",
    "name:zho_x_preferred":[
        "\u6613\u5bb6\u6751"
    ],
    "wof:name":"Yijiacun",
    "wof:placetype":"locality"
},
  "geometry": {"coordinates":[102.065,25.12],"type":"Point"}
}