{
  "type": "Feature",
  "properties": {
    "gn:admin1_code":"08",
    "gn:asciiname":"Sandaogang",
    "gn:country_code":"CN",
    "gn:dem":133,
    "gn:feature_class":"P",
    "gn:feature_code":"PPLA4",
    "gn:name":"Sandaogang",
    "gn:population":0,
    "gn:timezone":"Asia/Shanghai",
    "iso:country":"CN",
    "name:und_x_variant":[
        "San\u2019daoga",
        "San-tao-kang-ts\u2019un",
        "San-tao-kang",
        "Sandaogang",
        "Sandaogang Zhen"
    ],
    "name:zho_x_preferred":[
        "\u4e09\u9053\u5c97"
    ],
    "name:zho_x_variant":[
        "\u4e09\u9053\u5c97\u9547"
    ],
    "wof:name":"Sandaogang",
    "wof:placetype":"locality"
},
  "geometry": {"coordinates":[130.10378,46.11452],"type":"Point"}
}