{
  "type": "Feature",
  "properties": {
    "gn:admin1_code":"25",
    "gn:asciiname":"Maying",
    "gn:country_code":"CN",
    "gn:dem":42,
    "gn:feature_class":"P",
    "gn:feature_code":"PPL",
    "gn:name":"Maying",
    "gn:population":0,
    "gn:timezone":"Asia/Shanghai",
    "iso:country":"CN",
    "name:deu_x_preferred":[
        "Maying"
    ],
    "wof:name":"Maying",
    "wof:placetype":"locality"
},
  "geometry": {"coordinates":[116.01972000000001,35.80083],"type":"Point"}
}