{
  "type": "Feature",
  "properties": {
    "gn:admin1_code":"3.0",
    "gn:asciiname":"Xingangshan",
    "gn:country_code":"CN",
    "gn:dem":90,
    "gn:feature_class":"P",
    "gn:feature_code":"PPLA4",
    "gn:name":"Xingangshan",
    "gn:population":0,
    "gn:timezone":"Asia/Shanghai",
    "iso:country":"CN",
    "name:und_x_variant":[
        "\u65b0\u5c97\u5c71",
        "Xingangshan Zhen",
        "\u65b0\u5c97\u5c71\u9547"
    ],
    "wof:name":"Xingangshan",
    "wof:placetype":"locality"
},
  "geometry": {"coordinates":[117.94298000000001,29.10486],"type":"Point"}
}