{
  "type": "Feature",
  "properties": {
    "gn:admin1_code":"30.0",
    "gn:asciiname":"Shenziqian",
    "gn:country_code":"CN",
    "gn:dem":195,
    "gn:feature_class":"P",
    "gn:feature_code":"PPL",
    "gn:name":"Shenziqian",
    "gn:population":0,
    "gn:timezone":"Asia/Shanghai",
    "iso:country":"CN",
    "name:zho_x_preferred":[
        "\u795e\u5b50\u524d"
    ],
    "wof:name":"Shenziqian",
    "wof:placetype":"locality"
},
  "geometry": {"coordinates":[115.06999,23.75622000000001],"type":"Point"}
}