{
  "type": "Feature",
  "properties": {
    "gn:admin1_code":"12.0",
    "gn:asciiname":"Dayuanfen",
    "gn:country_code":"CN",
    "gn:dem":1337,
    "gn:feature_class":"P",
    "gn:feature_code":"PPL",
    "gn:name":"Dayuanfen",
    "gn:population":0,
    "gn:timezone":"Asia/Shanghai",
    "iso:country":"CN",
    "name:zho_x_preferred":[
        "\u5927\u56ed\u575f"
    ],
    "wof:name":"Dayuanfen",
    "wof:placetype":"locality"
},
  "geometry": {"coordinates":[109.93225,31.91999],"type":"Point"}
}