{
  "type": "Feature",
  "properties": {
    "gn:admin1_code":"24.0",
    "gn:asciiname":"Xincheng",
    "gn:country_code":"CN",
    "gn:dem":813,
    "gn:feature_class":"P",
    "gn:feature_code":"PPL",
    "gn:name":"Xincheng",
    "gn:population":0,
    "gn:timezone":"Asia/Shanghai",
    "iso:country":"CN",
    "name:und_x_variant":[
        "Hsin-ch\u2019eng-ts\u2019un",
        "Hsin-ch\u2019eng",
        "Xincheng"
    ],
    "name:zho_x_preferred":[
        "\u65b0\u57ce"
    ],
    "wof:name":"Xincheng",
    "wof:placetype":"locality"
},
  "geometry": {"coordinates":[112.53062,37.95393],"type":"Point"}
}