{
  "type": "Feature",
  "properties": {
    "gn:admin1_code":"14.0",
    "gn:asciiname":"Zhigung",
    "gn:cc2":"CN",
    "gn:country_code":"CN",
    "gn:dem":4235,
    "gn:feature_class":"P",
    "gn:feature_code":"PPL",
    "gn:name":"Zhigung",
    "gn:population":0,
    "gn:timezone":"Asia/Urumqi",
    "iso:country":"CN",
    "name:ara_x_preferred":[
        "\u062c\u064a\u063a\u0648\u0646\u063a"
    ],
    "name:msa_x_preferred":[
        "Zhigung"
    ],
    "name:und_x_variant":[
        "Chih-k\u2019ung",
        "Zhigung"
    ],
    "wof:name":"Zhigung",
    "wof:placetype":"locality"
},
  "geometry": {"coordinates":[91.83333,29.01667],"type":"Point"}
}