{
  "type": "Feature",
  "properties": {
    "gn:admin1_code":"19.0",
    "gn:asciiname":"Gushuzicun",
    "gn:country_code":"CN",
    "gn:dem":41,
    "gn:feature_class":"P",
    "gn:feature_code":"PPL",
    "gn:name":"Gushuzicun",
    "gn:population":0,
    "gn:timezone":"Asia/Shanghai",
    "iso:country":"CN",
    "name:zho_x_preferred":[
        "\u5b64\u6811\u5b50\u6751"
    ],
    "wof:name":"Gushuzicun",
    "wof:placetype":"locality"
},
  "geometry": {"coordinates":[122.89,42.1045],"type":"Point"}
}