{
  "type": "Feature",
  "properties": {
    "gn:admin1_code":"29.0",
    "gn:asciiname":"Jusiding",
    "gn:country_code":"CN",
    "gn:dem":3130,
    "gn:feature_class":"P",
    "gn:feature_code":"PPL",
    "gn:name":"Jusiding",
    "gn:population":0,
    "gn:timezone":"Asia/Shanghai",
    "iso:country":"CN",
    "name:zho_x_preferred":[
        "\u5177\u53f8\u9876"
    ],
    "wof:name":"Jusiding",
    "wof:placetype":"locality"
},
  "geometry": {"coordinates":[99.4615,28.0882],"type":"Point"}
}