{
  "type": "Feature",
  "properties": {
    "gn:admin1_code":"11.0",
    "gn:asciiname":"Fengshuping",
    "gn:country_code":"CN",
    "gn:dem":351,
    "gn:feature_class":"P",
    "gn:feature_code":"PPL",
    "gn:name":"Fengshuping",
    "gn:population":0,
    "gn:timezone":"Asia/Shanghai",
    "iso:country":"CN",
    "name:zho_x_preferred":[
        "\u67ab\u6811\u576a"
    ],
    "wof:name":"Fengshuping",
    "wof:placetype":"locality"
},
  "geometry": {"coordinates":[112.62393,26.09584],"type":"Point"}
}