{
  "type": "Feature",
  "properties": {
    "gn:admin1_code":"32.0",
    "gn:asciiname":"Jiankang",
    "gn:country_code":"CN",
    "gn:dem":506,
    "gn:feature_class":"P",
    "gn:feature_code":"PPL",
    "gn:name":"Jiankang",
    "gn:population":0,
    "gn:timezone":"Asia/Shanghai",
    "iso:country":"CN",
    "name:ceb_x_preferred":[
        "Jianye Qu"
    ],
    "name:fra_x_preferred":[
        "Jianye"
    ],
    "name:ind_x_preferred":[
        "Jiankang"
    ],
    "name:jpn_x_preferred":[
        "\u5efa\u5eb7"
    ],
    "name:kor_x_preferred":[
        "\uac74\uac15"
    ],
    "name:nld_x_preferred":[
        "Jiankang"
    ],
    "name:rus_x_preferred":[
        "\u0426\u0437\u044f\u043d\u044c\u043a\u0430\u043d"
    ],
    "name:spa_x_preferred":[
        "Jiankang"
    ],
    "name:urd_x_preferred":[
        "\u062c\u06cc\u0627\u0646\u06a9\u0627\u0646\u06af"
    ],
    "name:vie_x_preferred":[
        "Ki\u1ebfn Khang"
    ],
    "name:zho_x_preferred":[
        "\u5065\u5eb7"
    ],
    "name:zho_x_variant":[
        "\u516d\u671d\u5efa\u5eb7\u90fd\u57ce\u9057\u5740"
    ],
    "wof:name":"Jiankang",
    "wof:placetype":"locality"
},
  "geometry": {"coordinates":[104.21599999999999,30.5421],"type":"Point"}
}