{
  "type": "Feature",
  "properties": {
    "gn:admin1_code":"3.0",
    "gn:asciiname":"Xifancun",
    "gn:country_code":"CN",
    "gn:dem":42,
    "gn:feature_class":"P",
    "gn:feature_code":"PPL",
    "gn:name":"Xifancun",
    "gn:population":0,
    "gn:timezone":"Asia/Shanghai",
    "iso:country":"CN",
    "name:und_x_variant":[
        "\u897f\u51e1\u6751"
    ],
    "wof:name":"Xifancun",
    "wof:placetype":"locality"
},
  "geometry": {"coordinates":[115.84987,28.90688],"type":"Point"}
}