{
  "type": "Feature",
  "properties": {
    "gn:admin1_code":"26.0",
    "gn:asciiname":"Dengzhanman",
    "gn:country_code":"CN",
    "gn:dem":1337,
    "gn:feature_class":"P",
    "gn:feature_code":"PPL",
    "gn:name":"Dengzhanman",
    "gn:population":0,
    "gn:timezone":"Asia/Shanghai",
    "iso:country":"CN",
    "name:zho_x_preferred":[
        "\u706f\u76cf\u6ee1"
    ],
    "wof:name":"Dengzhanman",
    "wof:placetype":"locality"
},
  "geometry": {"coordinates":[108.37442,32.39911],"type":"Point"}
}