{
  "type": "Feature",
  "properties": {
    "gn:admin1_code":"20.0",
    "gn:asciiname":"Wuyicun",
    "gn:country_code":"CN",
    "gn:dem":551,
    "gn:feature_class":"P",
    "gn:feature_code":"PPL",
    "gn:name":"Wuyicun",
    "gn:population":0,
    "gn:timezone":"Asia/Shanghai",
    "iso:country":"CN",
    "name:zho_x_preferred":[
        "\u4e94\u4e00\u6751"
    ],
    "wof:name":"Wuyicun",
    "wof:placetype":"locality"
},
  "geometry": {"coordinates":[117.40773,49.15987],"type":"Point"}
}