{
  "type": "Feature",
  "properties": {
    "gn:admin1_code":"31.0",
    "gn:asciiname":"Maizao",
    "gn:country_code":"CN",
    "gn:dem":66,
    "gn:feature_class":"P",
    "gn:feature_code":"PPL",
    "gn:name":"Maizao",
    "gn:population":0,
    "gn:timezone":"Asia/Shanghai",
    "iso:country":"CN",
    "name:und_x_variant":[
        "\u8fc8\u9020"
    ],
    "wof:name":"Maizao",
    "wof:placetype":"locality"
},
  "geometry": {"coordinates":[109.87102,18.54031],"type":"Point"}
}