{
  "type": "Feature",
  "properties": {
    "gn:admin1_code":"4.0",
    "gn:asciiname":"Tongmingcun",
    "gn:country_code":"CN",
    "gn:dem":1,
    "gn:feature_class":"P",
    "gn:feature_code":"PPL",
    "gn:name":"Tongmingcun",
    "gn:population":0,
    "gn:timezone":"Asia/Shanghai",
    "iso:country":"CN",
    "name:zho_x_preferred":[
        "\u540c\u660e\u6751"
    ],
    "wof:name":"Tongmingcun",
    "wof:placetype":"locality"
},
  "geometry": {"coordinates":[120.34923999999999,32.71755],"type":"Point"}
}