{
  "type": "Feature",
  "properties": {
    "gn:admin1_code":"9.0",
    "gn:asciiname":"Jinxiaozhuang",
    "gn:country_code":"CN",
    "gn:dem":85,
    "gn:feature_class":"P",
    "gn:feature_code":"PPL",
    "gn:name":"Jinxiaozhuang",
    "gn:population":0,
    "gn:timezone":"Asia/Shanghai",
    "iso:country":"CN",
    "name:zho_x_preferred":[
        "\u9773\u5c0f\u5e84"
    ],
    "wof:name":"Jinxiaozhuang",
    "wof:placetype":"locality"
},
  "geometry": {"coordinates":[114.35137,36.20112],"type":"Point"}
}