{
  "type": "Feature",
  "properties": {
    "gn:admin1_code":"30",
    "gn:asciiname":"Shuangkou",
    "gn:country_code":"CN",
    "gn:dem":238,
    "gn:feature_class":"P",
    "gn:feature_code":"PPL",
    "gn:name":"Shuangkou",
    "gn:population":0,
    "gn:timezone":"Asia/Shanghai",
    "iso:country":"CN",
    "name:und_x_variant":[
        "Shuangkou"
    ],
    "name:zho_x_preferred":[
        "\u53cc\u53e3"
    ],
    "wof:name":"Shuangkou",
    "wof:placetype":"locality"
},
  "geometry": {"coordinates":[115.95739,24.19919],"type":"Point"}
}