{
  "type": "Feature",
  "properties": {
    "gn:admin1_code":"32.0",
    "gn:asciiname":"Jingtizi",
    "gn:country_code":"CN",
    "gn:dem":759,
    "gn:feature_class":"P",
    "gn:feature_code":"PPL",
    "gn:name":"Jingtizi",
    "gn:population":0,
    "gn:timezone":"Asia/Shanghai",
    "iso:country":"CN",
    "name:zho_x_preferred":[
        "\u4e95\u68af\u5b50"
    ],
    "wof:name":"Jingtizi",
    "wof:placetype":"locality"
},
  "geometry": {"coordinates":[105.149,32.1735],"type":"Point"}
}