{
  "type": "Feature",
  "properties": {
    "gn:admin1_code":"20",
    "gn:asciiname":"Baochang",
    "gn:country_code":"CN",
    "gn:dem":1456,
    "gn:feature_class":"P",
    "gn:feature_code":"PPLA3",
    "gn:name":"Baochang",
    "gn:population":0,
    "gn:timezone":"Asia/Shanghai",
    "iso:country":"CN",
    "name:und_x_variant":[
        "Koting",
        "T\u2019ai-p\u2019u-ssu-ch\u2019i",
        "Pao-ch\u2019ang",
        "Taibusi Qi",
        "Pao-ch\u2019ang-chen",
        "Pao-ch\u2019ang-hsien",
        "Baochang",
        "\u5b9d\u660c",
        "Taipusi Qi",
        "Baochang Zhen",
        "\u5b9d\u660c\u9547",
        "\u592a\u4ec6\u5bfa\u65d7"
    ],
    "wof:name":"Baochang",
    "wof:placetype":"locality"
},
  "geometry": {"coordinates":[115.27889,41.88444000000001],"type":"Point"}
}