{
  "type": "Feature",
  "properties": {
    "gn:admin1_code":"11",
    "gn:asciiname":"Zhangjiang",
    "gn:country_code":"CN",
    "gn:dem":46,
    "gn:feature_class":"P",
    "gn:feature_code":"PPLA3",
    "gn:name":"Zhangjiang",
    "gn:population":0,
    "gn:timezone":"Asia/Shanghai",
    "iso:country":"CN",
    "name:und_x_variant":[
        "Taoyuan",
        "Zhangjiang",
        "Zhangjiang Zhen",
        "Taoyuan Xian",
        "\u6f33\u6c5f\u9547",
        "\u6843\u6e90\u53bf",
        "\u6843\u6e90"
    ],
    "name:zho_x_preferred":[
        "T\u2019ao-y\u00fcan-hsien"
    ],
    "name:zho_x_variant":[
        "\u6f33\u6c5f"
    ],
    "wof:name":"Zhangjiang",
    "wof:placetype":"locality"
},
  "geometry": {"coordinates":[111.4799,28.91103],"type":"Point"}
}