{
  "type": "Feature",
  "properties": {
    "gn:admin1_code":"25.0",
    "gn:asciiname":"Chugezhuang",
    "gn:country_code":"CN",
    "gn:dem":178,
    "gn:feature_class":"P",
    "gn:feature_code":"PPL",
    "gn:name":"Chugezhuang",
    "gn:population":0,
    "gn:timezone":"Asia/Shanghai",
    "iso:country":"CN",
    "name:zho_x_preferred":[
        "\u521d\u683c\u5e84"
    ],
    "wof:name":"Chugezhuang",
    "wof:placetype":"locality"
},
  "geometry": {"coordinates":[120.99475,37.57464],"type":"Point"}
}