{
  "type": "Feature",
  "properties": {
    "gn:admin1_code":"29.0",
    "gn:asciiname":"Huangjiashan",
    "gn:country_code":"CN",
    "gn:dem":2216,
    "gn:feature_class":"P",
    "gn:feature_code":"PPL",
    "gn:name":"Huangjiashan",
    "gn:population":0,
    "gn:timezone":"Asia/Shanghai",
    "iso:country":"CN",
    "name:und_x_variant":[
        "\u9ec4\u5bb6\u5c71"
    ],
    "wof:name":"Huangjiashan",
    "wof:placetype":"locality"
},
  "geometry": {"coordinates":[103.52800000000001,27.1071],"type":"Point"}
}