{
  "type": "Feature",
  "properties": {
    "gn:admin1_code":"12.0",
    "gn:asciiname":"Xiaomei Lingbei",
    "gn:country_code":"CN",
    "gn:dem":108,
    "gn:feature_class":"P",
    "gn:feature_code":"PPL",
    "gn:name":"Xiaomei Lingbei",
    "gn:population":0,
    "gn:timezone":"Asia/Shanghai",
    "iso:country":"CN",
    "name:zho_x_preferred":[
        "Xiaomei Lingbei"
    ],
    "name:zho_x_variant":[
        "\u5c0f\u6885\u5cad\u80cc"
    ],
    "wof:name":"Xiaomei Lingbei",
    "wof:placetype":"locality"
},
  "geometry": {"coordinates":[114.23336,29.43089],"type":"Point"}
}