{
  "type": "Feature",
  "properties": {
    "gn:admin1_code":"9.0",
    "gn:asciiname":"Sihegou",
    "gn:country_code":"CN",
    "gn:dem":267,
    "gn:feature_class":"P",
    "gn:feature_code":"PPL",
    "gn:name":"Sihegou",
    "gn:population":0,
    "gn:timezone":"Asia/Shanghai",
    "iso:country":"CN",
    "name:zho_x_preferred":[
        "\u5bfa\u6cb3\u6c9f"
    ],
    "wof:name":"Sihegou",
    "wof:placetype":"locality"
},
  "geometry": {"coordinates":[113.50493,34.56234],"type":"Point"}
}