{
  "type": "Feature",
  "properties": {
    "gn:admin1_code":"26.0",
    "gn:asciiname":"Yangjiahe",
    "gn:country_code":"CN",
    "gn:dem":1638,
    "gn:feature_class":"P",
    "gn:feature_code":"PPL",
    "gn:name":"Yangjiahe",
    "gn:population":0,
    "gn:timezone":"Asia/Shanghai",
    "iso:country":"CN",
    "name:und_x_variant":[
        "\u6768\u5bb6\u6cb3"
    ],
    "wof:name":"Yangjiahe",
    "wof:placetype":"locality"
},
  "geometry": {"coordinates":[106.84461,33.8022],"type":"Point"}
}