{
  "type": "Feature",
  "properties": {
    "gn:admin1_code":"12.0",
    "gn:asciiname":"Yaoyanwan",
    "gn:country_code":"CN",
    "gn:dem":141,
    "gn:feature_class":"P",
    "gn:feature_code":"PPL",
    "gn:name":"Yaoyanwan",
    "gn:population":0,
    "gn:timezone":"Asia/Shanghai",
    "iso:country":"CN",
    "name:zho_x_preferred":[
        "\u7a91\u5830\u6e7e"
    ],
    "wof:name":"Yaoyanwan",
    "wof:placetype":"locality"
},
  "geometry": {"coordinates":[112.01692,31.06837],"type":"Point"}
}