{
  "type": "Feature",
  "properties": {
    "gn:admin1_code":"29.0",
    "gn:asciiname":"Wenwuzhai",
    "gn:country_code":"CN",
    "gn:dem":1707,
    "gn:feature_class":"P",
    "gn:feature_code":"PPL",
    "gn:name":"Wenwuzhai",
    "gn:population":0,
    "gn:timezone":"Asia/Shanghai",
    "iso:country":"CN",
    "name:zho_x_preferred":[
        "\u6587\u6b66\u5be8"
    ],
    "wof:name":"Wenwuzhai",
    "wof:placetype":"locality"
},
  "geometry": {"coordinates":[101.65300000000001,23.041],"type":"Point"}
}