{
  "type": "Feature",
  "properties": {
    "gn:admin1_code":"15.0",
    "gn:asciiname":"Shangshuicha",
    "gn:country_code":"CN",
    "gn:dem":2030,
    "gn:feature_class":"P",
    "gn:feature_code":"PPL",
    "gn:name":"Shangshuicha",
    "gn:population":0,
    "gn:timezone":"Asia/Shanghai",
    "iso:country":"CN",
    "name:und_x_variant":[
        "\u4e0a\u6c34\u5c94"
    ],
    "wof:name":"Shangshuicha",
    "wof:placetype":"locality"
},
  "geometry": {"coordinates":[105.24382,35.67015],"type":"Point"}
}