{
  "type": "Feature",
  "properties": {
    "gn:admin1_code":"15.0",
    "gn:asciiname":"Xihu",
    "gn:country_code":"CN",
    "gn:dem":1072,
    "gn:feature_class":"P",
    "gn:feature_code":"PPLA4",
    "gn:name":"Xihu",
    "gn:population":0,
    "gn:timezone":"Asia/Urumqi",
    "iso:country":"CN",
    "name:und_x_variant":[
        "Xihu Xiang"
    ],
    "name:zho_x_preferred":[
        "\u897f\u6e56"
    ],
    "name:zho_x_variant":[
        "\u897f\u6e56\u4e61"
    ],
    "wof:name":"Xihu",
    "wof:placetype":"locality"
},
  "geometry": {"coordinates":[94.99059,40.5385],"type":"Point"}
}