{
  "type": "Feature",
  "properties": {
    "gn:admin1_code":"29.0",
    "gn:asciiname":"Dongdao",
    "gn:country_code":"CN",
    "gn:dem":2435,
    "gn:feature_class":"P",
    "gn:feature_code":"PPL",
    "gn:name":"Dongdao",
    "gn:population":0,
    "gn:timezone":"Asia/Shanghai",
    "iso:country":"CN",
    "name:zho_x_preferred":[
        "\u61c2\u5200"
    ],
    "wof:name":"Dongdao",
    "wof:placetype":"locality"
},
  "geometry": {"coordinates":[102.354,25.9182],"type":"Point"}
}