{
  "type": "Feature",
  "properties": {
    "gn:admin1_code":"32.0",
    "gn:asciiname":"Luobigong",
    "gn:country_code":"CN",
    "gn:dem":3696,
    "gn:feature_class":"P",
    "gn:feature_code":"PPL",
    "gn:name":"Luobigong",
    "gn:population":0,
    "gn:timezone":"Asia/Shanghai",
    "iso:country":"CN",
    "name:zho_x_preferred":[
        "\u6d1b\u5fc5\u8d21"
    ],
    "wof:name":"Luobigong",
    "wof:placetype":"locality"
},
  "geometry": {"coordinates":[99.0227,30.159],"type":"Point"}
}