{
  "type": "Feature",
  "properties": {
    "gn:admin1_code":"15.0",
    "gn:asciiname":"Gutang",
    "gn:country_code":"CN",
    "gn:dem":1777,
    "gn:feature_class":"P",
    "gn:feature_code":"PPL",
    "gn:name":"Gutang",
    "gn:population":0,
    "gn:timezone":"Asia/Shanghai",
    "iso:country":"CN",
    "name:und_x_variant":[
        "\u53e4\u5858"
    ],
    "wof:name":"Gutang",
    "wof:placetype":"locality"
},
  "geometry": {"coordinates":[105.2197,33.89842],"type":"Point"}
}