{
  "type": "Feature",
  "properties": {
    "gn:admin1_code":"10",
    "gn:asciiname":"Haomenling",
    "gn:country_code":"CN",
    "gn:dem":1039,
    "gn:feature_class":"P",
    "gn:feature_code":"PPL",
    "gn:name":"Haomenling",
    "gn:population":0,
    "gn:timezone":"Asia/Shanghai",
    "iso:country":"CN",
    "name:zho_x_preferred":[
        "\u6d69\u95e8\u5cad"
    ],
    "wof:name":"Haomenling",
    "wof:placetype":"locality"
},
  "geometry": {"coordinates":[115.81522,40.83143],"type":"Point"}
}