{
  "type": "Feature",
  "properties": {
    "gn:admin1_code":"32.0",
    "gn:asciiname":"Xindou",
    "gn:country_code":"CN",
    "gn:dem":3185,
    "gn:feature_class":"P",
    "gn:feature_code":"PPLA3",
    "gn:name":"Xindou",
    "gn:population":0,
    "gn:timezone":"Asia/Shanghai",
    "iso:country":"CN",
    "name:und_x_variant":[
        "Zhaggo",
        "Laojie",
        "Drango",
        "Chango",
        "Lukho",
        "Chang",
        "Luhuo",
        "Chiu-lu-ho",
        "Lu-ho",
        "Changku",
        "Dango Gomba",
        "Xindou",
        "Xindou Zhen"
    ],
    "name:zho_x_preferred":[
        "\u65b0\u90fd"
    ],
    "name:zho_x_variant":[
        "\u65b0\u90fd\u9547"
    ],
    "wof:name":"Xindou",
    "wof:placetype":"locality"
},
  "geometry": {"coordinates":[100.67847,31.39648],"type":"Point"}
}