{
  "type": "Feature",
  "properties": {
    "gn:admin1_code":"26.0",
    "gn:asciiname":"Fenglihecun",
    "gn:country_code":"CN",
    "gn:dem":965,
    "gn:feature_class":"P",
    "gn:feature_code":"PPL",
    "gn:name":"Fenglihecun",
    "gn:population":0,
    "gn:timezone":"Asia/Shanghai",
    "iso:country":"CN",
    "name:zho_x_preferred":[
        "\u51af\u674e\u6cb3\u6751"
    ],
    "wof:name":"Fenglihecun",
    "wof:placetype":"locality"
},
  "geometry": {"coordinates":[109.49021999999999,35.72045],"type":"Point"}
}