{
  "type": "Feature",
  "properties": {
    "gn:admin1_code":"2.0",
    "gn:asciiname":"Shengjiabang",
    "gn:country_code":"CN",
    "gn:dem":4,
    "gn:feature_class":"P",
    "gn:feature_code":"PPL",
    "gn:name":"Shengjiabang",
    "gn:population":0,
    "gn:timezone":"Asia/Shanghai",
    "iso:country":"CN",
    "name:zho_x_preferred":[
        "\u76db\u5bb6\u6d5c"
    ],
    "wof:name":"Shengjiabang",
    "wof:placetype":"locality"
},
  "geometry": {"coordinates":[121.17192,30.70508],"type":"Point"}
}