{
  "type": "Feature",
  "properties": {
    "gn:admin1_code":"30.0",
    "gn:asciiname":"Qimashi",
    "gn:country_code":"CN",
    "gn:dem":110,
    "gn:feature_class":"P",
    "gn:feature_code":"PPL",
    "gn:name":"Qimashi",
    "gn:population":0,
    "gn:timezone":"Asia/Shanghai",
    "iso:country":"CN",
    "name:zho_x_preferred":[
        "\u9a91\u9a6c\u77f3"
    ],
    "wof:name":"Qimashi",
    "wof:placetype":"locality"
},
  "geometry": {"coordinates":[113.78765,24.79657000000001],"type":"Point"}
}