{
  "type": "Feature",
  "properties": {
    "gn:admin1_code":"21.0",
    "gn:asciiname":"Hajia Zhuangzi",
    "gn:country_code":"CN",
    "gn:dem":2038,
    "gn:feature_class":"P",
    "gn:feature_code":"PPL",
    "gn:name":"Hajia Zhuangzi",
    "gn:population":0,
    "gn:timezone":"Asia/Shanghai",
    "iso:country":"CN",
    "name:zho_x_preferred":[
        "\u54c8\u5bb6\u5e84\u5b50"
    ],
    "wof:name":"Hajia Zhuangzi",
    "wof:placetype":"locality"
},
  "geometry": {"coordinates":[105.61199999999999,36.5193],"type":"Point"}
}