{
  "type": "Feature",
  "properties": {
    "gn:admin1_code":"26",
    "gn:asciiname":"Ganqiaomiao",
    "gn:country_code":"CN",
    "gn:dem":1021,
    "gn:feature_class":"P",
    "gn:feature_code":"PPL",
    "gn:name":"Ganqiaomiao",
    "gn:population":0,
    "gn:timezone":"Asia/Shanghai",
    "iso:country":"CN",
    "wof:name":"Ganqiaomiao",
    "wof:placetype":"locality"
},
  "geometry": {"coordinates":[108.97972,35.09944],"type":"Point"}
}