{
  "type": "Feature",
  "properties": {
    "gn:admin1_code":"2.0",
    "gn:asciiname":"Zhentangdian",
    "gn:country_code":"CN",
    "gn:dem":12,
    "gn:feature_class":"P",
    "gn:feature_code":"PPL",
    "gn:name":"Zhentangdian",
    "gn:population":0,
    "gn:timezone":"Asia/Shanghai",
    "iso:country":"CN",
    "name:und_x_variant":[
        "\u9547\u5858\u6bbf"
    ],
    "wof:name":"Zhentangdian",
    "wof:placetype":"locality"
},
  "geometry": {"coordinates":[120.68678,30.09],"type":"Point"}
}