{
  "type": "Feature",
  "properties": {
    "gn:admin1_code":"25.0",
    "gn:asciiname":"Jiaogezhuang",
    "gn:country_code":"CN",
    "gn:dem":9,
    "gn:feature_class":"P",
    "gn:feature_code":"PPL",
    "gn:name":"Jiaogezhuang",
    "gn:population":0,
    "gn:timezone":"Asia/Shanghai",
    "iso:country":"CN",
    "name:zho_x_preferred":[
        "\u77eb\u683c\u5e84"
    ],
    "wof:name":"Jiaogezhuang",
    "wof:placetype":"locality"
},
  "geometry": {"coordinates":[120.82680999999999,37.80154],"type":"Point"}
}