{
  "type": "Feature",
  "properties": {
    "gn:admin1_code":"11.0",
    "gn:asciiname":"Lianpenggang",
    "gn:country_code":"CN",
    "gn:dem":73,
    "gn:feature_class":"P",
    "gn:feature_code":"PPL",
    "gn:name":"Lianpenggang",
    "gn:population":0,
    "gn:timezone":"Asia/Shanghai",
    "iso:country":"CN",
    "name:zho_x_preferred":[
        "Lianpenggang"
    ],
    "name:zho_x_variant":[
        "\u83b2\u84ec\u5c97"
    ],
    "wof:name":"Lianpenggang",
    "wof:placetype":"locality"
},
  "geometry": {"coordinates":[111.53731999999999,29.20608],"type":"Point"}
}