{
  "type": "Feature",
  "properties": {
    "gn:admin1_code":"20.0",
    "gn:asciiname":"Xiaoxinliqi",
    "gn:country_code":"CN",
    "gn:dem":423,
    "gn:feature_class":"P",
    "gn:feature_code":"PPL",
    "gn:name":"Xiaoxinliqi",
    "gn:population":0,
    "gn:timezone":"Asia/Shanghai",
    "iso:country":"CN",
    "name:zho_x_preferred":[
        "\u5c0f\u65b0\u529b\u5947"
    ],
    "wof:name":"Xiaoxinliqi",
    "wof:placetype":"locality"
},
  "geometry": {"coordinates":[123.08007000000001,49.04701],"type":"Point"}
}