{
  "type": "Feature",
  "properties": {
    "gn:admin1_code":"19.0",
    "gn:asciiname":"Xiaoyanchang",
    "gn:country_code":"CN",
    "gn:dem":4,
    "gn:feature_class":"P",
    "gn:feature_code":"PPL",
    "gn:name":"Xiaoyanchang",
    "gn:population":0,
    "gn:timezone":"Asia/Shanghai",
    "iso:country":"CN",
    "name:zho_x_preferred":[
        "\u5c0f\u76d0\u573a"
    ],
    "wof:name":"Xiaoyanchang",
    "wof:placetype":"locality"
},
  "geometry": {"coordinates":[121.75700000000001,39.3261],"type":"Point"}
}