{
  "type": "Feature",
  "properties": {
    "gn:admin1_code":"8.0",
    "gn:asciiname":"Fu'an Canchangtun",
    "gn:country_code":"CN",
    "gn:dem":185,
    "gn:feature_class":"P",
    "gn:feature_code":"PPL",
    "gn:name":"Fu\u2019an Canchangtun",
    "gn:population":0,
    "gn:timezone":"Asia/Shanghai",
    "iso:country":"CN",
    "name:und_x_variant":[
        "Fu\u2019an Canchangtun"
    ],
    "name:zho_x_preferred":[
        "\u5bcc\u5b89\u8695\u573a\u5c6f"
    ],
    "wof:name":"Fu'an Canchangtun",
    "wof:placetype":"locality"
},
  "geometry": {"coordinates":[131.22921000000002,46.62528],"type":"Point"}
}