{
  "type": "Feature",
  "properties": {
    "gn:admin1_code":"8.0",
    "gn:asciiname":"Dacaofang",
    "gn:country_code":"CN",
    "gn:dem":142,
    "gn:feature_class":"P",
    "gn:feature_code":"PPL",
    "gn:name":"Dacaofang",
    "gn:population":0,
    "gn:timezone":"Asia/Shanghai",
    "iso:country":"CN",
    "name:zho_x_preferred":[
        "\u5927\u8349\u623f"
    ],
    "wof:name":"Dacaofang",
    "wof:placetype":"locality"
},
  "geometry": {"coordinates":[124.38406000000001,46.97686],"type":"Point"}
}