{
  "type": "Feature",
  "properties": {
    "gn:admin1_code":"32.0",
    "gn:asciiname":"Zhangren",
    "gn:country_code":"CN",
    "gn:dem":2669,
    "gn:feature_class":"P",
    "gn:feature_code":"PPL",
    "gn:name":"Zhangren",
    "gn:population":0,
    "gn:timezone":"Asia/Shanghai",
    "iso:country":"CN",
    "name:zho_x_preferred":[
        "\u5f20\u4ec1"
    ],
    "wof:name":"Zhangren",
    "wof:placetype":"locality"
},
  "geometry": {"coordinates":[99.1489,28.7415],"type":"Point"}
}