{
  "type": "Feature",
  "properties": {
    "gn:admin1_code":"12",
    "gn:asciiname":"Luoqiao",
    "gn:country_code":"CN",
    "gn:dem":18,
    "gn:feature_class":"P",
    "gn:feature_code":"PPLA4",
    "gn:name":"Luoqiao",
    "gn:population":0,
    "gn:timezone":"Asia/Shanghai",
    "iso:country":"CN",
    "name:und_x_variant":[
        "\u7f57\u6865",
        "Luoqiao Jiedao",
        "\u7f57\u6865\u8857\u9053"
    ],
    "wof:name":"Luoqiao",
    "wof:placetype":"locality"
},
  "geometry": {"coordinates":[114.95426,30.14678],"type":"Point"}
}