{
  "type": "Feature",
  "properties": {
    "gn:admin1_code":"20.0",
    "gn:asciiname":"Tarigen Baolige",
    "gn:country_code":"CN",
    "gn:dem":699,
    "gn:feature_class":"P",
    "gn:feature_code":"PPL",
    "gn:name":"Tarigen Baolige",
    "gn:population":0,
    "gn:timezone":"Asia/Shanghai",
    "iso:country":"CN",
    "name:zho_x_preferred":[
        "\u5854\u65e5\u6839\u5b9d\u529b\u683c"
    ],
    "wof:name":"Tarigen Baolige",
    "wof:placetype":"locality"
},
  "geometry": {"coordinates":[118.57437,48.17579],"type":"Point"}
}