{
  "type": "Feature",
  "properties": {
    "gn:admin1_code":"26.0",
    "gn:asciiname":"Wuzhaifu",
    "gn:country_code":"CN",
    "gn:dem":431,
    "gn:feature_class":"P",
    "gn:feature_code":"PPL",
    "gn:name":"Wuzhaifu",
    "gn:population":0,
    "gn:timezone":"Asia/Shanghai",
    "iso:country":"CN",
    "name:zho_x_preferred":[
        "\u6b66\u5be8\u5e9c"
    ],
    "wof:name":"Wuzhaifu",
    "wof:placetype":"locality"
},
  "geometry": {"coordinates":[108.84985,34.57743],"type":"Point"}
}