{
  "type": "Feature",
  "properties": {
    "gn:admin1_code":"26.0",
    "gn:asciiname":"Goulinba",
    "gn:country_code":"CN",
    "gn:dem":1128,
    "gn:feature_class":"P",
    "gn:feature_code":"PPL",
    "gn:name":"Goulinba",
    "gn:population":0,
    "gn:timezone":"Asia/Shanghai",
    "iso:country":"CN",
    "name:und_x_variant":[
        "\u6784\u6797\u575d"
    ],
    "wof:name":"Goulinba",
    "wof:placetype":"locality"
},
  "geometry": {"coordinates":[105.93149,33.46295],"type":"Point"}
}