{
  "type": "Feature",
  "properties": {
    "gn:admin1_code":"1.0",
    "gn:asciiname":"Xiaohan",
    "gn:country_code":"CN",
    "gn:dem":32,
    "gn:feature_class":"P",
    "gn:feature_code":"PPL",
    "gn:name":"Xiaohan",
    "gn:population":0,
    "gn:timezone":"Asia/Shanghai",
    "iso:country":"CN",
    "name:afr_x_preferred":[
        "Xiaohan"
    ],
    "name:cdo_x_preferred":[
        "Si\u0113u-h\u00e0ng"
    ],
    "name:fra_x_preferred":[
        "Xiaohan"
    ],
    "name:hak_x_preferred":[
        "S\u00e9u-h\u00f2n"
    ],
    "name:swe_x_preferred":[
        "Xiaohan"
    ],
    "name:vie_x_preferred":[
        "Ti\u1ec3u h\u00e0n"
    ],
    "name:zha_x_preferred":[
        "Siujhanz"
    ],
    "name:zho_x_preferred":[
        "\u8096\u57be"
    ],
    "wof:name":"Xiaohan",
    "wof:placetype":"locality"
},
  "geometry": {"coordinates":[118.64051000000001,31.07456],"type":"Point"}
}