{
  "type": "Feature",
  "properties": {
    "gn:admin1_code":"29.0",
    "gn:asciiname":"Nanshan",
    "gn:country_code":"CN",
    "gn:dem":2529,
    "gn:feature_class":"P",
    "gn:feature_code":"PPL",
    "gn:name":"Nanshan",
    "gn:population":0,
    "gn:timezone":"Asia/Shanghai",
    "iso:country":"CN",
    "name:zho_x_preferred":[
        "\u5357\u5c71"
    ],
    "wof:name":"Nanshan",
    "wof:placetype":"locality"
},
  "geometry": {"coordinates":[100.318,26.5043],"type":"Point"}
}