{
  "type": "Feature",
  "properties": {
    "gn:admin1_code":"4.0",
    "gn:asciiname":"Lujiashan",
    "gn:country_code":"CN",
    "gn:dem":37,
    "gn:feature_class":"P",
    "gn:feature_code":"PPL",
    "gn:name":"L\u00fcjiashan",
    "gn:population":0,
    "gn:timezone":"Asia/Shanghai",
    "iso:country":"CN",
    "name:und_x_variant":[
        "L\u00fcjiashan"
    ],
    "name:zho_x_preferred":[
        "\u5415\u5bb6\u5c71"
    ],
    "wof:name":"Lujiashan",
    "wof:placetype":"locality"
},
  "geometry": {"coordinates":[119.1387,31.64582],"type":"Point"}
}