{
  "type": "Feature",
  "properties": {
    "gn:admin1_code":"19.0",
    "gn:asciiname":"Xiapozi",
    "gn:country_code":"CN",
    "gn:dem":275,
    "gn:feature_class":"P",
    "gn:feature_code":"PPL",
    "gn:name":"Xiapozi",
    "gn:population":0,
    "gn:timezone":"Asia/Shanghai",
    "iso:country":"CN",
    "name:zho_x_preferred":[
        "\u4e0b\u5761\u5b50"
    ],
    "wof:name":"Xiapozi",
    "wof:placetype":"locality"
},
  "geometry": {"coordinates":[119.996,40.772],"type":"Point"}
}