{
  "type": "Feature",
  "properties": {
    "gn:admin1_code":"19.0",
    "gn:asciiname":"Xilinggou",
    "gn:country_code":"CN",
    "gn:dem":464,
    "gn:feature_class":"P",
    "gn:feature_code":"PPL",
    "gn:name":"Xilinggou",
    "gn:population":0,
    "gn:timezone":"Asia/Shanghai",
    "iso:country":"CN",
    "name:zho_x_preferred":[
        "\u897f\u5cad\u6c9f"
    ],
    "wof:name":"Xilinggou",
    "wof:placetype":"locality"
},
  "geometry": {"coordinates":[125.20999999999999,41.6327],"type":"Point"}
}