{
  "type": "Feature",
  "properties": {
    "gn:admin1_code":"29.0",
    "gn:asciiname":"Mu'aizhai",
    "gn:country_code":"CN",
    "gn:dem":1481,
    "gn:feature_class":"P",
    "gn:feature_code":"PPL",
    "gn:name":"Mu\u2019aizhai",
    "gn:population":0,
    "gn:timezone":"Asia/Shanghai",
    "iso:country":"CN",
    "name:und_x_variant":[
        "Mu\u2019aizhai"
    ],
    "name:zho_x_preferred":[
        "\u6728\u827e\u5be8"
    ],
    "wof:name":"Mu'aizhai",
    "wof:placetype":"locality"
},
  "geometry": {"coordinates":[98.2757,24.185],"type":"Point"}
}