{
  "type": "Feature",
  "properties": {
    "gn:admin1_code":"20.0",
    "gn:asciiname":"Bo'erke",
    "gn:country_code":"CN",
    "gn:dem":268,
    "gn:feature_class":"P",
    "gn:feature_code":"PPL",
    "gn:name":"Bo\u2019erke",
    "gn:population":0,
    "gn:timezone":"Asia/Shanghai",
    "iso:country":"CN",
    "name:und_x_variant":[
        "Bo\u2019erke"
    ],
    "name:zho_x_preferred":[
        "\u4f2f\u5c14\u79d1"
    ],
    "wof:name":"Bo'erke",
    "wof:placetype":"locality"
},
  "geometry": {"coordinates":[123.95458000000001,48.78917],"type":"Point"}
}