{
  "type": "Feature",
  "properties": {
    "gn:admin1_code":"25",
    "gn:asciiname":"Jiantouji",
    "gn:cc2":"CN",
    "gn:country_code":"CN",
    "gn:dem":37,
    "gn:feature_class":"P",
    "gn:feature_code":"PPL",
    "gn:name":"Jiantouji",
    "gn:population":0,
    "gn:timezone":"Asia/Shanghai",
    "iso:country":"CN",
    "name:und_x_variant":[
        "Chien-t\u2019ou-chi",
        "Jiantou",
        "Jiantouji"
    ],
    "wof:name":"Jiantouji",
    "wof:placetype":"locality"
},
  "geometry": {"coordinates":[117.53333000000001,34.55],"type":"Point"}
}