{
  "type": "Feature",
  "properties": {
    "gn:admin1_code":"3.0",
    "gn:asciiname":"Gudang",
    "gn:country_code":"CN",
    "gn:dem":237,
    "gn:feature_class":"P",
    "gn:feature_code":"PPL",
    "gn:name":"Gudang",
    "gn:population":0,
    "gn:timezone":"Asia/Shanghai",
    "iso:country":"CN",
    "name:und_x_variant":[
        "\u53e4\u515a"
    ],
    "wof:name":"Gudang",
    "wof:placetype":"locality"
},
  "geometry": {"coordinates":[116.15284,26.13548],"type":"Point"}
}