{
  "type": "Feature",
  "properties": {
    "gn:admin1_code":"2",
    "gn:asciiname":"Xianrenqiao",
    "gn:country_code":"CN",
    "gn:dem":381,
    "gn:feature_class":"P",
    "gn:feature_code":"PPL",
    "gn:name":"Xianrenqiao",
    "gn:population":0,
    "gn:timezone":"Asia/Shanghai",
    "iso:country":"CN",
    "name:und_x_variant":[
        "\u4ed9\u4eba\u6865"
    ],
    "name:zho_x_preferred":[
        "\u4ed9\u4eba\u6865"
    ],
    "wof:name":"Xianrenqiao",
    "wof:placetype":"locality"
},
  "geometry": {"coordinates":[121.20111,29.00944],"type":"Point"}
}