{
  "type": "Feature",
  "properties": {
    "gn:admin1_code":"8.0",
    "gn:asciiname":"Wukeshu",
    "gn:country_code":"CN",
    "gn:dem":77,
    "gn:feature_class":"P",
    "gn:feature_code":"PPL",
    "gn:name":"Wukeshu",
    "gn:population":0,
    "gn:timezone":"Asia/Shanghai",
    "iso:country":"CN",
    "name:zho_x_preferred":[
        "\u4e94\u68f5\u6811"
    ],
    "wof:name":"Wukeshu",
    "wof:placetype":"locality"
},
  "geometry": {"coordinates":[132.60235,45.40784],"type":"Point"}
}