{
  "type": "Feature",
  "properties": {
    "gn:admin1_code":"11.0",
    "gn:asciiname":"Maziqiao",
    "gn:country_code":"CN",
    "gn:dem":128,
    "gn:feature_class":"P",
    "gn:feature_code":"PPL",
    "gn:name":"Maziqiao",
    "gn:population":0,
    "gn:timezone":"Asia/Shanghai",
    "iso:country":"CN",
    "name:zho_x_preferred":[
        "\u9a6c\u5b50\u6865"
    ],
    "wof:name":"Maziqiao",
    "wof:placetype":"locality"
},
  "geometry": {"coordinates":[110.12902,28.05721],"type":"Point"}
}