{
  "type": "Feature",
  "properties": {
    "gn:admin1_code":"4.0",
    "gn:asciiname":"Xixicun",
    "gn:country_code":"CN",
    "gn:dem":1,
    "gn:feature_class":"P",
    "gn:feature_code":"PPL",
    "gn:name":"Xixicun",
    "gn:population":0,
    "gn:timezone":"Asia/Shanghai",
    "iso:country":"CN",
    "name:zho_x_preferred":[
        "\u897f\u6eaa\u6751"
    ],
    "wof:name":"Xixicun",
    "wof:placetype":"locality"
},
  "geometry": {"coordinates":[119.64069000000001,33.18872],"type":"Point"}
}