{
  "type": "Feature",
  "properties": {
    "gn:admin1_code":"4.0",
    "gn:asciiname":"Dongxu",
    "gn:country_code":"CN",
    "gn:dem":1,
    "gn:feature_class":"P",
    "gn:feature_code":"PPL",
    "gn:name":"Dongxu",
    "gn:population":0,
    "gn:timezone":"Asia/Shanghai",
    "iso:country":"CN",
    "name:zho_x_preferred":[
        "Dongxu"
    ],
    "name:zho_x_variant":[
        "\u4e1c\u5729"
    ],
    "wof:name":"Dongxu",
    "wof:placetype":"locality"
},
  "geometry": {"coordinates":[119.55231999999999,34.47131],"type":"Point"}
}