{
  "type": "Feature",
  "properties": {
    "gn:admin1_code":"16.0",
    "gn:asciiname":"Yunluo",
    "gn:country_code":"CN",
    "gn:dem":88,
    "gn:feature_class":"P",
    "gn:feature_code":"PPL",
    "gn:name":"Yunluo",
    "gn:population":0,
    "gn:timezone":"Asia/Shanghai",
    "iso:country":"CN",
    "name:zho_x_preferred":[
        "\u4e91\u7f57"
    ],
    "wof:name":"Yunluo",
    "wof:placetype":"locality"
},
  "geometry": {"coordinates":[110.53400000000001,22.2223],"type":"Point"}
}