{
  "type": "Feature",
  "properties": {
    "gn:admin1_code":"32.0",
    "gn:asciiname":"Gumuluo",
    "gn:country_code":"CN",
    "gn:dem":2600,
    "gn:feature_class":"P",
    "gn:feature_code":"PPL",
    "gn:name":"Gumuluo",
    "gn:population":0,
    "gn:timezone":"Asia/Shanghai",
    "iso:country":"CN",
    "name:zho_x_preferred":[
        "\u53e4\u6728\u6d1b"
    ],
    "wof:name":"Gumuluo",
    "wof:placetype":"locality"
},
  "geometry": {"coordinates":[102.42400000000001,27.7532],"type":"Point"}
}