{
  "type": "Feature",
  "properties": {
    "gn:admin1_code":"8.0",
    "gn:asciiname":"Zhongxingtun",
    "gn:country_code":"CN",
    "gn:dem":84,
    "gn:feature_class":"P",
    "gn:feature_code":"PPL",
    "gn:name":"Zhongxingtun",
    "gn:population":0,
    "gn:timezone":"Asia/Shanghai",
    "iso:country":"CN",
    "name:zho_x_preferred":[
        "\u4f17\u5174\u5c6f"
    ],
    "wof:name":"Zhongxingtun",
    "wof:placetype":"locality"
},
  "geometry": {"coordinates":[133.02448000000001,45.80738],"type":"Point"}
}