{
  "type": "Feature",
  "properties": {
    "gn:admin1_code":"14",
    "gn:asciiname":"Garmaling",
    "gn:country_code":"CN",
    "gn:dem":4479,
    "gn:feature_class":"P",
    "gn:feature_code":"PPL",
    "gn:name":"Garmaling",
    "gn:population":0,
    "gn:timezone":"Asia/Urumqi",
    "iso:country":"CN",
    "name:bod_x_preferred":[
        "\u0f40\u0f62\u0f0b\u0f58\u0f0b\u0f42\u0fb3\u0f72\u0f44"
    ],
    "wof:name":"Garmaling",
    "wof:placetype":"locality"
},
  "geometry": {"coordinates":[91.05602,28.94139],"type":"Point"}
}