{
  "type": "Feature",
  "properties": {
    "gn:admin1_code":"9.0",
    "gn:asciiname":"Changhu",
    "gn:country_code":"CN",
    "gn:dem":51,
    "gn:feature_class":"P",
    "gn:feature_code":"PPL",
    "gn:name":"Changhu",
    "gn:population":0,
    "gn:timezone":"Asia/Shanghai",
    "iso:country":"CN",
    "name:zho_x_preferred":[
        "\u5e38\u6e56"
    ],
    "wof:name":"Changhu",
    "wof:placetype":"locality"
},
  "geometry": {"coordinates":[114.53176999999999,32.89237],"type":"Point"}
}