{
  "type": "Feature",
  "properties": {
    "gn:admin1_code":"29.0",
    "gn:asciiname":"Caogudui",
    "gn:country_code":"CN",
    "gn:dem":1322,
    "gn:feature_class":"P",
    "gn:feature_code":"PPL",
    "gn:name":"Caogudui",
    "gn:population":0,
    "gn:timezone":"Asia/Shanghai",
    "iso:country":"CN",
    "name:zho_x_preferred":[
        "\u8349\u53e4\u5806"
    ],
    "wof:name":"Caogudui",
    "wof:placetype":"locality"
},
  "geometry": {"coordinates":[101.842,23.0839],"type":"Point"}
}