{
  "type": "Feature",
  "properties": {
    "gn:admin1_code":"02",
    "gn:asciiname":"Pai-yen-ts'un",
    "gn:country_code":"CN",
    "gn:dem":63,
    "gn:feature_class":"P",
    "gn:feature_code":"PPL",
    "gn:name":"Pai-yen-ts\u2019un",
    "gn:population":0,
    "gn:timezone":"Asia/Shanghai",
    "iso:country":"CN",
    "wof:name":"Pai-yen-ts'un",
    "wof:placetype":"locality"
},
  "geometry": {"coordinates":[120.93528000000001,28.20583],"type":"Point"}
}