{
  "type": "Feature",
  "properties": {
    "gn:admin1_code":"26.0",
    "gn:asciiname":"Mengdong",
    "gn:country_code":"CN",
    "gn:dem":426,
    "gn:feature_class":"P",
    "gn:feature_code":"PPL",
    "gn:name":"Mengdong",
    "gn:population":0,
    "gn:timezone":"Asia/Shanghai",
    "iso:country":"CN",
    "name:zho_x_preferred":[
        "\u5b5f\u4e1c"
    ],
    "name:zho_x_variant":[
        "\u52d0\u8463\u93ae"
    ],
    "wof:name":"Mengdong",
    "wof:placetype":"locality"
},
  "geometry": {"coordinates":[109.4372,34.8791],"type":"Point"}
}