{
  "type": "Feature",
  "properties": {
    "gn:admin1_code":"29.0",
    "gn:asciiname":"Xinlonggou",
    "gn:country_code":"CN",
    "gn:dem":2540,
    "gn:feature_class":"P",
    "gn:feature_code":"PPL",
    "gn:name":"Xinlonggou",
    "gn:population":0,
    "gn:timezone":"Asia/Shanghai",
    "iso:country":"CN",
    "name:zho_x_preferred":[
        "\u65b0\u9f99\u6c9f"
    ],
    "wof:name":"Xinlonggou",
    "wof:placetype":"locality"
},
  "geometry": {"coordinates":[102.254,25.9786],"type":"Point"}
}