{
  "type": "Feature",
  "properties": {
    "gn:admin1_code":"30.0",
    "gn:asciiname":"Shifo'an",
    "gn:country_code":"CN",
    "gn:dem":11,
    "gn:feature_class":"P",
    "gn:feature_code":"PPL",
    "gn:name":"Shifo\u2019an",
    "gn:population":0,
    "gn:timezone":"Asia/Shanghai",
    "iso:country":"CN",
    "name:und_x_variant":[
        "Shifo\u2019an"
    ],
    "name:zho_x_preferred":[
        "\u77f3\u4f5b\u5eb5"
    ],
    "wof:name":"Shifo'an",
    "wof:placetype":"locality"
},
  "geometry": {"coordinates":[115.85051,22.90786],"type":"Point"}
}