{
  "type": "Feature",
  "properties": {
    "gn:admin1_code":"1.0",
    "gn:asciiname":"Zimiaocun",
    "gn:country_code":"CN",
    "gn:dem":31,
    "gn:feature_class":"P",
    "gn:feature_code":"PPL",
    "gn:name":"Zimiaocun",
    "gn:population":0,
    "gn:timezone":"Asia/Shanghai",
    "iso:country":"CN",
    "name:zho_x_preferred":[
        "\u8a3e\u5e99\u6751"
    ],
    "wof:name":"Zimiaocun",
    "wof:placetype":"locality"
},
  "geometry": {"coordinates":[115.99256,32.97204],"type":"Point"}
}