{
  "type": "Feature",
  "properties": {
    "gn:admin1_code":"23.0",
    "gn:asciiname":"Qiaoxing",
    "gn:country_code":"CN",
    "gn:dem":4,
    "gn:feature_class":"P",
    "gn:feature_code":"PPL",
    "gn:name":"Qiaoxing",
    "gn:population":0,
    "gn:timezone":"Asia/Shanghai",
    "iso:country":"CN",
    "name:und_x_variant":[
        "\u6865\u884c"
    ],
    "wof:name":"Qiaoxing",
    "wof:placetype":"locality"
},
  "geometry": {"coordinates":[121.31561000000001,30.86052],"type":"Point"}
}