{
  "type": "Feature",
  "properties": {
    "gn:admin1_code":"14.0",
    "gn:asciiname":"Meiduo",
    "gn:country_code":"CN",
    "gn:dem":4500,
    "gn:feature_class":"P",
    "gn:feature_code":"PPL",
    "gn:name":"Meiduo",
    "gn:population":0,
    "gn:timezone":"Asia/Urumqi",
    "iso:country":"CN",
    "name:zho_x_preferred":[
        "\u7f8e\u591a"
    ],
    "wof:name":"Meiduo",
    "wof:placetype":"locality"
},
  "geometry": {"coordinates":[97.38975000000001,29.59763],"type":"Point"}
}