{
  "type": "Feature",
  "properties": {
    "gn:admin1_code":"16.0",
    "gn:asciiname":"Xieli",
    "gn:country_code":"CN",
    "gn:dem":116,
    "gn:feature_class":"P",
    "gn:feature_code":"PPL",
    "gn:name":"Xieli",
    "gn:population":0,
    "gn:timezone":"Asia/Shanghai",
    "iso:country":"CN",
    "name:zho_x_preferred":[
        "\u659c\u5398"
    ],
    "wof:name":"Xieli",
    "wof:placetype":"locality"
},
  "geometry": {"coordinates":[111.64100000000001,23.7162],"type":"Point"}
}