{
  "type": "Feature",
  "properties": {
    "gn:admin1_code":"11.0",
    "gn:asciiname":"Bagongfen",
    "gn:country_code":"CN",
    "gn:dem":253,
    "gn:feature_class":"P",
    "gn:feature_code":"PPL",
    "gn:name":"Bagongfen",
    "gn:population":0,
    "gn:timezone":"Asia/Shanghai",
    "iso:country":"CN",
    "name:zho_x_preferred":[
        "\u516b\u516c\u5206"
    ],
    "wof:name":"Bagongfen",
    "wof:placetype":"locality"
},
  "geometry": {"coordinates":[112.88914,26.00357],"type":"Point"}
}