{
  "type": "Feature",
  "properties": {
    "gn:admin1_code":"30.0",
    "gn:asciiname":"Dagoukeng",
    "gn:country_code":"CN",
    "gn:dem":79,
    "gn:feature_class":"P",
    "gn:feature_code":"PPL",
    "gn:name":"Dagoukeng",
    "gn:population":0,
    "gn:timezone":"Asia/Shanghai",
    "iso:country":"CN",
    "name:zho_x_preferred":[
        "\u5927\u72d7\u5751"
    ],
    "wof:name":"Dagoukeng",
    "wof:placetype":"locality"
},
  "geometry": {"coordinates":[113.14361,24.04889],"type":"Point"}
}