{
  "type": "Feature",
  "properties": {
    "gn:admin1_code":"19.0",
    "gn:asciiname":"Liujia Buzi",
    "gn:country_code":"CN",
    "gn:dem":160,
    "gn:feature_class":"P",
    "gn:feature_code":"PPL",
    "gn:name":"Liujia Buzi",
    "gn:population":0,
    "gn:timezone":"Asia/Shanghai",
    "iso:country":"CN",
    "name:und_x_variant":[
        "\u5218\u5bb6\u5821\u5b50",
        "Liujia Puzi"
    ],
    "wof:name":"Liujia Buzi",
    "wof:placetype":"locality"
},
  "geometry": {"coordinates":[123.31103,40.11636],"type":"Point"}
}