{
  "type": "Feature",
  "properties": {
    "gn:admin1_code":"3.0",
    "gn:asciiname":"Shizhuping",
    "gn:country_code":"CN",
    "gn:dem":181,
    "gn:feature_class":"P",
    "gn:feature_code":"PPL",
    "gn:name":"Shizhuping",
    "gn:population":0,
    "gn:timezone":"Asia/Shanghai",
    "iso:country":"CN",
    "name:zho_x_preferred":[
        "\u5b9e\u7af9\u576a"
    ],
    "wof:name":"Shizhuping",
    "wof:placetype":"locality"
},
  "geometry": {"coordinates":[115.68899999999999,25.7042],"type":"Point"}
}