{
  "type": "Feature",
  "properties": {
    "gn:admin1_code":"16.0",
    "gn:asciiname":"Pingshi",
    "gn:country_code":"CN",
    "gn:dem":166,
    "gn:feature_class":"P",
    "gn:feature_code":"PPL",
    "gn:name":"Pingshi",
    "gn:population":0,
    "gn:timezone":"Asia/Shanghai",
    "iso:country":"CN",
    "name:ceb_x_preferred":[
        "Pingshi"
    ],
    "name:swe_x_preferred":[
        "Pingshi"
    ],
    "name:zho_x_preferred":[
        "\u5e73\u77f3"
    ],
    "wof:name":"Pingshi",
    "wof:placetype":"locality"
},
  "geometry": {"coordinates":[109.06,25.119],"type":"Point"}
}