{
  "type": "Feature",
  "properties": {
    "gn:admin1_code":"18.0",
    "gn:asciiname":"Xidingzhai",
    "gn:country_code":"CN",
    "gn:dem":752,
    "gn:feature_class":"P",
    "gn:feature_code":"PPL",
    "gn:name":"Xidingzhai",
    "gn:population":0,
    "gn:timezone":"Asia/Shanghai",
    "iso:country":"CN",
    "name:zho_x_preferred":[
        "\u897f\u4e01\u5be8"
    ],
    "wof:name":"Xidingzhai",
    "wof:placetype":"locality"
},
  "geometry": {"coordinates":[107.855,25.8424],"type":"Point"}
}