{
  "type": "Feature",
  "properties": {
    "gn:admin1_code":"18.0",
    "gn:asciiname":"Gongde",
    "gn:country_code":"CN",
    "gn:dem":1263,
    "gn:feature_class":"P",
    "gn:feature_code":"PPL",
    "gn:name":"Gongde",
    "gn:population":0,
    "gn:timezone":"Asia/Shanghai",
    "iso:country":"CN",
    "name:zho_x_preferred":[
        "\u516c\u5fb7"
    ],
    "wof:name":"Gongde",
    "wof:placetype":"locality"
},
  "geometry": {"coordinates":[105.367,25.5401],"type":"Point"}
}