{
  "type": "Feature",
  "properties": {
    "gn:admin1_code":"14.0",
    "gn:asciiname":"Sanmai",
    "gn:country_code":"CN",
    "gn:dem":4178,
    "gn:feature_class":"P",
    "gn:feature_code":"PPL",
    "gn:name":"Sanmai",
    "gn:population":0,
    "gn:timezone":"Asia/Urumqi",
    "iso:country":"CN",
    "name:zho_x_preferred":[
        "\u4e09\u9ea6"
    ],
    "wof:name":"Sanmai",
    "wof:placetype":"locality"
},
  "geometry": {"coordinates":[88.0698,29.1575],"type":"Point"}
}