{
  "type": "Feature",
  "properties": {
    "gn:admin1_code":"31.0",
    "gn:asciiname":"Qunxian",
    "gn:country_code":"CN",
    "gn:dem":34,
    "gn:feature_class":"P",
    "gn:feature_code":"PPL",
    "gn:name":"Qunxian",
    "gn:population":0,
    "gn:timezone":"Asia/Shanghai",
    "iso:country":"CN",
    "name:zho_x_preferred":[
        "Qunxian"
    ],
    "name:zho_x_variant":[
        "\u7fa4\u5148"
    ],
    "wof:name":"Qunxian",
    "wof:placetype":"locality"
},
  "geometry": {"coordinates":[110.61539,19.3719],"type":"Point"}
}