{
  "type": "Feature",
  "properties": {
    "gn:admin1_code":"22.0",
    "gn:asciiname":"Gongchen",
    "gn:country_code":"CN",
    "gn:dem":47,
    "gn:feature_class":"P",
    "gn:feature_code":"PPLA3",
    "gn:name":"Gongchen",
    "gn:population":0,
    "gn:timezone":"Asia/Shanghai",
    "iso:country":"CN",
    "name:und_x_variant":[
        "Gongchen Jiedao",
        "Fangshan Qu"
    ],
    "name:zho_x_preferred":[
        "\u62f1\u8fb0"
    ],
    "name:zho_x_variant":[
        "\u62f1\u8fb0\u8857\u9053",
        "\u623f\u5c71\u533a"
    ],
    "wof:name":"Gongchen",
    "wof:placetype":"locality"
},
  "geometry": {"coordinates":[116.13755999999999,39.72796],"type":"Point"}
}