{
  "type": "Feature",
  "properties": {
    "gn:admin1_code":"5.0",
    "gn:asciiname":"Jiulonggou",
    "gn:country_code":"CN",
    "gn:dem":251,
    "gn:feature_class":"P",
    "gn:feature_code":"PPL",
    "gn:name":"Jiulonggou",
    "gn:population":0,
    "gn:timezone":"Asia/Shanghai",
    "iso:country":"CN",
    "name:zho_x_preferred":[
        "\u4e5d\u9f99\u6c9f"
    ],
    "wof:name":"Jiulonggou",
    "wof:placetype":"locality"
},
  "geometry": {"coordinates":[127.40231,44.53761],"type":"Point"}
}