{
  "type": "Feature",
  "properties": {
    "gn:admin1_code":"12.0",
    "gn:asciiname":"Huyu",
    "gn:country_code":"CN",
    "gn:dem":69,
    "gn:feature_class":"P",
    "gn:feature_code":"PPL",
    "gn:name":"Huyu",
    "gn:population":0,
    "gn:timezone":"Asia/Shanghai",
    "iso:country":"CN",
    "name:zho_x_preferred":[
        "Huyu"
    ],
    "name:zho_x_variant":[
        "\u80e1\u7389"
    ],
    "wof:name":"Huyu",
    "wof:placetype":"locality"
},
  "geometry": {"coordinates":[115.18174999999999,29.7084],"type":"Point"}
}