{
  "type": "Feature",
  "properties": {
    "gn:admin1_code":"11.0",
    "gn:asciiname":"Mianhuaping",
    "gn:country_code":"CN",
    "gn:dem":469,
    "gn:feature_class":"P",
    "gn:feature_code":"PPL",
    "gn:name":"Mianhuaping",
    "gn:population":0,
    "gn:timezone":"Asia/Shanghai",
    "iso:country":"CN",
    "name:zho_x_preferred":[
        "\u68c9\u82b1\u576a"
    ],
    "wof:name":"Mianhuaping",
    "wof:placetype":"locality"
},
  "geometry": {"coordinates":[112.0262,24.97813],"type":"Point"}
}