{
  "type": "Feature",
  "properties": {
    "gn:admin1_code":"4.0",
    "gn:asciiname":"Minliancun",
    "gn:country_code":"CN",
    "gn:dem":3,
    "gn:feature_class":"P",
    "gn:feature_code":"PPL",
    "gn:name":"Minliancun",
    "gn:population":0,
    "gn:timezone":"Asia/Shanghai",
    "iso:country":"CN",
    "name:zho_x_preferred":[
        "\u6c11\u8054\u6751"
    ],
    "wof:name":"Minliancun",
    "wof:placetype":"locality"
},
  "geometry": {"coordinates":[120.28912,33.42767],"type":"Point"}
}