{
  "type": "Feature",
  "properties": {
    "gn:admin1_code":"24.0",
    "gn:asciiname":"Wayaoshang",
    "gn:country_code":"CN",
    "gn:dem":1261,
    "gn:feature_class":"P",
    "gn:feature_code":"PPL",
    "gn:name":"Wayaoshang",
    "gn:population":0,
    "gn:timezone":"Asia/Shanghai",
    "iso:country":"CN",
    "name:zho_x_preferred":[
        "\u74e6\u7a91\u4e0a"
    ],
    "wof:name":"Wayaoshang",
    "wof:placetype":"locality"
},
  "geometry": {"coordinates":[113.4105,35.71199],"type":"Point"}
}