{
  "type": "Feature",
  "properties": {
    "gn:admin1_code":"29",
    "gn:asciiname":"Ganlongtan",
    "gn:country_code":"CN",
    "gn:dem":1949,
    "gn:feature_class":"P",
    "gn:feature_code":"PPL",
    "gn:name":"Ganlongtan",
    "gn:population":0,
    "gn:timezone":"Asia/Shanghai",
    "iso:country":"CN",
    "name:zho_x_preferred":[
        "\u5e72\u9f99\u6f6d"
    ],
    "wof:name":"Ganlongtan",
    "wof:placetype":"locality"
},
  "geometry": {"coordinates":[103.00729,24.51746],"type":"Point"}
}