{
  "type": "Feature",
  "properties": {
    "gn:admin1_code":"5.0",
    "gn:asciiname":"Xiniu Hutu",
    "gn:country_code":"CN",
    "gn:dem":111,
    "gn:feature_class":"P",
    "gn:feature_code":"PPL",
    "gn:name":"Xiniu Hutu",
    "gn:population":0,
    "gn:timezone":"Asia/Shanghai",
    "iso:country":"CN",
    "name:zho_x_preferred":[
        "\u897f\u725b\u6237\u5410"
    ],
    "wof:name":"Xiniu Hutu",
    "wof:placetype":"locality"
},
  "geometry": {"coordinates":[123.73497,43.49289],"type":"Point"}
}