{
  "type": "Feature",
  "properties": {
    "gn:admin1_code":"3.0",
    "gn:asciiname":"Xiling",
    "gn:country_code":"CN",
    "gn:dem":355,
    "gn:feature_class":"P",
    "gn:feature_code":"PPL",
    "gn:name":"Xiling",
    "gn:population":0,
    "gn:timezone":"Asia/Shanghai",
    "iso:country":"CN",
    "name:ceb_x_preferred":[
        "Xiling"
    ],
    "name:deu_x_preferred":[
        "Xiling"
    ],
    "name:nor_x_preferred":[
        "Xiling"
    ],
    "name:und_x_variant":[
        "\u6eaa\u5cad"
    ],
    "wof:name":"Xiling",
    "wof:placetype":"locality"
},
  "geometry": {"coordinates":[116.54677,26.89831],"type":"Point"}
}