{
  "type": "Feature",
  "properties": {
    "gn:admin1_code":"5.0",
    "gn:asciiname":"Renhecun",
    "gn:country_code":"CN",
    "gn:dem":365,
    "gn:feature_class":"P",
    "gn:feature_code":"PPL",
    "gn:name":"Renhecun",
    "gn:population":0,
    "gn:timezone":"Asia/Shanghai",
    "iso:country":"CN",
    "name:zho_x_preferred":[
        "\u4eba\u548c\u6751"
    ],
    "wof:name":"Renhecun",
    "wof:placetype":"locality"
},
  "geometry": {"coordinates":[125.1225,42.70644],"type":"Point"}
}