{
  "type": "Feature",
  "properties": {
    "gn:admin1_code":"29.0",
    "gn:asciiname":"Dahaodi",
    "gn:country_code":"CN",
    "gn:dem":2206,
    "gn:feature_class":"P",
    "gn:feature_code":"PPL",
    "gn:name":"Dahaodi",
    "gn:population":0,
    "gn:timezone":"Asia/Shanghai",
    "iso:country":"CN",
    "name:zho_x_preferred":[
        "\u5927\u84bf\u5730"
    ],
    "wof:name":"Dahaodi",
    "wof:placetype":"locality"
},
  "geometry": {"coordinates":[103.85599999999999,27.3212],"type":"Point"}
}