{
  "type": "Feature",
  "properties": {
    "gn:admin1_code":"14.0",
    "gn:asciiname":"Nakaikangba",
    "gn:country_code":"CN",
    "gn:dem":4258,
    "gn:feature_class":"P",
    "gn:feature_code":"PPL",
    "gn:name":"Nakaikangba",
    "gn:population":0,
    "gn:timezone":"Asia/Urumqi",
    "iso:country":"CN",
    "name:zho_x_preferred":[
        "\u90a3\u5f00\u5eb7\u5df4"
    ],
    "wof:name":"Nakaikangba",
    "wof:placetype":"locality"
},
  "geometry": {"coordinates":[90.62770999999999,29.72566],"type":"Point"}
}