{
  "type": "Feature",
  "properties": {
    "gn:country":"CN",
    "gn:fcode":"PPLA3",
    "gn:population":83936,
    "iso:country":"CN",
    "name:und_x_variant":[
        "Chiang-tu"
    ],
    "name:zho_x_preferred":[
        "\u4ed9\u5973"
    ],
    "name:zho_x_variant":[
        "\u6c5f\u90fd\u5e02"
    ],
    "qs:name":"Xiann\u00fc",
    "qs:photos_9r":0,
    "qs:photos_sr":0,
    "qs:pop_sr":"8",
    "wof:name":"Xiann\u00fc",
    "wof:placetype":"locality",
    "wof:population":83936
},
  "geometry": {"coordinates":[119.56048,32.42806],"type":"Point"}
}