{
  "type": "Feature",
  "properties": {
    "gn:admin1_code":"18",
    "gn:asciiname":"Haiba",
    "gn:country_code":"CN",
    "gn:dem":1867,
    "gn:feature_class":"P",
    "gn:feature_code":"PPL",
    "gn:name":"Haiba",
    "gn:population":0,
    "gn:timezone":"Asia/Shanghai",
    "iso:country":"CN",
    "name:ceb_x_preferred":[
        "Haiba"
    ],
    "name:est_x_preferred":[
        "Haiba"
    ],
    "name:fra_x_preferred":[
        "Haiba"
    ],
    "name:hye_x_preferred":[
        "\u0540\u0561\u056b\u0562\u0561"
    ],
    "name:nld_x_preferred":[
        "Haiba"
    ],
    "name:pol_x_preferred":[
        "Haiba"
    ],
    "name:ron_x_preferred":[
        "Haiba"
    ],
    "name:rus_x_preferred":[
        "\u0425\u0430\u0439\u0431\u0430"
    ],
    "name:sco_x_preferred":[
        "Haiba"
    ],
    "name:spa_x_preferred":[
        "Haiba"
    ],
    "name:ukr_x_preferred":[
        "\u0413\u0430\u0439\u0431\u0430"
    ],
    "name:vol_x_preferred":[
        "Haiba"
    ],
    "name:zho_x_preferred":[
        "\u6d77\u575d"
    ],
    "wof:name":"Haiba",
    "wof:placetype":"locality"
},
  "geometry": {"coordinates":[104.986,26.9898],"type":"Point"}
}