{
  "type": "Feature",
  "properties": {
    "gn:admin1_code":"4.0",
    "gn:asciiname":"Xiyuancun",
    "gn:country_code":"CN",
    "gn:dem":3,
    "gn:feature_class":"P",
    "gn:feature_code":"PPL",
    "gn:name":"Xiyuancun",
    "gn:population":0,
    "gn:timezone":"Asia/Shanghai",
    "iso:country":"CN",
    "name:zho_x_preferred":[
        "\u897f\u56ed\u6751"
    ],
    "wof:name":"Xiyuancun",
    "wof:placetype":"locality"
},
  "geometry": {"coordinates":[120.24204,31.89542],"type":"Point"}
}