{
  "type": "Feature",
  "properties": {
    "gn:admin1_code":"04",
    "gn:asciiname":"Puzhuang",
    "gn:country_code":"CN",
    "gn:dem":7,
    "gn:feature_class":"P",
    "gn:feature_code":"PPL",
    "gn:name":"Puzhuang",
    "gn:population":0,
    "gn:timezone":"Asia/Shanghai",
    "iso:country":"CN",
    "name:und_x_variant":[
        "P\u2019u-chuang",
        "P\u2019u-chuang-chen",
        "Puzhuang"
    ],
    "wof:name":"Puzhuang",
    "wof:placetype":"locality"
},
  "geometry": {"coordinates":[120.50062,31.16343],"type":"Point"}
}