{
  "type": "Feature",
  "properties": {
    "gn:admin1_code":"24",
    "gn:asciiname":"Xianjiagou",
    "gn:cc2":"CN",
    "gn:country_code":"CN",
    "gn:dem":1363,
    "gn:feature_class":"P",
    "gn:feature_code":"PPL",
    "gn:name":"Xianjiagou",
    "gn:population":0,
    "gn:timezone":"Asia/Shanghai",
    "iso:country":"CN",
    "name:und_x_variant":[
        "Hsien-chia-kou",
        "Xianjiagou"
    ],
    "wof:name":"Xianjiagou",
    "wof:placetype":"locality"
},
  "geometry": {"coordinates":[111.84833,37.49111],"type":"Point"}
}