{
  "type": "Feature",
  "properties": {
    "gn:admin1_code":"21.0",
    "gn:asciiname":"Shahexian",
    "gn:country_code":"CN",
    "gn:dem":2306,
    "gn:feature_class":"P",
    "gn:feature_code":"PPL",
    "gn:name":"Shahexian",
    "gn:population":0,
    "gn:timezone":"Asia/Shanghai",
    "iso:country":"CN",
    "name:zho_x_preferred":[
        "\u6c99\u6cb3\u5c98"
    ],
    "wof:name":"Shahexian",
    "wof:placetype":"locality"
},
  "geometry": {"coordinates":[106.15600000000001,35.8775],"type":"Point"}
}