{
  "type": "Feature",
  "properties": {
    "gn:admin1_code":"15.0",
    "gn:asciiname":"Niangniangchi",
    "gn:country_code":"CN",
    "gn:dem":2451,
    "gn:feature_class":"P",
    "gn:feature_code":"PPL",
    "gn:name":"Niangniangchi",
    "gn:population":0,
    "gn:timezone":"Asia/Shanghai",
    "iso:country":"CN",
    "name:zho_x_preferred":[
        "\u5a18\u5a18\u6c60"
    ],
    "wof:name":"Niangniangchi",
    "wof:placetype":"locality"
},
  "geometry": {"coordinates":[103.33799999999999,35.3296],"type":"Point"}
}