{
  "type": "Feature",
  "properties": {
    "gn:admin1_code":"25",
    "gn:asciiname":"Dawengshan",
    "gn:country_code":"CN",
    "gn:dem":185,
    "gn:feature_class":"P",
    "gn:feature_code":"PPL",
    "gn:name":"Dawengshan",
    "gn:population":0,
    "gn:timezone":"Asia/Shanghai",
    "iso:country":"CN",
    "name:zho_x_preferred":[
        "\u5927\u74ee\u5c71"
    ],
    "wof:name":"Dawengshan",
    "wof:placetype":"locality"
},
  "geometry": {"coordinates":[118.727,35.9521],"type":"Point"}
}