{
  "type": "Feature",
  "properties": {
    "gn:admin1_code":"11.0",
    "gn:asciiname":"Tang'aoshang",
    "gn:country_code":"CN",
    "gn:dem":309,
    "gn:feature_class":"P",
    "gn:feature_code":"PPL",
    "gn:name":"Tang\u2019aoshang",
    "gn:population":0,
    "gn:timezone":"Asia/Shanghai",
    "iso:country":"CN",
    "name:und_x_variant":[
        "Tang\u2019aoshang"
    ],
    "name:zho_x_preferred":[
        "\u5858\u5773\u4e0a"
    ],
    "wof:name":"Tang'aoshang",
    "wof:placetype":"locality"
},
  "geometry": {"coordinates":[110.45341000000001,28.03451],"type":"Point"}
}