{
  "type": "Feature",
  "properties": {
    "gn:admin1_code":"03",
    "gn:asciiname":"Laoguan",
    "gn:cc2":"CN",
    "gn:country_code":"CN",
    "gn:dem":87,
    "gn:feature_class":"P",
    "gn:feature_code":"PPL",
    "gn:name":"Laoguan",
    "gn:population":0,
    "gn:timezone":"Asia/Shanghai",
    "iso:country":"CN",
    "name:und_x_variant":[
        "Lao-kuan",
        "Laokwan",
        "Laoguan"
    ],
    "wof:name":"Laoguan",
    "wof:placetype":"locality"
},
  "geometry": {"coordinates":[113.61667,27.63333],"type":"Point"}
}