{
  "type": "Feature",
  "properties": {
    "gn:admin1_code":"5.0",
    "gn:asciiname":"Yanjiangcun",
    "gn:country_code":"CN",
    "gn:dem":446,
    "gn:feature_class":"P",
    "gn:feature_code":"PPL",
    "gn:name":"Yanjiangcun",
    "gn:population":0,
    "gn:timezone":"Asia/Shanghai",
    "iso:country":"CN",
    "name:zho_x_preferred":[
        "\u6cbf\u6c5f\u6751"
    ],
    "wof:name":"Yanjiangcun",
    "wof:placetype":"locality"
},
  "geometry": {"coordinates":[127.86099,42.73038],"type":"Point"}
}