{
  "type": "Feature",
  "properties": {
    "gn:admin1_code":"9",
    "gn:asciiname":"Dongliuzhuang",
    "gn:country_code":"CN",
    "gn:dem":46,
    "gn:feature_class":"P",
    "gn:feature_code":"PPL",
    "gn:name":"Dongliuzhuang",
    "gn:population":0,
    "gn:timezone":"Asia/Shanghai",
    "iso:country":"CN",
    "name:zho_x_preferred":[
        "\u4e1c\u5218\u5e84"
    ],
    "wof:name":"Dongliuzhuang",
    "wof:placetype":"locality"
},
  "geometry": {"coordinates":[115.077,33.8081],"type":"Point"}
}