{
  "type": "Feature",
  "properties": {
    "gn:admin1_code":"04",
    "gn:asciiname":"Jingtang",
    "gn:country_code":"CN",
    "gn:dem":9,
    "gn:feature_class":"P",
    "gn:feature_code":"PPL",
    "gn:name":"Jingtang",
    "gn:population":0,
    "gn:timezone":"Asia/Shanghai",
    "iso:country":"CN",
    "name:und_x_variant":[
        "Chin-t\u2019ang-ts\u2019un",
        "Ch\u2019in-t\u2019ai",
        "Ching-t\u2019ang",
        "Jingtang"
    ],
    "name:zho_x_preferred":[
        "\u9cb8\u5858"
    ],
    "wof:name":"Jingtang",
    "wof:placetype":"locality"
},
  "geometry": {"coordinates":[119.62736,31.34576],"type":"Point"}
}