{
  "type": "Feature",
  "properties": {
    "gn:admin1_code":"12.0",
    "gn:asciiname":"Aojia Goukou",
    "gn:country_code":"CN",
    "gn:dem":839,
    "gn:feature_class":"P",
    "gn:feature_code":"PPL",
    "gn:name":"Aojia Goukou",
    "gn:population":0,
    "gn:timezone":"Asia/Shanghai",
    "iso:country":"CN",
    "name:zho_x_preferred":[
        "\u6556\u5bb6\u6c9f\u53e3"
    ],
    "wof:name":"Aojia Goukou",
    "wof:placetype":"locality"
},
  "geometry": {"coordinates":[110.15624,32.56460999999999],"type":"Point"}
}