{
  "type": "Feature",
  "properties": {
    "gn:admin1_code":"25",
    "gn:asciiname":"Zaoxi",
    "gn:country_code":"CN",
    "gn:dem":13,
    "gn:feature_class":"P",
    "gn:feature_code":"PPL",
    "gn:name":"Zaoxi",
    "gn:population":0,
    "gn:timezone":"Asia/Shanghai",
    "iso:country":"CN",
    "name:zho_x_preferred":[
        "\u7076\u897f"
    ],
    "wof:name":"Zaoxi",
    "wof:placetype":"locality"
},
  "geometry": {"coordinates":[117.291,37.772],"type":"Point"}
}