{
  "type": "Feature",
  "properties": {
    "gn:admin1_code":"26",
    "gn:asciiname":"Qiao'ergou",
    "gn:country_code":"CN",
    "gn:dem":1074,
    "gn:feature_class":"P",
    "gn:feature_code":"PPL",
    "gn:name":"Qiao\u2019ergou",
    "gn:population":0,
    "gn:timezone":"Asia/Shanghai",
    "iso:country":"CN",
    "name:und_x_variant":[
        "Ch\u2019iao-kou",
        "Qiaogou",
        "Qiao\u2019ergou"
    ],
    "wof:name":"Qiao'ergou",
    "wof:placetype":"locality"
},
  "geometry": {"coordinates":[109.51667,36.63333],"type":"Point"}
}