{
  "type": "Feature",
  "properties": {
    "gn:admin1_code":"29.0",
    "gn:asciiname":"Jiagou",
    "gn:country_code":"CN",
    "gn:dem":772,
    "gn:feature_class":"P",
    "gn:feature_code":"PPL",
    "gn:name":"Jiagou",
    "gn:population":0,
    "gn:timezone":"Asia/Shanghai",
    "iso:country":"CN",
    "name:zho_x_preferred":[
        "\u5939\u6c9f"
    ],
    "wof:name":"Jiagou",
    "wof:placetype":"locality"
},
  "geometry": {"coordinates":[103.977,22.9179],"type":"Point"}
}