{
  "type": "Feature",
  "properties": {
    "gn:admin1_code":"19.0",
    "gn:asciiname":"Qianchangzi",
    "gn:country_code":"CN",
    "gn:dem":179,
    "gn:feature_class":"P",
    "gn:feature_code":"PPL",
    "gn:name":"Qianchangzi",
    "gn:population":0,
    "gn:timezone":"Asia/Shanghai",
    "iso:country":"CN",
    "name:und_x_variant":[
        "\u524d\u5382\u5b50"
    ],
    "name:zho_x_preferred":[
        "\u524d\u5382\u5b50"
    ],
    "wof:name":"Qianchangzi",
    "wof:placetype":"locality"
},
  "geometry": {"coordinates":[123.83207,41.38602],"type":"Point"}
}