{
  "type": "Feature",
  "properties": {
    "gn:admin1_code":"4.0",
    "gn:asciiname":"Huiyuan",
    "gn:country_code":"CN",
    "gn:dem":5,
    "gn:feature_class":"P",
    "gn:feature_code":"PPL",
    "gn:name":"Huiyuan",
    "gn:population":0,
    "gn:timezone":"Asia/Shanghai",
    "iso:country":"CN",
    "name:ara_x_preferred":[
        "\u0647\u0648\u064a\u0648\u0627\u0646"
    ],
    "name:deu_x_preferred":[
        "Huiyuan"
    ],
    "name:nld_x_preferred":[
        "Huiyuan"
    ],
    "name:rus_x_preferred":[
        "\u0425\u0443\u044d\u0439\u044e\u0430\u043d\u044c"
    ],
    "name:und_x_variant":[
        "\u6c47\u6e90"
    ],
    "name:zho_x_preferred":[
        "Huiyuanzhen"
    ],
    "name:zho_x_variant":[
        "\u6c47\u6e90\u9547"
    ],
    "wof:name":"Huiyuan",
    "wof:placetype":"locality"
},
  "geometry": {"coordinates":[121.21578999999998,31.99441],"type":"Point"}
}