{
  "type": "Feature",
  "properties": {
    "gn:admin1_code":"2",
    "gn:asciiname":"Lisongshan",
    "gn:country_code":"CN",
    "gn:dem":279,
    "gn:feature_class":"P",
    "gn:feature_code":"PPL",
    "gn:name":"Lisongshan",
    "gn:population":0,
    "gn:timezone":"Asia/Shanghai",
    "iso:country":"CN",
    "name:und_x_variant":[
        "\u91cc\u677e\u5c71"
    ],
    "wof:name":"Lisongshan",
    "wof:placetype":"locality"
},
  "geometry": {"coordinates":[119.90278000000001,29.71333],"type":"Point"}
}