{
  "type": "Feature",
  "properties": {
    "gn:admin1_code":"30.0",
    "gn:asciiname":"Hongqi",
    "gn:country_code":"CN",
    "gn:dem":-3,
    "gn:feature_class":"P",
    "gn:feature_code":"PPLA4",
    "gn:name":"Hongqi",
    "gn:population":0,
    "gn:timezone":"Asia/Shanghai",
    "iso:country":"CN",
    "name:und_x_variant":[
        "Hongqi Zhen",
        "\u7ea2\u65d7\u9547"
    ],
    "name:zho_x_preferred":[
        "\u7ea2\u65d7"
    ],
    "wof:name":"Hongqi",
    "wof:placetype":"locality"
},
  "geometry": {"coordinates":[113.34266,22.14785],"type":"Point"}
}