{
  "type": "Feature",
  "properties": {
    "gn:admin1_code":"4.0",
    "gn:asciiname":"Shangliuxudai",
    "gn:country_code":"CN",
    "gn:dem":5,
    "gn:feature_class":"P",
    "gn:feature_code":"PPL",
    "gn:name":"Shangliuxudai",
    "gn:population":0,
    "gn:timezone":"Asia/Shanghai",
    "iso:country":"CN",
    "name:zho_x_preferred":[
        "\u4e0a\u516d\u5729\u57ed"
    ],
    "wof:name":"Shangliuxudai",
    "wof:placetype":"locality"
},
  "geometry": {"coordinates":[119.76167,32.2263],"type":"Point"}
}