{
  "type": "Feature",
  "properties": {
    "gn:admin1_code":"16.0",
    "gn:asciiname":"Pingqiang",
    "gn:country_code":"CN",
    "gn:dem":157,
    "gn:feature_class":"P",
    "gn:feature_code":"PPL",
    "gn:name":"Pingqiang",
    "gn:population":0,
    "gn:timezone":"Asia/Shanghai",
    "iso:country":"CN",
    "name:zho_x_preferred":[
        "\u5e73\u7f8c"
    ],
    "wof:name":"Pingqiang",
    "wof:placetype":"locality"
},
  "geometry": {"coordinates":[107.73699999999999,23.2313],"type":"Point"}
}