{
  "type": "Feature",
  "properties": {
    "gn:admin1_code":"18",
    "gn:asciiname":"Banshangou",
    "gn:country_code":"CN",
    "gn:dem":833,
    "gn:feature_class":"P",
    "gn:feature_code":"PPL",
    "gn:name":"Banshangou",
    "gn:population":0,
    "gn:timezone":"Asia/Shanghai",
    "iso:country":"CN",
    "name:zho_x_preferred":[
        "\u677f\u5c71\u6c9f"
    ],
    "wof:name":"Banshangou",
    "wof:placetype":"locality"
},
  "geometry": {"coordinates":[107.708,27.0763],"type":"Point"}
}