{
  "type": "Feature",
  "properties": {
    "gn:admin1_code":"15.0",
    "gn:asciiname":"Panjiawan",
    "gn:country_code":"CN",
    "gn:dem":1826,
    "gn:feature_class":"P",
    "gn:feature_code":"PPL",
    "gn:name":"Panjiawan",
    "gn:population":0,
    "gn:timezone":"Asia/Shanghai",
    "iso:country":"CN",
    "name:zho_x_preferred":[
        "\u6f58\u5bb6\u6e7e"
    ],
    "wof:name":"Panjiawan",
    "wof:placetype":"locality"
},
  "geometry": {"coordinates":[105.01793000000001,33.22876],"type":"Point"}
}