{
  "type": "Feature",
  "properties": {
    "gn:admin1_code":"16.0",
    "gn:asciiname":"Yangjiajiangkou",
    "gn:country_code":"CN",
    "gn:dem":158,
    "gn:feature_class":"P",
    "gn:feature_code":"PPL",
    "gn:name":"Yangjiajiangkou",
    "gn:population":0,
    "gn:timezone":"Asia/Shanghai",
    "iso:country":"CN",
    "name:zho_x_preferred":[
        "\u6768\u5bb6\u6c5f\u53e3"
    ],
    "wof:name":"Yangjiajiangkou",
    "wof:placetype":"locality"
},
  "geometry": {"coordinates":[108.47199999999999,24.5765],"type":"Point"}
}