{
  "type": "Feature",
  "properties": {
    "gn:admin1_code":"08",
    "gn:asciiname":"Qiujiadian",
    "gn:cc2":"CN",
    "gn:country_code":"CN",
    "gn:dem":186,
    "gn:feature_class":"P",
    "gn:feature_code":"PPL",
    "gn:name":"Qiujiadian",
    "gn:population":0,
    "gn:timezone":"Asia/Shanghai",
    "iso:country":"CN",
    "name:und_x_variant":[
        "Ch\u2019iu-chia-tien",
        "Qiujiadian"
    ],
    "wof:name":"Qiujiadian",
    "wof:placetype":"locality"
},
  "geometry": {"coordinates":[126.28361,46.34611],"type":"Point"}
}