{
  "type": "Feature",
  "properties": {
    "gn:admin1_code":"16.0",
    "gn:asciiname":"Gongmei",
    "gn:country_code":"CN",
    "gn:dem":196,
    "gn:feature_class":"P",
    "gn:feature_code":"PPL",
    "gn:name":"Gongmei",
    "gn:population":0,
    "gn:timezone":"Asia/Shanghai",
    "iso:country":"CN",
    "name:zho_x_preferred":[
        "\u516c\u7709"
    ],
    "wof:name":"Gongmei",
    "wof:placetype":"locality"
},
  "geometry": {"coordinates":[111.70099999999999,24.1193],"type":"Point"}
}