{
  "type": "Feature",
  "properties": {
    "gn:admin1_code":"30.0",
    "gn:asciiname":"Kongtangcun",
    "gn:country_code":"CN",
    "gn:dem":89,
    "gn:feature_class":"P",
    "gn:feature_code":"PPL",
    "gn:name":"Kongtangcun",
    "gn:population":0,
    "gn:timezone":"Asia/Shanghai",
    "iso:country":"CN",
    "name:zho_x_preferred":[
        "\u5b54\u5858\u6751"
    ],
    "wof:name":"Kongtangcun",
    "wof:placetype":"locality"
},
  "geometry": {"coordinates":[112.16670000000001,24.07193],"type":"Point"}
}