{
  "type": "Feature",
  "properties": {
    "gn:admin1_code":"16.0",
    "gn:asciiname":"Shitan",
    "gn:country_code":"CN",
    "gn:dem":461,
    "gn:feature_class":"P",
    "gn:feature_code":"PPL",
    "gn:name":"Shitan",
    "gn:population":0,
    "gn:timezone":"Asia/Shanghai",
    "iso:country":"CN",
    "name:zho_x_preferred":[
        "\u77f3\u6ee9"
    ],
    "name:zho_x_variant":[
        "\u77f3\u6f6d\u9547"
    ],
    "wof:name":"Shitan",
    "wof:placetype":"locality"
},
  "geometry": {"coordinates":[108.946,24.7383],"type":"Point"}
}