{
  "type": "Feature",
  "properties": {
    "gn:admin1_code":"11.0",
    "gn:asciiname":"Fenshuiwan",
    "gn:country_code":"CN",
    "gn:dem":105,
    "gn:feature_class":"P",
    "gn:feature_code":"PPL",
    "gn:name":"Fenshuiwan",
    "gn:population":0,
    "gn:timezone":"Asia/Shanghai",
    "iso:country":"CN",
    "name:zho_x_preferred":[
        "Fenshuiwan"
    ],
    "name:zho_x_variant":[
        "\u5206\u6c34\u6e7e"
    ],
    "wof:name":"Fenshuiwan",
    "wof:placetype":"locality"
},
  "geometry": {"coordinates":[111.24651,28.92336],"type":"Point"}
}