{
  "type": "Feature",
  "properties": {
    "gn:admin1_code":"1.0",
    "gn:asciiname":"Shilicun",
    "gn:country_code":"CN",
    "gn:dem":193,
    "gn:feature_class":"P",
    "gn:feature_code":"PPL",
    "gn:name":"Shilicun",
    "gn:population":0,
    "gn:timezone":"Asia/Shanghai",
    "iso:country":"CN",
    "name:zho_x_preferred":[
        "\u5e02\u91cc\u6751"
    ],
    "wof:name":"Shilicun",
    "wof:placetype":"locality"
},
  "geometry": {"coordinates":[117.34832,30.05432],"type":"Point"}
}