{
  "type": "Feature",
  "properties": {
    "gn:admin1_code":"29.0",
    "gn:asciiname":"Zilamen",
    "gn:country_code":"CN",
    "gn:dem":1584,
    "gn:feature_class":"P",
    "gn:feature_code":"PPL",
    "gn:name":"Zilamen",
    "gn:population":0,
    "gn:timezone":"Asia/Shanghai",
    "iso:country":"CN",
    "name:zho_x_preferred":[
        "\u5b50\u8fa3\u95e8"
    ],
    "wof:name":"Zilamen",
    "wof:placetype":"locality"
},
  "geometry": {"coordinates":[101.724,26.1095],"type":"Point"}
}