{
  "type": "Feature",
  "properties": {
    "gn:admin1_code":"30.0",
    "gn:asciiname":"Hushi",
    "gn:country_code":"CN",
    "gn:dem":33,
    "gn:feature_class":"P",
    "gn:feature_code":"PPL",
    "gn:name":"Hushi",
    "gn:population":0,
    "gn:timezone":"Asia/Urumqi",
    "iso:country":"CN",
    "name:heb_x_preferred":[
        "\u05d7\u05d5\u05e9\u05d9"
    ],
    "name:zho_x_preferred":[
        "\u864e\u4ed5"
    ],
    "wof:name":"Hushi",
    "wof:placetype":"locality"
},
  "geometry": {"coordinates":[110.37392,20.57467],"type":"Point"}
}