{
  "type": "Feature",
  "properties": {
    "gn:admin1_code":"1.0",
    "gn:asciiname":"Xiuyang",
    "gn:country_code":"CN",
    "gn:dem":154,
    "gn:feature_class":"P",
    "gn:feature_code":"PPL",
    "gn:name":"Xiuyang",
    "gn:population":0,
    "gn:timezone":"Asia/Shanghai",
    "iso:country":"CN",
    "name:zho_x_preferred":[
        "\u79c0\u9633"
    ],
    "wof:name":"Xiuyang",
    "wof:placetype":"locality"
},
  "geometry": {"coordinates":[118.16834,29.76303],"type":"Point"}
}