{
  "type": "Feature",
  "properties": {
    "gn:admin1_code":"25.0",
    "gn:asciiname":"Qianchuiliu",
    "gn:country_code":"CN",
    "gn:dem":86,
    "gn:feature_class":"P",
    "gn:feature_code":"PPL",
    "gn:name":"Qianchuiliu",
    "gn:population":0,
    "gn:timezone":"Asia/Shanghai",
    "iso:country":"CN",
    "name:zho_x_preferred":[
        "\u524d\u5782\u67f3"
    ],
    "wof:name":"Qianchuiliu",
    "wof:placetype":"locality"
},
  "geometry": {"coordinates":[121.22447,37.10647],"type":"Point"}
}