{
  "type": "Feature",
  "properties": {
    "gn:admin1_code":"29.0",
    "gn:asciiname":"Liangzi",
    "gn:country_code":"CN",
    "gn:dem":1742,
    "gn:feature_class":"P",
    "gn:feature_code":"PPL",
    "gn:name":"Liangzi",
    "gn:population":0,
    "gn:timezone":"Asia/Shanghai",
    "iso:country":"CN",
    "name:zho_x_preferred":[
        "\u6881\u5b50"
    ],
    "wof:name":"Liangzi",
    "wof:placetype":"locality"
},
  "geometry": {"coordinates":[100.226,23.8335],"type":"Point"}
}