{
  "type": "Feature",
  "properties": {
    "gn:admin1_code":"31.0",
    "gn:asciiname":"Tougan",
    "gn:country_code":"CN",
    "gn:dem":107,
    "gn:feature_class":"P",
    "gn:feature_code":"PPL",
    "gn:name":"Tougan",
    "gn:population":0,
    "gn:timezone":"Asia/Shanghai",
    "iso:country":"CN",
    "name:ben_x_preferred":[
        "\u099f\u09cb\u0989\u0997\u09be\u09a8"
    ],
    "name:ceb_x_preferred":[
        "Tougan"
    ],
    "name:deu_x_preferred":[
        "Tougan"
    ],
    "name:ell_x_preferred":[
        "\u03a4\u03bf\u03c5\u03b3\u03ba\u03ac\u03bd"
    ],
    "name:fas_x_preferred":[
        "\u062a\u0648\u06af\u0627\u0646"
    ],
    "name:fra_x_preferred":[
        "Tougan"
    ],
    "name:frr_x_preferred":[
        "Tougan"
    ],
    "name:heb_x_preferred":[
        "\u05d8\u05d5\u05d2\u05df"
    ],
    "name:hin_x_preferred":[
        "\u0924\u094b\u0909\u0917\u0928"
    ],
    "name:hun_x_preferred":[
        "Tougan"
    ],
    "name:ind_x_preferred":[
        "Tougan"
    ],
    "name:ita_x_preferred":[
        "Tougan"
    ],
    "name:kor_x_preferred":[
        "\ud22c\uac04"
    ],
    "name:nld_x_preferred":[
        "Tougan"
    ],
    "name:pol_x_preferred":[
        "Tougan"
    ],
    "name:por_x_preferred":[
        "Tougan"
    ],
    "name:ron_x_preferred":[
        "Tougan"
    ],
    "name:rus_x_preferred":[
        "\u0422\u0443\u0433\u0430\u043d"
    ],
    "name:spa_x_preferred":[
        "Tougan"
    ],
    "name:swe_x_preferred":[
        "Tougan"
    ],
    "name:tur_x_preferred":[
        "Tougan"
    ],
    "name:ukr_x_preferred":[
        "\u0422\u0443\u0433\u0430\u043d"
    ],
    "name:urd_x_preferred":[
        "\u062a\u0624\u06af\u0627\u0646"
    ],
    "name:vie_x_preferred":[
        "Tougan"
    ],
    "name:war_x_preferred":[
        "Tougan"
    ],
    "name:zho_cn_x_preferred":[
        "\u56fe\u5188"
    ],
    "name:zho_tw_x_preferred":[
        "\u5716\u5ca1"
    ],
    "name:zho_x_preferred":[
        "\u5934\u5e72"
    ],
    "wof:name":"Tougan",
    "wof:placetype":"locality"
},
  "geometry": {"coordinates":[109.76434999999999,19.63949],"type":"Point"}
}