{
  "type": "Feature",
  "properties": {
    "gn:admin1_code":"31.0",
    "gn:asciiname":"Tougan",
    "gn:country_code":"CN",
    "gn:dem":107,
    "gn:feature_class":"P",
    "gn:feature_code":"PPL",
    "gn:name":"Tougan",
    "gn:population":0,
    "gn:timezone":"Asia/Shanghai",
    "iso:country":"CN",
    "name:ceb_x_preferred":[
        "Tougan"
    ],
    "name:deu_x_preferred":[
        "Tougan"
    ],
    "name:fra_x_preferred":[
        "Tougan"
    ],
    "name:frr_x_preferred":[
        "Tougan"
    ],
    "name:ita_x_preferred":[
        "Tougan"
    ],
    "name:nld_x_preferred":[
        "Tougan"
    ],
    "name:pol_x_preferred":[
        "Tougan"
    ],
    "name:por_x_preferred":[
        "Tougan"
    ],
    "name:ron_x_preferred":[
        "Tougan"
    ],
    "name:rus_x_preferred":[
        "\u0422\u0443\u0433\u0430\u043d"
    ],
    "name:spa_x_preferred":[
        "Tougan"
    ],
    "name:swe_x_preferred":[
        "Tougan"
    ],
    "name:ukr_x_preferred":[
        "\u0422\u0443\u0433\u0430\u043d"
    ],
    "name:urd_x_preferred":[
        "\u062a\u0624\u06af\u0627\u0646"
    ],
    "name:war_x_preferred":[
        "Tougan"
    ],
    "name:zho_x_preferred":[
        "\u5934\u5e72"
    ],
    "wof:name":"Tougan",
    "wof:placetype":"locality"
},
  "geometry": {"coordinates":[109.76434999999999,19.63949],"type":"Point"}
}