{
  "type": "Feature",
  "properties": {
    "gn:admin1_code":"12.0",
    "gn:asciiname":"Luojia'ao",
    "gn:country_code":"CN",
    "gn:dem":75,
    "gn:feature_class":"P",
    "gn:feature_code":"PPL",
    "gn:name":"Luojia\u2019ao",
    "gn:population":0,
    "gn:timezone":"Asia/Shanghai",
    "iso:country":"CN",
    "name:und_x_variant":[
        "Luojia\u2019ao"
    ],
    "name:zho_x_preferred":[
        "\u7f57\u5bb6\u5773"
    ],
    "wof:name":"Luojia'ao",
    "wof:placetype":"locality"
},
  "geometry": {"coordinates":[114.38688999999999,31.33147],"type":"Point"}
}