{
  "type": "Feature",
  "properties": {
    "gn:admin1_code":"04",
    "gn:asciiname":"Shanghai Nongchang",
    "gn:country_code":"CN",
    "gn:dem":4,
    "gn:feature_class":"P",
    "gn:feature_code":"PPLF",
    "gn:name":"Shanghai Nongchang",
    "gn:population":0,
    "gn:timezone":"Asia/Shanghai",
    "iso:country":"CN",
    "name:und_x_variant":[
        "Shang-hai-nung-ch\u2019ang",
        "Shanghai Nongchang"
    ],
    "wof:name":"Shanghai Nongchang",
    "wof:placetype":"locality"
},
  "geometry": {"coordinates":[120.71666999999999,32.96667],"type":"Point"}
}