{
  "type": "Feature",
  "properties": {
    "gn:admin1_code":"7.0",
    "gn:asciiname":"Jincuo",
    "gn:country_code":"CN",
    "gn:dem":31,
    "gn:feature_class":"P",
    "gn:feature_code":"PPL",
    "gn:name":"Jincuo",
    "gn:population":0,
    "gn:timezone":"Asia/Shanghai",
    "iso:country":"CN",
    "name:zho_x_preferred":[
        "\u9526\u539d"
    ],
    "wof:name":"Jincuo",
    "wof:placetype":"locality"
},
  "geometry": {"coordinates":[118.74518999999999,24.9516],"type":"Point"}
}