{
  "type": "Feature",
  "properties": {
    "gn:admin1_code":"19.0",
    "gn:asciiname":"Dongjianguo",
    "gn:country_code":"CN",
    "gn:dem":182,
    "gn:feature_class":"P",
    "gn:feature_code":"PPL",
    "gn:name":"Dongjianguo",
    "gn:population":0,
    "gn:timezone":"Asia/Shanghai",
    "iso:country":"CN",
    "name:zho_x_preferred":[
        "\u4e1c\u78b1\u9505"
    ],
    "wof:name":"Dongjianguo",
    "wof:placetype":"locality"
},
  "geometry": {"coordinates":[121.92,42.2878],"type":"Point"}
}