{
  "type": "Feature",
  "properties": {
    "gn:admin1_code":"24.0",
    "gn:asciiname":"Shilingou",
    "gn:country_code":"CN",
    "gn:dem":1578,
    "gn:feature_class":"P",
    "gn:feature_code":"PPL",
    "gn:name":"Shilingou",
    "gn:population":0,
    "gn:timezone":"Asia/Shanghai",
    "iso:country":"CN",
    "name:zho_x_preferred":[
        "\u77f3\u6797\u6c9f"
    ],
    "wof:name":"Shilingou",
    "wof:placetype":"locality"
},
  "geometry": {"coordinates":[111.33522000000001,38.18727],"type":"Point"}
}