{
  "type": "Feature",
  "properties": {
    "gn:admin1_code":"8.0",
    "gn:asciiname":"Huabincun",
    "gn:country_code":"CN",
    "gn:dem":154,
    "gn:feature_class":"P",
    "gn:feature_code":"PPL",
    "gn:name":"Huabincun",
    "gn:population":0,
    "gn:timezone":"Asia/Shanghai",
    "iso:country":"CN",
    "name:zho_x_preferred":[
        "\u534e\u6ee8\u6751"
    ],
    "wof:name":"Huabincun",
    "wof:placetype":"locality"
},
  "geometry": {"coordinates":[126.50184,45.65928],"type":"Point"}
}