{
  "type": "Feature",
  "properties": {
    "gn:admin1_code":"19.0",
    "gn:asciiname":"Xujiagou",
    "gn:country_code":"CN",
    "gn:dem":286,
    "gn:feature_class":"P",
    "gn:feature_code":"PPL",
    "gn:name":"Xujiagou",
    "gn:population":0,
    "gn:timezone":"Asia/Shanghai",
    "iso:country":"CN",
    "name:und_x_variant":[
        "\u5f90\u5bb6\u6c9f"
    ],
    "name:zho_x_preferred":[
        "\u5f90\u5bb6\u6c9f"
    ],
    "wof:name":"Xujiagou",
    "wof:placetype":"locality"
},
  "geometry": {"coordinates":[123.23989,40.85257],"type":"Point"}
}