{
  "type": "Feature",
  "properties": {
    "gn:admin1_code":"20.0",
    "gn:asciiname":"Nanhala Wusu",
    "gn:country_code":"CN",
    "gn:dem":1605,
    "gn:feature_class":"P",
    "gn:feature_code":"PPL",
    "gn:name":"Nanhala Wusu",
    "gn:population":0,
    "gn:timezone":"Asia/Shanghai",
    "iso:country":"CN",
    "name:und_x_variant":[
        "\u5357\u54c8\u62c9\u4e4c\u7d20"
    ],
    "wof:name":"Nanhala Wusu",
    "wof:placetype":"locality"
},
  "geometry": {"coordinates":[111.43225,41.31237],"type":"Point"}
}