{
  "type": "Feature",
  "properties": {
    "gn:admin1_code":"29.0",
    "gn:asciiname":"Shuimusi",
    "gn:country_code":"CN",
    "gn:dem":2494,
    "gn:feature_class":"P",
    "gn:feature_code":"PPL",
    "gn:name":"Shuimusi",
    "gn:population":0,
    "gn:timezone":"Asia/Shanghai",
    "iso:country":"CN",
    "name:zho_x_preferred":[
        "\u6c34\u76ee\u5bfa"
    ],
    "wof:name":"Shuimusi",
    "wof:placetype":"locality"
},
  "geometry": {"coordinates":[100.616,25.3703],"type":"Point"}
}