{
  "type": "Feature",
  "properties": {
    "gn:admin1_code":"21.0",
    "gn:asciiname":"Xiaojia Jingtang",
    "gn:country_code":"CN",
    "gn:dem":1325,
    "gn:feature_class":"P",
    "gn:feature_code":"PPL",
    "gn:name":"Xiaojia Jingtang",
    "gn:population":0,
    "gn:timezone":"Asia/Shanghai",
    "iso:country":"CN",
    "name:zho_x_preferred":[
        "\u8096\u5bb6\u4e95\u5802"
    ],
    "wof:name":"Xiaojia Jingtang",
    "wof:placetype":"locality"
},
  "geometry": {"coordinates":[106.66500000000001,38.1867],"type":"Point"}
}