{
  "type": "Feature",
  "properties": {
    "gn:admin1_code":"1.0",
    "gn:asciiname":"Jiutangcun",
    "gn:country_code":"CN",
    "gn:dem":16,
    "gn:feature_class":"P",
    "gn:feature_code":"PPL",
    "gn:name":"Jiutangcun",
    "gn:population":0,
    "gn:timezone":"Asia/Shanghai",
    "iso:country":"CN",
    "name:zho_x_preferred":[
        "\u4e5d\u5858\u6751"
    ],
    "wof:name":"Jiutangcun",
    "wof:placetype":"locality"
},
  "geometry": {"coordinates":[117.09220000000001,30.55637],"type":"Point"}
}