{
  "type": "Feature",
  "properties": {
    "gn:admin1_code":"8.0",
    "gn:asciiname":"Guang'en",
    "gn:country_code":"CN",
    "gn:dem":229,
    "gn:feature_class":"P",
    "gn:feature_code":"PPLA4",
    "gn:name":"Guang\u2019en",
    "gn:population":0,
    "gn:timezone":"Asia/Shanghai",
    "iso:country":"CN",
    "name:zho_x_preferred":[
        "Guang\u2019en"
    ],
    "name:zho_x_variant":[
        "\u5149\u6069",
        "Guang\u2019en Xiang",
        "\u5149\u6069\u4e61"
    ],
    "wof:name":"Guang'en",
    "wof:placetype":"locality"
},
  "geometry": {"coordinates":[127.81626,45.64777],"type":"Point"}
}