{
  "type": "Feature",
  "properties": {
    "gn:admin1_code":"4.0",
    "gn:asciiname":"Dingshacun",
    "gn:country_code":"CN",
    "gn:dem":2,
    "gn:feature_class":"P",
    "gn:feature_code":"PPL",
    "gn:name":"Dingshacun",
    "gn:population":0,
    "gn:timezone":"Asia/Shanghai",
    "iso:country":"CN",
    "name:zho_x_preferred":[
        "\u4e01\u6c99\u6751"
    ],
    "wof:name":"Dingshacun",
    "wof:placetype":"locality"
},
  "geometry": {"coordinates":[119.74267999999999,32.95392],"type":"Point"}
}