{
  "type": "Feature",
  "properties": {
    "gn:admin1_code":"2.0",
    "gn:asciiname":"Laohu",
    "gn:country_code":"CN",
    "gn:dem":10,
    "gn:feature_class":"P",
    "gn:feature_code":"PPL",
    "gn:name":"Laohu",
    "gn:population":0,
    "gn:timezone":"Asia/Shanghai",
    "iso:country":"CN",
    "name:zho_x_preferred":[
        "\u6d9d\u6e56"
    ],
    "wof:name":"Laohu",
    "wof:placetype":"locality"
},
  "geometry": {"coordinates":[120.94297,28.11171],"type":"Point"}
}