{
  "type": "Feature",
  "properties": {
    "gn:admin1_code":"25",
    "gn:asciiname":"Guanzhuangzi",
    "gn:country_code":"CN",
    "gn:dem":4,
    "gn:feature_class":"P",
    "gn:feature_code":"PPL",
    "gn:name":"Guanzhuangzi",
    "gn:population":0,
    "gn:timezone":"Asia/Shanghai",
    "iso:country":"CN",
    "name:zho_x_preferred":[
        "\u5173\u5e84\u5b50"
    ],
    "wof:name":"Guanzhuangzi",
    "wof:placetype":"locality"
},
  "geometry": {"coordinates":[117.886,37.884],"type":"Point"}
}