{
  "type": "Feature",
  "properties": {
    "gn:admin1_code":"16",
    "gn:asciiname":"Nanxincun",
    "gn:country_code":"CN",
    "gn:dem":190,
    "gn:feature_class":"P",
    "gn:feature_code":"PPL",
    "gn:name":"Nanxincun",
    "gn:population":0,
    "gn:timezone":"Asia/Shanghai",
    "iso:country":"CN",
    "name:zho_x_preferred":[
        "\u5357\u65b0\u6751"
    ],
    "wof:name":"Nanxincun",
    "wof:placetype":"locality"
},
  "geometry": {"coordinates":[110.276,24.9487],"type":"Point"}
}