{
  "type": "Feature",
  "properties": {
    "gn:admin1_code":"19.0",
    "gn:asciiname":"Yaomutou Yingzi",
    "gn:country_code":"CN",
    "gn:dem":122,
    "gn:feature_class":"P",
    "gn:feature_code":"PPL",
    "gn:name":"Yaomutou Yingzi",
    "gn:population":0,
    "gn:timezone":"Asia/Shanghai",
    "iso:country":"CN",
    "name:zho_x_preferred":[
        "\u8170\u6728\u5934\u8425\u5b50"
    ],
    "wof:name":"Yaomutou Yingzi",
    "wof:placetype":"locality"
},
  "geometry": {"coordinates":[122.29900000000001,42.5516],"type":"Point"}
}