{
  "type": "Feature",
  "properties": {
    "gn:admin1_code":"16.0",
    "gn:asciiname":"Baijiu",
    "gn:country_code":"CN",
    "gn:dem":107,
    "gn:feature_class":"P",
    "gn:feature_code":"PPL",
    "gn:name":"Baijiu",
    "gn:population":0,
    "gn:timezone":"Asia/Shanghai",
    "iso:country":"CN",
    "name:cat_x_preferred":[
        "Baijiu"
    ],
    "name:cdo_x_preferred":[
        "Si\u0115u-ci\u016b"
    ],
    "name:ces_x_preferred":[
        "Paj-\u0165iou"
    ],
    "name:deu_x_preferred":[
        "Baijiu"
    ],
    "name:fin_x_preferred":[
        "Baijiu"
    ],
    "name:fra_x_preferred":[
        "Baijiu"
    ],
    "name:heb_x_preferred":[
        "\u05d1\u05d0\u05d9\u05d2'\u05d9\u05d5"
    ],
    "name:hun_x_preferred":[
        "Pajcsiu"
    ],
    "name:ita_x_preferred":[
        "Baijiu"
    ],
    "name:jpn_x_preferred":[
        "\u767d\u9152"
    ],
    "name:kor_x_preferred":[
        "\ubc14\uc774\uc8fc"
    ],
    "name:lit_x_preferred":[
        "Baltieji g\u0117rimai"
    ],
    "name:nor_x_preferred":[
        "Baijiu"
    ],
    "name:pol_x_preferred":[
        "Baijiu"
    ],
    "name:rus_x_preferred":[
        "\u0411\u0430\u0439\u0446\u0437\u044e"
    ],
    "name:swe_x_preferred":[
        "Baijiu"
    ],
    "name:tur_x_preferred":[
        "Baijiu"
    ],
    "name:uig_x_preferred":[
        "\u0626\u0627\u0642 \u06be\u0627\u0631\u0627\u0642"
    ],
    "name:wuu_x_preferred":[
        "\u767d\u9152"
    ],
    "name:zho_x_preferred":[
        "\u767d\u9e20"
    ],
    "name:zho_x_variant":[
        "\u767d\u9152"
    ],
    "wof:name":"Baijiu",
    "wof:placetype":"locality"
},
  "geometry": {"coordinates":[108.889,22.9378],"type":"Point"}
}