{
  "type": "Feature",
  "properties": {
    "gn:admin1_code":"9.0",
    "gn:asciiname":"Renxiao Weizi",
    "gn:country_code":"CN",
    "gn:dem":40,
    "gn:feature_class":"P",
    "gn:feature_code":"PPL",
    "gn:name":"Renxiao Weizi",
    "gn:population":0,
    "gn:timezone":"Asia/Shanghai",
    "iso:country":"CN",
    "name:zho_x_preferred":[
        "\u4efb\u5c0f\u56f4\u5b50"
    ],
    "wof:name":"Renxiao Weizi",
    "wof:placetype":"locality"
},
  "geometry": {"coordinates":[115.45806,32.38837],"type":"Point"}
}