{
  "type": "Feature",
  "properties": {
    "gn:admin1_code":"13.0",
    "gn:asciiname":"Karjaw",
    "gn:country_code":"CN",
    "gn:dem":1292,
    "gn:feature_class":"P",
    "gn:feature_code":"PPLA4",
    "gn:name":"Karjaw",
    "gn:population":0,
    "gn:timezone":"Asia/Urumqi",
    "iso:country":"CN",
    "name:uig_x_preferred":[
        "K\u0329arjaw"
    ],
    "name:uig_x_variant":[
        "Qarjaw",
        "\u0642\u0627\u0631\u062c\u0627\u06cb",
        "\u049a\u0430\u0440\u0497\u0430\u0432"
    ],
    "name:und_x_variant":[
        "Ka\u2019erjiao",
        "Ka\u2019erjiao Xiang"
    ],
    "name:zho_x_preferred":[
        "\u5580\u5c14\u4ea4"
    ],
    "name:zho_x_variant":[
        "\u5580\u5c14\u4ea4\u4e61"
    ],
    "wof:name":"Karjaw",
    "wof:placetype":"locality"
},
  "geometry": {"coordinates":[86.39848000000001,47.19094000000001],"type":"Point"}
}