{
  "type": "Feature",
  "properties": {
    "gn:admin1_code":"23.0",
    "gn:asciiname":"Lijiatang",
    "gn:country_code":"CN",
    "gn:dem":3,
    "gn:feature_class":"P",
    "gn:feature_code":"PPL",
    "gn:name":"Lijiatang",
    "gn:population":0,
    "gn:timezone":"Asia/Shanghai",
    "iso:country":"CN",
    "name:zho_x_preferred":[
        "Lijiatang"
    ],
    "name:zho_x_variant":[
        "\u674e\u5bb6\u5802"
    ],
    "wof:name":"Lijiatang",
    "wof:placetype":"locality"
},
  "geometry": {"coordinates":[121.50201,31.08501],"type":"Point"}
}