{
  "type": "Feature",
  "properties": {
    "gn:admin1_code":"9.0",
    "gn:asciiname":"Shengwangtai",
    "gn:country_code":"CN",
    "gn:dem":294,
    "gn:feature_class":"P",
    "gn:feature_code":"PPL",
    "gn:name":"Shengwangtai",
    "gn:population":0,
    "gn:timezone":"Asia/Shanghai",
    "iso:country":"CN",
    "name:zho_x_preferred":[
        "\u5723\u738b\u53f0"
    ],
    "wof:name":"Shengwangtai",
    "wof:placetype":"locality"
},
  "geometry": {"coordinates":[112.60554999999999,34.1472],"type":"Point"}
}