{
  "type": "Feature",
  "properties": {
    "gn:admin1_code":"26",
    "gn:asciiname":"Tiangecun",
    "gn:country_code":"CN",
    "gn:dem":494,
    "gn:feature_class":"P",
    "gn:feature_code":"PPL",
    "gn:name":"Tiangecun",
    "gn:population":0,
    "gn:timezone":"Asia/Shanghai",
    "iso:country":"CN",
    "name:und_x_variant":[
        "Tiange"
    ],
    "name:zho_x_preferred":[
        "\u5929\u9601"
    ],
    "name:zho_x_variant":[
        "\u5929\u9601\u6751"
    ],
    "wof:name":"Tiangecun",
    "wof:placetype":"locality"
},
  "geometry": {"coordinates":[108.63536999999999,34.45221],"type":"Point"}
}