{
  "type": "Feature",
  "properties": {
    "gn:admin1_code":"16.0",
    "gn:asciiname":"Gudi",
    "gn:country_code":"CN",
    "gn:dem":125,
    "gn:feature_class":"P",
    "gn:feature_code":"PPL",
    "gn:name":"Gudi",
    "gn:population":0,
    "gn:timezone":"Asia/Shanghai",
    "iso:country":"CN",
    "name:ceb_x_preferred":[
        "Gudi"
    ],
    "name:swe_x_preferred":[
        "Gudi"
    ],
    "name:zho_x_preferred":[
        "\u53e4\u4f4e"
    ],
    "wof:name":"Gudi",
    "wof:placetype":"locality"
},
  "geometry": {"coordinates":[110.754,23.8147],"type":"Point"}
}