{
  "type": "Feature",
  "properties": {
    "gn:admin1_code":"19.0",
    "gn:asciiname":"Gedianzi",
    "gn:country_code":"CN",
    "gn:dem":25,
    "gn:feature_class":"P",
    "gn:feature_code":"PPL",
    "gn:name":"Gedianzi",
    "gn:population":0,
    "gn:timezone":"Asia/Shanghai",
    "iso:country":"CN",
    "name:zho_x_preferred":[
        "\u845b\u7538\u5b50"
    ],
    "wof:name":"Gedianzi",
    "wof:placetype":"locality"
},
  "geometry": {"coordinates":[121.642,39.251],"type":"Point"}
}