{
  "type": "Feature",
  "properties": {
    "gn:admin1_code":"04",
    "gn:asciiname":"Bache",
    "gn:country_code":"CN",
    "gn:dem":6,
    "gn:feature_class":"P",
    "gn:feature_code":"PPL",
    "gn:name":"Bache",
    "gn:population":0,
    "gn:timezone":"Asia/Shanghai",
    "iso:country":"CN",
    "name:bar_x_preferred":[
        "Bache"
    ],
    "name:ceb_x_preferred":[
        "Bache"
    ],
    "name:deu_x_preferred":[
        "Bache"
    ],
    "name:fin_x_preferred":[
        "Bache"
    ],
    "name:pol_x_preferred":[
        "Bache"
    ],
    "name:swe_x_preferred":[
        "Bache"
    ],
    "wof:name":"Bache",
    "wof:placetype":"locality"
},
  "geometry": {"coordinates":[120.6675,31.07688],"type":"Point"}
}