{
  "type": "Feature",
  "properties": {
    "gn:admin1_code":"18.0",
    "gn:asciiname":"Lancaoping",
    "gn:country_code":"CN",
    "gn:dem":265,
    "gn:feature_class":"P",
    "gn:feature_code":"PPL",
    "gn:name":"Lancaoping",
    "gn:population":0,
    "gn:timezone":"Asia/Shanghai",
    "iso:country":"CN",
    "name:zho_x_preferred":[
        "\u70c2\u8349\u576a"
    ],
    "wof:name":"Lancaoping",
    "wof:placetype":"locality"
},
  "geometry": {"coordinates":[109.44799999999999,26.9869],"type":"Point"}
}