{
  "type": "Feature",
  "properties": {
    "gn:admin1_code":"32.0",
    "gn:asciiname":"Baiguowan",
    "gn:country_code":"CN",
    "gn:dem":674,
    "gn:feature_class":"P",
    "gn:feature_code":"PPL",
    "gn:name":"Baiguowan",
    "gn:population":0,
    "gn:timezone":"Asia/Shanghai",
    "iso:country":"CN",
    "name:zho_x_preferred":[
        "\u767d\u679c\u6e7e"
    ],
    "wof:name":"Baiguowan",
    "wof:placetype":"locality"
},
  "geometry": {"coordinates":[104.07088,28.72732],"type":"Point"}
}