{
  "type": "Feature",
  "properties": {
    "gn:admin1_code":"10",
    "gn:asciiname":"Dongjing'an",
    "gn:country_code":"CN",
    "gn:dem":61,
    "gn:feature_class":"P",
    "gn:feature_code":"PPL",
    "gn:name":"Dongjing\u2019an",
    "gn:population":0,
    "gn:timezone":"Asia/Shanghai",
    "iso:country":"CN",
    "name:und_x_variant":[
        "Dongjing\u2019an"
    ],
    "name:zho_x_preferred":[
        "\u4e1c\u9759\u5eb5"
    ],
    "wof:name":"Dongjing'an",
    "wof:placetype":"locality"
},
  "geometry": {"coordinates":[114.574,37.0525],"type":"Point"}
}