{
  "type": "Feature",
  "properties": {
    "gn:admin1_code":"18",
    "gn:asciiname":"Huangjiasi",
    "gn:country_code":"CN",
    "gn:dem":805,
    "gn:feature_class":"P",
    "gn:feature_code":"PPL",
    "gn:name":"Huangjiasi",
    "gn:population":0,
    "gn:timezone":"Asia/Shanghai",
    "iso:country":"CN",
    "name:zho_x_preferred":[
        "\u9ec4\u5bb6\u5bfa"
    ],
    "wof:name":"Huangjiasi",
    "wof:placetype":"locality"
},
  "geometry": {"coordinates":[108.217,27.8572],"type":"Point"}
}