{
  "type": "Feature",
  "properties": {
    "gn:admin1_code":"7.0",
    "gn:asciiname":"Lifenglin",
    "gn:country_code":"CN",
    "gn:dem":784,
    "gn:feature_class":"P",
    "gn:feature_code":"PPL",
    "gn:name":"Lifenglin",
    "gn:population":0,
    "gn:timezone":"Asia/Shanghai",
    "iso:country":"CN",
    "name:zho_x_preferred":[
        "\u91cc\u51e4\u6797"
    ],
    "wof:name":"Lifenglin",
    "wof:placetype":"locality"
},
  "geometry": {"coordinates":[119.01725999999999,26.93951],"type":"Point"}
}