{
  "type": "Feature",
  "properties": {
    "gn:admin1_code":"25.0",
    "gn:asciiname":"Dataoshan",
    "gn:cc2":"CN",
    "gn:country_code":"CN",
    "gn:dem":96,
    "gn:feature_class":"P",
    "gn:feature_code":"PPL",
    "gn:name":"Dataoshan",
    "gn:population":0,
    "gn:timezone":"Asia/Shanghai",
    "iso:country":"CN",
    "name:zho_x_preferred":[
        "\u5927\u6843\u5c71"
    ],
    "wof:name":"Dataoshan",
    "wof:placetype":"locality"
},
  "geometry": {"coordinates":[119.67433,35.86472],"type":"Point"}
}