{
  "type": "Feature",
  "properties": {
    "gn:admin1_code":"9.0",
    "gn:asciiname":"Wangguizhuang",
    "gn:country_code":"CN",
    "gn:dem":59,
    "gn:feature_class":"P",
    "gn:feature_code":"PPL",
    "gn:name":"Wangguizhuang",
    "gn:population":0,
    "gn:timezone":"Asia/Shanghai",
    "iso:country":"CN",
    "name:zho_x_preferred":[
        "\u738b\u8d35\u5e84"
    ],
    "wof:name":"Wangguizhuang",
    "wof:placetype":"locality"
},
  "geometry": {"coordinates":[114.54292,36.00602],"type":"Point"}
}