{
  "type": "Feature",
  "properties": {
    "gn:admin1_code":"29.0",
    "gn:asciiname":"Xiasanba",
    "gn:country_code":"CN",
    "gn:dem":1530,
    "gn:feature_class":"P",
    "gn:feature_code":"PPL",
    "gn:name":"Xiasanba",
    "gn:population":0,
    "gn:timezone":"Asia/Shanghai",
    "iso:country":"CN",
    "name:zho_x_preferred":[
        "\u4e0b\u4e09\u575d"
    ],
    "wof:name":"Xiasanba",
    "wof:placetype":"locality"
},
  "geometry": {"coordinates":[101.295,23.7911],"type":"Point"}
}