{
  "type": "Feature",
  "properties": {
    "gn:admin1_code":"32.0",
    "gn:asciiname":"Gengduo",
    "gn:country_code":"CN",
    "gn:dem":2266,
    "gn:feature_class":"P",
    "gn:feature_code":"PPL",
    "gn:name":"Gengduo",
    "gn:population":0,
    "gn:timezone":"Asia/Shanghai",
    "iso:country":"CN",
    "name:zho_x_preferred":[
        "\u57c2\u591a"
    ],
    "wof:name":"Gengduo",
    "wof:placetype":"locality"
},
  "geometry": {"coordinates":[100.61,28.2161],"type":"Point"}
}