{
  "type": "Feature",
  "properties": {
    "gn:admin1_code":"11.0",
    "gn:asciiname":"Xinxiangkou",
    "gn:country_code":"CN",
    "gn:dem":36,
    "gn:feature_class":"P",
    "gn:feature_code":"PPL",
    "gn:name":"Xinxiangkou",
    "gn:population":0,
    "gn:timezone":"Asia/Shanghai",
    "iso:country":"CN",
    "name:zho_x_preferred":[
        "\u65b0\u5df7\u53e3"
    ],
    "wof:name":"Xinxiangkou",
    "wof:placetype":"locality"
},
  "geometry": {"coordinates":[112.36985,28.70137],"type":"Point"}
}