{
  "type": "Feature",
  "properties": {
    "gn:admin1_code":"14.0",
    "gn:asciiname":"Gyigang",
    "gn:country_code":"CN",
    "gn:dem":3284,
    "gn:feature_class":"P",
    "gn:feature_code":"PPLA3",
    "gn:name":"Gyigang",
    "gn:population":0,
    "gn:timezone":"Asia/Urumqi",
    "iso:country":"CN",
    "name:bod_x_preferred":[
        "Gyigang"
    ],
    "name:msa_x_preferred":[
        "Gyigang"
    ],
    "name:und_x_variant":[
        "Zay\u00fc",
        "Ch\u2019a-y\u00fc",
        "Sang-ang-ch\u2019\u00fc",
        "Chi-kung",
        "Gyigang"
    ],
    "name:zho_x_preferred":[
        "Jigong"
    ],
    "name:zho_x_variant":[
        "\u5409\u516c",
        "Chayu Xian",
        "\u5bdf\u9685\u53bf"
    ],
    "wof:name":"Gyigang",
    "wof:placetype":"locality"
},
  "geometry": {"coordinates":[97.51667,28.66667],"type":"Point"}
}