{
  "type": "Feature",
  "properties": {
    "gn:admin1_code":"12.0",
    "gn:asciiname":"Yaoling",
    "gn:country_code":"CN",
    "gn:dem":470,
    "gn:feature_class":"P",
    "gn:feature_code":"PPL",
    "gn:name":"Yaoling",
    "gn:population":0,
    "gn:timezone":"Asia/Shanghai",
    "iso:country":"CN",
    "name:zho_x_preferred":[
        "\u8170\u5cad"
    ],
    "wof:name":"Yaoling",
    "wof:placetype":"locality"
},
  "geometry": {"coordinates":[110.28994,32.33811],"type":"Point"}
}