{
  "type": "Feature",
  "properties": {
    "gn:admin1_code":"19",
    "gn:asciiname":"Jianchangcun",
    "gn:country_code":"CN",
    "gn:dem":414,
    "gn:feature_class":"P",
    "gn:feature_code":"PPL",
    "gn:name":"Jianchangcun",
    "gn:population":0,
    "gn:timezone":"Asia/Shanghai",
    "iso:country":"CN",
    "name:und_x_variant":[
        "Jianchang"
    ],
    "name:zho_x_preferred":[
        "\u78b1\u5382\u6751"
    ],
    "wof:name":"Jianchangcun",
    "wof:placetype":"locality"
},
  "geometry": {"coordinates":[119.62929,40.64054],"type":"Point"}
}