{
  "type": "Feature",
  "properties": {
    "gn:admin1_code":"32.0",
    "gn:asciiname":"Jinniushan",
    "gn:country_code":"CN",
    "gn:dem":333,
    "gn:feature_class":"P",
    "gn:feature_code":"PPL",
    "gn:name":"Jinniushan",
    "gn:population":0,
    "gn:timezone":"Asia/Shanghai",
    "iso:country":"CN",
    "name:zho_x_preferred":[
        "\u91d1\u725b\u5c71"
    ],
    "wof:name":"Jinniushan",
    "wof:placetype":"locality"
},
  "geometry": {"coordinates":[105.9083,30.82768],"type":"Point"}
}