{
  "type": "Feature",
  "properties": {
    "gn:admin1_code":"24",
    "gn:asciiname":"Tancun",
    "gn:country_code":"CN",
    "gn:dem":995,
    "gn:feature_class":"P",
    "gn:feature_code":"PPL",
    "gn:name":"Tancun",
    "gn:population":0,
    "gn:timezone":"Asia/Shanghai",
    "iso:country":"CN",
    "name:und_x_variant":[
        "T\u2019an-ts\u2019un",
        "Tancun"
    ],
    "name:zho_x_preferred":[
        "\u6f6d\u6751"
    ],
    "wof:name":"Tancun",
    "wof:placetype":"locality"
},
  "geometry": {"coordinates":[112.95583000000001,37.02259],"type":"Point"}
}