{
  "type": "Feature",
  "properties": {
    "gn:admin1_code":"26.0",
    "gn:asciiname":"Baicaoshan",
    "gn:country_code":"CN",
    "gn:dem":1932,
    "gn:feature_class":"P",
    "gn:feature_code":"PPL",
    "gn:name":"Baicaoshan",
    "gn:population":0,
    "gn:timezone":"Asia/Shanghai",
    "iso:country":"CN",
    "name:zho_x_preferred":[
        "\u767d\u8349\u5c71"
    ],
    "wof:name":"Baicaoshan",
    "wof:placetype":"locality"
},
  "geometry": {"coordinates":[106.56516000000001,35.06693],"type":"Point"}
}