{
  "type": "Feature",
  "properties": {
    "gn:admin1_code":"29.0",
    "gn:asciiname":"Zhonghetaoping",
    "gn:country_code":"CN",
    "gn:dem":2118,
    "gn:feature_class":"P",
    "gn:feature_code":"PPL",
    "gn:name":"Zhonghetaoping",
    "gn:population":0,
    "gn:timezone":"Asia/Shanghai",
    "iso:country":"CN",
    "name:zho_x_preferred":[
        "\u4e2d\u6838\u6843\u5e73"
    ],
    "wof:name":"Zhonghetaoping",
    "wof:placetype":"locality"
},
  "geometry": {"coordinates":[99.6892,24.9637],"type":"Point"}
}