{
  "type": "Feature",
  "properties": {
    "gn:admin1_code":"14.0",
    "gn:asciiname":"Rannacun",
    "gn:country_code":"CN",
    "gn:dem":4107,
    "gn:feature_class":"P",
    "gn:feature_code":"PPL",
    "gn:name":"Rannacun",
    "gn:population":0,
    "gn:timezone":"Asia/Urumqi",
    "iso:country":"CN",
    "name:zho_x_preferred":[
        "\u7136\u90a3\u6751"
    ],
    "wof:name":"Rannacun",
    "wof:placetype":"locality"
},
  "geometry": {"coordinates":[96.79130000000001,29.50412],"type":"Point"}
}