{
  "type": "Feature",
  "properties": {
    "gn:admin1_code":"29",
    "gn:asciiname":"Dongshiji",
    "gn:country_code":"CN",
    "gn:dem":1293,
    "gn:feature_class":"P",
    "gn:feature_code":"PPL",
    "gn:name":"Dongshiji",
    "gn:population":0,
    "gn:timezone":"Asia/Shanghai",
    "iso:country":"CN",
    "name:zho_x_preferred":[
        "\u8463\u4ed5\u57fa"
    ],
    "wof:name":"Dongshiji",
    "wof:placetype":"locality"
},
  "geometry": {"coordinates":[105.13800000000001,23.8545],"type":"Point"}
}