{
  "type": "Feature",
  "properties": {
    "gn:admin1_code":"15.0",
    "gn:asciiname":"Lucaogou",
    "gn:country_code":"CN",
    "gn:dem":2275,
    "gn:feature_class":"P",
    "gn:feature_code":"PPL",
    "gn:name":"L\u00fccaogou",
    "gn:population":0,
    "gn:timezone":"Asia/Shanghai",
    "iso:country":"CN",
    "name:und_x_variant":[
        "L\u00fccaogou"
    ],
    "name:zho_x_preferred":[
        "\u7eff\u8349\u6c9f"
    ],
    "wof:name":"Lucaogou",
    "wof:placetype":"locality"
},
  "geometry": {"coordinates":[103.584,37.2629],"type":"Point"}
}