{
  "type": "Feature",
  "properties": {
    "gn:admin1_code":"11.0",
    "gn:asciiname":"Longquan",
    "gn:country_code":"CN",
    "gn:dem":213,
    "gn:feature_class":"P",
    "gn:feature_code":"PPLA3",
    "gn:name":"Longquan",
    "gn:population":0,
    "gn:timezone":"Asia/Shanghai",
    "iso:country":"CN",
    "name:und_x_variant":[
        "Xintian",
        "Sintien-hsien",
        "Hsin-t\u2019ien-hsien",
        "Hsin-t\u2019ien",
        "Longquanzhen",
        "Longquan"
    ],
    "name:zho_x_preferred":[
        "Hsin-t\u2019ien-hsien"
    ],
    "name:zho_x_variant":[
        "Hsin-t\u2019ien"
    ],
    "wof:name":"Longquan",
    "wof:placetype":"locality"
},
  "geometry": {"coordinates":[112.21167,25.90139],"type":"Point"}
}