{
  "type": "Feature",
  "properties": {
    "gn:admin1_code":"3.0",
    "gn:asciiname":"Niutouling",
    "gn:country_code":"CN",
    "gn:dem":462,
    "gn:feature_class":"P",
    "gn:feature_code":"PPL",
    "gn:name":"Niutouling",
    "gn:population":0,
    "gn:timezone":"Asia/Shanghai",
    "iso:country":"CN",
    "name:und_x_variant":[
        "\u725b\u5934\u5cad"
    ],
    "wof:name":"Niutouling",
    "wof:placetype":"locality"
},
  "geometry": {"coordinates":[114.76712000000001,28.6568],"type":"Point"}
}