{
  "type": "Feature",
  "properties": {
    "gn:admin1_code":"11.0",
    "gn:asciiname":"Zhangshuwan",
    "gn:country_code":"CN",
    "gn:dem":116,
    "gn:feature_class":"P",
    "gn:feature_code":"PPL",
    "gn:name":"Zhangshuwan",
    "gn:population":0,
    "gn:timezone":"Asia/Shanghai",
    "iso:country":"CN",
    "name:zho_x_preferred":[
        "\u6a1f\u6811\u6e7e"
    ],
    "wof:name":"Zhangshuwan",
    "wof:placetype":"locality"
},
  "geometry": {"coordinates":[112.54271,27.33433],"type":"Point"}
}