{
  "type": "Feature",
  "properties": {
    "gn:admin1_code":"33.0",
    "gn:asciiname":"Taibai",
    "gn:country_code":"CN",
    "gn:dem":539,
    "gn:feature_class":"P",
    "gn:feature_code":"PPL",
    "gn:name":"Taibai",
    "gn:population":0,
    "gn:timezone":"Asia/Shanghai",
    "iso:country":"CN",
    "name:deu_x_preferred":[
        "Taibai"
    ],
    "name:fra_x_preferred":[
        "Taibai"
    ],
    "name:zho_x_preferred":[
        "\u592a\u767d"
    ],
    "wof:name":"Taibai",
    "wof:placetype":"locality"
},
  "geometry": {"coordinates":[107.46872999999999,30.02451],"type":"Point"}
}