{
  "type": "Feature",
  "properties": {
    "gn:admin1_code":"32.0",
    "gn:asciiname":"Muzhi",
    "gn:country_code":"CN",
    "gn:dem":2078,
    "gn:feature_class":"P",
    "gn:feature_code":"PPL",
    "gn:name":"Muzhi",
    "gn:population":0,
    "gn:timezone":"Asia/Shanghai",
    "iso:country":"CN",
    "name:zho_x_preferred":[
        "\u6728\u679d"
    ],
    "wof:name":"Muzhi",
    "wof:placetype":"locality"
},
  "geometry": {"coordinates":[101.941,31.1721],"type":"Point"}
}