{
  "type": "Feature",
  "properties": {
    "gn:country":"CN",
    "gn:fcode":"PPLA4",
    "gn:pop":159383,
    "iso:country":"CN",
    "name:ara_x_preferred":[
        "\u062e\u064a\u062a\u0634\u064a\u0646\u063a"
    ],
    "name:eng_x_preferred":[
        "Zhicheng"
    ],
    "name:mlg_x_preferred":[
        "Zhicheng"
    ],
    "name:nob_x_preferred":[
        "Zhicheng"
    ],
    "name:por_x_preferred":[
        "Zhicheng"
    ],
    "name:swe_x_preferred":[
        "Zhicheng"
    ],
    "name:unk_x_variant":[
        "Chih-chiang-hsien"
    ],
    "name:zho_x_preferred":[
        "\u679d\u57ce\u9547"
    ],
    "ne:ADM0CAP":0.0,
    "ne:ADM0NAME":"China",
    "ne:ADM0_A3":"CHN",
    "ne:ADM1NAME":"Hubei",
    "ne:ADMIN1_COD":12,
    "ne:CAPALT":0,
    "ne:CHANGED":0,
    "ne:CHECKME":0,
    "ne:COMPARE":0,
    "ne:DIFFASCII":0,
    "ne:ELEVATION":0.0,
    "ne:FEATURECLA":"Populated place",
    "ne:FEATURE_CL":"P",
    "ne:FEATURE_CO":"PPL",
    "ne:GEONAMEID":1784554,
    "ne:GEONAMESNO":"GeoNames spatial join with similar names only.",
    "ne:GN_ASCII":"Zhicheng",
    "ne:GN_POP":159383,
    "ne:GTOPO30":52.0,
    "ne:ISO_A2":"CN",
    "ne:LABELRANK":1,
    "ne:LATITUDE":30.300436,
    "ne:LONGITUDE":111.500005,
    "ne:LS_MATCH":1,
    "ne:LS_NAME":"Zicheng",
    "ne:MAX_AREAKM":261.0,
    "ne:MAX_AREAMI":101.0,
    "ne:MAX_BBXMAX":111.591667,
    "ne:MAX_BBXMIN":111.35,
    "ne:MAX_BBYMAX":30.541667,
    "ne:MAX_BBYMIN":30.208333,
    "ne:MAX_NATSCA":20.0,
    "ne:MAX_PERKM":255.0,
    "ne:MAX_PERMI":158.0,
    "ne:MAX_POP10":225734,
    "ne:MAX_POP20":237042,
    "ne:MAX_POP300":0,
    "ne:MAX_POP310":0,
    "ne:MAX_POP50":0,
    "ne:MEAN_BBXC":111.454607,
    "ne:MEAN_BBYC":30.349534,
    "ne:MEGACITY":0,
    "ne:MIN_AREAKM":246.0,
    "ne:MIN_AREAMI":95.0,
    "ne:MIN_BBXMAX":111.591667,
    "ne:MIN_BBXMIN":111.35,
    "ne:MIN_BBYMAX":30.510084,
    "ne:MIN_BBYMIN":30.208333,
    "ne:MIN_PERKM":235.0,
    "ne:MIN_PERMI":146.0,
    "ne:NAME":"Zicheng",
    "ne:NAMEASCII":"Zicheng",
    "ne:NAMEDIFF":0,
    "ne:NATSCALE":20,
    "ne:POP1950":0,
    "ne:POP1955":0,
    "ne:POP1960":0,
    "ne:POP1965":0,
    "ne:POP1970":0,
    "ne:POP1975":0,
    "ne:POP1980":0,
    "ne:POP1985":0,
    "ne:POP1990":0,
    "ne:POP1995":0,
    "ne:POP2000":0,
    "ne:POP2005":0,
    "ne:POP2010":0,
    "ne:POP2015":0,
    "ne:POP2020":0,
    "ne:POP2025":0,
    "ne:POP2050":0,
    "ne:POP_MAX":237042,
    "ne:POP_MIN":159383,
    "ne:POP_OTHER":283079,
    "ne:RANK_MAX":10,
    "ne:RANK_MIN":9,
    "ne:SCALERANK":7,
    "ne:SOV0NAME":"China",
    "ne:SOV_A3":"CHN",
    "ne:TIMEZONE":"Asia/Chongqing",
    "ne:UN_FID":0,
    "ne:UN_LAT":0.0,
    "ne:UN_LONG":0.0,
    "ne:WORLDCITY":0,
    "qs:name":"\u679d\u57ce\u9547",
    "qs:name_adm0":"\u4e2d\u570b",
    "qs:name_adm1":"\u6e56\u5317\u7701",
    "qs:photos_9k":1,
    "qs:photos_9r":1,
    "qs:photos_all":4,
    "qs:photos_sr":0,
    "qs:placetype":"Town",
    "qs:pop_sr":"10",
    "wof:name":"\u679d\u57ce\u9547",
    "wof:placetype":"locality",
    "wof:population":159383
},
  "geometry": {"coordinates":[111.50472000000001,30.29556],"type":"Point"}
}