{
  "type": "Feature",
  "properties": {
    "gn:admin1_code":"18",
    "gn:asciiname":"Qunjiashan",
    "gn:country_code":"CN",
    "gn:dem":894,
    "gn:feature_class":"P",
    "gn:feature_code":"PPL",
    "gn:name":"Qunjiashan",
    "gn:population":0,
    "gn:timezone":"Asia/Shanghai",
    "iso:country":"CN",
    "name:zho_x_preferred":[
        "\u7fa4\u5bb6\u5c71"
    ],
    "wof:name":"Qunjiashan",
    "wof:placetype":"locality"
},
  "geometry": {"coordinates":[108.182,27.3967],"type":"Point"}
}