{
  "type": "Feature",
  "properties": {
    "gn:admin1_code":"4.0",
    "gn:asciiname":"Zhoupengzhuangcun",
    "gn:country_code":"CN",
    "gn:dem":38,
    "gn:feature_class":"P",
    "gn:feature_code":"PPL",
    "gn:name":"Zhoupengzhuangcun",
    "gn:population":0,
    "gn:timezone":"Asia/Shanghai",
    "iso:country":"CN",
    "name:zho_x_preferred":[
        "\u5468\u5f6d\u5e84\u6751"
    ],
    "wof:name":"Zhoupengzhuangcun",
    "wof:placetype":"locality"
},
  "geometry": {"coordinates":[116.65167,34.83051],"type":"Point"}
}