{
  "type": "Feature",
  "properties": {
    "gn:admin1_code":"11",
    "gn:asciiname":"Baimiaoxiang",
    "gn:cc2":"CN",
    "gn:country_code":"CN",
    "gn:dem":222,
    "gn:feature_class":"P",
    "gn:feature_code":"PPL",
    "gn:name":"Baimiaoxiang",
    "gn:population":0,
    "gn:timezone":"Asia/Shanghai",
    "iso:country":"CN",
    "name:und_x_variant":[
        "Baimiaojing",
        "Baimiaoxiang"
    ],
    "wof:name":"Baimiaoxiang",
    "wof:placetype":"locality"
},
  "geometry": {"coordinates":[111.92749999999999,27.70444],"type":"Point"}
}