{
  "type": "Feature",
  "properties": {
    "gn:admin1_code":"16.0",
    "gn:asciiname":"Zhongjiantang",
    "gn:country_code":"CN",
    "gn:dem":97,
    "gn:feature_class":"P",
    "gn:feature_code":"PPL",
    "gn:name":"Zhongjiantang",
    "gn:population":0,
    "gn:timezone":"Asia/Shanghai",
    "iso:country":"CN",
    "name:zho_x_preferred":[
        "\u4e2d\u95f4\u5858"
    ],
    "wof:name":"Zhongjiantang",
    "wof:placetype":"locality"
},
  "geometry": {"coordinates":[110.462,22.2145],"type":"Point"}
}