{
  "type": "Feature",
  "properties": {
    "gn:admin1_code":"24.0",
    "gn:asciiname":"Qianjiazhuangcun",
    "gn:country_code":"CN",
    "gn:dem":1032,
    "gn:feature_class":"P",
    "gn:feature_code":"PPL",
    "gn:name":"Qianjiazhuangcun",
    "gn:population":0,
    "gn:timezone":"Asia/Shanghai",
    "iso:country":"CN",
    "name:zho_x_preferred":[
        "\u5343\u5bb6\u5e84\u6751"
    ],
    "wof:name":"Qianjiazhuangcun",
    "wof:placetype":"locality"
},
  "geometry": {"coordinates":[110.94425,36.73398],"type":"Point"}
}