{
  "type": "Feature",
  "properties": {
    "gn:admin1_code":"10",
    "gn:asciiname":"Xizangzhuang",
    "gn:country_code":"CN",
    "gn:dem":7,
    "gn:feature_class":"P",
    "gn:feature_code":"PPL",
    "gn:name":"Xizangzhuang",
    "gn:population":0,
    "gn:timezone":"Asia/Shanghai",
    "iso:country":"CN",
    "name:zho_x_preferred":[
        "\u897f\u81e7\u5e84"
    ],
    "wof:name":"Xizangzhuang",
    "wof:placetype":"locality"
},
  "geometry": {"coordinates":[116.726,38.8225],"type":"Point"}
}