{
  "type": "Feature",
  "properties": {
    "gn:admin1_code":"32.0",
    "gn:asciiname":"Shufangwan",
    "gn:country_code":"CN",
    "gn:dem":392,
    "gn:feature_class":"P",
    "gn:feature_code":"PPL",
    "gn:name":"Shufangwan",
    "gn:population":0,
    "gn:timezone":"Asia/Shanghai",
    "iso:country":"CN",
    "name:zho_x_preferred":[
        "\u4e66\u623f\u6e7e"
    ],
    "wof:name":"Shufangwan",
    "wof:placetype":"locality"
},
  "geometry": {"coordinates":[104.97607000000001,30.54499],"type":"Point"}
}