{
  "type": "Feature",
  "properties": {
    "gn:admin1_code":"3.0",
    "gn:asciiname":"Yaoshang",
    "gn:country_code":"CN",
    "gn:dem":84,
    "gn:feature_class":"P",
    "gn:feature_code":"PPL",
    "gn:name":"Yaoshang",
    "gn:population":0,
    "gn:timezone":"Asia/Shanghai",
    "iso:country":"CN",
    "name:und_x_variant":[
        "\u7a91\u4e0a"
    ],
    "wof:name":"Yaoshang",
    "wof:placetype":"locality"
},
  "geometry": {"coordinates":[114.75055999999999,27.3997],"type":"Point"}
}