{
  "type": "Feature",
  "properties": {
    "gn:admin1_code":"11.0",
    "gn:asciiname":"Shuangjiajiao",
    "gn:country_code":"CN",
    "gn:dem":32,
    "gn:feature_class":"P",
    "gn:feature_code":"PPL",
    "gn:name":"Shuangjiajiao",
    "gn:population":0,
    "gn:timezone":"Asia/Shanghai",
    "iso:country":"CN",
    "name:zho_x_preferred":[
        "Shuangjiajiao"
    ],
    "name:zho_x_variant":[
        "\u53cc\u5bb6\u89d2"
    ],
    "wof:name":"Shuangjiajiao",
    "wof:placetype":"locality"
},
  "geometry": {"coordinates":[111.86051999999999,28.97237],"type":"Point"}
}