{
  "type": "Feature",
  "properties": {
    "gn:admin1_code":"29.0",
    "gn:asciiname":"Xiaozhelan",
    "gn:country_code":"CN",
    "gn:dem":482,
    "gn:feature_class":"P",
    "gn:feature_code":"PPL",
    "gn:name":"Xiaozhelan",
    "gn:population":0,
    "gn:timezone":"Asia/Shanghai",
    "iso:country":"CN",
    "name:zho_x_preferred":[
        "\u5c0f\u8005\u5170"
    ],
    "wof:name":"Xiaozhelan",
    "wof:placetype":"locality"
},
  "geometry": {"coordinates":[103.553,22.8058],"type":"Point"}
}