{
  "type": "Feature",
  "properties": {
    "gn:admin1_code":"18.0",
    "gn:asciiname":"Longtang'ao",
    "gn:country_code":"CN",
    "gn:dem":880,
    "gn:feature_class":"P",
    "gn:feature_code":"PPL",
    "gn:name":"Longtang\u2019ao",
    "gn:population":0,
    "gn:timezone":"Asia/Shanghai",
    "iso:country":"CN",
    "name:und_x_variant":[
        "Longtang\u2019ao"
    ],
    "name:zho_x_preferred":[
        "\u9f99\u5858\u5773"
    ],
    "wof:name":"Longtang'ao",
    "wof:placetype":"locality"
},
  "geometry": {"coordinates":[108.51300000000001,27.607],"type":"Point"}
}