{
  "type": "Feature",
  "properties": {
    "gn:admin1_code":"18",
    "gn:asciiname":"Zheyang",
    "gn:country_code":"CN",
    "gn:dem":599,
    "gn:feature_class":"P",
    "gn:feature_code":"PPL",
    "gn:name":"Zheyang",
    "gn:population":0,
    "gn:timezone":"Asia/Shanghai",
    "iso:country":"CN",
    "name:zho_x_preferred":[
        "\u8fd9\u592e"
    ],
    "wof:name":"Zheyang",
    "wof:placetype":"locality"
},
  "geometry": {"coordinates":[105.913,25.4626],"type":"Point"}
}