{
  "type": "Feature",
  "properties": {
    "gn:admin1_code":"18.0",
    "gn:asciiname":"Fati",
    "gn:country_code":"CN",
    "gn:dem":1544,
    "gn:feature_class":"P",
    "gn:feature_code":"PPL",
    "gn:name":"Fati",
    "gn:population":0,
    "gn:timezone":"Asia/Shanghai",
    "iso:country":"CN",
    "name:fra_x_preferred":[
        "Fati"
    ],
    "wof:name":"Fati",
    "wof:placetype":"locality"
},
  "geometry": {"coordinates":[104.74167,26.15],"type":"Point"}
}