{
  "type": "Feature",
  "properties": {
    "gn:admin1_code":"14.0",
    "gn:asciiname":"Meituoli",
    "gn:country_code":"CN",
    "gn:dem":4580,
    "gn:feature_class":"P",
    "gn:feature_code":"PPL",
    "gn:name":"Meituoli",
    "gn:population":0,
    "gn:timezone":"Asia/Urumqi",
    "iso:country":"CN",
    "name:zho_x_preferred":[
        "\u6885\u6258\u5229"
    ],
    "wof:name":"Meituoli",
    "wof:placetype":"locality"
},
  "geometry": {"coordinates":[95.71409,31.06396],"type":"Point"}
}