{
  "type": "Feature",
  "properties": {
    "gn:admin1_code":"25",
    "gn:asciiname":"Bashuihe",
    "gn:country_code":"CN",
    "gn:dem":57,
    "gn:feature_class":"P",
    "gn:feature_code":"PPL",
    "gn:name":"Bashuihe",
    "gn:population":0,
    "gn:timezone":"Asia/Shanghai",
    "iso:country":"CN",
    "name:zho_x_preferred":[
        "\u516b\u6c34\u6cb3"
    ],
    "wof:name":"Bashuihe",
    "wof:placetype":"locality"
},
  "geometry": {"coordinates":[120.65778,36.13528],"type":"Point"}
}