{
  "type": "Feature",
  "properties": {
    "gn:admin1_code":"18.0",
    "gn:asciiname":"De'e Xiazhai",
    "gn:country_code":"CN",
    "gn:dem":267,
    "gn:feature_class":"P",
    "gn:feature_code":"PPL",
    "gn:name":"De\u2019e Xiazhai",
    "gn:population":0,
    "gn:timezone":"Asia/Shanghai",
    "iso:country":"CN",
    "name:und_x_variant":[
        "De\u2019e Xiazhai"
    ],
    "name:zho_x_preferred":[
        "\u5fb7\u9e45\u4e0b\u5be8"
    ],
    "wof:name":"De'e Xiazhai",
    "wof:placetype":"locality"
},
  "geometry": {"coordinates":[109.247,25.8258],"type":"Point"}
}