{
  "type": "Feature",
  "properties": {
    "gn:admin1_code":"3.0",
    "gn:asciiname":"Bailuqian",
    "gn:country_code":"CN",
    "gn:dem":485,
    "gn:feature_class":"P",
    "gn:feature_code":"PPL",
    "gn:name":"Bailuqian",
    "gn:population":0,
    "gn:timezone":"Asia/Shanghai",
    "iso:country":"CN",
    "name:und_x_variant":[
        "\u767d\u8def\u524d"
    ],
    "wof:name":"Bailuqian",
    "wof:placetype":"locality"
},
  "geometry": {"coordinates":[116.16079000000001,26.53501],"type":"Point"}
}