{
  "type": "Feature",
  "properties": {
    "gn:admin1_code":"32.0",
    "gn:asciiname":"Duobao",
    "gn:country_code":"CN",
    "gn:dem":1807,
    "gn:feature_class":"P",
    "gn:feature_code":"PPL",
    "gn:name":"Duobao",
    "gn:population":0,
    "gn:timezone":"Asia/Shanghai",
    "iso:country":"CN",
    "name:zho_x_preferred":[
        "\u579b\u5b9d"
    ],
    "wof:name":"Duobao",
    "wof:placetype":"locality"
},
  "geometry": {"coordinates":[102.239,26.6439],"type":"Point"}
}