{
  "type": "Feature",
  "properties": {
    "gn:admin1_code":"2",
    "gn:asciiname":"Jiankeng",
    "gn:country_code":"CN",
    "gn:dem":970,
    "gn:feature_class":"P",
    "gn:feature_code":"PPL",
    "gn:name":"Jiankeng",
    "gn:population":0,
    "gn:timezone":"Asia/Shanghai",
    "iso:country":"CN",
    "name:und_x_variant":[
        "\u8350\u5751"
    ],
    "wof:name":"Jiankeng",
    "wof:placetype":"locality"
},
  "geometry": {"coordinates":[119.17167000000001,27.46556],"type":"Point"}
}