{
  "type": "Feature",
  "properties": {
    "gn:admin1_code":"5",
    "gn:asciiname":"Daxingchuan Xitun",
    "gn:country_code":"CN",
    "gn:dem":666,
    "gn:feature_class":"P",
    "gn:feature_code":"PPL",
    "gn:name":"Daxingchuan Xitun",
    "gn:population":0,
    "gn:timezone":"Asia/Shanghai",
    "iso:country":"CN",
    "name:zho_x_preferred":[
        "\u5927\u5174\u5ddd\u897f\u5c6f"
    ],
    "wof:name":"Daxingchuan Xitun",
    "wof:placetype":"locality"
},
  "geometry": {"coordinates":[127.91800000000001,43.2504],"type":"Point"}
}