{
  "type": "Feature",
  "properties": {
    "gn:admin1_code":"30",
    "gn:asciiname":"Liangxi",
    "gn:country_code":"CN",
    "gn:dem":172,
    "gn:feature_class":"P",
    "gn:feature_code":"PPL",
    "gn:name":"Liangxi",
    "gn:population":0,
    "gn:timezone":"Asia/Shanghai",
    "iso:country":"CN",
    "name:und_x_variant":[
        "\u7cae\u6eaa"
    ],
    "wof:name":"Liangxi",
    "wof:placetype":"locality"
},
  "geometry": {"coordinates":[115.01328999999998,24.36878],"type":"Point"}
}