{
  "type": "Feature",
  "properties": {
    "gn:admin1_code":"32.0",
    "gn:asciiname":"Maoziyan",
    "gn:country_code":"CN",
    "gn:dem":1132,
    "gn:feature_class":"P",
    "gn:feature_code":"PPL",
    "gn:name":"Maoziyan",
    "gn:population":0,
    "gn:timezone":"Asia/Shanghai",
    "iso:country":"CN",
    "name:zho_x_preferred":[
        "\u732b\u5b50\u5ca9"
    ],
    "wof:name":"Maoziyan",
    "wof:placetype":"locality"
},
  "geometry": {"coordinates":[102.57299999999999,30.0399],"type":"Point"}
}