{
  "type": "Feature",
  "properties": {
    "gn:admin1_code":"32.0",
    "gn:asciiname":"Changguo",
    "gn:country_code":"CN",
    "gn:dem":3826,
    "gn:feature_class":"P",
    "gn:feature_code":"PPL",
    "gn:name":"Changguo",
    "gn:population":0,
    "gn:timezone":"Asia/Urumqi",
    "iso:country":"CN",
    "name:zho_x_preferred":[
        "\u660c\u8fc7"
    ],
    "wof:name":"Changguo",
    "wof:placetype":"locality"
},
  "geometry": {"coordinates":[97.42165,32.74335],"type":"Point"}
}