{
  "type": "Feature",
  "properties": {
    "gn:admin1_code":"10",
    "gn:asciiname":"Fanzhuang",
    "gn:country_code":"CN",
    "gn:dem":45,
    "gn:feature_class":"P",
    "gn:feature_code":"PPL",
    "gn:name":"Fanzhuang",
    "gn:population":0,
    "gn:timezone":"Asia/Shanghai",
    "iso:country":"CN",
    "name:zho_x_preferred":[
        "\u6a0a\u5e84"
    ],
    "name:zho_x_variant":[
        "\u8303\u5e84\u9547"
    ],
    "wof:name":"Fanzhuang",
    "wof:placetype":"locality"
},
  "geometry": {"coordinates":[115.06576,36.62395],"type":"Point"}
}