{
  "type": "Feature",
  "properties": {
    "gn:admin1_code":"02",
    "gn:asciiname":"Chou-chia-shih-ch'iao",
    "gn:country_code":"CN",
    "gn:dem":8,
    "gn:feature_class":"P",
    "gn:feature_code":"PPL",
    "gn:name":"Chou-chia-shih-ch\u2019iao",
    "gn:population":0,
    "gn:timezone":"Asia/Shanghai",
    "iso:country":"CN",
    "wof:name":"Chou-chia-shih-ch'iao",
    "wof:placetype":"locality"
},
  "geometry": {"coordinates":[121.10583,30.63806],"type":"Point"}
}