{
  "type": "Feature",
  "properties": {
    "gn:admin1_code":"15.0",
    "gn:asciiname":"Zhahazui",
    "gn:country_code":"CN",
    "gn:dem":2547,
    "gn:feature_class":"P",
    "gn:feature_code":"PPL",
    "gn:name":"Zhahazui",
    "gn:population":0,
    "gn:timezone":"Asia/Shanghai",
    "iso:country":"CN",
    "name:und_x_variant":[
        "\u624e\u54c8\u5480"
    ],
    "wof:name":"Zhahazui",
    "wof:placetype":"locality"
},
  "geometry": {"coordinates":[104.54165999999999,34.48429],"type":"Point"}
}