{
  "type": "Feature",
  "properties": {
    "gn:admin1_code":"8.0",
    "gn:asciiname":"Mingshang Badui",
    "gn:country_code":"CN",
    "gn:dem":69,
    "gn:feature_class":"P",
    "gn:feature_code":"PPLF",
    "gn:name":"Mingshang Badui",
    "gn:population":0,
    "gn:timezone":"Asia/Shanghai",
    "iso:country":"CN",
    "name:zho_x_preferred":[
        "\u540d\u5c71\u516b\u961f"
    ],
    "wof:name":"Mingshang Badui",
    "wof:placetype":"locality"
},
  "geometry": {"coordinates":[131.13061999999999,47.66951],"type":"Point"}
}