{
  "type": "Feature",
  "properties": {
    "gn:admin1_code":"16.0",
    "gn:asciiname":"Guashan",
    "gn:country_code":"CN",
    "gn:dem":43,
    "gn:feature_class":"P",
    "gn:feature_code":"PPL",
    "gn:name":"Guashan",
    "gn:population":0,
    "gn:timezone":"Asia/Shanghai",
    "iso:country":"CN",
    "name:zho_x_preferred":[
        "\u74dc\u5c71"
    ],
    "wof:name":"Guashan",
    "wof:placetype":"locality"
},
  "geometry": {"coordinates":[109.396,21.6811],"type":"Point"}
}