{
  "type": "Feature",
  "properties": {
    "gn:admin1_code":"15.0",
    "gn:asciiname":"Chuanzi",
    "gn:country_code":"CN",
    "gn:dem":2430,
    "gn:feature_class":"P",
    "gn:feature_code":"PPL",
    "gn:name":"Chuanzi",
    "gn:population":0,
    "gn:timezone":"Asia/Shanghai",
    "iso:country":"CN",
    "name:zho_x_preferred":[
        "\u5ddd\u5b50"
    ],
    "wof:name":"Chuanzi",
    "wof:placetype":"locality"
},
  "geometry": {"coordinates":[104.146,35.3356],"type":"Point"}
}