{
  "type": "Feature",
  "properties": {
    "gn:admin1_code":"11.0",
    "gn:asciiname":"Biejiangkou",
    "gn:country_code":"CN",
    "gn:dem":366,
    "gn:feature_class":"P",
    "gn:feature_code":"PPL",
    "gn:name":"Biejiangkou",
    "gn:population":0,
    "gn:timezone":"Asia/Shanghai",
    "iso:country":"CN",
    "name:zho_x_preferred":[
        "\u522b\u6c5f\u53e3"
    ],
    "wof:name":"Biejiangkou",
    "wof:placetype":"locality"
},
  "geometry": {"coordinates":[111.98229000000001,25.33059],"type":"Point"}
}