{
  "type": "Feature",
  "properties": {
    "gn:admin1_code":"8.0",
    "gn:asciiname":"Hediyingzi",
    "gn:country_code":"CN",
    "gn:dem":112,
    "gn:feature_class":"P",
    "gn:feature_code":"PPL",
    "gn:name":"Hediyingzi",
    "gn:population":0,
    "gn:timezone":"Asia/Shanghai",
    "iso:country":"CN",
    "name:zho_x_preferred":[
        "\u4f55\u5730\u8425\u5b50"
    ],
    "wof:name":"Hediyingzi",
    "wof:placetype":"locality"
},
  "geometry": {"coordinates":[128.05462,49.49069],"type":"Point"}
}