{
  "type": "Feature",
  "properties": {
    "gn:admin1_code":"9.0",
    "gn:asciiname":"Xiazhai",
    "gn:country_code":"CN",
    "gn:dem":396,
    "gn:feature_class":"P",
    "gn:feature_code":"PPL",
    "gn:name":"Xiazhai",
    "gn:population":0,
    "gn:timezone":"Asia/Shanghai",
    "iso:country":"CN",
    "name:deu_x_preferred":[
        "Xiazhai"
    ],
    "name:zho_x_preferred":[
        "\u4e0b\u5be8"
    ],
    "wof:name":"Xiazhai",
    "wof:placetype":"locality"
},
  "geometry": {"coordinates":[111.08843,34.69626],"type":"Point"}
}