{
  "type": "Feature",
  "properties": {
    "gn:admin1_code":"32.0",
    "gn:asciiname":"Benda",
    "gn:country_code":"CN",
    "gn:dem":3493,
    "gn:feature_class":"P",
    "gn:feature_code":"PPL",
    "gn:name":"Benda",
    "gn:population":0,
    "gn:timezone":"Asia/Shanghai",
    "iso:country":"CN",
    "name:cat_x_preferred":[
        "Benda"
    ],
    "name:ceb_x_preferred":[
        "Benda"
    ],
    "name:ces_x_preferred":[
        "Benda"
    ],
    "name:deu_x_preferred":[
        "Benda"
    ],
    "name:eus_x_preferred":[
        "Benda"
    ],
    "name:fra_x_preferred":[
        "Benda"
    ],
    "name:glg_x_preferred":[
        "Benda"
    ],
    "name:heb_x_preferred":[
        "\u05d1\u05e0\u05d3\u05d4"
    ],
    "name:ind_x_preferred":[
        "Benda"
    ],
    "name:ita_x_preferred":[
        "Benda"
    ],
    "name:jpn_x_preferred":[
        "\u30d9\u30f3\u30c0"
    ],
    "name:nld_x_preferred":[
        "Benda"
    ],
    "name:pol_x_preferred":[
        "Benda"
    ],
    "name:por_x_preferred":[
        "Benda"
    ],
    "name:rus_x_preferred":[
        "\u0411\u0435\u043d\u0434\u0430"
    ],
    "name:slv_x_preferred":[
        "Benda"
    ],
    "name:swe_x_preferred":[
        "Benda"
    ],
    "name:ukr_x_preferred":[
        "\u0411\u0435\u043d\u0434\u0430"
    ],
    "name:und_x_variant":[
        "Deka",
        "P\u00eanda",
        "Benda"
    ],
    "name:zho_x_preferred":[
        "\u5954\u8fbe"
    ],
    "wof:name":"Benda",
    "wof:placetype":"locality"
},
  "geometry": {"coordinates":[97.51036000000001,32.65951],"type":"Point"}
}