{
  "type": "Feature",
  "properties": {
    "gn:admin1_code":"32.0",
    "gn:asciiname":"Benda",
    "gn:country_code":"CN",
    "gn:dem":3493,
    "gn:feature_class":"P",
    "gn:feature_code":"PPL",
    "gn:name":"Benda",
    "gn:population":0,
    "gn:timezone":"Asia/Shanghai",
    "iso:country":"CN",
    "name:und_x_variant":[
        "Deka",
        "P\u00eanda",
        "Benda"
    ],
    "name:zho_x_preferred":[
        "\u5954\u8fbe"
    ],
    "wof:name":"Benda",
    "wof:placetype":"locality"
},
  "geometry": {"coordinates":[97.51036000000001,32.65951],"type":"Point"}
}