{
  "type": "Feature",
  "properties": {
    "gn:admin1_code":"22.0",
    "gn:asciiname":"Tuanshan",
    "gn:country_code":"CN",
    "gn:dem":510,
    "gn:feature_class":"P",
    "gn:feature_code":"PPL",
    "gn:name":"Tuanshan",
    "gn:population":0,
    "gn:timezone":"Asia/Shanghai",
    "iso:country":"CN",
    "name:zho_x_preferred":[
        "\u56e2\u5c71"
    ],
    "wof:name":"Tuanshan",
    "wof:placetype":"locality"
},
  "geometry": {"coordinates":[116.08807,40.52908],"type":"Point"}
}