{
  "type": "Feature",
  "properties": {
    "gn:admin1_code":"02",
    "gn:asciiname":"Da'aoling",
    "gn:country_code":"CN",
    "gn:dem":84,
    "gn:feature_class":"P",
    "gn:feature_code":"PPL",
    "gn:name":"Da\u2019aoling",
    "gn:population":0,
    "gn:timezone":"Asia/Shanghai",
    "iso:country":"CN",
    "name:zho_x_preferred":[
        "Da\u2019aoling"
    ],
    "wof:name":"Da'aoling",
    "wof:placetype":"locality"
},
  "geometry": {"coordinates":[121.13978,27.7999],"type":"Point"}
}