{
  "type": "Feature",
  "properties": {
    "gn:admin1_code":"12.0",
    "gn:asciiname":"Taiziqiao",
    "gn:country_code":"CN",
    "gn:dem":68,
    "gn:feature_class":"P",
    "gn:feature_code":"PPL",
    "gn:name":"Taiziqiao",
    "gn:population":0,
    "gn:timezone":"Asia/Shanghai",
    "iso:country":"CN",
    "name:zho_x_preferred":[
        "Taiziqiao"
    ],
    "name:zho_x_variant":[
        "\u592a\u5b50\u6865"
    ],
    "wof:name":"Taiziqiao",
    "wof:placetype":"locality"
},
  "geometry": {"coordinates":[111.77319,30.83102],"type":"Point"}
}