{
  "type": "Feature",
  "properties": {
    "gn:admin1_code":"30.0",
    "gn:asciiname":"Shangliantang",
    "gn:country_code":"CN",
    "gn:dem":25,
    "gn:feature_class":"P",
    "gn:feature_code":"PPL",
    "gn:name":"Shangliantang",
    "gn:population":0,
    "gn:timezone":"Asia/Shanghai",
    "iso:country":"CN",
    "name:zho_x_preferred":[
        "\u4e0a\u83b2\u5858"
    ],
    "wof:name":"Shangliantang",
    "wof:placetype":"locality"
},
  "geometry": {"coordinates":[113.8379,23.35605],"type":"Point"}
}