{
  "type": "Feature",
  "properties": {
    "gn:admin1_code":"29.0",
    "gn:asciiname":"Sipailaduo",
    "gn:country_code":"CN",
    "gn:dem":1910,
    "gn:feature_class":"P",
    "gn:feature_code":"PPL",
    "gn:name":"Sipailaduo",
    "gn:population":0,
    "gn:timezone":"Asia/Shanghai",
    "iso:country":"CN",
    "name:zho_x_preferred":[
        "\u56db\u6392\u62c9\u591a"
    ],
    "wof:name":"Sipailaduo",
    "wof:placetype":"locality"
},
  "geometry": {"coordinates":[98.8312,26.1162],"type":"Point"}
}