{
  "type": "Feature",
  "properties": {
    "gn:admin1_code":"13.0",
    "gn:asciiname":"Jiayimazha",
    "gn:country_code":"CN",
    "gn:dem":1227,
    "gn:feature_class":"P",
    "gn:feature_code":"PPL",
    "gn:name":"Jiayimazha",
    "gn:population":0,
    "gn:timezone":"Asia/Shanghai",
    "iso:country":"CN",
    "name:zho_x_preferred":[
        "\u52a0\u4f9d\u9ebb\u624e"
    ],
    "wof:name":"Jiayimazha",
    "wof:placetype":"locality"
},
  "geometry": {"coordinates":[76.50171,39.05626],"type":"Point"}
}