{
  "type": "Feature",
  "properties": {
    "gn:admin1_code":"12.0",
    "gn:asciiname":"Yaowangtai",
    "gn:country_code":"CN",
    "gn:dem":36,
    "gn:feature_class":"P",
    "gn:feature_code":"PPL",
    "gn:name":"Yaowangtai",
    "gn:population":0,
    "gn:timezone":"Asia/Shanghai",
    "iso:country":"CN",
    "name:zho_x_preferred":[
        "\u59da\u738b\u53f0"
    ],
    "wof:name":"Yaowangtai",
    "wof:placetype":"locality"
},
  "geometry": {"coordinates":[112.67442,30.84541],"type":"Point"}
}