{
  "type": "Feature",
  "properties": {
    "gn:admin1_code":"32.0",
    "gn:asciiname":"Qixingtang",
    "gn:country_code":"CN",
    "gn:dem":3669,
    "gn:feature_class":"P",
    "gn:feature_code":"PPL",
    "gn:name":"Qixingtang",
    "gn:population":0,
    "gn:timezone":"Asia/Shanghai",
    "iso:country":"CN",
    "name:zho_x_preferred":[
        "\u4e03\u661f\u5802"
    ],
    "wof:name":"Qixingtang",
    "wof:placetype":"locality"
},
  "geometry": {"coordinates":[100.715,31.6321],"type":"Point"}
}