{
  "type": "Feature",
  "properties": {
    "gn:admin1_code":"18.0",
    "gn:asciiname":"Rongxincun",
    "gn:country_code":"CN",
    "gn:dem":308,
    "gn:feature_class":"P",
    "gn:feature_code":"PPL",
    "gn:name":"Rongxincun",
    "gn:population":0,
    "gn:timezone":"Asia/Shanghai",
    "iso:country":"CN",
    "name:zho_x_preferred":[
        "\u6995\u65b0\u6751"
    ],
    "wof:name":"Rongxincun",
    "wof:placetype":"locality"
},
  "geometry": {"coordinates":[109.09099999999999,25.9241],"type":"Point"}
}