{
  "type": "Feature",
  "properties": {
    "gn:admin1_code":"18",
    "gn:asciiname":"Langfengguan",
    "gn:country_code":"CN",
    "gn:dem":1318,
    "gn:feature_class":"P",
    "gn:feature_code":"PPL",
    "gn:name":"Langfengguan",
    "gn:population":0,
    "gn:timezone":"Asia/Shanghai",
    "iso:country":"CN",
    "name:zho_x_preferred":[
        "\u6d6a\u98ce\u5173"
    ],
    "wof:name":"Langfengguan",
    "wof:placetype":"locality"
},
  "geometry": {"coordinates":[105.889,25.9924],"type":"Point"}
}