{
  "type": "Feature",
  "properties": {
    "gn:admin1_code":"3.0",
    "gn:asciiname":"Jiangjiali",
    "gn:country_code":"CN",
    "gn:dem":129,
    "gn:feature_class":"P",
    "gn:feature_code":"PPL",
    "gn:name":"Jiangjiali",
    "gn:population":0,
    "gn:timezone":"Asia/Shanghai",
    "iso:country":"CN",
    "name:und_x_variant":[
        "\u6c5f\u5bb6\u91cc"
    ],
    "wof:name":"Jiangjiali",
    "wof:placetype":"locality"
},
  "geometry": {"coordinates":[114.31201,28.14735],"type":"Point"}
}