{
  "type": "Feature",
  "properties": {
    "gn:admin1_code":"11.0",
    "gn:asciiname":"Lao'anchang",
    "gn:country_code":"CN",
    "gn:dem":305,
    "gn:feature_class":"P",
    "gn:feature_code":"PPL",
    "gn:name":"Lao\u2019anchang",
    "gn:population":0,
    "gn:timezone":"Asia/Shanghai",
    "iso:country":"CN",
    "name:zho_x_preferred":[
        "Lao\u2019anchang"
    ],
    "name:zho_x_variant":[
        "\u8001\u5b89\u573a"
    ],
    "wof:name":"Lao'anchang",
    "wof:placetype":"locality"
},
  "geometry": {"coordinates":[114.04456999999999,28.39738],"type":"Point"}
}