{
  "type": "Feature",
  "properties": {
    "gn:admin1_code":"4.0",
    "gn:asciiname":"Dongshenxu",
    "gn:country_code":"CN",
    "gn:dem":9,
    "gn:feature_class":"P",
    "gn:feature_code":"PPL",
    "gn:name":"Dongshenxu",
    "gn:population":0,
    "gn:timezone":"Asia/Shanghai",
    "iso:country":"CN",
    "name:zho_x_preferred":[
        "\u4e1c\u795e\u5729"
    ],
    "wof:name":"Dongshenxu",
    "wof:placetype":"locality"
},
  "geometry": {"coordinates":[119.44513000000001,31.58061],"type":"Point"}
}