{
  "type": "Feature",
  "properties": {
    "gn:admin1_code":"7.0",
    "gn:asciiname":"Chi'an",
    "gn:country_code":"CN",
    "gn:dem":615,
    "gn:feature_class":"P",
    "gn:feature_code":"PPL",
    "gn:name":"Chi\u2019an",
    "gn:population":0,
    "gn:timezone":"Asia/Shanghai",
    "iso:country":"CN",
    "name:und_x_variant":[
        "Chi\u2019an"
    ],
    "name:zho_x_preferred":[
        "\u8d64\u5cb8"
    ],
    "wof:name":"Chi'an",
    "wof:placetype":"locality"
},
  "geometry": {"coordinates":[118.99045,26.01572],"type":"Point"}
}