{
  "type": "Feature",
  "properties": {
    "gn:admin1_code":"09",
    "gn:asciiname":"Liancun",
    "gn:cc2":"CN",
    "gn:country_code":"CN",
    "gn:dem":41,
    "gn:feature_class":"P",
    "gn:feature_code":"PPL",
    "gn:name":"Liancun",
    "gn:population":0,
    "gn:timezone":"Asia/Shanghai",
    "iso:country":"CN",
    "name:und_x_variant":[
        "Lien-ts\u2019un-chi",
        "Liancun"
    ],
    "wof:name":"Liancun",
    "wof:placetype":"locality"
},
  "geometry": {"coordinates":[115.12639,32.65278],"type":"Point"}
}