{
  "type": "Feature",
  "properties": {
    "gn:admin1_code":"8.0",
    "gn:asciiname":"Yuyeshe",
    "gn:country_code":"CN",
    "gn:dem":204,
    "gn:feature_class":"P",
    "gn:feature_code":"PPL",
    "gn:name":"Yuyeshe",
    "gn:population":0,
    "gn:timezone":"Asia/Shanghai",
    "iso:country":"CN",
    "name:zho_x_preferred":[
        "\u6e14\u4e1a\u793e"
    ],
    "wof:name":"Yuyeshe",
    "wof:placetype":"locality"
},
  "geometry": {"coordinates":[125.17591000000002,48.48159],"type":"Point"}
}