{
  "type": "Feature",
  "properties": {
    "gn:admin1_code":"5.0",
    "gn:asciiname":"Renhetun",
    "gn:country_code":"CN",
    "gn:dem":161,
    "gn:feature_class":"P",
    "gn:feature_code":"PPL",
    "gn:name":"Renhetun",
    "gn:population":0,
    "gn:timezone":"Asia/Shanghai",
    "iso:country":"CN",
    "name:zho_x_preferred":[
        "\u4eba\u548c\u5c6f"
    ],
    "wof:name":"Renhetun",
    "wof:placetype":"locality"
},
  "geometry": {"coordinates":[122.37578000000001,44.42718],"type":"Point"}
}