{
  "type": "Feature",
  "properties": {
    "gn:admin1_code":"19.0",
    "gn:asciiname":"Nansijiazicun",
    "gn:country_code":"CN",
    "gn:dem":67,
    "gn:feature_class":"P",
    "gn:feature_code":"PPL",
    "gn:name":"Nansijiazicun",
    "gn:population":0,
    "gn:timezone":"Asia/Shanghai",
    "iso:country":"CN",
    "name:zho_x_preferred":[
        "\u5357\u56db\u5bb6\u5b50\u6751"
    ],
    "wof:name":"Nansijiazicun",
    "wof:placetype":"locality"
},
  "geometry": {"coordinates":[123.471,42.0103],"type":"Point"}
}