{
  "type": "Feature",
  "properties": {
    "gn:admin1_code":"2.0",
    "gn:asciiname":"Duimenjiang",
    "gn:country_code":"CN",
    "gn:dem":51,
    "gn:feature_class":"P",
    "gn:feature_code":"PPL",
    "gn:name":"Duimenjiang",
    "gn:population":0,
    "gn:timezone":"Asia/Shanghai",
    "iso:country":"CN",
    "name:zho_x_preferred":[
        "\u5151\u95e8\u6c5f"
    ],
    "wof:name":"Duimenjiang",
    "wof:placetype":"locality"
},
  "geometry": {"coordinates":[119.27312999999999,29.10717],"type":"Point"}
}