{
  "type": "Feature",
  "properties": {
    "gn:admin1_code":"33.0",
    "gn:asciiname":"Jinqiao",
    "gn:country_code":"CN",
    "gn:dem":796,
    "gn:feature_class":"P",
    "gn:feature_code":"PPL",
    "gn:name":"Jinqiao",
    "gn:population":0,
    "gn:timezone":"Asia/Shanghai",
    "iso:country":"CN",
    "name:zho_x_preferred":[
        "\u91d1\u6865"
    ],
    "wof:name":"Jinqiao",
    "wof:placetype":"locality"
},
  "geometry": {"coordinates":[108.1421,31.19378],"type":"Point"}
}