{
  "type": "Feature",
  "properties": {
    "gn:admin1_code":"11.0",
    "gn:asciiname":"Xiaoshantang",
    "gn:country_code":"CN",
    "gn:dem":127,
    "gn:feature_class":"P",
    "gn:feature_code":"PPL",
    "gn:name":"Xiaoshantang",
    "gn:population":0,
    "gn:timezone":"Asia/Shanghai",
    "iso:country":"CN",
    "name:zho_x_preferred":[
        "\u7b71\u5c71\u5858"
    ],
    "wof:name":"Xiaoshantang",
    "wof:placetype":"locality"
},
  "geometry": {"coordinates":[112.26969,27.45873],"type":"Point"}
}