{
  "type": "Feature",
  "properties": {
    "gn:admin1_code":"12.0",
    "gn:asciiname":"Shuangdunjie",
    "gn:country_code":"CN",
    "gn:dem":51,
    "gn:feature_class":"P",
    "gn:feature_code":"PPL",
    "gn:name":"Shuangdunjie",
    "gn:population":0,
    "gn:timezone":"Asia/Shanghai",
    "iso:country":"CN",
    "name:zho_x_preferred":[
        "\u53cc\u58a9\u8857"
    ],
    "wof:name":"Shuangdunjie",
    "wof:placetype":"locality"
},
  "geometry": {"coordinates":[113.66079999999999,30.94048],"type":"Point"}
}