{
  "type": "Feature",
  "properties": {
    "gn:admin1_code":"12.0",
    "gn:asciiname":"Kuangshan",
    "gn:country_code":"CN",
    "gn:dem":45,
    "gn:feature_class":"P",
    "gn:feature_code":"PPL",
    "gn:name":"Kuangshan",
    "gn:population":0,
    "gn:timezone":"Asia/Shanghai",
    "iso:country":"CN",
    "name:zho_x_preferred":[
        "\u77ff\u5c71"
    ],
    "wof:name":"Kuangshan",
    "wof:placetype":"locality"
},
  "geometry": {"coordinates":[115.51339,30.357],"type":"Point"}
}