{
  "type": "Feature",
  "properties": {
    "gn:admin1_code":"15.0",
    "gn:asciiname":"Zirun",
    "gn:country_code":"CN",
    "gn:dem":2745,
    "gn:feature_class":"P",
    "gn:feature_code":"PPL",
    "gn:name":"Zirun",
    "gn:population":0,
    "gn:timezone":"Asia/Shanghai",
    "iso:country":"CN",
    "name:und_x_variant":[
        "\u8d44\u6da6"
    ],
    "wof:name":"Zirun",
    "wof:placetype":"locality"
},
  "geometry": {"coordinates":[103.27218000000001,34.05552],"type":"Point"}
}