{
  "type": "Feature",
  "properties": {
    "gn:admin1_code":"4.0",
    "gn:asciiname":"Xijiaocun",
    "gn:country_code":"CN",
    "gn:dem":11,
    "gn:feature_class":"P",
    "gn:feature_code":"PPL",
    "gn:name":"Xijiaocun",
    "gn:population":0,
    "gn:timezone":"Asia/Shanghai",
    "iso:country":"CN",
    "name:zho_x_preferred":[
        "\u897f\u90ca\u6751"
    ],
    "wof:name":"Xijiaocun",
    "wof:placetype":"locality"
},
  "geometry": {"coordinates":[119.28270999999999,33.2337],"type":"Point"}
}