{
  "type": "Feature",
  "properties": {
    "gn:admin1_code":"15.0",
    "gn:asciiname":"Choujialiang",
    "gn:country_code":"CN",
    "gn:dem":1809,
    "gn:feature_class":"P",
    "gn:feature_code":"PPL",
    "gn:name":"Choujialiang",
    "gn:population":0,
    "gn:timezone":"Asia/Shanghai",
    "iso:country":"CN",
    "name:und_x_variant":[
        "\u4ec7\u5bb6\u6881"
    ],
    "wof:name":"Choujialiang",
    "wof:placetype":"locality"
},
  "geometry": {"coordinates":[105.93143000000001,35.2234],"type":"Point"}
}