{
  "type": "Feature",
  "properties": {
    "gn:admin1_code":"24.0",
    "gn:asciiname":"Shuimen",
    "gn:country_code":"CN",
    "gn:dem":1795,
    "gn:feature_class":"P",
    "gn:feature_code":"PPL",
    "gn:name":"Shuimen",
    "gn:population":0,
    "gn:timezone":"Asia/Shanghai",
    "iso:country":"CN",
    "name:zho_x_preferred":[
        "\u6c34\u95e8"
    ],
    "wof:name":"Shuimen",
    "wof:placetype":"locality"
},
  "geometry": {"coordinates":[111.78918,38.76132],"type":"Point"}
}