{
  "type": "Feature",
  "properties": {
    "gn:admin1_code":"1.0",
    "gn:asciiname":"Hexichen",
    "gn:country_code":"CN",
    "gn:dem":22,
    "gn:feature_class":"P",
    "gn:feature_code":"PPL",
    "gn:name":"Hexichen",
    "gn:population":0,
    "gn:timezone":"Asia/Shanghai",
    "iso:country":"CN",
    "name:und_x_variant":[
        "\u6cb3\u897f\u9648"
    ],
    "wof:name":"Hexichen",
    "wof:placetype":"locality"
},
  "geometry": {"coordinates":[118.89431,30.86717],"type":"Point"}
}