{
  "type": "Feature",
  "properties": {
    "gn:admin1_code":"25",
    "gn:asciiname":"Qianhangbu",
    "gn:country_code":"CN",
    "gn:dem":21,
    "gn:feature_class":"P",
    "gn:feature_code":"PPL",
    "gn:name":"Qianhangbu",
    "gn:population":0,
    "gn:timezone":"Asia/Shanghai",
    "iso:country":"CN",
    "name:zho_x_preferred":[
        "\u524d\u676d\u57e0"
    ],
    "wof:name":"Qianhangbu",
    "wof:placetype":"locality"
},
  "geometry": {"coordinates":[119.06999999999999,36.7548],"type":"Point"}
}