{
  "type": "Feature",
  "properties": {
    "gn:admin1_code":"11.0",
    "gn:asciiname":"Xianshigang",
    "gn:country_code":"CN",
    "gn:dem":97,
    "gn:feature_class":"P",
    "gn:feature_code":"PPL",
    "gn:name":"Xianshigang",
    "gn:population":0,
    "gn:timezone":"Asia/Shanghai",
    "iso:country":"CN",
    "name:zho_x_preferred":[
        "Xianshigang"
    ],
    "name:zho_x_variant":[
        "\u8854\u98df\u5c97"
    ],
    "wof:name":"Xianshigang",
    "wof:placetype":"locality"
},
  "geometry": {"coordinates":[111.46896,29.34743],"type":"Point"}
}