{
  "type": "Feature",
  "properties": {
    "gn:admin1_code":"3.0",
    "gn:asciiname":"Yanyingshan",
    "gn:country_code":"CN",
    "gn:dem":83,
    "gn:feature_class":"P",
    "gn:feature_code":"PPL",
    "gn:name":"Yanyingshan",
    "gn:population":0,
    "gn:timezone":"Asia/Shanghai",
    "iso:country":"CN",
    "name:zho_x_preferred":[
        "\u5ca9\u9e70\u5c71"
    ],
    "wof:name":"Yanyingshan",
    "wof:placetype":"locality"
},
  "geometry": {"coordinates":[113.724,27.6912],"type":"Point"}
}