{
  "type": "Feature",
  "properties": {
    "gn:admin1_code":"16.0",
    "gn:asciiname":"Zhi'an",
    "gn:country_code":"CN",
    "gn:dem":182,
    "gn:feature_class":"P",
    "gn:feature_code":"PPL",
    "gn:name":"Zhi\u2019an",
    "gn:population":0,
    "gn:timezone":"Asia/Shanghai",
    "iso:country":"CN",
    "name:und_x_variant":[
        "Zhi\u2019an"
    ],
    "name:zho_x_preferred":[
        "\u6cbb\u5b89"
    ],
    "wof:name":"Zhi'an",
    "wof:placetype":"locality"
},
  "geometry": {"coordinates":[109.506,25.1602],"type":"Point"}
}