{
  "type": "Feature",
  "properties": {
    "gn:admin1_code":"29.0",
    "gn:asciiname":"Lishanwa",
    "gn:country_code":"CN",
    "gn:dem":1332,
    "gn:feature_class":"P",
    "gn:feature_code":"PPL",
    "gn:name":"Lishanwa",
    "gn:population":0,
    "gn:timezone":"Asia/Shanghai",
    "iso:country":"CN",
    "name:zho_x_preferred":[
        "\u6817\u5c71\u6d3c"
    ],
    "wof:name":"Lishanwa",
    "wof:placetype":"locality"
},
  "geometry": {"coordinates":[98.80410000000001,25.2504],"type":"Point"}
}