{
  "type": "Feature",
  "properties": {
    "gn:admin1_code":"24.0",
    "gn:asciiname":"Baotou",
    "gn:country_code":"CN",
    "gn:dem":740,
    "gn:feature_class":"P",
    "gn:feature_code":"PPL",
    "gn:name":"Baotou",
    "gn:population":0,
    "gn:timezone":"Asia/Shanghai",
    "iso:country":"CN",
    "name:und_x_variant":[
        "\u5821\u5934"
    ],
    "wof:name":"Baotou",
    "wof:placetype":"locality"
},
  "geometry": {"coordinates":[111.20246000000002,35.43184],"type":"Point"}
}