{
  "type": "Feature",
  "properties": {
    "gn:admin1_code":"32",
    "gn:asciiname":"Wanghe",
    "gn:country_code":"CN",
    "gn:dem":525,
    "gn:feature_class":"P",
    "gn:feature_code":"PPL",
    "gn:name":"Wanghe",
    "gn:population":0,
    "gn:timezone":"Asia/Shanghai",
    "iso:country":"CN",
    "name:zho_x_preferred":[
        "\u738b\u6cb3"
    ],
    "wof:name":"Wanghe",
    "wof:placetype":"locality"
},
  "geometry": {"coordinates":[105.41043999999999,31.65153],"type":"Point"}
}