{
  "type": "Feature",
  "properties": {
    "gn:admin1_code":"14.0",
    "gn:asciiname":"Shirongka",
    "gn:country_code":"CN",
    "gn:dem":3862,
    "gn:feature_class":"P",
    "gn:feature_code":"PPL",
    "gn:name":"Shirongka",
    "gn:population":0,
    "gn:timezone":"Asia/Urumqi",
    "iso:country":"CN",
    "name:zho_x_preferred":[
        "\u5b9e\u8363\u5361"
    ],
    "wof:name":"Shirongka",
    "wof:placetype":"locality"
},
  "geometry": {"coordinates":[97.23745,31.53489],"type":"Point"}
}