{
  "type": "Feature",
  "properties": {
    "gn:admin1_code":"20.0",
    "gn:admin2_code":"8740492",
    "gn:asciiname":"Jianan",
    "gn:country_code":"CN",
    "gn:dem":369,
    "gn:feature_class":"P",
    "gn:feature_code":"PPL",
    "gn:name":"Jianan",
    "gn:population":0,
    "gn:timezone":"Asia/Shanghai",
    "iso:country":"CN",
    "name:zho_x_preferred":[
        "\u52a0\u5357"
    ],
    "wof:name":"Jianan",
    "wof:placetype":"locality"
},
  "geometry": {"coordinates":[124.14724,50.34997],"type":"Point"}
}