{
  "type": "Feature",
  "properties": {
    "gn:admin1_code":"14.0",
    "gn:asciiname":"Ji'aka",
    "gn:country_code":"CN",
    "gn:dem":4335,
    "gn:feature_class":"P",
    "gn:feature_code":"PPL",
    "gn:name":"Ji\u2019aka",
    "gn:population":0,
    "gn:timezone":"Asia/Urumqi",
    "iso:country":"CN",
    "name:und_x_variant":[
        "Ji\u2019aka"
    ],
    "name:zho_x_preferred":[
        "\u51e0\u963f\u5361"
    ],
    "wof:name":"Ji'aka",
    "wof:placetype":"locality"
},
  "geometry": {"coordinates":[94.51356,31.27221],"type":"Point"}
}