{
  "type": "Feature",
  "properties": {
    "gn:admin1_code":"24.0",
    "gn:asciiname":"Xialijiazhuang",
    "gn:country_code":"CN",
    "gn:dem":1387,
    "gn:feature_class":"P",
    "gn:feature_code":"PPL",
    "gn:name":"Xialijiazhuang",
    "gn:population":0,
    "gn:timezone":"Asia/Shanghai",
    "iso:country":"CN",
    "name:zho_x_preferred":[
        "\u4e0b\u674e\u5bb6\u5e84"
    ],
    "wof:name":"Xialijiazhuang",
    "wof:placetype":"locality"
},
  "geometry": {"coordinates":[112.14396000000001,36.60308],"type":"Point"}
}