{
  "type": "Feature",
  "properties": {
    "gn:admin1_code":"32.0",
    "gn:asciiname":"Houtoushan",
    "gn:country_code":"CN",
    "gn:dem":464,
    "gn:feature_class":"P",
    "gn:feature_code":"PPL",
    "gn:name":"Houtoushan",
    "gn:population":0,
    "gn:timezone":"Asia/Shanghai",
    "iso:country":"CN",
    "name:zho_x_preferred":[
        "\u540e\u5934\u5c71"
    ],
    "wof:name":"Houtoushan",
    "wof:placetype":"locality"
},
  "geometry": {"coordinates":[105.74299999999999,31.4202],"type":"Point"}
}