{
  "type": "Feature",
  "properties": {
    "gn:admin1_code":"6.0",
    "gn:asciiname":"Laiqiang",
    "gn:country_code":"CN",
    "gn:dem":3855,
    "gn:feature_class":"P",
    "gn:feature_code":"PPL",
    "gn:name":"Laiqiang",
    "gn:population":0,
    "gn:timezone":"Asia/Urumqi",
    "iso:country":"CN",
    "name:zho_x_preferred":[
        "\u6765\u5f3a"
    ],
    "wof:name":"Laiqiang",
    "wof:placetype":"locality"
},
  "geometry": {"coordinates":[96.84108000000001,32.11085],"type":"Point"}
}