{
  "type": "Feature",
  "properties": {
    "gn:admin1_code":"12.0",
    "gn:asciiname":"Panqiao",
    "gn:country_code":"CN",
    "gn:dem":31,
    "gn:feature_class":"P",
    "gn:feature_code":"PPL",
    "gn:name":"Panqiao",
    "gn:population":0,
    "gn:timezone":"Asia/Shanghai",
    "iso:country":"CN",
    "name:zho_x_preferred":[
        "Panqiao"
    ],
    "name:zho_x_variant":[
        "\u6f58\u6865"
    ],
    "wof:name":"Panqiao",
    "wof:placetype":"locality"
},
  "geometry": {"coordinates":[115.17505,29.95417],"type":"Point"}
}