{
  "type": "Feature",
  "properties": {
    "gn:admin1_code":"32.0",
    "gn:asciiname":"Marong",
    "gn:country_code":"CN",
    "gn:dem":4114,
    "gn:feature_class":"P",
    "gn:feature_code":"PPL",
    "gn:name":"Marong",
    "gn:population":0,
    "gn:timezone":"Asia/Shanghai",
    "iso:country":"CN",
    "name:zho_x_preferred":[
        "\u9ebb\u7ed2"
    ],
    "wof:name":"Marong",
    "wof:placetype":"locality"
},
  "geometry": {"coordinates":[99.4109,31.1876],"type":"Point"}
}