{
  "type": "Feature",
  "properties": {
    "gn:admin1_code":"22.0",
    "gn:asciiname":"Maoshancun",
    "gn:country_code":"CN",
    "gn:dem":621,
    "gn:feature_class":"P",
    "gn:feature_code":"PPL",
    "gn:name":"Maoshancun",
    "gn:population":0,
    "gn:timezone":"Asia/Shanghai",
    "iso:country":"CN",
    "name:zho_x_preferred":[
        "\u5e3d\u5c71\u6751"
    ],
    "wof:name":"Maoshancun",
    "wof:placetype":"locality"
},
  "geometry": {"coordinates":[116.62153000000001,41.00234],"type":"Point"}
}