{
  "type": "Feature",
  "properties": {
    "gn:admin1_code":"5.0",
    "gn:asciiname":"Lijiadian",
    "gn:country_code":"CN",
    "gn:dem":175,
    "gn:feature_class":"P",
    "gn:feature_code":"PPL",
    "gn:name":"Lijiadian",
    "gn:population":0,
    "gn:timezone":"Asia/Shanghai",
    "iso:country":"CN",
    "name:zho_x_preferred":[
        "\u674e\u5bb6\u5e97"
    ],
    "wof:name":"Lijiadian",
    "wof:placetype":"locality"
},
  "geometry": {"coordinates":[125.58253000000001,44.81738],"type":"Point"}
}