{
  "type": "Feature",
  "properties": {
    "gn:admin1_code":"26.0",
    "gn:asciiname":"Dengjia Yuanzi",
    "gn:country_code":"CN",
    "gn:dem":851,
    "gn:feature_class":"P",
    "gn:feature_code":"PPL",
    "gn:name":"Dengjia Yuanzi",
    "gn:population":0,
    "gn:timezone":"Asia/Shanghai",
    "iso:country":"CN",
    "name:und_x_variant":[
        "\u9093\u5bb6\u9662\u5b50"
    ],
    "wof:name":"Dengjia Yuanzi",
    "wof:placetype":"locality"
},
  "geometry": {"coordinates":[108.03071,33.22284000000001],"type":"Point"}
}