{
  "type": "Feature",
  "properties": {
    "gn:admin1_code":"11.0",
    "gn:asciiname":"Wenxing Wuchang",
    "gn:country_code":"CN",
    "gn:dem":149,
    "gn:feature_class":"P",
    "gn:feature_code":"PPL",
    "gn:name":"Wenxing Wuchang",
    "gn:population":0,
    "gn:timezone":"Asia/Shanghai",
    "iso:country":"CN",
    "name:zho_x_preferred":[
        "\u6587\u661f\u5c4b\u573a"
    ],
    "wof:name":"Wenxing Wuchang",
    "wof:placetype":"locality"
},
  "geometry": {"coordinates":[113.21784,27.20199],"type":"Point"}
}