{
  "type": "Feature",
  "properties": {
    "gn:admin1_code":"15.0",
    "gn:asciiname":"Jiadai",
    "gn:country_code":"CN",
    "gn:dem":2062,
    "gn:feature_class":"P",
    "gn:feature_code":"PPL",
    "gn:name":"Jiadai",
    "gn:population":0,
    "gn:timezone":"Asia/Shanghai",
    "iso:country":"CN",
    "name:und_x_variant":[
        "\u52a0\u5cb1"
    ],
    "name:zho_x_preferred":[
        "\u52a0\u5cb1"
    ],
    "wof:name":"Jiadai",
    "wof:placetype":"locality"
},
  "geometry": {"coordinates":[104.363,33.76192],"type":"Point"}
}