{
  "type": "Feature",
  "properties": {
    "gn:admin1_code":"16.0",
    "gn:asciiname":"Xiaoshe Bacun",
    "gn:country_code":"CN",
    "gn:dem":135,
    "gn:feature_class":"P",
    "gn:feature_code":"PPL",
    "gn:name":"Xiaoshe Bacun",
    "gn:population":0,
    "gn:timezone":"Asia/Shanghai",
    "iso:country":"CN",
    "name:zho_x_preferred":[
        "\u5c0f\u793e\u516b\u6751"
    ],
    "wof:name":"Xiaoshe Bacun",
    "wof:placetype":"locality"
},
  "geometry": {"coordinates":[109.628,24.6392],"type":"Point"}
}