{
  "type": "Feature",
  "properties": {
    "gn:admin1_code":"29.0",
    "gn:asciiname":"Huangzhuchang",
    "gn:country_code":"CN",
    "gn:dem":2568,
    "gn:feature_class":"P",
    "gn:feature_code":"PPL",
    "gn:name":"Huangzhuchang",
    "gn:population":0,
    "gn:timezone":"Asia/Shanghai",
    "iso:country":"CN",
    "name:zho_x_preferred":[
        "\u9ec4\u7af9\u5382"
    ],
    "wof:name":"Huangzhuchang",
    "wof:placetype":"locality"
},
  "geometry": {"coordinates":[99.4648,26.7296],"type":"Point"}
}