{
  "type": "Feature",
  "properties": {
    "gn:admin1_code":"5.0",
    "gn:asciiname":"Xiduluzui",
    "gn:country_code":"CN",
    "gn:dem":180,
    "gn:feature_class":"P",
    "gn:feature_code":"PPL",
    "gn:name":"Xiduluzui",
    "gn:population":0,
    "gn:timezone":"Asia/Shanghai",
    "iso:country":"CN",
    "name:zho_x_preferred":[
        "\u897f\u561f\u565c\u5480"
    ],
    "wof:name":"Xiduluzui",
    "wof:placetype":"locality"
},
  "geometry": {"coordinates":[124.72843,43.78488],"type":"Point"}
}