{
  "type": "Feature",
  "properties": {
    "gn:admin1_code":"14.0",
    "gn:asciiname":"Runa",
    "gn:country_code":"CN",
    "gn:dem":2749,
    "gn:feature_class":"P",
    "gn:feature_code":"PPL",
    "gn:name":"Runa",
    "gn:population":0,
    "gn:timezone":"Asia/Urumqi",
    "iso:country":"CN",
    "name:ast_x_preferred":[
        "Runa"
    ],
    "name:ceb_x_preferred":[
        "Runa"
    ],
    "name:deu_x_preferred":[
        "Runa"
    ],
    "name:fra_x_preferred":[
        "Runa"
    ],
    "name:heb_x_preferred":[
        "\u05e8\u05d5\u05e0\u05d4"
    ],
    "name:hun_x_preferred":[
        "R\u00fana"
    ],
    "name:nld_x_preferred":[
        "Runa"
    ],
    "name:slk_x_preferred":[
        "Runa"
    ],
    "name:spa_x_preferred":[
        "Runa"
    ],
    "name:swe_x_preferred":[
        "Runa"
    ],
    "name:ukr_x_preferred":[
        "\u0420\u0443\u043d\u0430"
    ],
    "name:zho_x_preferred":[
        "\u8339\u90a3"
    ],
    "wof:name":"Runa",
    "wof:placetype":"locality"
},
  "geometry": {"coordinates":[97.41162,29.71406],"type":"Point"}
}