{
  "type": "Feature",
  "properties": {
    "gn:admin1_code":"32.0",
    "gn:asciiname":"Neiguping",
    "gn:country_code":"CN",
    "gn:dem":640,
    "gn:feature_class":"P",
    "gn:feature_code":"PPL",
    "gn:name":"Neiguping",
    "gn:population":0,
    "gn:timezone":"Asia/Shanghai",
    "iso:country":"CN",
    "name:zho_x_preferred":[
        "\u5185\u53e4\u576a"
    ],
    "wof:name":"Neiguping",
    "wof:placetype":"locality"
},
  "geometry": {"coordinates":[104.34099999999999,29.557],"type":"Point"}
}