{
  "type": "Feature",
  "properties": {
    "gn:admin1_code":"32.0",
    "gn:asciiname":"Yaori",
    "gn:country_code":"CN",
    "gn:dem":3069,
    "gn:feature_class":"P",
    "gn:feature_code":"PPL",
    "gn:name":"Yaori",
    "gn:population":0,
    "gn:timezone":"Asia/Shanghai",
    "iso:country":"CN",
    "name:zho_x_preferred":[
        "\u836f\u65e5"
    ],
    "wof:name":"Yaori",
    "wof:placetype":"locality"
},
  "geometry": {"coordinates":[99.30549999999999,28.7927],"type":"Point"}
}