{
  "type": "Feature",
  "properties": {
    "gn:admin1_code":"25",
    "gn:asciiname":"Duxi",
    "gn:country_code":"CN",
    "gn:dem":37,
    "gn:feature_class":"P",
    "gn:feature_code":"PPL",
    "gn:name":"Duxi",
    "gn:population":0,
    "gn:timezone":"Asia/Shanghai",
    "iso:country":"CN",
    "name:zho_x_preferred":[
        "\u72ec\u897f"
    ],
    "wof:name":"Duxi",
    "wof:placetype":"locality"
},
  "geometry": {"coordinates":[116.744,35.1002],"type":"Point"}
}