{
  "type": "Feature",
  "properties": {
    "gn:admin1_code":"9.0",
    "gn:asciiname":"Peishanmiao",
    "gn:country_code":"CN",
    "gn:dem":75,
    "gn:feature_class":"P",
    "gn:feature_code":"PPL",
    "gn:name":"Peishanmiao",
    "gn:population":0,
    "gn:timezone":"Asia/Shanghai",
    "iso:country":"CN",
    "name:zho_x_preferred":[
        "\u88f4\u5c71\u5e99"
    ],
    "wof:name":"Peishanmiao",
    "wof:placetype":"locality"
},
  "geometry": {"coordinates":[113.81901999999999,34.00419],"type":"Point"}
}