{
  "type": "Feature",
  "properties": {
    "gn:admin1_code":"7.0",
    "gn:asciiname":"Gaizhuyang",
    "gn:country_code":"CN",
    "gn:dem":1051,
    "gn:feature_class":"P",
    "gn:feature_code":"PPL",
    "gn:name":"Gaizhuyang",
    "gn:population":0,
    "gn:timezone":"Asia/Shanghai",
    "iso:country":"CN",
    "name:und_x_variant":[
        "\u76d6\u7af9\u6d0b"
    ],
    "name:zho_x_preferred":[
        "\u76d6\u7af9\u6d0b"
    ],
    "wof:name":"Gaizhuyang",
    "wof:placetype":"locality"
},
  "geometry": {"coordinates":[117.58981,26.62936],"type":"Point"}
}