{
  "type": "Feature",
  "properties": {
    "gn:admin1_code":"26.0",
    "gn:asciiname":"Jiajiapan",
    "gn:country_code":"CN",
    "gn:dem":1165,
    "gn:feature_class":"P",
    "gn:feature_code":"PPL",
    "gn:name":"Jiajiapan",
    "gn:population":0,
    "gn:timezone":"Asia/Shanghai",
    "iso:country":"CN",
    "name:zho_x_preferred":[
        "\u8d3e\u5bb6\u7554"
    ],
    "wof:name":"Jiajiapan",
    "wof:placetype":"locality"
},
  "geometry": {"coordinates":[110.36323,39.31727],"type":"Point"}
}