{
  "type": "Feature",
  "properties": {
    "gn:admin1_code":"4.0",
    "gn:asciiname":"Xishenjiazhuang",
    "gn:country_code":"CN",
    "gn:dem":7,
    "gn:feature_class":"P",
    "gn:feature_code":"PPL",
    "gn:name":"Xishenjiazhuang",
    "gn:population":0,
    "gn:timezone":"Asia/Shanghai",
    "iso:country":"CN",
    "name:und_x_variant":[
        "\u897f\u6c88\u5bb6\u5e84"
    ],
    "name:zho_x_preferred":[
        "\u897f\u6c88\u5bb6\u5e84"
    ],
    "wof:name":"Xishenjiazhuang",
    "wof:placetype":"locality"
},
  "geometry": {"coordinates":[120.04331000000001,32.47492],"type":"Point"}
}