{
  "type": "Feature",
  "properties": {
    "gn:admin1_code":"26.0",
    "gn:asciiname":"Liujiacao",
    "gn:country_code":"CN",
    "gn:dem":818,
    "gn:feature_class":"P",
    "gn:feature_code":"PPL",
    "gn:name":"Liujiacao",
    "gn:population":0,
    "gn:timezone":"Asia/Shanghai",
    "iso:country":"CN",
    "name:und_x_variant":[
        "\u5218\u5bb6\u69fd"
    ],
    "wof:name":"Liujiacao",
    "wof:placetype":"locality"
},
  "geometry": {"coordinates":[107.08486000000001,34.32229],"type":"Point"}
}