{
  "type": "Feature",
  "properties": {
    "gn:admin1_code":"5.0",
    "gn:asciiname":"Fu'ancun",
    "gn:country_code":"CN",
    "gn:dem":323,
    "gn:feature_class":"P",
    "gn:feature_code":"PPL",
    "gn:name":"Fu\u2019ancun",
    "gn:population":0,
    "gn:timezone":"Asia/Shanghai",
    "iso:country":"CN",
    "name:und_x_variant":[
        "Fu\u2019ancun",
        "Fu-an-t\u2019un"
    ],
    "name:zho_x_preferred":[
        "\u5bcc\u5b89\u6751"
    ],
    "wof:name":"Fu'ancun",
    "wof:placetype":"locality"
},
  "geometry": {"coordinates":[125.15585,42.80653],"type":"Point"}
}