{
  "type": "Feature",
  "properties": {
    "gn:admin1_code":"02",
    "gn:asciiname":"Fengqiao",
    "gn:country_code":"CN",
    "gn:dem":8,
    "gn:feature_class":"P",
    "gn:feature_code":"PPLA4",
    "gn:name":"Fengqiao",
    "gn:population":0,
    "gn:timezone":"Asia/Shanghai",
    "iso:country":"CN",
    "name:und_x_variant":[
        "\u51e4\u6865",
        "Fengqiao Zhen",
        "\u51e4\u6865\u9547"
    ],
    "wof:name":"Fengqiao",
    "wof:placetype":"locality"
},
  "geometry": {"coordinates":[120.85448999999998,30.66108],"type":"Point"}
}