{
  "type": "Feature",
  "properties": {
    "gn:admin1_code":"19.0",
    "gn:asciiname":"Dalinggou",
    "gn:country_code":"CN",
    "gn:dem":17,
    "gn:feature_class":"P",
    "gn:feature_code":"PPL",
    "gn:name":"Dalinggou",
    "gn:population":0,
    "gn:timezone":"Asia/Shanghai",
    "iso:country":"CN",
    "name:und_x_variant":[
        "\u5927\u5cad\u6c9f"
    ],
    "wof:name":"Dalinggou",
    "wof:placetype":"locality"
},
  "geometry": {"coordinates":[122.25208000000001,40.39693],"type":"Point"}
}