{
  "type": "Feature",
  "properties": {
    "gn:admin1_code":"33.0",
    "gn:asciiname":"Shuangniu",
    "gn:country_code":"CN",
    "gn:dem":1259,
    "gn:feature_class":"P",
    "gn:feature_code":"PPL",
    "gn:name":"Shuangniu",
    "gn:population":0,
    "gn:timezone":"Asia/Shanghai",
    "iso:country":"CN",
    "name:zho_x_preferred":[
        "\u53cc\u725b"
    ],
    "wof:name":"Shuangniu",
    "wof:placetype":"locality"
},
  "geometry": {"coordinates":[109.48994,30.7597],"type":"Point"}
}