{
  "type": "Feature",
  "properties": {
    "gn:admin1_code":"08",
    "gn:asciiname":"Nanhutou",
    "gn:cc2":"CN",
    "gn:country_code":"CN",
    "gn:dem":343,
    "gn:feature_class":"P",
    "gn:feature_code":"PPL",
    "gn:name":"Nanhutou",
    "gn:population":0,
    "gn:timezone":"Asia/Shanghai",
    "iso:country":"CN",
    "name:und_x_variant":[
        "Hu-nan-t\u2019ou",
        "Nan-hu-t\u2019ou-t\u2019un",
        "Nanhutou"
    ],
    "wof:name":"Nanhutou",
    "wof:placetype":"locality"
},
  "geometry": {"coordinates":[128.90806000000001,43.77056],"type":"Point"}
}