{
  "type": "Feature",
  "properties": {
    "gn:admin1_code":"32.0",
    "gn:asciiname":"Nu'erbei",
    "gn:country_code":"CN",
    "gn:dem":452,
    "gn:feature_class":"P",
    "gn:feature_code":"PPL",
    "gn:name":"N\u00fc\u2019erbei",
    "gn:population":0,
    "gn:timezone":"Asia/Shanghai",
    "iso:country":"CN",
    "name:und_x_variant":[
        "N\u00fc\u2019erbei"
    ],
    "name:zho_x_preferred":[
        "\u5973\u513f\u7891"
    ],
    "wof:name":"Nu'erbei",
    "wof:placetype":"locality"
},
  "geometry": {"coordinates":[104.706,31.0426],"type":"Point"}
}