{
  "type": "Feature",
  "properties": {
    "gn:admin1_code":"30",
    "gn:asciiname":"Chegang",
    "gn:country_code":"CN",
    "gn:dem":59,
    "gn:feature_class":"P",
    "gn:feature_code":"PPLA4",
    "gn:name":"Chegang",
    "gn:population":0,
    "gn:timezone":"Asia/Shanghai",
    "iso:country":"CN",
    "name:und_x_variant":[
        "Ch\u2019e-kang",
        "Ch\u2019e-kang-hs\u00fc",
        "Chegang",
        "Chegang Zhen",
        "\u8f66\u5c97\u9547"
    ],
    "name:zho_x_preferred":[
        "\u8f66\u5c97"
    ],
    "wof:name":"Chegang",
    "wof:placetype":"locality"
},
  "geometry": {"coordinates":[112.23604,22.7771],"type":"Point"}
}