{
  "type": "Feature",
  "properties": {
    "gn:admin1_code":"33.0",
    "gn:asciiname":"Huyan",
    "gn:country_code":"CN",
    "gn:dem":310,
    "gn:feature_class":"P",
    "gn:feature_code":"PPL",
    "gn:name":"Huyan",
    "gn:population":0,
    "gn:timezone":"Asia/Shanghai",
    "iso:country":"CN",
    "name:aze_x_preferred":[
        "Qiyan q\u0259bil\u0259si"
    ],
    "name:cat_x_preferred":[
        "Huyan"
    ],
    "name:kor_x_preferred":[
        "\ud638\uc5f0\uc528"
    ],
    "name:rus_x_preferred":[
        "\u0425\u0443\u044f\u043d\u044c"
    ],
    "name:zho_x_preferred":[
        "\u864e\u5ca9"
    ],
    "name:zho_x_variant":[
        "\u547c\u5ef6\u59d3"
    ],
    "wof:name":"Huyan",
    "wof:placetype":"locality"
},
  "geometry": {"coordinates":[106.315,29.5402],"type":"Point"}
}