{
  "type": "Feature",
  "properties": {
    "gn:admin1_code":"9.0",
    "gn:asciiname":"Xiazhuang",
    "gn:country_code":"CN",
    "gn:dem":137,
    "gn:feature_class":"P",
    "gn:feature_code":"PPL",
    "gn:name":"Xiazhuang",
    "gn:population":0,
    "gn:timezone":"Asia/Shanghai",
    "iso:country":"CN",
    "name:und_x_variant":[
        "\u4e0b\u5e84"
    ],
    "name:zho_x_preferred":[
        "\u4e0b\u5e84"
    ],
    "wof:name":"Xiazhuang",
    "wof:placetype":"locality"
},
  "geometry": {"coordinates":[113.01452999999999,33.14704],"type":"Point"}
}