{
  "type": "Feature",
  "properties": {
    "gn:admin1_code":"26",
    "gn:asciiname":"Beiputuo",
    "gn:country_code":"CN",
    "gn:dem":919,
    "gn:feature_class":"P",
    "gn:feature_code":"PPL",
    "gn:name":"Beiputuo",
    "gn:population":0,
    "gn:timezone":"Asia/Shanghai",
    "iso:country":"CN",
    "wof:name":"Beiputuo",
    "wof:placetype":"locality"
},
  "geometry": {"coordinates":[109.90167,34.0275],"type":"Point"}
}