{
  "type": "Feature",
  "properties": {
    "gn:admin1_code":"26.0",
    "gn:asciiname":"Caobacun",
    "gn:country_code":"CN",
    "gn:dem":1749,
    "gn:feature_class":"P",
    "gn:feature_code":"PPL",
    "gn:name":"Caobacun",
    "gn:population":0,
    "gn:timezone":"Asia/Shanghai",
    "iso:country":"CN",
    "name:zho_x_preferred":[
        "\u8349\u575d\u6751"
    ],
    "wof:name":"Caobacun",
    "wof:placetype":"locality"
},
  "geometry": {"coordinates":[107.8165,32.58481],"type":"Point"}
}