{
  "type": "Feature",
  "properties": {
    "gn:admin1_code":"29.0",
    "gn:asciiname":"Caowantou",
    "gn:country_code":"CN",
    "gn:dem":354,
    "gn:feature_class":"P",
    "gn:feature_code":"PPL",
    "gn:name":"Caowantou",
    "gn:population":0,
    "gn:timezone":"Asia/Shanghai",
    "iso:country":"CN",
    "name:zho_x_preferred":[
        "\u6f15\u6e7e\u5934"
    ],
    "wof:name":"Caowantou",
    "wof:placetype":"locality"
},
  "geometry": {"coordinates":[104.202,28.6369],"type":"Point"}
}