{
  "type": "Feature",
  "properties": {
    "gn:admin1_code":"10.0",
    "gn:asciiname":"Yujiazhuang",
    "gn:country_code":"CN",
    "gn:dem":51,
    "gn:feature_class":"P",
    "gn:feature_code":"PPL",
    "gn:name":"Yujiazhuang",
    "gn:population":0,
    "gn:timezone":"Asia/Shanghai",
    "iso:country":"CN",
    "name:und_x_variant":[
        "\u4f59\u5bb6\u5e84"
    ],
    "name:zho_x_preferred":[
        "\u4e8e\u5bb6\u5e84"
    ],
    "wof:name":"Yujiazhuang",
    "wof:placetype":"locality"
},
  "geometry": {"coordinates":[114.985,38.0687],"type":"Point"}
}