{
  "type": "Feature",
  "properties": {
    "gn:admin1_code":"32.0",
    "gn:asciiname":"Muwanzhai",
    "gn:country_code":"CN",
    "gn:dem":2377,
    "gn:feature_class":"P",
    "gn:feature_code":"PPL",
    "gn:name":"Muwanzhai",
    "gn:population":0,
    "gn:timezone":"Asia/Shanghai",
    "iso:country":"CN",
    "name:zho_x_preferred":[
        "\u6728\u7897\u5be8"
    ],
    "wof:name":"Muwanzhai",
    "wof:placetype":"locality"
},
  "geometry": {"coordinates":[103.221,31.4184],"type":"Point"}
}