{
  "type": "Feature",
  "properties": {
    "gn:admin1_code":"7.0",
    "gn:asciiname":"Yuchu",
    "gn:country_code":"CN",
    "gn:dem":484,
    "gn:feature_class":"P",
    "gn:feature_code":"PPL",
    "gn:name":"Yuchu",
    "gn:population":0,
    "gn:timezone":"Asia/Shanghai",
    "iso:country":"CN",
    "name:zho_x_preferred":[
        "\u4f59\u5904"
    ],
    "wof:name":"Yuchu",
    "wof:placetype":"locality"
},
  "geometry": {"coordinates":[118.40676000000001,28.28287000000001],"type":"Point"}
}