{
  "type": "Feature",
  "properties": {
    "gn:admin1_code":"26.0",
    "gn:asciiname":"Chuli",
    "gn:country_code":"CN",
    "gn:dem":835,
    "gn:feature_class":"P",
    "gn:feature_code":"PPL",
    "gn:name":"Chuli",
    "gn:population":0,
    "gn:timezone":"Asia/Shanghai",
    "iso:country":"CN",
    "name:fin_x_preferred":[
        "Chuli"
    ],
    "name:glg_x_preferred":[
        "Chuli"
    ],
    "name:ita_x_preferred":[
        "Chuli"
    ],
    "name:pol_x_preferred":[
        "Manuel V\u00e1zquez"
    ],
    "name:spa_x_preferred":[
        "Chuli"
    ],
    "name:tgk_x_preferred":[
        "\u041a\u0443\u043b\u0438"
    ],
    "name:und_x_variant":[
        "\u5904\u793c"
    ],
    "wof:name":"Chuli",
    "wof:placetype":"locality"
},
  "geometry": {"coordinates":[107.3683,34.54827],"type":"Point"}
}