{
  "type": "Feature",
  "properties": {
    "gn:admin1_code":"9.0",
    "gn:asciiname":"Quanpo",
    "gn:country_code":"CN",
    "gn:dem":615,
    "gn:feature_class":"P",
    "gn:feature_code":"PPL",
    "gn:name":"Quanpo",
    "gn:population":0,
    "gn:timezone":"Asia/Shanghai",
    "iso:country":"CN",
    "name:zho_x_preferred":[
        "\u5168\u5761"
    ],
    "wof:name":"Quanpo",
    "wof:placetype":"locality"
},
  "geometry": {"coordinates":[111.82989999999999,33.36790999999999],"type":"Point"}
}