{
  "type": "Feature",
  "properties": {
    "gn:country":"CN",
    "gn:fcode":"PPL",
    "gn:population":104277,
    "iso:country":"CN",
    "name:ast_x_preferred":[
        "Pulandian"
    ],
    "name:ceb_x_preferred":[
        "Pulandian"
    ],
    "name:cym_x_preferred":[
        "Ardal Pulandian"
    ],
    "name:deu_x_preferred":[
        "Pulandian"
    ],
    "name:eng_x_preferred":[
        "Pulandian District"
    ],
    "name:fra_x_preferred":[
        "Pulandian"
    ],
    "name:gan_x_preferred":[
        "\u666e\u5170\u5e97\u533a"
    ],
    "name:hye_x_preferred":[
        "\u054a\u0578\u0582\u056c\u0561\u0576\u0564\u0575\u0561\u0576 \u0577\u0580\u057b\u0561\u0576"
    ],
    "name:jpn_x_preferred":[
        "\u666e\u862d\u5e97\u533a"
    ],
    "name:kor_x_preferred":[
        "\ud478\ub780\ub3ac \uc2dc"
    ],
    "name:mlg_x_preferred":[
        "Pulandian"
    ],
    "name:nan_x_preferred":[
        "Ph\u00f3\u0358-l\u00e2n-ti\u00e0m-khu"
    ],
    "name:nld_x_preferred":[
        "Pulandian"
    ],
    "name:nob_x_preferred":[
        "Pulandian"
    ],
    "name:rus_x_preferred":[
        "\u041f\u0443\u043b\u0430\u043d\u044c\u0434\u044f\u043d\u044c"
    ],
    "name:spa_x_preferred":[
        "Pulandian"
    ],
    "name:swe_x_preferred":[
        "Pulandian"
    ],
    "name:und_x_variant":[
        "Xinjin"
    ],
    "name:urd_x_preferred":[
        "\u067e\u0648\u0644\u0627\u0646\u062f\u06cc\u0627\u0646"
    ],
    "name:wuu_x_preferred":[
        "\u666e\u5170\u5e97\u533a"
    ],
    "name:zho_x_preferred":[
        "\u666e\u5170\u5e97\u533a"
    ],
    "qs:name":"\u666e\u5170\u5e97",
    "qs:name_adm0":"\u4e2d\u570b",
    "qs:name_adm1":"\u8fbd\u5b81\u7701",
    "qs:photos_9k":1,
    "qs:photos_9r":3,
    "qs:photos_all":92,
    "qs:photos_sr":0,
    "qs:placetype":"Town",
    "qs:pop_sr":"9",
    "wd:wordcount":358,
    "wof:name":"\u666e\u5170\u5e97",
    "wof:placetype":"locality",
    "wof:population":104277
},
  "geometry": {"coordinates":[121.96693999999999,39.39528],"type":"Point"}
}