{
  "type": "Feature",
  "properties": {
    "gn:country":"CN",
    "gn:fcode":"PPL",
    "gn:pop":104277,
    "iso:country":"CN",
    "name:unk_x_variant":[
        "Xinjin"
    ],
    "qs:name":"\u666e\u5170\u5e97",
    "qs:name_adm0":"\u4e2d\u570b",
    "qs:name_adm1":"\u8fbd\u5b81\u7701",
    "qs:photos_9k":1,
    "qs:photos_9r":3,
    "qs:photos_all":92,
    "qs:photos_sr":0,
    "qs:placetype":"Town",
    "qs:pop_sr":"9",
    "wd:wordcount":358,
    "wof:name":"\u666e\u5170\u5e97",
    "wof:placetype":"locality",
    "wof:population":104277
},
  "geometry": {"coordinates":[121.96693999999999,39.39528],"type":"Point"}
}