{
  "type": "Feature",
  "properties": {
    "gn:admin1_code":"24.0",
    "gn:asciiname":"Shijia Yezhuang",
    "gn:country_code":"CN",
    "gn:dem":931,
    "gn:feature_class":"P",
    "gn:feature_code":"PPL",
    "gn:name":"Shijia Yezhuang",
    "gn:population":0,
    "gn:timezone":"Asia/Shanghai",
    "iso:country":"CN",
    "name:zho_x_preferred":[
        "\u65bd\u5bb6\u91ce\u5e84"
    ],
    "wof:name":"Shijia Yezhuang",
    "wof:placetype":"locality"
},
  "geometry": {"coordinates":[112.62387,38.81392],"type":"Point"}
}