{
  "type": "Feature",
  "properties": {
    "gn:admin1_code":"18",
    "gn:asciiname":"Bulong",
    "gn:country_code":"CN",
    "gn:dem":1298,
    "gn:feature_class":"P",
    "gn:feature_code":"PPL",
    "gn:name":"Bulong",
    "gn:population":0,
    "gn:timezone":"Asia/Shanghai",
    "iso:country":"CN",
    "name:zho_x_preferred":[
        "\u8865\u5785"
    ],
    "wof:name":"Bulong",
    "wof:placetype":"locality"
},
  "geometry": {"coordinates":[106.128,26.4617],"type":"Point"}
}