{
  "type": "Feature",
  "properties": {
    "gn:admin1_code":"19.0",
    "gn:asciiname":"Wohugou",
    "gn:country_code":"CN",
    "gn:dem":282,
    "gn:feature_class":"P",
    "gn:feature_code":"PPL",
    "gn:name":"Wohugou",
    "gn:population":0,
    "gn:timezone":"Asia/Shanghai",
    "iso:country":"CN",
    "name:und_x_variant":[
        "\u5367\u864e\u6c9f"
    ],
    "wof:name":"Wohugou",
    "wof:placetype":"locality"
},
  "geometry": {"coordinates":[123.38035000000001,40.90294],"type":"Point"}
}