{
  "type": "Feature",
  "properties": {
    "gn:admin1_code":"29.0",
    "gn:asciiname":"Biena",
    "gn:country_code":"CN",
    "gn:dem":1912,
    "gn:feature_class":"P",
    "gn:feature_code":"PPL",
    "gn:name":"Biena",
    "gn:population":0,
    "gn:timezone":"Asia/Shanghai",
    "iso:country":"CN",
    "name:zho_x_preferred":[
        "\u522b\u90a3"
    ],
    "wof:name":"Biena",
    "wof:placetype":"locality"
},
  "geometry": {"coordinates":[101.536,23.4248],"type":"Point"}
}