{
  "type": "Feature",
  "properties": {
    "gn:admin1_code":"24",
    "gn:asciiname":"Getaitou",
    "gn:cc2":"CN",
    "gn:country_code":"CN",
    "gn:dem":1148,
    "gn:feature_class":"P",
    "gn:feature_code":"PPL",
    "gn:name":"Getaitou",
    "gn:population":0,
    "gn:timezone":"Asia/Shanghai",
    "iso:country":"CN",
    "name:und_x_variant":[
        "Ko-t\u2019ai-t\u2019ou",
        "Getaitou"
    ],
    "wof:name":"Getaitou",
    "wof:placetype":"locality"
},
  "geometry": {"coordinates":[112.28028,37.69528],"type":"Point"}
}