{
  "type": "Feature",
  "properties": {
    "gn:admin1_code":"15.0",
    "gn:asciiname":"Juwan",
    "gn:country_code":"CN",
    "gn:dem":1941,
    "gn:feature_class":"P",
    "gn:feature_code":"PPL",
    "gn:name":"Juwan",
    "gn:population":0,
    "gn:timezone":"Asia/Shanghai",
    "iso:country":"CN",
    "name:zho_x_preferred":[
        "\u5c45\u6e7e"
    ],
    "wof:name":"Juwan",
    "wof:placetype":"locality"
},
  "geometry": {"coordinates":[105.01300000000001,34.8861],"type":"Point"}
}