{
  "type": "Feature",
  "properties": {
    "gn:admin1_code":"32.0",
    "gn:asciiname":"Lianxingqiao",
    "gn:country_code":"CN",
    "gn:dem":400,
    "gn:feature_class":"P",
    "gn:feature_code":"PPL",
    "gn:name":"Lianxingqiao",
    "gn:population":0,
    "gn:timezone":"Asia/Shanghai",
    "iso:country":"CN",
    "name:zho_x_preferred":[
        "\u8054\u661f\u6865"
    ],
    "wof:name":"Lianxingqiao",
    "wof:placetype":"locality"
},
  "geometry": {"coordinates":[104.25586,29.79311],"type":"Point"}
}