{
  "type": "Feature",
  "properties": {
    "gn:admin1_code":"8.0",
    "gn:asciiname":"Wudaogang Sanfenchang",
    "gn:country_code":"CN",
    "gn:dem":160,
    "gn:feature_class":"P",
    "gn:feature_code":"PPLF",
    "gn:name":"Wudaogang Sanfenchang",
    "gn:population":0,
    "gn:timezone":"Asia/Shanghai",
    "iso:country":"CN",
    "name:zho_x_preferred":[
        "\u4e94\u9053\u5c97\u4e09\u5206\u573a"
    ],
    "wof:name":"Wudaogang Sanfenchang",
    "wof:placetype":"locality"
},
  "geometry": {"coordinates":[130.12951000000001,47.34947],"type":"Point"}
}