{
  "type": "Feature",
  "properties": {
    "gn:admin1_code":"30.0",
    "gn:asciiname":"Zhutouyan",
    "gn:country_code":"CN",
    "gn:dem":380,
    "gn:feature_class":"P",
    "gn:feature_code":"PPL",
    "gn:name":"Zhutouyan",
    "gn:population":0,
    "gn:timezone":"Asia/Shanghai",
    "iso:country":"CN",
    "name:zho_x_preferred":[
        "Zhutouyan"
    ],
    "name:zho_x_variant":[
        "\u732a\u5934\u5ca9"
    ],
    "wof:name":"Zhutouyan",
    "wof:placetype":"locality"
},
  "geometry": {"coordinates":[112.84139,24.74639],"type":"Point"}
}