{
  "type": "Feature",
  "properties": {
    "gn:admin1_code":"3.0",
    "gn:asciiname":"Xiaoyincun",
    "gn:country_code":"CN",
    "gn:dem":280,
    "gn:feature_class":"P",
    "gn:feature_code":"PPL",
    "gn:name":"Xiaoyincun",
    "gn:population":0,
    "gn:timezone":"Asia/Shanghai",
    "iso:country":"CN",
    "name:und_x_variant":[
        "\u5c0f\u541f\u6751"
    ],
    "wof:name":"Xiaoyincun",
    "wof:placetype":"locality"
},
  "geometry": {"coordinates":[116.11647000000001,26.98868],"type":"Point"}
}