{
  "type": "Feature",
  "properties": {
    "gn:admin1_code":"25",
    "gn:asciiname":"Taitou Nancun",
    "gn:country_code":"CN",
    "gn:dem":17,
    "gn:feature_class":"P",
    "gn:feature_code":"PPL",
    "gn:name":"Taitou Nancun",
    "gn:population":0,
    "gn:timezone":"Asia/Shanghai",
    "iso:country":"CN",
    "name:zho_x_preferred":[
        "\u53f0\u5934\u5357\u6751"
    ],
    "wof:name":"Taitou Nancun",
    "wof:placetype":"locality"
},
  "geometry": {"coordinates":[119.66200000000001,36.7431],"type":"Point"}
}