{
  "type": "Feature",
  "properties": {
    "gn:admin1_code":"8.0",
    "gn:asciiname":"Guofucun",
    "gn:country_code":"CN",
    "gn:dem":290,
    "gn:feature_class":"P",
    "gn:feature_code":"PPL",
    "gn:name":"Guofucun",
    "gn:population":0,
    "gn:timezone":"Asia/Shanghai",
    "iso:country":"CN",
    "name:zho_x_preferred":[
        "\u56fd\u5bcc\u6751"
    ],
    "wof:name":"Guofucun",
    "wof:placetype":"locality"
},
  "geometry": {"coordinates":[126.15965,47.97179000000001],"type":"Point"}
}