{
  "type": "Feature",
  "properties": {
    "gn:admin1_code":"8.0",
    "gn:asciiname":"Xinjiancun",
    "gn:country_code":"CN",
    "gn:dem":269,
    "gn:feature_class":"P",
    "gn:feature_code":"PPL",
    "gn:name":"Xinjiancun",
    "gn:population":0,
    "gn:timezone":"Asia/Shanghai",
    "iso:country":"CN",
    "name:zho_x_preferred":[
        "\u65b0\u5efa\u6751"
    ],
    "wof:name":"Xinjiancun",
    "wof:placetype":"locality"
},
  "geometry": {"coordinates":[130.28692000000001,45.42655],"type":"Point"}
}