{
  "type": "Feature",
  "properties": {
    "gn:admin1_code":"1.0",
    "gn:asciiname":"Liulicun",
    "gn:country_code":"CN",
    "gn:dem":39,
    "gn:feature_class":"P",
    "gn:feature_code":"PPL",
    "gn:name":"Liulicun",
    "gn:population":0,
    "gn:timezone":"Asia/Shanghai",
    "iso:country":"CN",
    "name:zho_x_preferred":[
        "\u516d\u91cc\u6751"
    ],
    "wof:name":"Liulicun",
    "wof:placetype":"locality"
},
  "geometry": {"coordinates":[116.21671000000001,32.20982],"type":"Point"}
}