{
  "type": "Feature",
  "properties": {
    "gn:admin1_code":"24.0",
    "gn:asciiname":"Yueyanzhuang",
    "gn:country_code":"CN",
    "gn:dem":1475,
    "gn:feature_class":"P",
    "gn:feature_code":"PPL",
    "gn:name":"Yueyanzhuang",
    "gn:population":0,
    "gn:timezone":"Asia/Shanghai",
    "iso:country":"CN",
    "name:und_x_variant":[
        "\u5cb3\u6cbf\u5e84"
    ],
    "name:zho_x_preferred":[
        "\u5cb3\u6cbf\u5e84"
    ],
    "wof:name":"Yueyanzhuang",
    "wof:placetype":"locality"
},
  "geometry": {"coordinates":[113.73058,39.37762],"type":"Point"}
}