{
  "type": "Feature",
  "properties": {
    "gn:admin1_code":"11.0",
    "gn:asciiname":"Bagongtang",
    "gn:country_code":"CN",
    "gn:dem":107,
    "gn:feature_class":"P",
    "gn:feature_code":"PPL",
    "gn:name":"Bagongtang",
    "gn:population":0,
    "gn:timezone":"Asia/Shanghai",
    "iso:country":"CN",
    "name:zho_x_preferred":[
        "\u5df4\u516c\u5858"
    ],
    "wof:name":"Bagongtang",
    "wof:placetype":"locality"
},
  "geometry": {"coordinates":[112.73782,27.93187],"type":"Point"}
}