{
  "type": "Feature",
  "properties": {
    "gn:admin1_code":"18.0",
    "gn:asciiname":"Douxi",
    "gn:country_code":"CN",
    "gn:dem":922,
    "gn:feature_class":"P",
    "gn:feature_code":"PPL",
    "gn:name":"Douxi",
    "gn:population":0,
    "gn:timezone":"Asia/Shanghai",
    "iso:country":"CN",
    "wof:name":"Douxi",
    "wof:placetype":"locality"
},
  "geometry": {"coordinates":[108.61778,28.15111],"type":"Point"}
}