{
  "type": "Feature",
  "properties": {
    "gn:admin1_code":"01",
    "gn:asciiname":"Donghekou",
    "gn:cc2":"CN",
    "gn:country_code":"CN",
    "gn:dem":69,
    "gn:feature_class":"P",
    "gn:feature_code":"PPL",
    "gn:name":"Donghekou",
    "gn:population":0,
    "gn:timezone":"Asia/Shanghai",
    "iso:country":"CN",
    "name:und_x_variant":[
        "Tung-liang-ho-k\u2019ou",
        "Tung-ho-k\u2019ou",
        "Donghekou"
    ],
    "wof:name":"Donghekou",
    "wof:placetype":"locality"
},
  "geometry": {"coordinates":[116.58389,31.41972],"type":"Point"}
}