{
  "type": "Feature",
  "properties": {
    "gn:admin1_code":"14",
    "gn:asciiname":"Lalong",
    "gn:country_code":"CN",
    "gn:dem":4120,
    "gn:feature_class":"P",
    "gn:feature_code":"PPL",
    "gn:name":"Lalong",
    "gn:population":0,
    "gn:timezone":"Asia/Urumqi",
    "iso:country":"CN",
    "name:spa_x_preferred":[
        "Lalong"
    ],
    "name:urd_x_preferred":[
        "\u0644\u0627\u0644\u0648\u0646\u06af"
    ],
    "name:zho_x_preferred":[
        "\u62c9\u9f99"
    ],
    "wof:name":"Lalong",
    "wof:placetype":"locality"
},
  "geometry": {"coordinates":[89.2373,29.8121],"type":"Point"}
}