{
  "type": "Feature",
  "properties": {
    "gn:admin1_code":"3.0",
    "gn:asciiname":"Shuida Ba",
    "gn:country_code":"CN",
    "gn:dem":36,
    "gn:feature_class":"P",
    "gn:feature_code":"PPL",
    "gn:name":"Shuida Ba",
    "gn:population":0,
    "gn:timezone":"Asia/Shanghai",
    "iso:country":"CN",
    "name:und_x_variant":[
        "\u6c34\u6253\u575d"
    ],
    "wof:name":"Shuida Ba",
    "wof:placetype":"locality"
},
  "geometry": {"coordinates":[116.43353999999999,28.1341],"type":"Point"}
}