{
  "type": "Feature",
  "properties": {
    "gn:admin1_code":"15.0",
    "gn:asciiname":"Haodizhang",
    "gn:country_code":"CN",
    "gn:dem":2122,
    "gn:feature_class":"P",
    "gn:feature_code":"PPL",
    "gn:name":"Haodizhang",
    "gn:population":0,
    "gn:timezone":"Asia/Shanghai",
    "iso:country":"CN",
    "name:zho_x_preferred":[
        "\u597d\u5730\u638c"
    ],
    "wof:name":"Haodizhang",
    "wof:placetype":"locality"
},
  "geometry": {"coordinates":[106.215,35.3237],"type":"Point"}
}