{
  "type": "Feature",
  "properties": {
    "gn:admin1_code":"3",
    "gn:asciiname":"Yaoyinggang",
    "gn:country_code":"CN",
    "gn:dem":549,
    "gn:feature_class":"P",
    "gn:feature_code":"PPL",
    "gn:name":"Yaoyinggang",
    "gn:population":0,
    "gn:timezone":"Asia/Shanghai",
    "iso:country":"CN",
    "name:zho_x_preferred":[
        "\u7a91\u9e70\u5c97"
    ],
    "wof:name":"Yaoyinggang",
    "wof:placetype":"locality"
},
  "geometry": {"coordinates":[114.239,26.1676],"type":"Point"}
}