{
  "type": "Feature",
  "properties": {
    "gn:admin1_code":"6.0",
    "gn:asciiname":"Lerong Gongba",
    "gn:country_code":"CN",
    "gn:dem":4026,
    "gn:feature_class":"P",
    "gn:feature_code":"PPL",
    "gn:name":"Lerong Gongba",
    "gn:population":0,
    "gn:timezone":"Asia/Urumqi",
    "iso:country":"CN",
    "name:zho_x_preferred":[
        "\u52d2\u7ed2\u8d21\u5df4"
    ],
    "wof:name":"Lerong Gongba",
    "wof:placetype":"locality"
},
  "geometry": {"coordinates":[96.72705999999999,33.37106],"type":"Point"}
}