{
  "type": "Feature",
  "properties": {
    "gn:admin1_code":"19.0",
    "gn:asciiname":"Yangquanzicun",
    "gn:country_code":"CN",
    "gn:dem":57,
    "gn:feature_class":"P",
    "gn:feature_code":"PPL",
    "gn:name":"Yangquanzicun",
    "gn:population":0,
    "gn:timezone":"Asia/Shanghai",
    "iso:country":"CN",
    "name:zho_x_preferred":[
        "\u7f8a\u5708\u5b50\u6751"
    ],
    "wof:name":"Yangquanzicun",
    "wof:placetype":"locality"
},
  "geometry": {"coordinates":[121.53440000000001,39.04225],"type":"Point"}
}