{
  "type": "Feature",
  "properties": {
    "gn:admin1_code":"15.0",
    "gn:asciiname":"Yanwuping",
    "gn:country_code":"CN",
    "gn:dem":1488,
    "gn:feature_class":"P",
    "gn:feature_code":"PPL",
    "gn:name":"Yanwuping",
    "gn:population":0,
    "gn:timezone":"Asia/Shanghai",
    "iso:country":"CN",
    "name:und_x_variant":[
        "\u70df\u96fe\u576a"
    ],
    "wof:name":"Yanwuping",
    "wof:placetype":"locality"
},
  "geometry": {"coordinates":[105.32317,33.00282],"type":"Point"}
}