{
  "type": "Feature",
  "properties": {
    "gn:admin1_code":"8.0",
    "gn:asciiname":"Beixindiancun",
    "gn:country_code":"CN",
    "gn:dem":227,
    "gn:feature_class":"P",
    "gn:feature_code":"PPL",
    "gn:name":"Beixindiancun",
    "gn:population":0,
    "gn:timezone":"Asia/Shanghai",
    "iso:country":"CN",
    "name:zho_x_preferred":[
        "\u5317\u65b0\u5e97\u6751"
    ],
    "wof:name":"Beixindiancun",
    "wof:placetype":"locality"
},
  "geometry": {"coordinates":[127.74875,44.7754],"type":"Point"}
}