{
  "type": "Feature",
  "properties": {
    "gn:admin1_code":"9.0",
    "gn:asciiname":"Panxinzhuang",
    "gn:country_code":"CN",
    "gn:dem":94,
    "gn:feature_class":"P",
    "gn:feature_code":"PPL",
    "gn:name":"Panxinzhuang",
    "gn:population":0,
    "gn:timezone":"Asia/Shanghai",
    "iso:country":"CN",
    "name:zho_x_preferred":[
        "\u6f58\u65b0\u5e84"
    ],
    "wof:name":"Panxinzhuang",
    "wof:placetype":"locality"
},
  "geometry": {"coordinates":[113.99638,32.684],"type":"Point"}
}