{
  "type": "Feature",
  "properties": {
    "gn:admin1_code":"7",
    "gn:asciiname":"Qianbu",
    "gn:country_code":"CN",
    "gn:dem":17,
    "gn:feature_class":"P",
    "gn:feature_code":"PPL",
    "gn:name":"Qianbu",
    "gn:population":0,
    "gn:timezone":"Asia/Shanghai",
    "iso:country":"CN",
    "name:zho_x_preferred":[
        "\u524d\u57d4"
    ],
    "wof:name":"Qianbu",
    "wof:placetype":"locality"
},
  "geometry": {"coordinates":[118.87667,25.36472],"type":"Point"}
}