{
  "type": "Feature",
  "properties": {
    "gn:admin1_code":"19.0",
    "gn:asciiname":"Liangshuicun",
    "gn:country_code":"CN",
    "gn:dem":32,
    "gn:feature_class":"P",
    "gn:feature_code":"PPL",
    "gn:name":"Liangshuicun",
    "gn:population":0,
    "gn:timezone":"Asia/Shanghai",
    "iso:country":"CN",
    "name:zho_x_preferred":[
        "\u51c9\u6c34\u6751"
    ],
    "wof:name":"Liangshuicun",
    "wof:placetype":"locality"
},
  "geometry": {"coordinates":[120.14015000000001,40.21668],"type":"Point"}
}