{
  "type": "Feature",
  "properties": {
    "gn:admin1_code":"23.0",
    "gn:asciiname":"Zhuanqiao",
    "gn:cc2":"CN",
    "gn:country_code":"CN",
    "gn:dem":5,
    "gn:feature_class":"P",
    "gn:feature_code":"PPL",
    "gn:name":"Zhuanqiao",
    "gn:population":0,
    "gn:timezone":"Asia/Shanghai",
    "iso:country":"CN",
    "name:und_x_variant":[
        "Chuan-ch\u2019iao",
        "Chuan-ch\u2019iao-chen",
        "Zhuanqiao",
        "\u989b\u6865"
    ],
    "wof:name":"Zhuanqiao",
    "wof:placetype":"locality"
},
  "geometry": {"coordinates":[121.38861,31.07444000000001],"type":"Point"}
}