{
  "type": "Feature",
  "properties": {
    "gn:admin1_code":"30",
    "gn:asciiname":"Shatoulong",
    "gn:country_code":"CN",
    "gn:dem":5,
    "gn:feature_class":"P",
    "gn:feature_code":"PPL",
    "gn:name":"Shatoulong",
    "gn:population":0,
    "gn:timezone":"Asia/Shanghai",
    "iso:country":"CN",
    "name:und_x_variant":[
        "Shaqu",
        "Shatoulong"
    ],
    "name:zho_x_preferred":[
        "\u6c99\u5934\u5785"
    ],
    "wof:name":"Shatoulong",
    "wof:placetype":"locality"
},
  "geometry": {"coordinates":[111.91580999999999,21.71163],"type":"Point"}
}