{
  "type": "Feature",
  "properties": {
    "gn:admin1_code":"7.0",
    "gn:asciiname":"Jiangshi",
    "gn:country_code":"CN",
    "gn:dem":350,
    "gn:feature_class":"P",
    "gn:feature_code":"PPL",
    "gn:name":"Jiangshi",
    "gn:population":0,
    "gn:timezone":"Asia/Shanghai",
    "iso:country":"CN",
    "name:deu_x_preferred":[
        "Jiang Shi"
    ],
    "name:epo_x_preferred":[
        "\u011cjang\u015dio"
    ],
    "name:fra_x_preferred":[
        "Jiangshi"
    ],
    "name:ind_x_preferred":[
        "Jiangshi"
    ],
    "name:jpn_x_preferred":[
        "\u30ad\u30e7\u30f3\u30b7\u30fc"
    ],
    "name:msa_x_preferred":[
        "Jiang Shi"
    ],
    "name:por_x_preferred":[
        "Jiangshi"
    ],
    "name:rus_x_preferred":[
        "\u0426\u0437\u044f\u043d\u0448\u0438"
    ],
    "name:spa_x_preferred":[
        "Jiang Shi"
    ],
    "name:swe_x_preferred":[
        "Kiang-Tsi"
    ],
    "name:tha_x_preferred":[
        "\u0e40\u0e08\u0e35\u0e22\u0e07\u0e0b\u0e37\u0e2d"
    ],
    "name:vie_x_preferred":[
        "C\u01b0\u01a1ng thi"
    ],
    "name:zho_x_preferred":[
        "\u5c06\u77f3"
    ],
    "wof:name":"Jiangshi",
    "wof:placetype":"locality"
},
  "geometry": {"coordinates":[117.26658999999999,27.09244],"type":"Point"}
}