{
  "type": "Feature",
  "properties": {
    "gn:admin1_code":"7",
    "gn:asciiname":"Shangban",
    "gn:country_code":"CN",
    "gn:dem":225,
    "gn:feature_class":"P",
    "gn:feature_code":"PPL",
    "gn:name":"Shangban",
    "gn:population":0,
    "gn:timezone":"Asia/Shanghai",
    "iso:country":"CN",
    "name:zho_x_preferred":[
        "\u4e0a\u5742"
    ],
    "wof:name":"Shangban",
    "wof:placetype":"locality"
},
  "geometry": {"coordinates":[117.54861,25.33972],"type":"Point"}
}