{
  "type": "Feature",
  "properties": {
    "gn:admin1_code":"4.0",
    "gn:asciiname":"Xiangxiang",
    "gn:country_code":"CN",
    "gn:dem":31,
    "gn:feature_class":"P",
    "gn:feature_code":"PPL",
    "gn:name":"Xiangxiang",
    "gn:population":0,
    "gn:timezone":"Asia/Shanghai",
    "iso:country":"CN",
    "name:ceb_x_preferred":[
        "Xiangxiang"
    ],
    "name:deu_x_preferred":[
        "Xiangxiang"
    ],
    "name:fra_x_preferred":[
        "Xiangxiang"
    ],
    "name:hak_x_preferred":[
        "Siong-hi\u00f4ng-s\u1e73"
    ],
    "name:ita_x_preferred":[
        "Xiangxiang"
    ],
    "name:jpn_x_preferred":[
        "\u6e58\u90f7\u5e02"
    ],
    "name:kik_x_preferred":[
        "Xiangxiang"
    ],
    "name:kor_x_preferred":[
        "\uc0f9\uc0f9\uc2dc"
    ],
    "name:mlg_x_preferred":[
        "Xiangxiang"
    ],
    "name:nor_x_preferred":[
        "Xiangxiang"
    ],
    "name:pam_x_preferred":[
        "Xiangxiang"
    ],
    "name:pol_x_preferred":[
        "Xiangxiang"
    ],
    "name:swe_x_preferred":[
        "Xiangxiang"
    ],
    "name:vie_x_preferred":[
        "T\u01b0\u01a1ng H\u01b0\u01a1ng"
    ],
    "name:war_x_preferred":[
        "Xiangxiang"
    ],
    "name:wuu_x_preferred":[
        "\u6e58\u4e61\u5e02"
    ],
    "name:zho_x_preferred":[
        "\u9999\u5df7"
    ],
    "name:zho_x_variant":[
        "\u6e58\u4e61\u5e02"
    ],
    "wof:name":"Xiangxiang",
    "wof:placetype":"locality"
},
  "geometry": {"coordinates":[119.34658,32.45745],"type":"Point"}
}