{
  "type": "Feature",
  "properties": {
    "gn:admin1_code":"3.0",
    "gn:asciiname":"Yaowan",
    "gn:country_code":"CN",
    "gn:dem":35,
    "gn:feature_class":"P",
    "gn:feature_code":"PPL",
    "gn:name":"Yaowan",
    "gn:population":0,
    "gn:timezone":"Asia/Shanghai",
    "iso:country":"CN",
    "name:und_x_variant":[
        "\u7a91\u6e7e"
    ],
    "wof:name":"Yaowan",
    "wof:placetype":"locality"
},
  "geometry": {"coordinates":[115.40958999999999,28.03297],"type":"Point"}
}