{
  "type": "Feature",
  "properties": {
    "gn:admin1_code":"24.0",
    "gn:asciiname":"Zhangjiazhuangcun",
    "gn:country_code":"CN",
    "gn:dem":1092,
    "gn:feature_class":"P",
    "gn:feature_code":"PPL",
    "gn:name":"Zhangjiazhuangcun",
    "gn:population":0,
    "gn:timezone":"Asia/Shanghai",
    "iso:country":"CN",
    "name:und_x_variant":[
        "Chang-chia-chuang",
        "Zhangjiazhuang",
        "Zhangjiazhuangcun"
    ],
    "name:zho_x_preferred":[
        "\u5f20\u5bb6\u5e84\u6751"
    ],
    "wof:name":"Zhangjiazhuangcun",
    "wof:placetype":"locality"
},
  "geometry": {"coordinates":[110.98539,37.20121],"type":"Point"}
}