{
  "type": "Feature",
  "properties": {
    "gn:admin1_code":"30.0",
    "gn:asciiname":"Ma'anwei",
    "gn:country_code":"CN",
    "gn:dem":148,
    "gn:feature_class":"P",
    "gn:feature_code":"PPL",
    "gn:name":"Ma\u2019anwei",
    "gn:population":0,
    "gn:timezone":"Asia/Shanghai",
    "iso:country":"CN",
    "name:zho_x_preferred":[
        "Ma\u2019anwei"
    ],
    "name:zho_x_variant":[
        "\u9a6c\u5b89\u56f4"
    ],
    "wof:name":"Ma'anwei",
    "wof:placetype":"locality"
},
  "geometry": {"coordinates":[114.74562,24.09132],"type":"Point"}
}