{
  "type": "Feature",
  "properties": {
    "gn:admin1_code":"29.0",
    "gn:asciiname":"Shangyangxi",
    "gn:country_code":"CN",
    "gn:dem":2039,
    "gn:feature_class":"P",
    "gn:feature_code":"PPL",
    "gn:name":"Shangyangxi",
    "gn:population":0,
    "gn:timezone":"Asia/Shanghai",
    "iso:country":"CN",
    "name:zho_x_preferred":[
        "\u4e0a\u9633\u6eaa"
    ],
    "wof:name":"Shangyangxi",
    "wof:placetype":"locality"
},
  "geometry": {"coordinates":[100.105,25.8094],"type":"Point"}
}