{
  "type": "Feature",
  "properties": {
    "gn:admin1_code":"29.0",
    "gn:asciiname":"Shikouzi",
    "gn:country_code":"CN",
    "gn:dem":2113,
    "gn:feature_class":"P",
    "gn:feature_code":"PPL",
    "gn:name":"Shikouzi",
    "gn:population":0,
    "gn:timezone":"Asia/Shanghai",
    "iso:country":"CN",
    "name:zho_x_preferred":[
        "\u77f3\u53e3\u5b50"
    ],
    "wof:name":"Shikouzi",
    "wof:placetype":"locality"
},
  "geometry": {"coordinates":[104.31399999999999,26.0027],"type":"Point"}
}