{
  "type": "Feature",
  "properties": {
    "gn:admin1_code":"32.0",
    "gn:asciiname":"Baitaiyang",
    "gn:country_code":"CN",
    "gn:dem":1752,
    "gn:feature_class":"P",
    "gn:feature_code":"PPL",
    "gn:name":"Baitaiyang",
    "gn:population":0,
    "gn:timezone":"Asia/Shanghai",
    "iso:country":"CN",
    "name:zho_x_preferred":[
        "\u767d\u592a\u9633"
    ],
    "wof:name":"Baitaiyang",
    "wof:placetype":"locality"
},
  "geometry": {"coordinates":[102.55868,29.41912],"type":"Point"}
}