{
  "type": "Feature",
  "properties": {
    "gn:admin1_code":"9.0",
    "gn:asciiname":"Hushanpu",
    "gn:country_code":"CN",
    "gn:dem":153,
    "gn:feature_class":"P",
    "gn:feature_code":"PPL",
    "gn:name":"Hushanpu",
    "gn:population":0,
    "gn:timezone":"Asia/Shanghai",
    "iso:country":"CN",
    "name:zho_x_preferred":[
        "\u5cb5\u5c71\u94fa"
    ],
    "wof:name":"Hushanpu",
    "wof:placetype":"locality"
},
  "geometry": {"coordinates":[111.45353,32.95635],"type":"Point"}
}