{
  "type": "Feature",
  "properties": {
    "gn:admin1_code":"24.0",
    "gn:asciiname":"Gongdongling",
    "gn:country_code":"CN",
    "gn:dem":1491,
    "gn:feature_class":"P",
    "gn:feature_code":"PPL",
    "gn:name":"Gongdongling",
    "gn:population":0,
    "gn:timezone":"Asia/Shanghai",
    "iso:country":"CN",
    "name:zho_x_preferred":[
        "\u5de5\u6d1e\u5cad"
    ],
    "wof:name":"Gongdongling",
    "wof:placetype":"locality"
},
  "geometry": {"coordinates":[111.98609,35.5309],"type":"Point"}
}