{
  "type": "Feature",
  "properties": {
    "gn:admin1_code":"5.0",
    "gn:asciiname":"Gaijiatong",
    "gn:country_code":"CN",
    "gn:dem":140,
    "gn:feature_class":"P",
    "gn:feature_code":"PPL",
    "gn:name":"Gaijiatong",
    "gn:population":0,
    "gn:timezone":"Asia/Shanghai",
    "iso:country":"CN",
    "name:zho_x_preferred":[
        "\u76d6\u5bb6\u901a"
    ],
    "wof:name":"Gaijiatong",
    "wof:placetype":"locality"
},
  "geometry": {"coordinates":[125.30110000000001,44.82477],"type":"Point"}
}