{
  "type": "Feature",
  "properties": {
    "gn:admin1_code":"16.0",
    "gn:asciiname":"Zhu'exia",
    "gn:country_code":"CN",
    "gn:dem":757,
    "gn:feature_class":"P",
    "gn:feature_code":"PPL",
    "gn:name":"Zhu\u2019exia",
    "gn:population":0,
    "gn:timezone":"Asia/Shanghai",
    "iso:country":"CN",
    "name:und_x_variant":[
        "Zhu\u2019exia"
    ],
    "name:zho_x_preferred":[
        "\u9010\u83aa\u4e0b"
    ],
    "wof:name":"Zhu'exia",
    "wof:placetype":"locality"
},
  "geometry": {"coordinates":[106.33,23.1282],"type":"Point"}
}