{
  "type": "Feature",
  "properties": {
    "gn:admin1_code":"2.0",
    "gn:asciiname":"Dayuanli",
    "gn:country_code":"CN",
    "gn:dem":832,
    "gn:feature_class":"P",
    "gn:feature_code":"PPL",
    "gn:name":"Dayuanli",
    "gn:population":0,
    "gn:timezone":"Asia/Shanghai",
    "iso:country":"CN",
    "name:zho_x_preferred":[
        "\u5927\u6e90\u91cc"
    ],
    "wof:name":"Dayuanli",
    "wof:placetype":"locality"
},
  "geometry": {"coordinates":[118.94226999999999,30.0001],"type":"Point"}
}