{
  "type": "Feature",
  "properties": {
    "gn:admin1_code":"33.0",
    "gn:asciiname":"Tianpingqiu",
    "gn:country_code":"CN",
    "gn:dem":350,
    "gn:feature_class":"P",
    "gn:feature_code":"PPL",
    "gn:name":"Tianpingqiu",
    "gn:population":0,
    "gn:timezone":"Asia/Shanghai",
    "iso:country":"CN",
    "name:zho_x_preferred":[
        "\u5929\u5e73\u4e18"
    ],
    "wof:name":"Tianpingqiu",
    "wof:placetype":"locality"
},
  "geometry": {"coordinates":[106.07552,30.17133],"type":"Point"}
}