{
  "type": "Feature",
  "properties": {
    "gn:admin1_code":"16",
    "gn:asciiname":"Xiaozeng",
    "gn:country_code":"CN",
    "gn:dem":747,
    "gn:feature_class":"P",
    "gn:feature_code":"PPL",
    "gn:name":"Xiaozeng",
    "gn:population":0,
    "gn:timezone":"Asia/Shanghai",
    "iso:country":"CN",
    "name:zho_x_preferred":[
        "\u5c0f\u7511"
    ],
    "wof:name":"Xiaozeng",
    "wof:placetype":"locality"
},
  "geometry": {"coordinates":[109.90300000000001,25.2873],"type":"Point"}
}