{
  "type": "Feature",
  "properties": {
    "gn:admin1_code":"10.0",
    "gn:asciiname":"Zhongyukou",
    "gn:country_code":"CN",
    "gn:dem":151,
    "gn:feature_class":"P",
    "gn:feature_code":"PPL",
    "gn:name":"Zhongyukou",
    "gn:population":0,
    "gn:timezone":"Asia/Shanghai",
    "iso:country":"CN",
    "name:zho_x_preferred":[
        "\u91cd\u5cea\u53e3"
    ],
    "name:zho_x_variant":[
        "\u4e2d\u9c7c\u53e3\u4e61"
    ],
    "wof:name":"Zhongyukou",
    "wof:placetype":"locality"
},
  "geometry": {"coordinates":[119.07447000000001,40.07537],"type":"Point"}
}