{
  "type": "Feature",
  "properties": {
    "gn:admin1_code":"24",
    "gn:asciiname":"Hongtubu",
    "gn:country_code":"CN",
    "gn:dem":1332,
    "gn:feature_class":"P",
    "gn:feature_code":"PPL",
    "gn:name":"Hongtubu",
    "gn:population":0,
    "gn:timezone":"Asia/Shanghai",
    "iso:country":"CN",
    "name:und_x_variant":[
        "Hung-t\u2019u-pao",
        "Hongtubu",
        "\u7ea2\u571f\u5821"
    ],
    "wof:name":"Hongtubu",
    "wof:placetype":"locality"
},
  "geometry": {"coordinates":[112.39847,40.10296],"type":"Point"}
}