{
  "type": "Feature",
  "properties": {
    "gn:admin1_code":"32.0",
    "gn:asciiname":"Dengjia Yuanzi",
    "gn:country_code":"CN",
    "gn:dem":316,
    "gn:feature_class":"P",
    "gn:feature_code":"PPL",
    "gn:name":"Dengjia Yuanzi",
    "gn:population":0,
    "gn:timezone":"Asia/Shanghai",
    "iso:country":"CN",
    "name:zho_x_preferred":[
        "\u9093\u5bb6\u9662\u5b50"
    ],
    "wof:name":"Dengjia Yuanzi",
    "wof:placetype":"locality"
},
  "geometry": {"coordinates":[105.032,29.60929],"type":"Point"}
}