{
  "type": "Feature",
  "properties": {
    "gn:admin1_code":"4.0",
    "gn:asciiname":"Zhujiazhuang",
    "gn:country_code":"CN",
    "gn:dem":2,
    "gn:feature_class":"P",
    "gn:feature_code":"PPL",
    "gn:name":"Zhujiazhuang",
    "gn:population":0,
    "gn:timezone":"Asia/Shanghai",
    "iso:country":"CN",
    "name:zho_x_preferred":[
        "\u6731\u5bb6\u5e84"
    ],
    "wof:name":"Zhujiazhuang",
    "wof:placetype":"locality"
},
  "geometry": {"coordinates":[119.68899999999999,32.9381],"type":"Point"}
}