{
  "type": "Feature",
  "properties": {
    "gn:admin1_code":"15.0",
    "gn:asciiname":"Helonggou",
    "gn:country_code":"CN",
    "gn:dem":2323,
    "gn:feature_class":"P",
    "gn:feature_code":"PPL",
    "gn:name":"Helonggou",
    "gn:population":0,
    "gn:timezone":"Asia/Shanghai",
    "iso:country":"CN",
    "name:zho_x_preferred":[
        "\u548c\u9f99\u6c9f"
    ],
    "wof:name":"Helonggou",
    "wof:placetype":"locality"
},
  "geometry": {"coordinates":[103.654,35.2838],"type":"Point"}
}