{
  "type": "Feature",
  "properties": {
    "gn:admin1_code":"3.0",
    "gn:asciiname":"Qianfangzhengjia",
    "gn:country_code":"CN",
    "gn:dem":72,
    "gn:feature_class":"P",
    "gn:feature_code":"PPL",
    "gn:name":"Qianfangzhengjia",
    "gn:population":0,
    "gn:timezone":"Asia/Shanghai",
    "iso:country":"CN",
    "name:und_x_variant":[
        "\u94b1\u574a\u90d1\u5bb6"
    ],
    "wof:name":"Qianfangzhengjia",
    "wof:placetype":"locality"
},
  "geometry": {"coordinates":[116.85584,28.02537],"type":"Point"}
}