{
  "type": "Feature",
  "properties": {
    "gn:admin1_code":"32.0",
    "gn:asciiname":"Shijiangzui",
    "gn:country_code":"CN",
    "gn:dem":2561,
    "gn:feature_class":"P",
    "gn:feature_code":"PPL",
    "gn:name":"Shijiangzui",
    "gn:population":0,
    "gn:timezone":"Asia/Shanghai",
    "iso:country":"CN",
    "name:zho_x_preferred":[
        "\u77f3\u6c5f\u5480"
    ],
    "wof:name":"Shijiangzui",
    "wof:placetype":"locality"
},
  "geometry": {"coordinates":[102.01000000000001,32.002],"type":"Point"}
}