{
  "type": "Feature",
  "properties": {
    "gn:admin1_code":"19.0",
    "gn:asciiname":"Sijiashancun",
    "gn:country_code":"CN",
    "gn:dem":73,
    "gn:feature_class":"P",
    "gn:feature_code":"PPL",
    "gn:name":"Sijiashancun",
    "gn:population":0,
    "gn:timezone":"Asia/Shanghai",
    "iso:country":"CN",
    "name:zho_x_preferred":[
        "\u56db\u67b6\u5c71\u6751"
    ],
    "wof:name":"Sijiashancun",
    "wof:placetype":"locality"
},
  "geometry": {"coordinates":[122.837,42.2803],"type":"Point"}
}