{
  "type": "Feature",
  "properties": {
    "gn:admin1_code":"12.0",
    "gn:asciiname":"Huanxiangba",
    "gn:country_code":"CN",
    "gn:dem":1110,
    "gn:feature_class":"P",
    "gn:feature_code":"PPL",
    "gn:name":"Huanxiangba",
    "gn:population":0,
    "gn:timezone":"Asia/Shanghai",
    "iso:country":"CN",
    "name:zho_x_preferred":[
        "\u6362\u9999\u6252"
    ],
    "wof:name":"Huanxiangba",
    "wof:placetype":"locality"
},
  "geometry": {"coordinates":[110.97165,32.21774],"type":"Point"}
}