{
  "type": "Feature",
  "properties": {
    "gn:admin1_code":"26.0",
    "gn:asciiname":"Yangqucun",
    "gn:country_code":"CN",
    "gn:dem":1248,
    "gn:feature_class":"P",
    "gn:feature_code":"PPL",
    "gn:name":"Yangqucun",
    "gn:population":0,
    "gn:timezone":"Asia/Shanghai",
    "iso:country":"CN",
    "name:zho_x_preferred":[
        "\u9633\u6e20\u6751"
    ],
    "wof:name":"Yangqucun",
    "wof:placetype":"locality"
},
  "geometry": {"coordinates":[109.03639,36.93803],"type":"Point"}
}