{
  "type": "Feature",
  "properties": {
    "gn:admin1_code":"23.0",
    "gn:asciiname":"Xibang",
    "gn:country_code":"CN",
    "gn:dem":4,
    "gn:feature_class":"P",
    "gn:feature_code":"PPL",
    "gn:name":"Xibang",
    "gn:population":0,
    "gn:timezone":"Asia/Shanghai",
    "iso:country":"CN",
    "name:zho_x_preferred":[
        "Xibang"
    ],
    "name:zho_x_variant":[
        "\u897f\u6d5c"
    ],
    "wof:name":"Xibang",
    "wof:placetype":"locality"
},
  "geometry": {"coordinates":[121.10198,31.19509],"type":"Point"}
}