{
  "type": "Feature",
  "properties": {
    "gn:admin1_code":"1.0",
    "gn:asciiname":"Zhouqiaocun",
    "gn:country_code":"CN",
    "gn:dem":14,
    "gn:feature_class":"P",
    "gn:feature_code":"PPL",
    "gn:name":"Zhouqiaocun",
    "gn:population":0,
    "gn:timezone":"Asia/Shanghai",
    "iso:country":"CN",
    "name:zho_x_preferred":[
        "\u5468\u6865\u6751"
    ],
    "wof:name":"Zhouqiaocun",
    "wof:placetype":"locality"
},
  "geometry": {"coordinates":[116.93188000000001,31.56462],"type":"Point"}
}