{
  "type": "Feature",
  "properties": {
    "gn:admin1_code":"29.0",
    "gn:asciiname":"Dunzidi",
    "gn:country_code":"CN",
    "gn:dem":1163,
    "gn:feature_class":"P",
    "gn:feature_code":"PPL",
    "gn:name":"Dunzidi",
    "gn:population":0,
    "gn:timezone":"Asia/Shanghai",
    "iso:country":"CN",
    "name:zho_x_preferred":[
        "\u58a9\u5b50\u5730"
    ],
    "wof:name":"Dunzidi",
    "wof:placetype":"locality"
},
  "geometry": {"coordinates":[98.8723,25.2599],"type":"Point"}
}