{
  "type": "Feature",
  "properties": {
    "gn:admin1_code":"14.0",
    "gn:asciiname":"Duobucun",
    "gn:country_code":"CN",
    "gn:dem":3081,
    "gn:feature_class":"P",
    "gn:feature_code":"PPL",
    "gn:name":"Duobucun",
    "gn:population":0,
    "gn:timezone":"Asia/Urumqi",
    "iso:country":"CN",
    "name:zho_x_preferred":[
        "\u591a\u5e03\u6751"
    ],
    "wof:name":"Duobucun",
    "wof:placetype":"locality"
},
  "geometry": {"coordinates":[94.14761,29.7451],"type":"Point"}
}