{
  "type": "Feature",
  "properties": {
    "gn:admin1_code":"20.0",
    "gn:asciiname":"Kelesitu",
    "gn:country_code":"CN",
    "gn:dem":985,
    "gn:feature_class":"P",
    "gn:feature_code":"PPL",
    "gn:name":"Kelesitu",
    "gn:population":0,
    "gn:timezone":"Asia/Shanghai",
    "iso:country":"CN",
    "name:zho_x_preferred":[
        "\u53ef\u52d2\u65af\u56fe"
    ],
    "wof:name":"Kelesitu",
    "wof:placetype":"locality"
},
  "geometry": {"coordinates":[100.83511,41.60245],"type":"Point"}
}