{
  "type": "Feature",
  "properties": {
    "gn:admin1_code":"26.0",
    "gn:asciiname":"Lusicun",
    "gn:country_code":"CN",
    "gn:dem":949,
    "gn:feature_class":"P",
    "gn:feature_code":"PPL",
    "gn:name":"Lusicun",
    "gn:population":0,
    "gn:timezone":"Asia/Shanghai",
    "iso:country":"CN",
    "name:zho_x_preferred":[
        "\u9c81\u5bfa\u6751"
    ],
    "wof:name":"Lusicun",
    "wof:placetype":"locality"
},
  "geometry": {"coordinates":[109.06553999999998,35.65862],"type":"Point"}
}