{
  "type": "Feature",
  "properties": {
    "gn:admin1_code":"32.0",
    "gn:asciiname":"Shimensi",
    "gn:country_code":"CN",
    "gn:dem":800,
    "gn:feature_class":"P",
    "gn:feature_code":"PPL",
    "gn:name":"Shimensi",
    "gn:population":0,
    "gn:timezone":"Asia/Shanghai",
    "iso:country":"CN",
    "name:zho_x_preferred":[
        "\u77f3\u95e8\u5bfa"
    ],
    "wof:name":"Shimensi",
    "wof:placetype":"locality"
},
  "geometry": {"coordinates":[104.04300000000001,28.7956],"type":"Point"}
}