{
  "type": "Feature",
  "properties": {
    "gn:admin1_code":"12.0",
    "gn:asciiname":"Yanxia",
    "gn:country_code":"CN",
    "gn:dem":80,
    "gn:feature_class":"P",
    "gn:feature_code":"PPLA4",
    "gn:name":"Yanxia",
    "gn:population":0,
    "gn:timezone":"Asia/Shanghai",
    "iso:country":"CN",
    "name:und_x_variant":[
        "Yen-hsia",
        "Yanxia",
        "\u71d5\u53a6",
        "Yanxia Xiang",
        "\u71d5\u53a6\u4e61"
    ],
    "wof:name":"Yanxia",
    "wof:placetype":"locality"
},
  "geometry": {"coordinates":[114.86279,29.56975],"type":"Point"}
}