{
  "type": "Feature",
  "properties": {
    "gn:admin1_code":"1.0",
    "gn:asciiname":"Qilucun",
    "gn:country_code":"CN",
    "gn:dem":21,
    "gn:feature_class":"P",
    "gn:feature_code":"PPL",
    "gn:name":"Qilucun",
    "gn:population":0,
    "gn:timezone":"Asia/Shanghai",
    "iso:country":"CN",
    "name:zho_x_preferred":[
        "\u6b67\u8def\u6751"
    ],
    "wof:name":"Qilucun",
    "wof:placetype":"locality"
},
  "geometry": {"coordinates":[117.97608,33.66021],"type":"Point"}
}