{
  "type": "Feature",
  "properties": {
    "gn:admin1_code":"10",
    "gn:asciiname":"Taiyanggouliang",
    "gn:country_code":"CN",
    "gn:dem":1068,
    "gn:feature_class":"P",
    "gn:feature_code":"PPL",
    "gn:name":"Taiyanggouliang",
    "gn:population":0,
    "gn:timezone":"Asia/Shanghai",
    "iso:country":"CN",
    "name:zho_x_preferred":[
        "\u592a\u9633\u6c9f\u6881"
    ],
    "wof:name":"Taiyanggouliang",
    "wof:placetype":"locality"
},
  "geometry": {"coordinates":[116.79656,41.38777],"type":"Point"}
}