{
  "type": "Feature",
  "properties": {
    "gn:admin1_code":"3",
    "gn:asciiname":"Qingcha",
    "gn:country_code":"CN",
    "gn:dem":595,
    "gn:feature_class":"P",
    "gn:feature_code":"PPL",
    "gn:name":"Qingcha",
    "gn:population":0,
    "gn:timezone":"Asia/Shanghai",
    "iso:country":"CN",
    "name:zho_x_preferred":[
        "\u9752\u8336"
    ],
    "wof:name":"Qingcha",
    "wof:placetype":"locality"
},
  "geometry": {"coordinates":[114.17143,26.11142000000001],"type":"Point"}
}