{
  "type": "Feature",
  "properties": {
    "gn:admin1_code":"29.0",
    "gn:asciiname":"Cangxi",
    "gn:country_code":"CN",
    "gn:dem":1542,
    "gn:feature_class":"P",
    "gn:feature_code":"PPL",
    "gn:name":"Cangxi",
    "gn:population":0,
    "gn:timezone":"Asia/Shanghai",
    "iso:country":"CN",
    "name:zho_x_preferred":[
        "\u6ca7\u6eaa"
    ],
    "wof:name":"Cangxi",
    "wof:placetype":"locality"
},
  "geometry": {"coordinates":[103.127,25.8875],"type":"Point"}
}