{
  "type": "Feature",
  "properties": {
    "gn:admin1_code":"9.0",
    "gn:asciiname":"Xisong'ao",
    "gn:country_code":"CN",
    "gn:dem":114,
    "gn:feature_class":"P",
    "gn:feature_code":"PPL",
    "gn:name":"Xisong\u2019ao",
    "gn:population":0,
    "gn:timezone":"Asia/Shanghai",
    "iso:country":"CN",
    "name:und_x_variant":[
        "Xisong\u2019ao"
    ],
    "name:zho_x_preferred":[
        "\u897f\u5b8b\u51f9"
    ],
    "wof:name":"Xisong'ao",
    "wof:placetype":"locality"
},
  "geometry": {"coordinates":[113.88103,32.44753],"type":"Point"}
}