{
  "type": "Feature",
  "properties": {
    "gn:admin1_code":"26.0",
    "gn:asciiname":"Hezhuangwan",
    "gn:country_code":"CN",
    "gn:dem":1298,
    "gn:feature_class":"P",
    "gn:feature_code":"PPL",
    "gn:name":"Hezhuangwan",
    "gn:population":0,
    "gn:timezone":"Asia/Shanghai",
    "iso:country":"CN",
    "name:zho_x_preferred":[
        "\u6cb3\u5e84\u6e7e"
    ],
    "wof:name":"Hezhuangwan",
    "wof:placetype":"locality"
},
  "geometry": {"coordinates":[109.14126,36.95652000000001],"type":"Point"}
}