{
  "type": "Feature",
  "properties": {
    "gn:admin1_code":"26.0",
    "gn:asciiname":"Dongjiazui",
    "gn:country_code":"CN",
    "gn:dem":1385,
    "gn:feature_class":"P",
    "gn:feature_code":"PPL",
    "gn:name":"Dongjiazui",
    "gn:population":0,
    "gn:timezone":"Asia/Shanghai",
    "iso:country":"CN",
    "name:und_x_variant":[
        "\u4e1c\u5bb6\u5480"
    ],
    "wof:name":"Dongjiazui",
    "wof:placetype":"locality"
},
  "geometry": {"coordinates":[107.67077,34.7555],"type":"Point"}
}