{
  "type": "Feature",
  "properties": {
    "gn:admin1_code":"11.0",
    "gn:asciiname":"Chenxinfa",
    "gn:country_code":"CN",
    "gn:dem":73,
    "gn:feature_class":"P",
    "gn:feature_code":"PPL",
    "gn:name":"Chenxinfa",
    "gn:population":0,
    "gn:timezone":"Asia/Shanghai",
    "iso:country":"CN",
    "name:zho_x_preferred":[
        "\u9648\u65b0\u53d1"
    ],
    "wof:name":"Chenxinfa",
    "wof:placetype":"locality"
},
  "geometry": {"coordinates":[113.10669,28.42353],"type":"Point"}
}