{
  "type": "Feature",
  "properties": {
    "gn:admin1_code":"19.0",
    "gn:asciiname":"Zhongjia Fangzi",
    "gn:country_code":"CN",
    "gn:dem":6,
    "gn:feature_class":"P",
    "gn:feature_code":"PPL",
    "gn:name":"Zhongjia Fangzi",
    "gn:population":0,
    "gn:timezone":"Asia/Shanghai",
    "iso:country":"CN",
    "name:zho_x_preferred":[
        "\u949f\u5bb6\u623f\u5b50"
    ],
    "wof:name":"Zhongjia Fangzi",
    "wof:placetype":"locality"
},
  "geometry": {"coordinates":[122.741,41.1647],"type":"Point"}
}