{
  "type": "Feature",
  "properties": {
    "gn:admin1_code":"16.0",
    "gn:asciiname":"Youli",
    "gn:cc2":"CN",
    "gn:country_code":"CN",
    "gn:dem":565,
    "gn:feature_class":"P",
    "gn:feature_code":"PPL",
    "gn:name":"Youli",
    "gn:population":0,
    "gn:timezone":"Asia/Shanghai",
    "iso:country":"CN",
    "name:und_x_variant":[
        "Yu-li",
        "Youli"
    ],
    "wof:name":"Youli",
    "wof:placetype":"locality"
},
  "geometry": {"coordinates":[106.53333000000001,24.93333],"type":"Point"}
}