{
  "type": "Feature",
  "properties": {
    "gn:admin1_code":"14.0",
    "gn:asciiname":"Zongben",
    "gn:country_code":"CN",
    "gn:dem":2259,
    "gn:feature_class":"P",
    "gn:feature_code":"PPL",
    "gn:name":"Zongben",
    "gn:population":0,
    "gn:timezone":"Asia/Urumqi",
    "iso:country":"CN",
    "name:zho_x_preferred":[
        "\u5b97\u672c"
    ],
    "wof:name":"Zongben",
    "wof:placetype":"locality"
},
  "geometry": {"coordinates":[94.81974,30.27412],"type":"Point"}
}