{
  "type": "Feature",
  "properties": {
    "gn:admin1_code":"18",
    "gn:asciiname":"Ajiazhai",
    "gn:country_code":"CN",
    "gn:dem":1591,
    "gn:feature_class":"P",
    "gn:feature_code":"PPL",
    "gn:name":"Ajiazhai",
    "gn:population":0,
    "gn:timezone":"Asia/Shanghai",
    "iso:country":"CN",
    "name:zho_x_preferred":[
        "\u963f\u621b\u5be8"
    ],
    "wof:name":"Ajiazhai",
    "wof:placetype":"locality"
},
  "geometry": {"coordinates":[104.979,26.6785],"type":"Point"}
}