{
  "type": "Feature",
  "properties": {
    "gn:admin1_code":"30.0",
    "gn:asciiname":"Fengchupai",
    "gn:country_code":"CN",
    "gn:dem":174,
    "gn:feature_class":"P",
    "gn:feature_code":"PPL",
    "gn:name":"Fengchupai",
    "gn:population":0,
    "gn:timezone":"Asia/Shanghai",
    "iso:country":"CN",
    "name:zho_x_preferred":[
        "Fengchupai"
    ],
    "name:zho_x_variant":[
        "\u67ab\u6775\u6392"
    ],
    "wof:name":"Fengchupai",
    "wof:placetype":"locality"
},
  "geometry": {"coordinates":[115.04194,24.41083],"type":"Point"}
}