{
  "type": "Feature",
  "properties": {
    "gn:country":"CN",
    "gn:fcode":"PPL",
    "gn:population":93297,
    "iso:country":"CN",
    "name:ceb_x_preferred":[
        "Dalai"
    ],
    "name:deu_x_preferred":[
        "Dalai"
    ],
    "name:fra_x_preferred":[
        "Dala\u00ef"
    ],
    "name:mlg_x_preferred":[
        "Dalai"
    ],
    "name:swe_x_preferred":[
        "Dalai"
    ],
    "name:und_x_variant":[
        "Talaicheng"
    ],
    "ne:ADM0CAP":0.0,
    "ne:ADM0NAME":"China",
    "ne:ADM0_A3":"CHN",
    "ne:ADM1NAME":"Jilin",
    "ne:ADMIN1_COD":5,
    "ne:CAPALT":0,
    "ne:CHANGED":0,
    "ne:CHECKME":0,
    "ne:COMPARE":0,
    "ne:DIFFASCII":0,
    "ne:ELEVATION":0.0,
    "ne:FEATURECLA":"Populated place",
    "ne:FEATURE_CL":"P",
    "ne:FEATURE_CO":"PPL",
    "ne:GEONAMEID":2037930,
    "ne:GEONAMESNO":"GeoNames rough area, rough name.",
    "ne:GN_ASCII":"Dalai",
    "ne:GN_POP":93297,
    "ne:GTOPO30":126.0,
    "ne:ISO_A2":"CN",
    "ne:LABELRANK":1,
    "ne:LATITUDE":45.499999,
    "ne:LONGITUDE":124.299999,
    "ne:LS_MATCH":1,
    "ne:LS_NAME":"Daan",
    "ne:MAX_AREAKM":19.0,
    "ne:MAX_AREAMI":7.0,
    "ne:MAX_BBXMAX":124.308333,
    "ne:MAX_BBXMIN":124.25,
    "ne:MAX_BBYMAX":45.525,
    "ne:MAX_BBYMIN":45.45,
    "ne:MAX_NATSCA":10.0,
    "ne:MAX_PERKM":28.0,
    "ne:MAX_PERMI":17.0,
    "ne:MAX_POP10":76294,
    "ne:MAX_POP20":0,
    "ne:MAX_POP300":0,
    "ne:MAX_POP310":0,
    "ne:MAX_POP50":0,
    "ne:MEAN_BBXC":124.283199,
    "ne:MEAN_BBYC":45.492876,
    "ne:MEGACITY":0,
    "ne:MIN_AREAKM":19.0,
    "ne:MIN_AREAMI":7.0,
    "ne:MIN_BBXMAX":124.308333,
    "ne:MIN_BBXMIN":124.25,
    "ne:MIN_BBYMAX":45.525,
    "ne:MIN_BBYMIN":45.45,
    "ne:MIN_PERKM":28.0,
    "ne:MIN_PERMI":17.0,
    "ne:NAME":"Daan",
    "ne:NAMEASCII":"Daan",
    "ne:NAMEDIFF":0,
    "ne:NATSCALE":10,
    "ne:POP1950":0,
    "ne:POP1955":0,
    "ne:POP1960":0,
    "ne:POP1965":0,
    "ne:POP1970":0,
    "ne:POP1975":0,
    "ne:POP1980":0,
    "ne:POP1985":0,
    "ne:POP1990":0,
    "ne:POP1995":0,
    "ne:POP2000":0,
    "ne:POP2005":0,
    "ne:POP2010":0,
    "ne:POP2015":0,
    "ne:POP2020":0,
    "ne:POP2025":0,
    "ne:POP2050":0,
    "ne:POP_MAX":93297,
    "ne:POP_MIN":76294,
    "ne:POP_OTHER":76294,
    "ne:RANK_MAX":8,
    "ne:RANK_MIN":8,
    "ne:SCALERANK":8,
    "ne:SOV0NAME":"China",
    "ne:SOV_A3":"CHN",
    "ne:TIMEZONE":"Asia/Harbin",
    "ne:UN_FID":0,
    "ne:UN_LAT":0.0,
    "ne:UN_LONG":0.0,
    "ne:WORLDCITY":0,
    "qs:name":"Dalai",
    "qs:photos_9r":0,
    "qs:photos_sr":0,
    "qs:pop_sr":"8",
    "wd:wordcount":21,
    "wof:name":"Dalai",
    "wof:placetype":"locality",
    "wof:population":93297
},
  "geometry": {"coordinates":[124.3,45.5],"type":"Point"}
}