{
  "type": "Feature",
  "properties": {
    "gn:admin1_code":"1.0",
    "gn:asciiname":"Balichencun",
    "gn:country_code":"CN",
    "gn:dem":38,
    "gn:feature_class":"P",
    "gn:feature_code":"PPL",
    "gn:name":"Balichencun",
    "gn:population":0,
    "gn:timezone":"Asia/Shanghai",
    "iso:country":"CN",
    "name:zho_x_preferred":[
        "\u516b\u91cc\u9648\u6751"
    ],
    "wof:name":"Balichencun",
    "wof:placetype":"locality"
},
  "geometry": {"coordinates":[115.23418999999998,33.03144],"type":"Point"}
}