{
  "type": "Feature",
  "properties": {
    "gn:admin1_code":"20.0",
    "gn:asciiname":"Damaohudong",
    "gn:country_code":"CN",
    "gn:dem":1588,
    "gn:feature_class":"P",
    "gn:feature_code":"PPL",
    "gn:name":"Damaohudong",
    "gn:population":0,
    "gn:timezone":"Asia/Shanghai",
    "iso:country":"CN",
    "name:und_x_variant":[
        "\u5927\u6bdb\u5ffd\u6d1e"
    ],
    "wof:name":"Damaohudong",
    "wof:placetype":"locality"
},
  "geometry": {"coordinates":[110.08602,41.28708],"type":"Point"}
}