{
  "type": "Feature",
  "properties": {
    "gn:admin1_code":"4.0",
    "gn:asciiname":"Zhangjiadun",
    "gn:country_code":"CN",
    "gn:dem":1,
    "gn:feature_class":"P",
    "gn:feature_code":"PPL",
    "gn:name":"Zhangjiadun",
    "gn:population":0,
    "gn:timezone":"Asia/Shanghai",
    "iso:country":"CN",
    "name:zho_x_preferred":[
        "Zhangjiadun"
    ],
    "name:zho_x_variant":[
        "\u5f20\u5bb6\u58a9"
    ],
    "wof:name":"Zhangjiadun",
    "wof:placetype":"locality"
},
  "geometry": {"coordinates":[119.85169,33.34435999999999],"type":"Point"}
}