{
  "type": "Feature",
  "properties": {
    "gn:admin1_code":"19.0",
    "gn:asciiname":"Banjietacun",
    "gn:country_code":"CN",
    "gn:dem":117,
    "gn:feature_class":"P",
    "gn:feature_code":"PPL",
    "gn:name":"Banjietacun",
    "gn:population":0,
    "gn:timezone":"Asia/Shanghai",
    "iso:country":"CN",
    "name:zho_x_preferred":[
        "\u534a\u622a\u5854\u6751"
    ],
    "wof:name":"Banjietacun",
    "wof:placetype":"locality"
},
  "geometry": {"coordinates":[121.974,42.089],"type":"Point"}
}