{
  "type": "Feature",
  "properties": {
    "gn:admin1_code":"11.0",
    "gn:asciiname":"Egongxi",
    "gn:country_code":"CN",
    "gn:dem":539,
    "gn:feature_class":"P",
    "gn:feature_code":"PPL",
    "gn:name":"Egongxi",
    "gn:population":0,
    "gn:timezone":"Asia/Shanghai",
    "iso:country":"CN",
    "name:zho_x_preferred":[
        "\u9e45\u516c\u6eaa"
    ],
    "wof:name":"Egongxi",
    "wof:placetype":"locality"
},
  "geometry": {"coordinates":[109.13273,27.30308],"type":"Point"}
}