{
  "type": "Feature",
  "properties": {
    "gn:admin1_code":"33",
    "gn:asciiname":"Puzi",
    "gn:country_code":"CN",
    "gn:dem":579,
    "gn:feature_class":"P",
    "gn:feature_code":"PPLA4",
    "gn:name":"Puzi",
    "gn:population":0,
    "gn:timezone":"Asia/Shanghai",
    "iso:country":"CN",
    "name:und_x_variant":[
        "Puziba",
        "Puzi Zhen"
    ],
    "name:zho_x_preferred":[
        "\u666e\u5b50"
    ],
    "name:zho_x_variant":[
        "\u666e\u5b50\u9547"
    ],
    "wof:name":"Puzi",
    "wof:placetype":"locality"
},
  "geometry": {"coordinates":[108.32825,29.63292],"type":"Point"}
}