{
  "type": "Feature",
  "properties": {
    "gn:admin1_code":"18",
    "gn:asciiname":"Zugu",
    "gn:country_code":"CN",
    "gn:dem":2303,
    "gn:feature_class":"P",
    "gn:feature_code":"PPL",
    "gn:name":"Zugu",
    "gn:population":0,
    "gn:timezone":"Asia/Shanghai",
    "iso:country":"CN",
    "name:zho_x_preferred":[
        "\u79df\u8c37"
    ],
    "wof:name":"Zugu",
    "wof:placetype":"locality"
},
  "geometry": {"coordinates":[103.864,26.6125],"type":"Point"}
}