{
  "type": "Feature",
  "properties": {
    "gn:admin1_code":"10",
    "gn:asciiname":"Houguanzhai",
    "gn:country_code":"CN",
    "gn:dem":39,
    "gn:feature_class":"P",
    "gn:feature_code":"PPL",
    "gn:name":"Houguanzhai",
    "gn:population":0,
    "gn:timezone":"Asia/Shanghai",
    "iso:country":"CN",
    "name:zho_x_preferred":[
        "\u540e\u89c2\u5be8"
    ],
    "wof:name":"Houguanzhai",
    "wof:placetype":"locality"
},
  "geometry": {"coordinates":[115.03247,36.80593],"type":"Point"}
}