{
  "type": "Feature",
  "properties": {
    "gn:admin1_code":"05",
    "gn:asciiname":"Linzigoucun",
    "gn:country_code":"CN",
    "gn:dem":380,
    "gn:feature_class":"P",
    "gn:feature_code":"PPL",
    "gn:name":"Linzigoucun",
    "gn:population":0,
    "gn:timezone":"Asia/Shanghai",
    "iso:country":"CN",
    "name:und_x_variant":[
        "Linzigou",
        "\u6797\u5b50\u6c9f",
        "Linzigoucun"
    ],
    "name:zho_x_preferred":[
        "\u6797\u5b50\u6c9f\u6751"
    ],
    "wof:name":"Linzigoucun",
    "wof:placetype":"locality"
},
  "geometry": {"coordinates":[129.98141000000001,43.31374],"type":"Point"}
}