{
  "type": "Feature",
  "properties": {
    "gn:admin1_code":"30.0",
    "gn:asciiname":"Shangban",
    "gn:country_code":"CN",
    "gn:dem":264,
    "gn:feature_class":"P",
    "gn:feature_code":"PPL",
    "gn:name":"Shangban",
    "gn:population":0,
    "gn:timezone":"Asia/Shanghai",
    "iso:country":"CN",
    "name:zho_x_preferred":[
        "Shangban"
    ],
    "name:zho_x_variant":[
        "\u4e0a\u534a"
    ],
    "wof:name":"Shangban",
    "wof:placetype":"locality"
},
  "geometry": {"coordinates":[112.63194,24.52056],"type":"Point"}
}