{
  "type": "Feature",
  "properties": {
    "gn:admin1_code":"19.0",
    "gn:asciiname":"Kangjia Buzi",
    "gn:country_code":"CN",
    "gn:dem":293,
    "gn:feature_class":"P",
    "gn:feature_code":"PPL",
    "gn:name":"Kangjia Buzi",
    "gn:population":0,
    "gn:timezone":"Asia/Shanghai",
    "iso:country":"CN",
    "name:und_x_variant":[
        "Kangjiabaozi",
        "Kangjia Buzi"
    ],
    "name:zho_x_preferred":[
        "\u5eb7\u5bb6\u5821\u5b50"
    ],
    "wof:name":"Kangjia Buzi",
    "wof:placetype":"locality"
},
  "geometry": {"coordinates":[123.78248000000001,40.63098],"type":"Point"}
}