{
  "type": "Feature",
  "properties": {
    "gn:admin1_code":"10.0",
    "gn:asciiname":"Nanduanyu",
    "gn:country_code":"CN",
    "gn:dem":690,
    "gn:feature_class":"P",
    "gn:feature_code":"PPL",
    "gn:name":"Nanduanyu",
    "gn:population":0,
    "gn:timezone":"Asia/Shanghai",
    "iso:country":"CN",
    "name:zho_x_preferred":[
        "\u5357\u6bb5\u5cea"
    ],
    "wof:name":"Nanduanyu",
    "wof:placetype":"locality"
},
  "geometry": {"coordinates":[113.92341999999999,38.52479],"type":"Point"}
}