{
  "type": "Feature",
  "properties": {
    "gn:admin1_code":"24",
    "gn:asciiname":"Kouquancun",
    "gn:country_code":"CN",
    "gn:dem":1942,
    "gn:feature_class":"P",
    "gn:feature_code":"PPL",
    "gn:name":"Kouquancun",
    "gn:population":0,
    "gn:timezone":"Asia/Shanghai",
    "iso:country":"CN",
    "wof:name":"Kouquancun",
    "wof:placetype":"locality"
},
  "geometry": {"coordinates":[113.875,39.86833],"type":"Point"}
}