{
  "type": "Feature",
  "properties": {
    "gn:admin1_code":"8.0",
    "gn:asciiname":"Changlincun",
    "gn:country_code":"CN",
    "gn:dem":61,
    "gn:feature_class":"P",
    "gn:feature_code":"PPL",
    "gn:name":"Changlincun",
    "gn:population":0,
    "gn:timezone":"Asia/Shanghai",
    "iso:country":"CN",
    "name:zho_x_preferred":[
        "\u957f\u6797\u6751"
    ],
    "wof:name":"Changlincun",
    "wof:placetype":"locality"
},
  "geometry": {"coordinates":[132.13426000000001,46.82235],"type":"Point"}
}