{
  "type": "Feature",
  "properties": {
    "gn:admin1_code":"18",
    "gn:asciiname":"Caoba",
    "gn:country_code":"CN",
    "gn:dem":489,
    "gn:feature_class":"P",
    "gn:feature_code":"PPL",
    "gn:name":"Caoba",
    "gn:population":0,
    "gn:timezone":"Asia/Shanghai",
    "iso:country":"CN",
    "name:cat_x_preferred":[
        "Caoba"
    ],
    "name:zho_x_preferred":[
        "\u8349\u575d"
    ],
    "wof:name":"Caoba",
    "wof:placetype":"locality"
},
  "geometry": {"coordinates":[108.349,28.404],"type":"Point"}
}