{
  "type": "Feature",
  "properties": {
    "gn:admin1_code":"9.0",
    "gn:asciiname":"Banjielou",
    "gn:country_code":"CN",
    "gn:dem":57,
    "gn:feature_class":"P",
    "gn:feature_code":"PPL",
    "gn:name":"Banjielou",
    "gn:population":0,
    "gn:timezone":"Asia/Shanghai",
    "iso:country":"CN",
    "name:zho_x_preferred":[
        "\u534a\u622a\u697c"
    ],
    "wof:name":"Banjielou",
    "wof:placetype":"locality"
},
  "geometry": {"coordinates":[114.3456,33.84632],"type":"Point"}
}