{
  "type": "Feature",
  "properties": {
    "gn:admin1_code":"16.0",
    "gn:asciiname":"Jiafa",
    "gn:country_code":"CN",
    "gn:dem":425,
    "gn:feature_class":"P",
    "gn:feature_code":"PPL",
    "gn:name":"Jiafa",
    "gn:population":0,
    "gn:timezone":"Asia/Shanghai",
    "iso:country":"CN",
    "name:zho_x_preferred":[
        "\u7532\u6cd5"
    ],
    "wof:name":"Jiafa",
    "wof:placetype":"locality"
},
  "geometry": {"coordinates":[106.92100000000001,24.8094],"type":"Point"}
}