{
  "type": "Feature",
  "properties": {
    "gn:admin1_code":"5",
    "gn:asciiname":"Ershijiazi",
    "gn:country_code":"CN",
    "gn:dem":277,
    "gn:feature_class":"P",
    "gn:feature_code":"PPL",
    "gn:name":"Ershijiazi",
    "gn:population":0,
    "gn:timezone":"Asia/Shanghai",
    "iso:country":"CN",
    "name:zho_x_preferred":[
        "\u4e8c\u5341\u5bb6\u5b50"
    ],
    "wof:name":"Ershijiazi",
    "wof:placetype":"locality"
},
  "geometry": {"coordinates":[127.10212,43.32797],"type":"Point"}
}