{
  "type": "Feature",
  "properties": {
    "gn:admin1_code":"14.0",
    "gn:asciiname":"Nahesimu",
    "gn:country_code":"CN",
    "gn:dem":4478,
    "gn:feature_class":"P",
    "gn:feature_code":"PPL",
    "gn:name":"Nahesimu",
    "gn:population":0,
    "gn:timezone":"Asia/Urumqi",
    "iso:country":"CN",
    "name:zho_x_preferred":[
        "\u90a3\u6cb3\u601d\u6bcd"
    ],
    "wof:name":"Nahesimu",
    "wof:placetype":"locality"
},
  "geometry": {"coordinates":[93.89565,31.80706],"type":"Point"}
}