{
  "type": "Feature",
  "properties": {
    "gn:admin1_code":"2.0",
    "gn:asciiname":"Yangshan",
    "gn:country_code":"CN",
    "gn:dem":8,
    "gn:feature_class":"P",
    "gn:feature_code":"PPL",
    "gn:name":"Yangshan",
    "gn:population":0,
    "gn:timezone":"Asia/Shanghai",
    "iso:country":"CN",
    "name:ceb_x_preferred":[
        "Yangshan"
    ],
    "name:deu_x_preferred":[
        "Yangshan"
    ],
    "name:fra_x_preferred":[
        "Yangshan"
    ],
    "name:rus_x_preferred":[
        "\u042f\u043d\u0448\u0430\u043d\u044c"
    ],
    "name:und_x_variant":[
        "\u6768\u5c71"
    ],
    "wof:name":"Yangshan",
    "wof:placetype":"locality"
},
  "geometry": {"coordinates":[120.54447999999999,30.80567000000001],"type":"Point"}
}