{
  "type": "Feature",
  "properties": {
    "gn:admin1_code":"9.0",
    "gn:asciiname":"Ganliu",
    "gn:country_code":"CN",
    "gn:dem":82,
    "gn:feature_class":"P",
    "gn:feature_code":"PPL",
    "gn:name":"Ganliu",
    "gn:population":0,
    "gn:timezone":"Asia/Shanghai",
    "iso:country":"CN",
    "name:zho_x_preferred":[
        "\u7518\u5218"
    ],
    "wof:name":"Ganliu",
    "wof:placetype":"locality"
},
  "geometry": {"coordinates":[113.45081999999999,33.62481],"type":"Point"}
}