{
  "type": "Feature",
  "properties": {
    "gn:admin1_code":"19",
    "gn:asciiname":"Tonggou Linchang",
    "gn:country_code":"CN",
    "gn:dem":526,
    "gn:feature_class":"P",
    "gn:feature_code":"PPLF",
    "gn:name":"Tonggou Linchang",
    "gn:population":0,
    "gn:timezone":"Asia/Shanghai",
    "iso:country":"CN",
    "name:und_x_variant":[
        "\u901a\u6c9f\u6797\u573a"
    ],
    "wof:name":"Tonggou Linchang",
    "wof:placetype":"locality"
},
  "geometry": {"coordinates":[124.4601,41.59023],"type":"Point"}
}