{
  "type": "Feature",
  "properties": {
    "gn:admin1_code":"30",
    "gn:asciiname":"Chatingcun",
    "gn:country_code":"CN",
    "gn:dem":26,
    "gn:feature_class":"P",
    "gn:feature_code":"PPL",
    "gn:name":"Chatingcun",
    "gn:population":0,
    "gn:timezone":"Asia/Urumqi",
    "iso:country":"CN",
    "name:zho_x_preferred":[
        "\u8336\u4ead\u6751"
    ],
    "wof:name":"Chatingcun",
    "wof:placetype":"locality"
},
  "geometry": {"coordinates":[111.17635,21.57759],"type":"Point"}
}