{
  "type": "Feature",
  "properties": {
    "gn:admin1_code":"5.0",
    "gn:asciiname":"Housan Jiazi",
    "gn:country_code":"CN",
    "gn:dem":150,
    "gn:feature_class":"P",
    "gn:feature_code":"PPL",
    "gn:name":"Housan Jiazi",
    "gn:population":0,
    "gn:timezone":"Asia/Shanghai",
    "iso:country":"CN",
    "name:zho_x_preferred":[
        "\u540e\u4e09\u5bb6\u5b50"
    ],
    "wof:name":"Housan Jiazi",
    "wof:placetype":"locality"
},
  "geometry": {"coordinates":[123.71247,43.83872],"type":"Point"}
}