{
  "type": "Feature",
  "properties": {
    "gn:admin1_code":"25.0",
    "gn:asciiname":"Wawukuang",
    "gn:country_code":"CN",
    "gn:dem":84,
    "gn:feature_class":"P",
    "gn:feature_code":"PPL",
    "gn:name":"Wawukuang",
    "gn:population":0,
    "gn:timezone":"Asia/Shanghai",
    "iso:country":"CN",
    "name:zho_x_preferred":[
        "\u74e6\u5c4b\u593c"
    ],
    "wof:name":"Wawukuang",
    "wof:placetype":"locality"
},
  "geometry": {"coordinates":[120.84733,36.95383],"type":"Point"}
}