{
  "type": "Feature",
  "properties": {
    "gn:admin1_code":"3.0",
    "gn:asciiname":"Gongling",
    "gn:country_code":"CN",
    "gn:dem":340,
    "gn:feature_class":"P",
    "gn:feature_code":"PPL",
    "gn:name":"Gongling",
    "gn:population":0,
    "gn:timezone":"Asia/Shanghai",
    "iso:country":"CN",
    "name:und_x_variant":[
        "\u62f1\u5cad"
    ],
    "wof:name":"Gongling",
    "wof:placetype":"locality"
},
  "geometry": {"coordinates":[114.54088,29.17413],"type":"Point"}
}