{
  "type": "Feature",
  "properties": {
    "gn:country":"CN",
    "gn:fcode":"PPL",
    "gn:pop":499,
    "iso:country":"CN",
    "qs:name":"Wawu",
    "qs:photos_9r":0,
    "qs:photos_sr":0,
    "qs:pop_sr":"2",
    "wof:name":"Wawu",
    "wof:placetype":"locality",
    "wof:population":499
},
  "geometry": {"coordinates":[109.40944,27.65556],"type":"Point"}
}