{
  "type": "Feature",
  "properties": {
    "gn:admin1_code":"32.0",
    "gn:asciiname":"Juehuo",
    "gn:country_code":"CN",
    "gn:dem":2655,
    "gn:feature_class":"P",
    "gn:feature_code":"PPL",
    "gn:name":"Juehuo",
    "gn:population":0,
    "gn:timezone":"Asia/Shanghai",
    "iso:country":"CN",
    "name:zho_x_preferred":[
        "\u89c9\u8c41"
    ],
    "wof:name":"Juehuo",
    "wof:placetype":"locality"
},
  "geometry": {"coordinates":[103.34838000000001,27.84885],"type":"Point"}
}