{
  "type": "Feature",
  "properties": {
    "gn:admin1_code":"26.0",
    "gn:asciiname":"Taoshuping",
    "gn:country_code":"CN",
    "gn:dem":1578,
    "gn:feature_class":"P",
    "gn:feature_code":"PPL",
    "gn:name":"Taoshuping",
    "gn:population":0,
    "gn:timezone":"Asia/Shanghai",
    "iso:country":"CN",
    "name:und_x_variant":[
        "\u6843\u6811\u5e73"
    ],
    "wof:name":"Taoshuping",
    "wof:placetype":"locality"
},
  "geometry": {"coordinates":[106.80285000000001,33.87113],"type":"Point"}
}