{
  "type": "Feature",
  "properties": {
    "gn:admin1_code":"18",
    "gn:asciiname":"Xiamuka",
    "gn:country_code":"CN",
    "gn:dem":1519,
    "gn:feature_class":"P",
    "gn:feature_code":"PPL",
    "gn:name":"Xiamuka",
    "gn:population":0,
    "gn:timezone":"Asia/Shanghai",
    "iso:country":"CN",
    "name:zho_x_preferred":[
        "\u4e0b\u6728\u5361"
    ],
    "wof:name":"Xiamuka",
    "wof:placetype":"locality"
},
  "geometry": {"coordinates":[104.98999999999999,25.6691],"type":"Point"}
}