{
  "type": "Feature",
  "properties": {
    "gn:admin1_code":"16.0",
    "gn:asciiname":"Jia'er",
    "gn:country_code":"CN",
    "gn:dem":621,
    "gn:feature_class":"P",
    "gn:feature_code":"PPL",
    "gn:name":"Jia\u2019er",
    "gn:population":0,
    "gn:timezone":"Asia/Shanghai",
    "iso:country":"CN",
    "name:und_x_variant":[
        "Jia\u2019er"
    ],
    "name:zho_x_preferred":[
        "\u52a0\u800c"
    ],
    "wof:name":"Jia'er",
    "wof:placetype":"locality"
},
  "geometry": {"coordinates":[107.261,24.2696],"type":"Point"}
}