{
  "type": "Feature",
  "properties": {
    "gn:admin1_code":"30",
    "gn:asciiname":"Shuangpei",
    "gn:country_code":"CN",
    "gn:dem":102,
    "gn:feature_class":"P",
    "gn:feature_code":"PPL",
    "gn:name":"Shuangpei",
    "gn:population":0,
    "gn:timezone":"Asia/Shanghai",
    "iso:country":"CN",
    "name:und_x_variant":[
        "\u53cc\u6c9b"
    ],
    "wof:name":"Shuangpei",
    "wof:placetype":"locality"
},
  "geometry": {"coordinates":[115.77,23.03778],"type":"Point"}
}