{
  "type": "Feature",
  "properties": {
    "gn:admin1_code":"26.0",
    "gn:asciiname":"Shajia'ao",
    "gn:country_code":"CN",
    "gn:dem":973,
    "gn:feature_class":"P",
    "gn:feature_code":"PPLA4",
    "gn:name":"Shajia\u2019ao",
    "gn:population":0,
    "gn:timezone":"Asia/Shanghai",
    "iso:country":"CN",
    "name:und_x_variant":[
        "Shajia\u2019ao",
        "\u6c99\u5bb6\u5773"
    ],
    "wof:name":"Shajia'ao",
    "wof:placetype":"locality"
},
  "geometry": {"coordinates":[107.23029,34.67274],"type":"Point"}
}