{
  "type": "Feature",
  "properties": {
    "gn:admin1_code":"14",
    "gn:asciiname":"Shenkezi",
    "gn:country_code":"CN",
    "gn:dem":3983,
    "gn:feature_class":"P",
    "gn:feature_code":"PPL",
    "gn:name":"Shenkezi",
    "gn:population":0,
    "gn:timezone":"Asia/Urumqi",
    "iso:country":"CN",
    "name:zho_x_preferred":[
        "\u7533\u514b\u5b5c"
    ],
    "wof:name":"Shenkezi",
    "wof:placetype":"locality"
},
  "geometry": {"coordinates":[88.5102,29.0424],"type":"Point"}
}