{
  "type": "Feature",
  "properties": {
    "gn:admin1_code":"25.0",
    "gn:asciiname":"Shangduo Yukuang",
    "gn:country_code":"CN",
    "gn:dem":89,
    "gn:feature_class":"P",
    "gn:feature_code":"PPL",
    "gn:name":"Shangduo Yukuang",
    "gn:population":0,
    "gn:timezone":"Asia/Shanghai",
    "iso:country":"CN",
    "name:zho_x_preferred":[
        "\u4e0a\u579b\u7389\u593c"
    ],
    "wof:name":"Shangduo Yukuang",
    "wof:placetype":"locality"
},
  "geometry": {"coordinates":[121.1934,37.11566],"type":"Point"}
}