{
  "type": "Feature",
  "properties": {
    "gn:admin1_code":"32.0",
    "gn:asciiname":"Wenyin",
    "gn:country_code":"CN",
    "gn:dem":758,
    "gn:feature_class":"P",
    "gn:feature_code":"PPL",
    "gn:name":"Wenyin",
    "gn:population":0,
    "gn:timezone":"Asia/Shanghai",
    "iso:country":"CN",
    "name:zho_x_preferred":[
        "\u6587\u5370"
    ],
    "wof:name":"Wenyin",
    "wof:placetype":"locality"
},
  "geometry": {"coordinates":[104.98918999999999,28.11748],"type":"Point"}
}