{
  "type": "Feature",
  "properties": {
    "gn:admin1_code":"11",
    "gn:asciiname":"Shangmachong",
    "gn:country_code":"CN",
    "gn:dem":626,
    "gn:feature_class":"P",
    "gn:feature_code":"PPL",
    "gn:name":"Shangmachong",
    "gn:population":0,
    "gn:timezone":"Asia/Shanghai",
    "iso:country":"CN",
    "name:zho_x_preferred":[
        "\u4e0a\u9ebb\u51b2"
    ],
    "wof:name":"Shangmachong",
    "wof:placetype":"locality"
},
  "geometry": {"coordinates":[111.66621000000001,25.09483],"type":"Point"}
}