{
  "type": "Feature",
  "properties": {
    "gn:admin1_code":"2.0",
    "gn:asciiname":"Lupu",
    "gn:country_code":"CN",
    "gn:dem":7,
    "gn:feature_class":"P",
    "gn:feature_code":"PPL",
    "gn:name":"Lupu",
    "gn:population":0,
    "gn:timezone":"Asia/Shanghai",
    "iso:country":"CN",
    "name:ceb_x_preferred":[
        "Lupu"
    ],
    "name:deu_x_preferred":[
        "Lupu"
    ],
    "name:fin_x_preferred":[
        "Lupu"
    ],
    "name:fra_x_preferred":[
        "Lupu"
    ],
    "name:ita_x_preferred":[
        "Lupu"
    ],
    "name:nld_x_preferred":[
        "Lupu"
    ],
    "name:ron_x_preferred":[
        "Lupu"
    ],
    "name:rus_x_preferred":[
        "\u041b\u0443\u043f\u0443"
    ],
    "name:swe_x_preferred":[
        "Lupu"
    ],
    "name:ukr_x_preferred":[
        "\u041b\u0443\u043f\u0443"
    ],
    "name:zho_x_preferred":[
        "\u82a6\u6d66"
    ],
    "wof:name":"Lupu",
    "wof:placetype":"locality"
},
  "geometry": {"coordinates":[121.74325,29.64691],"type":"Point"}
}