{
  "type": "Feature",
  "properties": {
    "gn:admin1_code":"29",
    "gn:asciiname":"Leyingcun",
    "gn:country_code":"CN",
    "gn:dem":2030,
    "gn:feature_class":"P",
    "gn:feature_code":"PPL",
    "gn:name":"Leyingcun",
    "gn:population":0,
    "gn:timezone":"Asia/Shanghai",
    "iso:country":"CN",
    "name:zho_x_preferred":[
        "\u4e50\u8425\u6751"
    ],
    "wof:name":"Leyingcun",
    "wof:placetype":"locality"
},
  "geometry": {"coordinates":[102.36933000000001,24.88963],"type":"Point"}
}