{
  "type": "Feature",
  "properties": {
    "gn:admin1_code":"12.0",
    "gn:asciiname":"Houping",
    "gn:country_code":"CN",
    "gn:dem":1708,
    "gn:feature_class":"P",
    "gn:feature_code":"PPL",
    "gn:name":"Houping",
    "gn:population":0,
    "gn:timezone":"Asia/Shanghai",
    "iso:country":"CN",
    "name:zho_x_preferred":[
        "Houping"
    ],
    "name:zho_x_variant":[
        "\u540e\u576a"
    ],
    "wof:name":"Houping",
    "wof:placetype":"locality"
},
  "geometry": {"coordinates":[109.98233999999999,30.08774],"type":"Point"}
}