{
  "type": "Feature",
  "properties": {
    "gn:admin1_code":"11.0",
    "gn:asciiname":"Caoduilong",
    "gn:country_code":"CN",
    "gn:dem":427,
    "gn:feature_class":"P",
    "gn:feature_code":"PPL",
    "gn:name":"Caoduilong",
    "gn:population":0,
    "gn:timezone":"Asia/Shanghai",
    "iso:country":"CN",
    "name:zho_x_preferred":[
        "\u66f9\u5bf9\u5785"
    ],
    "wof:name":"Caoduilong",
    "wof:placetype":"locality"
},
  "geometry": {"coordinates":[113.50471,25.79932],"type":"Point"}
}