{
  "type": "Feature",
  "properties": {
    "gn:admin1_code":"11.0",
    "gn:asciiname":"Getengchong",
    "gn:country_code":"CN",
    "gn:dem":133,
    "gn:feature_class":"P",
    "gn:feature_code":"PPL",
    "gn:name":"Getengchong",
    "gn:population":0,
    "gn:timezone":"Asia/Shanghai",
    "iso:country":"CN",
    "name:zho_x_preferred":[
        "\u845b\u85e4\u51b2"
    ],
    "wof:name":"Getengchong",
    "wof:placetype":"locality"
},
  "geometry": {"coordinates":[112.86336,27.35754],"type":"Point"}
}