{
  "type": "Feature",
  "properties": {
    "gn:admin1_code":"5.0",
    "gn:asciiname":"Qianjiushiyi",
    "gn:country_code":"CN",
    "gn:dem":155,
    "gn:feature_class":"P",
    "gn:feature_code":"PPL",
    "gn:name":"Qianjiushiyi",
    "gn:population":0,
    "gn:timezone":"Asia/Shanghai",
    "iso:country":"CN",
    "name:zho_x_preferred":[
        "\u524d\u4e5d\u5341\u4e00"
    ],
    "wof:name":"Qianjiushiyi",
    "wof:placetype":"locality"
},
  "geometry": {"coordinates":[123.62785,44.3281],"type":"Point"}
}