{
  "type": "Feature",
  "properties": {
    "gn:admin1_code":"29.0",
    "gn:asciiname":"Dongjiazhai",
    "gn:country_code":"CN",
    "gn:dem":1802,
    "gn:feature_class":"P",
    "gn:feature_code":"PPL",
    "gn:name":"Dongjiazhai",
    "gn:population":0,
    "gn:timezone":"Asia/Shanghai",
    "iso:country":"CN",
    "name:zho_x_preferred":[
        "\u8463\u5bb6\u5be8"
    ],
    "wof:name":"Dongjiazhai",
    "wof:placetype":"locality"
},
  "geometry": {"coordinates":[100.078,23.0921],"type":"Point"}
}