{
  "type": "Feature",
  "properties": {
    "gn:admin1_code":"32.0",
    "gn:asciiname":"Rongyan",
    "gn:country_code":"CN",
    "gn:dem":3285,
    "gn:feature_class":"P",
    "gn:feature_code":"PPL",
    "gn:name":"Rongyan",
    "gn:population":0,
    "gn:timezone":"Asia/Shanghai",
    "iso:country":"CN",
    "name:zho_x_preferred":[
        "\u7ed2\u7814"
    ],
    "wof:name":"Rongyan",
    "wof:placetype":"locality"
},
  "geometry": {"coordinates":[99.4889,28.8551],"type":"Point"}
}