{
  "type": "Feature",
  "properties": {
    "gn:admin1_code":"29.0",
    "gn:asciiname":"Songyuan",
    "gn:country_code":"CN",
    "gn:dem":1807,
    "gn:feature_class":"P",
    "gn:feature_code":"PPL",
    "gn:name":"Songyuan",
    "gn:population":0,
    "gn:timezone":"Asia/Shanghai",
    "iso:country":"CN",
    "name:zho_x_preferred":[
        "\u677e\u56ed"
    ],
    "wof:name":"Songyuan",
    "wof:placetype":"locality"
},
  "geometry": {"coordinates":[97.8839,24.8949],"type":"Point"}
}