{
  "type": "Feature",
  "properties": {
    "gn:admin1_code":"2.0",
    "gn:asciiname":"Houtianpu",
    "gn:country_code":"CN",
    "gn:dem":67,
    "gn:feature_class":"P",
    "gn:feature_code":"PPL",
    "gn:name":"Houtianpu",
    "gn:population":0,
    "gn:timezone":"Asia/Shanghai",
    "iso:country":"CN",
    "name:zho_x_preferred":[
        "\u540e\u7530\u94fa"
    ],
    "wof:name":"Houtianpu",
    "wof:placetype":"locality"
},
  "geometry": {"coordinates":[119.17564,28.97017],"type":"Point"}
}