{
  "type": "Feature",
  "properties": {
    "gn:admin1_code":"14.0",
    "gn:asciiname":"Qutacun",
    "gn:country_code":"CN",
    "gn:dem":4422,
    "gn:feature_class":"P",
    "gn:feature_code":"PPL",
    "gn:name":"Qutacun",
    "gn:population":0,
    "gn:timezone":"Asia/Urumqi",
    "iso:country":"CN",
    "name:zho_x_preferred":[
        "\u66f2\u5854\u6751"
    ],
    "wof:name":"Qutacun",
    "wof:placetype":"locality"
},
  "geometry": {"coordinates":[98.60679,30.102],"type":"Point"}
}