{
  "type": "Feature",
  "properties": {
    "gn:admin1_code":"13.0",
    "gn:asciiname":"Qiongsayi",
    "gn:country_code":"CN",
    "gn:dem":2625,
    "gn:feature_class":"P",
    "gn:feature_code":"PPL",
    "gn:name":"Qiongsayi",
    "gn:population":0,
    "gn:timezone":"Asia/Shanghai",
    "iso:country":"CN",
    "name:zho_x_preferred":[
        "\u743c\u8428\u4f9d"
    ],
    "wof:name":"Qiongsayi",
    "wof:placetype":"locality"
},
  "geometry": {"coordinates":[81.89471999999998,36.34696],"type":"Point"}
}