{
  "type": "Feature",
  "properties": {
    "gn:admin1_code":"26.0",
    "gn:asciiname":"Daheiwan",
    "gn:country_code":"CN",
    "gn:dem":1697,
    "gn:feature_class":"P",
    "gn:feature_code":"PPL",
    "gn:name":"Daheiwan",
    "gn:population":0,
    "gn:timezone":"Asia/Shanghai",
    "iso:country":"CN",
    "name:und_x_variant":[
        "\u5927\u9ed1\u6e7e"
    ],
    "wof:name":"Daheiwan",
    "wof:placetype":"locality"
},
  "geometry": {"coordinates":[106.71679,33.53615],"type":"Point"}
}