{
  "type": "Feature",
  "properties": {
    "gn:admin1_code":"04",
    "gn:asciiname":"Dingzhuangcun",
    "gn:country_code":"CN",
    "gn:dem":17,
    "gn:feature_class":"P",
    "gn:feature_code":"PPL",
    "gn:name":"Dingzhuangcun",
    "gn:population":0,
    "gn:timezone":"Asia/Shanghai",
    "iso:country":"CN",
    "name:und_x_variant":[
        "Ting-chia-p\u2019u",
        "Ting-chuang-p\u2019u",
        "Ting-chuang",
        "Dingjiapu",
        "Dingzhuang",
        "Dingzhuangcun"
    ],
    "name:zho_x_preferred":[
        "\u4e01\u5e84"
    ],
    "name:zho_x_variant":[
        "\u4e01\u5e84\u6751"
    ],
    "wof:name":"Dingzhuangcun",
    "wof:placetype":"locality"
},
  "geometry": {"coordinates":[119.46191,31.97931],"type":"Point"}
}