{
  "type": "Feature",
  "properties": {
    "gn:admin1_code":"13.0",
    "gn:asciiname":"Huayuan",
    "gn:country_code":"CN",
    "gn:dem":1626,
    "gn:feature_class":"P",
    "gn:feature_code":"PPL",
    "gn:name":"Huayuan",
    "gn:population":0,
    "gn:timezone":"Asia/Urumqi",
    "iso:country":"CN",
    "name:ceb_x_preferred":[
        "Huayuan"
    ],
    "name:deu_x_preferred":[
        "Huayuan"
    ],
    "name:kaz_x_preferred":[
        "\u062d\u06cb\u0627\u064a\u06cb\u0627\u0646 \u0627\u06cb\u0649\u0644\u0649"
    ],
    "name:kor_x_preferred":[
        "\ud654\uc704\uc548"
    ],
    "name:uig_x_preferred":[
        "\u062e\u06c7\u0627\u064a\u06c7\u06d5\u0646 \u064a\u06d0\u0632\u0649\u0633\u0649"
    ],
    "name:und_x_variant":[
        "Huayuan Xiang"
    ],
    "name:zho_x_preferred":[
        "\u82b1\u56ed\u4e61"
    ],
    "wof:name":"Huayuan",
    "wof:placetype":"locality"
},
  "geometry": {"coordinates":[92.95918,43.61744],"type":"Point"}
}