{
  "type": "Feature",
  "properties": {
    "gn:admin1_code":"31.0",
    "gn:asciiname":"Yulou",
    "gn:country_code":"CN",
    "gn:dem":37,
    "gn:feature_class":"P",
    "gn:feature_code":"PPL",
    "gn:name":"Yulou",
    "gn:population":0,
    "gn:timezone":"Asia/Shanghai",
    "iso:country":"CN",
    "name:zho_x_preferred":[
        "Yulou"
    ],
    "name:zho_x_variant":[
        "\u7389\u697c"
    ],
    "wof:name":"Yulou",
    "wof:placetype":"locality"
},
  "geometry": {"coordinates":[110.1093,19.93834],"type":"Point"}
}