{
  "type": "Feature",
  "properties": {
    "gn:admin1_code":"29.0",
    "gn:asciiname":"Dashuiqing",
    "gn:country_code":"CN",
    "gn:dem":2063,
    "gn:feature_class":"P",
    "gn:feature_code":"PPL",
    "gn:name":"Dashuiqing",
    "gn:population":0,
    "gn:timezone":"Asia/Shanghai",
    "iso:country":"CN",
    "name:zho_x_preferred":[
        "\u5927\u6c34\u7b90"
    ],
    "wof:name":"Dashuiqing",
    "wof:placetype":"locality"
},
  "geometry": {"coordinates":[100.32299999999999,26.1456],"type":"Point"}
}