{
  "type": "Feature",
  "properties": {
    "gn:admin1_code":"5.0",
    "gn:asciiname":"Houmu Sitai",
    "gn:country_code":"CN",
    "gn:dem":156,
    "gn:feature_class":"P",
    "gn:feature_code":"PPL",
    "gn:name":"Houmu Sitai",
    "gn:population":0,
    "gn:timezone":"Asia/Shanghai",
    "iso:country":"CN",
    "name:zho_x_preferred":[
        "\u540e\u6728\u56db\u53f0"
    ],
    "wof:name":"Houmu Sitai",
    "wof:placetype":"locality"
},
  "geometry": {"coordinates":[122.60321999999999,44.68776],"type":"Point"}
}