{
  "type": "Feature",
  "properties": {
    "gn:admin1_code":"13.0",
    "gn:asciiname":"Kudouke",
    "gn:country_code":"CN",
    "gn:dem":1106,
    "gn:feature_class":"P",
    "gn:feature_code":"PPL",
    "gn:name":"Kudouke",
    "gn:population":0,
    "gn:timezone":"Asia/Urumqi",
    "iso:country":"CN",
    "name:uig_x_preferred":[
        "Kuduk"
    ],
    "name:zho_x_preferred":[
        "\u5e93\u90fd\u514b"
    ],
    "wof:name":"Kudouke",
    "wof:placetype":"locality"
},
  "geometry": {"coordinates":[86.19609,38.46767],"type":"Point"}
}