{
  "type": "Feature",
  "properties": {
    "gn:admin1_code":"30.0",
    "gn:asciiname":"Liaowu",
    "gn:country_code":"CN",
    "gn:dem":266,
    "gn:feature_class":"P",
    "gn:feature_code":"PPL",
    "gn:name":"Liaowu",
    "gn:population":0,
    "gn:timezone":"Asia/Shanghai",
    "iso:country":"CN",
    "name:zho_x_preferred":[
        "Liaowu"
    ],
    "name:zho_x_variant":[
        "\u5ed6\u5c4b"
    ],
    "wof:name":"Liaowu",
    "wof:placetype":"locality"
},
  "geometry": {"coordinates":[114.06404999999999,24.66112],"type":"Point"}
}