{
  "type": "Feature",
  "properties": {
    "gn:admin1_code":"28",
    "gn:asciiname":"Liqizhuang",
    "gn:country_code":"CN",
    "gn:dem":6,
    "gn:feature_class":"P",
    "gn:feature_code":"PPLA4",
    "gn:name":"Liqizhuang",
    "gn:population":0,
    "gn:timezone":"Asia/Shanghai",
    "iso:country":"CN",
    "name:und_x_variant":[
        "Li-ch\u2019i-chuang",
        "Liqizhuang",
        "Liqizhuang Jiedao"
    ],
    "name:zho_x_preferred":[
        "\u674e\u4e03\u5e84"
    ],
    "name:zho_x_variant":[
        "\u674e\u4e03\u5e84\u8857\u9053"
    ],
    "wof:name":"Liqizhuang",
    "wof:placetype":"locality"
},
  "geometry": {"coordinates":[117.16198,39.06982],"type":"Point"}
}