{
  "type": "Feature",
  "properties": {
    "gn:admin1_code":"9.0",
    "gn:asciiname":"Dingzhuang",
    "gn:country_code":"CN",
    "gn:dem":136,
    "gn:feature_class":"P",
    "gn:feature_code":"PPL",
    "gn:name":"Dingzhuang",
    "gn:population":0,
    "gn:timezone":"Asia/Shanghai",
    "iso:country":"CN",
    "name:und_x_variant":[
        "\u4e01\u5e84",
        "Dingzhuang"
    ],
    "wof:name":"Dingzhuang",
    "wof:placetype":"locality"
},
  "geometry": {"coordinates":[112.92898999999998,33.68208],"type":"Point"}
}