{
  "type": "Feature",
  "properties": {
    "gn:admin1_code":"11.0",
    "gn:asciiname":"Ganjingyan",
    "gn:country_code":"CN",
    "gn:dem":171,
    "gn:feature_class":"P",
    "gn:feature_code":"PPL",
    "gn:name":"Ganjingyan",
    "gn:population":0,
    "gn:timezone":"Asia/Shanghai",
    "iso:country":"CN",
    "name:zho_x_preferred":[
        "\u5e72\u4e95\u5ca9"
    ],
    "wof:name":"Ganjingyan",
    "wof:placetype":"locality"
},
  "geometry": {"coordinates":[111.51049999999999,26.45048],"type":"Point"}
}