{
  "type": "Feature",
  "properties": {
    "gn:admin1_code":"25",
    "gn:asciiname":"Litangjia",
    "gn:country_code":"CN",
    "gn:dem":17,
    "gn:feature_class":"P",
    "gn:feature_code":"PPL",
    "gn:name":"Litangjia",
    "gn:population":0,
    "gn:timezone":"Asia/Shanghai",
    "iso:country":"CN",
    "name:zho_x_preferred":[
        "\u674e\u5802\u5bb6"
    ],
    "wof:name":"Litangjia",
    "wof:placetype":"locality"
},
  "geometry": {"coordinates":[116.898,37.5303],"type":"Point"}
}