{
  "type": "Feature",
  "properties": {
    "gn:admin1_code":"29.0",
    "gn:asciiname":"Qinghebu",
    "gn:country_code":"CN",
    "gn:dem":1816,
    "gn:feature_class":"P",
    "gn:feature_code":"PPL",
    "gn:name":"Qinghebu",
    "gn:population":0,
    "gn:timezone":"Asia/Shanghai",
    "iso:country":"CN",
    "name:zho_x_preferred":[
        "\u9752\u79be\u5821"
    ],
    "wof:name":"Qinghebu",
    "wof:placetype":"locality"
},
  "geometry": {"coordinates":[103.715,24.6562],"type":"Point"}
}