{
  "type": "Feature",
  "properties": {
    "gn:admin1_code":"14.0",
    "gn:asciiname":"Sha'a",
    "gn:country_code":"CN",
    "gn:dem":3514,
    "gn:feature_class":"P",
    "gn:feature_code":"PPL",
    "gn:name":"Sha\u2019a",
    "gn:population":0,
    "gn:timezone":"Asia/Urumqi",
    "iso:country":"CN",
    "name:und_x_variant":[
        "Sha\u2019a"
    ],
    "name:zho_x_preferred":[
        "\u6c99\u963f"
    ],
    "wof:name":"Sha'a",
    "wof:placetype":"locality"
},
  "geometry": {"coordinates":[97.23824,31.48478],"type":"Point"}
}