{
  "type": "Feature",
  "properties": {
    "gn:admin1_code":"29.0",
    "gn:asciiname":"Xiasixi",
    "gn:country_code":"CN",
    "gn:dem":1889,
    "gn:feature_class":"P",
    "gn:feature_code":"PPL",
    "gn:name":"Xiasixi",
    "gn:population":0,
    "gn:timezone":"Asia/Shanghai",
    "iso:country":"CN",
    "name:zho_x_preferred":[
        "\u4e0b\u6cd7\u6eaa"
    ],
    "wof:name":"Xiasixi",
    "wof:placetype":"locality"
},
  "geometry": {"coordinates":[101.337,25.7003],"type":"Point"}
}