{
  "type": "Feature",
  "properties": {
    "gn:admin1_code":"18",
    "gn:asciiname":"Youcunpo",
    "gn:country_code":"CN",
    "gn:dem":1046,
    "gn:feature_class":"P",
    "gn:feature_code":"PPL",
    "gn:name":"Youcunpo",
    "gn:population":0,
    "gn:timezone":"Asia/Shanghai",
    "iso:country":"CN",
    "name:zho_x_preferred":[
        "\u6e38\u6751\u5761"
    ],
    "wof:name":"Youcunpo",
    "wof:placetype":"locality"
},
  "geometry": {"coordinates":[106.968,27.89],"type":"Point"}
}