{
  "type": "Feature",
  "properties": {
    "gn:admin1_code":"12.0",
    "gn:asciiname":"Caijiatian",
    "gn:country_code":"CN",
    "gn:dem":53,
    "gn:feature_class":"P",
    "gn:feature_code":"PPL",
    "gn:name":"Caijiatian",
    "gn:population":0,
    "gn:timezone":"Asia/Shanghai",
    "iso:country":"CN",
    "name:zho_x_preferred":[
        "\u8521\u5bb6\u7530"
    ],
    "wof:name":"Caijiatian",
    "wof:placetype":"locality"
},
  "geometry": {"coordinates":[114.49731,31.06784],"type":"Point"}
}