{
  "type": "Feature",
  "properties": {
    "gn:admin1_code":"18",
    "gn:asciiname":"Shelahe",
    "gn:country_code":"CN",
    "gn:dem":1129,
    "gn:feature_class":"P",
    "gn:feature_code":"PPL",
    "gn:name":"Shelahe",
    "gn:population":0,
    "gn:timezone":"Asia/Shanghai",
    "iso:country":"CN",
    "name:zho_x_preferred":[
        "\u5c04\u62c9\u6cb3"
    ],
    "wof:name":"Shelahe",
    "wof:placetype":"locality"
},
  "geometry": {"coordinates":[104.962,26.4164],"type":"Point"}
}