{
  "type": "Feature",
  "properties": {
    "gn:admin1_code":"19.0",
    "gn:asciiname":"Daobuxin'aile",
    "gn:country_code":"CN",
    "gn:dem":71,
    "gn:feature_class":"P",
    "gn:feature_code":"PPL",
    "gn:name":"Daobuxin\u2019aile",
    "gn:population":0,
    "gn:timezone":"Asia/Shanghai",
    "iso:country":"CN",
    "name:zho_x_preferred":[
        "Daobuxin\u2019aile"
    ],
    "name:zho_x_variant":[
        "\u9053\u5e03\u65b0\u827e\u52d2"
    ],
    "wof:name":"Daobuxin'aile",
    "wof:placetype":"locality"
},
  "geometry": {"coordinates":[122.36982999999999,42.17207],"type":"Point"}
}