{
  "type": "Feature",
  "properties": {
    "gn:admin1_code":"8.0",
    "gn:asciiname":"Shuanghetun",
    "gn:country_code":"CN",
    "gn:dem":210,
    "gn:feature_class":"P",
    "gn:feature_code":"PPL",
    "gn:name":"Shuanghetun",
    "gn:population":0,
    "gn:timezone":"Asia/Shanghai",
    "iso:country":"CN",
    "name:zho_x_preferred":[
        "\u53cc\u5408\u5c6f"
    ],
    "wof:name":"Shuanghetun",
    "wof:placetype":"locality"
},
  "geometry": {"coordinates":[127.44127,44.91666],"type":"Point"}
}