{
  "type": "Feature",
  "properties": {
    "gn:admin1_code":"3.0",
    "gn:asciiname":"Jiankeng",
    "gn:country_code":"CN",
    "gn:dem":279,
    "gn:feature_class":"P",
    "gn:feature_code":"PPL",
    "gn:name":"Jiankeng",
    "gn:population":0,
    "gn:timezone":"Asia/Shanghai",
    "iso:country":"CN",
    "name:und_x_variant":[
        "\u6361\u5751"
    ],
    "wof:name":"Jiankeng",
    "wof:placetype":"locality"
},
  "geometry": {"coordinates":[115.46399,26.7384],"type":"Point"}
}