{
  "type": "Feature",
  "properties": {
    "gn:admin1_code":"32.0",
    "gn:asciiname":"Honggang",
    "gn:country_code":"CN",
    "gn:dem":3797,
    "gn:feature_class":"P",
    "gn:feature_code":"PPL",
    "gn:name":"Honggang",
    "gn:population":0,
    "gn:timezone":"Asia/Shanghai",
    "iso:country":"CN",
    "name:zho_x_preferred":[
        "\u7ea2\u5188"
    ],
    "wof:name":"Honggang",
    "wof:placetype":"locality"
},
  "geometry": {"coordinates":[100.203,28.5678],"type":"Point"}
}