{
  "type": "Feature",
  "properties": {
    "gn:admin1_code":"25",
    "gn:asciiname":"Malinggangzhen",
    "gn:country_code":"CN",
    "gn:dem":55,
    "gn:feature_class":"P",
    "gn:feature_code":"PPL",
    "gn:name":"Malinggangzhen",
    "gn:population":0,
    "gn:timezone":"Asia/Shanghai",
    "iso:country":"CN",
    "wof:name":"Malinggangzhen",
    "wof:placetype":"locality"
},
  "geometry": {"coordinates":[115.31861000000001,35.16056],"type":"Point"}
}