{
  "type": "Feature",
  "properties": {
    "gn:admin1_code":"29.0",
    "gn:asciiname":"Miaoshan",
    "gn:country_code":"CN",
    "gn:dem":2491,
    "gn:feature_class":"P",
    "gn:feature_code":"PPL",
    "gn:name":"Miaoshan",
    "gn:population":0,
    "gn:timezone":"Asia/Shanghai",
    "iso:country":"CN",
    "name:zho_x_preferred":[
        "\u5e99\u5c71"
    ],
    "wof:name":"Miaoshan",
    "wof:placetype":"locality"
},
  "geometry": {"coordinates":[100.342,25.0698],"type":"Point"}
}