{
  "type": "Feature",
  "properties": {
    "gn:admin1_code":"24.0",
    "gn:asciiname":"Wangxiang",
    "gn:country_code":"CN",
    "gn:dem":807,
    "gn:feature_class":"P",
    "gn:feature_code":"PPL",
    "gn:name":"Wangxiang",
    "gn:population":0,
    "gn:timezone":"Asia/Shanghai",
    "iso:country":"CN",
    "name:zho_x_preferred":[
        "\u738b\u9999"
    ],
    "wof:name":"Wangxiang",
    "wof:placetype":"locality"
},
  "geometry": {"coordinates":[112.71474000000001,37.57879000000001],"type":"Point"}
}