{
  "type": "Feature",
  "properties": {
    "gn:admin1_code":"4.0",
    "gn:asciiname":"Bishanli",
    "gn:country_code":"CN",
    "gn:dem":30,
    "gn:feature_class":"P",
    "gn:feature_code":"PPL",
    "gn:name":"Bishanli",
    "gn:population":0,
    "gn:timezone":"Asia/Shanghai",
    "iso:country":"CN",
    "name:zho_x_preferred":[
        "\u78a7\u5c71\u91cc"
    ],
    "wof:name":"Bishanli",
    "wof:placetype":"locality"
},
  "geometry": {"coordinates":[119.08252,31.55571],"type":"Point"}
}