{
  "type": "Feature",
  "properties": {
    "gn:admin1_code":"10",
    "gn:asciiname":"Sidao Fangzi",
    "gn:country_code":"CN",
    "gn:dem":269,
    "gn:feature_class":"P",
    "gn:feature_code":"PPL",
    "gn:name":"Sidao Fangzi",
    "gn:population":0,
    "gn:timezone":"Asia/Shanghai",
    "iso:country":"CN",
    "name:zho_x_preferred":[
        "\u56db\u9053\u623f\u5b50"
    ],
    "wof:name":"Sidao Fangzi",
    "wof:placetype":"locality"
},
  "geometry": {"coordinates":[118.08253999999999,40.28669],"type":"Point"}
}