{
  "type": "Feature",
  "properties": {
    "gn:admin1_code":"32.0",
    "gn:asciiname":"Shaicaoping",
    "gn:country_code":"CN",
    "gn:dem":694,
    "gn:feature_class":"P",
    "gn:feature_code":"PPL",
    "gn:name":"Shaicaoping",
    "gn:population":0,
    "gn:timezone":"Asia/Shanghai",
    "iso:country":"CN",
    "name:zho_x_preferred":[
        "\u6652\u8349\u576a"
    ],
    "wof:name":"Shaicaoping",
    "wof:placetype":"locality"
},
  "geometry": {"coordinates":[104.27349,28.47508],"type":"Point"}
}