{
  "type": "Feature",
  "properties": {
    "gn:admin1_code":"6.0",
    "gn:asciiname":"Wali",
    "gn:country_code":"CN",
    "gn:dem":2423,
    "gn:feature_class":"P",
    "gn:feature_code":"PPL",
    "gn:name":"Wali",
    "gn:population":0,
    "gn:timezone":"Asia/Shanghai",
    "iso:country":"CN",
    "name:zho_x_preferred":[
        "\u54c7\u91cc"
    ],
    "wof:name":"Wali",
    "wof:placetype":"locality"
},
  "geometry": {"coordinates":[101.49379,36.0251],"type":"Point"}
}