{
  "type": "Feature",
  "properties": {
    "gn:admin1_code":"10",
    "gn:asciiname":"Xinaling",
    "gn:country_code":"CN",
    "gn:dem":1532,
    "gn:feature_class":"P",
    "gn:feature_code":"PPL",
    "gn:name":"Xinaling",
    "gn:population":0,
    "gn:timezone":"Asia/Shanghai",
    "iso:country":"CN",
    "name:zho_x_preferred":[
        "\u897f\u7eb3\u5cad"
    ],
    "wof:name":"Xinaling",
    "wof:placetype":"locality"
},
  "geometry": {"coordinates":[115.25521000000001,41.18474000000001],"type":"Point"}
}