{
  "type": "Feature",
  "properties": {
    "gn:admin1_code":"29",
    "gn:asciiname":"Maoshezu",
    "gn:country_code":"CN",
    "gn:dem":1918,
    "gn:feature_class":"P",
    "gn:feature_code":"PPL",
    "gn:name":"Maoshezu",
    "gn:population":0,
    "gn:timezone":"Asia/Shanghai",
    "iso:country":"CN",
    "name:zho_x_preferred":[
        "\u8302\u820d\u7956"
    ],
    "wof:name":"Maoshezu",
    "wof:placetype":"locality"
},
  "geometry": {"coordinates":[103.42994,24.86133],"type":"Point"}
}