{
  "type": "Feature",
  "properties": {
    "gn:admin1_code":"10",
    "gn:asciiname":"Linggou",
    "gn:country_code":"CN",
    "gn:dem":586,
    "gn:feature_class":"P",
    "gn:feature_code":"PPL",
    "gn:name":"Linggou",
    "gn:population":0,
    "gn:timezone":"Asia/Shanghai",
    "iso:country":"CN",
    "name:zho_x_preferred":[
        "\u5cad\u6c9f"
    ],
    "wof:name":"Linggou",
    "wof:placetype":"locality"
},
  "geometry": {"coordinates":[117.69504000000001,40.77681],"type":"Point"}
}