{
  "type": "Feature",
  "properties": {
    "gn:admin1_code":"19.0",
    "gn:asciiname":"Shuangmiao",
    "gn:country_code":"CN",
    "gn:dem":368,
    "gn:feature_class":"P",
    "gn:feature_code":"PPL",
    "gn:name":"Shuangmiao",
    "gn:population":0,
    "gn:timezone":"Asia/Shanghai",
    "iso:country":"CN",
    "name:ceb_x_preferred":[
        "Shuangmiao"
    ],
    "name:swe_x_preferred":[
        "Shuangmiao"
    ],
    "name:zho_x_preferred":[
        "\u53cc\u5e99"
    ],
    "wof:name":"Shuangmiao",
    "wof:placetype":"locality"
},
  "geometry": {"coordinates":[119.66525,41.1032],"type":"Point"}
}