{
  "type": "Feature",
  "properties": {
    "gn:admin1_code":"26.0",
    "gn:asciiname":"Xiaochangcun",
    "gn:country_code":"CN",
    "gn:dem":847,
    "gn:feature_class":"P",
    "gn:feature_code":"PPLF",
    "gn:name":"Xiaochangcun",
    "gn:population":0,
    "gn:timezone":"Asia/Shanghai",
    "iso:country":"CN",
    "name:zho_x_preferred":[
        "\u6821\u573a\u6751"
    ],
    "wof:name":"Xiaochangcun",
    "wof:placetype":"locality"
},
  "geometry": {"coordinates":[108.49274,33.20386],"type":"Point"}
}