{
  "type": "Feature",
  "properties": {
    "gn:admin1_code":"8.0",
    "gn:asciiname":"Laogaojiatun",
    "gn:country_code":"CN",
    "gn:dem":174,
    "gn:feature_class":"P",
    "gn:feature_code":"PPL",
    "gn:name":"Laogaojiatun",
    "gn:population":0,
    "gn:timezone":"Asia/Shanghai",
    "iso:country":"CN",
    "name:zho_x_preferred":[
        "\u8001\u9ad8\u5bb6\u5c6f"
    ],
    "wof:name":"Laogaojiatun",
    "wof:placetype":"locality"
},
  "geometry": {"coordinates":[125.18035,47.49634],"type":"Point"}
}