{
  "type": "Feature",
  "properties": {
    "gn:admin1_code":"8.0",
    "gn:asciiname":"Getangli",
    "gn:country_code":"CN",
    "gn:dem":198,
    "gn:feature_class":"P",
    "gn:feature_code":"PPL",
    "gn:name":"Getangli",
    "gn:population":0,
    "gn:timezone":"Asia/Shanghai",
    "iso:country":"CN",
    "name:zho_x_preferred":[
        "\u86e4\u5858\u674e"
    ],
    "wof:name":"Getangli",
    "wof:placetype":"locality"
},
  "geometry": {"coordinates":[127.2747,44.91491],"type":"Point"}
}