{
  "type": "Feature",
  "properties": {
    "gn:admin1_code":"25",
    "gn:asciiname":"Ouchi",
    "gn:country_code":"CN",
    "gn:dem":411,
    "gn:feature_class":"P",
    "gn:feature_code":"PPL",
    "gn:name":"Ouchi",
    "gn:population":0,
    "gn:timezone":"Asia/Shanghai",
    "iso:country":"CN",
    "name:deu_x_preferred":[
        "Ouchi"
    ],
    "name:rus_x_preferred":[
        "\u041e\u0443\u0442\u0438"
    ],
    "name:zho_x_preferred":[
        "\u85d5\u6c60"
    ],
    "wof:name":"Ouchi",
    "wof:placetype":"locality"
},
  "geometry": {"coordinates":[117.259,36.4711],"type":"Point"}
}