{
  "type": "Feature",
  "properties": {
    "gn:admin1_code":"30.0",
    "gn:asciiname":"Taoling",
    "gn:country_code":"CN",
    "gn:dem":661,
    "gn:feature_class":"P",
    "gn:feature_code":"PPL",
    "gn:name":"Taoling",
    "gn:population":0,
    "gn:timezone":"Asia/Shanghai",
    "iso:country":"CN",
    "name:zho_x_preferred":[
        "Taoling"
    ],
    "name:zho_x_variant":[
        "\u6843\u5cad"
    ],
    "wof:name":"Taoling",
    "wof:placetype":"locality"
},
  "geometry": {"coordinates":[113.29701,24.94856],"type":"Point"}
}