{
  "type": "Feature",
  "properties": {
    "gn:admin1_code":"29.0",
    "gn:asciiname":"Zhida",
    "gn:country_code":"CN",
    "gn:dem":1509,
    "gn:feature_class":"P",
    "gn:feature_code":"PPL",
    "gn:name":"Zhida",
    "gn:population":0,
    "gn:timezone":"Asia/Shanghai",
    "iso:country":"CN",
    "name:zho_x_preferred":[
        "\u77e5\u8fbe"
    ],
    "wof:name":"Zhida",
    "wof:placetype":"locality"
},
  "geometry": {"coordinates":[98.843,27.363],"type":"Point"}
}