{
  "type": "Feature",
  "properties": {
    "gn:admin1_code":"5.0",
    "gn:asciiname":"Shichengli",
    "gn:country_code":"CN",
    "gn:dem":223,
    "gn:feature_class":"P",
    "gn:feature_code":"PPL",
    "gn:name":"Shichengli",
    "gn:population":0,
    "gn:timezone":"Asia/Shanghai",
    "iso:country":"CN",
    "name:zho_x_preferred":[
        "\u77f3\u6210\u7acb"
    ],
    "wof:name":"Shichengli",
    "wof:placetype":"locality"
},
  "geometry": {"coordinates":[124.99315,44.65867],"type":"Point"}
}