{
  "type": "Feature",
  "properties": {
    "gn:admin1_code":"12.0",
    "gn:asciiname":"Ruanjiayuan",
    "gn:country_code":"CN",
    "gn:dem":533,
    "gn:feature_class":"P",
    "gn:feature_code":"PPL",
    "gn:name":"Ruanjiayuan",
    "gn:population":0,
    "gn:timezone":"Asia/Shanghai",
    "iso:country":"CN",
    "name:zho_x_preferred":[
        "\u962e\u5bb6\u9662"
    ],
    "wof:name":"Ruanjiayuan",
    "wof:placetype":"locality"
},
  "geometry": {"coordinates":[110.33711,32.12607],"type":"Point"}
}