{
  "type": "Feature",
  "properties": {
    "gn:admin1_code":"10",
    "gn:asciiname":"Xinjiaying",
    "gn:country_code":"CN",
    "gn:dem":481,
    "gn:feature_class":"P",
    "gn:feature_code":"PPL",
    "gn:name":"Xinjiaying",
    "gn:population":0,
    "gn:timezone":"Asia/Shanghai",
    "iso:country":"CN",
    "name:zho_x_preferred":[
        "\u8f9b\u5bb6\u8425"
    ],
    "wof:name":"Xinjiaying",
    "wof:placetype":"locality"
},
  "geometry": {"coordinates":[117.57186000000002,40.96507],"type":"Point"}
}