{
  "type": "Feature",
  "properties": {
    "gn:admin1_code":"15.0",
    "gn:asciiname":"Zhuangkeli",
    "gn:country_code":"CN",
    "gn:dem":911,
    "gn:feature_class":"P",
    "gn:feature_code":"PPL",
    "gn:name":"Zhuangkeli",
    "gn:population":0,
    "gn:timezone":"Asia/Shanghai",
    "iso:country":"CN",
    "name:und_x_variant":[
        "\u5e84\u79d1\u91cc"
    ],
    "wof:name":"Zhuangkeli",
    "wof:placetype":"locality"
},
  "geometry": {"coordinates":[105.87586,33.01121],"type":"Point"}
}