{
  "type": "Feature",
  "properties": {
    "gn:admin1_code":"19.0",
    "gn:asciiname":"Cuocaogou",
    "gn:country_code":"CN",
    "gn:dem":329,
    "gn:feature_class":"P",
    "gn:feature_code":"PPL",
    "gn:name":"Cuocaogou",
    "gn:population":0,
    "gn:timezone":"Asia/Shanghai",
    "iso:country":"CN",
    "name:und_x_variant":[
        "\u9519\u8349\u6c9f"
    ],
    "wof:name":"Cuocaogou",
    "wof:placetype":"locality"
},
  "geometry": {"coordinates":[124.84537,41.75444],"type":"Point"}
}