{
  "type": "Feature",
  "properties": {
    "gn:admin1_code":"33.0",
    "gn:asciiname":"Dingmutuo",
    "gn:country_code":"CN",
    "gn:dem":1203,
    "gn:feature_class":"P",
    "gn:feature_code":"PPL",
    "gn:name":"Dingmutuo",
    "gn:population":0,
    "gn:timezone":"Asia/Shanghai",
    "iso:country":"CN",
    "name:zho_x_preferred":[
        "\u4e01\u6728\u5768"
    ],
    "wof:name":"Dingmutuo",
    "wof:placetype":"locality"
},
  "geometry": {"coordinates":[108.50433999999998,28.72517],"type":"Point"}
}