{
  "type": "Feature",
  "properties": {
    "gn:admin1_code":"10.0",
    "gn:asciiname":"Gushiyu",
    "gn:country_code":"CN",
    "gn:dem":172,
    "gn:feature_class":"P",
    "gn:feature_code":"PPL",
    "gn:name":"Gushiyu",
    "gn:population":0,
    "gn:timezone":"Asia/Shanghai",
    "iso:country":"CN",
    "name:zho_x_preferred":[
        "\u5b64\u77f3\u5cea"
    ],
    "wof:name":"Gushiyu",
    "wof:placetype":"locality"
},
  "geometry": {"coordinates":[119.48566,40.06675],"type":"Point"}
}