{
  "type": "Feature",
  "properties": {
    "gn:admin1_code":"11.0",
    "gn:asciiname":"Dakeng",
    "gn:country_code":"CN",
    "gn:dem":526,
    "gn:feature_class":"P",
    "gn:feature_code":"PPL",
    "gn:name":"Dakeng",
    "gn:population":0,
    "gn:timezone":"Asia/Shanghai",
    "iso:country":"CN",
    "name:zho_x_preferred":[
        "\u5927\u5751"
    ],
    "wof:name":"Dakeng",
    "wof:placetype":"locality"
},
  "geometry": {"coordinates":[113.90007,28.58094],"type":"Point"}
}