{
  "type": "Feature",
  "properties": {
    "gn:admin1_code":"29.0",
    "gn:asciiname":"Mawotang",
    "gn:country_code":"CN",
    "gn:dem":2146,
    "gn:feature_class":"P",
    "gn:feature_code":"PPL",
    "gn:name":"Mawotang",
    "gn:population":0,
    "gn:timezone":"Asia/Shanghai",
    "iso:country":"CN",
    "name:zho_x_preferred":[
        "\u9ebb\u7a9d\u5858"
    ],
    "wof:name":"Mawotang",
    "wof:placetype":"locality"
},
  "geometry": {"coordinates":[103.876,27.5374],"type":"Point"}
}