{
  "type": "Feature",
  "properties": {
    "gn:admin1_code":"26.0",
    "gn:asciiname":"Houfenyan",
    "gn:country_code":"CN",
    "gn:dem":1119,
    "gn:feature_class":"P",
    "gn:feature_code":"PPL",
    "gn:name":"Houfenyan",
    "gn:population":0,
    "gn:timezone":"Asia/Shanghai",
    "iso:country":"CN",
    "name:zho_x_preferred":[
        "\u540e\u575f\u5830"
    ],
    "wof:name":"Houfenyan",
    "wof:placetype":"locality"
},
  "geometry": {"coordinates":[111.11512,39.1394],"type":"Point"}
}