{
  "type": "Feature",
  "properties": {
    "gn:admin1_code":"16",
    "gn:asciiname":"Doutian",
    "gn:country_code":"CN",
    "gn:dem":255,
    "gn:feature_class":"P",
    "gn:feature_code":"PPL",
    "gn:name":"Doutian",
    "gn:population":0,
    "gn:timezone":"Asia/Shanghai",
    "iso:country":"CN",
    "name:zho_x_preferred":[
        "\u9661\u7530"
    ],
    "wof:name":"Doutian",
    "wof:placetype":"locality"
},
  "geometry": {"coordinates":[110.45099999999999,25.4506],"type":"Point"}
}