{
  "type": "Feature",
  "properties": {
    "gn:admin1_code":"26.0",
    "gn:asciiname":"Guanyinmiaota",
    "gn:country_code":"CN",
    "gn:dem":1224,
    "gn:feature_class":"P",
    "gn:feature_code":"PPL",
    "gn:name":"Guanyinmiaota",
    "gn:population":0,
    "gn:timezone":"Asia/Shanghai",
    "iso:country":"CN",
    "name:zho_x_preferred":[
        "\u89c2\u97f3\u5e99\u5854"
    ],
    "wof:name":"Guanyinmiaota",
    "wof:placetype":"locality"
},
  "geometry": {"coordinates":[109.27215,36.87818],"type":"Point"}
}