{
  "type": "Feature",
  "properties": {
    "gn:admin1_code":"16.0",
    "gn:asciiname":"Mijie",
    "gn:country_code":"CN",
    "gn:dem":139,
    "gn:feature_class":"P",
    "gn:feature_code":"PPL",
    "gn:name":"Mijie",
    "gn:population":0,
    "gn:timezone":"Asia/Shanghai",
    "iso:country":"CN",
    "name:zho_x_preferred":[
        "\u7c73\u89e3"
    ],
    "wof:name":"Mijie",
    "wof:placetype":"locality"
},
  "geometry": {"coordinates":[107.806,22.3176],"type":"Point"}
}