{
  "type": "Feature",
  "properties": {
    "gn:admin1_code":"32.0",
    "gn:asciiname":"Yuanziyan",
    "gn:country_code":"CN",
    "gn:dem":390,
    "gn:feature_class":"P",
    "gn:feature_code":"PPL",
    "gn:name":"Yuanziyan",
    "gn:population":0,
    "gn:timezone":"Asia/Shanghai",
    "iso:country":"CN",
    "name:zho_x_preferred":[
        "\u9662\u5b50\u5ca9"
    ],
    "wof:name":"Yuanziyan",
    "wof:placetype":"locality"
},
  "geometry": {"coordinates":[104.73572,29.09925],"type":"Point"}
}