{
  "type": "Feature",
  "properties": {
    "gn:admin1_code":"25.0",
    "gn:asciiname":"Xidoushan",
    "gn:country_code":"CN",
    "gn:dem":58,
    "gn:feature_class":"P",
    "gn:feature_code":"PPL",
    "gn:name":"Xidoushan",
    "gn:population":0,
    "gn:timezone":"Asia/Shanghai",
    "iso:country":"CN",
    "name:zho_x_preferred":[
        "\u897f\u9661\u5c71"
    ],
    "wof:name":"Xidoushan",
    "wof:placetype":"locality"
},
  "geometry": {"coordinates":[120.8164,36.92582],"type":"Point"}
}