{
  "type": "Feature",
  "properties": {
    "gn:admin1_code":"3.0",
    "gn:asciiname":"Laowu Xijia",
    "gn:country_code":"CN",
    "gn:dem":70,
    "gn:feature_class":"P",
    "gn:feature_code":"PPL",
    "gn:name":"Laowu Xijia",
    "gn:population":0,
    "gn:timezone":"Asia/Shanghai",
    "iso:country":"CN",
    "name:zho_x_preferred":[
        "\u8001\u5c4b\u5e2d\u5bb6"
    ],
    "wof:name":"Laowu Xijia",
    "wof:placetype":"locality"
},
  "geometry": {"coordinates":[117.36906999999999,28.2821],"type":"Point"}
}