{
  "type": "Feature",
  "properties": {
    "gn:admin1_code":"4.0",
    "gn:asciiname":"Song'erpu",
    "gn:country_code":"CN",
    "gn:dem":30,
    "gn:feature_class":"P",
    "gn:feature_code":"PPL",
    "gn:name":"Song\u2019erpu",
    "gn:population":0,
    "gn:timezone":"Asia/Shanghai",
    "iso:country":"CN",
    "name:und_x_variant":[
        "Song\u2019erpu"
    ],
    "name:zho_x_preferred":[
        "\u677e\u513f\u94fa"
    ],
    "wof:name":"Song'erpu",
    "wof:placetype":"locality"
},
  "geometry": {"coordinates":[119.08128000000001,31.28581],"type":"Point"}
}