{
  "type": "Feature",
  "properties": {
    "gn:admin1_code":"10.0",
    "gn:asciiname":"Heishankou",
    "gn:country_code":"CN",
    "gn:dem":617,
    "gn:feature_class":"P",
    "gn:feature_code":"PPL",
    "gn:name":"Heishankou",
    "gn:population":0,
    "gn:timezone":"Asia/Shanghai",
    "iso:country":"CN",
    "name:zho_x_preferred":[
        "\u9ed1\u5c71\u53e3"
    ],
    "wof:name":"Heishankou",
    "wof:placetype":"locality"
},
  "geometry": {"coordinates":[115.70099,40.38267000000001],"type":"Point"}
}