{
  "type": "Feature",
  "properties": {
    "gn:admin1_code":"12.0",
    "gn:asciiname":"Fengshan",
    "gn:country_code":"CN",
    "gn:dem":91,
    "gn:feature_class":"P",
    "gn:feature_code":"PPLA4",
    "gn:name":"Fengshan",
    "gn:population":0,
    "gn:timezone":"Asia/Shanghai",
    "iso:country":"CN",
    "name:ceb_x_preferred":[
        "Fengshan"
    ],
    "name:deu_x_preferred":[
        "Fengshan"
    ],
    "name:fra_x_preferred":[
        "Fengshan"
    ],
    "name:nor_x_preferred":[
        "Fengshan"
    ],
    "name:swe_x_preferred":[
        "Fengshan"
    ],
    "name:und_x_variant":[
        "\u51e4\u5c71",
        "Fengshan Zhen",
        "\u51e4\u5c71\u9547"
    ],
    "name:vie_x_preferred":[
        "Ph\u01b0\u1ee3ng S\u01a1n"
    ],
    "wof:name":"Fengshan",
    "wof:placetype":"locality"
},
  "geometry": {"coordinates":[115.39214,30.78848],"type":"Point"}
}