{
  "type": "Feature",
  "properties": {
    "gn:admin1_code":"30.0",
    "gn:asciiname":"Sanshengcun",
    "gn:country_code":"CN",
    "gn:dem":10,
    "gn:feature_class":"P",
    "gn:feature_code":"PPL",
    "gn:name":"Sanshengcun",
    "gn:population":0,
    "gn:timezone":"Asia/Shanghai",
    "iso:country":"CN",
    "name:zho_x_preferred":[
        "\u4e09\u80dc\u6751"
    ],
    "wof:name":"Sanshengcun",
    "wof:placetype":"locality"
},
  "geometry": {"coordinates":[116.60683,23.6097],"type":"Point"}
}