{
  "type": "Feature",
  "properties": {
    "gn:admin1_code":"18",
    "gn:asciiname":"Tongzishu",
    "gn:country_code":"CN",
    "gn:dem":1355,
    "gn:feature_class":"P",
    "gn:feature_code":"PPL",
    "gn:name":"Tongzishu",
    "gn:population":0,
    "gn:timezone":"Asia/Shanghai",
    "iso:country":"CN",
    "name:zho_x_preferred":[
        "\u6850\u6893\u6811"
    ],
    "wof:name":"Tongzishu",
    "wof:placetype":"locality"
},
  "geometry": {"coordinates":[105.889,26.4065],"type":"Point"}
}