{
  "type": "Feature",
  "properties": {
    "gn:admin1_code":"1.0",
    "gn:asciiname":"Guotaicun",
    "gn:country_code":"CN",
    "gn:dem":25,
    "gn:feature_class":"P",
    "gn:feature_code":"PPL",
    "gn:name":"Guotaicun",
    "gn:population":0,
    "gn:timezone":"Asia/Shanghai",
    "iso:country":"CN",
    "name:zho_x_preferred":[
        "\u90ed\u53f0\u6751"
    ],
    "wof:name":"Guotaicun",
    "wof:placetype":"locality"
},
  "geometry": {"coordinates":[115.7835,32.49158],"type":"Point"}
}