{
  "type": "Feature",
  "properties": {
    "gn:admin1_code":"31.0",
    "gn:asciiname":"Pingpo",
    "gn:country_code":"CN",
    "gn:dem":146,
    "gn:feature_class":"P",
    "gn:feature_code":"PPL",
    "gn:name":"Pingpo",
    "gn:population":0,
    "gn:timezone":"Asia/Shanghai",
    "iso:country":"CN",
    "name:zho_x_preferred":[
        "\u5e73\u5761"
    ],
    "wof:name":"Pingpo",
    "wof:placetype":"locality"
},
  "geometry": {"coordinates":[110.04756,19.38489],"type":"Point"}
}