{
  "type": "Feature",
  "properties": {
    "gn:admin1_code":"14.0",
    "gn:asciiname":"Chaba",
    "gn:country_code":"CN",
    "gn:dem":4189,
    "gn:feature_class":"P",
    "gn:feature_code":"PPL",
    "gn:name":"Chaba",
    "gn:population":0,
    "gn:timezone":"Asia/Urumqi",
    "iso:country":"CN",
    "name:ceb_x_preferred":[
        "Chaba"
    ],
    "name:deu_x_preferred":[
        "Chaba"
    ],
    "name:fra_x_preferred":[
        "Chaba"
    ],
    "name:jpn_x_preferred":[
        "\u30c1\u30e3\u30d0"
    ],
    "name:zho_x_preferred":[
        "\u67e5\u5df4"
    ],
    "wof:name":"Chaba",
    "wof:placetype":"locality"
},
  "geometry": {"coordinates":[91.81196,28.90877],"type":"Point"}
}