{
  "type": "Feature",
  "properties": {
    "gn:admin1_code":"32.0",
    "gn:asciiname":"Meijia Haokou",
    "gn:country_code":"CN",
    "gn:dem":519,
    "gn:feature_class":"P",
    "gn:feature_code":"PPL",
    "gn:name":"Meijia Haokou",
    "gn:population":0,
    "gn:timezone":"Asia/Shanghai",
    "iso:country":"CN",
    "name:zho_x_preferred":[
        "\u6885\u5bb6\u6d69\u53e3"
    ],
    "wof:name":"Meijia Haokou",
    "wof:placetype":"locality"
},
  "geometry": {"coordinates":[106.23,32.003],"type":"Point"}
}