{
  "type": "Feature",
  "properties": {
    "gn:admin1_code":"15.0",
    "gn:asciiname":"Songjia Duipo",
    "gn:country_code":"CN",
    "gn:dem":2296,
    "gn:feature_class":"P",
    "gn:feature_code":"PPL",
    "gn:name":"Songjia Duipo",
    "gn:population":0,
    "gn:timezone":"Asia/Shanghai",
    "iso:country":"CN",
    "name:zho_x_preferred":[
        "\u5b8b\u5bb6\u5bf9\u5761"
    ],
    "wof:name":"Songjia Duipo",
    "wof:placetype":"locality"
},
  "geometry": {"coordinates":[104.105,35.3122],"type":"Point"}
}