{
  "type": "Feature",
  "properties": {
    "gn:admin1_code":"29.0",
    "gn:asciiname":"Bengde",
    "gn:country_code":"CN",
    "gn:dem":2385,
    "gn:feature_class":"P",
    "gn:feature_code":"PPL",
    "gn:name":"Bengde",
    "gn:population":0,
    "gn:timezone":"Asia/Shanghai",
    "iso:country":"CN",
    "name:zho_x_preferred":[
        "\u868c\u5fb7"
    ],
    "wof:name":"Bengde",
    "wof:placetype":"locality"
},
  "geometry": {"coordinates":[103.015,26.0454],"type":"Point"}
}