{
  "type": "Feature",
  "properties": {
    "gn:admin1_code":"32.0",
    "gn:asciiname":"Luobuyuan",
    "gn:country_code":"CN",
    "gn:dem":280,
    "gn:feature_class":"P",
    "gn:feature_code":"PPL",
    "gn:name":"Luobuyuan",
    "gn:population":0,
    "gn:timezone":"Asia/Shanghai",
    "iso:country":"CN",
    "name:zho_x_preferred":[
        "\u841d\u535c\u56ed"
    ],
    "wof:name":"Luobuyuan",
    "wof:placetype":"locality"
},
  "geometry": {"coordinates":[105.48678,30.33921],"type":"Point"}
}