{
  "type": "Feature",
  "properties": {
    "gn:admin1_code":"12.0",
    "gn:asciiname":"Hujia Nanzui",
    "gn:country_code":"CN",
    "gn:dem":19,
    "gn:feature_class":"P",
    "gn:feature_code":"PPL",
    "gn:name":"Hujia Nanzui",
    "gn:population":0,
    "gn:timezone":"Asia/Shanghai",
    "iso:country":"CN",
    "name:und_x_variant":[
        "\u80e1\u5bb6\u5357\u5480"
    ],
    "wof:name":"Hujia Nanzui",
    "wof:placetype":"locality"
},
  "geometry": {"coordinates":[114.95659000000001,30.56977],"type":"Point"}
}