{
  "type": "Feature",
  "properties": {
    "gn:admin1_code":"30",
    "gn:asciiname":"Shuinanxu",
    "gn:country_code":"CN",
    "gn:dem":24,
    "gn:feature_class":"P",
    "gn:feature_code":"PPL",
    "gn:name":"Shuinanxu",
    "gn:population":0,
    "gn:timezone":"Asia/Shanghai",
    "iso:country":"CN",
    "name:zho_x_preferred":[
        "\u6c34\u5357\u5729"
    ],
    "wof:name":"Shuinanxu",
    "wof:placetype":"locality"
},
  "geometry": {"coordinates":[112.73161,22.23743],"type":"Point"}
}