{
  "type": "Feature",
  "properties": {
    "gn:admin1_code":"29",
    "gn:asciiname":"Niunitang",
    "gn:country_code":"CN",
    "gn:dem":2254,
    "gn:feature_class":"P",
    "gn:feature_code":"PPL",
    "gn:name":"Niunitang",
    "gn:population":0,
    "gn:timezone":"Asia/Shanghai",
    "iso:country":"CN",
    "name:zho_x_preferred":[
        "\u725b\u6ce5\u5858"
    ],
    "wof:name":"Niunitang",
    "wof:placetype":"locality"
},
  "geometry": {"coordinates":[103.09699999999999,24.6291],"type":"Point"}
}