{
  "type": "Feature",
  "properties": {
    "gn:admin1_code":"15.0",
    "gn:asciiname":"Wu'ercun",
    "gn:country_code":"CN",
    "gn:dem":1356,
    "gn:feature_class":"P",
    "gn:feature_code":"PPL",
    "gn:name":"Wu\u2019ercun",
    "gn:population":0,
    "gn:timezone":"Asia/Shanghai",
    "iso:country":"CN",
    "name:und_x_variant":[
        "Wu\u2019ercun"
    ],
    "name:zho_x_preferred":[
        "\u4e94\u4e8c\u6751"
    ],
    "wof:name":"Wu'ercun",
    "wof:placetype":"locality"
},
  "geometry": {"coordinates":[99.9054,39.3743],"type":"Point"}
}