{
  "type": "Feature",
  "properties": {
    "gn:admin1_code":"3.0",
    "gn:asciiname":"Ao'tangbei",
    "gn:country_code":"CN",
    "gn:dem":214,
    "gn:feature_class":"P",
    "gn:feature_code":"PPL",
    "gn:name":"Ao\u2019tangbei",
    "gn:population":0,
    "gn:timezone":"Asia/Shanghai",
    "iso:country":"CN",
    "name:und_x_variant":[
        "Ao\u2019tangbei",
        "\u5787\u5858\u80cc"
    ],
    "wof:name":"Ao'tangbei",
    "wof:placetype":"locality"
},
  "geometry": {"coordinates":[115.55277,26.68249],"type":"Point"}
}