{
  "type": "Feature",
  "properties": {
    "gn:admin1_code":"24.0",
    "gn:asciiname":"Yancheng",
    "gn:country_code":"CN",
    "gn:dem":1442,
    "gn:feature_class":"P",
    "gn:feature_code":"PPLA3",
    "gn:name":"Yancheng",
    "gn:population":0,
    "gn:timezone":"Asia/Shanghai",
    "iso:country":"CN",
    "name:afr_x_preferred":[
        "Yancheng"
    ],
    "name:ara_x_preferred":[
        "\u064a\u0627\u0646\u062a\u0634\u0646\u063a"
    ],
    "name:ast_x_preferred":[
        "Yancheng"
    ],
    "name:bul_x_preferred":[
        "\u0419\u0435\u043d\u0447\u044a\u043d"
    ],
    "name:cat_x_preferred":[
        "Yanxeng"
    ],
    "name:cdo_x_preferred":[
        "Si\u00e8ng-si\u00e0ng"
    ],
    "name:ceb_x_preferred":[
        "Yancheng"
    ],
    "name:ces_x_preferred":[
        "Jen-\u010dcheng"
    ],
    "name:dan_x_preferred":[
        "Yancheng"
    ],
    "name:deu_x_preferred":[
        "Yancheng"
    ],
    "name:epo_x_preferred":[
        "Jan\u0109engo"
    ],
    "name:eus_x_preferred":[
        "Yancheng"
    ],
    "name:fas_x_preferred":[
        "\u06cc\u0627\u0646\u0686\u0646\u06af"
    ],
    "name:fin_x_preferred":[
        "Yancheng"
    ],
    "name:fra_x_preferred":[
        "Yancheng"
    ],
    "name:ina_x_preferred":[
        "Yancheng"
    ],
    "name:ita_x_preferred":[
        "Yancheng"
    ],
    "name:jpn_x_preferred":[
        "\u5869\u57ce\u5e02"
    ],
    "name:kik_x_preferred":[
        "Yancheng"
    ],
    "name:kor_x_preferred":[
        "\uc60c\uccad\uc2dc"
    ],
    "name:mlg_x_preferred":[
        "Yancheng"
    ],
    "name:nld_x_preferred":[
        "Yancheng"
    ],
    "name:nno_x_preferred":[
        "Yancheng"
    ],
    "name:nor_x_preferred":[
        "Yancheng"
    ],
    "name:pol_x_preferred":[
        "Yancheng"
    ],
    "name:por_x_preferred":[
        "Yancheng"
    ],
    "name:rus_x_preferred":[
        "\u042f\u043d\u044c\u0447\u044d\u043d"
    ],
    "name:spa_x_preferred":[
        "Yancheng"
    ],
    "name:srp_x_preferred":[
        "\u0408\u0430\u043d\u0447\u0435\u043d\u0433"
    ],
    "name:swe_x_preferred":[
        "Yancheng"
    ],
    "name:tgl_x_preferred":[
        "Yancheng"
    ],
    "name:tur_x_preferred":[
        "Yancheng"
    ],
    "name:und_x_variant":[
        "Uchzhay",
        "Wu-chia",
        "Wu-chai-hsien",
        "Wu-chai",
        "Wuzhai",
        "Wuzhai Xian",
        "Yancheng Zhen",
        "\u4e94\u5be8\u53bf",
        "\u781a\u57ce\u9547"
    ],
    "name:urd_x_preferred":[
        "\u06cc\u0646\u0686\u06cc\u0646\u06af"
    ],
    "name:vie_x_preferred":[
        "Di\u00eam Th\u00e0nh"
    ],
    "name:war_x_preferred":[
        "Yancheng"
    ],
    "name:wuu_x_preferred":[
        "\u76d0\u57ce\u5e02"
    ],
    "name:zho_x_preferred":[
        "\u781a\u57ce"
    ],
    "name:zho_x_variant":[
        "\u76d0\u57ce\u5e02"
    ],
    "wof:name":"Yancheng",
    "wof:placetype":"locality"
},
  "geometry": {"coordinates":[111.86928,38.91538],"type":"Point"}
}