{
  "type": "Feature",
  "properties": {
    "gn:admin1_code":"24.0",
    "gn:asciiname":"Yancheng",
    "gn:country_code":"CN",
    "gn:dem":1442,
    "gn:feature_class":"P",
    "gn:feature_code":"PPLA3",
    "gn:name":"Yancheng",
    "gn:population":0,
    "gn:timezone":"Asia/Shanghai",
    "iso:country":"CN",
    "name:und_x_variant":[
        "Uchzhay",
        "Wu-chia",
        "Wu-chai-hsien",
        "Wu-chai",
        "Wuzhai",
        "Yancheng",
        "Wuzhai Xian",
        "Yancheng Zhen",
        "\u4e94\u5be8\u53bf",
        "\u781a\u57ce\u9547"
    ],
    "name:zho_x_preferred":[
        "\u781a\u57ce"
    ],
    "wof:name":"Yancheng",
    "wof:placetype":"locality"
},
  "geometry": {"coordinates":[111.86928,38.91538],"type":"Point"}
}