{
  "type": "Feature",
  "properties": {
    "gn:admin1_code":"3.0",
    "gn:asciiname":"Chengcun",
    "gn:country_code":"CN",
    "gn:dem":41,
    "gn:feature_class":"P",
    "gn:feature_code":"PPL",
    "gn:name":"Chengcun",
    "gn:population":0,
    "gn:timezone":"Asia/Shanghai",
    "iso:country":"CN",
    "name:und_x_variant":[
        "\u7a0b\u6751"
    ],
    "wof:name":"Chengcun",
    "wof:placetype":"locality"
},
  "geometry": {"coordinates":[115.02524,27.80231],"type":"Point"}
}