{
  "type": "Feature",
  "properties": {
    "gn:admin1_code":"29.0",
    "gn:asciiname":"Ayaluo",
    "gn:country_code":"CN",
    "gn:dem":1566,
    "gn:feature_class":"P",
    "gn:feature_code":"PPL",
    "gn:name":"Ayaluo",
    "gn:population":0,
    "gn:timezone":"Asia/Shanghai",
    "iso:country":"CN",
    "name:zho_x_preferred":[
        "\u963f\u4e9a\u6d1b"
    ],
    "wof:name":"Ayaluo",
    "wof:placetype":"locality"
},
  "geometry": {"coordinates":[98.87990000000001,25.8954],"type":"Point"}
}