{
  "type": "Feature",
  "properties": {
    "gn:admin1_code":"29.0",
    "gn:asciiname":"Jiunongding",
    "gn:country_code":"CN",
    "gn:dem":2245,
    "gn:feature_class":"P",
    "gn:feature_code":"PPL",
    "gn:name":"Jiunongding",
    "gn:population":0,
    "gn:timezone":"Asia/Shanghai",
    "iso:country":"CN",
    "name:zho_x_preferred":[
        "\u4e5d\u519c\u9876"
    ],
    "wof:name":"Jiunongding",
    "wof:placetype":"locality"
},
  "geometry": {"coordinates":[98.8845,28.3415],"type":"Point"}
}