{
  "type": "Feature",
  "properties": {
    "gn:admin1_code":"11.0",
    "gn:asciiname":"Shangtangjia",
    "gn:country_code":"CN",
    "gn:dem":389,
    "gn:feature_class":"P",
    "gn:feature_code":"PPL",
    "gn:name":"Shangtangjia",
    "gn:population":0,
    "gn:timezone":"Asia/Shanghai",
    "iso:country":"CN",
    "name:zho_x_preferred":[
        "\u4e0a\u5510\u5bb6"
    ],
    "wof:name":"Shangtangjia",
    "wof:placetype":"locality"
},
  "geometry": {"coordinates":[110.6644,28.19995],"type":"Point"}
}