{
  "type": "Feature",
  "properties": {
    "gn:admin1_code":"15.0",
    "gn:asciiname":"Zhaojiazhang",
    "gn:country_code":"CN",
    "gn:dem":1294,
    "gn:feature_class":"P",
    "gn:feature_code":"PPL",
    "gn:name":"Zhaojiazhang",
    "gn:population":0,
    "gn:timezone":"Asia/Shanghai",
    "iso:country":"CN",
    "name:und_x_variant":[
        "\u8d75\u5bb6\u638c"
    ],
    "wof:name":"Zhaojiazhang",
    "wof:placetype":"locality"
},
  "geometry": {"coordinates":[107.60375999999999,36.15078],"type":"Point"}
}