{
  "type": "Feature",
  "properties": {
    "gn:admin1_code":"3.0",
    "gn:asciiname":"Shanmaxia",
    "gn:country_code":"CN",
    "gn:dem":286,
    "gn:feature_class":"P",
    "gn:feature_code":"PPL",
    "gn:name":"Shanmaxia",
    "gn:population":0,
    "gn:timezone":"Asia/Shanghai",
    "iso:country":"CN",
    "name:und_x_variant":[
        "\u5c71\u9a6c\u4e0b"
    ],
    "wof:name":"Shanmaxia",
    "wof:placetype":"locality"
},
  "geometry": {"coordinates":[114.04156999999999,27.19198],"type":"Point"}
}