{
  "type": "Feature",
  "properties": {
    "gn:admin1_code":"1.0",
    "gn:asciiname":"Lizuicun",
    "gn:country_code":"CN",
    "gn:dem":25,
    "gn:feature_class":"P",
    "gn:feature_code":"PPL",
    "gn:name":"Lizuicun",
    "gn:population":0,
    "gn:timezone":"Asia/Shanghai",
    "iso:country":"CN",
    "name:zho_x_preferred":[
        "\u674e\u5480\u6751"
    ],
    "wof:name":"Lizuicun",
    "wof:placetype":"locality"
},
  "geometry": {"coordinates":[116.91791000000001,32.41669],"type":"Point"}
}