{
  "type": "Feature",
  "properties": {
    "gn:admin1_code":"8.0",
    "gn:asciiname":"Qixiangtun",
    "gn:country_code":"CN",
    "gn:dem":192,
    "gn:feature_class":"P",
    "gn:feature_code":"PPL",
    "gn:name":"Qixiangtun",
    "gn:population":0,
    "gn:timezone":"Asia/Shanghai",
    "iso:country":"CN",
    "name:zho_x_preferred":[
        "\u5176\u7965\u5c6f"
    ],
    "wof:name":"Qixiangtun",
    "wof:placetype":"locality"
},
  "geometry": {"coordinates":[128.06086000000002,45.26551],"type":"Point"}
}