{
  "type": "Feature",
  "properties": {
    "gn:admin1_code":"15.0",
    "gn:asciiname":"Baicaozui",
    "gn:country_code":"CN",
    "gn:dem":1644,
    "gn:feature_class":"P",
    "gn:feature_code":"PPL",
    "gn:name":"Baicaozui",
    "gn:population":0,
    "gn:timezone":"Asia/Shanghai",
    "iso:country":"CN",
    "name:zho_x_preferred":[
        "\u767d\u8349\u5480"
    ],
    "wof:name":"Baicaozui",
    "wof:placetype":"locality"
},
  "geometry": {"coordinates":[106.629,35.2779],"type":"Point"}
}