{
  "type": "Feature",
  "properties": {
    "gn:admin1_code":"16.0",
    "gn:asciiname":"Nanhu",
    "gn:country_code":"CN",
    "gn:dem":48,
    "gn:feature_class":"P",
    "gn:feature_code":"PPL",
    "gn:name":"Nanhu",
    "gn:population":0,
    "gn:timezone":"Asia/Shanghai",
    "iso:country":"CN",
    "name:deu_x_preferred":[
        "Nanhu"
    ],
    "name:zho_x_preferred":[
        "\u5357\u6e56"
    ],
    "wof:name":"Nanhu",
    "wof:placetype":"locality"
},
  "geometry": {"coordinates":[108.911,22.3351],"type":"Point"}
}