{
  "type": "Feature",
  "properties": {
    "gn:admin1_code":"05",
    "gn:asciiname":"Xianrendongshimokuang",
    "gn:country_code":"CN",
    "gn:dem":356,
    "gn:feature_class":"P",
    "gn:feature_code":"PPL",
    "gn:name":"Xianrendongshimokuang",
    "gn:population":0,
    "gn:timezone":"Asia/Shanghai",
    "iso:country":"CN",
    "wof:name":"Xianrendongshimokuang",
    "wof:placetype":"locality"
},
  "geometry": {"coordinates":[125.96417,43.27972000000001],"type":"Point"}
}