{
  "type": "Feature",
  "properties": {
    "gn:admin1_code":"2.0",
    "gn:asciiname":"Luojia",
    "gn:country_code":"CN",
    "gn:dem":213,
    "gn:feature_class":"P",
    "gn:feature_code":"PPL",
    "gn:name":"Luojia",
    "gn:population":0,
    "gn:timezone":"Asia/Shanghai",
    "iso:country":"CN",
    "name:und_x_variant":[
        "\u7f57\u5bb6",
        "Luojia"
    ],
    "wof:name":"Luojia",
    "wof:placetype":"locality"
},
  "geometry": {"coordinates":[119.90636000000001,29.61776],"type":"Point"}
}