{
  "type": "Feature",
  "properties": {
    "gn:admin1_code":"32.0",
    "gn:asciiname":"Dongneikawa",
    "gn:country_code":"CN",
    "gn:dem":3439,
    "gn:feature_class":"P",
    "gn:feature_code":"PPL",
    "gn:name":"Dongneikawa",
    "gn:population":0,
    "gn:timezone":"Asia/Shanghai",
    "iso:country":"CN",
    "name:zho_x_preferred":[
        "\u51ac\u5185\u5580\u74e6"
    ],
    "wof:name":"Dongneikawa",
    "wof:placetype":"locality"
},
  "geometry": {"coordinates":[102.661,33.7949],"type":"Point"}
}