{
  "type": "Feature",
  "properties": {
    "gn:admin1_code":"8.0",
    "gn:asciiname":"San'ancun",
    "gn:country_code":"CN",
    "gn:dem":143,
    "gn:feature_class":"P",
    "gn:feature_code":"PPL",
    "gn:name":"San\u2019ancun",
    "gn:population":0,
    "gn:timezone":"Asia/Shanghai",
    "iso:country":"CN",
    "name:und_x_variant":[
        "San\u2019ancun"
    ],
    "name:zho_x_preferred":[
        "\u4e09\u5b89\u6751"
    ],
    "wof:name":"San'ancun",
    "wof:placetype":"locality"
},
  "geometry": {"coordinates":[130.02834999999999,46.15901],"type":"Point"}
}