{
  "type": "Feature",
  "properties": {
    "gn:admin1_code":"32.0",
    "gn:asciiname":"Zexicun",
    "gn:country_code":"CN",
    "gn:dem":3781,
    "gn:feature_class":"P",
    "gn:feature_code":"PPL",
    "gn:name":"Zexicun",
    "gn:population":0,
    "gn:timezone":"Asia/Shanghai",
    "iso:country":"CN",
    "name:zho_x_preferred":[
        "\u6cfd\u897f\u6751"
    ],
    "wof:name":"Zexicun",
    "wof:placetype":"locality"
},
  "geometry": {"coordinates":[100.023,32.3028],"type":"Point"}
}