{
  "type": "Feature",
  "properties": {
    "gn:admin1_code":"29",
    "gn:asciiname":"Yezhutang",
    "gn:country_code":"CN",
    "gn:dem":1364,
    "gn:feature_class":"P",
    "gn:feature_code":"PPL",
    "gn:name":"Yezhutang",
    "gn:population":0,
    "gn:timezone":"Asia/Shanghai",
    "iso:country":"CN",
    "name:zho_x_preferred":[
        "\u91ce\u732a\u5858"
    ],
    "wof:name":"Yezhutang",
    "wof:placetype":"locality"
},
  "geometry": {"coordinates":[104.816,23.4701],"type":"Point"}
}