{
  "type": "Feature",
  "properties": {
    "gn:admin1_code":"8.0",
    "gn:asciiname":"Zhufutun",
    "gn:country_code":"CN",
    "gn:dem":158,
    "gn:feature_class":"P",
    "gn:feature_code":"PPL",
    "gn:name":"Zhufutun",
    "gn:population":0,
    "gn:timezone":"Asia/Shanghai",
    "iso:country":"CN",
    "name:zho_x_preferred":[
        "\u6731\u798f\u5c6f"
    ],
    "name:zho_x_variant":[
        "\u8bf8\u798f\u5c6f\u8857\u9053"
    ],
    "wof:name":"Zhufutun",
    "wof:placetype":"locality"
},
  "geometry": {"coordinates":[127.06941,46.2358],"type":"Point"}
}