{
  "type": "Feature",
  "properties": {
    "gn:admin1_code":"24.0",
    "gn:asciiname":"Si'ao",
    "gn:country_code":"CN",
    "gn:dem":1468,
    "gn:feature_class":"P",
    "gn:feature_code":"PPL",
    "gn:name":"Si\u2019ao",
    "gn:population":0,
    "gn:timezone":"Asia/Shanghai",
    "iso:country":"CN",
    "name:und_x_variant":[
        "Si\u2019ao"
    ],
    "name:zho_x_preferred":[
        "\u5bfa\u51f9"
    ],
    "wof:name":"Si'ao",
    "wof:placetype":"locality"
},
  "geometry": {"coordinates":[113.65057,36.11607],"type":"Point"}
}