{
  "type": "Feature",
  "properties": {
    "gn:admin1_code":"2.0",
    "gn:asciiname":"Wujitang",
    "gn:country_code":"CN",
    "gn:dem":358,
    "gn:feature_class":"P",
    "gn:feature_code":"PPL",
    "gn:name":"Wujitang",
    "gn:population":0,
    "gn:timezone":"Asia/Shanghai",
    "iso:country":"CN",
    "name:zho_x_preferred":[
        "\u5c4b\u57fa\u5802"
    ],
    "wof:name":"Wujitang",
    "wof:placetype":"locality"
},
  "geometry": {"coordinates":[119.11784,28.78002],"type":"Point"}
}