{
  "type": "Feature",
  "properties": {
    "gn:admin1_code":"29.0",
    "gn:asciiname":"Waikenai",
    "gn:country_code":"CN",
    "gn:dem":1798,
    "gn:feature_class":"P",
    "gn:feature_code":"PPL",
    "gn:name":"Waikenai",
    "gn:population":0,
    "gn:timezone":"Asia/Shanghai",
    "iso:country":"CN",
    "name:zho_x_preferred":[
        "\u5916\u53ef\u5948"
    ],
    "wof:name":"Waikenai",
    "wof:placetype":"locality"
},
  "geometry": {"coordinates":[101.53400000000001,25.72],"type":"Point"}
}