{
  "type": "Feature",
  "properties": {
    "gn:admin1_code":"32.0",
    "gn:asciiname":"Lejiaping",
    "gn:country_code":"CN",
    "gn:dem":1200,
    "gn:feature_class":"P",
    "gn:feature_code":"PPL",
    "gn:name":"Lejiaping",
    "gn:population":0,
    "gn:timezone":"Asia/Shanghai",
    "iso:country":"CN",
    "name:zho_x_preferred":[
        "\u4e50\u5bb6\u576a"
    ],
    "wof:name":"Lejiaping",
    "wof:placetype":"locality"
},
  "geometry": {"coordinates":[102.934,30.2889],"type":"Point"}
}