{
  "type": "Feature",
  "properties": {
    "gn:admin1_code":"11",
    "gn:asciiname":"Disheng",
    "gn:country_code":"CN",
    "gn:dem":517,
    "gn:feature_class":"P",
    "gn:feature_code":"PPL",
    "gn:name":"Disheng",
    "gn:population":0,
    "gn:timezone":"Asia/Shanghai",
    "iso:country":"CN",
    "name:zho_x_preferred":[
        "\u5730\u80dc"
    ],
    "wof:name":"Disheng",
    "wof:placetype":"locality"
},
  "geometry": {"coordinates":[110.12524999999999,27.08982],"type":"Point"}
}