{
  "type": "Feature",
  "properties": {
    "gn:admin1_code":"29.0",
    "gn:asciiname":"Laodaoqing",
    "gn:country_code":"CN",
    "gn:dem":1935,
    "gn:feature_class":"P",
    "gn:feature_code":"PPL",
    "gn:name":"Laodaoqing",
    "gn:population":0,
    "gn:timezone":"Asia/Shanghai",
    "iso:country":"CN",
    "name:zho_x_preferred":[
        "\u8001\u9053\u7b90"
    ],
    "wof:name":"Laodaoqing",
    "wof:placetype":"locality"
},
  "geometry": {"coordinates":[99.929,24.7987],"type":"Point"}
}