{
  "type": "Feature",
  "properties": {
    "gn:admin1_code":"14.0",
    "gn:asciiname":"Yongguocun",
    "gn:country_code":"CN",
    "gn:dem":3735,
    "gn:feature_class":"P",
    "gn:feature_code":"PPL",
    "gn:name":"Yongguocun",
    "gn:population":0,
    "gn:timezone":"Asia/Urumqi",
    "iso:country":"CN",
    "name:zho_x_preferred":[
        "\u6c38\u679c\u6751"
    ],
    "wof:name":"Yongguocun",
    "wof:placetype":"locality"
},
  "geometry": {"coordinates":[98.37898,30.74196],"type":"Point"}
}