{
  "type": "Feature",
  "properties": {
    "gn:admin1_code":"5.0",
    "gn:asciiname":"Wunugechicun",
    "gn:country_code":"CN",
    "gn:dem":148,
    "gn:feature_class":"P",
    "gn:feature_code":"PPL",
    "gn:name":"Wunugechicun",
    "gn:population":0,
    "gn:timezone":"Asia/Shanghai",
    "iso:country":"CN",
    "name:zho_x_preferred":[
        "\u4e4c\u52aa\u683c\u5c3a\u6751"
    ],
    "wof:name":"Wunugechicun",
    "wof:placetype":"locality"
},
  "geometry": {"coordinates":[123.14237,45.01815],"type":"Point"}
}