{
  "type": "Feature",
  "properties": {
    "gn:admin1_code":"19.0",
    "gn:asciiname":"Sutuozicun",
    "gn:country_code":"CN",
    "gn:dem":50,
    "gn:feature_class":"P",
    "gn:feature_code":"PPL",
    "gn:name":"Sutuozicun",
    "gn:population":0,
    "gn:timezone":"Asia/Shanghai",
    "iso:country":"CN",
    "name:zho_x_preferred":[
        "\u82cf\u5768\u5b50\u6751"
    ],
    "wof:name":"Sutuozicun",
    "wof:placetype":"locality"
},
  "geometry": {"coordinates":[122.622,42.0989],"type":"Point"}
}