{
  "type": "Feature",
  "properties": {
    "gn:admin1_code":"21.0",
    "gn:asciiname":"Hanjiaqu",
    "gn:country_code":"CN",
    "gn:dem":1802,
    "gn:feature_class":"P",
    "gn:feature_code":"PPL",
    "gn:name":"Hanjiaqu",
    "gn:population":0,
    "gn:timezone":"Asia/Shanghai",
    "iso:country":"CN",
    "name:und_x_variant":[
        "\u97e9\u5bb6\u6e20"
    ],
    "name:zho_x_preferred":[
        "\u97e9\u5bb6\u6e20"
    ],
    "wof:name":"Hanjiaqu",
    "wof:placetype":"locality"
},
  "geometry": {"coordinates":[106.49625,36.9421],"type":"Point"}
}