{
  "type": "Feature",
  "properties": {
    "gn:admin1_code":"26.0",
    "gn:asciiname":"Sunshizui",
    "gn:country_code":"CN",
    "gn:dem":1462,
    "gn:feature_class":"P",
    "gn:feature_code":"PPL",
    "gn:name":"Sunshizui",
    "gn:population":0,
    "gn:timezone":"Asia/Shanghai",
    "iso:country":"CN",
    "name:und_x_variant":[
        "\u5b59\u77f3\u5480"
    ],
    "wof:name":"Sunshizui",
    "wof:placetype":"locality"
},
  "geometry": {"coordinates":[107.35554999999999,36.97656],"type":"Point"}
}