{
  "type": "Feature",
  "properties": {
    "gn:admin1_code":"3.0",
    "gn:asciiname":"Zhoujiayuan",
    "gn:country_code":"CN",
    "gn:dem":424,
    "gn:feature_class":"P",
    "gn:feature_code":"PPL",
    "gn:name":"Zhoujiayuan",
    "gn:population":0,
    "gn:timezone":"Asia/Shanghai",
    "iso:country":"CN",
    "name:und_x_variant":[
        "\u5468\u5bb6\u6e90"
    ],
    "wof:name":"Zhoujiayuan",
    "wof:placetype":"locality"
},
  "geometry": {"coordinates":[114.44817999999999,28.40217],"type":"Point"}
}