{
  "type": "Feature",
  "properties": {
    "gn:admin1_code":"12.0",
    "gn:asciiname":"Anlejing",
    "gn:country_code":"CN",
    "gn:dem":677,
    "gn:feature_class":"P",
    "gn:feature_code":"PPL",
    "gn:name":"Anlejing",
    "gn:population":0,
    "gn:timezone":"Asia/Shanghai",
    "iso:country":"CN",
    "name:zho_x_preferred":[
        "\u5b89\u4e50\u4e95"
    ],
    "wof:name":"Anlejing",
    "wof:placetype":"locality"
},
  "geometry": {"coordinates":[109.72189,30.56125],"type":"Point"}
}