{
  "type": "Feature",
  "properties": {
    "gn:admin1_code":"7",
    "gn:asciiname":"Fudingjin",
    "gn:country_code":"CN",
    "gn:dem":15,
    "gn:feature_class":"P",
    "gn:feature_code":"PPL",
    "gn:name":"Fudingjin",
    "gn:population":0,
    "gn:timezone":"Asia/Shanghai",
    "iso:country":"CN",
    "name:zho_x_preferred":[
        "\u798f\u9f0e\u91d1"
    ],
    "wof:name":"Fudingjin",
    "wof:placetype":"locality"
},
  "geometry": {"coordinates":[117.17864,23.79604],"type":"Point"}
}