{
  "type": "Feature",
  "properties": {
    "gn:admin1_code":"30",
    "gn:asciiname":"Yamaliao",
    "gn:country_code":"CN",
    "gn:dem":606,
    "gn:feature_class":"P",
    "gn:feature_code":"PPL",
    "gn:name":"Yamaliao",
    "gn:population":0,
    "gn:timezone":"Asia/Shanghai",
    "iso:country":"CN",
    "name:zho_x_preferred":[
        "\u9e2d\u9ebb\u5bee"
    ],
    "wof:name":"Yamaliao",
    "wof:placetype":"locality"
},
  "geometry": {"coordinates":[115.86957,23.52437],"type":"Point"}
}