{
  "type": "Feature",
  "properties": {
    "gn:admin1_code":"29.0",
    "gn:asciiname":"Wuguai",
    "gn:country_code":"CN",
    "gn:dem":2121,
    "gn:feature_class":"P",
    "gn:feature_code":"PPL",
    "gn:name":"Wuguai",
    "gn:population":0,
    "gn:timezone":"Asia/Shanghai",
    "iso:country":"CN",
    "name:und_x_variant":[
        "\u4e94\u62d0"
    ],
    "wof:name":"Wuguai",
    "wof:placetype":"locality"
},
  "geometry": {"coordinates":[103.97799999999999,25.9846],"type":"Point"}
}