{
  "type": "Feature",
  "properties": {
    "gn:admin1_code":"09",
    "gn:asciiname":"Banqiao",
    "gn:country_code":"CN",
    "gn:dem":116,
    "gn:feature_class":"P",
    "gn:feature_code":"PPLA4",
    "gn:name":"Banqiao",
    "gn:population":0,
    "gn:timezone":"Asia/Shanghai",
    "iso:country":"CN",
    "name:und_x_variant":[
        "Pan-ch\u2019iao",
        "Banqiao Zhen",
        "Banqiao"
    ],
    "name:zho_x_preferred":[
        "\u677f\u6865"
    ],
    "wof:name":"Banqiao",
    "wof:placetype":"locality"
},
  "geometry": {"coordinates":[113.62124,32.99760999999999],"type":"Point"}
}