{
  "type": "Feature",
  "properties": {
    "gn:admin1_code":"9.0",
    "gn:asciiname":"Dashikan",
    "gn:country_code":"CN",
    "gn:dem":840,
    "gn:feature_class":"P",
    "gn:feature_code":"PPL",
    "gn:name":"Dashikan",
    "gn:population":0,
    "gn:timezone":"Asia/Shanghai",
    "iso:country":"CN",
    "name:und_x_variant":[
        "\u5927\u77f3\u574e",
        "Dashikan"
    ],
    "wof:name":"Dashikan",
    "wof:placetype":"locality"
},
  "geometry": {"coordinates":[112.07037,33.75335],"type":"Point"}
}