{
  "type": "Feature",
  "properties": {
    "gn:admin1_code":"33.0",
    "gn:asciiname":"Zhuantouya",
    "gn:country_code":"CN",
    "gn:dem":653,
    "gn:feature_class":"P",
    "gn:feature_code":"PPL",
    "gn:name":"Zhuantouya",
    "gn:population":0,
    "gn:timezone":"Asia/Shanghai",
    "iso:country":"CN",
    "name:zho_x_preferred":[
        "\u8f6c\u5934\u57ad"
    ],
    "wof:name":"Zhuantouya",
    "wof:placetype":"locality"
},
  "geometry": {"coordinates":[106.80500000000001,28.7058],"type":"Point"}
}