{
  "type": "Feature",
  "properties": {
    "gn:admin1_code":"02",
    "gn:asciiname":"Yuchitou",
    "gn:country_code":"CN",
    "gn:dem":2,
    "gn:feature_class":"P",
    "gn:feature_code":"PPL",
    "gn:name":"Yuchitou",
    "gn:population":0,
    "gn:timezone":"Asia/Shanghai",
    "iso:country":"CN",
    "name:und_x_variant":[
        "\u9c7c\u6c60\u5934"
    ],
    "wof:name":"Yuchitou",
    "wof:placetype":"locality"
},
  "geometry": {"coordinates":[121.11526000000001,30.82303],"type":"Point"}
}