{
  "type": "Feature",
  "properties": {
    "gn:admin1_code":"29",
    "gn:asciiname":"Zhangmuqing",
    "gn:country_code":"CN",
    "gn:dem":2082,
    "gn:feature_class":"P",
    "gn:feature_code":"PPL",
    "gn:name":"Zhangmuqing",
    "gn:population":0,
    "gn:timezone":"Asia/Shanghai",
    "iso:country":"CN",
    "name:zho_x_preferred":[
        "\u6a1f\u6728\u7b90"
    ],
    "wof:name":"Zhangmuqing",
    "wof:placetype":"locality"
},
  "geometry": {"coordinates":[102.51579,24.68441],"type":"Point"}
}