{
  "type": "Feature",
  "properties": {
    "gn:admin1_code":"25",
    "gn:asciiname":"Qingshiguan",
    "gn:country_code":"CN",
    "gn:dem":404,
    "gn:feature_class":"P",
    "gn:feature_code":"PPL",
    "gn:name":"Qingshiguan",
    "gn:population":0,
    "gn:timezone":"Asia/Shanghai",
    "iso:country":"CN",
    "name:zho_x_preferred":[
        "\u9752\u77f3\u5173"
    ],
    "wof:name":"Qingshiguan",
    "wof:placetype":"locality"
},
  "geometry": {"coordinates":[117.81699999999999,36.4385],"type":"Point"}
}