{
  "type": "Feature",
  "properties": {
    "gn:admin1_code":"29.0",
    "gn:asciiname":"Luoweiyi",
    "gn:country_code":"CN",
    "gn:dem":2199,
    "gn:feature_class":"P",
    "gn:feature_code":"PPL",
    "gn:name":"Luoweiyi",
    "gn:population":0,
    "gn:timezone":"Asia/Shanghai",
    "iso:country":"CN",
    "name:zho_x_preferred":[
        "\u7f57\u4f1f\u9091"
    ],
    "wof:name":"Luoweiyi",
    "wof:placetype":"locality"
},
  "geometry": {"coordinates":[100.173,26.5836],"type":"Point"}
}