{
  "type": "Feature",
  "properties": {
    "gn:admin1_code":"8.0",
    "gn:asciiname":"Hexingtun",
    "gn:country_code":"CN",
    "gn:dem":294,
    "gn:feature_class":"P",
    "gn:feature_code":"PPL",
    "gn:name":"Hexingtun",
    "gn:population":0,
    "gn:timezone":"Asia/Shanghai",
    "iso:country":"CN",
    "name:zho_x_preferred":[
        "\u5408\u5174\u5c6f"
    ],
    "wof:name":"Hexingtun",
    "wof:placetype":"locality"
},
  "geometry": {"coordinates":[127.30145,45.57329],"type":"Point"}
}