{
  "type": "Feature",
  "properties": {
    "gn:admin1_code":"29",
    "gn:asciiname":"Balazong",
    "gn:country_code":"CN",
    "gn:dem":1475,
    "gn:feature_class":"P",
    "gn:feature_code":"PPL",
    "gn:name":"Balazong",
    "gn:population":0,
    "gn:timezone":"Asia/Shanghai",
    "iso:country":"CN",
    "name:zho_x_preferred":[
        "\u628a\u62c9\u5b97"
    ],
    "wof:name":"Balazong",
    "wof:placetype":"locality"
},
  "geometry": {"coordinates":[102.101,24.4961],"type":"Point"}
}