{
  "type": "Feature",
  "properties": {
    "gn:admin1_code":"22",
    "gn:asciiname":"Lijiawu",
    "gn:country_code":"CN",
    "gn:dem":24,
    "gn:feature_class":"P",
    "gn:feature_code":"PPL",
    "gn:name":"Lijiawu",
    "gn:population":0,
    "gn:timezone":"Asia/Shanghai",
    "iso:country":"CN",
    "name:zho_x_preferred":[
        "\u674e\u5bb6\u52a1"
    ],
    "wof:name":"Lijiawu",
    "wof:placetype":"locality"
},
  "geometry": {"coordinates":[116.60516,39.70703],"type":"Point"}
}