{
  "type": "Feature",
  "properties": {
    "gn:admin1_code":"4.0",
    "gn:asciiname":"Gongjiabang",
    "gn:country_code":"CN",
    "gn:dem":104,
    "gn:feature_class":"P",
    "gn:feature_code":"PPL",
    "gn:name":"Gongjiabang",
    "gn:population":0,
    "gn:timezone":"Asia/Shanghai",
    "iso:country":"CN",
    "name:zho_x_preferred":[
        "\u9f9a\u5bb6\u6d5c"
    ],
    "wof:name":"Gongjiabang",
    "wof:placetype":"locality"
},
  "geometry": {"coordinates":[119.61060999999999,31.17457000000001],"type":"Point"}
}