{
  "type": "Feature",
  "properties": {
    "gn:admin1_code":"29.0",
    "gn:asciiname":"Lianhuachi",
    "gn:country_code":"CN",
    "gn:dem":1962,
    "gn:feature_class":"P",
    "gn:feature_code":"PPL",
    "gn:name":"Lianhuachi",
    "gn:population":0,
    "gn:timezone":"Asia/Shanghai",
    "iso:country":"CN",
    "name:zho_x_preferred":[
        "\u83b2\u82b1\u6c60"
    ],
    "wof:name":"Lianhuachi",
    "wof:placetype":"locality"
},
  "geometry": {"coordinates":[103.325,25.2438],"type":"Point"}
}