{
  "type": "Feature",
  "properties": {
    "gn:admin1_code":"18",
    "gn:asciiname":"Minzucun",
    "gn:country_code":"CN",
    "gn:dem":954,
    "gn:feature_class":"P",
    "gn:feature_code":"PPL",
    "gn:name":"Minzucun",
    "gn:population":0,
    "gn:timezone":"Asia/Shanghai",
    "iso:country":"CN",
    "name:zho_x_preferred":[
        "\u6c11\u65cf\u6751"
    ],
    "wof:name":"Minzucun",
    "wof:placetype":"locality"
},
  "geometry": {"coordinates":[105.14400000000001,25.9426],"type":"Point"}
}