{
  "type": "Feature",
  "properties": {
    "gn:admin1_code":"13.0",
    "gn:asciiname":"Jianggale Bage",
    "gn:country_code":"CN",
    "gn:dem":1733,
    "gn:feature_class":"P",
    "gn:feature_code":"PPL",
    "gn:name":"Jianggale Bage",
    "gn:population":0,
    "gn:timezone":"Asia/Shanghai",
    "iso:country":"CN",
    "name:zho_x_preferred":[
        "\u6c5f\u5c15\u52d2\u5df4\u683c"
    ],
    "wof:name":"Jianggale Bage",
    "wof:placetype":"locality"
},
  "geometry": {"coordinates":[78.62725,37.19006],"type":"Point"}
}