{
  "type": "Feature",
  "properties": {
    "gn:admin1_code":"32.0",
    "gn:asciiname":"Fanjiamiao",
    "gn:country_code":"CN",
    "gn:dem":533,
    "gn:feature_class":"P",
    "gn:feature_code":"PPL",
    "gn:name":"Fanjiamiao",
    "gn:population":0,
    "gn:timezone":"Asia/Shanghai",
    "iso:country":"CN",
    "name:zho_x_preferred":[
        "\u6a0a\u5bb6\u5e99"
    ],
    "wof:name":"Fanjiamiao",
    "wof:placetype":"locality"
},
  "geometry": {"coordinates":[104.60599999999999,31.3993],"type":"Point"}
}