{
  "type": "Feature",
  "properties": {
    "gn:admin1_code":"8.0",
    "gn:asciiname":"Zhifu",
    "gn:country_code":"CN",
    "gn:dem":182,
    "gn:feature_class":"P",
    "gn:feature_code":"PPLA4",
    "gn:name":"Zhifu",
    "gn:population":0,
    "gn:timezone":"Asia/Shanghai",
    "iso:country":"CN",
    "name:und_x_variant":[
        "Zhifu Xiang"
    ],
    "name:zho_x_preferred":[
        "\u81f4\u5bcc"
    ],
    "name:zho_x_variant":[
        "\u81f4\u5bcc\u4e61"
    ],
    "wof:name":"Zhifu",
    "wof:placetype":"locality"
},
  "geometry": {"coordinates":[127.40564999999999,46.99047],"type":"Point"}
}