{
  "type": "Feature",
  "properties": {
    "gn:admin1_code":"7",
    "gn:asciiname":"Shihoucun",
    "gn:country_code":"CN",
    "gn:dem":29,
    "gn:feature_class":"P",
    "gn:feature_code":"PPL",
    "gn:name":"Shihoucun",
    "gn:population":0,
    "gn:timezone":"Asia/Shanghai",
    "iso:country":"CN",
    "name:und_x_variant":[
        "Shihou"
    ],
    "name:zho_x_preferred":[
        "\u77f3\u540e\u6751"
    ],
    "wof:name":"Shihoucun",
    "wof:placetype":"locality"
},
  "geometry": {"coordinates":[118.05155000000001,24.40451],"type":"Point"}
}