{
  "type": "Feature",
  "properties": {
    "gn:admin1_code":"24",
    "gn:asciiname":"Chijianling",
    "gn:country_code":"CN",
    "gn:dem":1491,
    "gn:feature_class":"P",
    "gn:feature_code":"PPL",
    "gn:name":"Chijianling",
    "gn:population":0,
    "gn:timezone":"Asia/Shanghai",
    "iso:country":"CN",
    "name:und_x_variant":[
        "Ch\u2019ih-chien-ling",
        "Chijianling"
    ],
    "name:zho_x_preferred":[
        "\u8d64\u575a\u5cad"
    ],
    "wof:name":"Chijianling",
    "wof:placetype":"locality"
},
  "geometry": {"coordinates":[111.43217,38.14255],"type":"Point"}
}