{
  "type": "Feature",
  "properties": {
    "gn:admin1_code":"25.0",
    "gn:asciiname":"Dongliangmacun",
    "gn:country_code":"CN",
    "gn:dem":43,
    "gn:feature_class":"P",
    "gn:feature_code":"PPL",
    "gn:name":"Dongliangmacun",
    "gn:population":0,
    "gn:timezone":"Asia/Shanghai",
    "iso:country":"CN",
    "name:zho_x_preferred":[
        "\u4e1c\u4eae\u9a6c\u6751"
    ],
    "wof:name":"Dongliangmacun",
    "wof:placetype":"locality"
},
  "geometry": {"coordinates":[119.58018,35.7677],"type":"Point"}
}