{
  "type": "Feature",
  "properties": {
    "gn:admin1_code":"30.0",
    "gn:asciiname":"Neilicun",
    "gn:country_code":"CN",
    "gn:dem":11,
    "gn:feature_class":"P",
    "gn:feature_code":"PPL",
    "gn:name":"Neilicun",
    "gn:population":0,
    "gn:timezone":"Asia/Shanghai",
    "iso:country":"CN",
    "name:zho_x_preferred":[
        "\u5167\u91cc\u6751"
    ],
    "wof:name":"Neilicun",
    "wof:placetype":"locality"
},
  "geometry": {"coordinates":[117.09492,23.5792],"type":"Point"}
}