{
  "type": "Feature",
  "properties": {
    "gn:admin1_code":"26.0",
    "gn:asciiname":"Cang'eryan",
    "gn:country_code":"CN",
    "gn:dem":1584,
    "gn:feature_class":"P",
    "gn:feature_code":"PPL",
    "gn:name":"Cang\u2019eryan",
    "gn:population":0,
    "gn:timezone":"Asia/Shanghai",
    "iso:country":"CN",
    "name:und_x_variant":[
        "Cang\u2019eryan",
        "\u82cd\u8033\u5ca9"
    ],
    "wof:name":"Cang'eryan",
    "wof:placetype":"locality"
},
  "geometry": {"coordinates":[107.56910999999999,33.65548],"type":"Point"}
}