{
  "type": "Feature",
  "properties": {
    "gn:admin1_code":"5.0",
    "gn:asciiname":"Menggu Taolagao",
    "gn:country_code":"CN",
    "gn:dem":136,
    "gn:feature_class":"P",
    "gn:feature_code":"PPL",
    "gn:name":"Menggu Taolagao",
    "gn:population":0,
    "gn:timezone":"Asia/Shanghai",
    "iso:country":"CN",
    "name:zho_x_preferred":[
        "\u8499\u53e4\u5957\u62c9\u641e"
    ],
    "wof:name":"Menggu Taolagao",
    "wof:placetype":"locality"
},
  "geometry": {"coordinates":[123.542,45.91742],"type":"Point"}
}