{
  "type": "Feature",
  "properties": {
    "gn:admin1_code":"4.0",
    "gn:asciiname":"Fenhu",
    "gn:country_code":"CN",
    "gn:dem":5,
    "gn:feature_class":"P",
    "gn:feature_code":"PPLA4",
    "gn:name":"Fenhu",
    "gn:population":0,
    "gn:timezone":"Asia/Shanghai",
    "iso:country":"CN",
    "name:und_x_variant":[
        "Fenhu Zhen"
    ],
    "name:zho_x_preferred":[
        "\u6c7e\u6e56"
    ],
    "name:zho_x_variant":[
        "\u6c7e\u6e56\u9547"
    ],
    "wof:name":"Fenhu",
    "wof:placetype":"locality"
},
  "geometry": {"coordinates":[120.83696,31.01352],"type":"Point"}
}