{
  "type": "Feature",
  "properties": {
    "gn:admin1_code":"8.0",
    "gn:asciiname":"Jianshan Shiliudui",
    "gn:country_code":"CN",
    "gn:dem":333,
    "gn:feature_class":"P",
    "gn:feature_code":"PPLF",
    "gn:name":"Jianshan Shiliudui",
    "gn:population":0,
    "gn:timezone":"Asia/Shanghai",
    "iso:country":"CN",
    "name:zho_x_preferred":[
        "\u5c16\u5c71\u5341\u516d\u961f"
    ],
    "wof:name":"Jianshan Shiliudui",
    "wof:placetype":"locality"
},
  "geometry": {"coordinates":[125.58901000000002,48.90693],"type":"Point"}
}