{
  "type": "Feature",
  "properties": {
    "gn:admin1_code":"29.0",
    "gn:asciiname":"Xincheng",
    "gn:country_code":"CN",
    "gn:dem":1095,
    "gn:feature_class":"P",
    "gn:feature_code":"PPL",
    "gn:name":"Xincheng",
    "gn:population":0,
    "gn:timezone":"Asia/Shanghai",
    "iso:country":"CN",
    "name:ceb_x_preferred":[
        "Xincheng"
    ],
    "name:deu_x_preferred":[
        "Xincheng"
    ],
    "name:fra_x_preferred":[
        "Xincheng"
    ],
    "name:jpn_x_preferred":[
        "\u65b0\u57ce\u533a"
    ],
    "name:kor_x_preferred":[
        "\uc2e0\uccad\uad6c"
    ],
    "name:mlg_x_preferred":[
        "Xincheng"
    ],
    "name:nor_x_preferred":[
        "Xincheng"
    ],
    "name:rus_x_preferred":[
        "\u0421\u0438\u043d\u044c\u0447\u044d\u043d"
    ],
    "name:swe_x_preferred":[
        "Xincheng"
    ],
    "name:zho_x_preferred":[
        "\u65b0\u57ce"
    ],
    "name:zho_x_variant":[
        "\u65b0\u57ce\u533a"
    ],
    "wof:name":"Xincheng",
    "wof:placetype":"locality"
},
  "geometry": {"coordinates":[99.6202,24.5384],"type":"Point"}
}