{
  "type": "Feature",
  "properties": {
    "gn:admin1_code":"5.0",
    "gn:asciiname":"Guangshi",
    "gn:country_code":"CN",
    "gn:dem":205,
    "gn:feature_class":"P",
    "gn:feature_code":"PPL",
    "gn:name":"Guangshi",
    "gn:population":0,
    "gn:timezone":"Asia/Shanghai",
    "iso:country":"CN",
    "name:und_x_variant":[
        "\u5149\u77f3"
    ],
    "wof:name":"Guangshi",
    "wof:placetype":"locality"
},
  "geometry": {"coordinates":[129.39153000000002,42.90207],"type":"Point"}
}