{
  "type": "Feature",
  "properties": {
    "gn:admin1_code":"30.0",
    "gn:asciiname":"Qutancun",
    "gn:country_code":"CN",
    "gn:dem":117,
    "gn:feature_class":"P",
    "gn:feature_code":"PPL",
    "gn:name":"Qutancun",
    "gn:population":0,
    "gn:timezone":"Asia/Shanghai",
    "iso:country":"CN",
    "name:zho_x_preferred":[
        "\u66f2\u6ee9\u6751"
    ],
    "wof:name":"Qutancun",
    "wof:placetype":"locality"
},
  "geometry": {"coordinates":[116.73238000000001,24.31599],"type":"Point"}
}