{
  "type": "Feature",
  "properties": {
    "gn:admin1_code":"3.0",
    "gn:asciiname":"Dabeili",
    "gn:country_code":"CN",
    "gn:dem":522,
    "gn:feature_class":"P",
    "gn:feature_code":"PPL",
    "gn:name":"Dabeili",
    "gn:population":0,
    "gn:timezone":"Asia/Shanghai",
    "iso:country":"CN",
    "name:zho_x_preferred":[
        "\u5927\u9642\u91cc"
    ],
    "wof:name":"Dabeili",
    "wof:placetype":"locality"
},
  "geometry": {"coordinates":[117.503,29.5717],"type":"Point"}
}