{
  "type": "Feature",
  "properties": {
    "gn:admin1_code":"32.0",
    "gn:asciiname":"Gaoyanggu",
    "gn:country_code":"CN",
    "gn:dem":2559,
    "gn:feature_class":"P",
    "gn:feature_code":"PPL",
    "gn:name":"Gaoyanggu",
    "gn:population":0,
    "gn:timezone":"Asia/Shanghai",
    "iso:country":"CN",
    "name:zho_x_preferred":[
        "\u9ad8\u7f8a\u53e4"
    ],
    "wof:name":"Gaoyanggu",
    "wof:placetype":"locality"
},
  "geometry": {"coordinates":[100.184,28.2907],"type":"Point"}
}