{
  "type": "Feature",
  "properties": {
    "gn:admin1_code":"9.0",
    "gn:asciiname":"Jiaolin",
    "gn:country_code":"CN",
    "gn:dem":103,
    "gn:feature_class":"P",
    "gn:feature_code":"PPL",
    "gn:name":"Jiaolin",
    "gn:population":0,
    "gn:timezone":"Asia/Shanghai",
    "iso:country":"CN",
    "name:zho_x_preferred":[
        "\u7126\u6797"
    ],
    "wof:name":"Jiaolin",
    "wof:placetype":"locality"
},
  "geometry": {"coordinates":[112.26102,32.67537],"type":"Point"}
}