{
  "type": "Feature",
  "properties": {
    "gn:admin1_code":"32.0",
    "gn:asciiname":"Gaodongyan",
    "gn:country_code":"CN",
    "gn:dem":685,
    "gn:feature_class":"P",
    "gn:feature_code":"PPL",
    "gn:name":"Gaodongyan",
    "gn:population":0,
    "gn:timezone":"Asia/Shanghai",
    "iso:country":"CN",
    "name:zho_x_preferred":[
        "\u9ad8\u6d1e\u5ca9"
    ],
    "wof:name":"Gaodongyan",
    "wof:placetype":"locality"
},
  "geometry": {"coordinates":[107.96599999999999,31.2591],"type":"Point"}
}