{
  "type": "Feature",
  "properties": {
    "gn:admin1_code":"24.0",
    "gn:asciiname":"Foguangzhuang",
    "gn:country_code":"CN",
    "gn:dem":941,
    "gn:feature_class":"P",
    "gn:feature_code":"PPL",
    "gn:name":"Foguangzhuang",
    "gn:population":0,
    "gn:timezone":"Asia/Shanghai",
    "iso:country":"CN",
    "name:zho_x_preferred":[
        "\u4f5b\u5149\u5e84"
    ],
    "wof:name":"Foguangzhuang",
    "wof:placetype":"locality"
},
  "geometry": {"coordinates":[113.20066,39.14119],"type":"Point"}
}