{
  "type": "Feature",
  "properties": {
    "gn:admin1_code":"15.0",
    "gn:asciiname":"Shengjia Yangshan",
    "gn:country_code":"CN",
    "gn:dem":2351,
    "gn:feature_class":"P",
    "gn:feature_code":"PPL",
    "gn:name":"Shengjia Yangshan",
    "gn:population":0,
    "gn:timezone":"Asia/Shanghai",
    "iso:country":"CN",
    "name:zho_x_preferred":[
        "\u76db\u5bb6\u9633\u5c71"
    ],
    "wof:name":"Shengjia Yangshan",
    "wof:placetype":"locality"
},
  "geometry": {"coordinates":[104.22499999999999,35.251],"type":"Point"}
}