{
  "type": "Feature",
  "properties": {
    "gn:admin1_code":"11.0",
    "gn:asciiname":"Yaomaka",
    "gn:country_code":"CN",
    "gn:dem":655,
    "gn:feature_class":"P",
    "gn:feature_code":"PPL",
    "gn:name":"Yaomaka",
    "gn:population":0,
    "gn:timezone":"Asia/Shanghai",
    "iso:country":"CN",
    "name:zho_x_preferred":[
        "\u8000\u9a6c\u5361"
    ],
    "wof:name":"Yaomaka",
    "wof:placetype":"locality"
},
  "geometry": {"coordinates":[109.56789999999999,28.60485],"type":"Point"}
}