{
  "type": "Feature",
  "properties": {
    "gn:admin1_code":"13.0",
    "gn:asciiname":"Keluole Bake",
    "gn:country_code":"CN",
    "gn:dem":2146,
    "gn:feature_class":"P",
    "gn:feature_code":"PPL",
    "gn:name":"Keluole Bake",
    "gn:population":0,
    "gn:timezone":"Asia/Shanghai",
    "iso:country":"CN",
    "name:zho_x_preferred":[
        "\u514b\u6d1b\u52d2\u5df4\u514b"
    ],
    "wof:name":"Keluole Bake",
    "wof:placetype":"locality"
},
  "geometry": {"coordinates":[80.17914,36.68559000000001],"type":"Point"}
}