{
  "type": "Feature",
  "properties": {
    "gn:admin1_code":"18",
    "gn:asciiname":"Longjia Wanzi",
    "gn:country_code":"CN",
    "gn:dem":2069,
    "gn:feature_class":"P",
    "gn:feature_code":"PPL",
    "gn:name":"Longjia Wanzi",
    "gn:population":0,
    "gn:timezone":"Asia/Shanghai",
    "iso:country":"CN",
    "name:zho_x_preferred":[
        "\u9f99\u5bb6\u6e7e\u5b50"
    ],
    "wof:name":"Longjia Wanzi",
    "wof:placetype":"locality"
},
  "geometry": {"coordinates":[104.779,27.0131],"type":"Point"}
}