{
  "type": "Feature",
  "properties": {
    "gn:admin1_code":"11.0",
    "gn:asciiname":"Wangxiyuan",
    "gn:country_code":"CN",
    "gn:dem":770,
    "gn:feature_class":"P",
    "gn:feature_code":"PPL",
    "gn:name":"Wangxiyuan",
    "gn:population":0,
    "gn:timezone":"Asia/Shanghai",
    "iso:country":"CN",
    "name:zho_x_preferred":[
        "\u65fa\u6eaa\u56ed"
    ],
    "wof:name":"Wangxiyuan",
    "wof:placetype":"locality"
},
  "geometry": {"coordinates":[110.18998000000001,26.4747],"type":"Point"}
}