{
  "type": "Feature",
  "properties": {
    "gn:admin1_code":"10",
    "gn:asciiname":"Manaigou",
    "gn:country_code":"CN",
    "gn:dem":1437,
    "gn:feature_class":"P",
    "gn:feature_code":"PPL",
    "gn:name":"Manaigou",
    "gn:population":0,
    "gn:timezone":"Asia/Shanghai",
    "iso:country":"CN",
    "name:zho_x_preferred":[
        "\u5988\u5976\u6c9f"
    ],
    "wof:name":"Manaigou",
    "wof:placetype":"locality"
},
  "geometry": {"coordinates":[113.97654,41.17113],"type":"Point"}
}