{
  "type": "Feature",
  "properties": {
    "gn:admin1_code":"2.0",
    "gn:asciiname":"Tangli",
    "gn:country_code":"CN",
    "gn:dem":62,
    "gn:feature_class":"P",
    "gn:feature_code":"PPL",
    "gn:name":"Tangli",
    "gn:population":0,
    "gn:timezone":"Asia/Shanghai",
    "iso:country":"CN",
    "name:zho_x_preferred":[
        "\u68e0\u91cc"
    ],
    "wof:name":"Tangli",
    "wof:placetype":"locality"
},
  "geometry": {"coordinates":[120.32367000000001,29.53082],"type":"Point"}
}