{
  "type": "Feature",
  "properties": {
    "gn:admin1_code":"19.0",
    "gn:asciiname":"Qijiazi",
    "gn:country_code":"CN",
    "gn:dem":140,
    "gn:feature_class":"P",
    "gn:feature_code":"PPL",
    "gn:name":"Qijiazi",
    "gn:population":0,
    "gn:timezone":"Asia/Shanghai",
    "iso:country":"CN",
    "name:zho_x_preferred":[
        "\u4e03\u5bb6\u5b50"
    ],
    "wof:name":"Qijiazi",
    "wof:placetype":"locality"
},
  "geometry": {"coordinates":[124.026,42.8079],"type":"Point"}
}