{
  "type": "Feature",
  "properties": {
    "gn:admin1_code":"15.0",
    "gn:asciiname":"Wujiaping",
    "gn:country_code":"CN",
    "gn:dem":2178,
    "gn:feature_class":"P",
    "gn:feature_code":"PPL",
    "gn:name":"Wujiaping",
    "gn:population":0,
    "gn:timezone":"Asia/Shanghai",
    "iso:country":"CN",
    "name:zho_x_preferred":[
        "\u5434\u5bb6\u576a"
    ],
    "wof:name":"Wujiaping",
    "wof:placetype":"locality"
},
  "geometry": {"coordinates":[103.032,36.5026],"type":"Point"}
}