{
  "type": "Feature",
  "properties": {
    "gn:admin1_code":"26.0",
    "gn:asciiname":"Houxiangliu",
    "gn:country_code":"CN",
    "gn:dem":449,
    "gn:feature_class":"P",
    "gn:feature_code":"PPL",
    "gn:name":"Houxiangliu",
    "gn:population":0,
    "gn:timezone":"Asia/Shanghai",
    "iso:country":"CN",
    "name:zho_x_preferred":[
        "\u540e\u5df7\u5218"
    ],
    "wof:name":"Houxiangliu",
    "wof:placetype":"locality"
},
  "geometry": {"coordinates":[109.47526000000001,34.9432],"type":"Point"}
}