{
  "type": "Feature",
  "properties": {
    "gn:admin1_code":"18",
    "gn:asciiname":"Shalangwan",
    "gn:country_code":"CN",
    "gn:dem":1228,
    "gn:feature_class":"P",
    "gn:feature_code":"PPL",
    "gn:name":"Shalangwan",
    "gn:population":0,
    "gn:timezone":"Asia/Shanghai",
    "iso:country":"CN",
    "name:zho_x_preferred":[
        "\u6c99\u6d6a\u6e7e"
    ],
    "wof:name":"Shalangwan",
    "wof:placetype":"locality"
},
  "geometry": {"coordinates":[107.52200000000001,27.9106],"type":"Point"}
}