{
  "type": "Feature",
  "properties": {
    "gn:admin1_code":"1.0",
    "gn:asciiname":"Sifangcun",
    "gn:country_code":"CN",
    "gn:dem":26,
    "gn:feature_class":"P",
    "gn:feature_code":"PPL",
    "gn:name":"Sifangcun",
    "gn:population":0,
    "gn:timezone":"Asia/Shanghai",
    "iso:country":"CN",
    "name:zho_x_preferred":[
        "\u53f8\u623f\u6751"
    ],
    "wof:name":"Sifangcun",
    "wof:placetype":"locality"
},
  "geometry": {"coordinates":[117.32391,33.54132],"type":"Point"}
}