{
  "type": "Feature",
  "properties": {
    "gn:admin1_code":"9.0",
    "gn:asciiname":"Hanzhuang",
    "gn:country_code":"CN",
    "gn:dem":525,
    "gn:feature_class":"P",
    "gn:feature_code":"PPL",
    "gn:name":"Hanzhuang",
    "gn:population":0,
    "gn:timezone":"Asia/Shanghai",
    "iso:country":"CN",
    "name:und_x_variant":[
        "\u97e9\u5e84",
        "Hanzhuang"
    ],
    "wof:name":"Hanzhuang",
    "wof:placetype":"locality"
},
  "geometry": {"coordinates":[112.33204000000001,33.61868],"type":"Point"}
}