{
  "type": "Feature",
  "properties": {
    "gn:admin1_code":"32.0",
    "gn:asciiname":"Datong",
    "gn:country_code":"CN",
    "gn:dem":313,
    "gn:feature_class":"P",
    "gn:feature_code":"PPL",
    "gn:name":"Datong",
    "gn:population":0,
    "gn:timezone":"Asia/Shanghai",
    "iso:country":"CN",
    "name:rus_x_preferred":[
        "\u0414\u0430\u0442\u0443\u043d"
    ],
    "name:zho_x_preferred":[
        "\u5927\u540c"
    ],
    "wof:name":"Datong",
    "wof:placetype":"locality"
},
  "geometry": {"coordinates":[105.87536,30.50619],"type":"Point"}
}