{
  "type": "Feature",
  "properties": {
    "gn:admin1_code":"15.0",
    "gn:asciiname":"Shiqiao",
    "gn:country_code":"CN",
    "gn:dem":1859,
    "gn:feature_class":"P",
    "gn:feature_code":"PPL",
    "gn:name":"Shiqiao",
    "gn:population":0,
    "gn:timezone":"Asia/Shanghai",
    "iso:country":"CN",
    "name:zho_x_preferred":[
        "\u77f3\u6865"
    ],
    "wof:name":"Shiqiao",
    "wof:placetype":"locality"
},
  "geometry": {"coordinates":[106.27200000000001,35.1924],"type":"Point"}
}