{
  "type": "Feature",
  "properties": {
    "gn:admin1_code":"29.0",
    "gn:asciiname":"Jiucaiping",
    "gn:country_code":"CN",
    "gn:dem":2199,
    "gn:feature_class":"P",
    "gn:feature_code":"PPL",
    "gn:name":"Jiucaiping",
    "gn:population":0,
    "gn:timezone":"Asia/Shanghai",
    "iso:country":"CN",
    "name:zho_x_preferred":[
        "\u97ed\u83dc\u576a"
    ],
    "wof:name":"Jiucaiping",
    "wof:placetype":"locality"
},
  "geometry": {"coordinates":[103.759,25.2722],"type":"Point"}
}