{
  "type": "Feature",
  "properties": {
    "gn:admin1_code":"15.0",
    "gn:asciiname":"Miao'erya",
    "gn:country_code":"CN",
    "gn:dem":1481,
    "gn:feature_class":"P",
    "gn:feature_code":"PPL",
    "gn:name":"Miao\u2019erya",
    "gn:population":0,
    "gn:timezone":"Asia/Shanghai",
    "iso:country":"CN",
    "name:und_x_variant":[
        "Miao\u2019erya",
        "\u5e99\u513f\u57ad"
    ],
    "wof:name":"Miao'erya",
    "wof:placetype":"locality"
},
  "geometry": {"coordinates":[105.54349000000001,33.39199],"type":"Point"}
}