{
  "type": "Feature",
  "properties": {
    "gn:admin1_code":"3.0",
    "gn:asciiname":"Jiupinkeng",
    "gn:country_code":"CN",
    "gn:dem":203,
    "gn:feature_class":"P",
    "gn:feature_code":"PPL",
    "gn:name":"Jiupinkeng",
    "gn:population":0,
    "gn:timezone":"Asia/Shanghai",
    "iso:country":"CN",
    "name:und_x_variant":[
        "\u4e5d\u54c1\u5751"
    ],
    "wof:name":"Jiupinkeng",
    "wof:placetype":"locality"
},
  "geometry": {"coordinates":[115.93514,25.66781],"type":"Point"}
}