{
  "type": "Feature",
  "properties": {
    "gn:admin1_code":"12.0",
    "gn:asciiname":"Hanjinggou",
    "gn:country_code":"CN",
    "gn:dem":265,
    "gn:feature_class":"P",
    "gn:feature_code":"PPL",
    "gn:name":"Hanjinggou",
    "gn:population":0,
    "gn:timezone":"Asia/Shanghai",
    "iso:country":"CN",
    "name:zho_x_preferred":[
        "\u65f1\u4e95\u6c9f"
    ],
    "wof:name":"Hanjinggou",
    "wof:placetype":"locality"
},
  "geometry": {"coordinates":[114.14870000000001,31.77336],"type":"Point"}
}