{
  "type": "Feature",
  "properties": {
    "gn:admin1_code":"7",
    "gn:asciiname":"Hou'an",
    "gn:country_code":"CN",
    "gn:dem":51,
    "gn:feature_class":"P",
    "gn:feature_code":"PPL",
    "gn:name":"Hou\u2019an",
    "gn:population":0,
    "gn:timezone":"Asia/Shanghai",
    "iso:country":"CN",
    "name:zho_x_preferred":[
        "\u540e\u57b5"
    ],
    "name:zho_x_variant":[
        "Hou\u2019an"
    ],
    "wof:name":"Hou'an",
    "wof:placetype":"locality"
},
  "geometry": {"coordinates":[118.32299999999999,24.67698],"type":"Point"}
}