{
  "type": "Feature",
  "properties": {
    "gn:admin1_code":"32.0",
    "gn:asciiname":"Shitiantang",
    "gn:country_code":"CN",
    "gn:dem":396,
    "gn:feature_class":"P",
    "gn:feature_code":"PPL",
    "gn:name":"Shitiantang",
    "gn:population":0,
    "gn:timezone":"Asia/Shanghai",
    "iso:country":"CN",
    "name:zho_x_preferred":[
        "\u77f3\u5929\u5802"
    ],
    "wof:name":"Shitiantang",
    "wof:placetype":"locality"
},
  "geometry": {"coordinates":[105.095,28.3655],"type":"Point"}
}