{
  "type": "Feature",
  "properties": {
    "gn:admin1_code":"4.0",
    "gn:asciiname":"Zhouhe",
    "gn:country_code":"CN",
    "gn:dem":19,
    "gn:feature_class":"P",
    "gn:feature_code":"PPL",
    "gn:name":"Zhouhe",
    "gn:population":0,
    "gn:timezone":"Asia/Shanghai",
    "iso:country":"CN",
    "name:zho_x_preferred":[
        "\u5468\u6cb3"
    ],
    "wof:name":"Zhouhe",
    "wof:placetype":"locality"
},
  "geometry": {"coordinates":[118.262,33.6167],"type":"Point"}
}