{
  "type": "Feature",
  "properties": {
    "gn:admin1_code":"26.0",
    "gn:asciiname":"Jiufangwan",
    "gn:country_code":"CN",
    "gn:dem":1306,
    "gn:feature_class":"P",
    "gn:feature_code":"PPL",
    "gn:name":"Jiufangwan",
    "gn:population":0,
    "gn:timezone":"Asia/Shanghai",
    "iso:country":"CN",
    "name:zho_x_preferred":[
        "\u9152\u623f\u6e7e"
    ],
    "wof:name":"Jiufangwan",
    "wof:placetype":"locality"
},
  "geometry": {"coordinates":[108.11309,32.61416],"type":"Point"}
}