{
  "type": "Feature",
  "properties": {
    "gn:admin1_code":"4.0",
    "gn:asciiname":"Qiaotuancun",
    "gn:country_code":"CN",
    "gn:dem":25,
    "gn:feature_class":"P",
    "gn:feature_code":"PPL",
    "gn:name":"Qiaotuancun",
    "gn:population":0,
    "gn:timezone":"Asia/Shanghai",
    "iso:country":"CN",
    "name:und_x_variant":[
        "Qiaotuan",
        "Qiaotuancun"
    ],
    "name:zho_x_preferred":[
        "\u4e54\u56e2"
    ],
    "name:zho_x_variant":[
        "\u4e54\u56e2\u6751"
    ],
    "wof:name":"Qiaotuancun",
    "wof:placetype":"locality"
},
  "geometry": {"coordinates":[118.61351999999999,34.48029],"type":"Point"}
}