{
  "type": "Feature",
  "properties": {
    "gn:admin1_code":"11.0",
    "gn:asciiname":"Qiangbeidi",
    "gn:country_code":"CN",
    "gn:dem":268,
    "gn:feature_class":"P",
    "gn:feature_code":"PPL",
    "gn:name":"Qiangbeidi",
    "gn:population":0,
    "gn:timezone":"Asia/Shanghai",
    "iso:country":"CN",
    "name:zho_x_preferred":[
        "\u5899\u80cc\u5730"
    ],
    "wof:name":"Qiangbeidi",
    "wof:placetype":"locality"
},
  "geometry": {"coordinates":[110.01011,27.61262],"type":"Point"}
}