{
  "type": "Feature",
  "properties": {
    "gn:admin1_code":"30.0",
    "gn:asciiname":"Shangwei",
    "gn:country_code":"CN",
    "gn:dem":16,
    "gn:feature_class":"P",
    "gn:feature_code":"PPL",
    "gn:name":"Shangwei",
    "gn:population":0,
    "gn:timezone":"Asia/Shanghai",
    "iso:country":"CN",
    "name:zho_x_preferred":[
        "\u4e0a\u56f4"
    ],
    "wof:name":"Shangwei",
    "wof:placetype":"locality"
},
  "geometry": {"coordinates":[114.48014000000001,23.1884],"type":"Point"}
}