{
  "type": "Feature",
  "properties": {
    "gn:admin1_code":"1.0",
    "gn:asciiname":"Yaojiabian",
    "gn:country_code":"CN",
    "gn:dem":46,
    "gn:feature_class":"P",
    "gn:feature_code":"PPL",
    "gn:name":"Yaojiabian",
    "gn:population":0,
    "gn:timezone":"Asia/Shanghai",
    "iso:country":"CN",
    "name:zho_x_preferred":[
        "Yaojiabian"
    ],
    "name:zho_x_variant":[
        "\u59da\u5bb6\u8fb9"
    ],
    "wof:name":"Yaojiabian",
    "wof:placetype":"locality"
},
  "geometry": {"coordinates":[119.29273999999999,31.09067000000001],"type":"Point"}
}