{
  "type": "Feature",
  "properties": {
    "gn:admin1_code":"2.0",
    "gn:asciiname":"Mashecun",
    "gn:country_code":"CN",
    "gn:dem":8,
    "gn:feature_class":"P",
    "gn:feature_code":"PPL",
    "gn:name":"Mashecun",
    "gn:population":0,
    "gn:timezone":"Asia/Shanghai",
    "iso:country":"CN",
    "name:und_x_variant":[
        "Mashe",
        "\u9a6c\u538d",
        "Mashecun"
    ],
    "name:zho_x_preferred":[
        "\u9a6c\u538d\u6751"
    ],
    "wof:name":"Mashecun",
    "wof:placetype":"locality"
},
  "geometry": {"coordinates":[120.74981,30.82588],"type":"Point"}
}