{
  "type": "Feature",
  "properties": {
    "gn:admin1_code":"32.0",
    "gn:asciiname":"Songlinping",
    "gn:country_code":"CN",
    "gn:dem":1334,
    "gn:feature_class":"P",
    "gn:feature_code":"PPL",
    "gn:name":"Songlinping",
    "gn:population":0,
    "gn:timezone":"Asia/Shanghai",
    "iso:country":"CN",
    "name:zho_x_preferred":[
        "\u677e\u6797\u576a"
    ],
    "wof:name":"Songlinping",
    "wof:placetype":"locality"
},
  "geometry": {"coordinates":[105.65859,27.81994000000001],"type":"Point"}
}