{
  "type": "Feature",
  "properties": {
    "gn:admin1_code":"32.0",
    "gn:asciiname":"Nanmugou",
    "gn:country_code":"CN",
    "gn:dem":404,
    "gn:feature_class":"P",
    "gn:feature_code":"PPL",
    "gn:name":"Nanmugou",
    "gn:population":0,
    "gn:timezone":"Asia/Shanghai",
    "iso:country":"CN",
    "name:zho_x_preferred":[
        "\u6960\u6728\u6c9f"
    ],
    "wof:name":"Nanmugou",
    "wof:placetype":"locality"
},
  "geometry": {"coordinates":[104.7413,29.91733],"type":"Point"}
}