{
  "type": "Feature",
  "properties": {
    "gn:admin1_code":"19.0",
    "gn:asciiname":"Dahuahonggoucun",
    "gn:country_code":"CN",
    "gn:dem":157,
    "gn:feature_class":"P",
    "gn:feature_code":"PPL",
    "gn:name":"Dahuahonggoucun",
    "gn:population":0,
    "gn:timezone":"Asia/Shanghai",
    "iso:country":"CN",
    "name:zho_x_preferred":[
        "\u5927\u82b1\u7ea2\u6c9f\u6751"
    ],
    "wof:name":"Dahuahonggoucun",
    "wof:placetype":"locality"
},
  "geometry": {"coordinates":[122.633,40.3551],"type":"Point"}
}