{
  "type": "Feature",
  "properties": {
    "gn:admin1_code":"30",
    "gn:asciiname":"Shangdong",
    "gn:country_code":"CN",
    "gn:dem":304,
    "gn:feature_class":"P",
    "gn:feature_code":"PPL",
    "gn:name":"Shangdong",
    "gn:population":0,
    "gn:timezone":"Asia/Shanghai",
    "iso:country":"CN",
    "name:und_x_variant":[
        "\u4e0a\u6d1e",
        "Shangdong"
    ],
    "wof:name":"Shangdong",
    "wof:placetype":"locality"
},
  "geometry": {"coordinates":[112.48574000000001,24.97442],"type":"Point"}
}