{
  "type": "Feature",
  "properties": {
    "gn:admin1_code":"32.0",
    "gn:asciiname":"Guangda Linchang",
    "gn:country_code":"CN",
    "gn:dem":1520,
    "gn:feature_class":"P",
    "gn:feature_code":"PPLF",
    "gn:name":"Guangda Linchang",
    "gn:population":0,
    "gn:timezone":"Asia/Shanghai",
    "iso:country":"CN",
    "name:zho_x_preferred":[
        "\u5e7f\u5927\u6797\u573a"
    ],
    "wof:name":"Guangda Linchang",
    "wof:placetype":"locality"
},
  "geometry": {"coordinates":[105.54061000000002,28.21948],"type":"Point"}
}