{
  "type": "Feature",
  "properties": {
    "gn:admin1_code":"26.0",
    "gn:asciiname":"Wangjia Maocun",
    "gn:country_code":"CN",
    "gn:dem":1102,
    "gn:feature_class":"P",
    "gn:feature_code":"PPL",
    "gn:name":"Wangjia Maocun",
    "gn:population":0,
    "gn:timezone":"Asia/Shanghai",
    "iso:country":"CN",
    "name:zho_x_preferred":[
        "\u738b\u5bb6\u5cc1\u6751"
    ],
    "wof:name":"Wangjia Maocun",
    "wof:placetype":"locality"
},
  "geometry": {"coordinates":[109.437,37.5685],"type":"Point"}
}