{
  "type": "Feature",
  "properties": {
    "gn:admin1_code":"10",
    "gn:asciiname":"Nanyingzi",
    "gn:country_code":"CN",
    "gn:dem":1064,
    "gn:feature_class":"P",
    "gn:feature_code":"PPL",
    "gn:name":"Nanyingzi",
    "gn:population":0,
    "gn:timezone":"Asia/Shanghai",
    "iso:country":"CN",
    "name:zho_x_preferred":[
        "\u5357\u8425\u5b50"
    ],
    "wof:name":"Nanyingzi",
    "wof:placetype":"locality"
},
  "geometry": {"coordinates":[116.93476,41.89647],"type":"Point"}
}