{
  "type": "Feature",
  "properties": {
    "iso:country":"CN",
    "name:eng_x_preferred":[
        "Suqian"
    ],
    "name:zho_x_preferred":[
        "\u5bbf\u8fc1\u5e02"
    ],
    "qs:name":"\u5bbf\u8fc1\u5e02",
    "qs:name_adm0":"\u4e2d\u570b",
    "qs:name_adm1":"\u6c5f\u82cf\u7701",
    "qs:photos":34,
    "qs:photos_1k":7,
    "qs:photos_9k":1,
    "qs:photos_9r":2,
    "qs:photos_all":34,
    "qs:photos_sr":2,
    "qs:placetype":"LocalAdmin",
    "qs:pop_sr":"0",
    "wof:name":"Suqian",
    "wof:placetype":"localadmin"
},
  "geometry": {"coordinates":[118.265085,33.944619],"type":"Point"}
}