{
  "type": "Feature",
  "properties": {
    "gn:admin1_code":"30.0",
    "gn:asciiname":"Dazhuyuan",
    "gn:country_code":"CN",
    "gn:dem":430,
    "gn:feature_class":"P",
    "gn:feature_code":"PPL",
    "gn:name":"Dazhuyuan",
    "gn:population":0,
    "gn:timezone":"Asia/Shanghai",
    "iso:country":"CN",
    "name:zho_x_preferred":[
        "Dazhuyuan"
    ],
    "name:zho_x_variant":[
        "\u5927\u7af9\u56ed"
    ],
    "wof:name":"Dazhuyuan",
    "wof:placetype":"locality"
},
  "geometry": {"coordinates":[112.51194,24.10083],"type":"Point"}
}