{
  "type": "Feature",
  "properties": {
    "gn:admin1_code":"11.0",
    "gn:asciiname":"Liaojiachong",
    "gn:country_code":"CN",
    "gn:dem":465,
    "gn:feature_class":"P",
    "gn:feature_code":"PPL",
    "gn:name":"Liaojiachong",
    "gn:population":0,
    "gn:timezone":"Asia/Shanghai",
    "iso:country":"CN",
    "name:zho_x_preferred":[
        "\u5ed6\u5bb6\u51b2"
    ],
    "wof:name":"Liaojiachong",
    "wof:placetype":"locality"
},
  "geometry": {"coordinates":[111.82689999999999,27.40589000000001],"type":"Point"}
}