{
  "type": "Feature",
  "properties": {
    "gn:admin1_code":"26",
    "gn:asciiname":"Liujiamao",
    "gn:cc2":"CN",
    "gn:country_code":"CN",
    "gn:dem":1111,
    "gn:feature_class":"P",
    "gn:feature_code":"PPL",
    "gn:name":"Liujiamao",
    "gn:population":0,
    "gn:timezone":"Asia/Shanghai",
    "iso:country":"CN",
    "name:und_x_variant":[
        "Liu-chia-mao",
        "Liujiamao"
    ],
    "wof:name":"Liujiamao",
    "wof:placetype":"locality"
},
  "geometry": {"coordinates":[109.12778,38.205],"type":"Point"}
}