{
  "type": "Feature",
  "properties": {
    "gn:admin1_code":"1.0",
    "gn:asciiname":"Qianguocun",
    "gn:country_code":"CN",
    "gn:dem":40,
    "gn:feature_class":"P",
    "gn:feature_code":"PPL",
    "gn:name":"Qianguocun",
    "gn:population":0,
    "gn:timezone":"Asia/Shanghai",
    "iso:country":"CN",
    "name:zho_x_preferred":[
        "\u524d\u90ed\u6751"
    ],
    "wof:name":"Qianguocun",
    "wof:placetype":"locality"
},
  "geometry": {"coordinates":[115.38812,33.33832],"type":"Point"}
}