{
  "type": "Feature",
  "properties": {
    "gn:admin1_code":"32.0",
    "gn:asciiname":"Zejue",
    "gn:country_code":"CN",
    "gn:dem":2229,
    "gn:feature_class":"P",
    "gn:feature_code":"PPL",
    "gn:name":"Zejue",
    "gn:population":0,
    "gn:timezone":"Asia/Shanghai",
    "iso:country":"CN",
    "name:zho_x_preferred":[
        "\u5219\u89c9"
    ],
    "wof:name":"Zejue",
    "wof:placetype":"locality"
},
  "geometry": {"coordinates":[102.8481,28.12356],"type":"Point"}
}