{
  "type": "Feature",
  "properties": {
    "gn:admin1_code":"11.0",
    "gn:asciiname":"Rigeta",
    "gn:country_code":"CN",
    "gn:dem":813,
    "gn:feature_class":"P",
    "gn:feature_code":"PPL",
    "gn:name":"Rigeta",
    "gn:population":0,
    "gn:timezone":"Asia/Shanghai",
    "iso:country":"CN",
    "name:zho_x_preferred":[
        "\u65e5\u683c\u5854"
    ],
    "wof:name":"Rigeta",
    "wof:placetype":"locality"
},
  "geometry": {"coordinates":[109.82943,28.59042],"type":"Point"}
}