{
  "type": "Feature",
  "properties": {
    "gn:admin1_code":"26.0",
    "gn:asciiname":"Caijiayoufang",
    "gn:country_code":"CN",
    "gn:dem":1051,
    "gn:feature_class":"P",
    "gn:feature_code":"PPL",
    "gn:name":"Caijiayoufang",
    "gn:population":0,
    "gn:timezone":"Asia/Shanghai",
    "iso:country":"CN",
    "name:zho_x_preferred":[
        "\u8521\u5bb6\u6cb9\u623f"
    ],
    "wof:name":"Caijiayoufang",
    "wof:placetype":"locality"
},
  "geometry": {"coordinates":[109.68407000000001,33.48016],"type":"Point"}
}