{
  "type": "Feature",
  "properties": {
    "gn:admin1_code":"05",
    "gn:asciiname":"Xilinhe Linchang",
    "gn:country_code":"CN",
    "gn:dem":611,
    "gn:feature_class":"P",
    "gn:feature_code":"PPLF",
    "gn:name":"Xilinhe Linchang",
    "gn:population":0,
    "gn:timezone":"Asia/Shanghai",
    "iso:country":"CN",
    "name:und_x_variant":[
        "\u897f\u6797\u6cb3\u6797\u573a",
        "\u7ec6\u9cde\u6cb3\u6797\u573a"
    ],
    "wof:name":"Xilinhe Linchang",
    "wof:placetype":"locality"
},
  "geometry": {"coordinates":[127.86781000000001,42.58823],"type":"Point"}
}