{
  "type": "Feature",
  "properties": {
    "gn:admin1_code":"30.0",
    "gn:asciiname":"Dangyan",
    "gn:country_code":"CN",
    "gn:dem":119,
    "gn:feature_class":"P",
    "gn:feature_code":"PPL",
    "gn:name":"Dangyan",
    "gn:population":0,
    "gn:timezone":"Asia/Shanghai",
    "iso:country":"CN",
    "name:zho_x_preferred":[
        "Dangyan"
    ],
    "name:zho_x_variant":[
        "\u515a\u6f14"
    ],
    "wof:name":"Dangyan",
    "wof:placetype":"locality"
},
  "geometry": {"coordinates":[114.74336,24.07444],"type":"Point"}
}