{
  "type": "Feature",
  "properties": {
    "gn:admin1_code":"9.0",
    "gn:asciiname":"Longwogou",
    "gn:country_code":"CN",
    "gn:dem":1165,
    "gn:feature_class":"P",
    "gn:feature_code":"PPL",
    "gn:name":"Longwogou",
    "gn:population":0,
    "gn:timezone":"Asia/Shanghai",
    "iso:country":"CN",
    "name:zho_x_preferred":[
        "\u9f99\u5367\u6c9f"
    ],
    "wof:name":"Longwogou",
    "wof:placetype":"locality"
},
  "geometry": {"coordinates":[111.63011000000002,34.13332],"type":"Point"}
}