{
  "type": "Feature",
  "properties": {
    "gn:admin1_code":"15.0",
    "gn:asciiname":"Tianshengchang",
    "gn:country_code":"CN",
    "gn:dem":1244,
    "gn:feature_class":"P",
    "gn:feature_code":"PPL",
    "gn:name":"Tianshengchang",
    "gn:population":0,
    "gn:timezone":"Asia/Shanghai",
    "iso:country":"CN",
    "name:zho_x_preferred":[
        "\u5929\u751f\u573a"
    ],
    "wof:name":"Tianshengchang",
    "wof:placetype":"locality"
},
  "geometry": {"coordinates":[98.94329999999999,40.1092],"type":"Point"}
}