{
  "type": "Feature",
  "properties": {
    "gn:admin1_code":"31.0",
    "gn:asciiname":"Taocunxia",
    "gn:country_code":"CN",
    "gn:dem":44,
    "gn:feature_class":"P",
    "gn:feature_code":"PPL",
    "gn:name":"Taocunxia",
    "gn:population":0,
    "gn:timezone":"Asia/Shanghai",
    "iso:country":"CN",
    "name:zho_x_preferred":[
        "\u6843\u6751\u4e0b"
    ],
    "wof:name":"Taocunxia",
    "wof:placetype":"locality"
},
  "geometry": {"coordinates":[110.43438,19.84406],"type":"Point"}
}