{
  "type": "Feature",
  "properties": {
    "gn:admin1_code":"20.0",
    "gn:asciiname":"Longquan",
    "gn:country_code":"CN",
    "gn:dem":368,
    "gn:feature_class":"P",
    "gn:feature_code":"PPL",
    "gn:name":"Longquan",
    "gn:population":0,
    "gn:timezone":"Asia/Shanghai",
    "iso:country":"CN",
    "name:deu_x_preferred":[
        "Longquan"
    ],
    "name:fra_x_preferred":[
        "Longquan"
    ],
    "name:ita_x_preferred":[
        "Longquan"
    ],
    "name:jpn_x_preferred":[
        "\u7adc\u6cc9\u5e02"
    ],
    "name:kik_x_preferred":[
        "Longquan"
    ],
    "name:kor_x_preferred":[
        "\ub8fd\ucde8\uc548\uc2dc"
    ],
    "name:mlg_x_preferred":[
        "Longquan"
    ],
    "name:nld_x_preferred":[
        "Longquan"
    ],
    "name:nor_x_preferred":[
        "Longquan"
    ],
    "name:rus_x_preferred":[
        "\u041b\u0443\u043d\u0446\u044e\u0430\u043d\u044c"
    ],
    "name:swe_x_preferred":[
        "Longquan"
    ],
    "name:tgl_x_preferred":[
        "Longquan"
    ],
    "name:urd_x_preferred":[
        "\u0644\u0648\u0646\u06af\u0634\u0648\u0627\u0646"
    ],
    "name:vie_x_preferred":[
        "Long Tuy\u1ec1n"
    ],
    "name:war_x_preferred":[
        "Longquan"
    ],
    "name:wuu_x_preferred":[
        "\u9f99\u6cc9\u5e02"
    ],
    "name:zho_x_preferred":[
        "\u9f99\u6cc9"
    ],
    "name:zho_x_variant":[
        "\u9f99\u6cc9\u5e02"
    ],
    "wof:name":"Longquan",
    "wof:placetype":"locality"
},
  "geometry": {"coordinates":[124.97020999999999,49.40675],"type":"Point"}
}