{
  "type": "Feature",
  "properties": {
    "gn:admin1_code":"4.0",
    "gn:asciiname":"Xijiazhuang",
    "gn:country_code":"CN",
    "gn:dem":3,
    "gn:feature_class":"P",
    "gn:feature_code":"PPL",
    "gn:name":"Xijiazhuang",
    "gn:population":0,
    "gn:timezone":"Asia/Shanghai",
    "iso:country":"CN",
    "name:zho_x_preferred":[
        "\u595a\u5bb6\u5e84"
    ],
    "wof:name":"Xijiazhuang",
    "wof:placetype":"locality"
},
  "geometry": {"coordinates":[121.048,32.3384],"type":"Point"}
}