{
  "type": "Feature",
  "properties": {
    "gn:admin1_code":"30.0",
    "gn:asciiname":"Goumeicun",
    "gn:country_code":"CN",
    "gn:dem":6,
    "gn:feature_class":"P",
    "gn:feature_code":"PPL",
    "gn:name":"Goumeicun",
    "gn:population":0,
    "gn:timezone":"Asia/Shanghai",
    "iso:country":"CN",
    "name:zho_x_preferred":[
        "\u6c9f\u7f8e\u6751"
    ],
    "wof:name":"Goumeicun",
    "wof:placetype":"locality"
},
  "geometry": {"coordinates":[116.28999,23.54643],"type":"Point"}
}