{
  "type": "Feature",
  "properties": {
    "gn:admin1_code":"11.0",
    "gn:asciiname":"Shanghuangjia",
    "gn:country_code":"CN",
    "gn:dem":400,
    "gn:feature_class":"P",
    "gn:feature_code":"PPL",
    "gn:name":"Shanghuangjia",
    "gn:population":0,
    "gn:timezone":"Asia/Shanghai",
    "iso:country":"CN",
    "name:zho_x_preferred":[
        "\u4e0a\u9ec4\u5bb6"
    ],
    "wof:name":"Shanghuangjia",
    "wof:placetype":"locality"
},
  "geometry": {"coordinates":[113.39277,25.68449],"type":"Point"}
}