{
  "type": "Feature",
  "properties": {
    "gn:admin1_code":"12.0",
    "gn:asciiname":"Dajinzhuang",
    "gn:country_code":"CN",
    "gn:dem":224,
    "gn:feature_class":"P",
    "gn:feature_code":"PPL",
    "gn:name":"Dajinzhuang",
    "gn:population":0,
    "gn:timezone":"Asia/Shanghai",
    "iso:country":"CN",
    "name:zho_x_preferred":[
        "\u5927\u91d1\u5e84"
    ],
    "wof:name":"Dajinzhuang",
    "wof:placetype":"locality"
},
  "geometry": {"coordinates":[113.00433,32.35529],"type":"Point"}
}