{
  "type": "Feature",
  "properties": {
    "gn:admin1_code":"19",
    "gn:asciiname":"Yingchang",
    "gn:country_code":"CN",
    "gn:dem":332,
    "gn:feature_class":"P",
    "gn:feature_code":"PPL",
    "gn:name":"Yingchang",
    "gn:population":0,
    "gn:timezone":"Asia/Shanghai",
    "iso:country":"CN",
    "name:ces_x_preferred":[
        "Jing-\u010dchang"
    ],
    "name:fra_x_preferred":[
        "Yingchang"
    ],
    "name:mon_x_preferred":[
        "\u0418\u043d\u0447\u0430\u043d"
    ],
    "name:zho_x_preferred":[
        "\u61c9\u660c\u57ce"
    ],
    "wof:name":"Yingchang",
    "wof:placetype":"locality"
},
  "geometry": {"coordinates":[124.93333,42.41667],"type":"Point"}
}