{
  "type": "Feature",
  "properties": {
    "gn:admin1_code":"14.0",
    "gn:asciiname":"Ri'a'ejiao",
    "gn:country_code":"CN",
    "gn:dem":3963,
    "gn:feature_class":"P",
    "gn:feature_code":"PPL",
    "gn:name":"Ri\u2019a\u2019ejiao",
    "gn:population":0,
    "gn:timezone":"Asia/Urumqi",
    "iso:country":"CN",
    "name:und_x_variant":[
        "Ri\u2019a\u2019ejiao"
    ],
    "name:zho_x_preferred":[
        "\u65e5\u554a\u4fc4\u89d2"
    ],
    "wof:name":"Ri'a'ejiao",
    "wof:placetype":"locality"
},
  "geometry": {"coordinates":[97.46013000000001,32.0676],"type":"Point"}
}