{
  "type": "Feature",
  "properties": {
    "gn:admin1_code":"24.0",
    "gn:asciiname":"Yushuzhang",
    "gn:country_code":"CN",
    "gn:dem":1674,
    "gn:feature_class":"P",
    "gn:feature_code":"PPL",
    "gn:name":"Yushuzhang",
    "gn:population":0,
    "gn:timezone":"Asia/Shanghai",
    "iso:country":"CN",
    "name:zho_x_preferred":[
        "\u6986\u6811\u638c"
    ],
    "wof:name":"Yushuzhang",
    "wof:placetype":"locality"
},
  "geometry": {"coordinates":[111.57344000000001,38.0567],"type":"Point"}
}