{
  "type": "Feature",
  "properties": {
    "gn:admin1_code":"5.0",
    "gn:asciiname":"Bao'antun",
    "gn:country_code":"CN",
    "gn:dem":160,
    "gn:feature_class":"P",
    "gn:feature_code":"PPL",
    "gn:name":"Bao\u2019antun",
    "gn:population":0,
    "gn:timezone":"Asia/Shanghai",
    "iso:country":"CN",
    "name:und_x_variant":[
        "Bao\u2019antun"
    ],
    "name:zho_x_preferred":[
        "\u4fdd\u5b89\u5c6f"
    ],
    "wof:name":"Bao'antun",
    "wof:placetype":"locality"
},
  "geometry": {"coordinates":[122.56796,45.49693],"type":"Point"}
}