{
  "type": "Feature",
  "properties": {
    "gn:admin1_code":"21.0",
    "gn:asciiname":"Jiugeyao",
    "gn:country_code":"CN",
    "gn:dem":1541,
    "gn:feature_class":"P",
    "gn:feature_code":"PPL",
    "gn:name":"Jiugeyao",
    "gn:population":0,
    "gn:timezone":"Asia/Shanghai",
    "iso:country":"CN",
    "name:zho_x_preferred":[
        "\u4e5d\u4e2a\u7a91"
    ],
    "wof:name":"Jiugeyao",
    "wof:placetype":"locality"
},
  "geometry": {"coordinates":[106.00700000000001,37.8057],"type":"Point"}
}