{
  "type": "Feature",
  "properties": {
    "gn:admin1_code":"33.0",
    "gn:asciiname":"Wenhui",
    "gn:country_code":"CN",
    "gn:dem":422,
    "gn:feature_class":"P",
    "gn:feature_code":"PPL",
    "gn:name":"Wenhui",
    "gn:population":0,
    "gn:timezone":"Asia/Shanghai",
    "iso:country":"CN",
    "name:zho_x_preferred":[
        "\u6587\u6c47"
    ],
    "wof:name":"Wenhui",
    "wof:placetype":"locality"
},
  "geometry": {"coordinates":[107.63370999999999,29.96203],"type":"Point"}
}