{
  "type": "Feature",
  "properties": {
    "gn:admin1_code":"26.0",
    "gn:asciiname":"Zhujia Goukou",
    "gn:country_code":"CN",
    "gn:dem":983,
    "gn:feature_class":"P",
    "gn:feature_code":"PPL",
    "gn:name":"Zhujia Goukou",
    "gn:population":0,
    "gn:timezone":"Asia/Shanghai",
    "iso:country":"CN",
    "name:zho_x_preferred":[
        "\u6731\u5bb6\u6c9f\u53e3"
    ],
    "wof:name":"Zhujia Goukou",
    "wof:placetype":"locality"
},
  "geometry": {"coordinates":[110.14484,34.07799],"type":"Point"}
}