{
  "type": "Feature",
  "properties": {
    "gn:admin1_code":"22.0",
    "gn:asciiname":"Dongliyuan",
    "gn:country_code":"CN",
    "gn:dem":36,
    "gn:feature_class":"P",
    "gn:feature_code":"PPL",
    "gn:name":"Dongliyuan",
    "gn:population":0,
    "gn:timezone":"Asia/Shanghai",
    "iso:country":"CN",
    "name:zho_x_preferred":[
        "\u4e1c\u68a8\u56ed"
    ],
    "wof:name":"Dongliyuan",
    "wof:placetype":"locality"
},
  "geometry": {"coordinates":[116.35493,39.58899],"type":"Point"}
}