{
  "type": "Feature",
  "properties": {
    "gn:admin1_code":"19",
    "gn:asciiname":"Nuanhezi",
    "gn:country_code":"CN",
    "gn:dem":516,
    "gn:feature_class":"P",
    "gn:feature_code":"PPL",
    "gn:name":"Nuanhezi",
    "gn:population":0,
    "gn:timezone":"Asia/Shanghai",
    "iso:country":"CN",
    "name:und_x_variant":[
        "\u6696\u6cb3\u5b50"
    ],
    "wof:name":"Nuanhezi",
    "wof:placetype":"locality"
},
  "geometry": {"coordinates":[124.94755000000001,41.32312],"type":"Point"}
}