{
  "type": "Feature",
  "properties": {
    "gn:admin1_code":"15.0",
    "gn:asciiname":"Gouhe",
    "gn:country_code":"CN",
    "gn:dem":2233,
    "gn:feature_class":"P",
    "gn:feature_code":"PPL",
    "gn:name":"Gouhe",
    "gn:population":0,
    "gn:timezone":"Asia/Shanghai",
    "iso:country":"CN",
    "name:zho_x_preferred":[
        "\u82df\u6cb3"
    ],
    "wof:name":"Gouhe",
    "wof:placetype":"locality"
},
  "geometry": {"coordinates":[105.221,34.4908],"type":"Point"}
}