{
  "type": "Feature",
  "properties": {
    "gn:admin1_code":"12.0",
    "gn:asciiname":"Lianfeng",
    "gn:country_code":"CN",
    "gn:dem":750,
    "gn:feature_class":"P",
    "gn:feature_code":"PPL",
    "gn:name":"Lianfeng",
    "gn:population":0,
    "gn:timezone":"Asia/Shanghai",
    "iso:country":"CN",
    "name:zho_x_preferred":[
        "\u8054\u4e30"
    ],
    "wof:name":"Lianfeng",
    "wof:placetype":"locality"
},
  "geometry": {"coordinates":[109.00870999999999,30.05978],"type":"Point"}
}