{
  "type": "Feature",
  "properties": {
    "gn:admin1_code":"2.0",
    "gn:asciiname":"Xiashanmen",
    "gn:country_code":"CN",
    "gn:dem":123,
    "gn:feature_class":"P",
    "gn:feature_code":"PPL",
    "gn:name":"Xiashanmen",
    "gn:population":0,
    "gn:timezone":"Asia/Shanghai",
    "iso:country":"CN",
    "name:zho_x_preferred":[
        "\u4e0b\u5c71\u95e8"
    ],
    "wof:name":"Xiashanmen",
    "wof:placetype":"locality"
},
  "geometry": {"coordinates":[120.00539999999999,28.8346],"type":"Point"}
}