{
  "type": "Feature",
  "properties": {
    "gn:admin1_code":"3.0",
    "gn:asciiname":"Dawu Xiajia",
    "gn:country_code":"CN",
    "gn:dem":27,
    "gn:feature_class":"P",
    "gn:feature_code":"PPL",
    "gn:name":"Dawu Xiajia",
    "gn:population":0,
    "gn:timezone":"Asia/Shanghai",
    "iso:country":"CN",
    "name:und_x_variant":[
        "\u5927\u5c4b\u590f\u5bb6"
    ],
    "wof:name":"Dawu Xiajia",
    "wof:placetype":"locality"
},
  "geometry": {"coordinates":[115.52733000000001,29.76932],"type":"Point"}
}