{
  "type": "Feature",
  "properties": {
    "gn:admin1_code":"6.0",
    "gn:asciiname":"Mominlong",
    "gn:country_code":"CN",
    "gn:dem":4250,
    "gn:feature_class":"P",
    "gn:feature_code":"PPL",
    "gn:name":"Mominlong",
    "gn:population":0,
    "gn:timezone":"Asia/Urumqi",
    "iso:country":"CN",
    "name:zho_x_preferred":[
        "\u83ab\u654f\u9647"
    ],
    "wof:name":"Mominlong",
    "wof:placetype":"locality"
},
  "geometry": {"coordinates":[97.28972,32.79912],"type":"Point"}
}