{
  "type": "Feature",
  "properties": {
    "gn:admin1_code":"10.0",
    "gn:asciiname":"Tuling",
    "gn:country_code":"CN",
    "gn:dem":246,
    "gn:feature_class":"P",
    "gn:feature_code":"PPL",
    "gn:name":"Tuling",
    "gn:population":0,
    "gn:timezone":"Asia/Shanghai",
    "iso:country":"CN",
    "name:und_x_variant":[
        "\u571f\u5cad"
    ],
    "name:zho_x_preferred":[
        "\u6d82\u5cad\u9547"
    ],
    "wof:name":"Tuling",
    "wof:placetype":"locality"
},
  "geometry": {"coordinates":[114.53824,38.7999],"type":"Point"}
}