{
  "type": "Feature",
  "properties": {
    "gn:admin1_code":"15.0",
    "gn:asciiname":"Gegu",
    "gn:country_code":"CN",
    "gn:dem":2836,
    "gn:feature_class":"P",
    "gn:feature_code":"PPL",
    "gn:name":"Gegu",
    "gn:population":0,
    "gn:timezone":"Asia/Shanghai",
    "iso:country":"CN",
    "name:und_x_variant":[
        "\u683c\u53e4"
    ],
    "wof:name":"Gegu",
    "wof:placetype":"locality"
},
  "geometry": {"coordinates":[103.33944,34.47357],"type":"Point"}
}