{
  "type": "Feature",
  "properties": {
    "gn:admin1_code":"32.0",
    "gn:asciiname":"Heiniantanggou",
    "gn:country_code":"CN",
    "gn:dem":339,
    "gn:feature_class":"P",
    "gn:feature_code":"PPL",
    "gn:name":"Heiniantanggou",
    "gn:population":0,
    "gn:timezone":"Asia/Shanghai",
    "iso:country":"CN",
    "name:zho_x_preferred":[
        "\u9ed1\u57dd\u5510\u6c9f"
    ],
    "wof:name":"Heiniantanggou",
    "wof:placetype":"locality"
},
  "geometry": {"coordinates":[105.20650000000001,30.3028],"type":"Point"}
}