{
  "type": "Feature",
  "properties": {
    "gn:admin1_code":"02",
    "gn:asciiname":"Chaoyangcun",
    "gn:country_code":"CN",
    "gn:dem":191,
    "gn:feature_class":"P",
    "gn:feature_code":"PPL",
    "gn:name":"Chaoyangcun",
    "gn:population":0,
    "gn:timezone":"Asia/Shanghai",
    "iso:country":"CN",
    "name:und_x_variant":[
        "Chao-yang-tun",
        "Chaoyang",
        "Chaoyangcun"
    ],
    "name:zho_x_preferred":[
        "\u671d\u9633"
    ],
    "name:zho_x_variant":[
        "\u671d\u9633\u6751"
    ],
    "wof:name":"Chaoyangcun",
    "wof:placetype":"locality"
},
  "geometry": {"coordinates":[121.20618,28.08243],"type":"Point"}
}