{
  "type": "Feature",
  "properties": {
    "gn:admin1_code":"11",
    "gn:asciiname":"Shenkou",
    "gn:country_code":"CN",
    "gn:dem":260,
    "gn:feature_class":"P",
    "gn:feature_code":"PPL",
    "gn:name":"Shenkou",
    "gn:population":0,
    "gn:timezone":"Asia/Shanghai",
    "iso:country":"CN",
    "name:zho_x_preferred":[
        "\u795e\u53e3"
    ],
    "wof:name":"Shenkou",
    "wof:placetype":"locality"
},
  "geometry": {"coordinates":[111.23538000000001,25.19943],"type":"Point"}
}