{
  "type": "Feature",
  "properties": {
    "gn:admin1_code":"30.0",
    "gn:asciiname":"Lishui",
    "gn:country_code":"CN",
    "gn:dem":4,
    "gn:feature_class":"P",
    "gn:feature_code":"PPL",
    "gn:name":"Lishui",
    "gn:population":0,
    "gn:timezone":"Asia/Shanghai",
    "iso:country":"CN",
    "name:afr_x_preferred":[
        "Lishui"
    ],
    "name:ara_x_preferred":[
        "\u0644\u064a\u0634\u0648\u064a"
    ],
    "name:cat_x_preferred":[
        "Lishui"
    ],
    "name:cdo_x_preferred":[
        "L\u00e2\u0324-c\u016bi"
    ],
    "name:ceb_x_preferred":[
        "Lishui"
    ],
    "name:ces_x_preferred":[
        "Li-\u0161uej"
    ],
    "name:dan_x_preferred":[
        "Lishui"
    ],
    "name:deu_x_preferred":[
        "Lishui"
    ],
    "name:est_x_preferred":[
        "Lishui Shi"
    ],
    "name:eus_x_preferred":[
        "Lishui"
    ],
    "name:fas_x_preferred":[
        "\u0644\u06cc\u0634\u0627\u06cc"
    ],
    "name:fin_x_preferred":[
        "Lishui"
    ],
    "name:fra_x_preferred":[
        "Lishui"
    ],
    "name:ita_x_preferred":[
        "Lishui"
    ],
    "name:jpn_x_preferred":[
        "\u9e97\u6c34\u5e02"
    ],
    "name:kaz_x_preferred":[
        "\u041b\u0438\u0448\u0443\u0439"
    ],
    "name:kik_x_preferred":[
        "Lishui"
    ],
    "name:kor_x_preferred":[
        "\ub9ac\uc218\uc774\uc2dc"
    ],
    "name:mlg_x_preferred":[
        "Lishui"
    ],
    "name:nld_x_preferred":[
        "Lishui"
    ],
    "name:nor_x_preferred":[
        "Lishui"
    ],
    "name:pol_x_preferred":[
        "Lishui"
    ],
    "name:por_x_preferred":[
        "Lishui"
    ],
    "name:rus_x_preferred":[
        "\u041b\u0438\u0448\u0443\u0439"
    ],
    "name:spa_x_preferred":[
        "Lishui"
    ],
    "name:swe_x_preferred":[
        "Lishui"
    ],
    "name:tgl_x_preferred":[
        "Lishui"
    ],
    "name:tur_x_preferred":[
        "Lishui"
    ],
    "name:urd_x_preferred":[
        "\u0644\u06cc\u0634\u0648\u0626\u06cc"
    ],
    "name:vie_x_preferred":[
        "L\u1ec7 Th\u1ee7y"
    ],
    "name:war_x_preferred":[
        "Lishui"
    ],
    "name:wuu_x_preferred":[
        "\u9e97\u6c34\u5e02"
    ],
    "name:zho_x_preferred":[
        "\u9e97\u6c34"
    ],
    "name:zho_x_variant":[
        "\u4e3d\u6c34\u5e02"
    ],
    "wof:name":"Lishui",
    "wof:placetype":"locality"
},
  "geometry": {"coordinates":[112.91674,22.84923],"type":"Point"}
}