{
  "type": "Feature",
  "properties": {
    "gn:admin1_code":"19.0",
    "gn:asciiname":"Hengdaohezi",
    "gn:country_code":"CN",
    "gn:dem":512,
    "gn:feature_class":"P",
    "gn:feature_code":"PPL",
    "gn:name":"Hengdaohezi",
    "gn:population":0,
    "gn:timezone":"Asia/Shanghai",
    "iso:country":"CN",
    "name:und_x_variant":[
        "\u6a2a\u9053\u6cb3\u5b50"
    ],
    "name:zho_x_preferred":[
        "\u6a2a\u9053\u6cb3\u5b50"
    ],
    "wof:name":"Hengdaohezi",
    "wof:placetype":"locality"
},
  "geometry": {"coordinates":[124.87652,41.26621],"type":"Point"}
}