{
  "type": "Feature",
  "properties": {
    "gn:admin1_code":"30.0",
    "gn:asciiname":"Shanghuanglongcun",
    "gn:country_code":"CN",
    "gn:dem":8,
    "gn:feature_class":"P",
    "gn:feature_code":"PPL",
    "gn:name":"Shanghuanglongcun",
    "gn:population":0,
    "gn:timezone":"Asia/Shanghai",
    "iso:country":"CN",
    "name:zho_x_preferred":[
        "\u4e0a\u9ec4\u9686\u6751"
    ],
    "wof:name":"Shanghuanglongcun",
    "wof:placetype":"locality"
},
  "geometry": {"coordinates":[116.90176,23.62865],"type":"Point"}
}