{
  "type": "Feature",
  "properties": {
    "gn:admin1_code":"12.0",
    "gn:asciiname":"Yangchuantou",
    "gn:country_code":"CN",
    "gn:dem":26,
    "gn:feature_class":"P",
    "gn:feature_code":"PPL",
    "gn:name":"Yangchuantou",
    "gn:population":0,
    "gn:timezone":"Asia/Shanghai",
    "iso:country":"CN",
    "name:zho_x_preferred":[
        "\u6d0b\u8239\u5934"
    ],
    "wof:name":"Yangchuantou",
    "wof:placetype":"locality"
},
  "geometry": {"coordinates":[113.83958,30.71343],"type":"Point"}
}