{
  "type": "Feature",
  "properties": {
    "gn:admin1_code":"9",
    "gn:asciiname":"Juling",
    "gn:country_code":"CN",
    "gn:dem":64,
    "gn:feature_class":"P",
    "gn:feature_code":"PPLA4",
    "gn:name":"Juling",
    "gn:population":0,
    "gn:timezone":"Asia/Shanghai",
    "iso:country":"CN",
    "name:und_x_variant":[
        "\u5de8\u9675",
        "Juling Zhen",
        "\u5de8\u9675\u9547"
    ],
    "wof:name":"Juling",
    "wof:placetype":"locality"
},
  "geometry": {"coordinates":[113.96004000000001,33.8622],"type":"Point"}
}