{
  "type": "Feature",
  "properties": {
    "gn:admin1_code":"32.0",
    "gn:asciiname":"Yechengcong",
    "gn:country_code":"CN",
    "gn:dem":3823,
    "gn:feature_class":"P",
    "gn:feature_code":"PPL",
    "gn:name":"Yechengcong",
    "gn:population":0,
    "gn:timezone":"Asia/Shanghai",
    "iso:country":"CN",
    "name:zho_x_preferred":[
        "\u91ce\u57ce\u4ece"
    ],
    "wof:name":"Yechengcong",
    "wof:placetype":"locality"
},
  "geometry": {"coordinates":[98.45629,31.89259],"type":"Point"}
}