{
  "type": "Feature",
  "properties": {
    "gn:admin1_code":"24.0",
    "gn:asciiname":"Xincunzi",
    "gn:country_code":"CN",
    "gn:dem":1468,
    "gn:feature_class":"P",
    "gn:feature_code":"PPL",
    "gn:name":"Xincunzi",
    "gn:population":0,
    "gn:timezone":"Asia/Shanghai",
    "iso:country":"CN",
    "name:zho_x_preferred":[
        "\u8f9b\u6751\u5b50"
    ],
    "wof:name":"Xincunzi",
    "wof:placetype":"locality"
},
  "geometry": {"coordinates":[112.25163000000001,40.08349000000001],"type":"Point"}
}