{
  "type": "Feature",
  "properties": {
    "gn:admin1_code":"5.0",
    "gn:asciiname":"Xisanpenhe",
    "gn:country_code":"CN",
    "gn:dem":185,
    "gn:feature_class":"P",
    "gn:feature_code":"PPL",
    "gn:name":"Xisanpenhe",
    "gn:population":0,
    "gn:timezone":"Asia/Shanghai",
    "iso:country":"CN",
    "name:zho_x_preferred":[
        "\u897f\u4e09\u76c6\u6cb3"
    ],
    "wof:name":"Xisanpenhe",
    "wof:placetype":"locality"
},
  "geometry": {"coordinates":[126.31053,44.34416],"type":"Point"}
}