{
  "type": "Feature",
  "properties": {
    "gn:admin1_code":"9.0",
    "gn:asciiname":"Qilibei",
    "gn:country_code":"CN",
    "gn:dem":62,
    "gn:feature_class":"P",
    "gn:feature_code":"PPL",
    "gn:name":"Qilibei",
    "gn:population":0,
    "gn:timezone":"Asia/Shanghai",
    "iso:country":"CN",
    "name:und_x_variant":[
        "\u4e03\u91cc\u5317"
    ],
    "name:zho_x_preferred":[
        "\u4e03\u91cc\u5317"
    ],
    "wof:name":"Qilibei",
    "wof:placetype":"locality"
},
  "geometry": {"coordinates":[113.93304000000001,33.84129],"type":"Point"}
}