{
  "type": "Feature",
  "properties": {
    "gn:admin1_code":"30.0",
    "gn:asciiname":"Yaocuoweicun",
    "gn:country_code":"CN",
    "gn:dem":7,
    "gn:feature_class":"P",
    "gn:feature_code":"PPL",
    "gn:name":"Yaocuoweicun",
    "gn:population":0,
    "gn:timezone":"Asia/Shanghai",
    "iso:country":"CN",
    "name:zho_x_preferred":[
        "\u59da\u539d\u56f4\u6751"
    ],
    "wof:name":"Yaocuoweicun",
    "wof:placetype":"locality"
},
  "geometry": {"coordinates":[116.34074,23.36171],"type":"Point"}
}