{
  "type": "Feature",
  "properties": {
    "gn:admin1_code":"30.0",
    "gn:asciiname":"Zhoulei",
    "gn:country_code":"CN",
    "gn:dem":585,
    "gn:feature_class":"P",
    "gn:feature_code":"PPL",
    "gn:name":"Zhoulei",
    "gn:population":0,
    "gn:timezone":"Asia/Shanghai",
    "iso:country":"CN",
    "name:zho_x_preferred":[
        "Zhoulei"
    ],
    "name:zho_x_variant":[
        "\u5468\u96f7"
    ],
    "wof:name":"Zhoulei",
    "wof:placetype":"locality"
},
  "geometry": {"coordinates":[113.09806,25.14611],"type":"Point"}
}