{
  "type": "Feature",
  "properties": {
    "gn:admin1_code":"26.0",
    "gn:asciiname":"Yuandun",
    "gn:country_code":"CN",
    "gn:dem":742,
    "gn:feature_class":"P",
    "gn:feature_code":"PPLA4",
    "gn:name":"Yuandun",
    "gn:population":0,
    "gn:timezone":"Asia/Shanghai",
    "iso:country":"CN",
    "name:und_x_variant":[
        "Chiu-tun-tzu",
        "Y\u00fcan-tun-tzu",
        "Yuandunzi",
        "Y\u00fcan-tun",
        "Yuandun",
        "\u5143\u58a9",
        "Yuandun Zhen",
        "\u5143\u58a9\u9547"
    ],
    "wof:name":"Yuandun",
    "wof:placetype":"locality"
},
  "geometry": {"coordinates":[106.6392,33.02784],"type":"Point"}
}