{
  "type": "Feature",
  "properties": {
    "gn:admin1_code":"32",
    "gn:asciiname":"Lingguan",
    "gn:country_code":"CN",
    "gn:dem":771,
    "gn:feature_class":"P",
    "gn:feature_code":"PPL",
    "gn:name":"Lingguan",
    "gn:population":0,
    "gn:timezone":"Asia/Shanghai",
    "iso:country":"CN",
    "name:zho_x_preferred":[
        "\u7075\u5173"
    ],
    "wof:name":"Lingguan",
    "wof:placetype":"locality"
},
  "geometry": {"coordinates":[102.82899999999999,30.24549],"type":"Point"}
}