{
  "type": "Feature",
  "properties": {
    "gn:admin1_code":"26.0",
    "gn:asciiname":"Nanzhangcun",
    "gn:country_code":"CN",
    "gn:dem":1219,
    "gn:feature_class":"P",
    "gn:feature_code":"PPL",
    "gn:name":"Nanzhangcun",
    "gn:population":0,
    "gn:timezone":"Asia/Shanghai",
    "iso:country":"CN",
    "name:zho_x_preferred":[
        "\u5357\u5f20\u6751"
    ],
    "wof:name":"Nanzhangcun",
    "wof:placetype":"locality"
},
  "geometry": {"coordinates":[108.38873,34.96964000000001],"type":"Point"}
}