{
  "type": "Feature",
  "properties": {
    "gn:admin1_code":"29.0",
    "gn:asciiname":"Xiushuitang",
    "gn:country_code":"CN",
    "gn:dem":2017,
    "gn:feature_class":"P",
    "gn:feature_code":"PPL",
    "gn:name":"Xiushuitang",
    "gn:population":0,
    "gn:timezone":"Asia/Shanghai",
    "iso:country":"CN",
    "name:zho_x_preferred":[
        "\u9508\u6c34\u5858"
    ],
    "wof:name":"Xiushuitang",
    "wof:placetype":"locality"
},
  "geometry": {"coordinates":[100.88500000000001,24.8355],"type":"Point"}
}