{
  "type": "Feature",
  "properties": {
    "gn:admin1_code":"18",
    "gn:asciiname":"Tangfang",
    "gn:country_code":"CN",
    "gn:dem":1872,
    "gn:feature_class":"P",
    "gn:feature_code":"PPL",
    "gn:name":"Tangfang",
    "gn:population":0,
    "gn:timezone":"Asia/Shanghai",
    "iso:country":"CN",
    "name:zho_x_preferred":[
        "\u5510\u623f"
    ],
    "wof:name":"Tangfang",
    "wof:placetype":"locality"
},
  "geometry": {"coordinates":[104.532,27.2151],"type":"Point"}
}