{
  "type": "Feature",
  "properties": {
    "gn:admin1_code":"1.0",
    "gn:asciiname":"Wangmiaocun",
    "gn:country_code":"CN",
    "gn:dem":56,
    "gn:feature_class":"P",
    "gn:feature_code":"PPL",
    "gn:name":"Wangmiaocun",
    "gn:population":0,
    "gn:timezone":"Asia/Shanghai",
    "iso:country":"CN",
    "name:zho_x_preferred":[
        "\u738b\u5e99\u6751"
    ],
    "wof:name":"Wangmiaocun",
    "wof:placetype":"locality"
},
  "geometry": {"coordinates":[117.22302999999999,32.35342],"type":"Point"}
}