{
  "type": "Feature",
  "properties": {
    "gn:admin1_code":"4.0",
    "gn:asciiname":"Yanwacun",
    "gn:country_code":"CN",
    "gn:dem":28,
    "gn:feature_class":"P",
    "gn:feature_code":"PPL",
    "gn:name":"Yanwacun",
    "gn:population":0,
    "gn:timezone":"Asia/Shanghai",
    "iso:country":"CN",
    "name:zho_x_preferred":[
        "\u5830\u6d3c\u6751"
    ],
    "wof:name":"Yanwacun",
    "wof:placetype":"locality"
},
  "geometry": {"coordinates":[118.05267000000001,34.32849],"type":"Point"}
}