{
  "type": "Feature",
  "properties": {
    "gn:admin1_code":"32.0",
    "gn:asciiname":"Yankouyizu",
    "gn:country_code":"CN",
    "gn:dem":2201,
    "gn:feature_class":"P",
    "gn:feature_code":"PPL",
    "gn:name":"Yankouyizu",
    "gn:population":0,
    "gn:timezone":"Asia/Shanghai",
    "iso:country":"CN",
    "name:zho_x_preferred":[
        "\u5ca9\u53e3\u5f5d\u65cf"
    ],
    "wof:name":"Yankouyizu",
    "wof:placetype":"locality"
},
  "geometry": {"coordinates":[101.29849,27.11013],"type":"Point"}
}