{
  "type": "Feature",
  "properties": {
    "gn:admin1_code":"02",
    "gn:asciiname":"Yantouzui",
    "gn:country_code":"CN",
    "gn:dem":123,
    "gn:feature_class":"P",
    "gn:feature_code":"PPL",
    "gn:name":"Yantouzui",
    "gn:population":0,
    "gn:timezone":"Asia/Shanghai",
    "iso:country":"CN",
    "name:zho_x_preferred":[
        "\u5ca9\u5934\u5480"
    ],
    "wof:name":"Yantouzui",
    "wof:placetype":"locality"
},
  "geometry": {"coordinates":[120.29268,27.75111],"type":"Point"}
}