{
  "type": "Feature",
  "properties": {
    "gn:admin1_code":"29.0",
    "gn:asciiname":"Gaojiacun",
    "gn:country_code":"CN",
    "gn:dem":2159,
    "gn:feature_class":"P",
    "gn:feature_code":"PPL",
    "gn:name":"Gaojiacun",
    "gn:population":0,
    "gn:timezone":"Asia/Shanghai",
    "iso:country":"CN",
    "name:zho_x_preferred":[
        "\u9ad8\u5bb6\u6751"
    ],
    "wof:name":"Gaojiacun",
    "wof:placetype":"locality"
},
  "geometry": {"coordinates":[103.423,26.4444],"type":"Point"}
}