{
  "type": "Feature",
  "properties": {
    "gn:admin1_code":"1.0",
    "gn:asciiname":"Yongfeng",
    "gn:country_code":"CN",
    "gn:dem":41,
    "gn:feature_class":"P",
    "gn:feature_code":"PPL",
    "gn:name":"Yongfeng",
    "gn:population":0,
    "gn:timezone":"Asia/Shanghai",
    "iso:country":"CN",
    "name:und_x_variant":[
        "\u6c38\u4e30",
        "Yongfengzhencun",
        "\u6c38\u4e30\u9547\u6751"
    ],
    "wof:name":"Yongfeng",
    "wof:placetype":"locality"
},
  "geometry": {"coordinates":[116.83284999999999,29.72139],"type":"Point"}
}