{
  "type": "Feature",
  "properties": {
    "gn:admin1_code":"11.0",
    "gn:asciiname":"Tiedingzhai",
    "gn:country_code":"CN",
    "gn:dem":218,
    "gn:feature_class":"P",
    "gn:feature_code":"PPL",
    "gn:name":"Tiedingzhai",
    "gn:population":0,
    "gn:timezone":"Asia/Shanghai",
    "iso:country":"CN",
    "name:zho_x_preferred":[
        "\u94c1\u9489\u5be8"
    ],
    "wof:name":"Tiedingzhai",
    "wof:placetype":"locality"
},
  "geometry": {"coordinates":[113.09314999999999,25.93728],"type":"Point"}
}