{
  "type": "Feature",
  "properties": {
    "gn:admin1_code":"16.0",
    "gn:asciiname":"Changhong",
    "gn:country_code":"CN",
    "gn:dem":136,
    "gn:feature_class":"P",
    "gn:feature_code":"PPL",
    "gn:name":"Changhong",
    "gn:population":0,
    "gn:timezone":"Asia/Shanghai",
    "iso:country":"CN",
    "name:fra_x_preferred":[
        "Changhong"
    ],
    "name:ind_x_preferred":[
        "Changhong"
    ],
    "name:ita_x_preferred":[
        "Changhong"
    ],
    "name:rus_x_preferred":[
        "Changhong"
    ],
    "name:zho_x_preferred":[
        "\u957f\u7ea2"
    ],
    "name:zho_x_variant":[
        "\u957f\u8679\u7535\u5668"
    ],
    "wof:name":"Changhong",
    "wof:placetype":"locality"
},
  "geometry": {"coordinates":[109.46599999999999,25.2035],"type":"Point"}
}