{
  "type": "Feature",
  "properties": {
    "gn:admin1_code":"6.0",
    "gn:asciiname":"Suna Gunba",
    "gn:country_code":"CN",
    "gn:dem":3647,
    "gn:feature_class":"P",
    "gn:feature_code":"PPL",
    "gn:name":"Suna Gunba",
    "gn:population":0,
    "gn:timezone":"Asia/Shanghai",
    "iso:country":"CN",
    "name:zho_x_preferred":[
        "\u82cf\u7eb3\u68cd\u5df4"
    ],
    "wof:name":"Suna Gunba",
    "wof:placetype":"locality"
},
  "geometry": {"coordinates":[101.44127,35.01253],"type":"Point"}
}