{
  "type": "Feature",
  "properties": {
    "gn:admin1_code":"3.0",
    "gn:asciiname":"Santiaoling",
    "gn:country_code":"CN",
    "gn:dem":425,
    "gn:feature_class":"P",
    "gn:feature_code":"PPL",
    "gn:name":"Santiaoling",
    "gn:population":0,
    "gn:timezone":"Asia/Shanghai",
    "iso:country":"CN",
    "name:und_x_variant":[
        "\u4e09\u6761\u5cad"
    ],
    "wof:name":"Santiaoling",
    "wof:placetype":"locality"
},
  "geometry": {"coordinates":[114.22973,28.23526],"type":"Point"}
}