{
  "type": "Feature",
  "properties": {
    "gn:admin1_code":"26.0",
    "gn:asciiname":"Dingchacun",
    "gn:country_code":"CN",
    "gn:dem":1349,
    "gn:feature_class":"P",
    "gn:feature_code":"PPL",
    "gn:name":"Dingchacun",
    "gn:population":0,
    "gn:timezone":"Asia/Shanghai",
    "iso:country":"CN",
    "name:zho_x_preferred":[
        "\u4e01\u5c94\u6751"
    ],
    "wof:name":"Dingchacun",
    "wof:placetype":"locality"
},
  "geometry": {"coordinates":[108.61682999999999,36.97907],"type":"Point"}
}