{
  "type": "Feature",
  "properties": {
    "gn:admin1_code":"2.0",
    "gn:asciiname":"Tianlong",
    "gn:country_code":"CN",
    "gn:dem":445,
    "gn:feature_class":"P",
    "gn:feature_code":"PPL",
    "gn:name":"Tianlong",
    "gn:population":0,
    "gn:timezone":"Asia/Shanghai",
    "iso:country":"CN",
    "name:ast_x_preferred":[
        "Tianlong"
    ],
    "name:fra_x_preferred":[
        "Tianlong"
    ],
    "name:msa_x_preferred":[
        "Tianlong"
    ],
    "name:nor_x_preferred":[
        "Tianlong"
    ],
    "name:pol_x_preferred":[
        "Tianlong"
    ],
    "name:spa_x_preferred":[
        "Tianlong"
    ],
    "name:swe_x_preferred":[
        "Tianlong"
    ],
    "name:und_x_variant":[
        "\u7530\u5784"
    ],
    "wof:name":"Tianlong",
    "wof:placetype":"locality"
},
  "geometry": {"coordinates":[119.42231,30.07063],"type":"Point"}
}