{
  "type": "Feature",
  "properties": {
    "gn:admin1_code":"20",
    "gn:asciiname":"Bayan Obo Sum",
    "gn:cc2":"CN",
    "gn:country_code":"CN",
    "gn:dem":1459,
    "gn:feature_class":"P",
    "gn:feature_code":"PPL",
    "gn:name":"Bayan Obo Sum",
    "gn:population":0,
    "gn:timezone":"Asia/Shanghai",
    "iso:country":"CN",
    "name:und_x_variant":[
        "A-ha-o-po",
        "Bayan Obo Sum"
    ],
    "wof:name":"Bayan Obo Sum",
    "wof:placetype":"locality"
},
  "geometry": {"coordinates":[110.12333,41.85806],"type":"Point"}
}