{
  "type": "Feature",
  "properties": {
    "gn:admin1_code":"25.0",
    "gn:asciiname":"Beiluotang",
    "gn:country_code":"CN",
    "gn:dem":96,
    "gn:feature_class":"P",
    "gn:feature_code":"PPL",
    "gn:name":"Beiluotang",
    "gn:population":0,
    "gn:timezone":"Asia/Shanghai",
    "iso:country":"CN",
    "name:zho_x_preferred":[
        "\u5317\u6d1b\u6c64"
    ],
    "wof:name":"Beiluotang",
    "wof:placetype":"locality"
},
  "geometry": {"coordinates":[120.86636,37.46135],"type":"Point"}
}