{
  "type": "Feature",
  "properties": {
    "gn:admin1_code":"26",
    "gn:asciiname":"Xiaoyingcun",
    "gn:country_code":"CN",
    "gn:dem":503,
    "gn:feature_class":"P",
    "gn:feature_code":"PPL",
    "gn:name":"Xiaoyingcun",
    "gn:population":0,
    "gn:timezone":"Asia/Shanghai",
    "iso:country":"CN",
    "name:und_x_variant":[
        "\u5c0f\u5e94\u6751"
    ],
    "name:zho_x_preferred":[
        "\u5c0f\u5e94\u6751"
    ],
    "wof:name":"Xiaoyingcun",
    "wof:placetype":"locality"
},
  "geometry": {"coordinates":[108.58262999999999,34.55271],"type":"Point"}
}