{
  "type": "Feature",
  "properties": {
    "gn:admin1_code":"19.0",
    "gn:asciiname":"Toudaohezi",
    "gn:country_code":"CN",
    "gn:dem":334,
    "gn:feature_class":"P",
    "gn:feature_code":"PPL",
    "gn:name":"Toudaohezi",
    "gn:population":0,
    "gn:timezone":"Asia/Shanghai",
    "iso:country":"CN",
    "name:und_x_variant":[
        "\u5934\u9053\u6cb3\u5b50"
    ],
    "wof:name":"Toudaohezi",
    "wof:placetype":"locality"
},
  "geometry": {"coordinates":[124.15024,41.1964],"type":"Point"}
}