{
  "type": "Feature",
  "properties": {
    "gn:admin1_code":"16.0",
    "gn:asciiname":"Weishan",
    "gn:country_code":"CN",
    "gn:dem":631,
    "gn:feature_class":"P",
    "gn:feature_code":"PPL",
    "gn:name":"Weishan",
    "gn:population":0,
    "gn:timezone":"Asia/Shanghai",
    "iso:country":"CN",
    "name:ceb_x_preferred":[
        "Weishan"
    ],
    "name:deu_x_preferred":[
        "Weishan"
    ],
    "name:fra_x_preferred":[
        "Weishan"
    ],
    "name:nor_x_preferred":[
        "Weishan"
    ],
    "name:swe_x_preferred":[
        "Weishan"
    ],
    "name:zho_x_preferred":[
        "\u6e2d\u5c71"
    ],
    "wof:name":"Weishan",
    "wof:placetype":"locality"
},
  "geometry": {"coordinates":[105.738,24.1493],"type":"Point"}
}