{
  "type": "Feature",
  "properties": {
    "gn:admin1_code":"6.0",
    "gn:asciiname":"Mingre",
    "gn:country_code":"CN",
    "gn:dem":3640,
    "gn:feature_class":"P",
    "gn:feature_code":"PPL",
    "gn:name":"Mingre",
    "gn:population":0,
    "gn:timezone":"Asia/Urumqi",
    "iso:country":"CN",
    "name:zho_x_preferred":[
        "\u660e\u60f9"
    ],
    "wof:name":"Mingre",
    "wof:placetype":"locality"
},
  "geometry": {"coordinates":[97.33660999999999,32.89978],"type":"Point"}
}