{
  "type": "Feature",
  "properties": {
    "gn:admin1_code":"26.0",
    "gn:asciiname":"Nuwangping",
    "gn:country_code":"CN",
    "gn:dem":1043,
    "gn:feature_class":"P",
    "gn:feature_code":"PPL",
    "gn:name":"N\u00fcwangping",
    "gn:population":0,
    "gn:timezone":"Asia/Shanghai",
    "iso:country":"CN",
    "name:und_x_variant":[
        "N\u00fcwangping"
    ],
    "name:zho_x_preferred":[
        "\u5973\u738b\u576a"
    ],
    "wof:name":"Nuwangping",
    "wof:placetype":"locality"
},
  "geometry": {"coordinates":[108.10728,33.32451],"type":"Point"}
}