{
  "type": "Feature",
  "properties": {
    "gn:admin1_code":"23.0",
    "gn:asciiname":"Xuejiazhai",
    "gn:country_code":"CN",
    "gn:dem":3,
    "gn:feature_class":"P",
    "gn:feature_code":"PPL",
    "gn:name":"Xuejiazhai",
    "gn:population":0,
    "gn:timezone":"Asia/Shanghai",
    "iso:country":"CN",
    "name:zho_x_preferred":[
        "Xuejiazhai"
    ],
    "name:zho_x_variant":[
        "\u859b\u5bb6\u5b85"
    ],
    "wof:name":"Xuejiazhai",
    "wof:placetype":"locality"
},
  "geometry": {"coordinates":[121.70796,31.18362],"type":"Point"}
}