{
  "type": "Feature",
  "properties": {
    "gn:admin1_code":"30.0",
    "gn:asciiname":"Daxiangang",
    "gn:country_code":"CN",
    "gn:dem":7,
    "gn:feature_class":"P",
    "gn:feature_code":"PPL",
    "gn:name":"Daxiangang",
    "gn:population":0,
    "gn:timezone":"Asia/Shanghai",
    "iso:country":"CN",
    "name:zho_x_preferred":[
        "\u5927\u4ed9\u5c97"
    ],
    "wof:name":"Daxiangang",
    "wof:placetype":"locality"
},
  "geometry": {"coordinates":[112.87718999999998,23.0437],"type":"Point"}
}