{
  "type": "Feature",
  "properties": {
    "gn:admin1_code":"3",
    "gn:asciiname":"Qingnian Zonghe Kenzhichang",
    "gn:country_code":"CN",
    "gn:dem":80,
    "gn:feature_class":"P",
    "gn:feature_code":"PPLF",
    "gn:name":"Qingnian Zonghe Kenzhichang",
    "gn:population":0,
    "gn:timezone":"Asia/Shanghai",
    "iso:country":"CN",
    "name:und_x_variant":[
        "\u9752\u5e74\u7efc\u5408\u57a6\u6b96\u573a",
        "Qingnianzonghekenzhichang"
    ],
    "name:zho_x_preferred":[
        "Qingnian Zonghe Kenzhichang"
    ],
    "wof:name":"Qingnian Zonghe Kenzhichang",
    "wof:placetype":"locality"
},
  "geometry": {"coordinates":[116.27079000000001,27.67436],"type":"Point"}
}