{
  "type": "Feature",
  "properties": {
    "gn:admin1_code":"16",
    "gn:asciiname":"Wenglie",
    "gn:country_code":"CN",
    "gn:dem":441,
    "gn:feature_class":"P",
    "gn:feature_code":"PPL",
    "gn:name":"Wenglie",
    "gn:population":0,
    "gn:timezone":"Asia/Shanghai",
    "iso:country":"CN",
    "name:zho_x_preferred":[
        "\u7fc1\u5217"
    ],
    "wof:name":"Wenglie",
    "wof:placetype":"locality"
},
  "geometry": {"coordinates":[109.842,25.6772],"type":"Point"}
}