{
  "type": "Feature",
  "properties": {
    "gn:admin1_code":"32.0",
    "gn:asciiname":"Daka",
    "gn:country_code":"CN",
    "gn:dem":2968,
    "gn:feature_class":"P",
    "gn:feature_code":"PPL",
    "gn:name":"Daka",
    "gn:population":0,
    "gn:timezone":"Asia/Shanghai",
    "iso:country":"CN",
    "name:ceb_x_preferred":[
        "Daka"
    ],
    "name:deu_x_preferred":[
        "Daka"
    ],
    "name:kor_x_preferred":[
        "\ub2e4\uce74"
    ],
    "name:pol_x_preferred":[
        "Daka"
    ],
    "name:swe_x_preferred":[
        "Daka"
    ],
    "name:zho_x_preferred":[
        "\u6253\u5361"
    ],
    "wof:name":"Daka",
    "wof:placetype":"locality"
},
  "geometry": {"coordinates":[100.89400000000001,28.5591],"type":"Point"}
}