{
  "type": "Feature",
  "properties": {
    "gn:admin1_code":"16",
    "gn:asciiname":"Qibaokeng",
    "gn:country_code":"CN",
    "gn:dem":643,
    "gn:feature_class":"P",
    "gn:feature_code":"PPL",
    "gn:name":"Qibaokeng",
    "gn:population":0,
    "gn:timezone":"Asia/Shanghai",
    "iso:country":"CN",
    "name:zho_x_preferred":[
        "\u4e03\u5b9d\u5751"
    ],
    "wof:name":"Qibaokeng",
    "wof:placetype":"locality"
},
  "geometry": {"coordinates":[111.325,25.8285],"type":"Point"}
}