{
  "type": "Feature",
  "properties": {
    "gn:admin1_code":"11",
    "gn:asciiname":"Moyanpeng",
    "gn:country_code":"CN",
    "gn:dem":1069,
    "gn:feature_class":"P",
    "gn:feature_code":"PPL",
    "gn:name":"Moyanpeng",
    "gn:population":0,
    "gn:timezone":"Asia/Shanghai",
    "iso:country":"CN",
    "name:und_x_variant":[
        "\u58a8\u70df\u68da",
        "Moyanpeng"
    ],
    "wof:name":"Moyanpeng",
    "wof:placetype":"locality"
},
  "geometry": {"coordinates":[111.93722,25.28778],"type":"Point"}
}