{
  "type": "Feature",
  "properties": {
    "gn:admin1_code":"2.0",
    "gn:asciiname":"Shanglouzhai",
    "gn:country_code":"CN",
    "gn:dem":90,
    "gn:feature_class":"P",
    "gn:feature_code":"PPL",
    "gn:name":"Shanglouzhai",
    "gn:population":0,
    "gn:timezone":"Asia/Shanghai",
    "iso:country":"CN",
    "name:und_x_variant":[
        "\u4e0a\u697c\u5b85",
        "Shanglouzhai"
    ],
    "wof:name":"Shanglouzhai",
    "wof:placetype":"locality"
},
  "geometry": {"coordinates":[119.93333,29.2622],"type":"Point"}
}