{
  "type": "Feature",
  "properties": {
    "gn:admin1_code":"9.0",
    "gn:asciiname":"Zuowa",
    "gn:country_code":"CN",
    "gn:dem":61,
    "gn:feature_class":"P",
    "gn:feature_code":"PPL",
    "gn:name":"Zuowa",
    "gn:population":0,
    "gn:timezone":"Asia/Shanghai",
    "iso:country":"CN",
    "name:zho_x_preferred":[
        "\u5de6\u6d3c"
    ],
    "wof:name":"Zuowa",
    "wof:placetype":"locality"
},
  "geometry": {"coordinates":[114.66558999999999,34.40948],"type":"Point"}
}