{
  "type": "Feature",
  "properties": {
    "gn:admin1_code":"18",
    "gn:asciiname":"Yangliujing",
    "gn:country_code":"CN",
    "gn:dem":1232,
    "gn:feature_class":"P",
    "gn:feature_code":"PPL",
    "gn:name":"Yangliujing",
    "gn:population":0,
    "gn:timezone":"Asia/Shanghai",
    "iso:country":"CN",
    "name:zho_x_preferred":[
        "\u6768\u67f3\u4e95"
    ],
    "wof:name":"Yangliujing",
    "wof:placetype":"locality"
},
  "geometry": {"coordinates":[105.36499999999999,25.7428],"type":"Point"}
}