{
  "type": "Feature",
  "properties": {
    "gn:admin1_code":"3.0",
    "gn:asciiname":"Shiyanling",
    "gn:country_code":"CN",
    "gn:dem":68,
    "gn:feature_class":"P",
    "gn:feature_code":"PPL",
    "gn:name":"Shiyanling",
    "gn:population":0,
    "gn:timezone":"Asia/Shanghai",
    "iso:country":"CN",
    "name:und_x_variant":[
        "\u77f3\u5ca9\u5cad"
    ],
    "wof:name":"Shiyanling",
    "wof:placetype":"locality"
},
  "geometry": {"coordinates":[114.95689,27.19442],"type":"Point"}
}