{
  "type": "Feature",
  "properties": {
    "gn:admin1_code":"19.0",
    "gn:asciiname":"Yugangzicun",
    "gn:country_code":"CN",
    "gn:dem":2,
    "gn:feature_class":"P",
    "gn:feature_code":"PPL",
    "gn:name":"Yugangzicun",
    "gn:population":0,
    "gn:timezone":"Asia/Shanghai",
    "iso:country":"CN",
    "name:zho_x_preferred":[
        "\u4e8e\u5c97\u5b50\u6751"
    ],
    "wof:name":"Yugangzicun",
    "wof:placetype":"locality"
},
  "geometry": {"coordinates":[121.938,41.1079],"type":"Point"}
}