{
  "type": "Feature",
  "properties": {
    "gn:admin1_code":"14.0",
    "gn:asciiname":"Qangma",
    "gn:country_code":"CN",
    "gn:dem":4557,
    "gn:feature_class":"P",
    "gn:feature_code":"PPLF",
    "gn:name":"Qangma",
    "gn:population":0,
    "gn:timezone":"Asia/Urumqi",
    "iso:country":"CN",
    "name:bod_x_preferred":[
        "Qangma"
    ],
    "name:zho_x_preferred":[
        "Qiangma"
    ],
    "name:zho_x_variant":[
        "\u5f3a\u9a6c",
        "Bangqiong",
        "\u90a6\u7a79"
    ],
    "wof:name":"Qangma",
    "wof:placetype":"locality"
},
  "geometry": {"coordinates":[89.40100000000002,31.801],"type":"Point"}
}