{
  "type": "Feature",
  "properties": {
    "gn:admin1_code":"11.0",
    "gn:asciiname":"Yuanzigou",
    "gn:country_code":"CN",
    "gn:dem":535,
    "gn:feature_class":"P",
    "gn:feature_code":"PPL",
    "gn:name":"Yuanzigou",
    "gn:population":0,
    "gn:timezone":"Asia/Shanghai",
    "iso:country":"CN",
    "name:zho_x_preferred":[
        "\u9662\u5b50\u6c9f"
    ],
    "wof:name":"Yuanzigou",
    "wof:placetype":"locality"
},
  "geometry": {"coordinates":[109.35999,29.34904],"type":"Point"}
}