{
  "type": "Feature",
  "properties": {
    "gn:admin1_code":"29.0",
    "gn:asciiname":"Luoguotang",
    "gn:country_code":"CN",
    "gn:dem":2272,
    "gn:feature_class":"P",
    "gn:feature_code":"PPL",
    "gn:name":"Luoguotang",
    "gn:population":0,
    "gn:timezone":"Asia/Shanghai",
    "iso:country":"CN",
    "name:zho_x_preferred":[
        "\u9523\u9505\u5858"
    ],
    "wof:name":"Luoguotang",
    "wof:placetype":"locality"
},
  "geometry": {"coordinates":[101.39,25.4725],"type":"Point"}
}