{
  "type": "Feature",
  "properties": {
    "gn:admin1_code":"25.0",
    "gn:asciiname":"Gongjiacun",
    "gn:country_code":"CN",
    "gn:dem":34,
    "gn:feature_class":"P",
    "gn:feature_code":"PPL",
    "gn:name":"Gongjiacun",
    "gn:population":0,
    "gn:timezone":"Asia/Shanghai",
    "iso:country":"CN",
    "name:zho_x_preferred":[
        "\u5bab\u5bb6\u6751"
    ],
    "wof:name":"Gongjiacun",
    "wof:placetype":"locality"
},
  "geometry": {"coordinates":[121.70873,36.85302],"type":"Point"}
}