{
  "type": "Feature",
  "properties": {
    "gn:admin1_code":"25.0",
    "gn:asciiname":"Xiyucun",
    "gn:country_code":"CN",
    "gn:dem":65,
    "gn:feature_class":"P",
    "gn:feature_code":"PPL",
    "gn:name":"Xiyucun",
    "gn:population":0,
    "gn:timezone":"Asia/Shanghai",
    "iso:country":"CN",
    "name:zho_x_preferred":[
        "\u897f\u4e8e\u6751"
    ],
    "wof:name":"Xiyucun",
    "wof:placetype":"locality"
},
  "geometry": {"coordinates":[117.31468999999998,34.93591],"type":"Point"}
}