{
  "type": "Feature",
  "properties": {
    "gn:admin1_code":"18",
    "gn:asciiname":"Wanxianzhuang",
    "gn:country_code":"CN",
    "gn:dem":773,
    "gn:feature_class":"P",
    "gn:feature_code":"PPL",
    "gn:name":"Wanxianzhuang",
    "gn:population":0,
    "gn:timezone":"Asia/Shanghai",
    "iso:country":"CN",
    "name:zho_x_preferred":[
        "\u4e07\u9669\u5e84"
    ],
    "wof:name":"Wanxianzhuang",
    "wof:placetype":"locality"
},
  "geometry": {"coordinates":[107.149,27.6495],"type":"Point"}
}