{
  "type": "Feature",
  "properties": {
    "gn:admin1_code":"32.0",
    "gn:asciiname":"Leda",
    "gn:country_code":"CN",
    "gn:dem":3822,
    "gn:feature_class":"P",
    "gn:feature_code":"PPL",
    "gn:name":"Leda",
    "gn:population":0,
    "gn:timezone":"Asia/Shanghai",
    "iso:country":"CN",
    "name:als_x_preferred":[
        "Leda"
    ],
    "name:bul_x_preferred":[
        "\u041b\u0435\u0434\u0430"
    ],
    "name:cat_x_preferred":[
        "Leda"
    ],
    "name:ceb_x_preferred":[
        "Leda"
    ],
    "name:ces_x_preferred":[
        "Leda"
    ],
    "name:cym_x_preferred":[
        "Leda"
    ],
    "name:dan_x_preferred":[
        "Leda"
    ],
    "name:deu_x_preferred":[
        "Leda"
    ],
    "name:epo_x_preferred":[
        "Leda"
    ],
    "name:eus_x_preferred":[
        "Leda"
    ],
    "name:fra_x_preferred":[
        "Leda"
    ],
    "name:hrv_x_preferred":[
        "Leda"
    ],
    "name:hun_x_preferred":[
        "L\u00e9da"
    ],
    "name:ita_x_preferred":[
        "Leda"
    ],
    "name:kor_x_preferred":[
        "\ub808\ub2e4"
    ],
    "name:lat_x_preferred":[
        "Leda"
    ],
    "name:lit_x_preferred":[
        "Leda"
    ],
    "name:mkd_x_preferred":[
        "\u041b\u0435\u0434\u0430"
    ],
    "name:nds_x_preferred":[
        "Leda"
    ],
    "name:nld_x_preferred":[
        "Leda"
    ],
    "name:nor_x_preferred":[
        "Leda"
    ],
    "name:pol_x_preferred":[
        "Leda"
    ],
    "name:por_x_preferred":[
        "Leda"
    ],
    "name:ron_x_preferred":[
        "Leda"
    ],
    "name:rus_x_preferred":[
        "\u041b\u0435\u0434\u0430"
    ],
    "name:slk_x_preferred":[
        "Leda"
    ],
    "name:slv_x_preferred":[
        "Leda"
    ],
    "name:spa_x_preferred":[
        "Leda"
    ],
    "name:srp_x_preferred":[
        "\u041b\u0435\u0434\u0430"
    ],
    "name:swe_x_preferred":[
        "Leda"
    ],
    "name:ukr_x_preferred":[
        "\u041b\u0435\u0434\u0430"
    ],
    "name:zho_x_preferred":[
        "\u52d2\u8fbe"
    ],
    "wof:name":"Leda",
    "wof:placetype":"locality"
},
  "geometry": {"coordinates":[98.9931,32.2567],"type":"Point"}
}