{
  "type": "Feature",
  "properties": {
    "gn:admin1_code":"32.0",
    "gn:asciiname":"Leda",
    "gn:country_code":"CN",
    "gn:dem":3822,
    "gn:feature_class":"P",
    "gn:feature_code":"PPL",
    "gn:name":"Leda",
    "gn:population":0,
    "gn:timezone":"Asia/Shanghai",
    "iso:country":"CN",
    "name:zho_x_preferred":[
        "\u52d2\u8fbe"
    ],
    "wof:name":"Leda",
    "wof:placetype":"locality"
},
  "geometry": {"coordinates":[98.9931,32.2567],"type":"Point"}
}