{
  "type": "Feature",
  "properties": {
    "gn:admin1_code":"26",
    "gn:asciiname":"Weiqiang",
    "gn:country_code":"CN",
    "gn:dem":377,
    "gn:feature_class":"P",
    "gn:feature_code":"PPL",
    "gn:name":"Weiqiang",
    "gn:population":0,
    "gn:timezone":"Asia/Shanghai",
    "iso:country":"CN",
    "name:und_x_variant":[
        "\u56f4\u5899",
        "Weiqiang"
    ],
    "wof:name":"Weiqiang",
    "wof:placetype":"locality"
},
  "geometry": {"coordinates":[109.04374,34.38469],"type":"Point"}
}