{
  "type": "Feature",
  "properties": {
    "gn:admin1_code":"9.0",
    "gn:asciiname":"Dengzhuang",
    "gn:country_code":"CN",
    "gn:dem":248,
    "gn:feature_class":"P",
    "gn:feature_code":"PPL",
    "gn:name":"Dengzhuang",
    "gn:population":0,
    "gn:timezone":"Asia/Shanghai",
    "iso:country":"CN",
    "name:zho_x_preferred":[
        "\u9093\u5e84"
    ],
    "wof:name":"Dengzhuang",
    "wof:placetype":"locality"
},
  "geometry": {"coordinates":[113.35854999999999,32.51095],"type":"Point"}
}