{
  "type": "Feature",
  "properties": {
    "gn:admin1_code":"11",
    "gn:asciiname":"Yangshantou",
    "gn:country_code":"CN",
    "gn:dem":504,
    "gn:feature_class":"P",
    "gn:feature_code":"PPL",
    "gn:name":"Yangshantou",
    "gn:population":0,
    "gn:timezone":"Asia/Shanghai",
    "iso:country":"CN",
    "name:zho_x_preferred":[
        "\u6d0b\u5c71\u5934"
    ],
    "wof:name":"Yangshantou",
    "wof:placetype":"locality"
},
  "geometry": {"coordinates":[112.27386,25.43922],"type":"Point"}
}