{
  "type": "Feature",
  "properties": {
    "gn:admin1_code":"2.0",
    "gn:asciiname":"Houshan",
    "gn:country_code":"CN",
    "gn:dem":55,
    "gn:feature_class":"P",
    "gn:feature_code":"PPL",
    "gn:name":"Houshan",
    "gn:population":0,
    "gn:timezone":"Asia/Shanghai",
    "iso:country":"CN",
    "name:und_x_variant":[
        "\u540e\u5c71",
        "Houshan"
    ],
    "wof:name":"Houshan",
    "wof:placetype":"locality"
},
  "geometry": {"coordinates":[119.65434999999999,29.05913],"type":"Point"}
}