{
  "type": "Feature",
  "properties": {
    "gn:admin1_code":"9.0",
    "gn:asciiname":"Xiwusi",
    "gn:country_code":"CN",
    "gn:dem":342,
    "gn:feature_class":"P",
    "gn:feature_code":"PPL",
    "gn:name":"Xiwusi",
    "gn:population":0,
    "gn:timezone":"Asia/Shanghai",
    "iso:country":"CN",
    "name:zho_x_preferred":[
        "\u897f\u4e94\u53f8"
    ],
    "wof:name":"Xiwusi",
    "wof:placetype":"locality"
},
  "geometry": {"coordinates":[113.14633000000001,34.45533],"type":"Point"}
}