{
  "type": "Feature",
  "properties": {
    "gn:admin1_code":"29",
    "gn:asciiname":"Nalang",
    "gn:country_code":"CN",
    "gn:dem":1256,
    "gn:feature_class":"P",
    "gn:feature_code":"PPL",
    "gn:name":"Nalang",
    "gn:population":0,
    "gn:timezone":"Asia/Shanghai",
    "iso:country":"CN",
    "name:zho_x_preferred":[
        "\u90a3\u6994"
    ],
    "wof:name":"Nalang",
    "wof:placetype":"locality"
},
  "geometry": {"coordinates":[104.883,23.6152],"type":"Point"}
}