{
  "type": "Feature",
  "properties": {
    "gn:admin1_code":"14.0",
    "gn:asciiname":"Calecun",
    "gn:country_code":"CN",
    "gn:dem":4357,
    "gn:feature_class":"P",
    "gn:feature_code":"PPL",
    "gn:name":"Calecun",
    "gn:population":0,
    "gn:timezone":"Asia/Urumqi",
    "iso:country":"CN",
    "name:zho_x_preferred":[
        "\u64e6\u52d2\u6751"
    ],
    "wof:name":"Calecun",
    "wof:placetype":"locality"
},
  "geometry": {"coordinates":[92.91482999999999,31.68352],"type":"Point"}
}