{
  "type": "Feature",
  "properties": {
    "gn:admin1_code":"29",
    "gn:asciiname":"Luojiasongyuan",
    "gn:country_code":"CN",
    "gn:dem":1898,
    "gn:feature_class":"P",
    "gn:feature_code":"PPL",
    "gn:name":"Luojiasongyuan",
    "gn:population":0,
    "gn:timezone":"Asia/Shanghai",
    "iso:country":"CN",
    "name:zho_x_preferred":[
        "\u7f57\u5bb6\u677e\u56ed"
    ],
    "wof:name":"Luojiasongyuan",
    "wof:placetype":"locality"
},
  "geometry": {"coordinates":[102.98555,24.64434],"type":"Point"}
}