{
  "type": "Feature",
  "properties": {
    "gn:admin1_code":"32.0",
    "gn:asciiname":"Guazidi",
    "gn:country_code":"CN",
    "gn:dem":589,
    "gn:feature_class":"P",
    "gn:feature_code":"PPL",
    "gn:name":"Guazidi",
    "gn:population":0,
    "gn:timezone":"Asia/Shanghai",
    "iso:country":"CN",
    "name:zho_x_preferred":[
        "\u74dc\u5b50\u5730"
    ],
    "wof:name":"Guazidi",
    "wof:placetype":"locality"
},
  "geometry": {"coordinates":[103.297,27.6474],"type":"Point"}
}