{
  "type": "Feature",
  "properties": {
    "gn:admin1_code":"5.0",
    "gn:asciiname":"Shuangzijing",
    "gn:country_code":"CN",
    "gn:dem":140,
    "gn:feature_class":"P",
    "gn:feature_code":"PPL",
    "gn:name":"Shuangzijing",
    "gn:population":0,
    "gn:timezone":"Asia/Shanghai",
    "iso:country":"CN",
    "name:zho_x_preferred":[
        "\u971c\u5b57\u4e95"
    ],
    "wof:name":"Shuangzijing",
    "wof:placetype":"locality"
},
  "geometry": {"coordinates":[124.08086000000002,45.11743],"type":"Point"}
}