{
  "type": "Feature",
  "properties": {
    "gn:admin1_code":"19.0",
    "gn:asciiname":"Chashangao",
    "gn:country_code":"CN",
    "gn:dem":87,
    "gn:feature_class":"P",
    "gn:feature_code":"PPL",
    "gn:name":"Chashangao",
    "gn:population":0,
    "gn:timezone":"Asia/Shanghai",
    "iso:country":"CN",
    "name:und_x_variant":[
        "\u5c94\u5c71\u7a3f"
    ],
    "name:zho_x_preferred":[
        "\u5c94\u5c71\u7a3f"
    ],
    "wof:name":"Chashangao",
    "wof:placetype":"locality"
},
  "geometry": {"coordinates":[122.7731,42.38473],"type":"Point"}
}