{
  "type": "Feature",
  "properties": {
    "gn:admin1_code":"6.0",
    "gn:asciiname":"Jirenmu",
    "gn:country_code":"CN",
    "gn:dem":3609,
    "gn:feature_class":"P",
    "gn:feature_code":"PPL",
    "gn:name":"Jirenmu",
    "gn:population":0,
    "gn:timezone":"Asia/Shanghai",
    "iso:country":"CN",
    "name:zho_x_preferred":[
        "\u5409\u4ec1\u6728"
    ],
    "wof:name":"Jirenmu",
    "wof:placetype":"locality"
},
  "geometry": {"coordinates":[101.65261,34.60123],"type":"Point"}
}