{
  "type": "Feature",
  "properties": {
    "gn:admin1_code":"1.0",
    "gn:asciiname":"Huajicun",
    "gn:country_code":"CN",
    "gn:dem":44,
    "gn:feature_class":"P",
    "gn:feature_code":"PPL",
    "gn:name":"Huajicun",
    "gn:population":0,
    "gn:timezone":"Asia/Shanghai",
    "iso:country":"CN",
    "name:zho_x_preferred":[
        "\u82b1\u96c6\u6751"
    ],
    "wof:name":"Huajicun",
    "wof:placetype":"locality"
},
  "geometry": {"coordinates":[117.62909000000001,31.75488],"type":"Point"}
}