{
  "type": "Feature",
  "properties": {
    "gn:admin1_code":"30.0",
    "gn:asciiname":"Mingyangcun",
    "gn:country_code":"CN",
    "gn:dem":92,
    "gn:feature_class":"P",
    "gn:feature_code":"PPL",
    "gn:name":"Mingyangcun",
    "gn:population":0,
    "gn:timezone":"Asia/Shanghai",
    "iso:country":"CN",
    "name:zho_x_preferred":[
        "\u540d\u626c\u6751"
    ],
    "wof:name":"Mingyangcun",
    "wof:placetype":"locality"
},
  "geometry": {"coordinates":[116.87148000000001,24.09452000000001],"type":"Point"}
}