{
  "type": "Feature",
  "properties": {
    "gn:admin1_code":"12.0",
    "gn:asciiname":"Hejia'ao",
    "gn:country_code":"CN",
    "gn:dem":114,
    "gn:feature_class":"P",
    "gn:feature_code":"PPL",
    "gn:name":"Hejia\u2019ao",
    "gn:population":0,
    "gn:timezone":"Asia/Shanghai",
    "iso:country":"CN",
    "name:zho_x_preferred":[
        "Hejia\u2019ao"
    ],
    "name:zho_x_variant":[
        "\u4f55\u5bb6\u51f9"
    ],
    "wof:name":"Hejia'ao",
    "wof:placetype":"locality"
},
  "geometry": {"coordinates":[113.46432,31.37774000000001],"type":"Point"}
}