{
  "type": "Feature",
  "properties": {
    "gn:admin1_code":"9.0",
    "gn:asciiname":"Xiaoshuanggou",
    "gn:country_code":"CN",
    "gn:dem":67,
    "gn:feature_class":"P",
    "gn:feature_code":"PPL",
    "gn:name":"Xiaoshuanggou",
    "gn:population":0,
    "gn:timezone":"Asia/Shanghai",
    "iso:country":"CN",
    "name:zho_x_preferred":[
        "\u5c0f\u53cc\u6c9f"
    ],
    "wof:name":"Xiaoshuanggou",
    "wof:placetype":"locality"
},
  "geometry": {"coordinates":[114.41685,34.51381],"type":"Point"}
}