{
  "type": "Feature",
  "properties": {
    "gn:admin1_code":"26.0",
    "gn:asciiname":"Liujiagou",
    "gn:country_code":"CN",
    "gn:dem":560,
    "gn:feature_class":"P",
    "gn:feature_code":"PPL",
    "gn:name":"Liujiagou",
    "gn:population":0,
    "gn:timezone":"Asia/Shanghai",
    "iso:country":"CN",
    "name:und_x_variant":[
        "\u67f3\u5bb6\u6c9f"
    ],
    "wof:name":"Liujiagou",
    "wof:placetype":"locality"
},
  "geometry": {"coordinates":[107.51000000000001,32.99485],"type":"Point"}
}