{
  "type": "Feature",
  "properties": {
    "gn:admin1_code":"14.0",
    "gn:asciiname":"Qogco",
    "gn:country_code":"CN",
    "gn:dem":4452,
    "gn:feature_class":"P",
    "gn:feature_code":"PPLF",
    "gn:name":"Qogco",
    "gn:population":0,
    "gn:timezone":"Asia/Urumqi",
    "iso:country":"CN",
    "name:bod_x_preferred":[
        "Qogco"
    ],
    "name:und_x_variant":[
        "Qucuo"
    ],
    "name:zho_x_preferred":[
        "\u66f2\u9519"
    ],
    "wof:name":"Qogco",
    "wof:placetype":"locality"
},
  "geometry": {"coordinates":[90.52278,28.34088],"type":"Point"}
}