{
  "type": "Feature",
  "properties": {
    "gn:admin1_code":"32.0",
    "gn:asciiname":"Yunfeng",
    "gn:country_code":"CN",
    "gn:dem":336,
    "gn:feature_class":"P",
    "gn:feature_code":"PPL",
    "gn:name":"Yunfeng",
    "gn:population":0,
    "gn:timezone":"Asia/Shanghai",
    "iso:country":"CN",
    "name:zho_x_preferred":[
        "\u4e91\u5cf0"
    ],
    "wof:name":"Yunfeng",
    "wof:placetype":"locality"
},
  "geometry": {"coordinates":[105.34699999999999,29.6308],"type":"Point"}
}