{
  "type": "Feature",
  "properties": {
    "gn:admin1_code":"12.0",
    "gn:asciiname":"Siwutaizi",
    "gn:country_code":"CN",
    "gn:dem":29,
    "gn:feature_class":"P",
    "gn:feature_code":"PPL",
    "gn:name":"Siwutaizi",
    "gn:population":0,
    "gn:timezone":"Asia/Shanghai",
    "iso:country":"CN",
    "name:zho_x_preferred":[
        "\u56db\u5c4b\u53f0\u5b50"
    ],
    "wof:name":"Siwutaizi",
    "wof:placetype":"locality"
},
  "geometry": {"coordinates":[112.67919000000001,29.8704],"type":"Point"}
}