{
  "type": "Feature",
  "properties": {
    "gn:admin1_code":"18",
    "gn:asciiname":"Tiekuangshan",
    "gn:country_code":"CN",
    "gn:dem":2210,
    "gn:feature_class":"P",
    "gn:feature_code":"PPL",
    "gn:name":"Tiekuangshan",
    "gn:population":0,
    "gn:timezone":"Asia/Shanghai",
    "iso:country":"CN",
    "name:zho_x_preferred":[
        "\u94c1\u77ff\u5c71"
    ],
    "wof:name":"Tiekuangshan",
    "wof:placetype":"locality"
},
  "geometry": {"coordinates":[104.664,26.9835],"type":"Point"}
}