{
  "type": "Feature",
  "properties": {
    "gn:admin1_code":"16.0",
    "gn:asciiname":"Gecong",
    "gn:country_code":"CN",
    "gn:dem":607,
    "gn:feature_class":"P",
    "gn:feature_code":"PPL",
    "gn:name":"Gecong",
    "gn:population":0,
    "gn:timezone":"Asia/Shanghai",
    "iso:country":"CN",
    "name:zho_x_preferred":[
        "\u6208\u4ece"
    ],
    "wof:name":"Gecong",
    "wof:placetype":"locality"
},
  "geometry": {"coordinates":[107.61199999999999,24.156],"type":"Point"}
}