{
  "type": "Feature",
  "properties": {
    "gn:admin1_code":"14.0",
    "gn:asciiname":"Qumiba",
    "gn:country_code":"CN",
    "gn:dem":4483,
    "gn:feature_class":"P",
    "gn:feature_code":"PPL",
    "gn:name":"Qumiba",
    "gn:population":0,
    "gn:timezone":"Asia/Urumqi",
    "iso:country":"CN",
    "name:zho_x_preferred":[
        "\u66f2\u5bc6\u5df4"
    ],
    "wof:name":"Qumiba",
    "wof:placetype":"locality"
},
  "geometry": {"coordinates":[86.82550000000001,28.6489],"type":"Point"}
}