{
  "type": "Feature",
  "properties": {
    "gn:admin1_code":"7",
    "gn:asciiname":"Xikeng",
    "gn:country_code":"CN",
    "gn:dem":887,
    "gn:feature_class":"P",
    "gn:feature_code":"PPL",
    "gn:name":"Xikeng",
    "gn:population":0,
    "gn:timezone":"Asia/Shanghai",
    "iso:country":"CN",
    "name:und_x_variant":[
        "\u897f\u5751"
    ],
    "wof:name":"Xikeng",
    "wof:placetype":"locality"
},
  "geometry": {"coordinates":[119.06638999999998,27.13056],"type":"Point"}
}