{
  "type": "Feature",
  "properties": {
    "gn:admin1_code":"11.0",
    "gn:asciiname":"Xiangxincun",
    "gn:country_code":"CN",
    "gn:dem":288,
    "gn:feature_class":"P",
    "gn:feature_code":"PPL",
    "gn:name":"Xiangxincun",
    "gn:population":0,
    "gn:timezone":"Asia/Shanghai",
    "iso:country":"CN",
    "name:zho_x_preferred":[
        "\u5411\u65b0\u6751"
    ],
    "wof:name":"Xiangxincun",
    "wof:placetype":"locality"
},
  "geometry": {"coordinates":[111.80991000000002,24.95645],"type":"Point"}
}