{
  "type": "Feature",
  "properties": {
    "gn:admin1_code":"16.0",
    "gn:asciiname":"Zhai'ao",
    "gn:country_code":"CN",
    "gn:dem":293,
    "gn:feature_class":"P",
    "gn:feature_code":"PPL",
    "gn:name":"Zhai\u2019ao",
    "gn:population":0,
    "gn:timezone":"Asia/Shanghai",
    "iso:country":"CN",
    "name:und_x_variant":[
        "Zhai\u2019ao"
    ],
    "name:zho_x_preferred":[
        "\u5be8\u71ac"
    ],
    "wof:name":"Zhai'ao",
    "wof:placetype":"locality"
},
  "geometry": {"coordinates":[107.798,24.7608],"type":"Point"}
}