{
  "type": "Feature",
  "properties": {
    "gn:admin1_code":"7.0",
    "gn:asciiname":"Yankeng",
    "gn:country_code":"CN",
    "gn:dem":427,
    "gn:feature_class":"P",
    "gn:feature_code":"PPL",
    "gn:name":"Yankeng",
    "gn:population":0,
    "gn:timezone":"Asia/Shanghai",
    "iso:country":"CN",
    "name:zho_x_preferred":[
        "Yankeng"
    ],
    "name:zho_x_variant":[
        "\u71d5\u5751"
    ],
    "wof:name":"Yankeng",
    "wof:placetype":"locality"
},
  "geometry": {"coordinates":[118.65889,26.545],"type":"Point"}
}