{
  "type": "Feature",
  "properties": {
    "gn:admin1_code":"5.0",
    "gn:asciiname":"Chisong",
    "gn:country_code":"CN",
    "gn:dem":527,
    "gn:feature_class":"P",
    "gn:feature_code":"PPLA4",
    "gn:name":"Chisong",
    "gn:population":0,
    "gn:timezone":"Asia/Shanghai",
    "iso:country":"CN",
    "name:und_x_variant":[
        "\u8d64\u677e",
        "Chisong Xiang",
        "\u8d64\u677e\u4e61"
    ],
    "wof:name":"Chisong",
    "wof:placetype":"locality"
},
  "geometry": {"coordinates":[127.00561999999999,42.57996],"type":"Point"}
}