{
  "type": "Feature",
  "properties": {
    "gn:admin1_code":"19.0",
    "gn:asciiname":"Xialouzicun",
    "gn:country_code":"CN",
    "gn:dem":80,
    "gn:feature_class":"P",
    "gn:feature_code":"PPL",
    "gn:name":"Xialouzicun",
    "gn:population":0,
    "gn:timezone":"Asia/Shanghai",
    "iso:country":"CN",
    "name:zho_x_preferred":[
        "\u4e0b\u697c\u5b50\u6751"
    ],
    "wof:name":"Xialouzicun",
    "wof:placetype":"locality"
},
  "geometry": {"coordinates":[123.672,41.7106],"type":"Point"}
}