{
  "type": "Feature",
  "properties": {
    "gn:admin1_code":"4.0",
    "gn:asciiname":"Tianting",
    "gn:country_code":"CN",
    "gn:dem":0,
    "gn:feature_class":"P",
    "gn:feature_code":"PPL",
    "gn:name":"Tianting",
    "gn:population":0,
    "gn:timezone":"Asia/Shanghai",
    "iso:country":"CN",
    "name:zho_x_preferred":[
        "\u5929\u4ead"
    ],
    "wof:name":"Tianting",
    "wof:placetype":"locality"
},
  "geometry": {"coordinates":[119.50311000000001,33.37549],"type":"Point"}
}