{
  "type": "Feature",
  "properties": {
    "gn:admin1_code":"8.0",
    "gn:asciiname":"Yongjincun",
    "gn:country_code":"CN",
    "gn:dem":181,
    "gn:feature_class":"P",
    "gn:feature_code":"PPL",
    "gn:name":"Yongjincun",
    "gn:population":0,
    "gn:timezone":"Asia/Shanghai",
    "iso:country":"CN",
    "name:zho_x_preferred":[
        "\u6c38\u8fdb\u6751"
    ],
    "wof:name":"Yongjincun",
    "wof:placetype":"locality"
},
  "geometry": {"coordinates":[127.35038,46.82892],"type":"Point"}
}