{
  "type": "Feature",
  "properties": {
    "gn:admin1_code":"4.0",
    "gn:asciiname":"Lujicun",
    "gn:country_code":"CN",
    "gn:dem":19,
    "gn:feature_class":"P",
    "gn:feature_code":"PPL",
    "gn:name":"Lujicun",
    "gn:population":0,
    "gn:timezone":"Asia/Shanghai",
    "iso:country":"CN",
    "name:und_x_variant":[
        "Luji",
        "Lujicun"
    ],
    "name:zho_x_preferred":[
        "\u5362\u96c6"
    ],
    "name:zho_x_variant":[
        "\u5362\u96c6\u6751"
    ],
    "wof:name":"Lujicun",
    "wof:placetype":"locality"
},
  "geometry": {"coordinates":[118.42968999999999,33.91229000000001],"type":"Point"}
}