{
  "type": "Feature",
  "properties": {
    "gn:admin1_code":"7.0",
    "gn:asciiname":"Linkeng",
    "gn:country_code":"CN",
    "gn:dem":334,
    "gn:feature_class":"P",
    "gn:feature_code":"PPL",
    "gn:name":"Linkeng",
    "gn:population":0,
    "gn:timezone":"Asia/Shanghai",
    "iso:country":"CN",
    "name:und_x_variant":[
        "\u6797\u5751"
    ],
    "name:zho_x_preferred":[
        "\u6797\u5751"
    ],
    "wof:name":"Linkeng",
    "wof:placetype":"locality"
},
  "geometry": {"coordinates":[118.2655,26.36367000000001],"type":"Point"}
}