{
  "type": "Feature",
  "properties": {
    "gn:admin1_code":"4.0",
    "gn:asciiname":"Xuntangcun",
    "gn:country_code":"CN",
    "gn:dem":7,
    "gn:feature_class":"P",
    "gn:feature_code":"PPL",
    "gn:name":"Xuntangcun",
    "gn:population":0,
    "gn:timezone":"Asia/Shanghai",
    "iso:country":"CN",
    "name:zho_x_preferred":[
        "\u5de1\u5858\u6751"
    ],
    "wof:name":"Xuntangcun",
    "wof:placetype":"locality"
},
  "geometry": {"coordinates":[120.07765000000001,31.74701],"type":"Point"}
}