{
  "type": "Feature",
  "properties": {
    "gn:admin1_code":"15.0",
    "gn:asciiname":"Xiwangjiayuan",
    "gn:country_code":"CN",
    "gn:dem":1428,
    "gn:feature_class":"P",
    "gn:feature_code":"PPL",
    "gn:name":"Xiwangjiayuan",
    "gn:population":0,
    "gn:timezone":"Asia/Shanghai",
    "iso:country":"CN",
    "name:und_x_variant":[
        "\u897f\u738b\u5bb6\u586c"
    ],
    "wof:name":"Xiwangjiayuan",
    "wof:placetype":"locality"
},
  "geometry": {"coordinates":[107.65000000000001,36.023],"type":"Point"}
}