{
  "type": "Feature",
  "properties": {
    "gn:admin1_code":"20",
    "gn:asciiname":"Huret",
    "gn:cc2":"CN",
    "gn:country_code":"CN",
    "gn:dem":1583,
    "gn:feature_class":"P",
    "gn:feature_code":"PPL",
    "gn:name":"Huret",
    "gn:population":0,
    "gn:timezone":"Asia/Shanghai",
    "iso:country":"CN",
    "name:und_x_variant":[
        "K\u2019u-lun-t\u2019u",
        "Huret"
    ],
    "wof:name":"Huret",
    "wof:placetype":"locality"
},
  "geometry": {"coordinates":[111.97806,41.60722],"type":"Point"}
}