{
  "type": "Feature",
  "properties": {
    "gn:admin1_code":"8.0",
    "gn:asciiname":"Shaheyan",
    "gn:country_code":"CN",
    "gn:dem":239,
    "gn:feature_class":"P",
    "gn:feature_code":"PPL",
    "gn:name":"Shaheyan",
    "gn:population":0,
    "gn:timezone":"Asia/Shanghai",
    "iso:country":"CN",
    "name:zho_x_preferred":[
        "\u6c99\u6cb3\u6cbf"
    ],
    "wof:name":"Shaheyan",
    "wof:placetype":"locality"
},
  "geometry": {"coordinates":[125.26202000000001,48.01752000000001],"type":"Point"}
}