{
  "type": "Feature",
  "properties": {
    "gn:admin1_code":"30.0",
    "gn:asciiname":"Fengmukeng",
    "gn:country_code":"CN",
    "gn:dem":209,
    "gn:feature_class":"P",
    "gn:feature_code":"PPL",
    "gn:name":"Fengmukeng",
    "gn:population":0,
    "gn:timezone":"Asia/Shanghai",
    "iso:country":"CN",
    "name:zho_x_preferred":[
        "Fengmukeng"
    ],
    "name:zho_x_variant":[
        "\u67ab\u6728\u5751"
    ],
    "wof:name":"Fengmukeng",
    "wof:placetype":"locality"
},
  "geometry": {"coordinates":[114.8847,24.02392],"type":"Point"}
}