{
  "type": "Feature",
  "properties": {
    "gn:admin1_code":"8.0",
    "gn:asciiname":"Shenjiayao",
    "gn:country_code":"CN",
    "gn:dem":172,
    "gn:feature_class":"P",
    "gn:feature_code":"PPL",
    "gn:name":"Shenjiayao",
    "gn:population":0,
    "gn:timezone":"Asia/Shanghai",
    "iso:country":"CN",
    "name:zho_x_preferred":[
        "\u7533\u5bb6\u7a91"
    ],
    "wof:name":"Shenjiayao",
    "wof:placetype":"locality"
},
  "geometry": {"coordinates":[125.23563,47.39536],"type":"Point"}
}