{
  "type": "Feature",
  "properties": {
    "gn:admin1_code":"18.0",
    "gn:asciiname":"Zaina",
    "gn:country_code":"CN",
    "gn:dem":617,
    "gn:feature_class":"P",
    "gn:feature_code":"PPL",
    "gn:name":"Zaina",
    "gn:population":0,
    "gn:timezone":"Asia/Shanghai",
    "iso:country":"CN",
    "name:deu_x_preferred":[
        "Zaina"
    ],
    "name:fra_x_preferred":[
        "Zaina"
    ],
    "name:zho_x_preferred":[
        "\u5bb0\u90a3"
    ],
    "wof:name":"Zaina",
    "wof:placetype":"locality"
},
  "geometry": {"coordinates":[108.488,25.6223],"type":"Point"}
}