{
  "type": "Feature",
  "properties": {
    "gn:admin1_code":"26.0",
    "gn:asciiname":"Yanggua",
    "gn:country_code":"CN",
    "gn:dem":1195,
    "gn:feature_class":"P",
    "gn:feature_code":"PPL",
    "gn:name":"Yanggua",
    "gn:population":0,
    "gn:timezone":"Asia/Shanghai",
    "iso:country":"CN",
    "name:zho_x_preferred":[
        "\u9633\u576c"
    ],
    "wof:name":"Yanggua",
    "wof:placetype":"locality"
},
  "geometry": {"coordinates":[110.85354,39.23248],"type":"Point"}
}