{
  "type": "Feature",
  "properties": {
    "gn:admin1_code":"9.0",
    "gn:asciiname":"Yiyang Chengguanzhen",
    "gn:country_code":"CN",
    "gn:dem":363,
    "gn:feature_class":"P",
    "gn:feature_code":"PPLA3",
    "gn:name":"Yiyang Chengguanzhen",
    "gn:population":0,
    "gn:timezone":"Asia/Shanghai",
    "iso:country":"CN",
    "name:und_x_variant":[
        "I-yang-hsien",
        "Yiang",
        "I-yang",
        "Yiyang",
        "Yiyang Chengguanzhen"
    ],
    "name:zho_x_preferred":[
        "\u5b9c\u9633\u57ce\u5173\u9547"
    ],
    "wof:name":"Yiyang Chengguanzhen",
    "wof:placetype":"locality"
},
  "geometry": {"coordinates":[112.16222,34.51083],"type":"Point"}
}