{
  "type": "Feature",
  "properties": {
    "gn:admin1_code":"9",
    "gn:asciiname":"Huangzhuang",
    "gn:country_code":"CN",
    "gn:dem":1419,
    "gn:feature_class":"P",
    "gn:feature_code":"PPL",
    "gn:name":"Huangzhuang",
    "gn:population":0,
    "gn:timezone":"Asia/Shanghai",
    "iso:country":"CN",
    "wof:name":"Huangzhuang",
    "wof:placetype":"locality"
},
  "geometry": {"coordinates":[111.49028,34.17194],"type":"Point"}
}