{
  "type": "Feature",
  "properties": {
    "gn:admin1_code":"20",
    "gn:asciiname":"Dongtucheng",
    "gn:country_code":"CN",
    "gn:dem":1567,
    "gn:feature_class":"P",
    "gn:feature_code":"PPLA4",
    "gn:name":"Dongtucheng",
    "gn:population":0,
    "gn:timezone":"Asia/Shanghai",
    "iso:country":"CN",
    "name:und_x_variant":[
        "Tung-t\u2019u-ch\u2019eng-tzu",
        "Dongtucheng Xiang",
        "Dongtucheng",
        "\u4e1c\u571f\u57ce",
        "\u4e1c\u571f\u57ce\u4e61"
    ],
    "wof:name":"Dongtucheng",
    "wof:placetype":"locality"
},
  "geometry": {"coordinates":[111.26076999999999,41.11859000000001],"type":"Point"}
}