{
  "type": "Feature",
  "properties": {
    "gn:admin1_code":"15.0",
    "gn:asciiname":"Zhangjia Hetan",
    "gn:country_code":"CN",
    "gn:dem":957,
    "gn:feature_class":"P",
    "gn:feature_code":"PPL",
    "gn:name":"Zhangjia Hetan",
    "gn:population":0,
    "gn:timezone":"Asia/Shanghai",
    "iso:country":"CN",
    "name:zho_x_preferred":[
        "\u5f20\u5bb6\u6cb3\u6ee9"
    ],
    "wof:name":"Zhangjia Hetan",
    "wof:placetype":"locality"
},
  "geometry": {"coordinates":[107.89400000000001,35.3129],"type":"Point"}
}