{
  "type": "Feature",
  "properties": {
    "gn:admin1_code":"14.0",
    "gn:asciiname":"Gawari",
    "gn:country_code":"CN",
    "gn:dem":4474,
    "gn:feature_class":"P",
    "gn:feature_code":"PPL",
    "gn:name":"Gawari",
    "gn:population":0,
    "gn:timezone":"Asia/Urumqi",
    "iso:country":"CN",
    "name:zho_x_preferred":[
        "\u560e\u74e6\u65e5"
    ],
    "wof:name":"Gawari",
    "wof:placetype":"locality"
},
  "geometry": {"coordinates":[95.51754,31.15275],"type":"Point"}
}