{
  "type": "Feature",
  "properties": {
    "gn:admin1_code":"14.0",
    "gn:asciiname":"Xiabujie",
    "gn:country_code":"CN",
    "gn:dem":4688,
    "gn:feature_class":"P",
    "gn:feature_code":"PPL",
    "gn:name":"Xiabujie",
    "gn:population":0,
    "gn:timezone":"Asia/Urumqi",
    "iso:country":"CN",
    "name:zho_x_preferred":[
        "\u867e\u4e0d\u8282"
    ],
    "wof:name":"Xiabujie",
    "wof:placetype":"locality"
},
  "geometry": {"coordinates":[86.7231,30.7134],"type":"Point"}
}