{
  "type": "Feature",
  "properties": {
    "gn:admin1_code":"30",
    "gn:asciiname":"Gaoqi",
    "gn:country_code":"CN",
    "gn:dem":337,
    "gn:feature_class":"P",
    "gn:feature_code":"PPL",
    "gn:name":"Gaoqi",
    "gn:population":0,
    "gn:timezone":"Asia/Shanghai",
    "iso:country":"CN",
    "name:und_x_variant":[
        "Gaoshe",
        "Gaoqi"
    ],
    "name:zho_x_preferred":[
        "\u9ad8\u78dc"
    ],
    "wof:name":"Gaoqi",
    "wof:placetype":"locality"
},
  "geometry": {"coordinates":[116.40715,24.07885],"type":"Point"}
}