{
  "type": "Feature",
  "properties": {
    "gn:admin1_code":"16",
    "gn:asciiname":"Tanshan",
    "gn:country_code":"CN",
    "gn:dem":366,
    "gn:feature_class":"P",
    "gn:feature_code":"PPL",
    "gn:name":"Tanshan",
    "gn:population":0,
    "gn:timezone":"Asia/Shanghai",
    "iso:country":"CN",
    "name:zho_x_preferred":[
        "\u70ad\u5c71"
    ],
    "wof:name":"Tanshan",
    "wof:placetype":"locality"
},
  "geometry": {"coordinates":[110.45399999999999,24.4297],"type":"Point"}
}