{
  "type": "Feature",
  "properties": {
    "gn:admin1_code":"09",
    "gn:asciiname":"Angao",
    "gn:country_code":"CN",
    "gn:dem":168,
    "gn:feature_class":"P",
    "gn:feature_code":"PPLA4",
    "gn:name":"Angao",
    "gn:population":0,
    "gn:timezone":"Asia/Shanghai",
    "iso:country":"CN",
    "name:und_x_variant":[
        "An-kao",
        "\u5b89\u768b",
        "Angao Zhen",
        "\u5b89\u768b\u9547",
        "Angao"
    ],
    "wof:name":"Angao",
    "wof:placetype":"locality"
},
  "geometry": {"coordinates":[112.38367,33.11602],"type":"Point"}
}