{
  "type": "Feature",
  "properties": {
    "gn:admin1_code":"02",
    "gn:asciiname":"Qitangnan",
    "gn:country_code":"CN",
    "gn:dem":5,
    "gn:feature_class":"P",
    "gn:feature_code":"PPL",
    "gn:name":"Qitangnan",
    "gn:population":0,
    "gn:timezone":"Asia/Shanghai",
    "iso:country":"CN",
    "name:und_x_variant":[
        "\u4e03\u5858\u5357"
    ],
    "wof:name":"Qitangnan",
    "wof:placetype":"locality"
},
  "geometry": {"coordinates":[121.22545,30.27768],"type":"Point"}
}