{
  "type": "Feature",
  "properties": {
    "gn:admin1_code":"12.0",
    "gn:asciiname":"Hetaoyuan",
    "gn:country_code":"CN",
    "gn:dem":1314,
    "gn:feature_class":"P",
    "gn:feature_code":"PPL",
    "gn:name":"Hetaoyuan",
    "gn:population":0,
    "gn:timezone":"Asia/Shanghai",
    "iso:country":"CN",
    "name:zho_x_preferred":[
        "\u6838\u6843\u56ed"
    ],
    "wof:name":"Hetaoyuan",
    "wof:placetype":"locality"
},
  "geometry": {"coordinates":[108.73618999999999,30.43682],"type":"Point"}
}