{
  "type": "Feature",
  "properties": {
    "gn:admin1_code":"18",
    "gn:asciiname":"Caodixia",
    "gn:country_code":"CN",
    "gn:dem":936,
    "gn:feature_class":"P",
    "gn:feature_code":"PPL",
    "gn:name":"Caodixia",
    "gn:population":0,
    "gn:timezone":"Asia/Shanghai",
    "iso:country":"CN",
    "name:zho_x_preferred":[
        "\u69fd\u5e95\u4e0b"
    ],
    "wof:name":"Caodixia",
    "wof:placetype":"locality"
},
  "geometry": {"coordinates":[108.26000000000001,27.2524],"type":"Point"}
}