{
  "type": "Feature",
  "properties": {
    "gn:admin1_code":"29.0",
    "gn:asciiname":"Qianqiao",
    "gn:country_code":"CN",
    "gn:dem":1739,
    "gn:feature_class":"P",
    "gn:feature_code":"PPL",
    "gn:name":"Qianqiao",
    "gn:population":0,
    "gn:timezone":"Asia/Shanghai",
    "iso:country":"CN",
    "name:zho_x_preferred":[
        "\u6b20\u6865"
    ],
    "wof:name":"Qianqiao",
    "wof:placetype":"locality"
},
  "geometry": {"coordinates":[98.5933,24.6458],"type":"Point"}
}