{
  "type": "Feature",
  "properties": {
    "gn:admin1_code":"24.0",
    "gn:asciiname":"Wangjiali",
    "gn:country_code":"CN",
    "gn:dem":1089,
    "gn:feature_class":"P",
    "gn:feature_code":"PPL",
    "gn:name":"Wangjiali",
    "gn:population":0,
    "gn:timezone":"Asia/Shanghai",
    "iso:country":"CN",
    "name:zho_x_preferred":[
        "\u738b\u5bb6\u91cc"
    ],
    "wof:name":"Wangjiali",
    "wof:placetype":"locality"
},
  "geometry": {"coordinates":[111.08275999999999,38.89191],"type":"Point"}
}