{
  "type": "Feature",
  "properties": {
    "gn:admin1_code":"26.0",
    "gn:asciiname":"Hanhecun",
    "gn:country_code":"CN",
    "gn:dem":1379,
    "gn:feature_class":"P",
    "gn:feature_code":"PPL",
    "gn:name":"Hanhecun",
    "gn:population":0,
    "gn:timezone":"Asia/Shanghai",
    "iso:country":"CN",
    "name:zho_x_preferred":[
        "\u97e9\u6cb3\u6751"
    ],
    "wof:name":"Hanhecun",
    "wof:placetype":"locality"
},
  "geometry": {"coordinates":[109.26869000000001,32.11043],"type":"Point"}
}