{
  "type": "Feature",
  "properties": {
    "gn:admin1_code":"18",
    "gn:asciiname":"Hengshuitang",
    "gn:country_code":"CN",
    "gn:dem":1177,
    "gn:feature_class":"P",
    "gn:feature_code":"PPL",
    "gn:name":"Hengshuitang",
    "gn:population":0,
    "gn:timezone":"Asia/Shanghai",
    "iso:country":"CN",
    "name:zho_x_preferred":[
        "\u6a2a\u6c34\u5858"
    ],
    "wof:name":"Hengshuitang",
    "wof:placetype":"locality"
},
  "geometry": {"coordinates":[105.24299999999999,25.0728],"type":"Point"}
}