{
  "type": "Feature",
  "properties": {
    "gn:admin1_code":"24.0",
    "gn:asciiname":"Wujialiang",
    "gn:country_code":"CN",
    "gn:dem":1503,
    "gn:feature_class":"P",
    "gn:feature_code":"PPL",
    "gn:name":"Wujialiang",
    "gn:population":0,
    "gn:timezone":"Asia/Shanghai",
    "iso:country":"CN",
    "name:zho_x_preferred":[
        "\u6b66\u5bb6\u6881"
    ],
    "wof:name":"Wujialiang",
    "wof:placetype":"locality"
},
  "geometry": {"coordinates":[111.62239,38.02991],"type":"Point"}
}