{
  "type": "Feature",
  "properties": {
    "gn:admin1_code":"26.0",
    "gn:asciiname":"Yinpoliang",
    "gn:country_code":"CN",
    "gn:dem":761,
    "gn:feature_class":"P",
    "gn:feature_code":"PPL",
    "gn:name":"Yinpoliang",
    "gn:population":0,
    "gn:timezone":"Asia/Shanghai",
    "iso:country":"CN",
    "name:und_x_variant":[
        "\u94f6\u5761\u6881"
    ],
    "wof:name":"Yinpoliang",
    "wof:placetype":"locality"
},
  "geometry": {"coordinates":[106.03838,33.09791],"type":"Point"}
}