{
  "type": "Feature",
  "properties": {
    "gn:admin1_code":"19.0",
    "gn:asciiname":"Beilianggang",
    "gn:country_code":"CN",
    "gn:dem":292,
    "gn:feature_class":"P",
    "gn:feature_code":"PPL",
    "gn:name":"Beilianggang",
    "gn:population":0,
    "gn:timezone":"Asia/Shanghai",
    "iso:country":"CN",
    "name:zho_x_preferred":[
        "\u5317\u6881\u5c97"
    ],
    "wof:name":"Beilianggang",
    "wof:placetype":"locality"
},
  "geometry": {"coordinates":[120.001,40.7793],"type":"Point"}
}