{
  "type": "Feature",
  "properties": {
    "gn:admin1_code":"12.0",
    "gn:asciiname":"Liujiabeishang",
    "gn:country_code":"CN",
    "gn:dem":31,
    "gn:feature_class":"P",
    "gn:feature_code":"PPL",
    "gn:name":"Liujiabeishang",
    "gn:population":0,
    "gn:timezone":"Asia/Shanghai",
    "iso:country":"CN",
    "name:zho_x_preferred":[
        "\u5218\u5bb6\u5317\u4e0a"
    ],
    "wof:name":"Liujiabeishang",
    "wof:placetype":"locality"
},
  "geometry": {"coordinates":[112.50388999999998,30.37518],"type":"Point"}
}