{
  "type": "Feature",
  "properties": {
    "gn:admin1_code":"2.0",
    "gn:asciiname":"Beikengyuan",
    "gn:country_code":"CN",
    "gn:dem":299,
    "gn:feature_class":"P",
    "gn:feature_code":"PPL",
    "gn:name":"Beikengyuan",
    "gn:population":0,
    "gn:timezone":"Asia/Shanghai",
    "iso:country":"CN",
    "name:zho_x_preferred":[
        "\u5317\u5751\u6e90"
    ],
    "wof:name":"Beikengyuan",
    "wof:placetype":"locality"
},
  "geometry": {"coordinates":[118.9791,29.34436],"type":"Point"}
}