{
  "type": "Feature",
  "properties": {
    "gn:admin1_code":"8.0",
    "gn:asciiname":"Kangningcun",
    "gn:country_code":"CN",
    "gn:dem":178,
    "gn:feature_class":"P",
    "gn:feature_code":"PPL",
    "gn:name":"Kangningcun",
    "gn:population":0,
    "gn:timezone":"Asia/Shanghai",
    "iso:country":"CN",
    "name:zho_x_preferred":[
        "\u5eb7\u5b81\u6751"
    ],
    "wof:name":"Kangningcun",
    "wof:placetype":"locality"
},
  "geometry": {"coordinates":[126.22703,45.50706],"type":"Point"}
}