{
  "type": "Feature",
  "properties": {
    "gn:admin1_code":"3",
    "gn:asciiname":"Heyuan",
    "gn:country_code":"CN",
    "gn:dem":288,
    "gn:feature_class":"P",
    "gn:feature_code":"PPL",
    "gn:name":"Heyuan",
    "gn:population":0,
    "gn:timezone":"Asia/Shanghai",
    "iso:country":"CN",
    "name:ara_x_preferred":[
        "\u0647\u064a\u0648\u0627\u0646"
    ],
    "name:cdo_x_preferred":[
        "\u00d2\u0324-ngu\u00f2ng"
    ],
    "name:ceb_x_preferred":[
        "Heyuan"
    ],
    "name:ces_x_preferred":[
        "Che-j\u00fcan"
    ],
    "name:cym_x_preferred":[
        "Heyuan"
    ],
    "name:dan_x_preferred":[
        "Heyuan"
    ],
    "name:deu_x_preferred":[
        "Heyuan"
    ],
    "name:eus_x_preferred":[
        "Heyuan"
    ],
    "name:fas_x_preferred":[
        "\u0647\u06cc\u0648\u0627\u0646"
    ],
    "name:fin_x_preferred":[
        "Heyuan"
    ],
    "name:fra_x_preferred":[
        "Heyuan"
    ],
    "name:hak_x_preferred":[
        "H\u00f2-ngi\u00e8n-s\u1e73"
    ],
    "name:hun_x_preferred":[
        "Heyuan"
    ],
    "name:ind_x_preferred":[
        "Heyuan"
    ],
    "name:ita_x_preferred":[
        "Heyuan"
    ],
    "name:jpn_x_preferred":[
        "\u6cb3\u6e90\u5e02"
    ],
    "name:kik_x_preferred":[
        "Heyuan"
    ],
    "name:kor_x_preferred":[
        "\ud5c8\uc704\uc548\uc2dc"
    ],
    "name:mlg_x_preferred":[
        "Heyuan"
    ],
    "name:msa_x_preferred":[
        "Heyuan"
    ],
    "name:nld_x_preferred":[
        "Heyuan"
    ],
    "name:nno_x_preferred":[
        "Heyuan"
    ],
    "name:nor_x_preferred":[
        "Heyuan"
    ],
    "name:pam_x_preferred":[
        "Heyuan"
    ],
    "name:pnb_x_preferred":[
        "\u06c1\u06cc \u06cc\u0648\u0622\u0646"
    ],
    "name:pol_x_preferred":[
        "Heyuan"
    ],
    "name:rus_x_preferred":[
        "\u0425\u044d\u044e\u0430\u043d\u044c"
    ],
    "name:spa_x_preferred":[
        "Heyuan"
    ],
    "name:swa_x_preferred":[
        "Heyuan"
    ],
    "name:swe_x_preferred":[
        "Heyuan"
    ],
    "name:tur_x_preferred":[
        "Heyuan"
    ],
    "name:urd_x_preferred":[
        "\u06c1\u06cc\u0626\u0648\u0627\u0646"
    ],
    "name:vie_x_preferred":[
        "H\u00e0 Nguy\u00ean"
    ],
    "name:war_x_preferred":[
        "Heyuan"
    ],
    "name:wuu_x_preferred":[
        "\u6cb3\u6e90\u5e02"
    ],
    "name:zho_x_preferred":[
        "\u6cb3\u6e90\u5e02"
    ],
    "wof:name":"Heyuan",
    "wof:placetype":"locality"
},
  "geometry": {"coordinates":[114.43277999999999,26.18528],"type":"Point"}
}