{
  "type": "Feature",
  "properties": {
    "gn:admin1_code":"19.0",
    "gn:asciiname":"Shuangtaizi",
    "gn:country_code":"CN",
    "gn:dem":142,
    "gn:feature_class":"P",
    "gn:feature_code":"PPL",
    "gn:name":"Shuangtaizi",
    "gn:population":0,
    "gn:timezone":"Asia/Shanghai",
    "iso:country":"CN",
    "name:zho_x_preferred":[
        "\u53cc\u53f0\u5b50"
    ],
    "wof:name":"Shuangtaizi",
    "wof:placetype":"locality"
},
  "geometry": {"coordinates":[123.983,42.7219],"type":"Point"}
}