{
  "type": "Feature",
  "properties": {
    "gn:admin1_code":"02",
    "gn:asciiname":"Tianhoucun",
    "gn:country_code":"CN",
    "gn:dem":7,
    "gn:feature_class":"P",
    "gn:feature_code":"PPL",
    "gn:name":"Tianhoucun",
    "gn:population":0,
    "gn:timezone":"Asia/Shanghai",
    "iso:country":"CN",
    "name:und_x_variant":[
        "Tianhou",
        "Tianhoucun"
    ],
    "name:zho_x_preferred":[
        "\u7530\u540e"
    ],
    "name:zho_x_variant":[
        "\u7530\u540e\u6751"
    ],
    "wof:name":"Tianhoucun",
    "wof:placetype":"locality"
},
  "geometry": {"coordinates":[121.53574999999999,28.36551],"type":"Point"}
}