{
  "type": "Feature",
  "properties": {
    "gn:admin1_code":"10",
    "gn:asciiname":"Suohuang",
    "gn:country_code":"CN",
    "gn:dem":540,
    "gn:feature_class":"P",
    "gn:feature_code":"PPL",
    "gn:name":"Suohuang",
    "gn:population":0,
    "gn:timezone":"Asia/Shanghai",
    "iso:country":"CN",
    "name:zho_x_preferred":[
        "\u9501\u7c27"
    ],
    "wof:name":"Suohuang",
    "wof:placetype":"locality"
},
  "geometry": {"coordinates":[114.119,37.2766],"type":"Point"}
}