{
  "type": "Feature",
  "properties": {
    "gn:admin1_code":"26.0",
    "gn:asciiname":"Fuchangliang",
    "gn:country_code":"CN",
    "gn:dem":1210,
    "gn:feature_class":"P",
    "gn:feature_code":"PPL",
    "gn:name":"Fuchangliang",
    "gn:population":0,
    "gn:timezone":"Asia/Shanghai",
    "iso:country":"CN",
    "name:zho_x_preferred":[
        "\u5bcc\u660c\u6881"
    ],
    "wof:name":"Fuchangliang",
    "wof:placetype":"locality"
},
  "geometry": {"coordinates":[109.65252,37.40835],"type":"Point"}
}