{
  "type": "Feature",
  "properties": {
    "gn:admin1_code":"24.0",
    "gn:asciiname":"Xia'an",
    "gn:country_code":"CN",
    "gn:dem":959,
    "gn:feature_class":"P",
    "gn:feature_code":"PPL",
    "gn:name":"Xia\u2019an",
    "gn:population":0,
    "gn:timezone":"Asia/Shanghai",
    "iso:country":"CN",
    "name:und_x_variant":[
        "Hsia-an-ts\u2019un",
        "Hsia-an",
        "Xia\u2019an"
    ],
    "wof:name":"Xia'an",
    "wof:placetype":"locality"
},
  "geometry": {"coordinates":[111.13388999999999,37.57861],"type":"Point"}
}