{
  "type": "Feature",
  "properties": {
    "gn:admin1_code":"4.0",
    "gn:asciiname":"Shaoqiao",
    "gn:country_code":"CN",
    "gn:dem":4,
    "gn:feature_class":"P",
    "gn:feature_code":"PPL",
    "gn:name":"Shaoqiao",
    "gn:population":0,
    "gn:timezone":"Asia/Shanghai",
    "iso:country":"CN",
    "name:und_x_variant":[
        "\u90b5\u6865"
    ],
    "wof:name":"Shaoqiao",
    "wof:placetype":"locality"
},
  "geometry": {"coordinates":[121.17363,31.56749000000001],"type":"Point"}
}