{
  "type": "Feature",
  "properties": {
    "gn:admin1_code":"2.0",
    "gn:asciiname":"Dawukou",
    "gn:country_code":"CN",
    "gn:dem":171,
    "gn:feature_class":"P",
    "gn:feature_code":"PPL",
    "gn:name":"Dawukou",
    "gn:population":0,
    "gn:timezone":"Asia/Shanghai",
    "iso:country":"CN",
    "name:zho_x_preferred":[
        "\u8fbe\u575e\u53e3"
    ],
    "wof:name":"Dawukou",
    "wof:placetype":"locality"
},
  "geometry": {"coordinates":[118.51810999999999,28.75869],"type":"Point"}
}