{
  "type": "Feature",
  "properties": {
    "gn:admin1_code":"3.0",
    "gn:asciiname":"Zhekeng",
    "gn:country_code":"CN",
    "gn:dem":331,
    "gn:feature_class":"P",
    "gn:feature_code":"PPL",
    "gn:name":"Zhekeng",
    "gn:population":0,
    "gn:timezone":"Asia/Shanghai",
    "iso:country":"CN",
    "name:und_x_variant":[
        "\u8517\u5751"
    ],
    "wof:name":"Zhekeng",
    "wof:placetype":"locality"
},
  "geometry": {"coordinates":[115.37273999999999,25.50229],"type":"Point"}
}