{
  "type": "Feature",
  "properties": {
    "gn:admin1_code":"29.0",
    "gn:asciiname":"Puma",
    "gn:country_code":"CN",
    "gn:dem":1228,
    "gn:feature_class":"P",
    "gn:feature_code":"PPL",
    "gn:name":"Puma",
    "gn:population":0,
    "gn:timezone":"Asia/Shanghai",
    "iso:country":"CN",
    "name:ast_x_preferred":[
        "Puma"
    ],
    "name:cat_x_preferred":[
        "Puma"
    ],
    "name:ceb_x_preferred":[
        "Puma"
    ],
    "name:ces_x_preferred":[
        "Puma"
    ],
    "name:dan_x_preferred":[
        "Puma"
    ],
    "name:deu_x_preferred":[
        "Puma"
    ],
    "name:est_x_preferred":[
        "Puma"
    ],
    "name:fas_x_preferred":[
        "\u067e\u0648\u0645\u0627"
    ],
    "name:fra_x_preferred":[
        "Puma"
    ],
    "name:heb_x_preferred":[
        "\u05e4\u05d5\u05de\u05d4"
    ],
    "name:hrv_x_preferred":[
        "Puma"
    ],
    "name:hun_x_preferred":[
        "Puma"
    ],
    "name:hye_x_preferred":[
        "\u054a\u0578\u0582\u0574\u0561"
    ],
    "name:ina_x_preferred":[
        "Puma"
    ],
    "name:ind_x_preferred":[
        "Puma"
    ],
    "name:ita_x_preferred":[
        "Puma"
    ],
    "name:jpn_x_preferred":[
        "Puma"
    ],
    "name:kor_x_preferred":[
        "\ud4e8\ub9c8"
    ],
    "name:lin_x_preferred":[
        "Puma"
    ],
    "name:lit_x_preferred":[
        "Puma"
    ],
    "name:nld_x_preferred":[
        "Puma"
    ],
    "name:nor_x_preferred":[
        "Puma"
    ],
    "name:pol_x_preferred":[
        "Puma"
    ],
    "name:por_x_preferred":[
        "Puma"
    ],
    "name:ron_x_preferred":[
        "Puma"
    ],
    "name:rus_x_preferred":[
        "\u041f\u0443\u043c\u0430"
    ],
    "name:slk_x_preferred":[
        "Puma"
    ],
    "name:spa_x_preferred":[
        "Puma"
    ],
    "name:sqi_x_preferred":[
        "Puma"
    ],
    "name:srp_x_preferred":[
        "Puma"
    ],
    "name:swe_x_preferred":[
        "Puma"
    ],
    "name:tgl_x_preferred":[
        "Puma"
    ],
    "name:tur_x_preferred":[
        "Puma"
    ],
    "name:ukr_x_preferred":[
        "\u041f\u0443\u043c\u0430"
    ],
    "name:vie_x_preferred":[
        "Puma"
    ],
    "name:zho_x_preferred":[
        "\u666e\u739b"
    ],
    "wof:name":"Puma",
    "wof:placetype":"locality"
},
  "geometry": {"coordinates":[103.526,22.7406],"type":"Point"}
}