{
  "type": "Feature",
  "properties": {
    "gn:admin1_code":"18",
    "gn:asciiname":"Xiongjiazhai",
    "gn:country_code":"CN",
    "gn:dem":831,
    "gn:feature_class":"P",
    "gn:feature_code":"PPL",
    "gn:name":"Xiongjiazhai",
    "gn:population":0,
    "gn:timezone":"Asia/Shanghai",
    "iso:country":"CN",
    "name:zho_x_preferred":[
        "\u718a\u5bb6\u5be8"
    ],
    "wof:name":"Xiongjiazhai",
    "wof:placetype":"locality"
},
  "geometry": {"coordinates":[108.114,28.0803],"type":"Point"}
}