{
  "type": "Feature",
  "properties": {
    "gn:admin1_code":"11.0",
    "gn:asciiname":"Zhujiadian",
    "gn:country_code":"CN",
    "gn:dem":83,
    "gn:feature_class":"P",
    "gn:feature_code":"PPL",
    "gn:name":"Zhujiadian",
    "gn:population":0,
    "gn:timezone":"Asia/Shanghai",
    "iso:country":"CN",
    "name:zho_x_preferred":[
        "Zhujiadian"
    ],
    "name:zho_x_variant":[
        "\u6731\u5bb6\u5e97"
    ],
    "wof:name":"Zhujiadian",
    "wof:placetype":"locality"
},
  "geometry": {"coordinates":[111.12193000000001,28.92964000000001],"type":"Point"}
}