{
  "type": "Feature",
  "properties": {
    "gn:admin1_code":"1.0",
    "gn:asciiname":"Molicun",
    "gn:country_code":"CN",
    "gn:dem":37,
    "gn:feature_class":"P",
    "gn:feature_code":"PPL",
    "gn:name":"Molicun",
    "gn:population":0,
    "gn:timezone":"Asia/Shanghai",
    "iso:country":"CN",
    "name:zho_x_preferred":[
        "\u8c8a\u674e\u6751"
    ],
    "wof:name":"Molicun",
    "wof:placetype":"locality"
},
  "geometry": {"coordinates":[115.54485,33.13147],"type":"Point"}
}