{
  "type": "Feature",
  "properties": {
    "gn:admin1_code":"14.0",
    "gn:asciiname":"Se'ernie",
    "gn:country_code":"CN",
    "gn:dem":4878,
    "gn:feature_class":"P",
    "gn:feature_code":"PPL",
    "gn:name":"Se\u2019ernie",
    "gn:population":0,
    "gn:timezone":"Asia/Urumqi",
    "iso:country":"CN",
    "name:und_x_variant":[
        "Se\u2019ernie"
    ],
    "name:zho_x_preferred":[
        "\u8272\u5c14\u8042"
    ],
    "wof:name":"Se'ernie",
    "wof:placetype":"locality"
},
  "geometry": {"coordinates":[86.93980000000001,30.6214],"type":"Point"}
}