{
  "type": "Feature",
  "properties": {
    "gn:admin1_code":"25.0",
    "gn:asciiname":"Dapankou",
    "gn:country_code":"CN",
    "gn:dem":90,
    "gn:feature_class":"P",
    "gn:feature_code":"PPL",
    "gn:name":"Dapankou",
    "gn:population":0,
    "gn:timezone":"Asia/Shanghai",
    "iso:country":"CN",
    "name:zho_x_preferred":[
        "\u5927\u6cee\u53e3"
    ],
    "wof:name":"Dapankou",
    "wof:placetype":"locality"
},
  "geometry": {"coordinates":[121.29302,37.22425],"type":"Point"}
}