{
  "type": "Feature",
  "properties": {
    "gn:admin1_code":"4.0",
    "gn:asciiname":"Jinlong",
    "gn:country_code":"CN",
    "gn:dem":1,
    "gn:feature_class":"P",
    "gn:feature_code":"PPL",
    "gn:name":"Jinlong",
    "gn:population":0,
    "gn:timezone":"Asia/Shanghai",
    "iso:country":"CN",
    "name:und_x_variant":[
        "\u91d1\u9f99"
    ],
    "wof:name":"Jinlong",
    "wof:placetype":"locality"
},
  "geometry": {"coordinates":[120.47723999999999,32.97093],"type":"Point"}
}