{
  "type": "Feature",
  "properties": {
    "gn:admin1_code":"14.0",
    "gn:asciiname":"Gazhucun",
    "gn:country_code":"CN",
    "gn:dem":4739,
    "gn:feature_class":"P",
    "gn:feature_code":"PPL",
    "gn:name":"Gazhucun",
    "gn:population":0,
    "gn:timezone":"Asia/Urumqi",
    "iso:country":"CN",
    "name:zho_x_preferred":[
        "\u560e\u7af9\u6751"
    ],
    "wof:name":"Gazhucun",
    "wof:placetype":"locality"
},
  "geometry": {"coordinates":[90.09951,29.15911],"type":"Point"}
}