{
  "type": "Feature",
  "properties": {
    "gn:admin1_code":"5.0",
    "gn:asciiname":"Xiao'aihaotang",
    "gn:country_code":"CN",
    "gn:dem":251,
    "gn:feature_class":"P",
    "gn:feature_code":"PPL",
    "gn:name":"Xiao\u2019aihaotang",
    "gn:population":0,
    "gn:timezone":"Asia/Shanghai",
    "iso:country":"CN",
    "name:und_x_variant":[
        "Xiao\u2019aihaotang"
    ],
    "name:zho_x_preferred":[
        "\u5c0f\u827e\u84bf\u5858"
    ],
    "wof:name":"Xiao'aihaotang",
    "wof:placetype":"locality"
},
  "geometry": {"coordinates":[124.63072,44.46113],"type":"Point"}
}