{
  "type": "Feature",
  "properties": {
    "gn:admin1_code":"3.0",
    "gn:asciiname":"Jiushan",
    "gn:country_code":"CN",
    "gn:dem":82,
    "gn:feature_class":"P",
    "gn:feature_code":"PPL",
    "gn:name":"Jiushan",
    "gn:population":0,
    "gn:timezone":"Asia/Shanghai",
    "iso:country":"CN",
    "name:und_x_variant":[
        "\u97ed\u5c71"
    ],
    "wof:name":"Jiushan",
    "wof:placetype":"locality"
},
  "geometry": {"coordinates":[115.50700000000001,29.70492],"type":"Point"}
}