{
  "type": "Feature",
  "properties": {
    "gn:admin1_code":"22.0",
    "gn:asciiname":"Duijiaogoucun",
    "gn:country_code":"CN",
    "gn:dem":614,
    "gn:feature_class":"P",
    "gn:feature_code":"PPL",
    "gn:name":"Duijiaogoucun",
    "gn:population":0,
    "gn:timezone":"Asia/Shanghai",
    "iso:country":"CN",
    "name:zho_x_preferred":[
        "\u5bf9\u89d2\u6c9f\u6751"
    ],
    "wof:name":"Duijiaogoucun",
    "wof:placetype":"locality"
},
  "geometry": {"coordinates":[116.45285,40.57522],"type":"Point"}
}