{
  "type": "Feature",
  "properties": {
    "gn:admin1_code":"8.0",
    "gn:asciiname":"Lianfa Sidui",
    "gn:country_code":"CN",
    "gn:dem":344,
    "gn:feature_class":"P",
    "gn:feature_code":"PPLF",
    "gn:name":"Lianfa Sidui",
    "gn:population":0,
    "gn:timezone":"Asia/Shanghai",
    "iso:country":"CN",
    "name:zho_x_preferred":[
        "\u8054\u53d1\u56db\u961f"
    ],
    "wof:name":"Lianfa Sidui",
    "wof:placetype":"locality"
},
  "geometry": {"coordinates":[125.65961,48.25623],"type":"Point"}
}