{
  "type": "Feature",
  "properties": {
    "gn:admin1_code":"15",
    "gn:asciiname":"Taibai",
    "gn:country_code":"CN",
    "gn:dem":1009,
    "gn:feature_class":"P",
    "gn:feature_code":"PPLA4",
    "gn:name":"Taibai",
    "gn:population":0,
    "gn:timezone":"Asia/Shanghai",
    "iso:country":"CN",
    "name:deu_x_preferred":[
        "Taibai"
    ],
    "name:fra_x_preferred":[
        "Taibai"
    ],
    "name:und_x_variant":[
        "\u592a\u767d"
    ],
    "wof:name":"Taibai",
    "wof:placetype":"locality"
},
  "geometry": {"coordinates":[106.16231999999999,34.05791],"type":"Point"}
}