{
  "type": "Feature",
  "properties": {
    "gn:admin1_code":"2.0",
    "gn:asciiname":"Huangliping",
    "gn:country_code":"CN",
    "gn:dem":41,
    "gn:feature_class":"P",
    "gn:feature_code":"PPL",
    "gn:name":"Huangliping",
    "gn:population":0,
    "gn:timezone":"Asia/Shanghai",
    "iso:country":"CN",
    "name:zho_x_preferred":[
        "\u9ec4\u6817\u576a"
    ],
    "wof:name":"Huangliping",
    "wof:placetype":"locality"
},
  "geometry": {"coordinates":[119.46948999999999,29.54531],"type":"Point"}
}