{
  "type": "Feature",
  "properties": {
    "gn:admin1_code":"4.0",
    "gn:asciiname":"Jishecun",
    "gn:country_code":"CN",
    "gn:dem":-1,
    "gn:feature_class":"P",
    "gn:feature_code":"PPL",
    "gn:name":"Jishecun",
    "gn:population":0,
    "gn:timezone":"Asia/Shanghai",
    "iso:country":"CN",
    "name:zho_x_preferred":[
        "\u5d47\u820d\u6751"
    ],
    "wof:name":"Jishecun",
    "wof:placetype":"locality"
},
  "geometry": {"coordinates":[119.88531999999999,33.55029],"type":"Point"}
}