{
  "type": "Feature",
  "properties": {
    "gn:admin1_code":"05",
    "gn:asciiname":"Shih-ta-yuan",
    "gn:country_code":"CN",
    "gn:dem":377,
    "gn:feature_class":"P",
    "gn:feature_code":"PPL",
    "gn:name":"Shih-ta-y\u00fcan",
    "gn:population":0,
    "gn:timezone":"Asia/Shanghai",
    "iso:country":"CN",
    "wof:name":"Shih-ta-yuan",
    "wof:placetype":"locality"
},
  "geometry": {"coordinates":[126.18416999999999,42.52528],"type":"Point"}
}