{
  "type": "Feature",
  "properties": {
    "gn:admin1_code":"25.0",
    "gn:asciiname":"Lunanbu",
    "gn:country_code":"CN",
    "gn:dem":94,
    "gn:feature_class":"P",
    "gn:feature_code":"PPL",
    "gn:name":"Lunanbu",
    "gn:population":0,
    "gn:timezone":"Asia/Shanghai",
    "iso:country":"CN",
    "name:zho_x_preferred":[
        "\u8def\u5357\u57e0"
    ],
    "wof:name":"Lunanbu",
    "wof:placetype":"locality"
},
  "geometry": {"coordinates":[120.34419,36.94872],"type":"Point"}
}