{
  "type": "Feature",
  "properties": {
    "gn:admin1_code":"18",
    "gn:asciiname":"Fujiagou",
    "gn:country_code":"CN",
    "gn:dem":697,
    "gn:feature_class":"P",
    "gn:feature_code":"PPL",
    "gn:name":"Fujiagou",
    "gn:population":0,
    "gn:timezone":"Asia/Shanghai",
    "iso:country":"CN",
    "name:zho_x_preferred":[
        "\u5085\u5bb6\u6c9f"
    ],
    "wof:name":"Fujiagou",
    "wof:placetype":"locality"
},
  "geometry": {"coordinates":[106.03400000000001,27.7133],"type":"Point"}
}