{
  "type": "Feature",
  "properties": {
    "gn:admin1_code":"12.0",
    "gn:asciiname":"Danziya",
    "gn:country_code":"CN",
    "gn:dem":1024,
    "gn:feature_class":"P",
    "gn:feature_code":"PPL",
    "gn:name":"Danziya",
    "gn:population":0,
    "gn:timezone":"Asia/Shanghai",
    "iso:country":"CN",
    "name:zho_x_preferred":[
        "\u62c5\u5b50\u57ad"
    ],
    "wof:name":"Danziya",
    "wof:placetype":"locality"
},
  "geometry": {"coordinates":[111.21308999999999,31.31734],"type":"Point"}
}