{
  "type": "Feature",
  "properties": {
    "gn:admin1_code":"20",
    "gn:asciiname":"Qagan Bulag",
    "gn:cc2":"CN",
    "gn:country_code":"CN",
    "gn:dem":1327,
    "gn:feature_class":"P",
    "gn:feature_code":"PPL",
    "gn:name":"Qagan Bulag",
    "gn:population":0,
    "gn:timezone":"Asia/Shanghai",
    "iso:country":"CN",
    "name:und_x_variant":[
        "Ch\u2019a-han-eh\u2019ih",
        "Qagan Bulag"
    ],
    "wof:name":"Qagan Bulag",
    "wof:placetype":"locality"
},
  "geometry": {"coordinates":[104.66667,38.36667],"type":"Point"}
}