{
  "type": "Feature",
  "properties": {
    "gn:admin1_code":"29.0",
    "gn:asciiname":"Zhadi",
    "gn:country_code":"CN",
    "gn:dem":1524,
    "gn:feature_class":"P",
    "gn:feature_code":"PPL",
    "gn:name":"Zhadi",
    "gn:population":0,
    "gn:timezone":"Asia/Shanghai",
    "iso:country":"CN",
    "name:zho_x_preferred":[
        "\u69a8\u5730"
    ],
    "wof:name":"Zhadi",
    "wof:placetype":"locality"
},
  "geometry": {"coordinates":[98.55459999999999,24.6164],"type":"Point"}
}