{
  "type": "Feature",
  "properties": {
    "gn:admin1_code":"25",
    "gn:asciiname":"Luangou",
    "gn:country_code":"CN",
    "gn:dem":42,
    "gn:feature_class":"P",
    "gn:feature_code":"PPL",
    "gn:name":"Luangou",
    "gn:population":0,
    "gn:timezone":"Asia/Shanghai",
    "iso:country":"CN",
    "name:zho_x_preferred":[
        "\u4e71\u6c9f"
    ],
    "wof:name":"Luangou",
    "wof:placetype":"locality"
},
  "geometry": {"coordinates":[117.637,34.7201],"type":"Point"}
}