{
  "type": "Feature",
  "properties": {
    "gn:admin1_code":"15.0",
    "gn:asciiname":"Zhonglu",
    "gn:country_code":"CN",
    "gn:dem":1308,
    "gn:feature_class":"P",
    "gn:feature_code":"PPL",
    "gn:name":"Zhonglu",
    "gn:population":0,
    "gn:timezone":"Asia/Shanghai",
    "iso:country":"CN",
    "name:fas_x_preferred":[
        "\u0698\u0648\u0646\u06af\u0644\u0648"
    ],
    "name:zho_x_preferred":[
        "\u4e2d\u8def"
    ],
    "name:zho_x_variant":[
        "\u5fe0\u8def\u9547"
    ],
    "wof:name":"Zhonglu",
    "wof:placetype":"locality"
},
  "geometry": {"coordinates":[107.10899999999999,35.3468],"type":"Point"}
}