{
  "type": "Feature",
  "properties": {
    "gn:admin1_code":"25.0",
    "gn:asciiname":"Fangling",
    "gn:country_code":"CN",
    "gn:dem":15,
    "gn:feature_class":"P",
    "gn:feature_code":"PPL",
    "gn:name":"Fangling",
    "gn:population":0,
    "gn:timezone":"Asia/Shanghai",
    "iso:country":"CN",
    "name:zho_x_preferred":[
        "\u574a\u5cad"
    ],
    "wof:name":"Fangling",
    "wof:placetype":"locality"
},
  "geometry": {"coordinates":[119.60980000000001,36.4174],"type":"Point"}
}