{
  "type": "Feature",
  "properties": {
    "gn:admin1_code":"32.0",
    "gn:asciiname":"Guluzui",
    "gn:country_code":"CN",
    "gn:dem":377,
    "gn:feature_class":"P",
    "gn:feature_code":"PPL",
    "gn:name":"Guluzui",
    "gn:population":0,
    "gn:timezone":"Asia/Shanghai",
    "iso:country":"CN",
    "name:zho_x_preferred":[
        "\u53e4\u8def\u5480"
    ],
    "wof:name":"Guluzui",
    "wof:placetype":"locality"
},
  "geometry": {"coordinates":[104.70174,29.16419],"type":"Point"}
}