{
  "type": "Feature",
  "properties": {
    "gn:admin1_code":"32.0",
    "gn:asciiname":"Wuxingqiao",
    "gn:country_code":"CN",
    "gn:dem":486,
    "gn:feature_class":"P",
    "gn:feature_code":"PPL",
    "gn:name":"Wuxingqiao",
    "gn:population":0,
    "gn:timezone":"Asia/Shanghai",
    "iso:country":"CN",
    "name:zho_x_preferred":[
        "\u4e94\u661f\u6865"
    ],
    "wof:name":"Wuxingqiao",
    "wof:placetype":"locality"
},
  "geometry": {"coordinates":[105.11991,31.24031],"type":"Point"}
}