{
  "type": "Feature",
  "properties": {
    "gn:admin1_code":"15.0",
    "gn:asciiname":"Sujiawan",
    "gn:country_code":"CN",
    "gn:dem":1283,
    "gn:feature_class":"P",
    "gn:feature_code":"PPL",
    "gn:name":"Sujiawan",
    "gn:population":0,
    "gn:timezone":"Asia/Shanghai",
    "iso:country":"CN",
    "name:und_x_variant":[
        "\u82cf\u5bb6\u6e7e"
    ],
    "wof:name":"Sujiawan",
    "wof:placetype":"locality"
},
  "geometry": {"coordinates":[107.19428000000001,36.70433],"type":"Point"}
}