{
  "type": "Feature",
  "properties": {
    "gn:admin1_code":"4.0",
    "gn:asciiname":"Fanshen Sanzu",
    "gn:country_code":"CN",
    "gn:dem":4,
    "gn:feature_class":"P",
    "gn:feature_code":"PPLF",
    "gn:name":"Fanshen Sanzu",
    "gn:population":0,
    "gn:timezone":"Asia/Shanghai",
    "iso:country":"CN",
    "name:zho_x_preferred":[
        "\u7ffb\u8eab\u4e09\u7ec4"
    ],
    "wof:name":"Fanshen Sanzu",
    "wof:placetype":"locality"
},
  "geometry": {"coordinates":[120.52697999999999,32.57376],"type":"Point"}
}