{
  "type": "Feature",
  "properties": {
    "gn:admin1_code":"32.0",
    "gn:asciiname":"Mocaowan",
    "gn:country_code":"CN",
    "gn:dem":2996,
    "gn:feature_class":"P",
    "gn:feature_code":"PPL",
    "gn:name":"Mocaowan",
    "gn:population":0,
    "gn:timezone":"Asia/Shanghai",
    "iso:country":"CN",
    "name:zho_x_preferred":[
        "\u78e8\u69fd\u6e7e"
    ],
    "wof:name":"Mocaowan",
    "wof:placetype":"locality"
},
  "geometry": {"coordinates":[100.86199999999999,27.6454],"type":"Point"}
}