{
  "type": "Feature",
  "properties": {
    "gn:admin1_code":"20",
    "gn:asciiname":"Jinlin",
    "gn:cc2":"CN",
    "gn:country_code":"CN",
    "gn:dem":874,
    "gn:feature_class":"P",
    "gn:feature_code":"PPL",
    "gn:name":"Jinlin",
    "gn:population":0,
    "gn:timezone":"Asia/Shanghai",
    "iso:country":"CN",
    "name:eng_x_preferred":[
        "Jinlin"
    ],
    "name:rus_x_preferred":[
        "\u0426\u0437\u0438\u043d\u044c\u043b\u0438\u043d\u044c"
    ],
    "name:und_x_variant":[
        "Chin-lin"
    ],
    "name:zho_x_preferred":[
        "\u91d1\u6797"
    ],
    "wof:name":"Jinlin",
    "wof:placetype":"locality"
},
  "geometry": {"coordinates":[121.27778000000001,51.14722],"type":"Point"}
}