{
  "type": "Feature",
  "properties": {
    "gn:admin1_code":"32.0",
    "gn:asciiname":"Baziqiang",
    "gn:country_code":"CN",
    "gn:dem":444,
    "gn:feature_class":"P",
    "gn:feature_code":"PPL",
    "gn:name":"Baziqiang",
    "gn:population":0,
    "gn:timezone":"Asia/Shanghai",
    "iso:country":"CN",
    "name:zho_x_preferred":[
        "\u516b\u5b57\u5899"
    ],
    "wof:name":"Baziqiang",
    "wof:placetype":"locality"
},
  "geometry": {"coordinates":[105.22199999999999,30.0323],"type":"Point"}
}