{
  "type": "Feature",
  "properties": {
    "gn:admin1_code":"18",
    "gn:asciiname":"Gaoxinzhai",
    "gn:country_code":"CN",
    "gn:dem":1219,
    "gn:feature_class":"P",
    "gn:feature_code":"PPL",
    "gn:name":"Gaoxinzhai",
    "gn:population":0,
    "gn:timezone":"Asia/Shanghai",
    "iso:country":"CN",
    "name:zho_x_preferred":[
        "\u9ad8\u65b0\u5be8"
    ],
    "wof:name":"Gaoxinzhai",
    "wof:placetype":"locality"
},
  "geometry": {"coordinates":[105.69199999999999,26.3135],"type":"Point"}
}