{
  "type": "Feature",
  "properties": {
    "gn:admin1_code":"12.0",
    "gn:asciiname":"Tianlongping",
    "gn:country_code":"CN",
    "gn:dem":164,
    "gn:feature_class":"P",
    "gn:feature_code":"PPL",
    "gn:name":"Tianlongping",
    "gn:population":0,
    "gn:timezone":"Asia/Shanghai",
    "iso:country":"CN",
    "name:zho_x_preferred":[
        "\u5929\u9f99\u576a"
    ],
    "wof:name":"Tianlongping",
    "wof:placetype":"locality"
},
  "geometry": {"coordinates":[113.7199,29.51535],"type":"Point"}
}