{
  "type": "Feature",
  "properties": {
    "gn:admin1_code":"11",
    "gn:asciiname":"Piaotang",
    "gn:country_code":"CN",
    "gn:dem":106,
    "gn:feature_class":"P",
    "gn:feature_code":"PPL",
    "gn:name":"Piaotang",
    "gn:population":0,
    "gn:timezone":"Asia/Shanghai",
    "iso:country":"CN",
    "name:zho_x_preferred":[
        "\u74e2\u5858"
    ],
    "wof:name":"Piaotang",
    "wof:placetype":"locality"
},
  "geometry": {"coordinates":[112.28865,26.77499000000001],"type":"Point"}
}