{
  "type": "Feature",
  "properties": {
    "gn:admin1_code":"24.0",
    "gn:asciiname":"Anning",
    "gn:country_code":"CN",
    "gn:dem":978,
    "gn:feature_class":"P",
    "gn:feature_code":"PPL",
    "gn:name":"Anning",
    "gn:population":0,
    "gn:timezone":"Asia/Shanghai",
    "iso:country":"CN",
    "name:ceb_x_preferred":[
        "Anning"
    ],
    "name:deu_x_preferred":[
        "Anning"
    ],
    "name:fra_x_preferred":[
        "Anning"
    ],
    "name:nds_x_preferred":[
        "Anning"
    ],
    "name:nld_x_preferred":[
        "Anning"
    ],
    "name:nor_x_preferred":[
        "Anning"
    ],
    "name:rus_x_preferred":[
        "\u0410\u043d\u044c\u043d\u0438\u043d"
    ],
    "name:swe_x_preferred":[
        "Anning"
    ],
    "name:vie_x_preferred":[
        "An Ninh"
    ],
    "name:zho_x_preferred":[
        "\u5b89\u5b81"
    ],
    "wof:name":"Anning",
    "wof:placetype":"locality"
},
  "geometry": {"coordinates":[113.15853,36.46173],"type":"Point"}
}