{
  "type": "Feature",
  "properties": {
    "gn:admin1_code":"15.0",
    "gn:asciiname":"Chaweigou",
    "gn:country_code":"CN",
    "gn:dem":988,
    "gn:feature_class":"P",
    "gn:feature_code":"PPL",
    "gn:name":"Chaweigou",
    "gn:population":0,
    "gn:timezone":"Asia/Shanghai",
    "iso:country":"CN",
    "name:und_x_variant":[
        "\u8336\u5473\u6c9f"
    ],
    "wof:name":"Chaweigou",
    "wof:placetype":"locality"
},
  "geometry": {"coordinates":[105.81595,33.08478],"type":"Point"}
}