{
  "type": "Feature",
  "properties": {
    "gn:admin1_code":"16",
    "gn:asciiname":"Haozhoutian",
    "gn:country_code":"CN",
    "gn:dem":272,
    "gn:feature_class":"P",
    "gn:feature_code":"PPL",
    "gn:name":"Haozhoutian",
    "gn:population":0,
    "gn:timezone":"Asia/Shanghai",
    "iso:country":"CN",
    "name:zho_x_preferred":[
        "\u8c6a\u5dde\u7530"
    ],
    "wof:name":"Haozhoutian",
    "wof:placetype":"locality"
},
  "geometry": {"coordinates":[110.562,25.4243],"type":"Point"}
}