{
  "type": "Feature",
  "properties": {
    "gn:admin1_code":"32.0",
    "gn:asciiname":"Minsheng",
    "gn:country_code":"CN",
    "gn:dem":1669,
    "gn:feature_class":"P",
    "gn:feature_code":"PPL",
    "gn:name":"Minsheng",
    "gn:population":0,
    "gn:timezone":"Asia/Shanghai",
    "iso:country":"CN",
    "name:zho_x_preferred":[
        "\u6c11\u80dc"
    ],
    "wof:name":"Minsheng",
    "wof:placetype":"locality"
},
  "geometry": {"coordinates":[102.07205999999999,28.07998],"type":"Point"}
}