{
  "type": "Feature",
  "properties": {
    "gn:admin1_code":"29.0",
    "gn:asciiname":"Renjia",
    "gn:country_code":"CN",
    "gn:dem":1878,
    "gn:feature_class":"P",
    "gn:feature_code":"PPL",
    "gn:name":"Renjia",
    "gn:population":0,
    "gn:timezone":"Asia/Shanghai",
    "iso:country":"CN",
    "name:zho_x_preferred":[
        "\u4efb\u5bb6"
    ],
    "wof:name":"Renjia",
    "wof:placetype":"locality"
},
  "geometry": {"coordinates":[100.131,24.2002],"type":"Point"}
}