{
  "type": "Feature",
  "properties": {
    "gn:admin1_code":"8.0",
    "gn:asciiname":"Liuhai Shantun",
    "gn:country_code":"CN",
    "gn:dem":239,
    "gn:feature_class":"P",
    "gn:feature_code":"PPL",
    "gn:name":"Liuhai Shantun",
    "gn:population":0,
    "gn:timezone":"Asia/Shanghai",
    "iso:country":"CN",
    "name:zho_x_preferred":[
        "\u5218\u6d77\u5c71\u5c6f"
    ],
    "wof:name":"Liuhai Shantun",
    "wof:placetype":"locality"
},
  "geometry": {"coordinates":[127.00115,47.79122],"type":"Point"}
}