{
  "type": "Feature",
  "properties": {
    "gn:admin1_code":"18",
    "gn:asciiname":"Longchaoshu",
    "gn:country_code":"CN",
    "gn:dem":752,
    "gn:feature_class":"P",
    "gn:feature_code":"PPL",
    "gn:name":"Longchaoshu",
    "gn:population":0,
    "gn:timezone":"Asia/Shanghai",
    "iso:country":"CN",
    "name:zho_x_preferred":[
        "\u9f99\u671d\u6811"
    ],
    "wof:name":"Longchaoshu",
    "wof:placetype":"locality"
},
  "geometry": {"coordinates":[105.643,25.9385],"type":"Point"}
}