{
  "type": "Feature",
  "properties": {
    "gn:admin1_code":"4.0",
    "gn:asciiname":"Xiaoguanmiao",
    "gn:country_code":"CN",
    "gn:dem":5,
    "gn:feature_class":"P",
    "gn:feature_code":"PPL",
    "gn:name":"Xiaoguanmiao",
    "gn:population":0,
    "gn:timezone":"Asia/Shanghai",
    "iso:country":"CN",
    "name:und_x_variant":[
        "\u5c0f\u5173\u5e99"
    ],
    "wof:name":"Xiaoguanmiao",
    "wof:placetype":"locality"
},
  "geometry": {"coordinates":[121.09166999999999,32.38798],"type":"Point"}
}