{
  "type": "Feature",
  "properties": {
    "gn:admin1_code":"7",
    "gn:asciiname":"Tantou",
    "gn:country_code":"CN",
    "gn:dem":135,
    "gn:feature_class":"P",
    "gn:feature_code":"PPLA4",
    "gn:name":"Tantou",
    "gn:population":0,
    "gn:timezone":"Asia/Shanghai",
    "iso:country":"CN",
    "name:ceb_x_preferred":[
        "Tantou"
    ],
    "name:deu_x_preferred":[
        "Tantou"
    ],
    "name:fra_x_preferred":[
        "Tantou"
    ],
    "name:swe_x_preferred":[
        "Tantou"
    ],
    "name:und_x_variant":[
        "\u6f6d\u5934",
        "Tantou",
        "Tantou Zhen"
    ],
    "name:zho_x_preferred":[
        "\u6f6d\u5934\u9547"
    ],
    "wof:name":"Tantou",
    "wof:placetype":"locality"
},
  "geometry": {"coordinates":[119.66067,27.20479000000001],"type":"Point"}
}