{
  "type": "Feature",
  "properties": {
    "gn:admin1_code":"18.0",
    "gn:asciiname":"Poyang",
    "gn:country_code":"CN",
    "gn:dem":890,
    "gn:feature_class":"P",
    "gn:feature_code":"PPL",
    "gn:name":"Poyang",
    "gn:population":0,
    "gn:timezone":"Asia/Shanghai",
    "iso:country":"CN",
    "name:ceb_x_preferred":[
        "Poyang"
    ],
    "name:deu_x_preferred":[
        "Poyang"
    ],
    "name:zho_x_preferred":[
        "\u5761\u4ef0"
    ],
    "wof:name":"Poyang",
    "wof:placetype":"locality"
},
  "geometry": {"coordinates":[107.673,25.625],"type":"Point"}
}