{
  "type": "Feature",
  "properties": {
    "gn:admin1_code":"3.0",
    "gn:asciiname":"Hengkengwei",
    "gn:country_code":"CN",
    "gn:dem":553,
    "gn:feature_class":"P",
    "gn:feature_code":"PPL",
    "gn:name":"Hengkengwei",
    "gn:population":0,
    "gn:timezone":"Asia/Shanghai",
    "iso:country":"CN",
    "name:und_x_variant":[
        "\u6a2a\u5751\u5c3e"
    ],
    "wof:name":"Hengkengwei",
    "wof:placetype":"locality"
},
  "geometry": {"coordinates":[115.74629,26.80132],"type":"Point"}
}