{
  "type": "Feature",
  "properties": {
    "gn:admin1_code":"9.0",
    "gn:asciiname":"Liuwan",
    "gn:country_code":"CN",
    "gn:dem":156,
    "gn:feature_class":"P",
    "gn:feature_code":"PPL",
    "gn:name":"Liuwan",
    "gn:population":0,
    "gn:timezone":"Asia/Shanghai",
    "iso:country":"CN",
    "name:und_x_variant":[
        "\u67f3\u6e7e",
        "Liuwan"
    ],
    "wof:name":"Liuwan",
    "wof:placetype":"locality"
},
  "geometry": {"coordinates":[112.41826,33.05560999999999],"type":"Point"}
}