{
  "type": "Feature",
  "properties": {
    "gn:admin1_code":"18",
    "gn:asciiname":"Zhongba",
    "gn:country_code":"CN",
    "gn:dem":611,
    "gn:feature_class":"P",
    "gn:feature_code":"PPL",
    "gn:name":"Zhongba",
    "gn:population":0,
    "gn:timezone":"Asia/Shanghai",
    "iso:country":"CN",
    "name:ceb_x_preferred":[
        "Zhongba"
    ],
    "name:deu_x_preferred":[
        "Zhongba"
    ],
    "name:zho_x_preferred":[
        "\u4e2d\u575d"
    ],
    "wof:name":"Zhongba",
    "wof:placetype":"locality"
},
  "geometry": {"coordinates":[108.328,27.5819],"type":"Point"}
}