{
  "type": "Feature",
  "properties": {
    "gn:admin1_code":"9.0",
    "gn:asciiname":"Yangqiying",
    "gn:country_code":"CN",
    "gn:dem":156,
    "gn:feature_class":"P",
    "gn:feature_code":"PPL",
    "gn:name":"Yangqiying",
    "gn:population":0,
    "gn:timezone":"Asia/Shanghai",
    "iso:country":"CN",
    "name:zho_x_preferred":[
        "\u6768\u5176\u8425"
    ],
    "wof:name":"Yangqiying",
    "wof:placetype":"locality"
},
  "geometry": {"coordinates":[112.98757000000001,34.01527],"type":"Point"}
}