{
  "type": "Feature",
  "properties": {
    "gn:admin1_code":"30.0",
    "gn:asciiname":"Zhengjia",
    "gn:country_code":"CN",
    "gn:dem":304,
    "gn:feature_class":"P",
    "gn:feature_code":"PPL",
    "gn:name":"Zhengjia",
    "gn:population":0,
    "gn:timezone":"Asia/Shanghai",
    "iso:country":"CN",
    "name:zho_x_preferred":[
        "Zhengjia"
    ],
    "name:zho_x_variant":[
        "\u90d1\u5bb6"
    ],
    "wof:name":"Zhengjia",
    "wof:placetype":"locality"
},
  "geometry": {"coordinates":[113.09667,25.40139],"type":"Point"}
}