{
  "type": "Feature",
  "properties": {
    "gn:admin1_code":"15.0",
    "gn:asciiname":"Lahaka",
    "gn:country_code":"CN",
    "gn:dem":2780,
    "gn:feature_class":"P",
    "gn:feature_code":"PPL",
    "gn:name":"Lahaka",
    "gn:population":0,
    "gn:timezone":"Asia/Shanghai",
    "iso:country":"CN",
    "name:und_x_variant":[
        "\u62c9\u54c8\u5361"
    ],
    "wof:name":"Lahaka",
    "wof:placetype":"locality"
},
  "geometry": {"coordinates":[103.57574,34.00709000000001],"type":"Point"}
}