{
  "type": "Feature",
  "properties": {
    "gn:admin1_code":"16.0",
    "gn:asciiname":"Yaoguanchang",
    "gn:country_code":"CN",
    "gn:dem":1170,
    "gn:feature_class":"P",
    "gn:feature_code":"PPL",
    "gn:name":"Yaoguanchang",
    "gn:population":0,
    "gn:timezone":"Asia/Shanghai",
    "iso:country":"CN",
    "name:zho_x_preferred":[
        "\u7a91\u7f50\u5382"
    ],
    "wof:name":"Yaoguanchang",
    "wof:placetype":"locality"
},
  "geometry": {"coordinates":[107.032,24.8808],"type":"Point"}
}