{
  "type": "Feature",
  "properties": {
    "gn:admin1_code":"12.0",
    "gn:asciiname":"Hualiushu",
    "gn:country_code":"CN",
    "gn:dem":425,
    "gn:feature_class":"P",
    "gn:feature_code":"PPL",
    "gn:name":"Hualiushu",
    "gn:population":0,
    "gn:timezone":"Asia/Shanghai",
    "iso:country":"CN",
    "name:zho_x_preferred":[
        "\u82b1\u67f3\u6811"
    ],
    "wof:name":"Hualiushu",
    "wof:placetype":"locality"
},
  "geometry": {"coordinates":[110.83448,32.95567],"type":"Point"}
}