{
  "type": "Feature",
  "properties": {
    "gn:admin1_code":"16.0",
    "gn:asciiname":"Banlan",
    "gn:country_code":"CN",
    "gn:dem":151,
    "gn:feature_class":"P",
    "gn:feature_code":"PPL",
    "gn:name":"Banlan",
    "gn:population":0,
    "gn:timezone":"Asia/Shanghai",
    "iso:country":"CN",
    "name:zho_x_preferred":[
        "\u677f\u61d2"
    ],
    "wof:name":"Banlan",
    "wof:placetype":"locality"
},
  "geometry": {"coordinates":[107.059,22.4889],"type":"Point"}
}