{
  "type": "Feature",
  "properties": {
    "gn:admin1_code":"4.0",
    "gn:asciiname":"Fanrong Liuzu",
    "gn:country_code":"CN",
    "gn:dem":-1,
    "gn:feature_class":"P",
    "gn:feature_code":"PPLF",
    "gn:name":"Fanrong Liuzu",
    "gn:population":0,
    "gn:timezone":"Asia/Shanghai",
    "iso:country":"CN",
    "name:zho_x_preferred":[
        "\u7e41\u8363\u516d\u7ec4"
    ],
    "wof:name":"Fanrong Liuzu",
    "wof:placetype":"locality"
},
  "geometry": {"coordinates":[120.134,33.6249],"type":"Point"}
}