{
  "type": "Feature",
  "properties": {
    "gn:admin1_code":"8.0",
    "gn:asciiname":"Wangguozong",
    "gn:country_code":"CN",
    "gn:dem":119,
    "gn:feature_class":"P",
    "gn:feature_code":"PPL",
    "gn:name":"Wangguozong",
    "gn:population":0,
    "gn:timezone":"Asia/Shanghai",
    "iso:country":"CN",
    "name:zho_x_preferred":[
        "\u738b\u56fd\u5b97"
    ],
    "wof:name":"Wangguozong",
    "wof:placetype":"locality"
},
  "geometry": {"coordinates":[127.26403999999999,46.13714],"type":"Point"}
}