{
  "type": "Feature",
  "properties": {
    "gn:admin1_code":"31",
    "gn:asciiname":"Binglian",
    "gn:country_code":"CN",
    "gn:dem":38,
    "gn:feature_class":"P",
    "gn:feature_code":"PPL",
    "gn:name":"Binglian",
    "gn:population":0,
    "gn:timezone":"Asia/Shanghai",
    "iso:country":"CN",
    "name:und_x_variant":[
        "\u51b0\u5ec9"
    ],
    "wof:name":"Binglian",
    "wof:placetype":"locality"
},
  "geometry": {"coordinates":[109.65555999999999,19.83639],"type":"Point"}
}