{
  "type": "Feature",
  "properties": {
    "gn:admin1_code":"25",
    "gn:asciiname":"Ershi'er Wuzi",
    "gn:country_code":"CN",
    "gn:dem":2,
    "gn:feature_class":"P",
    "gn:feature_code":"PPL",
    "gn:name":"Ershi\u2019er Wuzi",
    "gn:population":0,
    "gn:timezone":"Asia/Shanghai",
    "iso:country":"CN",
    "name:und_x_variant":[
        "Ershi\u2019er Wuzi"
    ],
    "name:zho_x_preferred":[
        "\u4e8c\u5341\u4e8c\u5c4b\u5b50"
    ],
    "wof:name":"Ershi'er Wuzi",
    "wof:placetype":"locality"
},
  "geometry": {"coordinates":[118.761,38.0488],"type":"Point"}
}