{
  "type": "Feature",
  "properties": {
    "gn:admin1_code":"8.0",
    "gn:asciiname":"Yuquan",
    "gn:country_code":"CN",
    "gn:dem":114,
    "gn:feature_class":"P",
    "gn:feature_code":"PPL",
    "gn:name":"Yuquan",
    "gn:population":0,
    "gn:timezone":"Asia/Shanghai",
    "iso:country":"CN",
    "name:zho_x_preferred":[
        "\u7389\u6cc9"
    ],
    "wof:name":"Yuquan",
    "wof:placetype":"locality"
},
  "geometry": {"coordinates":[127.86505,45.90829],"type":"Point"}
}