{
  "type": "Feature",
  "properties": {
    "gn:admin1_code":"13",
    "gn:asciiname":"Qigaibulake",
    "gn:country_code":"CN",
    "gn:dem":1328,
    "gn:feature_class":"P",
    "gn:feature_code":"PPL",
    "gn:name":"Qigaibulake",
    "gn:population":0,
    "gn:timezone":"Asia/Urumqi",
    "iso:country":"CN",
    "name:zho_x_preferred":[
        "\u5176\u76d6\u5e03\u62c9\u514b"
    ],
    "wof:name":"Qigaibulake",
    "wof:placetype":"locality"
},
  "geometry": {"coordinates":[87.58354,41.22014],"type":"Point"}
}