{
  "type": "Feature",
  "properties": {
    "gn:admin1_code":"10",
    "gn:asciiname":"Junzibu",
    "gn:country_code":"CN",
    "gn:dem":1244,
    "gn:feature_class":"P",
    "gn:feature_code":"PPL",
    "gn:name":"Junzibu",
    "gn:population":0,
    "gn:timezone":"Asia/Shanghai",
    "iso:country":"CN",
    "name:und_x_variant":[
        "Junzibao"
    ],
    "name:zho_x_preferred":[
        "\u541b\u5b50\u5821"
    ],
    "wof:name":"Junzibu",
    "wof:placetype":"locality"
},
  "geometry": {"coordinates":[115.57306,41.22083],"type":"Point"}
}