{
  "type": "Feature",
  "properties": {
    "gn:admin1_code":"9",
    "gn:asciiname":"Wenzhuang",
    "gn:country_code":"CN",
    "gn:dem":55,
    "gn:feature_class":"P",
    "gn:feature_code":"PPL",
    "gn:name":"Wenzhuang",
    "gn:population":0,
    "gn:timezone":"Asia/Shanghai",
    "iso:country":"CN",
    "name:zho_x_preferred":[
        "\u95fb\u5e84"
    ],
    "wof:name":"Wenzhuang",
    "wof:placetype":"locality"
},
  "geometry": {"coordinates":[115.15000000000001,34.3107],"type":"Point"}
}