{
  "type": "Feature",
  "properties": {
    "gn:admin1_code":"19.0",
    "gn:asciiname":"Wuxiaoshantai",
    "gn:country_code":"CN",
    "gn:dem":100,
    "gn:feature_class":"P",
    "gn:feature_code":"PPL",
    "gn:name":"Wuxiaoshantai",
    "gn:population":0,
    "gn:timezone":"Asia/Shanghai",
    "iso:country":"CN",
    "name:zho_x_preferred":[
        "\u5434\u5c0f\u5c71\u53f0"
    ],
    "wof:name":"Wuxiaoshantai",
    "wof:placetype":"locality"
},
  "geometry": {"coordinates":[120.432,40.6176],"type":"Point"}
}