{
  "type": "Feature",
  "properties": {
    "gn:admin1_code":"12.0",
    "gn:asciiname":"Longbeifeng",
    "gn:country_code":"CN",
    "gn:dem":1209,
    "gn:feature_class":"P",
    "gn:feature_code":"PPL",
    "gn:name":"Longbeifeng",
    "gn:population":0,
    "gn:timezone":"Asia/Shanghai",
    "iso:country":"CN",
    "name:zho_x_preferred":[
        "\u9f99\u80cc\u98ce"
    ],
    "wof:name":"Longbeifeng",
    "wof:placetype":"locality"
},
  "geometry": {"coordinates":[111.47581,31.557],"type":"Point"}
}