{
  "type": "Feature",
  "properties": {
    "gn:admin1_code":"9.0",
    "gn:asciiname":"Shanmeng",
    "gn:country_code":"CN",
    "gn:dem":120,
    "gn:feature_class":"P",
    "gn:feature_code":"PPL",
    "gn:name":"Shanmeng",
    "gn:population":0,
    "gn:timezone":"Asia/Shanghai",
    "iso:country":"CN",
    "name:zho_x_preferred":[
        "\u5c71\u5b5f\u5c97"
    ],
    "wof:name":"Shanmeng",
    "wof:placetype":"locality"
},
  "geometry": {"coordinates":[113.44110999999999,33.39209],"type":"Point"}
}