{
  "type": "Feature",
  "properties": {
    "gn:admin1_code":"5.0",
    "gn:asciiname":"Xiachaijiatun",
    "gn:country_code":"CN",
    "gn:dem":170,
    "gn:feature_class":"P",
    "gn:feature_code":"PPL",
    "gn:name":"Xiachaijiatun",
    "gn:population":0,
    "gn:timezone":"Asia/Shanghai",
    "iso:country":"CN",
    "name:zho_x_preferred":[
        "\u4e0b\u67f4\u5bb6\u5c6f"
    ],
    "wof:name":"Xiachaijiatun",
    "wof:placetype":"locality"
},
  "geometry": {"coordinates":[124.4464,43.31591],"type":"Point"}
}