{
  "type": "Feature",
  "properties": {
    "gn:admin1_code":"8.0",
    "gn:asciiname":"Yishengcun",
    "gn:country_code":"CN",
    "gn:dem":169,
    "gn:feature_class":"P",
    "gn:feature_code":"PPL",
    "gn:name":"Yishengcun",
    "gn:population":0,
    "gn:timezone":"Asia/Shanghai",
    "iso:country":"CN",
    "name:zho_x_preferred":[
        "\u76ca\u80dc\u6751"
    ],
    "wof:name":"Yishengcun",
    "wof:placetype":"locality"
},
  "geometry": {"coordinates":[126.55483,45.34175],"type":"Point"}
}