{
  "type": "Feature",
  "properties": {
    "gn:admin1_code":"11.0",
    "gn:asciiname":"Babaopushang",
    "gn:country_code":"CN",
    "gn:dem":171,
    "gn:feature_class":"P",
    "gn:feature_code":"PPL",
    "gn:name":"Babaopushang",
    "gn:population":0,
    "gn:timezone":"Asia/Shanghai",
    "iso:country":"CN",
    "name:zho_x_preferred":[
        "\u516b\u5b9d\u94fa\u4e0a"
    ],
    "wof:name":"Babaopushang",
    "wof:placetype":"locality"
},
  "geometry": {"coordinates":[113.16318,26.00683],"type":"Point"}
}