{
  "type": "Feature",
  "properties": {
    "gn:admin1_code":"19.0",
    "gn:asciiname":"Badaguzi",
    "gn:country_code":"CN",
    "gn:dem":238,
    "gn:feature_class":"P",
    "gn:feature_code":"PPL",
    "gn:name":"Badaguzi",
    "gn:population":0,
    "gn:timezone":"Asia/Shanghai",
    "iso:country":"CN",
    "name:und_x_variant":[
        "\u516b\u5927\u80a1\u5b50"
    ],
    "name:zho_x_preferred":[
        "\u516b\u5927\u80a1\u5b50"
    ],
    "wof:name":"Badaguzi",
    "wof:placetype":"locality"
},
  "geometry": {"coordinates":[122.56261000000001,42.7941],"type":"Point"}
}