{
  "type": "Feature",
  "properties": {
    "gn:admin1_code":"29.0",
    "gn:asciiname":"Mangla",
    "gn:country_code":"CN",
    "gn:dem":814,
    "gn:feature_class":"P",
    "gn:feature_code":"PPL",
    "gn:name":"Mangla",
    "gn:population":0,
    "gn:timezone":"Asia/Shanghai",
    "iso:country":"CN",
    "name:pol_x_preferred":[
        "Mangla"
    ],
    "name:por_x_preferred":[
        "Mangla"
    ],
    "name:urd_x_preferred":[
        "\u0645\u0646\u06af\u0644\u0627"
    ],
    "name:zho_x_preferred":[
        "\u5fd9\u814a"
    ],
    "wof:name":"Mangla",
    "wof:placetype":"locality"
},
  "geometry": {"coordinates":[99.3826,24.1391],"type":"Point"}
}