{
  "type": "Feature",
  "properties": {
    "gn:admin1_code":"30.0",
    "gn:asciiname":"Dishiwei",
    "gn:country_code":"CN",
    "gn:dem":-1,
    "gn:feature_class":"P",
    "gn:feature_code":"PPL",
    "gn:name":"Dishiwei",
    "gn:population":0,
    "gn:timezone":"Asia/Shanghai",
    "iso:country":"CN",
    "name:zho_x_preferred":[
        "\u7b2c\u5341\u56f4"
    ],
    "wof:name":"Dishiwei",
    "wof:placetype":"locality"
},
  "geometry": {"coordinates":[113.43937,22.27528],"type":"Point"}
}