{
  "type": "Feature",
  "properties": {
    "gn:admin1_code":"8.0",
    "gn:asciiname":"Qianfengtun",
    "gn:country_code":"CN",
    "gn:dem":60,
    "gn:feature_class":"P",
    "gn:feature_code":"PPL",
    "gn:name":"Qianfengtun",
    "gn:population":0,
    "gn:timezone":"Asia/Shanghai",
    "iso:country":"CN",
    "name:zho_x_preferred":[
        "\u524d\u950b\u5c6f"
    ],
    "wof:name":"Qianfengtun",
    "wof:placetype":"locality"
},
  "geometry": {"coordinates":[131.50961000000001,47.69523],"type":"Point"}
}