{
  "type": "Feature",
  "properties": {
    "gn:admin1_code":"15.0",
    "gn:asciiname":"Zhaojiawan",
    "gn:country_code":"CN",
    "gn:dem":1992,
    "gn:feature_class":"P",
    "gn:feature_code":"PPL",
    "gn:name":"Zhaojiawan",
    "gn:population":0,
    "gn:timezone":"Asia/Shanghai",
    "iso:country":"CN",
    "name:und_x_variant":[
        "\u8d75\u5bb6\u6e7e"
    ],
    "wof:name":"Zhaojiawan",
    "wof:placetype":"locality"
},
  "geometry": {"coordinates":[105.32498,35.74845],"type":"Point"}
}