{
  "type": "Feature",
  "properties": {
    "gn:admin1_code":"29.0",
    "gn:asciiname":"Jiejigou",
    "gn:country_code":"CN",
    "gn:dem":2471,
    "gn:feature_class":"P",
    "gn:feature_code":"PPL",
    "gn:name":"Jiejigou",
    "gn:population":0,
    "gn:timezone":"Asia/Shanghai",
    "iso:country":"CN",
    "name:zho_x_preferred":[
        "\u8282\u796d\u6c9f"
    ],
    "wof:name":"Jiejigou",
    "wof:placetype":"locality"
},
  "geometry": {"coordinates":[103.367,26.7221],"type":"Point"}
}