{
  "type": "Feature",
  "properties": {
    "gn:admin1_code":"3.0",
    "gn:asciiname":"Shiyunkeng",
    "gn:country_code":"CN",
    "gn:dem":138,
    "gn:feature_class":"P",
    "gn:feature_code":"PPL",
    "gn:name":"Shiyunkeng",
    "gn:population":0,
    "gn:timezone":"Asia/Shanghai",
    "iso:country":"CN",
    "name:und_x_variant":[
        "\u77f3\u4e91\u5751"
    ],
    "wof:name":"Shiyunkeng",
    "wof:placetype":"locality"
},
  "geometry": {"coordinates":[115.52276999999999,26.02973],"type":"Point"}
}