{
  "type": "Feature",
  "properties": {
    "gn:admin1_code":"32.0",
    "gn:asciiname":"Dengxia",
    "gn:country_code":"CN",
    "gn:dem":2839,
    "gn:feature_class":"P",
    "gn:feature_code":"PPL",
    "gn:name":"Dengxia",
    "gn:population":0,
    "gn:timezone":"Asia/Shanghai",
    "iso:country":"CN",
    "name:zho_x_preferred":[
        "\u9093\u590f"
    ],
    "wof:name":"Dengxia",
    "wof:placetype":"locality"
},
  "geometry": {"coordinates":[101.03700000000001,29.2457],"type":"Point"}
}