{
  "type": "Feature",
  "properties": {
    "gn:admin1_code":"4.0",
    "gn:asciiname":"Hongqi",
    "gn:country_code":"CN",
    "gn:dem":3,
    "gn:feature_class":"P",
    "gn:feature_code":"PPL",
    "gn:name":"Hongqi",
    "gn:population":0,
    "gn:timezone":"Asia/Shanghai",
    "iso:country":"CN",
    "name:ceb_x_preferred":[
        "Hongqi"
    ],
    "name:deu_x_preferred":[
        "Hongqi"
    ],
    "name:fra_x_preferred":[
        "Hongqi"
    ],
    "name:nor_x_preferred":[
        "Hongqi"
    ],
    "name:zho_x_preferred":[
        "\u7ea2\u65d7"
    ],
    "wof:name":"Hongqi",
    "wof:placetype":"locality"
},
  "geometry": {"coordinates":[120.22597,32.06597],"type":"Point"}
}