{
  "type": "Feature",
  "properties": {
    "gn:admin1_code":"7.0",
    "gn:asciiname":"Lijiazhan",
    "gn:country_code":"CN",
    "gn:dem":171,
    "gn:feature_class":"P",
    "gn:feature_code":"PPL",
    "gn:name":"Lijiazhan",
    "gn:population":0,
    "gn:timezone":"Asia/Shanghai",
    "iso:country":"CN",
    "name:und_x_variant":[
        "\u674e\u5bb6\u576a"
    ],
    "name:zho_x_preferred":[
        "Lijiazhan"
    ],
    "wof:name":"Lijiazhan",
    "wof:placetype":"locality"
},
  "geometry": {"coordinates":[119.23793000000001,26.14722],"type":"Point"}
}