{
  "type": "Feature",
  "properties": {
    "gn:admin1_code":"25.0",
    "gn:asciiname":"Niubaikoucun",
    "gn:country_code":"CN",
    "gn:dem":55,
    "gn:feature_class":"P",
    "gn:feature_code":"PPL",
    "gn:name":"Niubaikoucun",
    "gn:population":0,
    "gn:timezone":"Asia/Shanghai",
    "iso:country":"CN",
    "name:zho_x_preferred":[
        "\u725b\u767e\u53e3\u6751"
    ],
    "wof:name":"Niubaikoucun",
    "wof:placetype":"locality"
},
  "geometry": {"coordinates":[120.67022,36.84684],"type":"Point"}
}