{
  "type": "Feature",
  "properties": {
    "gn:admin1_code":"14.0",
    "gn:asciiname":"Langbu",
    "gn:country_code":"CN",
    "gn:dem":3400,
    "gn:feature_class":"P",
    "gn:feature_code":"PPL",
    "gn:name":"Langbu",
    "gn:population":0,
    "gn:timezone":"Asia/Urumqi",
    "iso:country":"CN",
    "name:zho_x_preferred":[
        "\u6717\u5e03"
    ],
    "wof:name":"Langbu",
    "wof:placetype":"locality"
},
  "geometry": {"coordinates":[85.4392,28.4468],"type":"Point"}
}