{
  "type": "Feature",
  "properties": {
    "gn:admin1_code":"3.0",
    "gn:asciiname":"Feizhuwu",
    "gn:country_code":"CN",
    "gn:dem":46,
    "gn:feature_class":"P",
    "gn:feature_code":"PPL",
    "gn:name":"Feizhuwu",
    "gn:population":0,
    "gn:timezone":"Asia/Shanghai",
    "iso:country":"CN",
    "name:zho_x_preferred":[
        "\u80a5\u732a\u575e"
    ],
    "wof:name":"Feizhuwu",
    "wof:placetype":"locality"
},
  "geometry": {"coordinates":[116.97,29.1984],"type":"Point"}
}