{
  "type": "Feature",
  "properties": {
    "gn:admin1_code":"29.0",
    "gn:asciiname":"Xiamanpin",
    "gn:country_code":"CN",
    "gn:dem":1675,
    "gn:feature_class":"P",
    "gn:feature_code":"PPL",
    "gn:name":"Xiamanpin",
    "gn:population":0,
    "gn:timezone":"Asia/Shanghai",
    "iso:country":"CN",
    "name:zho_x_preferred":[
        "\u4e0b\u6162\u54c1"
    ],
    "wof:name":"Xiamanpin",
    "wof:placetype":"locality"
},
  "geometry": {"coordinates":[99.9365,24.0523],"type":"Point"}
}