{
  "type": "Feature",
  "properties": {
    "gn:admin1_code":"12.0",
    "gn:asciiname":"Kongzhi",
    "gn:country_code":"CN",
    "gn:dem":28,
    "gn:feature_class":"P",
    "gn:feature_code":"PPL",
    "gn:name":"Kongzhi",
    "gn:population":0,
    "gn:timezone":"Asia/Shanghai",
    "iso:country":"CN",
    "name:zho_x_preferred":[
        "Kongzhi"
    ],
    "name:zho_x_variant":[
        "\u5b54\u5fd7"
    ],
    "wof:name":"Kongzhi",
    "wof:placetype":"locality"
},
  "geometry": {"coordinates":[114.94414999999999,29.70071],"type":"Point"}
}