{
  "type": "Feature",
  "properties": {
    "gn:admin1_code":"19.0",
    "gn:asciiname":"Anjiawobu",
    "gn:country_code":"CN",
    "gn:dem":71,
    "gn:feature_class":"P",
    "gn:feature_code":"PPL",
    "gn:name":"Anjiawobu",
    "gn:population":0,
    "gn:timezone":"Asia/Shanghai",
    "iso:country":"CN",
    "name:zho_x_preferred":[
        "\u5b89\u5bb6\u7a9d\u5821"
    ],
    "wof:name":"Anjiawobu",
    "wof:placetype":"locality"
},
  "geometry": {"coordinates":[122.43600000000001,42.2474],"type":"Point"}
}