{
  "type": "Feature",
  "properties": {
    "gn:admin1_code":"4.0",
    "gn:asciiname":"Tangming",
    "gn:country_code":"CN",
    "gn:dem":4,
    "gn:feature_class":"P",
    "gn:feature_code":"PPL",
    "gn:name":"Tangming",
    "gn:population":0,
    "gn:timezone":"Asia/Shanghai",
    "iso:country":"CN",
    "name:zho_x_preferred":[
        "\u6c64\u94ed"
    ],
    "wof:name":"Tangming",
    "wof:placetype":"locality"
},
  "geometry": {"coordinates":[120.44444,32.9841],"type":"Point"}
}