{
  "type": "Feature",
  "properties": {
    "gn:admin1_code":"24.0",
    "gn:asciiname":"Yumuqiao",
    "gn:country_code":"CN",
    "gn:dem":1427,
    "gn:feature_class":"P",
    "gn:feature_code":"PPL",
    "gn:name":"Yumuqiao",
    "gn:population":0,
    "gn:timezone":"Asia/Shanghai",
    "iso:country":"CN",
    "name:zho_x_preferred":[
        "\u6986\u6728\u6865"
    ],
    "wof:name":"Yumuqiao",
    "wof:placetype":"locality"
},
  "geometry": {"coordinates":[112.04139000000001,38.6369],"type":"Point"}
}