{
  "type": "Feature",
  "properties": {
    "gn:admin1_code":"29",
    "gn:asciiname":"Xialinse",
    "gn:country_code":"CN",
    "gn:dem":1002,
    "gn:feature_class":"P",
    "gn:feature_code":"PPL",
    "gn:name":"Xialinse",
    "gn:population":0,
    "gn:timezone":"Asia/Shanghai",
    "iso:country":"CN",
    "name:zho_x_preferred":[
        "\u4e0b\u6797\u8272"
    ],
    "wof:name":"Xialinse",
    "wof:placetype":"locality"
},
  "geometry": {"coordinates":[105.708,23.6483],"type":"Point"}
}