{
  "type": "Feature",
  "properties": {
    "gn:admin1_code":"05",
    "gn:asciiname":"Sandaogangzi",
    "gn:country_code":"CN",
    "gn:dem":247,
    "gn:feature_class":"P",
    "gn:feature_code":"PPL",
    "gn:name":"Sandaogangzi",
    "gn:population":0,
    "gn:timezone":"Asia/Shanghai",
    "iso:country":"CN",
    "wof:name":"Sandaogangzi",
    "wof:placetype":"locality"
},
  "geometry": {"coordinates":[125.02943999999999,43.25639],"type":"Point"}
}