{
  "type": "Feature",
  "properties": {
    "gn:admin1_code":"19.0",
    "gn:asciiname":"Xi'erlao",
    "gn:country_code":"CN",
    "gn:dem":111,
    "gn:feature_class":"P",
    "gn:feature_code":"PPL",
    "gn:name":"Xi\u2019erlao",
    "gn:population":0,
    "gn:timezone":"Asia/Shanghai",
    "iso:country":"CN",
    "name:und_x_variant":[
        "\u897f\u4e8c\u8001"
    ],
    "name:zho_x_preferred":[
        "Xi\u2019erlao"
    ],
    "name:zho_x_variant":[
        "\u897f\u4e8c\u8001"
    ],
    "wof:name":"Xi'erlao",
    "wof:placetype":"locality"
},
  "geometry": {"coordinates":[122.42246000000002,42.5013],"type":"Point"}
}