{
  "type": "Feature",
  "properties": {
    "gn:admin1_code":"19.0",
    "gn:asciiname":"Tonglingcun",
    "gn:country_code":"CN",
    "gn:dem":77,
    "gn:feature_class":"P",
    "gn:feature_code":"PPL",
    "gn:name":"Tonglingcun",
    "gn:population":0,
    "gn:timezone":"Asia/Shanghai",
    "iso:country":"CN",
    "name:zho_x_preferred":[
        "\u4f5f\u5cad\u6751"
    ],
    "wof:name":"Tonglingcun",
    "wof:placetype":"locality"
},
  "geometry": {"coordinates":[122.79597,39.81969],"type":"Point"}
}