{
  "type": "Feature",
  "properties": {
    "gn:admin1_code":"16.0",
    "gn:asciiname":"Mozhidong",
    "gn:country_code":"CN",
    "gn:dem":286,
    "gn:feature_class":"P",
    "gn:feature_code":"PPL",
    "gn:name":"Mozhidong",
    "gn:population":0,
    "gn:timezone":"Asia/Shanghai",
    "iso:country":"CN",
    "name:zho_x_preferred":[
        "\u83ab\u6cbb\u5cd2"
    ],
    "wof:name":"Mozhidong",
    "wof:placetype":"locality"
},
  "geometry": {"coordinates":[108.518,24.4298],"type":"Point"}
}