{
  "type": "Feature",
  "properties": {
    "gn:admin1_code":"8.0",
    "gn:asciiname":"Zhouyutangcun",
    "gn:country_code":"CN",
    "gn:dem":148,
    "gn:feature_class":"P",
    "gn:feature_code":"PPL",
    "gn:name":"Zhouyutangcun",
    "gn:population":0,
    "gn:timezone":"Asia/Shanghai",
    "iso:country":"CN",
    "name:zho_x_preferred":[
        "\u5468\u7389\u5802\u6751"
    ],
    "wof:name":"Zhouyutangcun",
    "wof:placetype":"locality"
},
  "geometry": {"coordinates":[129.86267000000001,46.13265],"type":"Point"}
}