{
  "type": "Feature",
  "properties": {
    "gn:admin1_code":"1.0",
    "gn:asciiname":"Wanquan",
    "gn:country_code":"CN",
    "gn:dem":17,
    "gn:feature_class":"P",
    "gn:feature_code":"PPL",
    "gn:name":"Wanquan",
    "gn:population":0,
    "gn:timezone":"Asia/Shanghai",
    "iso:country":"CN",
    "name:ceb_x_preferred":[
        "Wanquan"
    ],
    "name:deu_x_preferred":[
        "Wanquan"
    ],
    "name:zho_x_preferred":[
        "Wanquan"
    ],
    "name:zho_x_variant":[
        "\u4e07\u5168"
    ],
    "wof:name":"Wanquan",
    "wof:placetype":"locality"
},
  "geometry": {"coordinates":[119.2381,31.02867],"type":"Point"}
}