{
  "type": "Feature",
  "properties": {
    "gn:admin1_code":"15.0",
    "gn:asciiname":"Jianhua",
    "gn:country_code":"CN",
    "gn:dem":1913,
    "gn:feature_class":"P",
    "gn:feature_code":"PPL",
    "gn:name":"Jianhua",
    "gn:population":0,
    "gn:timezone":"Asia/Shanghai",
    "iso:country":"CN",
    "name:und_x_variant":[
        "\u5efa\u534e"
    ],
    "name:zho_x_preferred":[
        "\u5efa\u534e"
    ],
    "wof:name":"Jianhua",
    "wof:placetype":"locality"
},
  "geometry": {"coordinates":[104.69842,33.07719],"type":"Point"}
}