{
  "type": "Feature",
  "properties": {
    "gn:admin1_code":"30",
    "gn:asciiname":"Shangguotou",
    "gn:country_code":"CN",
    "gn:dem":8,
    "gn:feature_class":"P",
    "gn:feature_code":"PPL",
    "gn:name":"Shangguotou",
    "gn:population":0,
    "gn:timezone":"Asia/Urumqi",
    "iso:country":"CN",
    "name:zho_x_preferred":[
        "\u4e0a\u90ed\u5934"
    ],
    "wof:name":"Shangguotou",
    "wof:placetype":"locality"
},
  "geometry": {"coordinates":[110.49275,21.2065],"type":"Point"}
}