{
  "type": "Feature",
  "properties": {
    "gn:admin1_code":"11",
    "gn:asciiname":"Liexi",
    "gn:country_code":"CN",
    "gn:dem":384,
    "gn:feature_class":"P",
    "gn:feature_code":"PPLA4",
    "gn:name":"Liexi",
    "gn:population":0,
    "gn:timezone":"Asia/Shanghai",
    "iso:country":"CN",
    "name:und_x_variant":[
        "Liexi Xiang"
    ],
    "name:zho_x_preferred":[
        "\u5217\u5915"
    ],
    "name:zho_x_variant":[
        "\u5217\u5915\u4e61"
    ],
    "wof:name":"Liexi",
    "wof:placetype":"locality"
},
  "geometry": {"coordinates":[109.83238,28.78611],"type":"Point"}
}