{
  "type": "Feature",
  "properties": {
    "gn:admin1_code":"18.0",
    "gn:asciiname":"Zaigao",
    "gn:country_code":"CN",
    "gn:dem":328,
    "gn:feature_class":"P",
    "gn:feature_code":"PPL",
    "gn:name":"Zaigao",
    "gn:population":0,
    "gn:timezone":"Asia/Shanghai",
    "iso:country":"CN",
    "name:zho_x_preferred":[
        "\u5bb0\u544a"
    ],
    "wof:name":"Zaigao",
    "wof:placetype":"locality"
},
  "geometry": {"coordinates":[108.55800000000001,25.9476],"type":"Point"}
}