{
  "type": "Feature",
  "properties": {
    "gn:admin1_code":"33.0",
    "gn:asciiname":"Dongcheng",
    "gn:country_code":"CN",
    "gn:dem":293,
    "gn:feature_class":"P",
    "gn:feature_code":"PPLA4",
    "gn:name":"Dongcheng",
    "gn:population":0,
    "gn:timezone":"Asia/Shanghai",
    "iso:country":"CN",
    "name:ceb_x_preferred":[
        "Dongcheng"
    ],
    "name:deu_x_preferred":[
        "Dongcheng"
    ],
    "name:eus_x_preferred":[
        "Dongcheng"
    ],
    "name:nld_x_preferred":[
        "Dongcheng"
    ],
    "name:und_x_variant":[
        "Dongcheng Jiedao"
    ],
    "name:zho_x_preferred":[
        "\u4e1c\u57ce"
    ],
    "name:zho_x_variant":[
        "\u4e1c\u57ce\u8857\u9053"
    ],
    "wof:name":"Dongcheng",
    "wof:placetype":"locality"
},
  "geometry": {"coordinates":[106.07326,29.84775],"type":"Point"}
}