{
  "type": "Feature",
  "properties": {
    "gn:admin1_code":"8.0",
    "gn:asciiname":"Xingwangcun",
    "gn:country_code":"CN",
    "gn:dem":174,
    "gn:feature_class":"P",
    "gn:feature_code":"PPL",
    "gn:name":"Xingwangcun",
    "gn:population":0,
    "gn:timezone":"Asia/Shanghai",
    "iso:country":"CN",
    "name:zho_x_preferred":[
        "\u5174\u65fa\u6751"
    ],
    "wof:name":"Xingwangcun",
    "wof:placetype":"locality"
},
  "geometry": {"coordinates":[126.49138000000001,45.38025],"type":"Point"}
}