{
  "type": "Feature",
  "properties": {
    "gn:admin1_code":"22",
    "gn:asciiname":"Xifuying",
    "gn:country_code":"CN",
    "gn:dem":494,
    "gn:feature_class":"P",
    "gn:feature_code":"PPL",
    "gn:name":"Xifuying",
    "gn:population":0,
    "gn:timezone":"Asia/Shanghai",
    "iso:country":"CN",
    "name:und_x_variant":[
        "Hsi-fu-ying",
        "Xifuying"
    ],
    "name:zho_x_preferred":[
        "\u897f\u82fb\u8425"
    ],
    "wof:name":"Xifuying",
    "wof:placetype":"locality"
},
  "geometry": {"coordinates":[116.62031,40.92988],"type":"Point"}
}