{
  "type": "Feature",
  "properties": {
    "gn:admin1_code":"24",
    "gn:asciiname":"Hujiayaocun",
    "gn:country_code":"CN",
    "gn:dem":1178,
    "gn:feature_class":"P",
    "gn:feature_code":"PPL",
    "gn:name":"Hujiayaocun",
    "gn:population":0,
    "gn:timezone":"Asia/Shanghai",
    "iso:country":"CN",
    "name:und_x_variant":[
        "Hu-chia-yao",
        "Hujiayao",
        "Hujiayaocun"
    ],
    "name:zho_x_preferred":[
        "\u80e1\u5bb6\u7a91\u6751"
    ],
    "wof:name":"Hujiayaocun",
    "wof:placetype":"locality"
},
  "geometry": {"coordinates":[113.20065,40.37548],"type":"Point"}
}