{
  "type": "Feature",
  "properties": {
    "gn:admin1_code":"29.0",
    "gn:asciiname":"Laben'oubian",
    "gn:country_code":"CN",
    "gn:dem":1774,
    "gn:feature_class":"P",
    "gn:feature_code":"PPL",
    "gn:name":"Laben\u2019oubian",
    "gn:population":0,
    "gn:timezone":"Asia/Shanghai",
    "iso:country":"CN",
    "name:und_x_variant":[
        "Laben\u2019oubian"
    ],
    "name:zho_x_preferred":[
        "\u814a\u672c\u6b27\u6241"
    ],
    "wof:name":"Laben'oubian",
    "wof:placetype":"locality"
},
  "geometry": {"coordinates":[98.837,26.172],"type":"Point"}
}