{
  "type": "Feature",
  "properties": {
    "gn:admin1_code":"11",
    "gn:asciiname":"Laowu Xiangjia",
    "gn:country_code":"CN",
    "gn:dem":307,
    "gn:feature_class":"P",
    "gn:feature_code":"PPL",
    "gn:name":"Laowu Xiangjia",
    "gn:population":0,
    "gn:timezone":"Asia/Shanghai",
    "iso:country":"CN",
    "name:zho_x_preferred":[
        "\u8001\u5c4b\u5411\u5bb6"
    ],
    "wof:name":"Laowu Xiangjia",
    "wof:placetype":"locality"
},
  "geometry": {"coordinates":[111.55252,26.96458],"type":"Point"}
}