{
  "type": "Feature",
  "properties": {
    "gn:admin1_code":"4.0",
    "gn:asciiname":"Sixuqiao",
    "gn:country_code":"CN",
    "gn:dem":5,
    "gn:feature_class":"P",
    "gn:feature_code":"PPL",
    "gn:name":"Sixuqiao",
    "gn:population":0,
    "gn:timezone":"Asia/Shanghai",
    "iso:country":"CN",
    "name:und_x_variant":[
        "\u56db\u5729\u6865"
    ],
    "wof:name":"Sixuqiao",
    "wof:placetype":"locality"
},
  "geometry": {"coordinates":[120.94136,31.95629000000001],"type":"Point"}
}