{
  "type": "Feature",
  "properties": {
    "gn:admin1_code":"9.0",
    "gn:asciiname":"Zhangkuanzhuang",
    "gn:country_code":"CN",
    "gn:dem":89,
    "gn:feature_class":"P",
    "gn:feature_code":"PPL",
    "gn:name":"Zhangkuanzhuang",
    "gn:population":0,
    "gn:timezone":"Asia/Shanghai",
    "iso:country":"CN",
    "name:zho_x_preferred":[
        "\u5f20\u5bbd\u5e84"
    ],
    "wof:name":"Zhangkuanzhuang",
    "wof:placetype":"locality"
},
  "geometry": {"coordinates":[113.51170999999999,33.39155],"type":"Point"}
}