{
  "type": "Feature",
  "properties": {
    "gn:admin1_code":"33.0",
    "gn:asciiname":"Jinshan",
    "gn:country_code":"CN",
    "gn:dem":300,
    "gn:feature_class":"P",
    "gn:feature_code":"PPL",
    "gn:name":"Jinshan",
    "gn:population":0,
    "gn:timezone":"Asia/Shanghai",
    "iso:country":"CN",
    "name:ceb_x_preferred":[
        "Jinshan"
    ],
    "name:deu_x_preferred":[
        "Jinshan"
    ],
    "name:sco_x_preferred":[
        "Jinshan"
    ],
    "name:swe_x_preferred":[
        "Jinshan"
    ],
    "name:zho_x_preferred":[
        "\u91d1\u5c71"
    ],
    "wof:name":"Jinshan",
    "wof:placetype":"locality"
},
  "geometry": {"coordinates":[105.87389,29.68742],"type":"Point"}
}