{
  "type": "Feature",
  "properties": {
    "gn:admin1_code":"4.0",
    "gn:asciiname":"Yaowangcun",
    "gn:country_code":"CN",
    "gn:dem":5,
    "gn:feature_class":"P",
    "gn:feature_code":"PPL",
    "gn:name":"Yaowangcun",
    "gn:population":0,
    "gn:timezone":"Asia/Shanghai",
    "iso:country":"CN",
    "name:zho_x_preferred":[
        "\u836f\u738b\u6751"
    ],
    "wof:name":"Yaowangcun",
    "wof:placetype":"locality"
},
  "geometry": {"coordinates":[119.20453000000001,32.9231],"type":"Point"}
}