{
  "type": "Feature",
  "properties": {
    "gn:admin1_code":"12.0",
    "gn:asciiname":"Taiyangling",
    "gn:country_code":"CN",
    "gn:dem":659,
    "gn:feature_class":"P",
    "gn:feature_code":"PPL",
    "gn:name":"Taiyangling",
    "gn:population":0,
    "gn:timezone":"Asia/Shanghai",
    "iso:country":"CN",
    "name:zho_x_preferred":[
        "\u592a\u9633\u5cad"
    ],
    "wof:name":"Taiyangling",
    "wof:placetype":"locality"
},
  "geometry": {"coordinates":[110.59684,31.15097],"type":"Point"}
}