{
  "type": "Feature",
  "properties": {
    "gn:admin1_code":"10.0",
    "gn:asciiname":"Nanyuanxilou",
    "gn:country_code":"CN",
    "gn:dem":12,
    "gn:feature_class":"P",
    "gn:feature_code":"PPL",
    "gn:name":"Nanyuanxilou",
    "gn:population":0,
    "gn:timezone":"Asia/Shanghai",
    "iso:country":"CN",
    "name:zho_x_preferred":[
        "\u5357\u56ed\u897f\u697c"
    ],
    "wof:name":"Nanyuanxilou",
    "wof:placetype":"locality"
},
  "geometry": {"coordinates":[119.73721999999999,39.99751],"type":"Point"}
}