{
  "type": "Feature",
  "properties": {
    "gn:admin1_code":"12.0",
    "gn:asciiname":"Dapengjiawan",
    "gn:country_code":"CN",
    "gn:dem":40,
    "gn:feature_class":"P",
    "gn:feature_code":"PPL",
    "gn:name":"Dapengjiawan",
    "gn:population":0,
    "gn:timezone":"Asia/Shanghai",
    "iso:country":"CN",
    "name:zho_x_preferred":[
        "\u5927\u5f6d\u5bb6\u6e7e"
    ],
    "wof:name":"Dapengjiawan",
    "wof:placetype":"locality"
},
  "geometry": {"coordinates":[112.52643999999999,30.62541],"type":"Point"}
}