{
  "type": "Feature",
  "properties": {
    "gn:admin1_code":"18.0",
    "gn:asciiname":"Jiaoliang",
    "gn:country_code":"CN",
    "gn:dem":963,
    "gn:feature_class":"P",
    "gn:feature_code":"PPL",
    "gn:name":"Jiaoliang",
    "gn:population":0,
    "gn:timezone":"Asia/Shanghai",
    "iso:country":"CN",
    "name:zho_x_preferred":[
        "\u811a\u4e24"
    ],
    "wof:name":"Jiaoliang",
    "wof:placetype":"locality"
},
  "geometry": {"coordinates":[108.121,26.2974],"type":"Point"}
}