{
  "type": "Feature",
  "properties": {
    "gn:admin1_code":"04",
    "gn:asciiname":"Xiejiaqiao",
    "gn:cc2":"CN",
    "gn:country_code":"CN",
    "gn:dem":6,
    "gn:feature_class":"P",
    "gn:feature_code":"PPL",
    "gn:name":"Xiejiaqiao",
    "gn:population":0,
    "gn:timezone":"Asia/Shanghai",
    "iso:country":"CN",
    "name:und_x_variant":[
        "Hsieh-chia-ch\u2019iao",
        "Xiejiaqiao"
    ],
    "wof:name":"Xiejiaqiao",
    "wof:placetype":"locality"
},
  "geometry": {"coordinates":[121.04583,32.28194000000001],"type":"Point"}
}