{
  "type": "Feature",
  "properties": {
    "gn:admin1_code":"14.0",
    "gn:asciiname":"Gaijiaka",
    "gn:country_code":"CN",
    "gn:dem":5094,
    "gn:feature_class":"P",
    "gn:feature_code":"PPL",
    "gn:name":"Gaijiaka",
    "gn:population":0,
    "gn:timezone":"Asia/Urumqi",
    "iso:country":"CN",
    "name:bod_x_preferred":[
        "Kai\u2019gyaka"
    ],
    "name:zho_x_preferred":[
        "Gaijiaka"
    ],
    "name:zho_x_variant":[
        "\u76d6\u52a0\u5361"
    ],
    "wof:name":"Gaijiaka",
    "wof:placetype":"locality"
},
  "geometry": {"coordinates":[94.04000000000001,32.206],"type":"Point"}
}