{
  "type": "Feature",
  "properties": {
    "gn:admin1_code":"32.0",
    "gn:asciiname":"Azhiwu",
    "gn:country_code":"CN",
    "gn:dem":1960,
    "gn:feature_class":"P",
    "gn:feature_code":"PPL",
    "gn:name":"Azhiwu",
    "gn:population":0,
    "gn:timezone":"Asia/Shanghai",
    "iso:country":"CN",
    "name:zho_x_preferred":[
        "\u963f\u652f\u543e"
    ],
    "wof:name":"Azhiwu",
    "wof:placetype":"locality"
},
  "geometry": {"coordinates":[102.598,28.6548],"type":"Point"}
}