{
  "type": "Feature",
  "properties": {
    "gn:admin1_code":"20.0",
    "gn:asciiname":"Yonghengdui",
    "gn:country_code":"CN",
    "gn:dem":319,
    "gn:feature_class":"P",
    "gn:feature_code":"PPLF",
    "gn:name":"Yonghengdui",
    "gn:population":0,
    "gn:timezone":"Asia/Shanghai",
    "iso:country":"CN",
    "name:zho_x_preferred":[
        "\u6c38\u6052\u961f"
    ],
    "wof:name":"Yonghengdui",
    "wof:placetype":"locality"
},
  "geometry": {"coordinates":[123.14599,48.13175],"type":"Point"}
}