{
  "type": "Feature",
  "properties": {
    "gn:admin1_code":"33.0",
    "gn:asciiname":"Jinyun",
    "gn:country_code":"CN",
    "gn:dem":703,
    "gn:feature_class":"P",
    "gn:feature_code":"PPL",
    "gn:name":"Jinyun",
    "gn:population":0,
    "gn:timezone":"Asia/Shanghai",
    "iso:country":"CN",
    "name:zho_x_preferred":[
        "\u7f19\u4e91"
    ],
    "wof:name":"Jinyun",
    "wof:placetype":"locality"
},
  "geometry": {"coordinates":[106.38529,29.84116],"type":"Point"}
}