{
  "type": "Feature",
  "properties": {
    "gn:admin1_code":"21.0",
    "gn:asciiname":"Kujing",
    "gn:country_code":"CN",
    "gn:dem":1825,
    "gn:feature_class":"P",
    "gn:feature_code":"PPL",
    "gn:name":"Kujing",
    "gn:population":0,
    "gn:timezone":"Asia/Shanghai",
    "iso:country":"CN",
    "name:und_x_variant":[
        "\u82e6\u4e95"
    ],
    "name:zho_x_preferred":[
        "\u82e6\u4e95"
    ],
    "wof:name":"Kujing",
    "wof:placetype":"locality"
},
  "geometry": {"coordinates":[106.19685,36.00663],"type":"Point"}
}