{
  "type": "Feature",
  "properties": {
    "gn:admin1_code":"24.0",
    "gn:asciiname":"Wangjiagou",
    "gn:cc2":"CN",
    "gn:country_code":"CN",
    "gn:dem":934,
    "gn:feature_class":"P",
    "gn:feature_code":"PPL",
    "gn:name":"Wangjiagou",
    "gn:population":0,
    "gn:timezone":"Asia/Shanghai",
    "iso:country":"CN",
    "name:und_x_variant":[
        "Wang-chia-kou",
        "Wangjiagou"
    ],
    "wof:name":"Wangjiagou",
    "wof:placetype":"locality"
},
  "geometry": {"coordinates":[111.14082999999999,37.55778],"type":"Point"}
}