{
  "type": "Feature",
  "properties": {
    "gn:admin1_code":"7.0",
    "gn:asciiname":"Shuiweilou",
    "gn:country_code":"CN",
    "gn:dem":478,
    "gn:feature_class":"P",
    "gn:feature_code":"PPL",
    "gn:name":"Shuiweilou",
    "gn:population":0,
    "gn:timezone":"Asia/Shanghai",
    "iso:country":"CN",
    "name:zho_x_preferred":[
        "\u6c34\u5c3e\u697c"
    ],
    "wof:name":"Shuiweilou",
    "wof:placetype":"locality"
},
  "geometry": {"coordinates":[119.5763,26.54606],"type":"Point"}
}