{
  "type": "Feature",
  "properties": {
    "gn:admin1_code":"8.0",
    "gn:asciiname":"Erzhan Qidui",
    "gn:country_code":"CN",
    "gn:dem":458,
    "gn:feature_class":"P",
    "gn:feature_code":"PPLF",
    "gn:name":"Erzhan Qidui",
    "gn:population":0,
    "gn:timezone":"Asia/Shanghai",
    "iso:country":"CN",
    "name:zho_x_preferred":[
        "\u4e8c\u7ad9\u4e03\u961f"
    ],
    "wof:name":"Erzhan Qidui",
    "wof:placetype":"locality"
},
  "geometry": {"coordinates":[129.72134,45.05004],"type":"Point"}
}