{
  "type": "Feature",
  "properties": {
    "gn:admin1_code":"32",
    "gn:asciiname":"Shiya",
    "gn:country_code":"CN",
    "gn:dem":404,
    "gn:feature_class":"P",
    "gn:feature_code":"PPL",
    "gn:name":"Shiya",
    "gn:population":0,
    "gn:timezone":"Asia/Shanghai",
    "iso:country":"CN",
    "name:und_x_variant":[
        "Shiyazhen",
        "Shih-ya-chen",
        "Shiya"
    ],
    "name:zho_x_preferred":[
        "\u77f3\u57ad"
    ],
    "wof:name":"Shiya",
    "wof:placetype":"locality"
},
  "geometry": {"coordinates":[106.49487999999999,30.47059],"type":"Point"}
}