{
  "type": "Feature",
  "properties": {
    "gn:admin1_code":"32.0",
    "gn:asciiname":"Babai",
    "gn:country_code":"CN",
    "gn:dem":717,
    "gn:feature_class":"P",
    "gn:feature_code":"PPL",
    "gn:name":"Babai",
    "gn:population":0,
    "gn:timezone":"Asia/Shanghai",
    "iso:country":"CN",
    "name:zho_x_preferred":[
        "\u516b\u67cf"
    ],
    "wof:name":"Babai",
    "wof:placetype":"locality"
},
  "geometry": {"coordinates":[107.431,31.739],"type":"Point"}
}