{
  "type": "Feature",
  "properties": {
    "gn:admin1_code":"3.0",
    "gn:asciiname":"Wuli",
    "gn:country_code":"CN",
    "gn:dem":94,
    "gn:feature_class":"P",
    "gn:feature_code":"PPL",
    "gn:name":"Wuli",
    "gn:population":0,
    "gn:timezone":"Asia/Shanghai",
    "iso:country":"CN",
    "name:ceb_x_preferred":[
        "Wuli"
    ],
    "name:deu_x_preferred":[
        "Wuli"
    ],
    "name:fra_x_preferred":[
        "Wuli"
    ],
    "name:swe_x_preferred":[
        "Wuli"
    ],
    "name:und_x_variant":[
        "\u6b66\u91cc"
    ],
    "wof:name":"Wuli",
    "wof:placetype":"locality"
},
  "geometry": {"coordinates":[115.02723,27.58126],"type":"Point"}
}