{
  "type": "Feature",
  "properties": {
    "gn:admin1_code":"32.0",
    "gn:asciiname":"Ricun",
    "gn:country_code":"CN",
    "gn:dem":3439,
    "gn:feature_class":"P",
    "gn:feature_code":"PPL",
    "gn:name":"Ricun",
    "gn:population":0,
    "gn:timezone":"Asia/Shanghai",
    "iso:country":"CN",
    "name:zho_x_preferred":[
        "\u65e5\u6751"
    ],
    "wof:name":"Ricun",
    "wof:placetype":"locality"
},
  "geometry": {"coordinates":[100.91956999999999,29.78669],"type":"Point"}
}