{
  "type": "Feature",
  "properties": {
    "gn:admin1_code":"26.0",
    "gn:asciiname":"Tanziwan",
    "gn:country_code":"CN",
    "gn:dem":1380,
    "gn:feature_class":"P",
    "gn:feature_code":"PPL",
    "gn:name":"Tanziwan",
    "gn:population":0,
    "gn:timezone":"Asia/Shanghai",
    "iso:country":"CN",
    "name:zho_x_preferred":[
        "\u575b\u5b50\u6e7e"
    ],
    "wof:name":"Tanziwan",
    "wof:placetype":"locality"
},
  "geometry": {"coordinates":[108.55086,33.31329],"type":"Point"}
}