{
  "type": "Feature",
  "properties": {
    "gn:admin1_code":"29",
    "gn:asciiname":"Hongyuan",
    "gn:country_code":"CN",
    "gn:dem":1511,
    "gn:feature_class":"P",
    "gn:feature_code":"PPL",
    "gn:name":"Hongyuan",
    "gn:population":0,
    "gn:timezone":"Asia/Shanghai",
    "iso:country":"CN",
    "name:ceb_x_preferred":[
        "Hongyuan"
    ],
    "name:zho_x_preferred":[
        "\u7ea2\u5143"
    ],
    "wof:name":"Hongyuan",
    "wof:placetype":"locality"
},
  "geometry": {"coordinates":[103.164,24.6452],"type":"Point"}
}