{
  "type": "Feature",
  "properties": {
    "gn:admin1_code":"18.0",
    "gn:asciiname":"Cenliwan",
    "gn:country_code":"CN",
    "gn:dem":678,
    "gn:feature_class":"P",
    "gn:feature_code":"PPL",
    "gn:name":"Cenliwan",
    "gn:population":0,
    "gn:timezone":"Asia/Shanghai",
    "iso:country":"CN",
    "name:zho_x_preferred":[
        "\u5c91\u68a8\u6e7e"
    ],
    "wof:name":"Cenliwan",
    "wof:placetype":"locality"
},
  "geometry": {"coordinates":[109.16800000000001,27.0379],"type":"Point"}
}