{
  "type": "Feature",
  "properties": {
    "gn:admin1_code":"32.0",
    "gn:asciiname":"Qinggangzui",
    "gn:country_code":"CN",
    "gn:dem":806,
    "gn:feature_class":"P",
    "gn:feature_code":"PPL",
    "gn:name":"Qinggangzui",
    "gn:population":0,
    "gn:timezone":"Asia/Shanghai",
    "iso:country":"CN",
    "name:zho_x_preferred":[
        "\u9752\u6760\u5480"
    ],
    "wof:name":"Qinggangzui",
    "wof:placetype":"locality"
},
  "geometry": {"coordinates":[102.58499999999999,29.3188],"type":"Point"}
}