{
  "type": "Feature",
  "properties": {
    "gn:admin1_code":"31",
    "gn:asciiname":"Xiqing Nongchang Ershisidui",
    "gn:country_code":"CN",
    "gn:dem":56,
    "gn:feature_class":"P",
    "gn:feature_code":"PPLF",
    "gn:name":"Xiqing Nongchang Ershisidui",
    "gn:population":0,
    "gn:timezone":"Asia/Shanghai",
    "iso:country":"CN",
    "name:und_x_variant":[
        "\u897f\u5e86\u519c\u573a\u4e8c\u5341\u56db\u961f",
        "Xiqingershiliulian"
    ],
    "wof:name":"Xiqing Nongchang Ershisidui",
    "wof:placetype":"locality"
},
  "geometry": {"coordinates":[109.46389000000001,19.61583],"type":"Point"}
}