{
  "type": "Feature",
  "properties": {
    "gn:admin1_code":"8.0",
    "gn:asciiname":"Erli",
    "gn:country_code":"CN",
    "gn:dem":177,
    "gn:feature_class":"P",
    "gn:feature_code":"PPL",
    "gn:name":"Erli",
    "gn:population":0,
    "gn:timezone":"Asia/Shanghai",
    "iso:country":"CN",
    "name:azb_x_preferred":[
        "\u0627\u0631\u0644\u06cc"
    ],
    "name:bel_x_preferred":[
        "\u042d\u0440\u043b\u0456"
    ],
    "name:bul_x_preferred":[
        "\u0415\u0440\u043b\u0438"
    ],
    "name:cat_x_preferred":[
        "Erli"
    ],
    "name:ceb_x_preferred":[
        "Erli"
    ],
    "name:deu_x_preferred":[
        "Erli"
    ],
    "name:epo_x_preferred":[
        "Erli"
    ],
    "name:eus_x_preferred":[
        "Erli"
    ],
    "name:fas_x_preferred":[
        "\u0627\u0631\u0644\u06cc"
    ],
    "name:fra_x_preferred":[
        "Erli"
    ],
    "name:hun_x_preferred":[
        "Erli"
    ],
    "name:hye_x_preferred":[
        "\u0537\u0580\u056c\u056b"
    ],
    "name:ina_x_preferred":[
        "Erli"
    ],
    "name:ita_x_preferred":[
        "Erli"
    ],
    "name:jpn_x_preferred":[
        "\u30a8\u30eb\u30ea"
    ],
    "name:lat_x_preferred":[
        "Erlis"
    ],
    "name:lij_x_preferred":[
        "Erli"
    ],
    "name:lmo_x_preferred":[
        "Erli"
    ],
    "name:msa_x_preferred":[
        "Erli"
    ],
    "name:nap_x_preferred":[
        "Erli"
    ],
    "name:nld_x_preferred":[
        "Erli"
    ],
    "name:pms_x_preferred":[
        "Erli"
    ],
    "name:pol_x_preferred":[
        "Erli"
    ],
    "name:por_x_preferred":[
        "Erli"
    ],
    "name:ron_x_preferred":[
        "Erli"
    ],
    "name:rus_x_preferred":[
        "\u042d\u0440\u043b\u0438"
    ],
    "name:scn_x_preferred":[
        "Erli"
    ],
    "name:spa_x_preferred":[
        "Erli"
    ],
    "name:srp_x_preferred":[
        "\u0415\u0440\u043b\u0438"
    ],
    "name:ukr_x_preferred":[
        "\u0415\u0440\u043b\u0456"
    ],
    "name:uzb_x_preferred":[
        "Erli"
    ],
    "name:vie_x_preferred":[
        "Erli"
    ],
    "name:vol_x_preferred":[
        "Erli"
    ],
    "name:war_x_preferred":[
        "Erli"
    ],
    "name:zho_x_preferred":[
        "\u4e8c\u91cc"
    ],
    "wof:name":"Erli",
    "wof:placetype":"locality"
},
  "geometry": {"coordinates":[127.21283,45.04639],"type":"Point"}
}