{
  "type": "Feature",
  "properties": {
    "gn:admin1_code":"32.0",
    "gn:asciiname":"Maluoba",
    "gn:country_code":"CN",
    "gn:dem":1161,
    "gn:feature_class":"P",
    "gn:feature_code":"PPL",
    "gn:name":"Maluoba",
    "gn:population":0,
    "gn:timezone":"Asia/Shanghai",
    "iso:country":"CN",
    "name:zho_x_preferred":[
        "\u9a6c\u843d\u575d"
    ],
    "wof:name":"Maluoba",
    "wof:placetype":"locality"
},
  "geometry": {"coordinates":[105.655,28.2758],"type":"Point"}
}