{
  "type": "Feature",
  "properties": {
    "gn:admin1_code":"13.0",
    "gn:asciiname":"Ai'jieke",
    "gn:country_code":"CN",
    "gn:dem":3001,
    "gn:feature_class":"P",
    "gn:feature_code":"PPL",
    "gn:name":"Ai\u2019jieke",
    "gn:population":0,
    "gn:timezone":"Asia/Shanghai",
    "iso:country":"CN",
    "name:und_x_variant":[
        "Ai\u2019jieke",
        "\u827e\u6770\u514b"
    ],
    "wof:name":"Ai'jieke",
    "wof:placetype":"locality"
},
  "geometry": {"coordinates":[75.94740999999998,38.52336],"type":"Point"}
}