{
  "type": "Feature",
  "properties": {
    "gn:admin1_code":"10",
    "gn:asciiname":"Yubeiqiaozhen",
    "gn:country_code":"CN",
    "gn:dem":55,
    "gn:feature_class":"P",
    "gn:feature_code":"PPL",
    "gn:name":"Yubeiqiaozhen",
    "gn:population":0,
    "gn:timezone":"Asia/Shanghai",
    "iso:country":"CN",
    "wof:name":"Yubeiqiaozhen",
    "wof:placetype":"locality"
},
  "geometry": {"coordinates":[114.57417,37.11194],"type":"Point"}
}