{
  "type": "Feature",
  "properties": {
    "gn:admin1_code":"33.0",
    "gn:asciiname":"Tianbazi",
    "gn:country_code":"CN",
    "gn:dem":628,
    "gn:feature_class":"P",
    "gn:feature_code":"PPL",
    "gn:name":"Tianbazi",
    "gn:population":0,
    "gn:timezone":"Asia/Shanghai",
    "iso:country":"CN",
    "name:zho_x_preferred":[
        "\u7530\u575d\u5b50"
    ],
    "wof:name":"Tianbazi",
    "wof:placetype":"locality"
},
  "geometry": {"coordinates":[109.08763,28.36616],"type":"Point"}
}