{
  "type": "Feature",
  "properties": {
    "gn:admin1_code":"3.0",
    "gn:asciiname":"Huangcaolong",
    "gn:country_code":"CN",
    "gn:dem":346,
    "gn:feature_class":"P",
    "gn:feature_code":"PPL",
    "gn:name":"Huangcaolong",
    "gn:population":0,
    "gn:timezone":"Asia/Shanghai",
    "iso:country":"CN",
    "name:und_x_variant":[
        "\u9ec4\u8349\u5785"
    ],
    "wof:name":"Huangcaolong",
    "wof:placetype":"locality"
},
  "geometry": {"coordinates":[114.78542,29.00816],"type":"Point"}
}