{
  "type": "Feature",
  "properties": {
    "gn:admin1_code":"4.0",
    "gn:asciiname":"Dingda",
    "gn:country_code":"CN",
    "gn:dem":4,
    "gn:feature_class":"P",
    "gn:feature_code":"PPL",
    "gn:name":"Dingda",
    "gn:population":0,
    "gn:timezone":"Asia/Shanghai",
    "iso:country":"CN",
    "name:und_x_variant":[
        "\u4e01\u8fbe"
    ],
    "name:zho_x_preferred":[
        "\u4e01\u8fbe"
    ],
    "wof:name":"Dingda",
    "wof:placetype":"locality"
},
  "geometry": {"coordinates":[120.74363999999998,32.32366],"type":"Point"}
}