{
  "type": "Feature",
  "properties": {
    "gn:admin1_code":"11.0",
    "gn:asciiname":"Damuling",
    "gn:country_code":"CN",
    "gn:dem":78,
    "gn:feature_class":"P",
    "gn:feature_code":"PPL",
    "gn:name":"Damuling",
    "gn:population":0,
    "gn:timezone":"Asia/Shanghai",
    "iso:country":"CN",
    "name:zho_x_preferred":[
        "\u5927\u7267\u5cad"
    ],
    "wof:name":"Damuling",
    "wof:placetype":"locality"
},
  "geometry": {"coordinates":[112.88934999999999,26.76531],"type":"Point"}
}