{
  "type": "Feature",
  "properties": {
    "gn:admin1_code":"26.0",
    "gn:asciiname":"Xiyucun",
    "gn:country_code":"CN",
    "gn:dem":988,
    "gn:feature_class":"P",
    "gn:feature_code":"PPL",
    "gn:name":"Xiyucun",
    "gn:population":0,
    "gn:timezone":"Asia/Shanghai",
    "iso:country":"CN",
    "name:zho_x_preferred":[
        "\u897f\u5cea\u6751"
    ],
    "wof:name":"Xiyucun",
    "wof:placetype":"locality"
},
  "geometry": {"coordinates":[109.69551,34.32230999999999],"type":"Point"}
}