{
  "type": "Feature",
  "properties": {
    "gn:admin1_code":"26.0",
    "gn:asciiname":"Longweimaocun",
    "gn:country_code":"CN",
    "gn:dem":1048,
    "gn:feature_class":"P",
    "gn:feature_code":"PPL",
    "gn:name":"Longweimaocun",
    "gn:population":0,
    "gn:timezone":"Asia/Shanghai",
    "iso:country":"CN",
    "name:zho_x_preferred":[
        "\u9f99\u5c3e\u5cc1\u6751"
    ],
    "wof:name":"Longweimaocun",
    "wof:placetype":"locality"
},
  "geometry": {"coordinates":[110.46617999999999,38.46937],"type":"Point"}
}