{
  "type": "Feature",
  "properties": {
    "gn:admin1_code":"15.0",
    "gn:asciiname":"Shimenwan",
    "gn:country_code":"CN",
    "gn:dem":2216,
    "gn:feature_class":"P",
    "gn:feature_code":"PPL",
    "gn:name":"Shimenwan",
    "gn:population":0,
    "gn:timezone":"Asia/Shanghai",
    "iso:country":"CN",
    "name:und_x_variant":[
        "\u77f3\u95e8\u6e7e"
    ],
    "wof:name":"Shimenwan",
    "wof:placetype":"locality"
},
  "geometry": {"coordinates":[104.80906,34.33838],"type":"Point"}
}