{
  "type": "Feature",
  "properties": {
    "gn:admin1_code":"9.0",
    "gn:asciiname":"Ouyang",
    "gn:country_code":"CN",
    "gn:dem":95,
    "gn:feature_class":"P",
    "gn:feature_code":"PPL",
    "gn:name":"Ouyang",
    "gn:population":0,
    "gn:timezone":"Asia/Shanghai",
    "iso:country":"CN",
    "name:ast_x_preferred":[
        "Ouyang"
    ],
    "name:ces_x_preferred":[
        "Ou-jang"
    ],
    "name:deu_x_preferred":[
        "Ouyang"
    ],
    "name:nld_x_preferred":[
        "Ouyang"
    ],
    "name:rus_x_preferred":[
        "\u041e\u0443\u044f\u043d"
    ],
    "name:spa_x_preferred":[
        "Ouyang"
    ],
    "name:vie_x_preferred":[
        "\u00c2u D\u01b0\u01a1ng"
    ],
    "name:zho_x_preferred":[
        "\u6b27\u9633\u5e84"
    ],
    "name:zho_x_variant":[
        "\u6b27\u9633\u59d3"
    ],
    "wof:name":"Ouyang",
    "wof:placetype":"locality"
},
  "geometry": {"coordinates":[113.35436,33.5194],"type":"Point"}
}