{
  "type": "Feature",
  "properties": {
    "gn:admin1_code":"9.0",
    "gn:asciiname":"Piankan",
    "gn:country_code":"CN",
    "gn:dem":312,
    "gn:feature_class":"P",
    "gn:feature_code":"PPL",
    "gn:name":"Piankan",
    "gn:population":0,
    "gn:timezone":"Asia/Shanghai",
    "iso:country":"CN",
    "name:zho_x_preferred":[
        "\u504f\u770b"
    ],
    "wof:name":"Piankan",
    "wof:placetype":"locality"
},
  "geometry": {"coordinates":[112.2841,35.02492],"type":"Point"}
}