{
  "type": "Feature",
  "properties": {
    "gn:admin1_code":"30.0",
    "gn:asciiname":"Junmincun",
    "gn:country_code":"CN",
    "gn:dem":6,
    "gn:feature_class":"P",
    "gn:feature_code":"PPL",
    "gn:name":"Junmincun",
    "gn:population":0,
    "gn:timezone":"Asia/Shanghai",
    "iso:country":"CN",
    "name:zho_x_preferred":[
        "\u519b\u6c11\u6751"
    ],
    "wof:name":"Junmincun",
    "wof:placetype":"locality"
},
  "geometry": {"coordinates":[116.61461,23.45438],"type":"Point"}
}