{
  "type": "Feature",
  "properties": {
    "gn:admin1_code":"24.0",
    "gn:asciiname":"Waziping",
    "gn:cc2":"CN",
    "gn:country_code":"CN",
    "gn:dem":1282,
    "gn:feature_class":"P",
    "gn:feature_code":"PPL",
    "gn:name":"Waziping",
    "gn:population":0,
    "gn:timezone":"Asia/Shanghai",
    "iso:country":"CN",
    "name:und_x_variant":[
        "Wa-tzu-p\u2019ing",
        "Waziping"
    ],
    "wof:name":"Waziping",
    "wof:placetype":"locality"
},
  "geometry": {"coordinates":[113.13889,38.50333],"type":"Point"}
}