{
  "type": "Feature",
  "properties": {
    "gn:admin1_code":"19.0",
    "gn:asciiname":"Huangqicun",
    "gn:country_code":"CN",
    "gn:dem":361,
    "gn:feature_class":"P",
    "gn:feature_code":"PPL",
    "gn:name":"Huangqicun",
    "gn:population":0,
    "gn:timezone":"Asia/Shanghai",
    "iso:country":"CN",
    "name:zho_x_preferred":[
        "\u9ec4\u65d7\u6751"
    ],
    "wof:name":"Huangqicun",
    "wof:placetype":"locality"
},
  "geometry": {"coordinates":[125.05,41.7749],"type":"Point"}
}