{
  "type": "Feature",
  "properties": {
    "gn:admin1_code":"9.0",
    "gn:asciiname":"Yewan",
    "gn:country_code":"CN",
    "gn:dem":178,
    "gn:feature_class":"P",
    "gn:feature_code":"PPL",
    "gn:name":"Yewan",
    "gn:population":0,
    "gn:timezone":"Asia/Shanghai",
    "iso:country":"CN",
    "name:und_x_variant":[
        "\u53f6\u6e7e",
        "Yewan"
    ],
    "wof:name":"Yewan",
    "wof:placetype":"locality"
},
  "geometry": {"coordinates":[112.43532,33.09034],"type":"Point"}
}