{
  "type": "Feature",
  "properties": {
    "gn:admin1_code":"16.0",
    "gn:asciiname":"Helaoping",
    "gn:country_code":"CN",
    "gn:dem":78,
    "gn:feature_class":"P",
    "gn:feature_code":"PPL",
    "gn:name":"Helaoping",
    "gn:population":0,
    "gn:timezone":"Asia/Shanghai",
    "iso:country":"CN",
    "name:zho_x_preferred":[
        "\u4f55\u8001\u576a"
    ],
    "wof:name":"Helaoping",
    "wof:placetype":"locality"
},
  "geometry": {"coordinates":[110.245,22.0808],"type":"Point"}
}