{
  "type": "Feature",
  "properties": {
    "gn:admin1_code":"5.0",
    "gn:asciiname":"Gaotaizicun",
    "gn:country_code":"CN",
    "gn:dem":252,
    "gn:feature_class":"P",
    "gn:feature_code":"PPL",
    "gn:name":"Gaotaizicun",
    "gn:population":0,
    "gn:timezone":"Asia/Shanghai",
    "iso:country":"CN",
    "name:zho_x_preferred":[
        "\u9ad8\u53f0\u5b50\u6751"
    ],
    "wof:name":"Gaotaizicun",
    "wof:placetype":"locality"
},
  "geometry": {"coordinates":[126.80747,44.26536],"type":"Point"}
}