{
  "type": "Feature",
  "properties": {
    "gn:admin1_code":"07",
    "gn:asciiname":"Baisha",
    "gn:country_code":"CN",
    "gn:dem":112,
    "gn:feature_class":"P",
    "gn:feature_code":"PPLA4",
    "gn:name":"Baisha",
    "gn:population":0,
    "gn:timezone":"Asia/Shanghai",
    "iso:country":"CN",
    "name:ceb_x_preferred":[
        "Baisha"
    ],
    "name:deu_x_preferred":[
        "Baisha"
    ],
    "name:fra_x_preferred":[
        "Baisha"
    ],
    "name:nld_x_preferred":[
        "Baisha"
    ],
    "name:und_x_variant":[
        "Pai-sha",
        "\u767d\u6c99",
        "Baisha Zhen",
        "\u767d\u6c99\u9547"
    ],
    "wof:name":"Baisha",
    "wof:placetype":"locality"
},
  "geometry": {"coordinates":[119.01011,25.59503],"type":"Point"}
}