{
  "type": "Feature",
  "properties": {
    "gn:admin1_code":"9.0",
    "gn:asciiname":"Hudongcun",
    "gn:country_code":"CN",
    "gn:dem":94,
    "gn:feature_class":"P",
    "gn:feature_code":"PPL",
    "gn:name":"Hudongcun",
    "gn:population":0,
    "gn:timezone":"Asia/Shanghai",
    "iso:country":"CN",
    "name:zho_x_preferred":[
        "\u6e56\u4e1c\u6751"
    ],
    "wof:name":"Hudongcun",
    "wof:placetype":"locality"
},
  "geometry": {"coordinates":[112.67999,32.5178],"type":"Point"}
}