{
  "type": "Feature",
  "properties": {
    "gn:admin1_code":"29.0",
    "gn:asciiname":"Dilandang",
    "gn:country_code":"CN",
    "gn:dem":1692,
    "gn:feature_class":"P",
    "gn:feature_code":"PPL",
    "gn:name":"Dilandang",
    "gn:population":0,
    "gn:timezone":"Asia/Shanghai",
    "iso:country":"CN",
    "name:zho_x_preferred":[
        "\u8fea\u5170\u5f53"
    ],
    "wof:name":"Dilandang",
    "wof:placetype":"locality"
},
  "geometry": {"coordinates":[98.3263,27.9849],"type":"Point"}
}