{
  "type": "Feature",
  "properties": {
    "gn:admin1_code":"8.0",
    "gn:asciiname":"Dalengchangtun",
    "gn:country_code":"CN",
    "gn:dem":105,
    "gn:feature_class":"P",
    "gn:feature_code":"PPL",
    "gn:name":"Dalengchangtun",
    "gn:population":0,
    "gn:timezone":"Asia/Shanghai",
    "iso:country":"CN",
    "name:zho_x_preferred":[
        "\u5927\u695e\u573a\u5c6f"
    ],
    "wof:name":"Dalengchangtun",
    "wof:placetype":"locality"
},
  "geometry": {"coordinates":[128.42633000000001,45.9591],"type":"Point"}
}