{
  "type": "Feature",
  "properties": {
    "gn:admin1_code":"24",
    "gn:asciiname":"Shangxin'an",
    "gn:country_code":"CN",
    "gn:dem":1266,
    "gn:feature_class":"P",
    "gn:feature_code":"PPL",
    "gn:name":"Shangxin\u2019an",
    "gn:population":0,
    "gn:timezone":"Asia/Shanghai",
    "iso:country":"CN",
    "name:und_x_variant":[
        "Shang-hsin-an",
        "Shangxin\u2019an",
        "\u4e0a\u8f9b\u5b89"
    ],
    "wof:name":"Shangxin'an",
    "wof:placetype":"locality"
},
  "geometry": {"coordinates":[113.66127,39.83104],"type":"Point"}
}