{
  "type": "Feature",
  "properties": {
    "gn:admin1_code":"19.0",
    "gn:asciiname":"Dashuiquanzi",
    "gn:country_code":"CN",
    "gn:dem":210,
    "gn:feature_class":"P",
    "gn:feature_code":"PPL",
    "gn:name":"Dashuiquanzi",
    "gn:population":0,
    "gn:timezone":"Asia/Shanghai",
    "iso:country":"CN",
    "name:zho_x_preferred":[
        "\u5927\u6c34\u6cc9\u5b50"
    ],
    "wof:name":"Dashuiquanzi",
    "wof:placetype":"locality"
},
  "geometry": {"coordinates":[121.11,41.6515],"type":"Point"}
}