{
  "type": "Feature",
  "properties": {
    "gn:admin1_code":"30",
    "gn:asciiname":"Dabukou",
    "gn:country_code":"CN",
    "gn:dem":33,
    "gn:feature_class":"P",
    "gn:feature_code":"PPL",
    "gn:name":"Dabukou",
    "gn:population":0,
    "gn:timezone":"Asia/Shanghai",
    "iso:country":"CN",
    "name:und_x_variant":[
        "\u5927\u6b65\u53e3"
    ],
    "name:zho_x_preferred":[
        "\u5927\u6b65\u53e3"
    ],
    "wof:name":"Dabukou",
    "wof:placetype":"locality"
},
  "geometry": {"coordinates":[113.85833,23.36167],"type":"Point"}
}