{
  "type": "Feature",
  "properties": {
    "gn:admin1_code":"29.0",
    "gn:asciiname":"Fangniuchang",
    "gn:country_code":"CN",
    "gn:dem":3225,
    "gn:feature_class":"P",
    "gn:feature_code":"PPLF",
    "gn:name":"Fangniuchang",
    "gn:population":0,
    "gn:timezone":"Asia/Shanghai",
    "iso:country":"CN",
    "name:zho_x_preferred":[
        "\u653e\u725b\u573a"
    ],
    "wof:name":"Fangniuchang",
    "wof:placetype":"locality"
},
  "geometry": {"coordinates":[99.0455,26.0487],"type":"Point"}
}