{
  "type": "Feature",
  "properties": {
    "gn:admin1_code":"26.0",
    "gn:asciiname":"Shirengounao",
    "gn:country_code":"CN",
    "gn:dem":895,
    "gn:feature_class":"P",
    "gn:feature_code":"PPL",
    "gn:name":"Shirengounao",
    "gn:population":0,
    "gn:timezone":"Asia/Shanghai",
    "iso:country":"CN",
    "name:zho_x_preferred":[
        "\u77f3\u4eba\u6c9f\u8111"
    ],
    "wof:name":"Shirengounao",
    "wof:placetype":"locality"
},
  "geometry": {"coordinates":[110.61145,33.37968],"type":"Point"}
}