{
  "type": "Feature",
  "properties": {
    "gn:admin1_code":"15",
    "gn:asciiname":"Tumen",
    "gn:country_code":"CN",
    "gn:dem":1619,
    "gn:feature_class":"P",
    "gn:feature_code":"PPL",
    "gn:name":"Tumen",
    "gn:population":0,
    "gn:timezone":"Asia/Shanghai",
    "iso:country":"CN",
    "name:ceb_x_preferred":[
        "Tumen"
    ],
    "name:deu_x_preferred":[
        "Tumen"
    ],
    "name:fra_x_preferred":[
        "Tumen"
    ],
    "name:ita_x_preferred":[
        "Tumen"
    ],
    "name:nds_x_preferred":[
        "Tumen"
    ],
    "name:nld_x_preferred":[
        "Tumen"
    ],
    "name:nor_x_preferred":[
        "Tumen"
    ],
    "name:pol_x_preferred":[
        "Tumen"
    ],
    "name:spa_x_preferred":[
        "Tumen"
    ],
    "name:swe_x_preferred":[
        "Tumen"
    ],
    "wof:name":"Tumen",
    "wof:placetype":"locality"
},
  "geometry": {"coordinates":[105.87833000000001,34.76639],"type":"Point"}
}