{
  "type": "Feature",
  "properties": {
    "gn:admin1_code":"9",
    "gn:asciiname":"Shiling",
    "gn:country_code":"CN",
    "gn:dem":82,
    "gn:feature_class":"P",
    "gn:feature_code":"PPLA4",
    "gn:name":"Shiling",
    "gn:population":0,
    "gn:timezone":"Asia/Shanghai",
    "iso:country":"CN",
    "name:und_x_variant":[
        "\u5e08\u7075",
        "Shiling Zhen",
        "\u5e08\u7075\u9547"
    ],
    "wof:name":"Shiling",
    "wof:placetype":"locality"
},
  "geometry": {"coordinates":[113.81918,33.39677],"type":"Point"}
}