{
  "type": "Feature",
  "properties": {
    "gn:admin1_code":"29.0",
    "gn:asciiname":"Hejia Dawan",
    "gn:country_code":"CN",
    "gn:dem":1421,
    "gn:feature_class":"P",
    "gn:feature_code":"PPL",
    "gn:name":"Hejia Dawan",
    "gn:population":0,
    "gn:timezone":"Asia/Shanghai",
    "iso:country":"CN",
    "name:zho_x_preferred":[
        "\u4f55\u5bb6\u5927\u6e7e"
    ],
    "wof:name":"Hejia Dawan",
    "wof:placetype":"locality"
},
  "geometry": {"coordinates":[104.547,27.6945],"type":"Point"}
}