{
  "type": "Feature",
  "properties": {
    "gn:admin1_code":"7.0",
    "gn:asciiname":"Qiaotou",
    "gn:country_code":"CN",
    "gn:dem":269,
    "gn:feature_class":"P",
    "gn:feature_code":"PPL",
    "gn:name":"Qiaotou",
    "gn:population":0,
    "gn:timezone":"Asia/Shanghai",
    "iso:country":"CN",
    "name:und_x_variant":[
        "\u6865\u5934"
    ],
    "name:zho_x_preferred":[
        "\u6865\u5934"
    ],
    "wof:name":"Qiaotou",
    "wof:placetype":"locality"
},
  "geometry": {"coordinates":[117.19233,26.05405],"type":"Point"}
}