{
  "type": "Feature",
  "properties": {
    "gn:admin1_code":"18.0",
    "gn:asciiname":"Shizijie",
    "gn:country_code":"CN",
    "gn:dem":516,
    "gn:feature_class":"P",
    "gn:feature_code":"PPL",
    "gn:name":"Shizijie",
    "gn:population":0,
    "gn:timezone":"Asia/Shanghai",
    "iso:country":"CN",
    "name:zho_x_preferred":[
        "\u5341\u5b57\u8857"
    ],
    "wof:name":"Shizijie",
    "wof:placetype":"locality"
},
  "geometry": {"coordinates":[107.81,25.9983],"type":"Point"}
}