{
  "type": "Feature",
  "properties": {
    "gn:admin1_code":"05",
    "gn:asciiname":"Dahenglu",
    "gn:country_code":"CN",
    "gn:dem":367,
    "gn:feature_class":"P",
    "gn:feature_code":"PPL",
    "gn:name":"Dahenglu",
    "gn:population":0,
    "gn:timezone":"Asia/Shanghai",
    "iso:country":"CN",
    "name:und_x_variant":[
        "\u5927\u6a2a\u8def",
        "Ta-heng-lu"
    ],
    "wof:name":"Dahenglu",
    "wof:placetype":"locality"
},
  "geometry": {"coordinates":[125.80361000000001,40.99194],"type":"Point"}
}