{
  "type": "Feature",
  "properties": {
    "gn:admin1_code":"19.0",
    "gn:asciiname":"Xiyang Jiaowancun",
    "gn:country_code":"CN",
    "gn:dem":32,
    "gn:feature_class":"P",
    "gn:feature_code":"PPL",
    "gn:name":"Xiyang Jiaowancun",
    "gn:population":0,
    "gn:timezone":"Asia/Shanghai",
    "iso:country":"CN",
    "name:und_x_variant":[
        "Xiyangjiaowancun",
        "Xiyang Jiaowancun"
    ],
    "name:zho_x_preferred":[
        "\u897f\u7f8a\u89d2\u6e7e\u6751"
    ],
    "wof:name":"Xiyang Jiaowancun",
    "wof:placetype":"locality"
},
  "geometry": {"coordinates":[123.28036000000002,41.51127],"type":"Point"}
}