{
  "type": "Feature",
  "properties": {
    "gn:admin1_code":"19",
    "gn:asciiname":"Laohutunmanzu",
    "gn:cc2":"CN",
    "gn:country_code":"CN",
    "gn:dem":56,
    "gn:feature_class":"P",
    "gn:feature_code":"PPL",
    "gn:name":"Laohutunmanzu",
    "gn:population":0,
    "gn:timezone":"Asia/Shanghai",
    "iso:country":"CN",
    "name:und_x_variant":[
        "Laohutun",
        "Laohutunmanzu"
    ],
    "wof:name":"Laohutunmanzu",
    "wof:placetype":"locality"
},
  "geometry": {"coordinates":[121.81667,39.65],"type":"Point"}
}