{
  "type": "Feature",
  "properties": {
    "gn:admin1_code":"24.0",
    "gn:asciiname":"Erdun",
    "gn:country_code":"CN",
    "gn:dem":1605,
    "gn:feature_class":"P",
    "gn:feature_code":"PPL",
    "gn:name":"Erdun",
    "gn:population":0,
    "gn:timezone":"Asia/Shanghai",
    "iso:country":"CN",
    "name:zho_x_preferred":[
        "\u4e8c\u58a9"
    ],
    "wof:name":"Erdun",
    "wof:placetype":"locality"
},
  "geometry": {"coordinates":[112.00845,39.82567],"type":"Point"}
}