{
  "type": "Feature",
  "properties": {
    "gn:admin1_code":"11.0",
    "gn:asciiname":"Zhushanjiao",
    "gn:country_code":"CN",
    "gn:dem":653,
    "gn:feature_class":"P",
    "gn:feature_code":"PPL",
    "gn:name":"Zhushanjiao",
    "gn:population":0,
    "gn:timezone":"Asia/Shanghai",
    "iso:country":"CN",
    "name:zho_x_preferred":[
        "\u7af9\u5c71\u811a"
    ],
    "wof:name":"Zhushanjiao",
    "wof:placetype":"locality"
},
  "geometry": {"coordinates":[110.48480000000001,27.31267],"type":"Point"}
}