{
  "type": "Feature",
  "properties": {
    "gn:admin1_code":"32.0",
    "gn:asciiname":"Yinjiajie",
    "gn:country_code":"CN",
    "gn:dem":511,
    "gn:feature_class":"P",
    "gn:feature_code":"PPL",
    "gn:name":"Yinjiajie",
    "gn:population":0,
    "gn:timezone":"Asia/Shanghai",
    "iso:country":"CN",
    "name:zho_x_preferred":[
        "\u94f6\u5bb6\u8857"
    ],
    "wof:name":"Yinjiajie",
    "wof:placetype":"locality"
},
  "geometry": {"coordinates":[104.52442000000001,29.79363],"type":"Point"}
}