{
  "type": "Feature",
  "properties": {
    "gn:admin1_code":"30.0",
    "gn:asciiname":"Siluo",
    "gn:country_code":"CN",
    "gn:dem":119,
    "gn:feature_class":"P",
    "gn:feature_code":"PPL",
    "gn:name":"Siluo",
    "gn:population":0,
    "gn:timezone":"Asia/Shanghai",
    "iso:country":"CN",
    "name:zho_x_preferred":[
        "\u601d\u7f57"
    ],
    "wof:name":"Siluo",
    "wof:placetype":"locality"
},
  "geometry": {"coordinates":[111.73291999999999,22.63804],"type":"Point"}
}