{
  "type": "Feature",
  "properties": {
    "gn:admin1_code":"29.0",
    "gn:asciiname":"Lujia Caozi",
    "gn:country_code":"CN",
    "gn:dem":1972,
    "gn:feature_class":"P",
    "gn:feature_code":"PPL",
    "gn:name":"Lujia Caozi",
    "gn:population":0,
    "gn:timezone":"Asia/Shanghai",
    "iso:country":"CN",
    "name:zho_x_preferred":[
        "\u9646\u5bb6\u69fd\u5b50"
    ],
    "wof:name":"Lujia Caozi",
    "wof:placetype":"locality"
},
  "geometry": {"coordinates":[104.545,25.2212],"type":"Point"}
}