{
  "type": "Feature",
  "properties": {
    "gn:admin1_code":"32.0",
    "gn:asciiname":"Huangyan",
    "gn:country_code":"CN",
    "gn:dem":333,
    "gn:feature_class":"P",
    "gn:feature_code":"PPL",
    "gn:name":"Huangyan",
    "gn:population":0,
    "gn:timezone":"Asia/Shanghai",
    "iso:country":"CN",
    "name:ara_x_preferred":[
        "\u0647\u0648\u0627\u0646\u063a\u064a\u0627\u0646"
    ],
    "name:ben_x_preferred":[
        "\u09b9\u09c1\u09df\u09be\u0982\u0987\u09df\u09be\u09a8"
    ],
    "name:ell_x_preferred":[
        "\u03a7\u03bf\u03c5\u03b1\u03bd\u03b3\u03ba\u03b3\u03bf\u03c5\u03ac\u03bd"
    ],
    "name:fas_x_preferred":[
        "\u0647\u0648\u0627\u0646\u06af\u06cc\u0627\u0646"
    ],
    "name:heb_x_preferred":[
        "\u05d4\u05d5\u05d0\u05e0\u05d2\u05d9\u05d0\u05df"
    ],
    "name:hin_x_preferred":[
        "\u0939\u0941\u0906\u0902\u0917\u094d\u092f\u093e\u0928"
    ],
    "name:hun_x_preferred":[
        "Huangyan"
    ],
    "name:ind_x_preferred":[
        "Huangyan"
    ],
    "name:jpn_x_preferred":[
        "\u9ec4\u5ca9"
    ],
    "name:pol_x_preferred":[
        "Huangyan"
    ],
    "name:por_x_preferred":[
        "Huangyan"
    ],
    "name:spa_x_preferred":[
        "Huangyan"
    ],
    "name:tur_x_preferred":[
        "Huangyan"
    ],
    "name:ukr_x_preferred":[
        "\u0425\u0443\u0430\u043d\u2019\u044f\u043d\u044c"
    ],
    "name:zho_x_preferred":[
        "\u9ec4\u5ca9"
    ],
    "wof:name":"Huangyan",
    "wof:placetype":"locality"
},
  "geometry": {"coordinates":[105.17400000000001,28.9424],"type":"Point"}
}