{
  "type": "Feature",
  "properties": {
    "gn:admin1_code":"29.0",
    "gn:asciiname":"Mazhanjie",
    "gn:cc2":"CN",
    "gn:country_code":"CN",
    "gn:dem":2005,
    "gn:feature_class":"P",
    "gn:feature_code":"PPL",
    "gn:name":"Mazhanjie",
    "gn:population":0,
    "gn:timezone":"Asia/Shanghai",
    "iso:country":"CN",
    "name:und_x_variant":[
        "Ma-chan",
        "Mazhan",
        "Ma-chan-chieh",
        "Mazhanjie"
    ],
    "wof:name":"Mazhanjie",
    "wof:placetype":"locality"
},
  "geometry": {"coordinates":[98.46666999999999,25.15],"type":"Point"}
}