{
  "type": "Feature",
  "properties": {
    "gn:admin1_code":"32.0",
    "gn:asciiname":"Xiangyan",
    "gn:country_code":"CN",
    "gn:dem":661,
    "gn:feature_class":"P",
    "gn:feature_code":"PPL",
    "gn:name":"Xiangyan",
    "gn:population":0,
    "gn:timezone":"Asia/Shanghai",
    "iso:country":"CN",
    "name:und_x_variant":[
        "Xiangyanba",
        "Xiangyan"
    ],
    "name:zho_x_preferred":[
        "\u54cd\u5ca9"
    ],
    "wof:name":"Xiangyan",
    "wof:placetype":"locality"
},
  "geometry": {"coordinates":[104.78059,32.10556],"type":"Point"}
}