{
  "type": "Feature",
  "properties": {
    "gn:admin1_code":"26.0",
    "gn:asciiname":"Dashibao",
    "gn:country_code":"CN",
    "gn:dem":668,
    "gn:feature_class":"P",
    "gn:feature_code":"PPL",
    "gn:name":"Dashibao",
    "gn:population":0,
    "gn:timezone":"Asia/Shanghai",
    "iso:country":"CN",
    "name:und_x_variant":[
        "\u5927\u77f3\u5305"
    ],
    "wof:name":"Dashibao",
    "wof:placetype":"locality"
},
  "geometry": {"coordinates":[106.45779,33.23459],"type":"Point"}
}