{
  "type": "Feature",
  "properties": {
    "gn:admin1_code":"14.0",
    "gn:asciiname":"Garigongguo",
    "gn:country_code":"CN",
    "gn:dem":4317,
    "gn:feature_class":"P",
    "gn:feature_code":"PPL",
    "gn:name":"Garigongguo",
    "gn:population":0,
    "gn:timezone":"Asia/Urumqi",
    "iso:country":"CN",
    "name:zho_x_preferred":[
        "\u560e\u65e5\u5171\u679c"
    ],
    "wof:name":"Garigongguo",
    "wof:placetype":"locality"
},
  "geometry": {"coordinates":[95.47969000000001,31.22724],"type":"Point"}
}