{
  "type": "Feature",
  "properties": {
    "gn:admin1_code":"7.0",
    "gn:asciiname":"Zhengfangduan",
    "gn:country_code":"CN",
    "gn:dem":290,
    "gn:feature_class":"P",
    "gn:feature_code":"PPL",
    "gn:name":"Zhengfangduan",
    "gn:population":0,
    "gn:timezone":"Asia/Shanghai",
    "iso:country":"CN",
    "name:zho_x_preferred":[
        "\u90d1\u574a\u6bb5"
    ],
    "wof:name":"Zhengfangduan",
    "wof:placetype":"locality"
},
  "geometry": {"coordinates":[116.45307,25.65659],"type":"Point"}
}