{
  "type": "Feature",
  "properties": {
    "gn:admin1_code":"11.0",
    "gn:asciiname":"Hujia'ao",
    "gn:country_code":"CN",
    "gn:dem":116,
    "gn:feature_class":"P",
    "gn:feature_code":"PPL",
    "gn:name":"Hujia\u2019ao",
    "gn:population":0,
    "gn:timezone":"Asia/Shanghai",
    "iso:country":"CN",
    "name:und_x_variant":[
        "Hujia\u2019ao"
    ],
    "name:zho_x_preferred":[
        "\u80e1\u5bb6\u5773"
    ],
    "wof:name":"Hujia'ao",
    "wof:placetype":"locality"
},
  "geometry": {"coordinates":[112.27695,28.32142],"type":"Point"}
}