{
  "type": "Feature",
  "properties": {
    "gn:admin1_code":"26",
    "gn:asciiname":"Linghucun",
    "gn:country_code":"CN",
    "gn:dem":600,
    "gn:feature_class":"P",
    "gn:feature_code":"PPL",
    "gn:name":"Linghucun",
    "gn:population":0,
    "gn:timezone":"Asia/Shanghai",
    "iso:country":"CN",
    "name:zho_x_preferred":[
        "\u4ee4\u80e1\u6751"
    ],
    "name:zho_x_variant":[
        "\u53e6\u80e1\u6751"
    ],
    "wof:name":"Linghucun",
    "wof:placetype":"locality"
},
  "geometry": {"coordinates":[108.21451999999999,34.45109],"type":"Point"}
}