{
  "type": "Feature",
  "properties": {
    "gn:admin1_code":"08",
    "gn:asciiname":"Wutongcun",
    "gn:country_code":"CN",
    "gn:dem":179,
    "gn:feature_class":"P",
    "gn:feature_code":"PPL",
    "gn:name":"Wutongcun",
    "gn:population":0,
    "gn:timezone":"Asia/Shanghai",
    "iso:country":"CN",
    "name:und_x_variant":[
        "Wutong",
        "Wutongcun"
    ],
    "name:zho_x_preferred":[
        "\u68a7\u6850"
    ],
    "name:zho_x_variant":[
        "\u68a7\u6850\u6751"
    ],
    "wof:name":"Wutongcun",
    "wof:placetype":"locality"
},
  "geometry": {"coordinates":[129.16623999999999,47.1164],"type":"Point"}
}