{
  "type": "Feature",
  "properties": {
    "gn:admin1_code":"22.0",
    "gn:asciiname":"Houfeng",
    "gn:country_code":"CN",
    "gn:dem":39,
    "gn:feature_class":"P",
    "gn:feature_code":"PPL",
    "gn:name":"Houfeng",
    "gn:population":0,
    "gn:timezone":"Asia/Shanghai",
    "iso:country":"CN",
    "name:zho_x_preferred":[
        "\u540e\u4ff8"
    ],
    "wof:name":"Houfeng",
    "wof:placetype":"locality"
},
  "geometry": {"coordinates":[116.49606,39.8668],"type":"Point"}
}