{
  "type": "Feature",
  "properties": {
    "gn:admin1_code":"5.0",
    "gn:asciiname":"Tianbaocun",
    "gn:country_code":"CN",
    "gn:dem":151,
    "gn:feature_class":"P",
    "gn:feature_code":"PPL",
    "gn:name":"Tianbaocun",
    "gn:population":0,
    "gn:timezone":"Asia/Shanghai",
    "iso:country":"CN",
    "name:zho_x_preferred":[
        "\u5929\u5b9d\u6751"
    ],
    "wof:name":"Tianbaocun",
    "wof:placetype":"locality"
},
  "geometry": {"coordinates":[123.03298999999998,44.55688],"type":"Point"}
}