{
  "type": "Feature",
  "properties": {
    "gn:admin1_code":"12.0",
    "gn:asciiname":"Sanhua",
    "gn:country_code":"CN",
    "gn:dem":27,
    "gn:feature_class":"P",
    "gn:feature_code":"PPLA4",
    "gn:name":"Sanhua",
    "gn:population":0,
    "gn:timezone":"Asia/Shanghai",
    "iso:country":"CN",
    "name:deu_x_preferred":[
        "Sanhua"
    ],
    "name:fra_x_preferred":[
        "Sanhua"
    ],
    "name:ita_x_preferred":[
        "Sanhua"
    ],
    "name:por_x_preferred":[
        "Sanhua"
    ],
    "name:spa_x_preferred":[
        "Sanhua"
    ],
    "name:und_x_variant":[
        "\u6563\u82b1"
    ],
    "name:zho_x_preferred":[
        "Sanhua Zhen"
    ],
    "name:zho_x_variant":[
        "\u6563\u82b1\u9547"
    ],
    "wof:name":"Sanhua",
    "wof:placetype":"locality"
},
  "geometry": {"coordinates":[115.10859000000001,30.24238],"type":"Point"}
}