{
  "type": "Feature",
  "properties": {
    "gn:admin1_code":"32.0",
    "gn:asciiname":"Zhoujia Dafangzi",
    "gn:country_code":"CN",
    "gn:dem":512,
    "gn:feature_class":"P",
    "gn:feature_code":"PPL",
    "gn:name":"Zhoujia Dafangzi",
    "gn:population":0,
    "gn:timezone":"Asia/Shanghai",
    "iso:country":"CN",
    "name:zho_x_preferred":[
        "\u5468\u5bb6\u5927\u623f\u5b50"
    ],
    "wof:name":"Zhoujia Dafangzi",
    "wof:placetype":"locality"
},
  "geometry": {"coordinates":[104.50602000000001,31.26962],"type":"Point"}
}