{
  "type": "Feature",
  "properties": {
    "gn:admin1_code":"5.0",
    "gn:asciiname":"Chijiacun",
    "gn:country_code":"CN",
    "gn:dem":171,
    "gn:feature_class":"P",
    "gn:feature_code":"PPL",
    "gn:name":"Chijiacun",
    "gn:population":0,
    "gn:timezone":"Asia/Shanghai",
    "iso:country":"CN",
    "name:zho_x_preferred":[
        "\u8fdf\u5bb6\u6751"
    ],
    "wof:name":"Chijiacun",
    "wof:placetype":"locality"
},
  "geometry": {"coordinates":[125.10662000000001,44.3646],"type":"Point"}
}