{
  "type": "Feature",
  "properties": {
    "gn:admin1_code":"7",
    "gn:asciiname":"Xixu",
    "gn:country_code":"CN",
    "gn:dem":13,
    "gn:feature_class":"P",
    "gn:feature_code":"PPL",
    "gn:name":"Xixu",
    "gn:population":0,
    "gn:timezone":"Asia/Shanghai",
    "iso:country":"CN",
    "name:und_x_variant":[
        "\u897f\u8bb8"
    ],
    "name:zho_x_preferred":[
        "\u897f\u8bb8"
    ],
    "wof:name":"Xixu",
    "wof:placetype":"locality"
},
  "geometry": {"coordinates":[117.67417,23.96944],"type":"Point"}
}