{
  "type": "Feature",
  "properties": {
    "gn:admin1_code":"19.0",
    "gn:asciiname":"Longtan Hebei",
    "gn:country_code":"CN",
    "gn:dem":148,
    "gn:feature_class":"P",
    "gn:feature_code":"PPL",
    "gn:name":"Longtan Hebei",
    "gn:population":0,
    "gn:timezone":"Asia/Shanghai",
    "iso:country":"CN",
    "name:und_x_variant":[
        "\u9f99\u6f6d\u6cb3\u5317"
    ],
    "name:zho_x_preferred":[
        "\u9f99\u6f6d\u6cb3\u5317"
    ],
    "wof:name":"Longtan Hebei",
    "wof:placetype":"locality"
},
  "geometry": {"coordinates":[123.06536,40.14917],"type":"Point"}
}