{
  "type": "Feature",
  "properties": {
    "gn:admin1_code":"24",
    "gn:asciiname":"Dougou",
    "gn:cc2":"CN",
    "gn:country_code":"CN",
    "gn:dem":1564,
    "gn:feature_class":"P",
    "gn:feature_code":"PPL",
    "gn:name":"Dougou",
    "gn:population":0,
    "gn:timezone":"Asia/Shanghai",
    "iso:country":"CN",
    "name:und_x_variant":[
        "Tou-kou",
        "Dougou"
    ],
    "wof:name":"Dougou",
    "wof:placetype":"locality"
},
  "geometry": {"coordinates":[112.41667,38.95],"type":"Point"}
}