{
  "type": "Feature",
  "properties": {
    "gn:admin1_code":"19.0",
    "gn:asciiname":"Duishilazi",
    "gn:country_code":"CN",
    "gn:dem":531,
    "gn:feature_class":"P",
    "gn:feature_code":"PPL",
    "gn:name":"Duishilazi",
    "gn:population":0,
    "gn:timezone":"Asia/Shanghai",
    "iso:country":"CN",
    "name:und_x_variant":[
        "\u5bf9\u77f3\u782c\u5b50"
    ],
    "wof:name":"Duishilazi",
    "wof:placetype":"locality"
},
  "geometry": {"coordinates":[124.78288000000001,41.48263],"type":"Point"}
}