{
  "type": "Feature",
  "properties": {
    "gn:admin1_code":"9.0",
    "gn:asciiname":"Zhenggang",
    "gn:country_code":"CN",
    "gn:dem":131,
    "gn:feature_class":"P",
    "gn:feature_code":"PPL",
    "gn:name":"Zhenggang",
    "gn:population":0,
    "gn:timezone":"Asia/Shanghai",
    "iso:country":"CN",
    "name:zho_x_preferred":[
        "\u90d1\u5c97"
    ],
    "wof:name":"Zhenggang",
    "wof:placetype":"locality"
},
  "geometry": {"coordinates":[112.11053,32.47074],"type":"Point"}
}