{
  "type": "Feature",
  "properties": {
    "gn:admin1_code":"26.0",
    "gn:asciiname":"Libagou",
    "gn:country_code":"CN",
    "gn:dem":529,
    "gn:feature_class":"P",
    "gn:feature_code":"PPL",
    "gn:name":"Libagou",
    "gn:population":0,
    "gn:timezone":"Asia/Shanghai",
    "iso:country":"CN",
    "name:und_x_variant":[
        "\u7281\u8019\u6c9f"
    ],
    "wof:name":"Libagou",
    "wof:placetype":"locality"
},
  "geometry": {"coordinates":[107.94614,33.1344],"type":"Point"}
}