{
  "type": "Feature",
  "properties": {
    "gn:admin1_code":"7.0",
    "gn:asciiname":"Taxia",
    "gn:country_code":"CN",
    "gn:dem":140,
    "gn:feature_class":"P",
    "gn:feature_code":"PPL",
    "gn:name":"Taxia",
    "gn:population":0,
    "gn:timezone":"Asia/Shanghai",
    "iso:country":"CN",
    "name:zho_x_preferred":[
        "\u5854\u4e0b"
    ],
    "wof:name":"Taxia",
    "wof:placetype":"locality"
},
  "geometry": {"coordinates":[118.20390999999999,26.64062],"type":"Point"}
}