{
  "type": "Feature",
  "properties": {
    "gn:admin1_code":"26.0",
    "gn:asciiname":"Wandengsicun",
    "gn:country_code":"CN",
    "gn:dem":1519,
    "gn:feature_class":"P",
    "gn:feature_code":"PPL",
    "gn:name":"Wandengsicun",
    "gn:population":0,
    "gn:timezone":"Asia/Shanghai",
    "iso:country":"CN",
    "name:zho_x_preferred":[
        "\u4e07\u706f\u5bfa\u6751"
    ],
    "wof:name":"Wandengsicun",
    "wof:placetype":"locality"
},
  "geometry": {"coordinates":[109.56787,33.78782],"type":"Point"}
}