{
  "type": "Feature",
  "properties": {
    "gn:admin1_code":"33.0",
    "gn:asciiname":"Maoping",
    "gn:country_code":"CN",
    "gn:dem":704,
    "gn:feature_class":"P",
    "gn:feature_code":"PPL",
    "gn:name":"Maoping",
    "gn:population":0,
    "gn:timezone":"Asia/Shanghai",
    "iso:country":"CN",
    "name:ceb_x_preferred":[
        "Maoping"
    ],
    "name:deu_x_preferred":[
        "Maoping"
    ],
    "name:swe_x_preferred":[
        "Maoping"
    ],
    "name:zho_x_preferred":[
        "\u8305\u576a"
    ],
    "wof:name":"Maoping",
    "wof:placetype":"locality"
},
  "geometry": {"coordinates":[108.42571,29.66966],"type":"Point"}
}