{
  "type": "Feature",
  "properties": {
    "gn:admin1_code":"32.0",
    "gn:asciiname":"Hetaowan",
    "gn:country_code":"CN",
    "gn:dem":739,
    "gn:feature_class":"P",
    "gn:feature_code":"PPL",
    "gn:name":"Hetaowan",
    "gn:population":0,
    "gn:timezone":"Asia/Shanghai",
    "iso:country":"CN",
    "name:zho_x_preferred":[
        "\u6838\u6843\u6e7e"
    ],
    "wof:name":"Hetaowan",
    "wof:placetype":"locality"
},
  "geometry": {"coordinates":[103.75038000000001,29.1973],"type":"Point"}
}