{
  "type": "Feature",
  "properties": {
    "gn:admin1_code":"04",
    "gn:asciiname":"Mojiancun",
    "gn:country_code":"CN",
    "gn:dem":21,
    "gn:feature_class":"P",
    "gn:feature_code":"PPL",
    "gn:name":"Mojiancun",
    "gn:population":0,
    "gn:timezone":"Asia/Shanghai",
    "iso:country":"CN",
    "name:und_x_variant":[
        "Mo-tao-chien",
        "Modaojian",
        "Mojian",
        "Mojiancun"
    ],
    "name:zho_x_preferred":[
        "\u78e8\u6da7"
    ],
    "name:zho_x_variant":[
        "\u78e8\u6da7\u6751"
    ],
    "wof:name":"Mojiancun",
    "wof:placetype":"locality"
},
  "geometry": {"coordinates":[118.45672999999999,32.95129],"type":"Point"}
}