{
  "type": "Feature",
  "properties": {
    "gn:admin1_code":"2.0",
    "gn:asciiname":"Yachaqiu",
    "gn:country_code":"CN",
    "gn:dem":574,
    "gn:feature_class":"P",
    "gn:feature_code":"PPL",
    "gn:name":"Yachaqiu",
    "gn:population":0,
    "gn:timezone":"Asia/Shanghai",
    "iso:country":"CN",
    "name:zho_x_preferred":[
        "\u4e2b\u53c9\u4e18"
    ],
    "wof:name":"Yachaqiu",
    "wof:placetype":"locality"
},
  "geometry": {"coordinates":[119.24118,28.06078],"type":"Point"}
}