{
  "type": "Feature",
  "properties": {
    "gn:admin1_code":"29.0",
    "gn:asciiname":"Xichongnao",
    "gn:country_code":"CN",
    "gn:dem":1712,
    "gn:feature_class":"P",
    "gn:feature_code":"PPL",
    "gn:name":"Xichongnao",
    "gn:population":0,
    "gn:timezone":"Asia/Shanghai",
    "iso:country":"CN",
    "name:zho_x_preferred":[
        "\u897f\u51b2\u8111"
    ],
    "wof:name":"Xichongnao",
    "wof:placetype":"locality"
},
  "geometry": {"coordinates":[102.096,25.0271],"type":"Point"}
}