{
  "type": "Feature",
  "properties": {
    "gn:admin1_code":"19.0",
    "gn:asciiname":"Kanchuangou",
    "gn:country_code":"CN",
    "gn:dem":382,
    "gn:feature_class":"P",
    "gn:feature_code":"PPL",
    "gn:name":"Kanchuangou",
    "gn:population":0,
    "gn:timezone":"Asia/Shanghai",
    "iso:country":"CN",
    "name:und_x_variant":[
        "\u574e\u5ddd\u6c9f"
    ],
    "name:zho_x_preferred":[
        "\u574e\u5ddd\u6c9f"
    ],
    "wof:name":"Kanchuangou",
    "wof:placetype":"locality"
},
  "geometry": {"coordinates":[125.58996999999999,41.12033],"type":"Point"}
}