{
  "type": "Feature",
  "properties": {
    "gn:admin1_code":"7.0",
    "gn:asciiname":"Qidougang",
    "gn:country_code":"CN",
    "gn:dem":404,
    "gn:feature_class":"P",
    "gn:feature_code":"PPL",
    "gn:name":"Qidougang",
    "gn:population":0,
    "gn:timezone":"Asia/Shanghai",
    "iso:country":"CN",
    "name:zho_x_preferred":[
        "\u4e03\u6597\u5188"
    ],
    "wof:name":"Qidougang",
    "wof:placetype":"locality"
},
  "geometry": {"coordinates":[119.47893999999999,26.70439],"type":"Point"}
}