{
  "type": "Feature",
  "properties": {
    "gn:admin1_code":"6.0",
    "gn:asciiname":"Yaxiu",
    "gn:country_code":"CN",
    "gn:dem":3272,
    "gn:feature_class":"P",
    "gn:feature_code":"PPL",
    "gn:name":"Yaxiu",
    "gn:population":0,
    "gn:timezone":"Asia/Shanghai",
    "iso:country":"CN",
    "name:und_x_variant":[
        "\u4e9a\u79c0"
    ],
    "wof:name":"Yaxiu",
    "wof:placetype":"locality"
},
  "geometry": {"coordinates":[100.06677000000001,37.2989],"type":"Point"}
}