{
  "type": "Feature",
  "properties": {
    "gn:admin1_code":"3.0",
    "gn:asciiname":"Shanghuangwu",
    "gn:country_code":"CN",
    "gn:dem":751,
    "gn:feature_class":"P",
    "gn:feature_code":"PPL",
    "gn:name":"Shanghuangwu",
    "gn:population":0,
    "gn:timezone":"Asia/Shanghai",
    "iso:country":"CN",
    "name:und_x_variant":[
        "\u4e0a\u9ec4\u5c4b"
    ],
    "wof:name":"Shanghuangwu",
    "wof:placetype":"locality"
},
  "geometry": {"coordinates":[115.89643999999998,25.29228],"type":"Point"}
}