{
  "type": "Feature",
  "properties": {
    "gn:admin1_code":"1.0",
    "gn:asciiname":"Qukoucun",
    "gn:country_code":"CN",
    "gn:dem":202,
    "gn:feature_class":"P",
    "gn:feature_code":"PPL",
    "gn:name":"Qukoucun",
    "gn:population":0,
    "gn:timezone":"Asia/Shanghai",
    "iso:country":"CN",
    "name:zho_x_preferred":[
        "\u6e20\u53e3\u6751"
    ],
    "wof:name":"Qukoucun",
    "wof:placetype":"locality"
},
  "geometry": {"coordinates":[118.02410999999999,29.78748],"type":"Point"}
}