{
  "type": "Feature",
  "properties": {
    "gn:admin1_code":"5.0",
    "gn:asciiname":"Qianyonglizhuang",
    "gn:country_code":"CN",
    "gn:dem":187,
    "gn:feature_class":"P",
    "gn:feature_code":"PPL",
    "gn:name":"Qianyonglizhuang",
    "gn:population":0,
    "gn:timezone":"Asia/Shanghai",
    "iso:country":"CN",
    "name:zho_x_preferred":[
        "\u524d\u6c38\u7acb\u5e84"
    ],
    "wof:name":"Qianyonglizhuang",
    "wof:placetype":"locality"
},
  "geometry": {"coordinates":[125.56310000000001,44.2542],"type":"Point"}
}