{
  "type": "Feature",
  "properties": {
    "gn:admin1_code":"4.0",
    "gn:asciiname":"Qianhuxu",
    "gn:country_code":"CN",
    "gn:dem":10,
    "gn:feature_class":"P",
    "gn:feature_code":"PPL",
    "gn:name":"Qianhuxu",
    "gn:population":0,
    "gn:timezone":"Asia/Shanghai",
    "iso:country":"CN",
    "name:zho_x_preferred":[
        "\u524d\u80e1\u5729"
    ],
    "wof:name":"Qianhuxu",
    "wof:placetype":"locality"
},
  "geometry": {"coordinates":[120.57229,31.24863],"type":"Point"}
}