{
  "type": "Feature",
  "properties": {
    "gn:admin1_code":"15.0",
    "gn:asciiname":"Qijia",
    "gn:country_code":"CN",
    "gn:dem":1767,
    "gn:feature_class":"P",
    "gn:feature_code":"PPL",
    "gn:name":"Qijia",
    "gn:population":0,
    "gn:timezone":"Asia/Shanghai",
    "iso:country":"CN",
    "name:zho_x_preferred":[
        "\u7941\u5bb6"
    ],
    "wof:name":"Qijia",
    "wof:placetype":"locality"
},
  "geometry": {"coordinates":[103.319,35.8974],"type":"Point"}
}