{
  "type": "Feature",
  "properties": {
    "gn:admin1_code":"19.0",
    "gn:asciiname":"Qingniwa",
    "gn:country_code":"CN",
    "gn:dem":22,
    "gn:feature_class":"P",
    "gn:feature_code":"PPL",
    "gn:name":"Qingniwa",
    "gn:population":0,
    "gn:timezone":"Asia/Shanghai",
    "iso:country":"CN",
    "name:zho_x_preferred":[
        "\u6e05\u6ce5\u6d3c"
    ],
    "wof:name":"Qingniwa",
    "wof:placetype":"locality"
},
  "geometry": {"coordinates":[122.44,39.5485],"type":"Point"}
}