{
  "type": "Feature",
  "properties": {
    "gn:admin1_code":"14.0",
    "gn:asciiname":"Rendawa",
    "gn:country_code":"CN",
    "gn:dem":3616,
    "gn:feature_class":"P",
    "gn:feature_code":"PPL",
    "gn:name":"Rendawa",
    "gn:population":0,
    "gn:timezone":"Asia/Urumqi",
    "iso:country":"CN",
    "name:zho_x_preferred":[
        "\u4efb\u8fbe\u74e6"
    ],
    "wof:name":"Rendawa",
    "wof:placetype":"locality"
},
  "geometry": {"coordinates":[97.84350000000001,30.52752000000001],"type":"Point"}
}