{
  "type": "Feature",
  "properties": {
    "gn:admin1_code":"15.0",
    "gn:asciiname":"Yujialiang",
    "gn:country_code":"CN",
    "gn:dem":1903,
    "gn:feature_class":"P",
    "gn:feature_code":"PPL",
    "gn:name":"Yujialiang",
    "gn:population":0,
    "gn:timezone":"Asia/Shanghai",
    "iso:country":"CN",
    "name:zho_x_preferred":[
        "\u55bb\u5bb6\u6881"
    ],
    "wof:name":"Yujialiang",
    "wof:placetype":"locality"
},
  "geometry": {"coordinates":[103.633,36.4571],"type":"Point"}
}