{
  "type": "Feature",
  "properties": {
    "gn:admin1_code":"3.0",
    "gn:asciiname":"Xizaotang",
    "gn:country_code":"CN",
    "gn:dem":470,
    "gn:feature_class":"P",
    "gn:feature_code":"PPL",
    "gn:name":"Xizaotang",
    "gn:population":0,
    "gn:timezone":"Asia/Shanghai",
    "iso:country":"CN",
    "name:zho_x_preferred":[
        "\u6d17\u6fa1\u5858"
    ],
    "wof:name":"Xizaotang",
    "wof:placetype":"locality"
},
  "geometry": {"coordinates":[117.896,28.1979],"type":"Point"}
}