{
  "type": "Feature",
  "properties": {
    "gn:admin1_code":"9",
    "gn:asciiname":"Dongwei",
    "gn:country_code":"CN",
    "gn:dem":49,
    "gn:feature_class":"P",
    "gn:feature_code":"PPL",
    "gn:name":"Dongwei",
    "gn:population":0,
    "gn:timezone":"Asia/Shanghai",
    "iso:country":"CN",
    "name:zho_x_preferred":[
        "\u4e1c\u9b4f"
    ],
    "wof:name":"Dongwei",
    "wof:placetype":"locality"
},
  "geometry": {"coordinates":[115.32537000000001,36.01654],"type":"Point"}
}