{
  "type": "Feature",
  "properties": {
    "gn:admin1_code":"31",
    "gn:asciiname":"Lehao",
    "gn:country_code":"CN",
    "gn:dem":19,
    "gn:feature_class":"P",
    "gn:feature_code":"PPL",
    "gn:name":"Lehao",
    "gn:population":0,
    "gn:timezone":"Asia/Shanghai",
    "iso:country":"CN",
    "name:und_x_variant":[
        "\u4e50\u8c6a"
    ],
    "wof:name":"Lehao",
    "wof:placetype":"locality"
},
  "geometry": {"coordinates":[109.83667,19.94731],"type":"Point"}
}