{
  "type": "Feature",
  "properties": {
    "gn:admin1_code":"30.0",
    "gn:asciiname":"Liaowushan",
    "gn:country_code":"CN",
    "gn:dem":73,
    "gn:feature_class":"P",
    "gn:feature_code":"PPL",
    "gn:name":"Liaowushan",
    "gn:population":0,
    "gn:timezone":"Asia/Shanghai",
    "iso:country":"CN",
    "name:zho_x_preferred":[
        "\u5ed6\u5c4b\u5c71"
    ],
    "wof:name":"Liaowushan",
    "wof:placetype":"locality"
},
  "geometry": {"coordinates":[114.95090999999999,23.0923],"type":"Point"}
}