{
  "type": "Feature",
  "properties": {
    "gn:admin1_code":"19.0",
    "gn:asciiname":"Yaobucun",
    "gn:country_code":"CN",
    "gn:dem":132,
    "gn:feature_class":"P",
    "gn:feature_code":"PPL",
    "gn:name":"Yaobucun",
    "gn:population":0,
    "gn:timezone":"Asia/Shanghai",
    "iso:country":"CN",
    "name:zho_x_preferred":[
        "\u8170\u5821\u6751"
    ],
    "wof:name":"Yaobucun",
    "wof:placetype":"locality"
},
  "geometry": {"coordinates":[122.968,40.6438],"type":"Point"}
}