{
  "type": "Feature",
  "properties": {
    "gn:admin1_code":"2.0",
    "gn:asciiname":"Liangwangxu",
    "gn:country_code":"CN",
    "gn:dem":8,
    "gn:feature_class":"P",
    "gn:feature_code":"PPL",
    "gn:name":"Liangwangxu",
    "gn:population":0,
    "gn:timezone":"Asia/Shanghai",
    "iso:country":"CN",
    "name:und_x_variant":[
        "\u667e\u7f51\u5729"
    ],
    "wof:name":"Liangwangxu",
    "wof:placetype":"locality"
},
  "geometry": {"coordinates":[120.30107,30.48927],"type":"Point"}
}