{
  "type": "Feature",
  "properties": {
    "gn:admin1_code":"3.0",
    "gn:asciiname":"Xikeng",
    "gn:country_code":"CN",
    "gn:dem":228,
    "gn:feature_class":"P",
    "gn:feature_code":"PPL",
    "gn:name":"Xikeng",
    "gn:population":0,
    "gn:timezone":"Asia/Shanghai",
    "iso:country":"CN",
    "name:und_x_variant":[
        "\u897f\u5751",
        "Xikengtang"
    ],
    "wof:name":"Xikeng",
    "wof:placetype":"locality"
},
  "geometry": {"coordinates":[116.80942,27.61279],"type":"Point"}
}