{
  "type": "Feature",
  "properties": {
    "gn:admin1_code":"32.0",
    "gn:asciiname":"Gaotuyan",
    "gn:country_code":"CN",
    "gn:dem":573,
    "gn:feature_class":"P",
    "gn:feature_code":"PPL",
    "gn:name":"Gaotuyan",
    "gn:population":0,
    "gn:timezone":"Asia/Shanghai",
    "iso:country":"CN",
    "name:zho_x_preferred":[
        "\u9ad8\u571f\u5830"
    ],
    "wof:name":"Gaotuyan",
    "wof:placetype":"locality"
},
  "geometry": {"coordinates":[103.47721,30.27586],"type":"Point"}
}