{
  "type": "Feature",
  "properties": {
    "gn:admin1_code":"12.0",
    "gn:asciiname":"Tianjiazhou",
    "gn:country_code":"CN",
    "gn:dem":21,
    "gn:feature_class":"P",
    "gn:feature_code":"PPL",
    "gn:name":"Tianjiazhou",
    "gn:population":0,
    "gn:timezone":"Asia/Shanghai",
    "iso:country":"CN",
    "name:zho_x_preferred":[
        "Tianjiazhou"
    ],
    "name:zho_x_variant":[
        "\u7530\u5bb6\u6d32"
    ],
    "wof:name":"Tianjiazhou",
    "wof:placetype":"locality"
},
  "geometry": {"coordinates":[115.10317999999999,30.23452],"type":"Point"}
}