{
  "type": "Feature",
  "properties": {
    "gn:admin1_code":"29.0",
    "gn:asciiname":"Fadadi Shangcun",
    "gn:country_code":"CN",
    "gn:dem":2460,
    "gn:feature_class":"P",
    "gn:feature_code":"PPL",
    "gn:name":"Fadadi Shangcun",
    "gn:population":0,
    "gn:timezone":"Asia/Shanghai",
    "iso:country":"CN",
    "name:zho_x_preferred":[
        "\u53d1\u8fbe\u5730\u4e0a\u6751"
    ],
    "wof:name":"Fadadi Shangcun",
    "wof:placetype":"locality"
},
  "geometry": {"coordinates":[100.578,24.8751],"type":"Point"}
}