{
  "type": "Feature",
  "properties": {
    "gn:admin1_code":"29.0",
    "gn:asciiname":"Heshangzhuang",
    "gn:country_code":"CN",
    "gn:dem":1816,
    "gn:feature_class":"P",
    "gn:feature_code":"PPL",
    "gn:name":"Heshangzhuang",
    "gn:population":0,
    "gn:timezone":"Asia/Shanghai",
    "iso:country":"CN",
    "name:zho_x_preferred":[
        "\u548c\u5c1a\u5e84"
    ],
    "wof:name":"Heshangzhuang",
    "wof:placetype":"locality"
},
  "geometry": {"coordinates":[102.38500000000001,25.5628],"type":"Point"}
}