{
  "type": "Feature",
  "properties": {
    "gn:admin1_code":"29.0",
    "gn:asciiname":"Shenzu Laocun",
    "gn:country_code":"CN",
    "gn:dem":2105,
    "gn:feature_class":"P",
    "gn:feature_code":"PPL",
    "gn:name":"Shenzu Laocun",
    "gn:population":0,
    "gn:timezone":"Asia/Shanghai",
    "iso:country":"CN",
    "name:zho_x_preferred":[
        "\u7533\u7956\u8001\u6751"
    ],
    "wof:name":"Shenzu Laocun",
    "wof:placetype":"locality"
},
  "geometry": {"coordinates":[102.208,25.7483],"type":"Point"}
}