{
  "type": "Feature",
  "properties": {
    "gn:admin1_code":"30",
    "gn:asciiname":"Yuantouhu",
    "gn:country_code":"CN",
    "gn:dem":13,
    "gn:feature_class":"P",
    "gn:feature_code":"PPL",
    "gn:name":"Yuantouhu",
    "gn:population":0,
    "gn:timezone":"Asia/Shanghai",
    "iso:country":"CN",
    "name:zho_x_preferred":[
        "\u56ed\u5934\u6e56"
    ],
    "wof:name":"Yuantouhu",
    "wof:placetype":"locality"
},
  "geometry": {"coordinates":[116.05450999999999,23.04165],"type":"Point"}
}