{
  "type": "Feature",
  "properties": {
    "gn:admin1_code":"04",
    "gn:asciiname":"Qingshuigang",
    "gn:country_code":"CN",
    "gn:dem":5,
    "gn:feature_class":"P",
    "gn:feature_code":"PPL",
    "gn:name":"Qingshuigang",
    "gn:population":0,
    "gn:timezone":"Asia/Shanghai",
    "iso:country":"CN",
    "name:und_x_variant":[
        "Ch\u2019ing-chia-kang",
        "Qingshuigang",
        "\u6e05\u6c34\u6e2f"
    ],
    "wof:name":"Qingshuigang",
    "wof:placetype":"locality"
},
  "geometry": {"coordinates":[120.72962,31.41659000000001],"type":"Point"}
}