{
  "type": "Feature",
  "properties": {
    "gn:admin1_code":"5.0",
    "gn:asciiname":"Rongxingcun",
    "gn:country_code":"CN",
    "gn:dem":576,
    "gn:feature_class":"P",
    "gn:feature_code":"PPL",
    "gn:name":"Rongxingcun",
    "gn:population":0,
    "gn:timezone":"Asia/Shanghai",
    "iso:country":"CN",
    "name:zho_x_preferred":[
        "\u8363\u5174\u6751"
    ],
    "wof:name":"Rongxingcun",
    "wof:placetype":"locality"
},
  "geometry": {"coordinates":[128.21323000000001,43.18161],"type":"Point"}
}