{
  "type": "Feature",
  "properties": {
    "gn:admin1_code":"1.0",
    "gn:asciiname":"Zhangqiancun",
    "gn:country_code":"CN",
    "gn:dem":34,
    "gn:feature_class":"P",
    "gn:feature_code":"PPL",
    "gn:name":"Zhangqiancun",
    "gn:population":0,
    "gn:timezone":"Asia/Shanghai",
    "iso:country":"CN",
    "name:zho_x_preferred":[
        "\u5f20\u6d45\u6751"
    ],
    "wof:name":"Zhangqiancun",
    "wof:placetype":"locality"
},
  "geometry": {"coordinates":[116.218,33.63835],"type":"Point"}
}