{
  "type": "Feature",
  "properties": {
    "gn:admin1_code":"2.0",
    "gn:asciiname":"Xiwuli",
    "gn:country_code":"CN",
    "gn:dem":437,
    "gn:feature_class":"P",
    "gn:feature_code":"PPL",
    "gn:name":"Xiwuli",
    "gn:population":0,
    "gn:timezone":"Asia/Shanghai",
    "iso:country":"CN",
    "name:zho_x_preferred":[
        "\u897f\u575e\u91cc"
    ],
    "wof:name":"Xiwuli",
    "wof:placetype":"locality"
},
  "geometry": {"coordinates":[118.65936000000001,29.18985],"type":"Point"}
}