{
  "type": "Feature",
  "properties": {
    "gn:admin1_code":"25",
    "gn:asciiname":"Liuloudong",
    "gn:country_code":"CN",
    "gn:dem":49,
    "gn:feature_class":"P",
    "gn:feature_code":"PPL",
    "gn:name":"Liuloudong",
    "gn:population":0,
    "gn:timezone":"Asia/Shanghai",
    "iso:country":"CN",
    "name:zho_x_preferred":[
        "\u5218\u697c\u4e1c"
    ],
    "wof:name":"Liuloudong",
    "wof:placetype":"locality"
},
  "geometry": {"coordinates":[115.879,35.1536],"type":"Point"}
}