{
  "type": "Feature",
  "properties": {
    "gn:admin1_code":"9.0",
    "gn:asciiname":"Liucun",
    "gn:country_code":"CN",
    "gn:dem":194,
    "gn:feature_class":"P",
    "gn:feature_code":"PPL",
    "gn:name":"Liucun",
    "gn:population":0,
    "gn:timezone":"Asia/Shanghai",
    "iso:country":"CN",
    "name:und_x_variant":[
        "\u5218\u6751",
        "Liucun"
    ],
    "wof:name":"Liucun",
    "wof:placetype":"locality"
},
  "geometry": {"coordinates":[112.58336,33.36856],"type":"Point"}
}