{
  "type": "Feature",
  "properties": {
    "gn:admin1_code":"13",
    "gn:asciiname":"Cuixi",
    "gn:country_code":"CN",
    "gn:dem":917,
    "gn:feature_class":"P",
    "gn:feature_code":"PPL",
    "gn:name":"Cuixi",
    "gn:population":0,
    "gn:timezone":"Asia/Urumqi",
    "iso:country":"CN",
    "name:zho_x_preferred":[
        "\u7fe0\u897f"
    ],
    "wof:name":"Cuixi",
    "wof:placetype":"locality"
},
  "geometry": {"coordinates":[94.15058000000001,42.07361],"type":"Point"}
}