{
  "type": "Feature",
  "properties": {
    "gn:admin1_code":"4.0",
    "gn:asciiname":"Xiashu",
    "gn:country_code":"CN",
    "gn:dem":9,
    "gn:feature_class":"P",
    "gn:feature_code":"PPL",
    "gn:name":"Xiashu",
    "gn:population":0,
    "gn:timezone":"Asia/Shanghai",
    "iso:country":"CN",
    "name:zho_x_preferred":[
        "\u590f\u587e"
    ],
    "wof:name":"Xiashu",
    "wof:placetype":"locality"
},
  "geometry": {"coordinates":[120.13179,31.79279],"type":"Point"}
}