{
  "type": "Feature",
  "properties": {
    "gn:admin1_code":"19.0",
    "gn:asciiname":"Dabinggou",
    "gn:country_code":"CN",
    "gn:dem":474,
    "gn:feature_class":"P",
    "gn:feature_code":"PPL",
    "gn:name":"Dabinggou",
    "gn:population":0,
    "gn:timezone":"Asia/Shanghai",
    "iso:country":"CN",
    "name:zho_x_preferred":[
        "\u5927\u51b0\u6c9f"
    ],
    "wof:name":"Dabinggou",
    "wof:placetype":"locality"
},
  "geometry": {"coordinates":[119.90300000000001,40.808],"type":"Point"}
}