{
  "type": "Feature",
  "properties": {
    "gn:admin1_code":"26",
    "gn:asciiname":"Beiqian",
    "gn:country_code":"CN",
    "gn:dem":371,
    "gn:feature_class":"P",
    "gn:feature_code":"PPL",
    "gn:name":"Beiqian",
    "gn:population":0,
    "gn:timezone":"Asia/Shanghai",
    "iso:country":"CN",
    "name:zho_x_preferred":[
        "\u5317\u94b1"
    ],
    "wof:name":"Beiqian",
    "wof:placetype":"locality"
},
  "geometry": {"coordinates":[108.99709,34.38498],"type":"Point"}
}