{
  "type": "Feature",
  "properties": {
    "gn:admin1_code":"30",
    "gn:asciiname":"Zhuanwuzhai",
    "gn:country_code":"CN",
    "gn:dem":58,
    "gn:feature_class":"P",
    "gn:feature_code":"PPL",
    "gn:name":"Zhuanwuzhai",
    "gn:population":0,
    "gn:timezone":"Asia/Shanghai",
    "iso:country":"CN",
    "name:zho_x_preferred":[
        "\u7816\u5c4b\u5be8"
    ],
    "wof:name":"Zhuanwuzhai",
    "wof:placetype":"locality"
},
  "geometry": {"coordinates":[111.3794,21.93555],"type":"Point"}
}