{
  "type": "Feature",
  "properties": {
    "gn:admin1_code":"16.0",
    "gn:asciiname":"Geng'ou",
    "gn:country_code":"CN",
    "gn:dem":668,
    "gn:feature_class":"P",
    "gn:feature_code":"PPL",
    "gn:name":"Geng\u2019ou",
    "gn:population":0,
    "gn:timezone":"Asia/Shanghai",
    "iso:country":"CN",
    "name:und_x_variant":[
        "Geng\u2019ou"
    ],
    "name:zho_x_preferred":[
        "\u66f4\u5076"
    ],
    "wof:name":"Geng'ou",
    "wof:placetype":"locality"
},
  "geometry": {"coordinates":[107.235,25.2708],"type":"Point"}
}