{
  "type": "Feature",
  "properties": {
    "gn:admin1_code":"02",
    "gn:asciiname":"Qiligang",
    "gn:country_code":"CN",
    "gn:dem":-9999,
    "gn:feature_class":"P",
    "gn:feature_code":"PPL",
    "gn:name":"Qiligang",
    "gn:population":0,
    "gn:timezone":"Asia/Shanghai",
    "iso:country":"CN",
    "name:und_x_variant":[
        "Qili",
        "Qiligang"
    ],
    "name:zho_x_preferred":[
        "\u4e03\u91cc\u6e2f"
    ],
    "wof:name":"Qiligang",
    "wof:placetype":"locality"
},
  "geometry": {"coordinates":[120.89098,27.99529],"type":"Point"}
}