{
  "type": "Feature",
  "properties": {
    "gn:admin1_code":"26.0",
    "gn:asciiname":"Beixingcun",
    "gn:country_code":"CN",
    "gn:dem":847,
    "gn:feature_class":"P",
    "gn:feature_code":"PPL",
    "gn:name":"Beixingcun",
    "gn:population":0,
    "gn:timezone":"Asia/Shanghai",
    "iso:country":"CN",
    "name:zho_x_preferred":[
        "\u5317\u5174\u6751"
    ],
    "wof:name":"Beixingcun",
    "wof:placetype":"locality"
},
  "geometry": {"coordinates":[109.55538,35.13095],"type":"Point"}
}