{
  "type": "Feature",
  "properties": {
    "gn:admin1_code":"18",
    "gn:asciiname":"Gaolan",
    "gn:country_code":"CN",
    "gn:dem":1014,
    "gn:feature_class":"P",
    "gn:feature_code":"PPL",
    "gn:name":"Gaolan",
    "gn:population":0,
    "gn:timezone":"Asia/Shanghai",
    "iso:country":"CN",
    "name:zho_x_preferred":[
        "\u9ad8\u5c9a"
    ],
    "wof:name":"Gaolan",
    "wof:placetype":"locality"
},
  "geometry": {"coordinates":[107.512,27.2185],"type":"Point"}
}