{
  "type": "Feature",
  "properties": {
    "gn:admin1_code":"18",
    "gn:asciiname":"Shalaiqiao",
    "gn:country_code":"CN",
    "gn:dem":1325,
    "gn:feature_class":"P",
    "gn:feature_code":"PPL",
    "gn:name":"Shalaiqiao",
    "gn:population":0,
    "gn:timezone":"Asia/Shanghai",
    "iso:country":"CN",
    "name:zho_x_preferred":[
        "\u6740\u8d56\u6865"
    ],
    "wof:name":"Shalaiqiao",
    "wof:placetype":"locality"
},
  "geometry": {"coordinates":[105.46299999999999,25.1747],"type":"Point"}
}