{
  "type": "Feature",
  "properties": {
    "gn:admin1_code":"10",
    "gn:asciiname":"Nuandianbu",
    "gn:country_code":"CN",
    "gn:dem":805,
    "gn:feature_class":"P",
    "gn:feature_code":"PPL",
    "gn:name":"Nuandianbu",
    "gn:population":0,
    "gn:timezone":"Asia/Shanghai",
    "iso:country":"CN",
    "name:zho_x_preferred":[
        "\u6696\u5e97\u5821"
    ],
    "wof:name":"Nuandianbu",
    "wof:placetype":"locality"
},
  "geometry": {"coordinates":[114.7178,40.79671],"type":"Point"}
}