{
  "type": "Feature",
  "properties": {
    "gn:admin1_code":"9.0",
    "gn:asciiname":"Qian'an Huzhai",
    "gn:country_code":"CN",
    "gn:dem":67,
    "gn:feature_class":"P",
    "gn:feature_code":"PPL",
    "gn:name":"Qian\u2019an Huzhai",
    "gn:population":0,
    "gn:timezone":"Asia/Shanghai",
    "iso:country":"CN",
    "name:und_x_variant":[
        "Qian\u2019an Huzhai"
    ],
    "name:zho_x_preferred":[
        "\u524d\u5b89\u864e\u5be8"
    ],
    "wof:name":"Qian'an Huzhai",
    "wof:placetype":"locality"
},
  "geometry": {"coordinates":[114.47229,35.34597],"type":"Point"}
}