{
  "type": "Feature",
  "properties": {
    "gn:admin1_code":"3.0",
    "gn:asciiname":"Dalongcun",
    "gn:country_code":"CN",
    "gn:dem":41,
    "gn:feature_class":"P",
    "gn:feature_code":"PPL",
    "gn:name":"Dalongcun",
    "gn:population":0,
    "gn:timezone":"Asia/Shanghai",
    "iso:country":"CN",
    "name:und_x_variant":[
        "\u5927\u5784\u6751"
    ],
    "wof:name":"Dalongcun",
    "wof:placetype":"locality"
},
  "geometry": {"coordinates":[116.38684000000001,29.75386],"type":"Point"}
}