{
  "type": "Feature",
  "properties": {
    "gn:admin1_code":"19.0",
    "gn:asciiname":"Xiaguotun",
    "gn:country_code":"CN",
    "gn:dem":12,
    "gn:feature_class":"P",
    "gn:feature_code":"PPL",
    "gn:name":"Xiaguotun",
    "gn:population":0,
    "gn:timezone":"Asia/Shanghai",
    "iso:country":"CN",
    "name:zho_x_preferred":[
        "\u4e0b\u90ed\u5c6f"
    ],
    "wof:name":"Xiaguotun",
    "wof:placetype":"locality"
},
  "geometry": {"coordinates":[122.089,39.22],"type":"Point"}
}