{
  "type": "Feature",
  "properties": {
    "gn:admin1_code":"2.0",
    "gn:asciiname":"Yanhou",
    "gn:country_code":"CN",
    "gn:dem":345,
    "gn:feature_class":"P",
    "gn:feature_code":"PPL",
    "gn:name":"Yanhou",
    "gn:population":0,
    "gn:timezone":"Asia/Shanghai",
    "iso:country":"CN",
    "name:zho_x_preferred":[
        "\u5ca9\u540e"
    ],
    "wof:name":"Yanhou",
    "wof:placetype":"locality"
},
  "geometry": {"coordinates":[118.94746000000001,27.71185],"type":"Point"}
}