{
  "type": "Feature",
  "properties": {
    "gn:admin1_code":"15",
    "gn:asciiname":"Wangzhaiji",
    "gn:country_code":"CN",
    "gn:dem":1373,
    "gn:feature_class":"P",
    "gn:feature_code":"PPL",
    "gn:name":"Wangzhaiji",
    "gn:population":0,
    "gn:timezone":"Asia/Shanghai",
    "iso:country":"CN",
    "wof:name":"Wangzhaiji",
    "wof:placetype":"locality"
},
  "geometry": {"coordinates":[107.42028000000001,35.81028],"type":"Point"}
}