{
  "type": "Feature",
  "properties": {
    "gn:admin1_code":"7",
    "gn:asciiname":"Liancuo",
    "gn:country_code":"CN",
    "gn:dem":20,
    "gn:feature_class":"P",
    "gn:feature_code":"PPL",
    "gn:name":"Liancuo",
    "gn:population":0,
    "gn:timezone":"Asia/Shanghai",
    "iso:country":"CN",
    "name:zho_x_preferred":[
        "\u83b2\u539d"
    ],
    "wof:name":"Liancuo",
    "wof:placetype":"locality"
},
  "geometry": {"coordinates":[118.71889,24.74694],"type":"Point"}
}