{
  "type": "Feature",
  "properties": {
    "gn:admin1_code":"9.0",
    "gn:asciiname":"Wugang",
    "gn:country_code":"CN",
    "gn:dem":36,
    "gn:feature_class":"P",
    "gn:feature_code":"PPL",
    "gn:name":"Wugang",
    "gn:population":0,
    "gn:timezone":"Asia/Shanghai",
    "iso:country":"CN",
    "name:zho_x_preferred":[
        "\u5434\u5c97"
    ],
    "wof:name":"Wugang",
    "wof:placetype":"locality"
},
  "geometry": {"coordinates":[115.47992000000001,32.45572],"type":"Point"}
}