{
  "type": "Feature",
  "properties": {
    "gn:admin1_code":"18",
    "gn:asciiname":"Hetou",
    "gn:country_code":"CN",
    "gn:dem":1156,
    "gn:feature_class":"P",
    "gn:feature_code":"PPL",
    "gn:name":"Hetou",
    "gn:population":0,
    "gn:timezone":"Asia/Shanghai",
    "iso:country":"CN",
    "name:zho_x_preferred":[
        "\u6cb3\u5934"
    ],
    "wof:name":"Hetou",
    "wof:placetype":"locality"
},
  "geometry": {"coordinates":[105.76600000000001,26.3744],"type":"Point"}
}