{
  "type": "Feature",
  "properties": {
    "gn:admin1_code":"12.0",
    "gn:asciiname":"Chelukou",
    "gn:country_code":"CN",
    "gn:dem":39,
    "gn:feature_class":"P",
    "gn:feature_code":"PPL",
    "gn:name":"Chelukou",
    "gn:population":0,
    "gn:timezone":"Asia/Shanghai",
    "iso:country":"CN",
    "name:zho_x_preferred":[
        "\u8f66\u8def\u53e3"
    ],
    "wof:name":"Chelukou",
    "wof:placetype":"locality"
},
  "geometry": {"coordinates":[112.02717,30.23237],"type":"Point"}
}