{
  "type": "Feature",
  "properties": {
    "gn:admin1_code":"16.0",
    "gn:asciiname":"Lilin",
    "gn:country_code":"CN",
    "gn:dem":419,
    "gn:feature_class":"P",
    "gn:feature_code":"PPL",
    "gn:name":"Lilin",
    "gn:population":0,
    "gn:timezone":"Asia/Shanghai",
    "iso:country":"CN",
    "name:ara_x_preferred":[
        "\u0644\u064a\u0644\u064a\u0646"
    ],
    "name:ces_x_preferred":[
        "Lil\u00fa"
    ],
    "name:fra_x_preferred":[
        "Lil\u016b"
    ],
    "name:hun_x_preferred":[
        "Lilin"
    ],
    "name:ita_x_preferred":[
        "Lilim"
    ],
    "name:jpn_x_preferred":[
        "\u30ea\u30ea\u30f3"
    ],
    "name:rus_x_preferred":[
        "\u041b\u0438\u043b\u0438\u043c"
    ],
    "name:spa_x_preferred":[
        "Lilim"
    ],
    "name:swe_x_preferred":[
        "Lilim"
    ],
    "name:zho_x_preferred":[
        "\u91cc\u6797"
    ],
    "wof:name":"Lilin",
    "wof:placetype":"locality"
},
  "geometry": {"coordinates":[108.398,23.8557],"type":"Point"}
}