{
  "type": "Feature",
  "properties": {
    "gn:admin1_code":"08",
    "gn:asciiname":"Shisanzhan",
    "gn:country_code":"CN",
    "gn:dem":427,
    "gn:feature_class":"P",
    "gn:feature_code":"PPL",
    "gn:name":"Shisanzhan",
    "gn:population":0,
    "gn:timezone":"Asia/Shanghai",
    "iso:country":"CN",
    "name:eng_x_preferred":[
        "Shisanzhan"
    ],
    "name:rus_x_preferred":[
        "\u0428\u0438\u0441\u0430\u043d\u044c\u0447\u0436\u0430\u043d\u044c"
    ],
    "name:und_x_variant":[
        "Shih-san-chan"
    ],
    "name:zho_x_preferred":[
        "\u5341\u4e09\u7ad9"
    ],
    "wof:name":"Shisanzhan",
    "wof:placetype":"locality"
},
  "geometry": {"coordinates":[125.70814,51.36691],"type":"Point"}
}