{
  "type": "Feature",
  "properties": {
    "gn:admin1_code":"25",
    "gn:asciiname":"Houxianghe",
    "gn:country_code":"CN",
    "gn:dem":122,
    "gn:feature_class":"P",
    "gn:feature_code":"PPL",
    "gn:name":"Houxianghe",
    "gn:population":0,
    "gn:timezone":"Asia/Shanghai",
    "iso:country":"CN",
    "name:zho_x_preferred":[
        "\u540e\u76f8\u6cb3"
    ],
    "wof:name":"Houxianghe",
    "wof:placetype":"locality"
},
  "geometry": {"coordinates":[117.22,35.2688],"type":"Point"}
}