{
  "type": "Feature",
  "properties": {
    "gn:admin1_code":"25",
    "gn:asciiname":"Lishanjiang",
    "gn:country_code":"CN",
    "gn:dem":314,
    "gn:feature_class":"P",
    "gn:feature_code":"PPL",
    "gn:name":"Lishanjiang",
    "gn:population":0,
    "gn:timezone":"Asia/Shanghai",
    "iso:country":"CN",
    "name:zho_x_preferred":[
        "\u91cc\u5c71\u5c06"
    ],
    "wof:name":"Lishanjiang",
    "wof:placetype":"locality"
},
  "geometry": {"coordinates":[117.58499999999999,35.2967],"type":"Point"}
}