{
  "type": "Feature",
  "properties": {
    "gn:admin1_code":"11.0",
    "gn:asciiname":"Chengang",
    "gn:country_code":"CN",
    "gn:dem":323,
    "gn:feature_class":"P",
    "gn:feature_code":"PPL",
    "gn:name":"Chengang",
    "gn:population":0,
    "gn:timezone":"Asia/Shanghai",
    "iso:country":"CN",
    "name:zho_x_preferred":[
        "\u6668\u5c97"
    ],
    "wof:name":"Chengang",
    "wof:placetype":"locality"
},
  "geometry": {"coordinates":[112.56543000000001,25.58891],"type":"Point"}
}