{
  "type": "Feature",
  "properties": {
    "gn:admin1_code":"3.0",
    "gn:asciiname":"Santianfan",
    "gn:country_code":"CN",
    "gn:dem":117,
    "gn:feature_class":"P",
    "gn:feature_code":"PPL",
    "gn:name":"Santianfan",
    "gn:population":0,
    "gn:timezone":"Asia/Shanghai",
    "iso:country":"CN",
    "name:zho_x_preferred":[
        "\u4e09\u7530\u7548"
    ],
    "wof:name":"Santianfan",
    "wof:placetype":"locality"
},
  "geometry": {"coordinates":[117.42458000000001,28.19813],"type":"Point"}
}