{
  "type": "Feature",
  "properties": {
    "gn:admin1_code":"30.0",
    "gn:asciiname":"Qixingdun",
    "gn:country_code":"CN",
    "gn:dem":270,
    "gn:feature_class":"P",
    "gn:feature_code":"PPL",
    "gn:name":"Qixingdun",
    "gn:population":0,
    "gn:timezone":"Asia/Shanghai",
    "iso:country":"CN",
    "name:zho_x_preferred":[
        "\u4e03\u661f\u58a9"
    ],
    "wof:name":"Qixingdun",
    "wof:placetype":"locality"
},
  "geometry": {"coordinates":[113.95265000000001,23.65923],"type":"Point"}
}