{
  "type": "Feature",
  "properties": {
    "gn:admin1_code":"32.0",
    "gn:asciiname":"Chacaoping",
    "gn:country_code":"CN",
    "gn:dem":3771,
    "gn:feature_class":"P",
    "gn:feature_code":"PPL",
    "gn:name":"Chacaoping",
    "gn:population":0,
    "gn:timezone":"Asia/Shanghai",
    "iso:country":"CN",
    "name:zho_x_preferred":[
        "\u63d2\u8349\u576a"
    ],
    "wof:name":"Chacaoping",
    "wof:placetype":"locality"
},
  "geometry": {"coordinates":[101.69164000000001,31.13723],"type":"Point"}
}