{
  "type": "Feature",
  "properties": {
    "gn:admin1_code":"22.0",
    "gn:asciiname":"Dongjunzhuang",
    "gn:country_code":"CN",
    "gn:dem":33,
    "gn:feature_class":"P",
    "gn:feature_code":"PPL",
    "gn:name":"Dongjunzhuang",
    "gn:population":0,
    "gn:timezone":"Asia/Shanghai",
    "iso:country":"CN",
    "name:zho_x_preferred":[
        "\u4e1c\u519b\u5e84"
    ],
    "wof:name":"Dongjunzhuang",
    "wof:placetype":"locality"
},
  "geometry": {"coordinates":[116.61143,39.91402],"type":"Point"}
}