{
  "type": "Feature",
  "properties": {
    "gn:admin1_code":"30.0",
    "gn:asciiname":"Guolizai",
    "gn:country_code":"CN",
    "gn:dem":14,
    "gn:feature_class":"P",
    "gn:feature_code":"PPL",
    "gn:name":"Guolizai",
    "gn:population":0,
    "gn:timezone":"Asia/Shanghai",
    "iso:country":"CN",
    "name:zho_x_preferred":[
        "\u8fc7\u6ca5\u4ed4"
    ],
    "wof:name":"Guolizai",
    "wof:placetype":"locality"
},
  "geometry": {"coordinates":[114.46297,23.18729],"type":"Point"}
}