{
  "type": "Feature",
  "properties": {
    "gn:admin1_code":"29.0",
    "gn:asciiname":"Laowangpo",
    "gn:country_code":"CN",
    "gn:dem":2411,
    "gn:feature_class":"P",
    "gn:feature_code":"PPL",
    "gn:name":"Laowangpo",
    "gn:population":0,
    "gn:timezone":"Asia/Shanghai",
    "iso:country":"CN",
    "name:zho_x_preferred":[
        "\u8001\u738b\u5761"
    ],
    "wof:name":"Laowangpo",
    "wof:placetype":"locality"
},
  "geometry": {"coordinates":[102.102,25.5137],"type":"Point"}
}