{
  "type": "Feature",
  "properties": {
    "gn:admin1_code":"04",
    "gn:asciiname":"Touqiao",
    "gn:country_code":"CN",
    "gn:dem":4,
    "gn:feature_class":"P",
    "gn:feature_code":"PPL",
    "gn:name":"Touqiao",
    "gn:population":0,
    "gn:timezone":"Asia/Shanghai",
    "iso:country":"CN",
    "name:und_x_variant":[
        "T\u2019ou-ch\u2019iao-chen",
        "T\u2019ou-ch\u2019iao",
        "Touqiao"
    ],
    "name:zho_x_preferred":[
        "\u5934\u6865"
    ],
    "wof:name":"Touqiao",
    "wof:placetype":"locality"
},
  "geometry": {"coordinates":[119.64198,32.32686],"type":"Point"}
}