{
  "type": "Feature",
  "properties": {
    "gn:admin1_code":"30.0",
    "gn:asciiname":"Bali",
    "gn:country_code":"CN",
    "gn:dem":343,
    "gn:feature_class":"P",
    "gn:feature_code":"PPL",
    "gn:name":"Bali",
    "gn:population":0,
    "gn:timezone":"Asia/Shanghai",
    "iso:country":"CN",
    "name:zho_x_preferred":[
        "Bali"
    ],
    "name:zho_x_variant":[
        "\u575d\u4fda"
    ],
    "wof:name":"Bali",
    "wof:placetype":"locality"
},
  "geometry": {"coordinates":[113.90722,25.18694],"type":"Point"}
}