{
  "type": "Feature",
  "properties": {
    "gn:admin1_code":"30.0",
    "gn:asciiname":"Shigucheng",
    "gn:country_code":"CN",
    "gn:dem":265,
    "gn:feature_class":"P",
    "gn:feature_code":"PPL",
    "gn:name":"Shigucheng",
    "gn:population":0,
    "gn:timezone":"Asia/Shanghai",
    "iso:country":"CN",
    "name:zho_x_preferred":[
        "Shigucheng"
    ],
    "name:zho_x_variant":[
        "\u77f3\u53e4\u57ce"
    ],
    "wof:name":"Shigucheng",
    "wof:placetype":"locality"
},
  "geometry": {"coordinates":[114.99583,24.66944],"type":"Point"}
}