{
  "type": "Feature",
  "properties": {
    "gn:admin1_code":"25",
    "gn:asciiname":"Nanhuacun",
    "gn:country_code":"CN",
    "gn:dem":158,
    "gn:feature_class":"P",
    "gn:feature_code":"PPL",
    "gn:name":"Nanhuacun",
    "gn:population":0,
    "gn:timezone":"Asia/Shanghai",
    "iso:country":"CN",
    "name:zho_x_preferred":[
        "\u5357\u534e\u6751"
    ],
    "wof:name":"Nanhuacun",
    "wof:placetype":"locality"
},
  "geometry": {"coordinates":[117.45399999999999,35.6997],"type":"Point"}
}