{
  "type": "Feature",
  "properties": {
    "gn:admin1_code":"15.0",
    "gn:asciiname":"Datoushan",
    "gn:country_code":"CN",
    "gn:dem":2398,
    "gn:feature_class":"P",
    "gn:feature_code":"PPL",
    "gn:name":"Datoushan",
    "gn:population":0,
    "gn:timezone":"Asia/Shanghai",
    "iso:country":"CN",
    "name:zho_x_preferred":[
        "\u5927\u5934\u5c71"
    ],
    "wof:name":"Datoushan",
    "wof:placetype":"locality"
},
  "geometry": {"coordinates":[104.044,35.2254],"type":"Point"}
}