{
  "type": "Feature",
  "properties": {
    "gn:admin1_code":"32.0",
    "gn:asciiname":"Wule",
    "gn:country_code":"CN",
    "gn:dem":3882,
    "gn:feature_class":"P",
    "gn:feature_code":"PPL",
    "gn:name":"Wule",
    "gn:population":0,
    "gn:timezone":"Asia/Shanghai",
    "iso:country":"CN",
    "name:zho_x_preferred":[
        "\u4e4c\u52d2"
    ],
    "wof:name":"Wule",
    "wof:placetype":"locality"
},
  "geometry": {"coordinates":[100.19199999999999,31.8454],"type":"Point"}
}