{
  "type": "Feature",
  "properties": {
    "gn:admin1_code":"25.0",
    "gn:asciiname":"Jixian",
    "gn:country_code":"CN",
    "gn:dem":43,
    "gn:feature_class":"P",
    "gn:feature_code":"PPL",
    "gn:name":"Jixian",
    "gn:population":0,
    "gn:timezone":"Asia/Shanghai",
    "iso:country":"CN",
    "name:ceb_x_preferred":[
        "Jixian"
    ],
    "name:deu_x_preferred":[
        "Jixian"
    ],
    "name:zho_x_preferred":[
        "\u96c6\u8d24"
    ],
    "wof:name":"Jixian",
    "wof:placetype":"locality"
},
  "geometry": {"coordinates":[121.27818000000001,37.39655],"type":"Point"}
}