{
  "type": "Feature",
  "properties": {
    "gn:admin1_code":"19.0",
    "gn:asciiname":"Fengjia Xigou",
    "gn:country_code":"CN",
    "gn:dem":116,
    "gn:feature_class":"P",
    "gn:feature_code":"PPL",
    "gn:name":"Fengjia Xigou",
    "gn:population":0,
    "gn:timezone":"Asia/Shanghai",
    "iso:country":"CN",
    "name:zho_x_preferred":[
        "\u51af\u5bb6\u897f\u6c9f"
    ],
    "wof:name":"Fengjia Xigou",
    "wof:placetype":"locality"
},
  "geometry": {"coordinates":[123.381,41.1957],"type":"Point"}
}