{
  "type": "Feature",
  "properties": {
    "gn:admin1_code":"19.0",
    "gn:asciiname":"Gaoligou",
    "gn:country_code":"CN",
    "gn:dem":219,
    "gn:feature_class":"P",
    "gn:feature_code":"PPL",
    "gn:name":"Gaoligou",
    "gn:population":0,
    "gn:timezone":"Asia/Shanghai",
    "iso:country":"CN",
    "name:und_x_variant":[
        "\u9ad8\u529b\u6c9f"
    ],
    "wof:name":"Gaoligou",
    "wof:placetype":"locality"
},
  "geometry": {"coordinates":[124.30071,41.81707],"type":"Point"}
}