{
  "type": "Feature",
  "properties": {
    "gn:admin1_code":"12.0",
    "gn:asciiname":"Luojiaotang",
    "gn:country_code":"CN",
    "gn:dem":575,
    "gn:feature_class":"P",
    "gn:feature_code":"PPL",
    "gn:name":"Luojiaotang",
    "gn:population":0,
    "gn:timezone":"Asia/Shanghai",
    "iso:country":"CN",
    "name:zho_x_preferred":[
        "Luojiaotang"
    ],
    "name:zho_x_variant":[
        "\u843d\u89d2\u5858"
    ],
    "wof:name":"Luojiaotang",
    "wof:placetype":"locality"
},
  "geometry": {"coordinates":[109.11024,29.42875],"type":"Point"}
}