{
  "type": "Feature",
  "properties": {
    "gn:admin1_code":"14.0",
    "gn:asciiname":"Jide",
    "gn:country_code":"CN",
    "gn:dem":3877,
    "gn:feature_class":"P",
    "gn:feature_code":"PPL",
    "gn:name":"Jide",
    "gn:population":0,
    "gn:timezone":"Asia/Urumqi",
    "iso:country":"CN",
    "name:zho_x_preferred":[
        "\u5409\u5fb7"
    ],
    "wof:name":"Jide",
    "wof:placetype":"locality"
},
  "geometry": {"coordinates":[91.34907,29.1465],"type":"Point"}
}