{
  "type": "Feature",
  "properties": {
    "gn:admin1_code":"9.0",
    "gn:asciiname":"Zhai'ao",
    "gn:country_code":"CN",
    "gn:dem":381,
    "gn:feature_class":"P",
    "gn:feature_code":"PPL",
    "gn:name":"Zhai\u2019ao",
    "gn:population":0,
    "gn:timezone":"Asia/Shanghai",
    "iso:country":"CN",
    "name:und_x_variant":[
        "Zhai\u2019ao"
    ],
    "name:zho_x_preferred":[
        "\u5be8\u51f9"
    ],
    "wof:name":"Zhai'ao",
    "wof:placetype":"locality"
},
  "geometry": {"coordinates":[112.2302,34.62706],"type":"Point"}
}