{
  "type": "Feature",
  "properties": {
    "gn:admin1_code":"11.0",
    "gn:asciiname":"Raozhuping",
    "gn:country_code":"CN",
    "gn:dem":911,
    "gn:feature_class":"P",
    "gn:feature_code":"PPL",
    "gn:name":"Raozhuping",
    "gn:population":0,
    "gn:timezone":"Asia/Shanghai",
    "iso:country":"CN",
    "name:zho_x_preferred":[
        "\u6270\u7af9\u576a"
    ],
    "wof:name":"Raozhuping",
    "wof:placetype":"locality"
},
  "geometry": {"coordinates":[111.81837,25.25411],"type":"Point"}
}