{
  "type": "Feature",
  "properties": {
    "gn:admin1_code":"32.0",
    "gn:asciiname":"Putuo",
    "gn:country_code":"CN",
    "gn:dem":382,
    "gn:feature_class":"P",
    "gn:feature_code":"PPL",
    "gn:name":"Putuo",
    "gn:population":0,
    "gn:timezone":"Asia/Shanghai",
    "iso:country":"CN",
    "name:ceb_x_preferred":[
        "Putuo"
    ],
    "name:ces_x_preferred":[
        "Pchu-tchuo"
    ],
    "name:deu_x_preferred":[
        "Putuo"
    ],
    "name:fra_x_preferred":[
        "Putuo"
    ],
    "name:nor_x_preferred":[
        "Putuo"
    ],
    "name:pol_x_preferred":[
        "Putuo"
    ],
    "name:rus_x_preferred":[
        "\u041f\u0443\u0442\u043e"
    ],
    "name:swe_x_preferred":[
        "Putuo"
    ],
    "name:zho_x_preferred":[
        "\u666e\u9640"
    ],
    "wof:name":"Putuo",
    "wof:placetype":"locality"
},
  "geometry": {"coordinates":[104.93300000000001,30.8805],"type":"Point"}
}