{
  "type": "Feature",
  "properties": {
    "gn:admin1_code":"30.0",
    "gn:asciiname":"Youyuan",
    "gn:country_code":"CN",
    "gn:dem":185,
    "gn:feature_class":"P",
    "gn:feature_code":"PPL",
    "gn:name":"Youyuan",
    "gn:population":0,
    "gn:timezone":"Asia/Shanghai",
    "iso:country":"CN",
    "name:zho_x_preferred":[
        "\u7531\u5143"
    ],
    "wof:name":"Youyuan",
    "wof:placetype":"locality"
},
  "geometry": {"coordinates":[113.94682,23.69925],"type":"Point"}
}