{
  "type": "Feature",
  "properties": {
    "gn:admin1_code":"26.0",
    "gn:asciiname":"Dingyuancun",
    "gn:country_code":"CN",
    "gn:dem":829,
    "gn:feature_class":"P",
    "gn:feature_code":"PPL",
    "gn:name":"Dingyuancun",
    "gn:population":0,
    "gn:timezone":"Asia/Shanghai",
    "iso:country":"CN",
    "name:zho_x_preferred":[
        "\u4e01\u586c\u6751"
    ],
    "wof:name":"Dingyuancun",
    "wof:placetype":"locality"
},
  "geometry": {"coordinates":[110.38848,36.16265],"type":"Point"}
}