{
  "type": "Feature",
  "properties": {
    "gn:admin1_code":"16.0",
    "gn:asciiname":"Bangjia",
    "gn:country_code":"CN",
    "gn:dem":724,
    "gn:feature_class":"P",
    "gn:feature_code":"PPL",
    "gn:name":"Bangjia",
    "gn:population":0,
    "gn:timezone":"Asia/Shanghai",
    "iso:country":"CN",
    "name:zho_x_preferred":[
        "\u5e2e\u5bb6"
    ],
    "wof:name":"Bangjia",
    "wof:placetype":"locality"
},
  "geometry": {"coordinates":[110.035,23.8872],"type":"Point"}
}