{
  "type": "Feature",
  "properties": {
    "gn:admin1_code":"26.0",
    "gn:asciiname":"Shilipucun",
    "gn:country_code":"CN",
    "gn:dem":477,
    "gn:feature_class":"P",
    "gn:feature_code":"PPL",
    "gn:name":"Shilipucun",
    "gn:population":0,
    "gn:timezone":"Asia/Shanghai",
    "iso:country":"CN",
    "name:und_x_variant":[
        "\u5341\u91cc\u94fa\u6751"
    ],
    "wof:name":"Shilipucun",
    "wof:placetype":"locality"
},
  "geometry": {"coordinates":[109.26730000000001,34.19069],"type":"Point"}
}