{
  "type": "Feature",
  "properties": {
    "gn:admin1_code":"29.0",
    "gn:asciiname":"Xiawode",
    "gn:country_code":"CN",
    "gn:dem":905,
    "gn:feature_class":"P",
    "gn:feature_code":"PPL",
    "gn:name":"Xiawode",
    "gn:population":0,
    "gn:timezone":"Asia/Shanghai",
    "iso:country":"CN",
    "name:zho_x_preferred":[
        "\u4e0b\u7a9d\u5f97"
    ],
    "wof:name":"Xiawode",
    "wof:placetype":"locality"
},
  "geometry": {"coordinates":[104.51600000000001,24.5143],"type":"Point"}
}