{
  "type": "Feature",
  "properties": {
    "gn:admin1_code":"26.0",
    "gn:asciiname":"Dongshishi",
    "gn:country_code":"CN",
    "gn:dem":831,
    "gn:feature_class":"P",
    "gn:feature_code":"PPL",
    "gn:name":"Dongshishi",
    "gn:population":0,
    "gn:timezone":"Asia/Shanghai",
    "iso:country":"CN",
    "name:zho_x_preferred":[
        "\u4e1c\u77f3\u72ee"
    ],
    "wof:name":"Dongshishi",
    "wof:placetype":"locality"
},
  "geometry": {"coordinates":[109.56068999999999,35.19803],"type":"Point"}
}