{
  "type": "Feature",
  "properties": {
    "gn:admin1_code":"7.0",
    "gn:asciiname":"Xugongbian",
    "gn:country_code":"CN",
    "gn:dem":625,
    "gn:feature_class":"P",
    "gn:feature_code":"PPL",
    "gn:name":"Xugongbian",
    "gn:population":0,
    "gn:timezone":"Asia/Shanghai",
    "iso:country":"CN",
    "name:und_x_variant":[
        "\u8bb8\u516c\u8fb9"
    ],
    "name:zho_x_preferred":[
        "\u8bb8\u516c\u8fb9"
    ],
    "wof:name":"Xugongbian",
    "wof:placetype":"locality"
},
  "geometry": {"coordinates":[116.47454,26.3205],"type":"Point"}
}