{
  "type": "Feature",
  "properties": {
    "gn:admin1_code":"16",
    "gn:asciiname":"Kuitang",
    "gn:country_code":"CN",
    "gn:dem":188,
    "gn:feature_class":"P",
    "gn:feature_code":"PPL",
    "gn:name":"Kuitang",
    "gn:population":0,
    "gn:timezone":"Asia/Shanghai",
    "iso:country":"CN",
    "name:und_x_variant":[
        "K\u2019uei-t\u2019ang-hsiang",
        "K\u2019uei-t\u2019ang",
        "Kuitang"
    ],
    "name:zho_x_preferred":[
        "\u9997\u5858"
    ],
    "wof:name":"Kuitang",
    "wof:placetype":"locality"
},
  "geometry": {"coordinates":[106.968,22.1303],"type":"Point"}
}