{
  "type": "Feature",
  "properties": {
    "gn:admin1_code":"2",
    "gn:asciiname":"Fangcun",
    "gn:country_code":"CN",
    "gn:dem":192,
    "gn:feature_class":"P",
    "gn:feature_code":"PPL",
    "gn:name":"Fangcun",
    "gn:population":0,
    "gn:timezone":"Asia/Shanghai",
    "iso:country":"CN",
    "name:ceb_x_preferred":[
        "Fangcun"
    ],
    "name:swe_x_preferred":[
        "Fangcun"
    ],
    "wof:name":"Fangcun",
    "wof:placetype":"locality"
},
  "geometry": {"coordinates":[118.49679999999999,29.29113],"type":"Point"}
}