{
  "type": "Feature",
  "properties": {
    "gn:admin1_code":"5.0",
    "gn:asciiname":"Liudaocha",
    "gn:country_code":"CN",
    "gn:dem":708,
    "gn:feature_class":"P",
    "gn:feature_code":"PPL",
    "gn:name":"Liudaocha",
    "gn:population":0,
    "gn:timezone":"Asia/Shanghai",
    "iso:country":"CN",
    "name:und_x_variant":[
        "\u516d\u9053\u5c94"
    ],
    "wof:name":"Liudaocha",
    "wof:placetype":"locality"
},
  "geometry": {"coordinates":[126.35921999999999,41.68279],"type":"Point"}
}