{
  "type": "Feature",
  "properties": {
    "gn:admin1_code":"29.0",
    "gn:asciiname":"Sixingluo",
    "gn:country_code":"CN",
    "gn:dem":2834,
    "gn:feature_class":"P",
    "gn:feature_code":"PPL",
    "gn:name":"Sixingluo",
    "gn:population":0,
    "gn:timezone":"Asia/Shanghai",
    "iso:country":"CN",
    "name:zho_x_preferred":[
        "\u601d\u5f62\u843d"
    ],
    "wof:name":"Sixingluo",
    "wof:placetype":"locality"
},
  "geometry": {"coordinates":[100.113,26.7676],"type":"Point"}
}