{
  "type": "Feature",
  "properties": {
    "gn:admin1_code":"18.0",
    "gn:asciiname":"Zhaping",
    "gn:country_code":"CN",
    "gn:dem":1658,
    "gn:feature_class":"P",
    "gn:feature_code":"PPL",
    "gn:name":"Zhaping",
    "gn:population":0,
    "gn:timezone":"Asia/Shanghai",
    "iso:country":"CN",
    "wof:name":"Zhaping",
    "wof:placetype":"locality"
},
  "geometry": {"coordinates":[105.69777999999999,27.21361],"type":"Point"}
}