{
  "type": "Feature",
  "properties": {
    "gn:admin1_code":"10",
    "gn:asciiname":"Yulu",
    "gn:country_code":"CN",
    "gn:dem":378,
    "gn:feature_class":"P",
    "gn:feature_code":"PPL",
    "gn:name":"Yulu",
    "gn:population":0,
    "gn:timezone":"Asia/Shanghai",
    "iso:country":"CN",
    "name:ceb_x_preferred":[
        "Yulu"
    ],
    "name:deu_x_preferred":[
        "Yulu"
    ],
    "name:swe_x_preferred":[
        "Yulu"
    ],
    "name:zho_x_preferred":[
        "\u5fa1\u8def"
    ],
    "wof:name":"Yulu",
    "wof:placetype":"locality"
},
  "geometry": {"coordinates":[114.175,36.9082],"type":"Point"}
}