{
  "type": "Feature",
  "properties": {
    "gn:admin1_code":"16.0",
    "gn:asciiname":"Yangxu",
    "gn:cc2":"CN",
    "gn:country_code":"CN",
    "gn:dem":144,
    "gn:feature_class":"P",
    "gn:feature_code":"PPL",
    "gn:name":"Yangxu",
    "gn:population":0,
    "gn:timezone":"Asia/Shanghai",
    "iso:country":"CN",
    "name:und_x_variant":[
        "Yang-hs\u00fc",
        "Yangxu"
    ],
    "wof:name":"Yangxu",
    "wof:placetype":"locality"
},
  "geometry": {"coordinates":[106.36139,23.94694],"type":"Point"}
}