{
  "type": "Feature",
  "properties": {
    "gn:admin1_code":"13.0",
    "gn:asciiname":"Bole",
    "gn:country_code":"CN",
    "gn:dem":509,
    "gn:feature_class":"P",
    "gn:feature_code":"PPL",
    "gn:name":"Bole",
    "gn:population":0,
    "gn:timezone":"Asia/Shanghai",
    "iso:country":"CN",
    "name:ara_x_preferred":[
        "\u0628\u0648\u0644\u064a"
    ],
    "name:deu_x_preferred":[
        "Bortala"
    ],
    "name:eng_x_preferred":[
        "Bole"
    ],
    "name:fin_x_preferred":[
        "Bole"
    ],
    "name:fra_x_preferred":[
        "Bole"
    ],
    "name:ita_x_preferred":[
        "Bole"
    ],
    "name:jpn_x_preferred":[
        "\u30dc\u30eb\u30bf\u30e9\u5e02"
    ],
    "name:kik_x_preferred":[
        "Bole"
    ],
    "name:kor_x_preferred":[
        "\ubcf4\ub7ec\uc2dc"
    ],
    "name:lit_x_preferred":[
        "Boro Tala"
    ],
    "name:mon_x_preferred":[
        "\u0411\u043e\u0440\u0442\u0430\u043b \u0445\u043e\u0442"
    ],
    "name:nor_x_preferred":[
        "Bortala"
    ],
    "name:pol_x_preferred":[
        "Bole"
    ],
    "name:rus_x_preferred":[
        "\u0411\u043e\u0440\u043e-\u0422\u0430\u043b\u0430"
    ],
    "name:swe_x_preferred":[
        "B\u00f6rtala"
    ],
    "name:tur_x_preferred":[
        "Bortala"
    ],
    "name:uig_x_preferred":[
        "\u0628\u06c6\u0631\u062a\u0627\u0644\u0627"
    ],
    "name:uig_x_variant":[
        "\u0628\u0648\u0631\u062a\u0627\u0644\u0627 \u0634\u06d5\u06be\u0649\u0631\u0649"
    ],
    "name:urd_x_preferred":[
        "\u0628\u0648\u0644\u06d2"
    ],
    "name:vie_x_preferred":[
        "B\u00e1c L\u1ea1c"
    ],
    "name:war_x_preferred":[
        "Bole"
    ],
    "name:zho_x_preferred":[
        "\u535a\u4e50"
    ],
    "name:zho_x_variant":[
        "\u535a\u6a02",
        "B\u00f3l\u00e8",
        "\u535a\u4e50\u5e02"
    ],
    "wof:name":"Bole",
    "wof:placetype":"locality"
},
  "geometry": {"coordinates":[82.06993,44.89334],"type":"Point"}
}