{
  "type": "Feature",
  "properties": {
    "gn:admin1_code":"13.0",
    "gn:asciiname":"Bole",
    "gn:country_code":"CN",
    "gn:dem":509,
    "gn:feature_class":"P",
    "gn:feature_code":"PPL",
    "gn:name":"Bole",
    "gn:population":0,
    "gn:timezone":"Asia/Shanghai",
    "iso:country":"CN",
    "name:eng_x_preferred":[
        "Bole"
    ],
    "name:uig_x_preferred":[
        "\u0628\u06c6\u0631\u062a\u0627\u0644\u0627"
    ],
    "name:zho_x_preferred":[
        "\u535a\u4e50"
    ],
    "name:zho_x_variant":[
        "\u535a\u6a02",
        "B\u00f3l\u00e8"
    ],
    "wof:name":"Bole",
    "wof:placetype":"locality"
},
  "geometry": {"coordinates":[82.06993,44.89334],"type":"Point"}
}