{
  "type": "Feature",
  "properties": {
    "gn:admin1_code":"26.0",
    "gn:asciiname":"Chaijiagoucun",
    "gn:country_code":"CN",
    "gn:dem":1119,
    "gn:feature_class":"P",
    "gn:feature_code":"PPL",
    "gn:name":"Chaijiagoucun",
    "gn:population":0,
    "gn:timezone":"Asia/Shanghai",
    "iso:country":"CN",
    "name:und_x_variant":[
        "\u67f4\u5bb6\u6c9f\u6751"
    ],
    "wof:name":"Chaijiagoucun",
    "wof:placetype":"locality"
},
  "geometry": {"coordinates":[107.24616,33.46083],"type":"Point"}
}