{
  "type": "Feature",
  "properties": {
    "gn:admin1_code":"8.0",
    "gn:asciiname":"Baoshengcun",
    "gn:country_code":"CN",
    "gn:dem":272,
    "gn:feature_class":"P",
    "gn:feature_code":"PPL",
    "gn:name":"Baoshengcun",
    "gn:population":0,
    "gn:timezone":"Asia/Shanghai",
    "iso:country":"CN",
    "name:zho_x_preferred":[
        "\u4fdd\u80dc\u6751"
    ],
    "wof:name":"Baoshengcun",
    "wof:placetype":"locality"
},
  "geometry": {"coordinates":[126.3407,47.82332],"type":"Point"}
}