{
  "type": "Feature",
  "properties": {
    "gn:country":"CN",
    "gn:fcode":"PPL",
    "gn:population":0,
    "iso:country":"CN",
    "name:und_x_variant":[
        "Nanyang"
    ],
    "qs:name":"Namyang",
    "qs:name_adm0":"North Korea",
    "qs:name_adm1":"Hamgyong-bukto",
    "qs:photos":54,
    "qs:photos_1k":11,
    "qs:photos_9k":1,
    "qs:photos_9r":2,
    "qs:photos_all":54,
    "qs:photos_sr":2,
    "qs:placetype":"Town",
    "qs:pop_sr":"0",
    "wd:wordcount":25,
    "wof:name":"Namyang",
    "wof:placetype":"locality",
    "wof:population":0
},
  "geometry": {"coordinates":[129.58027999999999,42.71339],"type":"Point"}
}