{
  "type": "Feature",
  "properties": {
    "gn:admin1_code":"30.0",
    "gn:asciiname":"Baiweizhu",
    "gn:country_code":"CN",
    "gn:dem":70,
    "gn:feature_class":"P",
    "gn:feature_code":"PPL",
    "gn:name":"Baiweizhu",
    "gn:population":0,
    "gn:timezone":"Asia/Shanghai",
    "iso:country":"CN",
    "name:zho_x_preferred":[
        "\u767d\u5c3e\u7af9"
    ],
    "wof:name":"Baiweizhu",
    "wof:placetype":"locality"
},
  "geometry": {"coordinates":[113.13278,24.12444],"type":"Point"}
}