{
  "type": "Feature",
  "properties": {
    "gn:admin1_code":"4.0",
    "gn:asciiname":"Fengxi",
    "gn:country_code":"CN",
    "gn:dem":3,
    "gn:feature_class":"P",
    "gn:feature_code":"PPL",
    "gn:name":"Fengxi",
    "gn:population":0,
    "gn:timezone":"Asia/Shanghai",
    "iso:country":"CN",
    "name:deu_x_preferred":[
        "Fengxi"
    ],
    "name:zho_x_preferred":[
        "\u4e30\u897f"
    ],
    "wof:name":"Fengxi",
    "wof:placetype":"locality"
},
  "geometry": {"coordinates":[120.38443999999998,32.73346],"type":"Point"}
}