{
  "type": "Feature",
  "properties": {
    "gn:admin1_code":"3.0",
    "gn:asciiname":"Jingkou",
    "gn:country_code":"CN",
    "gn:dem":209,
    "gn:feature_class":"P",
    "gn:feature_code":"PPL",
    "gn:name":"Jingkou",
    "gn:population":0,
    "gn:timezone":"Asia/Shanghai",
    "iso:country":"CN",
    "name:und_x_variant":[
        "\u8ff3\u53e3"
    ],
    "wof:name":"Jingkou",
    "wof:placetype":"locality"
},
  "geometry": {"coordinates":[115.64270999999999,25.62383],"type":"Point"}
}