{
  "type": "Feature",
  "properties": {
    "gn:admin1_code":"12.0",
    "gn:asciiname":"Yufang",
    "gn:country_code":"CN",
    "gn:dem":211,
    "gn:feature_class":"P",
    "gn:feature_code":"PPL",
    "gn:name":"Yufang",
    "gn:population":0,
    "gn:timezone":"Asia/Shanghai",
    "iso:country":"CN",
    "name:zho_x_preferred":[
        "Yufang"
    ],
    "name:zho_x_variant":[
        "\u4f59\u574a"
    ],
    "wof:name":"Yufang",
    "wof:placetype":"locality"
},
  "geometry": {"coordinates":[114.0299,29.2593],"type":"Point"}
}