{
  "type": "Feature",
  "properties": {
    "gn:admin1_code":"1.0",
    "gn:asciiname":"Baishegang",
    "gn:country_code":"CN",
    "gn:dem":19,
    "gn:feature_class":"P",
    "gn:feature_code":"PPL",
    "gn:name":"Baishegang",
    "gn:population":0,
    "gn:timezone":"Asia/Shanghai",
    "iso:country":"CN",
    "name:zho_x_preferred":[
        "\u767d\u86c7\u5c97"
    ],
    "wof:name":"Baishegang",
    "wof:placetype":"locality"
},
  "geometry": {"coordinates":[118.54306,31.55547],"type":"Point"}
}