{
  "type": "Feature",
  "properties": {
    "gn:admin1_code":"4.0",
    "gn:asciiname":"Minqiangcun",
    "gn:country_code":"CN",
    "gn:dem":5,
    "gn:feature_class":"P",
    "gn:feature_code":"PPL",
    "gn:name":"Minqiangcun",
    "gn:population":0,
    "gn:timezone":"Asia/Shanghai",
    "iso:country":"CN",
    "name:zho_x_preferred":[
        "\u6c11\u5f3a\u6751"
    ],
    "wof:name":"Minqiangcun",
    "wof:placetype":"locality"
},
  "geometry": {"coordinates":[119.86047000000001,34.19427],"type":"Point"}
}