{
  "type": "Feature",
  "properties": {
    "gn:admin1_code":"2.0",
    "gn:asciiname":"Zhukeng",
    "gn:country_code":"CN",
    "gn:dem":230,
    "gn:feature_class":"P",
    "gn:feature_code":"PPL",
    "gn:name":"Zhukeng",
    "gn:population":0,
    "gn:timezone":"Asia/Shanghai",
    "iso:country":"CN",
    "name:zho_x_preferred":[
        "\u82ce\u5751"
    ],
    "wof:name":"Zhukeng",
    "wof:placetype":"locality"
},
  "geometry": {"coordinates":[119.26497000000001,28.90992],"type":"Point"}
}