{
  "type": "Feature",
  "properties": {
    "gn:admin1_code":"30.0",
    "gn:asciiname":"Siyun",
    "gn:country_code":"CN",
    "gn:dem":90,
    "gn:feature_class":"P",
    "gn:feature_code":"PPL",
    "gn:name":"Siyun",
    "gn:population":0,
    "gn:timezone":"Asia/Shanghai",
    "iso:country":"CN",
    "name:zho_x_preferred":[
        "\u6cd7\u4e91"
    ],
    "wof:name":"Siyun",
    "wof:placetype":"locality"
},
  "geometry": {"coordinates":[112.67694,22.70948],"type":"Point"}
}