{
  "type": "Feature",
  "properties": {
    "gn:country":"CN",
    "gn:fcode":"PPL",
    "gn:population":224871,
    "iso:country":"CN",
    "name:und_x_variant":[
        "T\u2019ien-men"
    ],
    "qs:name":"Jingling",
    "qs:photos_9r":0,
    "qs:photos_sr":0,
    "qs:pop_sr":"10",
    "wof:name":"Jingling",
    "wof:placetype":"locality",
    "wof:population":224871
},
  "geometry": {"coordinates":[113.09999999999999,30.65],"type":"Point"}
}