{
  "type": "Feature",
  "properties": {
    "gn:admin1_code":"26",
    "gn:asciiname":"Gaodian",
    "gn:country_code":"CN",
    "gn:dem":425,
    "gn:feature_class":"P",
    "gn:feature_code":"PPL",
    "gn:name":"Gaodian",
    "gn:population":0,
    "gn:timezone":"Asia/Shanghai",
    "iso:country":"CN",
    "name:und_x_variant":[
        "\u9ad8\u5e97"
    ],
    "name:zho_x_preferred":[
        "\u9ad8\u5e97"
    ],
    "wof:name":"Gaodian",
    "wof:placetype":"locality"
},
  "geometry": {"coordinates":[108.52361000000001,34.305],"type":"Point"}
}