{
  "type": "Feature",
  "properties": {
    "gn:admin1_code":"11.0",
    "gn:asciiname":"Shushanwu",
    "gn:country_code":"CN",
    "gn:dem":78,
    "gn:feature_class":"P",
    "gn:feature_code":"PPL",
    "gn:name":"Shushanwu",
    "gn:population":0,
    "gn:timezone":"Asia/Shanghai",
    "iso:country":"CN",
    "name:zho_x_preferred":[
        "\u6811\u5c71\u5c4b"
    ],
    "wof:name":"Shushanwu",
    "wof:placetype":"locality"
},
  "geometry": {"coordinates":[113.40241,28.22691],"type":"Point"}
}