{
  "type": "Feature",
  "properties": {
    "gn:admin1_code":"1.0",
    "gn:asciiname":"Laoyingcun",
    "gn:country_code":"CN",
    "gn:dem":32,
    "gn:feature_class":"P",
    "gn:feature_code":"PPL",
    "gn:name":"Laoyingcun",
    "gn:population":0,
    "gn:timezone":"Asia/Shanghai",
    "iso:country":"CN",
    "name:zho_x_preferred":[
        "\u8001\u8425\u6751"
    ],
    "wof:name":"Laoyingcun",
    "wof:placetype":"locality"
},
  "geometry": {"coordinates":[115.94307000000001,33.02888],"type":"Point"}
}