{
  "type": "Feature",
  "properties": {
    "gn:admin1_code":"19.0",
    "gn:asciiname":"Yaohaoligaole",
    "gn:country_code":"CN",
    "gn:dem":272,
    "gn:feature_class":"P",
    "gn:feature_code":"PPL",
    "gn:name":"Yaohaoligaole",
    "gn:population":0,
    "gn:timezone":"Asia/Shanghai",
    "iso:country":"CN",
    "name:zho_x_preferred":[
        "\u8170\u597d\u529b\u9ad8\u52d2"
    ],
    "wof:name":"Yaohaoligaole",
    "wof:placetype":"locality"
},
  "geometry": {"coordinates":[121.59099999999999,42.4958],"type":"Point"}
}