{
  "type": "Feature",
  "properties": {
    "gn:country":"CN",
    "gn:fcode":"PPL",
    "gn:pop":8240,
    "iso:country":"CN",
    "name:cdo_x_preferred":[
        "Li\u00e8ng-g\u014fng"
    ],
    "name:ceb_x_preferred":[
        "Lianjiang Xian"
    ],
    "name:deu_x_preferred":[
        "Lianjiang"
    ],
    "name:eng_x_preferred":[
        "Lianjiang County"
    ],
    "name:eus_x_preferred":[
        "Lianjiang konderria"
    ],
    "name:fas_x_preferred":[
        "\u0644\u06cc\u0627\u0646\u062c\u06cc\u0627\u0646\u06af"
    ],
    "name:gan_x_preferred":[
        "\u8fde\u6c5f\u53bf"
    ],
    "name:jpn_x_preferred":[
        "\u9023\u6c5f\u770c"
    ],
    "name:kor_x_preferred":[
        "\ub844\uc7a5\ud604"
    ],
    "name:lzh_x_preferred":[
        "\u9023\u6c5f\u7e23"
    ],
    "name:mwl_x_preferred":[
        "Lianjiang"
    ],
    "name:nan_x_preferred":[
        "Li\u00e2n-kang-ko\u0101n"
    ],
    "name:nld_x_preferred":[
        "Lianjiang"
    ],
    "name:nob_x_preferred":[
        "Lianjiang"
    ],
    "name:spa_x_preferred":[
        "Lianjiang"
    ],
    "name:swe_x_preferred":[
        "Lianjiang"
    ],
    "name:unk_x_variant":[
        "Tung-tai"
    ],
    "name:vie_x_preferred":[
        "Li\u00ean Giang"
    ],
    "name:wuu_x_preferred":[
        "\u8fde\u6c5f\u53bf"
    ],
    "name:yue_x_preferred":[
        "\u9023\u6c5f\u7e23"
    ],
    "name:zho_x_preferred":[
        "\u4e1c\u5cb1"
    ],
    "name:zho_x_variant":[
        "\u4e1c\u5cb1\u9547",
        "\u8fde\u6c5f\u53bf"
    ],
    "qs:name":"Dongdai",
    "qs:photos_9r":0,
    "qs:photos_sr":0,
    "qs:pop_sr":"5",
    "wd:wordcount":1098,
    "wof:name":"Dongdai",
    "wof:placetype":"locality",
    "wof:population":8240
},
  "geometry": {"coordinates":[119.61694,26.24194],"type":"Point"}
}