{
  "type": "Feature",
  "properties": {
    "gn:country":"CN",
    "gn:fcode":"PPL",
    "gn:pop":8240,
    "iso:country":"CN",
    "name:unk_x_variant":[
        "Tung-tai"
    ],
    "name:zho_x_preferred":[
        "\u4e1c\u5cb1"
    ],
    "name:zho_x_variant":[
        "\u4e1c\u5cb1\u9547"
    ],
    "qs:name":"Dongdai",
    "qs:photos_9r":0,
    "qs:photos_sr":0,
    "qs:pop_sr":"5",
    "wd:wordcount":1098,
    "wof:name":"Dongdai",
    "wof:placetype":"locality",
    "wof:population":8240
},
  "geometry": {"coordinates":[119.61694,26.24194],"type":"Point"}
}