{
  "type": "Feature",
  "properties": {
    "gn:admin1_code":"3.0",
    "gn:asciiname":"Fengtian",
    "gn:country_code":"CN",
    "gn:dem":99,
    "gn:feature_class":"P",
    "gn:feature_code":"PPL",
    "gn:name":"Fengtian",
    "gn:population":0,
    "gn:timezone":"Asia/Shanghai",
    "iso:country":"CN",
    "name:ceb_x_preferred":[
        "Fengtian"
    ],
    "name:deu_x_preferred":[
        "Fengtian"
    ],
    "name:pol_x_preferred":[
        "Fengtian"
    ],
    "name:rus_x_preferred":[
        "\u0424\u044d\u043d\u0442\u044f\u043d\u044c"
    ],
    "name:vie_x_preferred":[
        "Ph\u1ee5ng Thi\u00ean"
    ],
    "name:zho_x_preferred":[
        "\u4e30\u7530"
    ],
    "wof:name":"Fengtian",
    "wof:placetype":"locality"
},
  "geometry": {"coordinates":[117.735,29.2126],"type":"Point"}
}