{
  "type": "Feature",
  "properties": {
    "gn:admin1_code":"3.0",
    "gn:asciiname":"Nanshanlu",
    "gn:country_code":"CN",
    "gn:dem":331,
    "gn:feature_class":"P",
    "gn:feature_code":"PPL",
    "gn:name":"Nanshanlu",
    "gn:population":0,
    "gn:timezone":"Asia/Shanghai",
    "iso:country":"CN",
    "name:und_x_variant":[
        "\u5357\u5c71\u8def"
    ],
    "wof:name":"Nanshanlu",
    "wof:placetype":"locality"
},
  "geometry": {"coordinates":[117.8079,29.53515],"type":"Point"}
}