{
  "type": "Feature",
  "properties": {
    "gn:admin1_code":"32.0",
    "gn:asciiname":"Anze",
    "gn:country_code":"CN",
    "gn:dem":2482,
    "gn:feature_class":"P",
    "gn:feature_code":"PPL",
    "gn:name":"Anze",
    "gn:population":0,
    "gn:timezone":"Asia/Shanghai",
    "iso:country":"CN",
    "name:zho_x_preferred":[
        "\u978d\u5219"
    ],
    "wof:name":"Anze",
    "wof:placetype":"locality"
},
  "geometry": {"coordinates":[102.761,27.8315],"type":"Point"}
}