{
  "type": "Feature",
  "properties": {
    "gn:admin1_code":"32",
    "gn:asciiname":"Jiangjiazui",
    "gn:country_code":"CN",
    "gn:dem":336,
    "gn:feature_class":"P",
    "gn:feature_code":"PPL",
    "gn:name":"Jiangjiazui",
    "gn:population":0,
    "gn:timezone":"Asia/Shanghai",
    "iso:country":"CN",
    "name:zho_x_preferred":[
        "\u6c5f\u5bb6\u5634"
    ],
    "wof:name":"Jiangjiazui",
    "wof:placetype":"locality"
},
  "geometry": {"coordinates":[106.50766000000002,30.36554000000001],"type":"Point"}
}