{
  "type": "Feature",
  "properties": {
    "gn:admin1_code":"8.0",
    "gn:asciiname":"Erduan",
    "gn:country_code":"CN",
    "gn:dem":557,
    "gn:feature_class":"P",
    "gn:feature_code":"PPL",
    "gn:name":"Erduan",
    "gn:population":0,
    "gn:timezone":"Asia/Shanghai",
    "iso:country":"CN",
    "name:zho_x_preferred":[
        "\u4e8c\u6bb5"
    ],
    "wof:name":"Erduan",
    "wof:placetype":"locality"
},
  "geometry": {"coordinates":[129.98088999999999,44.08286],"type":"Point"}
}