{
  "type": "Feature",
  "properties": {
    "gn:admin1_code":"26.0",
    "gn:asciiname":"Nangezhenliang",
    "gn:country_code":"CN",
    "gn:dem":1238,
    "gn:feature_class":"P",
    "gn:feature_code":"PPL",
    "gn:name":"Nangezhenliang",
    "gn:population":0,
    "gn:timezone":"Asia/Shanghai",
    "iso:country":"CN",
    "name:zho_x_preferred":[
        "\u5357\u572a\u9488\u6881"
    ],
    "wof:name":"Nangezhenliang",
    "wof:placetype":"locality"
},
  "geometry": {"coordinates":[108.80345,37.91493],"type":"Point"}
}