{
  "type": "Feature",
  "properties": {
    "gn:admin1_code":"3.0",
    "gn:asciiname":"Kuimeishan",
    "gn:country_code":"CN",
    "gn:dem":737,
    "gn:feature_class":"P",
    "gn:feature_code":"PPL",
    "gn:name":"Kuimeishan",
    "gn:population":0,
    "gn:timezone":"Asia/Shanghai",
    "iso:country":"CN",
    "name:zho_x_preferred":[
        "\u5cbf\u7f8e\u5c71"
    ],
    "wof:name":"Kuimeishan",
    "wof:placetype":"locality"
},
  "geometry": {"coordinates":[114.89100000000001,24.7102],"type":"Point"}
}