{
  "type": "Feature",
  "properties": {
    "gn:admin1_code":"4.0",
    "gn:asciiname":"Guiwucun",
    "gn:country_code":"CN",
    "gn:dem":68,
    "gn:feature_class":"P",
    "gn:feature_code":"PPL",
    "gn:name":"Guiwucun",
    "gn:population":0,
    "gn:timezone":"Asia/Shanghai",
    "iso:country":"CN",
    "name:zho_x_preferred":[
        "\u6842\u4e94\u6751"
    ],
    "wof:name":"Guiwucun",
    "wof:placetype":"locality"
},
  "geometry": {"coordinates":[118.45093,32.87488],"type":"Point"}
}