{
  "type": "Feature",
  "properties": {
    "gn:admin1_code":"19.0",
    "gn:asciiname":"Qiandazitun",
    "gn:country_code":"CN",
    "gn:dem":117,
    "gn:feature_class":"P",
    "gn:feature_code":"PPL",
    "gn:name":"Qiandazitun",
    "gn:population":0,
    "gn:timezone":"Asia/Shanghai",
    "iso:country":"CN",
    "name:zho_x_preferred":[
        "\u94b1\u642d\u5b50\u5c6f"
    ],
    "wof:name":"Qiandazitun",
    "wof:placetype":"locality"
},
  "geometry": {"coordinates":[120.75212000000001,40.98182],"type":"Point"}
}