{
  "type": "Feature",
  "properties": {
    "gn:admin1_code":"4.0",
    "gn:asciiname":"Xinxiancun Yizu",
    "gn:country_code":"CN",
    "gn:dem":5,
    "gn:feature_class":"P",
    "gn:feature_code":"PPLF",
    "gn:name":"Xinxiancun Yizu",
    "gn:population":0,
    "gn:timezone":"Asia/Shanghai",
    "iso:country":"CN",
    "name:zho_x_preferred":[
        "\u65b0\u5148\u6751\u4e00\u7ec4"
    ],
    "wof:name":"Xinxiancun Yizu",
    "wof:placetype":"locality"
},
  "geometry": {"coordinates":[120.77630000000001,32.93531],"type":"Point"}
}