{
  "type": "Feature",
  "properties": {
    "gn:admin1_code":"24.0",
    "gn:asciiname":"Dachegou",
    "gn:country_code":"CN",
    "gn:dem":1072,
    "gn:feature_class":"P",
    "gn:feature_code":"PPL",
    "gn:name":"Dachegou",
    "gn:population":0,
    "gn:timezone":"Asia/Shanghai",
    "iso:country":"CN",
    "name:zho_x_preferred":[
        "\u5927\u8f66\u6c9f"
    ],
    "wof:name":"Dachegou",
    "wof:placetype":"locality"
},
  "geometry": {"coordinates":[113.70516000000001,38.13711],"type":"Point"}
}