{
  "type": "Feature",
  "properties": {
    "gn:admin1_code":"14.0",
    "gn:asciiname":"Jianzong",
    "gn:country_code":"CN",
    "gn:dem":4327,
    "gn:feature_class":"P",
    "gn:feature_code":"PPL",
    "gn:name":"Jianzong",
    "gn:population":0,
    "gn:timezone":"Asia/Urumqi",
    "iso:country":"CN",
    "name:zho_x_preferred":[
        "\u7b80\u603b"
    ],
    "wof:name":"Jianzong",
    "wof:placetype":"locality"
},
  "geometry": {"coordinates":[86.91540000000001,29.1661],"type":"Point"}
}