{
  "type": "Feature",
  "properties": {
    "gn:admin1_code":"3.0",
    "gn:asciiname":"Xiewuchang",
    "gn:country_code":"CN",
    "gn:dem":545,
    "gn:feature_class":"P",
    "gn:feature_code":"PPL",
    "gn:name":"Xiewuchang",
    "gn:population":0,
    "gn:timezone":"Asia/Shanghai",
    "iso:country":"CN",
    "name:und_x_variant":[
        "\u8c22\u5c4b\u573a"
    ],
    "wof:name":"Xiewuchang",
    "wof:placetype":"locality"
},
  "geometry": {"coordinates":[115.29129,25.60547],"type":"Point"}
}