{
  "type": "Feature",
  "properties": {
    "gn:admin1_code":"08",
    "gn:asciiname":"Touqia",
    "gn:cc2":"CN",
    "gn:country_code":"CN",
    "gn:dem":224,
    "gn:feature_class":"P",
    "gn:feature_code":"PPL",
    "gn:name":"Touqia",
    "gn:population":0,
    "gn:timezone":"Asia/Shanghai",
    "iso:country":"CN",
    "name:und_x_variant":[
        "T\u2019ou-k\u2019a",
        "T\u2019ou-ch\u2019ia",
        "Touqia"
    ],
    "wof:name":"Touqia",
    "wof:placetype":"locality"
},
  "geometry": {"coordinates":[126.16667,52.03333],"type":"Point"}
}