{
  "type": "Feature",
  "properties": {
    "gn:admin1_code":"29.0",
    "gn:asciiname":"Longweishan",
    "gn:country_code":"CN",
    "gn:dem":2716,
    "gn:feature_class":"P",
    "gn:feature_code":"PPL",
    "gn:name":"Longweishan",
    "gn:population":0,
    "gn:timezone":"Asia/Shanghai",
    "iso:country":"CN",
    "name:zho_x_preferred":[
        "\u9f99\u5c3e\u5c71"
    ],
    "wof:name":"Longweishan",
    "wof:placetype":"locality"
},
  "geometry": {"coordinates":[99.8901,26.3461],"type":"Point"}
}