{
  "type": "Feature",
  "properties": {
    "gn:admin1_code":"3.0",
    "gn:asciiname":"Guikeng",
    "gn:country_code":"CN",
    "gn:dem":331,
    "gn:feature_class":"P",
    "gn:feature_code":"PPL",
    "gn:name":"Guikeng",
    "gn:population":0,
    "gn:timezone":"Asia/Shanghai",
    "iso:country":"CN",
    "name:zho_x_preferred":[
        "\u6842\u5751"
    ],
    "wof:name":"Guikeng",
    "wof:placetype":"locality"
},
  "geometry": {"coordinates":[115.84699999999999,25.5108],"type":"Point"}
}