{
  "type": "Feature",
  "properties": {
    "gn:admin1_code":"12.0",
    "gn:asciiname":"Dengjiagang",
    "gn:country_code":"CN",
    "gn:dem":141,
    "gn:feature_class":"P",
    "gn:feature_code":"PPL",
    "gn:name":"Dengjiagang",
    "gn:population":0,
    "gn:timezone":"Asia/Shanghai",
    "iso:country":"CN",
    "name:zho_x_preferred":[
        "\u9093\u5bb6\u5c97"
    ],
    "wof:name":"Dengjiagang",
    "wof:placetype":"locality"
},
  "geometry": {"coordinates":[111.80826999999999,32.48753],"type":"Point"}
}