{
  "type": "Feature",
  "properties": {
    "gn:admin1_code":"12.0",
    "gn:asciiname":"Liaojiawan",
    "gn:country_code":"CN",
    "gn:dem":69,
    "gn:feature_class":"P",
    "gn:feature_code":"PPL",
    "gn:name":"Liaojiawan",
    "gn:population":0,
    "gn:timezone":"Asia/Shanghai",
    "iso:country":"CN",
    "name:zho_x_preferred":[
        "\u5ed6\u5bb6\u6e7e"
    ],
    "wof:name":"Liaojiawan",
    "wof:placetype":"locality"
},
  "geometry": {"coordinates":[112.11396000000001,30.79991],"type":"Point"}
}