{
  "type": "Feature",
  "properties": {
    "gn:admin1_code":"25",
    "gn:asciiname":"Sunrukou",
    "gn:country_code":"CN",
    "gn:dem":36,
    "gn:feature_class":"P",
    "gn:feature_code":"PPL",
    "gn:name":"Sunrukou",
    "gn:population":0,
    "gn:timezone":"Asia/Shanghai",
    "iso:country":"CN",
    "name:zho_x_preferred":[
        "\u5b59\u5165\u53e3"
    ],
    "wof:name":"Sunrukou",
    "wof:placetype":"locality"
},
  "geometry": {"coordinates":[115.771,36.6263],"type":"Point"}
}