{
  "type": "Feature",
  "properties": {
    "gn:admin1_code":"31.0",
    "gn:asciiname":"Jiucunshan",
    "gn:country_code":"CN",
    "gn:dem":236,
    "gn:feature_class":"P",
    "gn:feature_code":"PPL",
    "gn:name":"Jiucunshan",
    "gn:population":0,
    "gn:timezone":"Asia/Shanghai",
    "iso:country":"CN",
    "name:zho_x_preferred":[
        "\u4e45\u6751\u5c71"
    ],
    "wof:name":"Jiucunshan",
    "wof:placetype":"locality"
},
  "geometry": {"coordinates":[110.02173999999999,18.64535],"type":"Point"}
}