{
  "type": "Feature",
  "properties": {
    "gn:admin1_code":"11.0",
    "gn:asciiname":"Hujiata",
    "gn:country_code":"CN",
    "gn:dem":40,
    "gn:feature_class":"P",
    "gn:feature_code":"PPL",
    "gn:name":"Hujiata",
    "gn:population":0,
    "gn:timezone":"Asia/Shanghai",
    "iso:country":"CN",
    "name:zho_x_preferred":[
        "Hujiata"
    ],
    "name:zho_x_variant":[
        "\u80e1\u5bb6\u5854"
    ],
    "wof:name":"Hujiata",
    "wof:placetype":"locality"
},
  "geometry": {"coordinates":[111.74318,29.77253],"type":"Point"}
}