{
  "type": "Feature",
  "properties": {
    "gn:admin1_code":"26.0",
    "gn:asciiname":"Xiahuoyaoxian",
    "gn:country_code":"CN",
    "gn:dem":1552,
    "gn:feature_class":"P",
    "gn:feature_code":"PPL",
    "gn:name":"Xiahuoyaoxian",
    "gn:population":0,
    "gn:timezone":"Asia/Shanghai",
    "iso:country":"CN",
    "name:zho_x_preferred":[
        "\u4e0b\u4f19\u5d3e\u5c98"
    ],
    "wof:name":"Xiahuoyaoxian",
    "wof:placetype":"locality"
},
  "geometry": {"coordinates":[107.44951,37.09589],"type":"Point"}
}