{
  "type": "Feature",
  "properties": {
    "gn:admin1_code":"7.0",
    "gn:asciiname":"Luanzhou",
    "gn:country_code":"CN",
    "gn:dem":760,
    "gn:feature_class":"P",
    "gn:feature_code":"PPL",
    "gn:name":"Luanzhou",
    "gn:population":0,
    "gn:timezone":"Asia/Shanghai",
    "iso:country":"CN",
    "name:deu_x_preferred":[
        "Luanzhou"
    ],
    "name:fas_x_preferred":[
        "\u0634\u0647\u0631\u0633\u062a\u0627\u0646 \u0644\u0648\u0627\u0646\u0698\u0648\u0648"
    ],
    "name:ita_x_preferred":[
        "Luanzhou"
    ],
    "name:jpn_x_preferred":[
        "\u30e9\u30f3\u5dde\u5e02"
    ],
    "name:kor_x_preferred":[
        "\ub87c\uc800\uc6b0\uc2dc"
    ],
    "name:nor_x_preferred":[
        "Luan"
    ],
    "name:rus_x_preferred":[
        "\u041b\u0443\u0430\u043d\u044c\u0447\u0436\u043e\u0443"
    ],
    "name:swe_x_preferred":[
        "Luan"
    ],
    "name:urd_x_preferred":[
        "\u0644\u0648\u0627\u0646\u0698\u0624"
    ],
    "name:vie_x_preferred":[
        "Loan Ch\u00e2u"
    ],
    "name:zho_x_preferred":[
        "\u92ae\u6d32"
    ],
    "name:zho_x_variant":[
        "\u6ee6\u5dde\u5e02"
    ],
    "wof:name":"Luanzhou",
    "wof:placetype":"locality"
},
  "geometry": {"coordinates":[117.55325999999999,26.72972],"type":"Point"}
}