{
  "type": "Feature",
  "properties": {
    "gn:admin1_code":"32.0",
    "gn:asciiname":"Dongziyan",
    "gn:country_code":"CN",
    "gn:dem":466,
    "gn:feature_class":"P",
    "gn:feature_code":"PPL",
    "gn:name":"Dongziyan",
    "gn:population":0,
    "gn:timezone":"Asia/Shanghai",
    "iso:country":"CN",
    "name:zho_x_preferred":[
        "\u6d1e\u5b50\u5830"
    ],
    "wof:name":"Dongziyan",
    "wof:placetype":"locality"
},
  "geometry": {"coordinates":[103.947,30.191],"type":"Point"}
}