{
  "type": "Feature",
  "properties": {
    "gn:admin1_code":"9",
    "gn:asciiname":"Xuwan",
    "gn:country_code":"CN",
    "gn:dem":119,
    "gn:feature_class":"P",
    "gn:feature_code":"PPL",
    "gn:name":"Xuwan",
    "gn:population":0,
    "gn:timezone":"Asia/Shanghai",
    "iso:country":"CN",
    "name:und_x_variant":[
        "\u5f90\u6e7e"
    ],
    "wof:name":"Xuwan",
    "wof:placetype":"locality"
},
  "geometry": {"coordinates":[113.27706000000001,33.27970999999999],"type":"Point"}
}