{
  "type": "Feature",
  "properties": {
    "gn:admin1_code":"14.0",
    "gn:asciiname":"Siu",
    "gn:country_code":"CN",
    "gn:dem":4267,
    "gn:feature_class":"P",
    "gn:feature_code":"PPLF",
    "gn:name":"Siu",
    "gn:population":0,
    "gn:timezone":"Asia/Urumqi",
    "iso:country":"CN",
    "name:bod_x_preferred":[
        "Siu"
    ],
    "name:zho_x_preferred":[
        "Sewu"
    ],
    "name:zho_x_variant":[
        "\u8272\u543e",
        "Lierong",
        "\u5217\u8363"
    ],
    "wof:name":"Siu",
    "wof:placetype":"locality"
},
  "geometry": {"coordinates":[92.1815,28.94398],"type":"Point"}
}