{
  "type": "Feature",
  "properties": {
    "gn:admin1_code":"9.0",
    "gn:asciiname":"Daloumen",
    "gn:country_code":"CN",
    "gn:dem":696,
    "gn:feature_class":"P",
    "gn:feature_code":"PPL",
    "gn:name":"Daloumen",
    "gn:population":0,
    "gn:timezone":"Asia/Shanghai",
    "iso:country":"CN",
    "name:zho_x_preferred":[
        "\u5927\u697c\u95e8"
    ],
    "wof:name":"Daloumen",
    "wof:placetype":"locality"
},
  "geometry": {"coordinates":[112.04653,33.39477],"type":"Point"}
}