{
  "type": "Feature",
  "properties": {
    "gn:admin1_code":"18.0",
    "gn:asciiname":"Tiandong",
    "gn:country_code":"CN",
    "gn:dem":627,
    "gn:feature_class":"P",
    "gn:feature_code":"PPL",
    "gn:name":"Tiandong",
    "gn:population":0,
    "gn:timezone":"Asia/Shanghai",
    "iso:country":"CN",
    "name:zho_x_preferred":[
        "\u7530\u61c2"
    ],
    "wof:name":"Tiandong",
    "wof:placetype":"locality"
},
  "geometry": {"coordinates":[108.20099999999999,25.9162],"type":"Point"}
}