{
  "type": "Feature",
  "properties": {
    "gn:admin1_code":"30",
    "gn:asciiname":"Qipan",
    "gn:country_code":"CN",
    "gn:dem":31,
    "gn:feature_class":"P",
    "gn:feature_code":"PPL",
    "gn:name":"Qipan",
    "gn:population":0,
    "gn:timezone":"Asia/Shanghai",
    "iso:country":"CN",
    "name:zho_x_preferred":[
        "\u68cb\u76d8"
    ],
    "wof:name":"Qipan",
    "wof:placetype":"locality"
},
  "geometry": {"coordinates":[116.42859,23.63663],"type":"Point"}
}