{
  "type": "Feature",
  "properties": {
    "gn:admin1_code":"20.0",
    "gn:asciiname":"Xiayaozi",
    "gn:country_code":"CN",
    "gn:dem":1183,
    "gn:feature_class":"P",
    "gn:feature_code":"PPL",
    "gn:name":"Xiayaozi",
    "gn:population":0,
    "gn:timezone":"Asia/Shanghai",
    "iso:country":"CN",
    "name:und_x_variant":[
        "\u4e0b\u7a91\u5b50"
    ],
    "wof:name":"Xiayaozi",
    "wof:placetype":"locality"
},
  "geometry": {"coordinates":[111.7821,40.0622],"type":"Point"}
}