{
  "type": "Feature",
  "properties": {
    "gn:admin1_code":"21.0",
    "gn:asciiname":"Majiaping",
    "gn:country_code":"CN",
    "gn:dem":1683,
    "gn:feature_class":"P",
    "gn:feature_code":"PPL",
    "gn:name":"Majiaping",
    "gn:population":0,
    "gn:timezone":"Asia/Shanghai",
    "iso:country":"CN",
    "name:und_x_variant":[
        "\u9a6c\u5bb6\u576a"
    ],
    "name:zho_x_preferred":[
        "\u9a6c\u5bb6\u576a"
    ],
    "wof:name":"Majiaping",
    "wof:placetype":"locality"
},
  "geometry": {"coordinates":[106.41875,36.06728],"type":"Point"}
}