{
  "type": "Feature",
  "properties": {
    "gn:admin1_code":"8.0",
    "gn:asciiname":"Xincuncun",
    "gn:country_code":"CN",
    "gn:dem":162,
    "gn:feature_class":"P",
    "gn:feature_code":"PPL",
    "gn:name":"Xincuncun",
    "gn:population":0,
    "gn:timezone":"Asia/Shanghai",
    "iso:country":"CN",
    "name:zho_x_preferred":[
        "\u65b0\u6751\u6751"
    ],
    "wof:name":"Xincuncun",
    "wof:placetype":"locality"
},
  "geometry": {"coordinates":[123.92471,47.74616],"type":"Point"}
}