{
  "type": "Feature",
  "properties": {
    "gn:admin1_code":"15.0",
    "gn:asciiname":"Gagao'ernangre",
    "gn:country_code":"CN",
    "gn:dem":3212,
    "gn:feature_class":"P",
    "gn:feature_code":"PPL",
    "gn:name":"Gagao\u2019ernangre",
    "gn:population":0,
    "gn:timezone":"Asia/Shanghai",
    "iso:country":"CN",
    "name:und_x_variant":[
        "Gagao\u2019ernangre",
        "\u5c15\u544a\u5c14\u56ca\u70ed"
    ],
    "wof:name":"Gagao'ernangre",
    "wof:placetype":"locality"
},
  "geometry": {"coordinates":[102.36275999999999,35.05499],"type":"Point"}
}