{
  "type": "Feature",
  "properties": {
    "gn:admin1_code":"16.0",
    "gn:asciiname":"Xidayan",
    "gn:country_code":"CN",
    "gn:dem":126,
    "gn:feature_class":"P",
    "gn:feature_code":"PPL",
    "gn:name":"Xidayan",
    "gn:population":0,
    "gn:timezone":"Asia/Shanghai",
    "iso:country":"CN",
    "name:zho_x_preferred":[
        "\u897f\u5927\u5ca9"
    ],
    "wof:name":"Xidayan",
    "wof:placetype":"locality"
},
  "geometry": {"coordinates":[109.121,24.9981],"type":"Point"}
}