{
  "type": "Feature",
  "properties": {
    "gn:admin1_code":"29.0",
    "gn:asciiname":"Nong'e",
    "gn:country_code":"CN",
    "gn:dem":751,
    "gn:feature_class":"P",
    "gn:feature_code":"PPL",
    "gn:name":"Nong\u2019e",
    "gn:population":0,
    "gn:timezone":"Asia/Shanghai",
    "iso:country":"CN",
    "name:und_x_variant":[
        "Nong\u2019e"
    ],
    "name:zho_x_preferred":[
        "\u5f04\u989d"
    ],
    "wof:name":"Nong'e",
    "wof:placetype":"locality"
},
  "geometry": {"coordinates":[97.6527,23.8834],"type":"Point"}
}