{
  "type": "Feature",
  "properties": {
    "gn:admin1_code":"9.0",
    "gn:asciiname":"Beiluminggou",
    "gn:country_code":"CN",
    "gn:dem":895,
    "gn:feature_class":"P",
    "gn:feature_code":"PPL",
    "gn:name":"Beiluminggou",
    "gn:population":0,
    "gn:timezone":"Asia/Shanghai",
    "iso:country":"CN",
    "name:zho_x_preferred":[
        "\u5317\u9e7f\u9e23\u6c9f"
    ],
    "wof:name":"Beiluminggou",
    "wof:placetype":"locality"
},
  "geometry": {"coordinates":[112.19284,33.8613],"type":"Point"}
}