{
  "type": "Feature",
  "properties": {
    "gn:admin1_code":"29.0",
    "gn:asciiname":"Hushipo",
    "gn:country_code":"CN",
    "gn:dem":1226,
    "gn:feature_class":"P",
    "gn:feature_code":"PPL",
    "gn:name":"Hushipo",
    "gn:population":0,
    "gn:timezone":"Asia/Shanghai",
    "iso:country":"CN",
    "name:zho_x_preferred":[
        "\u62a4\u58eb\u5761"
    ],
    "wof:name":"Hushipo",
    "wof:placetype":"locality"
},
  "geometry": {"coordinates":[98.2711,24.8389],"type":"Point"}
}