{
  "type": "Feature",
  "properties": {
    "gn:admin1_code":"23.0",
    "gn:asciiname":"Xinhai Nongchang",
    "gn:country_code":"CN",
    "gn:dem":3,
    "gn:feature_class":"P",
    "gn:feature_code":"PPLF",
    "gn:name":"Xinhai Nongchang",
    "gn:population":0,
    "gn:timezone":"Asia/Shanghai",
    "iso:country":"CN",
    "name:und_x_variant":[
        "Xinhai",
        "Xinhai Nongchang"
    ],
    "wof:name":"Xinhai Nongchang",
    "wof:placetype":"locality"
},
  "geometry": {"coordinates":[121.28194000000001,31.82222],"type":"Point"}
}