{
  "type": "Feature",
  "properties": {
    "gn:admin1_code":"24.0",
    "gn:asciiname":"Checuncun",
    "gn:country_code":"CN",
    "gn:dem":363,
    "gn:feature_class":"P",
    "gn:feature_code":"PPL",
    "gn:name":"Checuncun",
    "gn:population":0,
    "gn:timezone":"Asia/Shanghai",
    "iso:country":"CN",
    "name:zho_x_preferred":[
        "\u8f66\u6751\u6751"
    ],
    "wof:name":"Checuncun",
    "wof:placetype":"locality"
},
  "geometry": {"coordinates":[110.99221,34.73421],"type":"Point"}
}