{
  "type": "Feature",
  "properties": {
    "gn:admin1_code":"29.0",
    "gn:asciiname":"Zhongzhai",
    "gn:country_code":"CN",
    "gn:dem":1926,
    "gn:feature_class":"P",
    "gn:feature_code":"PPL",
    "gn:name":"Zhongzhai",
    "gn:population":0,
    "gn:timezone":"Asia/Shanghai",
    "iso:country":"CN",
    "name:zho_x_preferred":[
        "\u4e2d\u5be8"
    ],
    "wof:name":"Zhongzhai",
    "wof:placetype":"locality"
},
  "geometry": {"coordinates":[104.071,23.0411],"type":"Point"}
}