{
  "type": "Feature",
  "properties": {
    "gn:admin1_code":"02",
    "gn:asciiname":"Changtu",
    "gn:country_code":"CN",
    "gn:dem":4,
    "gn:feature_class":"P",
    "gn:feature_code":"PPLA4",
    "gn:name":"Changtu",
    "gn:population":0,
    "gn:timezone":"Asia/Shanghai",
    "iso:country":"CN",
    "name:und_x_variant":[
        "Changtuzhen",
        "Wojingtan",
        "\u502d\u4e95\u8c2d",
        "\u957f\u6d82\u9547",
        "\u957f\u6d82"
    ],
    "wof:name":"Changtu",
    "wof:placetype":"locality"
},
  "geometry": {"coordinates":[122.30334000000001,30.25405],"type":"Point"}
}