{
  "type": "Feature",
  "properties": {
    "gn:admin1_code":"11.0",
    "gn:asciiname":"Sanjiaotang",
    "gn:country_code":"CN",
    "gn:dem":100,
    "gn:feature_class":"P",
    "gn:feature_code":"PPL",
    "gn:name":"Sanjiaotang",
    "gn:population":0,
    "gn:timezone":"Asia/Shanghai",
    "iso:country":"CN",
    "name:zho_x_preferred":[
        "\u4e09\u89d2\u5858"
    ],
    "wof:name":"Sanjiaotang",
    "wof:placetype":"locality"
},
  "geometry": {"coordinates":[112.72332,26.38794],"type":"Point"}
}