{
  "type": "Feature",
  "properties": {
    "gn:admin1_code":"26.0",
    "gn:asciiname":"Dayangoucun",
    "gn:country_code":"CN",
    "gn:dem":931,
    "gn:feature_class":"P",
    "gn:feature_code":"PPL",
    "gn:name":"Dayangoucun",
    "gn:population":0,
    "gn:timezone":"Asia/Shanghai",
    "iso:country":"CN",
    "name:zho_x_preferred":[
        "\u5927\u5830\u6c9f\u6751"
    ],
    "wof:name":"Dayangoucun",
    "wof:placetype":"locality"
},
  "geometry": {"coordinates":[108.64292,33.59534],"type":"Point"}
}