{
  "type": "Feature",
  "properties": {
    "gn:admin1_code":"1.0",
    "gn:asciiname":"Zhanlicun",
    "gn:country_code":"CN",
    "gn:dem":502,
    "gn:feature_class":"P",
    "gn:feature_code":"PPL",
    "gn:name":"Zhanlicun",
    "gn:population":0,
    "gn:timezone":"Asia/Shanghai",
    "iso:country":"CN",
    "name:zho_x_preferred":[
        "\u5360\u68a8\u6751"
    ],
    "wof:name":"Zhanlicun",
    "wof:placetype":"locality"
},
  "geometry": {"coordinates":[118.00269,29.64447],"type":"Point"}
}