{
  "type": "Feature",
  "properties": {
    "gn:admin1_code":"06",
    "gn:asciiname":"Gaomiao",
    "gn:cc2":"CN",
    "gn:country_code":"CN",
    "gn:dem":1928,
    "gn:feature_class":"P",
    "gn:feature_code":"PPL",
    "gn:name":"Gaomiao",
    "gn:population":0,
    "gn:timezone":"Asia/Shanghai",
    "iso:country":"CN",
    "name:und_x_variant":[
        "Kao-miao-tzu",
        "Kao-miao-chen",
        "Kao-miao",
        "Gaomiao"
    ],
    "wof:name":"Gaomiao",
    "wof:placetype":"locality"
},
  "geometry": {"coordinates":[102.53806,36.445],"type":"Point"}
}