{
  "type": "Feature",
  "properties": {
    "gn:admin1_code":"14.0",
    "gn:asciiname":"Lajia",
    "gn:country_code":"CN",
    "gn:dem":3807,
    "gn:feature_class":"P",
    "gn:feature_code":"PPLF",
    "gn:name":"Lajia",
    "gn:population":0,
    "gn:timezone":"Asia/Urumqi",
    "iso:country":"CN",
    "name:bod_x_preferred":[
        "La\u2019gyab"
    ],
    "name:cat_x_preferred":[
        "Lajia"
    ],
    "name:dan_x_preferred":[
        "Lajia"
    ],
    "name:deu_x_preferred":[
        "Lajia"
    ],
    "name:fra_x_preferred":[
        "Lajia"
    ],
    "name:hun_x_preferred":[
        "Lacsia"
    ],
    "name:jpn_x_preferred":[
        "\u5587\u5bb6\u907a\u8de1"
    ],
    "name:lat_x_preferred":[
        "Lajia"
    ],
    "name:nor_x_preferred":[
        "Lajia"
    ],
    "name:zho_x_preferred":[
        "Lajia"
    ],
    "name:zho_x_variant":[
        "\u62c9\u52a0",
        "Ruoba",
        "\u82e5\u5df4",
        "\u5587\u5bb6\u9057\u5740"
    ],
    "wof:name":"Lajia",
    "wof:placetype":"locality"
},
  "geometry": {"coordinates":[97.301,30.701],"type":"Point"}
}