{
  "type": "Feature",
  "properties": {
    "gn:admin1_code":"12.0",
    "gn:asciiname":"Xiangshuidong",
    "gn:country_code":"CN",
    "gn:dem":1220,
    "gn:feature_class":"P",
    "gn:feature_code":"PPL",
    "gn:name":"Xiangshuidong",
    "gn:population":0,
    "gn:timezone":"Asia/Shanghai",
    "iso:country":"CN",
    "name:zho_x_preferred":[
        "\u54cd\u6c34\u6d1e"
    ],
    "wof:name":"Xiangshuidong",
    "wof:placetype":"locality"
},
  "geometry": {"coordinates":[109.60448999999998,32.02976],"type":"Point"}
}