{
  "type": "Feature",
  "properties": {
    "gn:admin1_code":"8.0",
    "gn:asciiname":"Qixingcun",
    "gn:country_code":"CN",
    "gn:dem":285,
    "gn:feature_class":"P",
    "gn:feature_code":"PPL",
    "gn:name":"Qixingcun",
    "gn:population":0,
    "gn:timezone":"Asia/Shanghai",
    "iso:country":"CN",
    "name:zho_x_preferred":[
        "\u5947\u5174\u6751"
    ],
    "wof:name":"Qixingcun",
    "wof:placetype":"locality"
},
  "geometry": {"coordinates":[129.21559999999999,44.55089],"type":"Point"}
}