{
  "type": "Feature",
  "properties": {
    "gn:admin1_code":"24.0",
    "gn:asciiname":"Qianhujiabei",
    "gn:country_code":"CN",
    "gn:dem":1127,
    "gn:feature_class":"P",
    "gn:feature_code":"PPL",
    "gn:name":"Qianhujiabei",
    "gn:population":0,
    "gn:timezone":"Asia/Shanghai",
    "iso:country":"CN",
    "name:zho_x_preferred":[
        "\u524d\u80e1\u5bb6\u80cc"
    ],
    "wof:name":"Qianhujiabei",
    "wof:placetype":"locality"
},
  "geometry": {"coordinates":[112.37015,36.09144000000001],"type":"Point"}
}