{
  "type": "Feature",
  "properties": {
    "gn:admin1_code":"30.0",
    "gn:asciiname":"Guikengwei",
    "gn:country_code":"CN",
    "gn:dem":611,
    "gn:feature_class":"P",
    "gn:feature_code":"PPL",
    "gn:name":"Guikengwei",
    "gn:population":0,
    "gn:timezone":"Asia/Shanghai",
    "iso:country":"CN",
    "name:zho_x_preferred":[
        "Guikengwei"
    ],
    "name:zho_x_variant":[
        "\u6842\u5751\u5c3e"
    ],
    "wof:name":"Guikengwei",
    "wof:placetype":"locality"
},
  "geometry": {"coordinates":[113.30403,24.99148],"type":"Point"}
}