{
  "type": "Feature",
  "properties": {
    "gn:admin1_code":"20.0",
    "gn:asciiname":"Cuncaowan",
    "gn:country_code":"CN",
    "gn:dem":1611,
    "gn:feature_class":"P",
    "gn:feature_code":"PPL",
    "gn:name":"Cuncaowan",
    "gn:population":0,
    "gn:timezone":"Asia/Shanghai",
    "iso:country":"CN",
    "name:und_x_variant":[
        "\u5bf8\u8349\u6e7e"
    ],
    "wof:name":"Cuncaowan",
    "wof:placetype":"locality"
},
  "geometry": {"coordinates":[111.6694,41.09612],"type":"Point"}
}