{
  "type": "Feature",
  "properties": {
    "gn:admin1_code":"33",
    "gn:asciiname":"Panlong",
    "gn:country_code":"CN",
    "gn:dem":258,
    "gn:feature_class":"P",
    "gn:feature_code":"PPLA4",
    "gn:name":"Panlong",
    "gn:population":0,
    "gn:timezone":"Asia/Shanghai",
    "iso:country":"CN",
    "name:ceb_x_preferred":[
        "Panlong"
    ],
    "name:deu_x_preferred":[
        "Panlong"
    ],
    "name:fra_x_preferred":[
        "Panlong"
    ],
    "name:nor_x_preferred":[
        "Panlong"
    ],
    "name:und_x_variant":[
        "Pan-shin-chen",
        "P\u2019an-t\u2019o",
        "P\u2019an-shih-chen",
        "Panshizhen",
        "Panlong Zhen"
    ],
    "name:zho_x_preferred":[
        "\u76d8\u9f99"
    ],
    "name:zho_x_variant":[
        "\u76d8\u9f99\u9547"
    ],
    "wof:name":"Panlong",
    "wof:placetype":"locality"
},
  "geometry": {"coordinates":[108.70965,30.90654],"type":"Point"}
}