{
  "type": "Feature",
  "properties": {
    "gn:admin1_code":"32.0",
    "gn:asciiname":"Jiaji",
    "gn:country_code":"CN",
    "gn:dem":2795,
    "gn:feature_class":"P",
    "gn:feature_code":"PPL",
    "gn:name":"Jiaji",
    "gn:population":0,
    "gn:timezone":"Asia/Shanghai",
    "iso:country":"CN",
    "name:zho_x_preferred":[
        "\u7532\u5409"
    ],
    "wof:name":"Jiaji",
    "wof:placetype":"locality"
},
  "geometry": {"coordinates":[103.27612000000001,33.67089],"type":"Point"}
}