{
  "type": "Feature",
  "properties": {
    "gn:admin1_code":"30",
    "gn:asciiname":"Weiganzhai",
    "gn:country_code":"CN",
    "gn:dem":23,
    "gn:feature_class":"P",
    "gn:feature_code":"PPL",
    "gn:name":"Weiganzhai",
    "gn:population":0,
    "gn:timezone":"Asia/Shanghai",
    "iso:country":"CN",
    "name:zho_x_preferred":[
        "\u6845\u6746\u5be8"
    ],
    "wof:name":"Weiganzhai",
    "wof:placetype":"locality"
},
  "geometry": {"coordinates":[111.56476000000001,22.02825],"type":"Point"}
}