{
  "type": "Feature",
  "properties": {
    "gn:admin1_code":"32.0",
    "gn:asciiname":"Zhuadongyan",
    "gn:country_code":"CN",
    "gn:dem":554,
    "gn:feature_class":"P",
    "gn:feature_code":"PPL",
    "gn:name":"Zhuadongyan",
    "gn:population":0,
    "gn:timezone":"Asia/Shanghai",
    "iso:country":"CN",
    "name:zho_x_preferred":[
        "\u6293\u6d1e\u5ca9"
    ],
    "wof:name":"Zhuadongyan",
    "wof:placetype":"locality"
},
  "geometry": {"coordinates":[104.53,28.253],"type":"Point"}
}