{
  "type": "Feature",
  "properties": {
    "gn:admin1_code":"26.0",
    "gn:asciiname":"Nantuncun",
    "gn:country_code":"CN",
    "gn:dem":1171,
    "gn:feature_class":"P",
    "gn:feature_code":"PPL",
    "gn:name":"Nantuncun",
    "gn:population":0,
    "gn:timezone":"Asia/Shanghai",
    "iso:country":"CN",
    "name:zho_x_preferred":[
        "\u5357\u5c6f\u6751"
    ],
    "wof:name":"Nantuncun",
    "wof:placetype":"locality"
},
  "geometry": {"coordinates":[109.24415999999999,36.62208],"type":"Point"}
}