{
  "type": "Feature",
  "properties": {
    "gn:admin1_code":"29.0",
    "gn:asciiname":"Baha",
    "gn:country_code":"CN",
    "gn:dem":1185,
    "gn:feature_class":"P",
    "gn:feature_code":"PPL",
    "gn:name":"Baha",
    "gn:population":0,
    "gn:timezone":"Asia/Shanghai",
    "iso:country":"CN",
    "name:ceb_x_preferred":[
        "Baha"
    ],
    "name:deu_x_preferred":[
        "Baha"
    ],
    "name:msa_x_preferred":[
        "Baha"
    ],
    "name:pol_x_preferred":[
        "Baha"
    ],
    "name:rus_x_preferred":[
        "\u0411\u0430\u0445\u0430"
    ],
    "name:swe_x_preferred":[
        "Baha"
    ],
    "name:zho_x_preferred":[
        "\u575d\u54c8"
    ],
    "wof:name":"Baha",
    "wof:placetype":"locality"
},
  "geometry": {"coordinates":[101.90900000000001,22.9833],"type":"Point"}
}