{
  "type": "Feature",
  "properties": {
    "gn:admin1_code":"20.0",
    "gn:asciiname":"Lianmeng",
    "gn:country_code":"CN",
    "gn:dem":272,
    "gn:feature_class":"P",
    "gn:feature_code":"PPL",
    "gn:name":"Lianmeng",
    "gn:population":0,
    "gn:timezone":"Asia/Shanghai",
    "iso:country":"CN",
    "name:zho_x_preferred":[
        "\u8054\u76df"
    ],
    "wof:name":"Lianmeng",
    "wof:placetype":"locality"
},
  "geometry": {"coordinates":[123.82586000000001,48.44711],"type":"Point"}
}