{
  "type": "Feature",
  "properties": {
    "gn:admin1_code":"14.0",
    "gn:asciiname":"Jiatading",
    "gn:country_code":"CN",
    "gn:dem":4103,
    "gn:feature_class":"P",
    "gn:feature_code":"PPLF",
    "gn:name":"Jiatading",
    "gn:population":0,
    "gn:timezone":"Asia/Urumqi",
    "iso:country":"CN",
    "name:bod_x_preferred":[
        "Jagtagd\u00eang"
    ],
    "name:zho_x_preferred":[
        "Jiatading"
    ],
    "name:zho_x_variant":[
        "\u52a0\u5b83\u9876"
    ],
    "wof:name":"Jiatading",
    "wof:placetype":"locality"
},
  "geometry": {"coordinates":[98.55,29.65],"type":"Point"}
}