{
  "type": "Feature",
  "properties": {
    "gn:admin1_code":"8.0",
    "gn:asciiname":"Fujiayoufang",
    "gn:country_code":"CN",
    "gn:dem":218,
    "gn:feature_class":"P",
    "gn:feature_code":"PPL",
    "gn:name":"Fujiayoufang",
    "gn:population":0,
    "gn:timezone":"Asia/Shanghai",
    "iso:country":"CN",
    "name:zho_x_preferred":[
        "\u4ed8\u5bb6\u6cb9\u623f"
    ],
    "wof:name":"Fujiayoufang",
    "wof:placetype":"locality"
},
  "geometry": {"coordinates":[127.17713000000001,45.17936],"type":"Point"}
}