{
  "type": "Feature",
  "properties": {
    "gn:admin1_code":"19.0",
    "gn:asciiname":"Zhuhongcun",
    "gn:country_code":"CN",
    "gn:dem":140,
    "gn:feature_class":"P",
    "gn:feature_code":"PPL",
    "gn:name":"Zhuhongcun",
    "gn:population":0,
    "gn:timezone":"Asia/Shanghai",
    "iso:country":"CN",
    "name:zho_x_preferred":[
        "\u6731\u7ea2\u6751"
    ],
    "wof:name":"Zhuhongcun",
    "wof:placetype":"locality"
},
  "geometry": {"coordinates":[122.99932,40.803],"type":"Point"}
}