{
  "type": "Feature",
  "properties": {
    "gn:admin1_code":"14.0",
    "gn:asciiname":"Dongdatang",
    "gn:country_code":"CN",
    "gn:dem":4200,
    "gn:feature_class":"P",
    "gn:feature_code":"PPL",
    "gn:name":"Dongdatang",
    "gn:population":0,
    "gn:timezone":"Asia/Urumqi",
    "iso:country":"CN",
    "name:bod_x_preferred":[
        "Dongdatang"
    ],
    "name:zho_x_preferred":[
        "Dongtatang"
    ],
    "name:zho_x_variant":[
        "\u51ac\u5854\u5858"
    ],
    "wof:name":"Dongdatang",
    "wof:placetype":"locality"
},
  "geometry": {"coordinates":[97.001,31.601],"type":"Point"}
}