{
  "type": "Feature",
  "properties": {
    "gn:admin1_code":"15.0",
    "gn:asciiname":"Guanlugou",
    "gn:country_code":"CN",
    "gn:dem":1984,
    "gn:feature_class":"P",
    "gn:feature_code":"PPL",
    "gn:name":"Guanlugou",
    "gn:population":0,
    "gn:timezone":"Asia/Shanghai",
    "iso:country":"CN",
    "name:zho_x_preferred":[
        "\u5b98\u8def\u6c9f"
    ],
    "wof:name":"Guanlugou",
    "wof:placetype":"locality"
},
  "geometry": {"coordinates":[103.526,36.5673],"type":"Point"}
}