{
  "type": "Feature",
  "properties": {
    "gn:admin1_code":"12.0",
    "gn:asciiname":"Guoyuandun",
    "gn:country_code":"CN",
    "gn:dem":526,
    "gn:feature_class":"P",
    "gn:feature_code":"PPL",
    "gn:name":"Guoyuandun",
    "gn:population":0,
    "gn:timezone":"Asia/Shanghai",
    "iso:country":"CN",
    "name:zho_x_preferred":[
        "Guoyuandun"
    ],
    "name:zho_x_variant":[
        "\u679c\u56ed\u58a9"
    ],
    "wof:name":"Guoyuandun",
    "wof:placetype":"locality"
},
  "geometry": {"coordinates":[111.10191,30.83469],"type":"Point"}
}