{
  "type": "Feature",
  "properties": {
    "gn:admin1_code":"19.0",
    "gn:asciiname":"Qianmayiling",
    "gn:country_code":"CN",
    "gn:dem":206,
    "gn:feature_class":"P",
    "gn:feature_code":"PPL",
    "gn:name":"Qianmayiling",
    "gn:population":0,
    "gn:timezone":"Asia/Shanghai",
    "iso:country":"CN",
    "name:zho_x_preferred":[
        "\u524d\u8682\u8681\u5cad"
    ],
    "wof:name":"Qianmayiling",
    "wof:placetype":"locality"
},
  "geometry": {"coordinates":[124.70644,42.38685],"type":"Point"}
}