{
  "type": "Feature",
  "properties": {
    "gn:admin1_code":"32.0",
    "gn:asciiname":"Maojiahe",
    "gn:country_code":"CN",
    "gn:dem":894,
    "gn:feature_class":"P",
    "gn:feature_code":"PPL",
    "gn:name":"Maojiahe",
    "gn:population":0,
    "gn:timezone":"Asia/Shanghai",
    "iso:country":"CN",
    "name:zho_x_preferred":[
        "\u5e3d\u67b6\u6cb3"
    ],
    "wof:name":"Maojiahe",
    "wof:placetype":"locality"
},
  "geometry": {"coordinates":[105.03588999999999,32.41085],"type":"Point"}
}