{
  "type": "Feature",
  "properties": {
    "gn:admin1_code":"19.0",
    "gn:asciiname":"Longsanjiacun",
    "gn:country_code":"CN",
    "gn:dem":80,
    "gn:feature_class":"P",
    "gn:feature_code":"PPL",
    "gn:name":"Longsanjiacun",
    "gn:population":0,
    "gn:timezone":"Asia/Shanghai",
    "iso:country":"CN",
    "name:zho_x_preferred":[
        "\u9f99\u4e09\u5bb6\u6751"
    ],
    "wof:name":"Longsanjiacun",
    "wof:placetype":"locality"
},
  "geometry": {"coordinates":[123.624,41.7125],"type":"Point"}
}