{
  "type": "Feature",
  "properties": {
    "gn:admin1_code":"33.0",
    "gn:asciiname":"Jiuda",
    "gn:country_code":"CN",
    "gn:dem":953,
    "gn:feature_class":"P",
    "gn:feature_code":"PPL",
    "gn:name":"Jiuda",
    "gn:population":0,
    "gn:timezone":"Asia/Shanghai",
    "iso:country":"CN",
    "name:zho_x_preferred":[
        "\u4e5d\u6253"
    ],
    "wof:name":"Jiuda",
    "wof:placetype":"locality"
},
  "geometry": {"coordinates":[108.83176,28.6827],"type":"Point"}
}