{
  "type": "Feature",
  "properties": {
    "gn:admin1_code":"29.0",
    "gn:asciiname":"Moshihe",
    "gn:country_code":"CN",
    "gn:dem":1675,
    "gn:feature_class":"P",
    "gn:feature_code":"PPL",
    "gn:name":"Moshihe",
    "gn:population":0,
    "gn:timezone":"Asia/Shanghai",
    "iso:country":"CN",
    "name:zho_x_preferred":[
        "\u78e8\u77f3\u6cb3"
    ],
    "wof:name":"Moshihe",
    "wof:placetype":"locality"
},
  "geometry": {"coordinates":[97.62949999999999,24.5679],"type":"Point"}
}