{
  "type": "Feature",
  "properties": {
    "gn:admin1_code":"24.0",
    "gn:asciiname":"Shangbadong",
    "gn:country_code":"CN",
    "gn:dem":884,
    "gn:feature_class":"P",
    "gn:feature_code":"PPL",
    "gn:name":"Shangbadong",
    "gn:population":0,
    "gn:timezone":"Asia/Shanghai",
    "iso:country":"CN",
    "name:zho_x_preferred":[
        "\u4e0a\u516b\u6d1e"
    ],
    "wof:name":"Shangbadong",
    "wof:placetype":"locality"
},
  "geometry": {"coordinates":[112.42287,37.27148],"type":"Point"}
}