{
  "type": "Feature",
  "properties": {
    "gn:admin1_code":"18.0",
    "gn:asciiname":"Yecha",
    "gn:country_code":"CN",
    "gn:dem":788,
    "gn:feature_class":"P",
    "gn:feature_code":"PPL",
    "gn:name":"Yecha",
    "gn:population":0,
    "gn:timezone":"Asia/Shanghai",
    "iso:country":"CN",
    "name:zho_x_preferred":[
        "\u91ce\u8336"
    ],
    "wof:name":"Yecha",
    "wof:placetype":"locality"
},
  "geometry": {"coordinates":[107.27200000000001,28.4118],"type":"Point"}
}