{
  "type": "Feature",
  "properties": {
    "gn:admin1_code":"12",
    "gn:asciiname":"Gufengling",
    "gn:cc2":"CN",
    "gn:country_code":"CN",
    "gn:dem":61,
    "gn:feature_class":"P",
    "gn:feature_code":"PPL",
    "gn:name":"Gufengling",
    "gn:population":0,
    "gn:timezone":"Asia/Shanghai",
    "iso:country":"CN",
    "name:und_x_variant":[
        "Ku-feng-ling",
        "Gufengling"
    ],
    "wof:name":"Gufengling",
    "wof:placetype":"locality"
},
  "geometry": {"coordinates":[114.6675,31.40694],"type":"Point"}
}