{
  "type": "Feature",
  "properties": {
    "gn:country":"CN",
    "gn:fcode":"PPLA3",
    "gn:population":71053,
    "iso:country":"CN",
    "name:ceb_x_preferred":[
        "Chengyang"
    ],
    "name:deu_x_preferred":[
        "Chengyang"
    ],
    "name:rus_x_preferred":[
        "\u0424\u0443\u0430\u043d\u044f"
    ],
    "name:und_x_variant":[
        "Hanyang"
    ],
    "name:zho_x_preferred":[
        "\u57ce\u9633"
    ],
    "name:zho_x_variant":[
        "\u798f\u5b89",
        "\u798f\u5b89\u5e02",
        "\u57ce\u9633\u4e61"
    ],
    "ne:ADM0CAP":0.0,
    "ne:ADM0NAME":"China",
    "ne:ADM0_A3":"CHN",
    "ne:ADM1NAME":"Fujian",
    "ne:ADMIN1_COD":7,
    "ne:CAPALT":0,
    "ne:CHANGED":0,
    "ne:CHECKME":0,
    "ne:COMPARE":0,
    "ne:DIFFASCII":0,
    "ne:ELEVATION":0.0,
    "ne:FEATURECLA":"Populated place",
    "ne:FEATURE_CL":"P",
    "ne:FEATURE_CO":"PPL",
    "ne:GEONAMEID":1808872,
    "ne:GEONAMESNO":"GeoNames spatial join with similar names only.",
    "ne:GN_ASCII":"Fu'an",
    "ne:GN_POP":71053,
    "ne:GTOPO30":20.0,
    "ne:ISO_A2":"CN",
    "ne:LABELRANK":1,
    "ne:LATITUDE":27.070426,
    "ne:LONGITUDE":119.620026,
    "ne:LS_MATCH":1,
    "ne:LS_NAME":"Fuan",
    "ne:MAX_AREAKM":28.0,
    "ne:MAX_AREAMI":11.0,
    "ne:MAX_BBXMAX":119.675,
    "ne:MAX_BBXMIN":119.6,
    "ne:MAX_BBYMAX":27.141667,
    "ne:MAX_BBYMIN":27.066667,
    "ne:MAX_NATSCA":20.0,
    "ne:MAX_PERKM":38.0,
    "ne:MAX_PERMI":24.0,
    "ne:MAX_POP10":92470,
    "ne:MAX_POP20":92470,
    "ne:MAX_POP300":0,
    "ne:MAX_POP310":0,
    "ne:MAX_POP50":0,
    "ne:MEAN_BBXC":119.638401,
    "ne:MEAN_BBYC":27.10259,
    "ne:MEGACITY":0,
    "ne:MIN_AREAKM":28.0,
    "ne:MIN_AREAMI":11.0,
    "ne:MIN_BBXMAX":119.675,
    "ne:MIN_BBXMIN":119.6,
    "ne:MIN_BBYMAX":27.141667,
    "ne:MIN_BBYMIN":27.066667,
    "ne:MIN_PERKM":38.0,
    "ne:MIN_PERMI":24.0,
    "ne:NAME":"Fuan",
    "ne:NAMEASCII":"Fuan",
    "ne:NAMEDIFF":0,
    "ne:NATSCALE":20,
    "ne:POP1950":0,
    "ne:POP1955":0,
    "ne:POP1960":0,
    "ne:POP1965":0,
    "ne:POP1970":0,
    "ne:POP1975":0,
    "ne:POP1980":0,
    "ne:POP1985":0,
    "ne:POP1990":0,
    "ne:POP1995":0,
    "ne:POP2000":0,
    "ne:POP2005":0,
    "ne:POP2010":0,
    "ne:POP2015":0,
    "ne:POP2020":0,
    "ne:POP2025":0,
    "ne:POP2050":0,
    "ne:POP_MAX":92470,
    "ne:POP_MIN":71053,
    "ne:POP_OTHER":0,
    "ne:RANK_MAX":8,
    "ne:RANK_MIN":8,
    "ne:SCALERANK":7,
    "ne:SOV0NAME":"China",
    "ne:SOV_A3":"CHN",
    "ne:TIMEZONE":"Asia/Shanghai",
    "ne:UN_FID":0,
    "ne:UN_LAT":0.0,
    "ne:UN_LONG":0.0,
    "ne:WORLDCITY":0,
    "qs:name":"Chengyang",
    "qs:photos_9r":0,
    "qs:photos_sr":0,
    "qs:pop_sr":"8",
    "wd:wordcount":39,
    "wof:name":"Chengyang",
    "wof:placetype":"locality",
    "wof:population":71053
},
  "geometry": {"coordinates":[119.64528,27.08917],"type":"Point"}
}