{
  "type": "Feature",
  "properties": {
    "gn:admin1_code":"11.0",
    "gn:asciiname":"Xiongjiaping",
    "gn:country_code":"CN",
    "gn:dem":176,
    "gn:feature_class":"P",
    "gn:feature_code":"PPL",
    "gn:name":"Xiongjiaping",
    "gn:population":0,
    "gn:timezone":"Asia/Shanghai",
    "iso:country":"CN",
    "name:zho_x_preferred":[
        "\u718a\u5bb6\u576a"
    ],
    "wof:name":"Xiongjiaping",
    "wof:placetype":"locality"
},
  "geometry": {"coordinates":[111.93420999999999,27.17344000000001],"type":"Point"}
}