{
  "type": "Feature",
  "properties": {
    "gn:admin1_code":"20",
    "gn:asciiname":"Bumbat",
    "gn:cc2":"CN",
    "gn:country_code":"CN",
    "gn:dem":916,
    "gn:feature_class":"P",
    "gn:feature_code":"PPL",
    "gn:name":"Bumbat",
    "gn:population":0,
    "gn:timezone":"Asia/Shanghai",
    "iso:country":"CN",
    "name:und_x_variant":[
        "Peng-pa-t\u2019e",
        "Bumbat"
    ],
    "wof:name":"Bumbat",
    "wof:placetype":"locality"
},
  "geometry": {"coordinates":[112.68333,43.76667],"type":"Point"}
}