{
  "type": "Feature",
  "properties": {
    "gn:admin1_code":"10.0",
    "gn:asciiname":"Baiwangzhuang",
    "gn:country_code":"CN",
    "gn:dem":250,
    "gn:feature_class":"P",
    "gn:feature_code":"PPL",
    "gn:name":"Baiwangzhuang",
    "gn:population":0,
    "gn:timezone":"Asia/Shanghai",
    "iso:country":"CN",
    "name:und_x_variant":[
        "\u767d\u738b\u5e84"
    ],
    "wof:name":"Baiwangzhuang",
    "wof:placetype":"locality"
},
  "geometry": {"coordinates":[114.18742,38.04938],"type":"Point"}
}