{
  "type": "Feature",
  "properties": {
    "gn:admin1_code":"32.0",
    "gn:asciiname":"Gaoping",
    "gn:country_code":"CN",
    "gn:dem":1260,
    "gn:feature_class":"P",
    "gn:feature_code":"PPL",
    "gn:name":"Gaoping",
    "gn:population":0,
    "gn:timezone":"Asia/Shanghai",
    "iso:country":"CN",
    "name:zho_x_preferred":[
        "\u9ad8\u576a"
    ],
    "wof:name":"Gaoping",
    "wof:placetype":"locality"
},
  "geometry": {"coordinates":[104.471,32.2008],"type":"Point"}
}