{
  "type": "Feature",
  "properties": {
    "gn:admin1_code":"18",
    "gn:asciiname":"Guanmenyan",
    "gn:country_code":"CN",
    "gn:dem":756,
    "gn:feature_class":"P",
    "gn:feature_code":"PPL",
    "gn:name":"Guanmenyan",
    "gn:population":0,
    "gn:timezone":"Asia/Shanghai",
    "iso:country":"CN",
    "name:zho_x_preferred":[
        "\u5173\u95e8\u5ca9"
    ],
    "wof:name":"Guanmenyan",
    "wof:placetype":"locality"
},
  "geometry": {"coordinates":[107.879,28.3433],"type":"Point"}
}