{
  "type": "Feature",
  "properties": {
    "gn:admin1_code":"7.0",
    "gn:asciiname":"Jisheng",
    "gn:country_code":"CN",
    "gn:dem":313,
    "gn:feature_class":"P",
    "gn:feature_code":"PPL",
    "gn:name":"Jisheng",
    "gn:population":0,
    "gn:timezone":"Asia/Shanghai",
    "iso:country":"CN",
    "name:zho_x_preferred":[
        "\u8ba1\u6607"
    ],
    "wof:name":"Jisheng",
    "wof:placetype":"locality"
},
  "geometry": {"coordinates":[116.37366000000002,25.86023],"type":"Point"}
}