{
  "type": "Feature",
  "properties": {
    "gn:admin1_code":"11",
    "gn:asciiname":"Mazijiang",
    "gn:country_code":"CN",
    "gn:dem":168,
    "gn:feature_class":"P",
    "gn:feature_code":"PPL",
    "gn:name":"Mazijiang",
    "gn:population":0,
    "gn:timezone":"Asia/Shanghai",
    "iso:country":"CN",
    "name:zho_x_preferred":[
        "\u9a6c\u5b50\u6c5f"
    ],
    "wof:name":"Mazijiang",
    "wof:placetype":"locality"
},
  "geometry": {"coordinates":[111.36190000000001,25.98491],"type":"Point"}
}