{
  "type": "Feature",
  "properties": {
    "gn:admin1_code":"33.0",
    "gn:asciiname":"Yandixia",
    "gn:country_code":"CN",
    "gn:dem":771,
    "gn:feature_class":"P",
    "gn:feature_code":"PPL",
    "gn:name":"Yandixia",
    "gn:population":0,
    "gn:timezone":"Asia/Shanghai",
    "iso:country":"CN",
    "name:zho_x_preferred":[
        "\u5ca9\u5e95\u4e0b"
    ],
    "wof:name":"Yandixia",
    "wof:placetype":"locality"
},
  "geometry": {"coordinates":[106.813,28.6214],"type":"Point"}
}