{
  "type": "Feature",
  "properties": {
    "gn:admin1_code":"10.0",
    "gn:asciiname":"Liudianzhuang",
    "gn:country_code":"CN",
    "gn:dem":17,
    "gn:feature_class":"P",
    "gn:feature_code":"PPL",
    "gn:name":"Liudianzhuang",
    "gn:population":0,
    "gn:timezone":"Asia/Shanghai",
    "iso:country":"CN",
    "name:zho_x_preferred":[
        "\u5218\u4f43\u5e84"
    ],
    "wof:name":"Liudianzhuang",
    "wof:placetype":"locality"
},
  "geometry": {"coordinates":[115.79600000000001,38.5306],"type":"Point"}
}