{
  "type": "Feature",
  "properties": {
    "gn:admin1_code":"29",
    "gn:asciiname":"Xiaoheishan",
    "gn:country_code":"CN",
    "gn:dem":2000,
    "gn:feature_class":"P",
    "gn:feature_code":"PPL",
    "gn:name":"Xiaoheishan",
    "gn:population":0,
    "gn:timezone":"Asia/Shanghai",
    "iso:country":"CN",
    "name:zho_x_preferred":[
        "\u5c0f\u9ed1\u5c71"
    ],
    "wof:name":"Xiaoheishan",
    "wof:placetype":"locality"
},
  "geometry": {"coordinates":[102.001,24.7187],"type":"Point"}
}