{
  "type": "Feature",
  "properties": {
    "gn:admin1_code":"16",
    "gn:asciiname":"Datangbian",
    "gn:country_code":"CN",
    "gn:dem":332,
    "gn:feature_class":"P",
    "gn:feature_code":"PPL",
    "gn:name":"Datangbian",
    "gn:population":0,
    "gn:timezone":"Asia/Shanghai",
    "iso:country":"CN",
    "name:zho_x_preferred":[
        "\u5927\u5858\u8fb9"
    ],
    "wof:name":"Datangbian",
    "wof:placetype":"locality"
},
  "geometry": {"coordinates":[110.61499999999999,25.3426],"type":"Point"}
}