{
  "type": "Feature",
  "properties": {
    "gn:admin1_code":"3.0",
    "gn:asciiname":"Xugang",
    "gn:country_code":"CN",
    "gn:dem":529,
    "gn:feature_class":"P",
    "gn:feature_code":"PPL",
    "gn:name":"Xugang",
    "gn:population":0,
    "gn:timezone":"Asia/Shanghai",
    "iso:country":"CN",
    "name:und_x_variant":[
        "\u5729\u5c97"
    ],
    "wof:name":"Xugang",
    "wof:placetype":"locality"
},
  "geometry": {"coordinates":[115.51347,25.19995],"type":"Point"}
}