{
  "type": "Feature",
  "properties": {
    "gn:admin1_code":"3.0",
    "gn:asciiname":"Zhangcha",
    "gn:country_code":"CN",
    "gn:dem":87,
    "gn:feature_class":"P",
    "gn:feature_code":"PPL",
    "gn:name":"Zhangcha",
    "gn:population":0,
    "gn:timezone":"Asia/Shanghai",
    "iso:country":"CN",
    "name:und_x_variant":[
        "\u6a1f\u69ce"
    ],
    "wof:name":"Zhangcha",
    "wof:placetype":"locality"
},
  "geometry": {"coordinates":[114.58329999999999,28.26692],"type":"Point"}
}