{
  "type": "Feature",
  "properties": {
    "gn:admin1_code":"3",
    "gn:asciiname":"Simaoping",
    "gn:country_code":"CN",
    "gn:dem":441,
    "gn:feature_class":"P",
    "gn:feature_code":"PPL",
    "gn:name":"Simaoping",
    "gn:population":0,
    "gn:timezone":"Asia/Shanghai",
    "iso:country":"CN",
    "name:zho_x_preferred":[
        "\u4e1d\u8305\u576a"
    ],
    "wof:name":"Simaoping",
    "wof:placetype":"locality"
},
  "geometry": {"coordinates":[114.523,25.6519],"type":"Point"}
}