{
  "type": "Feature",
  "properties": {
    "gn:admin1_code":"21.0",
    "gn:asciiname":"Yujia Buzi",
    "gn:country_code":"CN",
    "gn:dem":1816,
    "gn:feature_class":"P",
    "gn:feature_code":"PPL",
    "gn:name":"Yujia Buzi",
    "gn:population":0,
    "gn:timezone":"Asia/Shanghai",
    "iso:country":"CN",
    "name:und_x_variant":[
        "\u4f59\u5bb6\u5821\u5b50"
    ],
    "name:zho_x_preferred":[
        "\u4f59\u5bb6\u5821\u5b50"
    ],
    "wof:name":"Yujia Buzi",
    "wof:placetype":"locality"
},
  "geometry": {"coordinates":[105.87272,35.72047],"type":"Point"}
}