{
  "type": "Feature",
  "properties": {
    "gn:admin1_code":"15.0",
    "gn:asciiname":"Suoluo",
    "gn:country_code":"CN",
    "gn:dem":1456,
    "gn:feature_class":"P",
    "gn:feature_code":"PPL",
    "gn:name":"Suoluo",
    "gn:population":0,
    "gn:timezone":"Asia/Shanghai",
    "iso:country":"CN",
    "name:und_x_variant":[
        "\u7d22\u7f57"
    ],
    "wof:name":"Suoluo",
    "wof:placetype":"locality"
},
  "geometry": {"coordinates":[106.40989,33.74245999999999],"type":"Point"}
}