{
  "type": "Feature",
  "properties": {
    "gn:admin1_code":"6.0",
    "gn:asciiname":"Balie",
    "gn:country_code":"CN",
    "gn:dem":4316,
    "gn:feature_class":"P",
    "gn:feature_code":"PPL",
    "gn:name":"Balie",
    "gn:population":0,
    "gn:timezone":"Asia/Urumqi",
    "iso:country":"CN",
    "name:zho_x_preferred":[
        "\u5df4\u5217"
    ],
    "wof:name":"Balie",
    "wof:placetype":"locality"
},
  "geometry": {"coordinates":[95.38088,32.23659],"type":"Point"}
}