{
  "type": "Feature",
  "properties": {
    "gn:admin1_code":"3.0",
    "gn:asciiname":"Zhangnaoshan",
    "gn:country_code":"CN",
    "gn:dem":781,
    "gn:feature_class":"P",
    "gn:feature_code":"PPL",
    "gn:name":"Zhangnaoshan",
    "gn:population":0,
    "gn:timezone":"Asia/Shanghai",
    "iso:country":"CN",
    "name:zho_x_preferred":[
        "\u6a1f\u8111\u5c71"
    ],
    "wof:name":"Zhangnaoshan",
    "wof:placetype":"locality"
},
  "geometry": {"coordinates":[115.938,25.3142],"type":"Point"}
}