{
  "type": "Feature",
  "properties": {
    "gn:admin1_code":"8.0",
    "gn:asciiname":"Donghuashutun",
    "gn:country_code":"CN",
    "gn:dem":114,
    "gn:feature_class":"P",
    "gn:feature_code":"PPL",
    "gn:name":"Donghuashutun",
    "gn:population":0,
    "gn:timezone":"Asia/Shanghai",
    "iso:country":"CN",
    "name:zho_x_preferred":[
        "\u4e1c\u6866\u6811\u5c6f"
    ],
    "wof:name":"Donghuashutun",
    "wof:placetype":"locality"
},
  "geometry": {"coordinates":[127.7281,45.99312000000001],"type":"Point"}
}