{
  "type": "Feature",
  "properties": {
    "gn:admin1_code":"32.0",
    "gn:asciiname":"Xiabakou",
    "gn:country_code":"CN",
    "gn:dem":815,
    "gn:feature_class":"P",
    "gn:feature_code":"PPL",
    "gn:name":"Xiabakou",
    "gn:population":0,
    "gn:timezone":"Asia/Shanghai",
    "iso:country":"CN",
    "name:zho_x_preferred":[
        "\u867e\u6252\u53e3"
    ],
    "wof:name":"Xiabakou",
    "wof:placetype":"locality"
},
  "geometry": {"coordinates":[107.98699999999999,31.185],"type":"Point"}
}