{
  "type": "Feature",
  "properties": {
    "gn:admin1_code":"12.0",
    "gn:asciiname":"Maojiaji",
    "gn:country_code":"CN",
    "gn:dem":131,
    "gn:feature_class":"P",
    "gn:feature_code":"PPL",
    "gn:name":"Maojiaji",
    "gn:population":0,
    "gn:timezone":"Asia/Shanghai",
    "iso:country":"CN",
    "name:zho_x_preferred":[
        "\u6bdb\u5bb6\u96c6"
    ],
    "wof:name":"Maojiaji",
    "wof:placetype":"locality"
},
  "geometry": {"coordinates":[114.26461,31.49748],"type":"Point"}
}