{
  "type": "Feature",
  "properties": {
    "gn:admin1_code":"5.0",
    "gn:asciiname":"Qianshanquantun",
    "gn:country_code":"CN",
    "gn:dem":209,
    "gn:feature_class":"P",
    "gn:feature_code":"PPL",
    "gn:name":"Qianshanquantun",
    "gn:population":0,
    "gn:timezone":"Asia/Shanghai",
    "iso:country":"CN",
    "name:zho_x_preferred":[
        "\u524d\u5c71\u6cc9\u5c6f"
    ],
    "wof:name":"Qianshanquantun",
    "wof:placetype":"locality"
},
  "geometry": {"coordinates":[126.97685,44.71002],"type":"Point"}
}