{
  "type": "Feature",
  "properties": {
    "gn:admin1_code":"9",
    "gn:asciiname":"Doucun",
    "gn:country_code":"CN",
    "gn:dem":50,
    "gn:feature_class":"P",
    "gn:feature_code":"PPL",
    "gn:name":"Doucun",
    "gn:population":0,
    "gn:timezone":"Asia/Shanghai",
    "iso:country":"CN",
    "name:zho_x_preferred":[
        "\u8c46\u6751"
    ],
    "wof:name":"Doucun",
    "wof:placetype":"locality"
},
  "geometry": {"coordinates":[115.16583,36.10078],"type":"Point"}
}