{
  "type": "Feature",
  "properties": {
    "gn:admin1_code":"11.0",
    "gn:asciiname":"Xiushui",
    "gn:country_code":"CN",
    "gn:dem":472,
    "gn:feature_class":"P",
    "gn:feature_code":"PPL",
    "gn:name":"Xiushui",
    "gn:population":0,
    "gn:timezone":"Asia/Shanghai",
    "iso:country":"CN",
    "name:deu_x_preferred":[
        "Xiushui"
    ],
    "name:fra_x_preferred":[
        "Xiushui"
    ],
    "name:zho_x_preferred":[
        "\u79c0\u6c34"
    ],
    "wof:name":"Xiushui",
    "wof:placetype":"locality"
},
  "geometry": {"coordinates":[110.30874,26.7582],"type":"Point"}
}