{
  "type": "Feature",
  "properties": {
    "gn:admin1_code":"32.0",
    "gn:asciiname":"Qiahejue",
    "gn:country_code":"CN",
    "gn:dem":2488,
    "gn:feature_class":"P",
    "gn:feature_code":"PPL",
    "gn:name":"Qiahejue",
    "gn:population":0,
    "gn:timezone":"Asia/Shanghai",
    "iso:country":"CN",
    "name:zho_x_preferred":[
        "\u6d3d\u5408\u89c9"
    ],
    "wof:name":"Qiahejue",
    "wof:placetype":"locality"
},
  "geometry": {"coordinates":[103.057,28.0407],"type":"Point"}
}