{
  "type": "Feature",
  "properties": {
    "gn:admin1_code":"2.0",
    "gn:asciiname":"Zhujiatou",
    "gn:country_code":"CN",
    "gn:dem":180,
    "gn:feature_class":"P",
    "gn:feature_code":"PPL",
    "gn:name":"Zhujiatou",
    "gn:population":0,
    "gn:timezone":"Asia/Shanghai",
    "iso:country":"CN",
    "name:und_x_variant":[
        "\u6731\u5bb6\u5934"
    ],
    "name:zho_x_preferred":[
        "Zhujiatou"
    ],
    "wof:name":"Zhujiatou",
    "wof:placetype":"locality"
},
  "geometry": {"coordinates":[119.54561,30.23467],"type":"Point"}
}