{
  "type": "Feature",
  "properties": {
    "gn:admin1_code":"7.0",
    "gn:asciiname":"Lianqiao",
    "gn:country_code":"CN",
    "gn:dem":344,
    "gn:feature_class":"P",
    "gn:feature_code":"PPL",
    "gn:name":"Lianqiao",
    "gn:population":0,
    "gn:timezone":"Asia/Shanghai",
    "iso:country":"CN",
    "name:zho_x_preferred":[
        "\u8054\u6865"
    ],
    "wof:name":"Lianqiao",
    "wof:placetype":"locality"
},
  "geometry": {"coordinates":[117.20341000000001,24.83526],"type":"Point"}
}