{
  "type": "Feature",
  "properties": {
    "gn:admin1_code":"32.0",
    "gn:asciiname":"Pujia Liangzi",
    "gn:country_code":"CN",
    "gn:dem":1735,
    "gn:feature_class":"P",
    "gn:feature_code":"PPL",
    "gn:name":"Pujia Liangzi",
    "gn:population":0,
    "gn:timezone":"Asia/Shanghai",
    "iso:country":"CN",
    "name:zho_x_preferred":[
        "\u666e\u5bb6\u7cb1\u5b50"
    ],
    "wof:name":"Pujia Liangzi",
    "wof:placetype":"locality"
},
  "geometry": {"coordinates":[102.84099999999999,26.8972],"type":"Point"}
}