{
  "type": "Feature",
  "properties": {
    "gn:country":"CN",
    "gn:fcode":"PPLA3",
    "gn:pop":67273,
    "iso:country":"CN",
    "name:unk_x_variant":[
        "P\u2019ing-chuang"
    ],
    "qs:name":"Pingzhuang",
    "qs:photos_9r":0,
    "qs:photos_sr":0,
    "qs:pop_sr":"8",
    "wof:name":"Pingzhuang",
    "wof:placetype":"locality",
    "wof:population":67273
},
  "geometry": {"coordinates":[119.28888999999999,42.03722],"type":"Point"}
}