{
  "type": "Feature",
  "properties": {
    "gn:admin1_code":"29.0",
    "gn:asciiname":"Mangkeng",
    "gn:country_code":"CN",
    "gn:dem":491,
    "gn:feature_class":"P",
    "gn:feature_code":"PPL",
    "gn:name":"Mangkeng",
    "gn:population":0,
    "gn:timezone":"Asia/Shanghai",
    "iso:country":"CN",
    "name:ind_x_preferred":[
        "Mangkeng"
    ],
    "name:zho_x_preferred":[
        "\u8292\u5751"
    ],
    "wof:name":"Mangkeng",
    "wof:placetype":"locality"
},
  "geometry": {"coordinates":[99.0868,23.5879],"type":"Point"}
}