{
  "type": "Feature",
  "properties": {
    "gn:admin1_code":"3.0",
    "gn:asciiname":"Liukeng",
    "gn:country_code":"CN",
    "gn:dem":306,
    "gn:feature_class":"P",
    "gn:feature_code":"PPL",
    "gn:name":"Liukeng",
    "gn:population":0,
    "gn:timezone":"Asia/Shanghai",
    "iso:country":"CN",
    "name:und_x_variant":[
        "\u6d41\u5751"
    ],
    "wof:name":"Liukeng",
    "wof:placetype":"locality"
},
  "geometry": {"coordinates":[115.66346,26.77757],"type":"Point"}
}