{
  "type": "Feature",
  "properties": {
    "gn:admin1_code":"24.0",
    "gn:asciiname":"Xiaoyezhuang",
    "gn:country_code":"CN",
    "gn:dem":1548,
    "gn:feature_class":"P",
    "gn:feature_code":"PPL",
    "gn:name":"Xiaoyezhuang",
    "gn:population":0,
    "gn:timezone":"Asia/Shanghai",
    "iso:country":"CN",
    "name:zho_x_preferred":[
        "\u5c0f\u91ce\u5e84"
    ],
    "wof:name":"Xiaoyezhuang",
    "wof:placetype":"locality"
},
  "geometry": {"coordinates":[112.20851,39.77425],"type":"Point"}
}