{
  "type": "Feature",
  "properties": {
    "gn:admin1_code":"18.0",
    "gn:asciiname":"Tangshang",
    "gn:country_code":"CN",
    "gn:dem":1395,
    "gn:feature_class":"P",
    "gn:feature_code":"PPL",
    "gn:name":"Tangshang",
    "gn:population":0,
    "gn:timezone":"Asia/Shanghai",
    "iso:country":"CN",
    "wof:name":"Tangshang",
    "wof:placetype":"locality"
},
  "geometry": {"coordinates":[105.13333,26.33333],"type":"Point"}
}