{
  "type": "Feature",
  "properties": {
    "gn:admin1_code":"11.0",
    "gn:asciiname":"Mashazhou",
    "gn:country_code":"CN",
    "gn:dem":31,
    "gn:feature_class":"P",
    "gn:feature_code":"PPL",
    "gn:name":"Mashazhou",
    "gn:population":0,
    "gn:timezone":"Asia/Shanghai",
    "iso:country":"CN",
    "name:zho_x_preferred":[
        "\u9ebb\u6c99\u6d32"
    ],
    "wof:name":"Mashazhou",
    "wof:placetype":"locality"
},
  "geometry": {"coordinates":[112.70152,28.55181],"type":"Point"}
}