{
  "type": "Feature",
  "properties": {
    "gn:admin1_code":"7.0",
    "gn:asciiname":"Zhufeng",
    "gn:country_code":"CN",
    "gn:dem":946,
    "gn:feature_class":"P",
    "gn:feature_code":"PPL",
    "gn:name":"Zhufeng",
    "gn:population":0,
    "gn:timezone":"Asia/Shanghai",
    "iso:country":"CN",
    "name:zho_x_preferred":[
        "\u73e0\u5cf0"
    ],
    "wof:name":"Zhufeng",
    "wof:placetype":"locality"
},
  "geometry": {"coordinates":[118.45707,26.08493],"type":"Point"}
}