{
  "type": "Feature",
  "properties": {
    "gn:admin1_code":"5.0",
    "gn:asciiname":"Xinghecun",
    "gn:country_code":"CN",
    "gn:dem":184,
    "gn:feature_class":"P",
    "gn:feature_code":"PPL",
    "gn:name":"Xinghecun",
    "gn:population":0,
    "gn:timezone":"Asia/Shanghai",
    "iso:country":"CN",
    "name:zho_x_preferred":[
        "\u5174\u548c\u6751"
    ],
    "wof:name":"Xinghecun",
    "wof:placetype":"locality"
},
  "geometry": {"coordinates":[125.3614,44.98552],"type":"Point"}
}