{
  "type": "Feature",
  "properties": {
    "gn:admin1_code":"5.0",
    "gn:asciiname":"Wutaicun",
    "gn:country_code":"CN",
    "gn:dem":615,
    "gn:feature_class":"P",
    "gn:feature_code":"PPL",
    "gn:name":"Wutaicun",
    "gn:population":0,
    "gn:timezone":"Asia/Shanghai",
    "iso:country":"CN",
    "name:zho_x_preferred":[
        "\u4e94\u53f0\u6751"
    ],
    "wof:name":"Wutaicun",
    "wof:placetype":"locality"
},
  "geometry": {"coordinates":[126.63381,42.4657],"type":"Point"}
}