{
  "type": "Feature",
  "properties": {
    "gn:admin1_code":"14.0",
    "gn:asciiname":"Xiedongcun",
    "gn:country_code":"CN",
    "gn:dem":4513,
    "gn:feature_class":"P",
    "gn:feature_code":"PPL",
    "gn:name":"Xiedongcun",
    "gn:population":0,
    "gn:timezone":"Asia/Shanghai",
    "iso:country":"CN",
    "name:und_x_variant":[
        "Xiandongle",
        "Xiedongcun"
    ],
    "name:zho_x_preferred":[
        "\u659c\u4e1c\u6751"
    ],
    "name:zho_x_variant":[
        "\u659c\u4e1c\u6751"
    ],
    "wof:name":"Xiedongcun",
    "wof:placetype":"locality"
},
  "geometry": {"coordinates":[81.1168,32.3578],"type":"Point"}
}