{
  "type": "Feature",
  "properties": {
    "gn:admin1_code":"29.0",
    "gn:asciiname":"Gantang",
    "gn:country_code":"CN",
    "gn:dem":1661,
    "gn:feature_class":"P",
    "gn:feature_code":"PPL",
    "gn:name":"Gantang",
    "gn:population":0,
    "gn:timezone":"Asia/Shanghai",
    "iso:country":"CN",
    "name:zho_x_preferred":[
        "\u5e72\u5858"
    ],
    "name:zho_x_variant":[
        "\u5e72\u5858\u7ad9"
    ],
    "wof:name":"Gantang",
    "wof:placetype":"locality"
},
  "geometry": {"coordinates":[103.244,22.8297],"type":"Point"}
}