{
  "type": "Feature",
  "properties": {
    "gn:admin1_code":"26.0",
    "gn:asciiname":"Goujialing",
    "gn:country_code":"CN",
    "gn:dem":1230,
    "gn:feature_class":"P",
    "gn:feature_code":"PPL",
    "gn:name":"Goujialing",
    "gn:population":0,
    "gn:timezone":"Asia/Shanghai",
    "iso:country":"CN",
    "name:und_x_variant":[
        "\u82df\u5bb6\u5cad"
    ],
    "wof:name":"Goujialing",
    "wof:placetype":"locality"
},
  "geometry": {"coordinates":[107.59608,34.59896],"type":"Point"}
}