{
  "type": "Feature",
  "properties": {
    "gn:admin1_code":"16.0",
    "gn:asciiname":"Zuokou",
    "gn:country_code":"CN",
    "gn:dem":48,
    "gn:feature_class":"P",
    "gn:feature_code":"PPL",
    "gn:name":"Zuokou",
    "gn:population":0,
    "gn:timezone":"Asia/Shanghai",
    "iso:country":"CN",
    "name:zho_x_preferred":[
        "\u5ea7\u53e3"
    ],
    "wof:name":"Zuokou",
    "wof:placetype":"locality"
},
  "geometry": {"coordinates":[111.55500000000001,23.6686],"type":"Point"}
}