{
  "type": "Feature",
  "properties": {
    "gn:admin1_code":"29.0",
    "gn:asciiname":"Xiaopingdi",
    "gn:country_code":"CN",
    "gn:dem":1689,
    "gn:feature_class":"P",
    "gn:feature_code":"PPL",
    "gn:name":"Xiaopingdi",
    "gn:population":0,
    "gn:timezone":"Asia/Shanghai",
    "iso:country":"CN",
    "name:zho_x_preferred":[
        "\u5c0f\u5e73\u5730"
    ],
    "wof:name":"Xiaopingdi",
    "wof:placetype":"locality"
},
  "geometry": {"coordinates":[101.681,26.198],"type":"Point"}
}