{
  "type": "Feature",
  "properties": {
    "gn:admin1_code":"30.0",
    "gn:asciiname":"Luojing",
    "gn:country_code":"CN",
    "gn:dem":104,
    "gn:feature_class":"P",
    "gn:feature_code":"PPLA4",
    "gn:name":"Luojing",
    "gn:population":0,
    "gn:timezone":"Asia/Shanghai",
    "iso:country":"CN",
    "name:und_x_variant":[
        "Lo-ching-hs\u00fc",
        "Lo-ching",
        "Lokeng",
        "Luojing",
        "Luojing Zhen",
        "\u7f57\u955c\u9547"
    ],
    "name:zho_x_preferred":[
        "\u7f57\u955c"
    ],
    "wof:name":"Luojing",
    "wof:placetype":"locality"
},
  "geometry": {"coordinates":[111.44376,22.54146],"type":"Point"}
}