{
  "type": "Feature",
  "properties": {
    "gn:admin1_code":"7",
    "gn:asciiname":"Niushanding",
    "gn:country_code":"CN",
    "gn:dem":183,
    "gn:feature_class":"P",
    "gn:feature_code":"PPL",
    "gn:name":"Niushanding",
    "gn:population":0,
    "gn:timezone":"Asia/Shanghai",
    "iso:country":"CN",
    "name:zho_x_preferred":[
        "\u725b\u5c71\u9876"
    ],
    "wof:name":"Niushanding",
    "wof:placetype":"locality"
},
  "geometry": {"coordinates":[119.57581999999999,25.71456],"type":"Point"}
}