{
  "type": "Feature",
  "properties": {
    "gn:admin1_code":"13.0",
    "gn:asciiname":"Jetaral",
    "gn:country_code":"CN",
    "gn:dem":494,
    "gn:feature_class":"P",
    "gn:feature_code":"PPLA4",
    "gn:name":"Jetaral",
    "gn:population":0,
    "gn:timezone":"Asia/Urumqi",
    "iso:country":"CN",
    "name:und_x_variant":[
        "Jetaral Xiang",
        "Jetaral",
        "Jiete\u2019arel\u2019e",
        "Jiete\u2019arel\u2019e Xiang"
    ],
    "name:zho_x_preferred":[
        "\u89e3\u7279\u963f\u70ed\u52d2"
    ],
    "name:zho_x_variant":[
        "\u89e3\u7279\u963f\u70ed\u52d2\u4e61"
    ],
    "wof:name":"Jetaral",
    "wof:placetype":"locality"
},
  "geometry": {"coordinates":[87.44535999999999,47.0977],"type":"Point"}
}