{
  "type": "Feature",
  "properties": {
    "gn:admin1_code":"18.0",
    "gn:asciiname":"Banmai",
    "gn:country_code":"CN",
    "gn:dem":438,
    "gn:feature_class":"P",
    "gn:feature_code":"PPL",
    "gn:name":"Banmai",
    "gn:population":0,
    "gn:timezone":"Asia/Shanghai",
    "iso:country":"CN",
    "name:zho_x_preferred":[
        "\u677f\u9ea6"
    ],
    "wof:name":"Banmai",
    "wof:placetype":"locality"
},
  "geometry": {"coordinates":[107.785,25.3139],"type":"Point"}
}