{
  "type": "Feature",
  "properties": {
    "gn:admin1_code":"18.0",
    "gn:asciiname":"Pingjiu",
    "gn:country_code":"CN",
    "gn:dem":1030,
    "gn:feature_class":"P",
    "gn:feature_code":"PPL",
    "gn:name":"Pingjiu",
    "gn:population":0,
    "gn:timezone":"Asia/Shanghai",
    "iso:country":"CN",
    "name:zho_x_preferred":[
        "\u5e73\u9e20"
    ],
    "wof:name":"Pingjiu",
    "wof:placetype":"locality"
},
  "geometry": {"coordinates":[108.932,26.6761],"type":"Point"}
}