{
  "type": "Feature",
  "properties": {
    "gn:admin1_code":"15.0",
    "gn:asciiname":"Xiaochi",
    "gn:country_code":"CN",
    "gn:dem":2034,
    "gn:feature_class":"P",
    "gn:feature_code":"PPL",
    "gn:name":"Xiaochi",
    "gn:population":0,
    "gn:timezone":"Asia/Shanghai",
    "iso:country":"CN",
    "name:und_x_variant":[
        "\u5c0f\u6c60"
    ],
    "wof:name":"Xiaochi",
    "wof:placetype":"locality"
},
  "geometry": {"coordinates":[105.12811000000001,33.87707],"type":"Point"}
}