{
  "type": "Feature",
  "properties": {
    "gn:admin1_code":"16.0",
    "gn:asciiname":"Fugaocun",
    "gn:country_code":"CN",
    "gn:dem":51,
    "gn:feature_class":"P",
    "gn:feature_code":"PPL",
    "gn:name":"Fugaocun",
    "gn:population":0,
    "gn:timezone":"Asia/Shanghai",
    "iso:country":"CN",
    "name:zho_x_preferred":[
        "\u798f\u9ad8\u6751"
    ],
    "wof:name":"Fugaocun",
    "wof:placetype":"locality"
},
  "geometry": {"coordinates":[110.014,23.2199],"type":"Point"}
}