{
  "type": "Feature",
  "properties": {
    "gn:admin1_code":"30",
    "gn:asciiname":"Xiaojing",
    "gn:country_code":"CN",
    "gn:dem":82,
    "gn:feature_class":"P",
    "gn:feature_code":"PPL",
    "gn:name":"Xiaojing",
    "gn:population":0,
    "gn:timezone":"Asia/Shanghai",
    "iso:country":"CN",
    "name:nld_x_preferred":[
        "Xiaojing"
    ],
    "name:swe_x_preferred":[
        "Xiaojing"
    ],
    "wof:name":"Xiaojing",
    "wof:placetype":"locality"
},
  "geometry": {"coordinates":[116.715,24.56222],"type":"Point"}
}