{
  "type": "Feature",
  "properties": {
    "gn:admin1_code":"32.0",
    "gn:asciiname":"Huashi",
    "gn:country_code":"CN",
    "gn:dem":410,
    "gn:feature_class":"P",
    "gn:feature_code":"PPL",
    "gn:name":"Huashi",
    "gn:population":0,
    "gn:timezone":"Asia/Shanghai",
    "iso:country":"CN",
    "name:deu_x_preferred":[
        "Huashi"
    ],
    "name:zho_x_preferred":[
        "\u6ed1\u77f3"
    ],
    "wof:name":"Huashi",
    "wof:placetype":"locality"
},
  "geometry": {"coordinates":[105.39400000000001,29.8166],"type":"Point"}
}