{
  "type": "Feature",
  "properties": {
    "gn:admin1_code":"9.0",
    "gn:asciiname":"Liuhuo",
    "gn:country_code":"CN",
    "gn:dem":182,
    "gn:feature_class":"P",
    "gn:feature_code":"PPL",
    "gn:name":"Liuhuo",
    "gn:population":0,
    "gn:timezone":"Asia/Shanghai",
    "iso:country":"CN",
    "name:zho_x_preferred":[
        "\u5218\u4f19"
    ],
    "wof:name":"Liuhuo",
    "wof:placetype":"locality"
},
  "geometry": {"coordinates":[111.30476000000002,32.98134],"type":"Point"}
}