{
  "type": "Feature",
  "properties": {
    "gn:admin1_code":"20.0",
    "gn:asciiname":"Dongjiaba",
    "gn:country_code":"CN",
    "gn:dem":1427,
    "gn:feature_class":"P",
    "gn:feature_code":"PPL",
    "gn:name":"Dongjiaba",
    "gn:population":0,
    "gn:timezone":"Asia/Shanghai",
    "iso:country":"CN",
    "name:und_x_variant":[
        "\u4e1c\u7532\u575d"
    ],
    "wof:name":"Dongjiaba",
    "wof:placetype":"locality"
},
  "geometry": {"coordinates":[110.12075,40.98419000000001],"type":"Point"}
}