{
  "type": "Feature",
  "properties": {
    "gn:admin1_code":"1.0",
    "gn:asciiname":"Guaijicun",
    "gn:country_code":"CN",
    "gn:dem":22,
    "gn:feature_class":"P",
    "gn:feature_code":"PPL",
    "gn:name":"Guaijicun",
    "gn:population":0,
    "gn:timezone":"Asia/Shanghai",
    "iso:country":"CN",
    "name:zho_x_preferred":[
        "\u62d0\u96c6\u6751"
    ],
    "wof:name":"Guaijicun",
    "wof:placetype":"locality"
},
  "geometry": {"coordinates":[117.09546,32.85979],"type":"Point"}
}