{
  "type": "Feature",
  "properties": {
    "gn:admin1_code":"15.0",
    "gn:asciiname":"Wangshan",
    "gn:country_code":"CN",
    "gn:dem":1351,
    "gn:feature_class":"P",
    "gn:feature_code":"PPL",
    "gn:name":"Wangshan",
    "gn:population":0,
    "gn:timezone":"Asia/Shanghai",
    "iso:country":"CN",
    "name:zho_x_preferred":[
        "\u738b\u5c71"
    ],
    "wof:name":"Wangshan",
    "wof:placetype":"locality"
},
  "geometry": {"coordinates":[107.24299999999999,35.8958],"type":"Point"}
}