{
  "type": "Feature",
  "properties": {
    "gn:admin1_code":"7",
    "gn:asciiname":"Langqi",
    "gn:country_code":"CN",
    "gn:dem":16,
    "gn:feature_class":"P",
    "gn:feature_code":"PPL",
    "gn:name":"Langqi",
    "gn:population":0,
    "gn:timezone":"Asia/Shanghai",
    "iso:country":"CN",
    "name:zho_x_preferred":[
        "\u7405\u5c90"
    ],
    "wof:name":"Langqi",
    "wof:placetype":"locality"
},
  "geometry": {"coordinates":[119.44889000000001,25.90198],"type":"Point"}
}