{
  "type": "Feature",
  "properties": {
    "gn:admin1_code":"14.0",
    "gn:asciiname":"Yongxie",
    "gn:country_code":"CN",
    "gn:dem":3518,
    "gn:feature_class":"P",
    "gn:feature_code":"PPL",
    "gn:name":"Yongxie",
    "gn:population":0,
    "gn:timezone":"Asia/Urumqi",
    "iso:country":"CN",
    "name:zho_x_preferred":[
        "\u62e5\u8c22"
    ],
    "wof:name":"Yongxie",
    "wof:placetype":"locality"
},
  "geometry": {"coordinates":[98.09354999999999,29.24935],"type":"Point"}
}