{
  "type": "Feature",
  "properties": {
    "gn:admin1_code":"19.0",
    "gn:asciiname":"Sanchakou",
    "gn:country_code":"CN",
    "gn:dem":137,
    "gn:feature_class":"P",
    "gn:feature_code":"PPL",
    "gn:name":"Sanchakou",
    "gn:population":0,
    "gn:timezone":"Asia/Shanghai",
    "iso:country":"CN",
    "name:ceb_x_preferred":[
        "Sanchakou"
    ],
    "name:swe_x_preferred":[
        "Sanchakou"
    ],
    "name:zho_x_preferred":[
        "\u4e09\u53c9\u53e3"
    ],
    "name:zho_x_variant":[
        "\u4e09\u5c94\u53e3"
    ],
    "wof:name":"Sanchakou",
    "wof:placetype":"locality"
},
  "geometry": {"coordinates":[122.04134999999999,42.36071],"type":"Point"}
}