{
  "type": "Feature",
  "properties": {
    "gn:admin1_code":"29.0",
    "gn:asciiname":"Langtanqing",
    "gn:country_code":"CN",
    "gn:dem":1442,
    "gn:feature_class":"P",
    "gn:feature_code":"PPL",
    "gn:name":"Langtanqing",
    "gn:population":0,
    "gn:timezone":"Asia/Shanghai",
    "iso:country":"CN",
    "name:zho_x_preferred":[
        "\u6d6a\u6f6d\u7b90"
    ],
    "wof:name":"Langtanqing",
    "wof:placetype":"locality"
},
  "geometry": {"coordinates":[100.51600000000001,24.5005],"type":"Point"}
}