{
  "type": "Feature",
  "properties": {
    "gn:admin1_code":"10",
    "gn:asciiname":"Xueta",
    "gn:country_code":"CN",
    "gn:dem":35,
    "gn:feature_class":"P",
    "gn:feature_code":"PPL",
    "gn:name":"Xueta",
    "gn:population":0,
    "gn:timezone":"Asia/Shanghai",
    "iso:country":"CN",
    "name:ara_x_preferred":[
        "\u062c\u0648\u0626\u062a\u0627"
    ],
    "name:ast_x_preferred":[
        "Chueta"
    ],
    "name:bre_x_preferred":[
        "Xuetes"
    ],
    "name:cat_x_preferred":[
        "Xuetes"
    ],
    "name:deu_x_preferred":[
        "Xueta"
    ],
    "name:est_x_preferred":[
        "Xueta'd"
    ],
    "name:fas_x_preferred":[
        "\u0686\u0648\u0626\u062a\u0627"
    ],
    "name:fra_x_preferred":[
        "Chuetas"
    ],
    "name:glg_x_preferred":[
        "Xuetas"
    ],
    "name:heb_x_preferred":[
        "\u05e6'\u05d5\u05d0\u05d8\u05d4"
    ],
    "name:lad_x_preferred":[
        "Xuetas"
    ],
    "name:nld_x_preferred":[
        "Xueta"
    ],
    "name:por_x_preferred":[
        "Chueta"
    ],
    "name:rus_x_preferred":[
        "\u0428\u0443\u044d\u0442\u0430\u0441"
    ],
    "name:spa_x_preferred":[
        "Chueta"
    ],
    "name:zho_x_preferred":[
        "\u96ea\u5854"
    ],
    "wof:name":"Xueta",
    "wof:placetype":"locality"
},
  "geometry": {"coordinates":[115.378,37.1444],"type":"Point"}
}