{
  "type": "Feature",
  "properties": {
    "gn:admin1_code":"19.0",
    "gn:asciiname":"Halagatu",
    "gn:country_code":"CN",
    "gn:dem":116,
    "gn:feature_class":"P",
    "gn:feature_code":"PPL",
    "gn:name":"Halagatu",
    "gn:population":0,
    "gn:timezone":"Asia/Shanghai",
    "iso:country":"CN",
    "name:und_x_variant":[
        "\u54c8\u62c9\u560e\u571f"
    ],
    "name:zho_x_preferred":[
        "\u54c8\u62c9\u560e\u571f"
    ],
    "wof:name":"Halagatu",
    "wof:placetype":"locality"
},
  "geometry": {"coordinates":[122.68095,42.55676],"type":"Point"}
}