{
  "type": "Feature",
  "properties": {
    "gn:admin1_code":"29",
    "gn:asciiname":"Lan-ch'iao",
    "gn:country_code":"CN",
    "gn:dem":612,
    "gn:feature_class":"P",
    "gn:feature_code":"PPL",
    "gn:name":"Lan-ch\u2019iao",
    "gn:population":0,
    "gn:timezone":"Asia/Shanghai",
    "iso:country":"CN",
    "wof:name":"Lan-ch'iao",
    "wof:placetype":"locality"
},
  "geometry": {"coordinates":[103.91943999999999,22.81472],"type":"Point"}
}