{
  "type": "Feature",
  "properties": {
    "gn:admin1_code":"16.0",
    "gn:asciiname":"Zhadong",
    "gn:country_code":"CN",
    "gn:dem":310,
    "gn:feature_class":"P",
    "gn:feature_code":"PPL",
    "gn:name":"Zhadong",
    "gn:population":0,
    "gn:timezone":"Asia/Shanghai",
    "iso:country":"CN",
    "name:zho_x_preferred":[
        "\u4e4d\u6d1e"
    ],
    "wof:name":"Zhadong",
    "wof:placetype":"locality"
},
  "geometry": {"coordinates":[108.602,24.6152],"type":"Point"}
}