{
  "type": "Feature",
  "properties": {
    "gn:admin1_code":"24.0",
    "gn:asciiname":"Sujiazhuang",
    "gn:country_code":"CN",
    "gn:dem":1073,
    "gn:feature_class":"P",
    "gn:feature_code":"PPL",
    "gn:name":"Sujiazhuang",
    "gn:population":0,
    "gn:timezone":"Asia/Shanghai",
    "iso:country":"CN",
    "name:zho_x_preferred":[
        "\u82cf\u5bb6\u5e84"
    ],
    "wof:name":"Sujiazhuang",
    "wof:placetype":"locality"
},
  "geometry": {"coordinates":[112.0788,36.0853],"type":"Point"}
}