{
  "type": "Feature",
  "properties": {
    "gn:admin1_code":"6.0",
    "gn:asciiname":"Zhaluo",
    "gn:country_code":"CN",
    "gn:dem":3538,
    "gn:feature_class":"P",
    "gn:feature_code":"PPL",
    "gn:name":"Zhaluo",
    "gn:population":0,
    "gn:timezone":"Asia/Shanghai",
    "iso:country":"CN",
    "name:zho_x_preferred":[
        "\u624e\u6d1b"
    ],
    "wof:name":"Zhaluo",
    "wof:placetype":"locality"
},
  "geometry": {"coordinates":[100.79948,32.77045],"type":"Point"}
}