{
  "type": "Feature",
  "properties": {
    "gn:admin1_code":"26",
    "gn:asciiname":"Hezhai",
    "gn:country_code":"CN",
    "gn:dem":359,
    "gn:feature_class":"P",
    "gn:feature_code":"PPLA4",
    "gn:name":"Hezhai",
    "gn:population":0,
    "gn:timezone":"Asia/Shanghai",
    "iso:country":"CN",
    "name:und_x_variant":[
        "Hejunzhai",
        "Hezhai",
        "Hezhai Zhen"
    ],
    "name:zho_x_preferred":[
        "\u4f55\u5be8"
    ],
    "wof:name":"Hezhai",
    "wof:placetype":"locality"
},
  "geometry": {"coordinates":[109.31779,34.51723],"type":"Point"}
}