{
  "type": "Feature",
  "properties": {
    "gn:admin1_code":"1.0",
    "gn:asciiname":"Dailiucun",
    "gn:country_code":"CN",
    "gn:dem":25,
    "gn:feature_class":"P",
    "gn:feature_code":"PPL",
    "gn:name":"Dailiucun",
    "gn:population":0,
    "gn:timezone":"Asia/Shanghai",
    "iso:country":"CN",
    "name:zho_x_preferred":[
        "\u6234\u5218\u6751"
    ],
    "name:zho_x_variant":[
        "\u4ee3\u5218\u6751"
    ],
    "wof:name":"Dailiucun",
    "wof:placetype":"locality"
},
  "geometry": {"coordinates":[116.80792,33.21808],"type":"Point"}
}