{
  "type": "Feature",
  "properties": {
    "gn:admin1_code":"1.0",
    "gn:asciiname":"Tangdiancun",
    "gn:country_code":"CN",
    "gn:dem":27,
    "gn:feature_class":"P",
    "gn:feature_code":"PPL",
    "gn:name":"Tangdiancun",
    "gn:population":0,
    "gn:timezone":"Asia/Shanghai",
    "iso:country":"CN",
    "name:zho_x_preferred":[
        "\u6c64\u5e97\u6751"
    ],
    "wof:name":"Tangdiancun",
    "wof:placetype":"locality"
},
  "geometry": {"coordinates":[116.37626000000002,32.90424],"type":"Point"}
}