{
  "type": "Feature",
  "properties": {
    "gn:admin1_code":"26.0",
    "gn:asciiname":"Laijiawan",
    "gn:country_code":"CN",
    "gn:dem":570,
    "gn:feature_class":"P",
    "gn:feature_code":"PPL",
    "gn:name":"Laijiawan",
    "gn:population":0,
    "gn:timezone":"Asia/Shanghai",
    "iso:country":"CN",
    "name:zho_x_preferred":[
        "\u6765\u5bb6\u6e7e"
    ],
    "wof:name":"Laijiawan",
    "wof:placetype":"locality"
},
  "geometry": {"coordinates":[108.72667,32.8244],"type":"Point"}
}