{
  "type": "Feature",
  "properties": {
    "gn:admin1_code":"5.0",
    "gn:asciiname":"Liujia Wopeng",
    "gn:country_code":"CN",
    "gn:dem":133,
    "gn:feature_class":"P",
    "gn:feature_code":"PPL",
    "gn:name":"Liujia Wopeng",
    "gn:population":0,
    "gn:timezone":"Asia/Shanghai",
    "iso:country":"CN",
    "name:zho_x_preferred":[
        "\u5218\u5bb6\u7a9d\u68da"
    ],
    "wof:name":"Liujia Wopeng",
    "wof:placetype":"locality"
},
  "geometry": {"coordinates":[123.51864,45.69552],"type":"Point"}
}