{
  "type": "Feature",
  "properties": {
    "gn:admin1_code":"3.0",
    "gn:asciiname":"Liutian",
    "gn:country_code":"CN",
    "gn:dem":192,
    "gn:feature_class":"P",
    "gn:feature_code":"PPL",
    "gn:name":"Liutian",
    "gn:population":0,
    "gn:timezone":"Asia/Shanghai",
    "iso:country":"CN",
    "name:und_x_variant":[
        "\u7559\u7530"
    ],
    "wof:name":"Liutian",
    "wof:placetype":"locality"
},
  "geometry": {"coordinates":[115.26588,25.9398],"type":"Point"}
}