{
  "type": "Feature",
  "properties": {
    "gn:admin1_code":"18",
    "gn:asciiname":"Dashanshang",
    "gn:country_code":"CN",
    "gn:dem":1375,
    "gn:feature_class":"P",
    "gn:feature_code":"PPL",
    "gn:name":"Dashanshang",
    "gn:population":0,
    "gn:timezone":"Asia/Shanghai",
    "iso:country":"CN",
    "name:zho_x_preferred":[
        "\u5927\u5c71\u4e0a"
    ],
    "wof:name":"Dashanshang",
    "wof:placetype":"locality"
},
  "geometry": {"coordinates":[106.18000000000001,26.3272],"type":"Point"}
}