{
  "type": "Feature",
  "properties": {
    "gn:admin1_code":"5.0",
    "gn:asciiname":"Cangku Gouxicha",
    "gn:country_code":"CN",
    "gn:dem":797,
    "gn:feature_class":"P",
    "gn:feature_code":"PPL",
    "gn:name":"Cangku Gouxicha",
    "gn:population":0,
    "gn:timezone":"Asia/Shanghai",
    "iso:country":"CN",
    "name:zho_x_preferred":[
        "\u4ed3\u5e93\u6c9f\u897f\u5c94"
    ],
    "wof:name":"Cangku Gouxicha",
    "wof:placetype":"locality"
},
  "geometry": {"coordinates":[126.31777,41.97408],"type":"Point"}
}