{
  "type": "Feature",
  "properties": {
    "gn:admin1_code":"5.0",
    "gn:asciiname":"Laohatuncun",
    "gn:country_code":"CN",
    "gn:dem":187,
    "gn:feature_class":"P",
    "gn:feature_code":"PPL",
    "gn:name":"Laohatuncun",
    "gn:population":0,
    "gn:timezone":"Asia/Shanghai",
    "iso:country":"CN",
    "name:zho_x_preferred":[
        "\u8001\u5964\u5c6f\u6751"
    ],
    "wof:name":"Laohatuncun",
    "wof:placetype":"locality"
},
  "geometry": {"coordinates":[124.50995,43.87026],"type":"Point"}
}