{
  "type": "Feature",
  "properties": {
    "gn:admin1_code":"16.0",
    "gn:asciiname":"Wuben",
    "gn:country_code":"CN",
    "gn:dem":122,
    "gn:feature_class":"P",
    "gn:feature_code":"PPL",
    "gn:name":"Wuben",
    "gn:population":0,
    "gn:timezone":"Asia/Shanghai",
    "iso:country":"CN",
    "name:zho_x_preferred":[
        "\u52a1\u672c"
    ],
    "wof:name":"Wuben",
    "wof:placetype":"locality"
},
  "geometry": {"coordinates":[108.754,23.2525],"type":"Point"}
}