{
  "type": "Feature",
  "properties": {
    "gn:admin1_code":"32.0",
    "gn:asciiname":"Kongdongba",
    "gn:country_code":"CN",
    "gn:dem":363,
    "gn:feature_class":"P",
    "gn:feature_code":"PPL",
    "gn:name":"Kongdongba",
    "gn:population":0,
    "gn:timezone":"Asia/Shanghai",
    "iso:country":"CN",
    "name:zho_x_preferred":[
        "\u7a7a\u6d1e\u575d"
    ],
    "wof:name":"Kongdongba",
    "wof:placetype":"locality"
},
  "geometry": {"coordinates":[107.19199999999999,30.6175],"type":"Point"}
}