{
  "type": "Feature",
  "properties": {
    "gn:admin1_code":"24.0",
    "gn:asciiname":"Yaojiawancun",
    "gn:country_code":"CN",
    "gn:dem":918,
    "gn:feature_class":"P",
    "gn:feature_code":"PPL",
    "gn:name":"Yaojiawancun",
    "gn:population":0,
    "gn:timezone":"Asia/Shanghai",
    "iso:country":"CN",
    "name:zho_x_preferred":[
        "\u836f\u5bb6\u6e7e\u6751"
    ],
    "wof:name":"Yaojiawancun",
    "wof:placetype":"locality"
},
  "geometry": {"coordinates":[110.62114,36.74448],"type":"Point"}
}