{
  "type": "Feature",
  "properties": {
    "gn:admin1_code":"4.0",
    "gn:asciiname":"Sanqiao",
    "gn:country_code":"CN",
    "gn:dem":4,
    "gn:feature_class":"P",
    "gn:feature_code":"PPL",
    "gn:name":"Sanqiao",
    "gn:population":0,
    "gn:timezone":"Asia/Shanghai",
    "iso:country":"CN",
    "name:deu_x_preferred":[
        "Sanqiao"
    ],
    "name:und_x_variant":[
        "\u4e09\u6865"
    ],
    "name:zho_x_preferred":[
        "\u4e09\u6865"
    ],
    "wof:name":"Sanqiao",
    "wof:placetype":"locality"
},
  "geometry": {"coordinates":[120.53081,32.47729],"type":"Point"}
}