{
  "type": "Feature",
  "properties": {
    "gn:admin1_code":"5.0",
    "gn:asciiname":"Xingshuchuancun",
    "gn:country_code":"CN",
    "gn:dem":140,
    "gn:feature_class":"P",
    "gn:feature_code":"PPL",
    "gn:name":"Xingshuchuancun",
    "gn:population":0,
    "gn:timezone":"Asia/Shanghai",
    "iso:country":"CN",
    "name:zho_x_preferred":[
        "\u674f\u6811\u5ddd\u6751"
    ],
    "wof:name":"Xingshuchuancun",
    "wof:placetype":"locality"
},
  "geometry": {"coordinates":[123.43838,45.18256],"type":"Point"}
}