{
  "type": "Feature",
  "properties": {
    "gn:admin1_code":"1.0",
    "gn:asciiname":"Lantiancun",
    "gn:country_code":"CN",
    "gn:dem":47,
    "gn:feature_class":"P",
    "gn:feature_code":"PPL",
    "gn:name":"Lantiancun",
    "gn:population":0,
    "gn:timezone":"Asia/Shanghai",
    "iso:country":"CN",
    "name:zho_x_preferred":[
        "\u5170\u7530\u6751"
    ],
    "wof:name":"Lantiancun",
    "wof:placetype":"locality"
},
  "geometry": {"coordinates":[117.14315999999999,30.30053],"type":"Point"}
}