{
  "type": "Feature",
  "properties": {
    "gn:admin1_code":"15.0",
    "gn:asciiname":"Shimensi",
    "gn:country_code":"CN",
    "gn:dem":2436,
    "gn:feature_class":"P",
    "gn:feature_code":"PPL",
    "gn:name":"Shimensi",
    "gn:population":0,
    "gn:timezone":"Asia/Shanghai",
    "iso:country":"CN",
    "name:und_x_variant":[
        "\u77f3\u95e8\u5bfa"
    ],
    "wof:name":"Shimensi",
    "wof:placetype":"locality"
},
  "geometry": {"coordinates":[103.81695000000001,34.77114],"type":"Point"}
}