{
  "type": "Feature",
  "properties": {
    "gn:admin1_code":"32.0",
    "gn:asciiname":"Yisa",
    "gn:country_code":"CN",
    "gn:dem":4011,
    "gn:feature_class":"P",
    "gn:feature_code":"PPL",
    "gn:name":"Yisa",
    "gn:population":0,
    "gn:timezone":"Asia/Shanghai",
    "iso:country":"CN",
    "name:zho_x_preferred":[
        "\u4f9d\u8428"
    ],
    "wof:name":"Yisa",
    "wof:placetype":"locality"
},
  "geometry": {"coordinates":[101.232,29.8006],"type":"Point"}
}