{
  "type": "Feature",
  "properties": {
    "gn:admin1_code":"12.0",
    "gn:asciiname":"Zhongxinji",
    "gn:country_code":"CN",
    "gn:dem":46,
    "gn:feature_class":"P",
    "gn:feature_code":"PPL",
    "gn:name":"Zhongxinji",
    "gn:population":0,
    "gn:timezone":"Asia/Shanghai",
    "iso:country":"CN",
    "name:zho_x_preferred":[
        "\u4e2d\u5fc3\u96c6"
    ],
    "wof:name":"Zhongxinji",
    "wof:placetype":"locality"
},
  "geometry": {"coordinates":[112.53377999999999,31.02252],"type":"Point"}
}