{
  "type": "Feature",
  "properties": {
    "gn:admin1_code":"7.0",
    "gn:asciiname":"Qulicun",
    "gn:country_code":"CN",
    "gn:dem":361,
    "gn:feature_class":"P",
    "gn:feature_code":"PPL",
    "gn:name":"Qulicun",
    "gn:population":0,
    "gn:timezone":"Asia/Shanghai",
    "iso:country":"CN",
    "name:und_x_variant":[
        "\u6e20\u91cc\u6751"
    ],
    "name:zho_x_preferred":[
        "\u6e20\u91cc\u6751"
    ],
    "wof:name":"Qulicun",
    "wof:placetype":"locality"
},
  "geometry": {"coordinates":[117.18937,26.84891],"type":"Point"}
}