{
  "type": "Feature",
  "properties": {
    "gn:admin1_code":"30",
    "gn:asciiname":"Luojiaoli",
    "gn:country_code":"CN",
    "gn:dem":152,
    "gn:feature_class":"P",
    "gn:feature_code":"PPL",
    "gn:name":"Luojiaoli",
    "gn:population":0,
    "gn:timezone":"Asia/Shanghai",
    "iso:country":"CN",
    "name:zho_x_preferred":[
        "\u7f57\u89d2\u91cc"
    ],
    "wof:name":"Luojiaoli",
    "wof:placetype":"locality"
},
  "geometry": {"coordinates":[115.63324,24.21805],"type":"Point"}
}