{
  "type": "Feature",
  "properties": {
    "gn:admin1_code":"8.0",
    "gn:asciiname":"Xiaobajingzi",
    "gn:country_code":"CN",
    "gn:dem":183,
    "gn:feature_class":"P",
    "gn:feature_code":"PPL",
    "gn:name":"Xiaobajingzi",
    "gn:population":0,
    "gn:timezone":"Asia/Shanghai",
    "iso:country":"CN",
    "name:zho_x_preferred":[
        "\u5c0f\u516b\u4e95\u5b50"
    ],
    "wof:name":"Xiaobajingzi",
    "wof:placetype":"locality"
},
  "geometry": {"coordinates":[125.42074,46.07878],"type":"Point"}
}