{
  "type": "Feature",
  "properties": {
    "gn:admin1_code":"4.0",
    "gn:asciiname":"Houzuocun",
    "gn:country_code":"CN",
    "gn:dem":11,
    "gn:feature_class":"P",
    "gn:feature_code":"PPL",
    "gn:name":"Houzuocun",
    "gn:population":0,
    "gn:timezone":"Asia/Shanghai",
    "iso:country":"CN",
    "name:zho_x_preferred":[
        "\u540e\u5de6\u6751"
    ],
    "wof:name":"Houzuocun",
    "wof:placetype":"locality"
},
  "geometry": {"coordinates":[118.95269999999999,33.40649000000001],"type":"Point"}
}