{
  "type": "Feature",
  "properties": {
    "gn:admin1_code":"5.0",
    "gn:asciiname":"Qianfengcun",
    "gn:country_code":"CN",
    "gn:dem":172,
    "gn:feature_class":"P",
    "gn:feature_code":"PPL",
    "gn:name":"Qianfengcun",
    "gn:population":0,
    "gn:timezone":"Asia/Shanghai",
    "iso:country":"CN",
    "name:zho_x_preferred":[
        "\u524d\u950b\u6751"
    ],
    "wof:name":"Qianfengcun",
    "wof:placetype":"locality"
},
  "geometry": {"coordinates":[125.22932,44.48907],"type":"Point"}
}