{
  "type": "Feature",
  "properties": {
    "gn:admin1_code":"30",
    "gn:asciiname":"Shishan",
    "gn:country_code":"CN",
    "gn:dem":32,
    "gn:feature_class":"P",
    "gn:feature_code":"PPL",
    "gn:name":"Shishan",
    "gn:population":0,
    "gn:timezone":"Asia/Urumqi",
    "iso:country":"CN",
    "name:zho_x_preferred":[
        "\u77f3\u5c71"
    ],
    "wof:name":"Shishan",
    "wof:placetype":"locality"
},
  "geometry": {"coordinates":[110.78917,21.84304],"type":"Point"}
}