{
  "type": "Feature",
  "properties": {
    "gn:admin1_code":"32.0",
    "gn:asciiname":"Ganzi",
    "gn:country_code":"CN",
    "gn:dem":2512,
    "gn:feature_class":"P",
    "gn:feature_code":"PPL",
    "gn:name":"Ganzi",
    "gn:population":0,
    "gn:timezone":"Asia/Shanghai",
    "iso:country":"CN",
    "name:ceb_x_preferred":[
        "Ganzi"
    ],
    "name:deu_x_preferred":[
        "Ganzi"
    ],
    "name:swe_x_preferred":[
        "Ganzi"
    ],
    "name:zho_x_preferred":[
        "\u7518\u5b50"
    ],
    "wof:name":"Ganzi",
    "wof:placetype":"locality"
},
  "geometry": {"coordinates":[102.614,28.2606],"type":"Point"}
}