{
  "type": "Feature",
  "properties": {
    "gn:admin1_code":"12",
    "gn:asciiname":"Lukou",
    "gn:country_code":"CN",
    "gn:dem":33,
    "gn:feature_class":"P",
    "gn:feature_code":"PPLA4",
    "gn:name":"Lukou",
    "gn:population":0,
    "gn:timezone":"Asia/Shanghai",
    "iso:country":"CN",
    "name:und_x_variant":[
        "\u8def\u53e3",
        "Lukou Zhen",
        "\u8def\u53e3\u9547"
    ],
    "wof:name":"Lukou",
    "wof:placetype":"locality"
},
  "geometry": {"coordinates":[114.93639,30.49255],"type":"Point"}
}