{
  "type": "Feature",
  "properties": {
    "gn:admin1_code":"9.0",
    "gn:asciiname":"Dahaixiang",
    "gn:country_code":"CN",
    "gn:dem":90,
    "gn:feature_class":"P",
    "gn:feature_code":"PPL",
    "gn:name":"Dahaixiang",
    "gn:population":0,
    "gn:timezone":"Asia/Shanghai",
    "iso:country":"CN",
    "name:zho_x_preferred":[
        "\u5927\u6d77\u4e61"
    ],
    "wof:name":"Dahaixiang",
    "wof:placetype":"locality"
},
  "geometry": {"coordinates":[113.54297,35.45825],"type":"Point"}
}