{
  "type": "Feature",
  "properties": {
    "gn:admin1_code":"20.0",
    "gn:asciiname":"Tongsheng",
    "gn:country_code":"CN",
    "gn:dem":256,
    "gn:feature_class":"P",
    "gn:feature_code":"PPL",
    "gn:name":"Tongsheng",
    "gn:population":0,
    "gn:timezone":"Asia/Shanghai",
    "iso:country":"CN",
    "name:zho_x_preferred":[
        "\u540c\u751f"
    ],
    "wof:name":"Tongsheng",
    "wof:placetype":"locality"
},
  "geometry": {"coordinates":[123.24554000000001,48.1873],"type":"Point"}
}