{
  "type": "Feature",
  "properties": {
    "gn:admin1_code":"11.0",
    "gn:asciiname":"Wanyangxi",
    "gn:country_code":"CN",
    "gn:dem":109,
    "gn:feature_class":"P",
    "gn:feature_code":"PPL",
    "gn:name":"Wanyangxi",
    "gn:population":0,
    "gn:timezone":"Asia/Shanghai",
    "iso:country":"CN",
    "name:zho_x_preferred":[
        "\u4e07\u7f8a\u6eaa"
    ],
    "wof:name":"Wanyangxi",
    "wof:placetype":"locality"
},
  "geometry": {"coordinates":[111.0039,28.82153],"type":"Point"}
}