{
  "type": "Feature",
  "properties": {
    "gn:admin1_code":"25",
    "gn:asciiname":"Xisibu",
    "gn:country_code":"CN",
    "gn:dem":182,
    "gn:feature_class":"P",
    "gn:feature_code":"PPL",
    "gn:name":"Xisibu",
    "gn:population":0,
    "gn:timezone":"Asia/Shanghai",
    "iso:country":"CN",
    "name:zho_x_preferred":[
        "\u897f\u5bfa\u5821"
    ],
    "wof:name":"Xisibu",
    "wof:placetype":"locality"
},
  "geometry": {"coordinates":[118.322,35.6618],"type":"Point"}
}