{
  "type": "Feature",
  "properties": {
    "gn:admin1_code":"11.0",
    "gn:asciiname":"Biandan'ao",
    "gn:country_code":"CN",
    "gn:dem":313,
    "gn:feature_class":"P",
    "gn:feature_code":"PPL",
    "gn:name":"Biandan\u2019ao",
    "gn:population":0,
    "gn:timezone":"Asia/Shanghai",
    "iso:country":"CN",
    "name:und_x_variant":[
        "Biandan\u2019ao"
    ],
    "name:zho_x_preferred":[
        "\u6241\u62c5\u5773"
    ],
    "wof:name":"Biandan'ao",
    "wof:placetype":"locality"
},
  "geometry": {"coordinates":[111.61333,28.2969],"type":"Point"}
}