{
  "type": "Feature",
  "properties": {
    "gn:admin1_code":"32.0",
    "gn:asciiname":"Abi",
    "gn:country_code":"CN",
    "gn:dem":3653,
    "gn:feature_class":"P",
    "gn:feature_code":"PPL",
    "gn:name":"Abi",
    "gn:population":0,
    "gn:timezone":"Asia/Shanghai",
    "iso:country":"CN",
    "name:zho_x_preferred":[
        "\u963f\u6bd4"
    ],
    "wof:name":"Abi",
    "wof:placetype":"locality"
},
  "geometry": {"coordinates":[99.2251,32.2686],"type":"Point"}
}