{
  "type": "Feature",
  "properties": {
    "gn:admin1_code":"08",
    "gn:asciiname":"Ta-yu-shu",
    "gn:country_code":"CN",
    "gn:dem":136,
    "gn:feature_class":"P",
    "gn:feature_code":"PPL",
    "gn:name":"Ta-y\u00fc-shu",
    "gn:population":0,
    "gn:timezone":"Asia/Shanghai",
    "iso:country":"CN",
    "wof:name":"Ta-yu-shu",
    "wof:placetype":"locality"
},
  "geometry": {"coordinates":[126.33472,46.63361],"type":"Point"}
}