{
  "type": "Feature",
  "properties": {
    "gn:admin1_code":"7",
    "gn:asciiname":"Qili",
    "gn:country_code":"CN",
    "gn:dem":410,
    "gn:feature_class":"P",
    "gn:feature_code":"PPL",
    "gn:name":"Qili",
    "gn:population":0,
    "gn:timezone":"Asia/Shanghai",
    "iso:country":"CN",
    "name:und_x_variant":[
        "\u4e03\u91cc"
    ],
    "wof:name":"Qili",
    "wof:placetype":"locality"
},
  "geometry": {"coordinates":[116.24930000000001,25.44447000000001],"type":"Point"}
}