{
  "type": "Feature",
  "properties": {
    "gn:admin1_code":"18",
    "gn:asciiname":"Longhuichang",
    "gn:country_code":"CN",
    "gn:dem":1056,
    "gn:feature_class":"P",
    "gn:feature_code":"PPL",
    "gn:name":"Longhuichang",
    "gn:population":0,
    "gn:timezone":"Asia/Shanghai",
    "iso:country":"CN",
    "name:zho_x_preferred":[
        "\u9f99\u4f1a\u573a"
    ],
    "wof:name":"Longhuichang",
    "wof:placetype":"locality"
},
  "geometry": {"coordinates":[106.89100000000001,28.1607],"type":"Point"}
}