{
  "type": "Feature",
  "properties": {
    "gn:admin1_code":"3.0",
    "gn:asciiname":"Zhukeng",
    "gn:country_code":"CN",
    "gn:dem":287,
    "gn:feature_class":"P",
    "gn:feature_code":"PPL",
    "gn:name":"Zhukeng",
    "gn:population":0,
    "gn:timezone":"Asia/Shanghai",
    "iso:country":"CN",
    "name:und_x_variant":[
        "\u73e0\u5751"
    ],
    "wof:name":"Zhukeng",
    "wof:placetype":"locality"
},
  "geometry": {"coordinates":[115.68742,26.2932],"type":"Point"}
}