{
  "type": "Feature",
  "properties": {
    "gn:admin1_code":"26.0",
    "gn:asciiname":"Lingdicun",
    "gn:country_code":"CN",
    "gn:dem":540,
    "gn:feature_class":"P",
    "gn:feature_code":"PPL",
    "gn:name":"Lingdicun",
    "gn:population":0,
    "gn:timezone":"Asia/Shanghai",
    "iso:country":"CN",
    "name:und_x_variant":[
        "\u5cad\u5e95\u6751"
    ],
    "wof:name":"Lingdicun",
    "wof:placetype":"locality"
},
  "geometry": {"coordinates":[107.42610000000001,33.29838],"type":"Point"}
}