{
  "type": "Feature",
  "properties": {
    "gn:admin1_code":"18.0",
    "gn:asciiname":"Shidong",
    "gn:country_code":"CN",
    "gn:dem":1287,
    "gn:feature_class":"P",
    "gn:feature_code":"PPL",
    "gn:name":"Shidong",
    "gn:population":0,
    "gn:timezone":"Asia/Shanghai",
    "iso:country":"CN",
    "name:zho_x_preferred":[
        "\u77f3\u6d1e"
    ],
    "name:zho_x_variant":[
        "\u8bd7\u6d1e\u9547"
    ],
    "wof:name":"Shidong",
    "wof:placetype":"locality"
},
  "geometry": {"coordinates":[106.319,26.1426],"type":"Point"}
}