{
  "type": "Feature",
  "properties": {
    "gn:admin1_code":"20.0",
    "gn:asciiname":"Hongsheng Dadui Nongyedian",
    "gn:country_code":"CN",
    "gn:dem":728,
    "gn:feature_class":"P",
    "gn:feature_code":"PPL",
    "gn:name":"Hongsheng Dadui Nongyedian",
    "gn:population":0,
    "gn:timezone":"Asia/Shanghai",
    "iso:country":"CN",
    "name:zho_x_preferred":[
        "\u7ea2\u5347\u5927\u961f\u519c\u4e1a\u70b9"
    ],
    "wof:name":"Hongsheng Dadui Nongyedian",
    "wof:placetype":"locality"
},
  "geometry": {"coordinates":[121.49188999999998,49.53824],"type":"Point"}
}