{
  "type": "Feature",
  "properties": {
    "gn:admin1_code":"12.0",
    "gn:asciiname":"Jiebeitou",
    "gn:country_code":"CN",
    "gn:dem":70,
    "gn:feature_class":"P",
    "gn:feature_code":"PPL",
    "gn:name":"Jiebeitou",
    "gn:population":0,
    "gn:timezone":"Asia/Shanghai",
    "iso:country":"CN",
    "name:zho_x_preferred":[
        "\u754c\u7891\u5934"
    ],
    "wof:name":"Jiebeitou",
    "wof:placetype":"locality"
},
  "geometry": {"coordinates":[112.08588,31.71232],"type":"Point"}
}