{
  "type": "Feature",
  "properties": {
    "gn:admin1_code":"26.0",
    "gn:asciiname":"Xiwangzhai",
    "gn:country_code":"CN",
    "gn:dem":969,
    "gn:feature_class":"P",
    "gn:feature_code":"PPL",
    "gn:name":"Xiwangzhai",
    "gn:population":0,
    "gn:timezone":"Asia/Shanghai",
    "iso:country":"CN",
    "name:zho_x_preferred":[
        "\u897f\u738b\u5be8"
    ],
    "wof:name":"Xiwangzhai",
    "wof:placetype":"locality"
},
  "geometry": {"coordinates":[111.13858,39.20262],"type":"Point"}
}