{
  "type": "Feature",
  "properties": {
    "gn:admin1_code":"4.0",
    "gn:asciiname":"Maziyang",
    "gn:country_code":"CN",
    "gn:dem":7,
    "gn:feature_class":"P",
    "gn:feature_code":"PPL",
    "gn:name":"Maziyang",
    "gn:population":0,
    "gn:timezone":"Asia/Shanghai",
    "iso:country":"CN",
    "name:zho_x_preferred":[
        "Maziyang"
    ],
    "name:zho_x_variant":[
        "\u9a6c\u5b57\u6768"
    ],
    "wof:name":"Maziyang",
    "wof:placetype":"locality"
},
  "geometry": {"coordinates":[119.08359,33.33215],"type":"Point"}
}