{
  "type": "Feature",
  "properties": {
    "gn:admin1_code":"21.0",
    "gn:asciiname":"Dongmen",
    "gn:country_code":"CN",
    "gn:dem":1133,
    "gn:feature_class":"P",
    "gn:feature_code":"PPL",
    "gn:name":"Dongmen",
    "gn:population":0,
    "gn:timezone":"Asia/Shanghai",
    "iso:country":"CN",
    "name:ita_x_preferred":[
        "Dongmen"
    ],
    "name:zho_x_preferred":[
        "\u4e1c\u95e8"
    ],
    "wof:name":"Dongmen",
    "wof:placetype":"locality"
},
  "geometry": {"coordinates":[106.133,37.9328],"type":"Point"}
}