{
  "type": "Feature",
  "properties": {
    "gn:admin1_code":"19.0",
    "gn:asciiname":"Donggouli",
    "gn:country_code":"CN",
    "gn:dem":121,
    "gn:feature_class":"P",
    "gn:feature_code":"PPL",
    "gn:name":"Donggouli",
    "gn:population":0,
    "gn:timezone":"Asia/Shanghai",
    "iso:country":"CN",
    "name:zho_x_preferred":[
        "\u4e1c\u6c9f\u91cc"
    ],
    "wof:name":"Donggouli",
    "wof:placetype":"locality"
},
  "geometry": {"coordinates":[121.75700000000001,39.1545],"type":"Point"}
}