{
  "type": "Feature",
  "properties": {
    "gn:admin1_code":"5.0",
    "gn:asciiname":"Zixing",
    "gn:country_code":"CN",
    "gn:dem":52,
    "gn:feature_class":"P",
    "gn:feature_code":"PPL",
    "gn:name":"Zixing",
    "gn:population":0,
    "gn:timezone":"Asia/Shanghai",
    "iso:country":"CN",
    "name:und_x_variant":[
        "\u81ea\u5174"
    ],
    "wof:name":"Zixing",
    "wof:placetype":"locality"
},
  "geometry": {"coordinates":[130.42317,42.90194],"type":"Point"}
}