{
  "type": "Feature",
  "properties": {
    "gn:admin1_code":"1.0",
    "gn:asciiname":"Hujicun",
    "gn:country_code":"CN",
    "gn:dem":27,
    "gn:feature_class":"P",
    "gn:feature_code":"PPL",
    "gn:name":"Hujicun",
    "gn:population":0,
    "gn:timezone":"Asia/Shanghai",
    "iso:country":"CN",
    "name:zho_x_preferred":[
        "\u80e1\u96c6\u6751"
    ],
    "wof:name":"Hujicun",
    "wof:placetype":"locality"
},
  "geometry": {"coordinates":[117.39082999999999,33.83144],"type":"Point"}
}