{
  "type": "Feature",
  "properties": {
    "gn:admin1_code":"29.0",
    "gn:asciiname":"Hepotou",
    "gn:country_code":"CN",
    "gn:dem":1932,
    "gn:feature_class":"P",
    "gn:feature_code":"PPL",
    "gn:name":"Hepotou",
    "gn:population":0,
    "gn:timezone":"Asia/Shanghai",
    "iso:country":"CN",
    "name:zho_x_preferred":[
        "\u6cb3\u5761\u5934"
    ],
    "wof:name":"Hepotou",
    "wof:placetype":"locality"
},
  "geometry": {"coordinates":[99.3998,25.0786],"type":"Point"}
}