{
  "type": "Feature",
  "properties": {
    "gn:admin1_code":"13",
    "gn:asciiname":"Shaliangtou",
    "gn:country_code":"CN",
    "gn:dem":1047,
    "gn:feature_class":"P",
    "gn:feature_code":"PPL",
    "gn:name":"Shaliangtou",
    "gn:population":0,
    "gn:timezone":"Asia/Urumqi",
    "iso:country":"CN",
    "name:und_x_variant":[
        "\u6c99\u6881\u5934"
    ],
    "wof:name":"Shaliangtou",
    "wof:placetype":"locality"
},
  "geometry": {"coordinates":[86.74178000000001,42.17175],"type":"Point"}
}