{
  "type": "Feature",
  "properties": {
    "gn:admin1_code":"11.0",
    "gn:asciiname":"Liangjing",
    "gn:country_code":"CN",
    "gn:dem":462,
    "gn:feature_class":"P",
    "gn:feature_code":"PPL",
    "gn:name":"Liangjing",
    "gn:population":0,
    "gn:timezone":"Asia/Shanghai",
    "iso:country":"CN",
    "name:zho_x_preferred":[
        "Liangjing"
    ],
    "name:zho_x_variant":[
        "\u51c9\u4e95"
    ],
    "wof:name":"Liangjing",
    "wof:placetype":"locality"
},
  "geometry": {"coordinates":[111.28491,29.7632],"type":"Point"}
}