{
  "type": "Feature",
  "properties": {
    "gn:admin1_code":"14",
    "gn:asciiname":"Samcam",
    "gn:country_code":"CN",
    "gn:dem":3954,
    "gn:feature_class":"P",
    "gn:feature_code":"PPL",
    "gn:name":"Samcam",
    "gn:population":0,
    "gn:timezone":"Asia/Urumqi",
    "iso:country":"CN",
    "name:bod_x_preferred":[
        "\u0f66\u0f0b\u0f58\u0f5a\u0f58\u0f66"
    ],
    "wof:name":"Samcam",
    "wof:placetype":"locality"
},
  "geometry": {"coordinates":[90.71222,29.90115],"type":"Point"}
}