{
  "type": "Feature",
  "properties": {
    "gn:admin1_code":"19",
    "gn:asciiname":"Sitaizicun",
    "gn:country_code":"CN",
    "gn:dem":106,
    "gn:feature_class":"P",
    "gn:feature_code":"PPL",
    "gn:name":"Sitaizicun",
    "gn:population":0,
    "gn:timezone":"Asia/Shanghai",
    "iso:country":"CN",
    "name:und_x_variant":[
        "Sitaizi",
        "\u56db\u53f0\u5b50",
        "Sitaizicun"
    ],
    "name:zho_x_preferred":[
        "\u56db\u53f0\u5b50\u6751"
    ],
    "wof:name":"Sitaizicun",
    "wof:placetype":"locality"
},
  "geometry": {"coordinates":[123.98399000000001,40.4816],"type":"Point"}
}