{
  "type": "Feature",
  "properties": {
    "gn:admin1_code":"30",
    "gn:asciiname":"Reshuixu",
    "gn:country_code":"CN",
    "gn:dem":113,
    "gn:feature_class":"P",
    "gn:feature_code":"PPL",
    "gn:name":"Reshuixu",
    "gn:population":0,
    "gn:timezone":"Asia/Shanghai",
    "iso:country":"CN",
    "name:und_x_variant":[
        "\u70ed\u6c34\u5729"
    ],
    "wof:name":"Reshuixu",
    "wof:placetype":"locality"
},
  "geometry": {"coordinates":[115.10928,23.44928],"type":"Point"}
}