{
  "type": "Feature",
  "properties": {
    "gn:admin1_code":"13.0",
    "gn:asciiname":"K'a-ti-k'o",
    "gn:country_code":"CN",
    "gn:dem":834,
    "gn:feature_class":"P",
    "gn:feature_code":"PPL",
    "gn:name":"K\u2019a-ti-k\u2019o",
    "gn:population":0,
    "gn:timezone":"Asia/Urumqi",
    "iso:country":"CN",
    "wof:name":"K'a-ti-k'o",
    "wof:placetype":"locality"
},
  "geometry": {"coordinates":[88.16333,40.38361],"type":"Point"}
}