{
  "type": "Feature",
  "properties": {
    "gn:admin1_code":"3",
    "gn:asciiname":"Tangbeikengwei",
    "gn:country_code":"CN",
    "gn:dem":317,
    "gn:feature_class":"P",
    "gn:feature_code":"PPL",
    "gn:name":"Tangbeikengwei",
    "gn:population":0,
    "gn:timezone":"Asia/Shanghai",
    "iso:country":"CN",
    "name:zho_x_preferred":[
        "\u5858\u80cc\u5751\u5c3e"
    ],
    "wof:name":"Tangbeikengwei",
    "wof:placetype":"locality"
},
  "geometry": {"coordinates":[114.84999999999999,26.41],"type":"Point"}
}