{
  "type": "Feature",
  "properties": {
    "gn:admin1_code":"29.0",
    "gn:asciiname":"Tianguanfen",
    "gn:country_code":"CN",
    "gn:dem":2349,
    "gn:feature_class":"P",
    "gn:feature_code":"PPL",
    "gn:name":"Tianguanfen",
    "gn:population":0,
    "gn:timezone":"Asia/Shanghai",
    "iso:country":"CN",
    "name:zho_x_preferred":[
        "\u5929\u5b98\u575f"
    ],
    "wof:name":"Tianguanfen",
    "wof:placetype":"locality"
},
  "geometry": {"coordinates":[99.9616,26.3279],"type":"Point"}
}