{
  "type": "Feature",
  "properties": {
    "gn:admin1_code":"4.0",
    "gn:asciiname":"Zhongsanzaocun",
    "gn:country_code":"CN",
    "gn:dem":0,
    "gn:feature_class":"P",
    "gn:feature_code":"PPL",
    "gn:name":"Zhongsanzaocun",
    "gn:population":0,
    "gn:timezone":"Asia/Shanghai",
    "iso:country":"CN",
    "name:zho_x_preferred":[
        "\u4e2d\u4e09\u7076\u6751"
    ],
    "wof:name":"Zhongsanzaocun",
    "wof:placetype":"locality"
},
  "geometry": {"coordinates":[119.77533,33.89148],"type":"Point"}
}