{
  "type": "Feature",
  "properties": {
    "gn:admin1_code":"15.0",
    "gn:asciiname":"Baishitoujing",
    "gn:country_code":"CN",
    "gn:dem":1772,
    "gn:feature_class":"P",
    "gn:feature_code":"PPL",
    "gn:name":"Baishitoujing",
    "gn:population":0,
    "gn:timezone":"Asia/Shanghai",
    "iso:country":"CN",
    "name:zho_x_preferred":[
        "\u767d\u77f3\u5934\u4e95"
    ],
    "wof:name":"Baishitoujing",
    "wof:placetype":"locality"
},
  "geometry": {"coordinates":[103.17,37.6138],"type":"Point"}
}