{
  "type": "Feature",
  "properties": {
    "gn:admin1_code":"19.0",
    "gn:asciiname":"Sunzhangzi",
    "gn:country_code":"CN",
    "gn:dem":410,
    "gn:feature_class":"P",
    "gn:feature_code":"PPL",
    "gn:name":"Sunzhangzi",
    "gn:population":0,
    "gn:timezone":"Asia/Shanghai",
    "iso:country":"CN",
    "name:zho_x_preferred":[
        "\u5b59\u6756\u5b50"
    ],
    "wof:name":"Sunzhangzi",
    "wof:placetype":"locality"
},
  "geometry": {"coordinates":[120.2915,41.80774],"type":"Point"}
}