{
  "type": "Feature",
  "properties": {
    "gn:admin1_code":"24.0",
    "gn:asciiname":"Yuping",
    "gn:country_code":"CN",
    "gn:dem":1548,
    "gn:feature_class":"P",
    "gn:feature_code":"PPL",
    "gn:name":"Yuping",
    "gn:population":0,
    "gn:timezone":"Asia/Shanghai",
    "iso:country":"CN",
    "name:und_x_variant":[
        "\u6986\u576a"
    ],
    "wof:name":"Yuping",
    "wof:placetype":"locality"
},
  "geometry": {"coordinates":[112.63475,39.5859],"type":"Point"}
}