{
  "type": "Feature",
  "properties": {
    "gn:admin1_code":"10.0",
    "gn:asciiname":"Baqie",
    "gn:country_code":"CN",
    "gn:dem":66,
    "gn:feature_class":"P",
    "gn:feature_code":"PPL",
    "gn:name":"Baqie",
    "gn:population":0,
    "gn:timezone":"Asia/Shanghai",
    "iso:country":"CN",
    "name:und_x_variant":[
        "\u62d4\u8304"
    ],
    "wof:name":"Baqie",
    "wof:placetype":"locality"
},
  "geometry": {"coordinates":[114.99890000000001,38.65457],"type":"Point"}
}