{
  "type": "Feature",
  "properties": {
    "gn:admin1_code":"1.0",
    "gn:asciiname":"Yongxingcun",
    "gn:country_code":"CN",
    "gn:dem":26,
    "gn:feature_class":"P",
    "gn:feature_code":"PPL",
    "gn:name":"Yongxingcun",
    "gn:population":0,
    "gn:timezone":"Asia/Shanghai",
    "iso:country":"CN",
    "name:zho_x_preferred":[
        "\u6c38\u5e78\u6751"
    ],
    "wof:name":"Yongxingcun",
    "wof:placetype":"locality"
},
  "geometry": {"coordinates":[116.48979,32.90724],"type":"Point"}
}