{
  "type": "Feature",
  "properties": {
    "gn:admin1_code":"4.0",
    "gn:asciiname":"Yetian",
    "gn:country_code":"CN",
    "gn:dem":9,
    "gn:feature_class":"P",
    "gn:feature_code":"PPL",
    "gn:name":"Yetian",
    "gn:population":0,
    "gn:timezone":"Asia/Shanghai",
    "iso:country":"CN",
    "name:zho_x_preferred":[
        "\u91ce\u7530"
    ],
    "wof:name":"Yetian",
    "wof:placetype":"locality"
},
  "geometry": {"coordinates":[119.6414,31.6812],"type":"Point"}
}