{
  "type": "Feature",
  "properties": {
    "gn:admin1_code":"16.0",
    "gn:asciiname":"Banneicun",
    "gn:country_code":"CN",
    "gn:dem":199,
    "gn:feature_class":"P",
    "gn:feature_code":"PPL",
    "gn:name":"Banneicun",
    "gn:population":0,
    "gn:timezone":"Asia/Shanghai",
    "iso:country":"CN",
    "name:zho_x_preferred":[
        "\u677f\u5185\u6751"
    ],
    "wof:name":"Banneicun",
    "wof:placetype":"locality"
},
  "geometry": {"coordinates":[108.58199999999999,23.7861],"type":"Point"}
}