{
  "type": "Feature",
  "properties": {
    "gn:admin1_code":"4.0",
    "gn:asciiname":"Sanjiu Qizu",
    "gn:country_code":"CN",
    "gn:dem":4,
    "gn:feature_class":"P",
    "gn:feature_code":"PPL",
    "gn:name":"Sanjiu Qizu",
    "gn:population":0,
    "gn:timezone":"Asia/Shanghai",
    "iso:country":"CN",
    "name:zho_x_preferred":[
        "\u4e09\u4e5d\u4e03\u7ec4"
    ],
    "wof:name":"Sanjiu Qizu",
    "wof:placetype":"locality"
},
  "geometry": {"coordinates":[120.49187000000001,32.72619],"type":"Point"}
}