{
  "type": "Feature",
  "properties": {
    "gn:admin1_code":"12.0",
    "gn:asciiname":"Sidui",
    "gn:country_code":"CN",
    "gn:dem":22,
    "gn:feature_class":"P",
    "gn:feature_code":"PPLF",
    "gn:name":"Sidui",
    "gn:population":0,
    "gn:timezone":"Asia/Shanghai",
    "iso:country":"CN",
    "name:und_x_variant":[
        "\u56db\u961f"
    ],
    "wof:name":"Sidui",
    "wof:placetype":"locality"
},
  "geometry": {"coordinates":[114.19462,30.64716],"type":"Point"}
}