{
  "type": "Feature",
  "properties": {
    "gn:admin1_code":"14.0",
    "gn:asciiname":"Paiga",
    "gn:country_code":"CN",
    "gn:dem":4167,
    "gn:feature_class":"P",
    "gn:feature_code":"PPL",
    "gn:name":"Paiga",
    "gn:population":0,
    "gn:timezone":"Asia/Urumqi",
    "iso:country":"CN",
    "name:zho_x_preferred":[
        "\u6392\u560e"
    ],
    "wof:name":"Paiga",
    "wof:placetype":"locality"
},
  "geometry": {"coordinates":[91.15225,29.08727],"type":"Point"}
}