{
  "type": "Feature",
  "properties": {
    "gn:admin1_code":"19.0",
    "gn:asciiname":"Chaogouya",
    "gn:country_code":"CN",
    "gn:dem":9,
    "gn:feature_class":"P",
    "gn:feature_code":"PPL",
    "gn:name":"Chaogouya",
    "gn:population":0,
    "gn:timezone":"Asia/Shanghai",
    "iso:country":"CN",
    "name:und_x_variant":[
        "\u6f6e\u6c9f\u5d16"
    ],
    "name:zho_x_preferred":[
        "\u6f6e\u6c9f\u5d16"
    ],
    "wof:name":"Chaogouya",
    "wof:placetype":"locality"
},
  "geometry": {"coordinates":[123.41486999999999,39.80133],"type":"Point"}
}