{
  "type": "Feature",
  "properties": {
    "gn:admin1_code":"10.0",
    "gn:asciiname":"Zhangliuzhuang",
    "gn:cc2":"CN",
    "gn:country_code":"CN",
    "gn:dem":3,
    "gn:feature_class":"P",
    "gn:feature_code":"PPL",
    "gn:name":"Zhangliuzhuang",
    "gn:population":0,
    "gn:timezone":"Asia/Shanghai",
    "iso:country":"CN",
    "name:und_x_variant":[
        "Chang-liu-chuang",
        "Changliu",
        "Zhangliuzhuang"
    ],
    "name:zho_x_preferred":[
        "\u5f20\u516d\u5e84"
    ],
    "wof:name":"Zhangliuzhuang",
    "wof:placetype":"locality"
},
  "geometry": {"coordinates":[117.98333,39.53333],"type":"Point"}
}