{
  "type": "Feature",
  "properties": {
    "gn:admin1_code":"02",
    "gn:asciiname":"Wuyantou",
    "gn:cc2":"CN",
    "gn:country_code":"CN",
    "gn:dem":11,
    "gn:feature_class":"P",
    "gn:feature_code":"PPL",
    "gn:name":"Wuyantou",
    "gn:population":0,
    "gn:timezone":"Asia/Shanghai",
    "iso:country":"CN",
    "name:und_x_variant":[
        "Wu-yen-t\u2019ou",
        "Wuyantou"
    ],
    "wof:name":"Wuyantou",
    "wof:placetype":"locality"
},
  "geometry": {"coordinates":[122.15278000000001,30.17139],"type":"Point"}
}