{
  "type": "Feature",
  "properties": {
    "gn:admin1_code":"2.0",
    "gn:asciiname":"Gongnongting",
    "gn:country_code":"CN",
    "gn:dem":69,
    "gn:feature_class":"P",
    "gn:feature_code":"PPLF",
    "gn:name":"Gongnongting",
    "gn:population":0,
    "gn:timezone":"Asia/Shanghai",
    "iso:country":"CN",
    "name:und_x_variant":[
        "\u5de5\u519c\u4ead"
    ],
    "name:zho_x_preferred":[
        "Gongnongting"
    ],
    "wof:name":"Gongnongting",
    "wof:placetype":"locality"
},
  "geometry": {"coordinates":[119.69265,30.26333],"type":"Point"}
}