{
  "type": "Feature",
  "properties": {
    "gn:admin1_code":"32.0",
    "gn:asciiname":"Momozhai",
    "gn:country_code":"CN",
    "gn:dem":3083,
    "gn:feature_class":"P",
    "gn:feature_code":"PPL",
    "gn:name":"Momozhai",
    "gn:population":0,
    "gn:timezone":"Asia/Shanghai",
    "iso:country":"CN",
    "name:zho_x_preferred":[
        "\u998d\u998d\u5be8"
    ],
    "wof:name":"Momozhai",
    "wof:placetype":"locality"
},
  "geometry": {"coordinates":[102.446,31.1157],"type":"Point"}
}