{
  "type": "Feature",
  "properties": {
    "gn:admin1_code":"09",
    "gn:asciiname":"Pingle",
    "gn:cc2":"CN",
    "gn:country_code":"CN",
    "gn:dem":137,
    "gn:feature_class":"P",
    "gn:feature_code":"PPL",
    "gn:name":"Pingle",
    "gn:population":0,
    "gn:timezone":"Asia/Shanghai",
    "iso:country":"CN",
    "name:und_x_variant":[
        "P\u2019ing-lo",
        "Pingle"
    ],
    "wof:name":"Pingle",
    "wof:placetype":"locality"
},
  "geometry": {"coordinates":[112.58278,34.74667],"type":"Point"}
}