{
  "type": "Feature",
  "properties": {
    "gn:admin1_code":"29.0",
    "gn:asciiname":"Yangkancao",
    "gn:country_code":"CN",
    "gn:dem":3501,
    "gn:feature_class":"P",
    "gn:feature_code":"PPL",
    "gn:name":"Yangkancao",
    "gn:population":0,
    "gn:timezone":"Asia/Shanghai",
    "iso:country":"CN",
    "name:zho_x_preferred":[
        "\u7f8a\u69db\u69fd"
    ],
    "wof:name":"Yangkancao",
    "wof:placetype":"locality"
},
  "geometry": {"coordinates":[100.62,27.5354],"type":"Point"}
}