{
  "type": "Feature",
  "properties": {
    "gn:admin1_code":"32.0",
    "gn:asciiname":"Shuiyinggong",
    "gn:country_code":"CN",
    "gn:dem":452,
    "gn:feature_class":"P",
    "gn:feature_code":"PPL",
    "gn:name":"Shuiyinggong",
    "gn:population":0,
    "gn:timezone":"Asia/Shanghai",
    "iso:country":"CN",
    "name:zho_x_preferred":[
        "\u6c34\u8425\u5bab"
    ],
    "wof:name":"Shuiyinggong",
    "wof:placetype":"locality"
},
  "geometry": {"coordinates":[106.20591,32.16902],"type":"Point"}
}