{
  "type": "Feature",
  "properties": {
    "gn:admin1_code":"33.0",
    "gn:asciiname":"Yubei",
    "gn:country_code":"CN",
    "gn:dem":836,
    "gn:feature_class":"P",
    "gn:feature_code":"PPL",
    "gn:name":"Yubei",
    "gn:population":0,
    "gn:timezone":"Asia/Shanghai",
    "iso:country":"CN",
    "name:zho_x_preferred":[
        "\u6e14\u5317"
    ],
    "wof:name":"Yubei",
    "wof:placetype":"locality"
},
  "geometry": {"coordinates":[108.35178000000001,31.11228],"type":"Point"}
}