{
  "type": "Feature",
  "properties": {
    "gn:admin1_code":"7",
    "gn:asciiname":"Hefeng",
    "gn:country_code":"CN",
    "gn:dem":949,
    "gn:feature_class":"P",
    "gn:feature_code":"PPL",
    "gn:name":"Hefeng",
    "gn:population":0,
    "gn:timezone":"Asia/Shanghai",
    "iso:country":"CN",
    "name:zho_x_preferred":[
        "\u548c\u4e30"
    ],
    "wof:name":"Hefeng",
    "wof:placetype":"locality"
},
  "geometry": {"coordinates":[117.34913,25.04891],"type":"Point"}
}