{
  "type": "Feature",
  "properties": {
    "gn:admin1_code":"26.0",
    "gn:asciiname":"Gaojiagoucun",
    "gn:country_code":"CN",
    "gn:dem":1052,
    "gn:feature_class":"P",
    "gn:feature_code":"PPL",
    "gn:name":"Gaojiagoucun",
    "gn:population":0,
    "gn:timezone":"Asia/Shanghai",
    "iso:country":"CN",
    "name:zho_x_preferred":[
        "\u9ad8\u5bb6\u6c9f\u6751"
    ],
    "wof:name":"Gaojiagoucun",
    "wof:placetype":"locality"
},
  "geometry": {"coordinates":[109.50736999999999,36.64983],"type":"Point"}
}