{
  "type": "Feature",
  "properties": {
    "gn:admin1_code":"29.0",
    "gn:asciiname":"Dafeige",
    "gn:country_code":"CN",
    "gn:dem":1821,
    "gn:feature_class":"P",
    "gn:feature_code":"PPL",
    "gn:name":"Dafeige",
    "gn:population":0,
    "gn:timezone":"Asia/Shanghai",
    "iso:country":"CN",
    "name:zho_x_preferred":[
        "\u5927\u975e\u683c"
    ],
    "wof:name":"Dafeige",
    "wof:placetype":"locality"
},
  "geometry": {"coordinates":[104.22799999999999,24.9717],"type":"Point"}
}