{
  "type": "Feature",
  "properties": {
    "gn:admin1_code":"5.0",
    "gn:asciiname":"Loushang",
    "gn:country_code":"CN",
    "gn:dem":368,
    "gn:feature_class":"P",
    "gn:feature_code":"PPL",
    "gn:name":"Loushang",
    "gn:population":0,
    "gn:timezone":"Asia/Shanghai",
    "iso:country":"CN",
    "name:zho_x_preferred":[
        "\u697c\u4e0a"
    ],
    "wof:name":"Loushang",
    "wof:placetype":"locality"
},
  "geometry": {"coordinates":[128.55159,43.75703],"type":"Point"}
}