{
  "type": "Feature",
  "properties": {
    "gn:admin1_code":"4.0",
    "gn:asciiname":"Zhonggangzu",
    "gn:country_code":"CN",
    "gn:dem":6,
    "gn:feature_class":"P",
    "gn:feature_code":"PPL",
    "gn:name":"Zhonggangzu",
    "gn:population":0,
    "gn:timezone":"Asia/Shanghai",
    "iso:country":"CN",
    "name:zho_x_preferred":[
        "\u4e2d\u6e2f\u7ec4"
    ],
    "wof:name":"Zhonggangzu",
    "wof:placetype":"locality"
},
  "geometry": {"coordinates":[120.26358999999999,32.35546],"type":"Point"}
}