{
  "type": "Feature",
  "properties": {
    "gn:admin1_code":"11.0",
    "gn:asciiname":"Baimianshi",
    "gn:country_code":"CN",
    "gn:dem":1015,
    "gn:feature_class":"P",
    "gn:feature_code":"PPL",
    "gn:name":"Baimianshi",
    "gn:population":0,
    "gn:timezone":"Asia/Shanghai",
    "iso:country":"CN",
    "name:zho_x_preferred":[
        "\u767d\u9762\u77f3"
    ],
    "wof:name":"Baimianshi",
    "wof:placetype":"locality"
},
  "geometry": {"coordinates":[113.72808000000001,26.14069],"type":"Point"}
}