{
  "type": "Feature",
  "properties": {
    "gn:admin1_code":"05",
    "gn:asciiname":"Badaogou",
    "gn:country_code":"CN",
    "gn:dem":445,
    "gn:feature_class":"P",
    "gn:feature_code":"PPLA4",
    "gn:name":"Badaogou",
    "gn:population":0,
    "gn:timezone":"Asia/Shanghai",
    "iso:country":"CN",
    "name:und_x_variant":[
        "\u516b\u9053\u6c9f",
        "Badaogou Zhen",
        "\u516b\u9053\u6c9f\u9547"
    ],
    "wof:name":"Badaogou",
    "wof:placetype":"locality"
},
  "geometry": {"coordinates":[127.26466000000001,41.51726],"type":"Point"}
}