{
  "type": "Feature",
  "properties": {
    "gn:admin1_code":"29.0",
    "gn:asciiname":"Gege",
    "gn:country_code":"CN",
    "gn:dem":1267,
    "gn:feature_class":"P",
    "gn:feature_code":"PPL",
    "gn:name":"Gege",
    "gn:population":0,
    "gn:timezone":"Asia/Shanghai",
    "iso:country":"CN",
    "name:ceb_x_preferred":[
        "Gege"
    ],
    "name:deu_x_preferred":[
        "Gege"
    ],
    "name:swe_x_preferred":[
        "Gege"
    ],
    "name:zho_x_preferred":[
        "\u54e5\u683c"
    ],
    "wof:name":"Gege",
    "wof:placetype":"locality"
},
  "geometry": {"coordinates":[99.6131,22.5387],"type":"Point"}
}