{
  "type": "Feature",
  "properties": {
    "gn:admin1_code":"29.0",
    "gn:asciiname":"Dalongtan Xiacun",
    "gn:country_code":"CN",
    "gn:dem":1777,
    "gn:feature_class":"P",
    "gn:feature_code":"PPL",
    "gn:name":"Dalongtan Xiacun",
    "gn:population":0,
    "gn:timezone":"Asia/Shanghai",
    "iso:country":"CN",
    "name:zho_x_preferred":[
        "\u5927\u9f99\u6f6d\u4e0b\u6751"
    ],
    "wof:name":"Dalongtan Xiacun",
    "wof:placetype":"locality"
},
  "geometry": {"coordinates":[100.74299999999999,25.2578],"type":"Point"}
}