{
  "type": "Feature",
  "properties": {
    "gn:admin1_code":"29.0",
    "gn:asciiname":"Muhuazhai",
    "gn:country_code":"CN",
    "gn:dem":1564,
    "gn:feature_class":"P",
    "gn:feature_code":"PPL",
    "gn:name":"Muhuazhai",
    "gn:population":0,
    "gn:timezone":"Asia/Shanghai",
    "iso:country":"CN",
    "name:zho_x_preferred":[
        "\u6728\u82b1\u5be8"
    ],
    "wof:name":"Muhuazhai",
    "wof:placetype":"locality"
},
  "geometry": {"coordinates":[101.014,23.3057],"type":"Point"}
}