{
  "type": "Feature",
  "properties": {
    "gn:admin1_code":"11.0",
    "gn:asciiname":"Hesuitian",
    "gn:country_code":"CN",
    "gn:dem":664,
    "gn:feature_class":"P",
    "gn:feature_code":"PPL",
    "gn:name":"Hesuitian",
    "gn:population":0,
    "gn:timezone":"Asia/Shanghai",
    "iso:country":"CN",
    "name:zho_x_preferred":[
        "\u79be\u7a57\u7530"
    ],
    "wof:name":"Hesuitian",
    "wof:placetype":"locality"
},
  "geometry": {"coordinates":[110.30707,26.83226],"type":"Point"}
}