{
  "type": "Feature",
  "properties": {
    "gn:admin1_code":"29.0",
    "gn:asciiname":"Moshijiang",
    "gn:country_code":"CN",
    "gn:dem":1636,
    "gn:feature_class":"P",
    "gn:feature_code":"PPL",
    "gn:name":"Moshijiang",
    "gn:population":0,
    "gn:timezone":"Asia/Shanghai",
    "iso:country":"CN",
    "name:zho_x_preferred":[
        "\u78e8\u77f3\u6c5f"
    ],
    "wof:name":"Moshijiang",
    "wof:placetype":"locality"
},
  "geometry": {"coordinates":[101.129,25.843],"type":"Point"}
}