{
  "type": "Feature",
  "properties": {
    "gn:admin1_code":"4.0",
    "gn:asciiname":"Chaofucun",
    "gn:country_code":"CN",
    "gn:dem":5,
    "gn:feature_class":"P",
    "gn:feature_code":"PPL",
    "gn:name":"Chaofucun",
    "gn:population":0,
    "gn:timezone":"Asia/Shanghai",
    "iso:country":"CN",
    "name:zho_x_preferred":[
        "\u671d\u798f\u6751"
    ],
    "wof:name":"Chaofucun",
    "wof:placetype":"locality"
},
  "geometry": {"coordinates":[120.69311999999999,32.66827],"type":"Point"}
}