{
  "type": "Feature",
  "properties": {
    "gn:admin1_code":"24.0",
    "gn:asciiname":"Beiliuyao",
    "gn:country_code":"CN",
    "gn:dem":1300,
    "gn:feature_class":"P",
    "gn:feature_code":"PPL",
    "gn:name":"Beiliuyao",
    "gn:population":0,
    "gn:timezone":"Asia/Shanghai",
    "iso:country":"CN",
    "name:zho_x_preferred":[
        "\u5317\u5218\u7a91"
    ],
    "wof:name":"Beiliuyao",
    "wof:placetype":"locality"
},
  "geometry": {"coordinates":[112.92576,40.33047],"type":"Point"}
}