{
  "type": "Feature",
  "properties": {
    "gn:admin1_code":"30.0",
    "gn:asciiname":"Jichangping",
    "gn:country_code":"CN",
    "gn:dem":364,
    "gn:feature_class":"P",
    "gn:feature_code":"PPL",
    "gn:name":"Jichangping",
    "gn:population":0,
    "gn:timezone":"Asia/Urumqi",
    "iso:country":"CN",
    "name:zho_x_preferred":[
        "\u9e21\u957f\u576a"
    ],
    "wof:name":"Jichangping",
    "wof:placetype":"locality"
},
  "geometry": {"coordinates":[110.82447999999999,22.39462],"type":"Point"}
}