{
  "type": "Feature",
  "properties": {
    "gn:admin1_code":"12.0",
    "gn:asciiname":"Shayanwan",
    "gn:country_code":"CN",
    "gn:dem":227,
    "gn:feature_class":"P",
    "gn:feature_code":"PPL",
    "gn:name":"Shayanwan",
    "gn:population":0,
    "gn:timezone":"Asia/Shanghai",
    "iso:country":"CN",
    "name:zho_x_preferred":[
        "\u6c99\u5830\u6e7e"
    ],
    "wof:name":"Shayanwan",
    "wof:placetype":"locality"
},
  "geometry": {"coordinates":[111.93603,31.20196],"type":"Point"}
}