{
  "type": "Feature",
  "properties": {
    "gn:admin1_code":"29.0",
    "gn:asciiname":"Shuiyinshui",
    "gn:country_code":"CN",
    "gn:dem":1608,
    "gn:feature_class":"P",
    "gn:feature_code":"PPL",
    "gn:name":"Shuiyinshui",
    "gn:population":0,
    "gn:timezone":"Asia/Shanghai",
    "iso:country":"CN",
    "name:zho_x_preferred":[
        "\u6c34\u94f6\u6c34"
    ],
    "wof:name":"Shuiyinshui",
    "wof:placetype":"locality"
},
  "geometry": {"coordinates":[99.0866,24.6709],"type":"Point"}
}