{
  "type": "Feature",
  "properties": {
    "gn:admin1_code":"19.0",
    "gn:asciiname":"Dongnaodehai",
    "gn:country_code":"CN",
    "gn:dem":201,
    "gn:feature_class":"P",
    "gn:feature_code":"PPL",
    "gn:name":"Dongnaodehai",
    "gn:population":0,
    "gn:timezone":"Asia/Shanghai",
    "iso:country":"CN",
    "name:zho_x_preferred":[
        "\u4e1c\u95f9\u5fb7\u6d77"
    ],
    "wof:name":"Dongnaodehai",
    "wof:placetype":"locality"
},
  "geometry": {"coordinates":[122.17026,42.68301],"type":"Point"}
}