{
  "type": "Feature",
  "properties": {
    "gn:admin1_code":"31.0",
    "gn:asciiname":"Guannancun",
    "gn:country_code":"CN",
    "gn:dem":33,
    "gn:feature_class":"P",
    "gn:feature_code":"PPL",
    "gn:name":"Guannancun",
    "gn:population":0,
    "gn:timezone":"Asia/Shanghai",
    "iso:country":"CN",
    "name:und_x_variant":[
        "Guannan",
        "Kuan-nan"
    ],
    "name:zho_x_preferred":[
        "\u51a0\u5357\u6751"
    ],
    "name:zho_x_variant":[
        "\u51a0\u5357"
    ],
    "wof:name":"Guannancun",
    "wof:placetype":"locality"
},
  "geometry": {"coordinates":[110.774,19.4839],"type":"Point"}
}