{
  "type": "Feature",
  "properties": {
    "gn:admin1_code":"32.0",
    "gn:asciiname":"Eyi",
    "gn:country_code":"CN",
    "gn:dem":3527,
    "gn:feature_class":"P",
    "gn:feature_code":"PPL",
    "gn:name":"Eyi",
    "gn:population":0,
    "gn:timezone":"Asia/Shanghai",
    "iso:country":"CN",
    "name:zho_x_preferred":[
        "\u4fc4\u4f9d"
    ],
    "wof:name":"Eyi",
    "wof:placetype":"locality"
},
  "geometry": {"coordinates":[101.236,31.8172],"type":"Point"}
}