{
  "type": "Feature",
  "properties": {
    "gn:admin1_code":"12.0",
    "gn:asciiname":"Dongjiachong",
    "gn:country_code":"CN",
    "gn:dem":1041,
    "gn:feature_class":"P",
    "gn:feature_code":"PPL",
    "gn:name":"Dongjiachong",
    "gn:population":0,
    "gn:timezone":"Asia/Shanghai",
    "iso:country":"CN",
    "name:zho_x_preferred":[
        "\u8463\u5bb6\u51b2"
    ],
    "wof:name":"Dongjiachong",
    "wof:placetype":"locality"
},
  "geometry": {"coordinates":[110.60399,31.06161],"type":"Point"}
}