{
  "type": "Feature",
  "properties": {
    "gn:admin1_code":"10",
    "gn:asciiname":"Bashihan",
    "gn:country_code":"CN",
    "gn:dem":327,
    "gn:feature_class":"P",
    "gn:feature_code":"PPL",
    "gn:name":"Bashihan",
    "gn:population":0,
    "gn:timezone":"Asia/Shanghai",
    "iso:country":"CN",
    "name:zho_x_preferred":[
        "\u516b\u4ec0\u6c57"
    ],
    "wof:name":"Bashihan",
    "wof:placetype":"locality"
},
  "geometry": {"coordinates":[117.07959,40.8077],"type":"Point"}
}