{
  "type": "Feature",
  "properties": {
    "gn:admin1_code":"25",
    "gn:asciiname":"Beiloucun",
    "gn:country_code":"CN",
    "gn:dem":184,
    "gn:feature_class":"P",
    "gn:feature_code":"PPL",
    "gn:name":"Beiloucun",
    "gn:population":0,
    "gn:timezone":"Asia/Shanghai",
    "iso:country":"CN",
    "name:und_x_variant":[
        "Beilou",
        "Beiloucun"
    ],
    "name:zho_x_preferred":[
        "\u5317\u697c"
    ],
    "name:zho_x_variant":[
        "\u5317\u697c\u6751"
    ],
    "wof:name":"Beiloucun",
    "wof:placetype":"locality"
},
  "geometry": {"coordinates":[118.125,35.78],"type":"Point"}
}