{
  "type": "Feature",
  "properties": {
    "gn:admin1_code":"3.0",
    "gn:asciiname":"Xikeng Jiangjia",
    "gn:country_code":"CN",
    "gn:dem":111,
    "gn:feature_class":"P",
    "gn:feature_code":"PPL",
    "gn:name":"Xikeng Jiangjia",
    "gn:population":0,
    "gn:timezone":"Asia/Shanghai",
    "iso:country":"CN",
    "name:zho_x_preferred":[
        "\u897f\u5751\u6c5f\u5bb6"
    ],
    "wof:name":"Xikeng Jiangjia",
    "wof:placetype":"locality"
},
  "geometry": {"coordinates":[117.37869000000001,28.17418],"type":"Point"}
}