{
  "type": "Feature",
  "properties": {
    "gn:admin1_code":"10",
    "gn:asciiname":"Chaoyangshan",
    "gn:country_code":"CN",
    "gn:dem":520,
    "gn:feature_class":"P",
    "gn:feature_code":"PPL",
    "gn:name":"Chaoyangshan",
    "gn:population":0,
    "gn:timezone":"Asia/Shanghai",
    "iso:country":"CN",
    "name:zho_x_preferred":[
        "\u671d\u9633\u5c71"
    ],
    "wof:name":"Chaoyangshan",
    "wof:placetype":"locality"
},
  "geometry": {"coordinates":[118.81234000000001,40.63896],"type":"Point"}
}