{
  "type": "Feature",
  "properties": {
    "gn:admin1_code":"8.0",
    "gn:asciiname":"Lijiashaoguo",
    "gn:country_code":"CN",
    "gn:dem":176,
    "gn:feature_class":"P",
    "gn:feature_code":"PPL",
    "gn:name":"Lijiashaoguo",
    "gn:population":0,
    "gn:timezone":"Asia/Shanghai",
    "iso:country":"CN",
    "name:zho_x_preferred":[
        "\u674e\u5bb6\u70e7\u9505"
    ],
    "wof:name":"Lijiashaoguo",
    "wof:placetype":"locality"
},
  "geometry": {"coordinates":[125.87152,46.56207],"type":"Point"}
}