{
  "type": "Feature",
  "properties": {
    "gn:admin1_code":"19.0",
    "gn:asciiname":"Haikou",
    "gn:country_code":"CN",
    "gn:dem":17,
    "gn:feature_class":"P",
    "gn:feature_code":"PPL",
    "gn:name":"Haikou",
    "gn:population":0,
    "gn:timezone":"Asia/Shanghai",
    "iso:country":"CN",
    "name:und_x_variant":[
        "\u6d77\u53e3"
    ],
    "name:zho_x_preferred":[
        "\u6d77\u53e3"
    ],
    "wof:name":"Haikou",
    "wof:placetype":"locality"
},
  "geometry": {"coordinates":[120.79956,40.61418],"type":"Point"}
}