{
  "type": "Feature",
  "properties": {
    "gn:admin1_code":"11.0",
    "gn:asciiname":"Dianpeng",
    "gn:country_code":"CN",
    "gn:dem":475,
    "gn:feature_class":"P",
    "gn:feature_code":"PPL",
    "gn:name":"Dianpeng",
    "gn:population":0,
    "gn:timezone":"Asia/Shanghai",
    "iso:country":"CN",
    "name:zho_x_preferred":[
        "\u975b\u68da"
    ],
    "wof:name":"Dianpeng",
    "wof:placetype":"locality"
},
  "geometry": {"coordinates":[109.2526,28.62041],"type":"Point"}
}