{
  "type": "Feature",
  "properties": {
    "gn:admin1_code":"30.0",
    "gn:asciiname":"Neihu",
    "gn:country_code":"CN",
    "gn:dem":11,
    "gn:feature_class":"P",
    "gn:feature_code":"PPLA4",
    "gn:name":"Neihu",
    "gn:population":0,
    "gn:timezone":"Asia/Shanghai",
    "iso:country":"CN",
    "name:fas_x_preferred":[
        "\u0646\u06cc\u0647\u0648"
    ],
    "name:und_x_variant":[
        "Neihu Zhen"
    ],
    "name:zho_x_preferred":[
        "\u5185\u6e56"
    ],
    "name:zho_x_variant":[
        "\u5185\u6e56\u9547"
    ],
    "wof:name":"Neihu",
    "wof:placetype":"locality"
},
  "geometry": {"coordinates":[115.82402999999999,22.97882],"type":"Point"}
}