{
  "type": "Feature",
  "properties": {
    "gn:admin1_code":"11.0",
    "gn:asciiname":"Xiaqingshui",
    "gn:country_code":"CN",
    "gn:dem":317,
    "gn:feature_class":"P",
    "gn:feature_code":"PPL",
    "gn:name":"Xiaqingshui",
    "gn:population":0,
    "gn:timezone":"Asia/Shanghai",
    "iso:country":"CN",
    "name:zho_x_preferred":[
        "\u4e0b\u6e05\u6c34"
    ],
    "wof:name":"Xiaqingshui",
    "wof:placetype":"locality"
},
  "geometry": {"coordinates":[112.39824,25.46357],"type":"Point"}
}