{
  "type": "Feature",
  "properties": {
    "gn:admin1_code":"1.0",
    "gn:asciiname":"Zouguaicun",
    "gn:country_code":"CN",
    "gn:dem":97,
    "gn:feature_class":"P",
    "gn:feature_code":"PPL",
    "gn:name":"Zouguaicun",
    "gn:population":0,
    "gn:timezone":"Asia/Shanghai",
    "iso:country":"CN",
    "name:zho_x_preferred":[
        "\u90b9\u62d0\u6751"
    ],
    "wof:name":"Zouguaicun",
    "wof:placetype":"locality"
},
  "geometry": {"coordinates":[116.45353,31.55329],"type":"Point"}
}