{
  "type": "Feature",
  "properties": {
    "gn:admin1_code":"3.0",
    "gn:asciiname":"Raoyuan",
    "gn:country_code":"CN",
    "gn:dem":71,
    "gn:feature_class":"P",
    "gn:feature_code":"PPL",
    "gn:name":"Raoyuan",
    "gn:population":0,
    "gn:timezone":"Asia/Shanghai",
    "iso:country":"CN",
    "name:und_x_variant":[
        "\u9976\u6e90"
    ],
    "wof:name":"Raoyuan",
    "wof:placetype":"locality"
},
  "geometry": {"coordinates":[115.15188999999999,26.95957000000001],"type":"Point"}
}