{
  "type": "Feature",
  "properties": {
    "gn:admin1_code":"12",
    "gn:asciiname":"Dengcun",
    "gn:country_code":"CN",
    "gn:dem":876,
    "gn:feature_class":"P",
    "gn:feature_code":"PPL",
    "gn:name":"Dengcun",
    "gn:population":0,
    "gn:timezone":"Asia/Shanghai",
    "iso:country":"CN",
    "wof:name":"Dengcun",
    "wof:placetype":"locality"
},
  "geometry": {"coordinates":[110.98333,30.96667],"type":"Point"}
}