{
  "type": "Feature",
  "properties": {
    "gn:admin1_code":"29.0",
    "gn:asciiname":"Jiaozishan",
    "gn:country_code":"CN",
    "gn:dem":2093,
    "gn:feature_class":"P",
    "gn:feature_code":"PPL",
    "gn:name":"Jiaozishan",
    "gn:population":0,
    "gn:timezone":"Asia/Shanghai",
    "iso:country":"CN",
    "name:zho_x_preferred":[
        "\u8f7f\u5b50\u5c71"
    ],
    "wof:name":"Jiaozishan",
    "wof:placetype":"locality"
},
  "geometry": {"coordinates":[103.712,25.3812],"type":"Point"}
}