{
  "type": "Feature",
  "properties": {
    "gn:admin1_code":"4.0",
    "gn:asciiname":"Jijiashe",
    "gn:country_code":"CN",
    "gn:dem":2,
    "gn:feature_class":"P",
    "gn:feature_code":"PPL",
    "gn:name":"Jijiashe",
    "gn:population":0,
    "gn:timezone":"Asia/Shanghai",
    "iso:country":"CN",
    "name:zho_x_preferred":[
        "\u5d47\u5bb6\u820d"
    ],
    "wof:name":"Jijiashe",
    "wof:placetype":"locality"
},
  "geometry": {"coordinates":[119.75198,32.73895],"type":"Point"}
}