{
  "type": "Feature",
  "properties": {
    "gn:admin1_code":"29.0",
    "gn:asciiname":"Huangcun",
    "gn:country_code":"CN",
    "gn:dem":2169,
    "gn:feature_class":"P",
    "gn:feature_code":"PPL",
    "gn:name":"Huangcun",
    "gn:population":0,
    "gn:timezone":"Asia/Shanghai",
    "iso:country":"CN",
    "name:und_x_variant":[
        "\u9ec4\u6751"
    ],
    "wof:name":"Huangcun",
    "wof:placetype":"locality"
},
  "geometry": {"coordinates":[104.40083,26.42882],"type":"Point"}
}