{
  "type": "Feature",
  "properties": {
    "gn:admin1_code":"04",
    "gn:asciiname":"Caixiangcun",
    "gn:country_code":"CN",
    "gn:dem":30,
    "gn:feature_class":"P",
    "gn:feature_code":"PPL",
    "gn:name":"Caixiangcun",
    "gn:population":0,
    "gn:timezone":"Asia/Shanghai",
    "iso:country":"CN",
    "name:und_x_variant":[
        "Ts\u2019ai-hsiang-chen",
        "Ts\u2019ai-hsiang",
        "Ts\u2019ai-chia-chen",
        "Caixiang",
        "Caixiangcun"
    ],
    "name:zho_x_preferred":[
        "\u8521\u5df7"
    ],
    "name:zho_x_variant":[
        "\u8521\u5df7\u6751"
    ],
    "wof:name":"Caixiangcun",
    "wof:placetype":"locality"
},
  "geometry": {"coordinates":[119.22729,31.71613],"type":"Point"}
}