{
  "type": "Feature",
  "properties": {
    "gn:admin1_code":"25",
    "gn:asciiname":"Qianyicun",
    "gn:country_code":"CN",
    "gn:dem":79,
    "gn:feature_class":"P",
    "gn:feature_code":"PPL",
    "gn:name":"Qianyicun",
    "gn:population":0,
    "gn:timezone":"Asia/Shanghai",
    "iso:country":"CN",
    "name:zho_x_preferred":[
        "\u94b1\u4e00\u6751"
    ],
    "wof:name":"Qianyicun",
    "wof:placetype":"locality"
},
  "geometry": {"coordinates":[116.613,36.1771],"type":"Point"}
}