{
  "type": "Feature",
  "properties": {
    "gn:admin1_code":"30.0",
    "gn:asciiname":"Mingdongcun",
    "gn:country_code":"CN",
    "gn:dem":4,
    "gn:feature_class":"P",
    "gn:feature_code":"PPL",
    "gn:name":"Mingdongcun",
    "gn:population":0,
    "gn:timezone":"Asia/Shanghai",
    "iso:country":"CN",
    "name:zho_x_preferred":[
        "\u94ed\u4e1c\u6751"
    ],
    "wof:name":"Mingdongcun",
    "wof:placetype":"locality"
},
  "geometry": {"coordinates":[116.42867,22.96442],"type":"Point"}
}