{
  "type": "Feature",
  "properties": {
    "gn:admin1_code":"11.0",
    "gn:asciiname":"Butian",
    "gn:country_code":"CN",
    "gn:dem":316,
    "gn:feature_class":"P",
    "gn:feature_code":"PPL",
    "gn:name":"Butian",
    "gn:population":0,
    "gn:timezone":"Asia/Shanghai",
    "iso:country":"CN",
    "name:und_x_variant":[
        "Buting"
    ],
    "name:zho_x_preferred":[
        "\u57e0\u7530"
    ],
    "wof:name":"Butian",
    "wof:placetype":"locality"
},
  "geometry": {"coordinates":[111.14315999999999,26.94476],"type":"Point"}
}