{
  "type": "Feature",
  "properties": {
    "gn:admin1_code":"32.0",
    "gn:asciiname":"Seba",
    "gn:country_code":"CN",
    "gn:dem":3414,
    "gn:feature_class":"P",
    "gn:feature_code":"PPL",
    "gn:name":"Seba",
    "gn:population":0,
    "gn:timezone":"Asia/Shanghai",
    "iso:country":"CN",
    "name:deu_x_preferred":[
        "Seba"
    ],
    "name:fra_x_preferred":[
        "S\u00e9ba"
    ],
    "name:nds_x_preferred":[
        "Seba"
    ],
    "name:nor_x_preferred":[
        "Seba"
    ],
    "name:por_x_preferred":[
        "Seba"
    ],
    "name:rus_x_preferred":[
        "\u0421\u0435\u0431\u0430"
    ],
    "name:swe_x_preferred":[
        "Seba"
    ],
    "name:zho_x_preferred":[
        "\u8272\u5df4"
    ],
    "wof:name":"Seba",
    "wof:placetype":"locality"
},
  "geometry": {"coordinates":[98.9747,30.6231],"type":"Point"}
}