{
  "type": "Feature",
  "properties": {
    "gn:admin1_code":"30.0",
    "gn:asciiname":"Erdushui",
    "gn:country_code":"CN",
    "gn:dem":80,
    "gn:feature_class":"P",
    "gn:feature_code":"PPL",
    "gn:name":"Erdushui",
    "gn:population":0,
    "gn:timezone":"Asia/Shanghai",
    "iso:country":"CN",
    "name:zho_x_preferred":[
        "\u4e8c\u5ea6\u6c34"
    ],
    "wof:name":"Erdushui",
    "wof:placetype":"locality"
},
  "geometry": {"coordinates":[113.49476,23.91056],"type":"Point"}
}