{
  "type": "Feature",
  "properties": {
    "gn:admin1_code":"19.0",
    "gn:asciiname":"Hongshila",
    "gn:country_code":"CN",
    "gn:dem":703,
    "gn:feature_class":"P",
    "gn:feature_code":"PPL",
    "gn:name":"Hongshila",
    "gn:population":0,
    "gn:timezone":"Asia/Shanghai",
    "iso:country":"CN",
    "name:zho_x_preferred":[
        "\u7ea2\u77f3\u782c"
    ],
    "wof:name":"Hongshila",
    "wof:placetype":"locality"
},
  "geometry": {"coordinates":[119.913,41.5043],"type":"Point"}
}