{
  "type": "Feature",
  "properties": {
    "gn:admin1_code":"14.0",
    "gn:asciiname":"Namsarling",
    "gn:country_code":"CN",
    "gn:dem":4656,
    "gn:feature_class":"P",
    "gn:feature_code":"PPL",
    "gn:name":"Namsarling",
    "gn:population":0,
    "gn:timezone":"Asia/Urumqi",
    "iso:country":"CN",
    "name:bod_x_preferred":[
        "Namsarling"
    ],
    "name:zho_x_preferred":[
        "Nansalin"
    ],
    "name:zho_x_variant":[
        "\u5357\u8428\u6797",
        "Pengang Gongshe",
        "\u76c6\u5c97\u516c\u793e"
    ],
    "wof:name":"Namsarling",
    "wof:placetype":"locality"
},
  "geometry": {"coordinates":[86.301,28.901],"type":"Point"}
}