{
  "type": "Feature",
  "properties": {
    "gn:admin1_code":"15.0",
    "gn:asciiname":"Tuqiaogou",
    "gn:country_code":"CN",
    "gn:dem":1914,
    "gn:feature_class":"P",
    "gn:feature_code":"PPL",
    "gn:name":"Tuqiaogou",
    "gn:population":0,
    "gn:timezone":"Asia/Shanghai",
    "iso:country":"CN",
    "name:zho_x_preferred":[
        "\u571f\u6865\u6c9f"
    ],
    "wof:name":"Tuqiaogou",
    "wof:placetype":"locality"
},
  "geometry": {"coordinates":[104.636,35.555],"type":"Point"}
}