{
  "type": "Feature",
  "properties": {
    "gn:admin1_code":"16.0",
    "gn:asciiname":"Fubu",
    "gn:country_code":"CN",
    "gn:dem":439,
    "gn:feature_class":"P",
    "gn:feature_code":"PPL",
    "gn:name":"Fubu",
    "gn:population":0,
    "gn:timezone":"Asia/Shanghai",
    "iso:country":"CN",
    "name:zho_x_preferred":[
        "\u4f0f\u5e03"
    ],
    "wof:name":"Fubu",
    "wof:placetype":"locality"
},
  "geometry": {"coordinates":[107.14700000000001,23.2804],"type":"Point"}
}