{
  "type": "Feature",
  "properties": {
    "gn:admin1_code":"26.0",
    "gn:asciiname":"Liaojiagou",
    "gn:country_code":"CN",
    "gn:dem":658,
    "gn:feature_class":"P",
    "gn:feature_code":"PPL",
    "gn:name":"Liaojiagou",
    "gn:population":0,
    "gn:timezone":"Asia/Shanghai",
    "iso:country":"CN",
    "name:und_x_variant":[
        "\u5ed6\u5bb6\u6c9f"
    ],
    "wof:name":"Liaojiagou",
    "wof:placetype":"locality"
},
  "geometry": {"coordinates":[107.25716,34.29993],"type":"Point"}
}