{
  "type": "Feature",
  "properties": {
    "gn:admin1_code":"14.0",
    "gn:asciiname":"Xiongdui",
    "gn:country_code":"CN",
    "gn:dem":4857,
    "gn:feature_class":"P",
    "gn:feature_code":"PPL",
    "gn:name":"Xiongdui",
    "gn:population":0,
    "gn:timezone":"Asia/Urumqi",
    "iso:country":"CN",
    "name:zho_x_preferred":[
        "\u718a\u961f"
    ],
    "wof:name":"Xiongdui",
    "wof:placetype":"locality"
},
  "geometry": {"coordinates":[86.23820000000001,29.7033],"type":"Point"}
}