{
  "type": "Feature",
  "properties": {
    "gn:admin1_code":"26.0",
    "gn:asciiname":"Xujia Yuanzi",
    "gn:country_code":"CN",
    "gn:dem":1103,
    "gn:feature_class":"P",
    "gn:feature_code":"PPL",
    "gn:name":"Xujia Yuanzi",
    "gn:population":0,
    "gn:timezone":"Asia/Shanghai",
    "iso:country":"CN",
    "name:zho_x_preferred":[
        "\u5f90\u5bb6\u9662\u5b50"
    ],
    "wof:name":"Xujia Yuanzi",
    "wof:placetype":"locality"
},
  "geometry": {"coordinates":[109.75646,33.59657],"type":"Point"}
}