{
  "type": "Feature",
  "properties": {
    "gn:admin1_code":"14.0",
    "gn:asciiname":"Gangnong",
    "gn:country_code":"CN",
    "gn:dem":4907,
    "gn:feature_class":"P",
    "gn:feature_code":"PPL",
    "gn:name":"Gangnong",
    "gn:population":0,
    "gn:timezone":"Asia/Urumqi",
    "iso:country":"CN",
    "name:zho_x_preferred":[
        "\u6e2f\u5f04"
    ],
    "wof:name":"Gangnong",
    "wof:placetype":"locality"
},
  "geometry": {"coordinates":[87.2812,31.1789],"type":"Point"}
}