{
  "type": "Feature",
  "properties": {
    "gn:admin1_code":"3.0",
    "gn:asciiname":"Chengmen",
    "gn:country_code":"CN",
    "gn:dem":164,
    "gn:feature_class":"P",
    "gn:feature_code":"PPL",
    "gn:name":"Chengmen",
    "gn:population":0,
    "gn:timezone":"Asia/Shanghai",
    "iso:country":"CN",
    "name:und_x_variant":[
        "\u57ce\u95e8"
    ],
    "wof:name":"Chengmen",
    "wof:placetype":"locality"
},
  "geometry": {"coordinates":[115.29939,25.94478],"type":"Point"}
}