{
  "type": "Feature",
  "properties": {
    "gn:admin1_code":"30.0",
    "gn:asciiname":"Cheshangcun",
    "gn:country_code":"CN",
    "gn:dem":127,
    "gn:feature_class":"P",
    "gn:feature_code":"PPL",
    "gn:name":"Cheshangcun",
    "gn:population":0,
    "gn:timezone":"Asia/Shanghai",
    "iso:country":"CN",
    "name:zho_x_preferred":[
        "\u8f66\u4e0a\u6751"
    ],
    "wof:name":"Cheshangcun",
    "wof:placetype":"locality"
},
  "geometry": {"coordinates":[116.40904,24.27813],"type":"Point"}
}