{
  "type": "Feature",
  "properties": {
    "gn:admin1_code":"29.0",
    "gn:asciiname":"Bozha",
    "gn:country_code":"CN",
    "gn:dem":2687,
    "gn:feature_class":"P",
    "gn:feature_code":"PPL",
    "gn:name":"Bozha",
    "gn:population":0,
    "gn:timezone":"Asia/Shanghai",
    "iso:country":"CN",
    "name:zho_x_preferred":[
        "\u6ce2\u4e4d"
    ],
    "wof:name":"Bozha",
    "wof:placetype":"locality"
},
  "geometry": {"coordinates":[101.09999999999999,26.0904],"type":"Point"}
}