{
  "type": "Feature",
  "properties": {
    "gn:admin1_code":"3.0",
    "gn:asciiname":"Maozhushan Linchang",
    "gn:country_code":"CN",
    "gn:dem":422,
    "gn:feature_class":"P",
    "gn:feature_code":"PPLF",
    "gn:name":"Maozhushan Linchang",
    "gn:population":0,
    "gn:timezone":"Asia/Shanghai",
    "iso:country":"CN",
    "name:und_x_variant":[
        "\u6bdb\u7af9\u5c71\u6797\u573a"
    ],
    "wof:name":"Maozhushan Linchang",
    "wof:placetype":"locality"
},
  "geometry": {"coordinates":[114.86358,28.84459],"type":"Point"}
}