{
  "type": "Feature",
  "properties": {
    "gn:admin1_code":"30.0",
    "gn:asciiname":"Hutou",
    "gn:country_code":"CN",
    "gn:dem":315,
    "gn:feature_class":"P",
    "gn:feature_code":"PPL",
    "gn:name":"Hutou",
    "gn:population":0,
    "gn:timezone":"Asia/Shanghai",
    "iso:country":"CN",
    "name:zho_x_preferred":[
        "Hutou"
    ],
    "name:zho_x_variant":[
        "\u864e\u5934"
    ],
    "wof:name":"Hutou",
    "wof:placetype":"locality"
},
  "geometry": {"coordinates":[115.39528,24.62806],"type":"Point"}
}