{
  "type": "Feature",
  "properties": {
    "gn:admin1_code":"12.0",
    "gn:asciiname":"Lianwutai",
    "gn:country_code":"CN",
    "gn:dem":32,
    "gn:feature_class":"P",
    "gn:feature_code":"PPL",
    "gn:name":"Lianwutai",
    "gn:population":0,
    "gn:timezone":"Asia/Shanghai",
    "iso:country":"CN",
    "name:zho_x_preferred":[
        "\u8fde\u4f0d\u53f0"
    ],
    "wof:name":"Lianwutai",
    "wof:placetype":"locality"
},
  "geometry": {"coordinates":[112.60426,30.54751],"type":"Point"}
}