{
  "type": "Feature",
  "properties": {
    "gn:admin1_code":"14.0",
    "gn:asciiname":"Horrimai",
    "gn:country_code":"CN",
    "gn:dem":4001,
    "gn:feature_class":"P",
    "gn:feature_code":"PPL",
    "gn:name":"Horrimai",
    "gn:population":0,
    "gn:timezone":"Asia/Urumqi",
    "iso:country":"CN",
    "name:bod_x_preferred":[
        "Horrimai"
    ],
    "name:zho_x_preferred":[
        "Huorimai"
    ],
    "name:zho_x_variant":[
        "\u970d\u65e5\u9ea6"
    ],
    "wof:name":"Horrimai",
    "wof:placetype":"locality"
},
  "geometry": {"coordinates":[96.601,31.301],"type":"Point"}
}