{
  "type": "Feature",
  "properties": {
    "gn:admin1_code":"16.0",
    "gn:asciiname":"Laoli",
    "gn:country_code":"CN",
    "gn:dem":531,
    "gn:feature_class":"P",
    "gn:feature_code":"PPL",
    "gn:name":"Laoli",
    "gn:population":0,
    "gn:timezone":"Asia/Shanghai",
    "iso:country":"CN",
    "name:zho_x_preferred":[
        "\u52b3\u91cc"
    ],
    "wof:name":"Laoli",
    "wof:placetype":"locality"
},
  "geometry": {"coordinates":[106.67700000000001,25.0391],"type":"Point"}
}