{
  "type": "Feature",
  "properties": {
    "gn:admin1_code":"31.0",
    "gn:asciiname":"Bainan",
    "gn:country_code":"CN",
    "gn:dem":121,
    "gn:feature_class":"P",
    "gn:feature_code":"PPL",
    "gn:name":"Bainan",
    "gn:population":0,
    "gn:timezone":"Asia/Shanghai",
    "iso:country":"CN",
    "name:zho_x_preferred":[
        "\u767d\u5357"
    ],
    "wof:name":"Bainan",
    "wof:placetype":"locality"
},
  "geometry": {"coordinates":[109.56835,19.58778],"type":"Point"}
}