{
  "type": "Feature",
  "properties": {
    "gn:admin1_code":"15.0",
    "gn:asciiname":"Dashagou",
    "gn:country_code":"CN",
    "gn:dem":1974,
    "gn:feature_class":"P",
    "gn:feature_code":"PPL",
    "gn:name":"Dashagou",
    "gn:population":0,
    "gn:timezone":"Asia/Shanghai",
    "iso:country":"CN",
    "name:zho_x_preferred":[
        "\u5927\u6c99\u6c9f"
    ],
    "wof:name":"Dashagou",
    "wof:placetype":"locality"
},
  "geometry": {"coordinates":[103.62,37.4739],"type":"Point"}
}