{
  "type": "Feature",
  "properties": {
    "gn:admin1_code":"14.0",
    "gn:asciiname":"Gendi",
    "gn:country_code":"CN",
    "gn:dem":3493,
    "gn:feature_class":"P",
    "gn:feature_code":"PPL",
    "gn:name":"Gendi",
    "gn:population":0,
    "gn:timezone":"Asia/Urumqi",
    "iso:country":"CN",
    "name:zho_x_preferred":[
        "\u6839\u5e95"
    ],
    "wof:name":"Gendi",
    "wof:placetype":"locality"
},
  "geometry": {"coordinates":[98.7919,31.3093],"type":"Point"}
}