{
  "type": "Feature",
  "properties": {
    "gn:admin1_code":"16.0",
    "gn:asciiname":"Xiaobada",
    "gn:country_code":"CN",
    "gn:dem":798,
    "gn:feature_class":"P",
    "gn:feature_code":"PPL",
    "gn:name":"Xiaobada",
    "gn:population":0,
    "gn:timezone":"Asia/Shanghai",
    "iso:country":"CN",
    "name:zho_x_preferred":[
        "\u5c0f\u516b\u8fbe"
    ],
    "wof:name":"Xiaobada",
    "wof:placetype":"locality"
},
  "geometry": {"coordinates":[104.717,24.5407],"type":"Point"}
}