{
  "type": "Feature",
  "properties": {
    "gn:admin1_code":"4.0",
    "gn:asciiname":"Linshangcun",
    "gn:country_code":"CN",
    "gn:dem":4,
    "gn:feature_class":"P",
    "gn:feature_code":"PPL",
    "gn:name":"Linshangcun",
    "gn:population":0,
    "gn:timezone":"Asia/Shanghai",
    "iso:country":"CN",
    "name:zho_x_preferred":[
        "\u6797\u4e0a\u6751"
    ],
    "wof:name":"Linshangcun",
    "wof:placetype":"locality"
},
  "geometry": {"coordinates":[119.58588,33.35852],"type":"Point"}
}