{
  "type": "Feature",
  "properties": {
    "gn:admin1_code":"16.0",
    "gn:asciiname":"Gan'ai",
    "gn:country_code":"CN",
    "gn:dem":470,
    "gn:feature_class":"P",
    "gn:feature_code":"PPL",
    "gn:name":"Gan\u2019ai",
    "gn:population":0,
    "gn:timezone":"Asia/Shanghai",
    "iso:country":"CN",
    "name:und_x_variant":[
        "Gan\u2019ai"
    ],
    "name:zho_x_preferred":[
        "\u7518\u827e"
    ],
    "wof:name":"Gan'ai",
    "wof:placetype":"locality"
},
  "geometry": {"coordinates":[107.59399999999999,23.491],"type":"Point"}
}