{
  "type": "Feature",
  "properties": {
    "gn:admin1_code":"4.0",
    "gn:asciiname":"Zhimacun",
    "gn:country_code":"CN",
    "gn:dem":10,
    "gn:feature_class":"P",
    "gn:feature_code":"PPL",
    "gn:name":"Zhimacun",
    "gn:population":0,
    "gn:timezone":"Asia/Shanghai",
    "iso:country":"CN",
    "name:zho_x_preferred":[
        "\u829d\u9ebb\u6751"
    ],
    "wof:name":"Zhimacun",
    "wof:placetype":"locality"
},
  "geometry": {"coordinates":[118.81328999999999,34.45789],"type":"Point"}
}