{
  "type": "Feature",
  "properties": {
    "gn:admin1_code":"8.0",
    "gn:asciiname":"Changshengcun",
    "gn:country_code":"CN",
    "gn:dem":99,
    "gn:feature_class":"P",
    "gn:feature_code":"PPL",
    "gn:name":"Changshengcun",
    "gn:population":0,
    "gn:timezone":"Asia/Shanghai",
    "iso:country":"CN",
    "name:zho_x_preferred":[
        "\u660c\u76db\u6751"
    ],
    "wof:name":"Changshengcun",
    "wof:placetype":"locality"
},
  "geometry": {"coordinates":[133.84708999999998,46.87143],"type":"Point"}
}