{
  "type": "Feature",
  "properties": {
    "gn:admin1_code":"4.0",
    "gn:asciiname":"Jiuzongcun",
    "gn:country_code":"CN",
    "gn:dem":3,
    "gn:feature_class":"P",
    "gn:feature_code":"PPL",
    "gn:name":"Jiuzongcun",
    "gn:population":0,
    "gn:timezone":"Asia/Shanghai",
    "iso:country":"CN",
    "name:zho_x_preferred":[
        "\u4e5d\u603b\u6751"
    ],
    "wof:name":"Jiuzongcun",
    "wof:placetype":"locality"
},
  "geometry": {"coordinates":[120.74487000000001,32.66888],"type":"Point"}
}