{
  "type": "Feature",
  "properties": {
    "gn:admin1_code":"8.0",
    "gn:asciiname":"Zhangfengxiang",
    "gn:country_code":"CN",
    "gn:dem":180,
    "gn:feature_class":"P",
    "gn:feature_code":"PPL",
    "gn:name":"Zhangfengxiang",
    "gn:population":0,
    "gn:timezone":"Asia/Shanghai",
    "iso:country":"CN",
    "name:zho_x_preferred":[
        "\u5f20\u51e4\u7965"
    ],
    "wof:name":"Zhangfengxiang",
    "wof:placetype":"locality"
},
  "geometry": {"coordinates":[126.82877000000001,46.77766],"type":"Point"}
}