{
  "type": "Feature",
  "properties": {
    "gn:admin1_code":"32.0",
    "gn:asciiname":"Aoyicun",
    "gn:country_code":"CN",
    "gn:dem":4106,
    "gn:feature_class":"P",
    "gn:feature_code":"PPL",
    "gn:name":"Aoyicun",
    "gn:population":0,
    "gn:timezone":"Asia/Shanghai",
    "iso:country":"CN",
    "name:zho_x_preferred":[
        "\u50b2\u4e00\u6751"
    ],
    "wof:name":"Aoyicun",
    "wof:placetype":"locality"
},
  "geometry": {"coordinates":[97.58880000000001,32.8115],"type":"Point"}
}