{
  "type": "Feature",
  "properties": {
    "gn:admin1_code":"4.0",
    "gn:asciiname":"Shixucun",
    "gn:country_code":"CN",
    "gn:dem":4,
    "gn:feature_class":"P",
    "gn:feature_code":"PPL",
    "gn:name":"Shixucun",
    "gn:population":0,
    "gn:timezone":"Asia/Shanghai",
    "iso:country":"CN",
    "name:zho_x_preferred":[
        "\u4f8d\u5729\u6751"
    ],
    "wof:name":"Shixucun",
    "wof:placetype":"locality"
},
  "geometry": {"coordinates":[119.23108000000001,34.24010999999999],"type":"Point"}
}