{
  "type": "Feature",
  "properties": {
    "gn:admin1_code":"11.0",
    "gn:asciiname":"Daijiapeng",
    "gn:country_code":"CN",
    "gn:dem":165,
    "gn:feature_class":"P",
    "gn:feature_code":"PPL",
    "gn:name":"Daijiapeng",
    "gn:population":0,
    "gn:timezone":"Asia/Shanghai",
    "iso:country":"CN",
    "name:zho_x_preferred":[
        "\u6234\u5bb6\u68da"
    ],
    "wof:name":"Daijiapeng",
    "wof:placetype":"locality"
},
  "geometry": {"coordinates":[111.29712000000001,28.82967],"type":"Point"}
}