{
  "type": "Feature",
  "properties": {
    "gn:admin1_code":"13.0",
    "gn:asciiname":"Kayrak",
    "gn:country_code":"CN",
    "gn:dem":819,
    "gn:feature_class":"P",
    "gn:feature_code":"PPL",
    "gn:name":"Kayrak",
    "gn:population":0,
    "gn:timezone":"Asia/Urumqi",
    "iso:country":"CN",
    "name:ceb_x_preferred":[
        "Kayrak"
    ],
    "name:msa_x_preferred":[
        "Kayrak"
    ],
    "name:vie_x_preferred":[
        "Kayrak"
    ],
    "wof:name":"Kayrak",
    "wof:placetype":"locality"
},
  "geometry": {"coordinates":[87.99325,39.36635],"type":"Point"}
}