{
  "type": "Feature",
  "properties": {
    "gn:admin1_code":"19.0",
    "gn:asciiname":"Shidonggoucun",
    "gn:country_code":"CN",
    "gn:dem":154,
    "gn:feature_class":"P",
    "gn:feature_code":"PPL",
    "gn:name":"Shidonggoucun",
    "gn:population":0,
    "gn:timezone":"Asia/Shanghai",
    "iso:country":"CN",
    "name:zho_x_preferred":[
        "\u77f3\u6d1e\u6c9f\u6751"
    ],
    "wof:name":"Shidonggoucun",
    "wof:placetype":"locality"
},
  "geometry": {"coordinates":[124.182,42.3861],"type":"Point"}
}