{
  "type": "Feature",
  "properties": {
    "gn:admin1_code":"9.0",
    "gn:asciiname":"Wangshantuo",
    "gn:country_code":"CN",
    "gn:dem":1115,
    "gn:feature_class":"P",
    "gn:feature_code":"PPL",
    "gn:name":"Wangshantuo",
    "gn:population":0,
    "gn:timezone":"Asia/Shanghai",
    "iso:country":"CN",
    "name:zho_x_preferred":[
        "\u738b\u5c71\u9a6e"
    ],
    "wof:name":"Wangshantuo",
    "wof:placetype":"locality"
},
  "geometry": {"coordinates":[110.6177,34.35437],"type":"Point"}
}