{
  "type": "Feature",
  "properties": {
    "gn:admin1_code":"29",
    "gn:asciiname":"Tiejiangfang",
    "gn:country_code":"CN",
    "gn:dem":1994,
    "gn:feature_class":"P",
    "gn:feature_code":"PPL",
    "gn:name":"Tiejiangfang",
    "gn:population":0,
    "gn:timezone":"Asia/Shanghai",
    "iso:country":"CN",
    "name:zho_x_preferred":[
        "\u94c1\u5320\u623f"
    ],
    "wof:name":"Tiejiangfang",
    "wof:placetype":"locality"
},
  "geometry": {"coordinates":[101.77500000000001,24.5719],"type":"Point"}
}