{
  "type": "Feature",
  "properties": {
    "gn:admin1_code":"25.0",
    "gn:asciiname":"Fanglicun",
    "gn:country_code":"CN",
    "gn:dem":46,
    "gn:feature_class":"P",
    "gn:feature_code":"PPL",
    "gn:name":"Fanglicun",
    "gn:population":0,
    "gn:timezone":"Asia/Shanghai",
    "iso:country":"CN",
    "name:zho_x_preferred":[
        "\u65b9\u91cc\u6751"
    ],
    "wof:name":"Fanglicun",
    "wof:placetype":"locality"
},
  "geometry": {"coordinates":[121.42395999999999,36.7747],"type":"Point"}
}