{
  "type": "Feature",
  "properties": {
    "gn:admin1_code":"16",
    "gn:asciiname":"Yangjiazhai",
    "gn:country_code":"CN",
    "gn:dem":757,
    "gn:feature_class":"P",
    "gn:feature_code":"PPL",
    "gn:name":"Yangjiazhai",
    "gn:population":0,
    "gn:timezone":"Asia/Shanghai",
    "iso:country":"CN",
    "wof:name":"Yangjiazhai",
    "wof:placetype":"locality"
},
  "geometry": {"coordinates":[110.69611,25.87278],"type":"Point"}
}