{
  "type": "Feature",
  "properties": {
    "gn:admin1_code":"1.0",
    "gn:asciiname":"Cangyuancun",
    "gn:country_code":"CN",
    "gn:dem":600,
    "gn:feature_class":"P",
    "gn:feature_code":"PPL",
    "gn:name":"Cangyuancun",
    "gn:population":0,
    "gn:timezone":"Asia/Shanghai",
    "iso:country":"CN",
    "name:zho_x_preferred":[
        "\u4ed3\u56ed\u6751"
    ],
    "wof:name":"Cangyuancun",
    "wof:placetype":"locality"
},
  "geometry": {"coordinates":[116.20446,30.99974000000001],"type":"Point"}
}