{
  "type": "Feature",
  "properties": {
    "gn:admin1_code":"32.0",
    "gn:asciiname":"Shanhuasi",
    "gn:country_code":"CN",
    "gn:dem":409,
    "gn:feature_class":"P",
    "gn:feature_code":"PPL",
    "gn:name":"Shanhuasi",
    "gn:population":0,
    "gn:timezone":"Asia/Shanghai",
    "iso:country":"CN",
    "name:zho_x_preferred":[
        "\u5584\u534e\u5bfa"
    ],
    "wof:name":"Shanhuasi",
    "wof:placetype":"locality"
},
  "geometry": {"coordinates":[104.79707000000001,30.40292],"type":"Point"}
}