{
  "type": "Feature",
  "properties": {
    "gn:admin1_code":"13",
    "gn:asciiname":"Suopa Tuolake",
    "gn:country_code":"CN",
    "gn:dem":908,
    "gn:feature_class":"P",
    "gn:feature_code":"PPL",
    "gn:name":"Suopa Tuolake",
    "gn:population":0,
    "gn:timezone":"Asia/Urumqi",
    "iso:country":"CN",
    "name:und_x_variant":[
        "\u7d22\u5e15\u6258\u62c9\u514b"
    ],
    "wof:name":"Suopa Tuolake",
    "wof:placetype":"locality"
},
  "geometry": {"coordinates":[94.83638999999999,43.54455],"type":"Point"}
}