{
  "type": "Feature",
  "properties": {
    "gn:admin1_code":"10.0",
    "gn:asciiname":"Wuwangkou",
    "gn:country_code":"CN",
    "gn:dem":502,
    "gn:feature_class":"P",
    "gn:feature_code":"PPLA4",
    "gn:name":"Wuwangkou",
    "gn:population":0,
    "gn:timezone":"Asia/Shanghai",
    "iso:country":"CN",
    "name:und_x_variant":[
        "\u5434\u738b\u53e3",
        "Wuwangkou Xiang",
        "\u5434\u738b\u53e3\u4e61"
    ],
    "wof:name":"Wuwangkou",
    "wof:placetype":"locality"
},
  "geometry": {"coordinates":[114.01858,39.04512],"type":"Point"}
}