{
  "type": "Feature",
  "properties": {
    "gn:admin1_code":"12.0",
    "gn:asciiname":"Damoping",
    "gn:country_code":"CN",
    "gn:dem":768,
    "gn:feature_class":"P",
    "gn:feature_code":"PPL",
    "gn:name":"Damoping",
    "gn:population":0,
    "gn:timezone":"Asia/Shanghai",
    "iso:country":"CN",
    "name:zho_x_preferred":[
        "\u5927\u78e8\u576a"
    ],
    "wof:name":"Damoping",
    "wof:placetype":"locality"
},
  "geometry": {"coordinates":[110.39728999999998,30.91965],"type":"Point"}
}