{
  "type": "Feature",
  "properties": {
    "gn:admin1_code":"25.0",
    "gn:asciiname":"Aolicun",
    "gn:country_code":"CN",
    "gn:dem":1,
    "gn:feature_class":"P",
    "gn:feature_code":"PPL",
    "gn:name":"Aolicun",
    "gn:population":0,
    "gn:timezone":"Asia/Shanghai",
    "iso:country":"CN",
    "name:zho_x_preferred":[
        "\u5ed2\u91cc\u6751"
    ],
    "wof:name":"Aolicun",
    "wof:placetype":"locality"
},
  "geometry": {"coordinates":[119.53369000000001,37.02206],"type":"Point"}
}