{
  "type": "Feature",
  "properties": {
    "gn:admin1_code":"29.0",
    "gn:asciiname":"Lusaping",
    "gn:country_code":"CN",
    "gn:dem":1562,
    "gn:feature_class":"P",
    "gn:feature_code":"PPL",
    "gn:name":"Lusaping",
    "gn:population":0,
    "gn:timezone":"Asia/Shanghai",
    "iso:country":"CN",
    "name:zho_x_preferred":[
        "\u9c81\u8428\u5e73"
    ],
    "wof:name":"Lusaping",
    "wof:placetype":"locality"
},
  "geometry": {"coordinates":[103.357,23.792],"type":"Point"}
}