{
  "type": "Feature",
  "properties": {
    "gn:admin1_code":"12.0",
    "gn:asciiname":"Matashi",
    "gn:country_code":"CN",
    "gn:dem":196,
    "gn:feature_class":"P",
    "gn:feature_code":"PPL",
    "gn:name":"Matashi",
    "gn:population":0,
    "gn:timezone":"Asia/Shanghai",
    "iso:country":"CN",
    "name:zho_x_preferred":[
        "Matashi"
    ],
    "name:zho_x_variant":[
        "\u9a6c\u8e0f\u77f3"
    ],
    "wof:name":"Matashi",
    "wof:placetype":"locality"
},
  "geometry": {"coordinates":[111.45121,30.21458],"type":"Point"}
}