{
  "type": "Feature",
  "properties": {
    "gn:admin1_code":"16",
    "gn:asciiname":"Niujiang",
    "gn:country_code":"CN",
    "gn:dem":399,
    "gn:feature_class":"P",
    "gn:feature_code":"PPL",
    "gn:name":"Niujiang",
    "gn:population":0,
    "gn:timezone":"Asia/Shanghai",
    "iso:country":"CN",
    "name:zho_x_preferred":[
        "\u725b\u6c5f"
    ],
    "wof:name":"Niujiang",
    "wof:placetype":"locality"
},
  "geometry": {"coordinates":[110.04300000000001,25.6225],"type":"Point"}
}