{
  "type": "Feature",
  "properties": {
    "gn:admin1_code":"19.0",
    "gn:asciiname":"Sanhebucun",
    "gn:country_code":"CN",
    "gn:dem":80,
    "gn:feature_class":"P",
    "gn:feature_code":"PPL",
    "gn:name":"Sanhebucun",
    "gn:population":0,
    "gn:timezone":"Asia/Shanghai",
    "iso:country":"CN",
    "name:zho_x_preferred":[
        "\u4e09\u5408\u5821\u6751"
    ],
    "wof:name":"Sanhebucun",
    "wof:placetype":"locality"
},
  "geometry": {"coordinates":[123.44754,42.81996],"type":"Point"}
}