{
  "type": "Feature",
  "properties": {
    "gn:admin1_code":"19.0",
    "gn:asciiname":"Shihuiyaozi",
    "gn:country_code":"CN",
    "gn:dem":92,
    "gn:feature_class":"P",
    "gn:feature_code":"PPL",
    "gn:name":"Shihuiyaozi",
    "gn:population":0,
    "gn:timezone":"Asia/Shanghai",
    "iso:country":"CN",
    "name:zho_x_preferred":[
        "\u77f3\u7070\u7a91\u5b50"
    ],
    "wof:name":"Shihuiyaozi",
    "wof:placetype":"locality"
},
  "geometry": {"coordinates":[120.69871000000001,40.86581],"type":"Point"}
}