{
  "type": "Feature",
  "properties": {
    "gn:admin1_code":"16.0",
    "gn:asciiname":"Nachu",
    "gn:country_code":"CN",
    "gn:dem":473,
    "gn:feature_class":"P",
    "gn:feature_code":"PPL",
    "gn:name":"Nachu",
    "gn:population":0,
    "gn:timezone":"Asia/Shanghai",
    "iso:country":"CN",
    "name:zho_x_preferred":[
        "\u90a3\u9664"
    ],
    "wof:name":"Nachu",
    "wof:placetype":"locality"
},
  "geometry": {"coordinates":[107.09,23.9174],"type":"Point"}
}