{
  "type": "Feature",
  "properties": {
    "gn:admin1_code":"30.0",
    "gn:asciiname":"Jiaogongtang",
    "gn:country_code":"CN",
    "gn:dem":151,
    "gn:feature_class":"P",
    "gn:feature_code":"PPL",
    "gn:name":"Jiaogongtang",
    "gn:population":0,
    "gn:timezone":"Asia/Shanghai",
    "iso:country":"CN",
    "name:zho_x_preferred":[
        "\u89d2\u516c\u5858"
    ],
    "wof:name":"Jiaogongtang",
    "wof:placetype":"locality"
},
  "geometry": {"coordinates":[114.46760999999999,25.20537],"type":"Point"}
}