{
  "type": "Feature",
  "properties": {
    "gn:admin1_code":"9.0",
    "gn:asciiname":"Hujia",
    "gn:country_code":"CN",
    "gn:dem":346,
    "gn:feature_class":"P",
    "gn:feature_code":"PPL",
    "gn:name":"Hujia",
    "gn:population":0,
    "gn:timezone":"Asia/Shanghai",
    "iso:country":"CN",
    "name:und_x_variant":[
        "\u6237\u5bb6",
        "Hujia"
    ],
    "wof:name":"Hujia",
    "wof:placetype":"locality"
},
  "geometry": {"coordinates":[112.41418,33.29206],"type":"Point"}
}