{
  "type": "Feature",
  "properties": {
    "gn:admin1_code":"12.0",
    "gn:asciiname":"Kuangjiazhongwan",
    "gn:country_code":"CN",
    "gn:dem":23,
    "gn:feature_class":"P",
    "gn:feature_code":"PPL",
    "gn:name":"Kuangjiazhongwan",
    "gn:population":0,
    "gn:timezone":"Asia/Shanghai",
    "iso:country":"CN",
    "name:zho_x_preferred":[
        "\u5321\u5bb6\u4e2d\u6e7e"
    ],
    "wof:name":"Kuangjiazhongwan",
    "wof:placetype":"locality"
},
  "geometry": {"coordinates":[113.15286,29.87989],"type":"Point"}
}