{
  "type": "Feature",
  "properties": {
    "gn:admin1_code":"1.0",
    "gn:asciiname":"Zhangloucun",
    "gn:country_code":"CN",
    "gn:dem":40,
    "gn:feature_class":"P",
    "gn:feature_code":"PPL",
    "gn:name":"Zhangloucun",
    "gn:population":0,
    "gn:timezone":"Asia/Shanghai",
    "iso:country":"CN",
    "name:und_x_variant":[
        "Chang-lou",
        "Zhanglou",
        "Zhangloucun"
    ],
    "name:zho_x_preferred":[
        "\u5f20\u697c\u6751"
    ],
    "wof:name":"Zhangloucun",
    "wof:placetype":"locality"
},
  "geometry": {"coordinates":[115.32616000000002,32.65984],"type":"Point"}
}