{
  "type": "Feature",
  "properties": {
    "gn:admin1_code":"6.0",
    "gn:asciiname":"Xiezhi",
    "gn:country_code":"CN",
    "gn:dem":3032,
    "gn:feature_class":"P",
    "gn:feature_code":"PPL",
    "gn:name":"Xiezhi",
    "gn:population":0,
    "gn:timezone":"Asia/Shanghai",
    "iso:country":"CN",
    "name:und_x_variant":[
        "\u534f\u77e5"
    ],
    "wof:name":"Xiezhi",
    "wof:placetype":"locality"
},
  "geometry": {"coordinates":[102.22121,35.5996],"type":"Point"}
}