{
  "type": "Feature",
  "properties": {
    "gn:admin1_code":"6.0",
    "gn:asciiname":"Xiezhi",
    "gn:country_code":"CN",
    "gn:dem":3032,
    "gn:feature_class":"P",
    "gn:feature_code":"PPL",
    "gn:name":"Xiezhi",
    "gn:population":0,
    "gn:timezone":"Asia/Shanghai",
    "iso:country":"CN",
    "name:fin_x_preferred":[
        "Xiezhi"
    ],
    "name:fra_x_preferred":[
        "Haetae"
    ],
    "name:ind_x_preferred":[
        "Xiezhi"
    ],
    "name:jpn_x_preferred":[
        "\u30ab\u30a4\u30c1"
    ],
    "name:pol_x_preferred":[
        "Xiezhi"
    ],
    "name:tha_x_preferred":[
        "\u0e40\u0e0b\u0e35\u0e48\u0e22\u0e08\u0e37\u0e49\u0e2d"
    ],
    "name:und_x_variant":[
        "\u534f\u77e5"
    ],
    "wof:name":"Xiezhi",
    "wof:placetype":"locality"
},
  "geometry": {"coordinates":[102.22121,35.5996],"type":"Point"}
}