{
  "type": "Feature",
  "properties": {
    "gn:admin1_code":"2.0",
    "gn:asciiname":"Houwang",
    "gn:country_code":"CN",
    "gn:dem":36,
    "gn:feature_class":"P",
    "gn:feature_code":"PPL",
    "gn:name":"Houwang",
    "gn:population":0,
    "gn:timezone":"Asia/Shanghai",
    "iso:country":"CN",
    "name:und_x_variant":[
        "\u540e\u738b",
        "Houwang"
    ],
    "wof:name":"Houwang",
    "wof:placetype":"locality"
},
  "geometry": {"coordinates":[119.39943,29.10344000000001],"type":"Point"}
}