{
  "type": "Feature",
  "properties": {
    "gn:admin1_code":"26.0",
    "gn:asciiname":"Wu'erguacun",
    "gn:country_code":"CN",
    "gn:dem":994,
    "gn:feature_class":"P",
    "gn:feature_code":"PPL",
    "gn:name":"Wu\u2019erguacun",
    "gn:population":0,
    "gn:timezone":"Asia/Shanghai",
    "iso:country":"CN",
    "name:und_x_variant":[
        "Wu\u2019erguacun"
    ],
    "name:zho_x_preferred":[
        "\u4e94\u513f\u576c\u6751"
    ],
    "wof:name":"Wu'erguacun",
    "wof:placetype":"locality"
},
  "geometry": {"coordinates":[110.25014,37.81631],"type":"Point"}
}