{
  "type": "Feature",
  "properties": {
    "gn:admin1_code":"1.0",
    "gn:asciiname":"Baihuacun",
    "gn:country_code":"CN",
    "gn:dem":76,
    "gn:feature_class":"P",
    "gn:feature_code":"PPL",
    "gn:name":"Baihuacun",
    "gn:population":0,
    "gn:timezone":"Asia/Shanghai",
    "iso:country":"CN",
    "name:zho_x_preferred":[
        "\u767e\u82b1\u6751"
    ],
    "wof:name":"Baihuacun",
    "wof:placetype":"locality"
},
  "geometry": {"coordinates":[117.09765,31.29331],"type":"Point"}
}