{
  "type": "Feature",
  "properties": {
    "gn:admin1_code":"22",
    "gn:asciiname":"Yuzishan",
    "gn:cc2":"CN",
    "gn:country_code":"CN",
    "gn:dem":423,
    "gn:feature_class":"P",
    "gn:feature_code":"PPL",
    "gn:name":"Yuzishan",
    "gn:population":0,
    "gn:timezone":"Asia/Shanghai",
    "iso:country":"CN",
    "name:und_x_variant":[
        "Yu-tzu-Shan",
        "Yuzishan"
    ],
    "wof:name":"Yuzishan",
    "wof:placetype":"locality"
},
  "geometry": {"coordinates":[117.15000000000001,40.25],"type":"Point"}
}