{
  "type": "Feature",
  "properties": {
    "gn:admin1_code":"12",
    "gn:asciiname":"Jindongsi",
    "gn:country_code":"CN",
    "gn:dem":666,
    "gn:feature_class":"P",
    "gn:feature_code":"PPL",
    "gn:name":"Jindongsi",
    "gn:population":0,
    "gn:timezone":"Asia/Shanghai",
    "iso:country":"CN",
    "name:und_x_variant":[
        "\u91d1\u6d1e\u53f8"
    ],
    "wof:name":"Jindongsi",
    "wof:placetype":"locality"
},
  "geometry": {"coordinates":[109.10435,29.9306],"type":"Point"}
}