{
  "type": "Feature",
  "properties": {
    "gn:admin1_code":"7.0",
    "gn:asciiname":"Luoshan'ao",
    "gn:country_code":"CN",
    "gn:dem":292,
    "gn:feature_class":"P",
    "gn:feature_code":"PPL",
    "gn:name":"Luoshan\u2019ao",
    "gn:population":0,
    "gn:timezone":"Asia/Shanghai",
    "iso:country":"CN",
    "name:zho_x_preferred":[
        "\u7f57\u5c71\u51f9"
    ],
    "name:zho_x_variant":[
        "Luoshan\u2019ao"
    ],
    "wof:name":"Luoshan'ao",
    "wof:placetype":"locality"
},
  "geometry": {"coordinates":[118.35612,27.88845],"type":"Point"}
}