{
  "type": "Feature",
  "properties": {
    "gn:admin1_code":"15.0",
    "gn:asciiname":"Ya'an",
    "gn:country_code":"CN",
    "gn:dem":3049,
    "gn:feature_class":"P",
    "gn:feature_code":"PPL",
    "gn:name":"Ya\u2019an",
    "gn:population":0,
    "gn:timezone":"Asia/Shanghai",
    "iso:country":"CN",
    "name:und_x_variant":[
        "Ya\u2019an",
        "\u4e9a\u5b89"
    ],
    "wof:name":"Ya'an",
    "wof:placetype":"locality"
},
  "geometry": {"coordinates":[103.13800000000001,34.1096],"type":"Point"}
}