{
  "type": "Feature",
  "properties": {
    "gn:admin1_code":"15.0",
    "gn:asciiname":"Ya'an",
    "gn:country_code":"CN",
    "gn:dem":3049,
    "gn:feature_class":"P",
    "gn:feature_code":"PPL",
    "gn:name":"Ya\u2019an",
    "gn:population":0,
    "gn:timezone":"Asia/Shanghai",
    "iso:country":"CN",
    "name:ara_x_preferred":[
        "\u064a\u0627\u0627\u0646"
    ],
    "name:cat_x_preferred":[
        "Ya'an"
    ],
    "name:cdo_x_preferred":[
        "Ng\u0101-\u0103ng"
    ],
    "name:ces_x_preferred":[
        "Ja-an"
    ],
    "name:dan_x_preferred":[
        "Ya'an"
    ],
    "name:deu_x_preferred":[
        "Ya\u2019an"
    ],
    "name:est_x_preferred":[
        "Ya'an Shi"
    ],
    "name:eus_x_preferred":[
        "Ya'an"
    ],
    "name:fas_x_preferred":[
        "\u06cc\u0627\u0627\u0646"
    ],
    "name:fin_x_preferred":[
        "Ya\u2019an"
    ],
    "name:fra_x_preferred":[
        "Ya'an"
    ],
    "name:hak_x_preferred":[
        "Ng\u00e2-\u00f4n-s\u1e73"
    ],
    "name:ind_x_preferred":[
        "Yaan"
    ],
    "name:ita_x_preferred":[
        "Ya'an"
    ],
    "name:jpn_x_preferred":[
        "\u96c5\u5b89\u5e02"
    ],
    "name:kaz_x_preferred":[
        "\u042f\u0430\u043d\u044c"
    ],
    "name:kik_x_preferred":[
        "Ya'an"
    ],
    "name:kor_x_preferred":[
        "\uc57c\uc548\uc2dc"
    ],
    "name:nld_x_preferred":[
        "Ya'an"
    ],
    "name:nno_x_preferred":[
        "Ya'an"
    ],
    "name:nor_x_preferred":[
        "Ya'an"
    ],
    "name:pol_x_preferred":[
        "Ya\u2019an"
    ],
    "name:rus_x_preferred":[
        "\u042f\u0430\u043d\u044c"
    ],
    "name:spa_x_preferred":[
        "Ya'an"
    ],
    "name:swe_x_preferred":[
        "Ya'an"
    ],
    "name:tur_x_preferred":[
        "Ya'an"
    ],
    "name:und_x_variant":[
        "Ya\u2019an",
        "\u4e9a\u5b89"
    ],
    "name:urd_x_preferred":[
        "\u06cc\u0622\u0646"
    ],
    "name:vie_x_preferred":[
        "Nh\u00e3 An"
    ],
    "name:war_x_preferred":[
        "Yaan"
    ],
    "name:wuu_x_preferred":[
        "\u96c5\u5b89\u5e02"
    ],
    "name:zho_x_preferred":[
        "\u96c5\u5b89\u5e02"
    ],
    "wof:name":"Ya'an",
    "wof:placetype":"locality"
},
  "geometry": {"coordinates":[103.13800000000001,34.1096],"type":"Point"}
}