{
  "type": "Feature",
  "properties": {
    "gn:admin1_code":"29.0",
    "gn:asciiname":"Yaocaoping",
    "gn:country_code":"CN",
    "gn:dem":2723,
    "gn:feature_class":"P",
    "gn:feature_code":"PPL",
    "gn:name":"Yaocaoping",
    "gn:population":0,
    "gn:timezone":"Asia/Shanghai",
    "iso:country":"CN",
    "name:zho_x_preferred":[
        "\u836f\u8349\u576a"
    ],
    "wof:name":"Yaocaoping",
    "wof:placetype":"locality"
},
  "geometry": {"coordinates":[100.587,26.6977],"type":"Point"}
}