{
  "type": "Feature",
  "properties": {
    "gn:admin1_code":"11",
    "gn:asciiname":"Hongshandian",
    "gn:country_code":"CN",
    "gn:dem":133,
    "gn:feature_class":"P",
    "gn:feature_code":"PPL",
    "gn:name":"Hongshandian",
    "gn:population":0,
    "gn:timezone":"Asia/Shanghai",
    "iso:country":"CN",
    "name:zho_x_preferred":[
        "\u6d2a\u5c71\u6bbf\u9547"
    ],
    "wof:name":"Hongshandian",
    "wof:placetype":"locality"
},
  "geometry": {"coordinates":[112.09944,27.59139],"type":"Point"}
}