{
  "type": "Feature",
  "properties": {
    "gn:admin1_code":"25",
    "gn:asciiname":"Jiekuangyuanjia",
    "gn:country_code":"CN",
    "gn:dem":68,
    "gn:feature_class":"P",
    "gn:feature_code":"PPL",
    "gn:name":"Jiekuangyuanjia",
    "gn:population":0,
    "gn:timezone":"Asia/Shanghai",
    "iso:country":"CN",
    "name:zho_x_preferred":[
        "\u63a5\u593c\u8881\u5bb6"
    ],
    "wof:name":"Jiekuangyuanjia",
    "wof:placetype":"locality"
},
  "geometry": {"coordinates":[120.916,37.7155],"type":"Point"}
}