{
  "type": "Feature",
  "properties": {
    "gn:admin1_code":"14.0",
    "gn:asciiname":"Caneilong",
    "gn:country_code":"CN",
    "gn:dem":4154,
    "gn:feature_class":"P",
    "gn:feature_code":"PPL",
    "gn:name":"Caneilong",
    "gn:population":0,
    "gn:timezone":"Asia/Urumqi",
    "iso:country":"CN",
    "name:zho_x_preferred":[
        "\u64e6\u5185\u9f99"
    ],
    "wof:name":"Caneilong",
    "wof:placetype":"locality"
},
  "geometry": {"coordinates":[96.71397,31.20134],"type":"Point"}
}