{
  "type": "Feature",
  "properties": {
    "gn:admin1_code":"3.0",
    "gn:asciiname":"Tuanlongsi",
    "gn:country_code":"CN",
    "gn:dem":217,
    "gn:feature_class":"P",
    "gn:feature_code":"PPL",
    "gn:name":"Tuanlongsi",
    "gn:population":0,
    "gn:timezone":"Asia/Shanghai",
    "iso:country":"CN",
    "name:und_x_variant":[
        "\u56e2\u9f99\u5bfa"
    ],
    "wof:name":"Tuanlongsi",
    "wof:placetype":"locality"
},
  "geometry": {"coordinates":[115.90631,25.65546],"type":"Point"}
}