{
  "type": "Feature",
  "properties": {
    "gn:admin1_code":"24",
    "gn:asciiname":"Xisanjiao",
    "gn:country_code":"CN",
    "gn:dem":1165,
    "gn:feature_class":"P",
    "gn:feature_code":"PPL",
    "gn:name":"Xisanjiao",
    "gn:population":0,
    "gn:timezone":"Asia/Shanghai",
    "iso:country":"CN",
    "name:und_x_variant":[
        "San-chiao-ts\u2019un",
        "San-chiao",
        "Sanjiao",
        "Xisanjiao"
    ],
    "name:zho_x_preferred":[
        "\u897f\u4e09\u89d2"
    ],
    "wof:name":"Xisanjiao",
    "wof:placetype":"locality"
},
  "geometry": {"coordinates":[113.14473,38.75665],"type":"Point"}
}