{
  "type": "Feature",
  "properties": {
    "gn:admin1_code":"12.0",
    "gn:asciiname":"Zhanjiawan",
    "gn:country_code":"CN",
    "gn:dem":57,
    "gn:feature_class":"P",
    "gn:feature_code":"PPL",
    "gn:name":"Zhanjiawan",
    "gn:population":0,
    "gn:timezone":"Asia/Shanghai",
    "iso:country":"CN",
    "name:zho_x_preferred":[
        "\u7ad9\u5bb6\u6e7e"
    ],
    "wof:name":"Zhanjiawan",
    "wof:placetype":"locality"
},
  "geometry": {"coordinates":[112.28997,31.55357],"type":"Point"}
}