{
  "type": "Feature",
  "properties": {
    "gn:admin1_code":"4.0",
    "gn:asciiname":"Xindong",
    "gn:country_code":"CN",
    "gn:dem":-1,
    "gn:feature_class":"P",
    "gn:feature_code":"PPL",
    "gn:name":"Xindong",
    "gn:population":0,
    "gn:timezone":"Asia/Shanghai",
    "iso:country":"CN",
    "name:zho_x_preferred":[
        "Xindong"
    ],
    "name:zho_x_variant":[
        "\u65b0\u4e1c"
    ],
    "wof:name":"Xindong",
    "wof:placetype":"locality"
},
  "geometry": {"coordinates":[120.27068,34.00776],"type":"Point"}
}