{
  "type": "Feature",
  "properties": {
    "gn:admin1_code":"29.0",
    "gn:asciiname":"Daposhu",
    "gn:country_code":"CN",
    "gn:dem":2030,
    "gn:feature_class":"P",
    "gn:feature_code":"PPL",
    "gn:name":"Daposhu",
    "gn:population":0,
    "gn:timezone":"Asia/Shanghai",
    "iso:country":"CN",
    "name:zho_x_preferred":[
        "\u5927\u5a46\u6811"
    ],
    "wof:name":"Daposhu",
    "wof:placetype":"locality"
},
  "geometry": {"coordinates":[102.438,25.6793],"type":"Point"}
}