{
  "type": "Feature",
  "properties": {
    "gn:admin1_code":"24.0",
    "gn:asciiname":"Xiaohetou",
    "gn:cc2":"CN",
    "gn:country_code":"CN",
    "gn:dem":1350,
    "gn:feature_class":"P",
    "gn:feature_code":"PPL",
    "gn:name":"Xiaohetou",
    "gn:population":0,
    "gn:timezone":"Asia/Shanghai",
    "iso:country":"CN",
    "name:und_x_variant":[
        "Hsiao-ho-t\u2019ou",
        "Xiaohetou"
    ],
    "wof:name":"Xiaohetou",
    "wof:placetype":"locality"
},
  "geometry": {"coordinates":[111.76888999999998,39.03417],"type":"Point"}
}