{
  "type": "Feature",
  "properties": {
    "gn:admin1_code":"11.0",
    "gn:asciiname":"Douchongtou",
    "gn:country_code":"CN",
    "gn:dem":1084,
    "gn:feature_class":"P",
    "gn:feature_code":"PPL",
    "gn:name":"Douchongtou",
    "gn:population":0,
    "gn:timezone":"Asia/Shanghai",
    "iso:country":"CN",
    "name:zho_x_preferred":[
        "\u9661\u51b2\u5934"
    ],
    "wof:name":"Douchongtou",
    "wof:placetype":"locality"
},
  "geometry": {"coordinates":[110.17707,26.3035],"type":"Point"}
}