{
  "type": "Feature",
  "properties": {
    "gn:admin1_code":"14.0",
    "gn:asciiname":"Dayadi",
    "gn:country_code":"CN",
    "gn:dem":3638,
    "gn:feature_class":"P",
    "gn:feature_code":"PPL",
    "gn:name":"Dayadi",
    "gn:population":0,
    "gn:timezone":"Asia/Urumqi",
    "iso:country":"CN",
    "name:zho_x_preferred":[
        "\u8fbe\u4e9a\u5e95"
    ],
    "wof:name":"Dayadi",
    "wof:placetype":"locality"
},
  "geometry": {"coordinates":[95.72824,30.91253],"type":"Point"}
}