{
  "type": "Feature",
  "properties": {
    "gn:admin1_code":"29.0",
    "gn:asciiname":"Damanzhao",
    "gn:country_code":"CN",
    "gn:dem":1321,
    "gn:feature_class":"P",
    "gn:feature_code":"PPL",
    "gn:name":"Damanzhao",
    "gn:population":0,
    "gn:timezone":"Asia/Shanghai",
    "iso:country":"CN",
    "name:zho_x_preferred":[
        "\u5927\u6ee1\u5146"
    ],
    "wof:name":"Damanzhao",
    "wof:placetype":"locality"
},
  "geometry": {"coordinates":[100.247,24.4313],"type":"Point"}
}