{
  "type": "Feature",
  "properties": {
    "gn:admin1_code":"6.0",
    "gn:asciiname":"Shangduoba",
    "gn:country_code":"CN",
    "gn:dem":2065,
    "gn:feature_class":"P",
    "gn:feature_code":"PPL",
    "gn:name":"Shangduoba",
    "gn:population":0,
    "gn:timezone":"Asia/Shanghai",
    "iso:country":"CN",
    "name:zho_x_preferred":[
        "\u4e0a\u54c6\u5df4"
    ],
    "wof:name":"Shangduoba",
    "wof:placetype":"locality"
},
  "geometry": {"coordinates":[101.91766,36.07877],"type":"Point"}
}