{
  "type": "Feature",
  "properties": {
    "gn:admin1_code":"26.0",
    "gn:asciiname":"Haoxin Zhuangcun",
    "gn:country_code":"CN",
    "gn:dem":979,
    "gn:feature_class":"P",
    "gn:feature_code":"PPL",
    "gn:name":"Haoxin Zhuangcun",
    "gn:population":0,
    "gn:timezone":"Asia/Shanghai",
    "iso:country":"CN",
    "name:zho_x_preferred":[
        "\u90dd\u65b0\u5e84\u6751"
    ],
    "wof:name":"Haoxin Zhuangcun",
    "wof:placetype":"locality"
},
  "geometry": {"coordinates":[109.989,37.8845],"type":"Point"}
}