{
  "type": "Feature",
  "properties": {
    "gn:admin1_code":"16.0",
    "gn:asciiname":"Ganchang",
    "gn:country_code":"CN",
    "gn:dem":252,
    "gn:feature_class":"P",
    "gn:feature_code":"PPL",
    "gn:name":"Ganchang",
    "gn:population":0,
    "gn:timezone":"Asia/Shanghai",
    "iso:country":"CN",
    "name:zho_x_preferred":[
        "\u611f\u5e38"
    ],
    "wof:name":"Ganchang",
    "wof:placetype":"locality"
},
  "geometry": {"coordinates":[107.779,23.6414],"type":"Point"}
}