{
  "type": "Feature",
  "properties": {
    "gn:admin1_code":"3.0",
    "gn:asciiname":"Jiangjunqian",
    "gn:country_code":"CN",
    "gn:dem":524,
    "gn:feature_class":"P",
    "gn:feature_code":"PPL",
    "gn:name":"Jiangjunqian",
    "gn:population":0,
    "gn:timezone":"Asia/Shanghai",
    "iso:country":"CN",
    "name:und_x_variant":[
        "\u5c06\u519b\u524d"
    ],
    "wof:name":"Jiangjunqian",
    "wof:placetype":"locality"
},
  "geometry": {"coordinates":[115.82071999999999,26.01457000000001],"type":"Point"}
}