{
  "type": "Feature",
  "properties": {
    "gn:admin1_code":"20.0",
    "gn:asciiname":"Baga Borihe",
    "gn:country_code":"CN",
    "gn:dem":362,
    "gn:feature_class":"P",
    "gn:feature_code":"PPLA4",
    "gn:name":"Baga Borihe",
    "gn:population":0,
    "gn:timezone":"Asia/Shanghai",
    "iso:country":"CN",
    "name:und_x_variant":[
        "Baga Borihe Sumu"
    ],
    "name:zho_x_preferred":[
        "\u5df4\u560e\u6ce2\u65e5\u548c"
    ],
    "name:zho_x_variant":[
        "\u5df4\u560e\u6ce2\u65e5\u548c\u82cf\u6728"
    ],
    "wof:name":"Baga Borihe",
    "wof:placetype":"locality"
},
  "geometry": {"coordinates":[120.5599,42.92555],"type":"Point"}
}