{
  "type": "Feature",
  "properties": {
    "gn:admin1_code":"24.0",
    "gn:asciiname":"Dazecun",
    "gn:country_code":"CN",
    "gn:dem":516,
    "gn:feature_class":"P",
    "gn:feature_code":"PPL",
    "gn:name":"Dazecun",
    "gn:population":0,
    "gn:timezone":"Asia/Shanghai",
    "iso:country":"CN",
    "name:und_x_variant":[
        "\u5927\u6cfd\u6751"
    ],
    "name:zho_x_preferred":[
        "\u5927\u6cfd\u6751"
    ],
    "wof:name":"Dazecun",
    "wof:placetype":"locality"
},
  "geometry": {"coordinates":[111.29044,35.30793],"type":"Point"}
}