{
  "type": "Feature",
  "properties": {
    "gn:admin1_code":"29.0",
    "gn:asciiname":"Dawopu",
    "gn:country_code":"CN",
    "gn:dem":2422,
    "gn:feature_class":"P",
    "gn:feature_code":"PPL",
    "gn:name":"Dawopu",
    "gn:population":0,
    "gn:timezone":"Asia/Shanghai",
    "iso:country":"CN",
    "name:zho_x_preferred":[
        "\u5927\u7a9d\u94fa"
    ],
    "wof:name":"Dawopu",
    "wof:placetype":"locality"
},
  "geometry": {"coordinates":[101.251,26.184],"type":"Point"}
}