{
  "type": "Feature",
  "properties": {
    "gn:admin1_code":"26.0",
    "gn:asciiname":"Yangdaoyucun",
    "gn:country_code":"CN",
    "gn:dem":959,
    "gn:feature_class":"P",
    "gn:feature_code":"PPL",
    "gn:name":"Yangdaoyucun",
    "gn:population":0,
    "gn:timezone":"Asia/Shanghai",
    "iso:country":"CN",
    "name:zho_x_preferred":[
        "\u6768\u9053\u5cea\u6751"
    ],
    "wof:name":"Yangdaoyucun",
    "wof:placetype":"locality"
},
  "geometry": {"coordinates":[110.17659,37.40833],"type":"Point"}
}