{
  "type": "Feature",
  "properties": {
    "gn:admin1_code":"25.0",
    "gn:asciiname":"Qianshiziyuancun",
    "gn:country_code":"CN",
    "gn:dem":36,
    "gn:feature_class":"P",
    "gn:feature_code":"PPL",
    "gn:name":"Qianshiziyuancun",
    "gn:population":0,
    "gn:timezone":"Asia/Shanghai",
    "iso:country":"CN",
    "name:zho_x_preferred":[
        "\u524d\u67ff\u5b50\u56ed\u6751"
    ],
    "wof:name":"Qianshiziyuancun",
    "wof:placetype":"locality"
},
  "geometry": {"coordinates":[119.47064,36.35538],"type":"Point"}
}