{
  "type": "Feature",
  "properties": {
    "gn:admin1_code":"19.0",
    "gn:asciiname":"Hanjiayucun",
    "gn:country_code":"CN",
    "gn:dem":192,
    "gn:feature_class":"P",
    "gn:feature_code":"PPL",
    "gn:name":"Hanjiayucun",
    "gn:population":0,
    "gn:timezone":"Asia/Shanghai",
    "iso:country":"CN",
    "name:zho_x_preferred":[
        "\u97e9\u5bb6\u5cea\u6751"
    ],
    "wof:name":"Hanjiayucun",
    "wof:placetype":"locality"
},
  "geometry": {"coordinates":[123.17648,41.0152],"type":"Point"}
}