{
  "type": "Feature",
  "properties": {
    "gn:admin1_code":"11",
    "gn:asciiname":"Qingshanpu",
    "gn:cc2":"CN",
    "gn:country_code":"CN",
    "gn:dem":80,
    "gn:feature_class":"P",
    "gn:feature_code":"PPL",
    "gn:name":"Qingshanpu",
    "gn:population":0,
    "gn:timezone":"Asia/Shanghai",
    "iso:country":"CN",
    "name:und_x_variant":[
        "Ch\u2019ing-shan-shih",
        "Qingshanshi",
        "Qingshanpu"
    ],
    "name:zho_x_preferred":[
        "\u9752\u5c71\u94fa\u9547"
    ],
    "wof:name":"Qingshanpu",
    "wof:placetype":"locality"
},
  "geometry": {"coordinates":[113.17139,28.46528],"type":"Point"}
}