{
  "type": "Feature",
  "properties": {
    "gn:admin1_code":"11.0",
    "gn:asciiname":"Languchong",
    "gn:country_code":"CN",
    "gn:dem":152,
    "gn:feature_class":"P",
    "gn:feature_code":"PPL",
    "gn:name":"Languchong",
    "gn:population":0,
    "gn:timezone":"Asia/Shanghai",
    "iso:country":"CN",
    "name:zho_x_preferred":[
        "\u680f\u8c37\u51b2"
    ],
    "wof:name":"Languchong",
    "wof:placetype":"locality"
},
  "geometry": {"coordinates":[111.24057000000001,28.7919],"type":"Point"}
}