{
  "type": "Feature",
  "properties": {
    "gn:admin1_code":"30.0",
    "gn:asciiname":"Rongshu",
    "gn:country_code":"CN",
    "gn:dem":41,
    "gn:feature_class":"P",
    "gn:feature_code":"PPL",
    "gn:name":"Rongshu",
    "gn:population":0,
    "gn:timezone":"Asia/Shanghai",
    "iso:country":"CN",
    "name:zho_x_preferred":[
        "\u6995\u6811"
    ],
    "wof:name":"Rongshu",
    "wof:placetype":"locality"
},
  "geometry": {"coordinates":[112.22557,22.73557000000001],"type":"Point"}
}