{
  "type": "Feature",
  "properties": {
    "gn:admin1_code":"15.0",
    "gn:asciiname":"Loutai",
    "gn:country_code":"CN",
    "gn:dem":1239,
    "gn:feature_class":"P",
    "gn:feature_code":"PPL",
    "gn:name":"Loutai",
    "gn:population":0,
    "gn:timezone":"Asia/Shanghai",
    "iso:country":"CN",
    "name:zho_x_preferred":[
        "\u6402\u53f0"
    ],
    "wof:name":"Loutai",
    "wof:placetype":"locality"
},
  "geometry": {"coordinates":[107.78,35.4234],"type":"Point"}
}