{
  "type": "Feature",
  "properties": {
    "gn:admin1_code":"8.0",
    "gn:asciiname":"Fumin",
    "gn:country_code":"CN",
    "gn:dem":195,
    "gn:feature_class":"P",
    "gn:feature_code":"PPL",
    "gn:name":"Fumin",
    "gn:population":0,
    "gn:timezone":"Asia/Shanghai",
    "iso:country":"CN",
    "name:deu_x_preferred":[
        "Fumin"
    ],
    "name:fra_x_preferred":[
        "Fumin"
    ],
    "name:zho_x_preferred":[
        "\u5bcc\u6c11"
    ],
    "wof:name":"Fumin",
    "wof:placetype":"locality"
},
  "geometry": {"coordinates":[124.00684,48.20399000000001],"type":"Point"}
}