{
  "type": "Feature",
  "properties": {
    "gn:admin1_code":"15.0",
    "gn:asciiname":"Yaoyu",
    "gn:country_code":"CN",
    "gn:dem":1400,
    "gn:feature_class":"P",
    "gn:feature_code":"PPL",
    "gn:name":"Yaoyu",
    "gn:population":0,
    "gn:timezone":"Asia/Shanghai",
    "iso:country":"CN",
    "name:zho_x_preferred":[
        "\u7476\u5cea"
    ],
    "wof:name":"Yaoyu",
    "wof:placetype":"locality"
},
  "geometry": {"coordinates":[105.105,34.1272],"type":"Point"}
}