{
  "type": "Feature",
  "properties": {
    "gn:admin1_code":"9.0",
    "gn:asciiname":"Dongdajiao",
    "gn:country_code":"CN",
    "gn:dem":125,
    "gn:feature_class":"P",
    "gn:feature_code":"PPL",
    "gn:name":"Dongdajiao",
    "gn:population":0,
    "gn:timezone":"Asia/Shanghai",
    "iso:country":"CN",
    "name:zho_x_preferred":[
        "\u4e1c\u5927\u90ca"
    ],
    "wof:name":"Dongdajiao",
    "wof:placetype":"locality"
},
  "geometry": {"coordinates":[112.63484,34.6897],"type":"Point"}
}