{
  "type": "Feature",
  "properties": {
    "gn:admin1_code":"30.0",
    "gn:asciiname":"Dapokeng",
    "gn:country_code":"CN",
    "gn:dem":132,
    "gn:feature_class":"P",
    "gn:feature_code":"PPL",
    "gn:name":"Dapokeng",
    "gn:population":0,
    "gn:timezone":"Asia/Shanghai",
    "iso:country":"CN",
    "name:zho_x_preferred":[
        "\u5927\u5761\u5751"
    ],
    "wof:name":"Dapokeng",
    "wof:placetype":"locality"
},
  "geometry": {"coordinates":[113.57306,23.93652],"type":"Point"}
}