{
  "type": "Feature",
  "properties": {
    "gn:country":"CN",
    "gn:fcode":"PPL",
    "gn:population":198423,
    "iso:country":"CN",
    "name:ceb_x_preferred":[
        "Kaiyuan"
    ],
    "name:deu_x_preferred":[
        "Kaiyuan"
    ],
    "name:fra_x_preferred":[
        "Kaiyuan"
    ],
    "name:kor_x_preferred":[
        "\uce74\uc774\uc704\uc548\uc2dc"
    ],
    "name:mlg_x_preferred":[
        "Kaiyuan"
    ],
    "name:nld_x_preferred":[
        "Kaiyuan"
    ],
    "name:nor_x_preferred":[
        "Kaiyuan"
    ],
    "name:pol_x_preferred":[
        "Kaiyuan"
    ],
    "name:rus_x_preferred":[
        "\u041a\u0430\u0439\u044e\u0430\u043d\u044c"
    ],
    "name:swe_x_preferred":[
        "Kaiyuan"
    ],
    "name:und_x_variant":[
        "Ami-hsien"
    ],
    "qs:name":"Kaiyuan",
    "qs:photos_9r":0,
    "qs:photos_sr":0,
    "qs:pop_sr":"9",
    "wd:wordcount":147,
    "wof:name":"Kaiyuan",
    "wof:placetype":"locality",
    "wof:population":198423
},
  "geometry": {"coordinates":[103.30372,23.69767],"type":"Point"}
}