{
  "type": "Feature",
  "properties": {
    "gn:country":"CN",
    "gn:fcode":"PPL",
    "gn:pop":198423,
    "iso:country":"CN",
    "name:rus_x_preferred":[
        "\u041a\u0430\u0439\u044e\u0430\u043d\u044c"
    ],
    "name:unk_x_variant":[
        "Ami-hsien"
    ],
    "qs:name":"Kaiyuan",
    "qs:photos_9r":0,
    "qs:photos_sr":0,
    "qs:pop_sr":"9",
    "wd:wordcount":147,
    "wof:name":"Kaiyuan",
    "wof:placetype":"locality",
    "wof:population":198423
},
  "geometry": {"coordinates":[103.30372,23.69767],"type":"Point"}
}