{
  "type": "Feature",
  "properties": {
    "gn:admin1_code":"16.0",
    "gn:asciiname":"Shuijintiantou",
    "gn:country_code":"CN",
    "gn:dem":139,
    "gn:feature_class":"P",
    "gn:feature_code":"PPL",
    "gn:name":"Shuijintiantou",
    "gn:population":0,
    "gn:timezone":"Asia/Shanghai",
    "iso:country":"CN",
    "name:zho_x_preferred":[
        "\u6c34\u6d78\u7530\u5934"
    ],
    "wof:name":"Shuijintiantou",
    "wof:placetype":"locality"
},
  "geometry": {"coordinates":[110.637,23.093],"type":"Point"}
}