{
  "type": "Feature",
  "properties": {
    "gn:admin1_code":"33.0",
    "gn:asciiname":"Gaiping",
    "gn:country_code":"CN",
    "gn:dem":1122,
    "gn:feature_class":"P",
    "gn:feature_code":"PPL",
    "gn:name":"Gaiping",
    "gn:population":0,
    "gn:timezone":"Asia/Shanghai",
    "iso:country":"CN",
    "name:zho_x_preferred":[
        "\u76d6\u576a"
    ],
    "wof:name":"Gaiping",
    "wof:placetype":"locality"
},
  "geometry": {"coordinates":[107.86368,29.5904],"type":"Point"}
}