{
  "type": "Feature",
  "properties": {
    "gn:admin1_code":"29.0",
    "gn:asciiname":"Baihushan",
    "gn:country_code":"CN",
    "gn:dem":1364,
    "gn:feature_class":"P",
    "gn:feature_code":"PPL",
    "gn:name":"Baihushan",
    "gn:population":0,
    "gn:timezone":"Asia/Shanghai",
    "iso:country":"CN",
    "name:zho_x_preferred":[
        "\u767d\u864e\u5c71"
    ],
    "wof:name":"Baihushan",
    "wof:placetype":"locality"
},
  "geometry": {"coordinates":[99.24169999999999,24.2702],"type":"Point"}
}