{
  "type": "Feature",
  "properties": {
    "gn:admin1_code":"20.0",
    "gn:asciiname":"Wugenaobao",
    "gn:country_code":"CN",
    "gn:dem":1506,
    "gn:feature_class":"P",
    "gn:feature_code":"PPL",
    "gn:name":"Wugenaobao",
    "gn:population":0,
    "gn:timezone":"Asia/Shanghai",
    "iso:country":"CN",
    "name:und_x_variant":[
        "\u4e94\u4e2a\u8111\u5305"
    ],
    "wof:name":"Wugenaobao",
    "wof:placetype":"locality"
},
  "geometry": {"coordinates":[113.01139999999999,41.61004000000001],"type":"Point"}
}