{
  "type": "Feature",
  "properties": {
    "gn:admin1_code":"19.0",
    "gn:asciiname":"Guandongchangcun",
    "gn:country_code":"CN",
    "gn:dem":510,
    "gn:feature_class":"P",
    "gn:feature_code":"PPL",
    "gn:name":"Guandongchangcun",
    "gn:population":0,
    "gn:timezone":"Asia/Shanghai",
    "iso:country":"CN",
    "name:zho_x_preferred":[
        "\u5173\u4e1c\u573a\u6751"
    ],
    "wof:name":"Guandongchangcun",
    "wof:placetype":"locality"
},
  "geometry": {"coordinates":[125.042,41.9201],"type":"Point"}
}