{
  "type": "Feature",
  "properties": {
    "gn:admin1_code":"7.0",
    "gn:asciiname":"Daying Kengxi",
    "gn:country_code":"CN",
    "gn:dem":199,
    "gn:feature_class":"P",
    "gn:feature_code":"PPL",
    "gn:name":"Daying Kengxi",
    "gn:population":0,
    "gn:timezone":"Asia/Shanghai",
    "iso:country":"CN",
    "name:und_x_variant":[
        "\u5927\u8425\u5751\u6eaa"
    ],
    "name:zho_x_preferred":[
        "Daying Kengxi"
    ],
    "wof:name":"Daying Kengxi",
    "wof:placetype":"locality"
},
  "geometry": {"coordinates":[119.24314,26.16342],"type":"Point"}
}