{
  "type": "Feature",
  "properties": {
    "gn:admin1_code":"3",
    "gn:asciiname":"Xiaobacun",
    "gn:country_code":"CN",
    "gn:dem":50,
    "gn:feature_class":"P",
    "gn:feature_code":"PPL",
    "gn:name":"Xiaobacun",
    "gn:population":0,
    "gn:timezone":"Asia/Shanghai",
    "iso:country":"CN",
    "name:und_x_variant":[
        "\u5c0f\u5df4\u6751"
    ],
    "wof:name":"Xiaobacun",
    "wof:placetype":"locality"
},
  "geometry": {"coordinates":[115.72589000000001,28.02373],"type":"Point"}
}