{
  "type": "Feature",
  "properties": {
    "gn:admin1_code":"29.0",
    "gn:asciiname":"Xiangziping",
    "gn:country_code":"CN",
    "gn:dem":1283,
    "gn:feature_class":"P",
    "gn:feature_code":"PPL",
    "gn:name":"Xiangziping",
    "gn:population":0,
    "gn:timezone":"Asia/Shanghai",
    "iso:country":"CN",
    "name:zho_x_preferred":[
        "\u6a61\u5b50\u576a"
    ],
    "wof:name":"Xiangziping",
    "wof:placetype":"locality"
},
  "geometry": {"coordinates":[100.423,26.4748],"type":"Point"}
}