{
  "type": "Feature",
  "properties": {
    "gn:admin1_code":"29.0",
    "gn:asciiname":"Ganlanzhai",
    "gn:country_code":"CN",
    "gn:dem":1491,
    "gn:feature_class":"P",
    "gn:feature_code":"PPL",
    "gn:name":"Ganlanzhai",
    "gn:population":0,
    "gn:timezone":"Asia/Shanghai",
    "iso:country":"CN",
    "name:zho_x_preferred":[
        "\u6a44\u6984\u5be8"
    ],
    "wof:name":"Ganlanzhai",
    "wof:placetype":"locality"
},
  "geometry": {"coordinates":[98.9479,24.2656],"type":"Point"}
}