{
  "type": "Feature",
  "properties": {
    "gn:admin1_code":"9.0",
    "gn:asciiname":"Jiufu",
    "gn:country_code":"CN",
    "gn:dem":1253,
    "gn:feature_class":"P",
    "gn:feature_code":"PPL",
    "gn:name":"Jiufu",
    "gn:population":0,
    "gn:timezone":"Asia/Shanghai",
    "iso:country":"CN",
    "name:zho_x_preferred":[
        "\u9152\u5bcc"
    ],
    "wof:name":"Jiufu",
    "wof:placetype":"locality"
},
  "geometry": {"coordinates":[110.56466,34.20296],"type":"Point"}
}