{
  "type": "Feature",
  "properties": {
    "gn:admin1_code":"18",
    "gn:asciiname":"Nilagai",
    "gn:country_code":"CN",
    "gn:dem":1640,
    "gn:feature_class":"P",
    "gn:feature_code":"PPL",
    "gn:name":"Nilagai",
    "gn:population":0,
    "gn:timezone":"Asia/Shanghai",
    "iso:country":"CN",
    "name:zho_x_preferred":[
        "\u6ce5\u62c9\u76d6"
    ],
    "wof:name":"Nilagai",
    "wof:placetype":"locality"
},
  "geometry": {"coordinates":[105.03,25.5767],"type":"Point"}
}