{
  "type": "Feature",
  "properties": {
    "gn:admin1_code":"1.0",
    "gn:asciiname":"Lidongloucun",
    "gn:country_code":"CN",
    "gn:dem":23,
    "gn:feature_class":"P",
    "gn:feature_code":"PPL",
    "gn:name":"Lidongloucun",
    "gn:population":0,
    "gn:timezone":"Asia/Shanghai",
    "iso:country":"CN",
    "name:zho_x_preferred":[
        "\u674e\u4e1c\u697c\u6751"
    ],
    "wof:name":"Lidongloucun",
    "wof:placetype":"locality"
},
  "geometry": {"coordinates":[116.30364,32.13899],"type":"Point"}
}