{
  "type": "Feature",
  "properties": {
    "gn:admin1_code":"24",
    "gn:asciiname":"Majiazao",
    "gn:cc2":"CN",
    "gn:country_code":"CN",
    "gn:dem":1017,
    "gn:feature_class":"P",
    "gn:feature_code":"PPL",
    "gn:name":"Majiazao",
    "gn:population":0,
    "gn:timezone":"Asia/Shanghai",
    "iso:country":"CN",
    "name:und_x_variant":[
        "Ma-chia-ts\u2019ao",
        "Majiazao"
    ],
    "wof:name":"Majiazao",
    "wof:placetype":"locality"
},
  "geometry": {"coordinates":[114.05889000000001,40.135],"type":"Point"}
}