{
  "type": "Feature",
  "properties": {
    "gn:admin1_code":"11.0",
    "gn:asciiname":"Wulidui",
    "gn:country_code":"CN",
    "gn:dem":155,
    "gn:feature_class":"P",
    "gn:feature_code":"PPL",
    "gn:name":"Wulidui",
    "gn:population":0,
    "gn:timezone":"Asia/Shanghai",
    "iso:country":"CN",
    "name:und_x_variant":[
        "Wu-li-tui",
        "Wulidui"
    ],
    "name:zho_x_preferred":[
        "\u4e94\u91cc\u5806"
    ],
    "wof:name":"Wulidui",
    "wof:placetype":"locality"
},
  "geometry": {"coordinates":[112.07793999999998,28.10701],"type":"Point"}
}