{
  "type": "Feature",
  "properties": {
    "gn:admin1_code":"12.0",
    "gn:asciiname":"Shuangyanwan",
    "gn:country_code":"CN",
    "gn:dem":1137,
    "gn:feature_class":"P",
    "gn:feature_code":"PPL",
    "gn:name":"Shuangyanwan",
    "gn:population":0,
    "gn:timezone":"Asia/Shanghai",
    "iso:country":"CN",
    "name:zho_x_preferred":[
        "\u53cc\u5830\u6e7e"
    ],
    "wof:name":"Shuangyanwan",
    "wof:placetype":"locality"
},
  "geometry": {"coordinates":[110.49015,29.945],"type":"Point"}
}