{
  "type": "Feature",
  "properties": {
    "gn:admin1_code":"30.0",
    "gn:asciiname":"Xiahuangdi",
    "gn:country_code":"CN",
    "gn:dem":239,
    "gn:feature_class":"P",
    "gn:feature_code":"PPL",
    "gn:name":"Xiahuangdi",
    "gn:population":0,
    "gn:timezone":"Asia/Shanghai",
    "iso:country":"CN",
    "name:zho_x_preferred":[
        "\u4e0b\u9ec4\u5730"
    ],
    "wof:name":"Xiahuangdi",
    "wof:placetype":"locality"
},
  "geometry": {"coordinates":[116.00978000000001,24.60362000000001],"type":"Point"}
}