{
  "type": "Feature",
  "properties": {
    "gn:admin1_code":"1.0",
    "gn:asciiname":"Erlang",
    "gn:country_code":"CN",
    "gn:dem":32,
    "gn:feature_class":"P",
    "gn:feature_code":"PPL",
    "gn:name":"Erlang",
    "gn:population":0,
    "gn:timezone":"Asia/Shanghai",
    "iso:country":"CN",
    "name:cat_x_preferred":[
        "Erlang"
    ],
    "name:ces_x_preferred":[
        "Erlang"
    ],
    "name:deu_x_preferred":[
        "Erlang"
    ],
    "name:fin_x_preferred":[
        "Erlang"
    ],
    "name:fra_x_preferred":[
        "Erlang"
    ],
    "name:ita_x_preferred":[
        "Erlang"
    ],
    "name:nld_x_preferred":[
        "Erlang"
    ],
    "name:nor_x_preferred":[
        "Erlang"
    ],
    "name:pol_x_preferred":[
        "Erlang"
    ],
    "name:por_x_preferred":[
        "Erlang"
    ],
    "name:slv_x_preferred":[
        "Erlang"
    ],
    "name:spa_x_preferred":[
        "Erlang"
    ],
    "name:zho_x_preferred":[
        "Erlang"
    ],
    "wof:name":"Erlang",
    "wof:placetype":"locality"
},
  "geometry": {"coordinates":[115.81667,33.41667],"type":"Point"}
}