{
  "type": "Feature",
  "properties": {
    "gn:admin1_code":"18",
    "gn:asciiname":"Wensugou",
    "gn:country_code":"CN",
    "gn:dem":920,
    "gn:feature_class":"P",
    "gn:feature_code":"PPL",
    "gn:name":"Wensugou",
    "gn:population":0,
    "gn:timezone":"Asia/Shanghai",
    "iso:country":"CN",
    "name:zho_x_preferred":[
        "\u6587\u82cf\u6c9f"
    ],
    "wof:name":"Wensugou",
    "wof:placetype":"locality"
},
  "geometry": {"coordinates":[107.675,27.1271],"type":"Point"}
}