{
  "type": "Feature",
  "properties": {
    "gn:admin1_code":"14.0",
    "gn:asciiname":"Longda",
    "gn:country_code":"CN",
    "gn:dem":3893,
    "gn:feature_class":"P",
    "gn:feature_code":"PPL",
    "gn:name":"Longda",
    "gn:population":0,
    "gn:timezone":"Asia/Urumqi",
    "iso:country":"CN",
    "name:zho_x_preferred":[
        "\u9f99\u8fbe"
    ],
    "wof:name":"Longda",
    "wof:placetype":"locality"
},
  "geometry": {"coordinates":[98.02719,31.17555],"type":"Point"}
}