{
  "type": "Feature",
  "properties": {
    "gn:admin1_code":"24.0",
    "gn:asciiname":"Baiting",
    "gn:country_code":"CN",
    "gn:dem":1118,
    "gn:feature_class":"P",
    "gn:feature_code":"PPL",
    "gn:name":"Baiting",
    "gn:population":0,
    "gn:timezone":"Asia/Shanghai",
    "iso:country":"CN",
    "name:zho_x_preferred":[
        "\u67cf\u4ead"
    ],
    "wof:name":"Baiting",
    "wof:placetype":"locality"
},
  "geometry": {"coordinates":[111.80750999999999,36.39947],"type":"Point"}
}