{
  "type": "Feature",
  "properties": {
    "gn:admin1_code":"29.0",
    "gn:asciiname":"Lihuishan",
    "gn:country_code":"CN",
    "gn:dem":1906,
    "gn:feature_class":"P",
    "gn:feature_code":"PPL",
    "gn:name":"Lihuishan",
    "gn:population":0,
    "gn:timezone":"Asia/Shanghai",
    "iso:country":"CN",
    "name:zho_x_preferred":[
        "\u674e\u56de\u5c71"
    ],
    "wof:name":"Lihuishan",
    "wof:placetype":"locality"
},
  "geometry": {"coordinates":[99.0301,25.63300000000001],"type":"Point"}
}