{
  "type": "Feature",
  "properties": {
    "gn:admin1_code":"29.0",
    "gn:asciiname":"Laonanpeng",
    "gn:country_code":"CN",
    "gn:dem":1510,
    "gn:feature_class":"P",
    "gn:feature_code":"PPL",
    "gn:name":"Laonanpeng",
    "gn:population":0,
    "gn:timezone":"Asia/Shanghai",
    "iso:country":"CN",
    "name:zho_x_preferred":[
        "\u8001\u5357\u68da"
    ],
    "wof:name":"Laonanpeng",
    "wof:placetype":"locality"
},
  "geometry": {"coordinates":[99.9487,22.6056],"type":"Point"}
}