{
  "type": "Feature",
  "properties": {
    "gn:admin1_code":"33.0",
    "gn:asciiname":"Chuanqianba",
    "gn:country_code":"CN",
    "gn:dem":1764,
    "gn:feature_class":"P",
    "gn:feature_code":"PPL",
    "gn:name":"Chuanqianba",
    "gn:population":0,
    "gn:timezone":"Asia/Shanghai",
    "iso:country":"CN",
    "name:zho_x_preferred":[
        "\u5ddd\u5811\u575d"
    ],
    "wof:name":"Chuanqianba",
    "wof:placetype":"locality"
},
  "geometry": {"coordinates":[107.84648,29.68221],"type":"Point"}
}