{
  "type": "Feature",
  "properties": {
    "gn:admin1_code":"30",
    "gn:asciiname":"Mowucun",
    "gn:country_code":"CN",
    "gn:dem":16,
    "gn:feature_class":"P",
    "gn:feature_code":"PPL",
    "gn:name":"Mowucun",
    "gn:population":0,
    "gn:timezone":"Asia/Urumqi",
    "iso:country":"CN",
    "name:zho_x_preferred":[
        "\u83ab\u5c4b\u6751"
    ],
    "wof:name":"Mowucun",
    "wof:placetype":"locality"
},
  "geometry": {"coordinates":[110.83028,21.69878],"type":"Point"}
}