{
  "type": "Feature",
  "properties": {
    "gn:admin1_code":"31.0",
    "gn:asciiname":"Pozai",
    "gn:country_code":"CN",
    "gn:dem":4,
    "gn:feature_class":"P",
    "gn:feature_code":"PPL",
    "gn:name":"Pozai",
    "gn:population":0,
    "gn:timezone":"Asia/Shanghai",
    "iso:country":"CN",
    "name:und_x_variant":[
        "\u5761\u4ed4"
    ],
    "wof:name":"Pozai",
    "wof:placetype":"locality"
},
  "geometry": {"coordinates":[110.45276,18.84684],"type":"Point"}
}