{
  "type": "Feature",
  "properties": {
    "gn:admin1_code":"12.0",
    "gn:asciiname":"Yazikou",
    "gn:country_code":"CN",
    "gn:dem":229,
    "gn:feature_class":"P",
    "gn:feature_code":"PPL",
    "gn:name":"Yazikou",
    "gn:population":0,
    "gn:timezone":"Asia/Shanghai",
    "iso:country":"CN",
    "name:zho_x_preferred":[
        "\u57ad\u5b50\u53e3"
    ],
    "wof:name":"Yazikou",
    "wof:placetype":"locality"
},
  "geometry": {"coordinates":[111.34754,32.16233],"type":"Point"}
}