{
  "type": "Feature",
  "properties": {
    "gn:admin1_code":"15.0",
    "gn:asciiname":"Gangou",
    "gn:country_code":"CN",
    "gn:dem":915,
    "gn:feature_class":"P",
    "gn:feature_code":"PPL",
    "gn:name":"Gangou",
    "gn:population":0,
    "gn:timezone":"Asia/Shanghai",
    "iso:country":"CN",
    "name:und_x_variant":[
        "\u7518\u6c9f"
    ],
    "wof:name":"Gangou",
    "wof:placetype":"locality"
},
  "geometry": {"coordinates":[106.19468000000001,33.94755],"type":"Point"}
}