{
  "type": "Feature",
  "properties": {
    "gn:admin1_code":"12.0",
    "gn:asciiname":"Xiangduoyan",
    "gn:country_code":"CN",
    "gn:dem":1272,
    "gn:feature_class":"P",
    "gn:feature_code":"PPL",
    "gn:name":"Xiangduoyan",
    "gn:population":0,
    "gn:timezone":"Asia/Shanghai",
    "iso:country":"CN",
    "name:zho_x_preferred":[
        "\u7965\u6735\u5ca9"
    ],
    "wof:name":"Xiangduoyan",
    "wof:placetype":"locality"
},
  "geometry": {"coordinates":[110.63449,30.59347],"type":"Point"}
}