{
  "type": "Feature",
  "properties": {
    "gn:admin1_code":"7.0",
    "gn:asciiname":"Juxi",
    "gn:country_code":"CN",
    "gn:dem":708,
    "gn:feature_class":"P",
    "gn:feature_code":"PPL",
    "gn:name":"Juxi",
    "gn:population":0,
    "gn:timezone":"Asia/Shanghai",
    "iso:country":"CN",
    "name:zho_x_preferred":[
        "\u8392\u6eaa"
    ],
    "wof:name":"Juxi",
    "wof:placetype":"locality"
},
  "geometry": {"coordinates":[119.32380000000001,26.69702],"type":"Point"}
}