{
  "type": "Feature",
  "properties": {
    "gn:admin1_code":"15",
    "gn:asciiname":"Changguan",
    "gn:country_code":"CN",
    "gn:dem":1280,
    "gn:feature_class":"P",
    "gn:feature_code":"PPL",
    "gn:name":"Changguan",
    "gn:population":0,
    "gn:timezone":"Asia/Shanghai",
    "iso:country":"CN",
    "name:zho_x_preferred":[
        "\u957f\u5b98"
    ],
    "name:zho_x_variant":[
        "\u957f\u5b98\u9547"
    ],
    "wof:name":"Changguan",
    "wof:placetype":"locality"
},
  "geometry": {"coordinates":[107.748,35.4918],"type":"Point"}
}