{
  "type": "Feature",
  "properties": {
    "gn:admin1_code":"21.0",
    "gn:asciiname":"Xiejiagengzi",
    "gn:country_code":"CN",
    "gn:dem":1904,
    "gn:feature_class":"P",
    "gn:feature_code":"PPL",
    "gn:name":"Xiejiagengzi",
    "gn:population":0,
    "gn:timezone":"Asia/Shanghai",
    "iso:country":"CN",
    "name:zho_x_preferred":[
        "\u8c22\u5bb6\u57c2\u5b50"
    ],
    "wof:name":"Xiejiagengzi",
    "wof:placetype":"locality"
},
  "geometry": {"coordinates":[105.58884,35.79344000000001],"type":"Point"}
}