{
  "type": "Feature",
  "properties": {
    "gn:admin1_code":"30.0",
    "gn:asciiname":"Tutian",
    "gn:country_code":"CN",
    "gn:dem":270,
    "gn:feature_class":"P",
    "gn:feature_code":"PPL",
    "gn:name":"Tutian",
    "gn:population":0,
    "gn:timezone":"Asia/Shanghai",
    "iso:country":"CN",
    "name:zho_x_preferred":[
        "\u56fe\u7530"
    ],
    "wof:name":"Tutian",
    "wof:placetype":"locality"
},
  "geometry": {"coordinates":[113.75332,23.35123],"type":"Point"}
}