{
  "type": "Feature",
  "properties": {
    "gn:admin1_code":"32.0",
    "gn:asciiname":"Yanghaishe",
    "gn:country_code":"CN",
    "gn:dem":3841,
    "gn:feature_class":"P",
    "gn:feature_code":"PPL",
    "gn:name":"Yanghaishe",
    "gn:population":0,
    "gn:timezone":"Asia/Shanghai",
    "iso:country":"CN",
    "name:zho_x_preferred":[
        "\u6768\u6d77\u793e"
    ],
    "wof:name":"Yanghaishe",
    "wof:placetype":"locality"
},
  "geometry": {"coordinates":[98.5641,31.9086],"type":"Point"}
}