{
  "type": "Feature",
  "properties": {
    "gn:admin1_code":"26.0",
    "gn:asciiname":"Mianjiagou",
    "gn:country_code":"CN",
    "gn:dem":1244,
    "gn:feature_class":"P",
    "gn:feature_code":"PPL",
    "gn:name":"Mianjiagou",
    "gn:population":0,
    "gn:timezone":"Asia/Shanghai",
    "iso:country":"CN",
    "name:zho_x_preferred":[
        "\u68c9\u5bb6\u6c9f"
    ],
    "wof:name":"Mianjiagou",
    "wof:placetype":"locality"
},
  "geometry": {"coordinates":[109.49091,33.96924],"type":"Point"}
}