{
  "type": "Feature",
  "properties": {
    "gn:admin1_code":"25",
    "gn:asciiname":"Houliguozhe",
    "gn:country_code":"CN",
    "gn:dem":12,
    "gn:feature_class":"P",
    "gn:feature_code":"PPL",
    "gn:name":"Houliguozhe",
    "gn:population":0,
    "gn:timezone":"Asia/Shanghai",
    "iso:country":"CN",
    "name:zho_x_preferred":[
        "\u540e\u674e\u679c\u8005"
    ],
    "wof:name":"Houliguozhe",
    "wof:placetype":"locality"
},
  "geometry": {"coordinates":[117.886,37.4333],"type":"Point"}
}