{
  "type": "Feature",
  "properties": {
    "gn:admin1_code":"16.0",
    "gn:asciiname":"Daji",
    "gn:country_code":"CN",
    "gn:dem":555,
    "gn:feature_class":"P",
    "gn:feature_code":"PPL",
    "gn:name":"Daji",
    "gn:population":0,
    "gn:timezone":"Asia/Shanghai",
    "iso:country":"CN",
    "name:zho_x_preferred":[
        "\u5927\u5409"
    ],
    "wof:name":"Daji",
    "wof:placetype":"locality"
},
  "geometry": {"coordinates":[108.188,25.2937],"type":"Point"}
}