{
  "type": "Feature",
  "properties": {
    "gn:admin1_code":"16.0",
    "gn:asciiname":"Daji",
    "gn:country_code":"CN",
    "gn:dem":555,
    "gn:feature_class":"P",
    "gn:feature_code":"PPL",
    "gn:name":"Daji",
    "gn:population":0,
    "gn:timezone":"Asia/Shanghai",
    "iso:country":"CN",
    "name:cat_x_preferred":[
        "Daji"
    ],
    "name:deu_x_preferred":[
        "Daji"
    ],
    "name:fra_x_preferred":[
        "Daji"
    ],
    "name:ind_x_preferred":[
        "Daji"
    ],
    "name:por_x_preferred":[
        "Daji"
    ],
    "name:spa_x_preferred":[
        "Daji"
    ],
    "name:tha_x_preferred":[
        "\u0e15\u0e4b\u0e32\u0e08\u0e35\u0e48"
    ],
    "name:vie_x_preferred":[
        "\u0110\u00e1t K\u1ef7"
    ],
    "name:zho_x_preferred":[
        "\u5927\u5409"
    ],
    "wof:name":"Daji",
    "wof:placetype":"locality"
},
  "geometry": {"coordinates":[108.188,25.2937],"type":"Point"}
}