{
  "type": "Feature",
  "properties": {
    "gn:admin1_code":"14.0",
    "gn:asciiname":"Qianjincun",
    "gn:country_code":"CN",
    "gn:dem":2113,
    "gn:feature_class":"P",
    "gn:feature_code":"PPL",
    "gn:name":"Qianjincun",
    "gn:population":0,
    "gn:timezone":"Asia/Urumqi",
    "iso:country":"CN",
    "name:zho_x_preferred":[
        "\u524d\u8fdb\u6751"
    ],
    "wof:name":"Qianjincun",
    "wof:placetype":"locality"
},
  "geometry": {"coordinates":[98.39185000000001,28.49649],"type":"Point"}
}