{
  "type": "Feature",
  "properties": {
    "gn:admin1_code":"32.0",
    "gn:asciiname":"Malaha",
    "gn:country_code":"CN",
    "gn:dem":1631,
    "gn:feature_class":"P",
    "gn:feature_code":"PPL",
    "gn:name":"Malaha",
    "gn:population":0,
    "gn:timezone":"Asia/Shanghai",
    "iso:country":"CN",
    "name:zho_x_preferred":[
        "\u9a6c\u62c9\u54c8"
    ],
    "wof:name":"Malaha",
    "wof:placetype":"locality"
},
  "geometry": {"coordinates":[102.82299999999999,28.9408],"type":"Point"}
}