{
  "type": "Feature",
  "properties": {
    "gn:admin1_code":"32.0",
    "gn:asciiname":"Luotuo Biliang",
    "gn:country_code":"CN",
    "gn:dem":557,
    "gn:feature_class":"P",
    "gn:feature_code":"PPL",
    "gn:name":"Luotuo Biliang",
    "gn:population":0,
    "gn:timezone":"Asia/Shanghai",
    "iso:country":"CN",
    "name:zho_x_preferred":[
        "\u9a86\u9a7c\u9f3b\u6881"
    ],
    "wof:name":"Luotuo Biliang",
    "wof:placetype":"locality"
},
  "geometry": {"coordinates":[105.806,31.6482],"type":"Point"}
}