{
  "type": "Feature",
  "properties": {
    "gn:admin1_code":"18",
    "gn:asciiname":"Banong",
    "gn:country_code":"CN",
    "gn:dem":957,
    "gn:feature_class":"P",
    "gn:feature_code":"PPL",
    "gn:name":"Banong",
    "gn:population":0,
    "gn:timezone":"Asia/Shanghai",
    "iso:country":"CN",
    "name:zho_x_preferred":[
        "\u516b\u5f04"
    ],
    "wof:name":"Banong",
    "wof:placetype":"locality"
},
  "geometry": {"coordinates":[105.879,24.845],"type":"Point"}
}