{
  "type": "Feature",
  "properties": {
    "gn:admin1_code":"30",
    "gn:asciiname":"Qingshan",
    "gn:country_code":"CN",
    "gn:dem":18,
    "gn:feature_class":"P",
    "gn:feature_code":"PPL",
    "gn:name":"Qingshan",
    "gn:population":0,
    "gn:timezone":"Asia/Urumqi",
    "iso:country":"CN",
    "name:zho_x_preferred":[
        "\u9752\u5c71"
    ],
    "wof:name":"Qingshan",
    "wof:placetype":"locality"
},
  "geometry": {"coordinates":[111.16609,21.52062],"type":"Point"}
}