{
  "type": "Feature",
  "properties": {
    "gn:admin1_code":"12.0",
    "gn:asciiname":"Niulanchang",
    "gn:country_code":"CN",
    "gn:dem":803,
    "gn:feature_class":"P",
    "gn:feature_code":"PPL",
    "gn:name":"Niulanchang",
    "gn:population":0,
    "gn:timezone":"Asia/Shanghai",
    "iso:country":"CN",
    "name:zho_x_preferred":[
        "\u725b\u680f\u573a"
    ],
    "wof:name":"Niulanchang",
    "wof:placetype":"locality"
},
  "geometry": {"coordinates":[109.05901,30.04324],"type":"Point"}
}