{
  "type": "Feature",
  "properties": {
    "gn:admin1_code":"14.0",
    "gn:asciiname":"Nirongcun",
    "gn:country_code":"CN",
    "gn:dem":3970,
    "gn:feature_class":"P",
    "gn:feature_code":"PPL",
    "gn:name":"Nirongcun",
    "gn:population":0,
    "gn:timezone":"Asia/Urumqi",
    "iso:country":"CN",
    "name:zho_x_preferred":[
        "\u5c3c\u8363\u6751"
    ],
    "wof:name":"Nirongcun",
    "wof:placetype":"locality"
},
  "geometry": {"coordinates":[90.124,29.44952],"type":"Point"}
}