{
  "type": "Feature",
  "properties": {
    "gn:admin1_code":"29.0",
    "gn:asciiname":"Shengping",
    "gn:country_code":"CN",
    "gn:dem":3362,
    "gn:feature_class":"P",
    "gn:feature_code":"PPLA3",
    "gn:name":"Shengping",
    "gn:population":0,
    "gn:timezone":"Asia/Shanghai",
    "iso:country":"CN",
    "name:und_x_variant":[
        "A-tun",
        "Atun-hsien",
        "Tehtsin",
        "A-tun-tzu",
        "Tehching",
        "Atun-tse",
        "Atung",
        "Dong",
        "Atuntze",
        "Shengping",
        "Deqin"
    ],
    "name:zho_x_preferred":[
        "Te-ch\u2019in"
    ],
    "name:zho_x_variant":[
        "Te-ch\u2019in-she-chih-ch\u00fc",
        "Te-ch\u2019in-hsien-tsang-tsu-tzu-chih-ch\u2019\u00fc",
        "\u5347\u5e73",
        "\u5fb7\u94a6"
    ],
    "wof:name":"Shengping",
    "wof:placetype":"locality"
},
  "geometry": {"coordinates":[98.91139,28.48563],"type":"Point"}
}