{
  "type": "Feature",
  "properties": {
    "gn:admin1_code":"25",
    "gn:asciiname":"Wangluzhuang",
    "gn:country_code":"CN",
    "gn:dem":28,
    "gn:feature_class":"P",
    "gn:feature_code":"PPL",
    "gn:name":"Wangl\u00fczhuang",
    "gn:population":0,
    "gn:timezone":"Asia/Shanghai",
    "iso:country":"CN",
    "name:und_x_variant":[
        "Wangl\u00fczhuang"
    ],
    "name:zho_x_preferred":[
        "\u738b\u5f8b\u5e84"
    ],
    "wof:name":"Wangluzhuang",
    "wof:placetype":"locality"
},
  "geometry": {"coordinates":[116.375,37.3153],"type":"Point"}
}