{
  "type": "Feature",
  "properties": {
    "gn:admin1_code":"8.0",
    "gn:asciiname":"Sanchangcun",
    "gn:country_code":"CN",
    "gn:dem":138,
    "gn:feature_class":"P",
    "gn:feature_code":"PPL",
    "gn:name":"Sanchangcun",
    "gn:population":0,
    "gn:timezone":"Asia/Shanghai",
    "iso:country":"CN",
    "name:zho_x_preferred":[
        "\u4e09\u573a\u6751"
    ],
    "wof:name":"Sanchangcun",
    "wof:placetype":"locality"
},
  "geometry": {"coordinates":[126.32523,45.6265],"type":"Point"}
}