{
  "type": "Feature",
  "properties": {
    "gn:admin1_code":"07",
    "gn:asciiname":"Dazhouhou",
    "gn:country_code":"CN",
    "gn:dem":191,
    "gn:feature_class":"P",
    "gn:feature_code":"PPL",
    "gn:name":"Dazhouhou",
    "gn:population":0,
    "gn:timezone":"Asia/Shanghai",
    "iso:country":"CN",
    "name:zho_x_preferred":[
        "\u5927\u6d32\u540e"
    ],
    "wof:name":"Dazhouhou",
    "wof:placetype":"locality"
},
  "geometry": {"coordinates":[117.38556,25.98917],"type":"Point"}
}