{
  "type": "Feature",
  "properties": {
    "gn:admin1_code":"7.0",
    "gn:asciiname":"Xiangshanyang",
    "gn:country_code":"CN",
    "gn:dem":781,
    "gn:feature_class":"P",
    "gn:feature_code":"PPL",
    "gn:name":"Xiangshanyang",
    "gn:population":0,
    "gn:timezone":"Asia/Shanghai",
    "iso:country":"CN",
    "name:zho_x_preferred":[
        "\u9999\u5c71\u6d0b"
    ],
    "wof:name":"Xiangshanyang",
    "wof:placetype":"locality"
},
  "geometry": {"coordinates":[117.98186,26.13906],"type":"Point"}
}