{
  "type": "Feature",
  "properties": {
    "gn:admin1_code":"25.0",
    "gn:asciiname":"Tazhuangcun",
    "gn:country_code":"CN",
    "gn:dem":22,
    "gn:feature_class":"P",
    "gn:feature_code":"PPL",
    "gn:name":"Tazhuangcun",
    "gn:population":0,
    "gn:timezone":"Asia/Shanghai",
    "iso:country":"CN",
    "name:zho_x_preferred":[
        "\u5854\u5e84\u6751"
    ],
    "wof:name":"Tazhuangcun",
    "wof:placetype":"locality"
},
  "geometry": {"coordinates":[121.44974999999999,37.01884],"type":"Point"}
}