{
  "type": "Feature",
  "properties": {
    "gn:admin1_code":"12.0",
    "gn:asciiname":"Yushiwan",
    "gn:country_code":"CN",
    "gn:dem":185,
    "gn:feature_class":"P",
    "gn:feature_code":"PPL",
    "gn:name":"Yushiwan",
    "gn:population":0,
    "gn:timezone":"Asia/Shanghai",
    "iso:country":"CN",
    "name:zho_x_preferred":[
        "\u9047\u4e8b\u6e7e"
    ],
    "wof:name":"Yushiwan",
    "wof:placetype":"locality"
},
  "geometry": {"coordinates":[111.81008,31.93482],"type":"Point"}
}