{
  "type": "Feature",
  "properties": {
    "gn:admin1_code":"5.0",
    "gn:asciiname":"Qiantaokesu",
    "gn:country_code":"CN",
    "gn:dem":134,
    "gn:feature_class":"P",
    "gn:feature_code":"PPL",
    "gn:name":"Qiantaokesu",
    "gn:population":0,
    "gn:timezone":"Asia/Shanghai",
    "iso:country":"CN",
    "name:zho_x_preferred":[
        "\u524d\u5957\u514b\u82cf"
    ],
    "wof:name":"Qiantaokesu",
    "wof:placetype":"locality"
},
  "geometry": {"coordinates":[123.54237000000001,45.67076],"type":"Point"}
}