{
  "type": "Feature",
  "properties": {
    "gn:admin1_code":"3",
    "gn:asciiname":"Xinggangshang",
    "gn:country_code":"CN",
    "gn:dem":62,
    "gn:feature_class":"P",
    "gn:feature_code":"PPL",
    "gn:name":"Xinggangshang",
    "gn:population":0,
    "gn:timezone":"Asia/Shanghai",
    "iso:country":"CN",
    "name:zho_x_preferred":[
        "\u661f\u5c97\u4e0a"
    ],
    "wof:name":"Xinggangshang",
    "wof:placetype":"locality"
},
  "geometry": {"coordinates":[114.89400000000001,26.818],"type":"Point"}
}