{
  "type": "Feature",
  "properties": {
    "gn:admin1_code":"33.0",
    "gn:asciiname":"Houping",
    "gn:country_code":"CN",
    "gn:dem":1204,
    "gn:feature_class":"P",
    "gn:feature_code":"PPLA4",
    "gn:name":"Houping",
    "gn:population":0,
    "gn:timezone":"Asia/Shanghai",
    "iso:country":"CN",
    "name:und_x_variant":[
        "Houping Xiang"
    ],
    "name:zho_x_preferred":[
        "\u540e\u576a"
    ],
    "name:zho_x_variant":[
        "\u540e\u576a\u4e61"
    ],
    "wof:name":"Houping",
    "wof:placetype":"locality"
},
  "geometry": {"coordinates":[108.02951000000002,29.60199],"type":"Point"}
}