{
  "type": "Feature",
  "properties": {
    "gn:admin1_code":"29.0",
    "gn:asciiname":"Manzisi",
    "gn:country_code":"CN",
    "gn:dem":3104,
    "gn:feature_class":"P",
    "gn:feature_code":"PPL",
    "gn:name":"Manzisi",
    "gn:population":0,
    "gn:timezone":"Asia/Shanghai",
    "iso:country":"CN",
    "name:zho_x_preferred":[
        "\u6ee1\u5b50\u53f8"
    ],
    "wof:name":"Manzisi",
    "wof:placetype":"locality"
},
  "geometry": {"coordinates":[100.152,26.7721],"type":"Point"}
}