{
  "type": "Feature",
  "properties": {
    "gn:admin1_code":"4.0",
    "gn:asciiname":"Yuangoudai",
    "gn:country_code":"CN",
    "gn:dem":5,
    "gn:feature_class":"P",
    "gn:feature_code":"PPL",
    "gn:name":"Yuangoudai",
    "gn:population":0,
    "gn:timezone":"Asia/Shanghai",
    "iso:country":"CN",
    "name:zho_x_preferred":[
        "\u56ed\u6c9f\u57ed"
    ],
    "wof:name":"Yuangoudai",
    "wof:placetype":"locality"
},
  "geometry": {"coordinates":[119.806,32.16209],"type":"Point"}
}