{
  "type": "Feature",
  "properties": {
    "gn:admin1_code":"32.0",
    "gn:asciiname":"Wada",
    "gn:country_code":"CN",
    "gn:dem":3728,
    "gn:feature_class":"P",
    "gn:feature_code":"PPL",
    "gn:name":"Wada",
    "gn:population":0,
    "gn:timezone":"Asia/Shanghai",
    "iso:country":"CN",
    "name:ceb_x_preferred":[
        "Wada"
    ],
    "name:deu_x_preferred":[
        "Wada"
    ],
    "name:fra_x_preferred":[
        "Wada"
    ],
    "name:mar_x_preferred":[
        "\u0935\u093e\u0921\u093e"
    ],
    "name:pol_x_preferred":[
        "Wada"
    ],
    "name:rus_x_preferred":[
        "\u0412\u0430\u0434\u0430"
    ],
    "name:swe_x_preferred":[
        "Wada"
    ],
    "name:zho_x_preferred":[
        "\u74e6\u5927"
    ],
    "wof:name":"Wada",
    "wof:placetype":"locality"
},
  "geometry": {"coordinates":[101.16553,29.99478],"type":"Point"}
}