{
  "type": "Feature",
  "properties": {
    "gn:admin1_code":"11.0",
    "gn:asciiname":"Fengshu'ao",
    "gn:country_code":"CN",
    "gn:dem":120,
    "gn:feature_class":"P",
    "gn:feature_code":"PPL",
    "gn:name":"Fengshu\u2019ao",
    "gn:population":0,
    "gn:timezone":"Asia/Shanghai",
    "iso:country":"CN",
    "name:und_x_variant":[
        "Fengshu\u2019ao"
    ],
    "name:zho_x_preferred":[
        "\u67ab\u6811\u5773"
    ],
    "wof:name":"Fengshu'ao",
    "wof:placetype":"locality"
},
  "geometry": {"coordinates":[113.40452000000001,27.57615],"type":"Point"}
}