{
  "type": "Feature",
  "properties": {
    "gn:admin1_code":"10.0",
    "gn:asciiname":"Wangcheng",
    "gn:country_code":"CN",
    "gn:dem":11,
    "gn:feature_class":"P",
    "gn:feature_code":"PPL",
    "gn:name":"Wangcheng",
    "gn:population":0,
    "gn:timezone":"Asia/Shanghai",
    "iso:country":"CN",
    "name:deu_x_preferred":[
        "Wangcheng"
    ],
    "name:zho_x_preferred":[
        "\u738b\u7a0b"
    ],
    "wof:name":"Wangcheng",
    "wof:placetype":"locality"
},
  "geometry": {"coordinates":[116.666,38.3995],"type":"Point"}
}