{
  "type": "Feature",
  "properties": {
    "gn:admin1_code":"16",
    "gn:asciiname":"Baixu",
    "gn:cc2":"CN",
    "gn:country_code":"CN",
    "gn:dem":99,
    "gn:feature_class":"P",
    "gn:feature_code":"PPL",
    "gn:name":"Baixu",
    "gn:population":0,
    "gn:timezone":"Asia/Shanghai",
    "iso:country":"CN",
    "name:und_x_variant":[
        "Pai-hs\u00fc",
        "Baixu"
    ],
    "wof:name":"Baixu",
    "wof:placetype":"locality"
},
  "geometry": {"coordinates":[108.75,23.41667],"type":"Point"}
}