{
  "type": "Feature",
  "properties": {
    "gn:admin1_code":"23",
    "gn:asciiname":"San-tai-chih",
    "gn:country_code":"CN",
    "gn:dem":7,
    "gn:feature_class":"P",
    "gn:feature_code":"PPL",
    "gn:name":"San-tai-chih",
    "gn:population":0,
    "gn:timezone":"Asia/Shanghai",
    "iso:country":"CN",
    "wof:name":"San-tai-chih",
    "wof:placetype":"locality"
},
  "geometry": {"coordinates":[121.20471999999999,30.89917],"type":"Point"}
}