{
  "type": "Feature",
  "properties": {
    "gn:admin1_code":"03",
    "gn:asciiname":"Gufengxu",
    "gn:country_code":"CN",
    "gn:dem":264,
    "gn:feature_class":"P",
    "gn:feature_code":"PPL",
    "gn:name":"Gufengxu",
    "gn:population":0,
    "gn:timezone":"Asia/Shanghai",
    "iso:country":"CN",
    "name:zho_x_preferred":[
        "\u53e4\u4e30\u5729"
    ],
    "wof:name":"Gufengxu",
    "wof:placetype":"locality"
},
  "geometry": {"coordinates":[115.72877,24.9344],"type":"Point"}
}