{
  "type": "Feature",
  "properties": {
    "gn:admin1_code":"12.0",
    "gn:asciiname":"Sanjiaozhai",
    "gn:country_code":"CN",
    "gn:dem":945,
    "gn:feature_class":"P",
    "gn:feature_code":"PPL",
    "gn:name":"Sanjiaozhai",
    "gn:population":0,
    "gn:timezone":"Asia/Shanghai",
    "iso:country":"CN",
    "name:zho_x_preferred":[
        "\u4e09\u89d2\u5be8"
    ],
    "wof:name":"Sanjiaozhai",
    "wof:placetype":"locality"
},
  "geometry": {"coordinates":[110.13902,30.37691],"type":"Point"}
}