{
  "type": "Feature",
  "properties": {
    "gn:admin1_code":"26.0",
    "gn:asciiname":"Zhanjia Xinfangzi",
    "gn:country_code":"CN",
    "gn:dem":547,
    "gn:feature_class":"P",
    "gn:feature_code":"PPL",
    "gn:name":"Zhanjia Xinfangzi",
    "gn:population":0,
    "gn:timezone":"Asia/Shanghai",
    "iso:country":"CN",
    "name:zho_x_preferred":[
        "\u8a79\u5bb6\u65b0\u623f\u5b50"
    ],
    "wof:name":"Zhanjia Xinfangzi",
    "wof:placetype":"locality"
},
  "geometry": {"coordinates":[108.56896999999999,32.61322],"type":"Point"}
}