{
  "type": "Feature",
  "properties": {
    "gn:admin1_code":"11",
    "gn:asciiname":"Hengjiangqiao",
    "gn:country_code":"CN",
    "gn:dem":121,
    "gn:feature_class":"P",
    "gn:feature_code":"PPL",
    "gn:name":"Hengjiangqiao",
    "gn:population":0,
    "gn:timezone":"Asia/Shanghai",
    "iso:country":"CN",
    "name:zho_x_preferred":[
        "\u6a2a\u6c5f\u6865"
    ],
    "wof:name":"Hengjiangqiao",
    "wof:placetype":"locality"
},
  "geometry": {"coordinates":[111.80186,26.7419],"type":"Point"}
}