{
  "type": "Feature",
  "properties": {
    "gn:admin1_code":"08",
    "gn:asciiname":"Laoheishan",
    "gn:country_code":"CN",
    "gn:dem":352,
    "gn:feature_class":"P",
    "gn:feature_code":"PPLA4",
    "gn:name":"Laoheishan",
    "gn:population":0,
    "gn:timezone":"Asia/Shanghai",
    "iso:country":"CN",
    "name:und_x_variant":[
        "Lao-hei-shan-pen-ts\u2019un",
        "Laoheishan",
        "\u8001\u9ed1\u5c71",
        "Laoheishan Zhen",
        "\u8001\u9ed1\u5c71\u9547"
    ],
    "wof:name":"Laoheishan",
    "wof:placetype":"locality"
},
  "geometry": {"coordinates":[130.88012000000001,43.71176],"type":"Point"}
}