{
  "type": "Feature",
  "properties": {
    "gn:country":"CN",
    "gn:fcode":"PPL",
    "gn:pop":66147,
    "iso:country":"CN",
    "name:eng_x_preferred":[
        "Huanren"
    ],
    "name:fas_x_preferred":[
        "\u0634\u0647\u0631 \u0647\u0648\u0627\u0646\u0631\u0646"
    ],
    "name:gan_x_preferred":[
        "\u6853\u4ec1\u9547"
    ],
    "name:jpn_x_preferred":[
        "\u6853\u4ec1\u93ae"
    ],
    "name:unk_x_variant":[
        "Chiu-huai-jen"
    ],
    "name:wuu_x_preferred":[
        "\u6853\u4ec1\u9547"
    ],
    "name:zho_x_preferred":[
        "\u6853\u4ec1\u9547"
    ],
    "ne:ADM0CAP":0.0,
    "ne:ADM0NAME":"China",
    "ne:ADM0_A3":"CHN",
    "ne:ADM1NAME":"Liaoning",
    "ne:ADMIN1_COD":19,
    "ne:CAPALT":0,
    "ne:CHANGED":0,
    "ne:CHECKME":0,
    "ne:COMPARE":0,
    "ne:DIFFASCII":0,
    "ne:ELEVATION":0.0,
    "ne:FEATURECLA":"Populated place",
    "ne:FEATURE_CL":"P",
    "ne:FEATURE_CO":"PPL",
    "ne:GEONAMEID":2036713,
    "ne:GEONAMESNO":"GeoNames match with ascii name + lat + long whole numbers.",
    "ne:GN_ASCII":"Huanren",
    "ne:GN_POP":66147,
    "ne:GTOPO30":278.0,
    "ne:ISO_A2":"CN",
    "ne:LABELRANK":1,
    "ne:LATITUDE":41.256331,
    "ne:LONGITUDE":125.345982,
    "ne:LS_MATCH":1,
    "ne:LS_NAME":"Huanren",
    "ne:MAX_AREAKM":29.0,
    "ne:MAX_AREAMI":11.0,
    "ne:MAX_BBXMAX":125.391667,
    "ne:MAX_BBXMIN":125.308333,
    "ne:MAX_BBYMAX":41.316667,
    "ne:MAX_BBYMIN":41.25,
    "ne:MAX_NATSCA":20.0,
    "ne:MAX_PERKM":46.0,
    "ne:MAX_PERMI":29.0,
    "ne:MAX_POP10":116621,
    "ne:MAX_POP20":116621,
    "ne:MAX_POP300":0,
    "ne:MAX_POP310":0,
    "ne:MAX_POP50":0,
    "ne:MEAN_BBXC":125.350463,
    "ne:MEAN_BBYC":41.2825,
    "ne:MEGACITY":0,
    "ne:MIN_AREAKM":29.0,
    "ne:MIN_AREAMI":11.0,
    "ne:MIN_BBXMAX":125.391667,
    "ne:MIN_BBXMIN":125.308333,
    "ne:MIN_BBYMAX":41.316667,
    "ne:MIN_BBYMIN":41.25,
    "ne:MIN_PERKM":46.0,
    "ne:MIN_PERMI":29.0,
    "ne:NAME":"Huanren",
    "ne:NAMEASCII":"Huanren",
    "ne:NAMEDIFF":0,
    "ne:NATSCALE":20,
    "ne:POP1950":0,
    "ne:POP1955":0,
    "ne:POP1960":0,
    "ne:POP1965":0,
    "ne:POP1970":0,
    "ne:POP1975":0,
    "ne:POP1980":0,
    "ne:POP1985":0,
    "ne:POP1990":0,
    "ne:POP1995":0,
    "ne:POP2000":0,
    "ne:POP2005":0,
    "ne:POP2010":0,
    "ne:POP2015":0,
    "ne:POP2020":0,
    "ne:POP2025":0,
    "ne:POP2050":0,
    "ne:POP_MAX":116621,
    "ne:POP_MIN":66147,
    "ne:POP_OTHER":116462,
    "ne:RANK_MAX":9,
    "ne:RANK_MIN":8,
    "ne:SCALERANK":7,
    "ne:SOV0NAME":"China",
    "ne:SOV_A3":"CHN",
    "ne:TIMEZONE":"Asia/Harbin",
    "ne:UN_FID":0,
    "ne:UN_LAT":0.0,
    "ne:UN_LONG":0.0,
    "ne:WORLDCITY":0,
    "qs:name":"Huanren",
    "qs:photos_9r":0,
    "qs:photos_sr":0,
    "qs:pop_sr":"9",
    "wd:wordcount":30,
    "wof:name":"Huanren",
    "wof:placetype":"locality",
    "wof:population":66147
},
  "geometry": {"coordinates":[125.36667,41.26472],"type":"Point"}
}