{
  "type": "Feature",
  "properties": {
    "gn:admin1_code":"29.0",
    "gn:asciiname":"Potou Dazhai",
    "gn:country_code":"CN",
    "gn:dem":1614,
    "gn:feature_class":"P",
    "gn:feature_code":"PPL",
    "gn:name":"Potou Dazhai",
    "gn:population":0,
    "gn:timezone":"Asia/Shanghai",
    "iso:country":"CN",
    "name:zho_x_preferred":[
        "\u5761\u5934\u5927\u5be8"
    ],
    "wof:name":"Potou Dazhai",
    "wof:placetype":"locality"
},
  "geometry": {"coordinates":[102.592,23.1261],"type":"Point"}
}