{
  "type": "Feature",
  "properties": {
    "gn:admin1_code":"9.0",
    "gn:asciiname":"Xiaojing",
    "gn:country_code":"CN",
    "gn:dem":956,
    "gn:feature_class":"P",
    "gn:feature_code":"PPL",
    "gn:name":"Xiaojing",
    "gn:population":0,
    "gn:timezone":"Asia/Shanghai",
    "iso:country":"CN",
    "name:zho_x_preferred":[
        "\u5c0f\u4e95"
    ],
    "wof:name":"Xiaojing",
    "wof:placetype":"locality"
},
  "geometry": {"coordinates":[113.64024000000001,35.68249],"type":"Point"}
}