{
  "type": "Feature",
  "properties": {
    "gn:admin1_code":"4.0",
    "gn:asciiname":"Guangyi Jiuzu",
    "gn:country_code":"CN",
    "gn:dem":3,
    "gn:feature_class":"P",
    "gn:feature_code":"PPL",
    "gn:name":"Guangyi Jiuzu",
    "gn:population":0,
    "gn:timezone":"Asia/Shanghai",
    "iso:country":"CN",
    "name:zho_x_preferred":[
        "\u5e7f\u76ca\u4e5d\u7ec4"
    ],
    "wof:name":"Guangyi Jiuzu",
    "wof:placetype":"locality"
},
  "geometry": {"coordinates":[119.17954,31.30543],"type":"Point"}
}