{
  "type": "Feature",
  "properties": {
    "gn:admin1_code":"15.0",
    "gn:asciiname":"Dayazi",
    "gn:country_code":"CN",
    "gn:dem":1373,
    "gn:feature_class":"P",
    "gn:feature_code":"PPL",
    "gn:name":"Dayazi",
    "gn:population":0,
    "gn:timezone":"Asia/Shanghai",
    "iso:country":"CN",
    "name:zho_x_preferred":[
        "\u5927\u5d16\u5b50"
    ],
    "wof:name":"Dayazi",
    "wof:placetype":"locality"
},
  "geometry": {"coordinates":[104.381,37.2244],"type":"Point"}
}