{
  "type": "Feature",
  "properties": {
    "gn:admin1_code":"32.0",
    "gn:asciiname":"Nizhongcun",
    "gn:country_code":"CN",
    "gn:dem":2996,
    "gn:feature_class":"P",
    "gn:feature_code":"PPL",
    "gn:name":"Nizhongcun",
    "gn:population":0,
    "gn:timezone":"Asia/Shanghai",
    "iso:country":"CN",
    "name:zho_x_preferred":[
        "\u5c3c\u4e2d\u6751"
    ],
    "wof:name":"Nizhongcun",
    "wof:placetype":"locality"
},
  "geometry": {"coordinates":[99.1669,28.7589],"type":"Point"}
}