{
  "type": "Feature",
  "properties": {
    "gn:admin1_code":"30",
    "gn:asciiname":"Jiadong",
    "gn:country_code":"CN",
    "gn:dem":667,
    "gn:feature_class":"P",
    "gn:feature_code":"PPL",
    "gn:name":"Jiadong",
    "gn:population":0,
    "gn:timezone":"Asia/Urumqi",
    "iso:country":"CN",
    "name:zho_x_preferred":[
        "\u5bb6\u578c"
    ],
    "wof:name":"Jiadong",
    "wof:placetype":"locality"
},
  "geometry": {"coordinates":[111.29719,22.28298],"type":"Point"}
}