{
  "type": "Feature",
  "properties": {
    "gn:admin1_code":"30",
    "gn:asciiname":"Jiadong",
    "gn:country_code":"CN",
    "gn:dem":667,
    "gn:feature_class":"P",
    "gn:feature_code":"PPL",
    "gn:name":"Jiadong",
    "gn:population":0,
    "gn:timezone":"Asia/Urumqi",
    "iso:country":"CN",
    "name:deu_x_preferred":[
        "Jiadong"
    ],
    "name:hak_x_preferred":[
        "K\u00e2-t\u00fbng-hi\u00f4ng"
    ],
    "name:jpn_x_preferred":[
        "\u4f73\u51ac\u90f7"
    ],
    "name:kor_x_preferred":[
        "\uc790\ub465\ud5a5"
    ],
    "name:vie_x_preferred":[
        "Giai \u0110\u00f4ng"
    ],
    "name:zho_x_preferred":[
        "\u5bb6\u578c"
    ],
    "name:zho_x_variant":[
        "\u4f73\u51ac\u9109"
    ],
    "wof:name":"Jiadong",
    "wof:placetype":"locality"
},
  "geometry": {"coordinates":[111.29719,22.28298],"type":"Point"}
}