{
  "type": "Feature",
  "properties": {
    "gn:admin1_code":"32.0",
    "gn:asciiname":"Jiukuaibei",
    "gn:country_code":"CN",
    "gn:dem":487,
    "gn:feature_class":"P",
    "gn:feature_code":"PPL",
    "gn:name":"Jiukuaibei",
    "gn:population":0,
    "gn:timezone":"Asia/Shanghai",
    "iso:country":"CN",
    "name:zho_x_preferred":[
        "\u4e5d\u5757\u7891"
    ],
    "wof:name":"Jiukuaibei",
    "wof:placetype":"locality"
},
  "geometry": {"coordinates":[103.657,29.2752],"type":"Point"}
}