{
  "type": "Feature",
  "properties": {
    "gn:admin1_code":"7.0",
    "gn:asciiname":"Shegongpai",
    "gn:country_code":"CN",
    "gn:dem":646,
    "gn:feature_class":"P",
    "gn:feature_code":"PPL",
    "gn:name":"Shegongpai",
    "gn:population":0,
    "gn:timezone":"Asia/Shanghai",
    "iso:country":"CN",
    "name:zho_x_preferred":[
        "\u793e\u516c\u6392"
    ],
    "wof:name":"Shegongpai",
    "wof:placetype":"locality"
},
  "geometry": {"coordinates":[115.95101,25.12731],"type":"Point"}
}