{
  "type": "Feature",
  "properties": {
    "gn:admin1_code":"05",
    "gn:asciiname":"Jingouling",
    "gn:country_code":"CN",
    "gn:dem":596,
    "gn:feature_class":"P",
    "gn:feature_code":"PPL",
    "gn:name":"Jingouling",
    "gn:population":0,
    "gn:timezone":"Asia/Shanghai",
    "iso:country":"CN",
    "name:und_x_variant":[
        "\u91d1\u6c9f\u5cad"
    ],
    "wof:name":"Jingouling",
    "wof:placetype":"locality"
},
  "geometry": {"coordinates":[130.17948000000001,43.35475],"type":"Point"}
}