{
  "type": "Feature",
  "properties": {
    "gn:admin1_code":"12.0",
    "gn:asciiname":"Yangdawan",
    "gn:country_code":"CN",
    "gn:dem":33,
    "gn:feature_class":"P",
    "gn:feature_code":"PPL",
    "gn:name":"Yangdawan",
    "gn:population":0,
    "gn:timezone":"Asia/Shanghai",
    "iso:country":"CN",
    "name:zho_x_preferred":[
        "\u6768\u5927\u6e7e"
    ],
    "wof:name":"Yangdawan",
    "wof:placetype":"locality"
},
  "geometry": {"coordinates":[113.63946,30.88025],"type":"Point"}
}