{
  "type": "Feature",
  "properties": {
    "gn:admin1_code":"1.0",
    "gn:asciiname":"Zhuxincun",
    "gn:country_code":"CN",
    "gn:dem":35,
    "gn:feature_class":"P",
    "gn:feature_code":"PPL",
    "gn:name":"Zhuxincun",
    "gn:population":0,
    "gn:timezone":"Asia/Shanghai",
    "iso:country":"CN",
    "name:zho_x_preferred":[
        "\u7af9\u65b0\u6751"
    ],
    "wof:name":"Zhuxincun",
    "wof:placetype":"locality"
},
  "geometry": {"coordinates":[116.7136,32.14521],"type":"Point"}
}