{
  "type": "Feature",
  "properties": {
    "gn:admin1_code":"29.0",
    "gn:asciiname":"Zhengjiacun",
    "gn:country_code":"CN",
    "gn:dem":2162,
    "gn:feature_class":"P",
    "gn:feature_code":"PPL",
    "gn:name":"Zhengjiacun",
    "gn:population":0,
    "gn:timezone":"Asia/Shanghai",
    "iso:country":"CN",
    "name:zho_x_preferred":[
        "\u90d1\u5bb6\u6751"
    ],
    "wof:name":"Zhengjiacun",
    "wof:placetype":"locality"
},
  "geometry": {"coordinates":[103.52500000000001,26.5081],"type":"Point"}
}