{
  "type": "Feature",
  "properties": {
    "gn:admin1_code":"25",
    "gn:asciiname":"Chenjia Guanzhuang",
    "gn:country_code":"CN",
    "gn:dem":204,
    "gn:feature_class":"P",
    "gn:feature_code":"PPL",
    "gn:name":"Chenjia Guanzhuang",
    "gn:population":0,
    "gn:timezone":"Asia/Shanghai",
    "iso:country":"CN",
    "name:zho_x_preferred":[
        "\u9648\u5bb6\u5b98\u5e84"
    ],
    "wof:name":"Chenjia Guanzhuang",
    "wof:placetype":"locality"
},
  "geometry": {"coordinates":[119.181,35.3701],"type":"Point"}
}