{
  "type": "Feature",
  "properties": {
    "gn:admin1_code":"30.0",
    "gn:asciiname":"Daluojia",
    "gn:country_code":"CN",
    "gn:dem":213,
    "gn:feature_class":"P",
    "gn:feature_code":"PPL",
    "gn:name":"Daluojia",
    "gn:population":0,
    "gn:timezone":"Asia/Shanghai",
    "iso:country":"CN",
    "name:zho_x_preferred":[
        "Daluojia"
    ],
    "name:zho_x_variant":[
        "\u5927\u7f57\u5bb6"
    ],
    "wof:name":"Daluojia",
    "wof:placetype":"locality"
},
  "geometry": {"coordinates":[112.93778,25.32333],"type":"Point"}
}