{
  "type": "Feature",
  "properties": {
    "gn:admin1_code":"8.0",
    "gn:asciiname":"Ziyoucun",
    "gn:country_code":"CN",
    "gn:dem":217,
    "gn:feature_class":"P",
    "gn:feature_code":"PPL",
    "gn:name":"Ziyoucun",
    "gn:population":0,
    "gn:timezone":"Asia/Shanghai",
    "iso:country":"CN",
    "name:zho_x_preferred":[
        "\u81ea\u7531\u6751"
    ],
    "wof:name":"Ziyoucun",
    "wof:placetype":"locality"
},
  "geometry": {"coordinates":[126.50614,47.5705],"type":"Point"}
}