{
  "type": "Feature",
  "properties": {
    "gn:admin1_code":"5.0",
    "gn:asciiname":"Lujiacun",
    "gn:country_code":"CN",
    "gn:dem":150,
    "gn:feature_class":"P",
    "gn:feature_code":"PPL",
    "gn:name":"Lujiacun",
    "gn:population":0,
    "gn:timezone":"Asia/Shanghai",
    "iso:country":"CN",
    "name:zho_x_preferred":[
        "\u9646\u5bb6\u6751"
    ],
    "wof:name":"Lujiacun",
    "wof:placetype":"locality"
},
  "geometry": {"coordinates":[122.85939999999999,45.75438],"type":"Point"}
}