{
  "type": "Feature",
  "properties": {
    "gn:admin1_code":"30",
    "gn:asciiname":"Lijiangkeng",
    "gn:country_code":"CN",
    "gn:dem":392,
    "gn:feature_class":"P",
    "gn:feature_code":"PPL",
    "gn:name":"Lijiangkeng",
    "gn:population":0,
    "gn:timezone":"Asia/Shanghai",
    "iso:country":"CN",
    "wof:name":"Lijiangkeng",
    "wof:placetype":"locality"
},
  "geometry": {"coordinates":[116.66472,23.79722000000001],"type":"Point"}
}