{
  "type": "Feature",
  "properties": {
    "gn:admin1_code":"24.0",
    "gn:asciiname":"Baohe",
    "gn:country_code":"CN",
    "gn:dem":506,
    "gn:feature_class":"P",
    "gn:feature_code":"PPL",
    "gn:name":"Baohe",
    "gn:population":0,
    "gn:timezone":"Asia/Shanghai",
    "iso:country":"CN",
    "name:und_x_variant":[
        "\u5821\u6cb3"
    ],
    "wof:name":"Baohe",
    "wof:placetype":"locality"
},
  "geometry": {"coordinates":[111.48312,35.60387],"type":"Point"}
}