{
  "type": "Feature",
  "properties": {
    "gn:admin1_code":"32.0",
    "gn:asciiname":"Wangcunli",
    "gn:country_code":"CN",
    "gn:dem":1090,
    "gn:feature_class":"P",
    "gn:feature_code":"PPL",
    "gn:name":"Wangcunli",
    "gn:population":0,
    "gn:timezone":"Asia/Shanghai",
    "iso:country":"CN",
    "name:zho_x_preferred":[
        "\u738b\u6751\u91cc"
    ],
    "wof:name":"Wangcunli",
    "wof:placetype":"locality"
},
  "geometry": {"coordinates":[104.73935,32.32834],"type":"Point"}
}