{
  "type": "Feature",
  "properties": {
    "gn:admin1_code":"25",
    "gn:asciiname":"Jiangzhuang",
    "gn:country_code":"CN",
    "gn:dem":40,
    "gn:feature_class":"P",
    "gn:feature_code":"PPL",
    "gn:name":"Jiangzhuang",
    "gn:population":0,
    "gn:timezone":"Asia/Shanghai",
    "iso:country":"CN",
    "name:zho_x_preferred":[
        "\u848b\u5e84"
    ],
    "wof:name":"Jiangzhuang",
    "wof:placetype":"locality"
},
  "geometry": {"coordinates":[117.14700000000001,34.8499],"type":"Point"}
}