{
  "type": "Feature",
  "properties": {
    "gn:admin1_code":"26.0",
    "gn:asciiname":"Yangtiangou",
    "gn:country_code":"CN",
    "gn:dem":611,
    "gn:feature_class":"P",
    "gn:feature_code":"PPL",
    "gn:name":"Yangtiangou",
    "gn:population":0,
    "gn:timezone":"Asia/Shanghai",
    "iso:country":"CN",
    "name:zho_x_preferred":[
        "\u79e7\u7530\u6c9f"
    ],
    "wof:name":"Yangtiangou",
    "wof:placetype":"locality"
},
  "geometry": {"coordinates":[110.94842,33.45506],"type":"Point"}
}