{
  "type": "Feature",
  "properties": {
    "gn:admin1_code":"29.0",
    "gn:asciiname":"Jiangxiyanwa",
    "gn:country_code":"CN",
    "gn:dem":1773,
    "gn:feature_class":"P",
    "gn:feature_code":"PPL",
    "gn:name":"Jiangxiyanwa",
    "gn:population":0,
    "gn:timezone":"Asia/Shanghai",
    "iso:country":"CN",
    "name:zho_x_preferred":[
        "\u6c5f\u897f\u5ca9\u74e6"
    ],
    "wof:name":"Jiangxiyanwa",
    "wof:placetype":"locality"
},
  "geometry": {"coordinates":[99.0235,27.5061],"type":"Point"}
}