{
  "type": "Feature",
  "properties": {
    "gn:admin1_code":"4.0",
    "gn:asciiname":"Panguling",
    "gn:country_code":"CN",
    "gn:dem":9,
    "gn:feature_class":"P",
    "gn:feature_code":"PPL",
    "gn:name":"Panguling",
    "gn:population":0,
    "gn:timezone":"Asia/Shanghai",
    "iso:country":"CN",
    "name:zho_x_preferred":[
        "\u76d8\u53e4\u5cad"
    ],
    "wof:name":"Panguling",
    "wof:placetype":"locality"
},
  "geometry": {"coordinates":[119.24709,35.09352],"type":"Point"}
}