{
  "type": "Feature",
  "properties": {
    "gn:admin1_code":"7.0",
    "gn:asciiname":"Yangbei",
    "gn:country_code":"CN",
    "gn:dem":355,
    "gn:feature_class":"P",
    "gn:feature_code":"PPL",
    "gn:name":"Yangbei",
    "gn:population":0,
    "gn:timezone":"Asia/Shanghai",
    "iso:country":"CN",
    "name:und_x_variant":[
        "\u7f8a\u80cc"
    ],
    "name:zho_x_preferred":[
        "\u7f8a\u80cc"
    ],
    "wof:name":"Yangbei",
    "wof:placetype":"locality"
},
  "geometry": {"coordinates":[116.78991000000001,26.92691],"type":"Point"}
}