{
  "type": "Feature",
  "properties": {
    "gn:admin1_code":"9.0",
    "gn:asciiname":"Magang",
    "gn:country_code":"CN",
    "gn:dem":111,
    "gn:feature_class":"P",
    "gn:feature_code":"PPL",
    "gn:name":"Magang",
    "gn:population":0,
    "gn:timezone":"Asia/Shanghai",
    "iso:country":"CN",
    "name:ceb_x_preferred":[
        "Magang"
    ],
    "name:swe_x_preferred":[
        "Magang"
    ],
    "name:und_x_variant":[
        "\u9a6c\u5c97"
    ],
    "name:zho_x_preferred":[
        "\u9a6c\u5c97"
    ],
    "wof:name":"Magang",
    "wof:placetype":"locality"
},
  "geometry": {"coordinates":[113.90860000000001,32.98588],"type":"Point"}
}