{
  "type": "Feature",
  "properties": {
    "gn:admin1_code":"12.0",
    "gn:asciiname":"Chengjiayuan",
    "gn:country_code":"CN",
    "gn:dem":690,
    "gn:feature_class":"P",
    "gn:feature_code":"PPL",
    "gn:name":"Chengjiayuan",
    "gn:population":0,
    "gn:timezone":"Asia/Shanghai",
    "iso:country":"CN",
    "name:zho_x_preferred":[
        "\u7a0b\u5bb6\u9662"
    ],
    "wof:name":"Chengjiayuan",
    "wof:placetype":"locality"
},
  "geometry": {"coordinates":[110.24755,32.15497],"type":"Point"}
}