{
  "type": "Feature",
  "properties": {
    "gn:admin1_code":"32.0",
    "gn:asciiname":"Shuiduxi",
    "gn:country_code":"CN",
    "gn:dem":1180,
    "gn:feature_class":"P",
    "gn:feature_code":"PPL",
    "gn:name":"Shuiduxi",
    "gn:population":0,
    "gn:timezone":"Asia/Shanghai",
    "iso:country":"CN",
    "name:zho_x_preferred":[
        "\u6c34\u6e21\u6eaa"
    ],
    "wof:name":"Shuiduxi",
    "wof:placetype":"locality"
},
  "geometry": {"coordinates":[103.54333,28.417],"type":"Point"}
}