{
  "type": "Feature",
  "properties": {
    "gn:admin1_code":"15.0",
    "gn:asciiname":"Baguasi",
    "gn:country_code":"CN",
    "gn:dem":1339,
    "gn:feature_class":"P",
    "gn:feature_code":"PPL",
    "gn:name":"Baguasi",
    "gn:population":0,
    "gn:timezone":"Asia/Shanghai",
    "iso:country":"CN",
    "name:zho_x_preferred":[
        "\u516b\u5366\u5bfa"
    ],
    "wof:name":"Baguasi",
    "wof:placetype":"locality"
},
  "geometry": {"coordinates":[108.681,36.2923],"type":"Point"}
}