{
  "type": "Feature",
  "properties": {
    "gn:admin1_code":"18.0",
    "gn:asciiname":"Dong'ai",
    "gn:country_code":"CN",
    "gn:dem":915,
    "gn:feature_class":"P",
    "gn:feature_code":"PPL",
    "gn:name":"Dong\u2019ai",
    "gn:population":0,
    "gn:timezone":"Asia/Shanghai",
    "iso:country":"CN",
    "name:und_x_variant":[
        "Dong\u2019ai"
    ],
    "name:zho_x_preferred":[
        "\u8463\u57c3"
    ],
    "wof:name":"Dong'ai",
    "wof:placetype":"locality"
},
  "geometry": {"coordinates":[107.705,25.661],"type":"Point"}
}