{
  "type": "Feature",
  "properties": {
    "gn:admin1_code":"11.0",
    "gn:asciiname":"Yanwan Chenjia",
    "gn:country_code":"CN",
    "gn:dem":113,
    "gn:feature_class":"P",
    "gn:feature_code":"PPL",
    "gn:name":"Yanwan Chenjia",
    "gn:population":0,
    "gn:timezone":"Asia/Shanghai",
    "iso:country":"CN",
    "name:zho_x_preferred":[
        "Yanwan Chenjia"
    ],
    "name:zho_x_variant":[
        "\u5830\u6e7e\u9648\u5bb6"
    ],
    "wof:name":"Yanwan Chenjia",
    "wof:placetype":"locality"
},
  "geometry": {"coordinates":[111.82449,29.32806],"type":"Point"}
}