{
  "type": "Feature",
  "properties": {
    "gn:admin1_code":"12.0",
    "gn:asciiname":"Hongshichao",
    "gn:country_code":"CN",
    "gn:dem":35,
    "gn:feature_class":"P",
    "gn:feature_code":"PPL",
    "gn:name":"Hongshichao",
    "gn:population":0,
    "gn:timezone":"Asia/Shanghai",
    "iso:country":"CN",
    "name:zho_x_preferred":[
        "Hongshichao"
    ],
    "name:zho_x_variant":[
        "\u7ea2\u77f3\u5de2"
    ],
    "wof:name":"Hongshichao",
    "wof:placetype":"locality"
},
  "geometry": {"coordinates":[115.12945999999999,30.28708],"type":"Point"}
}