{
  "type": "Feature",
  "properties": {
    "gn:admin1_code":"14.0",
    "gn:asciiname":"Jaggong",
    "gn:country_code":"CN",
    "gn:dem":4153,
    "gn:feature_class":"P",
    "gn:feature_code":"PPLA4",
    "gn:name":"Jaggong",
    "gn:population":0,
    "gn:timezone":"Asia/Urumqi",
    "iso:country":"CN",
    "name:bod_x_preferred":[
        "Jaggong"
    ],
    "name:und_x_variant":[
        "Jiagong Xiang"
    ],
    "name:zho_x_preferred":[
        "Jiagong"
    ],
    "name:zho_x_variant":[
        "\u52a0\u8d21",
        "\u52a0\u8d21\u4e61"
    ],
    "wof:name":"Jaggong",
    "wof:placetype":"locality"
},
  "geometry": {"coordinates":[93.95318,30.6953],"type":"Point"}
}