{
  "type": "Feature",
  "properties": {
    "gn:admin1_code":"16",
    "gn:asciiname":"Hekou Yaozuxiang",
    "gn:country_code":"CN",
    "gn:dem":599,
    "gn:feature_class":"P",
    "gn:feature_code":"PPL",
    "gn:name":"Hekou Yaozuxiang",
    "gn:population":0,
    "gn:timezone":"Asia/Shanghai",
    "iso:country":"CN",
    "wof:name":"Hekou Yaozuxiang",
    "wof:placetype":"locality"
},
  "geometry": {"coordinates":[110.37582999999999,25.94333],"type":"Point"}
}