{
  "type": "Feature",
  "properties": {
    "gn:admin1_code":"29.0",
    "gn:asciiname":"Tuoluozhe",
    "gn:country_code":"CN",
    "gn:dem":1875,
    "gn:feature_class":"P",
    "gn:feature_code":"PPL",
    "gn:name":"Tuoluozhe",
    "gn:population":0,
    "gn:timezone":"Asia/Shanghai",
    "iso:country":"CN",
    "name:zho_x_preferred":[
        "\u62d6\u843d\u7740"
    ],
    "wof:name":"Tuoluozhe",
    "wof:placetype":"locality"
},
  "geometry": {"coordinates":[104.09399999999999,27.3581],"type":"Point"}
}