{
  "type": "Feature",
  "properties": {
    "gn:admin1_code":"32.0",
    "gn:asciiname":"Dakuahuona",
    "gn:country_code":"CN",
    "gn:dem":4178,
    "gn:feature_class":"P",
    "gn:feature_code":"PPL",
    "gn:name":"Dakuahuona",
    "gn:population":0,
    "gn:timezone":"Asia/Shanghai",
    "iso:country":"CN",
    "name:zho_x_preferred":[
        "\u5927\u5938\u6216\u90a3"
    ],
    "wof:name":"Dakuahuona",
    "wof:placetype":"locality"
},
  "geometry": {"coordinates":[101.334,28.0183],"type":"Point"}
}