{
  "type": "Feature",
  "properties": {
    "gn:admin1_code":"26.0",
    "gn:asciiname":"Shangjinshijiancun",
    "gn:country_code":"CN",
    "gn:dem":1210,
    "gn:feature_class":"P",
    "gn:feature_code":"PPL",
    "gn:name":"Shangjinshijiancun",
    "gn:population":0,
    "gn:timezone":"Asia/Shanghai",
    "iso:country":"CN",
    "name:zho_x_preferred":[
        "\u4e0a\u91d1\u72ee\u5251\u6751"
    ],
    "wof:name":"Shangjinshijiancun",
    "wof:placetype":"locality"
},
  "geometry": {"coordinates":[110.18752000000001,33.41656],"type":"Point"}
}