{
  "type": "Feature",
  "properties": {
    "gn:admin1_code":"12.0",
    "gn:asciiname":"Zhuzhi",
    "gn:country_code":"CN",
    "gn:dem":1149,
    "gn:feature_class":"P",
    "gn:feature_code":"PPL",
    "gn:name":"Zhuzhi",
    "gn:population":0,
    "gn:timezone":"Asia/Shanghai",
    "iso:country":"CN",
    "name:zho_x_preferred":[
        "Zhuzhi"
    ],
    "name:zho_x_variant":[
        "\u7af9\u679d"
    ],
    "wof:name":"Zhuzhi",
    "wof:placetype":"locality"
},
  "geometry": {"coordinates":[110.32711999999999,29.88614],"type":"Point"}
}