{
  "type": "Feature",
  "properties": {
    "gn:admin1_code":"30.0",
    "gn:asciiname":"Huangshakeng",
    "gn:country_code":"CN",
    "gn:dem":380,
    "gn:feature_class":"P",
    "gn:feature_code":"PPL",
    "gn:name":"Huangshakeng",
    "gn:population":0,
    "gn:timezone":"Asia/Shanghai",
    "iso:country":"CN",
    "name:zho_x_preferred":[
        "Huangshakeng"
    ],
    "name:zho_x_variant":[
        "\u9ec4\u6c99\u5751"
    ],
    "wof:name":"Huangshakeng",
    "wof:placetype":"locality"
},
  "geometry": {"coordinates":[113.93722,25.15194],"type":"Point"}
}