{
  "type": "Feature",
  "properties": {
    "gn:admin1_code":"1.0",
    "gn:asciiname":"Xiaoluoge",
    "gn:country_code":"CN",
    "gn:dem":8,
    "gn:feature_class":"P",
    "gn:feature_code":"PPL",
    "gn:name":"Xiaoluoge",
    "gn:population":0,
    "gn:timezone":"Asia/Shanghai",
    "iso:country":"CN",
    "name:zho_x_preferred":[
        "\u5c0f\u9a86\u5404"
    ],
    "wof:name":"Xiaoluoge",
    "wof:placetype":"locality"
},
  "geometry": {"coordinates":[118.25291,31.31687],"type":"Point"}
}