{
  "type": "Feature",
  "properties": {
    "gn:admin1_code":"32.0",
    "gn:asciiname":"Zijingou",
    "gn:country_code":"CN",
    "gn:dem":403,
    "gn:feature_class":"P",
    "gn:feature_code":"PPL",
    "gn:name":"Zijingou",
    "gn:population":0,
    "gn:timezone":"Asia/Shanghai",
    "iso:country":"CN",
    "name:zho_x_preferred":[
        "\u7d2b\u91d1\u6c9f"
    ],
    "wof:name":"Zijingou",
    "wof:placetype":"locality"
},
  "geometry": {"coordinates":[103.881,29.8822],"type":"Point"}
}