{
  "type": "Feature",
  "properties": {
    "gn:admin1_code":"11",
    "gn:asciiname":"Xikou",
    "gn:country_code":"CN",
    "gn:dem":335,
    "gn:feature_class":"P",
    "gn:feature_code":"PPL",
    "gn:name":"Xikou",
    "gn:population":0,
    "gn:timezone":"Asia/Shanghai",
    "iso:country":"CN",
    "name:fas_x_preferred":[
        "\u0634\u06cc\u06a9\u0648"
    ],
    "name:ita_x_preferred":[
        "Xikou"
    ],
    "name:nor_x_preferred":[
        "Xikou"
    ],
    "name:swe_x_preferred":[
        "Xikou"
    ],
    "name:zho_x_preferred":[
        "\u6eaa\u53e3\u9547"
    ],
    "wof:name":"Xikou",
    "wof:placetype":"locality"
},
  "geometry": {"coordinates":[110.06083,27.68944],"type":"Point"}
}