{
  "type": "Feature",
  "properties": {
    "gn:admin1_code":"2.0",
    "gn:asciiname":"Shizhuyang",
    "gn:country_code":"CN",
    "gn:dem":25,
    "gn:feature_class":"P",
    "gn:feature_code":"PPL",
    "gn:name":"Shizhuyang",
    "gn:population":0,
    "gn:timezone":"Asia/Shanghai",
    "iso:country":"CN",
    "name:zho_x_preferred":[
        "\u77f3\u67f1\u6d0b"
    ],
    "wof:name":"Shizhuyang",
    "wof:placetype":"locality"
},
  "geometry": {"coordinates":[120.88894999999999,29.85958],"type":"Point"}
}