{
  "type": "Feature",
  "properties": {
    "gn:admin1_code":"1.0",
    "gn:asciiname":"Yuesicun",
    "gn:country_code":"CN",
    "gn:dem":34,
    "gn:feature_class":"P",
    "gn:feature_code":"PPL",
    "gn:name":"Yuesicun",
    "gn:population":0,
    "gn:timezone":"Asia/Shanghai",
    "iso:country":"CN",
    "name:und_x_variant":[
        "Yuesi"
    ],
    "name:zho_x_preferred":[
        "\u5cb3\u5bfa\u6751"
    ],
    "wof:name":"Yuesicun",
    "wof:placetype":"locality"
},
  "geometry": {"coordinates":[116.075,33.69167],"type":"Point"}
}