{
  "type": "Feature",
  "properties": {
    "gn:admin1_code":"29.0",
    "gn:asciiname":"Tianning",
    "gn:country_code":"CN",
    "gn:dem":1081,
    "gn:feature_class":"P",
    "gn:feature_code":"PPL",
    "gn:name":"Tianning",
    "gn:population":0,
    "gn:timezone":"Asia/Shanghai",
    "iso:country":"CN",
    "name:deu_x_preferred":[
        "Tianning"
    ],
    "name:zho_x_preferred":[
        "\u5929\u5b81"
    ],
    "wof:name":"Tianning",
    "wof:placetype":"locality"
},
  "geometry": {"coordinates":[104.07213,28.11004],"type":"Point"}
}