{
  "type": "Feature",
  "properties": {
    "gn:admin1_code":"30.0",
    "gn:asciiname":"Shiliao",
    "gn:country_code":"CN",
    "gn:dem":874,
    "gn:feature_class":"P",
    "gn:feature_code":"PPL",
    "gn:name":"Shiliao",
    "gn:population":0,
    "gn:timezone":"Asia/Shanghai",
    "iso:country":"CN",
    "name:zho_x_preferred":[
        "\u77f3\u5bee"
    ],
    "wof:name":"Shiliao",
    "wof:placetype":"locality"
},
  "geometry": {"coordinates":[116.6198,23.98606],"type":"Point"}
}