{
  "type": "Feature",
  "properties": {
    "gn:admin1_code":"11",
    "gn:asciiname":"Quankou",
    "gn:country_code":"CN",
    "gn:dem":117,
    "gn:feature_class":"P",
    "gn:feature_code":"PPL",
    "gn:name":"Quankou",
    "gn:population":0,
    "gn:timezone":"Asia/Shanghai",
    "iso:country":"CN",
    "name:zho_x_preferred":[
        "\u6cc9\u53e3"
    ],
    "wof:name":"Quankou",
    "wof:placetype":"locality"
},
  "geometry": {"coordinates":[112.19356999999999,26.82868],"type":"Point"}
}