{
  "type": "Feature",
  "properties": {
    "gn:admin1_code":"22.0",
    "gn:asciiname":"Shangshibucun",
    "gn:country_code":"CN",
    "gn:dem":379,
    "gn:feature_class":"P",
    "gn:feature_code":"PPL",
    "gn:name":"Shangshibucun",
    "gn:population":0,
    "gn:timezone":"Asia/Shanghai",
    "iso:country":"CN",
    "name:zho_x_preferred":[
        "\u4e0a\u77f3\u5821\u6751"
    ],
    "wof:name":"Shangshibucun",
    "wof:placetype":"locality"
},
  "geometry": {"coordinates":[115.75382999999999,39.76017],"type":"Point"}
}