{
  "type": "Feature",
  "properties": {
    "gn:admin1_code":"10",
    "gn:asciiname":"Hezhuang",
    "gn:country_code":"CN",
    "gn:dem":46,
    "gn:feature_class":"P",
    "gn:feature_code":"PPL",
    "gn:name":"Hezhuang",
    "gn:population":0,
    "gn:timezone":"Asia/Shanghai",
    "iso:country":"CN",
    "name:ceb_x_preferred":[
        "Hezhuang"
    ],
    "name:swe_x_preferred":[
        "Hezhuang"
    ],
    "name:zho_x_preferred":[
        "\u548c\u5e84"
    ],
    "wof:name":"Hezhuang",
    "wof:placetype":"locality"
},
  "geometry": {"coordinates":[115.27997999999999,36.41202],"type":"Point"}
}