{
  "type": "Feature",
  "properties": {
    "gn:admin1_code":"33.0",
    "gn:asciiname":"Wubao",
    "gn:country_code":"CN",
    "gn:dem":478,
    "gn:feature_class":"P",
    "gn:feature_code":"PPLA4",
    "gn:name":"Wubao",
    "gn:population":0,
    "gn:timezone":"Asia/Shanghai",
    "iso:country":"CN",
    "name:und_x_variant":[
        "Wubao Zhen"
    ],
    "name:zho_x_preferred":[
        "\u4e94\u5b9d"
    ],
    "name:zho_x_variant":[
        "\u4e94\u5b9d\u9547"
    ],
    "wof:name":"Wubao",
    "wof:placetype":"locality"
},
  "geometry": {"coordinates":[106.83028,29.63235],"type":"Point"}
}