{
  "type": "Feature",
  "properties": {
    "gn:admin1_code":"4.0",
    "gn:asciiname":"Yangmiao",
    "gn:country_code":"CN",
    "gn:dem":14,
    "gn:feature_class":"P",
    "gn:feature_code":"PPLA4",
    "gn:name":"Yangmiao",
    "gn:population":0,
    "gn:timezone":"Asia/Shanghai",
    "iso:country":"CN",
    "name:und_x_variant":[
        "Yang-chia-miao",
        "Yangjiamiao",
        "Yangmiao",
        "Yangmiao Zhen"
    ],
    "name:zho_x_preferred":[
        "\u6768\u5e99"
    ],
    "name:zho_x_variant":[
        "\u6768\u5e99\u9547"
    ],
    "wof:name":"Yangmiao",
    "wof:placetype":"locality"
},
  "geometry": {"coordinates":[119.32980999999999,32.41603],"type":"Point"}
}