{
  "type": "Feature",
  "properties": {
    "gn:admin1_code":"25",
    "gn:asciiname":"Shijia",
    "gn:country_code":"CN",
    "gn:dem":22,
    "gn:feature_class":"P",
    "gn:feature_code":"PPL",
    "gn:name":"Shijia",
    "gn:population":0,
    "gn:timezone":"Asia/Shanghai",
    "iso:country":"CN",
    "name:zho_x_preferred":[
        "\u53f2\u5bb6"
    ],
    "wof:name":"Shijia",
    "wof:placetype":"locality"
},
  "geometry": {"coordinates":[118.51900000000001,36.9363],"type":"Point"}
}