{
  "type": "Feature",
  "properties": {
    "gn:admin1_code":"7",
    "gn:asciiname":"Mayang",
    "gn:country_code":"CN",
    "gn:dem":609,
    "gn:feature_class":"P",
    "gn:feature_code":"PPL",
    "gn:name":"Mayang",
    "gn:population":0,
    "gn:timezone":"Asia/Shanghai",
    "iso:country":"CN",
    "name:und_x_variant":[
        "\u9a6c\u6d0b",
        "Mayang"
    ],
    "wof:name":"Mayang",
    "wof:placetype":"locality"
},
  "geometry": {"coordinates":[119.50899,27.18082],"type":"Point"}
}