{
  "type": "Feature",
  "properties": {
    "gn:admin1_code":"09",
    "gn:asciiname":"Lishujie",
    "gn:country_code":"CN",
    "gn:dem":823,
    "gn:feature_class":"P",
    "gn:feature_code":"PPL",
    "gn:name":"Lishujie",
    "gn:population":0,
    "gn:timezone":"Asia/Shanghai",
    "iso:country":"CN",
    "name:zho_x_preferred":[
        "\u6817\u6811\u8857"
    ],
    "wof:name":"Lishujie",
    "wof:placetype":"locality"
},
  "geometry": {"coordinates":[111.97132999999999,33.76236],"type":"Point"}
}