{
  "type": "Feature",
  "properties": {
    "gn:admin1_code":"19.0",
    "gn:asciiname":"Shidonggoucun",
    "gn:country_code":"CN",
    "gn:dem":92,
    "gn:feature_class":"P",
    "gn:feature_code":"PPL",
    "gn:name":"Shidonggoucun",
    "gn:population":0,
    "gn:timezone":"Asia/Shanghai",
    "iso:country":"CN",
    "name:zho_x_preferred":[
        "\u77f3\u6d1e\u6c9f\u6751"
    ],
    "wof:name":"Shidonggoucun",
    "wof:placetype":"locality"
},
  "geometry": {"coordinates":[121.488,38.8589],"type":"Point"}
}