{
  "type": "Feature",
  "properties": {
    "gn:admin1_code":"29.0",
    "gn:asciiname":"Miaojia",
    "gn:country_code":"CN",
    "gn:dem":1724,
    "gn:feature_class":"P",
    "gn:feature_code":"PPL",
    "gn:name":"Miaojia",
    "gn:population":0,
    "gn:timezone":"Asia/Shanghai",
    "iso:country":"CN",
    "name:zho_x_preferred":[
        "\u82d7\u5bb6"
    ],
    "wof:name":"Miaojia",
    "wof:placetype":"locality"
},
  "geometry": {"coordinates":[99.6735,25.0235],"type":"Point"}
}