{
  "type": "Feature",
  "properties": {
    "gn:admin1_code":"10",
    "gn:asciiname":"Nanxiaochen",
    "gn:country_code":"CN",
    "gn:dem":37,
    "gn:feature_class":"P",
    "gn:feature_code":"PPL",
    "gn:name":"Nanxiaochen",
    "gn:population":0,
    "gn:timezone":"Asia/Shanghai",
    "iso:country":"CN",
    "name:zho_x_preferred":[
        "\u5357\u5c0f\u9648"
    ],
    "wof:name":"Nanxiaochen",
    "wof:placetype":"locality"
},
  "geometry": {"coordinates":[115.273,37.9788],"type":"Point"}
}