{
  "type": "Feature",
  "properties": {
    "gn:admin1_code":"16",
    "gn:asciiname":"Tong'an",
    "gn:country_code":"CN",
    "gn:dem":141,
    "gn:feature_class":"P",
    "gn:feature_code":"PPL",
    "gn:name":"Tong\u2019an",
    "gn:population":0,
    "gn:timezone":"Asia/Shanghai",
    "iso:country":"CN",
    "name:und_x_variant":[
        "T\u2019ung-an-hs\u00fc",
        "T\u2019ung-an",
        "Tong\u2019an"
    ],
    "wof:name":"Tong'an",
    "wof:placetype":"locality"
},
  "geometry": {"coordinates":[110.91667,24.58333],"type":"Point"}
}