{
  "type": "Feature",
  "properties": {
    "gn:admin1_code":"5.0",
    "gn:asciiname":"Baoxiancun",
    "gn:country_code":"CN",
    "gn:dem":391,
    "gn:feature_class":"P",
    "gn:feature_code":"PPL",
    "gn:name":"Baoxiancun",
    "gn:population":0,
    "gn:timezone":"Asia/Shanghai",
    "iso:country":"CN",
    "name:zho_x_preferred":[
        "\u4fdd\u8d24\u6751"
    ],
    "wof:name":"Baoxiancun",
    "wof:placetype":"locality"
},
  "geometry": {"coordinates":[125.60109,42.35109],"type":"Point"}
}