{
  "type": "Feature",
  "properties": {
    "gn:admin1_code":"10.0",
    "gn:asciiname":"Xihuangcun",
    "gn:cc2":"CN",
    "gn:country_code":"CN",
    "gn:dem":274,
    "gn:feature_class":"P",
    "gn:feature_code":"PPL",
    "gn:name":"Xihuangcun",
    "gn:population":0,
    "gn:timezone":"Asia/Shanghai",
    "iso:country":"CN",
    "name:und_x_variant":[
        "Hsi-huang-ts\u2019un",
        "Sihuangsi",
        "Xihuangcun"
    ],
    "wof:name":"Xihuangcun",
    "wof:placetype":"locality"
},
  "geometry": {"coordinates":[114.22278,37.14028],"type":"Point"}
}