{
  "type": "Feature",
  "properties": {
    "gn:admin1_code":"9",
    "gn:asciiname":"Chaozhai",
    "gn:country_code":"CN",
    "gn:dem":59,
    "gn:feature_class":"P",
    "gn:feature_code":"PPL",
    "gn:name":"Chaozhai",
    "gn:population":0,
    "gn:timezone":"Asia/Shanghai",
    "iso:country":"CN",
    "name:zho_x_preferred":[
        "\u6641\u5be8"
    ],
    "wof:name":"Chaozhai",
    "wof:placetype":"locality"
},
  "geometry": {"coordinates":[115.154,35.5095],"type":"Point"}
}