{
  "type": "Feature",
  "properties": {
    "gn:admin1_code":"11.0",
    "gn:asciiname":"Pingtouling",
    "gn:country_code":"CN",
    "gn:dem":735,
    "gn:feature_class":"P",
    "gn:feature_code":"PPL",
    "gn:name":"Pingtouling",
    "gn:population":0,
    "gn:timezone":"Asia/Shanghai",
    "iso:country":"CN",
    "name:zho_x_preferred":[
        "\u5e73\u5934\u5cad"
    ],
    "wof:name":"Pingtouling",
    "wof:placetype":"locality"
},
  "geometry": {"coordinates":[112.92806000000002,25.48095],"type":"Point"}
}