{
  "type": "Feature",
  "properties": {
    "gn:admin1_code":"20.0",
    "gn:asciiname":"Jiaqing",
    "gn:country_code":"CN",
    "gn:dem":1125,
    "gn:feature_class":"P",
    "gn:feature_code":"PPL",
    "gn:name":"Jiaqing",
    "gn:population":0,
    "gn:timezone":"Asia/Shanghai",
    "iso:country":"CN",
    "name:und_x_variant":[
        "\u67b7\u9752"
    ],
    "wof:name":"Jiaqing",
    "wof:placetype":"locality"
},
  "geometry": {"coordinates":[111.38768,39.78035],"type":"Point"}
}