{
  "type": "Feature",
  "properties": {
    "gn:admin1_code":"19.0",
    "gn:asciiname":"Songshu Lianggoucun",
    "gn:country_code":"CN",
    "gn:dem":221,
    "gn:feature_class":"P",
    "gn:feature_code":"PPL",
    "gn:name":"Songshu Lianggoucun",
    "gn:population":0,
    "gn:timezone":"Asia/Shanghai",
    "iso:country":"CN",
    "name:zho_x_preferred":[
        "\u677e\u6811\u6881\u6c9f\u6751"
    ],
    "wof:name":"Songshu Lianggoucun",
    "wof:placetype":"locality"
},
  "geometry": {"coordinates":[121.01600000000001,41.7921],"type":"Point"}
}