{
  "type": "Feature",
  "properties": {
    "gn:admin1_code":"32.0",
    "gn:asciiname":"Abaxian Muchang",
    "gn:country_code":"CN",
    "gn:dem":3491,
    "gn:feature_class":"P",
    "gn:feature_code":"PPLF",
    "gn:name":"Abaxian Muchang",
    "gn:population":0,
    "gn:timezone":"Asia/Shanghai",
    "iso:country":"CN",
    "name:zho_x_preferred":[
        "\u963f\u575d\u53bf\u7267\u573a"
    ],
    "wof:name":"Abaxian Muchang",
    "wof:placetype":"locality"
},
  "geometry": {"coordinates":[102.11969000000001,33.09894],"type":"Point"}
}