{
  "type": "Feature",
  "properties": {
    "gn:admin1_code":"4.0",
    "gn:asciiname":"Xuzui",
    "gn:country_code":"CN",
    "gn:dem":18,
    "gn:feature_class":"P",
    "gn:feature_code":"PPL",
    "gn:name":"Xuzui",
    "gn:population":0,
    "gn:timezone":"Asia/Shanghai",
    "iso:country":"CN",
    "name:zho_x_preferred":[
        "\u8bb8\u5634"
    ],
    "wof:name":"Xuzui",
    "wof:placetype":"locality"
},
  "geometry": {"coordinates":[118.621,33.11],"type":"Point"}
}