{
  "type": "Feature",
  "properties": {
    "gn:admin1_code":"32.0",
    "gn:asciiname":"Fangwuji",
    "gn:country_code":"CN",
    "gn:dem":353,
    "gn:feature_class":"P",
    "gn:feature_code":"PPL",
    "gn:name":"Fangwuji",
    "gn:population":0,
    "gn:timezone":"Asia/Shanghai",
    "iso:country":"CN",
    "name:zho_x_preferred":[
        "\u65b9\u5c4b\u57fa"
    ],
    "wof:name":"Fangwuji",
    "wof:placetype":"locality"
},
  "geometry": {"coordinates":[104.685,28.9952],"type":"Point"}
}