{
  "type": "Feature",
  "properties": {
    "gn:admin1_code":"30.0",
    "gn:asciiname":"Mazhong'ao",
    "gn:country_code":"CN",
    "gn:dem":297,
    "gn:feature_class":"P",
    "gn:feature_code":"PPL",
    "gn:name":"Mazhong\u2019ao",
    "gn:population":0,
    "gn:timezone":"Asia/Shanghai",
    "iso:country":"CN",
    "name:und_x_variant":[
        "Mazhong\u2019ao",
        "\u9a6c\u4e2d\u5787"
    ],
    "wof:name":"Mazhong'ao",
    "wof:placetype":"locality"
},
  "geometry": {"coordinates":[114.26479,24.45877],"type":"Point"}
}