{
  "type": "Feature",
  "properties": {
    "gn:admin1_code":"30",
    "gn:asciiname":"Beifeng",
    "gn:country_code":"CN",
    "gn:dem":13,
    "gn:feature_class":"P",
    "gn:feature_code":"PPL",
    "gn:name":"Beifeng",
    "gn:population":0,
    "gn:timezone":"Asia/Urumqi",
    "iso:country":"CN",
    "name:zho_x_preferred":[
        "\u5317\u4e30"
    ],
    "wof:name":"Beifeng",
    "wof:placetype":"locality"
},
  "geometry": {"coordinates":[110.92588000000001,21.56636],"type":"Point"}
}