{
  "type": "Feature",
  "properties": {
    "gn:admin1_code":"14.0",
    "gn:asciiname":"Suodaike",
    "gn:country_code":"CN",
    "gn:dem":4407,
    "gn:feature_class":"P",
    "gn:feature_code":"PPL",
    "gn:name":"Suodaike",
    "gn:population":0,
    "gn:timezone":"Asia/Urumqi",
    "iso:country":"CN",
    "name:zho_x_preferred":[
        "\u7d22\u5446\u53ef"
    ],
    "wof:name":"Suodaike",
    "wof:placetype":"locality"
},
  "geometry": {"coordinates":[91.36834,30.57706],"type":"Point"}
}