{
  "type": "Feature",
  "properties": {
    "gn:admin1_code":"12.0",
    "gn:asciiname":"Fanshang",
    "gn:country_code":"CN",
    "gn:dem":136,
    "gn:feature_class":"P",
    "gn:feature_code":"PPL",
    "gn:name":"Fanshang",
    "gn:population":0,
    "gn:timezone":"Asia/Shanghai",
    "iso:country":"CN",
    "name:zho_x_preferred":[
        "\u7548\u4e0a"
    ],
    "wof:name":"Fanshang",
    "wof:placetype":"locality"
},
  "geometry": {"coordinates":[113.30467,32.09013],"type":"Point"}
}