{
  "type": "Feature",
  "properties": {
    "gn:admin1_code":"32.0",
    "gn:asciiname":"Yajiaogou",
    "gn:country_code":"CN",
    "gn:dem":3090,
    "gn:feature_class":"P",
    "gn:feature_code":"PPL",
    "gn:name":"Yajiaogou",
    "gn:population":0,
    "gn:timezone":"Asia/Shanghai",
    "iso:country":"CN",
    "name:zho_x_preferred":[
        "\u9e2d\u811a\u6c9f"
    ],
    "wof:name":"Yajiaogou",
    "wof:placetype":"locality"
},
  "geometry": {"coordinates":[102.15246,30.84395],"type":"Point"}
}