{
  "type": "Feature",
  "properties": {
    "gn:admin1_code":"31.0",
    "gn:asciiname":"Shina",
    "gn:country_code":"CN",
    "gn:dem":78,
    "gn:feature_class":"P",
    "gn:feature_code":"PPL",
    "gn:name":"Shina",
    "gn:population":0,
    "gn:timezone":"Asia/Shanghai",
    "iso:country":"CN",
    "name:ceb_x_preferred":[
        "Shina"
    ],
    "name:swe_x_preferred":[
        "Shina"
    ],
    "name:und_x_variant":[
        "\u4ec0\u90a3"
    ],
    "name:uzb_x_preferred":[
        "Shina"
    ],
    "name:zho_x_preferred":[
        "\u652f\u90a3"
    ],
    "wof:name":"Shina",
    "wof:placetype":"locality"
},
  "geometry": {"coordinates":[109.80292,18.67136],"type":"Point"}
}