{
  "type": "Feature",
  "properties": {
    "gn:admin1_code":"15.0",
    "gn:asciiname":"Qiugousi",
    "gn:country_code":"CN",
    "gn:dem":1582,
    "gn:feature_class":"P",
    "gn:feature_code":"PPL",
    "gn:name":"Qiugousi",
    "gn:population":0,
    "gn:timezone":"Asia/Shanghai",
    "iso:country":"CN",
    "name:zho_x_preferred":[
        "\u6e6b\u6c9f\u5bfa"
    ],
    "wof:name":"Qiugousi",
    "wof:placetype":"locality"
},
  "geometry": {"coordinates":[105.16,34.7109],"type":"Point"}
}