{
  "type": "Feature",
  "properties": {
    "gn:admin1_code":"11.0",
    "gn:asciiname":"Leigutai",
    "gn:country_code":"CN",
    "gn:dem":45,
    "gn:feature_class":"P",
    "gn:feature_code":"PPL",
    "gn:name":"Leigutai",
    "gn:population":0,
    "gn:timezone":"Asia/Shanghai",
    "iso:country":"CN",
    "name:zho_x_preferred":[
        "\u64c2\u9f13\u53f0"
    ],
    "wof:name":"Leigutai",
    "wof:placetype":"locality"
},
  "geometry": {"coordinates":[112.97163,27.97968],"type":"Point"}
}