{
  "type": "Feature",
  "properties": {
    "gn:admin1_code":"8.0",
    "gn:asciiname":"Heshantun",
    "gn:country_code":"CN",
    "gn:dem":199,
    "gn:feature_class":"P",
    "gn:feature_code":"PPL",
    "gn:name":"Heshantun",
    "gn:population":0,
    "gn:timezone":"Asia/Shanghai",
    "iso:country":"CN",
    "name:zho_x_preferred":[
        "\u6cb3\u5c71\u5c6f"
    ],
    "wof:name":"Heshantun",
    "wof:placetype":"locality"
},
  "geometry": {"coordinates":[127.24141000000002,45.23089],"type":"Point"}
}