{
  "type": "Feature",
  "properties": {
    "gn:admin1_code":"26",
    "gn:asciiname":"Cuijiashanzhai",
    "gn:country_code":"CN",
    "gn:dem":522,
    "gn:feature_class":"P",
    "gn:feature_code":"PPL",
    "gn:name":"Cuijiashanzhai",
    "gn:population":0,
    "gn:timezone":"Asia/Shanghai",
    "iso:country":"CN",
    "wof:name":"Cuijiashanzhai",
    "wof:placetype":"locality"
},
  "geometry": {"coordinates":[107.16417,33.15778],"type":"Point"}
}