{
  "type": "Feature",
  "properties": {
    "gn:admin1_code":"24.0",
    "gn:asciiname":"Zhenggou",
    "gn:country_code":"CN",
    "gn:dem":1421,
    "gn:feature_class":"P",
    "gn:feature_code":"PPL",
    "gn:name":"Zhenggou",
    "gn:population":0,
    "gn:timezone":"Asia/Shanghai",
    "iso:country":"CN",
    "name:zho_x_preferred":[
        "\u6b63\u6c9f"
    ],
    "wof:name":"Zhenggou",
    "wof:placetype":"locality"
},
  "geometry": {"coordinates":[111.67428999999998,38.40843],"type":"Point"}
}