{
  "type": "Feature",
  "properties": {
    "gn:admin1_code":"31",
    "gn:asciiname":"Wuchang",
    "gn:country_code":"CN",
    "gn:dem":3,
    "gn:feature_class":"P",
    "gn:feature_code":"PPL",
    "gn:name":"Wuchang",
    "gn:population":0,
    "gn:timezone":"Asia/Shanghai",
    "iso:country":"CN",
    "name:und_x_variant":[
        "\u4e4c\u573a"
    ],
    "wof:name":"Wuchang",
    "wof:placetype":"locality"
},
  "geometry": {"coordinates":[110.48099999999999,18.7832],"type":"Point"}
}