{
  "type": "Feature",
  "properties": {
    "gn:admin1_code":"32.0",
    "gn:asciiname":"Yinhe",
    "gn:country_code":"CN",
    "gn:dem":2472,
    "gn:feature_class":"P",
    "gn:feature_code":"PPL",
    "gn:name":"Yinhe",
    "gn:population":0,
    "gn:timezone":"Asia/Shanghai",
    "iso:country":"CN",
    "name:zho_x_preferred":[
        "\u9634\u6cb3"
    ],
    "wof:name":"Yinhe",
    "wof:placetype":"locality"
},
  "geometry": {"coordinates":[101.35803,27.53389],"type":"Point"}
}