{
  "type": "Feature",
  "properties": {
    "gn:admin1_code":"10",
    "gn:asciiname":"Pangjiaqiao",
    "gn:country_code":"CN",
    "gn:dem":24,
    "gn:feature_class":"P",
    "gn:feature_code":"PPL",
    "gn:name":"Pangjiaqiao",
    "gn:population":0,
    "gn:timezone":"Asia/Shanghai",
    "iso:country":"CN",
    "name:zho_x_preferred":[
        "\u5e9e\u5bb6\u6865"
    ],
    "wof:name":"Pangjiaqiao",
    "wof:placetype":"locality"
},
  "geometry": {"coordinates":[116.45107,37.56800000000001],"type":"Point"}
}