{
  "type": "Feature",
  "properties": {
    "gn:admin1_code":"26.0",
    "gn:asciiname":"Huapi'ao",
    "gn:country_code":"CN",
    "gn:dem":1083,
    "gn:feature_class":"P",
    "gn:feature_code":"PPL",
    "gn:name":"Huapi\u2019ao",
    "gn:population":0,
    "gn:timezone":"Asia/Shanghai",
    "iso:country":"CN",
    "name:und_x_variant":[
        "Huapi\u2019ao"
    ],
    "name:zho_x_preferred":[
        "\u6866\u76ae\u51f9"
    ],
    "wof:name":"Huapi'ao",
    "wof:placetype":"locality"
},
  "geometry": {"coordinates":[109.75865,33.27198],"type":"Point"}
}