{
  "type": "Feature",
  "properties": {
    "gn:admin1_code":"7",
    "gn:asciiname":"Qianshan",
    "gn:country_code":"CN",
    "gn:dem":149,
    "gn:feature_class":"P",
    "gn:feature_code":"PPL",
    "gn:name":"Qianshan",
    "gn:population":0,
    "gn:timezone":"Asia/Shanghai",
    "iso:country":"CN",
    "name:ceb_x_preferred":[
        "Qianshan"
    ],
    "name:deu_x_preferred":[
        "Qianshan"
    ],
    "name:fra_x_preferred":[
        "Qianshan"
    ],
    "name:nor_x_preferred":[
        "Qianshan"
    ],
    "name:rus_x_preferred":[
        "\u0426\u044f\u043d\u044c\u0448\u0430\u043d\u044c"
    ],
    "name:swe_x_preferred":[
        "Qianshan"
    ],
    "name:und_x_variant":[
        "\u94b1\u5c71"
    ],
    "wof:name":"Qianshan",
    "wof:placetype":"locality"
},
  "geometry": {"coordinates":[118.67556,27.12361],"type":"Point"}
}