{
  "type": "Feature",
  "properties": {
    "gn:admin1_code":"30",
    "gn:asciiname":"Darentang",
    "gn:country_code":"CN",
    "gn:dem":52,
    "gn:feature_class":"P",
    "gn:feature_code":"PPL",
    "gn:name":"Darentang",
    "gn:population":0,
    "gn:timezone":"Asia/Urumqi",
    "iso:country":"CN",
    "name:zho_x_preferred":[
        "\u5927\u4ec1\u5858"
    ],
    "wof:name":"Darentang",
    "wof:placetype":"locality"
},
  "geometry": {"coordinates":[110.71919,22.0331],"type":"Point"}
}