{
  "type": "Feature",
  "properties": {
    "gn:admin1_code":"1.0",
    "gn:asciiname":"Shimacun",
    "gn:country_code":"CN",
    "gn:dem":24,
    "gn:feature_class":"P",
    "gn:feature_code":"PPL",
    "gn:name":"Shimacun",
    "gn:population":0,
    "gn:timezone":"Asia/Shanghai",
    "iso:country":"CN",
    "name:und_x_variant":[
        "Shima",
        "Shimacun"
    ],
    "name:zho_x_preferred":[
        "\u77f3\u9a6c\u6751"
    ],
    "wof:name":"Shimacun",
    "wof:placetype":"locality"
},
  "geometry": {"coordinates":[118.57989000000001,31.64093],"type":"Point"}
}