{
  "type": "Feature",
  "properties": {
    "gn:admin1_code":"14.0",
    "gn:asciiname":"Xarma",
    "gn:country_code":"CN",
    "gn:dem":4837,
    "gn:feature_class":"P",
    "gn:feature_code":"PPLA4",
    "gn:name":"Xarma",
    "gn:population":0,
    "gn:timezone":"Asia/Urumqi",
    "iso:country":"CN",
    "name:bod_x_preferred":[
        "Xarma"
    ],
    "name:fas_x_preferred":[
        "\u0634\u0627\u0631\u0645\u0627"
    ],
    "name:msa_x_preferred":[
        "Xarma"
    ],
    "name:und_x_variant":[
        "Xiama Xiang"
    ],
    "name:zho_x_preferred":[
        "Xiama"
    ],
    "name:zho_x_variant":[
        "\u590f\u739b",
        "\u590f\u739b\u4e61"
    ],
    "wof:name":"Xarma",
    "wof:placetype":"locality"
},
  "geometry": {"coordinates":[92.68124,30.79792],"type":"Point"}
}