{
  "type": "Feature",
  "properties": {
    "gn:admin1_code":"1.0",
    "gn:asciiname":"Shigangcun",
    "gn:country_code":"CN",
    "gn:dem":23,
    "gn:feature_class":"P",
    "gn:feature_code":"PPL",
    "gn:name":"Shigangcun",
    "gn:population":0,
    "gn:timezone":"Asia/Shanghai",
    "iso:country":"CN",
    "name:und_x_variant":[
        "Shigang"
    ],
    "name:zho_x_preferred":[
        "\u77f3\u5c97\u6751"
    ],
    "wof:name":"Shigangcun",
    "wof:placetype":"locality"
},
  "geometry": {"coordinates":[116.92165,31.5109],"type":"Point"}
}