{
  "type": "Feature",
  "properties": {
    "gn:admin1_code":"18",
    "gn:asciiname":"Tiziyan",
    "gn:country_code":"CN",
    "gn:dem":796,
    "gn:feature_class":"P",
    "gn:feature_code":"PPL",
    "gn:name":"Tiziyan",
    "gn:population":0,
    "gn:timezone":"Asia/Shanghai",
    "iso:country":"CN",
    "name:zho_x_preferred":[
        "\u68af\u5b50\u5830"
    ],
    "wof:name":"Tiziyan",
    "wof:placetype":"locality"
},
  "geometry": {"coordinates":[107.21899999999999,27.7394],"type":"Point"}
}