{
  "type": "Feature",
  "properties": {
    "gn:admin1_code":"12",
    "gn:asciiname":"Liangshuihe",
    "gn:country_code":"CN",
    "gn:dem":198,
    "gn:feature_class":"P",
    "gn:feature_code":"PPLA4",
    "gn:name":"Liangshuihe",
    "gn:population":0,
    "gn:timezone":"Asia/Shanghai",
    "iso:country":"CN",
    "name:und_x_variant":[
        "Liangshuihe Zhen"
    ],
    "name:zho_x_preferred":[
        "\u51c9\u6c34\u6cb3"
    ],
    "name:zho_x_variant":[
        "\u51c9\u6c34\u6cb3\u9547"
    ],
    "wof:name":"Liangshuihe",
    "wof:placetype":"locality"
},
  "geometry": {"coordinates":[111.4661,32.64635],"type":"Point"}
}