{
  "type": "Feature",
  "properties": {
    "gn:admin1_code":"15.0",
    "gn:asciiname":"Shuguang",
    "gn:country_code":"CN",
    "gn:dem":2647,
    "gn:feature_class":"P",
    "gn:feature_code":"PPL",
    "gn:name":"Shuguang",
    "gn:population":0,
    "gn:timezone":"Asia/Shanghai",
    "iso:country":"CN",
    "name:und_x_variant":[
        "\u66d9\u5149"
    ],
    "wof:name":"Shuguang",
    "wof:placetype":"locality"
},
  "geometry": {"coordinates":[104.22512,34.51857],"type":"Point"}
}