{
  "type": "Feature",
  "properties": {
    "gn:admin1_code":"2.0",
    "gn:asciiname":"Xiadianmiaocun",
    "gn:country_code":"CN",
    "gn:dem":6,
    "gn:feature_class":"P",
    "gn:feature_code":"PPL",
    "gn:name":"Xiadianmiaocun",
    "gn:population":0,
    "gn:timezone":"Asia/Shanghai",
    "iso:country":"CN",
    "name:und_x_variant":[
        "Hsia-tien-miao",
        "Xiadianmiao",
        "\u4e0b\u7538\u5e99",
        "Xiadianmiaocun"
    ],
    "name:zho_x_preferred":[
        "\u4e0b\u7538\u5e99\u6751"
    ],
    "wof:name":"Xiadianmiaocun",
    "wof:placetype":"locality"
},
  "geometry": {"coordinates":[120.84724,30.94716],"type":"Point"}
}