{
  "type": "Feature",
  "properties": {
    "gn:admin1_code":"12.0",
    "gn:asciiname":"Mantouzhai",
    "gn:country_code":"CN",
    "gn:dem":558,
    "gn:feature_class":"P",
    "gn:feature_code":"PPL",
    "gn:name":"Mantouzhai",
    "gn:population":0,
    "gn:timezone":"Asia/Shanghai",
    "iso:country":"CN",
    "name:zho_x_preferred":[
        "\u9992\u5934\u5be8"
    ],
    "wof:name":"Mantouzhai",
    "wof:placetype":"locality"
},
  "geometry": {"coordinates":[110.03983999999998,32.9157],"type":"Point"}
}