{
  "type": "Feature",
  "properties": {
    "gn:admin1_code":"4.0",
    "gn:asciiname":"Xiangling'an",
    "gn:country_code":"CN",
    "gn:dem":94,
    "gn:feature_class":"P",
    "gn:feature_code":"PPL",
    "gn:name":"Xiangling\u2019an",
    "gn:population":0,
    "gn:timezone":"Asia/Shanghai",
    "iso:country":"CN",
    "name:und_x_variant":[
        "Xiangling\u2019an"
    ],
    "name:zho_x_preferred":[
        "\u54cd\u94c3\u5eb5"
    ],
    "wof:name":"Xiangling'an",
    "wof:placetype":"locality"
},
  "geometry": {"coordinates":[118.57116000000001,32.06015],"type":"Point"}
}