{
  "type": "Feature",
  "properties": {
    "gn:admin1_code":"11",
    "gn:asciiname":"Shuitong Mushan",
    "gn:country_code":"CN",
    "gn:dem":326,
    "gn:feature_class":"P",
    "gn:feature_code":"PPL",
    "gn:name":"Shuitong Mushan",
    "gn:population":0,
    "gn:timezone":"Asia/Shanghai",
    "iso:country":"CN",
    "name:zho_x_preferred":[
        "\u6c34\u6850\u6728\u5c71"
    ],
    "wof:name":"Shuitong Mushan",
    "wof:placetype":"locality"
},
  "geometry": {"coordinates":[111.16128999999999,27.17054000000001],"type":"Point"}
}