{
  "type": "Feature",
  "properties": {
    "gn:admin1_code":"9.0",
    "gn:asciiname":"Linanchong",
    "gn:country_code":"CN",
    "gn:dem":139,
    "gn:feature_class":"P",
    "gn:feature_code":"PPL",
    "gn:name":"Linanchong",
    "gn:population":0,
    "gn:timezone":"Asia/Shanghai",
    "iso:country":"CN",
    "name:zho_x_preferred":[
        "\u674e\u5357\u51b2"
    ],
    "wof:name":"Linanchong",
    "wof:placetype":"locality"
},
  "geometry": {"coordinates":[115.02502,31.73429],"type":"Point"}
}