{
  "type": "Feature",
  "properties": {
    "gn:admin1_code":"32.0",
    "gn:asciiname":"Chuanyan",
    "gn:country_code":"CN",
    "gn:dem":340,
    "gn:feature_class":"P",
    "gn:feature_code":"PPL",
    "gn:name":"Chuanyan",
    "gn:population":0,
    "gn:timezone":"Asia/Shanghai",
    "iso:country":"CN",
    "name:zho_x_preferred":[
        "\u7a7f\u5ca9"
    ],
    "wof:name":"Chuanyan",
    "wof:placetype":"locality"
},
  "geometry": {"coordinates":[106.036,30.3892],"type":"Point"}
}