{
  "type": "Feature",
  "properties": {
    "gn:admin1_code":"11.0",
    "gn:asciiname":"Leigongling",
    "gn:country_code":"CN",
    "gn:dem":650,
    "gn:feature_class":"P",
    "gn:feature_code":"PPL",
    "gn:name":"Leigongling",
    "gn:population":0,
    "gn:timezone":"Asia/Shanghai",
    "iso:country":"CN",
    "name:zho_x_preferred":[
        "\u96f7\u516c\u5cad"
    ],
    "wof:name":"Leigongling",
    "wof:placetype":"locality"
},
  "geometry": {"coordinates":[112.02857,24.9389],"type":"Point"}
}