{
  "type": "Feature",
  "properties": {
    "gn:admin1_code":"9.0",
    "gn:asciiname":"Laosunying",
    "gn:country_code":"CN",
    "gn:dem":121,
    "gn:feature_class":"P",
    "gn:feature_code":"PPL",
    "gn:name":"Laosunying",
    "gn:population":0,
    "gn:timezone":"Asia/Shanghai",
    "iso:country":"CN",
    "name:zho_x_preferred":[
        "\u8001\u5b59\u8425"
    ],
    "wof:name":"Laosunying",
    "wof:placetype":"locality"
},
  "geometry": {"coordinates":[112.0125,32.77742],"type":"Point"}
}