{
  "type": "Feature",
  "properties": {
    "gn:admin1_code":"9",
    "gn:asciiname":"Lizhanrong",
    "gn:country_code":"CN",
    "gn:dem":55,
    "gn:feature_class":"P",
    "gn:feature_code":"PPL",
    "gn:name":"Lizhanrong",
    "gn:population":0,
    "gn:timezone":"Asia/Shanghai",
    "iso:country":"CN",
    "name:zho_x_preferred":[
        "\u674e\u5360\u8363"
    ],
    "wof:name":"Lizhanrong",
    "wof:placetype":"locality"
},
  "geometry": {"coordinates":[114.851,34.1199],"type":"Point"}
}