{
  "type": "Feature",
  "properties": {
    "gn:admin1_code":"11.0",
    "gn:asciiname":"Datouxi",
    "gn:country_code":"CN",
    "gn:dem":494,
    "gn:feature_class":"P",
    "gn:feature_code":"PPL",
    "gn:name":"Datouxi",
    "gn:population":0,
    "gn:timezone":"Asia/Shanghai",
    "iso:country":"CN",
    "name:zho_x_preferred":[
        "\u5927\u5934\u6eaa"
    ],
    "wof:name":"Datouxi",
    "wof:placetype":"locality"
},
  "geometry": {"coordinates":[109.66003000000001,29.11298],"type":"Point"}
}