{
  "type": "Feature",
  "properties": {
    "gn:admin1_code":"26.0",
    "gn:asciiname":"Xiayaowan",
    "gn:country_code":"CN",
    "gn:dem":1321,
    "gn:feature_class":"P",
    "gn:feature_code":"PPL",
    "gn:name":"Xiayaowan",
    "gn:population":0,
    "gn:timezone":"Asia/Shanghai",
    "iso:country":"CN",
    "name:und_x_variant":[
        "\u4e0b\u7a91\u6e7e"
    ],
    "wof:name":"Xiayaowan",
    "wof:placetype":"locality"
},
  "geometry": {"coordinates":[107.07905,33.99736],"type":"Point"}
}