{
  "type": "Feature",
  "properties": {
    "gn:admin1_code":"05",
    "gn:asciiname":"Gudonghe",
    "gn:country_code":"CN",
    "gn:dem":557,
    "gn:feature_class":"P",
    "gn:feature_code":"PPL",
    "gn:name":"Gudonghe",
    "gn:population":0,
    "gn:timezone":"Asia/Shanghai",
    "iso:country":"CN",
    "wof:name":"Gudonghe",
    "wof:placetype":"locality"
},
  "geometry": {"coordinates":[128.38306,42.93306],"type":"Point"}
}