{
  "type": "Feature",
  "properties": {
    "gn:admin1_code":"3.0",
    "gn:asciiname":"Baitian",
    "gn:country_code":"CN",
    "gn:dem":119,
    "gn:feature_class":"P",
    "gn:feature_code":"PPL",
    "gn:name":"Baitian",
    "gn:population":0,
    "gn:timezone":"Asia/Shanghai",
    "iso:country":"CN",
    "name:und_x_variant":[
        "\u767d\u7530"
    ],
    "wof:name":"Baitian",
    "wof:placetype":"locality"
},
  "geometry": {"coordinates":[116.35959,26.92634],"type":"Point"}
}