{
  "type": "Feature",
  "properties": {
    "gn:admin1_code":"14",
    "gn:asciiname":"Nazha",
    "gn:country_code":"CN",
    "gn:dem":4760,
    "gn:feature_class":"P",
    "gn:feature_code":"PPL",
    "gn:name":"Nazha",
    "gn:population":0,
    "gn:timezone":"Asia/Urumqi",
    "iso:country":"CN",
    "name:zho_x_preferred":[
        "\u90a3\u624e"
    ],
    "wof:name":"Nazha",
    "wof:placetype":"locality"
},
  "geometry": {"coordinates":[88.30540000000001,29.6672],"type":"Point"}
}