{
  "type": "Feature",
  "properties": {
    "gn:admin1_code":"8.0",
    "gn:asciiname":"Xinglonghe",
    "gn:country_code":"CN",
    "gn:dem":347,
    "gn:feature_class":"P",
    "gn:feature_code":"PPL",
    "gn:name":"Xinglonghe",
    "gn:population":0,
    "gn:timezone":"Asia/Shanghai",
    "iso:country":"CN",
    "name:zho_x_preferred":[
        "\u5174\u9686\u6cb3"
    ],
    "wof:name":"Xinglonghe",
    "wof:placetype":"locality"
},
  "geometry": {"coordinates":[127.82866,44.41206],"type":"Point"}
}