{
  "type": "Feature",
  "properties": {
    "gn:admin1_code":"11.0",
    "gn:asciiname":"Shangcheng",
    "gn:country_code":"CN",
    "gn:dem":296,
    "gn:feature_class":"P",
    "gn:feature_code":"PPL",
    "gn:name":"Shangcheng",
    "gn:population":0,
    "gn:timezone":"Asia/Shanghai",
    "iso:country":"CN",
    "name:ceb_x_preferred":[
        "Shangcheng"
    ],
    "name:deu_x_preferred":[
        "Shangcheng"
    ],
    "name:epo_x_preferred":[
        "Shangcheng"
    ],
    "name:fra_x_preferred":[
        "Shangcheng"
    ],
    "name:nor_x_preferred":[
        "Shangcheng"
    ],
    "name:rus_x_preferred":[
        "\u0428\u0430\u043d\u0447\u044d\u043d"
    ],
    "name:swe_x_preferred":[
        "Shangcheng"
    ],
    "name:zho_x_preferred":[
        "Shangcheng"
    ],
    "name:zho_x_variant":[
        "\u4e0a\u5448"
    ],
    "wof:name":"Shangcheng",
    "wof:placetype":"locality"
},
  "geometry": {"coordinates":[114.12297,28.24108],"type":"Point"}
}