{
  "type": "Feature",
  "properties": {
    "gn:admin1_code":"11",
    "gn:asciiname":"Fumaying",
    "gn:country_code":"CN",
    "gn:dem":339,
    "gn:feature_class":"P",
    "gn:feature_code":"PPL",
    "gn:name":"Fumaying",
    "gn:population":0,
    "gn:timezone":"Asia/Shanghai",
    "iso:country":"CN",
    "name:zho_x_preferred":[
        "\u8d74\u9a6c\u8425"
    ],
    "wof:name":"Fumaying",
    "wof:placetype":"locality"
},
  "geometry": {"coordinates":[111.63133999999999,25.10158],"type":"Point"}
}