{
  "type": "Feature",
  "properties": {
    "gn:admin1_code":"29.0",
    "gn:asciiname":"Qingshu",
    "gn:country_code":"CN",
    "gn:dem":1643,
    "gn:feature_class":"P",
    "gn:feature_code":"PPL",
    "gn:name":"Qingshu",
    "gn:population":0,
    "gn:timezone":"Asia/Shanghai",
    "iso:country":"CN",
    "name:zho_x_preferred":[
        "\u9752\u6811"
    ],
    "wof:name":"Qingshu",
    "wof:placetype":"locality"
},
  "geometry": {"coordinates":[100.959,24.8574],"type":"Point"}
}