{
  "type": "Feature",
  "properties": {
    "gn:admin1_code":"26.0",
    "gn:asciiname":"Taojiaya",
    "gn:country_code":"CN",
    "gn:dem":599,
    "gn:feature_class":"P",
    "gn:feature_code":"PPL",
    "gn:name":"Taojiaya",
    "gn:population":0,
    "gn:timezone":"Asia/Shanghai",
    "iso:country":"CN",
    "name:und_x_variant":[
        "\u9676\u5bb6\u57ad"
    ],
    "wof:name":"Taojiaya",
    "wof:placetype":"locality"
},
  "geometry": {"coordinates":[107.99316,33.2066],"type":"Point"}
}