{
  "type": "Feature",
  "properties": {
    "gn:admin1_code":"15.0",
    "gn:asciiname":"Xuanmagetuo",
    "gn:country_code":"CN",
    "gn:dem":1445,
    "gn:feature_class":"P",
    "gn:feature_code":"PPL",
    "gn:name":"Xuanmagetuo",
    "gn:population":0,
    "gn:timezone":"Asia/Shanghai",
    "iso:country":"CN",
    "name:und_x_variant":[
        "\u7384\u9a6c\u572a\u5768"
    ],
    "wof:name":"Xuanmagetuo",
    "wof:placetype":"locality"
},
  "geometry": {"coordinates":[107.88588,36.66288],"type":"Point"}
}