{
  "type": "Feature",
  "properties": {
    "gn:admin1_code":"30.0",
    "gn:asciiname":"Xiyoucun",
    "gn:country_code":"CN",
    "gn:dem":68,
    "gn:feature_class":"P",
    "gn:feature_code":"PPL",
    "gn:name":"Xiyoucun",
    "gn:population":0,
    "gn:timezone":"Asia/Shanghai",
    "iso:country":"CN",
    "name:zho_x_preferred":[
        "\u897f\u53cb\u6751"
    ],
    "wof:name":"Xiyoucun",
    "wof:placetype":"locality"
},
  "geometry": {"coordinates":[115.92303,23.46874],"type":"Point"}
}