{
  "type": "Feature",
  "properties": {
    "gn:admin1_code":"32.0",
    "gn:asciiname":"Yueri",
    "gn:country_code":"CN",
    "gn:dem":1663,
    "gn:feature_class":"P",
    "gn:feature_code":"PPL",
    "gn:name":"Yueri",
    "gn:population":0,
    "gn:timezone":"Asia/Shanghai",
    "iso:country":"CN",
    "name:zho_x_preferred":[
        "\u6708\u65e5"
    ],
    "wof:name":"Yueri",
    "wof:placetype":"locality"
},
  "geometry": {"coordinates":[103.02203,27.60764],"type":"Point"}
}