{
  "type": "Feature",
  "properties": {
    "gn:admin1_code":"1.0",
    "gn:asciiname":"Huaqiao",
    "gn:country_code":"CN",
    "gn:dem":71,
    "gn:feature_class":"P",
    "gn:feature_code":"PPL",
    "gn:name":"Huaqiao",
    "gn:population":0,
    "gn:timezone":"Asia/Shanghai",
    "iso:country":"CN",
    "name:ceb_x_preferred":[
        "Huaqiao"
    ],
    "name:deu_x_preferred":[
        "Huaqiao"
    ],
    "name:swe_x_preferred":[
        "Huaqiao"
    ],
    "name:zho_x_preferred":[
        "\u534e\u6865"
    ],
    "wof:name":"Huaqiao",
    "wof:placetype":"locality"
},
  "geometry": {"coordinates":[118.31717,30.7386],"type":"Point"}
}