{
  "type": "Feature",
  "properties": {
    "gn:admin1_code":"1.0",
    "gn:asciiname":"Yangdiancun",
    "gn:country_code":"CN",
    "gn:dem":59,
    "gn:feature_class":"P",
    "gn:feature_code":"PPL",
    "gn:name":"Yangdiancun",
    "gn:population":0,
    "gn:timezone":"Asia/Shanghai",
    "iso:country":"CN",
    "name:zho_x_preferred":[
        "\u6768\u5e97\u6751"
    ],
    "wof:name":"Yangdiancun",
    "wof:placetype":"locality"
},
  "geometry": {"coordinates":[117.67140000000001,32.37536],"type":"Point"}
}