{
  "type": "Feature",
  "properties": {
    "gn:admin1_code":"14.0",
    "gn:asciiname":"Lubu",
    "gn:country_code":"CN",
    "gn:dem":4297,
    "gn:feature_class":"P",
    "gn:feature_code":"PPL",
    "gn:name":"Lubu",
    "gn:population":0,
    "gn:timezone":"Asia/Urumqi",
    "iso:country":"CN",
    "name:zho_x_preferred":[
        "\u9c81\u5e03"
    ],
    "wof:name":"Lubu",
    "wof:placetype":"locality"
},
  "geometry": {"coordinates":[97.61862000000001,30.28857],"type":"Point"}
}