{
  "type": "Feature",
  "properties": {
    "gn:admin1_code":"16",
    "gn:asciiname":"Pengjiao",
    "gn:country_code":"CN",
    "gn:dem":208,
    "gn:feature_class":"P",
    "gn:feature_code":"PPL",
    "gn:name":"Pengjiao",
    "gn:population":0,
    "gn:timezone":"Asia/Shanghai",
    "iso:country":"CN",
    "name:zho_x_preferred":[
        "\u84ec\u53eb"
    ],
    "wof:name":"Pengjiao",
    "wof:placetype":"locality"
},
  "geometry": {"coordinates":[109.429,25.7356],"type":"Point"}
}