{
  "type": "Feature",
  "properties": {
    "gn:admin1_code":"14.0",
    "gn:asciiname":"Quduolu",
    "gn:country_code":"CN",
    "gn:dem":4621,
    "gn:feature_class":"P",
    "gn:feature_code":"PPL",
    "gn:name":"Quduolu",
    "gn:population":0,
    "gn:timezone":"Asia/Urumqi",
    "iso:country":"CN",
    "name:zho_x_preferred":[
        "\u66f2\u591a\u9c81"
    ],
    "wof:name":"Quduolu",
    "wof:placetype":"locality"
},
  "geometry": {"coordinates":[91.61117,31.32758],"type":"Point"}
}