{
  "type": "Feature",
  "properties": {
    "gn:country":"CN",
    "gn:fcode":"PPL",
    "gn:population":1718,
    "iso:country":"CN",
    "name:ast_x_preferred":[
        "Xiawuqi"
    ],
    "name:ceb_x_preferred":[
        "Xiawuqi"
    ],
    "name:cym_x_preferred":[
        "Xiawuqi"
    ],
    "name:eng_x_preferred":[
        "Xiawuqi"
    ],
    "name:gan_x_preferred":[
        "\u4e0b\u4f0d\u65d7\u9547"
    ],
    "name:jpn_x_preferred":[
        "\u4e0b\u4f0d\u65d7\u93ae"
    ],
    "name:mlg_x_preferred":[
        "Xiawuqi"
    ],
    "name:spa_x_preferred":[
        "Xiawuqi"
    ],
    "name:swe_x_preferred":[
        "Xiawuqi"
    ],
    "name:wuu_x_preferred":[
        "\u4e0b\u4f0d\u65d7\u9547"
    ],
    "name:zho_x_preferred":[
        "\u4e0b\u4f0d\u65d7\u9547"
    ],
    "qs:name":"Xiawuqi",
    "qs:photos_9r":0,
    "qs:photos_sr":0,
    "qs:pop_sr":"3",
    "wd:wordcount":184,
    "wof:name":"Xiawuqi",
    "wof:placetype":"locality",
    "wof:population":1718
},
  "geometry": {"coordinates":[117.05333,39.61361],"type":"Point"}
}