{
  "type": "Feature",
  "properties": {
    "gn:admin1_code":"10",
    "gn:asciiname":"Donghao",
    "gn:country_code":"CN",
    "gn:dem":1351,
    "gn:feature_class":"P",
    "gn:feature_code":"PPL",
    "gn:name":"Donghao",
    "gn:population":0,
    "gn:timezone":"Asia/Shanghai",
    "iso:country":"CN",
    "wof:name":"Donghao",
    "wof:placetype":"locality"
},
  "geometry": {"coordinates":[114.56139,41.32111],"type":"Point"}
}