{
  "type": "Feature",
  "properties": {
    "gn:country":"CN",
    "gn:fcode":"PPLA4",
    "gn:population":2830,
    "iso:country":"CN",
    "name:und_x_variant":[
        "\u5353\u6d0b"
    ],
    "qs:name":"Zhuoyang",
    "qs:photos_9r":0,
    "qs:photos_sr":0,
    "qs:pop_sr":"4",
    "wof:name":"Zhuoyang",
    "wof:placetype":"locality",
    "wof:population":2830
},
  "geometry": {"coordinates":[119.0215,26.63004],"type":"Point"}
}