{
  "type": "Feature",
  "properties": {
    "gn:admin1_code":"11.0",
    "gn:asciiname":"Tang'erbao",
    "gn:country_code":"CN",
    "gn:dem":522,
    "gn:feature_class":"P",
    "gn:feature_code":"PPL",
    "gn:name":"Tang\u2019erbao",
    "gn:population":0,
    "gn:timezone":"Asia/Shanghai",
    "iso:country":"CN",
    "name:zho_x_preferred":[
        "Tang\u2019erbao"
    ],
    "name:zho_x_variant":[
        "\u5510\u513f\u5305"
    ],
    "wof:name":"Tang'erbao",
    "wof:placetype":"locality"
},
  "geometry": {"coordinates":[109.91346,28.88589],"type":"Point"}
}