{
  "type": "Feature",
  "properties": {
    "gn:admin1_code":"3.0",
    "gn:asciiname":"Painao",
    "gn:country_code":"CN",
    "gn:dem":230,
    "gn:feature_class":"P",
    "gn:feature_code":"PPL",
    "gn:name":"Painao",
    "gn:population":0,
    "gn:timezone":"Asia/Shanghai",
    "iso:country":"CN",
    "name:und_x_variant":[
        "\u6392\u8111"
    ],
    "wof:name":"Painao",
    "wof:placetype":"locality"
},
  "geometry": {"coordinates":[115.78032,26.34189000000001],"type":"Point"}
}