{
  "type": "Feature",
  "properties": {
    "gn:admin1_code":"3",
    "gn:asciiname":"Xiucaipai",
    "gn:country_code":"CN",
    "gn:dem":304,
    "gn:feature_class":"P",
    "gn:feature_code":"PPL",
    "gn:name":"Xiucaipai",
    "gn:population":0,
    "gn:timezone":"Asia/Shanghai",
    "iso:country":"CN",
    "name:und_x_variant":[
        "\u79c0\u624d\u724c"
    ],
    "wof:name":"Xiucaipai",
    "wof:placetype":"locality"
},
  "geometry": {"coordinates":[114.66461,24.80505],"type":"Point"}
}