{
  "type": "Feature",
  "properties": {
    "gn:admin1_code":"10",
    "gn:asciiname":"Dachongyu",
    "gn:cc2":"CN",
    "gn:country_code":"CN",
    "gn:dem":542,
    "gn:feature_class":"P",
    "gn:feature_code":"PPL",
    "gn:name":"Dachongyu",
    "gn:population":0,
    "gn:timezone":"Asia/Shanghai",
    "iso:country":"CN",
    "name:und_x_variant":[
        "Ta-ch\u2019ung-y\u00fc",
        "Dachongyu"
    ],
    "wof:name":"Dachongyu",
    "wof:placetype":"locality"
},
  "geometry": {"coordinates":[117.68333,40.38333],"type":"Point"}
}