{
  "type": "Feature",
  "properties": {
    "gn:admin1_code":"16.0",
    "gn:asciiname":"Luodaitang",
    "gn:country_code":"CN",
    "gn:dem":49,
    "gn:feature_class":"P",
    "gn:feature_code":"PPL",
    "gn:name":"Luodaitang",
    "gn:population":0,
    "gn:timezone":"Asia/Shanghai",
    "iso:country":"CN",
    "name:zho_x_preferred":[
        "\u7f57\u5e26\u5858"
    ],
    "wof:name":"Luodaitang",
    "wof:placetype":"locality"
},
  "geometry": {"coordinates":[110.10899999999999,23.2836],"type":"Point"}
}