{
  "type": "Feature",
  "properties": {
    "gn:admin1_code":"15.0",
    "gn:asciiname":"Quanwanzi",
    "gn:country_code":"CN",
    "gn:dem":2074,
    "gn:feature_class":"P",
    "gn:feature_code":"PPL",
    "gn:name":"Quanwanzi",
    "gn:population":0,
    "gn:timezone":"Asia/Shanghai",
    "iso:country":"CN",
    "name:zho_x_preferred":[
        "\u5708\u6e7e\u5b50"
    ],
    "wof:name":"Quanwanzi",
    "wof:placetype":"locality"
},
  "geometry": {"coordinates":[104.139,36.2045],"type":"Point"}
}