{
  "type": "Feature",
  "properties": {
    "gn:admin1_code":"29",
    "gn:asciiname":"Nalang",
    "gn:country_code":"CN",
    "gn:dem":444,
    "gn:feature_class":"P",
    "gn:feature_code":"PPL",
    "gn:name":"Nalang",
    "gn:population":0,
    "gn:timezone":"Asia/Shanghai",
    "iso:country":"CN",
    "name:ceb_x_preferred":[
        "Nalang"
    ],
    "name:msa_x_preferred":[
        "Nalang"
    ],
    "name:new_x_preferred":[
        "\u0928\u093e\u0932\u093e\u0919"
    ],
    "name:pol_x_preferred":[
        "Nalang"
    ],
    "name:zho_x_preferred":[
        "\u90a3\u6717"
    ],
    "wof:name":"Nalang",
    "wof:placetype":"locality"
},
  "geometry": {"coordinates":[106.11799999999999,23.6345],"type":"Point"}
}