{
  "type": "Feature",
  "properties": {
    "gn:admin1_code":"8.0",
    "gn:asciiname":"Jinjiangcun",
    "gn:country_code":"CN",
    "gn:dem":47,
    "gn:feature_class":"P",
    "gn:feature_code":"PPL",
    "gn:name":"Jinjiangcun",
    "gn:population":0,
    "gn:timezone":"Asia/Shanghai",
    "iso:country":"CN",
    "name:zho_x_preferred":[
        "\u91d1\u6c5f\u6751"
    ],
    "wof:name":"Jinjiangcun",
    "wof:placetype":"locality"
},
  "geometry": {"coordinates":[133.70298,48.05393],"type":"Point"}
}