{
  "type": "Feature",
  "properties": {
    "gn:admin1_code":"15.0",
    "gn:asciiname":"Sangcang",
    "gn:country_code":"CN",
    "gn:dem":2852,
    "gn:feature_class":"P",
    "gn:feature_code":"PPL",
    "gn:name":"Sangcang",
    "gn:population":0,
    "gn:timezone":"Asia/Shanghai",
    "iso:country":"CN",
    "name:und_x_variant":[
        "\u6851\u85cf"
    ],
    "wof:name":"Sangcang",
    "wof:placetype":"locality"
},
  "geometry": {"coordinates":[103.78851,34.08664],"type":"Point"}
}