{
  "type": "Feature",
  "properties": {
    "gn:admin1_code":"04",
    "gn:asciiname":"Ouqu",
    "gn:country_code":"CN",
    "gn:dem":3,
    "gn:feature_class":"P",
    "gn:feature_code":"PPL",
    "gn:name":"Ouqu",
    "gn:population":0,
    "gn:timezone":"Asia/Shanghai",
    "iso:country":"CN",
    "name:zho_x_preferred":[
        "\u85d5\u6e20"
    ],
    "wof:name":"Ouqu",
    "wof:placetype":"locality"
},
  "geometry": {"coordinates":[120.77948000000001,31.62347],"type":"Point"}
}