{
  "type": "Feature",
  "properties": {
    "gn:admin1_code":"24.0",
    "gn:asciiname":"Cuijiayao",
    "gn:country_code":"CN",
    "gn:dem":1075,
    "gn:feature_class":"P",
    "gn:feature_code":"PPL",
    "gn:name":"Cuijiayao",
    "gn:population":0,
    "gn:timezone":"Asia/Shanghai",
    "iso:country":"CN",
    "name:zho_x_preferred":[
        "\u5d14\u5bb6\u7a91"
    ],
    "wof:name":"Cuijiayao",
    "wof:placetype":"locality"
},
  "geometry": {"coordinates":[112.49122,39.31632000000001],"type":"Point"}
}