{
  "type": "Feature",
  "properties": {
    "gn:admin1_code":"30",
    "gn:asciiname":"Maopingpo",
    "gn:country_code":"CN",
    "gn:dem":109,
    "gn:feature_class":"P",
    "gn:feature_code":"PPL",
    "gn:name":"Maopingpo",
    "gn:population":0,
    "gn:timezone":"Asia/Shanghai",
    "iso:country":"CN",
    "name:zho_x_preferred":[
        "\u8305\u576a\u5761"
    ],
    "wof:name":"Maopingpo",
    "wof:placetype":"locality"
},
  "geometry": {"coordinates":[111.73565000000001,22.40896],"type":"Point"}
}