{
  "type": "Feature",
  "properties": {
    "gn:admin1_code":"20.0",
    "gn:asciiname":"Xibo Weidian",
    "gn:country_code":"CN",
    "gn:dem":661,
    "gn:feature_class":"P",
    "gn:feature_code":"PPL",
    "gn:name":"Xibo Weidian",
    "gn:population":0,
    "gn:timezone":"Asia/Shanghai",
    "iso:country":"CN",
    "name:zho_x_preferred":[
        "\u9521\u52c3\u82c7\u70b9"
    ],
    "wof:name":"Xibo Weidian",
    "wof:placetype":"locality"
},
  "geometry": {"coordinates":[119.21907,48.83545],"type":"Point"}
}