{
  "type": "Feature",
  "properties": {
    "gn:admin1_code":"29.0",
    "gn:asciiname":"Shangliqi",
    "gn:country_code":"CN",
    "gn:dem":1964,
    "gn:feature_class":"P",
    "gn:feature_code":"PPL",
    "gn:name":"Shangliqi",
    "gn:population":0,
    "gn:timezone":"Asia/Shanghai",
    "iso:country":"CN",
    "name:zho_x_preferred":[
        "\u4e0a\u674e\u5176"
    ],
    "wof:name":"Shangliqi",
    "wof:placetype":"locality"
},
  "geometry": {"coordinates":[102.867,25.0562],"type":"Point"}
}