{
  "type": "Feature",
  "properties": {
    "gn:admin1_code":"26.0",
    "gn:asciiname":"Zuojiaping",
    "gn:country_code":"CN",
    "gn:dem":1256,
    "gn:feature_class":"P",
    "gn:feature_code":"PPL",
    "gn:name":"Zuojiaping",
    "gn:population":0,
    "gn:timezone":"Asia/Shanghai",
    "iso:country":"CN",
    "name:und_x_variant":[
        "\u4f50\u5bb6\u576a"
    ],
    "wof:name":"Zuojiaping",
    "wof:placetype":"locality"
},
  "geometry": {"coordinates":[107.88424999999999,33.8521],"type":"Point"}
}