{
  "type": "Feature",
  "properties": {
    "gn:admin1_code":"16.0",
    "gn:asciiname":"Puzhushan",
    "gn:country_code":"CN",
    "gn:dem":150,
    "gn:feature_class":"P",
    "gn:feature_code":"PPL",
    "gn:name":"Puzhushan",
    "gn:population":0,
    "gn:timezone":"Asia/Shanghai",
    "iso:country":"CN",
    "name:zho_x_preferred":[
        "\u84b2\u7af9\u5c71"
    ],
    "wof:name":"Puzhushan",
    "wof:placetype":"locality"
},
  "geometry": {"coordinates":[110.31100000000001,23.1656],"type":"Point"}
}