{
  "type": "Feature",
  "properties": {
    "gn:admin1_code":"4.0",
    "gn:asciiname":"Tianxiangcun",
    "gn:country_code":"CN",
    "gn:dem":2,
    "gn:feature_class":"P",
    "gn:feature_code":"PPL",
    "gn:name":"Tianxiangcun",
    "gn:population":0,
    "gn:timezone":"Asia/Shanghai",
    "iso:country":"CN",
    "name:zho_x_preferred":[
        "\u5929\u7965\u6751"
    ],
    "wof:name":"Tianxiangcun",
    "wof:placetype":"locality"
},
  "geometry": {"coordinates":[120.56171000000001,33.25452],"type":"Point"}
}