{
  "type": "Feature",
  "properties": {
    "gn:admin1_code":"3.0",
    "gn:asciiname":"Huache",
    "gn:country_code":"CN",
    "gn:dem":103,
    "gn:feature_class":"P",
    "gn:feature_code":"PPL",
    "gn:name":"Huache",
    "gn:population":0,
    "gn:timezone":"Asia/Shanghai",
    "iso:country":"CN",
    "name:und_x_variant":[
        "\u82b1\u8f66"
    ],
    "wof:name":"Huache",
    "wof:placetype":"locality"
},
  "geometry": {"coordinates":[114.52151000000001,27.20656],"type":"Point"}
}