{
  "type": "Feature",
  "properties": {
    "gn:admin1_code":"04",
    "gn:asciiname":"Beigongfang",
    "gn:country_code":"CN",
    "gn:dem":3,
    "gn:feature_class":"P",
    "gn:feature_code":"PPL",
    "gn:name":"Beigongfang",
    "gn:population":0,
    "gn:timezone":"Asia/Shanghai",
    "iso:country":"CN",
    "name:und_x_variant":[
        "\u5317\u516c\u623f"
    ],
    "wof:name":"Beigongfang",
    "wof:placetype":"locality"
},
  "geometry": {"coordinates":[121.23333,31.61111],"type":"Point"}
}