{
  "type": "Feature",
  "properties": {
    "gn:admin1_code":"25",
    "gn:asciiname":"Xigudefan",
    "gn:country_code":"CN",
    "gn:dem":426,
    "gn:feature_class":"P",
    "gn:feature_code":"PPL",
    "gn:name":"Xigudefan",
    "gn:population":0,
    "gn:timezone":"Asia/Shanghai",
    "iso:country":"CN",
    "name:zho_x_preferred":[
        "\u897f\u53e4\u5fb7\u8303"
    ],
    "wof:name":"Xigudefan",
    "wof:placetype":"locality"
},
  "geometry": {"coordinates":[117.846,36.3295],"type":"Point"}
}