{
  "type": "Feature",
  "properties": {
    "gn:admin1_code":"1.0",
    "gn:asciiname":"Liuhezhacun",
    "gn:country_code":"CN",
    "gn:dem":34,
    "gn:feature_class":"P",
    "gn:feature_code":"PPL",
    "gn:name":"Liuhezhacun",
    "gn:population":0,
    "gn:timezone":"Asia/Shanghai",
    "iso:country":"CN",
    "name:zho_x_preferred":[
        "\u67f3\u6cb3\u95f8\u6751"
    ],
    "wof:name":"Liuhezhacun",
    "wof:placetype":"locality"
},
  "geometry": {"coordinates":[115.71689000000001,33.03149000000001],"type":"Point"}
}