{
  "type": "Feature",
  "properties": {
    "gn:admin1_code":"18.0",
    "gn:asciiname":"Duyan",
    "gn:country_code":"CN",
    "gn:dem":428,
    "gn:feature_class":"P",
    "gn:feature_code":"PPL",
    "gn:name":"Duyan",
    "gn:population":0,
    "gn:timezone":"Asia/Shanghai",
    "iso:country":"CN",
    "name:zho_x_preferred":[
        "\u72ec\u5ca9"
    ],
    "wof:name":"Duyan",
    "wof:placetype":"locality"
},
  "geometry": {"coordinates":[109.28100000000001,27.7667],"type":"Point"}
}