{
  "type": "Feature",
  "properties": {
    "gn:admin1_code":"15.0",
    "gn:asciiname":"Pangjiazhuang",
    "gn:country_code":"CN",
    "gn:dem":1190,
    "gn:feature_class":"P",
    "gn:feature_code":"PPL",
    "gn:name":"Pangjiazhuang",
    "gn:population":0,
    "gn:timezone":"Asia/Shanghai",
    "iso:country":"CN",
    "name:und_x_variant":[
        "\u5e9e\u5bb6\u5e84"
    ],
    "wof:name":"Pangjiazhuang",
    "wof:placetype":"locality"
},
  "geometry": {"coordinates":[105.81607,33.44886],"type":"Point"}
}