{
  "type": "Feature",
  "properties": {
    "gn:admin1_code":"07",
    "gn:asciiname":"Gaoguanshan",
    "gn:country_code":"CN",
    "gn:dem":424,
    "gn:feature_class":"P",
    "gn:feature_code":"PPL",
    "gn:name":"Gaoguanshan",
    "gn:population":0,
    "gn:timezone":"Asia/Shanghai",
    "iso:country":"CN",
    "name:zho_x_preferred":[
        "\u9ad8\u5173\u5c71"
    ],
    "wof:name":"Gaoguanshan",
    "wof:placetype":"locality"
},
  "geometry": {"coordinates":[116.58038999999999,24.98867000000001],"type":"Point"}
}