{
  "type": "Feature",
  "properties": {
    "gn:admin1_code":"14.0",
    "gn:asciiname":"Tunburongcun",
    "gn:country_code":"CN",
    "gn:dem":3155,
    "gn:feature_class":"P",
    "gn:feature_code":"PPL",
    "gn:name":"Tunburongcun",
    "gn:population":0,
    "gn:timezone":"Asia/Urumqi",
    "iso:country":"CN",
    "name:zho_x_preferred":[
        "\u541e\u4e0d\u7ed2\u6751"
    ],
    "wof:name":"Tunburongcun",
    "wof:placetype":"locality"
},
  "geometry": {"coordinates":[94.00261,29.30813],"type":"Point"}
}