{
  "type": "Feature",
  "properties": {
    "gn:admin1_code":"20",
    "gn:asciiname":"Shang-shao-kuo",
    "gn:country_code":"CN",
    "gn:dem":663,
    "gn:feature_class":"P",
    "gn:feature_code":"PPL",
    "gn:name":"Shang-shao-kuo",
    "gn:population":0,
    "gn:timezone":"Asia/Shanghai",
    "iso:country":"CN",
    "wof:name":"Shang-shao-kuo",
    "wof:placetype":"locality"
},
  "geometry": {"coordinates":[119.05138999999998,42.01667],"type":"Point"}
}