{
  "type": "Feature",
  "properties": {
    "gn:admin1_code":"8.0",
    "gn:asciiname":"Lihonglin",
    "gn:country_code":"CN",
    "gn:dem":143,
    "gn:feature_class":"P",
    "gn:feature_code":"PPL",
    "gn:name":"Lihonglin",
    "gn:population":0,
    "gn:timezone":"Asia/Shanghai",
    "iso:country":"CN",
    "name:zho_x_preferred":[
        "\u674e\u6d2a\u6797"
    ],
    "wof:name":"Lihonglin",
    "wof:placetype":"locality"
},
  "geometry": {"coordinates":[125.08987999999999,45.85065],"type":"Point"}
}