{
  "type": "Feature",
  "properties": {
    "gn:admin1_code":"4.0",
    "gn:asciiname":"Weilaojiacun",
    "gn:country_code":"CN",
    "gn:dem":40,
    "gn:feature_class":"P",
    "gn:feature_code":"PPL",
    "gn:name":"Weilaojiacun",
    "gn:population":0,
    "gn:timezone":"Asia/Shanghai",
    "iso:country":"CN",
    "name:und_x_variant":[
        "Weilaojia",
        "Weilaojiacun"
    ],
    "name:zho_x_preferred":[
        "\u9b4f\u8001\u5bb6"
    ],
    "name:zho_x_variant":[
        "\u9b4f\u8001\u5bb6\u6751"
    ],
    "wof:name":"Weilaojiacun",
    "wof:placetype":"locality"
},
  "geometry": {"coordinates":[116.86108,34.65631],"type":"Point"}
}