{
  "type": "Feature",
  "properties": {
    "gn:admin1_code":"14.0",
    "gn:asciiname":"Bingjiuge",
    "gn:country_code":"CN",
    "gn:dem":4377,
    "gn:feature_class":"P",
    "gn:feature_code":"PPL",
    "gn:name":"Bingjiuge",
    "gn:population":0,
    "gn:timezone":"Asia/Urumqi",
    "iso:country":"CN",
    "name:zho_x_preferred":[
        "\u51b0\u4e45\u5404"
    ],
    "wof:name":"Bingjiuge",
    "wof:placetype":"locality"
},
  "geometry": {"coordinates":[96.24643,30.89464000000001],"type":"Point"}
}