{
  "type": "Feature",
  "properties": {
    "gn:admin1_code":"5.0",
    "gn:asciiname":"Yaodiancun",
    "gn:country_code":"CN",
    "gn:dem":425,
    "gn:feature_class":"P",
    "gn:feature_code":"PPL",
    "gn:name":"Yaodiancun",
    "gn:population":0,
    "gn:timezone":"Asia/Shanghai",
    "iso:country":"CN",
    "name:zho_x_preferred":[
        "\u8170\u7538\u6751"
    ],
    "wof:name":"Yaodiancun",
    "wof:placetype":"locality"
},
  "geometry": {"coordinates":[128.67192,43.72367],"type":"Point"}
}