{
  "type": "Feature",
  "properties": {
    "gn:admin1_code":"8.0",
    "gn:asciiname":"Bamendai",
    "gn:country_code":"CN",
    "gn:dem":144,
    "gn:feature_class":"P",
    "gn:feature_code":"PPL",
    "gn:name":"Bamendai",
    "gn:population":0,
    "gn:timezone":"Asia/Shanghai",
    "iso:country":"CN",
    "name:zho_x_preferred":[
        "\u5df4\u95e8\u4ee3"
    ],
    "wof:name":"Bamendai",
    "wof:placetype":"locality"
},
  "geometry": {"coordinates":[124.17609,46.65793],"type":"Point"}
}