{
  "type": "Feature",
  "properties": {
    "gn:admin1_code":"8.0",
    "gn:asciiname":"Mingwan Futun",
    "gn:country_code":"CN",
    "gn:dem":239,
    "gn:feature_class":"P",
    "gn:feature_code":"PPL",
    "gn:name":"Mingwan Futun",
    "gn:population":0,
    "gn:timezone":"Asia/Shanghai",
    "iso:country":"CN",
    "name:zho_x_preferred":[
        "\u660e\u4e07\u798f\u5c6f"
    ],
    "wof:name":"Mingwan Futun",
    "wof:placetype":"locality"
},
  "geometry": {"coordinates":[125.67843999999999,47.29881],"type":"Point"}
}