{
  "type": "Feature",
  "properties": {
    "gn:admin1_code":"2.0",
    "gn:asciiname":"Wuchuanbang",
    "gn:country_code":"CN",
    "gn:dem":4,
    "gn:feature_class":"P",
    "gn:feature_code":"PPL",
    "gn:name":"Wuchuanbang",
    "gn:population":0,
    "gn:timezone":"Asia/Shanghai",
    "iso:country":"CN",
    "name:und_x_variant":[
        "\u4e4c\u8239\u6d5c"
    ],
    "wof:name":"Wuchuanbang",
    "wof:placetype":"locality"
},
  "geometry": {"coordinates":[121.05595,30.69607],"type":"Point"}
}