{
  "type": "Feature",
  "properties": {
    "gn:admin1_code":"18",
    "gn:asciiname":"Luomudong",
    "gn:country_code":"CN",
    "gn:dem":952,
    "gn:feature_class":"P",
    "gn:feature_code":"PPL",
    "gn:name":"Luomudong",
    "gn:population":0,
    "gn:timezone":"Asia/Shanghai",
    "iso:country":"CN",
    "name:zho_x_preferred":[
        "\u7f57\u6bcd\u6d1e"
    ],
    "wof:name":"Luomudong",
    "wof:placetype":"locality"
},
  "geometry": {"coordinates":[107.633,28.0189],"type":"Point"}
}