{
  "type": "Feature",
  "properties": {
    "gn:admin1_code":"11",
    "gn:asciiname":"Chengtian",
    "gn:country_code":"CN",
    "gn:dem":444,
    "gn:feature_class":"P",
    "gn:feature_code":"PPL",
    "gn:name":"Chengtian",
    "gn:population":0,
    "gn:timezone":"Asia/Shanghai",
    "iso:country":"CN",
    "name:zho_x_preferred":[
        "\u6210\u7530"
    ],
    "wof:name":"Chengtian",
    "wof:placetype":"locality"
},
  "geometry": {"coordinates":[111.17198,27.60604],"type":"Point"}
}