{
  "type": "Feature",
  "properties": {
    "gn:admin1_code":"26.0",
    "gn:asciiname":"Wuliping",
    "gn:country_code":"CN",
    "gn:dem":991,
    "gn:feature_class":"P",
    "gn:feature_code":"PPL",
    "gn:name":"Wuliping",
    "gn:population":0,
    "gn:timezone":"Asia/Shanghai",
    "iso:country":"CN",
    "name:zho_x_preferred":[
        "\u4e94\u91cc\u576a"
    ],
    "wof:name":"Wuliping",
    "wof:placetype":"locality"
},
  "geometry": {"coordinates":[110.09341000000001,37.8788],"type":"Point"}
}