{
  "type": "Feature",
  "properties": {
    "gn:admin1_code":"8.0",
    "gn:asciiname":"Tongjiangcun",
    "gn:country_code":"CN",
    "gn:dem":111,
    "gn:feature_class":"P",
    "gn:feature_code":"PPL",
    "gn:name":"Tongjiangcun",
    "gn:population":0,
    "gn:timezone":"Asia/Shanghai",
    "iso:country":"CN",
    "name:zho_x_preferred":[
        "\u901a\u6c5f\u6751"
    ],
    "wof:name":"Tongjiangcun",
    "wof:placetype":"locality"
},
  "geometry": {"coordinates":[127.47028,45.9575],"type":"Point"}
}