{
  "type": "Feature",
  "properties": {
    "gn:admin1_code":"15",
    "gn:asciiname":"Hezheng Chengguanzhen",
    "gn:country_code":"CN",
    "gn:dem":2103,
    "gn:feature_class":"P",
    "gn:feature_code":"PPLA3",
    "gn:name":"Hezheng Chengguanzhen",
    "gn:population":0,
    "gn:timezone":"Asia/Shanghai",
    "iso:country":"CN",
    "name:und_x_variant":[
        "Ning-ho",
        "Khechzhen",
        "Ninkhe",
        "Ho-cheng-hsien",
        "Ning-ho-pao",
        "Ho-ch\u2019eng",
        "Ninghochwang",
        "Hezheng",
        "Hezheng Chengguanzhen",
        "Hezheng Xian"
    ],
    "name:zho_x_preferred":[
        "\u548c\u653f\u57ce\u5173\u9547"
    ],
    "name:zho_x_variant":[
        "\u548c\u653f\u53bf"
    ],
    "wof:name":"Hezheng Chengguanzhen",
    "wof:placetype":"locality"
},
  "geometry": {"coordinates":[103.35724999999999,35.42999000000001],"type":"Point"}
}