{
  "type": "Feature",
  "properties": {
    "gn:admin1_code":"11.0",
    "gn:asciiname":"Zhushanzui",
    "gn:country_code":"CN",
    "gn:dem":68,
    "gn:feature_class":"P",
    "gn:feature_code":"PPL",
    "gn:name":"Zhushanzui",
    "gn:population":0,
    "gn:timezone":"Asia/Shanghai",
    "iso:country":"CN",
    "name:zho_x_preferred":[
        "\u682a\u5c71\u5634"
    ],
    "wof:name":"Zhushanzui",
    "wof:placetype":"locality"
},
  "geometry": {"coordinates":[113.31153,27.71561],"type":"Point"}
}