{
  "type": "Feature",
  "properties": {
    "gn:admin1_code":"33.0",
    "gn:asciiname":"Tongdechang",
    "gn:country_code":"CN",
    "gn:dem":482,
    "gn:feature_class":"P",
    "gn:feature_code":"PPL",
    "gn:name":"Tongdechang",
    "gn:population":0,
    "gn:timezone":"Asia/Shanghai",
    "iso:country":"CN",
    "name:zho_x_preferred":[
        "\u540c\u5fb7\u573a"
    ],
    "wof:name":"Tongdechang",
    "wof:placetype":"locality"
},
  "geometry": {"coordinates":[107.62248999999998,30.23611],"type":"Point"}
}