{
  "type": "Feature",
  "properties": {
    "gn:admin1_code":"29.0",
    "gn:asciiname":"Dadong",
    "gn:country_code":"CN",
    "gn:dem":1700,
    "gn:feature_class":"P",
    "gn:feature_code":"PPL",
    "gn:name":"Dadong",
    "gn:population":0,
    "gn:timezone":"Asia/Shanghai",
    "iso:country":"CN",
    "name:zho_x_preferred":[
        "\u6253\u4e1c"
    ],
    "wof:name":"Dadong",
    "wof:placetype":"locality"
},
  "geometry": {"coordinates":[101.77500000000001,23.3129],"type":"Point"}
}