{
  "type": "Feature",
  "properties": {
    "gn:admin1_code":"8.0",
    "gn:asciiname":"Sanchakou Chaoxianzu",
    "gn:country_code":"CN",
    "gn:dem":98,
    "gn:feature_class":"P",
    "gn:feature_code":"PPLA4",
    "gn:name":"Sanchakou Chaoxianzu",
    "gn:population":0,
    "gn:timezone":"Asia/Shanghai",
    "iso:country":"CN",
    "name:und_x_variant":[
        "\u4e09\u5c94\u53e3\u671d\u9c9c\u65cf",
        "Sanchakou Chaoxianzu Zhen",
        "\u4e09\u5c94\u53e3\u671d\u9c9c\u65cf\u9547"
    ],
    "wof:name":"Sanchakou Chaoxianzu",
    "wof:placetype":"locality"
},
  "geometry": {"coordinates":[131.23639,44.01695],"type":"Point"}
}