{
  "type": "Feature",
  "properties": {
    "gn:admin1_code":"14.0",
    "gn:asciiname":"Zhongmei",
    "gn:country_code":"CN",
    "gn:dem":3881,
    "gn:feature_class":"P",
    "gn:feature_code":"PPL",
    "gn:name":"Zhongmei",
    "gn:population":0,
    "gn:timezone":"Asia/Urumqi",
    "iso:country":"CN",
    "name:zho_x_preferred":[
        "\u4e2d\u6885"
    ],
    "wof:name":"Zhongmei",
    "wof:placetype":"locality"
},
  "geometry": {"coordinates":[98.75773,30.26473],"type":"Point"}
}