{
  "type": "Feature",
  "properties": {
    "gn:admin1_code":"4.0",
    "gn:asciiname":"Sanlichong",
    "gn:country_code":"CN",
    "gn:dem":2,
    "gn:feature_class":"P",
    "gn:feature_code":"PPL",
    "gn:name":"Sanlichong",
    "gn:population":0,
    "gn:timezone":"Asia/Shanghai",
    "iso:country":"CN",
    "name:zho_x_preferred":[
        "Sanlichong"
    ],
    "name:zho_x_variant":[
        "\u4e09\u91cc\u51b2"
    ],
    "wof:name":"Sanlichong",
    "wof:placetype":"locality"
},
  "geometry": {"coordinates":[119.60612,33.95569],"type":"Point"}
}