{
  "type": "Feature",
  "properties": {
    "gn:admin1_code":"07",
    "gn:asciiname":"Dacuoji",
    "gn:country_code":"CN",
    "gn:dem":12,
    "gn:feature_class":"P",
    "gn:feature_code":"PPL",
    "gn:name":"Dacuoji",
    "gn:population":0,
    "gn:timezone":"Asia/Shanghai",
    "iso:country":"CN",
    "name:zho_x_preferred":[
        "\u5927\u539d\u57fa"
    ],
    "wof:name":"Dacuoji",
    "wof:placetype":"locality"
},
  "geometry": {"coordinates":[120.22504000000001,27.27799000000001],"type":"Point"}
}