{
  "type": "Feature",
  "properties": {
    "gn:admin1_code":"22.0",
    "gn:asciiname":"Lijiacun",
    "gn:country_code":"CN",
    "gn:dem":892,
    "gn:feature_class":"P",
    "gn:feature_code":"PPL",
    "gn:name":"Lijiacun",
    "gn:population":0,
    "gn:timezone":"Asia/Shanghai",
    "iso:country":"CN",
    "name:zho_x_preferred":[
        "\u674e\u5bb6\u6751"
    ],
    "wof:name":"Lijiacun",
    "wof:placetype":"locality"
},
  "geometry": {"coordinates":[115.66862999999999,39.99814],"type":"Point"}
}