{
  "type": "Feature",
  "properties": {
    "gn:admin1_code":"9.0",
    "gn:asciiname":"Gulugou",
    "gn:country_code":"CN",
    "gn:dem":233,
    "gn:feature_class":"P",
    "gn:feature_code":"PPL",
    "gn:name":"Gulugou",
    "gn:population":0,
    "gn:timezone":"Asia/Shanghai",
    "iso:country":"CN",
    "name:zho_x_preferred":[
        "\u53e4\u8def\u6c9f"
    ],
    "wof:name":"Gulugou",
    "wof:placetype":"locality"
},
  "geometry": {"coordinates":[112.81610999999999,34.75586],"type":"Point"}
}