{
  "type": "Feature",
  "properties": {
    "gn:admin1_code":"24.0",
    "gn:asciiname":"Zhongyangcun",
    "gn:country_code":"CN",
    "gn:dem":1330,
    "gn:feature_class":"P",
    "gn:feature_code":"PPL",
    "gn:name":"Zhongyangcun",
    "gn:population":0,
    "gn:timezone":"Asia/Shanghai",
    "iso:country":"CN",
    "name:zho_x_preferred":[
        "\u4e2d\u9633\u6751"
    ],
    "wof:name":"Zhongyangcun",
    "wof:placetype":"locality"
},
  "geometry": {"coordinates":[110.82637,36.85694],"type":"Point"}
}