{
  "type": "Feature",
  "properties": {
    "gn:admin1_code":"11.0",
    "gn:asciiname":"Yuxi",
    "gn:country_code":"CN",
    "gn:dem":359,
    "gn:feature_class":"P",
    "gn:feature_code":"PPL",
    "gn:name":"Yuxi",
    "gn:population":0,
    "gn:timezone":"Asia/Shanghai",
    "iso:country":"CN",
    "name:zho_x_preferred":[
        "\u79b9\u6eaa"
    ],
    "wof:name":"Yuxi",
    "wof:placetype":"locality"
},
  "geometry": {"coordinates":[110.33327,29.23784],"type":"Point"}
}