{
  "type": "Feature",
  "properties": {
    "gn:admin1_code":"10",
    "gn:asciiname":"Shantouzhuang Dongshan",
    "gn:country_code":"CN",
    "gn:dem":76,
    "gn:feature_class":"P",
    "gn:feature_code":"PPL",
    "gn:name":"Shantouzhuang Dongshan",
    "gn:population":0,
    "gn:timezone":"Asia/Shanghai",
    "iso:country":"CN",
    "name:zho_x_preferred":[
        "\u5c71\u5934\u5e84\u4e1c\u5c71"
    ],
    "wof:name":"Shantouzhuang Dongshan",
    "wof:placetype":"locality"
},
  "geometry": {"coordinates":[117.9504,40.01666],"type":"Point"}
}