{
  "type": "Feature",
  "properties": {
    "gn:admin1_code":"30",
    "gn:asciiname":"Mazhancun",
    "gn:country_code":"CN",
    "gn:dem":81,
    "gn:feature_class":"P",
    "gn:feature_code":"PPL",
    "gn:name":"Mazhancun",
    "gn:population":0,
    "gn:timezone":"Asia/Urumqi",
    "iso:country":"CN",
    "name:zho_x_preferred":[
        "\u9a6c\u7ad9\u6751"
    ],
    "wof:name":"Mazhancun",
    "wof:placetype":"locality"
},
  "geometry": {"coordinates":[110.57844,22.17248],"type":"Point"}
}