{
  "type": "Feature",
  "properties": {
    "gn:admin1_code":"12.0",
    "gn:asciiname":"Jinqiaozhu",
    "gn:country_code":"CN",
    "gn:dem":34,
    "gn:feature_class":"P",
    "gn:feature_code":"PPL",
    "gn:name":"Jinqiaozhu",
    "gn:population":0,
    "gn:timezone":"Asia/Shanghai",
    "iso:country":"CN",
    "name:und_x_variant":[
        "\u91d1\u6865\u6731"
    ],
    "wof:name":"Jinqiaozhu",
    "wof:placetype":"locality"
},
  "geometry": {"coordinates":[114.52642,30.12962000000001],"type":"Point"}
}