{
  "type": "Feature",
  "properties": {
    "gn:admin1_code":"4.0",
    "gn:asciiname":"Shayou",
    "gn:country_code":"CN",
    "gn:dem":6,
    "gn:feature_class":"P",
    "gn:feature_code":"PPL",
    "gn:name":"Shayou",
    "gn:population":0,
    "gn:timezone":"Asia/Shanghai",
    "iso:country":"CN",
    "name:zho_x_preferred":[
        "\u6c99\u6e38"
    ],
    "wof:name":"Shayou",
    "wof:placetype":"locality"
},
  "geometry": {"coordinates":[119.65667000000001,32.86644],"type":"Point"}
}