{
  "type": "Feature",
  "properties": {
    "gn:admin1_code":"12.0",
    "gn:asciiname":"Weixiaoyuan",
    "gn:country_code":"CN",
    "gn:dem":67,
    "gn:feature_class":"P",
    "gn:feature_code":"PPL",
    "gn:name":"Weixiaoyuan",
    "gn:population":0,
    "gn:timezone":"Asia/Shanghai",
    "iso:country":"CN",
    "name:zho_x_preferred":[
        "Weixiaoyuan"
    ],
    "name:zho_x_variant":[
        "\u9b4f\u5c0f\u9662"
    ],
    "wof:name":"Weixiaoyuan",
    "wof:placetype":"locality"
},
  "geometry": {"coordinates":[112.2734,30.95896],"type":"Point"}
}