{
  "type": "Feature",
  "properties": {
    "gn:admin1_code":"30.0",
    "gn:asciiname":"Jianling",
    "gn:country_code":"CN",
    "gn:dem":16,
    "gn:feature_class":"P",
    "gn:feature_code":"PPL",
    "gn:name":"Jianling",
    "gn:population":0,
    "gn:timezone":"Asia/Urumqi",
    "iso:country":"CN",
    "name:zho_x_preferred":[
        "\u5c16\u5cad"
    ],
    "wof:name":"Jianling",
    "wof:placetype":"locality"
},
  "geometry": {"coordinates":[110.48847000000001,20.53544],"type":"Point"}
}