{
  "type": "Feature",
  "properties": {
    "gn:admin1_code":"4.0",
    "gn:asciiname":"Wanzhucun",
    "gn:country_code":"CN",
    "gn:dem":-1,
    "gn:feature_class":"P",
    "gn:feature_code":"PPL",
    "gn:name":"Wanzhucun",
    "gn:population":0,
    "gn:timezone":"Asia/Shanghai",
    "iso:country":"CN",
    "name:zho_x_preferred":[
        "\u6e7e\u6731\u6751"
    ],
    "wof:name":"Wanzhucun",
    "wof:placetype":"locality"
},
  "geometry": {"coordinates":[119.97553000000001,32.94629],"type":"Point"}
}