{
  "type": "Feature",
  "properties": {
    "gn:admin1_code":"24.0",
    "gn:asciiname":"Yangquan",
    "gn:country_code":"CN",
    "gn:dem":1128,
    "gn:feature_class":"P",
    "gn:feature_code":"PPL",
    "gn:name":"Yangquan",
    "gn:population":0,
    "gn:timezone":"Asia/Shanghai",
    "iso:country":"CN",
    "name:zho_x_preferred":[
        "\u7f8a\u6cc9"
    ],
    "wof:name":"Yangquan",
    "wof:placetype":"locality"
},
  "geometry": {"coordinates":[113.15004999999999,38.26753],"type":"Point"}
}