{
  "type": "Feature",
  "properties": {
    "gn:admin1_code":"1.0",
    "gn:asciiname":"Dashantoucun",
    "gn:country_code":"CN",
    "gn:dem":28,
    "gn:feature_class":"P",
    "gn:feature_code":"PPL",
    "gn:name":"Dashantoucun",
    "gn:population":0,
    "gn:timezone":"Asia/Shanghai",
    "iso:country":"CN",
    "name:und_x_variant":[
        "Dashantou",
        "Dashantoucun"
    ],
    "name:zho_x_preferred":[
        "\u5927\u5c71\u5934"
    ],
    "name:zho_x_variant":[
        "\u5927\u5c71\u5934\u6751"
    ],
    "wof:name":"Dashantoucun",
    "wof:placetype":"locality"
},
  "geometry": {"coordinates":[118.58299,31.16497],"type":"Point"}
}