{
  "type": "Feature",
  "properties": {
    "gn:admin1_code":"18",
    "gn:asciiname":"Shiqiangyuan",
    "gn:country_code":"CN",
    "gn:dem":1483,
    "gn:feature_class":"P",
    "gn:feature_code":"PPL",
    "gn:name":"Shiqiangyuan",
    "gn:population":0,
    "gn:timezone":"Asia/Shanghai",
    "iso:country":"CN",
    "name:zho_x_preferred":[
        "\u77f3\u5899\u9662"
    ],
    "wof:name":"Shiqiangyuan",
    "wof:placetype":"locality"
},
  "geometry": {"coordinates":[105.514,27.0923],"type":"Point"}
}