{
  "type": "Feature",
  "properties": {
    "gn:admin1_code":"02",
    "gn:asciiname":"Taifang",
    "gn:cc2":"CN",
    "gn:country_code":"CN",
    "gn:dem":9,
    "gn:feature_class":"P",
    "gn:feature_code":"PPL",
    "gn:name":"Taifang",
    "gn:population":0,
    "gn:timezone":"Asia/Shanghai",
    "iso:country":"CN",
    "name:und_x_variant":[
        "T\u2019ai-fang-ts\u2019un",
        "Taifang",
        "\u53f0\u82b3"
    ],
    "name:zho_x_preferred":[
        "\u53f0\u82b3"
    ],
    "wof:name":"Taifang",
    "wof:placetype":"locality"
},
  "geometry": {"coordinates":[121.56222,29.28028],"type":"Point"}
}