{
  "type": "Feature",
  "properties": {
    "gn:admin1_code":"24.0",
    "gn:asciiname":"Huquangou",
    "gn:country_code":"CN",
    "gn:dem":1249,
    "gn:feature_class":"P",
    "gn:feature_code":"PPL",
    "gn:name":"Huquangou",
    "gn:population":0,
    "gn:timezone":"Asia/Shanghai",
    "iso:country":"CN",
    "name:zho_x_preferred":[
        "\u80e1\u6cc9\u6c9f"
    ],
    "wof:name":"Huquangou",
    "wof:placetype":"locality"
},
  "geometry": {"coordinates":[112.88925999999999,40.10605],"type":"Point"}
}