{
  "type": "Feature",
  "properties": {
    "gn:admin1_code":"3",
    "gn:asciiname":"Liuwugang",
    "gn:country_code":"CN",
    "gn:dem":158,
    "gn:feature_class":"P",
    "gn:feature_code":"PPL",
    "gn:name":"Liuwugang",
    "gn:population":0,
    "gn:timezone":"Asia/Shanghai",
    "iso:country":"CN",
    "name:zho_x_preferred":[
        "\u7559\u5c4b\u5c97"
    ],
    "wof:name":"Liuwugang",
    "wof:placetype":"locality"
},
  "geometry": {"coordinates":[114.56399999999999,25.7122],"type":"Point"}
}