{
  "type": "Feature",
  "properties": {
    "gn:admin1_code":"4.0",
    "gn:asciiname":"Xingyicun",
    "gn:cc2":"CN",
    "gn:country_code":"CN",
    "gn:dem":4,
    "gn:feature_class":"P",
    "gn:feature_code":"PPL",
    "gn:name":"Xingyicun",
    "gn:population":0,
    "gn:timezone":"Asia/Shanghai",
    "iso:country":"CN",
    "name:und_x_variant":[
        "Hsing-i-ts\u2019un",
        "Xingyicun"
    ],
    "wof:name":"Xingyicun",
    "wof:placetype":"locality"
},
  "geometry": {"coordinates":[121.75749999999999,31.96111],"type":"Point"}
}