{
  "type": "Feature",
  "properties": {
    "gn:admin1_code":"11.0",
    "gn:asciiname":"Tiandeng",
    "gn:country_code":"CN",
    "gn:dem":625,
    "gn:feature_class":"P",
    "gn:feature_code":"PPL",
    "gn:name":"Tiandeng",
    "gn:population":0,
    "gn:timezone":"Asia/Shanghai",
    "iso:country":"CN",
    "name:zho_x_preferred":[
        "\u7530\u8e6c"
    ],
    "wof:name":"Tiandeng",
    "wof:placetype":"locality"
},
  "geometry": {"coordinates":[112.07971000000001,24.84983],"type":"Point"}
}