{
  "type": "Feature",
  "properties": {
    "gn:admin1_code":"32.0",
    "gn:asciiname":"Fangjiaping",
    "gn:country_code":"CN",
    "gn:dem":1576,
    "gn:feature_class":"P",
    "gn:feature_code":"PPL",
    "gn:name":"Fangjiaping",
    "gn:population":0,
    "gn:timezone":"Asia/Shanghai",
    "iso:country":"CN",
    "name:und_x_variant":[
        "\u65b9\u5bb6\u576a"
    ],
    "wof:name":"Fangjiaping",
    "wof:placetype":"locality"
},
  "geometry": {"coordinates":[106.58636,32.42642],"type":"Point"}
}