{
  "type": "Feature",
  "properties": {
    "gn:admin1_code":"11.0",
    "gn:asciiname":"Tutangli",
    "gn:country_code":"CN",
    "gn:dem":235,
    "gn:feature_class":"P",
    "gn:feature_code":"PPL",
    "gn:name":"Tutangli",
    "gn:population":0,
    "gn:timezone":"Asia/Shanghai",
    "iso:country":"CN",
    "name:zho_x_preferred":[
        "\u571f\u5802\u91cc"
    ],
    "wof:name":"Tutangli",
    "wof:placetype":"locality"
},
  "geometry": {"coordinates":[110.39743,28.2482],"type":"Point"}
}