{
  "type": "Feature",
  "properties": {
    "gn:admin1_code":"29.0",
    "gn:asciiname":"Ennu",
    "gn:country_code":"CN",
    "gn:dem":2642,
    "gn:feature_class":"P",
    "gn:feature_code":"PPL",
    "gn:name":"Ennu",
    "gn:population":0,
    "gn:timezone":"Asia/Shanghai",
    "iso:country":"CN",
    "name:deu_x_preferred":[
        "Ennu"
    ],
    "name:est_x_preferred":[
        "Ennu"
    ],
    "name:fra_x_preferred":[
        "Ennu"
    ],
    "name:hye_x_preferred":[
        "\u0537\u0576\u0576\u0578\u0582"
    ],
    "name:pol_x_preferred":[
        "Ennu"
    ],
    "name:spa_x_preferred":[
        "Ennu"
    ],
    "name:vol_x_preferred":[
        "Ennu"
    ],
    "name:zho_x_preferred":[
        "\u6069\u52aa"
    ],
    "wof:name":"Ennu",
    "wof:placetype":"locality"
},
  "geometry": {"coordinates":[100.18300000000001,27.345],"type":"Point"}
}