{
  "type": "Feature",
  "properties": {
    "gn:admin1_code":"12.0",
    "gn:asciiname":"Maozishan",
    "gn:country_code":"CN",
    "gn:dem":1090,
    "gn:feature_class":"P",
    "gn:feature_code":"PPL",
    "gn:name":"Maozishan",
    "gn:population":0,
    "gn:timezone":"Asia/Shanghai",
    "iso:country":"CN",
    "name:zho_x_preferred":[
        "\u5cc1\u5b50\u5c71"
    ],
    "wof:name":"Maozishan",
    "wof:placetype":"locality"
},
  "geometry": {"coordinates":[109.68485,30.2446],"type":"Point"}
}