{
  "type": "Feature",
  "properties": {
    "gn:admin1_code":"26.0",
    "gn:asciiname":"Hexincun",
    "gn:country_code":"CN",
    "gn:dem":694,
    "gn:feature_class":"P",
    "gn:feature_code":"PPL",
    "gn:name":"Hexincun",
    "gn:population":0,
    "gn:timezone":"Asia/Shanghai",
    "iso:country":"CN",
    "name:zho_x_preferred":[
        "\u5408\u5fc3\u6751"
    ],
    "wof:name":"Hexincun",
    "wof:placetype":"locality"
},
  "geometry": {"coordinates":[108.12566,33.15101],"type":"Point"}
}