{
  "type": "Feature",
  "properties": {
    "gn:admin1_code":"18.0",
    "gn:asciiname":"Zhaiyang",
    "gn:country_code":"CN",
    "gn:dem":432,
    "gn:feature_class":"P",
    "gn:feature_code":"PPL",
    "gn:name":"Zhaiyang",
    "gn:population":0,
    "gn:timezone":"Asia/Shanghai",
    "iso:country":"CN",
    "name:zho_x_preferred":[
        "\u5be8\u7f8a"
    ],
    "wof:name":"Zhaiyang",
    "wof:placetype":"locality"
},
  "geometry": {"coordinates":[108.992,28.1136],"type":"Point"}
}