{
  "type": "Feature",
  "properties": {
    "gn:admin1_code":"3.0",
    "gn:asciiname":"Dabei",
    "gn:country_code":"CN",
    "gn:dem":234,
    "gn:feature_class":"P",
    "gn:feature_code":"PPL",
    "gn:name":"Dabei",
    "gn:population":0,
    "gn:timezone":"Asia/Shanghai",
    "iso:country":"CN",
    "name:zho_x_preferred":[
        "\u8fbe\u9642"
    ],
    "wof:name":"Dabei",
    "wof:placetype":"locality"
},
  "geometry": {"coordinates":[116.072,25.8051],"type":"Point"}
}