{
  "type": "Feature",
  "properties": {
    "gn:admin1_code":"31.0",
    "gn:asciiname":"Wenyu",
    "gn:country_code":"CN",
    "gn:dem":33,
    "gn:feature_class":"P",
    "gn:feature_code":"PPL",
    "gn:name":"Wenyu",
    "gn:population":0,
    "gn:timezone":"Asia/Shanghai",
    "iso:country":"CN",
    "name:zho_x_preferred":[
        "Wenyu"
    ],
    "name:zho_x_variant":[
        "\u6587\u6bd3"
    ],
    "wof:name":"Wenyu",
    "wof:placetype":"locality"
},
  "geometry": {"coordinates":[110.21229,20.00266],"type":"Point"}
}