{
  "type": "Feature",
  "properties": {
    "gn:admin1_code":"29",
    "gn:asciiname":"Taipingdian",
    "gn:country_code":"CN",
    "gn:dem":740,
    "gn:feature_class":"P",
    "gn:feature_code":"PPLA4",
    "gn:name":"Taipingdian",
    "gn:population":0,
    "gn:timezone":"Asia/Shanghai",
    "iso:country":"CN",
    "name:und_x_variant":[
        "\u592a\u5e73\u7538",
        "Taiping Xiang",
        "\u592a\u5e73\u4e61"
    ],
    "wof:name":"Taipingdian",
    "wof:placetype":"locality"
},
  "geometry": {"coordinates":[104.22203,28.55926],"type":"Point"}
}