{
  "type": "Feature",
  "properties": {
    "gn:admin1_code":"1.0",
    "gn:asciiname":"Laodongduicun",
    "gn:country_code":"CN",
    "gn:dem":21,
    "gn:feature_class":"P",
    "gn:feature_code":"PPLF",
    "gn:name":"Laodongduicun",
    "gn:population":0,
    "gn:timezone":"Asia/Shanghai",
    "iso:country":"CN",
    "name:und_x_variant":[
        "Laodongdui",
        "Laodongduicun"
    ],
    "name:zho_x_preferred":[
        "\u52b3\u52a8\u961f"
    ],
    "name:zho_x_variant":[
        "\u52b3\u52a8\u961f\u6751"
    ],
    "wof:name":"Laodongduicun",
    "wof:placetype":"locality"
},
  "geometry": {"coordinates":[118.96617999999999,31.20187],"type":"Point"}
}