{
  "type": "Feature",
  "properties": {
    "gn:admin1_code":"1.0",
    "gn:asciiname":"Tianfancun",
    "gn:country_code":"CN",
    "gn:dem":13,
    "gn:feature_class":"P",
    "gn:feature_code":"PPL",
    "gn:name":"Tianfancun",
    "gn:population":0,
    "gn:timezone":"Asia/Shanghai",
    "iso:country":"CN",
    "name:zho_x_preferred":[
        "\u7530\u7548\u6751"
    ],
    "wof:name":"Tianfancun",
    "wof:placetype":"locality"
},
  "geometry": {"coordinates":[117.57628,31.0897],"type":"Point"}
}