{
  "type": "Feature",
  "properties": {
    "gn:admin1_code":"30.0",
    "gn:asciiname":"Chizhutang",
    "gn:country_code":"CN",
    "gn:dem":439,
    "gn:feature_class":"P",
    "gn:feature_code":"PPL",
    "gn:name":"Chizhutang",
    "gn:population":0,
    "gn:timezone":"Asia/Shanghai",
    "iso:country":"CN",
    "name:zho_x_preferred":[
        "Chizhutang"
    ],
    "name:zho_x_variant":[
        "\u8d64\u7af9\u5858"
    ],
    "wof:name":"Chizhutang",
    "wof:placetype":"locality"
},
  "geometry": {"coordinates":[115.15472,24.12944],"type":"Point"}
}