{
  "type": "Feature",
  "properties": {
    "gn:admin1_code":"21.0",
    "gn:asciiname":"Siyanjing",
    "gn:country_code":"CN",
    "gn:dem":1265,
    "gn:feature_class":"P",
    "gn:feature_code":"PPL",
    "gn:name":"Siyanjing",
    "gn:population":0,
    "gn:timezone":"Asia/Shanghai",
    "iso:country":"CN",
    "name:zho_x_preferred":[
        "\u56db\u773c\u4e95"
    ],
    "wof:name":"Siyanjing",
    "wof:placetype":"locality"
},
  "geometry": {"coordinates":[105.76900000000001,37.7645],"type":"Point"}
}