{
  "type": "Feature",
  "properties": {
    "gn:admin1_code":"12.0",
    "gn:asciiname":"Changhuzui",
    "gn:country_code":"CN",
    "gn:dem":27,
    "gn:feature_class":"P",
    "gn:feature_code":"PPL",
    "gn:name":"Changhuzui",
    "gn:population":0,
    "gn:timezone":"Asia/Shanghai",
    "iso:country":"CN",
    "name:und_x_variant":[
        "\u957f\u6e56\u5480"
    ],
    "wof:name":"Changhuzui",
    "wof:placetype":"locality"
},
  "geometry": {"coordinates":[114.3329,30.72219],"type":"Point"}
}