{
  "type": "Feature",
  "properties": {
    "gn:admin1_code":"10.0",
    "gn:asciiname":"Yaozhanbu",
    "gn:country_code":"CN",
    "gn:dem":666,
    "gn:feature_class":"P",
    "gn:feature_code":"PPL",
    "gn:name":"Yaozhanbu",
    "gn:population":0,
    "gn:timezone":"Asia/Shanghai",
    "iso:country":"CN",
    "name:zho_x_preferred":[
        "\u8170\u7ad9\u5821"
    ],
    "wof:name":"Yaozhanbu",
    "wof:placetype":"locality"
},
  "geometry": {"coordinates":[114.80365999999999,40.70657],"type":"Point"}
}