{
  "type": "Feature",
  "properties": {
    "gn:admin1_code":"11.0",
    "gn:asciiname":"Yitangwan",
    "gn:country_code":"CN",
    "gn:dem":112,
    "gn:feature_class":"P",
    "gn:feature_code":"PPL",
    "gn:name":"Yitangwan",
    "gn:population":0,
    "gn:timezone":"Asia/Shanghai",
    "iso:country":"CN",
    "name:zho_x_preferred":[
        "\u4f9d\u5858\u6e7e"
    ],
    "wof:name":"Yitangwan",
    "wof:placetype":"locality"
},
  "geometry": {"coordinates":[113.24414,26.77981],"type":"Point"}
}