{
  "type": "Feature",
  "properties": {
    "gn:admin1_code":"16.0",
    "gn:asciiname":"Xihua",
    "gn:country_code":"CN",
    "gn:dem":772,
    "gn:feature_class":"P",
    "gn:feature_code":"PPL",
    "gn:name":"Xihua",
    "gn:population":0,
    "gn:timezone":"Asia/Shanghai",
    "iso:country":"CN",
    "name:ceb_x_preferred":[
        "Xihua"
    ],
    "name:zho_x_preferred":[
        "\u897f\u534e"
    ],
    "wof:name":"Xihua",
    "wof:placetype":"locality"
},
  "geometry": {"coordinates":[106.295,23.0854],"type":"Point"}
}