{
  "type": "Feature",
  "properties": {
    "gn:admin1_code":"8.0",
    "gn:asciiname":"Yangguang Linchang",
    "gn:country_code":"CN",
    "gn:dem":417,
    "gn:feature_class":"P",
    "gn:feature_code":"PPLF",
    "gn:name":"Yangguang Linchang",
    "gn:population":0,
    "gn:timezone":"Asia/Shanghai",
    "iso:country":"CN",
    "name:zho_x_preferred":[
        "\u9633\u5149\u6797\u573a"
    ],
    "wof:name":"Yangguang Linchang",
    "wof:placetype":"locality"
},
  "geometry": {"coordinates":[128.81415000000001,48.54316],"type":"Point"}
}