{
  "type": "Feature",
  "properties": {
    "gn:admin1_code":"18",
    "gn:asciiname":"Shangliting",
    "gn:country_code":"CN",
    "gn:dem":447,
    "gn:feature_class":"P",
    "gn:feature_code":"PPL",
    "gn:name":"Shangliting",
    "gn:population":0,
    "gn:timezone":"Asia/Shanghai",
    "iso:country":"CN",
    "name:zho_x_preferred":[
        "\u4e0a\u7acb\u4ead"
    ],
    "wof:name":"Shangliting",
    "wof:placetype":"locality"
},
  "geometry": {"coordinates":[106.61799999999999,25.4263],"type":"Point"}
}