{
  "type": "Feature",
  "properties": {
    "gn:admin1_code":"1.0",
    "gn:asciiname":"Taigangcun",
    "gn:country_code":"CN",
    "gn:dem":13,
    "gn:feature_class":"P",
    "gn:feature_code":"PPL",
    "gn:name":"Taigangcun",
    "gn:population":0,
    "gn:timezone":"Asia/Shanghai",
    "iso:country":"CN",
    "name:zho_x_preferred":[
        "\u592a\u5c97\u6751"
    ],
    "wof:name":"Taigangcun",
    "wof:placetype":"locality"
},
  "geometry": {"coordinates":[117.05406000000001,31.49781],"type":"Point"}
}