{
  "type": "Feature",
  "properties": {
    "gn:admin1_code":"26.0",
    "gn:asciiname":"Liutanzi",
    "gn:country_code":"CN",
    "gn:dem":1065,
    "gn:feature_class":"P",
    "gn:feature_code":"PPL",
    "gn:name":"Liutanzi",
    "gn:population":0,
    "gn:timezone":"Asia/Shanghai",
    "iso:country":"CN",
    "name:und_x_variant":[
        "\u67f3\u6f6d\u5b50"
    ],
    "wof:name":"Liutanzi",
    "wof:placetype":"locality"
},
  "geometry": {"coordinates":[106.80145,33.22831],"type":"Point"}
}