{
  "type": "Feature",
  "properties": {
    "gn:admin1_code":"16.0",
    "gn:asciiname":"Cewaicun",
    "gn:country_code":"CN",
    "gn:dem":251,
    "gn:feature_class":"P",
    "gn:feature_code":"PPL",
    "gn:name":"Cewaicun",
    "gn:population":0,
    "gn:timezone":"Asia/Shanghai",
    "iso:country":"CN",
    "name:zho_x_preferred":[
        "\u518c\u5916\u6751"
    ],
    "wof:name":"Cewaicun",
    "wof:placetype":"locality"
},
  "geometry": {"coordinates":[106.167,23.7772],"type":"Point"}
}