{
  "type": "Feature",
  "properties": {
    "gn:admin1_code":"07",
    "gn:asciiname":"Xikengwei",
    "gn:country_code":"CN",
    "gn:dem":587,
    "gn:feature_class":"P",
    "gn:feature_code":"PPL",
    "gn:name":"Xikengwei",
    "gn:population":0,
    "gn:timezone":"Asia/Shanghai",
    "iso:country":"CN",
    "name:zho_x_preferred":[
        "\u897f\u5751\u5c3e"
    ],
    "wof:name":"Xikengwei",
    "wof:placetype":"locality"
},
  "geometry": {"coordinates":[117.06992,25.49546],"type":"Point"}
}