{
  "type": "Feature",
  "properties": {
    "gn:admin1_code":"2",
    "gn:asciiname":"Fengtang",
    "gn:country_code":"CN",
    "gn:dem":396,
    "gn:feature_class":"P",
    "gn:feature_code":"PPL",
    "gn:name":"Fengtang",
    "gn:population":0,
    "gn:timezone":"Asia/Shanghai",
    "iso:country":"CN",
    "name:zho_x_preferred":[
        "\u67ab\u5802"
    ],
    "wof:name":"Fengtang",
    "wof:placetype":"locality"
},
  "geometry": {"coordinates":[118.92306000000001,27.70639000000001],"type":"Point"}
}