{
  "type": "Feature",
  "properties": {
    "gn:admin1_code":"25",
    "gn:asciiname":"Yanma",
    "gn:country_code":"CN",
    "gn:dem":120,
    "gn:feature_class":"P",
    "gn:feature_code":"PPL",
    "gn:name":"Yanma",
    "gn:population":0,
    "gn:timezone":"Asia/Shanghai",
    "iso:country":"CN",
    "name:und_x_variant":[
        "\u960e\u9a6c"
    ],
    "name:zho_x_preferred":[
        "\u960e\u9a6c"
    ],
    "wof:name":"Yanma",
    "wof:placetype":"locality"
},
  "geometry": {"coordinates":[119.21899999999999,35.59353],"type":"Point"}
}