{
  "type": "Feature",
  "properties": {
    "gn:admin1_code":"19.0",
    "gn:asciiname":"Dingjiajie",
    "gn:country_code":"CN",
    "gn:dem":484,
    "gn:feature_class":"P",
    "gn:feature_code":"PPL",
    "gn:name":"Dingjiajie",
    "gn:population":0,
    "gn:timezone":"Asia/Shanghai",
    "iso:country":"CN",
    "name:und_x_variant":[
        "\u4e01\u5bb6\u8857"
    ],
    "name:zho_x_preferred":[
        "\u4e01\u5bb6\u8857"
    ],
    "wof:name":"Dingjiajie",
    "wof:placetype":"locality"
},
  "geometry": {"coordinates":[125.15942,41.57061],"type":"Point"}
}