{
  "type": "Feature",
  "properties": {
    "gn:admin1_code":"3.0",
    "gn:asciiname":"Tuqiu",
    "gn:country_code":"CN",
    "gn:dem":24,
    "gn:feature_class":"P",
    "gn:feature_code":"PPL",
    "gn:name":"Tuqiu",
    "gn:population":0,
    "gn:timezone":"Asia/Shanghai",
    "iso:country":"CN",
    "name:und_x_variant":[
        "\u571f\u4e18"
    ],
    "wof:name":"Tuqiu",
    "wof:placetype":"locality"
},
  "geometry": {"coordinates":[115.98255,29.15755],"type":"Point"}
}