{
  "type": "Feature",
  "properties": {
    "gn:admin1_code":"14.0",
    "gn:asciiname":"Dongkongriwa",
    "gn:country_code":"CN",
    "gn:dem":3946,
    "gn:feature_class":"P",
    "gn:feature_code":"PPL",
    "gn:name":"Dongkongriwa",
    "gn:population":0,
    "gn:timezone":"Asia/Urumqi",
    "iso:country":"CN",
    "name:zho_x_preferred":[
        "\u4e1c\u7a7a\u65e5\u74e6"
    ],
    "wof:name":"Dongkongriwa",
    "wof:placetype":"locality"
},
  "geometry": {"coordinates":[98.14104,30.55879],"type":"Point"}
}