{
  "type": "Feature",
  "properties": {
    "gn:admin1_code":"15.0",
    "gn:asciiname":"Zhangou",
    "gn:country_code":"CN",
    "gn:dem":1756,
    "gn:feature_class":"P",
    "gn:feature_code":"PPL",
    "gn:name":"Zhangou",
    "gn:population":0,
    "gn:timezone":"Asia/Shanghai",
    "iso:country":"CN",
    "name:und_x_variant":[
        "\u7efd\u6c9f"
    ],
    "wof:name":"Zhangou",
    "wof:placetype":"locality"
},
  "geometry": {"coordinates":[105.0468,35.0957],"type":"Point"}
}