{
  "type": "Feature",
  "properties": {
    "gn:admin1_code":"29.0",
    "gn:asciiname":"Nongbu Xinzhai",
    "gn:country_code":"CN",
    "gn:dem":1670,
    "gn:feature_class":"P",
    "gn:feature_code":"PPL",
    "gn:name":"Nongbu Xinzhai",
    "gn:population":0,
    "gn:timezone":"Asia/Shanghai",
    "iso:country":"CN",
    "name:zho_x_preferred":[
        "\u5f04\u535c\u65b0\u5be8"
    ],
    "wof:name":"Nongbu Xinzhai",
    "wof:placetype":"locality"
},
  "geometry": {"coordinates":[102.363,23.2681],"type":"Point"}
}