{
  "type": "Feature",
  "properties": {
    "gn:admin1_code":"14.0",
    "gn:asciiname":"Mogacui",
    "gn:country_code":"CN",
    "gn:dem":3775,
    "gn:feature_class":"P",
    "gn:feature_code":"PPL",
    "gn:name":"Mogacui",
    "gn:population":0,
    "gn:timezone":"Asia/Urumqi",
    "iso:country":"CN",
    "name:zho_x_preferred":[
        "\u83ab\u560e\u8106"
    ],
    "wof:name":"Mogacui",
    "wof:placetype":"locality"
},
  "geometry": {"coordinates":[91.85704,29.05339],"type":"Point"}
}