{
  "type": "Feature",
  "properties": {
    "gn:admin1_code":"18.0",
    "gn:asciiname":"Niutang",
    "gn:country_code":"CN",
    "gn:dem":756,
    "gn:feature_class":"P",
    "gn:feature_code":"PPL",
    "gn:name":"Niutang",
    "gn:population":0,
    "gn:timezone":"Asia/Shanghai",
    "iso:country":"CN",
    "name:zho_x_preferred":[
        "\u725b\u5858"
    ],
    "wof:name":"Niutang",
    "wof:placetype":"locality"
},
  "geometry": {"coordinates":[107.88500000000001,28.4423],"type":"Point"}
}