{
  "type": "Feature",
  "properties": {
    "gn:admin1_code":"32.0",
    "gn:asciiname":"Shijing",
    "gn:country_code":"CN",
    "gn:dem":544,
    "gn:feature_class":"P",
    "gn:feature_code":"PPL",
    "gn:name":"Shijing",
    "gn:population":0,
    "gn:timezone":"Asia/Shanghai",
    "iso:country":"CN",
    "name:zho_x_preferred":[
        "\u8bc6\u7ecf"
    ],
    "wof:name":"Shijing",
    "wof:placetype":"locality"
},
  "geometry": {"coordinates":[104.44658,29.78931],"type":"Point"}
}