{
  "type": "Feature",
  "properties": {
    "gn:admin1_code":"7.0",
    "gn:asciiname":"Zhuzhoushan",
    "gn:country_code":"CN",
    "gn:dem":442,
    "gn:feature_class":"P",
    "gn:feature_code":"PPL",
    "gn:name":"Zhuzhoushan",
    "gn:population":0,
    "gn:timezone":"Asia/Shanghai",
    "iso:country":"CN",
    "name:zho_x_preferred":[
        "\u7af9\u5dde\u5c71"
    ],
    "wof:name":"Zhuzhoushan",
    "wof:placetype":"locality"
},
  "geometry": {"coordinates":[119.43198,27.10384],"type":"Point"}
}