{
  "type": "Feature",
  "properties": {
    "gn:admin1_code":"7",
    "gn:asciiname":"Chiling Xiacun",
    "gn:country_code":"CN",
    "gn:dem":211,
    "gn:feature_class":"P",
    "gn:feature_code":"PPL",
    "gn:name":"Chiling Xiacun",
    "gn:population":0,
    "gn:timezone":"Asia/Shanghai",
    "iso:country":"CN",
    "name:zho_x_preferred":[
        "\u8d64\u5cad\u4e0b\u6751"
    ],
    "wof:name":"Chiling Xiacun",
    "wof:placetype":"locality"
},
  "geometry": {"coordinates":[117.52346,24.95104],"type":"Point"}
}