{
  "type": "Feature",
  "properties": {
    "gn:admin1_code":"29",
    "gn:asciiname":"Dieshui",
    "gn:country_code":"CN",
    "gn:dem":1605,
    "gn:feature_class":"P",
    "gn:feature_code":"PPL",
    "gn:name":"Dieshui",
    "gn:population":0,
    "gn:timezone":"Asia/Shanghai",
    "iso:country":"CN",
    "name:zho_x_preferred":[
        "\u53e0\u6c34"
    ],
    "wof:name":"Dieshui",
    "wof:placetype":"locality"
},
  "geometry": {"coordinates":[103.18176,24.6672],"type":"Point"}
}