{
  "type": "Feature",
  "properties": {
    "gn:admin1_code":"10",
    "gn:asciiname":"Xiaheqiying",
    "gn:country_code":"CN",
    "gn:dem":1435,
    "gn:feature_class":"P",
    "gn:feature_code":"PPL",
    "gn:name":"Xiaheqiying",
    "gn:population":0,
    "gn:timezone":"Asia/Shanghai",
    "iso:country":"CN",
    "name:zho_x_preferred":[
        "\u4e0b\u548c\u6c14\u8425"
    ],
    "wof:name":"Xiaheqiying",
    "wof:placetype":"locality"
},
  "geometry": {"coordinates":[115.17585,41.14863],"type":"Point"}
}