{
  "type": "Feature",
  "properties": {
    "gn:admin1_code":"2.0",
    "gn:asciiname":"Zuoxi",
    "gn:country_code":"CN",
    "gn:dem":376,
    "gn:feature_class":"P",
    "gn:feature_code":"PPL",
    "gn:name":"Zuoxi",
    "gn:population":0,
    "gn:timezone":"Asia/Shanghai",
    "iso:country":"CN",
    "name:zho_x_preferred":[
        "\u4f50\u6eaa"
    ],
    "wof:name":"Zuoxi",
    "wof:placetype":"locality"
},
  "geometry": {"coordinates":[119.72875999999999,27.66309],"type":"Point"}
}