{
  "type": "Feature",
  "properties": {
    "gn:admin1_code":"12.0",
    "gn:asciiname":"Shangwangdang",
    "gn:country_code":"CN",
    "gn:dem":332,
    "gn:feature_class":"P",
    "gn:feature_code":"PPL",
    "gn:name":"Shangwangdang",
    "gn:population":0,
    "gn:timezone":"Asia/Shanghai",
    "iso:country":"CN",
    "name:zho_x_preferred":[
        "\u4e0a\u6c6a\u5b95"
    ],
    "wof:name":"Shangwangdang",
    "wof:placetype":"locality"
},
  "geometry": {"coordinates":[115.7273,30.16065],"type":"Point"}
}