{
  "type": "Feature",
  "properties": {
    "gn:admin1_code":"32.0",
    "gn:asciiname":"Yangpei",
    "gn:country_code":"CN",
    "gn:dem":3647,
    "gn:feature_class":"P",
    "gn:feature_code":"PPL",
    "gn:name":"Yangpei",
    "gn:population":0,
    "gn:timezone":"Asia/Shanghai",
    "iso:country":"CN",
    "name:zho_x_preferred":[
        "\u9633\u57f9"
    ],
    "wof:name":"Yangpei",
    "wof:placetype":"locality"
},
  "geometry": {"coordinates":[100.83199999999999,32.3274],"type":"Point"}
}