{
  "type": "Feature",
  "properties": {
    "gn:admin1_code":"19",
    "gn:asciiname":"Xindian",
    "gn:country_code":"CN",
    "gn:dem":116,
    "gn:feature_class":"P",
    "gn:feature_code":"PPLA4",
    "gn:name":"Xindian",
    "gn:population":0,
    "gn:timezone":"Asia/Shanghai",
    "iso:country":"CN",
    "name:ceb_x_preferred":[
        "Xindian"
    ],
    "name:deu_x_preferred":[
        "Xindian"
    ],
    "name:swe_x_preferred":[
        "Xindian"
    ],
    "name:und_x_variant":[
        "Xindian Zhen",
        "Xindian",
        "\u65b0\u7538\u9547",
        "Dashan",
        "\u65b0\u7538",
        "Xindian Manzu Zhen",
        "\u65b0\u7538\u6ee1\u65cf\u9547"
    ],
    "name:zho_x_preferred":[
        "\u5927\u5c71"
    ],
    "wof:name":"Xindian",
    "wof:placetype":"locality"
},
  "geometry": {"coordinates":[123.11266000000001,40.10735],"type":"Point"}
}