{
  "type": "Feature",
  "properties": {
    "gn:admin1_code":"15.0",
    "gn:asciiname":"Shandanxiang",
    "gn:country_code":"CN",
    "gn:dem":1511,
    "gn:feature_class":"P",
    "gn:feature_code":"PPL",
    "gn:name":"Shandanxiang",
    "gn:population":0,
    "gn:timezone":"Asia/Shanghai",
    "iso:country":"CN",
    "name:und_x_variant":[
        "\u5c71\u4e39\u4e61"
    ],
    "wof:name":"Shandanxiang",
    "wof:placetype":"locality"
},
  "geometry": {"coordinates":[104.83134,34.75106],"type":"Point"}
}