{
  "type": "Feature",
  "properties": {
    "gn:admin1_code":"3.0",
    "gn:asciiname":"Guyuan",
    "gn:country_code":"CN",
    "gn:dem":170,
    "gn:feature_class":"P",
    "gn:feature_code":"PPL",
    "gn:name":"Guyuan",
    "gn:population":0,
    "gn:timezone":"Asia/Shanghai",
    "iso:country":"CN",
    "name:und_x_variant":[
        "\u56fa\u6e90"
    ],
    "wof:name":"Guyuan",
    "wof:placetype":"locality"
},
  "geometry": {"coordinates":[116.36908,27.42797],"type":"Point"}
}