{
  "type": "Feature",
  "properties": {
    "gn:admin1_code":"26",
    "gn:asciiname":"Shiquanpu",
    "gn:cc2":"CN",
    "gn:country_code":"CN",
    "gn:dem":324,
    "gn:feature_class":"P",
    "gn:feature_code":"PPL",
    "gn:name":"Shiquanpu",
    "gn:population":0,
    "gn:timezone":"Asia/Shanghai",
    "iso:country":"CN",
    "name:und_x_variant":[
        "Shih-ch\u2019\u00fcan-p\u2019u",
        "Shiquanpu"
    ],
    "wof:name":"Shiquanpu",
    "wof:placetype":"locality"
},
  "geometry": {"coordinates":[108.84389,32.57639],"type":"Point"}
}