{
  "type": "Feature",
  "properties": {
    "gn:admin1_code":"10",
    "gn:asciiname":"Yanghuangying",
    "gn:country_code":"CN",
    "gn:dem":40,
    "gn:feature_class":"P",
    "gn:feature_code":"PPL",
    "gn:name":"Yanghuangying",
    "gn:population":0,
    "gn:timezone":"Asia/Shanghai",
    "iso:country":"CN",
    "name:zho_x_preferred":[
        "\u6768\u9ec4\u8425"
    ],
    "wof:name":"Yanghuangying",
    "wof:placetype":"locality"
},
  "geometry": {"coordinates":[115.39728999999998,36.76581],"type":"Point"}
}