{
  "type": "Feature",
  "properties": {
    "gn:admin1_code":"26.0",
    "gn:asciiname":"Nianpanliang",
    "gn:country_code":"CN",
    "gn:dem":1753,
    "gn:feature_class":"P",
    "gn:feature_code":"PPL",
    "gn:name":"Nianpanliang",
    "gn:population":0,
    "gn:timezone":"Asia/Shanghai",
    "iso:country":"CN",
    "name:und_x_variant":[
        "\u78be\u76d8\u6881"
    ],
    "wof:name":"Nianpanliang",
    "wof:placetype":"locality"
},
  "geometry": {"coordinates":[108.08976,33.85743],"type":"Point"}
}