{
  "type": "Feature",
  "properties": {
    "gn:admin1_code":"30.0",
    "gn:asciiname":"Fengshancun",
    "gn:country_code":"CN",
    "gn:dem":12,
    "gn:feature_class":"P",
    "gn:feature_code":"PPL",
    "gn:name":"Fengshancun",
    "gn:population":0,
    "gn:timezone":"Asia/Shanghai",
    "iso:country":"CN",
    "name:zho_x_preferred":[
        "\u51e4\u5c71\u6751"
    ],
    "wof:name":"Fengshancun",
    "wof:placetype":"locality"
},
  "geometry": {"coordinates":[116.62896000000001,23.68609],"type":"Point"}
}