{
  "type": "Feature",
  "properties": {
    "gn:admin1_code":"16.0",
    "gn:asciiname":"Weizai",
    "gn:country_code":"CN",
    "gn:dem":709,
    "gn:feature_class":"P",
    "gn:feature_code":"PPL",
    "gn:name":"Weizai",
    "gn:population":0,
    "gn:timezone":"Asia/Shanghai",
    "iso:country":"CN",
    "name:zho_x_preferred":[
        "\u59d4\u54c9"
    ],
    "wof:name":"Weizai",
    "wof:placetype":"locality"
},
  "geometry": {"coordinates":[105.521,24.7464],"type":"Point"}
}