{
  "type": "Feature",
  "properties": {
    "gn:admin1_code":"10.0",
    "gn:asciiname":"Yanshanli",
    "gn:country_code":"CN",
    "gn:dem":17,
    "gn:feature_class":"P",
    "gn:feature_code":"PPL",
    "gn:name":"Yanshanli",
    "gn:population":0,
    "gn:timezone":"Asia/Shanghai",
    "iso:country":"CN",
    "name:zho_x_preferred":[
        "\u71d5\u5c71\u91cc"
    ],
    "wof:name":"Yanshanli",
    "wof:placetype":"locality"
},
  "geometry": {"coordinates":[119.60505999999999,39.95439],"type":"Point"}
}