{
  "type": "Feature",
  "properties": {
    "gn:admin1_code":"07",
    "gn:asciiname":"Tianbei",
    "gn:country_code":"CN",
    "gn:dem":205,
    "gn:feature_class":"P",
    "gn:feature_code":"PPL",
    "gn:name":"Tianbei",
    "gn:population":0,
    "gn:timezone":"Asia/Shanghai",
    "iso:country":"CN",
    "name:zho_x_preferred":[
        "\u7530\u80cc"
    ],
    "wof:name":"Tianbei",
    "wof:placetype":"locality"
},
  "geometry": {"coordinates":[116.72808000000001,24.75188],"type":"Point"}
}