{
  "type": "Feature",
  "properties": {
    "gn:admin1_code":"19.0",
    "gn:asciiname":"Qingtuozi",
    "gn:country_code":"CN",
    "gn:dem":4,
    "gn:feature_class":"P",
    "gn:feature_code":"PPL",
    "gn:name":"Qingtuozi",
    "gn:population":0,
    "gn:timezone":"Asia/Shanghai",
    "iso:country":"CN",
    "name:zho_x_preferred":[
        "\u9752\u5768\u5b50"
    ],
    "wof:name":"Qingtuozi",
    "wof:placetype":"locality"
},
  "geometry": {"coordinates":[121.376,40.969],"type":"Point"}
}