{
  "type": "Feature",
  "properties": {
    "gn:admin1_code":"24.0",
    "gn:asciiname":"Qujiayao",
    "gn:country_code":"CN",
    "gn:dem":1341,
    "gn:feature_class":"P",
    "gn:feature_code":"PPL",
    "gn:name":"Qujiayao",
    "gn:population":0,
    "gn:timezone":"Asia/Shanghai",
    "iso:country":"CN",
    "name:zho_x_preferred":[
        "\u5c48\u5bb6\u7a91"
    ],
    "wof:name":"Qujiayao",
    "wof:placetype":"locality"
},
  "geometry": {"coordinates":[113.85585,39.88686],"type":"Point"}
}