{
  "type": "Feature",
  "properties": {
    "gn:admin1_code":"24.0",
    "gn:asciiname":"Xuejiashan",
    "gn:country_code":"CN",
    "gn:dem":948,
    "gn:feature_class":"P",
    "gn:feature_code":"PPL",
    "gn:name":"Xuejiashan",
    "gn:population":0,
    "gn:timezone":"Asia/Shanghai",
    "iso:country":"CN",
    "name:zho_x_preferred":[
        "\u859b\u5bb6\u5c71"
    ],
    "wof:name":"Xuejiashan",
    "wof:placetype":"locality"
},
  "geometry": {"coordinates":[110.71441000000002,35.92543],"type":"Point"}
}