{
  "type": "Feature",
  "properties": {
    "gn:admin1_code":"10",
    "gn:asciiname":"Caogejie",
    "gn:country_code":"CN",
    "gn:dem":1369,
    "gn:feature_class":"P",
    "gn:feature_code":"PPL",
    "gn:name":"Caogejie",
    "gn:population":0,
    "gn:timezone":"Asia/Shanghai",
    "iso:country":"CN",
    "name:zho_x_preferred":[
        "\u8349\u572a\u8282"
    ],
    "wof:name":"Caogejie",
    "wof:placetype":"locality"
},
  "geometry": {"coordinates":[115.03182,41.55668],"type":"Point"}
}