{
  "type": "Feature",
  "properties": {
    "gn:admin1_code":"3.0",
    "gn:asciiname":"Shuijingkeng",
    "gn:country_code":"CN",
    "gn:dem":529,
    "gn:feature_class":"P",
    "gn:feature_code":"PPL",
    "gn:name":"Shuijingkeng",
    "gn:population":0,
    "gn:timezone":"Asia/Shanghai",
    "iso:country":"CN",
    "name:und_x_variant":[
        "\u6c34\u8346\u5751"
    ],
    "wof:name":"Shuijingkeng",
    "wof:placetype":"locality"
},
  "geometry": {"coordinates":[114.16185,28.84497],"type":"Point"}
}