{
  "type": "Feature",
  "properties": {
    "gn:admin1_code":"2",
    "gn:asciiname":"Meiyuan",
    "gn:country_code":"CN",
    "gn:dem":404,
    "gn:feature_class":"P",
    "gn:feature_code":"PPL",
    "gn:name":"Meiyuan",
    "gn:population":0,
    "gn:timezone":"Asia/Shanghai",
    "iso:country":"CN",
    "name:und_x_variant":[
        "\u7f8e\u6e90"
    ],
    "wof:name":"Meiyuan",
    "wof:placetype":"locality"
},
  "geometry": {"coordinates":[118.95332999999999,27.78694],"type":"Point"}
}