{
  "type": "Feature",
  "properties": {
    "gn:admin1_code":"04",
    "gn:asciiname":"Xianggangqiao",
    "gn:cc2":"CN",
    "gn:country_code":"CN",
    "gn:dem":6,
    "gn:feature_class":"P",
    "gn:feature_code":"PPL",
    "gn:name":"Xianggangqiao",
    "gn:population":0,
    "gn:timezone":"Asia/Shanghai",
    "iso:country":"CN",
    "name:und_x_variant":[
        "Pu-kang-ch\u2019iao",
        "Xianggangqiao"
    ],
    "wof:name":"Xianggangqiao",
    "wof:placetype":"locality"
},
  "geometry": {"coordinates":[120.9375,32.23305999999999],"type":"Point"}
}