{
  "type": "Feature",
  "properties": {
    "gn:admin1_code":"15.0",
    "gn:asciiname":"Dongmaitan",
    "gn:country_code":"CN",
    "gn:dem":2535,
    "gn:feature_class":"P",
    "gn:feature_code":"PPL",
    "gn:name":"Dongmaitan",
    "gn:population":0,
    "gn:timezone":"Asia/Shanghai",
    "iso:country":"CN",
    "name:und_x_variant":[
        "\u51ac\u9ea6\u6ee9"
    ],
    "wof:name":"Dongmaitan",
    "wof:placetype":"locality"
},
  "geometry": {"coordinates":[104.07798,34.44934],"type":"Point"}
}