{
  "type": "Feature",
  "properties": {
    "gn:admin1_code":"32.0",
    "gn:asciiname":"Qipan",
    "gn:country_code":"CN",
    "gn:dem":1163,
    "gn:feature_class":"P",
    "gn:feature_code":"PPL",
    "gn:name":"Qipan",
    "gn:population":0,
    "gn:timezone":"Asia/Shanghai",
    "iso:country":"CN",
    "name:zho_x_preferred":[
        "\u4e03\u76d8"
    ],
    "wof:name":"Qipan",
    "wof:placetype":"locality"
},
  "geometry": {"coordinates":[102.979,30.0476],"type":"Point"}
}