{
  "type": "Feature",
  "properties": {
    "gn:admin1_code":"24.0",
    "gn:asciiname":"Guojiagetai",
    "gn:country_code":"CN",
    "gn:dem":1107,
    "gn:feature_class":"P",
    "gn:feature_code":"PPL",
    "gn:name":"Guojiagetai",
    "gn:population":0,
    "gn:timezone":"Asia/Shanghai",
    "iso:country":"CN",
    "name:zho_x_preferred":[
        "\u90ed\u5bb6\u572a\u53f0"
    ],
    "wof:name":"Guojiagetai",
    "wof:placetype":"locality"
},
  "geometry": {"coordinates":[111.17981,38.41016],"type":"Point"}
}