{
  "type": "Feature",
  "properties": {
    "gn:admin1_code":"33.0",
    "gn:asciiname":"Jinzi",
    "gn:country_code":"CN",
    "gn:dem":690,
    "gn:feature_class":"P",
    "gn:feature_code":"PPL",
    "gn:name":"Jinzi",
    "gn:population":0,
    "gn:timezone":"Asia/Shanghai",
    "iso:country":"CN",
    "name:zho_x_preferred":[
        "\u91d1\u5b50"
    ],
    "wof:name":"Jinzi",
    "wof:placetype":"locality"
},
  "geometry": {"coordinates":[107.83917,29.2171],"type":"Point"}
}