{
  "type": "Feature",
  "properties": {
    "gn:admin1_code":"8.0",
    "gn:asciiname":"Zhengyicun",
    "gn:country_code":"CN",
    "gn:dem":284,
    "gn:feature_class":"P",
    "gn:feature_code":"PPL",
    "gn:name":"Zhengyicun",
    "gn:population":0,
    "gn:timezone":"Asia/Shanghai",
    "iso:country":"CN",
    "name:zho_x_preferred":[
        "\u6b63\u4e49\u6751"
    ],
    "wof:name":"Zhengyicun",
    "wof:placetype":"locality"
},
  "geometry": {"coordinates":[126.2098,47.37081],"type":"Point"}
}