{
  "type": "Feature",
  "properties": {
    "gn:admin1_code":"9.0",
    "gn:asciiname":"Jincun",
    "gn:country_code":"CN",
    "gn:dem":68,
    "gn:feature_class":"P",
    "gn:feature_code":"PPL",
    "gn:name":"Jincun",
    "gn:population":0,
    "gn:timezone":"Asia/Shanghai",
    "iso:country":"CN",
    "name:zho_x_preferred":[
        "\u9773\u6751"
    ],
    "wof:name":"Jincun",
    "wof:placetype":"locality"
},
  "geometry": {"coordinates":[114.23247000000001,34.24802],"type":"Point"}
}