{
  "type": "Feature",
  "properties": {
    "gn:admin1_code":"29.0",
    "gn:asciiname":"Tangzishan",
    "gn:country_code":"CN",
    "gn:dem":1963,
    "gn:feature_class":"P",
    "gn:feature_code":"PPL",
    "gn:name":"Tangzishan",
    "gn:population":0,
    "gn:timezone":"Asia/Shanghai",
    "iso:country":"CN",
    "name:zho_x_preferred":[
        "\u5858\u5b50\u5c71"
    ],
    "wof:name":"Tangzishan",
    "wof:placetype":"locality"
},
  "geometry": {"coordinates":[100.776,25.4652],"type":"Point"}
}