{
  "type": "Feature",
  "properties": {
    "gn:admin1_code":"25.0",
    "gn:asciiname":"Beijiazhuangcun",
    "gn:country_code":"CN",
    "gn:dem":48,
    "gn:feature_class":"P",
    "gn:feature_code":"PPL",
    "gn:name":"Beijiazhuangcun",
    "gn:population":0,
    "gn:timezone":"Asia/Shanghai",
    "iso:country":"CN",
    "name:zho_x_preferred":[
        "\u5317\u7532\u5e84\u6751"
    ],
    "wof:name":"Beijiazhuangcun",
    "wof:placetype":"locality"
},
  "geometry": {"coordinates":[119.49267,36.40575],"type":"Point"}
}