{
  "type": "Feature",
  "properties": {
    "gn:admin1_code":"3",
    "gn:asciiname":"Neidong",
    "gn:country_code":"CN",
    "gn:dem":473,
    "gn:feature_class":"P",
    "gn:feature_code":"PPL",
    "gn:name":"Neidong",
    "gn:population":0,
    "gn:timezone":"Asia/Shanghai",
    "iso:country":"CN",
    "name:zho_x_preferred":[
        "\u5185\u6d1e"
    ],
    "wof:name":"Neidong",
    "wof:placetype":"locality"
},
  "geometry": {"coordinates":[114.10599999999999,25.3173],"type":"Point"}
}