{
  "type": "Feature",
  "properties": {
    "gn:admin1_code":"32.0",
    "gn:asciiname":"Fengtongpo",
    "gn:country_code":"CN",
    "gn:dem":320,
    "gn:feature_class":"P",
    "gn:feature_code":"PPL",
    "gn:name":"Fengtongpo",
    "gn:population":0,
    "gn:timezone":"Asia/Shanghai",
    "iso:country":"CN",
    "name:zho_x_preferred":[
        "\u98ce\u6850\u5761"
    ],
    "wof:name":"Fengtongpo",
    "wof:placetype":"locality"
},
  "geometry": {"coordinates":[105.3415,30.6181],"type":"Point"}
}