{
  "type": "Feature",
  "properties": {
    "gn:admin1_code":"3.0",
    "gn:asciiname":"Liaodi",
    "gn:country_code":"CN",
    "gn:dem":153,
    "gn:feature_class":"P",
    "gn:feature_code":"PPL",
    "gn:name":"Liaodi",
    "gn:population":0,
    "gn:timezone":"Asia/Shanghai",
    "iso:country":"CN",
    "name:und_x_variant":[
        "\u5ed6\u5730"
    ],
    "wof:name":"Liaodi",
    "wof:placetype":"locality"
},
  "geometry": {"coordinates":[115.57821,26.87318],"type":"Point"}
}