{
  "type": "Feature",
  "properties": {
    "gn:admin1_code":"32.0",
    "gn:asciiname":"Sula",
    "gn:country_code":"CN",
    "gn:dem":3492,
    "gn:feature_class":"P",
    "gn:feature_code":"PPL",
    "gn:name":"Sula",
    "gn:population":0,
    "gn:timezone":"Asia/Shanghai",
    "iso:country":"CN",
    "name:zho_x_preferred":[
        "\u82cf\u62c9"
    ],
    "wof:name":"Sula",
    "wof:placetype":"locality"
},
  "geometry": {"coordinates":[100.21299999999999,30.6409],"type":"Point"}
}