{
  "type": "Feature",
  "properties": {
    "gn:admin1_code":"18",
    "gn:asciiname":"Shuimu Xinzhai",
    "gn:country_code":"CN",
    "gn:dem":1230,
    "gn:feature_class":"P",
    "gn:feature_code":"PPL",
    "gn:name":"Shuimu Xinzhai",
    "gn:population":0,
    "gn:timezone":"Asia/Shanghai",
    "iso:country":"CN",
    "name:zho_x_preferred":[
        "\u6c34\u6bcd\u65b0\u5be8"
    ],
    "wof:name":"Shuimu Xinzhai",
    "wof:placetype":"locality"
},
  "geometry": {"coordinates":[105.63800000000001,26.2673],"type":"Point"}
}