{
  "type": "Feature",
  "properties": {
    "gn:admin1_code":"21.0",
    "gn:asciiname":"Licangjia",
    "gn:country_code":"CN",
    "gn:dem":1877,
    "gn:feature_class":"P",
    "gn:feature_code":"PPL",
    "gn:name":"Licangjia",
    "gn:population":0,
    "gn:timezone":"Asia/Shanghai",
    "iso:country":"CN",
    "name:und_x_variant":[
        "\u674e\u4ed3\u5bb6"
    ],
    "name:zho_x_preferred":[
        "\u674e\u4ed3\u5bb6"
    ],
    "wof:name":"Licangjia",
    "wof:placetype":"locality"
},
  "geometry": {"coordinates":[105.65966,35.78429000000001],"type":"Point"}
}