{
  "type": "Feature",
  "properties": {
    "gn:admin1_code":"10.0",
    "gn:asciiname":"Baimiao",
    "gn:country_code":"CN",
    "gn:dem":102,
    "gn:feature_class":"P",
    "gn:feature_code":"PPL",
    "gn:name":"Baimiao",
    "gn:population":0,
    "gn:timezone":"Asia/Shanghai",
    "iso:country":"CN",
    "name:und_x_variant":[
        "\u767d\u5e99"
    ],
    "wof:name":"Baimiao",
    "wof:placetype":"locality"
},
  "geometry": {"coordinates":[114.55453,38.42002],"type":"Point"}
}