{
  "type": "Feature",
  "properties": {
    "gn:admin1_code":"1.0",
    "gn:asciiname":"Qianjiacun",
    "gn:country_code":"CN",
    "gn:dem":23,
    "gn:feature_class":"P",
    "gn:feature_code":"PPL",
    "gn:name":"Qianjiacun",
    "gn:population":0,
    "gn:timezone":"Asia/Shanghai",
    "iso:country":"CN",
    "name:zho_x_preferred":[
        "\u524d\u5bb6\u6751"
    ],
    "wof:name":"Qianjiacun",
    "wof:placetype":"locality"
},
  "geometry": {"coordinates":[116.79215000000001,32.75031],"type":"Point"}
}