{
  "type": "Feature",
  "properties": {
    "gn:admin1_code":"9.0",
    "gn:asciiname":"Qiaoshangcun",
    "gn:country_code":"CN",
    "gn:dem":759,
    "gn:feature_class":"P",
    "gn:feature_code":"PPL",
    "gn:name":"Qiaoshangcun",
    "gn:population":0,
    "gn:timezone":"Asia/Shanghai",
    "iso:country":"CN",
    "name:zho_x_preferred":[
        "\u6865\u4e0a\u6751"
    ],
    "wof:name":"Qiaoshangcun",
    "wof:placetype":"locality"
},
  "geometry": {"coordinates":[111.45909,34.52805],"type":"Point"}
}