{
  "type": "Feature",
  "properties": {
    "gn:admin1_code":"4.0",
    "gn:asciiname":"Xiajia Xuzi",
    "gn:country_code":"CN",
    "gn:dem":7,
    "gn:feature_class":"P",
    "gn:feature_code":"PPL",
    "gn:name":"Xiajia Xuzi",
    "gn:population":0,
    "gn:timezone":"Asia/Shanghai",
    "iso:country":"CN",
    "name:zho_x_preferred":[
        "\u590f\u5bb6\u5729\u5b50"
    ],
    "wof:name":"Xiajia Xuzi",
    "wof:placetype":"locality"
},
  "geometry": {"coordinates":[119.49244,31.39874],"type":"Point"}
}