{
  "type": "Feature",
  "properties": {
    "gn:admin1_code":"29.0",
    "gn:asciiname":"Huatan",
    "gn:country_code":"CN",
    "gn:dem":777,
    "gn:feature_class":"P",
    "gn:feature_code":"PPL",
    "gn:name":"Huatan",
    "gn:population":0,
    "gn:timezone":"Asia/Shanghai",
    "iso:country":"CN",
    "name:und_x_variant":[
        "\u82b1\u575b"
    ],
    "wof:name":"Huatan",
    "wof:placetype":"locality"
},
  "geometry": {"coordinates":[104.24562,28.48887],"type":"Point"}
}