{
  "type": "Feature",
  "properties": {
    "gn:admin1_code":"29.0",
    "gn:asciiname":"Huatan",
    "gn:country_code":"CN",
    "gn:dem":777,
    "gn:feature_class":"P",
    "gn:feature_code":"PPL",
    "gn:name":"Huatan",
    "gn:population":0,
    "gn:timezone":"Asia/Shanghai",
    "iso:country":"CN",
    "name:hak_x_preferred":[
        "F\u00e2-th\u00e0n-hi\u00f4ng"
    ],
    "name:ita_x_preferred":[
        "Huatan"
    ],
    "name:jpn_x_preferred":[
        "\u82b1\u58c7\u90f7"
    ],
    "name:kor_x_preferred":[
        "\ud654\ud0c4\ud5a5"
    ],
    "name:pol_x_preferred":[
        "Huatan"
    ],
    "name:und_x_variant":[
        "\u82b1\u575b"
    ],
    "name:vie_x_preferred":[
        "Hoa \u0110\u00e0n"
    ],
    "name:zho_x_preferred":[
        "\u82b1\u58c7\u9109"
    ],
    "wof:name":"Huatan",
    "wof:placetype":"locality"
},
  "geometry": {"coordinates":[104.24562,28.48887],"type":"Point"}
}