{
  "type": "Feature",
  "properties": {
    "gn:admin1_code":"10",
    "gn:asciiname":"Shiwuhao",
    "gn:country_code":"CN",
    "gn:dem":1126,
    "gn:feature_class":"P",
    "gn:feature_code":"PPLF",
    "gn:name":"Shiwuhao",
    "gn:population":0,
    "gn:timezone":"Asia/Shanghai",
    "iso:country":"CN",
    "name:und_x_variant":[
        "Shih-wu-hao",
        "Shiwuhao"
    ],
    "name:zho_x_preferred":[
        "\u5341\u4e94\u53f7"
    ],
    "wof:name":"Shiwuhao",
    "wof:placetype":"locality"
},
  "geometry": {"coordinates":[117.68577000000001,42.17547],"type":"Point"}
}