{
  "type": "Feature",
  "properties": {
    "gn:admin1_code":"32.0",
    "gn:asciiname":"Tangzu",
    "gn:country_code":"CN",
    "gn:dem":3320,
    "gn:feature_class":"P",
    "gn:feature_code":"PPL",
    "gn:name":"Tangzu",
    "gn:population":0,
    "gn:timezone":"Asia/Shanghai",
    "iso:country":"CN",
    "name:zho_x_preferred":[
        "\u5510\u8db3"
    ],
    "wof:name":"Tangzu",
    "wof:placetype":"locality"
},
  "geometry": {"coordinates":[101.05500000000001,29.9013],"type":"Point"}
}