{
  "type": "Feature",
  "properties": {
    "gn:admin1_code":"15.0",
    "gn:asciiname":"Zhangjialing",
    "gn:country_code":"CN",
    "gn:dem":2864,
    "gn:feature_class":"P",
    "gn:feature_code":"PPL",
    "gn:name":"Zhangjialing",
    "gn:population":0,
    "gn:timezone":"Asia/Shanghai",
    "iso:country":"CN",
    "name:zho_x_preferred":[
        "\u5f20\u5bb6\u5cad"
    ],
    "wof:name":"Zhangjialing",
    "wof:placetype":"locality"
},
  "geometry": {"coordinates":[103.73699999999999,37.1093],"type":"Point"}
}