{
  "type": "Feature",
  "properties": {
    "gn:admin1_code":"14.0",
    "gn:asciiname":"Sange",
    "gn:country_code":"CN",
    "gn:dem":3617,
    "gn:feature_class":"P",
    "gn:feature_code":"PPL",
    "gn:name":"Sange",
    "gn:population":0,
    "gn:timezone":"Asia/Urumqi",
    "iso:country":"CN",
    "name:ceb_x_preferred":[
        "Sange"
    ],
    "name:deu_x_preferred":[
        "Sange"
    ],
    "name:fra_x_preferred":[
        "Sange"
    ],
    "name:swe_x_preferred":[
        "Sange"
    ],
    "name:zho_x_preferred":[
        "\u6851\u989d"
    ],
    "wof:name":"Sange",
    "wof:placetype":"locality"
},
  "geometry": {"coordinates":[93.452,30.0627],"type":"Point"}
}