{
  "type": "Feature",
  "properties": {
    "gn:admin1_code":"7",
    "gn:asciiname":"Nan Zhaixia",
    "gn:cc2":"CN",
    "gn:country_code":"CN",
    "gn:dem":12,
    "gn:feature_class":"P",
    "gn:feature_code":"PPL",
    "gn:name":"Nan Zhaixia",
    "gn:population":0,
    "gn:timezone":"Asia/Shanghai",
    "iso:country":"CN",
    "name:und_x_variant":[
        "Zhaixia",
        "Chai-hsia",
        "Nan Zhaixia"
    ],
    "wof:name":"Nan Zhaixia",
    "wof:placetype":"locality"
},
  "geometry": {"coordinates":[119.6075,25.77833],"type":"Point"}
}