{
  "type": "Feature",
  "properties": {
    "gn:admin1_code":"14.0",
    "gn:asciiname":"Zhagulu",
    "gn:country_code":"CN",
    "gn:dem":3268,
    "gn:feature_class":"P",
    "gn:feature_code":"PPL",
    "gn:name":"Zhagulu",
    "gn:population":0,
    "gn:timezone":"Asia/Urumqi",
    "iso:country":"CN",
    "name:zho_x_preferred":[
        "\u624e\u53e4\u9c81"
    ],
    "wof:name":"Zhagulu",
    "wof:placetype":"locality"
},
  "geometry": {"coordinates":[95.57753,29.84726],"type":"Point"}
}