{
  "type": "Feature",
  "properties": {
    "gn:admin1_code":"16.0",
    "gn:asciiname":"Baimie",
    "gn:country_code":"CN",
    "gn:dem":717,
    "gn:feature_class":"P",
    "gn:feature_code":"PPL",
    "gn:name":"Baimie",
    "gn:population":0,
    "gn:timezone":"Asia/Shanghai",
    "iso:country":"CN",
    "name:zho_x_preferred":[
        "\u767d\u8511"
    ],
    "wof:name":"Baimie",
    "wof:placetype":"locality"
},
  "geometry": {"coordinates":[110.89100000000001,24.3314],"type":"Point"}
}