{
  "type": "Feature",
  "properties": {
    "gn:admin1_code":"24.0",
    "gn:asciiname":"Douzhuang",
    "gn:country_code":"CN",
    "gn:dem":1033,
    "gn:feature_class":"P",
    "gn:feature_code":"PPL",
    "gn:name":"Douzhuang",
    "gn:population":0,
    "gn:timezone":"Asia/Shanghai",
    "iso:country":"CN",
    "name:und_x_variant":[
        "\u8c46\u5e84"
    ],
    "wof:name":"Douzhuang",
    "wof:placetype":"locality"
},
  "geometry": {"coordinates":[112.74784,39.35678],"type":"Point"}
}