{
  "type": "Feature",
  "properties": {
    "gn:admin1_code":"9.0",
    "gn:asciiname":"Baimiaohuang",
    "gn:country_code":"CN",
    "gn:dem":81,
    "gn:feature_class":"P",
    "gn:feature_code":"PPL",
    "gn:name":"Baimiaohuang",
    "gn:population":0,
    "gn:timezone":"Asia/Shanghai",
    "iso:country":"CN",
    "name:und_x_variant":[
        "\u767d\u5e99\u9ec4"
    ],
    "name:zho_x_preferred":[
        "\u767d\u5e99\u9ec4"
    ],
    "wof:name":"Baimiaohuang",
    "wof:placetype":"locality"
},
  "geometry": {"coordinates":[113.72132000000001,33.89146],"type":"Point"}
}