{
  "type": "Feature",
  "properties": {
    "gn:admin1_code":"7.0",
    "gn:asciiname":"Jiaolong",
    "gn:country_code":"CN",
    "gn:dem":207,
    "gn:feature_class":"P",
    "gn:feature_code":"PPL",
    "gn:name":"Jiaolong",
    "gn:population":0,
    "gn:timezone":"Asia/Shanghai",
    "iso:country":"CN",
    "name:msa_x_preferred":[
        "Jiaolong"
    ],
    "name:pol_x_preferred":[
        "Jiaolong"
    ],
    "name:vie_x_preferred":[
        "Thu\u1ed3ng lu\u1ed3ng"
    ],
    "name:zho_x_preferred":[
        "\u89d2\u9f99"
    ],
    "wof:name":"Jiaolong",
    "wof:placetype":"locality"
},
  "geometry": {"coordinates":[116.43046,25.15651],"type":"Point"}
}