{
  "type": "Feature",
  "properties": {
    "gn:admin1_code":"30.0",
    "gn:asciiname":"Shijiaotou",
    "gn:country_code":"CN",
    "gn:dem":27,
    "gn:feature_class":"P",
    "gn:feature_code":"PPL",
    "gn:name":"Shijiaotou",
    "gn:population":0,
    "gn:timezone":"Asia/Shanghai",
    "iso:country":"CN",
    "name:zho_x_preferred":[
        "\u77f3\u89d2\u5934"
    ],
    "wof:name":"Shijiaotou",
    "wof:placetype":"locality"
},
  "geometry": {"coordinates":[114.77007999999999,22.81732],"type":"Point"}
}