{
  "type": "Feature",
  "properties": {
    "gn:admin1_code":"4.0",
    "gn:asciiname":"Shudun",
    "gn:country_code":"CN",
    "gn:dem":3,
    "gn:feature_class":"P",
    "gn:feature_code":"PPL",
    "gn:name":"Shudun",
    "gn:population":0,
    "gn:timezone":"Asia/Shanghai",
    "iso:country":"CN",
    "name:und_x_variant":[
        "\u587e\u58a9"
    ],
    "name:zho_x_preferred":[
        "\u587e\u58a9"
    ],
    "wof:name":"Shudun",
    "wof:placetype":"locality"
},
  "geometry": {"coordinates":[120.11851,32.83501],"type":"Point"}
}