{
  "type": "Feature",
  "properties": {
    "gn:admin1_code":"2.0",
    "gn:asciiname":"Wailinshan",
    "gn:country_code":"CN",
    "gn:dem":452,
    "gn:feature_class":"P",
    "gn:feature_code":"PPL",
    "gn:name":"Wailinshan",
    "gn:population":0,
    "gn:timezone":"Asia/Shanghai",
    "iso:country":"CN",
    "name:zho_x_preferred":[
        "\u5916\u6797\u5c71"
    ],
    "wof:name":"Wailinshan",
    "wof:placetype":"locality"
},
  "geometry": {"coordinates":[120.63997000000001,29.0022],"type":"Point"}
}