{
  "type": "Feature",
  "properties": {
    "gn:admin1_code":"12.0",
    "gn:asciiname":"Chadianzi",
    "gn:country_code":"CN",
    "gn:dem":42,
    "gn:feature_class":"P",
    "gn:feature_code":"PPL",
    "gn:name":"Chadianzi",
    "gn:population":0,
    "gn:timezone":"Asia/Shanghai",
    "iso:country":"CN",
    "name:zho_x_preferred":[
        "Chadianzi"
    ],
    "name:zho_x_variant":[
        "\u8336\u5e97\u5b50"
    ],
    "wof:name":"Chadianzi",
    "wof:placetype":"locality"
},
  "geometry": {"coordinates":[111.42668,30.41017],"type":"Point"}
}