{
  "type": "Feature",
  "properties": {
    "gn:admin1_code":"18.0",
    "gn:asciiname":"Dijiasi",
    "gn:country_code":"CN",
    "gn:dem":715,
    "gn:feature_class":"P",
    "gn:feature_code":"PPL",
    "gn:name":"Dijiasi",
    "gn:population":0,
    "gn:timezone":"Asia/Shanghai",
    "iso:country":"CN",
    "name:zho_x_preferred":[
        "\u5730\u7532\u53f8"
    ],
    "wof:name":"Dijiasi",
    "wof:placetype":"locality"
},
  "geometry": {"coordinates":[109.244,28.1047],"type":"Point"}
}