{
  "type": "Feature",
  "properties": {
    "gn:admin1_code":"30.0",
    "gn:asciiname":"Jilongcun",
    "gn:country_code":"CN",
    "gn:dem":8,
    "gn:feature_class":"P",
    "gn:feature_code":"PPL",
    "gn:name":"Jilongcun",
    "gn:population":0,
    "gn:timezone":"Asia/Shanghai",
    "iso:country":"CN",
    "name:zho_x_preferred":[
        "\u5bc4\u9647\u6751"
    ],
    "wof:name":"Jilongcun",
    "wof:placetype":"locality"
},
  "geometry": {"coordinates":[116.26826,23.01732],"type":"Point"}
}