{
  "type": "Feature",
  "properties": {
    "gn:admin1_code":"3.0",
    "gn:asciiname":"Fengshuguo",
    "gn:country_code":"CN",
    "gn:dem":553,
    "gn:feature_class":"P",
    "gn:feature_code":"PPL",
    "gn:name":"Fengshuguo",
    "gn:population":0,
    "gn:timezone":"Asia/Shanghai",
    "iso:country":"CN",
    "name:und_x_variant":[
        "\u67ab\u6811\u57da"
    ],
    "wof:name":"Fengshuguo",
    "wof:placetype":"locality"
},
  "geometry": {"coordinates":[115.10146,26.16813],"type":"Point"}
}