{
  "type": "Feature",
  "properties": {
    "gn:admin1_code":"30",
    "gn:asciiname":"Xiazhongshe",
    "gn:country_code":"CN",
    "gn:dem":240,
    "gn:feature_class":"P",
    "gn:feature_code":"PPL",
    "gn:name":"Xiazhongshe",
    "gn:population":0,
    "gn:timezone":"Asia/Shanghai",
    "iso:country":"CN",
    "name:zho_x_preferred":[
        "\u4e0b\u4e2d\u8f0b"
    ],
    "wof:name":"Xiazhongshe",
    "wof:placetype":"locality"
},
  "geometry": {"coordinates":[115.57980000000001,24.21629],"type":"Point"}
}