{
  "type": "Feature",
  "properties": {
    "gn:admin1_code":"5.0",
    "gn:asciiname":"Jumintun",
    "gn:country_code":"CN",
    "gn:dem":154,
    "gn:feature_class":"P",
    "gn:feature_code":"PPL",
    "gn:name":"Jumintun",
    "gn:population":0,
    "gn:timezone":"Asia/Shanghai",
    "iso:country":"CN",
    "name:zho_x_preferred":[
        "\u5c45\u6c11\u5c6f"
    ],
    "wof:name":"Jumintun",
    "wof:placetype":"locality"
},
  "geometry": {"coordinates":[123.49151000000001,44.19469],"type":"Point"}
}