{
  "type": "Feature",
  "properties": {
    "gn:admin1_code":"30.0",
    "gn:asciiname":"Ling'an",
    "gn:country_code":"CN",
    "gn:dem":13,
    "gn:feature_class":"P",
    "gn:feature_code":"PPL",
    "gn:name":"Ling\u2019an",
    "gn:population":0,
    "gn:timezone":"Asia/Shanghai",
    "iso:country":"CN",
    "name:und_x_variant":[
        "Ling\u2019an"
    ],
    "name:zho_x_preferred":[
        "\u5dba\u5b89"
    ],
    "wof:name":"Ling'an",
    "wof:placetype":"locality"
},
  "geometry": {"coordinates":[112.73065,22.16225],"type":"Point"}
}