{
  "type": "Feature",
  "properties": {
    "gn:admin1_code":"16.0",
    "gn:asciiname":"Qinghegen",
    "gn:country_code":"CN",
    "gn:dem":45,
    "gn:feature_class":"P",
    "gn:feature_code":"PPL",
    "gn:name":"Qinghegen",
    "gn:population":0,
    "gn:timezone":"Asia/Shanghai",
    "iso:country":"CN",
    "name:zho_x_preferred":[
        "\u9752\u6cb3\u6839"
    ],
    "wof:name":"Qinghegen",
    "wof:placetype":"locality"
},
  "geometry": {"coordinates":[110.187,21.9245],"type":"Point"}
}