{
  "type": "Feature",
  "properties": {
    "gn:admin1_code":"3.0",
    "gn:asciiname":"Fengjingli",
    "gn:country_code":"CN",
    "gn:dem":209,
    "gn:feature_class":"P",
    "gn:feature_code":"PPL",
    "gn:name":"Fengjingli",
    "gn:population":0,
    "gn:timezone":"Asia/Shanghai",
    "iso:country":"CN",
    "name:und_x_variant":[
        "\u51e4\u9888\u91cc"
    ],
    "wof:name":"Fengjingli",
    "wof:placetype":"locality"
},
  "geometry": {"coordinates":[114.45358,28.36352],"type":"Point"}
}