{
  "type": "Feature",
  "properties": {
    "gn:admin1_code":"8.0",
    "gn:asciiname":"Shuangchengcun",
    "gn:country_code":"CN",
    "gn:dem":137,
    "gn:feature_class":"P",
    "gn:feature_code":"PPL",
    "gn:name":"Shuangchengcun",
    "gn:population":0,
    "gn:timezone":"Asia/Shanghai",
    "iso:country":"CN",
    "name:zho_x_preferred":[
        "\u53cc\u57ce\u6751"
    ],
    "wof:name":"Shuangchengcun",
    "wof:placetype":"locality"
},
  "geometry": {"coordinates":[126.59135000000001,46.30236],"type":"Point"}
}