{
  "type": "Feature",
  "properties": {
    "gn:admin1_code":"15.0",
    "gn:asciiname":"Tangbugou",
    "gn:country_code":"CN",
    "gn:dem":1986,
    "gn:feature_class":"P",
    "gn:feature_code":"PPL",
    "gn:name":"Tangbugou",
    "gn:population":0,
    "gn:timezone":"Asia/Shanghai",
    "iso:country":"CN",
    "name:und_x_variant":[
        "\u6c64\u535c\u6c9f"
    ],
    "name:zho_x_preferred":[
        "\u6c64\u535c\u6c9f"
    ],
    "wof:name":"Tangbugou",
    "wof:placetype":"locality"
},
  "geometry": {"coordinates":[104.51504,33.0401],"type":"Point"}
}