{
  "type": "Feature",
  "properties": {
    "gn:admin1_code":"11.0",
    "gn:asciiname":"Pingyang Wujia",
    "gn:country_code":"CN",
    "gn:dem":127,
    "gn:feature_class":"P",
    "gn:feature_code":"PPL",
    "gn:name":"Pingyang Wujia",
    "gn:population":0,
    "gn:timezone":"Asia/Shanghai",
    "iso:country":"CN",
    "name:zho_x_preferred":[
        "\u5e73\u9633\u4f0d\u5bb6"
    ],
    "wof:name":"Pingyang Wujia",
    "wof:placetype":"locality"
},
  "geometry": {"coordinates":[111.61228,26.57835],"type":"Point"}
}