{
  "type": "Feature",
  "properties": {
    "gn:admin1_code":"30.0",
    "gn:asciiname":"Yuchakeng",
    "gn:country_code":"CN",
    "gn:dem":737,
    "gn:feature_class":"P",
    "gn:feature_code":"PPL",
    "gn:name":"Yuchakeng",
    "gn:population":0,
    "gn:timezone":"Asia/Shanghai",
    "iso:country":"CN",
    "name:zho_x_preferred":[
        "Yuchakeng"
    ],
    "name:zho_x_variant":[
        "\u9c7c\u5c94\u5751"
    ],
    "wof:name":"Yuchakeng",
    "wof:placetype":"locality"
},
  "geometry": {"coordinates":[112.23806,24.8075],"type":"Point"}
}