{
  "type": "Feature",
  "properties": {
    "gn:admin1_code":"11.0",
    "gn:asciiname":"Lixianchong",
    "gn:country_code":"CN",
    "gn:dem":59,
    "gn:feature_class":"P",
    "gn:feature_code":"PPL",
    "gn:name":"Lixianchong",
    "gn:population":0,
    "gn:timezone":"Asia/Shanghai",
    "iso:country":"CN",
    "name:zho_x_preferred":[
        "\u674e\u5148\u51b2"
    ],
    "wof:name":"Lixianchong",
    "wof:placetype":"locality"
},
  "geometry": {"coordinates":[113.28708,29.23584],"type":"Point"}
}