{
  "type": "Feature",
  "properties": {
    "gn:admin1_code":"19.0",
    "gn:asciiname":"Qianyu",
    "gn:country_code":"CN",
    "gn:dem":106,
    "gn:feature_class":"P",
    "gn:feature_code":"PPL",
    "gn:name":"Qianyu",
    "gn:population":0,
    "gn:timezone":"Asia/Shanghai",
    "iso:country":"CN",
    "name:und_x_variant":[
        "\u524d\u5cea"
    ],
    "name:zho_x_preferred":[
        "\u524d\u5cea"
    ],
    "wof:name":"Qianyu",
    "wof:placetype":"locality"
},
  "geometry": {"coordinates":[123.51664,42.37761],"type":"Point"}
}