{
  "type": "Feature",
  "properties": {
    "gn:admin1_code":"32.0",
    "gn:asciiname":"Ci'en",
    "gn:country_code":"CN",
    "gn:dem":741,
    "gn:feature_class":"P",
    "gn:feature_code":"PPL",
    "gn:name":"Ci\u2019en",
    "gn:population":0,
    "gn:timezone":"Asia/Shanghai",
    "iso:country":"CN",
    "name:und_x_variant":[
        "Ci\u2019en"
    ],
    "name:zho_x_preferred":[
        "\u6148\u6069"
    ],
    "wof:name":"Ci'en",
    "wof:placetype":"locality"
},
  "geometry": {"coordinates":[105.486,31.795],"type":"Point"}
}