{
  "type": "Feature",
  "properties": {
    "gn:admin1_code":"8.0",
    "gn:asciiname":"Donglongzhen",
    "gn:country_code":"CN",
    "gn:dem":337,
    "gn:feature_class":"P",
    "gn:feature_code":"PPL",
    "gn:name":"Donglongzhen",
    "gn:population":0,
    "gn:timezone":"Asia/Shanghai",
    "iso:country":"CN",
    "name:zho_x_preferred":[
        "\u4e1c\u9f99\u9547"
    ],
    "wof:name":"Donglongzhen",
    "wof:placetype":"locality"
},
  "geometry": {"coordinates":[126.83172999999999,48.7127],"type":"Point"}
}