{
  "type": "Feature",
  "properties": {
    "gn:admin1_code":"18.0",
    "gn:asciiname":"Shangtangjialong",
    "gn:country_code":"CN",
    "gn:dem":661,
    "gn:feature_class":"P",
    "gn:feature_code":"PPL",
    "gn:name":"Shangtangjialong",
    "gn:population":0,
    "gn:timezone":"Asia/Shanghai",
    "iso:country":"CN",
    "name:zho_x_preferred":[
        "\u4e0a\u5858\u5bb6\u9f99"
    ],
    "wof:name":"Shangtangjialong",
    "wof:placetype":"locality"
},
  "geometry": {"coordinates":[108.795,27.3613],"type":"Point"}
}