{
  "type": "Feature",
  "properties": {
    "gn:admin1_code":"29.0",
    "gn:asciiname":"Yakou",
    "gn:country_code":"CN",
    "gn:dem":1505,
    "gn:feature_class":"P",
    "gn:feature_code":"PPL",
    "gn:name":"Yakou",
    "gn:population":0,
    "gn:timezone":"Asia/Shanghai",
    "iso:country":"CN",
    "name:zho_x_preferred":[
        "\u4e2b\u53e3"
    ],
    "wof:name":"Yakou",
    "wof:placetype":"locality"
},
  "geometry": {"coordinates":[100.48099999999999,24.4693],"type":"Point"}
}