{
  "type": "Feature",
  "properties": {
    "gn:admin1_code":"12.0",
    "gn:asciiname":"Xialiujiatai",
    "gn:country_code":"CN",
    "gn:dem":39,
    "gn:feature_class":"P",
    "gn:feature_code":"PPL",
    "gn:name":"Xialiujiatai",
    "gn:population":0,
    "gn:timezone":"Asia/Shanghai",
    "iso:country":"CN",
    "name:zho_x_preferred":[
        "\u590f\u5218\u5bb6\u53f0"
    ],
    "wof:name":"Xialiujiatai",
    "wof:placetype":"locality"
},
  "geometry": {"coordinates":[112.06744999999999,30.20271],"type":"Point"}
}