{
  "type": "Feature",
  "properties": {
    "gn:admin1_code":"18",
    "gn:asciiname":"Ertaipo",
    "gn:country_code":"CN",
    "gn:dem":1388,
    "gn:feature_class":"P",
    "gn:feature_code":"PPL",
    "gn:name":"Ertaipo",
    "gn:population":0,
    "gn:timezone":"Asia/Shanghai",
    "iso:country":"CN",
    "name:zho_x_preferred":[
        "\u4e8c\u53f0\u5761"
    ],
    "wof:name":"Ertaipo",
    "wof:placetype":"locality"
},
  "geometry": {"coordinates":[105.40300000000001,26.3771],"type":"Point"}
}