{
  "type": "Feature",
  "properties": {
    "gn:admin1_code":"18",
    "gn:asciiname":"Naizishan",
    "gn:country_code":"CN",
    "gn:dem":1466,
    "gn:feature_class":"P",
    "gn:feature_code":"PPL",
    "gn:name":"Naizishan",
    "gn:population":0,
    "gn:timezone":"Asia/Shanghai",
    "iso:country":"CN",
    "name:zho_x_preferred":[
        "\u5976\u5b50\u5c71"
    ],
    "wof:name":"Naizishan",
    "wof:placetype":"locality"
},
  "geometry": {"coordinates":[105.98999999999999,26.3773],"type":"Point"}
}