{
  "type": "Feature",
  "properties": {
    "gn:admin1_code":"15.0",
    "gn:asciiname":"Houquli",
    "gn:country_code":"CN",
    "gn:dem":627,
    "gn:feature_class":"P",
    "gn:feature_code":"PPL",
    "gn:name":"Houquli",
    "gn:population":0,
    "gn:timezone":"Asia/Shanghai",
    "iso:country":"CN",
    "name:zho_x_preferred":[
        "\u540e\u6e20\u91cc"
    ],
    "wof:name":"Houquli",
    "wof:placetype":"locality"
},
  "geometry": {"coordinates":[105.395,32.7774],"type":"Point"}
}