{
  "type": "Feature",
  "properties": {
    "gn:admin1_code":"29",
    "gn:asciiname":"Tianshengqiao",
    "gn:country_code":"CN",
    "gn:dem":2017,
    "gn:feature_class":"P",
    "gn:feature_code":"PPL",
    "gn:name":"Tianshengqiao",
    "gn:population":0,
    "gn:timezone":"Asia/Shanghai",
    "iso:country":"CN",
    "name:und_x_variant":[
        "T\u2019ien-sheng-ch\u2019iao",
        "Tianshengqiao",
        "\u5929\u751f\u6865"
    ],
    "wof:name":"Tianshengqiao",
    "wof:placetype":"locality"
},
  "geometry": {"coordinates":[103.88987,25.66296],"type":"Point"}
}