{
  "type": "Feature",
  "properties": {
    "gn:admin1_code":"20.0",
    "gn:asciiname":"Haolaigou",
    "gn:country_code":"CN",
    "gn:dem":1841,
    "gn:feature_class":"P",
    "gn:feature_code":"PPL",
    "gn:name":"Haolaigou",
    "gn:population":0,
    "gn:timezone":"Asia/Shanghai",
    "iso:country":"CN",
    "name:und_x_variant":[
        "\u58d5\u8d56\u6c9f"
    ],
    "wof:name":"Haolaigou",
    "wof:placetype":"locality"
},
  "geometry": {"coordinates":[110.30924,40.96987],"type":"Point"}
}