{
  "type": "Feature",
  "properties": {
    "gn:admin1_code":"9.0",
    "gn:asciiname":"Caofang",
    "gn:country_code":"CN",
    "gn:dem":971,
    "gn:feature_class":"P",
    "gn:feature_code":"PPL",
    "gn:name":"Caofang",
    "gn:population":0,
    "gn:timezone":"Asia/Shanghai",
    "iso:country":"CN",
    "name:zho_x_preferred":[
        "\u8349\u623f"
    ],
    "wof:name":"Caofang",
    "wof:placetype":"locality"
},
  "geometry": {"coordinates":[110.97071,34.13898],"type":"Point"}
}