{
  "type": "Feature",
  "properties": {
    "gn:admin1_code":"16.0",
    "gn:asciiname":"Bapang",
    "gn:country_code":"CN",
    "gn:dem":547,
    "gn:feature_class":"P",
    "gn:feature_code":"PPL",
    "gn:name":"Bapang",
    "gn:population":0,
    "gn:timezone":"Asia/Shanghai",
    "iso:country":"CN",
    "name:zho_x_preferred":[
        "\u5df4\u65c1"
    ],
    "wof:name":"Bapang",
    "wof:placetype":"locality"
},
  "geometry": {"coordinates":[107.03100000000001,24.5491],"type":"Point"}
}