{
  "type": "Feature",
  "properties": {
    "gn:admin1_code":"26.0",
    "gn:asciiname":"Shijiagouliang",
    "gn:country_code":"CN",
    "gn:dem":1198,
    "gn:feature_class":"P",
    "gn:feature_code":"PPL",
    "gn:name":"Shijiagouliang",
    "gn:population":0,
    "gn:timezone":"Asia/Shanghai",
    "iso:country":"CN",
    "name:zho_x_preferred":[
        "\u53f2\u5bb6\u6c9f\u6881"
    ],
    "wof:name":"Shijiagouliang",
    "wof:placetype":"locality"
},
  "geometry": {"coordinates":[106.97676,34.31354],"type":"Point"}
}