{
  "type": "Feature",
  "properties": {
    "gn:admin1_code":"31.0",
    "gn:asciiname":"Daomou",
    "gn:country_code":"CN",
    "gn:dem":14,
    "gn:feature_class":"P",
    "gn:feature_code":"PPL",
    "gn:name":"Daomou",
    "gn:population":0,
    "gn:timezone":"Asia/Shanghai",
    "iso:country":"CN",
    "name:zho_x_preferred":[
        "Daomou"
    ],
    "name:zho_x_variant":[
        "\u9053\u8c0b"
    ],
    "wof:name":"Daomou",
    "wof:placetype":"locality"
},
  "geometry": {"coordinates":[110.6862,19.93581],"type":"Point"}
}