{
  "type": "Feature",
  "properties": {
    "gn:admin1_code":"4.0",
    "gn:asciiname":"Shandong",
    "gn:country_code":"CN",
    "gn:dem":9,
    "gn:feature_class":"P",
    "gn:feature_code":"PPL",
    "gn:name":"Shandong",
    "gn:population":0,
    "gn:timezone":"Asia/Shanghai",
    "iso:country":"CN",
    "name:zho_x_preferred":[
        "Shandong"
    ],
    "name:zho_x_variant":[
        "\u5c71\u4e1c"
    ],
    "wof:name":"Shandong",
    "wof:placetype":"locality"
},
  "geometry": {"coordinates":[119.30065999999999,34.6183],"type":"Point"}
}