{
  "type": "Feature",
  "properties": {
    "gn:admin1_code":"1.0",
    "gn:asciiname":"Baiyangpucun",
    "gn:country_code":"CN",
    "gn:dem":25,
    "gn:feature_class":"P",
    "gn:feature_code":"PPL",
    "gn:name":"Baiyangpucun",
    "gn:population":0,
    "gn:timezone":"Asia/Shanghai",
    "iso:country":"CN",
    "name:zho_x_preferred":[
        "\u767e\u6d0b\u94fa\u6751"
    ],
    "wof:name":"Baiyangpucun",
    "wof:placetype":"locality"
},
  "geometry": {"coordinates":[116.79819000000001,31.49189],"type":"Point"}
}