{
  "type": "Feature",
  "properties": {
    "gn:admin1_code":"32.0",
    "gn:asciiname":"Wafang",
    "gn:country_code":"CN",
    "gn:dem":1526,
    "gn:feature_class":"P",
    "gn:feature_code":"PPL",
    "gn:name":"Wafang",
    "gn:population":0,
    "gn:timezone":"Asia/Shanghai",
    "iso:country":"CN",
    "name:zho_x_preferred":[
        "\u74e6\u623f"
    ],
    "wof:name":"Wafang",
    "wof:placetype":"locality"
},
  "geometry": {"coordinates":[104.49299999999999,31.9259],"type":"Point"}
}