{
  "type": "Feature",
  "properties": {
    "gn:admin1_code":"2.0",
    "gn:asciiname":"Sandaliao",
    "gn:country_code":"CN",
    "gn:dem":5,
    "gn:feature_class":"P",
    "gn:feature_code":"PPL",
    "gn:name":"Sandaliao",
    "gn:population":0,
    "gn:timezone":"Asia/Shanghai",
    "iso:country":"CN",
    "name:zho_x_preferred":[
        "\u4e09\u5927\u5bee"
    ],
    "wof:name":"Sandaliao",
    "wof:placetype":"locality"
},
  "geometry": {"coordinates":[120.55392999999999,27.69325],"type":"Point"}
}