{
  "type": "Feature",
  "properties": {
    "gn:admin1_code":"22.0",
    "gn:asciiname":"Beitiantangcun",
    "gn:country_code":"CN",
    "gn:dem":55,
    "gn:feature_class":"P",
    "gn:feature_code":"PPL",
    "gn:name":"Beitiantangcun",
    "gn:population":0,
    "gn:timezone":"Asia/Shanghai",
    "iso:country":"CN",
    "name:zho_x_preferred":[
        "\u5317\u5929\u5802\u6751"
    ],
    "wof:name":"Beitiantangcun",
    "wof:placetype":"locality"
},
  "geometry": {"coordinates":[116.2595,39.79856],"type":"Point"}
}