{
  "type": "Feature",
  "properties": {
    "gn:admin1_code":"25",
    "gn:asciiname":"Zhang Zhuangzi",
    "gn:country_code":"CN",
    "gn:dem":55,
    "gn:feature_class":"P",
    "gn:feature_code":"PPL",
    "gn:name":"Zhang Zhuangzi",
    "gn:population":0,
    "gn:timezone":"Asia/Shanghai",
    "iso:country":"CN",
    "name:zho_x_preferred":[
        "\u5f20\u5e84\u5b50"
    ],
    "wof:name":"Zhang Zhuangzi",
    "wof:placetype":"locality"
},
  "geometry": {"coordinates":[118.59,34.8393],"type":"Point"}
}