{
  "type": "Feature",
  "properties": {
    "gn:admin1_code":"15.0",
    "gn:asciiname":"Caojiaxian",
    "gn:country_code":"CN",
    "gn:dem":2311,
    "gn:feature_class":"P",
    "gn:feature_code":"PPL",
    "gn:name":"Caojiaxian",
    "gn:population":0,
    "gn:timezone":"Asia/Shanghai",
    "iso:country":"CN",
    "name:zho_x_preferred":[
        "\u66f9\u5bb6\u5c98"
    ],
    "wof:name":"Caojiaxian",
    "wof:placetype":"locality"
},
  "geometry": {"coordinates":[104.17700000000001,35.161],"type":"Point"}
}