{
  "type": "Feature",
  "properties": {
    "gn:admin1_code":"32.0",
    "gn:asciiname":"Muniujue",
    "gn:country_code":"CN",
    "gn:dem":2175,
    "gn:feature_class":"P",
    "gn:feature_code":"PPL",
    "gn:name":"Muniujue",
    "gn:population":0,
    "gn:timezone":"Asia/Shanghai",
    "iso:country":"CN",
    "name:zho_x_preferred":[
        "\u6728\u725b\u89c9"
    ],
    "wof:name":"Muniujue",
    "wof:placetype":"locality"
},
  "geometry": {"coordinates":[102.626,28.3906],"type":"Point"}
}