{
  "type": "Feature",
  "properties": {
    "gn:admin1_code":"18",
    "gn:asciiname":"Xiasuzuo",
    "gn:country_code":"CN",
    "gn:dem":1756,
    "gn:feature_class":"P",
    "gn:feature_code":"PPL",
    "gn:name":"Xiasuzuo",
    "gn:population":0,
    "gn:timezone":"Asia/Shanghai",
    "iso:country":"CN",
    "name:zho_x_preferred":[
        "\u4e0b\u82cf\u5ea7"
    ],
    "wof:name":"Xiasuzuo",
    "wof:placetype":"locality"
},
  "geometry": {"coordinates":[104.72,25.9979],"type":"Point"}
}