{
  "type": "Feature",
  "properties": {
    "gn:admin1_code":"3.0",
    "gn:asciiname":"Lushan",
    "gn:country_code":"CN",
    "gn:dem":22,
    "gn:feature_class":"P",
    "gn:feature_code":"PPL",
    "gn:name":"Lushan",
    "gn:population":0,
    "gn:timezone":"Asia/Shanghai",
    "iso:country":"CN",
    "name:und_x_variant":[
        "\u7089\u5c71"
    ],
    "wof:name":"Lushan",
    "wof:placetype":"locality"
},
  "geometry": {"coordinates":[116.96477,29.06194],"type":"Point"}
}