{
  "type": "Feature",
  "properties": {
    "gn:admin1_code":"1.0",
    "gn:asciiname":"Jiedongcun",
    "gn:country_code":"CN",
    "gn:dem":27,
    "gn:feature_class":"P",
    "gn:feature_code":"PPL",
    "gn:name":"Jiedongcun",
    "gn:population":0,
    "gn:timezone":"Asia/Shanghai",
    "iso:country":"CN",
    "name:zho_x_preferred":[
        "\u754c\u4e1c\u6751"
    ],
    "wof:name":"Jiedongcun",
    "wof:placetype":"locality"
},
  "geometry": {"coordinates":[116.62893,32.91763],"type":"Point"}
}