{
  "type": "Feature",
  "properties": {
    "gn:admin1_code":"10",
    "gn:asciiname":"Heishanxia",
    "gn:country_code":"CN",
    "gn:dem":843,
    "gn:feature_class":"P",
    "gn:feature_code":"PPL",
    "gn:name":"Heishanxia",
    "gn:population":0,
    "gn:timezone":"Asia/Shanghai",
    "iso:country":"CN",
    "name:zho_x_preferred":[
        "\u9ed1\u5c71\u4e0b"
    ],
    "wof:name":"Heishanxia",
    "wof:placetype":"locality"
},
  "geometry": {"coordinates":[117.45762999999999,41.81086],"type":"Point"}
}