{
  "type": "Feature",
  "properties": {
    "gn:admin1_code":"4.0",
    "gn:asciiname":"Daijiaxiang",
    "gn:country_code":"CN",
    "gn:dem":5,
    "gn:feature_class":"P",
    "gn:feature_code":"PPL",
    "gn:name":"Daijiaxiang",
    "gn:population":0,
    "gn:timezone":"Asia/Shanghai",
    "iso:country":"CN",
    "name:zho_x_preferred":[
        "\u6234\u5bb6\u5df7"
    ],
    "wof:name":"Daijiaxiang",
    "wof:placetype":"locality"
},
  "geometry": {"coordinates":[120.91719000000001,31.75215],"type":"Point"}
}