{
  "type": "Feature",
  "properties": {
    "gn:admin1_code":"10.0",
    "gn:asciiname":"Qianshuiyingnan",
    "gn:country_code":"CN",
    "gn:dem":79,
    "gn:feature_class":"P",
    "gn:feature_code":"PPL",
    "gn:name":"Qianshuiyingnan",
    "gn:population":0,
    "gn:timezone":"Asia/Shanghai",
    "iso:country":"CN",
    "name:zho_x_preferred":[
        "\u6d45\u6c34\u8425\u5357"
    ],
    "wof:name":"Qianshuiyingnan",
    "wof:placetype":"locality"
},
  "geometry": {"coordinates":[119.61382999999999,40.1025],"type":"Point"}
}