{
  "type": "Feature",
  "properties": {
    "gn:admin1_code":"32.0",
    "gn:asciiname":"Gerong",
    "gn:country_code":"CN",
    "gn:dem":2736,
    "gn:feature_class":"P",
    "gn:feature_code":"PPL",
    "gn:name":"Gerong",
    "gn:population":0,
    "gn:timezone":"Asia/Shanghai",
    "iso:country":"CN",
    "name:ind_x_preferred":[
        "Gerong"
    ],
    "name:jav_x_preferred":[
        "Gerong"
    ],
    "name:zho_x_preferred":[
        "\u683c\u7ed2"
    ],
    "wof:name":"Gerong",
    "wof:placetype":"locality"
},
  "geometry": {"coordinates":[99.28019999999999,28.741],"type":"Point"}
}