{
  "type": "Feature",
  "properties": {
    "gn:admin1_code":"10",
    "gn:asciiname":"Xicha",
    "gn:country_code":"CN",
    "gn:dem":1133,
    "gn:feature_class":"P",
    "gn:feature_code":"PPL",
    "gn:name":"Xicha",
    "gn:population":0,
    "gn:timezone":"Asia/Shanghai",
    "iso:country":"CN",
    "name:zho_x_preferred":[
        "\u897f\u5c94"
    ],
    "wof:name":"Xicha",
    "wof:placetype":"locality"
},
  "geometry": {"coordinates":[117.02691000000002,41.74642],"type":"Point"}
}