{
  "type": "Feature",
  "properties": {
    "gn:admin1_code":"14.0",
    "gn:asciiname":"Naka Maricun",
    "gn:country_code":"CN",
    "gn:dem":4448,
    "gn:feature_class":"P",
    "gn:feature_code":"PPL",
    "gn:name":"Naka Maricun",
    "gn:population":0,
    "gn:timezone":"Asia/Urumqi",
    "iso:country":"CN",
    "name:zho_x_preferred":[
        "\u90a3\u5494\u739b\u65e5\u6751"
    ],
    "wof:name":"Naka Maricun",
    "wof:placetype":"locality"
},
  "geometry": {"coordinates":[92.34629,31.33758],"type":"Point"}
}