{
  "type": "Feature",
  "properties": {
    "gn:admin1_code":"19.0",
    "gn:asciiname":"Yimafangcun",
    "gn:country_code":"CN",
    "gn:dem":26,
    "gn:feature_class":"P",
    "gn:feature_code":"PPL",
    "gn:name":"Yimafangcun",
    "gn:population":0,
    "gn:timezone":"Asia/Shanghai",
    "iso:country":"CN",
    "name:zho_x_preferred":[
        "\u9a7f\u9a6c\u65b9\u6751"
    ],
    "wof:name":"Yimafangcun",
    "wof:placetype":"locality"
},
  "geometry": {"coordinates":[121.568,41.2808],"type":"Point"}
}