{
  "type": "Feature",
  "properties": {
    "gn:admin1_code":"15.0",
    "gn:asciiname":"Miaozhangjia",
    "gn:country_code":"CN",
    "gn:dem":1330,
    "gn:feature_class":"P",
    "gn:feature_code":"PPL",
    "gn:name":"Miaozhangjia",
    "gn:population":0,
    "gn:timezone":"Asia/Shanghai",
    "iso:country":"CN",
    "name:zho_x_preferred":[
        "\u5e99\u5f20\u5bb6"
    ],
    "wof:name":"Miaozhangjia",
    "wof:placetype":"locality"
},
  "geometry": {"coordinates":[107.316,35.3815],"type":"Point"}
}