{
  "type": "Feature",
  "properties": {
    "gn:admin1_code":"30.0",
    "gn:asciiname":"Zhangcheshui",
    "gn:country_code":"CN",
    "gn:dem":722,
    "gn:feature_class":"P",
    "gn:feature_code":"PPL",
    "gn:name":"Zhangcheshui",
    "gn:population":0,
    "gn:timezone":"Asia/Shanghai",
    "iso:country":"CN",
    "name:zho_x_preferred":[
        "\u7ae0\u8f66\u6c34"
    ],
    "wof:name":"Zhangcheshui",
    "wof:placetype":"locality"
},
  "geometry": {"coordinates":[114.11208000000001,25.17994],"type":"Point"}
}