{
  "type": "Feature",
  "properties": {
    "gn:admin1_code":"8.0",
    "gn:asciiname":"Rongshengcun",
    "gn:country_code":"CN",
    "gn:dem":248,
    "gn:feature_class":"P",
    "gn:feature_code":"PPL",
    "gn:name":"Rongshengcun",
    "gn:population":0,
    "gn:timezone":"Asia/Shanghai",
    "iso:country":"CN",
    "name:zho_x_preferred":[
        "\u8363\u80dc\u6751"
    ],
    "wof:name":"Rongshengcun",
    "wof:placetype":"locality"
},
  "geometry": {"coordinates":[124.80083999999999,48.28778],"type":"Point"}
}