{
  "type": "Feature",
  "properties": {
    "gn:admin1_code":"19.0",
    "gn:asciiname":"Shangshuiquan",
    "gn:country_code":"CN",
    "gn:dem":365,
    "gn:feature_class":"P",
    "gn:feature_code":"PPL",
    "gn:name":"Shangshuiquan",
    "gn:population":0,
    "gn:timezone":"Asia/Shanghai",
    "iso:country":"CN",
    "name:zho_x_preferred":[
        "\u4e0a\u6c34\u6cc9"
    ],
    "wof:name":"Shangshuiquan",
    "wof:placetype":"locality"
},
  "geometry": {"coordinates":[120.26616,41.71179],"type":"Point"}
}