{
  "type": "Feature",
  "properties": {
    "gn:admin1_code":"16.0",
    "gn:asciiname":"Tangchongbutou",
    "gn:country_code":"CN",
    "gn:dem":42,
    "gn:feature_class":"P",
    "gn:feature_code":"PPL",
    "gn:name":"Tangchongbutou",
    "gn:population":0,
    "gn:timezone":"Asia/Shanghai",
    "iso:country":"CN",
    "name:zho_x_preferred":[
        "\u5858\u51b2\u6b65\u5934"
    ],
    "wof:name":"Tangchongbutou",
    "wof:placetype":"locality"
},
  "geometry": {"coordinates":[110.73,23.4503],"type":"Point"}
}