{
  "type": "Feature",
  "properties": {
    "gn:admin1_code":"10",
    "gn:asciiname":"Chahan Tuoluo",
    "gn:country_code":"CN",
    "gn:dem":1020,
    "gn:feature_class":"P",
    "gn:feature_code":"PPL",
    "gn:name":"Chahan Tuoluo",
    "gn:population":0,
    "gn:timezone":"Asia/Shanghai",
    "iso:country":"CN",
    "name:zho_x_preferred":[
        "\u5bdf\u6c57\u9640\u7f57"
    ],
    "wof:name":"Chahan Tuoluo",
    "wof:placetype":"locality"
},
  "geometry": {"coordinates":[114.91141,40.97805],"type":"Point"}
}