{
  "type": "Feature",
  "properties": {
    "gn:admin1_code":"7.0",
    "gn:asciiname":"Maxiangong",
    "gn:country_code":"CN",
    "gn:dem":378,
    "gn:feature_class":"P",
    "gn:feature_code":"PPL",
    "gn:name":"Maxiangong",
    "gn:population":0,
    "gn:timezone":"Asia/Shanghai",
    "iso:country":"CN",
    "name:zho_x_preferred":[
        "\u9a6c\u4ed9\u5bab"
    ],
    "wof:name":"Maxiangong",
    "wof:placetype":"locality"
},
  "geometry": {"coordinates":[120.23126000000001,27.19899],"type":"Point"}
}