{
  "type": "Feature",
  "properties": {
    "gn:admin1_code":"15.0",
    "gn:asciiname":"Baigu",
    "gn:country_code":"CN",
    "gn:dem":2750,
    "gn:feature_class":"P",
    "gn:feature_code":"PPL",
    "gn:name":"Baigu",
    "gn:population":0,
    "gn:timezone":"Asia/Shanghai",
    "iso:country":"CN",
    "name:und_x_variant":[
        "\u767d\u53e4"
    ],
    "name:zho_x_preferred":[
        "\u767d\u53e4"
    ],
    "wof:name":"Baigu",
    "wof:placetype":"locality"
},
  "geometry": {"coordinates":[103.92601999999999,33.75996],"type":"Point"}
}