{
  "type": "Feature",
  "properties": {
    "gn:admin1_code":"9.0",
    "gn:asciiname":"Fanjiatuo",
    "gn:country_code":"CN",
    "gn:dem":1030,
    "gn:feature_class":"P",
    "gn:feature_code":"PPL",
    "gn:name":"Fanjiatuo",
    "gn:population":0,
    "gn:timezone":"Asia/Shanghai",
    "iso:country":"CN",
    "name:zho_x_preferred":[
        "\u8303\u5bb6\u9a7c"
    ],
    "wof:name":"Fanjiatuo",
    "wof:placetype":"locality"
},
  "geometry": {"coordinates":[110.93174999999999,34.13761],"type":"Point"}
}