{
  "type": "Feature",
  "properties": {
    "gn:admin1_code":"15.0",
    "gn:asciiname":"Bantanjing",
    "gn:country_code":"CN",
    "gn:dem":1327,
    "gn:feature_class":"P",
    "gn:feature_code":"PPL",
    "gn:name":"Bantanjing",
    "gn:population":0,
    "gn:timezone":"Asia/Shanghai",
    "iso:country":"CN",
    "name:zho_x_preferred":[
        "\u677f\u6ee9\u4e95"
    ],
    "wof:name":"Bantanjing",
    "wof:placetype":"locality"
},
  "geometry": {"coordinates":[103.76000000000001,38.8147],"type":"Point"}
}