{
  "type": "Feature",
  "properties": {
    "gn:admin1_code":"5.0",
    "gn:asciiname":"Shandongtun",
    "gn:country_code":"CN",
    "gn:dem":154,
    "gn:feature_class":"P",
    "gn:feature_code":"PPL",
    "gn:name":"Shandongtun",
    "gn:population":0,
    "gn:timezone":"Asia/Shanghai",
    "iso:country":"CN",
    "name:zho_x_preferred":[
        "\u5c71\u4e1c\u5c6f"
    ],
    "wof:name":"Shandongtun",
    "wof:placetype":"locality"
},
  "geometry": {"coordinates":[124.30016000000001,43.6009],"type":"Point"}
}