{
  "type": "Feature",
  "properties": {
    "gn:admin1_code":"3.0",
    "gn:asciiname":"Lutianxiang",
    "gn:country_code":"CN",
    "gn:dem":31,
    "gn:feature_class":"P",
    "gn:feature_code":"PPLA4",
    "gn:name":"Lutianxiang",
    "gn:population":0,
    "gn:timezone":"Asia/Shanghai",
    "iso:country":"CN",
    "name:und_x_variant":[
        "\u82a6\u7530\u4e61"
    ],
    "wof:name":"Lutianxiang",
    "wof:placetype":"locality"
},
  "geometry": {"coordinates":[116.92547,28.94759],"type":"Point"}
}