{
  "type": "Feature",
  "properties": {
    "gn:admin1_code":"9",
    "gn:asciiname":"Guodian",
    "gn:country_code":"CN",
    "gn:dem":62,
    "gn:feature_class":"P",
    "gn:feature_code":"PPL",
    "gn:name":"Guodian",
    "gn:population":0,
    "gn:timezone":"Asia/Shanghai",
    "iso:country":"CN",
    "name:deu_x_preferred":[
        "Guodian"
    ],
    "name:zho_x_preferred":[
        "\u90ed\u5e97"
    ],
    "wof:name":"Guodian",
    "wof:placetype":"locality"
},
  "geometry": {"coordinates":[115.20099999999999,34.4726],"type":"Point"}
}