{
  "type": "Feature",
  "properties": {
    "gn:admin1_code":"18",
    "gn:asciiname":"Gongxikou",
    "gn:country_code":"CN",
    "gn:dem":294,
    "gn:feature_class":"P",
    "gn:feature_code":"PPL",
    "gn:name":"Gongxikou",
    "gn:population":0,
    "gn:timezone":"Asia/Shanghai",
    "iso:country":"CN",
    "name:zho_x_preferred":[
        "\u516c\u6eaa\u53e3"
    ],
    "wof:name":"Gongxikou",
    "wof:placetype":"locality"
},
  "geometry": {"coordinates":[108.292,28.9069],"type":"Point"}
}