{
  "type": "Feature",
  "properties": {
    "gn:admin1_code":"8.0",
    "gn:asciiname":"Xigouliyangdian",
    "gn:country_code":"CN",
    "gn:dem":141,
    "gn:feature_class":"P",
    "gn:feature_code":"PPL",
    "gn:name":"Xigouliyangdian",
    "gn:population":0,
    "gn:timezone":"Asia/Shanghai",
    "iso:country":"CN",
    "name:zho_x_preferred":[
        "\u897f\u6c9f\u91cc\u7f8a\u70b9"
    ],
    "wof:name":"Xigouliyangdian",
    "wof:placetype":"locality"
},
  "geometry": {"coordinates":[124.58481999999999,46.61266],"type":"Point"}
}