{
  "type": "Feature",
  "properties": {
    "gn:admin1_code":"16",
    "gn:asciiname":"Shangsujia",
    "gn:country_code":"CN",
    "gn:dem":114,
    "gn:feature_class":"P",
    "gn:feature_code":"PPL",
    "gn:name":"Shangsujia",
    "gn:population":0,
    "gn:timezone":"Asia/Shanghai",
    "iso:country":"CN",
    "name:zho_x_preferred":[
        "\u4e0a\u82cf\u5bb6"
    ],
    "wof:name":"Shangsujia",
    "wof:placetype":"locality"
},
  "geometry": {"coordinates":[110.66800000000001,24.6887],"type":"Point"}
}