{
  "type": "Feature",
  "properties": {
    "gn:admin1_code":"8.0",
    "gn:asciiname":"Xingshisicun",
    "gn:country_code":"CN",
    "gn:dem":171,
    "gn:feature_class":"P",
    "gn:feature_code":"PPL",
    "gn:name":"Xingshisicun",
    "gn:population":0,
    "gn:timezone":"Asia/Shanghai",
    "iso:country":"CN",
    "name:zho_x_preferred":[
        "\u5174\u5341\u56db\u6751"
    ],
    "wof:name":"Xingshisicun",
    "wof:placetype":"locality"
},
  "geometry": {"coordinates":[123.69155000000001,47.86864],"type":"Point"}
}