{
  "type": "Feature",
  "properties": {
    "gn:admin1_code":"18.0",
    "gn:asciiname":"Zhaitou",
    "gn:country_code":"CN",
    "gn:dem":608,
    "gn:feature_class":"P",
    "gn:feature_code":"PPL",
    "gn:name":"Zhaitou",
    "gn:population":0,
    "gn:timezone":"Asia/Shanghai",
    "iso:country":"CN",
    "name:zho_x_preferred":[
        "\u5be8\u5934"
    ],
    "wof:name":"Zhaitou",
    "wof:placetype":"locality"
},
  "geometry": {"coordinates":[108.59399999999999,26.8423],"type":"Point"}
}