{
  "type": "Feature",
  "properties": {
    "gn:admin1_code":"14.0",
    "gn:asciiname":"Nilonglong",
    "gn:country_code":"CN",
    "gn:dem":4452,
    "gn:feature_class":"P",
    "gn:feature_code":"PPL",
    "gn:name":"Nilonglong",
    "gn:population":0,
    "gn:timezone":"Asia/Urumqi",
    "iso:country":"CN",
    "name:zho_x_preferred":[
        "\u4f60\u5785\u9f99"
    ],
    "wof:name":"Nilonglong",
    "wof:placetype":"locality"
},
  "geometry": {"coordinates":[95.05941,30.92041],"type":"Point"}
}