{
  "type": "Feature",
  "properties": {
    "gn:admin1_code":"15.0",
    "gn:asciiname":"Wangjiashan",
    "gn:country_code":"CN",
    "gn:dem":962,
    "gn:feature_class":"P",
    "gn:feature_code":"PPL",
    "gn:name":"Wangjiashan",
    "gn:population":0,
    "gn:timezone":"Asia/Shanghai",
    "iso:country":"CN",
    "name:zho_x_preferred":[
        "\u738b\u5bb6\u5c71"
    ],
    "wof:name":"Wangjiashan",
    "wof:placetype":"locality"
},
  "geometry": {"coordinates":[105.15000000000001,32.7894],"type":"Point"}
}