{
  "type": "Feature",
  "properties": {
    "gn:admin1_code":"30.0",
    "gn:asciiname":"Gantoutang",
    "gn:country_code":"CN",
    "gn:dem":208,
    "gn:feature_class":"P",
    "gn:feature_code":"PPL",
    "gn:name":"Gantoutang",
    "gn:population":0,
    "gn:timezone":"Asia/Shanghai",
    "iso:country":"CN",
    "name:zho_x_preferred":[
        "\u5e72\u5934\u5858"
    ],
    "wof:name":"Gantoutang",
    "wof:placetype":"locality"
},
  "geometry": {"coordinates":[115.59724,23.65629],"type":"Point"}
}