{
  "type": "Feature",
  "properties": {
    "gn:admin1_code":"25.0",
    "gn:asciiname":"Xihuanglancun",
    "gn:country_code":"CN",
    "gn:dem":51,
    "gn:feature_class":"P",
    "gn:feature_code":"PPL",
    "gn:name":"Xihuanglancun",
    "gn:population":0,
    "gn:timezone":"Asia/Shanghai",
    "iso:country":"CN",
    "name:zho_x_preferred":[
        "\u897f\u9ec4\u5c9a\u6751"
    ],
    "wof:name":"Xihuanglancun",
    "wof:placetype":"locality"
},
  "geometry": {"coordinates":[121.99799,37.25698],"type":"Point"}
}