{
  "type": "Feature",
  "properties": {
    "gn:admin1_code":"29",
    "gn:asciiname":"Fuxingjie",
    "gn:country_code":"CN",
    "gn:dem":1478,
    "gn:feature_class":"P",
    "gn:feature_code":"PPL",
    "gn:name":"Fuxingjie",
    "gn:population":0,
    "gn:timezone":"Asia/Shanghai",
    "iso:country":"CN",
    "name:zho_x_preferred":[
        "\u590d\u5174\u8857"
    ],
    "wof:name":"Fuxingjie",
    "wof:placetype":"locality"
},
  "geometry": {"coordinates":[104.572,23.1115],"type":"Point"}
}