{
  "type": "Feature",
  "properties": {
    "gn:admin1_code":"29",
    "gn:asciiname":"Aoyaoshan",
    "gn:country_code":"CN",
    "gn:dem":1479,
    "gn:feature_class":"P",
    "gn:feature_code":"PPL",
    "gn:name":"Aoyaoshan",
    "gn:population":0,
    "gn:timezone":"Asia/Shanghai",
    "iso:country":"CN",
    "name:zho_x_preferred":[
        "\u51f9\u8170\u5c71"
    ],
    "wof:name":"Aoyaoshan",
    "wof:placetype":"locality"
},
  "geometry": {"coordinates":[102.10899999999999,23.782],"type":"Point"}
}