{
  "type": "Feature",
  "properties": {
    "gn:admin1_code":"11",
    "gn:asciiname":"Banqiao Dawu",
    "gn:country_code":"CN",
    "gn:dem":69,
    "gn:feature_class":"P",
    "gn:feature_code":"PPL",
    "gn:name":"Banqiao Dawu",
    "gn:population":0,
    "gn:timezone":"Asia/Shanghai",
    "iso:country":"CN",
    "name:zho_x_preferred":[
        "\u677f\u6865\u5927\u5c4b"
    ],
    "wof:name":"Banqiao Dawu",
    "wof:placetype":"locality"
},
  "geometry": {"coordinates":[112.46474000000001,26.52833],"type":"Point"}
}