{
  "type": "Feature",
  "properties": {
    "gn:admin1_code":"32.0",
    "gn:asciiname":"Sanhemian",
    "gn:country_code":"CN",
    "gn:dem":1254,
    "gn:feature_class":"P",
    "gn:feature_code":"PPL",
    "gn:name":"Sanhemian",
    "gn:population":0,
    "gn:timezone":"Asia/Shanghai",
    "iso:country":"CN",
    "name:zho_x_preferred":[
        "\u4e09\u548c\u9762"
    ],
    "wof:name":"Sanhemian",
    "wof:placetype":"locality"
},
  "geometry": {"coordinates":[107.07594,32.58058],"type":"Point"}
}