{
  "type": "Feature",
  "properties": {
    "gn:admin1_code":"12.0",
    "gn:asciiname":"Lujiatang",
    "gn:country_code":"CN",
    "gn:dem":76,
    "gn:feature_class":"P",
    "gn:feature_code":"PPL",
    "gn:name":"Lujiatang",
    "gn:population":0,
    "gn:timezone":"Asia/Shanghai",
    "iso:country":"CN",
    "name:zho_x_preferred":[
        "\u5362\u5bb6\u5858"
    ],
    "wof:name":"Lujiatang",
    "wof:placetype":"locality"
},
  "geometry": {"coordinates":[114.92952,30.75614],"type":"Point"}
}