{
  "type": "Feature",
  "properties": {
    "gn:admin1_code":"12.0",
    "gn:asciiname":"Dayan",
    "gn:country_code":"CN",
    "gn:dem":1523,
    "gn:feature_class":"P",
    "gn:feature_code":"PPL",
    "gn:name":"Dayan",
    "gn:population":0,
    "gn:timezone":"Asia/Shanghai",
    "iso:country":"CN",
    "name:zho_x_preferred":[
        "\u5927\u5830"
    ],
    "wof:name":"Dayan",
    "wof:placetype":"locality"
},
  "geometry": {"coordinates":[110.68262,30.34294],"type":"Point"}
}