{
  "type": "Feature",
  "properties": {
    "gn:admin1_code":"11.0",
    "gn:asciiname":"Chuhuang",
    "gn:country_code":"CN",
    "gn:dem":564,
    "gn:feature_class":"P",
    "gn:feature_code":"PPL",
    "gn:name":"Chuhuang",
    "gn:population":0,
    "gn:timezone":"Asia/Shanghai",
    "iso:country":"CN",
    "name:zho_x_preferred":[
        "\u51fa\u9ec4"
    ],
    "wof:name":"Chuhuang",
    "wof:placetype":"locality"
},
  "geometry": {"coordinates":[109.04524000000001,27.13296],"type":"Point"}
}