{
  "type": "Feature",
  "properties": {
    "gn:admin1_code":"8.0",
    "gn:asciiname":"Shuangyuecun",
    "gn:country_code":"CN",
    "gn:dem":118,
    "gn:feature_class":"P",
    "gn:feature_code":"PPL",
    "gn:name":"Shuangyuecun",
    "gn:population":0,
    "gn:timezone":"Asia/Shanghai",
    "iso:country":"CN",
    "name:zho_x_preferred":[
        "\u53cc\u8dc3\u6751"
    ],
    "wof:name":"Shuangyuecun",
    "wof:placetype":"locality"
},
  "geometry": {"coordinates":[129.97277,46.89787000000001],"type":"Point"}
}