{
  "type": "Feature",
  "properties": {
    "gn:admin1_code":"30.0",
    "gn:asciiname":"Wangtang",
    "gn:country_code":"CN",
    "gn:dem":11,
    "gn:feature_class":"P",
    "gn:feature_code":"PPL",
    "gn:name":"Wangtang",
    "gn:population":0,
    "gn:timezone":"Asia/Shanghai",
    "iso:country":"CN",
    "name:zho_x_preferred":[
        "\u65fa\u5858"
    ],
    "wof:name":"Wangtang",
    "wof:placetype":"locality"
},
  "geometry": {"coordinates":[112.65303,23.46308],"type":"Point"}
}