{
  "type": "Feature",
  "properties": {
    "gn:admin1_code":"11.0",
    "gn:asciiname":"Qiaodongqiao",
    "gn:country_code":"CN",
    "gn:dem":478,
    "gn:feature_class":"P",
    "gn:feature_code":"PPL",
    "gn:name":"Qiaodongqiao",
    "gn:population":0,
    "gn:timezone":"Asia/Shanghai",
    "iso:country":"CN",
    "name:zho_x_preferred":[
        "\u6865\u4e1c\u6865"
    ],
    "wof:name":"Qiaodongqiao",
    "wof:placetype":"locality"
},
  "geometry": {"coordinates":[109.29942,28.88424],"type":"Point"}
}