{
  "type": "Feature",
  "properties": {
    "gn:admin1_code":"9.0",
    "gn:asciiname":"Dongwanghe",
    "gn:country_code":"CN",
    "gn:dem":113,
    "gn:feature_class":"P",
    "gn:feature_code":"PPL",
    "gn:name":"Dongwanghe",
    "gn:population":0,
    "gn:timezone":"Asia/Shanghai",
    "iso:country":"CN",
    "name:zho_x_preferred":[
        "\u4e1c\u738b\u8d3a"
    ],
    "wof:name":"Dongwanghe",
    "wof:placetype":"locality"
},
  "geometry": {"coordinates":[113.04658999999999,35.05312],"type":"Point"}
}