{
  "type": "Feature",
  "properties": {
    "gn:admin1_code":"5.0",
    "gn:asciiname":"Honggen'aobao",
    "gn:country_code":"CN",
    "gn:dem":166,
    "gn:feature_class":"P",
    "gn:feature_code":"PPL",
    "gn:name":"Honggen\u2019aobao",
    "gn:population":0,
    "gn:timezone":"Asia/Shanghai",
    "iso:country":"CN",
    "name:und_x_variant":[
        "Honggen\u2019aobao"
    ],
    "name:zho_x_preferred":[
        "\u6d2a\u6839\u6556\u5305"
    ],
    "wof:name":"Honggen'aobao",
    "wof:placetype":"locality"
},
  "geometry": {"coordinates":[122.29567,45.21676],"type":"Point"}
}