{
  "type": "Feature",
  "properties": {
    "gn:admin1_code":"11.0",
    "gn:asciiname":"Xinshi",
    "gn:cc2":"CN",
    "gn:country_code":"CN",
    "gn:dem":54,
    "gn:feature_class":"P",
    "gn:feature_code":"PPL",
    "gn:name":"Xinshi",
    "gn:population":0,
    "gn:timezone":"Asia/Shanghai",
    "iso:country":"CN",
    "name:und_x_variant":[
        "Sinshih",
        "Hsin-shih",
        "Xinshi"
    ],
    "wof:name":"Xinshi",
    "wof:placetype":"locality"
},
  "geometry": {"coordinates":[113.17722000000001,28.77694],"type":"Point"}
}