{
  "type": "Feature",
  "properties": {
    "gn:admin1_code":"6.0",
    "gn:asciiname":"Duoyong",
    "gn:country_code":"CN",
    "gn:dem":4301,
    "gn:feature_class":"P",
    "gn:feature_code":"PPL",
    "gn:name":"Duoyong",
    "gn:population":0,
    "gn:timezone":"Asia/Urumqi",
    "iso:country":"CN",
    "name:zho_x_preferred":[
        "\u591a\u6d8c"
    ],
    "wof:name":"Duoyong",
    "wof:placetype":"locality"
},
  "geometry": {"coordinates":[97.45153999999999,34.84050999999999],"type":"Point"}
}