{
  "type": "Feature",
  "properties": {
    "gn:admin1_code":"32.0",
    "gn:asciiname":"Weita",
    "gn:country_code":"CN",
    "gn:dem":3596,
    "gn:feature_class":"P",
    "gn:feature_code":"PPL",
    "gn:name":"Weita",
    "gn:population":0,
    "gn:timezone":"Asia/Shanghai",
    "iso:country":"CN",
    "name:zho_x_preferred":[
        "\u7ef4\u5b83"
    ],
    "wof:name":"Weita",
    "wof:placetype":"locality"
},
  "geometry": {"coordinates":[101.15456,31.34841],"type":"Point"}
}