{
  "type": "Feature",
  "properties": {
    "gn:admin1_code":"26.0",
    "gn:asciiname":"Caojiagouliang",
    "gn:country_code":"CN",
    "gn:dem":1084,
    "gn:feature_class":"P",
    "gn:feature_code":"PPL",
    "gn:name":"Caojiagouliang",
    "gn:population":0,
    "gn:timezone":"Asia/Shanghai",
    "iso:country":"CN",
    "name:zho_x_preferred":[
        "\u66f9\u5bb6\u6c9f\u6881"
    ],
    "wof:name":"Caojiagouliang",
    "wof:placetype":"locality"
},
  "geometry": {"coordinates":[106.92874999999999,34.37307],"type":"Point"}
}