{
  "type": "Feature",
  "properties": {
    "gn:admin1_code":"3.0",
    "gn:asciiname":"Shexing",
    "gn:country_code":"CN",
    "gn:dem":37,
    "gn:feature_class":"P",
    "gn:feature_code":"PPL",
    "gn:name":"Shexing",
    "gn:population":0,
    "gn:timezone":"Asia/Shanghai",
    "iso:country":"CN",
    "name:und_x_variant":[
        "\u86c7\u5f62"
    ],
    "wof:name":"Shexing",
    "wof:placetype":"locality"
},
  "geometry": {"coordinates":[116.35352,29.11198],"type":"Point"}
}