{
  "type": "Feature",
  "properties": {
    "gn:admin1_code":"19.0",
    "gn:asciiname":"Xiaojianchang Yingzi",
    "gn:country_code":"CN",
    "gn:dem":530,
    "gn:feature_class":"P",
    "gn:feature_code":"PPL",
    "gn:name":"Xiaojianchang Yingzi",
    "gn:population":0,
    "gn:timezone":"Asia/Shanghai",
    "iso:country":"CN",
    "name:zho_x_preferred":[
        "\u5c0f\u5efa\u660c\u8425\u5b50"
    ],
    "wof:name":"Xiaojianchang Yingzi",
    "wof:placetype":"locality"
},
  "geometry": {"coordinates":[119.36269,42.25081],"type":"Point"}
}