{
  "type": "Feature",
  "properties": {
    "gn:admin1_code":"19.0",
    "gn:asciiname":"Xinghetai",
    "gn:country_code":"CN",
    "gn:dem":806,
    "gn:feature_class":"P",
    "gn:feature_code":"PPL",
    "gn:name":"Xinghetai",
    "gn:population":0,
    "gn:timezone":"Asia/Shanghai",
    "iso:country":"CN",
    "name:zho_x_preferred":[
        "\u674f\u6838\u53f0"
    ],
    "wof:name":"Xinghetai",
    "wof:placetype":"locality"
},
  "geometry": {"coordinates":[119.88800000000001,41.9783],"type":"Point"}
}