{
  "type": "Feature",
  "properties": {
    "gn:admin1_code":"15.0",
    "gn:asciiname":"Jingping",
    "gn:country_code":"CN",
    "gn:dem":1936,
    "gn:feature_class":"P",
    "gn:feature_code":"PPL",
    "gn:name":"Jingping",
    "gn:population":0,
    "gn:timezone":"Asia/Shanghai",
    "iso:country":"CN",
    "name:zho_x_preferred":[
        "\u4e95\u576a"
    ],
    "wof:name":"Jingping",
    "wof:placetype":"locality"
},
  "geometry": {"coordinates":[105.386,36.194],"type":"Point"}
}