{
  "type": "Feature",
  "properties": {
    "gn:admin1_code":"29.0",
    "gn:asciiname":"Xiaolishu",
    "gn:country_code":"CN",
    "gn:dem":2093,
    "gn:feature_class":"P",
    "gn:feature_code":"PPL",
    "gn:name":"Xiaolishu",
    "gn:population":0,
    "gn:timezone":"Asia/Shanghai",
    "iso:country":"CN",
    "name:zho_x_preferred":[
        "\u5c0f\u68a8\u6811"
    ],
    "wof:name":"Xiaolishu",
    "wof:placetype":"locality"
},
  "geometry": {"coordinates":[98.8069,24.3795],"type":"Point"}
}