{
  "type": "Feature",
  "properties": {
    "gn:admin1_code":"29.0",
    "gn:asciiname":"Heluo",
    "gn:country_code":"CN",
    "gn:dem":2590,
    "gn:feature_class":"P",
    "gn:feature_code":"PPL",
    "gn:name":"Heluo",
    "gn:population":0,
    "gn:timezone":"Asia/Shanghai",
    "iso:country":"CN",
    "name:zho_x_preferred":[
        "\u6cb3\u7f57"
    ],
    "wof:name":"Heluo",
    "wof:placetype":"locality"
},
  "geometry": {"coordinates":[99.7176,27.0839],"type":"Point"}
}