{
  "type": "Feature",
  "properties": {
    "gn:admin1_code":"4.0",
    "gn:asciiname":"Yibeicun",
    "gn:country_code":"CN",
    "gn:dem":3,
    "gn:feature_class":"P",
    "gn:feature_code":"PPL",
    "gn:name":"Yibeicun",
    "gn:population":0,
    "gn:timezone":"Asia/Shanghai",
    "iso:country":"CN",
    "name:zho_x_preferred":[
        "\u4f0a\u5317\u6751"
    ],
    "wof:name":"Yibeicun",
    "wof:placetype":"locality"
},
  "geometry": {"coordinates":[119.18292,34.38971],"type":"Point"}
}