{
  "type": "Feature",
  "properties": {
    "gn:admin1_code":"24",
    "gn:asciiname":"Nanweiquan",
    "gn:country_code":"CN",
    "gn:dem":861,
    "gn:feature_class":"P",
    "gn:feature_code":"PPL",
    "gn:name":"Nanweiquan",
    "gn:population":0,
    "gn:timezone":"Asia/Shanghai",
    "iso:country":"CN",
    "name:und_x_variant":[
        "Nan-wei-ch\u2019\u00fcan",
        "Nanweiquan"
    ],
    "name:zho_x_preferred":[
        "\u5357\u59d4\u6cc9"
    ],
    "wof:name":"Nanweiquan",
    "wof:placetype":"locality"
},
  "geometry": {"coordinates":[113.37846999999999,36.6871],"type":"Point"}
}