{
  "type": "Feature",
  "properties": {
    "gn:admin1_code":"20",
    "gn:asciiname":"Hondlon",
    "gn:cc2":"CN",
    "gn:country_code":"CN",
    "gn:dem":241,
    "gn:feature_class":"P",
    "gn:feature_code":"PPL",
    "gn:name":"Hondlon",
    "gn:population":0,
    "gn:timezone":"Asia/Shanghai",
    "iso:country":"CN",
    "name:und_x_variant":[
        "K\u2019un-tu-ling",
        "Hondlon"
    ],
    "wof:name":"Hondlon",
    "wof:placetype":"locality"
},
  "geometry": {"coordinates":[121.21666999999999,43.73333],"type":"Point"}
}