{
  "type": "Feature",
  "properties": {
    "gn:admin1_code":"5.0",
    "gn:asciiname":"Longshancun",
    "gn:country_code":"CN",
    "gn:dem":363,
    "gn:feature_class":"P",
    "gn:feature_code":"PPL",
    "gn:name":"Longshancun",
    "gn:population":0,
    "gn:timezone":"Asia/Shanghai",
    "iso:country":"CN",
    "name:zho_x_preferred":[
        "\u9f99\u5c71\u6751"
    ],
    "wof:name":"Longshancun",
    "wof:placetype":"locality"
},
  "geometry": {"coordinates":[125.56852000000001,42.78506],"type":"Point"}
}