{
  "type": "Feature",
  "properties": {
    "gn:admin1_code":"13.0",
    "gn:asciiname":"Bashimalegun",
    "gn:country_code":"CN",
    "gn:dem":3157,
    "gn:feature_class":"P",
    "gn:feature_code":"PPL",
    "gn:name":"Bashimalegun",
    "gn:population":0,
    "gn:timezone":"Asia/Urumqi",
    "iso:country":"CN",
    "name:zho_x_preferred":[
        "\u5df4\u4ec0\u739b\u52d2\u6eda"
    ],
    "wof:name":"Bashimalegun",
    "wof:placetype":"locality"
},
  "geometry": {"coordinates":[86.89518000000002,37.66261],"type":"Point"}
}