{
  "type": "Feature",
  "properties": {
    "gn:admin1_code":"11.0",
    "gn:asciiname":"Yandun",
    "gn:country_code":"CN",
    "gn:dem":82,
    "gn:feature_class":"P",
    "gn:feature_code":"PPL",
    "gn:name":"Yandun",
    "gn:population":0,
    "gn:timezone":"Asia/Shanghai",
    "iso:country":"CN",
    "name:ceb_x_preferred":[
        "Yandun"
    ],
    "name:swe_x_preferred":[
        "Yandun"
    ],
    "name:zho_x_preferred":[
        "\u70df\u58a9"
    ],
    "wof:name":"Yandun",
    "wof:placetype":"locality"
},
  "geometry": {"coordinates":[113.09932999999999,28.88612],"type":"Point"}
}