{
  "type": "Feature",
  "properties": {
    "gn:admin1_code":"12.0",
    "gn:asciiname":"Xiawuhuyuan",
    "gn:country_code":"CN",
    "gn:dem":33,
    "gn:feature_class":"P",
    "gn:feature_code":"PPL",
    "gn:name":"Xiawuhuyuan",
    "gn:population":0,
    "gn:timezone":"Asia/Shanghai",
    "iso:country":"CN",
    "name:zho_x_preferred":[
        "\u4e0b\u4e94\u6237\u57b8"
    ],
    "wof:name":"Xiawuhuyuan",
    "wof:placetype":"locality"
},
  "geometry": {"coordinates":[112.55154,29.91587],"type":"Point"}
}