{
  "type": "Feature",
  "properties": {
    "gn:admin1_code":"32.0",
    "gn:asciiname":"Songlingou",
    "gn:country_code":"CN",
    "gn:dem":337,
    "gn:feature_class":"P",
    "gn:feature_code":"PPL",
    "gn:name":"Songlingou",
    "gn:population":0,
    "gn:timezone":"Asia/Shanghai",
    "iso:country":"CN",
    "name:zho_x_preferred":[
        "\u677e\u6797\u6c9f"
    ],
    "wof:name":"Songlingou",
    "wof:placetype":"locality"
},
  "geometry": {"coordinates":[105.35299999999999,30.5114],"type":"Point"}
}