{
  "type": "Feature",
  "properties": {
    "gn:admin1_code":"8.0",
    "gn:asciiname":"Linchangcun",
    "gn:country_code":"CN",
    "gn:dem":119,
    "gn:feature_class":"P",
    "gn:feature_code":"PPL",
    "gn:name":"Linchangcun",
    "gn:population":0,
    "gn:timezone":"Asia/Shanghai",
    "iso:country":"CN",
    "name:zho_x_preferred":[
        "\u6797\u573a\u6751"
    ],
    "wof:name":"Linchangcun",
    "wof:placetype":"locality"
},
  "geometry": {"coordinates":[130.14604,47.07162],"type":"Point"}
}