{
  "type": "Feature",
  "properties": {
    "gn:admin1_code":"1.0",
    "gn:asciiname":"Quanyancun",
    "gn:country_code":"CN",
    "gn:dem":46,
    "gn:feature_class":"P",
    "gn:feature_code":"PPL",
    "gn:name":"Quanyancun",
    "gn:population":0,
    "gn:timezone":"Asia/Shanghai",
    "iso:country":"CN",
    "name:zho_x_preferred":[
        "\u6cc9\u5830\u6751"
    ],
    "wof:name":"Quanyancun",
    "wof:placetype":"locality"
},
  "geometry": {"coordinates":[116.87649999999999,31.35441],"type":"Point"}
}