{
  "type": "Feature",
  "properties": {
    "gn:admin1_code":"4.0",
    "gn:asciiname":"Wuyicun",
    "gn:country_code":"CN",
    "gn:dem":6,
    "gn:feature_class":"P",
    "gn:feature_code":"PPL",
    "gn:name":"Wuyicun",
    "gn:population":0,
    "gn:timezone":"Asia/Shanghai",
    "iso:country":"CN",
    "name:zho_x_preferred":[
        "\u4e94\u4e00\u6751"
    ],
    "wof:name":"Wuyicun",
    "wof:placetype":"locality"
},
  "geometry": {"coordinates":[120.11468000000001,31.78271],"type":"Point"}
}