{
  "type": "Feature",
  "properties": {
    "gn:admin1_code":"29.0",
    "gn:asciiname":"Haizhai",
    "gn:country_code":"CN",
    "gn:dem":1930,
    "gn:feature_class":"P",
    "gn:feature_code":"PPL",
    "gn:name":"Haizhai",
    "gn:population":0,
    "gn:timezone":"Asia/Shanghai",
    "iso:country":"CN",
    "name:zho_x_preferred":[
        "\u6d77\u5be8"
    ],
    "wof:name":"Haizhai",
    "wof:placetype":"locality"
},
  "geometry": {"coordinates":[103.938,25.3183],"type":"Point"}
}