{
  "type": "Feature",
  "properties": {
    "gn:admin1_code":"20.0",
    "gn:asciiname":"Gushanzi",
    "gn:country_code":"CN",
    "gn:dem":320,
    "gn:feature_class":"P",
    "gn:feature_code":"PPL",
    "gn:name":"Gushanzi",
    "gn:population":0,
    "gn:timezone":"Asia/Shanghai",
    "iso:country":"CN",
    "name:zho_x_preferred":[
        "\u5b64\u5c71\u5b50"
    ],
    "wof:name":"Gushanzi",
    "wof:placetype":"locality"
},
  "geometry": {"coordinates":[124.20802,48.8402],"type":"Point"}
}