{
  "type": "Feature",
  "properties": {
    "gn:admin1_code":"14.0",
    "gn:asciiname":"Buzhacun",
    "gn:country_code":"CN",
    "gn:dem":3987,
    "gn:feature_class":"P",
    "gn:feature_code":"PPL",
    "gn:name":"Buzhacun",
    "gn:population":0,
    "gn:timezone":"Asia/Urumqi",
    "iso:country":"CN",
    "name:zho_x_preferred":[
        "\u5e03\u624e\u6751"
    ],
    "wof:name":"Buzhacun",
    "wof:placetype":"locality"
},
  "geometry": {"coordinates":[94.78945,30.85304],"type":"Point"}
}