{
  "type": "Feature",
  "properties": {
    "gn:admin1_code":"29.0",
    "gn:asciiname":"Dafo",
    "gn:country_code":"CN",
    "gn:dem":2057,
    "gn:feature_class":"P",
    "gn:feature_code":"PPL",
    "gn:name":"Dafo",
    "gn:population":0,
    "gn:timezone":"Asia/Shanghai",
    "iso:country":"CN",
    "name:ceb_x_preferred":[
        "Dafo"
    ],
    "name:swe_x_preferred":[
        "Dafo"
    ],
    "name:zho_x_preferred":[
        "\u5927\u4f5b"
    ],
    "wof:name":"Dafo",
    "wof:placetype":"locality"
},
  "geometry": {"coordinates":[99.9783,26.1338],"type":"Point"}
}