{
  "type": "Feature",
  "properties": {
    "gn:admin1_code":"26.0",
    "gn:asciiname":"Lijiayuancun",
    "gn:country_code":"CN",
    "gn:dem":1100,
    "gn:feature_class":"P",
    "gn:feature_code":"PPL",
    "gn:name":"Lijiayuancun",
    "gn:population":0,
    "gn:timezone":"Asia/Shanghai",
    "iso:country":"CN",
    "name:zho_x_preferred":[
        "\u674e\u5bb6\u586c\u6751"
    ],
    "wof:name":"Lijiayuancun",
    "wof:placetype":"locality"
},
  "geometry": {"coordinates":[110.09869,36.13698],"type":"Point"}
}