{
  "type": "Feature",
  "properties": {
    "gn:admin1_code":"29.0",
    "gn:asciiname":"Aolushan",
    "gn:country_code":"CN",
    "gn:dem":1562,
    "gn:feature_class":"P",
    "gn:feature_code":"PPL",
    "gn:name":"Aolushan",
    "gn:population":0,
    "gn:timezone":"Asia/Shanghai",
    "iso:country":"CN",
    "name:zho_x_preferred":[
        "\u51f9\u788c\u5c71"
    ],
    "wof:name":"Aolushan",
    "wof:placetype":"locality"
},
  "geometry": {"coordinates":[99.9228,24.2229],"type":"Point"}
}