{
  "type": "Feature",
  "properties": {
    "gn:admin1_code":"18",
    "gn:asciiname":"Ruanqiaoshao",
    "gn:country_code":"CN",
    "gn:dem":1523,
    "gn:feature_class":"P",
    "gn:feature_code":"PPL",
    "gn:name":"Ruanqiaoshao",
    "gn:population":0,
    "gn:timezone":"Asia/Shanghai",
    "iso:country":"CN",
    "name:zho_x_preferred":[
        "\u8f6f\u6865\u54e8"
    ],
    "wof:name":"Ruanqiaoshao",
    "wof:placetype":"locality"
},
  "geometry": {"coordinates":[104.81399999999999,25.7985],"type":"Point"}
}