{
  "type": "Feature",
  "properties": {
    "gn:admin1_code":"14.0",
    "gn:asciiname":"Minna",
    "gn:country_code":"CN",
    "gn:dem":4272,
    "gn:feature_class":"P",
    "gn:feature_code":"PPL",
    "gn:name":"Minna",
    "gn:population":0,
    "gn:timezone":"Asia/Urumqi",
    "iso:country":"CN",
    "name:zho_x_preferred":[
        "\u6c11\u90a3"
    ],
    "wof:name":"Minna",
    "wof:placetype":"locality"
},
  "geometry": {"coordinates":[92.74325,28.68612000000001],"type":"Point"}
}