{
  "type": "Feature",
  "properties": {
    "gn:admin1_code":"14.0",
    "gn:asciiname":"Minna",
    "gn:country_code":"CN",
    "gn:dem":4272,
    "gn:feature_class":"P",
    "gn:feature_code":"PPL",
    "gn:name":"Minna",
    "gn:population":0,
    "gn:timezone":"Asia/Urumqi",
    "iso:country":"CN",
    "name:azb_x_preferred":[
        "\u0645\u0646\u0627"
    ],
    "name:cat_x_preferred":[
        "Minna"
    ],
    "name:ceb_x_preferred":[
        "Minna"
    ],
    "name:dan_x_preferred":[
        "Minna"
    ],
    "name:deu_x_preferred":[
        "Minna"
    ],
    "name:epo_x_preferred":[
        "Minna"
    ],
    "name:fas_x_preferred":[
        "\u0645\u0646\u0627"
    ],
    "name:fin_x_preferred":[
        "Minna"
    ],
    "name:fra_x_preferred":[
        "Minna"
    ],
    "name:hau_x_preferred":[
        "Minna"
    ],
    "name:hrv_x_preferred":[
        "Minna"
    ],
    "name:ibo_x_preferred":[
        "Minna"
    ],
    "name:ita_x_preferred":[
        "Minna"
    ],
    "name:jpn_x_preferred":[
        "\u30df\u30f3\u30ca"
    ],
    "name:mlg_x_preferred":[
        "Minna"
    ],
    "name:nld_x_preferred":[
        "Minna"
    ],
    "name:pol_x_preferred":[
        "Minna"
    ],
    "name:por_x_preferred":[
        "Minna"
    ],
    "name:ron_x_preferred":[
        "Minna"
    ],
    "name:rus_x_preferred":[
        "\u041c\u0438\u043d\u043d\u0430"
    ],
    "name:swe_x_preferred":[
        "Minna"
    ],
    "name:ukr_x_preferred":[
        "\u041c\u0456\u043d\u043d\u0430"
    ],
    "name:urd_x_preferred":[
        "\u0645\u06cc\u0646\u0627"
    ],
    "name:yor_x_preferred":[
        "Minna"
    ],
    "name:zho_x_preferred":[
        "\u6c11\u90a3"
    ],
    "wof:name":"Minna",
    "wof:placetype":"locality"
},
  "geometry": {"coordinates":[92.74325,28.68612000000001],"type":"Point"}
}