{
  "type": "Feature",
  "properties": {
    "gn:admin1_code":"19",
    "gn:asciiname":"Huangtuling",
    "gn:country_code":"CN",
    "gn:dem":164,
    "gn:feature_class":"P",
    "gn:feature_code":"PPLA4",
    "gn:name":"Huangtuling",
    "gn:population":0,
    "gn:timezone":"Asia/Shanghai",
    "iso:country":"CN",
    "name:und_x_variant":[
        "Huang-t\u2019u-ling-tzu",
        "Huangtuling",
        "\u9ec4\u571f\u5cad",
        "Huangtuling Zhen",
        "\u9ec4\u571f\u5cad\u9547"
    ],
    "wof:name":"Huangtuling",
    "wof:placetype":"locality"
},
  "geometry": {"coordinates":[122.79143999999999,40.41322],"type":"Point"}
}