{
  "type": "Feature",
  "properties": {
    "gn:admin1_code":"15.0",
    "gn:asciiname":"Jiangjia Fentan",
    "gn:country_code":"CN",
    "gn:dem":2400,
    "gn:feature_class":"P",
    "gn:feature_code":"PPL",
    "gn:name":"Jiangjia Fentan",
    "gn:population":0,
    "gn:timezone":"Asia/Shanghai",
    "iso:country":"CN",
    "name:zho_x_preferred":[
        "\u848b\u5bb6\u575f\u6ee9"
    ],
    "wof:name":"Jiangjia Fentan",
    "wof:placetype":"locality"
},
  "geometry": {"coordinates":[103.214,36.8468],"type":"Point"}
}