{
  "type": "Feature",
  "properties": {
    "gn:admin1_code":"11.0",
    "gn:asciiname":"Jianganping",
    "gn:country_code":"CN",
    "gn:dem":1077,
    "gn:feature_class":"P",
    "gn:feature_code":"PPL",
    "gn:name":"Jianganping",
    "gn:population":0,
    "gn:timezone":"Asia/Shanghai",
    "iso:country":"CN",
    "name:zho_x_preferred":[
        "\u67a7\u6746\u576a"
    ],
    "wof:name":"Jianganping",
    "wof:placetype":"locality"
},
  "geometry": {"coordinates":[110.58919,26.52577],"type":"Point"}
}