{
  "type": "Feature",
  "properties": {
    "gn:admin1_code":"32.0",
    "gn:asciiname":"Tangliba",
    "gn:country_code":"CN",
    "gn:dem":1897,
    "gn:feature_class":"P",
    "gn:feature_code":"PPL",
    "gn:name":"Tangliba",
    "gn:population":0,
    "gn:timezone":"Asia/Shanghai",
    "iso:country":"CN",
    "name:zho_x_preferred":[
        "\u7cd6\u68a8\u575d"
    ],
    "wof:name":"Tangliba",
    "wof:placetype":"locality"
},
  "geometry": {"coordinates":[102.20999999999999,28.5197],"type":"Point"}
}