{
  "type": "Feature",
  "properties": {
    "gn:admin1_code":"4.0",
    "gn:asciiname":"Qiaodongcun",
    "gn:country_code":"CN",
    "gn:dem":21,
    "gn:feature_class":"P",
    "gn:feature_code":"PPL",
    "gn:name":"Qiaodongcun",
    "gn:population":0,
    "gn:timezone":"Asia/Shanghai",
    "iso:country":"CN",
    "name:zho_x_preferred":[
        "\u6865\u4e1c\u6751"
    ],
    "wof:name":"Qiaodongcun",
    "wof:placetype":"locality"
},
  "geometry": {"coordinates":[118.62891,33.01532],"type":"Point"}
}