{
  "type": "Feature",
  "properties": {
    "gn:admin1_code":"24.0",
    "gn:asciiname":"Bai'er",
    "gn:country_code":"CN",
    "gn:dem":1143,
    "gn:feature_class":"P",
    "gn:feature_code":"PPL",
    "gn:name":"Bai\u2019er",
    "gn:population":0,
    "gn:timezone":"Asia/Shanghai",
    "iso:country":"CN",
    "name:und_x_variant":[
        "Bai\u2019er"
    ],
    "name:zho_x_preferred":[
        "\u767d\u8033"
    ],
    "wof:name":"Bai'er",
    "wof:placetype":"locality"
},
  "geometry": {"coordinates":[111.02952000000001,36.65322000000001],"type":"Point"}
}