{
  "type": "Feature",
  "properties": {
    "gn:admin1_code":"7.0",
    "gn:asciiname":"Qianling",
    "gn:country_code":"CN",
    "gn:dem":261,
    "gn:feature_class":"P",
    "gn:feature_code":"PPL",
    "gn:name":"Qianling",
    "gn:population":0,
    "gn:timezone":"Asia/Shanghai",
    "iso:country":"CN",
    "name:zho_x_preferred":[
        "\u4e7e\u5cad"
    ],
    "wof:name":"Qianling",
    "wof:placetype":"locality"
},
  "geometry": {"coordinates":[117.21469999999999,24.22218],"type":"Point"}
}