{
  "type": "Feature",
  "properties": {
    "gn:admin1_code":"19.0",
    "gn:asciiname":"Fangshen",
    "gn:country_code":"CN",
    "gn:dem":367,
    "gn:feature_class":"P",
    "gn:feature_code":"PPL",
    "gn:name":"Fangshen",
    "gn:population":0,
    "gn:timezone":"Asia/Shanghai",
    "iso:country":"CN",
    "name:und_x_variant":[
        "\u623f\u7533"
    ],
    "name:zho_x_preferred":[
        "\u623f\u7533"
    ],
    "wof:name":"Fangshen",
    "wof:placetype":"locality"
},
  "geometry": {"coordinates":[119.92601000000001,41.16213],"type":"Point"}
}