{
  "type": "Feature",
  "properties": {
    "gn:admin1_code":"12.0",
    "gn:asciiname":"Fujiaqiaoyuan",
    "gn:country_code":"CN",
    "gn:dem":41,
    "gn:feature_class":"P",
    "gn:feature_code":"PPL",
    "gn:name":"Fujiaqiaoyuan",
    "gn:population":0,
    "gn:timezone":"Asia/Shanghai",
    "iso:country":"CN",
    "name:zho_x_preferred":[
        "Fujiaqiaoyuan"
    ],
    "name:zho_x_variant":[
        "\u4ed8\u5bb6\u6865\u9662"
    ],
    "wof:name":"Fujiaqiaoyuan",
    "wof:placetype":"locality"
},
  "geometry": {"coordinates":[112.28727000000001,30.57156],"type":"Point"}
}