{
  "type": "Feature",
  "properties": {
    "gn:admin1_code":"11",
    "gn:asciiname":"Baiguchong",
    "gn:country_code":"CN",
    "gn:dem":454,
    "gn:feature_class":"P",
    "gn:feature_code":"PPL",
    "gn:name":"Baiguchong",
    "gn:population":0,
    "gn:timezone":"Asia/Shanghai",
    "iso:country":"CN",
    "name:zho_x_preferred":[
        "\u767d\u8c37\u51b2"
    ],
    "wof:name":"Baiguchong",
    "wof:placetype":"locality"
},
  "geometry": {"coordinates":[111.30616999999999,25.12195],"type":"Point"}
}