{
  "type": "Feature",
  "properties": {
    "gn:admin1_code":"33.0",
    "gn:asciiname":"Jianshe",
    "gn:country_code":"CN",
    "gn:dem":732,
    "gn:feature_class":"P",
    "gn:feature_code":"PPL",
    "gn:name":"Jianshe",
    "gn:population":0,
    "gn:timezone":"Asia/Shanghai",
    "iso:country":"CN",
    "name:ceb_x_preferred":[
        "Jianshe"
    ],
    "name:deu_x_preferred":[
        "Jianshe"
    ],
    "name:swe_x_preferred":[
        "Jianshe"
    ],
    "name:zho_x_preferred":[
        "\u5efa\u8bbe"
    ],
    "wof:name":"Jianshe",
    "wof:placetype":"locality"
},
  "geometry": {"coordinates":[107.15458999999998,29.44114],"type":"Point"}
}