{
  "type": "Feature",
  "properties": {
    "gn:admin1_code":"8.0",
    "gn:asciiname":"Beian Shiyan Nonchang Yidui",
    "gn:country_code":"CN",
    "gn:dem":310,
    "gn:feature_class":"P",
    "gn:feature_code":"PPLF",
    "gn:name":"Beian Shiyan Nonchang Yidui",
    "gn:population":0,
    "gn:timezone":"Asia/Shanghai",
    "iso:country":"CN",
    "name:zho_x_preferred":[
        "\u5317\u5b89\u5b9e\u9a8c\u519c\u573a\u4e00\u961f"
    ],
    "wof:name":"Beian Shiyan Nonchang Yidui",
    "wof:placetype":"locality"
},
  "geometry": {"coordinates":[126.56428,48.42907],"type":"Point"}
}