{
  "type": "Feature",
  "properties": {
    "gn:admin1_code":"26.0",
    "gn:asciiname":"Xuebaidiancun",
    "gn:country_code":"CN",
    "gn:dem":1387,
    "gn:feature_class":"P",
    "gn:feature_code":"PPL",
    "gn:name":"Xuebaidiancun",
    "gn:population":0,
    "gn:timezone":"Asia/Shanghai",
    "iso:country":"CN",
    "name:und_x_variant":[
        "Xuebaidian",
        "\u96ea\u767d\u6bbf"
    ],
    "name:zho_x_preferred":[
        "\u96ea\u767d\u6bbf\u6751"
    ],
    "wof:name":"Xuebaidiancun",
    "wof:placetype":"locality"
},
  "geometry": {"coordinates":[107.29917,34.79031],"type":"Point"}
}