{
  "type": "Feature",
  "properties": {
    "gn:admin1_code":"3",
    "gn:asciiname":"Zhenkou",
    "gn:country_code":"CN",
    "gn:dem":161,
    "gn:feature_class":"P",
    "gn:feature_code":"PPL",
    "gn:name":"Zhenkou",
    "gn:population":0,
    "gn:timezone":"Asia/Shanghai",
    "iso:country":"CN",
    "name:zho_x_preferred":[
        "\u5733\u53e3"
    ],
    "wof:name":"Zhenkou",
    "wof:placetype":"locality"
},
  "geometry": {"coordinates":[114.372,26.2528],"type":"Point"}
}