{
  "type": "Feature",
  "properties": {
    "gn:admin1_code":"29.0",
    "gn:asciiname":"Agenbo",
    "gn:country_code":"CN",
    "gn:dem":1962,
    "gn:feature_class":"P",
    "gn:feature_code":"PPL",
    "gn:name":"Agenbo",
    "gn:population":0,
    "gn:timezone":"Asia/Shanghai",
    "iso:country":"CN",
    "name:zho_x_preferred":[
        "\u963f\u6839\u7c38"
    ],
    "wof:name":"Agenbo",
    "wof:placetype":"locality"
},
  "geometry": {"coordinates":[101.35899999999999,25.9489],"type":"Point"}
}