{
  "type": "Feature",
  "properties": {
    "gn:admin1_code":"32.0",
    "gn:asciiname":"Yandao",
    "gn:country_code":"CN",
    "gn:dem":756,
    "gn:feature_class":"P",
    "gn:feature_code":"PPL",
    "gn:name":"Yandao",
    "gn:population":0,
    "gn:timezone":"Asia/Shanghai",
    "iso:country":"CN",
    "name:deu_x_preferred":[
        "Yingjing"
    ],
    "name:est_x_preferred":[
        "Yingjingi maakond"
    ],
    "name:fas_x_preferred":[
        "\u06cc\u0627\u0646\u06af\u0698\u06cc\u0646\u06af"
    ],
    "name:hak_x_preferred":[
        "Y\u00ecn-k\u00een-yen"
    ],
    "name:jpn_x_preferred":[
        "\u30a8\u30a4\u7d4c\u770c"
    ],
    "name:kor_x_preferred":[
        "\uc789\uc9d5\ud604"
    ],
    "name:nor_x_preferred":[
        "Yingjing"
    ],
    "name:rus_x_preferred":[
        "\u0418\u043d\u0446\u0437\u0438\u043d"
    ],
    "name:swe_x_preferred":[
        "Yingjing"
    ],
    "name:und_x_variant":[
        "Yungchinghsien",
        "Hsing-ching",
        "Jung-ching",
        "Ying-ching",
        "Jungking",
        "Jungking-hsien",
        "Jung-ching-hsien",
        "Yandao"
    ],
    "name:urd_x_preferred":[
        "\u06cc\u0646\u06af\u062c\u0646\u06af \u06a9\u0627\u0624\u0646\u0679\u06cc"
    ],
    "name:vie_x_preferred":[
        "Hu\u1ef3nh Kinh"
    ],
    "name:zho_x_preferred":[
        "\u8365\u7ecf\u53bf"
    ],
    "wof:name":"Yandao",
    "wof:placetype":"locality"
},
  "geometry": {"coordinates":[102.84712,29.79311],"type":"Point"}
}