{
  "type": "Feature",
  "properties": {
    "gn:admin1_code":"32.0",
    "gn:asciiname":"Yandao",
    "gn:country_code":"CN",
    "gn:dem":756,
    "gn:feature_class":"P",
    "gn:feature_code":"PPL",
    "gn:name":"Yandao",
    "gn:population":0,
    "gn:timezone":"Asia/Shanghai",
    "iso:country":"CN",
    "name:und_x_variant":[
        "Yungchinghsien",
        "Hsing-ching",
        "Jung-ching",
        "Ying-ching",
        "Jungking",
        "Yingjing",
        "Jungking-hsien",
        "Jung-ching-hsien",
        "Yandao"
    ],
    "wof:name":"Yandao",
    "wof:placetype":"locality"
},
  "geometry": {"coordinates":[102.84712,29.79311],"type":"Point"}
}