{
  "type": "Feature",
  "properties": {
    "gn:admin1_code":"3.0",
    "gn:asciiname":"Shang'ai",
    "gn:country_code":"CN",
    "gn:dem":417,
    "gn:feature_class":"P",
    "gn:feature_code":"PPL",
    "gn:name":"Shang\u2019ai",
    "gn:population":0,
    "gn:timezone":"Asia/Shanghai",
    "iso:country":"CN",
    "name:und_x_variant":[
        "Shang\u2019ai",
        "\u4e0a\u827e"
    ],
    "wof:name":"Shang'ai",
    "wof:placetype":"locality"
},
  "geometry": {"coordinates":[114.42915000000001,28.74231],"type":"Point"}
}