{
  "type": "Feature",
  "properties": {
    "gn:admin1_code":"30.0",
    "gn:asciiname":"Liu'an",
    "gn:country_code":"CN",
    "gn:dem":409,
    "gn:feature_class":"P",
    "gn:feature_code":"PPL",
    "gn:name":"Liu\u2019an",
    "gn:population":0,
    "gn:timezone":"Asia/Shanghai",
    "iso:country":"CN",
    "name:zho_x_preferred":[
        "Liu\u2019an"
    ],
    "name:zho_x_variant":[
        "\u516d\u6697"
    ],
    "wof:name":"Liu'an",
    "wof:placetype":"locality"
},
  "geometry": {"coordinates":[112.68111,23.84028],"type":"Point"}
}