{
  "type": "Feature",
  "properties": {
    "gn:admin1_code":"16.0",
    "gn:asciiname":"Bancheng",
    "gn:country_code":"CN",
    "gn:dem":153,
    "gn:feature_class":"P",
    "gn:feature_code":"PPL",
    "gn:name":"Bancheng",
    "gn:population":0,
    "gn:timezone":"Asia/Shanghai",
    "iso:country":"CN",
    "name:zho_x_preferred":[
        "\u677f\u57ce"
    ],
    "wof:name":"Bancheng",
    "wof:placetype":"locality"
},
  "geometry": {"coordinates":[108.155,23.839],"type":"Point"}
}