{
  "type": "Feature",
  "properties": {
    "gn:admin1_code":"15.0",
    "gn:asciiname":"Buzi",
    "gn:country_code":"CN",
    "gn:dem":1811,
    "gn:feature_class":"P",
    "gn:feature_code":"PPL",
    "gn:name":"Buzi",
    "gn:population":0,
    "gn:timezone":"Asia/Shanghai",
    "iso:country":"CN",
    "name:nld_x_preferred":[
        "Buzi"
    ],
    "name:zho_x_preferred":[
        "\u5821\u5b50"
    ],
    "wof:name":"Buzi",
    "wof:placetype":"locality"
},
  "geometry": {"coordinates":[104.95399999999999,35.6555],"type":"Point"}
}