{
  "type": "Feature",
  "properties": {
    "gn:admin1_code":"19.0",
    "gn:asciiname":"Dasidao Liangzi",
    "gn:country_code":"CN",
    "gn:dem":435,
    "gn:feature_class":"P",
    "gn:feature_code":"PPL",
    "gn:name":"Dasidao Liangzi",
    "gn:population":0,
    "gn:timezone":"Asia/Shanghai",
    "iso:country":"CN",
    "name:zho_x_preferred":[
        "\u5927\u56db\u9053\u6881\u5b50"
    ],
    "wof:name":"Dasidao Liangzi",
    "wof:placetype":"locality"
},
  "geometry": {"coordinates":[119.15549,40.85484],"type":"Point"}
}