{
  "type": "Feature",
  "properties": {
    "gn:admin1_code":"9.0",
    "gn:asciiname":"Diwutuan",
    "gn:country_code":"CN",
    "gn:dem":73,
    "gn:feature_class":"P",
    "gn:feature_code":"PPL",
    "gn:name":"Diwutuan",
    "gn:population":0,
    "gn:timezone":"Asia/Shanghai",
    "iso:country":"CN",
    "name:zho_x_preferred":[
        "\u7b2c\u4e94\u7583"
    ],
    "wof:name":"Diwutuan",
    "wof:placetype":"locality"
},
  "geometry": {"coordinates":[114.01363000000001,35.2799],"type":"Point"}
}