{
  "type": "Feature",
  "properties": {
    "gn:admin1_code":"11.0",
    "gn:asciiname":"Doupotuan",
    "gn:country_code":"CN",
    "gn:dem":427,
    "gn:feature_class":"P",
    "gn:feature_code":"PPL",
    "gn:name":"Doupotuan",
    "gn:population":0,
    "gn:timezone":"Asia/Shanghai",
    "iso:country":"CN",
    "name:zho_x_preferred":[
        "\u9661\u5761\u56e2"
    ],
    "wof:name":"Doupotuan",
    "wof:placetype":"locality"
},
  "geometry": {"coordinates":[109.70974,26.41078],"type":"Point"}
}