{
  "type": "Feature",
  "properties": {
    "gn:admin1_code":"26.0",
    "gn:asciiname":"Jinpenwancun",
    "gn:country_code":"CN",
    "gn:dem":1053,
    "gn:feature_class":"P",
    "gn:feature_code":"PPL",
    "gn:name":"Jinpenwancun",
    "gn:population":0,
    "gn:timezone":"Asia/Shanghai",
    "iso:country":"CN",
    "name:zho_x_preferred":[
        "\u91d1\u76c6\u6e7e\u6751"
    ],
    "wof:name":"Jinpenwancun",
    "wof:placetype":"locality"
},
  "geometry": {"coordinates":[109.746,36.3726],"type":"Point"}
}