{
  "type": "Feature",
  "properties": {
    "gn:admin1_code":"18",
    "gn:asciiname":"Po'ao",
    "gn:country_code":"CN",
    "gn:dem":1266,
    "gn:feature_class":"P",
    "gn:feature_code":"PPL",
    "gn:name":"Po\u2019ao",
    "gn:population":0,
    "gn:timezone":"Asia/Shanghai",
    "iso:country":"CN",
    "name:und_x_variant":[
        "Po\u2019ao"
    ],
    "name:zho_x_preferred":[
        "\u5761\u51f9"
    ],
    "wof:name":"Po'ao",
    "wof:placetype":"locality"
},
  "geometry": {"coordinates":[106.15000000000001,25.3297],"type":"Point"}
}