{
  "type": "Feature",
  "properties": {
    "gn:admin1_code":"30",
    "gn:asciiname":"Xiaodongjiao",
    "gn:country_code":"CN",
    "gn:dem":240,
    "gn:feature_class":"P",
    "gn:feature_code":"PPL",
    "gn:name":"Xiaodongjiao",
    "gn:population":0,
    "gn:timezone":"Asia/Shanghai",
    "iso:country":"CN",
    "name:zho_x_preferred":[
        "\u5c0f\u6d1e\u89d2"
    ],
    "wof:name":"Xiaodongjiao",
    "wof:placetype":"locality"
},
  "geometry": {"coordinates":[114.26347,23.8803],"type":"Point"}
}