{
  "type": "Feature",
  "properties": {
    "gn:admin1_code":"16",
    "gn:asciiname":"Ganzijin",
    "gn:country_code":"CN",
    "gn:dem":658,
    "gn:feature_class":"P",
    "gn:feature_code":"PPL",
    "gn:name":"Ganzijin",
    "gn:population":0,
    "gn:timezone":"Asia/Shanghai",
    "iso:country":"CN",
    "name:zho_x_preferred":[
        "\u67d1\u5b50\u6d78"
    ],
    "wof:name":"Ganzijin",
    "wof:placetype":"locality"
},
  "geometry": {"coordinates":[110.89,25.5385],"type":"Point"}
}