{
  "type": "Feature",
  "properties": {
    "gn:admin1_code":"3",
    "gn:asciiname":"Zhaishang",
    "gn:country_code":"CN",
    "gn:dem":116,
    "gn:feature_class":"P",
    "gn:feature_code":"PPL",
    "gn:name":"Zhaishang",
    "gn:population":0,
    "gn:timezone":"Asia/Shanghai",
    "iso:country":"CN",
    "name:zho_x_preferred":[
        "\u5be8\u4e0a"
    ],
    "wof:name":"Zhaishang",
    "wof:placetype":"locality"
},
  "geometry": {"coordinates":[114.739,25.7806],"type":"Point"}
}