{
  "type": "Feature",
  "properties": {
    "gn:admin1_code":"14.0",
    "gn:asciiname":"Gegalie Ema",
    "gn:country_code":"CN",
    "gn:dem":4798,
    "gn:feature_class":"P",
    "gn:feature_code":"PPL",
    "gn:name":"Gegalie Ema",
    "gn:population":0,
    "gn:timezone":"Asia/Urumqi",
    "iso:country":"CN",
    "name:zho_x_preferred":[
        "\u5404\u560e\u5217\u4fc4\u739b"
    ],
    "wof:name":"Gegalie Ema",
    "wof:placetype":"locality"
},
  "geometry": {"coordinates":[89.77593,31.1848],"type":"Point"}
}