{
  "type": "Feature",
  "properties": {
    "gn:admin1_code":"14.0",
    "gn:asciiname":"Shending",
    "gn:country_code":"CN",
    "gn:dem":3687,
    "gn:feature_class":"P",
    "gn:feature_code":"PPL",
    "gn:name":"Shending",
    "gn:population":0,
    "gn:timezone":"Asia/Urumqi",
    "iso:country":"CN",
    "name:zho_x_preferred":[
        "\u795e\u9876"
    ],
    "wof:name":"Shending",
    "wof:placetype":"locality"
},
  "geometry": {"coordinates":[93.06554,29.11781],"type":"Point"}
}