{
  "type": "Feature",
  "properties": {
    "gn:admin1_code":"14.0",
    "gn:asciiname":"Dushi",
    "gn:country_code":"CN",
    "gn:dem":4023,
    "gn:feature_class":"P",
    "gn:feature_code":"PPL",
    "gn:name":"Dushi",
    "gn:population":0,
    "gn:timezone":"Asia/Urumqi",
    "iso:country":"CN",
    "name:zho_x_preferred":[
        "\u72ec\u4e16"
    ],
    "wof:name":"Dushi",
    "wof:placetype":"locality"
},
  "geometry": {"coordinates":[93.58157,30.10373],"type":"Point"}
}