{
  "type": "Feature",
  "properties": {
    "gn:admin1_code":"29.0",
    "gn:asciiname":"Laowuzhai",
    "gn:country_code":"CN",
    "gn:dem":1495,
    "gn:feature_class":"P",
    "gn:feature_code":"PPL",
    "gn:name":"Laowuzhai",
    "gn:population":0,
    "gn:timezone":"Asia/Shanghai",
    "iso:country":"CN",
    "name:zho_x_preferred":[
        "\u8001\u4e4c\u5be8"
    ],
    "wof:name":"Laowuzhai",
    "wof:placetype":"locality"
},
  "geometry": {"coordinates":[103.18600000000001,22.9337],"type":"Point"}
}