{
  "type": "Feature",
  "properties": {
    "gn:admin1_code":"8.0",
    "gn:asciiname":"Jianshe Nongchang Jiudui",
    "gn:country_code":"CN",
    "gn:dem":250,
    "gn:feature_class":"P",
    "gn:feature_code":"PPLF",
    "gn:name":"Jianshe Nongchang Jiudui",
    "gn:population":0,
    "gn:timezone":"Asia/Shanghai",
    "iso:country":"CN",
    "name:zho_x_preferred":[
        "\u5efa\u8bbe\u519c\u573a\u4e5d\u961f"
    ],
    "wof:name":"Jianshe Nongchang Jiudui",
    "wof:placetype":"locality"
},
  "geometry": {"coordinates":[127.07228000000001,47.83582],"type":"Point"}
}