{
  "type": "Feature",
  "properties": {
    "gn:admin1_code":"29.0",
    "gn:asciiname":"Hualuping",
    "gn:country_code":"CN",
    "gn:dem":1976,
    "gn:feature_class":"P",
    "gn:feature_code":"PPL",
    "gn:name":"Hualuping",
    "gn:population":0,
    "gn:timezone":"Asia/Shanghai",
    "iso:country":"CN",
    "name:zho_x_preferred":[
        "\u82b1\u9e7f\u576a"
    ],
    "wof:name":"Hualuping",
    "wof:placetype":"locality"
},
  "geometry": {"coordinates":[103.718,27.2212],"type":"Point"}
}