{
  "type": "Feature",
  "properties": {
    "gn:admin1_code":"3.0",
    "gn:asciiname":"Wanshang",
    "gn:country_code":"CN",
    "gn:dem":113,
    "gn:feature_class":"P",
    "gn:feature_code":"PPL",
    "gn:name":"Wanshang",
    "gn:population":0,
    "gn:timezone":"Asia/Shanghai",
    "iso:country":"CN",
    "name:und_x_variant":[
        "\u6e7e\u4e0a"
    ],
    "wof:name":"Wanshang",
    "wof:placetype":"locality"
},
  "geometry": {"coordinates":[116.72205,28.42323],"type":"Point"}
}