{
  "type": "Feature",
  "properties": {
    "gn:admin1_code":"26",
    "gn:asciiname":"Baijiajian",
    "gn:cc2":"CN",
    "gn:country_code":"CN",
    "gn:dem":529,
    "gn:feature_class":"P",
    "gn:feature_code":"PPL",
    "gn:name":"Baijiajian",
    "gn:population":0,
    "gn:timezone":"Asia/Shanghai",
    "iso:country":"CN",
    "name:und_x_variant":[
        "Pai-chia-chien",
        "Baijiajian"
    ],
    "wof:name":"Baijiajian",
    "wof:placetype":"locality"
},
  "geometry": {"coordinates":[109.06667,34.81667],"type":"Point"}
}