{
  "type": "Feature",
  "properties": {
    "gn:admin1_code":"10",
    "gn:asciiname":"Yinzhuang",
    "gn:country_code":"CN",
    "gn:dem":23,
    "gn:feature_class":"P",
    "gn:feature_code":"PPL",
    "gn:name":"Yinzhuang",
    "gn:population":0,
    "gn:timezone":"Asia/Shanghai",
    "iso:country":"CN",
    "name:zho_x_preferred":[
        "\u5c39\u5e84"
    ],
    "wof:name":"Yinzhuang",
    "wof:placetype":"locality"
},
  "geometry": {"coordinates":[115.93300000000001,37.6502],"type":"Point"}
}