{
  "type": "Feature",
  "properties": {
    "gn:admin1_code":"2.0",
    "gn:asciiname":"Baocun",
    "gn:country_code":"CN",
    "gn:dem":108,
    "gn:feature_class":"P",
    "gn:feature_code":"PPL",
    "gn:name":"Baocun",
    "gn:population":0,
    "gn:timezone":"Asia/Shanghai",
    "iso:country":"CN",
    "name:und_x_variant":[
        "\u5305\u6751",
        "Baocun"
    ],
    "wof:name":"Baocun",
    "wof:placetype":"locality"
},
  "geometry": {"coordinates":[119.8244,29.02481],"type":"Point"}
}