{
  "type": "Feature",
  "properties": {
    "gn:admin1_code":"19.0",
    "gn:asciiname":"Nansishang",
    "gn:country_code":"CN",
    "gn:dem":206,
    "gn:feature_class":"P",
    "gn:feature_code":"PPL",
    "gn:name":"Nansishang",
    "gn:population":0,
    "gn:timezone":"Asia/Shanghai",
    "iso:country":"CN",
    "name:und_x_variant":[
        "\u5357\u5bfa\u4e0a"
    ],
    "wof:name":"Nansishang",
    "wof:placetype":"locality"
},
  "geometry": {"coordinates":[123.62174,40.57951],"type":"Point"}
}