{
  "type": "Feature",
  "properties": {
    "gn:admin1_code":"33.0",
    "gn:asciiname":"Longtoushang",
    "gn:country_code":"CN",
    "gn:dem":916,
    "gn:feature_class":"P",
    "gn:feature_code":"PPL",
    "gn:name":"Longtoushang",
    "gn:population":0,
    "gn:timezone":"Asia/Shanghai",
    "iso:country":"CN",
    "name:zho_x_preferred":[
        "\u9f99\u5934\u4e0a"
    ],
    "wof:name":"Longtoushang",
    "wof:placetype":"locality"
},
  "geometry": {"coordinates":[109.57705,31.65859],"type":"Point"}
}