{
  "type": "Feature",
  "properties": {
    "gn:admin1_code":"30",
    "gn:asciiname":"Fushan",
    "gn:country_code":"CN",
    "gn:dem":19,
    "gn:feature_class":"P",
    "gn:feature_code":"PPLA4",
    "gn:name":"Fushan",
    "gn:population":0,
    "gn:timezone":"Asia/Shanghai",
    "iso:country":"CN",
    "name:ceb_x_preferred":[
        "Fushan"
    ],
    "name:deu_x_preferred":[
        "Fushan"
    ],
    "name:fra_x_preferred":[
        "Fushan"
    ],
    "name:nor_x_preferred":[
        "Fushan"
    ],
    "name:rus_x_preferred":[
        "\u0424\u0443\u0448\u0430\u043d\u044c"
    ],
    "name:swe_x_preferred":[
        "Fushan"
    ],
    "name:und_x_variant":[
        "Fushan Zhen",
        "\u6d6e\u5c71\u9547"
    ],
    "name:zho_x_preferred":[
        "\u6d6e\u5c71"
    ],
    "wof:name":"Fushan",
    "wof:placetype":"locality"
},
  "geometry": {"coordinates":[116.88460000000001,23.85397],"type":"Point"}
}