{
  "type": "Feature",
  "properties": {
    "gn:admin1_code":"26.0",
    "gn:asciiname":"Sanxiaocun",
    "gn:country_code":"CN",
    "gn:dem":684,
    "gn:feature_class":"P",
    "gn:feature_code":"PPL",
    "gn:name":"Sanxiaocun",
    "gn:population":0,
    "gn:timezone":"Asia/Shanghai",
    "iso:country":"CN",
    "name:und_x_variant":[
        "\u4e09\u5b5d\u6751"
    ],
    "wof:name":"Sanxiaocun",
    "wof:placetype":"locality"
},
  "geometry": {"coordinates":[109.60066999999999,34.42998],"type":"Point"}
}