{
  "type": "Feature",
  "properties": {
    "gn:admin1_code":"29.0",
    "gn:asciiname":"Guodumi",
    "gn:country_code":"CN",
    "gn:dem":2463,
    "gn:feature_class":"P",
    "gn:feature_code":"PPL",
    "gn:name":"Guodumi",
    "gn:population":0,
    "gn:timezone":"Asia/Shanghai",
    "iso:country":"CN",
    "name:zho_x_preferred":[
        "\u679c\u72ec\u7c73"
    ],
    "wof:name":"Guodumi",
    "wof:placetype":"locality"
},
  "geometry": {"coordinates":[99.1223,27.2378],"type":"Point"}
}