{
  "type": "Feature",
  "properties": {
    "gn:admin1_code":"11",
    "gn:asciiname":"Jietoukou",
    "gn:country_code":"CN",
    "gn:dem":164,
    "gn:feature_class":"P",
    "gn:feature_code":"PPL",
    "gn:name":"Jietoukou",
    "gn:population":0,
    "gn:timezone":"Asia/Shanghai",
    "iso:country":"CN",
    "name:zho_x_preferred":[
        "\u754c\u5934\u53e3"
    ],
    "wof:name":"Jietoukou",
    "wof:placetype":"locality"
},
  "geometry": {"coordinates":[111.88968,27.82964],"type":"Point"}
}