{
  "type": "Feature",
  "properties": {
    "gn:admin1_code":"29.0",
    "gn:asciiname":"Oumula",
    "gn:country_code":"CN",
    "gn:dem":1475,
    "gn:feature_class":"P",
    "gn:feature_code":"PPL",
    "gn:name":"Oumula",
    "gn:population":0,
    "gn:timezone":"Asia/Shanghai",
    "iso:country":"CN",
    "name:zho_x_preferred":[
        "\u6b27\u4ea9\u62c9"
    ],
    "wof:name":"Oumula",
    "wof:placetype":"locality"
},
  "geometry": {"coordinates":[98.8571,25.9775],"type":"Point"}
}