{
  "type": "Feature",
  "properties": {
    "gn:admin1_code":"1.0",
    "gn:asciiname":"Zuolong",
    "gn:country_code":"CN",
    "gn:dem":455,
    "gn:feature_class":"P",
    "gn:feature_code":"PPL",
    "gn:name":"Zuolong",
    "gn:population":0,
    "gn:timezone":"Asia/Shanghai",
    "iso:country":"CN",
    "name:ces_x_preferred":[
        "Zuolong"
    ],
    "name:fin_x_preferred":[
        "Zuolong"
    ],
    "name:fra_x_preferred":[
        "Zuolong"
    ],
    "name:mal_x_preferred":[
        "\u0d38\u0d42\u0d13\u0d32\u0d4b\u0d19\u0d4d"
    ],
    "name:nld_x_preferred":[
        "Zuolong"
    ],
    "name:ori_x_preferred":[
        "Zuolong"
    ],
    "name:pol_x_preferred":[
        "Zuolong"
    ],
    "name:rus_x_preferred":[
        "Zuolong salleei"
    ],
    "name:slk_x_preferred":[
        "Zuolong"
    ],
    "name:spa_x_preferred":[
        "Zuolong"
    ],
    "name:ukr_x_preferred":[
        "Zuolong"
    ],
    "name:und_x_variant":[
        "\u5de6\u9f99"
    ],
    "name:vie_x_preferred":[
        "Zuolong"
    ],
    "name:zho_x_preferred":[
        "\u5de6\u9f8d\u5c6c"
    ],
    "wof:name":"Zuolong",
    "wof:placetype":"locality"
},
  "geometry": {"coordinates":[117.71124,29.59825],"type":"Point"}
}