{
  "type": "Feature",
  "properties": {
    "gn:admin1_code":"1.0",
    "gn:asciiname":"Zuolong",
    "gn:country_code":"CN",
    "gn:dem":455,
    "gn:feature_class":"P",
    "gn:feature_code":"PPL",
    "gn:name":"Zuolong",
    "gn:population":0,
    "gn:timezone":"Asia/Shanghai",
    "iso:country":"CN",
    "name:und_x_variant":[
        "\u5de6\u9f99"
    ],
    "wof:name":"Zuolong",
    "wof:placetype":"locality"
},
  "geometry": {"coordinates":[117.71124,29.59825],"type":"Point"}
}