{
  "type": "Feature",
  "properties": {
    "gn:admin1_code":"33.0",
    "gn:asciiname":"Dangtou",
    "gn:country_code":"CN",
    "gn:dem":1041,
    "gn:feature_class":"P",
    "gn:feature_code":"PPL",
    "gn:name":"Dangtou",
    "gn:population":0,
    "gn:timezone":"Asia/Shanghai",
    "iso:country":"CN",
    "name:zho_x_preferred":[
        "\u5f53\u5934"
    ],
    "wof:name":"Dangtou",
    "wof:placetype":"locality"
},
  "geometry": {"coordinates":[107.26300000000001,28.9753],"type":"Point"}
}