{
  "type": "Feature",
  "properties": {
    "gn:admin1_code":"2.0",
    "gn:asciiname":"Xiaowukou",
    "gn:country_code":"CN",
    "gn:dem":610,
    "gn:feature_class":"P",
    "gn:feature_code":"PPL",
    "gn:name":"Xiaowukou",
    "gn:population":0,
    "gn:timezone":"Asia/Shanghai",
    "iso:country":"CN",
    "name:und_x_variant":[
        "\u5c0f\u575e\u53e3"
    ],
    "wof:name":"Xiaowukou",
    "wof:placetype":"locality"
},
  "geometry": {"coordinates":[118.95244,30.32636],"type":"Point"}
}