{
  "type": "Feature",
  "properties": {
    "gn:admin1_code":"1.0",
    "gn:asciiname":"Longgengcun",
    "gn:country_code":"CN",
    "gn:dem":33,
    "gn:feature_class":"P",
    "gn:feature_code":"PPL",
    "gn:name":"Longgengcun",
    "gn:population":0,
    "gn:timezone":"Asia/Shanghai",
    "iso:country":"CN",
    "name:zho_x_preferred":[
        "\u9f99\u57c2\u6751"
    ],
    "wof:name":"Longgengcun",
    "wof:placetype":"locality"
},
  "geometry": {"coordinates":[115.98909999999999,32.46969],"type":"Point"}
}