{
  "type": "Feature",
  "properties": {
    "gn:admin1_code":"26.0",
    "gn:asciiname":"Nuanquanguacun",
    "gn:country_code":"CN",
    "gn:dem":905,
    "gn:feature_class":"P",
    "gn:feature_code":"PPL",
    "gn:name":"Nuanquanguacun",
    "gn:population":0,
    "gn:timezone":"Asia/Shanghai",
    "iso:country":"CN",
    "name:zho_x_preferred":[
        "\u6696\u6cc9\u576c\u6751"
    ],
    "wof:name":"Nuanquanguacun",
    "wof:placetype":"locality"
},
  "geometry": {"coordinates":[110.32486000000002,37.3223],"type":"Point"}
}