{
  "type": "Feature",
  "properties": {
    "gn:admin1_code":"16.0",
    "gn:asciiname":"Sanjialiao",
    "gn:country_code":"CN",
    "gn:dem":319,
    "gn:feature_class":"P",
    "gn:feature_code":"PPL",
    "gn:name":"Sanjialiao",
    "gn:population":0,
    "gn:timezone":"Asia/Shanghai",
    "iso:country":"CN",
    "name:zho_x_preferred":[
        "\u4e09\u5bb6\u5bee"
    ],
    "wof:name":"Sanjialiao",
    "wof:placetype":"locality"
},
  "geometry": {"coordinates":[111.40600000000001,24.2938],"type":"Point"}
}