{
  "type": "Feature",
  "properties": {
    "gn:admin1_code":"3.0",
    "gn:asciiname":"Wangjiazhuang",
    "gn:country_code":"CN",
    "gn:dem":267,
    "gn:feature_class":"P",
    "gn:feature_code":"PPL",
    "gn:name":"Wangjiazhuang",
    "gn:population":0,
    "gn:timezone":"Asia/Shanghai",
    "iso:country":"CN",
    "name:und_x_variant":[
        "\u6c6a\u5bb6\u5e84"
    ],
    "wof:name":"Wangjiazhuang",
    "wof:placetype":"locality"
},
  "geometry": {"coordinates":[116.33313,26.42472],"type":"Point"}
}