{
  "type": "Feature",
  "properties": {
    "gn:admin1_code":"19.0",
    "gn:asciiname":"Gaoluozicun",
    "gn:country_code":"CN",
    "gn:dem":14,
    "gn:feature_class":"P",
    "gn:feature_code":"PPL",
    "gn:name":"Gaoluozicun",
    "gn:population":0,
    "gn:timezone":"Asia/Shanghai",
    "iso:country":"CN",
    "name:zho_x_preferred":[
        "\u9ad8\u6d1b\u5b50\u6751"
    ],
    "wof:name":"Gaoluozicun",
    "wof:placetype":"locality"
},
  "geometry": {"coordinates":[123.08208999999999,41.31343],"type":"Point"}
}