{
  "type": "Feature",
  "properties": {
    "gn:admin1_code":"26.0",
    "gn:asciiname":"Yangjiahe",
    "gn:cc2":"CN",
    "gn:country_code":"CN",
    "gn:dem":979,
    "gn:feature_class":"P",
    "gn:feature_code":"PPL",
    "gn:name":"Yangjiahe",
    "gn:population":0,
    "gn:timezone":"Asia/Shanghai",
    "iso:country":"CN",
    "name:und_x_variant":[
        "Yang-chia-ho",
        "Yangjiahe"
    ],
    "wof:name":"Yangjiahe",
    "wof:placetype":"locality"
},
  "geometry": {"coordinates":[109.31667,35.03333],"type":"Point"}
}