{
  "type": "Feature",
  "properties": {
    "gn:admin1_code":"8.0",
    "gn:asciiname":"Liudi Yingzi",
    "gn:country_code":"CN",
    "gn:dem":225,
    "gn:feature_class":"P",
    "gn:feature_code":"PPL",
    "gn:name":"Liudi Yingzi",
    "gn:population":0,
    "gn:timezone":"Asia/Shanghai",
    "iso:country":"CN",
    "name:und_x_variant":[
        "\u5218\u5730\u8425\u5b50"
    ],
    "wof:name":"Liudi Yingzi",
    "wof:placetype":"locality"
},
  "geometry": {"coordinates":[126.8925,50.35225],"type":"Point"}
}