{
  "type": "Feature",
  "properties": {
    "gn:admin1_code":"10",
    "gn:asciiname":"Yanlin",
    "gn:country_code":"CN",
    "gn:dem":1352,
    "gn:feature_class":"P",
    "gn:feature_code":"PPL",
    "gn:name":"Yanlin",
    "gn:population":0,
    "gn:timezone":"Asia/Shanghai",
    "iso:country":"CN",
    "name:zho_x_preferred":[
        "\u960e\u6797"
    ],
    "wof:name":"Yanlin",
    "wof:placetype":"locality"
},
  "geometry": {"coordinates":[114.88822,41.43219000000001],"type":"Point"}
}