{
  "type": "Feature",
  "properties": {
    "gn:admin1_code":"11",
    "gn:asciiname":"Guanxikou",
    "gn:country_code":"CN",
    "gn:dem":253,
    "gn:feature_class":"P",
    "gn:feature_code":"PPL",
    "gn:name":"Guanxikou",
    "gn:population":0,
    "gn:timezone":"Asia/Shanghai",
    "iso:country":"CN",
    "name:zho_x_preferred":[
        "\u5b98\u6eaa\u53e3"
    ],
    "wof:name":"Guanxikou",
    "wof:placetype":"locality"
},
  "geometry": {"coordinates":[109.92887,27.14829000000001],"type":"Point"}
}