{
  "type": "Feature",
  "properties": {
    "gn:admin1_code":"21.0",
    "gn:asciiname":"Bailuwan",
    "gn:country_code":"CN",
    "gn:dem":1644,
    "gn:feature_class":"P",
    "gn:feature_code":"PPL",
    "gn:name":"Bailuwan",
    "gn:population":0,
    "gn:timezone":"Asia/Shanghai",
    "iso:country":"CN",
    "name:zho_x_preferred":[
        "\u767d\u8def\u6e7e"
    ],
    "wof:name":"Bailuwan",
    "wof:placetype":"locality"
},
  "geometry": {"coordinates":[106.72017,36.07712],"type":"Point"}
}