{
  "type": "Feature",
  "properties": {
    "gn:admin1_code":"3.0",
    "gn:asciiname":"Sheyuanling",
    "gn:country_code":"CN",
    "gn:dem":110,
    "gn:feature_class":"P",
    "gn:feature_code":"PPL",
    "gn:name":"Sheyuanling",
    "gn:population":0,
    "gn:timezone":"Asia/Shanghai",
    "iso:country":"CN",
    "name:zho_x_preferred":[
        "\u6444\u6e90\u5cad"
    ],
    "wof:name":"Sheyuanling",
    "wof:placetype":"locality"
},
  "geometry": {"coordinates":[117.42401,28.31066],"type":"Point"}
}