{
  "type": "Feature",
  "properties": {
    "gn:admin1_code":"29.0",
    "gn:asciiname":"Langbaying",
    "gn:country_code":"CN",
    "gn:dem":1469,
    "gn:feature_class":"P",
    "gn:feature_code":"PPL",
    "gn:name":"Langbaying",
    "gn:population":0,
    "gn:timezone":"Asia/Shanghai",
    "iso:country":"CN",
    "name:zho_x_preferred":[
        "\u6d6a\u575d\u8425"
    ],
    "wof:name":"Langbaying",
    "wof:placetype":"locality"
},
  "geometry": {"coordinates":[100.166,23.6321],"type":"Point"}
}