{
  "type": "Feature",
  "properties": {
    "gn:admin1_code":"1.0",
    "gn:asciiname":"Gubeicun",
    "gn:country_code":"CN",
    "gn:dem":227,
    "gn:feature_class":"P",
    "gn:feature_code":"PPL",
    "gn:name":"Gubeicun",
    "gn:population":0,
    "gn:timezone":"Asia/Shanghai",
    "iso:country":"CN",
    "name:zho_x_preferred":[
        "\u53e4\u7891\u6751"
    ],
    "wof:name":"Gubeicun",
    "wof:placetype":"locality"
},
  "geometry": {"coordinates":[115.79308,31.46535],"type":"Point"}
}