{
  "type": "Feature",
  "properties": {
    "gn:admin1_code":"24.0",
    "gn:asciiname":"Tuoshuiqu",
    "gn:country_code":"CN",
    "gn:dem":1946,
    "gn:feature_class":"P",
    "gn:feature_code":"PPL",
    "gn:name":"Tuoshuiqu",
    "gn:population":0,
    "gn:timezone":"Asia/Shanghai",
    "iso:country":"CN",
    "name:zho_x_preferred":[
        "\u62d6\u6c34\u6e20"
    ],
    "wof:name":"Tuoshuiqu",
    "wof:placetype":"locality"
},
  "geometry": {"coordinates":[112.26621000000002,38.58684],"type":"Point"}
}