{
  "type": "Feature",
  "properties": {
    "gn:admin1_code":"24.0",
    "gn:asciiname":"Tiantang",
    "gn:country_code":"CN",
    "gn:dem":1607,
    "gn:feature_class":"P",
    "gn:feature_code":"PPL",
    "gn:name":"Tiantang",
    "gn:population":0,
    "gn:timezone":"Asia/Shanghai",
    "iso:country":"CN",
    "name:zho_x_preferred":[
        "\u5929\u5802"
    ],
    "wof:name":"Tiantang",
    "wof:placetype":"locality"
},
  "geometry": {"coordinates":[113.47398,38.81189000000001],"type":"Point"}
}