{
  "type": "Feature",
  "properties": {
    "gn:admin1_code":"26.0",
    "gn:asciiname":"Xiaozhangtan",
    "gn:country_code":"CN",
    "gn:dem":341,
    "gn:feature_class":"P",
    "gn:feature_code":"PPL",
    "gn:name":"Xiaozhangtan",
    "gn:population":0,
    "gn:timezone":"Asia/Shanghai",
    "iso:country":"CN",
    "name:zho_x_preferred":[
        "\u5c0f\u5f20\u6ee9"
    ],
    "wof:name":"Xiaozhangtan",
    "wof:placetype":"locality"
},
  "geometry": {"coordinates":[109.66974999999999,34.57935],"type":"Point"}
}