{
  "type": "Feature",
  "properties": {
    "gn:admin1_code":"15.0",
    "gn:asciiname":"Haojialaozhuang",
    "gn:country_code":"CN",
    "gn:dem":1357,
    "gn:feature_class":"P",
    "gn:feature_code":"PPL",
    "gn:name":"Haojialaozhuang",
    "gn:population":0,
    "gn:timezone":"Asia/Shanghai",
    "iso:country":"CN",
    "name:und_x_variant":[
        "\u90dd\u5bb6\u8001\u5e84"
    ],
    "wof:name":"Haojialaozhuang",
    "wof:placetype":"locality"
},
  "geometry": {"coordinates":[107.48197999999999,36.66004],"type":"Point"}
}