{
  "type": "Feature",
  "properties": {
    "gn:admin1_code":"33.0",
    "gn:asciiname":"Yangjiaheba",
    "gn:country_code":"CN",
    "gn:dem":614,
    "gn:feature_class":"P",
    "gn:feature_code":"PPL",
    "gn:name":"Yangjiaheba",
    "gn:population":0,
    "gn:timezone":"Asia/Shanghai",
    "iso:country":"CN",
    "name:zho_x_preferred":[
        "\u6768\u5bb6\u6cb3\u575d"
    ],
    "wof:name":"Yangjiaheba",
    "wof:placetype":"locality"
},
  "geometry": {"coordinates":[107.16961999999999,30.15332],"type":"Point"}
}