{
  "type": "Feature",
  "properties": {
    "gn:admin1_code":"1.0",
    "gn:asciiname":"Sanchahecun",
    "gn:country_code":"CN",
    "gn:dem":61,
    "gn:feature_class":"P",
    "gn:feature_code":"PPL",
    "gn:name":"Sanchahecun",
    "gn:population":0,
    "gn:timezone":"Asia/Shanghai",
    "iso:country":"CN",
    "name:zho_x_preferred":[
        "\u4e09\u53c9\u6cb3\u6751"
    ],
    "wof:name":"Sanchahecun",
    "wof:placetype":"locality"
},
  "geometry": {"coordinates":[116.09599,31.77431],"type":"Point"}
}