{
  "type": "Feature",
  "properties": {
    "gn:admin1_code":"32.0",
    "gn:asciiname":"Shiyazi",
    "gn:country_code":"CN",
    "gn:dem":695,
    "gn:feature_class":"P",
    "gn:feature_code":"PPL",
    "gn:name":"Shiyazi",
    "gn:population":0,
    "gn:timezone":"Asia/Shanghai",
    "iso:country":"CN",
    "name:zho_x_preferred":[
        "\u77f3\u57ad\u5b50"
    ],
    "wof:name":"Shiyazi",
    "wof:placetype":"locality"
},
  "geometry": {"coordinates":[107.086,31.9785],"type":"Point"}
}