{
  "type": "Feature",
  "properties": {
    "gn:admin1_code":"29.0",
    "gn:asciiname":"Minsheng",
    "gn:country_code":"CN",
    "gn:dem":774,
    "gn:feature_class":"P",
    "gn:feature_code":"PPL",
    "gn:name":"Minsheng",
    "gn:population":0,
    "gn:timezone":"Asia/Shanghai",
    "iso:country":"CN",
    "name:und_x_variant":[
        "\u6c11\u80dc"
    ],
    "wof:name":"Minsheng",
    "wof:placetype":"locality"
},
  "geometry": {"coordinates":[103.85496000000001,28.45576],"type":"Point"}
}