{
  "type": "Feature",
  "properties": {
    "gn:admin1_code":"32.0",
    "gn:asciiname":"Ziyun",
    "gn:country_code":"CN",
    "gn:dem":308,
    "gn:feature_class":"P",
    "gn:feature_code":"PPL",
    "gn:name":"Ziyun",
    "gn:population":0,
    "gn:timezone":"Asia/Shanghai",
    "iso:country":"CN",
    "name:zho_x_preferred":[
        "\u7d2b\u4e91"
    ],
    "wof:name":"Ziyun",
    "wof:placetype":"locality"
},
  "geometry": {"coordinates":[106.64100000000001,30.41],"type":"Point"}
}