{
  "type": "Feature",
  "properties": {
    "gn:admin1_code":"8.0",
    "gn:asciiname":"Fuxin",
    "gn:country_code":"CN",
    "gn:dem":245,
    "gn:feature_class":"P",
    "gn:feature_code":"PPL",
    "gn:name":"Fuxin",
    "gn:population":0,
    "gn:timezone":"Asia/Shanghai",
    "iso:country":"CN",
    "name:afr_x_preferred":[
        "Fuxin"
    ],
    "name:ara_x_preferred":[
        "\u0641\u0648\u0634\u064a\u0646"
    ],
    "name:bul_x_preferred":[
        "\u0424\u0443\u0441\u0438\u043d"
    ],
    "name:cat_x_preferred":[
        "Fuxin"
    ],
    "name:cdo_x_preferred":[
        "P\u00e2iu-s\u012dng"
    ],
    "name:ces_x_preferred":[
        "Fu-sin"
    ],
    "name:dan_x_preferred":[
        "Fuxin"
    ],
    "name:deu_x_preferred":[
        "Fuxin"
    ],
    "name:epo_x_preferred":[
        "Fusin"
    ],
    "name:eus_x_preferred":[
        "Fuxin"
    ],
    "name:fas_x_preferred":[
        "\u0641\u0627\u06a9\u0633\u06cc\u0646"
    ],
    "name:fin_x_preferred":[
        "Fuxin"
    ],
    "name:fra_x_preferred":[
        "Fuxin"
    ],
    "name:ita_x_preferred":[
        "Fuxin"
    ],
    "name:jpn_x_preferred":[
        "\u961c\u65b0\u5e02"
    ],
    "name:kik_x_preferred":[
        "Fuxin"
    ],
    "name:kor_x_preferred":[
        "\ud478\uc2e0\uc2dc"
    ],
    "name:lit_x_preferred":[
        "Fusinas"
    ],
    "name:mlg_x_preferred":[
        "Fuxin"
    ],
    "name:mon_x_preferred":[
        "\u0424\u04af\u0448\u0438\u043d\u044c \u0445\u043e\u0442"
    ],
    "name:mwl_x_preferred":[
        "Fuxin"
    ],
    "name:nld_x_preferred":[
        "Fuxin"
    ],
    "name:nno_x_preferred":[
        "Fuxin"
    ],
    "name:nor_x_preferred":[
        "Fuxin"
    ],
    "name:pol_x_preferred":[
        "Fuxin"
    ],
    "name:por_x_preferred":[
        "Fuxin"
    ],
    "name:rus_x_preferred":[
        "\u0424\u0443\u0441\u0438\u043d\u044c"
    ],
    "name:sco_x_preferred":[
        "Fuxin"
    ],
    "name:spa_x_preferred":[
        "Fuxin"
    ],
    "name:srp_x_preferred":[
        "\u0424\u0443\u0441\u0438\u043d"
    ],
    "name:swe_x_preferred":[
        "Fuxin"
    ],
    "name:tur_x_preferred":[
        "Fuxin"
    ],
    "name:urd_x_preferred":[
        "\u0641\u0648\u0634\u0646"
    ],
    "name:vie_x_preferred":[
        "Ph\u1ee5 T\u00e2n"
    ],
    "name:war_x_preferred":[
        "Fuxin"
    ],
    "name:wuu_x_preferred":[
        "\u961c\u65b0\u5e02"
    ],
    "name:zho_x_preferred":[
        "\u5bcc\u65b0"
    ],
    "name:zho_x_variant":[
        "\u961c\u65b0\u5e02"
    ],
    "wof:name":"Fuxin",
    "wof:placetype":"locality"
},
  "geometry": {"coordinates":[123.30415000000001,47.89676],"type":"Point"}
}