{
  "type": "Feature",
  "properties": {
    "gn:admin1_code":"32.0",
    "gn:asciiname":"Longyin",
    "gn:country_code":"CN",
    "gn:dem":407,
    "gn:feature_class":"P",
    "gn:feature_code":"PPL",
    "gn:name":"Longyin",
    "gn:population":0,
    "gn:timezone":"Asia/Shanghai",
    "iso:country":"CN",
    "name:zho_x_preferred":[
        "\u9f99\u541f"
    ],
    "wof:name":"Longyin",
    "wof:placetype":"locality"
},
  "geometry": {"coordinates":[105.214,31.2594],"type":"Point"}
}