{
  "type": "Feature",
  "properties": {
    "gn:admin1_code":"24.0",
    "gn:asciiname":"Fengjiananzhuang",
    "gn:country_code":"CN",
    "gn:dem":1031,
    "gn:feature_class":"P",
    "gn:feature_code":"PPL",
    "gn:name":"Fengjiananzhuang",
    "gn:population":0,
    "gn:timezone":"Asia/Shanghai",
    "iso:country":"CN",
    "name:zho_x_preferred":[
        "\u51af\u5bb6\u5357\u5e84"
    ],
    "wof:name":"Fengjiananzhuang",
    "wof:placetype":"locality"
},
  "geometry": {"coordinates":[111.78346000000001,36.99088],"type":"Point"}
}