{
  "type": "Feature",
  "properties": {
    "gn:admin1_code":"31",
    "gn:asciiname":"Yazaitang",
    "gn:country_code":"CN",
    "gn:dem":30,
    "gn:feature_class":"P",
    "gn:feature_code":"PPL",
    "gn:name":"Yazaitang",
    "gn:population":0,
    "gn:timezone":"Asia/Shanghai",
    "iso:country":"CN",
    "name:und_x_variant":[
        "Ya-tzu-t\u2019ang",
        "Yazaitang",
        "\u9e2d\u4ed4\u5858"
    ],
    "wof:name":"Yazaitang",
    "wof:placetype":"locality"
},
  "geometry": {"coordinates":[109.21299999999999,18.3018],"type":"Point"}
}