{
  "type": "Feature",
  "properties": {
    "gn:admin1_code":"24",
    "gn:asciiname":"Niutouju",
    "gn:country_code":"CN",
    "gn:dem":1315,
    "gn:feature_class":"P",
    "gn:feature_code":"PPL",
    "gn:name":"Niutouju",
    "gn:population":0,
    "gn:timezone":"Asia/Shanghai",
    "iso:country":"CN",
    "wof:name":"Niutouju",
    "wof:placetype":"locality"
},
  "geometry": {"coordinates":[111.90222,37.68778],"type":"Point"}
}