{
  "type": "Feature",
  "properties": {
    "gn:admin1_code":"19.0",
    "gn:asciiname":"Yimaqin'aile",
    "gn:country_code":"CN",
    "gn:dem":88,
    "gn:feature_class":"P",
    "gn:feature_code":"PPL",
    "gn:name":"Yimaqin\u2019aile",
    "gn:population":0,
    "gn:timezone":"Asia/Shanghai",
    "iso:country":"CN",
    "name:zho_x_preferred":[
        "Yimaqin\u2019aile"
    ],
    "name:zho_x_variant":[
        "\u4f0a\u9a6c\u6c81\u827e\u52d2"
    ],
    "wof:name":"Yimaqin'aile",
    "wof:placetype":"locality"
},
  "geometry": {"coordinates":[122.26398,42.17018],"type":"Point"}
}