{
  "type": "Feature",
  "properties": {
    "gn:admin1_code":"3.0",
    "gn:asciiname":"Pengjiacun",
    "gn:country_code":"CN",
    "gn:dem":30,
    "gn:feature_class":"P",
    "gn:feature_code":"PPL",
    "gn:name":"Pengjiacun",
    "gn:population":0,
    "gn:timezone":"Asia/Shanghai",
    "iso:country":"CN",
    "name:und_x_variant":[
        "\u5f6d\u5bb6\u6751"
    ],
    "wof:name":"Pengjiacun",
    "wof:placetype":"locality"
},
  "geometry": {"coordinates":[115.67677999999999,28.114],"type":"Point"}
}