{
  "type": "Feature",
  "properties": {
    "gn:admin1_code":"8.0",
    "gn:asciiname":"Wuyancun",
    "gn:country_code":"CN",
    "gn:dem":140,
    "gn:feature_class":"P",
    "gn:feature_code":"PPL",
    "gn:name":"Wuyancun",
    "gn:population":0,
    "gn:timezone":"Asia/Shanghai",
    "iso:country":"CN",
    "name:zho_x_preferred":[
        "\u5434\u5f66\u6751"
    ],
    "wof:name":"Wuyancun",
    "wof:placetype":"locality"
},
  "geometry": {"coordinates":[129.78821000000002,46.46037000000001],"type":"Point"}
}