{
  "type": "Feature",
  "properties": {
    "gn:admin1_code":"29.0",
    "gn:asciiname":"Mailashan",
    "gn:country_code":"CN",
    "gn:dem":1593,
    "gn:feature_class":"P",
    "gn:feature_code":"PPL",
    "gn:name":"Mailashan",
    "gn:population":0,
    "gn:timezone":"Asia/Shanghai",
    "iso:country":"CN",
    "name:zho_x_preferred":[
        "\u9ea6\u62c9\u5c71"
    ],
    "wof:name":"Mailashan",
    "wof:placetype":"locality"
},
  "geometry": {"coordinates":[101.71599999999999,26.0463],"type":"Point"}
}