{
  "type": "Feature",
  "properties": {
    "gn:admin1_code":"29.0",
    "gn:asciiname":"Yunmao",
    "gn:country_code":"CN",
    "gn:dem":870,
    "gn:feature_class":"P",
    "gn:feature_code":"PPL",
    "gn:name":"Yunmao",
    "gn:population":0,
    "gn:timezone":"Asia/Shanghai",
    "iso:country":"CN",
    "name:zho_x_preferred":[
        "\u5141\u5192"
    ],
    "wof:name":"Yunmao",
    "wof:placetype":"locality"
},
  "geometry": {"coordinates":[98.306,24.2448],"type":"Point"}
}