{
  "type": "Feature",
  "properties": {
    "gn:admin1_code":"15",
    "gn:asciiname":"Yihuqiao",
    "gn:country_code":"CN",
    "gn:dem":2220,
    "gn:feature_class":"P",
    "gn:feature_code":"PPL",
    "gn:name":"Yihuqiao",
    "gn:population":0,
    "gn:timezone":"Asia/Shanghai",
    "iso:country":"CN",
    "wof:name":"Yihuqiao",
    "wof:placetype":"locality"
},
  "geometry": {"coordinates":[104.28861000000001,34.85139],"type":"Point"}
}