{
  "type": "Feature",
  "properties": {
    "gn:admin1_code":"5.0",
    "gn:asciiname":"Shi'erdaowancun",
    "gn:country_code":"CN",
    "gn:dem":520,
    "gn:feature_class":"P",
    "gn:feature_code":"PPL",
    "gn:name":"Shi\u2019erdaowancun",
    "gn:population":0,
    "gn:timezone":"Asia/Shanghai",
    "iso:country":"CN",
    "name:und_x_variant":[
        "Shi\u2019erdaowancun",
        "\u5341\u4e8c\u9053\u6e7e\u6751",
        "Shih-erh-tao-kou-wai",
        "Shi\u2019erdaogouwai"
    ],
    "wof:name":"Shi'erdaowancun",
    "wof:placetype":"locality"
},
  "geometry": {"coordinates":[127.61945,41.42813],"type":"Point"}
}