{
  "type": "Feature",
  "properties": {
    "gn:admin1_code":"2",
    "gn:asciiname":"Shuangqiao",
    "gn:country_code":"CN",
    "gn:dem":15,
    "gn:feature_class":"P",
    "gn:feature_code":"PPL",
    "gn:name":"Shuangqiao",
    "gn:population":0,
    "gn:timezone":"Asia/Shanghai",
    "iso:country":"CN",
    "name:ceb_x_preferred":[
        "Shuangqiao"
    ],
    "name:deu_x_preferred":[
        "Shuangqiao"
    ],
    "name:fra_x_preferred":[
        "Shuangqiao"
    ],
    "name:nor_x_preferred":[
        "Shuangqiao"
    ],
    "name:swe_x_preferred":[
        "Shuangqiao"
    ],
    "name:vie_x_preferred":[
        "Song Ki\u1ec1u"
    ],
    "wof:name":"Shuangqiao",
    "wof:placetype":"locality"
},
  "geometry": {"coordinates":[120.31778,29.72306],"type":"Point"}
}