{
  "type": "Feature",
  "properties": {
    "gn:admin1_code":"30.0",
    "gn:asciiname":"Nanqiao",
    "gn:country_code":"CN",
    "gn:dem":17,
    "gn:feature_class":"P",
    "gn:feature_code":"PPLA4",
    "gn:name":"Nanqiao",
    "gn:population":0,
    "gn:timezone":"Asia/Urumqi",
    "iso:country":"CN",
    "name:und_x_variant":[
        "Nanqiao Jiedao"
    ],
    "name:zho_x_preferred":[
        "\u5357\u6865"
    ],
    "name:zho_x_variant":[
        "\u5357\u6865\u8857\u9053"
    ],
    "wof:name":"Nanqiao",
    "wof:placetype":"locality"
},
  "geometry": {"coordinates":[110.35911000000002,21.2676],"type":"Point"}
}