{
  "type": "Feature",
  "properties": {
    "gn:admin1_code":"29.0",
    "gn:admin2_code":"1794208",
    "gn:admin3_code":"1280771.0",
    "gn:asciiname":"Jingmai Xinzhai",
    "gn:country_code":"CN",
    "gn:dem":1409,
    "gn:feature_class":"P",
    "gn:feature_code":"PPL",
    "gn:name":"Jingmai Xinzhai",
    "gn:population":0,
    "gn:timezone":"Asia/Shanghai",
    "iso:country":"CN",
    "name:eng_x_preferred":[
        "Jingmai"
    ],
    "name:zho_x_preferred":[
        "\u666f\u8fc8\u65b0\u5be8"
    ],
    "wof:name":"Jingmai Xinzhai",
    "wof:placetype":"locality"
},
  "geometry": {"coordinates":[100.029,22.2048],"type":"Point"}
}