{
  "type": "Feature",
  "properties": {
    "gn:admin1_code":"10.0",
    "gn:asciiname":"Pingtai",
    "gn:country_code":"CN",
    "gn:dem":662,
    "gn:feature_class":"P",
    "gn:feature_code":"PPL",
    "gn:name":"Pingtai",
    "gn:population":0,
    "gn:timezone":"Asia/Shanghai",
    "iso:country":"CN",
    "name:zho_x_preferred":[
        "\u5e73\u53f0"
    ],
    "wof:name":"Pingtai",
    "wof:placetype":"locality"
},
  "geometry": {"coordinates":[115.04455,39.05281],"type":"Point"}
}