{
  "type": "Feature",
  "properties": {
    "gn:admin1_code":"19.0",
    "gn:asciiname":"Jieguanting",
    "gn:country_code":"CN",
    "gn:dem":31,
    "gn:feature_class":"P",
    "gn:feature_code":"PPL",
    "gn:name":"Jieguanting",
    "gn:population":0,
    "gn:timezone":"Asia/Shanghai",
    "iso:country":"CN",
    "name:zho_x_preferred":[
        "\u63a5\u5b98\u5385"
    ],
    "wof:name":"Jieguanting",
    "wof:placetype":"locality"
},
  "geometry": {"coordinates":[121.782,39.8235],"type":"Point"}
}