{
  "type": "Feature",
  "properties": {
    "gn:admin1_code":"1.0",
    "gn:asciiname":"Fenshicun",
    "gn:country_code":"CN",
    "gn:dem":182,
    "gn:feature_class":"P",
    "gn:feature_code":"PPL",
    "gn:name":"Fenshicun",
    "gn:population":0,
    "gn:timezone":"Asia/Shanghai",
    "iso:country":"CN",
    "name:zho_x_preferred":[
        "\u5206\u77f3\u6751"
    ],
    "wof:name":"Fenshicun",
    "wof:placetype":"locality"
},
  "geometry": {"coordinates":[117.90428,30.45696],"type":"Point"}
}