{
  "type": "Feature",
  "properties": {
    "gn:admin1_code":"1.0",
    "gn:asciiname":"Cuijiachong",
    "gn:country_code":"CN",
    "gn:dem":16,
    "gn:feature_class":"P",
    "gn:feature_code":"PPL",
    "gn:name":"Cuijiachong",
    "gn:population":0,
    "gn:timezone":"Asia/Shanghai",
    "iso:country":"CN",
    "name:und_x_variant":[
        "\u5d14\u5bb6\u51b2"
    ],
    "wof:name":"Cuijiachong",
    "wof:placetype":"locality"
},
  "geometry": {"coordinates":[118.03162,30.99548],"type":"Point"}
}