{
  "type": "Feature",
  "properties": {
    "gn:admin1_code":"8.0",
    "gn:asciiname":"Zhangdafangzi",
    "gn:country_code":"CN",
    "gn:dem":180,
    "gn:feature_class":"P",
    "gn:feature_code":"PPL",
    "gn:name":"Zhangdafangzi",
    "gn:population":0,
    "gn:timezone":"Asia/Shanghai",
    "iso:country":"CN",
    "name:zho_x_preferred":[
        "\u5f20\u5927\u623f\u5b50"
    ],
    "wof:name":"Zhangdafangzi",
    "wof:placetype":"locality"
},
  "geometry": {"coordinates":[127.81918,46.43561],"type":"Point"}
}