{
  "type": "Feature",
  "properties": {
    "gn:admin1_code":"18",
    "gn:asciiname":"Sunjiapo",
    "gn:country_code":"CN",
    "gn:dem":1391,
    "gn:feature_class":"P",
    "gn:feature_code":"PPL",
    "gn:name":"Sunjiapo",
    "gn:population":0,
    "gn:timezone":"Asia/Shanghai",
    "iso:country":"CN",
    "name:zho_x_preferred":[
        "\u5b59\u5bb6\u5761"
    ],
    "wof:name":"Sunjiapo",
    "wof:placetype":"locality"
},
  "geometry": {"coordinates":[105.488,25.1092],"type":"Point"}
}