{
  "type": "Feature",
  "properties": {
    "gn:admin1_code":"19.0",
    "gn:asciiname":"Anjia Buzi",
    "gn:country_code":"CN",
    "gn:dem":160,
    "gn:feature_class":"P",
    "gn:feature_code":"PPL",
    "gn:name":"Anjia Buzi",
    "gn:population":0,
    "gn:timezone":"Asia/Shanghai",
    "iso:country":"CN",
    "name:und_x_variant":[
        "Anjia Puzi",
        "\u5b89\u5bb6\u5821\u5b50",
        "Anjia Buzi"
    ],
    "wof:name":"Anjia Buzi",
    "wof:placetype":"locality"
},
  "geometry": {"coordinates":[122.72856000000002,40.60695],"type":"Point"}
}