{
  "type": "Feature",
  "properties": {
    "gn:admin1_code":"13.0",
    "gn:asciiname":"Jiulian",
    "gn:country_code":"CN",
    "gn:dem":852,
    "gn:feature_class":"P",
    "gn:feature_code":"PPLF",
    "gn:name":"Jiulian",
    "gn:population":0,
    "gn:timezone":"Asia/Urumqi",
    "iso:country":"CN",
    "name:zho_x_preferred":[
        "\u4e5d\u8fde"
    ],
    "wof:name":"Jiulian",
    "wof:placetype":"locality"
},
  "geometry": {"coordinates":[87.69224,40.64093],"type":"Point"}
}