{
  "type": "Feature",
  "properties": {
    "gn:admin1_code":"26.0",
    "gn:asciiname":"Qingshui Yukou",
    "gn:country_code":"CN",
    "gn:dem":773,
    "gn:feature_class":"P",
    "gn:feature_code":"PPL",
    "gn:name":"Qingshui Yukou",
    "gn:population":0,
    "gn:timezone":"Asia/Shanghai",
    "iso:country":"CN",
    "name:zho_x_preferred":[
        "\u6e05\u6c34\u5cea\u53e3"
    ],
    "wof:name":"Qingshui Yukou",
    "wof:placetype":"locality"
},
  "geometry": {"coordinates":[109.27023,35.02789],"type":"Point"}
}