{
  "type": "Feature",
  "properties": {
    "gn:admin1_code":"32.0",
    "gn:asciiname":"Maobazi",
    "gn:country_code":"CN",
    "gn:dem":634,
    "gn:feature_class":"P",
    "gn:feature_code":"PPL",
    "gn:name":"Maobazi",
    "gn:population":0,
    "gn:timezone":"Asia/Shanghai",
    "iso:country":"CN",
    "name:zho_x_preferred":[
        "\u6bdb\u575d\u5b50"
    ],
    "wof:name":"Maobazi",
    "wof:placetype":"locality"
},
  "geometry": {"coordinates":[107.333,30.7413],"type":"Point"}
}