{
  "type": "Feature",
  "properties": {
    "gn:admin1_code":"04",
    "gn:asciiname":"Tianbu",
    "gn:country_code":"CN",
    "gn:dem":6,
    "gn:feature_class":"P",
    "gn:feature_code":"PPLA4",
    "gn:name":"Tianbu",
    "gn:population":0,
    "gn:timezone":"Asia/Shanghai",
    "iso:country":"CN",
    "name:und_x_variant":[
        "T\u2019ien-pu",
        "T\u2019ien-pu-chen",
        "Tianbu",
        "\u5929\u8865",
        "Tianbu Zhen",
        "\u5929\u8865\u9547"
    ],
    "wof:name":"Tianbu",
    "wof:placetype":"locality"
},
  "geometry": {"coordinates":[121.11369999999999,31.92758],"type":"Point"}
}