{
  "type": "Feature",
  "properties": {
    "gn:admin1_code":"8.0",
    "gn:asciiname":"Zhangguancun",
    "gn:country_code":"CN",
    "gn:dem":142,
    "gn:feature_class":"P",
    "gn:feature_code":"PPL",
    "gn:name":"Zhangguancun",
    "gn:population":0,
    "gn:timezone":"Asia/Shanghai",
    "iso:country":"CN",
    "name:zho_x_preferred":[
        "\u5f20\u5b98\u6751"
    ],
    "wof:name":"Zhangguancun",
    "wof:placetype":"locality"
},
  "geometry": {"coordinates":[126.25635,46.00615],"type":"Point"}
}