{
  "type": "Feature",
  "properties": {
    "gn:admin1_code":"26.0",
    "gn:asciiname":"Wanghepucun",
    "gn:country_code":"CN",
    "gn:dem":959,
    "gn:feature_class":"P",
    "gn:feature_code":"PPL",
    "gn:name":"Wanghepucun",
    "gn:population":0,
    "gn:timezone":"Asia/Shanghai",
    "iso:country":"CN",
    "name:zho_x_preferred":[
        "\u738b\u5408\u94fa\u6751"
    ],
    "wof:name":"Wanghepucun",
    "wof:placetype":"locality"
},
  "geometry": {"coordinates":[110.32459,37.52403],"type":"Point"}
}