{
  "type": "Feature",
  "properties": {
    "gn:admin1_code":"25",
    "gn:asciiname":"Wenquan",
    "gn:country_code":"CN",
    "gn:dem":466,
    "gn:feature_class":"P",
    "gn:feature_code":"PPL",
    "gn:name":"Wenquan",
    "gn:population":0,
    "gn:timezone":"Asia/Shanghai",
    "iso:country":"CN",
    "name:ceb_x_preferred":[
        "Wenquan"
    ],
    "name:deu_x_preferred":[
        "Wenquan"
    ],
    "name:swe_x_preferred":[
        "Wenquan"
    ],
    "name:zho_x_preferred":[
        "\u6587\u6cc9"
    ],
    "name:zho_x_variant":[
        "\u6e29\u6cc9"
    ],
    "wof:name":"Wenquan",
    "wof:placetype":"locality"
},
  "geometry": {"coordinates":[118.251,36.2843],"type":"Point"}
}