{
  "type": "Feature",
  "properties": {
    "gn:admin1_code":"16.0",
    "gn:asciiname":"Gengxiang",
    "gn:country_code":"CN",
    "gn:dem":178,
    "gn:feature_class":"P",
    "gn:feature_code":"PPL",
    "gn:name":"Gengxiang",
    "gn:population":0,
    "gn:timezone":"Asia/Shanghai",
    "iso:country":"CN",
    "name:zho_x_preferred":[
        "\u66f4\u7965"
    ],
    "wof:name":"Gengxiang",
    "wof:placetype":"locality"
},
  "geometry": {"coordinates":[109.069,24.66],"type":"Point"}
}