{
  "type": "Feature",
  "properties": {
    "gn:admin1_code":"24.0",
    "gn:asciiname":"Yingcun",
    "gn:country_code":"CN",
    "gn:dem":1088,
    "gn:feature_class":"P",
    "gn:feature_code":"PPL",
    "gn:name":"Yingcun",
    "gn:population":0,
    "gn:timezone":"Asia/Shanghai",
    "iso:country":"CN",
    "name:zho_x_preferred":[
        "\u83ba\u6751"
    ],
    "wof:name":"Yingcun",
    "wof:placetype":"locality"
},
  "geometry": {"coordinates":[111.06167000000001,38.78028],"type":"Point"}
}