{
  "type": "Feature",
  "properties": {
    "gn:admin1_code":"11",
    "gn:asciiname":"Nantang",
    "gn:country_code":"CN",
    "gn:dem":87,
    "gn:feature_class":"P",
    "gn:feature_code":"PPL",
    "gn:name":"Nantang",
    "gn:population":0,
    "gn:timezone":"Asia/Shanghai",
    "iso:country":"CN",
    "name:deu_x_preferred":[
        "Nantang"
    ],
    "name:zho_x_preferred":[
        "\u5357\u5858"
    ],
    "wof:name":"Nantang",
    "wof:placetype":"locality"
},
  "geometry": {"coordinates":[112.46426,26.9315],"type":"Point"}
}