{
  "type": "Feature",
  "properties": {
    "gn:admin1_code":"9.0",
    "gn:asciiname":"Chengmamu",
    "gn:country_code":"CN",
    "gn:dem":68,
    "gn:feature_class":"P",
    "gn:feature_code":"PPL",
    "gn:name":"Chengmamu",
    "gn:population":0,
    "gn:timezone":"Asia/Shanghai",
    "iso:country":"CN",
    "name:zho_x_preferred":[
        "\u7a0b\u9a6c\u7267"
    ],
    "wof:name":"Chengmamu",
    "wof:placetype":"locality"
},
  "geometry": {"coordinates":[114.53173,34.99266],"type":"Point"}
}