{
  "type": "Feature",
  "properties": {
    "gn:admin1_code":"29",
    "gn:asciiname":"Leshitang",
    "gn:country_code":"CN",
    "gn:dem":1154,
    "gn:feature_class":"P",
    "gn:feature_code":"PPL",
    "gn:name":"Leshitang",
    "gn:population":0,
    "gn:timezone":"Asia/Shanghai",
    "iso:country":"CN",
    "name:zho_x_preferred":[
        "\u4e50\u58eb\u5802"
    ],
    "wof:name":"Leshitang",
    "wof:placetype":"locality"
},
  "geometry": {"coordinates":[103.09699999999999,24.2202],"type":"Point"}
}