{
  "type": "Feature",
  "properties": {
    "gn:admin1_code":"1.0",
    "gn:asciiname":"Shuangxucun",
    "gn:country_code":"CN",
    "gn:dem":9,
    "gn:feature_class":"P",
    "gn:feature_code":"PPL",
    "gn:name":"Shuangxucun",
    "gn:population":0,
    "gn:timezone":"Asia/Shanghai",
    "iso:country":"CN",
    "name:zho_x_preferred":[
        "\u53cc\u5729\u6751"
    ],
    "wof:name":"Shuangxucun",
    "wof:placetype":"locality"
},
  "geometry": {"coordinates":[118.12951,31.73322000000001],"type":"Point"}
}