{
  "type": "Feature",
  "properties": {
    "gn:admin1_code":"3.0",
    "gn:asciiname":"Shangtang",
    "gn:country_code":"CN",
    "gn:dem":170,
    "gn:feature_class":"P",
    "gn:feature_code":"PPLA4",
    "gn:name":"Shangtang",
    "gn:population":0,
    "gn:timezone":"Asia/Shanghai",
    "iso:country":"CN",
    "name:und_x_variant":[
        "\u4e0a\u6c64",
        "Shangtang Xiang",
        "\u4e0a\u6c64\u4e61"
    ],
    "wof:name":"Shangtang",
    "wof:placetype":"locality"
},
  "geometry": {"coordinates":[114.64149999999999,29.31303],"type":"Point"}
}