{
  "type": "Feature",
  "properties": {
    "gn:admin1_code":"4.0",
    "gn:asciiname":"Caotangcun",
    "gn:country_code":"CN",
    "gn:dem":0,
    "gn:feature_class":"P",
    "gn:feature_code":"PPL",
    "gn:name":"Caotangcun",
    "gn:population":0,
    "gn:timezone":"Asia/Shanghai",
    "iso:country":"CN",
    "name:zho_x_preferred":[
        "\u66f9\u5510\u6751"
    ],
    "wof:name":"Caotangcun",
    "wof:placetype":"locality"
},
  "geometry": {"coordinates":[119.86029000000001,33.64288],"type":"Point"}
}