{
  "type": "Feature",
  "properties": {
    "gn:admin1_code":"24.0",
    "gn:asciiname":"Pushang",
    "gn:country_code":"CN",
    "gn:dem":1104,
    "gn:feature_class":"P",
    "gn:feature_code":"PPL",
    "gn:name":"Pushang",
    "gn:population":0,
    "gn:timezone":"Asia/Shanghai",
    "iso:country":"CN",
    "name:und_x_variant":[
        "\u94fa\u4e0a"
    ],
    "wof:name":"Pushang",
    "wof:placetype":"locality"
},
  "geometry": {"coordinates":[112.87007,39.70323],"type":"Point"}
}