{
  "type": "Feature",
  "properties": {
    "gn:admin1_code":"32.0",
    "gn:asciiname":"Pailou",
    "gn:country_code":"CN",
    "gn:dem":312,
    "gn:feature_class":"P",
    "gn:feature_code":"PPL",
    "gn:name":"Pailou",
    "gn:population":0,
    "gn:timezone":"Asia/Shanghai",
    "iso:country":"CN",
    "name:zho_x_preferred":[
        "\u724c\u697c"
    ],
    "wof:name":"Pailou",
    "wof:placetype":"locality"
},
  "geometry": {"coordinates":[105.04600000000001,29.2682],"type":"Point"}
}