{
  "type": "Feature",
  "properties": {
    "gn:admin1_code":"3.0",
    "gn:asciiname":"Xintianban",
    "gn:country_code":"CN",
    "gn:dem":155,
    "gn:feature_class":"P",
    "gn:feature_code":"PPL",
    "gn:name":"Xintianban",
    "gn:population":0,
    "gn:timezone":"Asia/Shanghai",
    "iso:country":"CN",
    "name:und_x_variant":[
        "\u65b0\u7530\u5742"
    ],
    "wof:name":"Xintianban",
    "wof:placetype":"locality"
},
  "geometry": {"coordinates":[115.29971999999999,29.57309],"type":"Point"}
}