{
  "type": "Feature",
  "properties": {
    "gn:admin1_code":"14.0",
    "gn:asciiname":"Paggo",
    "gn:country_code":"CN",
    "gn:dem":4537,
    "gn:feature_class":"P",
    "gn:feature_code":"PPL",
    "gn:name":"Paggo",
    "gn:population":0,
    "gn:timezone":"Asia/Urumqi",
    "iso:country":"CN",
    "name:bod_x_preferred":[
        "Paggo"
    ],
    "name:zho_x_preferred":[
        "Paguo"
    ],
    "name:zho_x_variant":[
        "\u5e15\u679c",
        "Xiaqu Gongshe",
        "\u4e0b\u66f2\u516c\u793e"
    ],
    "wof:name":"Paggo",
    "wof:placetype":"locality"
},
  "geometry": {"coordinates":[92.502,32.002],"type":"Point"}
}