{
  "type": "Feature",
  "properties": {
    "gn:admin1_code":"31",
    "gn:asciiname":"Donglu",
    "gn:country_code":"CN",
    "gn:dem":42,
    "gn:feature_class":"P",
    "gn:feature_code":"PPLA4",
    "gn:name":"Donglu",
    "gn:population":0,
    "gn:timezone":"Asia/Shanghai",
    "iso:country":"CN",
    "name:und_x_variant":[
        "\u4e1c\u8def",
        "Donglu Zhen",
        "\u4e1c\u8def\u9547"
    ],
    "wof:name":"Donglu",
    "wof:placetype":"locality"
},
  "geometry": {"coordinates":[110.67797,19.73869],"type":"Point"}
}