{
  "type": "Feature",
  "properties": {
    "gn:admin1_code":"19",
    "gn:asciiname":"Gaoshengcun",
    "gn:country_code":"CN",
    "gn:dem":3,
    "gn:feature_class":"P",
    "gn:feature_code":"PPL",
    "gn:name":"Gaoshengcun",
    "gn:population":0,
    "gn:timezone":"Asia/Shanghai",
    "iso:country":"CN",
    "name:und_x_variant":[
        "Gaosheng"
    ],
    "name:zho_x_preferred":[
        "\u9ad8\u5347\u6751"
    ],
    "wof:name":"Gaoshengcun",
    "wof:placetype":"locality"
},
  "geometry": {"coordinates":[122.20323,41.34335],"type":"Point"}
}