{
  "type": "Feature",
  "properties": {
    "gn:admin1_code":"20.0",
    "gn:asciiname":"Qianduiliangshan",
    "gn:country_code":"CN",
    "gn:dem":389,
    "gn:feature_class":"P",
    "gn:feature_code":"PPL",
    "gn:name":"Qianduiliangshan",
    "gn:population":0,
    "gn:timezone":"Asia/Shanghai",
    "iso:country":"CN",
    "name:zho_x_preferred":[
        "\u524d\u5806\u7cae\u5c71"
    ],
    "wof:name":"Qianduiliangshan",
    "wof:placetype":"locality"
},
  "geometry": {"coordinates":[123.35621,48.57804],"type":"Point"}
}