{
  "type": "Feature",
  "properties": {
    "gn:admin1_code":"4.0",
    "gn:asciiname":"Shenying",
    "gn:country_code":"CN",
    "gn:dem":7,
    "gn:feature_class":"P",
    "gn:feature_code":"PPL",
    "gn:name":"Shenying",
    "gn:population":0,
    "gn:timezone":"Asia/Shanghai",
    "iso:country":"CN",
    "name:zho_x_preferred":[
        "Shenying"
    ],
    "name:zho_x_variant":[
        "\u6c88\u8425"
    ],
    "wof:name":"Shenying",
    "wof:placetype":"locality"
},
  "geometry": {"coordinates":[119.16188,33.54595],"type":"Point"}
}