{
  "type": "Feature",
  "properties": {
    "gn:admin1_code":"05",
    "gn:asciiname":"Dandai",
    "gn:country_code":"CN",
    "gn:dem":137,
    "gn:feature_class":"P",
    "gn:feature_code":"PPLA4",
    "gn:name":"Dandai",
    "gn:population":0,
    "gn:timezone":"Asia/Shanghai",
    "iso:country":"CN",
    "name:und_x_variant":[
        "Dandai Xiang"
    ],
    "name:zho_x_preferred":[
        "\u4e39\u5cb1"
    ],
    "name:zho_x_variant":[
        "\u4e39\u5cb1\u4e61"
    ],
    "wof:name":"Dandai",
    "wof:placetype":"locality"
},
  "geometry": {"coordinates":[123.83965999999999,46.27372],"type":"Point"}
}