{
  "type": "Feature",
  "properties": {
    "gn:admin1_code":"14.0",
    "gn:asciiname":"Xuecun",
    "gn:country_code":"CN",
    "gn:dem":3704,
    "gn:feature_class":"P",
    "gn:feature_code":"PPL",
    "gn:name":"Xuecun",
    "gn:population":0,
    "gn:timezone":"Asia/Urumqi",
    "iso:country":"CN",
    "name:zho_x_preferred":[
        "\u96ea\u6751"
    ],
    "wof:name":"Xuecun",
    "wof:placetype":"locality"
},
  "geometry": {"coordinates":[92.94148,30.0355],"type":"Point"}
}