{
  "type": "Feature",
  "properties": {
    "gn:admin1_code":"9",
    "gn:asciiname":"Wuzhuang",
    "gn:country_code":"CN",
    "gn:dem":157,
    "gn:feature_class":"P",
    "gn:feature_code":"PPL",
    "gn:name":"Wuzhuang",
    "gn:population":0,
    "gn:timezone":"Asia/Shanghai",
    "iso:country":"CN",
    "name:und_x_variant":[
        "Meizhuang"
    ],
    "name:zho_x_preferred":[
        "\u5434\u5e84"
    ],
    "wof:name":"Wuzhuang",
    "wof:placetype":"locality"
},
  "geometry": {"coordinates":[113.42722000000001,33.11528],"type":"Point"}
}