{
  "type": "Feature",
  "properties": {
    "gn:admin1_code":"32.0",
    "gn:asciiname":"Xingfu",
    "gn:country_code":"CN",
    "gn:dem":918,
    "gn:feature_class":"P",
    "gn:feature_code":"PPL",
    "gn:name":"Xingfu",
    "gn:population":0,
    "gn:timezone":"Asia/Shanghai",
    "iso:country":"CN",
    "name:zho_x_preferred":[
        "\u5e78\u798f"
    ],
    "wof:name":"Xingfu",
    "wof:placetype":"locality"
},
  "geometry": {"coordinates":[102.765,29.7578],"type":"Point"}
}