{
  "type": "Feature",
  "properties": {
    "gn:admin1_code":"15.0",
    "gn:asciiname":"Yuanshuping",
    "gn:country_code":"CN",
    "gn:dem":2086,
    "gn:feature_class":"P",
    "gn:feature_code":"PPL",
    "gn:name":"Yuanshuping",
    "gn:population":0,
    "gn:timezone":"Asia/Shanghai",
    "iso:country":"CN",
    "name:zho_x_preferred":[
        "\u539f\u6811\u576a"
    ],
    "wof:name":"Yuanshuping",
    "wof:placetype":"locality"
},
  "geometry": {"coordinates":[104.688,35.6931],"type":"Point"}
}