{
  "type": "Feature",
  "properties": {
    "gn:admin1_code":"19.0",
    "gn:asciiname":"Tieling Wobu",
    "gn:country_code":"CN",
    "gn:dem":98,
    "gn:feature_class":"P",
    "gn:feature_code":"PPL",
    "gn:name":"Tieling Wobu",
    "gn:population":0,
    "gn:timezone":"Asia/Shanghai",
    "iso:country":"CN",
    "name:und_x_variant":[
        "Tielingwobao",
        "Tieling Wobu"
    ],
    "name:zho_x_preferred":[
        "\u94c1\u5cad\u7a9d\u5821"
    ],
    "wof:name":"Tieling Wobu",
    "wof:placetype":"locality"
},
  "geometry": {"coordinates":[123.64991000000001,42.98828],"type":"Point"}
}