{
  "type": "Feature",
  "properties": {
    "gn:admin1_code":"32.0",
    "gn:asciiname":"Xiaoyanke",
    "gn:country_code":"CN",
    "gn:dem":786,
    "gn:feature_class":"P",
    "gn:feature_code":"PPL",
    "gn:name":"Xiaoyanke",
    "gn:population":0,
    "gn:timezone":"Asia/Shanghai",
    "iso:country":"CN",
    "name:zho_x_preferred":[
        "\u5c0f\u5ca9\u58f3"
    ],
    "wof:name":"Xiaoyanke",
    "wof:placetype":"locality"
},
  "geometry": {"coordinates":[105.41800000000001,32.8047],"type":"Point"}
}