{
  "type": "Feature",
  "properties": {
    "gn:admin1_code":"33.0",
    "gn:asciiname":"Erziping",
    "gn:country_code":"CN",
    "gn:dem":841,
    "gn:feature_class":"P",
    "gn:feature_code":"PPL",
    "gn:name":"Erziping",
    "gn:population":0,
    "gn:timezone":"Asia/Shanghai",
    "iso:country":"CN",
    "name:zho_x_preferred":[
        "\u8033\u5b50\u576a"
    ],
    "wof:name":"Erziping",
    "wof:placetype":"locality"
},
  "geometry": {"coordinates":[107.80674,30.76075],"type":"Point"}
}