{
  "type": "Feature",
  "properties": {
    "gn:admin1_code":"15.0",
    "gn:asciiname":"Zhongjiacha",
    "gn:country_code":"CN",
    "gn:dem":1814,
    "gn:feature_class":"P",
    "gn:feature_code":"PPL",
    "gn:name":"Zhongjiacha",
    "gn:population":0,
    "gn:timezone":"Asia/Shanghai",
    "iso:country":"CN",
    "name:und_x_variant":[
        "\u949f\u5bb6\u5c94"
    ],
    "wof:name":"Zhongjiacha",
    "wof:placetype":"locality"
},
  "geometry": {"coordinates":[105.06999999999999,35.9905],"type":"Point"}
}