{
  "type": "Feature",
  "properties": {
    "gn:admin1_code":"4.0",
    "gn:asciiname":"Zhujiabiancun",
    "gn:country_code":"CN",
    "gn:dem":49,
    "gn:feature_class":"P",
    "gn:feature_code":"PPL",
    "gn:name":"Zhujiabiancun",
    "gn:population":0,
    "gn:timezone":"Asia/Shanghai",
    "iso:country":"CN",
    "name:und_x_variant":[
        "Chu-chia-pien",
        "Zhujiabian",
        "Zhujiabiancun"
    ],
    "name:zho_x_preferred":[
        "\u6731\u5bb6\u8fb9"
    ],
    "name:zho_x_variant":[
        "\u6731\u5bb6\u8fb9\u6751"
    ],
    "wof:name":"Zhujiabiancun",
    "wof:placetype":"locality"
},
  "geometry": {"coordinates":[119.18810999999999,31.63751],"type":"Point"}
}