{
  "type": "Feature",
  "properties": {
    "gn:admin1_code":"2.0",
    "gn:asciiname":"Xiabu",
    "gn:country_code":"CN",
    "gn:dem":462,
    "gn:feature_class":"P",
    "gn:feature_code":"PPL",
    "gn:name":"Xiabu",
    "gn:population":0,
    "gn:timezone":"Asia/Shanghai",
    "iso:country":"CN",
    "name:zho_x_preferred":[
        "\u971e\u5821"
    ],
    "wof:name":"Xiabu",
    "wof:placetype":"locality"
},
  "geometry": {"coordinates":[120.61498,29.75217],"type":"Point"}
}