{
  "type": "Feature",
  "properties": {
    "gn:admin1_code":"18",
    "gn:asciiname":"Changgengshang",
    "gn:country_code":"CN",
    "gn:dem":922,
    "gn:feature_class":"P",
    "gn:feature_code":"PPL",
    "gn:name":"Changgengshang",
    "gn:population":0,
    "gn:timezone":"Asia/Shanghai",
    "iso:country":"CN",
    "name:zho_x_preferred":[
        "\u957f\u57c2\u4e0a"
    ],
    "wof:name":"Changgengshang",
    "wof:placetype":"locality"
},
  "geometry": {"coordinates":[105.764,28.3785],"type":"Point"}
}