{
  "type": "Feature",
  "properties": {
    "gn:admin1_code":"29.0",
    "gn:asciiname":"Xinbijia",
    "gn:country_code":"CN",
    "gn:dem":1604,
    "gn:feature_class":"P",
    "gn:feature_code":"PPL",
    "gn:name":"Xinbijia",
    "gn:population":0,
    "gn:timezone":"Asia/Shanghai",
    "iso:country":"CN",
    "name:zho_x_preferred":[
        "\u65b0\u5fc5\u621b"
    ],
    "wof:name":"Xinbijia",
    "wof:placetype":"locality"
},
  "geometry": {"coordinates":[99.7911,22.6512],"type":"Point"}
}