{
  "type": "Feature",
  "properties": {
    "gn:admin1_code":"8.0",
    "gn:asciiname":"Jianshetun",
    "gn:country_code":"CN",
    "gn:dem":183,
    "gn:feature_class":"P",
    "gn:feature_code":"PPL",
    "gn:name":"Jianshetun",
    "gn:population":0,
    "gn:timezone":"Asia/Shanghai",
    "iso:country":"CN",
    "name:zho_x_preferred":[
        "\u5efa\u8bbe\u5c6f"
    ],
    "wof:name":"Jianshetun",
    "wof:placetype":"locality"
},
  "geometry": {"coordinates":[128.24348999999998,45.5312],"type":"Point"}
}