{
  "type": "Feature",
  "properties": {
    "gn:admin1_code":"5.0",
    "gn:asciiname":"Songzicun",
    "gn:country_code":"CN",
    "gn:dem":146,
    "gn:feature_class":"P",
    "gn:feature_code":"PPL",
    "gn:name":"Songzicun",
    "gn:population":0,
    "gn:timezone":"Asia/Shanghai",
    "iso:country":"CN",
    "name:zho_x_preferred":[
        "\u677e\u5b57\u6751"
    ],
    "wof:name":"Songzicun",
    "wof:placetype":"locality"
},
  "geometry": {"coordinates":[123.49536000000001,44.8292],"type":"Point"}
}