{
  "type": "Feature",
  "properties": {
    "gn:admin1_code":"3.0",
    "gn:asciiname":"Putianwu",
    "gn:country_code":"CN",
    "gn:dem":231,
    "gn:feature_class":"P",
    "gn:feature_code":"PPL",
    "gn:name":"Putianwu",
    "gn:population":0,
    "gn:timezone":"Asia/Shanghai",
    "iso:country":"CN",
    "name:zho_x_preferred":[
        "\u57d4\u7530\u575e"
    ],
    "wof:name":"Putianwu",
    "wof:placetype":"locality"
},
  "geometry": {"coordinates":[117.62065,28.6837],"type":"Point"}
}