{
  "type": "Feature",
  "properties": {
    "gn:admin1_code":"29.0",
    "gn:asciiname":"Nubatuoji",
    "gn:country_code":"CN",
    "gn:dem":1697,
    "gn:feature_class":"P",
    "gn:feature_code":"PPL",
    "gn:name":"Nubatuoji",
    "gn:population":0,
    "gn:timezone":"Asia/Shanghai",
    "iso:country":"CN",
    "name:zho_x_preferred":[
        "\u6012\u6252\u9a6e\u57fa"
    ],
    "wof:name":"Nubatuoji",
    "wof:placetype":"locality"
},
  "geometry": {"coordinates":[98.81780000000001,26.1361],"type":"Point"}
}