{
  "type": "Feature",
  "properties": {
    "gn:admin1_code":"10.0",
    "gn:asciiname":"Bodaowa",
    "gn:country_code":"CN",
    "gn:dem":13,
    "gn:feature_class":"P",
    "gn:feature_code":"PPL",
    "gn:name":"Bodaowa",
    "gn:population":0,
    "gn:timezone":"Asia/Shanghai",
    "iso:country":"CN",
    "name:zho_x_preferred":[
        "\u62e8\u9053\u6d3c"
    ],
    "wof:name":"Bodaowa",
    "wof:placetype":"locality"
},
  "geometry": {"coordinates":[119.43245,39.84633],"type":"Point"}
}