{
  "type": "Feature",
  "properties": {
    "gn:admin1_code":"10",
    "gn:asciiname":"Sandi Goumen",
    "gn:country_code":"CN",
    "gn:dem":542,
    "gn:feature_class":"P",
    "gn:feature_code":"PPL",
    "gn:name":"Sandi Goumen",
    "gn:population":0,
    "gn:timezone":"Asia/Shanghai",
    "iso:country":"CN",
    "name:zho_x_preferred":[
        "\u4e09\u5730\u6c9f\u95e8"
    ],
    "wof:name":"Sandi Goumen",
    "wof:placetype":"locality"
},
  "geometry": {"coordinates":[117.31738,40.91011],"type":"Point"}
}