{
  "type": "Feature",
  "properties": {
    "gn:admin1_code":"32.0",
    "gn:asciiname":"Guanfang",
    "gn:country_code":"CN",
    "gn:dem":1533,
    "gn:feature_class":"P",
    "gn:feature_code":"PPL",
    "gn:name":"Guanfang",
    "gn:population":0,
    "gn:timezone":"Asia/Shanghai",
    "iso:country":"CN",
    "name:zho_x_preferred":[
        "\u5b98\u623f"
    ],
    "wof:name":"Guanfang",
    "wof:placetype":"locality"
},
  "geometry": {"coordinates":[102.833,27.0033],"type":"Point"}
}