{
  "type": "Feature",
  "properties": {
    "gn:admin1_code":"5.0",
    "gn:asciiname":"Jiemancun",
    "gn:country_code":"CN",
    "gn:dem":150,
    "gn:feature_class":"P",
    "gn:feature_code":"PPL",
    "gn:name":"Jiemancun",
    "gn:population":0,
    "gn:timezone":"Asia/Shanghai",
    "iso:country":"CN",
    "name:zho_x_preferred":[
        "\u6770\u6ee1\u6751"
    ],
    "wof:name":"Jiemancun",
    "wof:placetype":"locality"
},
  "geometry": {"coordinates":[129.79724999999999,42.89881],"type":"Point"}
}