{
  "type": "Feature",
  "properties": {
    "gn:admin1_code":"3.0",
    "gn:asciiname":"Xiagaoli",
    "gn:country_code":"CN",
    "gn:dem":109,
    "gn:feature_class":"P",
    "gn:feature_code":"PPL",
    "gn:name":"Xiagaoli",
    "gn:population":0,
    "gn:timezone":"Asia/Shanghai",
    "iso:country":"CN",
    "name:und_x_variant":[
        "\u4e0b\u9ad8\u6817"
    ],
    "wof:name":"Xiagaoli",
    "wof:placetype":"locality"
},
  "geometry": {"coordinates":[114.47920999999999,27.90519],"type":"Point"}
}