{
  "type": "Feature",
  "properties": {
    "gn:admin1_code":"12.0",
    "gn:asciiname":"Chenjiagang",
    "gn:country_code":"CN",
    "gn:dem":76,
    "gn:feature_class":"P",
    "gn:feature_code":"PPL",
    "gn:name":"Chenjiagang",
    "gn:population":0,
    "gn:timezone":"Asia/Shanghai",
    "iso:country":"CN",
    "name:zho_x_preferred":[
        "\u9648\u5bb6\u5c97"
    ],
    "name:zho_x_variant":[
        "\u9648\u5bb6\u6e2f\u9547"
    ],
    "wof:name":"Chenjiagang",
    "wof:placetype":"locality"
},
  "geometry": {"coordinates":[112.31538999999999,31.47875],"type":"Point"}
}