{
  "type": "Feature",
  "properties": {
    "gn:admin1_code":"18.0",
    "gn:asciiname":"Decha",
    "gn:country_code":"CN",
    "gn:dem":763,
    "gn:feature_class":"P",
    "gn:feature_code":"PPL",
    "gn:name":"Decha",
    "gn:population":0,
    "gn:timezone":"Asia/Shanghai",
    "iso:country":"CN",
    "name:ceb_x_preferred":[
        "Decha"
    ],
    "name:fra_x_preferred":[
        "Decha"
    ],
    "name:swe_x_preferred":[
        "Decha"
    ],
    "name:zho_x_preferred":[
        "\u7684\u67e5"
    ],
    "wof:name":"Decha",
    "wof:placetype":"locality"
},
  "geometry": {"coordinates":[107.879,25.6939],"type":"Point"}
}