{
  "type": "Feature",
  "properties": {
    "gn:admin1_code":"24.0",
    "gn:asciiname":"Getaiping",
    "gn:country_code":"CN",
    "gn:dem":1373,
    "gn:feature_class":"P",
    "gn:feature_code":"PPL",
    "gn:name":"Getaiping",
    "gn:population":0,
    "gn:timezone":"Asia/Shanghai",
    "iso:country":"CN",
    "name:zho_x_preferred":[
        "\u572a\u53f0\u576a"
    ],
    "wof:name":"Getaiping",
    "wof:placetype":"locality"
},
  "geometry": {"coordinates":[112.15639,38.3251],"type":"Point"}
}