{
  "type": "Feature",
  "properties": {
    "gn:admin1_code":"16.0",
    "gn:asciiname":"Huajia",
    "gn:country_code":"CN",
    "gn:dem":138,
    "gn:feature_class":"P",
    "gn:feature_code":"PPL",
    "gn:name":"Huajia",
    "gn:population":0,
    "gn:timezone":"Asia/Shanghai",
    "iso:country":"CN",
    "name:zho_x_preferred":[
        "\u534e\u4f73"
    ],
    "wof:name":"Huajia",
    "wof:placetype":"locality"
},
  "geometry": {"coordinates":[108.621,22.5354],"type":"Point"}
}