{
  "type": "Feature",
  "properties": {
    "gn:admin1_code":"1.0",
    "gn:asciiname":"Chen'ercun",
    "gn:country_code":"CN",
    "gn:dem":25,
    "gn:feature_class":"P",
    "gn:feature_code":"PPL",
    "gn:name":"Chen\u2019ercun",
    "gn:population":0,
    "gn:timezone":"Asia/Shanghai",
    "iso:country":"CN",
    "name:und_x_variant":[
        "Chen\u2019ercun"
    ],
    "name:zho_x_preferred":[
        "\u9648\u4e8c\u6751"
    ],
    "wof:name":"Chen'ercun",
    "wof:placetype":"locality"
},
  "geometry": {"coordinates":[117.09072999999999,33.22221],"type":"Point"}
}