{
  "type": "Feature",
  "properties": {
    "gn:admin1_code":"33.0",
    "gn:asciiname":"Taoli",
    "gn:country_code":"CN",
    "gn:dem":432,
    "gn:feature_class":"P",
    "gn:feature_code":"PPL",
    "gn:name":"Taoli",
    "gn:population":0,
    "gn:timezone":"Asia/Shanghai",
    "iso:country":"CN",
    "name:zho_x_preferred":[
        "\u6843\u674e"
    ],
    "wof:name":"Taoli",
    "wof:placetype":"locality"
},
  "geometry": {"coordinates":[108.60905,30.73458],"type":"Point"}
}