{
  "type": "Feature",
  "properties": {
    "gn:admin1_code":"32.0",
    "gn:asciiname":"Tianmusi",
    "gn:country_code":"CN",
    "gn:dem":856,
    "gn:feature_class":"P",
    "gn:feature_code":"PPL",
    "gn:name":"Tianmusi",
    "gn:population":0,
    "gn:timezone":"Asia/Shanghai",
    "iso:country":"CN",
    "name:zho_x_preferred":[
        "\u5929\u76ee\u5bfa"
    ],
    "wof:name":"Tianmusi",
    "wof:placetype":"locality"
},
  "geometry": {"coordinates":[103.32997,30.08151],"type":"Point"}
}