{
  "type": "Feature",
  "properties": {
    "gn:admin1_code":"29.0",
    "gn:asciiname":"Pijiang",
    "gn:country_code":"CN",
    "gn:dem":2902,
    "gn:feature_class":"P",
    "gn:feature_code":"PPL",
    "gn:name":"Pijiang",
    "gn:population":0,
    "gn:timezone":"Asia/Shanghai",
    "iso:country":"CN",
    "name:zho_x_preferred":[
        "\u76ae\u5320"
    ],
    "wof:name":"Pijiang",
    "wof:placetype":"locality"
},
  "geometry": {"coordinates":[100.631,27.0529],"type":"Point"}
}