{
  "type": "Feature",
  "properties": {
    "gn:admin1_code":"14.0",
    "gn:asciiname":"Walong",
    "gn:country_code":"CN",
    "gn:dem":4548,
    "gn:feature_class":"P",
    "gn:feature_code":"PPL",
    "gn:name":"Walong",
    "gn:population":0,
    "gn:timezone":"Asia/Urumqi",
    "iso:country":"CN",
    "name:zho_x_preferred":[
        "\u74e6\u804b"
    ],
    "name:zho_x_variant":[
        "\u74e6\u5f04\u9547"
    ],
    "wof:name":"Walong",
    "wof:placetype":"locality"
},
  "geometry": {"coordinates":[97.31596,30.43415],"type":"Point"}
}