{
  "type": "Feature",
  "properties": {
    "gn:admin1_code":"8.0",
    "gn:asciiname":"Huzhucun",
    "gn:country_code":"CN",
    "gn:dem":175,
    "gn:feature_class":"P",
    "gn:feature_code":"PPL",
    "gn:name":"Huzhucun",
    "gn:population":0,
    "gn:timezone":"Asia/Shanghai",
    "iso:country":"CN",
    "name:zho_x_preferred":[
        "\u4e92\u52a9\u6751"
    ],
    "wof:name":"Huzhucun",
    "wof:placetype":"locality"
},
  "geometry": {"coordinates":[125.63551,45.71982],"type":"Point"}
}