{
  "type": "Feature",
  "properties": {
    "gn:admin1_code":"4.0",
    "gn:asciiname":"Jiejiadai",
    "gn:country_code":"CN",
    "gn:dem":4,
    "gn:feature_class":"P",
    "gn:feature_code":"PPL",
    "gn:name":"Jiejiadai",
    "gn:population":0,
    "gn:timezone":"Asia/Shanghai",
    "iso:country":"CN",
    "name:zho_x_preferred":[
        "\u89e3\u5bb6\u57ed"
    ],
    "wof:name":"Jiejiadai",
    "wof:placetype":"locality"
},
  "geometry": {"coordinates":[119.75512999999999,32.25747],"type":"Point"}
}