{
  "type": "Feature",
  "properties": {
    "gn:admin1_code":"5.0",
    "gn:asciiname":"Xiachedaoling",
    "gn:country_code":"CN",
    "gn:dem":416,
    "gn:feature_class":"P",
    "gn:feature_code":"PPL",
    "gn:name":"Xiachedaoling",
    "gn:population":0,
    "gn:timezone":"Asia/Shanghai",
    "iso:country":"CN",
    "name:und_x_variant":[
        "\u4e0b\u8f66\u9053\u5cad"
    ],
    "wof:name":"Xiachedaoling",
    "wof:placetype":"locality"
},
  "geometry": {"coordinates":[125.54333,41.53355],"type":"Point"}
}