{
  "type": "Feature",
  "properties": {
    "gn:admin1_code":"9.0",
    "gn:asciiname":"Shuangmiaoji",
    "gn:country_code":"CN",
    "gn:dem":58,
    "gn:feature_class":"P",
    "gn:feature_code":"PPL",
    "gn:name":"Shuangmiaoji",
    "gn:population":0,
    "gn:timezone":"Asia/Shanghai",
    "iso:country":"CN",
    "name:zho_x_preferred":[
        "\u53cc\u5e99\u96c6"
    ],
    "wof:name":"Shuangmiaoji",
    "wof:placetype":"locality"
},
  "geometry": {"coordinates":[115.50797,32.20841],"type":"Point"}
}