{
  "type": "Feature",
  "properties": {
    "gn:admin1_code":"11",
    "gn:asciiname":"Hekou",
    "gn:country_code":"CN",
    "gn:dem":42,
    "gn:feature_class":"P",
    "gn:feature_code":"PPL",
    "gn:name":"Hekou",
    "gn:population":0,
    "gn:timezone":"Asia/Shanghai",
    "iso:country":"CN",
    "name:ceb_x_preferred":[
        "Hekou"
    ],
    "name:deu_x_preferred":[
        "Hekou"
    ],
    "name:fra_x_preferred":[
        "Hekou"
    ],
    "name:nor_x_preferred":[
        "Hekou"
    ],
    "name:rus_x_preferred":[
        "\u0425\u044d\u043a\u043e\u0443"
    ],
    "name:swe_x_preferred":[
        "Hekou"
    ],
    "wof:name":"Hekou",
    "wof:placetype":"locality"
},
  "geometry": {"coordinates":[112.87860999999999,27.79306],"type":"Point"}
}