{
  "type": "Feature",
  "properties": {
    "gn:admin1_code":"14.0",
    "gn:asciiname":"Sejiang'oucun",
    "gn:country_code":"CN",
    "gn:dem":3817,
    "gn:feature_class":"P",
    "gn:feature_code":"PPL",
    "gn:name":"Sejiang\u2019oucun",
    "gn:population":0,
    "gn:timezone":"Asia/Urumqi",
    "iso:country":"CN",
    "name:und_x_variant":[
        "Sejiang\u2019oucun"
    ],
    "name:zho_x_preferred":[
        "\u8272\u6c5f\u6b27\u6751"
    ],
    "wof:name":"Sejiang'oucun",
    "wof:placetype":"locality"
},
  "geometry": {"coordinates":[92.86711,30.06032],"type":"Point"}
}