{
  "type": "Feature",
  "properties": {
    "gn:admin1_code":"16.0",
    "gn:asciiname":"Dengcaowen",
    "gn:country_code":"CN",
    "gn:dem":70,
    "gn:feature_class":"P",
    "gn:feature_code":"PPL",
    "gn:name":"Dengcaowen",
    "gn:population":0,
    "gn:timezone":"Asia/Shanghai",
    "iso:country":"CN",
    "name:zho_x_preferred":[
        "\u706f\u8349\u6c76"
    ],
    "wof:name":"Dengcaowen",
    "wof:placetype":"locality"
},
  "geometry": {"coordinates":[109.45699999999999,23.112],"type":"Point"}
}