{
  "type": "Feature",
  "properties": {
    "gn:admin1_code":"11",
    "gn:asciiname":"Zhengjiamenkou",
    "gn:country_code":"CN",
    "gn:dem":241,
    "gn:feature_class":"P",
    "gn:feature_code":"PPL",
    "gn:name":"Zhengjiamenkou",
    "gn:population":0,
    "gn:timezone":"Asia/Shanghai",
    "iso:country":"CN",
    "name:zho_x_preferred":[
        "\u90d1\u5bb6\u95e8\u53e3"
    ],
    "wof:name":"Zhengjiamenkou",
    "wof:placetype":"locality"
},
  "geometry": {"coordinates":[111.98520000000001,26.50322],"type":"Point"}
}