{
  "type": "Feature",
  "properties": {
    "gn:admin1_code":"14.0",
    "gn:asciiname":"Kare",
    "gn:country_code":"CN",
    "gn:dem":4668,
    "gn:feature_class":"P",
    "gn:feature_code":"PPL",
    "gn:name":"Kare",
    "gn:population":0,
    "gn:timezone":"Asia/Urumqi",
    "iso:country":"CN",
    "name:fra_x_preferred":[
        "Kare"
    ],
    "name:msa_x_preferred":[
        "Kare"
    ],
    "name:por_x_preferred":[
        "Kare"
    ],
    "name:slv_x_preferred":[
        "Kare"
    ],
    "name:srp_x_preferred":[
        "\u041a\u0430\u0440\u0435"
    ],
    "name:zho_x_preferred":[
        "\u5494\u70ed"
    ],
    "wof:name":"Kare",
    "wof:placetype":"locality"
},
  "geometry": {"coordinates":[91.62269999999999,31.35931],"type":"Point"}
}