{
  "type": "Feature",
  "properties": {
    "gn:admin1_code":"33.0",
    "gn:asciiname":"Tuchenggou",
    "gn:country_code":"CN",
    "gn:dem":617,
    "gn:feature_class":"P",
    "gn:feature_code":"PPL",
    "gn:name":"Tuchenggou",
    "gn:population":0,
    "gn:timezone":"Asia/Shanghai",
    "iso:country":"CN",
    "name:zho_x_preferred":[
        "\u571f\u57ce\u6c9f"
    ],
    "wof:name":"Tuchenggou",
    "wof:placetype":"locality"
},
  "geometry": {"coordinates":[106.727,28.6795],"type":"Point"}
}