{
  "type": "Feature",
  "properties": {
    "gn:admin1_code":"5.0",
    "gn:asciiname":"Xiaobeigou",
    "gn:country_code":"CN",
    "gn:dem":264,
    "gn:feature_class":"P",
    "gn:feature_code":"PPL",
    "gn:name":"Xiaobeigou",
    "gn:population":0,
    "gn:timezone":"Asia/Shanghai",
    "iso:country":"CN",
    "name:und_x_variant":[
        "\u5c0f\u5317\u6c9f"
    ],
    "wof:name":"Xiaobeigou",
    "wof:placetype":"locality"
},
  "geometry": {"coordinates":[129.26962,42.90792],"type":"Point"}
}