{
  "type": "Feature",
  "properties": {
    "gn:admin1_code":"14.0",
    "gn:asciiname":"Longqing",
    "gn:country_code":"CN",
    "gn:dem":4500,
    "gn:feature_class":"P",
    "gn:feature_code":"PPL",
    "gn:name":"Longqing",
    "gn:population":0,
    "gn:timezone":"Asia/Urumqi",
    "iso:country":"CN",
    "name:zho_x_preferred":[
        "\u9f99\u9752"
    ],
    "wof:name":"Longqing",
    "wof:placetype":"locality"
},
  "geometry": {"coordinates":[94.08069999999999,31.47923],"type":"Point"}
}