{
  "type": "Feature",
  "properties": {
    "gn:admin1_code":"20",
    "gn:asciiname":"Labudalin Nongmuchang Liudui",
    "gn:country_code":"CN",
    "gn:dem":573,
    "gn:feature_class":"P",
    "gn:feature_code":"PPLF",
    "gn:name":"Labudalin Nongmuchang Liudui",
    "gn:population":0,
    "gn:timezone":"Asia/Shanghai",
    "iso:country":"CN",
    "wof:name":"Labudalin Nongmuchang Liudui",
    "wof:placetype":"locality"
},
  "geometry": {"coordinates":[119.80249999999999,50.17944],"type":"Point"}
}