{
  "type": "Feature",
  "properties": {
    "gn:admin1_code":"18",
    "gn:asciiname":"Maopo",
    "gn:country_code":"CN",
    "gn:dem":1234,
    "gn:feature_class":"P",
    "gn:feature_code":"PPL",
    "gn:name":"Maopo",
    "gn:population":0,
    "gn:timezone":"Asia/Shanghai",
    "iso:country":"CN",
    "name:zho_x_preferred":[
        "\u732b\u5761"
    ],
    "wof:name":"Maopo",
    "wof:placetype":"locality"
},
  "geometry": {"coordinates":[106.312,26.7878],"type":"Point"}
}