{
  "type": "Feature",
  "properties": {
    "gn:admin1_code":"33.0",
    "gn:asciiname":"Nanlingguan",
    "gn:country_code":"CN",
    "gn:dem":1196,
    "gn:feature_class":"P",
    "gn:feature_code":"PPL",
    "gn:name":"Nanlingguan",
    "gn:population":0,
    "gn:timezone":"Asia/Shanghai",
    "iso:country":"CN",
    "name:zho_x_preferred":[
        "\u5357\u9675\u89c2"
    ],
    "wof:name":"Nanlingguan",
    "wof:placetype":"locality"
},
  "geometry": {"coordinates":[109.87569999999999,31.04144],"type":"Point"}
}