{
  "type": "Feature",
  "properties": {
    "gn:admin1_code":"5.0",
    "gn:asciiname":"Tongquancun",
    "gn:country_code":"CN",
    "gn:dem":132,
    "gn:feature_class":"P",
    "gn:feature_code":"PPL",
    "gn:name":"Tongquancun",
    "gn:population":0,
    "gn:timezone":"Asia/Shanghai",
    "iso:country":"CN",
    "name:zho_x_preferred":[
        "\u540c\u6743\u6751"
    ],
    "wof:name":"Tongquancun",
    "wof:placetype":"locality"
},
  "geometry": {"coordinates":[123.86725,45.46398],"type":"Point"}
}