{
  "type": "Feature",
  "properties": {
    "gn:admin1_code":"32.0",
    "gn:asciiname":"Jiaxue",
    "gn:country_code":"CN",
    "gn:dem":2311,
    "gn:feature_class":"P",
    "gn:feature_code":"PPL",
    "gn:name":"Jiaxue",
    "gn:population":0,
    "gn:timezone":"Asia/Shanghai",
    "iso:country":"CN",
    "name:zho_x_preferred":[
        "\u7532\u5b66"
    ],
    "wof:name":"Jiaxue",
    "wof:placetype":"locality"
},
  "geometry": {"coordinates":[99.2894,28.2927],"type":"Point"}
}