{
  "type": "Feature",
  "properties": {
    "gn:admin1_code":"29.0",
    "gn:asciiname":"Duoyijing",
    "gn:country_code":"CN",
    "gn:dem":1383,
    "gn:feature_class":"P",
    "gn:feature_code":"PPL",
    "gn:name":"Duoyijing",
    "gn:population":0,
    "gn:timezone":"Asia/Shanghai",
    "iso:country":"CN",
    "name:zho_x_preferred":[
        "\u591a\u4f9d\u4e95"
    ],
    "wof:name":"Duoyijing",
    "wof:placetype":"locality"
},
  "geometry": {"coordinates":[100.506,25.0784],"type":"Point"}
}