{
  "type": "Feature",
  "properties": {
    "gn:admin1_code":"30",
    "gn:asciiname":"Shangnanyang",
    "gn:country_code":"CN",
    "gn:dem":224,
    "gn:feature_class":"P",
    "gn:feature_code":"PPL",
    "gn:name":"Shangnanyang",
    "gn:population":0,
    "gn:timezone":"Asia/Shanghai",
    "iso:country":"CN",
    "name:und_x_variant":[
        "\u4e0a\u5357\u6d0b",
        "Shangnanyang"
    ],
    "wof:name":"Shangnanyang",
    "wof:placetype":"locality"
},
  "geometry": {"coordinates":[116.43892,24.12846],"type":"Point"}
}