{
  "type": "Feature",
  "properties": {
    "gn:admin1_code":"11.0",
    "gn:asciiname":"Zhujiapo",
    "gn:country_code":"CN",
    "gn:dem":1047,
    "gn:feature_class":"P",
    "gn:feature_code":"PPL",
    "gn:name":"Zhujiapo",
    "gn:population":0,
    "gn:timezone":"Asia/Shanghai",
    "iso:country":"CN",
    "name:zho_x_preferred":[
        "\u6731\u5bb6\u5761"
    ],
    "wof:name":"Zhujiapo",
    "wof:placetype":"locality"
},
  "geometry": {"coordinates":[109.64473999999998,29.47389],"type":"Point"}
}