{
  "type": "Feature",
  "properties": {
    "gn:admin1_code":"16.0",
    "gn:asciiname":"Jiuyang",
    "gn:country_code":"CN",
    "gn:dem":972,
    "gn:feature_class":"P",
    "gn:feature_code":"PPL",
    "gn:name":"Jiuyang",
    "gn:population":0,
    "gn:timezone":"Asia/Shanghai",
    "iso:country":"CN",
    "name:zho_x_preferred":[
        "\u4e5d\u7f8a"
    ],
    "wof:name":"Jiuyang",
    "wof:placetype":"locality"
},
  "geometry": {"coordinates":[108.65000000000001,25.305],"type":"Point"}
}