{
  "type": "Feature",
  "properties": {
    "gn:admin1_code":"32.0",
    "gn:asciiname":"Chuanzhumiao",
    "gn:country_code":"CN",
    "gn:dem":373,
    "gn:feature_class":"P",
    "gn:feature_code":"PPL",
    "gn:name":"Chuanzhumiao",
    "gn:population":0,
    "gn:timezone":"Asia/Shanghai",
    "iso:country":"CN",
    "name:zho_x_preferred":[
        "\u5ddd\u4e3b\u5e99"
    ],
    "wof:name":"Chuanzhumiao",
    "wof:placetype":"locality"
},
  "geometry": {"coordinates":[105.23426000000001,29.78881],"type":"Point"}
}