{
  "type": "Feature",
  "properties": {
    "gn:admin1_code":"16.0",
    "gn:asciiname":"Ba'e",
    "gn:country_code":"CN",
    "gn:dem":812,
    "gn:feature_class":"P",
    "gn:feature_code":"PPL",
    "gn:name":"Ba\u2019e",
    "gn:population":0,
    "gn:timezone":"Asia/Shanghai",
    "iso:country":"CN",
    "name:und_x_variant":[
        "Ba\u2019e"
    ],
    "name:zho_x_preferred":[
        "\u5df4\u5ce8"
    ],
    "wof:name":"Ba'e",
    "wof:placetype":"locality"
},
  "geometry": {"coordinates":[107.25700000000001,25.5024],"type":"Point"}
}