{
  "type": "Feature",
  "properties": {
    "gn:admin1_code":"26.0",
    "gn:asciiname":"Anzi",
    "gn:country_code":"CN",
    "gn:dem":1230,
    "gn:feature_class":"P",
    "gn:feature_code":"PPL",
    "gn:name":"Anzi",
    "gn:population":0,
    "gn:timezone":"Asia/Shanghai",
    "iso:country":"CN",
    "name:ceb_x_preferred":[
        "Anzi"
    ],
    "name:deu_x_preferred":[
        "Anzi"
    ],
    "name:hun_x_preferred":[
        "Anzi"
    ],
    "name:ita_x_preferred":[
        "Anzi"
    ],
    "name:ron_x_preferred":[
        "Anzi"
    ],
    "name:swe_x_preferred":[
        "Anzi"
    ],
    "name:zho_x_preferred":[
        "\u5b89\u5b50"
    ],
    "wof:name":"Anzi",
    "wof:placetype":"locality"
},
  "geometry": {"coordinates":[108.7075,35.11528],"type":"Point"}
}