{
  "type": "Feature",
  "properties": {
    "gn:admin1_code":"8.0",
    "gn:asciiname":"Sizuofang",
    "gn:country_code":"CN",
    "gn:dem":122,
    "gn:feature_class":"P",
    "gn:feature_code":"PPL",
    "gn:name":"Sizuofang",
    "gn:population":0,
    "gn:timezone":"Asia/Shanghai",
    "iso:country":"CN",
    "name:zho_x_preferred":[
        "\u56db\u5ea7\u623f"
    ],
    "wof:name":"Sizuofang",
    "wof:placetype":"locality"
},
  "geometry": {"coordinates":[126.16833,45.76454],"type":"Point"}
}