{
  "type": "Feature",
  "properties": {
    "gn:admin1_code":"15.0",
    "gn:asciiname":"Xinsheng",
    "gn:country_code":"CN",
    "gn:dem":1584,
    "gn:feature_class":"P",
    "gn:feature_code":"PPL",
    "gn:name":"Xinsheng",
    "gn:population":0,
    "gn:timezone":"Asia/Shanghai",
    "iso:country":"CN",
    "name:ceb_x_preferred":[
        "Xinsheng"
    ],
    "name:deu_x_preferred":[
        "Xinsheng"
    ],
    "name:swe_x_preferred":[
        "Xinsheng"
    ],
    "name:und_x_variant":[
        "\u65b0\u80dc"
    ],
    "wof:name":"Xinsheng",
    "wof:placetype":"locality"
},
  "geometry": {"coordinates":[105.80034999999999,35.36121],"type":"Point"}
}