{
  "type": "Feature",
  "properties": {
    "gn:admin1_code":"19.0",
    "gn:asciiname":"Chujiatun",
    "gn:country_code":"CN",
    "gn:dem":24,
    "gn:feature_class":"P",
    "gn:feature_code":"PPL",
    "gn:name":"Chujiatun",
    "gn:population":0,
    "gn:timezone":"Asia/Shanghai",
    "iso:country":"CN",
    "name:zho_x_preferred":[
        "\u521d\u5bb6\u5c6f"
    ],
    "wof:name":"Chujiatun",
    "wof:placetype":"locality"
},
  "geometry": {"coordinates":[123.38831999999999,39.91978],"type":"Point"}
}