{
  "type": "Feature",
  "properties": {
    "gn:admin1_code":"13",
    "gn:asciiname":"Kaxikuri",
    "gn:country_code":"CN",
    "gn:dem":1256,
    "gn:feature_class":"P",
    "gn:feature_code":"PPL",
    "gn:name":"Kaxikuri",
    "gn:population":0,
    "gn:timezone":"Asia/Shanghai",
    "iso:country":"CN",
    "name:zho_x_preferred":[
        "\u5580\u5e0c\u5e93\u65e5"
    ],
    "wof:name":"Kaxikuri",
    "wof:placetype":"locality"
},
  "geometry": {"coordinates":[76.24203,39.32359],"type":"Point"}
}