{
  "type": "Feature",
  "properties": {
    "gn:admin1_code":"26.0",
    "gn:asciiname":"Dafenyuan",
    "gn:country_code":"CN",
    "gn:dem":660,
    "gn:feature_class":"P",
    "gn:feature_code":"PPL",
    "gn:name":"Dafenyuan",
    "gn:population":0,
    "gn:timezone":"Asia/Shanghai",
    "iso:country":"CN",
    "name:und_x_variant":[
        "\u5927\u575f\u56ed"
    ],
    "wof:name":"Dafenyuan",
    "wof:placetype":"locality"
},
  "geometry": {"coordinates":[107.35129000000001,32.93662],"type":"Point"}
}