{
  "type": "Feature",
  "properties": {
    "gn:admin1_code":"14.0",
    "gn:asciiname":"Puqingduocun",
    "gn:country_code":"CN",
    "gn:dem":4776,
    "gn:feature_class":"P",
    "gn:feature_code":"PPL",
    "gn:name":"Puqingduocun",
    "gn:population":0,
    "gn:timezone":"Asia/Urumqi",
    "iso:country":"CN",
    "name:zho_x_preferred":[
        "\u666e\u5e86\u6735\u6751"
    ],
    "wof:name":"Puqingduocun",
    "wof:placetype":"locality"
},
  "geometry": {"coordinates":[91.40184000000001,31.14554],"type":"Point"}
}