{
  "type": "Feature",
  "properties": {
    "gn:admin1_code":"11",
    "gn:asciiname":"Shuangjiangkou",
    "gn:cc2":"CN",
    "gn:country_code":"CN",
    "gn:dem":57,
    "gn:feature_class":"P",
    "gn:feature_code":"PPL",
    "gn:name":"Shuangjiangkou",
    "gn:population":0,
    "gn:timezone":"Asia/Shanghai",
    "iso:country":"CN",
    "name:und_x_variant":[
        "Shuang-chiang-k\u2019ou",
        "Shuangjiangkou"
    ],
    "wof:name":"Shuangjiangkou",
    "wof:placetype":"locality"
},
  "geometry": {"coordinates":[112.68333,27.98333],"type":"Point"}
}