{
  "type": "Feature",
  "properties": {
    "gn:admin1_code":"30.0",
    "gn:asciiname":"Bantianwei",
    "gn:country_code":"CN",
    "gn:dem":292,
    "gn:feature_class":"P",
    "gn:feature_code":"PPL",
    "gn:name":"Bantianwei",
    "gn:population":0,
    "gn:timezone":"Asia/Shanghai",
    "iso:country":"CN",
    "name:zho_x_preferred":[
        "\u534a\u5929\u5c3e"
    ],
    "wof:name":"Bantianwei",
    "wof:placetype":"locality"
},
  "geometry": {"coordinates":[115.06741,23.32224],"type":"Point"}
}