{
  "type": "Feature",
  "properties": {
    "gn:admin1_code":"4.0",
    "gn:asciiname":"Mengwan",
    "gn:country_code":"CN",
    "gn:dem":6,
    "gn:feature_class":"P",
    "gn:feature_code":"PPL",
    "gn:name":"Mengwan",
    "gn:population":0,
    "gn:timezone":"Asia/Shanghai",
    "iso:country":"CN",
    "name:und_x_variant":[
        "\u5b5f\u6e7e"
    ],
    "name:zho_x_preferred":[
        "\u5b5f\u6e7e"
    ],
    "wof:name":"Mengwan",
    "wof:placetype":"locality"
},
  "geometry": {"coordinates":[120.0189,32.65395],"type":"Point"}
}