{
  "type": "Feature",
  "properties": {
    "gn:admin1_code":"10",
    "gn:asciiname":"Dongdibei",
    "gn:country_code":"CN",
    "gn:dem":40,
    "gn:feature_class":"P",
    "gn:feature_code":"PPL",
    "gn:name":"Dongdibei",
    "gn:population":0,
    "gn:timezone":"Asia/Shanghai",
    "iso:country":"CN",
    "name:zho_x_preferred":[
        "\u4e1c\u5824\u5317"
    ],
    "wof:name":"Dongdibei",
    "wof:placetype":"locality"
},
  "geometry": {"coordinates":[115.264,38.8193],"type":"Point"}
}