{
  "type": "Feature",
  "properties": {
    "gn:admin1_code":"11.0",
    "gn:asciiname":"Toujiankeng",
    "gn:country_code":"CN",
    "gn:dem":813,
    "gn:feature_class":"P",
    "gn:feature_code":"PPL",
    "gn:name":"Toujiankeng",
    "gn:population":0,
    "gn:timezone":"Asia/Shanghai",
    "iso:country":"CN",
    "name:zho_x_preferred":[
        "\u5934\u67a7\u5751"
    ],
    "wof:name":"Toujiankeng",
    "wof:placetype":"locality"
},
  "geometry": {"coordinates":[113.70628000000001,26.15585],"type":"Point"}
}