{
  "type": "Feature",
  "properties": {
    "gn:admin1_code":"12",
    "gn:asciiname":"Bailaya",
    "gn:country_code":"CN",
    "gn:dem":304,
    "gn:feature_class":"P",
    "gn:feature_code":"PPL",
    "gn:name":"Bailaya",
    "gn:population":0,
    "gn:timezone":"Asia/Shanghai",
    "iso:country":"CN",
    "name:zho_x_preferred":[
        "\u767d\u8721\u57ad"
    ],
    "wof:name":"Bailaya",
    "wof:placetype":"locality"
},
  "geometry": {"coordinates":[110.72129,32.90032],"type":"Point"}
}