{
  "type": "Feature",
  "properties": {
    "gn:admin1_code":"1.0",
    "gn:asciiname":"Hezhong",
    "gn:country_code":"CN",
    "gn:dem":20,
    "gn:feature_class":"P",
    "gn:feature_code":"PPL",
    "gn:name":"Hezhong",
    "gn:population":0,
    "gn:timezone":"Asia/Shanghai",
    "iso:country":"CN",
    "name:zho_x_preferred":[
        "\u6cb3\u4e2d"
    ],
    "wof:name":"Hezhong",
    "wof:placetype":"locality"
},
  "geometry": {"coordinates":[118.31676000000002,30.8382],"type":"Point"}
}