{
  "type": "Feature",
  "properties": {
    "gn:admin1_code":"16",
    "gn:asciiname":"Chima",
    "gn:cc2":"CN",
    "gn:country_code":"CN",
    "gn:dem":22,
    "gn:feature_class":"P",
    "gn:feature_code":"PPL",
    "gn:name":"Chima",
    "gn:population":0,
    "gn:timezone":"Asia/Shanghai",
    "iso:country":"CN",
    "name:ceb_x_preferred":[
        "Chima"
    ],
    "name:deu_x_preferred":[
        "Chima"
    ],
    "name:ita_x_preferred":[
        "Chima"
    ],
    "name:nld_x_preferred":[
        "Chima"
    ],
    "name:swe_x_preferred":[
        "Chima"
    ],
    "name:und_x_variant":[
        "Pai-ma-hs\u00fc",
        "Chima"
    ],
    "wof:name":"Chima",
    "wof:placetype":"locality"
},
  "geometry": {"coordinates":[110.59278,23.46028],"type":"Point"}
}