{
  "type": "Feature",
  "properties": {
    "gn:admin1_code":"15.0",
    "gn:asciiname":"Gongjiashan",
    "gn:country_code":"CN",
    "gn:dem":1535,
    "gn:feature_class":"P",
    "gn:feature_code":"PPL",
    "gn:name":"Gongjiashan",
    "gn:population":0,
    "gn:timezone":"Asia/Shanghai",
    "iso:country":"CN",
    "name:und_x_variant":[
        "\u5de9\u5bb6\u5c71"
    ],
    "wof:name":"Gongjiashan",
    "wof:placetype":"locality"
},
  "geometry": {"coordinates":[105.51007,33.33000999999999],"type":"Point"}
}