{
  "type": "Feature",
  "properties": {
    "gn:admin1_code":"1.0",
    "gn:asciiname":"Daluyingcun",
    "gn:country_code":"CN",
    "gn:dem":40,
    "gn:feature_class":"P",
    "gn:feature_code":"PPL",
    "gn:name":"Dal\u00fcyingcun",
    "gn:population":0,
    "gn:timezone":"Asia/Shanghai",
    "iso:country":"CN",
    "name:und_x_variant":[
        "Dal\u00fcyingcun"
    ],
    "name:zho_x_preferred":[
        "\u5927\u5415\u8425\u6751"
    ],
    "wof:name":"Daluyingcun",
    "wof:placetype":"locality"
},
  "geometry": {"coordinates":[115.31531,33.20111],"type":"Point"}
}