{
  "type": "Feature",
  "properties": {
    "gn:admin1_code":"24.0",
    "gn:asciiname":"Yantou",
    "gn:country_code":"CN",
    "gn:dem":1254,
    "gn:feature_class":"P",
    "gn:feature_code":"PPLA4",
    "gn:name":"Yantou",
    "gn:population":0,
    "gn:timezone":"Asia/Shanghai",
    "iso:country":"CN",
    "name:und_x_variant":[
        "Yen-t\u2019ou",
        "Yantou",
        "\u5ca9\u5934",
        "Yantou Xiang",
        "\u5ca9\u5934\u4e61"
    ],
    "wof:name":"Yantou",
    "wof:placetype":"locality"
},
  "geometry": {"coordinates":[113.32902,39.06059000000001],"type":"Point"}
}