{
  "type": "Feature",
  "properties": {
    "gn:admin1_code":"1.0",
    "gn:asciiname":"Chenlaojiacun",
    "gn:country_code":"CN",
    "gn:dem":32,
    "gn:feature_class":"P",
    "gn:feature_code":"PPL",
    "gn:name":"Chenlaojiacun",
    "gn:population":0,
    "gn:timezone":"Asia/Shanghai",
    "iso:country":"CN",
    "name:und_x_variant":[
        "Chenlaojia"
    ],
    "name:zho_x_preferred":[
        "\u9648\u8001\u5bb6\u6751"
    ],
    "wof:name":"Chenlaojiacun",
    "wof:placetype":"locality"
},
  "geometry": {"coordinates":[116.28333000000001,33.71667],"type":"Point"}
}