{
  "type": "Feature",
  "properties": {
    "gn:admin1_code":"02",
    "gn:asciiname":"Kongjiatan",
    "gn:cc2":"CN",
    "gn:country_code":"CN",
    "gn:dem":4,
    "gn:feature_class":"P",
    "gn:feature_code":"PPL",
    "gn:name":"Kongjiatan",
    "gn:population":0,
    "gn:timezone":"Asia/Shanghai",
    "iso:country":"CN",
    "name:und_x_variant":[
        "K\u2019ung-chia-t\u2019an",
        "Kongjiatan"
    ],
    "name:zho_x_preferred":[
        "\u5b54\u5bb6\u6f6d"
    ],
    "wof:name":"Kongjiatan",
    "wof:placetype":"locality"
},
  "geometry": {"coordinates":[121.59472,29.7375],"type":"Point"}
}