{
  "type": "Feature",
  "properties": {
    "gn:admin1_code":"10",
    "gn:asciiname":"Houmengji",
    "gn:country_code":"CN",
    "gn:dem":19,
    "gn:feature_class":"P",
    "gn:feature_code":"PPL",
    "gn:name":"Houmengji",
    "gn:population":0,
    "gn:timezone":"Asia/Shanghai",
    "iso:country":"CN",
    "name:zho_x_preferred":[
        "\u4faf\u68a6\u5409"
    ],
    "wof:name":"Houmengji",
    "wof:placetype":"locality"
},
  "geometry": {"coordinates":[116.66463,37.75995],"type":"Point"}
}