{
  "type": "Feature",
  "properties": {
    "gn:admin1_code":"14.0",
    "gn:asciiname":"Regailangcun",
    "gn:country_code":"CN",
    "gn:dem":4523,
    "gn:feature_class":"P",
    "gn:feature_code":"PPL",
    "gn:name":"Regailangcun",
    "gn:population":0,
    "gn:timezone":"Asia/Urumqi",
    "iso:country":"CN",
    "name:zho_x_preferred":[
        "\u70ed\u6539\u6717\u6751"
    ],
    "wof:name":"Regailangcun",
    "wof:placetype":"locality"
},
  "geometry": {"coordinates":[93.23435000000001,32.11653],"type":"Point"}
}