{
  "type": "Feature",
  "properties": {
    "gn:admin1_code":"11.0",
    "gn:asciiname":"Baqiuli",
    "gn:country_code":"CN",
    "gn:dem":1289,
    "gn:feature_class":"P",
    "gn:feature_code":"PPL",
    "gn:name":"Baqiuli",
    "gn:population":0,
    "gn:timezone":"Asia/Shanghai",
    "iso:country":"CN",
    "name:zho_x_preferred":[
        "\u516b\u4e18\u91cc"
    ],
    "wof:name":"Baqiuli",
    "wof:placetype":"locality"
},
  "geometry": {"coordinates":[113.8359,26.09314],"type":"Point"}
}