{
  "type": "Feature",
  "properties": {
    "gn:admin1_code":"18",
    "gn:asciiname":"Huangjia Dazhai",
    "gn:country_code":"CN",
    "gn:dem":1294,
    "gn:feature_class":"P",
    "gn:feature_code":"PPL",
    "gn:name":"Huangjia Dazhai",
    "gn:population":0,
    "gn:timezone":"Asia/Shanghai",
    "iso:country":"CN",
    "name:zho_x_preferred":[
        "\u9ec4\u5bb6\u5927\u5be8"
    ],
    "wof:name":"Huangjia Dazhai",
    "wof:placetype":"locality"
},
  "geometry": {"coordinates":[106.06100000000001,26.4825],"type":"Point"}
}