{
  "type": "Feature",
  "properties": {
    "gn:admin1_code":"6.0",
    "gn:asciiname":"Gobi Fenchang Erdui",
    "gn:country_code":"CN",
    "gn:dem":2817,
    "gn:feature_class":"P",
    "gn:feature_code":"PPLF",
    "gn:name":"Gobi Fenchang Erdui",
    "gn:population":0,
    "gn:timezone":"Asia/Urumqi",
    "iso:country":"CN",
    "name:und_x_variant":[
        "Ko-pi",
        "Gobi",
        "Gobi Fenchang Erdui",
        "\u6208\u58c1\u5206\u573a\u4e8c\u961f"
    ],
    "wof:name":"Gobi Fenchang Erdui",
    "wof:placetype":"locality"
},
  "geometry": {"coordinates":[96.9808,37.23439000000001],"type":"Point"}
}