{
  "type": "Feature",
  "properties": {
    "gn:admin1_code":"26.0",
    "gn:asciiname":"Gaochangou",
    "gn:country_code":"CN",
    "gn:dem":1165,
    "gn:feature_class":"P",
    "gn:feature_code":"PPL",
    "gn:name":"Gaochangou",
    "gn:population":0,
    "gn:timezone":"Asia/Shanghai",
    "iso:country":"CN",
    "name:zho_x_preferred":[
        "\u9ad8\u4ea7\u6c9f"
    ],
    "wof:name":"Gaochangou",
    "wof:placetype":"locality"
},
  "geometry": {"coordinates":[109.09841000000002,37.8866],"type":"Point"}
}