{
  "type": "Feature",
  "properties": {
    "gn:admin1_code":"12.0",
    "gn:asciiname":"Tizigou",
    "gn:country_code":"CN",
    "gn:dem":605,
    "gn:feature_class":"P",
    "gn:feature_code":"PPL",
    "gn:name":"Tizigou",
    "gn:population":0,
    "gn:timezone":"Asia/Shanghai",
    "iso:country":"CN",
    "name:zho_x_preferred":[
        "\u68af\u5b50\u6c9f"
    ],
    "wof:name":"Tizigou",
    "wof:placetype":"locality"
},
  "geometry": {"coordinates":[110.15534,33.16401],"type":"Point"}
}