{
  "type": "Feature",
  "properties": {
    "gn:admin1_code":"25",
    "gn:asciiname":"Jiangjiaguaitou",
    "gn:country_code":"CN",
    "gn:dem":130,
    "gn:feature_class":"P",
    "gn:feature_code":"PPL",
    "gn:name":"Jiangjiaguaitou",
    "gn:population":0,
    "gn:timezone":"Asia/Shanghai",
    "iso:country":"CN",
    "name:zho_x_preferred":[
        "\u59dc\u5bb6\u62d0\u5934"
    ],
    "wof:name":"Jiangjiaguaitou",
    "wof:placetype":"locality"
},
  "geometry": {"coordinates":[118.65000000000001,35.4986],"type":"Point"}
}