{
  "type": "Feature",
  "properties": {
    "gn:admin1_code":"8.0",
    "gn:asciiname":"Pingyuancun",
    "gn:country_code":"CN",
    "gn:dem":131,
    "gn:feature_class":"P",
    "gn:feature_code":"PPL",
    "gn:name":"Pingyuancun",
    "gn:population":0,
    "gn:timezone":"Asia/Shanghai",
    "iso:country":"CN",
    "name:zho_x_preferred":[
        "\u5e73\u539f\u6751"
    ],
    "wof:name":"Pingyuancun",
    "wof:placetype":"locality"
},
  "geometry": {"coordinates":[128.62917999999999,45.74963],"type":"Point"}
}