{
  "type": "Feature",
  "properties": {
    "gn:admin1_code":"25",
    "gn:asciiname":"Banguya",
    "gn:country_code":"CN",
    "gn:dem":241,
    "gn:feature_class":"P",
    "gn:feature_code":"PPL",
    "gn:name":"Banguya",
    "gn:population":0,
    "gn:timezone":"Asia/Shanghai",
    "iso:country":"CN",
    "name:zho_x_preferred":[
        "\u677f\u5d2e\u5d16"
    ],
    "wof:name":"Banguya",
    "wof:placetype":"locality"
},
  "geometry": {"coordinates":[118.126,35.8518],"type":"Point"}
}