{
  "type": "Feature",
  "properties": {
    "gn:admin1_code":"30.0",
    "gn:asciiname":"Dengwu",
    "gn:country_code":"CN",
    "gn:dem":651,
    "gn:feature_class":"P",
    "gn:feature_code":"PPL",
    "gn:name":"Dengwu",
    "gn:population":0,
    "gn:timezone":"Asia/Shanghai",
    "iso:country":"CN",
    "name:zho_x_preferred":[
        "Dengwu"
    ],
    "name:zho_x_variant":[
        "\u9093\u5c4b"
    ],
    "wof:name":"Dengwu",
    "wof:placetype":"locality"
},
  "geometry": {"coordinates":[113.96306,25.27389],"type":"Point"}
}