{
  "type": "Feature",
  "properties": {
    "gn:admin1_code":"6.0",
    "gn:asciiname":"Nani",
    "gn:country_code":"CN",
    "gn:dem":4040,
    "gn:feature_class":"P",
    "gn:feature_code":"PPL",
    "gn:name":"Nani",
    "gn:population":0,
    "gn:timezone":"Asia/Shanghai",
    "iso:country":"CN",
    "name:zho_x_preferred":[
        "\u90a3\u5c3c"
    ],
    "wof:name":"Nani",
    "wof:placetype":"locality"
},
  "geometry": {"coordinates":[99.68344,32.7779],"type":"Point"}
}