{
  "type": "Feature",
  "properties": {
    "gn:admin1_code":"15.0",
    "gn:asciiname":"Fengou",
    "gn:country_code":"CN",
    "gn:dem":2867,
    "gn:feature_class":"P",
    "gn:feature_code":"PPL",
    "gn:name":"Fengou",
    "gn:population":0,
    "gn:timezone":"Asia/Shanghai",
    "iso:country":"CN",
    "name:und_x_variant":[
        "\u575f\u6c9f"
    ],
    "wof:name":"Fengou",
    "wof:placetype":"locality"
},
  "geometry": {"coordinates":[103.71984,34.62314],"type":"Point"}
}