{
  "type": "Feature",
  "properties": {
    "gn:admin1_code":"12.0",
    "gn:asciiname":"Dingjiazui",
    "gn:country_code":"CN",
    "gn:dem":37,
    "gn:feature_class":"P",
    "gn:feature_code":"PPL",
    "gn:name":"Dingjiazui",
    "gn:population":0,
    "gn:timezone":"Asia/Shanghai",
    "iso:country":"CN",
    "name:zho_x_preferred":[
        "Dingjiazui"
    ],
    "name:zho_x_variant":[
        "\u4e01\u5bb6\u5480"
    ],
    "wof:name":"Dingjiazui",
    "wof:placetype":"locality"
},
  "geometry": {"coordinates":[112.09177,29.77212],"type":"Point"}
}