{
  "type": "Feature",
  "properties": {
    "gn:admin1_code":"3.0",
    "gn:asciiname":"Gongqingcheng",
    "gn:country_code":"CN",
    "gn:dem":30,
    "gn:feature_class":"P",
    "gn:feature_code":"PPL",
    "gn:name":"Gongqingcheng",
    "gn:population":0,
    "gn:timezone":"Asia/Shanghai",
    "iso:country":"CN",
    "name:ara_x_preferred":[
        "\u063a\u0648\u0646\u0643\u064a\u0646\u063a\u062a\u0634\u0627\u0646\u063a"
    ],
    "name:deu_x_preferred":[
        "Gongqingcheng"
    ],
    "name:ita_x_preferred":[
        "Gongqingcheng"
    ],
    "name:jpn_x_preferred":[
        "\u5171\u9752\u57ce\u5e02"
    ],
    "name:kik_x_preferred":[
        "Gongqingcheng"
    ],
    "name:kor_x_preferred":[
        "\uad81\uce6d\uccad\uc2dc"
    ],
    "name:mlg_x_preferred":[
        "Gongqing"
    ],
    "name:pol_x_preferred":[
        "Gongqingcheng"
    ],
    "name:urd_x_preferred":[
        "\u06af\u0648\u0646\u06af\u0686\u06cc\u0646\u06af\u0686\u06cc\u0646\u06af"
    ],
    "name:zho_x_preferred":[
        "\u5171\u9752\u57ce\u5e02"
    ],
    "wof:name":"Gongqingcheng",
    "wof:placetype":"locality"
},
  "geometry": {"coordinates":[115.80953,29.24915],"type":"Point"}
}