{
  "type": "Feature",
  "properties": {
    "gn:admin1_code":"19.0",
    "gn:asciiname":"Xi'ercha",
    "gn:country_code":"CN",
    "gn:dem":292,
    "gn:feature_class":"P",
    "gn:feature_code":"PPL",
    "gn:name":"Xi\u2019ercha",
    "gn:population":0,
    "gn:timezone":"Asia/Shanghai",
    "iso:country":"CN",
    "name:und_x_variant":[
        "\u897f\u4e8c\u5c94"
    ],
    "name:zho_x_preferred":[
        "Xi\u2019ercha"
    ],
    "name:zho_x_variant":[
        "\u897f\u4e8c\u5c94"
    ],
    "wof:name":"Xi'ercha",
    "wof:placetype":"locality"
},
  "geometry": {"coordinates":[124.44938,40.8515],"type":"Point"}
}