{
  "type": "Feature",
  "properties": {
    "gn:admin1_code":"33.0",
    "gn:asciiname":"Zengfu",
    "gn:country_code":"CN",
    "gn:dem":473,
    "gn:feature_class":"P",
    "gn:feature_code":"PPLA4",
    "gn:name":"Zengfu",
    "gn:population":0,
    "gn:timezone":"Asia/Shanghai",
    "iso:country":"CN",
    "name:und_x_variant":[
        "Zengfu Xiang"
    ],
    "name:zho_x_preferred":[
        "\u589e\u798f"
    ],
    "name:zho_x_variant":[
        "\u589e\u798f\u4e61"
    ],
    "wof:name":"Zengfu",
    "wof:placetype":"locality"
},
  "geometry": {"coordinates":[106.98577,29.51066],"type":"Point"}
}