{
  "type": "Feature",
  "properties": {
    "gn:admin1_code":"11.0",
    "gn:asciiname":"Huawuli",
    "gn:country_code":"CN",
    "gn:dem":131,
    "gn:feature_class":"P",
    "gn:feature_code":"PPL",
    "gn:name":"Huawuli",
    "gn:population":0,
    "gn:timezone":"Asia/Shanghai",
    "iso:country":"CN",
    "name:zho_x_preferred":[
        "\u82b1\u5c4b\u91cc"
    ],
    "wof:name":"Huawuli",
    "wof:placetype":"locality"
},
  "geometry": {"coordinates":[112.15947,28.1397],"type":"Point"}
}