{
  "type": "Feature",
  "properties": {
    "gn:admin1_code":"25",
    "gn:asciiname":"Chenpidong",
    "gn:country_code":"CN",
    "gn:dem":13,
    "gn:feature_class":"P",
    "gn:feature_code":"PPL",
    "gn:name":"Chenpidong",
    "gn:population":0,
    "gn:timezone":"Asia/Shanghai",
    "iso:country":"CN",
    "name:zho_x_preferred":[
        "\u9648\u76ae\u4e1c"
    ],
    "wof:name":"Chenpidong",
    "wof:placetype":"locality"
},
  "geometry": {"coordinates":[117.117,37.7133],"type":"Point"}
}