{
  "type": "Feature",
  "properties": {
    "gn:admin1_code":"1.0",
    "gn:asciiname":"Chatang",
    "gn:country_code":"CN",
    "gn:dem":162,
    "gn:feature_class":"P",
    "gn:feature_code":"PPL",
    "gn:name":"Chatang",
    "gn:population":0,
    "gn:timezone":"Asia/Shanghai",
    "iso:country":"CN",
    "name:cat_x_preferred":[
        "Chatang"
    ],
    "name:spa_x_preferred":[
        "Chatang"
    ],
    "name:zho_x_preferred":[
        "\u67e5\u5858"
    ],
    "name:zho_x_variant":[
        "\u8336\u6c64"
    ],
    "wof:name":"Chatang",
    "wof:placetype":"locality"
},
  "geometry": {"coordinates":[118.23096,29.73519000000001],"type":"Point"}
}