{
  "type": "Feature",
  "properties": {
    "gn:admin1_code":"18",
    "gn:asciiname":"Nongling",
    "gn:country_code":"CN",
    "gn:dem":1064,
    "gn:feature_class":"P",
    "gn:feature_code":"PPL",
    "gn:name":"Nongling",
    "gn:population":0,
    "gn:timezone":"Asia/Shanghai",
    "iso:country":"CN",
    "name:zho_x_preferred":[
        "\u5f04\u4ee4"
    ],
    "wof:name":"Nongling",
    "wof:placetype":"locality"
},
  "geometry": {"coordinates":[105.994,25.35],"type":"Point"}
}