{
  "type": "Feature",
  "properties": {
    "gn:admin1_code":"30",
    "gn:asciiname":"Jizhao",
    "gn:country_code":"CN",
    "gn:dem":18,
    "gn:feature_class":"P",
    "gn:feature_code":"PPL",
    "gn:name":"Jizhao",
    "gn:population":0,
    "gn:timezone":"Asia/Urumqi",
    "iso:country":"CN",
    "name:zho_x_preferred":[
        "\u5409\u5146"
    ],
    "wof:name":"Jizhao",
    "wof:placetype":"locality"
},
  "geometry": {"coordinates":[110.86539,21.39055],"type":"Point"}
}