{
  "type": "Feature",
  "properties": {
    "gn:admin1_code":"32.0",
    "gn:asciiname":"Daishichang",
    "gn:country_code":"CN",
    "gn:dem":1403,
    "gn:feature_class":"P",
    "gn:feature_code":"PPL",
    "gn:name":"Daishichang",
    "gn:population":0,
    "gn:timezone":"Asia/Shanghai",
    "iso:country":"CN",
    "name:zho_x_preferred":[
        "\u4ee3\u77f3\u5382"
    ],
    "wof:name":"Daishichang",
    "wof:placetype":"locality"
},
  "geometry": {"coordinates":[102.62482,29.72791],"type":"Point"}
}