{
  "type": "Feature",
  "properties": {
    "gn:admin1_code":"15.0",
    "gn:asciiname":"Xiabaishutan",
    "gn:country_code":"CN",
    "gn:dem":2452,
    "gn:feature_class":"P",
    "gn:feature_code":"PPL",
    "gn:name":"Xiabaishutan",
    "gn:population":0,
    "gn:timezone":"Asia/Shanghai",
    "iso:country":"CN",
    "name:und_x_variant":[
        "\u4e0b\u67cf\u6811\u6ee9"
    ],
    "wof:name":"Xiabaishutan",
    "wof:placetype":"locality"
},
  "geometry": {"coordinates":[103.95245,35.04254],"type":"Point"}
}