{
  "type": "Feature",
  "properties": {
    "gn:admin1_code":"30.0",
    "gn:asciiname":"Hantan",
    "gn:country_code":"CN",
    "gn:dem":102,
    "gn:feature_class":"P",
    "gn:feature_code":"PPL",
    "gn:name":"Hantan",
    "gn:population":0,
    "gn:timezone":"Asia/Shanghai",
    "iso:country":"CN",
    "name:zho_x_preferred":[
        "\u6c49\u6ee9"
    ],
    "wof:name":"Hantan",
    "wof:placetype":"locality"
},
  "geometry": {"coordinates":[115.1885,23.19577],"type":"Point"}
}