{
  "type": "Feature",
  "properties": {
    "gn:admin1_code":"12.0",
    "gn:asciiname":"Huaibaowo",
    "gn:country_code":"CN",
    "gn:dem":830,
    "gn:feature_class":"P",
    "gn:feature_code":"PPL",
    "gn:name":"Huaibaowo",
    "gn:population":0,
    "gn:timezone":"Asia/Shanghai",
    "iso:country":"CN",
    "name:zho_x_preferred":[
        "\u6000\u62b1\u7a9d"
    ],
    "wof:name":"Huaibaowo",
    "wof:placetype":"locality"
},
  "geometry": {"coordinates":[110.6014,30.32481],"type":"Point"}
}