{
  "type": "Feature",
  "properties": {
    "gn:admin1_code":"30",
    "gn:asciiname":"Canxing",
    "gn:country_code":"CN",
    "gn:dem":263,
    "gn:feature_class":"P",
    "gn:feature_code":"PPL",
    "gn:name":"Canxing",
    "gn:population":0,
    "gn:timezone":"Asia/Shanghai",
    "iso:country":"CN",
    "name:zho_x_preferred":[
        "\u8695\u5f62"
    ],
    "wof:name":"Canxing",
    "wof:placetype":"locality"
},
  "geometry": {"coordinates":[115.55826,24.53492],"type":"Point"}
}