{
  "type": "Feature",
  "properties": {
    "gn:admin1_code":"16.0",
    "gn:asciiname":"Yinshi",
    "gn:country_code":"CN",
    "gn:dem":171,
    "gn:feature_class":"P",
    "gn:feature_code":"PPL",
    "gn:name":"Yinshi",
    "gn:population":0,
    "gn:timezone":"Asia/Shanghai",
    "iso:country":"CN",
    "name:zho_x_preferred":[
        "\u94f6\u77f3"
    ],
    "wof:name":"Yinshi",
    "wof:placetype":"locality"
},
  "geometry": {"coordinates":[109.76300000000001,22.7683],"type":"Point"}
}