{
  "type": "Feature",
  "properties": {
    "gn:admin1_code":"26.0",
    "gn:asciiname":"Maozuishan",
    "gn:country_code":"CN",
    "gn:dem":1058,
    "gn:feature_class":"P",
    "gn:feature_code":"PPL",
    "gn:name":"Maozuishan",
    "gn:population":0,
    "gn:timezone":"Asia/Shanghai",
    "iso:country":"CN",
    "name:und_x_variant":[
        "\u5e3d\u5480\u5c71"
    ],
    "wof:name":"Maozuishan",
    "wof:placetype":"locality"
},
  "geometry": {"coordinates":[106.12268,33.40431],"type":"Point"}
}