{
  "type": "Feature",
  "properties": {
    "gn:admin1_code":"16.0",
    "gn:asciiname":"Zhangshu",
    "gn:country_code":"CN",
    "gn:dem":105,
    "gn:feature_class":"P",
    "gn:feature_code":"PPL",
    "gn:name":"Zhangshu",
    "gn:population":0,
    "gn:timezone":"Asia/Shanghai",
    "iso:country":"CN",
    "name:ces_x_preferred":[
        "\u010cang-\u0161u"
    ],
    "name:deu_x_preferred":[
        "Zhangshu"
    ],
    "name:fra_x_preferred":[
        "Zhangshu"
    ],
    "name:ita_x_preferred":[
        "Zhangshu"
    ],
    "name:jpn_x_preferred":[
        "\u6a1f\u6a39\u5e02"
    ],
    "name:kik_x_preferred":[
        "Zhangshu"
    ],
    "name:kor_x_preferred":[
        "\uc7a5\uc218\uc2dc"
    ],
    "name:nor_x_preferred":[
        "Zhangshu"
    ],
    "name:swe_x_preferred":[
        "Zhangshu"
    ],
    "name:urd_x_preferred":[
        "\u0698\u0627\u0646\u06af\u0634\u0648"
    ],
    "name:vie_x_preferred":[
        "Ch\u01b0\u01a1ng Th\u1ee5"
    ],
    "name:war_x_preferred":[
        "Zhangshu"
    ],
    "name:zho_x_preferred":[
        "\u6a1f\u6811"
    ],
    "name:zho_x_variant":[
        "\u6a1f\u6811\u5e02"
    ],
    "wof:name":"Zhangshu",
    "wof:placetype":"locality"
},
  "geometry": {"coordinates":[109.255,24.6535],"type":"Point"}
}