{
  "type": "Feature",
  "properties": {
    "gn:admin1_code":"11.0",
    "gn:asciiname":"Maowu",
    "gn:country_code":"CN",
    "gn:dem":107,
    "gn:feature_class":"P",
    "gn:feature_code":"PPL",
    "gn:name":"Maowu",
    "gn:population":0,
    "gn:timezone":"Asia/Shanghai",
    "iso:country":"CN",
    "name:zho_x_preferred":[
        "\u8305\u5c4b"
    ],
    "wof:name":"Maowu",
    "wof:placetype":"locality"
},
  "geometry": {"coordinates":[112.74472,27.4814],"type":"Point"}
}