{
  "type": "Feature",
  "properties": {
    "gn:admin1_code":"3.0",
    "gn:asciiname":"Dongzhuangwan",
    "gn:country_code":"CN",
    "gn:dem":32,
    "gn:feature_class":"P",
    "gn:feature_code":"PPL",
    "gn:name":"Dongzhuangwan",
    "gn:population":0,
    "gn:timezone":"Asia/Shanghai",
    "iso:country":"CN",
    "name:und_x_variant":[
        "\u4e1c\u5e84\u6e7e"
    ],
    "wof:name":"Dongzhuangwan",
    "wof:placetype":"locality"
},
  "geometry": {"coordinates":[116.23899,29.62255],"type":"Point"}
}