{
  "type": "Feature",
  "properties": {
    "gn:admin1_code":"5.0",
    "gn:asciiname":"Yongdecun",
    "gn:country_code":"CN",
    "gn:dem":311,
    "gn:feature_class":"P",
    "gn:feature_code":"PPL",
    "gn:name":"Yongdecun",
    "gn:population":0,
    "gn:timezone":"Asia/Shanghai",
    "iso:country":"CN",
    "name:zho_x_preferred":[
        "\u6c38\u5fb7\u6751"
    ],
    "wof:name":"Yongdecun",
    "wof:placetype":"locality"
},
  "geometry": {"coordinates":[121.98484999999999,45.91968],"type":"Point"}
}