{
  "type": "Feature",
  "properties": {
    "gn:admin1_code":"1.0",
    "gn:asciiname":"Wushicun",
    "gn:country_code":"CN",
    "gn:dem":33,
    "gn:feature_class":"P",
    "gn:feature_code":"PPL",
    "gn:name":"Wushicun",
    "gn:population":0,
    "gn:timezone":"Asia/Shanghai",
    "iso:country":"CN",
    "name:zho_x_preferred":[
        "\u4e4c\u77f3\u6751"
    ],
    "wof:name":"Wushicun",
    "wof:placetype":"locality"
},
  "geometry": {"coordinates":[117.46826,30.46186],"type":"Point"}
}