{
  "type": "Feature",
  "properties": {
    "gn:admin1_code":"29.0",
    "gn:asciiname":"Mi'er",
    "gn:country_code":"CN",
    "gn:dem":1236,
    "gn:feature_class":"P",
    "gn:feature_code":"PPL",
    "gn:name":"Mi\u2019er",
    "gn:population":0,
    "gn:timezone":"Asia/Shanghai",
    "iso:country":"CN",
    "name:und_x_variant":[
        "Mi\u2019er"
    ],
    "name:zho_x_preferred":[
        "\u54aa\u54a1"
    ],
    "wof:name":"Mi'er",
    "wof:placetype":"locality"
},
  "geometry": {"coordinates":[104.155,27.605],"type":"Point"}
}