{
  "type": "Feature",
  "properties": {
    "gn:admin1_code":"29",
    "gn:asciiname":"Damina",
    "gn:country_code":"CN",
    "gn:dem":1490,
    "gn:feature_class":"P",
    "gn:feature_code":"PPL",
    "gn:name":"Damina",
    "gn:population":0,
    "gn:timezone":"Asia/Shanghai",
    "iso:country":"CN",
    "name:zho_x_preferred":[
        "\u5927\u5bc6\u7eb3"
    ],
    "wof:name":"Damina",
    "wof:placetype":"locality"
},
  "geometry": {"coordinates":[103.29300000000001,24.1191],"type":"Point"}
}