{
  "type": "Feature",
  "properties": {
    "gn:admin1_code":"29.0",
    "gn:asciiname":"Shiyan",
    "gn:country_code":"CN",
    "gn:dem":2302,
    "gn:feature_class":"P",
    "gn:feature_code":"PPL",
    "gn:name":"Shiyan",
    "gn:population":0,
    "gn:timezone":"Asia/Shanghai",
    "iso:country":"CN",
    "name:zho_x_preferred":[
        "\u77f3\u5ca9"
    ],
    "wof:name":"Shiyan",
    "wof:placetype":"locality"
},
  "geometry": {"coordinates":[99.6615,26.3845],"type":"Point"}
}