{
  "type": "Feature",
  "properties": {
    "gn:admin1_code":"16.0",
    "gn:asciiname":"Hemei",
    "gn:country_code":"CN",
    "gn:dem":135,
    "gn:feature_class":"P",
    "gn:feature_code":"PPL",
    "gn:name":"Hemei",
    "gn:population":0,
    "gn:timezone":"Asia/Shanghai",
    "iso:country":"CN",
    "name:zho_x_preferred":[
        "\u5408\u7f8e"
    ],
    "wof:name":"Hemei",
    "wof:placetype":"locality"
},
  "geometry": {"coordinates":[108.35599999999999,23.0932],"type":"Point"}
}