{
  "type": "Feature",
  "properties": {
    "gn:admin1_code":"16.0",
    "gn:asciiname":"Hemei",
    "gn:country_code":"CN",
    "gn:dem":135,
    "gn:feature_class":"P",
    "gn:feature_code":"PPL",
    "gn:name":"Hemei",
    "gn:population":0,
    "gn:timezone":"Asia/Shanghai",
    "iso:country":"CN",
    "name:hak_x_preferred":[
        "F\u00f2-m\u00ee-ch\u1e73\u0301n"
    ],
    "name:ita_x_preferred":[
        "Hemei"
    ],
    "name:jpn_x_preferred":[
        "\u548c\u7f8e\u93ae"
    ],
    "name:kor_x_preferred":[
        "\ud5c8\uba54\uc774\uc9c4"
    ],
    "name:pol_x_preferred":[
        "Hemei"
    ],
    "name:vie_x_preferred":[
        "H\u00f2a M\u1ef9"
    ],
    "name:zho_x_preferred":[
        "\u5408\u7f8e"
    ],
    "name:zho_x_variant":[
        "\u548c\u7f8e\u93ae"
    ],
    "wof:name":"Hemei",
    "wof:placetype":"locality"
},
  "geometry": {"coordinates":[108.35599999999999,23.0932],"type":"Point"}
}