{
  "type": "Feature",
  "properties": {
    "gn:admin1_code":"4.0",
    "gn:asciiname":"Zhujiadai",
    "gn:country_code":"CN",
    "gn:dem":4,
    "gn:feature_class":"P",
    "gn:feature_code":"PPL",
    "gn:name":"Zhujiadai",
    "gn:population":0,
    "gn:timezone":"Asia/Shanghai",
    "iso:country":"CN",
    "name:zho_x_preferred":[
        "\u6731\u5bb6\u57ed"
    ],
    "wof:name":"Zhujiadai",
    "wof:placetype":"locality"
},
  "geometry": {"coordinates":[119.87233000000001,32.13183],"type":"Point"}
}