{
  "type": "Feature",
  "properties": {
    "gn:admin1_code":"11.0",
    "gn:asciiname":"Zuojia Xinwu",
    "gn:country_code":"CN",
    "gn:dem":187,
    "gn:feature_class":"P",
    "gn:feature_code":"PPL",
    "gn:name":"Zuojia Xinwu",
    "gn:population":0,
    "gn:timezone":"Asia/Shanghai",
    "iso:country":"CN",
    "name:zho_x_preferred":[
        "\u5de6\u5bb6\u65b0\u5c4b"
    ],
    "wof:name":"Zuojia Xinwu",
    "wof:placetype":"locality"
},
  "geometry": {"coordinates":[112.50317,27.59172],"type":"Point"}
}