{
  "type": "Feature",
  "properties": {
    "gn:admin1_code":"29",
    "gn:asciiname":"Qudongli",
    "gn:country_code":"CN",
    "gn:dem":1894,
    "gn:feature_class":"P",
    "gn:feature_code":"PPL",
    "gn:name":"Qudongli",
    "gn:population":0,
    "gn:timezone":"Asia/Shanghai",
    "iso:country":"CN",
    "name:zho_x_preferred":[
        "\u6e20\u4e1c\u91cc"
    ],
    "wof:name":"Qudongli",
    "wof:placetype":"locality"
},
  "geometry": {"coordinates":[102.634,24.6619],"type":"Point"}
}