{
  "type": "Feature",
  "properties": {
    "gn:admin1_code":"20.0",
    "gn:asciiname":"Qian Wangdui",
    "gn:country_code":"CN",
    "gn:dem":432,
    "gn:feature_class":"P",
    "gn:feature_code":"PPLF",
    "gn:name":"Qian Wangdui",
    "gn:population":0,
    "gn:timezone":"Asia/Shanghai",
    "iso:country":"CN",
    "name:zho_x_preferred":[
        "\u524d\u738b\u961f"
    ],
    "wof:name":"Qian Wangdui",
    "wof:placetype":"locality"
},
  "geometry": {"coordinates":[121.96930999999999,47.27944],"type":"Point"}
}