{
  "type": "Feature",
  "properties": {
    "gn:admin1_code":"30.0",
    "gn:asciiname":"Hengzhuangcun",
    "gn:country_code":"CN",
    "gn:dem":195,
    "gn:feature_class":"P",
    "gn:feature_code":"PPL",
    "gn:name":"Hengzhuangcun",
    "gn:population":0,
    "gn:timezone":"Asia/Shanghai",
    "iso:country":"CN",
    "name:zho_x_preferred":[
        "\u6a2a\u5e84\u6751"
    ],
    "wof:name":"Hengzhuangcun",
    "wof:placetype":"locality"
},
  "geometry": {"coordinates":[116.34068000000001,24.58645],"type":"Point"}
}