{
  "type": "Feature",
  "properties": {
    "gn:admin1_code":"13.0",
    "gn:asciiname":"Kule",
    "gn:country_code":"CN",
    "gn:dem":4211,
    "gn:feature_class":"P",
    "gn:feature_code":"PPL",
    "gn:name":"Kule",
    "gn:population":0,
    "gn:timezone":"Asia/Shanghai",
    "iso:country":"CN",
    "name:fra_x_preferred":[
        "Kule"
    ],
    "name:ita_x_preferred":[
        "Kule"
    ],
    "name:mlg_x_preferred":[
        "Kule"
    ],
    "name:nld_x_preferred":[
        "Kule"
    ],
    "name:pol_x_preferred":[
        "Kule"
    ],
    "name:swa_x_preferred":[
        "Kule"
    ],
    "name:swe_x_preferred":[
        "Kule"
    ],
    "name:tsn_x_preferred":[
        "Kule"
    ],
    "name:zho_x_preferred":[
        "\u5e93\u52d2"
    ],
    "wof:name":"Kule",
    "wof:placetype":"locality"
},
  "geometry": {"coordinates":[79.48458000000002,36.35455],"type":"Point"}
}