{
  "type": "Feature",
  "properties": {
    "gn:admin1_code":"7.0",
    "gn:asciiname":"Mulin Xiacun",
    "gn:country_code":"CN",
    "gn:dem":919,
    "gn:feature_class":"P",
    "gn:feature_code":"PPL",
    "gn:name":"Mulin Xiacun",
    "gn:population":0,
    "gn:timezone":"Asia/Shanghai",
    "iso:country":"CN",
    "name:zho_x_preferred":[
        "\u5893\u6797\u4e0b\u6751"
    ],
    "wof:name":"Mulin Xiacun",
    "wof:placetype":"locality"
},
  "geometry": {"coordinates":[119.0423,27.3412],"type":"Point"}
}