{
  "type": "Feature",
  "properties": {
    "gn:admin1_code":"32.0",
    "gn:asciiname":"Junlin",
    "gn:country_code":"CN",
    "gn:dem":367,
    "gn:feature_class":"P",
    "gn:feature_code":"PPL",
    "gn:name":"Junlin",
    "gn:population":0,
    "gn:timezone":"Asia/Shanghai",
    "iso:country":"CN",
    "name:zho_x_preferred":[
        "\u519b\u6797"
    ],
    "wof:name":"Junlin",
    "wof:placetype":"locality"
},
  "geometry": {"coordinates":[104.387,30.0226],"type":"Point"}
}