{
  "type": "Feature",
  "properties": {
    "gn:admin1_code":"20.0",
    "gn:asciiname":"Yemajing",
    "gn:cc2":"CN",
    "gn:country_code":"CN",
    "gn:dem":1564,
    "gn:feature_class":"P",
    "gn:feature_code":"PPL",
    "gn:name":"Yemajing",
    "gn:population":0,
    "gn:timezone":"Asia/Shanghai",
    "iso:country":"CN",
    "name:und_x_variant":[
        "Yeh-ma-ching",
        "Yemajing"
    ],
    "wof:name":"Yemajing",
    "wof:placetype":"locality"
},
  "geometry": {"coordinates":[102.95,39.55],"type":"Point"}
}