{
  "type": "Feature",
  "properties": {
    "gn:admin1_code":"2.0",
    "gn:asciiname":"Ningbozhan",
    "gn:country_code":"CN",
    "gn:dem":5,
    "gn:feature_class":"P",
    "gn:feature_code":"PPL",
    "gn:name":"Ningbozhan",
    "gn:population":0,
    "gn:timezone":"Asia/Shanghai",
    "iso:country":"CN",
    "name:zho_x_preferred":[
        "\u5b81\u6ce2\u7ad9"
    ],
    "wof:name":"Ningbozhan",
    "wof:placetype":"locality"
},
  "geometry": {"coordinates":[121.79949000000001,29.22369],"type":"Point"}
}