{
  "type": "Feature",
  "properties": {
    "gn:admin1_code":"1.0",
    "gn:asciiname":"Changxicun",
    "gn:country_code":"CN",
    "gn:dem":73,
    "gn:feature_class":"P",
    "gn:feature_code":"PPL",
    "gn:name":"Changxicun",
    "gn:population":0,
    "gn:timezone":"Asia/Shanghai",
    "iso:country":"CN",
    "name:zho_x_preferred":[
        "\u957f\u6eaa\u6751"
    ],
    "wof:name":"Changxicun",
    "wof:placetype":"locality"
},
  "geometry": {"coordinates":[116.9303,29.84967],"type":"Point"}
}