{
  "type": "Feature",
  "properties": {
    "gn:admin1_code":"4.0",
    "gn:asciiname":"Wulaocun",
    "gn:country_code":"CN",
    "gn:dem":10,
    "gn:feature_class":"P",
    "gn:feature_code":"PPLA3",
    "gn:name":"Wulaocun",
    "gn:population":0,
    "gn:timezone":"Asia/Shanghai",
    "iso:country":"CN",
    "name:und_x_variant":[
        "Wulaocun Jiedao",
        "Baixia Qu"
    ],
    "name:zho_x_preferred":[
        "\u4e94\u8001\u6751"
    ],
    "name:zho_x_variant":[
        "\u4e94\u8001\u6751\u8857\u9053",
        "\u767d\u4e0b\u533a"
    ],
    "wof:name":"Wulaocun",
    "wof:placetype":"locality"
},
  "geometry": {"coordinates":[118.79575,32.03437],"type":"Point"}
}