{
  "type": "Feature",
  "properties": {
    "gn:admin1_code":"30",
    "gn:asciiname":"Facaizhai",
    "gn:country_code":"CN",
    "gn:dem":43,
    "gn:feature_class":"P",
    "gn:feature_code":"PPL",
    "gn:name":"Facaizhai",
    "gn:population":0,
    "gn:timezone":"Asia/Shanghai",
    "iso:country":"CN",
    "name:zho_x_preferred":[
        "\u53d1\u8d22\u5be8"
    ],
    "wof:name":"Facaizhai",
    "wof:placetype":"locality"
},
  "geometry": {"coordinates":[111.61279,22.11273],"type":"Point"}
}