{
  "type": "Feature",
  "properties": {
    "gn:admin1_code":"3.0",
    "gn:asciiname":"Zhengcun",
    "gn:country_code":"CN",
    "gn:dem":128,
    "gn:feature_class":"P",
    "gn:feature_code":"PPL",
    "gn:name":"Zhengcun",
    "gn:population":0,
    "gn:timezone":"Asia/Shanghai",
    "iso:country":"CN",
    "name:zho_x_preferred":[
        "\u5f81\u6751"
    ],
    "wof:name":"Zhengcun",
    "wof:placetype":"locality"
},
  "geometry": {"coordinates":[114.492,28.9213],"type":"Point"}
}