{
  "type": "Feature",
  "properties": {
    "gn:admin1_code":"10.0",
    "gn:asciiname":"Huziyu",
    "gn:country_code":"CN",
    "gn:dem":1045,
    "gn:feature_class":"P",
    "gn:feature_code":"PPL",
    "gn:name":"Huziyu",
    "gn:population":0,
    "gn:timezone":"Asia/Shanghai",
    "iso:country":"CN",
    "name:zho_x_preferred":[
        "\u80e1\u5b50\u5cea"
    ],
    "wof:name":"Huziyu",
    "wof:placetype":"locality"
},
  "geometry": {"coordinates":[114.76953,39.49966],"type":"Point"}
}