{
  "type": "Feature",
  "properties": {
    "gn:admin1_code":"25",
    "gn:asciiname":"Gaoling",
    "gn:country_code":"CN",
    "gn:dem":62,
    "gn:feature_class":"P",
    "gn:feature_code":"PPLA4",
    "gn:name":"Gaoling",
    "gn:population":0,
    "gn:timezone":"Asia/Shanghai",
    "iso:country":"CN",
    "name:und_x_variant":[
        "Kao-ling",
        "Gaoling",
        "Gaoling Zhen"
    ],
    "name:zho_x_preferred":[
        "\u9ad8\u9675"
    ],
    "name:zho_x_variant":[
        "\u9ad8\u9675\u9547"
    ],
    "wof:name":"Gaoling",
    "wof:placetype":"locality"
},
  "geometry": {"coordinates":[121.52216,37.29386],"type":"Point"}
}