{
  "type": "Feature",
  "properties": {
    "gn:admin1_code":"19.0",
    "gn:asciiname":"Zhangjiajie",
    "gn:country_code":"CN",
    "gn:dem":282,
    "gn:feature_class":"P",
    "gn:feature_code":"PPL",
    "gn:name":"Zhangjiajie",
    "gn:population":0,
    "gn:timezone":"Asia/Shanghai",
    "iso:country":"CN",
    "name:und_x_variant":[
        "\u5f20\u5bb6\u8857"
    ],
    "name:zho_x_preferred":[
        "\u5f20\u5bb6\u8857"
    ],
    "wof:name":"Zhangjiajie",
    "wof:placetype":"locality"
},
  "geometry": {"coordinates":[123.09172,40.53537],"type":"Point"}
}