{
  "type": "Feature",
  "properties": {
    "gn:admin1_code":"19.0",
    "gn:asciiname":"Zuozigoucun",
    "gn:country_code":"CN",
    "gn:dem":180,
    "gn:feature_class":"P",
    "gn:feature_code":"PPL",
    "gn:name":"Zuozigoucun",
    "gn:population":0,
    "gn:timezone":"Asia/Shanghai",
    "iso:country":"CN",
    "name:zho_x_preferred":[
        "\u67de\u5b50\u6c9f\u6751"
    ],
    "wof:name":"Zuozigoucun",
    "wof:placetype":"locality"
},
  "geometry": {"coordinates":[124.63500000000001,42.3807],"type":"Point"}
}