{
  "type": "Feature",
  "properties": {
    "gn:admin1_code":"2.0",
    "gn:asciiname":"Jiaochangwu",
    "gn:country_code":"CN",
    "gn:dem":416,
    "gn:feature_class":"P",
    "gn:feature_code":"PPL",
    "gn:name":"Jiaochangwu",
    "gn:population":0,
    "gn:timezone":"Asia/Shanghai",
    "iso:country":"CN",
    "name:zho_x_preferred":[
        "\u6559\u573a\u575e"
    ],
    "wof:name":"Jiaochangwu",
    "wof:placetype":"locality"
},
  "geometry": {"coordinates":[120.27128,28.08626],"type":"Point"}
}