{
  "type": "Feature",
  "properties": {
    "gn:admin1_code":"30.0",
    "gn:asciiname":"Meizhaicun",
    "gn:country_code":"CN",
    "gn:dem":13,
    "gn:feature_class":"P",
    "gn:feature_code":"PPL",
    "gn:name":"Meizhaicun",
    "gn:population":0,
    "gn:timezone":"Asia/Shanghai",
    "iso:country":"CN",
    "name:und_x_variant":[
        "Meizhai"
    ],
    "name:zho_x_preferred":[
        "\u7f8e\u5b85\u6751"
    ],
    "wof:name":"Meizhaicun",
    "wof:placetype":"locality"
},
  "geometry": {"coordinates":[116.96247,23.55557],"type":"Point"}
}