{
  "type": "Feature",
  "properties": {
    "gn:admin1_code":"29",
    "gn:asciiname":"Shangbawei",
    "gn:country_code":"CN",
    "gn:dem":1649,
    "gn:feature_class":"P",
    "gn:feature_code":"PPL",
    "gn:name":"Shangbawei",
    "gn:population":0,
    "gn:timezone":"Asia/Shanghai",
    "iso:country":"CN",
    "name:zho_x_preferred":[
        "\u4e0a\u575d\u5c3e"
    ],
    "wof:name":"Shangbawei",
    "wof:placetype":"locality"
},
  "geometry": {"coordinates":[104.63800000000001,23.4216],"type":"Point"}
}