{
  "type": "Feature",
  "properties": {
    "gn:admin1_code":"4.0",
    "gn:asciiname":"Shendianqiao",
    "gn:country_code":"CN",
    "gn:dem":23,
    "gn:feature_class":"P",
    "gn:feature_code":"PPL",
    "gn:name":"Shendianqiao",
    "gn:population":0,
    "gn:timezone":"Asia/Shanghai",
    "iso:country":"CN",
    "name:zho_x_preferred":[
        "\u6c88\u57ab\u6865"
    ],
    "wof:name":"Shendianqiao",
    "wof:placetype":"locality"
},
  "geometry": {"coordinates":[119.07899,31.79399],"type":"Point"}
}