{
  "type": "Feature",
  "properties": {
    "gn:admin1_code":"30.0",
    "gn:asciiname":"Shamaoling",
    "gn:country_code":"CN",
    "gn:dem":112,
    "gn:feature_class":"P",
    "gn:feature_code":"PPL",
    "gn:name":"Shamaoling",
    "gn:population":0,
    "gn:timezone":"Asia/Shanghai",
    "iso:country":"CN",
    "name:zho_x_preferred":[
        "Shamaoling"
    ],
    "name:zho_x_variant":[
        "\u6c99\u5e3d\u5cad"
    ],
    "wof:name":"Shamaoling",
    "wof:placetype":"locality"
},
  "geometry": {"coordinates":[112.62027999999999,24.46194],"type":"Point"}
}