{
  "type": "Feature",
  "properties": {
    "gn:admin1_code":"9",
    "gn:asciiname":"Dongjiahe",
    "gn:country_code":"CN",
    "gn:dem":159,
    "gn:feature_class":"P",
    "gn:feature_code":"PPL",
    "gn:name":"Dongjiahe",
    "gn:population":0,
    "gn:timezone":"Asia/Shanghai",
    "iso:country":"CN",
    "wof:name":"Dongjiahe",
    "wof:placetype":"locality"
},
  "geometry": {"coordinates":[113.83778,32.16778],"type":"Point"}
}