{
  "type": "Feature",
  "properties": {
    "gn:admin1_code":"3.0",
    "gn:asciiname":"Tangnicun",
    "gn:country_code":"CN",
    "gn:dem":208,
    "gn:feature_class":"P",
    "gn:feature_code":"PPL",
    "gn:name":"Tangnicun",
    "gn:population":0,
    "gn:timezone":"Asia/Shanghai",
    "iso:country":"CN",
    "name:und_x_variant":[
        "\u5858\u6ce5\u6751"
    ],
    "wof:name":"Tangnicun",
    "wof:placetype":"locality"
},
  "geometry": {"coordinates":[115.73545,26.28878],"type":"Point"}
}