{
  "type": "Feature",
  "properties": {
    "gn:admin1_code":"7.0",
    "gn:asciiname":"Raofang",
    "gn:country_code":"CN",
    "gn:dem":312,
    "gn:feature_class":"P",
    "gn:feature_code":"PPL",
    "gn:name":"Raofang",
    "gn:population":0,
    "gn:timezone":"Asia/Shanghai",
    "iso:country":"CN",
    "name:zho_x_preferred":[
        "\u9976\u574a"
    ],
    "wof:name":"Raofang",
    "wof:placetype":"locality"
},
  "geometry": {"coordinates":[116.4147,25.76335],"type":"Point"}
}