{
  "type": "Feature",
  "properties": {
    "gn:admin1_code":"3.0",
    "gn:asciiname":"Guanyinshan",
    "gn:country_code":"CN",
    "gn:dem":564,
    "gn:feature_class":"P",
    "gn:feature_code":"PPL",
    "gn:name":"Guanyinshan",
    "gn:population":0,
    "gn:timezone":"Asia/Shanghai",
    "iso:country":"CN",
    "name:und_x_variant":[
        "\u89c2\u97f3\u5c71"
    ],
    "wof:name":"Guanyinshan",
    "wof:placetype":"locality"
},
  "geometry": {"coordinates":[115.57408999999998,24.93199],"type":"Point"}
}