{
  "type": "Feature",
  "properties": {
    "gn:admin1_code":"13.0",
    "gn:asciiname":"Ayakeya Wutale",
    "gn:country_code":"CN",
    "gn:dem":3981,
    "gn:feature_class":"P",
    "gn:feature_code":"PPL",
    "gn:name":"Ayakeya Wutale",
    "gn:population":0,
    "gn:timezone":"Asia/Urumqi",
    "iso:country":"CN",
    "name:zho_x_preferred":[
        "\u963f\u4e9a\u514b\u4e9a\u4e4c\u5854\u52d2"
    ],
    "wof:name":"Ayakeya Wutale",
    "wof:placetype":"locality"
},
  "geometry": {"coordinates":[86.72114999999999,37.95032],"type":"Point"}
}