{
  "type": "Feature",
  "properties": {
    "gn:admin1_code":"7.0",
    "gn:asciiname":"Fuquan",
    "gn:country_code":"CN",
    "gn:dem":421,
    "gn:feature_class":"P",
    "gn:feature_code":"PPL",
    "gn:name":"Fuquan",
    "gn:population":0,
    "gn:timezone":"Asia/Shanghai",
    "iso:country":"CN",
    "name:ceb_x_preferred":[
        "Fuquan"
    ],
    "name:deu_x_preferred":[
        "Fuquan"
    ],
    "name:zho_x_preferred":[
        "Fuquan"
    ],
    "name:zho_x_variant":[
        "\u798f\u5168"
    ],
    "wof:name":"Fuquan",
    "wof:placetype":"locality"
},
  "geometry": {"coordinates":[118.74417,26.69972000000001],"type":"Point"}
}