{
  "type": "Feature",
  "properties": {
    "gn:admin1_code":"29.0",
    "gn:asciiname":"Dayakou",
    "gn:country_code":"CN",
    "gn:dem":3950,
    "gn:feature_class":"P",
    "gn:feature_code":"PPL",
    "gn:name":"Dayakou",
    "gn:population":0,
    "gn:timezone":"Asia/Shanghai",
    "iso:country":"CN",
    "name:zho_x_preferred":[
        "\u5927\u57ad\u53e3"
    ],
    "wof:name":"Dayakou",
    "wof:placetype":"locality"
},
  "geometry": {"coordinates":[100.035,27.325],"type":"Point"}
}