{
  "type": "Feature",
  "properties": {
    "gn:admin1_code":"8.0",
    "gn:asciiname":"Guangxingcun",
    "gn:country_code":"CN",
    "gn:dem":170,
    "gn:feature_class":"P",
    "gn:feature_code":"PPL",
    "gn:name":"Guangxingcun",
    "gn:population":0,
    "gn:timezone":"Asia/Shanghai",
    "iso:country":"CN",
    "name:zho_x_preferred":[
        "\u5e7f\u5174\u6751"
    ],
    "wof:name":"Guangxingcun",
    "wof:placetype":"locality"
},
  "geometry": {"coordinates":[128.23976999999999,45.4406],"type":"Point"}
}