{
  "type": "Feature",
  "properties": {
    "gn:admin1_code":"9.0",
    "gn:asciiname":"Changyangzhuang",
    "gn:country_code":"CN",
    "gn:dem":44,
    "gn:feature_class":"P",
    "gn:feature_code":"PPL",
    "gn:name":"Changyangzhuang",
    "gn:population":0,
    "gn:timezone":"Asia/Shanghai",
    "iso:country":"CN",
    "name:zho_x_preferred":[
        "\u957f\u6768\u5e84"
    ],
    "wof:name":"Changyangzhuang",
    "wof:placetype":"locality"
},
  "geometry": {"coordinates":[115.06138,32.67919000000001],"type":"Point"}
}