{
  "type": "Feature",
  "properties": {
    "gn:admin1_code":"7.0",
    "gn:asciiname":"Gulu",
    "gn:country_code":"CN",
    "gn:dem":1150,
    "gn:feature_class":"P",
    "gn:feature_code":"PPL",
    "gn:name":"Gulu",
    "gn:population":0,
    "gn:timezone":"Asia/Shanghai",
    "iso:country":"CN",
    "name:zho_x_preferred":[
        "\u53e4\u7089"
    ],
    "wof:name":"Gulu",
    "wof:placetype":"locality"
},
  "geometry": {"coordinates":[116.85566,25.29068],"type":"Point"}
}