{
  "type": "Feature",
  "properties": {
    "gn:admin1_code":"02",
    "gn:asciiname":"Quanfu",
    "gn:country_code":"CN",
    "gn:dem":104,
    "gn:feature_class":"P",
    "gn:feature_code":"PPLA4",
    "gn:name":"Quanfu",
    "gn:population":0,
    "gn:timezone":"Asia/Shanghai",
    "iso:country":"CN",
    "name:und_x_variant":[
        "Nan-ma-shih",
        "Nanma",
        "Quanfu",
        "Nanma Zhen"
    ],
    "name:zho_x_preferred":[
        "\u6cc9\u5e9c"
    ],
    "name:zho_x_variant":[
        "\u5357\u9a6c\u9547"
    ],
    "wof:name":"Quanfu",
    "wof:placetype":"locality"
},
  "geometry": {"coordinates":[120.22017,29.1039],"type":"Point"}
}