{
  "type": "Feature",
  "properties": {
    "gn:admin1_code":"11",
    "gn:asciiname":"Da'anping",
    "gn:country_code":"CN",
    "gn:dem":1107,
    "gn:feature_class":"P",
    "gn:feature_code":"PPLA4",
    "gn:name":"Da\u2019anping",
    "gn:population":0,
    "gn:timezone":"Asia/Shanghai",
    "iso:country":"CN",
    "name:und_x_variant":[
        "Ta-an-p\u2019ing"
    ],
    "name:zho_x_preferred":[
        "\u5927\u5b89\u576a"
    ],
    "name:zho_x_variant":[
        "Da\u2019an Xiang",
        "\u5927\u5b89\u4e61",
        "Da\u2019anping"
    ],
    "wof:name":"Da'anping",
    "wof:placetype":"locality"
},
  "geometry": {"coordinates":[109.67139,29.53599],"type":"Point"}
}