{
  "type": "Feature",
  "properties": {
    "gn:admin1_code":"14.0",
    "gn:asciiname":"Gyamotang",
    "gn:country_code":"CN",
    "gn:dem":4955,
    "gn:feature_class":"P",
    "gn:feature_code":"PPLA3",
    "gn:name":"Gyamotang",
    "gn:population":0,
    "gn:timezone":"Asia/Urumqi",
    "iso:country":"CN",
    "name:bod_x_preferred":[
        "Gyamotang"
    ],
    "name:und_x_variant":[
        "Ting-ch\u2019ing-chen",
        "D\u00eangq\u00ean",
        "Te-ch\u2019ing",
        "Denchen",
        "Ting-ch\u2019ing-tsung",
        "Denchin",
        "Ting-ch\u2019ing",
        "Te-chin",
        "Gyamotang"
    ],
    "name:zho_x_preferred":[
        "Jiamotang"
    ],
    "name:zho_x_variant":[
        "\u52a0\u83ab\u5858",
        "Dingqing Xian",
        "\u4e01\u9752\u53bf"
    ],
    "wof:name":"Gyamotang",
    "wof:placetype":"locality"
},
  "geometry": {"coordinates":[95.43333,31.53333],"type":"Point"}
}