{
  "type": "Feature",
  "properties": {
    "gn:admin1_code":"33",
    "gn:asciiname":"Nanwenquan",
    "gn:cc2":"CN",
    "gn:country_code":"CN",
    "gn:dem":226,
    "gn:feature_class":"P",
    "gn:feature_code":"PPL",
    "gn:name":"Nanwenquan",
    "gn:population":0,
    "gn:timezone":"Asia/Shanghai",
    "iso:country":"CN",
    "name:und_x_variant":[
        "Hot Sulphur Springs",
        "Nan-wen-ch\u2019\u00fcan",
        "Wen-ch\u2019\u00fcan",
        "South Hot Springs",
        "Nanwenquan"
    ],
    "wof:name":"Nanwenquan",
    "wof:placetype":"locality"
},
  "geometry": {"coordinates":[106.56028000000001,29.43],"type":"Point"}
}