{
  "type": "Feature",
  "properties": {
    "gn:admin1_code":"19.0",
    "gn:asciiname":"Sipingjie Donggou",
    "gn:country_code":"CN",
    "gn:dem":395,
    "gn:feature_class":"P",
    "gn:feature_code":"PPL",
    "gn:name":"Sipingjie Donggou",
    "gn:population":0,
    "gn:timezone":"Asia/Shanghai",
    "iso:country":"CN",
    "name:und_x_variant":[
        "\u56db\u5e73\u8857\u4e1c\u6c9f"
    ],
    "name:zho_x_preferred":[
        "\u56db\u5e73\u8857\u4e1c\u6c9f"
    ],
    "wof:name":"Sipingjie Donggou",
    "wof:placetype":"locality"
},
  "geometry": {"coordinates":[125.24251,40.7967],"type":"Point"}
}