{
  "type": "Feature",
  "properties": {
    "gn:admin1_code":"19.0",
    "gn:asciiname":"Dongganhezi",
    "gn:country_code":"CN",
    "gn:dem":22,
    "gn:feature_class":"P",
    "gn:feature_code":"PPL",
    "gn:name":"Dongganhezi",
    "gn:population":0,
    "gn:timezone":"Asia/Shanghai",
    "iso:country":"CN",
    "name:zho_x_preferred":[
        "\u4e1c\u5e72\u6cb3\u5b50"
    ],
    "wof:name":"Dongganhezi",
    "wof:placetype":"locality"
},
  "geometry": {"coordinates":[123.12853,41.32866],"type":"Point"}
}