{
  "type": "Feature",
  "properties": {
    "gn:admin1_code":"4.0",
    "gn:asciiname":"Yuke",
    "gn:country_code":"CN",
    "gn:dem":5,
    "gn:feature_class":"P",
    "gn:feature_code":"PPL",
    "gn:name":"Yuke",
    "gn:population":0,
    "gn:timezone":"Asia/Shanghai",
    "iso:country":"CN",
    "name:zho_x_preferred":[
        "\u88d5\u8bfe"
    ],
    "wof:name":"Yuke",
    "wof:placetype":"locality"
},
  "geometry": {"coordinates":[119.21258,32.19288],"type":"Point"}
}