{
  "type": "Feature",
  "properties": {
    "gn:admin1_code":"10",
    "gn:asciiname":"Luotuo Bozi",
    "gn:country_code":"CN",
    "gn:dem":1085,
    "gn:feature_class":"P",
    "gn:feature_code":"PPL",
    "gn:name":"Luotuo Bozi",
    "gn:population":0,
    "gn:timezone":"Asia/Shanghai",
    "iso:country":"CN",
    "name:zho_x_preferred":[
        "\u9a86\u9a7c\u8116\u5b50"
    ],
    "wof:name":"Luotuo Bozi",
    "wof:placetype":"locality"
},
  "geometry": {"coordinates":[116.93783000000001,41.98127],"type":"Point"}
}