{
  "type": "Feature",
  "properties": {
    "gn:admin1_code":"21.0",
    "gn:asciiname":"Heijia Guaizi",
    "gn:country_code":"CN",
    "gn:dem":1781,
    "gn:feature_class":"P",
    "gn:feature_code":"PPL",
    "gn:name":"Heijia Guaizi",
    "gn:population":0,
    "gn:timezone":"Asia/Shanghai",
    "iso:country":"CN",
    "name:zho_x_preferred":[
        "\u9ed1\u5bb6\u62d0\u5b50"
    ],
    "wof:name":"Heijia Guaizi",
    "wof:placetype":"locality"
},
  "geometry": {"coordinates":[105.874,36.5037],"type":"Point"}
}