{
  "type": "Feature",
  "properties": {
    "gn:admin1_code":"15",
    "gn:asciiname":"Wudunzi",
    "gn:country_code":"CN",
    "gn:dem":2043,
    "gn:feature_class":"P",
    "gn:feature_code":"PPL",
    "gn:name":"Wudunzi",
    "gn:population":0,
    "gn:timezone":"Asia/Shanghai",
    "iso:country":"CN",
    "wof:name":"Wudunzi",
    "wof:placetype":"locality"
},
  "geometry": {"coordinates":[103.69638999999999,36.61306],"type":"Point"}
}