{
  "type": "Feature",
  "properties": {
    "gn:admin1_code":"19.0",
    "gn:asciiname":"Pianshilianzi",
    "gn:country_code":"CN",
    "gn:dem":299,
    "gn:feature_class":"P",
    "gn:feature_code":"PPL",
    "gn:name":"Pianshilianzi",
    "gn:population":0,
    "gn:timezone":"Asia/Shanghai",
    "iso:country":"CN",
    "name:zho_x_preferred":[
        "\u504f\u77f3\u8138\u5b50"
    ],
    "wof:name":"Pianshilianzi",
    "wof:placetype":"locality"
},
  "geometry": {"coordinates":[122.20699999999999,39.9382],"type":"Point"}
}