{
  "type": "Feature",
  "properties": {
    "gn:admin1_code":"5.0",
    "gn:asciiname":"Sanjiacun",
    "gn:country_code":"CN",
    "gn:dem":215,
    "gn:feature_class":"P",
    "gn:feature_code":"PPL",
    "gn:name":"Sanjiacun",
    "gn:population":0,
    "gn:timezone":"Asia/Shanghai",
    "iso:country":"CN",
    "name:zho_x_preferred":[
        "\u4e09\u5bb6\u6751"
    ],
    "wof:name":"Sanjiacun",
    "wof:placetype":"locality"
},
  "geometry": {"coordinates":[126.89507,44.5927],"type":"Point"}
}