{
  "type": "Feature",
  "properties": {
    "gn:admin1_code":"32.0",
    "gn:asciiname":"Waduo",
    "gn:country_code":"CN",
    "gn:dem":3257,
    "gn:feature_class":"P",
    "gn:feature_code":"PPL",
    "gn:name":"Waduo",
    "gn:population":0,
    "gn:timezone":"Asia/Shanghai",
    "iso:country":"CN",
    "name:zho_x_preferred":[
        "\u54c7\u591a"
    ],
    "wof:name":"Waduo",
    "wof:placetype":"locality"
},
  "geometry": {"coordinates":[101.866,32.807],"type":"Point"}
}