{
  "type": "Feature",
  "properties": {
    "gn:admin1_code":"19.0",
    "gn:asciiname":"Fujiagou",
    "gn:country_code":"CN",
    "gn:dem":70,
    "gn:feature_class":"P",
    "gn:feature_code":"PPL",
    "gn:name":"Fujiagou",
    "gn:population":0,
    "gn:timezone":"Asia/Shanghai",
    "iso:country":"CN",
    "name:zho_x_preferred":[
        "\u4ed8\u5bb6\u6c9f"
    ],
    "wof:name":"Fujiagou",
    "wof:placetype":"locality"
},
  "geometry": {"coordinates":[121.494,38.9995],"type":"Point"}
}