{
  "type": "Feature",
  "properties": {
    "gn:admin1_code":"33.0",
    "gn:asciiname":"Min'an",
    "gn:country_code":"CN",
    "gn:dem":733,
    "gn:feature_class":"P",
    "gn:feature_code":"PPL",
    "gn:name":"Min\u2019an",
    "gn:population":0,
    "gn:timezone":"Asia/Shanghai",
    "iso:country":"CN",
    "name:und_x_variant":[
        "Min\u2019an"
    ],
    "name:zho_x_preferred":[
        "\u6c11\u5b89"
    ],
    "name:zho_x_variant":[
        "\u6c11\u5b89\u8857\u9053"
    ],
    "wof:name":"Min'an",
    "wof:placetype":"locality"
},
  "geometry": {"coordinates":[108.53872,29.08113],"type":"Point"}
}