{
  "type": "Feature",
  "properties": {
    "gn:admin1_code":"12.0",
    "gn:asciiname":"Ziqiu",
    "gn:country_code":"CN",
    "gn:dem":292,
    "gn:feature_class":"P",
    "gn:feature_code":"PPLA4",
    "gn:name":"Ziqiu",
    "gn:population":0,
    "gn:timezone":"Asia/Shanghai",
    "iso:country":"CN",
    "name:und_x_variant":[
        "Tzu-ch\u2019iu",
        "Tzekiu",
        "Ziqiu",
        "Ziqiu Zhen"
    ],
    "name:zho_x_preferred":[
        "\u8d44\u4e18"
    ],
    "name:zho_x_variant":[
        "\u8d44\u4e18\u9547"
    ],
    "wof:name":"Ziqiu",
    "wof:placetype":"locality"
},
  "geometry": {"coordinates":[110.67801,30.43733],"type":"Point"}
}