{
  "type": "Feature",
  "properties": {
    "gn:admin1_code":"11.0",
    "gn:asciiname":"Shilong",
    "gn:country_code":"CN",
    "gn:dem":208,
    "gn:feature_class":"P",
    "gn:feature_code":"PPL",
    "gn:name":"Shilong",
    "gn:population":0,
    "gn:timezone":"Asia/Shanghai",
    "iso:country":"CN",
    "name:und_x_variant":[
        "Longjiawu"
    ],
    "name:zho_x_preferred":[
        "\u77f3\u9f99"
    ],
    "name:zho_x_variant":[
        "\u9f99\u5bb6\u5c4b"
    ],
    "wof:name":"Shilong",
    "wof:placetype":"locality"
},
  "geometry": {"coordinates":[113.84528,26.92746],"type":"Point"}
}