{
  "type": "Feature",
  "properties": {
    "gn:admin1_code":"3.0",
    "gn:asciiname":"Yejiadong",
    "gn:country_code":"CN",
    "gn:dem":206,
    "gn:feature_class":"P",
    "gn:feature_code":"PPL",
    "gn:name":"Yejiadong",
    "gn:population":0,
    "gn:timezone":"Asia/Shanghai",
    "iso:country":"CN",
    "name:und_x_variant":[
        "\u53f6\u5bb6\u6d1e"
    ],
    "wof:name":"Yejiadong",
    "wof:placetype":"locality"
},
  "geometry": {"coordinates":[115.99881000000001,25.8742],"type":"Point"}
}