{
  "type": "Feature",
  "properties": {
    "gn:admin1_code":"19.0",
    "gn:asciiname":"Gushuzi",
    "gn:country_code":"CN",
    "gn:dem":97,
    "gn:feature_class":"P",
    "gn:feature_code":"PPL",
    "gn:name":"Gushuzi",
    "gn:population":0,
    "gn:timezone":"Asia/Shanghai",
    "iso:country":"CN",
    "name:zho_x_preferred":[
        "\u5b64\u6811\u5b50"
    ],
    "wof:name":"Gushuzi",
    "wof:placetype":"locality"
},
  "geometry": {"coordinates":[123.43575,42.57793],"type":"Point"}
}