{
  "type": "Feature",
  "properties": {
    "gn:admin1_code":"18.0",
    "gn:asciiname":"Diyin",
    "gn:country_code":"CN",
    "gn:dem":865,
    "gn:feature_class":"P",
    "gn:feature_code":"PPL",
    "gn:name":"Diyin",
    "gn:population":0,
    "gn:timezone":"Asia/Shanghai",
    "iso:country":"CN",
    "name:zho_x_preferred":[
        "\u5730\u5370"
    ],
    "wof:name":"Diyin",
    "wof:placetype":"locality"
},
  "geometry": {"coordinates":[108.32599999999999,27.3739],"type":"Point"}
}