{
  "type": "Feature",
  "properties": {
    "gn:admin1_code":"4.0",
    "gn:asciiname":"Hefeng Erzu",
    "gn:country_code":"CN",
    "gn:dem":0,
    "gn:feature_class":"P",
    "gn:feature_code":"PPLF",
    "gn:name":"Hefeng Erzu",
    "gn:population":0,
    "gn:timezone":"Asia/Shanghai",
    "iso:country":"CN",
    "name:zho_x_preferred":[
        "\u8d3a\u4e30\u4e8c\u7ec4"
    ],
    "wof:name":"Hefeng Erzu",
    "wof:placetype":"locality"
},
  "geometry": {"coordinates":[120.387,33.6243],"type":"Point"}
}