{
  "type": "Feature",
  "properties": {
    "gn:admin1_code":"18",
    "gn:asciiname":"Shaojiba",
    "gn:country_code":"CN",
    "gn:dem":922,
    "gn:feature_class":"P",
    "gn:feature_code":"PPL",
    "gn:name":"Shaojiba",
    "gn:population":0,
    "gn:timezone":"Asia/Shanghai",
    "iso:country":"CN",
    "name:zho_x_preferred":[
        "\u7b72\u7b95\u575d"
    ],
    "wof:name":"Shaojiba",
    "wof:placetype":"locality"
},
  "geometry": {"coordinates":[106.122,27.6978],"type":"Point"}
}