{
  "type": "Feature",
  "properties": {
    "gn:admin1_code":"32.0",
    "gn:asciiname":"Jiangjunmiao",
    "gn:country_code":"CN",
    "gn:dem":1610,
    "gn:feature_class":"P",
    "gn:feature_code":"PPL",
    "gn:name":"Jiangjunmiao",
    "gn:population":0,
    "gn:timezone":"Asia/Shanghai",
    "iso:country":"CN",
    "name:zho_x_preferred":[
        "\u5c06\u519b\u5e99"
    ],
    "wof:name":"Jiangjunmiao",
    "wof:placetype":"locality"
},
  "geometry": {"coordinates":[103.19280000000001,30.50189],"type":"Point"}
}