{
  "type": "Feature",
  "properties": {
    "gn:admin1_code":"20.0",
    "gn:asciiname":"Sanpaozi",
    "gn:country_code":"CN",
    "gn:dem":716,
    "gn:feature_class":"P",
    "gn:feature_code":"PPL",
    "gn:name":"Sanpaozi",
    "gn:population":0,
    "gn:timezone":"Asia/Shanghai",
    "iso:country":"CN",
    "name:zho_x_preferred":[
        "\u4e09\u6ce1\u5b50"
    ],
    "wof:name":"Sanpaozi",
    "wof:placetype":"locality"
},
  "geometry": {"coordinates":[120.93958000000001,49.50565],"type":"Point"}
}