{
  "type": "Feature",
  "properties": {
    "gn:admin1_code":"11.0",
    "gn:asciiname":"Tietouling",
    "gn:country_code":"CN",
    "gn:dem":72,
    "gn:feature_class":"P",
    "gn:feature_code":"PPL",
    "gn:name":"Tietouling",
    "gn:population":0,
    "gn:timezone":"Asia/Shanghai",
    "iso:country":"CN",
    "name:zho_x_preferred":[
        "\u94c1\u5934\u5cad"
    ],
    "wof:name":"Tietouling",
    "wof:placetype":"locality"
},
  "geometry": {"coordinates":[112.97169,27.29235],"type":"Point"}
}