{
  "type": "Feature",
  "properties": {
    "gn:admin1_code":"29.0",
    "gn:asciiname":"Laoka Zhongzhai",
    "gn:country_code":"CN",
    "gn:dem":987,
    "gn:feature_class":"P",
    "gn:feature_code":"PPL",
    "gn:name":"Laoka Zhongzhai",
    "gn:population":0,
    "gn:timezone":"Asia/Shanghai",
    "iso:country":"CN",
    "name:zho_x_preferred":[
        "\u8001\u5361\u4e2d\u5be8"
    ],
    "wof:name":"Laoka Zhongzhai",
    "wof:placetype":"locality"
},
  "geometry": {"coordinates":[104.261,22.855],"type":"Point"}
}