{
  "type": "Feature",
  "properties": {
    "gn:admin1_code":"21.0",
    "gn:asciiname":"Lijia Buzi",
    "gn:country_code":"CN",
    "gn:dem":1619,
    "gn:feature_class":"P",
    "gn:feature_code":"PPL",
    "gn:name":"Lijia Buzi",
    "gn:population":0,
    "gn:timezone":"Asia/Shanghai",
    "iso:country":"CN",
    "name:zho_x_preferred":[
        "\u674e\u5bb6\u5821\u5b50"
    ],
    "wof:name":"Lijia Buzi",
    "wof:placetype":"locality"
},
  "geometry": {"coordinates":[106.54600000000001,37.0357],"type":"Point"}
}