{
  "type": "Feature",
  "properties": {
    "gn:admin1_code":"2.0",
    "gn:asciiname":"Meiyuan",
    "gn:country_code":"CN",
    "gn:dem":439,
    "gn:feature_class":"P",
    "gn:feature_code":"PPL",
    "gn:name":"Meiyuan",
    "gn:population":0,
    "gn:timezone":"Asia/Shanghai",
    "iso:country":"CN",
    "name:zho_x_preferred":[
        "\u6885\u56ed"
    ],
    "wof:name":"Meiyuan",
    "wof:placetype":"locality"
},
  "geometry": {"coordinates":[120.99517,28.70023],"type":"Point"}
}