{
  "type": "Feature",
  "properties": {
    "gn:admin1_code":"10",
    "gn:asciiname":"Sangshu Wopu",
    "gn:country_code":"CN",
    "gn:dem":257,
    "gn:feature_class":"P",
    "gn:feature_code":"PPL",
    "gn:name":"Sangshu Wopu",
    "gn:population":0,
    "gn:timezone":"Asia/Shanghai",
    "iso:country":"CN",
    "name:zho_x_preferred":[
        "\u6851\u6811\u7a9d\u94fa"
    ],
    "wof:name":"Sangshu Wopu",
    "wof:placetype":"locality"
},
  "geometry": {"coordinates":[119.48163999999998,40.23849000000001],"type":"Point"}
}