{
  "type": "Feature",
  "properties": {
    "gn:admin1_code":"16.0",
    "gn:asciiname":"Lingwei",
    "gn:country_code":"CN",
    "gn:dem":181,
    "gn:feature_class":"P",
    "gn:feature_code":"PPL",
    "gn:name":"Lingwei",
    "gn:population":0,
    "gn:timezone":"Asia/Shanghai",
    "iso:country":"CN",
    "name:zho_x_preferred":[
        "\u5cad\u5c3e"
    ],
    "wof:name":"Lingwei",
    "wof:placetype":"locality"
},
  "geometry": {"coordinates":[110.76300000000001,24.5079],"type":"Point"}
}