{
  "type": "Feature",
  "properties": {
    "gn:admin1_code":"30",
    "gn:asciiname":"Houling",
    "gn:country_code":"CN",
    "gn:dem":21,
    "gn:feature_class":"P",
    "gn:feature_code":"PPL",
    "gn:name":"Houling",
    "gn:population":0,
    "gn:timezone":"Asia/Urumqi",
    "iso:country":"CN",
    "name:zho_x_preferred":[
        "\u540e\u5cad"
    ],
    "wof:name":"Houling",
    "wof:placetype":"locality"
},
  "geometry": {"coordinates":[110.30707,20.79957000000001],"type":"Point"}
}