{
  "type": "Feature",
  "properties": {
    "gn:admin1_code":"11.0",
    "gn:asciiname":"Gaotuo",
    "gn:country_code":"CN",
    "gn:dem":687,
    "gn:feature_class":"P",
    "gn:feature_code":"PPL",
    "gn:name":"Gaotuo",
    "gn:population":0,
    "gn:timezone":"Asia/Shanghai",
    "iso:country":"CN",
    "name:zho_x_preferred":[
        "\u9ad8\u5768"
    ],
    "wof:name":"Gaotuo",
    "wof:placetype":"locality"
},
  "geometry": {"coordinates":[110.61476999999999,27.49744],"type":"Point"}
}