{
  "type": "Feature",
  "properties": {
    "gn:admin1_code":"5.0",
    "gn:asciiname":"Banshicun",
    "gn:country_code":"CN",
    "gn:dem":292,
    "gn:feature_class":"P",
    "gn:feature_code":"PPL",
    "gn:name":"Banshicun",
    "gn:population":0,
    "gn:timezone":"Asia/Shanghai",
    "iso:country":"CN",
    "name:zho_x_preferred":[
        "\u677f\u77f3\u6751"
    ],
    "wof:name":"Banshicun",
    "wof:placetype":"locality"
},
  "geometry": {"coordinates":[125.79378,43.39486],"type":"Point"}
}