{
  "type": "Feature",
  "properties": {
    "gn:admin1_code":"29",
    "gn:asciiname":"Songmaoke",
    "gn:country_code":"CN",
    "gn:dem":980,
    "gn:feature_class":"P",
    "gn:feature_code":"PPL",
    "gn:name":"Songmaoke",
    "gn:population":0,
    "gn:timezone":"Asia/Shanghai",
    "iso:country":"CN",
    "name:zho_x_preferred":[
        "\u677e\u6bdb\u68f5"
    ],
    "wof:name":"Songmaoke",
    "wof:placetype":"locality"
},
  "geometry": {"coordinates":[104.462,23.2232],"type":"Point"}
}