{
  "type": "Feature",
  "properties": {
    "gn:admin1_code":"07",
    "gn:asciiname":"Xiahaoshan",
    "gn:country_code":"CN",
    "gn:dem":699,
    "gn:feature_class":"P",
    "gn:feature_code":"PPL",
    "gn:name":"Xiahaoshan",
    "gn:population":0,
    "gn:timezone":"Asia/Shanghai",
    "iso:country":"CN",
    "name:zho_x_preferred":[
        "\u4e0b\u8c6a\u5c71"
    ],
    "wof:name":"Xiahaoshan",
    "wof:placetype":"locality"
},
  "geometry": {"coordinates":[117.40039,25.0708],"type":"Point"}
}