{
  "type": "Feature",
  "properties": {
    "gn:admin1_code":"19.0",
    "gn:asciiname":"Guanjiatun",
    "gn:country_code":"CN",
    "gn:dem":94,
    "gn:feature_class":"P",
    "gn:feature_code":"PPL",
    "gn:name":"Guanjiatun",
    "gn:population":0,
    "gn:timezone":"Asia/Shanghai",
    "iso:country":"CN",
    "name:zho_x_preferred":[
        "\u5173\u5bb6\u5c6f"
    ],
    "wof:name":"Guanjiatun",
    "wof:placetype":"locality"
},
  "geometry": {"coordinates":[123.34088,42.6979],"type":"Point"}
}