{
  "type": "Feature",
  "properties": {
    "gn:admin1_code":"2.0",
    "gn:asciiname":"Xialangqiao",
    "gn:country_code":"CN",
    "gn:dem":108,
    "gn:feature_class":"P",
    "gn:feature_code":"PPL",
    "gn:name":"Xialangqiao",
    "gn:population":0,
    "gn:timezone":"Asia/Shanghai",
    "iso:country":"CN",
    "name:zho_x_preferred":[
        "\u4e0b\u90ce\u6865"
    ],
    "wof:name":"Xialangqiao",
    "wof:placetype":"locality"
},
  "geometry": {"coordinates":[119.72077,28.90063],"type":"Point"}
}