{
  "type": "Feature",
  "properties": {
    "gn:admin1_code":"21.0",
    "gn:asciiname":"Songjiawa",
    "gn:country_code":"CN",
    "gn:dem":1667,
    "gn:feature_class":"P",
    "gn:feature_code":"PPL",
    "gn:name":"Songjiawa",
    "gn:population":0,
    "gn:timezone":"Asia/Shanghai",
    "iso:country":"CN",
    "name:und_x_variant":[
        "\u5b8b\u5bb6\u6d3c"
    ],
    "name:zho_x_preferred":[
        "\u5b8b\u5bb6\u6d3c"
    ],
    "wof:name":"Songjiawa",
    "wof:placetype":"locality"
},
  "geometry": {"coordinates":[106.26824000000001,36.18258],"type":"Point"}
}