{
  "type": "Feature",
  "properties": {
    "gn:admin1_code":"18.0",
    "gn:asciiname":"Xindian",
    "gn:country_code":"CN",
    "gn:dem":390,
    "gn:feature_class":"P",
    "gn:feature_code":"PPL",
    "gn:name":"Xindian",
    "gn:population":0,
    "gn:timezone":"Asia/Shanghai",
    "iso:country":"CN",
    "wof:name":"Xindian",
    "wof:placetype":"locality"
},
  "geometry": {"coordinates":[108.84889,27.19444],"type":"Point"}
}