{
  "type": "Feature",
  "properties": {
    "gn:admin1_code":"26.0",
    "gn:asciiname":"Yuejialiang",
    "gn:country_code":"CN",
    "gn:dem":1237,
    "gn:feature_class":"P",
    "gn:feature_code":"PPL",
    "gn:name":"Yuejialiang",
    "gn:population":0,
    "gn:timezone":"Asia/Shanghai",
    "iso:country":"CN",
    "name:zho_x_preferred":[
        "\u6708\u5bb6\u6881"
    ],
    "wof:name":"Yuejialiang",
    "wof:placetype":"locality"
},
  "geometry": {"coordinates":[109.51451000000002,37.62564],"type":"Point"}
}