{
  "type": "Feature",
  "properties": {
    "gn:admin1_code":"32.0",
    "gn:asciiname":"Sangengzi",
    "gn:country_code":"CN",
    "gn:dem":2503,
    "gn:feature_class":"P",
    "gn:feature_code":"PPL",
    "gn:name":"Sangengzi",
    "gn:population":0,
    "gn:timezone":"Asia/Shanghai",
    "iso:country":"CN",
    "name:zho_x_preferred":[
        "\u4e09\u57c2\u5b50"
    ],
    "wof:name":"Sangengzi",
    "wof:placetype":"locality"
},
  "geometry": {"coordinates":[102.146,31.2317],"type":"Point"}
}