{
  "type": "Feature",
  "properties": {
    "gn:admin1_code":"16.0",
    "gn:asciiname":"Yakouzhai",
    "gn:country_code":"CN",
    "gn:dem":1411,
    "gn:feature_class":"P",
    "gn:feature_code":"PPL",
    "gn:name":"Yakouzhai",
    "gn:population":0,
    "gn:timezone":"Asia/Shanghai",
    "iso:country":"CN",
    "name:zho_x_preferred":[
        "\u4e2b\u53e3\u5be8"
    ],
    "wof:name":"Yakouzhai",
    "wof:placetype":"locality"
},
  "geometry": {"coordinates":[105.51900000000001,24.6604],"type":"Point"}
}