{
  "type": "Feature",
  "properties": {
    "gn:admin1_code":"18.0",
    "gn:asciiname":"Tianlong",
    "gn:country_code":"CN",
    "gn:dem":1092,
    "gn:feature_class":"P",
    "gn:feature_code":"PPL",
    "gn:name":"Tianlong",
    "gn:population":0,
    "gn:timezone":"Asia/Shanghai",
    "iso:country":"CN",
    "wof:name":"Tianlong",
    "wof:placetype":"locality"
},
  "geometry": {"coordinates":[106.61583,28.23639],"type":"Point"}
}