{
  "type": "Feature",
  "properties": {
    "gn:admin1_code":"30.0",
    "gn:asciiname":"Jianzibei",
    "gn:country_code":"CN",
    "gn:dem":158,
    "gn:feature_class":"P",
    "gn:feature_code":"PPL",
    "gn:name":"Jianzibei",
    "gn:population":0,
    "gn:timezone":"Asia/Shanghai",
    "iso:country":"CN",
    "name:zho_x_preferred":[
        "Jianzibei"
    ],
    "name:zho_x_variant":[
        "\u7b80\u5b50\u80cc"
    ],
    "wof:name":"Jianzibei",
    "wof:placetype":"locality"
},
  "geometry": {"coordinates":[114.9575,24.37944],"type":"Point"}
}