{
  "type": "Feature",
  "properties": {
    "gn:admin1_code":"03",
    "gn:asciiname":"Shuibei",
    "gn:country_code":"CN",
    "gn:dem":52,
    "gn:feature_class":"P",
    "gn:feature_code":"PPLA4",
    "gn:name":"Shuibei",
    "gn:population":0,
    "gn:timezone":"Asia/Shanghai",
    "iso:country":"CN",
    "name:und_x_variant":[
        "Shui-pei",
        "Shui-pei-chieh",
        "Shuibei",
        "\u6c34\u5317",
        "Shuibei Zhen",
        "\u6c34\u5317\u9547"
    ],
    "wof:name":"Shuibei",
    "wof:placetype":"locality"
},
  "geometry": {"coordinates":[115.05725,28.04118],"type":"Point"}
}