{
  "type": "Feature",
  "properties": {
    "gn:admin1_code":"32.0",
    "gn:asciiname":"Loufangtou",
    "gn:country_code":"CN",
    "gn:dem":374,
    "gn:feature_class":"P",
    "gn:feature_code":"PPL",
    "gn:name":"Loufangtou",
    "gn:population":0,
    "gn:timezone":"Asia/Shanghai",
    "iso:country":"CN",
    "name:zho_x_preferred":[
        "\u697c\u623f\u5934"
    ],
    "wof:name":"Loufangtou",
    "wof:placetype":"locality"
},
  "geometry": {"coordinates":[105.01300000000001,28.8208],"type":"Point"}
}