{
  "type": "Feature",
  "properties": {
    "gn:admin1_code":"4.0",
    "gn:asciiname":"Huangxiecun",
    "gn:country_code":"CN",
    "gn:dem":6,
    "gn:feature_class":"P",
    "gn:feature_code":"PPL",
    "gn:name":"Huangxiecun",
    "gn:population":0,
    "gn:timezone":"Asia/Shanghai",
    "iso:country":"CN",
    "name:zho_x_preferred":[
        "\u9ec4\u8c22\u6751"
    ],
    "wof:name":"Huangxiecun",
    "wof:placetype":"locality"
},
  "geometry": {"coordinates":[120.32092,31.26933],"type":"Point"}
}