{
  "type": "Feature",
  "properties": {
    "gn:admin1_code":"19.0",
    "gn:asciiname":"Sanzuodian",
    "gn:country_code":"CN",
    "gn:dem":334,
    "gn:feature_class":"P",
    "gn:feature_code":"PPL",
    "gn:name":"Sanzuodian",
    "gn:population":0,
    "gn:timezone":"Asia/Shanghai",
    "iso:country":"CN",
    "name:und_x_variant":[
        "\u4e09\u5ea7\u5e97"
    ],
    "name:zho_x_preferred":[
        "\u4e09\u5ea7\u5e97"
    ],
    "wof:name":"Sanzuodian",
    "wof:placetype":"locality"
},
  "geometry": {"coordinates":[119.87654000000001,41.00766],"type":"Point"}
}