{
  "type": "Feature",
  "properties": {
    "gn:admin1_code":"9",
    "gn:asciiname":"Changlukou",
    "gn:country_code":"CN",
    "gn:dem":52,
    "gn:feature_class":"P",
    "gn:feature_code":"PPL",
    "gn:name":"Changlukou",
    "gn:population":0,
    "gn:timezone":"Asia/Shanghai",
    "iso:country":"CN",
    "name:zho_x_preferred":[
        "\u5e38\u8def\u53e3"
    ],
    "wof:name":"Changlukou",
    "wof:placetype":"locality"
},
  "geometry": {"coordinates":[115.587,34.379],"type":"Point"}
}