{
  "type": "Feature",
  "properties": {
    "gn:admin1_code":"32.0",
    "gn:asciiname":"Chayuanzi",
    "gn:country_code":"CN",
    "gn:dem":1294,
    "gn:feature_class":"P",
    "gn:feature_code":"PPL",
    "gn:name":"Chayuanzi",
    "gn:population":0,
    "gn:timezone":"Asia/Shanghai",
    "iso:country":"CN",
    "name:zho_x_preferred":[
        "\u8336\u9662\u5b50"
    ],
    "wof:name":"Chayuanzi",
    "wof:placetype":"locality"
},
  "geometry": {"coordinates":[108.10298,32.14152],"type":"Point"}
}