{
  "type": "Feature",
  "properties": {
    "gn:admin1_code":"11.0",
    "gn:asciiname":"Aogengtian",
    "gn:country_code":"CN",
    "gn:dem":372,
    "gn:feature_class":"P",
    "gn:feature_code":"PPL",
    "gn:name":"Aogengtian",
    "gn:population":0,
    "gn:timezone":"Asia/Shanghai",
    "iso:country":"CN",
    "name:zho_x_preferred":[
        "\u5773\u9888\u7530"
    ],
    "wof:name":"Aogengtian",
    "wof:placetype":"locality"
},
  "geometry": {"coordinates":[109.93597,27.22515],"type":"Point"}
}