{
  "type": "Feature",
  "properties": {
    "gn:admin1_code":"29.0",
    "gn:asciiname":"Chare",
    "gn:country_code":"CN",
    "gn:dem":3322,
    "gn:feature_class":"P",
    "gn:feature_code":"PPL",
    "gn:name":"Chare",
    "gn:population":0,
    "gn:timezone":"Asia/Shanghai",
    "iso:country":"CN",
    "name:zho_x_preferred":[
        "\u67e5\u70ed"
    ],
    "wof:name":"Chare",
    "wof:placetype":"locality"
},
  "geometry": {"coordinates":[99.6176,28.0426],"type":"Point"}
}