{
  "type": "Feature",
  "properties": {
    "gn:admin1_code":"24.0",
    "gn:asciiname":"Zhangli",
    "gn:country_code":"CN",
    "gn:dem":450,
    "gn:feature_class":"P",
    "gn:feature_code":"PPL",
    "gn:name":"Zhangli",
    "gn:population":0,
    "gn:timezone":"Asia/Shanghai",
    "iso:country":"CN",
    "name:und_x_variant":[
        "Chang-li-ts\u2019un",
        "Chang-li",
        "Zhangli",
        "\u5f20\u793c"
    ],
    "wof:name":"Zhangli",
    "wof:placetype":"locality"
},
  "geometry": {"coordinates":[111.47035,35.99136],"type":"Point"}
}