{
  "type": "Feature",
  "properties": {
    "gn:admin1_code":"8.0",
    "gn:asciiname":"Xiaosihetun",
    "gn:country_code":"CN",
    "gn:dem":133,
    "gn:feature_class":"P",
    "gn:feature_code":"PPL",
    "gn:name":"Xiaosihetun",
    "gn:population":0,
    "gn:timezone":"Asia/Shanghai",
    "iso:country":"CN",
    "name:zho_x_preferred":[
        "\u5c0f\u56db\u5408\u5c6f"
    ],
    "wof:name":"Xiaosihetun",
    "wof:placetype":"locality"
},
  "geometry": {"coordinates":[126.48638,46.33368],"type":"Point"}
}