{
  "type": "Feature",
  "properties": {
    "gn:admin1_code":"5.0",
    "gn:asciiname":"Taipingshancun",
    "gn:country_code":"CN",
    "gn:dem":129,
    "gn:feature_class":"P",
    "gn:feature_code":"PPL",
    "gn:name":"Taipingshancun",
    "gn:population":0,
    "gn:timezone":"Asia/Shanghai",
    "iso:country":"CN",
    "name:zho_x_preferred":[
        "\u592a\u5e73\u5c71\u6751"
    ],
    "wof:name":"Taipingshancun",
    "wof:placetype":"locality"
},
  "geometry": {"coordinates":[124.62689,45.32615],"type":"Point"}
}