{
  "type": "Feature",
  "properties": {
    "gn:admin1_code":"12.0",
    "gn:asciiname":"Maojiayuan",
    "gn:country_code":"CN",
    "gn:dem":632,
    "gn:feature_class":"P",
    "gn:feature_code":"PPL",
    "gn:name":"Maojiayuan",
    "gn:population":0,
    "gn:timezone":"Asia/Shanghai",
    "iso:country":"CN",
    "name:zho_x_preferred":[
        "\u6bdb\u5bb6\u9662"
    ],
    "wof:name":"Maojiayuan",
    "wof:placetype":"locality"
},
  "geometry": {"coordinates":[110.91630000000001,32.07275],"type":"Point"}
}