{
  "type": "Feature",
  "properties": {
    "gn:admin1_code":"30.0",
    "gn:asciiname":"Dawo",
    "gn:country_code":"CN",
    "gn:dem":14,
    "gn:feature_class":"P",
    "gn:feature_code":"PPL",
    "gn:name":"Dawo",
    "gn:population":0,
    "gn:timezone":"Asia/Shanghai",
    "iso:country":"CN",
    "name:fra_x_preferred":[
        "Dawo"
    ],
    "name:zho_x_preferred":[
        "\u5927\u6da1"
    ],
    "wof:name":"Dawo",
    "wof:placetype":"locality"
},
  "geometry": {"coordinates":[112.89815,23.06448],"type":"Point"}
}