{
  "type": "Feature",
  "properties": {
    "gn:admin1_code":"3.0",
    "gn:asciiname":"Chunling",
    "gn:country_code":"CN",
    "gn:dem":146,
    "gn:feature_class":"P",
    "gn:feature_code":"PPL",
    "gn:name":"Chunling",
    "gn:population":0,
    "gn:timezone":"Asia/Shanghai",
    "iso:country":"CN",
    "name:und_x_variant":[
        "\u6df3\u5cad"
    ],
    "wof:name":"Chunling",
    "wof:placetype":"locality"
},
  "geometry": {"coordinates":[116.14731,27.25363],"type":"Point"}
}