{
  "type": "Feature",
  "properties": {
    "gn:admin1_code":"16.0",
    "gn:asciiname":"Shangfu",
    "gn:country_code":"CN",
    "gn:dem":397,
    "gn:feature_class":"P",
    "gn:feature_code":"PPL",
    "gn:name":"Shangfu",
    "gn:population":0,
    "gn:timezone":"Asia/Shanghai",
    "iso:country":"CN",
    "name:zho_x_preferred":[
        "\u4e0a\u752b"
    ],
    "wof:name":"Shangfu",
    "wof:placetype":"locality"
},
  "geometry": {"coordinates":[108.22799999999999,25.3668],"type":"Point"}
}