{
  "type": "Feature",
  "properties": {
    "gn:admin1_code":"11.0",
    "gn:asciiname":"Duli",
    "gn:country_code":"CN",
    "gn:dem":113,
    "gn:feature_class":"P",
    "gn:feature_code":"PPL",
    "gn:name":"Duli",
    "gn:population":0,
    "gn:timezone":"Asia/Shanghai",
    "iso:country":"CN",
    "name:zho_x_preferred":[
        "\u6e21\u91cc"
    ],
    "wof:name":"Duli",
    "wof:placetype":"locality"
},
  "geometry": {"coordinates":[113.59537,26.76242],"type":"Point"}
}