{
  "type": "Feature",
  "properties": {
    "gn:admin1_code":"5.0",
    "gn:asciiname":"Dagengjia Wobu",
    "gn:country_code":"CN",
    "gn:dem":201,
    "gn:feature_class":"P",
    "gn:feature_code":"PPL",
    "gn:name":"Dagengjia Wobu",
    "gn:population":0,
    "gn:timezone":"Asia/Shanghai",
    "iso:country":"CN",
    "name:zho_x_preferred":[
        "\u5927\u803f\u5bb6\u7a9d\u5821"
    ],
    "wof:name":"Dagengjia Wobu",
    "wof:placetype":"locality"
},
  "geometry": {"coordinates":[126.20864,44.81622],"type":"Point"}
}