{
  "type": "Feature",
  "properties": {
    "gn:admin1_code":"15.0",
    "gn:asciiname":"Caojia Tunzhuangzi",
    "gn:country_code":"CN",
    "gn:dem":1405,
    "gn:feature_class":"P",
    "gn:feature_code":"PPL",
    "gn:name":"Caojia Tunzhuangzi",
    "gn:population":0,
    "gn:timezone":"Asia/Shanghai",
    "iso:country":"CN",
    "name:zho_x_preferred":[
        "\u66f9\u5bb6\u5c6f\u5e84\u5b50"
    ],
    "wof:name":"Caojia Tunzhuangzi",
    "wof:placetype":"locality"
},
  "geometry": {"coordinates":[100.149,39.2456],"type":"Point"}
}