{
  "type": "Feature",
  "properties": {
    "gn:admin1_code":"26.0",
    "gn:asciiname":"Xinalingaotu",
    "gn:country_code":"CN",
    "gn:dem":1282,
    "gn:feature_class":"P",
    "gn:feature_code":"PPL",
    "gn:name":"Xinalingaotu",
    "gn:population":0,
    "gn:timezone":"Asia/Shanghai",
    "iso:country":"CN",
    "name:zho_x_preferred":[
        "\u897f\u7eb3\u6797\u9ad8\u5154"
    ],
    "wof:name":"Xinalingaotu",
    "wof:placetype":"locality"
},
  "geometry": {"coordinates":[109.77929,38.68956],"type":"Point"}
}