{
  "type": "Feature",
  "properties": {
    "gn:admin1_code":"15.0",
    "gn:asciiname":"Nijiayuanzi",
    "gn:country_code":"CN",
    "gn:dem":1127,
    "gn:feature_class":"P",
    "gn:feature_code":"PPL",
    "gn:name":"Nijiayuanzi",
    "gn:population":0,
    "gn:timezone":"Asia/Shanghai",
    "iso:country":"CN",
    "name:und_x_variant":[
        "\u502a\u5bb6\u56ed\u5b50"
    ],
    "wof:name":"Nijiayuanzi",
    "wof:placetype":"locality"
},
  "geometry": {"coordinates":[107.72234,36.16161],"type":"Point"}
}