{
  "type": "Feature",
  "properties": {
    "gn:admin1_code":"25",
    "gn:asciiname":"Jiunuguan",
    "gn:country_code":"CN",
    "gn:dem":276,
    "gn:feature_class":"P",
    "gn:feature_code":"PPL",
    "gn:name":"Jiun\u00fcguan",
    "gn:population":0,
    "gn:timezone":"Asia/Shanghai",
    "iso:country":"CN",
    "name:und_x_variant":[
        "Jiun\u00fcguan"
    ],
    "name:zho_x_preferred":[
        "\u4e5d\u5973\u5173"
    ],
    "wof:name":"Jiunuguan",
    "wof:placetype":"locality"
},
  "geometry": {"coordinates":[117.789,35.6335],"type":"Point"}
}