{
  "type": "Feature",
  "properties": {
    "gn:admin1_code":"29",
    "gn:asciiname":"Xijiahei",
    "gn:country_code":"CN",
    "gn:dem":1575,
    "gn:feature_class":"P",
    "gn:feature_code":"PPL",
    "gn:name":"Xijiahei",
    "gn:population":0,
    "gn:timezone":"Asia/Shanghai",
    "iso:country":"CN",
    "name:zho_x_preferred":[
        "\u897f\u5bb6\u9ed1"
    ],
    "wof:name":"Xijiahei",
    "wof:placetype":"locality"
},
  "geometry": {"coordinates":[103.099,24.1132],"type":"Point"}
}