{
  "type": "Feature",
  "properties": {
    "gn:admin1_code":"20",
    "gn:asciiname":"Hobor",
    "gn:country_code":"CN",
    "gn:dem":1745,
    "gn:feature_class":"P",
    "gn:feature_code":"PPLA3",
    "gn:name":"Hobor",
    "gn:population":0,
    "gn:timezone":"Asia/Shanghai",
    "iso:country":"CN",
    "name:mon_x_preferred":[
        "Hobor"
    ],
    "name:und_x_variant":[
        "Qahar Youyi Zhongqi",
        "K\u2019o-pu-erh",
        "Ch\u2019a-yu-chung-ch\u2019i",
        "Ch\u2019a-ha-erh-yu-i-chung-ch\u2019i",
        "Chiu-t\u2019ao-lin",
        "Ch\u2019a-ha-erh-yu-chung-ch\u2019i",
        "T\u2019ao-lin",
        "Chakhar\u2019\u2019yuchzhuntsi",
        "Tao-lin-hsien",
        "Hobor",
        "\u79d1\u5e03\u5c14",
        "Chaha\u2019eryouyizhong Qi",
        "Kebu\u2019er Zhen",
        "\u79d1\u5e03\u5c14\u9547",
        "\u5bdf\u54c8\u5c14\u53f3\u7ffc\u4e2d\u65d7"
    ],
    "name:zho_x_preferred":[
        "Kebu\u2019er"
    ],
    "name:zho_x_variant":[
        "\u79d1\u5e03\u5c14\u9547"
    ],
    "wof:name":"Hobor",
    "wof:placetype":"locality"
},
  "geometry": {"coordinates":[112.62663000000001,41.27154],"type":"Point"}
}