{
  "type": "Feature",
  "properties": {
    "gn:admin1_code":"29",
    "gn:asciiname":"Laomeishu",
    "gn:country_code":"CN",
    "gn:dem":1847,
    "gn:feature_class":"P",
    "gn:feature_code":"PPL",
    "gn:name":"Laomeishu",
    "gn:population":0,
    "gn:timezone":"Asia/Shanghai",
    "iso:country":"CN",
    "name:zho_x_preferred":[
        "\u8001\u6885\u6811"
    ],
    "wof:name":"Laomeishu",
    "wof:placetype":"locality"
},
  "geometry": {"coordinates":[101.45099999999999,25.0868],"type":"Point"}
}