{
  "type": "Feature",
  "properties": {
    "gn:admin1_code":"3",
    "gn:asciiname":"Enziling",
    "gn:country_code":"CN",
    "gn:dem":443,
    "gn:feature_class":"P",
    "gn:feature_code":"PPL",
    "gn:name":"Enziling",
    "gn:population":0,
    "gn:timezone":"Asia/Shanghai",
    "iso:country":"CN",
    "name:zho_x_preferred":[
        "\u6069\u5b50\u5cad"
    ],
    "wof:name":"Enziling",
    "wof:placetype":"locality"
},
  "geometry": {"coordinates":[114.681,26.2879],"type":"Point"}
}