{
  "type": "Feature",
  "properties": {
    "gn:admin1_code":"24.0",
    "gn:asciiname":"Peipeiling",
    "gn:country_code":"CN",
    "gn:dem":973,
    "gn:feature_class":"P",
    "gn:feature_code":"PPL",
    "gn:name":"Peipeiling",
    "gn:population":0,
    "gn:timezone":"Asia/Shanghai",
    "iso:country":"CN",
    "name:zho_x_preferred":[
        "\u88f4\u88f4\u5cad"
    ],
    "wof:name":"Peipeiling",
    "wof:placetype":"locality"
},
  "geometry": {"coordinates":[111.32647,35.06013],"type":"Point"}
}