{
  "type": "Feature",
  "properties": {
    "gn:admin1_code":"30.0",
    "gn:asciiname":"Quzaikou",
    "gn:country_code":"CN",
    "gn:dem":67,
    "gn:feature_class":"P",
    "gn:feature_code":"PPL",
    "gn:name":"Quzaikou",
    "gn:population":0,
    "gn:timezone":"Asia/Shanghai",
    "iso:country":"CN",
    "name:zho_x_preferred":[
        "\u5c48\u4ed4\u53e3"
    ],
    "wof:name":"Quzaikou",
    "wof:placetype":"locality"
},
  "geometry": {"coordinates":[112.84083,23.81306],"type":"Point"}
}