{
  "type": "Feature",
  "properties": {
    "gn:admin1_code":"19.0",
    "gn:asciiname":"Beituchengcun",
    "gn:country_code":"CN",
    "gn:dem":76,
    "gn:feature_class":"P",
    "gn:feature_code":"PPL",
    "gn:name":"Beituchengcun",
    "gn:population":0,
    "gn:timezone":"Asia/Shanghai",
    "iso:country":"CN",
    "name:zho_x_preferred":[
        "\u5317\u571f\u57ce\u6751"
    ],
    "wof:name":"Beituchengcun",
    "wof:placetype":"locality"
},
  "geometry": {"coordinates":[122.97799999999999,42.4871],"type":"Point"}
}