{
  "type": "Feature",
  "properties": {
    "gn:admin1_code":"1.0",
    "gn:asciiname":"Huangzhuangcun",
    "gn:country_code":"CN",
    "gn:dem":28,
    "gn:feature_class":"P",
    "gn:feature_code":"PPL",
    "gn:name":"Huangzhuangcun",
    "gn:population":0,
    "gn:timezone":"Asia/Shanghai",
    "iso:country":"CN",
    "name:zho_x_preferred":[
        "\u9ec4\u5e84\u6751"
    ],
    "wof:name":"Huangzhuangcun",
    "wof:placetype":"locality"
},
  "geometry": {"coordinates":[116.21026000000001,32.56733],"type":"Point"}
}