{
  "type": "Feature",
  "properties": {
    "gn:admin1_code":"19",
    "gn:asciiname":"La-tzu-tsui",
    "gn:country_code":"CN",
    "gn:dem":399,
    "gn:feature_class":"P",
    "gn:feature_code":"PPL",
    "gn:name":"La-tzu-tsui",
    "gn:population":0,
    "gn:timezone":"Asia/Shanghai",
    "iso:country":"CN",
    "name:und_x_variant":[
        "Lazuicun"
    ],
    "name:zho_x_preferred":[
        "\u782c\u5634\u6751"
    ],
    "wof:name":"La-tzu-tsui",
    "wof:placetype":"locality"
},
  "geometry": {"coordinates":[125.06444,41.80806],"type":"Point"}
}