{
  "type": "Feature",
  "properties": {
    "gn:admin1_code":"29.0",
    "gn:asciiname":"Yuelinglong",
    "gn:country_code":"CN",
    "gn:dem":1144,
    "gn:feature_class":"P",
    "gn:feature_code":"PPL",
    "gn:name":"Yuelinglong",
    "gn:population":0,
    "gn:timezone":"Asia/Shanghai",
    "iso:country":"CN",
    "name:zho_x_preferred":[
        "\u6708\u73b2\u73d1"
    ],
    "wof:name":"Yuelinglong",
    "wof:placetype":"locality"
},
  "geometry": {"coordinates":[101.869,25.6758],"type":"Point"}
}