{
  "type": "Feature",
  "properties": {
    "gn:admin1_code":"30.0",
    "gn:asciiname":"Mian'ercun",
    "gn:country_code":"CN",
    "gn:dem":257,
    "gn:feature_class":"P",
    "gn:feature_code":"PPL",
    "gn:name":"Mian\u2019ercun",
    "gn:population":0,
    "gn:timezone":"Asia/Shanghai",
    "iso:country":"CN",
    "name:und_x_variant":[
        "Mian\u2019ercun"
    ],
    "name:zho_x_preferred":[
        "\u68c9\u4e8c\u6751"
    ],
    "wof:name":"Mian'ercun",
    "wof:placetype":"locality"
},
  "geometry": {"coordinates":[115.89631,24.50653],"type":"Point"}
}