{
  "type": "Feature",
  "properties": {
    "gn:admin1_code":"32.0",
    "gn:asciiname":"Banbiansi",
    "gn:country_code":"CN",
    "gn:dem":519,
    "gn:feature_class":"P",
    "gn:feature_code":"PPL",
    "gn:name":"Banbiansi",
    "gn:population":0,
    "gn:timezone":"Asia/Shanghai",
    "iso:country":"CN",
    "name:zho_x_preferred":[
        "\u534a\u8fb9\u5bfa"
    ],
    "wof:name":"Banbiansi",
    "wof:placetype":"locality"
},
  "geometry": {"coordinates":[104.033,30.0703],"type":"Point"}
}