{
  "type": "Feature",
  "properties": {
    "gn:admin1_code":"18.0",
    "gn:asciiname":"Yema",
    "gn:country_code":"CN",
    "gn:dem":896,
    "gn:feature_class":"P",
    "gn:feature_code":"PPL",
    "gn:name":"Yema",
    "gn:population":0,
    "gn:timezone":"Asia/Shanghai",
    "iso:country":"CN",
    "name:ceb_x_preferred":[
        "Yema"
    ],
    "name:swe_x_preferred":[
        "Yema"
    ],
    "name:zho_x_preferred":[
        "\u4e5f\u9ebb"
    ],
    "wof:name":"Yema",
    "wof:placetype":"locality"
},
  "geometry": {"coordinates":[108.17700000000001,26.2111],"type":"Point"}
}