{
  "type": "Feature",
  "properties": {
    "gn:admin1_code":"9",
    "gn:asciiname":"Wangchongming",
    "gn:country_code":"CN",
    "gn:dem":54,
    "gn:feature_class":"P",
    "gn:feature_code":"PPL",
    "gn:name":"Wangchongming",
    "gn:population":0,
    "gn:timezone":"Asia/Shanghai",
    "iso:country":"CN",
    "name:zho_x_preferred":[
        "\u738b\u5d07\u660e"
    ],
    "wof:name":"Wangchongming",
    "wof:placetype":"locality"
},
  "geometry": {"coordinates":[115.468,34.4486],"type":"Point"}
}