{
  "type": "Feature",
  "properties": {
    "gn:admin1_code":"8.0",
    "gn:asciiname":"Sujiatun",
    "gn:country_code":"CN",
    "gn:dem":180,
    "gn:feature_class":"P",
    "gn:feature_code":"PPL",
    "gn:name":"Sujiatun",
    "gn:population":0,
    "gn:timezone":"Asia/Shanghai",
    "iso:country":"CN",
    "name:zho_x_preferred":[
        "\u82cf\u5bb6\u5c6f"
    ],
    "wof:name":"Sujiatun",
    "wof:placetype":"locality"
},
  "geometry": {"coordinates":[127.24334,47.0953],"type":"Point"}
}