{
  "type": "Feature",
  "properties": {
    "gn:admin1_code":"8.0",
    "gn:asciiname":"Guchengdaocun",
    "gn:country_code":"CN",
    "gn:dem":254,
    "gn:feature_class":"P",
    "gn:feature_code":"PPL",
    "gn:name":"Guchengdaocun",
    "gn:population":0,
    "gn:timezone":"Asia/Shanghai",
    "iso:country":"CN",
    "name:zho_x_preferred":[
        "\u53e4\u57ce\u5c9b\u6751"
    ],
    "wof:name":"Guchengdaocun",
    "wof:placetype":"locality"
},
  "geometry": {"coordinates":[124.06567,53.389],"type":"Point"}
}