{
  "type": "Feature",
  "properties": {
    "gn:admin1_code":"16",
    "gn:asciiname":"Luzhu",
    "gn:country_code":"CN",
    "gn:dem":168,
    "gn:feature_class":"P",
    "gn:feature_code":"PPL",
    "gn:name":"L\u00fczhu",
    "gn:population":0,
    "gn:timezone":"Asia/Shanghai",
    "iso:country":"CN",
    "name:und_x_variant":[
        "L\u00fczhu"
    ],
    "name:zho_x_preferred":[
        "\u5415\u7af9"
    ],
    "wof:name":"Luzhu",
    "wof:placetype":"locality"
},
  "geometry": {"coordinates":[110.304,25.4464],"type":"Point"}
}