{
  "type": "Feature",
  "properties": {
    "gn:admin1_code":"15.0",
    "gn:asciiname":"Badacha",
    "gn:country_code":"CN",
    "gn:dem":2200,
    "gn:feature_class":"P",
    "gn:feature_code":"PPL",
    "gn:name":"Badacha",
    "gn:population":0,
    "gn:timezone":"Asia/Shanghai",
    "iso:country":"CN",
    "name:zho_x_preferred":[
        "\u516b\u8fbe\u5c94"
    ],
    "wof:name":"Badacha",
    "wof:placetype":"locality"
},
  "geometry": {"coordinates":[104.557,36.0384],"type":"Point"}
}