{
  "type": "Feature",
  "properties": {
    "gn:admin1_code":"30",
    "gn:asciiname":"Huangnitang",
    "gn:country_code":"CN",
    "gn:dem":464,
    "gn:feature_class":"P",
    "gn:feature_code":"PPL",
    "gn:name":"Huangnitang",
    "gn:population":0,
    "gn:timezone":"Asia/Shanghai",
    "iso:country":"CN",
    "name:zho_x_preferred":[
        "\u9ec4\u6ce5\u5858"
    ],
    "wof:name":"Huangnitang",
    "wof:placetype":"locality"
},
  "geometry": {"coordinates":[111.54368999999998,22.20315],"type":"Point"}
}