{
  "type": "Feature",
  "properties": {
    "gn:admin1_code":"11.0",
    "gn:asciiname":"Dingxinqiao",
    "gn:country_code":"CN",
    "gn:dem":266,
    "gn:feature_class":"P",
    "gn:feature_code":"PPL",
    "gn:name":"Dingxinqiao",
    "gn:population":0,
    "gn:timezone":"Asia/Shanghai",
    "iso:country":"CN",
    "name:zho_x_preferred":[
        "\u9f0e\u65b0\u6865"
    ],
    "wof:name":"Dingxinqiao",
    "wof:placetype":"locality"
},
  "geometry": {"coordinates":[111.42488,28.1381],"type":"Point"}
}