{
  "type": "Feature",
  "properties": {
    "gn:admin1_code":"14.0",
    "gn:asciiname":"Xiugeduo",
    "gn:country_code":"CN",
    "gn:dem":4278,
    "gn:feature_class":"P",
    "gn:feature_code":"PPL",
    "gn:name":"Xiugeduo",
    "gn:population":0,
    "gn:timezone":"Asia/Urumqi",
    "iso:country":"CN",
    "name:zho_x_preferred":[
        "\u4f11\u54e5\u8235"
    ],
    "wof:name":"Xiugeduo",
    "wof:placetype":"locality"
},
  "geometry": {"coordinates":[91.54172,30.32853],"type":"Point"}
}