{
  "type": "Feature",
  "properties": {
    "gn:admin1_code":"19.0",
    "gn:asciiname":"Sankuaishicun",
    "gn:country_code":"CN",
    "gn:dem":66,
    "gn:feature_class":"P",
    "gn:feature_code":"PPL",
    "gn:name":"Sankuaishicun",
    "gn:population":0,
    "gn:timezone":"Asia/Shanghai",
    "iso:country":"CN",
    "name:zho_x_preferred":[
        "\u4e09\u5757\u77f3\u6751"
    ],
    "wof:name":"Sankuaishicun",
    "wof:placetype":"locality"
},
  "geometry": {"coordinates":[122.46599999999999,42.1916],"type":"Point"}
}