{
  "type": "Feature",
  "properties": {
    "gn:admin1_code":"15.0",
    "gn:asciiname":"Jiajiadian",
    "gn:country_code":"CN",
    "gn:dem":1303,
    "gn:feature_class":"P",
    "gn:feature_code":"PPL",
    "gn:name":"Jiajiadian",
    "gn:population":0,
    "gn:timezone":"Asia/Shanghai",
    "iso:country":"CN",
    "name:und_x_variant":[
        "\u8d3e\u5bb6\u5e97"
    ],
    "wof:name":"Jiajiadian",
    "wof:placetype":"locality"
},
  "geometry": {"coordinates":[105.34754,33.44501],"type":"Point"}
}