{
  "type": "Feature",
  "properties": {
    "gn:admin1_code":"29.0",
    "gn:asciiname":"Shalamen",
    "gn:country_code":"CN",
    "gn:dem":1970,
    "gn:feature_class":"P",
    "gn:feature_code":"PPL",
    "gn:name":"Shalamen",
    "gn:population":0,
    "gn:timezone":"Asia/Shanghai",
    "iso:country":"CN",
    "name:zho_x_preferred":[
        "\u53a6\u62c9\u95e8"
    ],
    "wof:name":"Shalamen",
    "wof:placetype":"locality"
},
  "geometry": {"coordinates":[99.69370000000001,24.7659],"type":"Point"}
}