{
  "type": "Feature",
  "properties": {
    "gn:admin1_code":"20.0",
    "gn:asciiname":"Jinshang",
    "gn:country_code":"CN",
    "gn:dem":1794,
    "gn:feature_class":"P",
    "gn:feature_code":"PPL",
    "gn:name":"Jinshang",
    "gn:population":0,
    "gn:timezone":"Asia/Shanghai",
    "iso:country":"CN",
    "name:und_x_variant":[
        "\u4e95\u4e0a"
    ],
    "wof:name":"Jinshang",
    "wof:placetype":"locality"
},
  "geometry": {"coordinates":[112.78948,41.44728],"type":"Point"}
}