{
  "type": "Feature",
  "properties": {
    "gn:admin1_code":"3.0",
    "gn:asciiname":"Xuelingcun",
    "gn:country_code":"CN",
    "gn:dem":24,
    "gn:feature_class":"P",
    "gn:feature_code":"PPL",
    "gn:name":"Xuelingcun",
    "gn:population":0,
    "gn:timezone":"Asia/Shanghai",
    "iso:country":"CN",
    "name:und_x_variant":[
        "\u96ea\u5cad\u6751"
    ],
    "wof:name":"Xuelingcun",
    "wof:placetype":"locality"
},
  "geometry": {"coordinates":[116.62015,28.60284],"type":"Point"}
}