{
  "type": "Feature",
  "properties": {
    "gn:admin1_code":"24.0",
    "gn:asciiname":"Gudushang",
    "gn:country_code":"CN",
    "gn:dem":912,
    "gn:feature_class":"P",
    "gn:feature_code":"PPL",
    "gn:name":"Gudushang",
    "gn:population":0,
    "gn:timezone":"Asia/Shanghai",
    "iso:country":"CN",
    "name:zho_x_preferred":[
        "\u8c37\u90fd\u4e0a"
    ],
    "wof:name":"Gudushang",
    "wof:placetype":"locality"
},
  "geometry": {"coordinates":[113.18088,35.43322],"type":"Point"}
}