{
  "type": "Feature",
  "properties": {
    "gn:admin1_code":"8.0",
    "gn:asciiname":"Zhenjiang",
    "gn:country_code":"CN",
    "gn:dem":132,
    "gn:feature_class":"P",
    "gn:feature_code":"PPL",
    "gn:name":"Zhenjiang",
    "gn:population":0,
    "gn:timezone":"Asia/Shanghai",
    "iso:country":"CN",
    "name:afr_x_preferred":[
        "Zhenjiang"
    ],
    "name:ara_x_preferred":[
        "\u062a\u0634\u0646\u062c\u064a\u0627\u0646\u063a"
    ],
    "name:ast_x_preferred":[
        "Zhenjiang"
    ],
    "name:aze_x_preferred":[
        "\u00c7jentszyan"
    ],
    "name:bod_x_preferred":[
        "\u0f40\u0fb2\u0f7a\u0f53\u0f0b\u0f45\u0f44\u0f0b\u0f0d"
    ],
    "name:bul_x_preferred":[
        "\u0414\u0436\u044a\u043d\u0434\u0437\u044f\u043d"
    ],
    "name:cdo_x_preferred":[
        "D\u00e9ng-g\u014fng"
    ],
    "name:ceb_x_preferred":[
        "Zhenjiang"
    ],
    "name:ces_x_preferred":[
        "\u010cen-\u0165iang"
    ],
    "name:dan_x_preferred":[
        "Zhenjiang"
    ],
    "name:deu_x_preferred":[
        "Zhenjiang"
    ],
    "name:epo_x_preferred":[
        "\u0108\u0135encjan"
    ],
    "name:eus_x_preferred":[
        "Zhenjiang"
    ],
    "name:fas_x_preferred":[
        "\u062c\u0646\u062c\u06cc\u0627\u0646\u06af"
    ],
    "name:fin_x_preferred":[
        "Zhenjiang"
    ],
    "name:fra_x_preferred":[
        "Zhenjiang"
    ],
    "name:ind_x_preferred":[
        "Zhenjiang"
    ],
    "name:ita_x_preferred":[
        "Zhenjiang"
    ],
    "name:jpn_x_preferred":[
        "\u93ae\u6c5f\u5e02"
    ],
    "name:kik_x_preferred":[
        "Zhenjiang"
    ],
    "name:kor_x_preferred":[
        "\uc804\uc7a5\uc2dc"
    ],
    "name:mlg_x_preferred":[
        "Zhenjiang"
    ],
    "name:nld_x_preferred":[
        "Zhenjiang"
    ],
    "name:nno_x_preferred":[
        "Zhenjiang"
    ],
    "name:nor_x_preferred":[
        "Zhenjiang"
    ],
    "name:pol_x_preferred":[
        "Zhenjiang"
    ],
    "name:por_x_preferred":[
        "Zhenjiang"
    ],
    "name:rus_x_preferred":[
        "\u0427\u0436\u044d\u043d\u044c\u0446\u0437\u044f\u043d"
    ],
    "name:sco_x_preferred":[
        "Zhenjiang"
    ],
    "name:spa_x_preferred":[
        "Zhenjiang"
    ],
    "name:srp_x_preferred":[
        "\u040f\u0435\u043d\u0452\u0430\u043d\u0433"
    ],
    "name:swe_x_preferred":[
        "Zhenjiang"
    ],
    "name:tgl_x_preferred":[
        "Zhenjiang"
    ],
    "name:uig_x_preferred":[
        "\u062c\u0627\u06ad\u062c\u064a\u0627\u06ad \u0634\u06d5\u06be\u0649\u0631\u0649"
    ],
    "name:ukr_x_preferred":[
        "\u0427\u0436\u0435\u043d\u044c\u0446\u0437\u044f\u043d"
    ],
    "name:urd_x_preferred":[
        "\u0698\u06cc\u0646\u062c\u06cc\u0627\u0646\u06af"
    ],
    "name:vie_x_preferred":[
        "Tr\u1ea5n Giang"
    ],
    "name:war_x_preferred":[
        "Zhenjiang"
    ],
    "name:wuu_x_preferred":[
        "\u9547\u6c5f\u5e02"
    ],
    "name:zho_x_preferred":[
        "\u9547\u6c5f"
    ],
    "name:zho_x_variant":[
        "\u9547\u6c5f\u5e02"
    ],
    "wof:name":"Zhenjiang",
    "wof:placetype":"locality"
},
  "geometry": {"coordinates":[127.40228999999999,46.06328],"type":"Point"}
}