{
  "type": "Feature",
  "properties": {
    "gn:admin1_code":"30.0",
    "gn:asciiname":"Liuyuanshui",
    "gn:country_code":"CN",
    "gn:dem":129,
    "gn:feature_class":"P",
    "gn:feature_code":"PPL",
    "gn:name":"Liuyuanshui",
    "gn:population":0,
    "gn:timezone":"Asia/Shanghai",
    "iso:country":"CN",
    "name:zho_x_preferred":[
        "\u6d41\u6e90\u6c34"
    ],
    "wof:name":"Liuyuanshui",
    "wof:placetype":"locality"
},
  "geometry": {"coordinates":[114.15454,25.08256],"type":"Point"}
}