{
  "type": "Feature",
  "properties": {
    "gn:admin1_code":"9.0",
    "gn:asciiname":"Shishuao",
    "gn:country_code":"CN",
    "gn:dem":466,
    "gn:feature_class":"P",
    "gn:feature_code":"PPL",
    "gn:name":"Shishuao",
    "gn:population":0,
    "gn:timezone":"Asia/Shanghai",
    "iso:country":"CN",
    "name:und_x_variant":[
        "\u67ff\u6811\u51f9",
        "Shishuao"
    ],
    "wof:name":"Shishuao",
    "wof:placetype":"locality"
},
  "geometry": {"coordinates":[112.18795,33.53366],"type":"Point"}
}