{
  "type": "Feature",
  "properties": {
    "gn:admin1_code":"26.0",
    "gn:asciiname":"Wujiadian",
    "gn:country_code":"CN",
    "gn:dem":740,
    "gn:feature_class":"P",
    "gn:feature_code":"PPL",
    "gn:name":"Wujiadian",
    "gn:population":0,
    "gn:timezone":"Asia/Shanghai",
    "iso:country":"CN",
    "name:zho_x_preferred":[
        "\u90ac\u5bb6\u5e97"
    ],
    "wof:name":"Wujiadian",
    "wof:placetype":"locality"
},
  "geometry": {"coordinates":[110.59677000000001,33.3829],"type":"Point"}
}