{
  "type": "Feature",
  "properties": {
    "gn:admin1_code":"11",
    "gn:asciiname":"Hechi",
    "gn:country_code":"CN",
    "gn:dem":170,
    "gn:feature_class":"P",
    "gn:feature_code":"PPL",
    "gn:name":"Hechi",
    "gn:population":0,
    "gn:timezone":"Asia/Shanghai",
    "iso:country":"CN",
    "name:ara_x_preferred":[
        "\u0647\u064a\u0634\u064a"
    ],
    "name:aze_x_preferred":[
        "He\u00e7i"
    ],
    "name:cdo_x_preferred":[
        "\u00d2\u0324-di\u00e8"
    ],
    "name:ceb_x_preferred":[
        "Hechi Shi"
    ],
    "name:ces_x_preferred":[
        "Che-\u010dch\u2019"
    ],
    "name:dan_x_preferred":[
        "Hechi"
    ],
    "name:deu_x_preferred":[
        "Hechi"
    ],
    "name:eus_x_preferred":[
        "Hechi"
    ],
    "name:fas_x_preferred":[
        "\u0647\u06cc\u0686\u06cc"
    ],
    "name:fin_x_preferred":[
        "Hechi"
    ],
    "name:fra_x_preferred":[
        "Hechi"
    ],
    "name:hak_x_preferred":[
        "H\u00f2-chh\u1e73\u0300-s\u1e73"
    ],
    "name:ita_x_preferred":[
        "Hechi"
    ],
    "name:jpn_x_preferred":[
        "\u6cb3\u6c60\u5e02"
    ],
    "name:kik_x_preferred":[
        "Hechi"
    ],
    "name:kor_x_preferred":[
        "\ud5c8\uce20\uc2dc"
    ],
    "name:nld_x_preferred":[
        "Hechi"
    ],
    "name:nno_x_preferred":[
        "Hechi"
    ],
    "name:nor_x_preferred":[
        "Hechi"
    ],
    "name:pnb_x_preferred":[
        "\u06c1\u06cc\u0686\u06cc"
    ],
    "name:pol_x_preferred":[
        "Hechi"
    ],
    "name:por_x_preferred":[
        "Hechi"
    ],
    "name:rus_x_preferred":[
        "\u0425\u044d\u0447\u0438"
    ],
    "name:spa_x_preferred":[
        "Hechi"
    ],
    "name:swe_x_preferred":[
        "Hechi"
    ],
    "name:tur_x_preferred":[
        "Hechi"
    ],
    "name:ukr_x_preferred":[
        "\u0413\u0435\u0447\u0456"
    ],
    "name:urd_x_preferred":[
        "\u06c1\u06cc\u0686\u06cc"
    ],
    "name:vie_x_preferred":[
        "H\u00e0 Tr\u00ec"
    ],
    "name:war_x_preferred":[
        "Hechi"
    ],
    "name:zha_x_preferred":[
        "Hozciz"
    ],
    "name:zho_x_preferred":[
        "\u6cb3\u6c60\u5e02"
    ],
    "wof:name":"Hechi",
    "wof:placetype":"locality"
},
  "geometry": {"coordinates":[111.32832999999999,26.34056],"type":"Point"}
}