{
  "type": "Feature",
  "properties": {
    "gn:admin1_code":"32.0",
    "gn:asciiname":"Yangliuwan",
    "gn:country_code":"CN",
    "gn:dem":740,
    "gn:feature_class":"P",
    "gn:feature_code":"PPL",
    "gn:name":"Yangliuwan",
    "gn:population":0,
    "gn:timezone":"Asia/Shanghai",
    "iso:country":"CN",
    "name:zho_x_preferred":[
        "\u6768\u67f3\u6e7e"
    ],
    "wof:name":"Yangliuwan",
    "wof:placetype":"locality"
},
  "geometry": {"coordinates":[104.40494,29.60911],"type":"Point"}
}