{
  "type": "Feature",
  "properties": {
    "gn:admin1_code":"21.0",
    "gn:asciiname":"Zui'ershang",
    "gn:country_code":"CN",
    "gn:dem":1902,
    "gn:feature_class":"P",
    "gn:feature_code":"PPL",
    "gn:name":"Zui\u2019ershang",
    "gn:population":0,
    "gn:timezone":"Asia/Shanghai",
    "iso:country":"CN",
    "name:und_x_variant":[
        "Zui\u2019ershang"
    ],
    "name:zho_x_preferred":[
        "\u5480\u513f\u4e0a"
    ],
    "wof:name":"Zui'ershang",
    "wof:placetype":"locality"
},
  "geometry": {"coordinates":[106.374,35.7897],"type":"Point"}
}