{
  "type": "Feature",
  "properties": {
    "gn:admin1_code":"19.0",
    "gn:asciiname":"Yangguantuncun",
    "gn:country_code":"CN",
    "gn:dem":57,
    "gn:feature_class":"P",
    "gn:feature_code":"PPL",
    "gn:name":"Yangguantuncun",
    "gn:population":0,
    "gn:timezone":"Asia/Shanghai",
    "iso:country":"CN",
    "name:zho_x_preferred":[
        "\u6768\u5b98\u5c6f\u6751"
    ],
    "wof:name":"Yangguantuncun",
    "wof:placetype":"locality"
},
  "geometry": {"coordinates":[123.53100000000001,41.7686],"type":"Point"}
}