{
  "type": "Feature",
  "properties": {
    "gn:admin1_code":"11.0",
    "gn:asciiname":"Xiaotangchong",
    "gn:country_code":"CN",
    "gn:dem":92,
    "gn:feature_class":"P",
    "gn:feature_code":"PPL",
    "gn:name":"Xiaotangchong",
    "gn:population":0,
    "gn:timezone":"Asia/Shanghai",
    "iso:country":"CN",
    "name:zho_x_preferred":[
        "\u5c0f\u5858\u51b2"
    ],
    "wof:name":"Xiaotangchong",
    "wof:placetype":"locality"
},
  "geometry": {"coordinates":[112.76168,26.61193],"type":"Point"}
}