{
  "type": "Feature",
  "properties": {
    "gn:admin1_code":"14.0",
    "gn:asciiname":"Zhaxilincun",
    "gn:country_code":"CN",
    "gn:dem":3128,
    "gn:feature_class":"P",
    "gn:feature_code":"PPL",
    "gn:name":"Zhaxilincun",
    "gn:population":0,
    "gn:timezone":"Asia/Urumqi",
    "iso:country":"CN",
    "name:zho_x_preferred":[
        "\u624e\u897f\u6797\u6751"
    ],
    "wof:name":"Zhaxilincun",
    "wof:placetype":"locality"
},
  "geometry": {"coordinates":[92.92288000000001,29.0683],"type":"Point"}
}