{
  "type": "Feature",
  "properties": {
    "gn:admin1_code":"31",
    "gn:asciiname":"Xiaoling",
    "gn:country_code":"CN",
    "gn:dem":33,
    "gn:feature_class":"P",
    "gn:feature_code":"PPL",
    "gn:name":"Xiaoling",
    "gn:population":0,
    "gn:timezone":"Asia/Shanghai",
    "iso:country":"CN",
    "name:swe_x_preferred":[
        "Xiaoling"
    ],
    "name:und_x_variant":[
        "\u5c0f\u5cad"
    ],
    "wof:name":"Xiaoling",
    "wof:placetype":"locality"
},
  "geometry": {"coordinates":[108.697,19.0939],"type":"Point"}
}