{
  "type": "Feature",
  "properties": {
    "gn:admin1_code":"03",
    "gn:asciiname":"Guanshan",
    "gn:country_code":"CN",
    "gn:dem":83,
    "gn:feature_class":"P",
    "gn:feature_code":"PPLA4",
    "gn:name":"Guanshan",
    "gn:population":0,
    "gn:timezone":"Asia/Shanghai",
    "iso:country":"CN",
    "name:und_x_variant":[
        "Kuan-shan",
        "Guanshan",
        "\u51a0\u5c71",
        "Guanshan Xiang",
        "\u51a0\u5c71\u4e61"
    ],
    "wof:name":"Guanshan",
    "wof:placetype":"locality"
},
  "geometry": {"coordinates":[115.44618,27.09968],"type":"Point"}
}