{
  "type": "Feature",
  "properties": {
    "gn:admin1_code":"29.0",
    "gn:asciiname":"Laofubai",
    "gn:country_code":"CN",
    "gn:dem":1739,
    "gn:feature_class":"P",
    "gn:feature_code":"PPL",
    "gn:name":"Laofubai",
    "gn:population":0,
    "gn:timezone":"Asia/Shanghai",
    "iso:country":"CN",
    "name:zho_x_preferred":[
        "\u8001\u752b\u767d"
    ],
    "wof:name":"Laofubai",
    "wof:placetype":"locality"
},
  "geometry": {"coordinates":[103.506,23.3656],"type":"Point"}
}