{
  "type": "Feature",
  "properties": {
    "gn:admin1_code":"29.0",
    "gn:asciiname":"Tianweiba",
    "gn:country_code":"CN",
    "gn:dem":1629,
    "gn:feature_class":"P",
    "gn:feature_code":"PPL",
    "gn:name":"Tianweiba",
    "gn:population":0,
    "gn:timezone":"Asia/Shanghai",
    "iso:country":"CN",
    "name:zho_x_preferred":[
        "\u7530\u5c3e\u5df4"
    ],
    "wof:name":"Tianweiba",
    "wof:placetype":"locality"
},
  "geometry": {"coordinates":[103.673,23.3138],"type":"Point"}
}