{
  "type": "Feature",
  "properties": {
    "gn:admin1_code":"07",
    "gn:asciiname":"Annei",
    "gn:country_code":"CN",
    "gn:dem":33,
    "gn:feature_class":"P",
    "gn:feature_code":"PPL",
    "gn:name":"Annei",
    "gn:population":0,
    "gn:timezone":"Asia/Shanghai",
    "iso:country":"CN",
    "name:zho_x_preferred":[
        "\u57b5\u5185"
    ],
    "wof:name":"Annei",
    "wof:placetype":"locality"
},
  "geometry": {"coordinates":[118.47929999999999,25.02795],"type":"Point"}
}