{
  "type": "Feature",
  "properties": {
    "gn:admin1_code":"7.0",
    "gn:asciiname":"Guadun Shan",
    "gn:country_code":"CN",
    "gn:dem":1747,
    "gn:feature_class":"P",
    "gn:feature_code":"PPL",
    "gn:name":"Guadun Shan",
    "gn:population":0,
    "gn:timezone":"Asia/Shanghai",
    "iso:country":"CN",
    "name:zho_x_preferred":[
        "\u6302\u58a9\u5c71"
    ],
    "wof:name":"Guadun Shan",
    "wof:placetype":"locality"
},
  "geometry": {"coordinates":[117.64373000000001,27.74552000000001],"type":"Point"}
}