{
  "type": "Feature",
  "properties": {
    "gn:admin1_code":"29.0",
    "gn:asciiname":"Shigaoqing",
    "gn:country_code":"CN",
    "gn:dem":1204,
    "gn:feature_class":"P",
    "gn:feature_code":"PPL",
    "gn:name":"Shigaoqing",
    "gn:population":0,
    "gn:timezone":"Asia/Shanghai",
    "iso:country":"CN",
    "name:zho_x_preferred":[
        "\u77f3\u818f\u7b90"
    ],
    "wof:name":"Shigaoqing",
    "wof:placetype":"locality"
},
  "geometry": {"coordinates":[100.625,23.1644],"type":"Point"}
}