{
  "type": "Feature",
  "properties": {
    "gn:admin1_code":"3.0",
    "gn:asciiname":"Kuchexia",
    "gn:country_code":"CN",
    "gn:dem":218,
    "gn:feature_class":"P",
    "gn:feature_code":"PPL",
    "gn:name":"Kuchexia",
    "gn:population":0,
    "gn:timezone":"Asia/Shanghai",
    "iso:country":"CN",
    "name:und_x_variant":[
        "\u5e93\u8f66\u4e0b"
    ],
    "wof:name":"Kuchexia",
    "wof:placetype":"locality"
},
  "geometry": {"coordinates":[116.294,26.1395],"type":"Point"}
}