{
  "type": "Feature",
  "properties": {
    "gn:admin1_code":"05",
    "gn:asciiname":"Huangbai",
    "gn:country_code":"CN",
    "gn:dem":203,
    "gn:feature_class":"P",
    "gn:feature_code":"PPLA4",
    "gn:name":"Huangbai",
    "gn:population":0,
    "gn:timezone":"Asia/Shanghai",
    "iso:country":"CN",
    "name:und_x_variant":[
        "Huang-pai",
        "Huangbai",
        "\u9ec4\u67cf",
        "Qingshi Zhen",
        "\u9752\u77f3\u9547"
    ],
    "wof:name":"Huangbai",
    "wof:placetype":"locality"
},
  "geometry": {"coordinates":[126.35123,41.26929000000001],"type":"Point"}
}