{
  "type": "Feature",
  "properties": {
    "gn:admin1_code":"12.0",
    "gn:asciiname":"Pengxing",
    "gn:country_code":"CN",
    "gn:dem":35,
    "gn:feature_class":"P",
    "gn:feature_code":"PPLA4",
    "gn:name":"Pengxing",
    "gn:population":0,
    "gn:timezone":"Asia/Shanghai",
    "iso:country":"CN",
    "name:und_x_variant":[
        "Pengxing Xiang"
    ],
    "name:zho_x_preferred":[
        "\u670b\u5174"
    ],
    "name:zho_x_variant":[
        "\u670b\u5174\u4e61"
    ],
    "wof:name":"Pengxing",
    "wof:placetype":"locality"
},
  "geometry": {"coordinates":[113.91226,30.96575],"type":"Point"}
}