{
  "type": "Feature",
  "properties": {
    "gn:admin1_code":"15.0",
    "gn:asciiname":"Amasi Xiwan",
    "gn:country_code":"CN",
    "gn:dem":2159,
    "gn:feature_class":"P",
    "gn:feature_code":"PPL",
    "gn:name":"Amasi Xiwan",
    "gn:population":0,
    "gn:timezone":"Asia/Shanghai",
    "iso:country":"CN",
    "name:zho_x_preferred":[
        "\u963f\u9ebb\u5bfa\u897f\u6e7e"
    ],
    "wof:name":"Amasi Xiwan",
    "wof:placetype":"locality"
},
  "geometry": {"coordinates":[103.733,35.4554],"type":"Point"}
}