{
  "type": "Feature",
  "properties": {
    "gn:admin1_code":"16",
    "gn:asciiname":"Daguangtang",
    "gn:country_code":"CN",
    "gn:dem":211,
    "gn:feature_class":"P",
    "gn:feature_code":"PPL",
    "gn:name":"Daguangtang",
    "gn:population":0,
    "gn:timezone":"Asia/Shanghai",
    "iso:country":"CN",
    "name:zho_x_preferred":[
        "\u5927\u5e7f\u5858"
    ],
    "wof:name":"Daguangtang",
    "wof:placetype":"locality"
},
  "geometry": {"coordinates":[110.913,25.7211],"type":"Point"}
}