{
  "type": "Feature",
  "properties": {
    "gn:admin1_code":"22.0",
    "gn:asciiname":"Fangjia",
    "gn:country_code":"CN",
    "gn:dem":35,
    "gn:feature_class":"P",
    "gn:feature_code":"PPL",
    "gn:name":"Fangjia",
    "gn:population":0,
    "gn:timezone":"Asia/Shanghai",
    "iso:country":"CN",
    "name:zho_x_preferred":[
        "\u65b9\u5bb6"
    ],
    "wof:name":"Fangjia",
    "wof:placetype":"locality"
},
  "geometry": {"coordinates":[116.51640999999999,39.8977],"type":"Point"}
}