{
  "type": "Feature",
  "properties": {
    "gn:admin1_code":"26.0",
    "gn:asciiname":"Qianmiaoshancun",
    "gn:country_code":"CN",
    "gn:dem":784,
    "gn:feature_class":"P",
    "gn:feature_code":"PPL",
    "gn:name":"Qianmiaoshancun",
    "gn:population":0,
    "gn:timezone":"Asia/Shanghai",
    "iso:country":"CN",
    "name:zho_x_preferred":[
        "\u524d\u5e99\u5c71\u6751"
    ],
    "wof:name":"Qianmiaoshancun",
    "wof:placetype":"locality"
},
  "geometry": {"coordinates":[110.69002999999999,37.45795],"type":"Point"}
}