{
  "type": "Feature",
  "properties": {
    "gn:admin1_code":"16.0",
    "gn:asciiname":"Hezuo",
    "gn:country_code":"CN",
    "gn:dem":235,
    "gn:feature_class":"P",
    "gn:feature_code":"PPL",
    "gn:name":"Hezuo",
    "gn:population":0,
    "gn:timezone":"Asia/Shanghai",
    "iso:country":"CN",
    "name:ara_x_preferred":[
        "\u0647\u064a\u0632\u0648"
    ],
    "name:bod_x_preferred":[
        "\u0f42\u0f59\u0f7c\u0f66\u0f0b\u0f42\u0fb2\u0f7c\u0f44\u0f0b\u0f41\u0fb1\u0f72\u0f62\u0f0d"
    ],
    "name:deu_x_preferred":[
        "Hezuo"
    ],
    "name:fin_x_preferred":[
        "Hezuo"
    ],
    "name:fra_x_preferred":[
        "Hezuo"
    ],
    "name:ita_x_preferred":[
        "Hezuo"
    ],
    "name:jpn_x_preferred":[
        "\u5408\u4f5c\u5e02"
    ],
    "name:kik_x_preferred":[
        "Hezuo"
    ],
    "name:kor_x_preferred":[
        "\ud5c8\ucb64\uc2dc"
    ],
    "name:mlg_x_preferred":[
        "Hezuo"
    ],
    "name:mwl_x_preferred":[
        "Hezuo"
    ],
    "name:nor_x_preferred":[
        "Hezuo"
    ],
    "name:pam_x_preferred":[
        "Hezuo"
    ],
    "name:pnb_x_preferred":[
        "\u06c1\u06cc\u0632\u0648\u0624"
    ],
    "name:rus_x_preferred":[
        "\u0425\u044d\u0446\u0437\u043e"
    ],
    "name:spa_x_preferred":[
        "H\u00e9zu\u00f2 Sh\u00ec"
    ],
    "name:swe_x_preferred":[
        "Hezuo"
    ],
    "name:urd_x_preferred":[
        "\u06c1\u06cc\u0632\u0648\u0648"
    ],
    "name:vie_x_preferred":[
        "H\u1ee3p T\u00e1c"
    ],
    "name:zho_x_preferred":[
        "\u5408\u4f5c"
    ],
    "name:zho_x_variant":[
        "\u5408\u4f5c\u5e02"
    ],
    "wof:name":"Hezuo",
    "wof:placetype":"locality"
},
  "geometry": {"coordinates":[108.261,24.9747],"type":"Point"}
}