{
  "type": "Feature",
  "properties": {
    "gn:admin1_code":"26.0",
    "gn:asciiname":"Yuanze Pingcun",
    "gn:country_code":"CN",
    "gn:dem":974,
    "gn:feature_class":"P",
    "gn:feature_code":"PPL",
    "gn:name":"Yuanze Pingcun",
    "gn:population":0,
    "gn:timezone":"Asia/Shanghai",
    "iso:country":"CN",
    "name:zho_x_preferred":[
        "\u56ed\u5219\u576a\u6751"
    ],
    "wof:name":"Yuanze Pingcun",
    "wof:placetype":"locality"
},
  "geometry": {"coordinates":[109.926,37.5098],"type":"Point"}
}