{
  "type": "Feature",
  "properties": {
    "gn:admin1_code":"16.0",
    "gn:asciiname":"Shengwang",
    "gn:country_code":"CN",
    "gn:dem":553,
    "gn:feature_class":"P",
    "gn:feature_code":"PPL",
    "gn:name":"Shengwang",
    "gn:population":0,
    "gn:timezone":"Asia/Shanghai",
    "iso:country":"CN",
    "name:zho_x_preferred":[
        "\u5347\u5f80"
    ],
    "wof:name":"Shengwang",
    "wof:placetype":"locality"
},
  "geometry": {"coordinates":[107.779,23.7538],"type":"Point"}
}