{
  "type": "Feature",
  "properties": {
    "gn:admin1_code":"26.0",
    "gn:asciiname":"Jiuyuan Goucun",
    "gn:country_code":"CN",
    "gn:dem":880,
    "gn:feature_class":"P",
    "gn:feature_code":"PPL",
    "gn:name":"Jiuyuan Goucun",
    "gn:population":0,
    "gn:timezone":"Asia/Shanghai",
    "iso:country":"CN",
    "name:zho_x_preferred":[
        "\u97ed\u56ed\u6c9f\u6751"
    ],
    "wof:name":"Jiuyuan Goucun",
    "wof:placetype":"locality"
},
  "geometry": {"coordinates":[110.279,37.558],"type":"Point"}
}