{
  "type": "Feature",
  "properties": {
    "gn:admin1_code":"26",
    "gn:asciiname":"Shuangru",
    "gn:cc2":"CN",
    "gn:country_code":"CN",
    "gn:dem":303,
    "gn:feature_class":"P",
    "gn:feature_code":"PPL",
    "gn:name":"Shuangru",
    "gn:population":0,
    "gn:timezone":"Asia/Shanghai",
    "iso:country":"CN",
    "name:und_x_variant":[
        "Shuang-ju",
        "Shuang-ju-p\u2019u",
        "Shuangru"
    ],
    "wof:name":"Shuangru",
    "wof:placetype":"locality"
},
  "geometry": {"coordinates":[108.66667,32.78333],"type":"Point"}
}