{
  "type": "Feature",
  "properties": {
    "gn:admin1_code":"2.0",
    "gn:asciiname":"Suanzhangling",
    "gn:country_code":"CN",
    "gn:dem":19,
    "gn:feature_class":"P",
    "gn:feature_code":"PPL",
    "gn:name":"Suanzhangling",
    "gn:population":0,
    "gn:timezone":"Asia/Shanghai",
    "iso:country":"CN",
    "name:und_x_variant":[
        "\u7b97\u5e10\u5cad"
    ],
    "name:zho_x_preferred":[
        "Suanzhangling"
    ],
    "wof:name":"Suanzhangling",
    "wof:placetype":"locality"
},
  "geometry": {"coordinates":[120.03691999999999,30.08834],"type":"Point"}
}