{
  "type": "Feature",
  "properties": {
    "gn:admin1_code":"7",
    "gn:asciiname":"Yunshan",
    "gn:country_code":"CN",
    "gn:dem":142,
    "gn:feature_class":"P",
    "gn:feature_code":"PPL",
    "gn:name":"Yunshan",
    "gn:population":0,
    "gn:timezone":"Asia/Shanghai",
    "iso:country":"CN",
    "name:zho_x_preferred":[
        "\u82b8\u5c71"
    ],
    "wof:name":"Yunshan",
    "wof:placetype":"locality"
},
  "geometry": {"coordinates":[117.82841000000001,24.53356],"type":"Point"}
}