{
  "type": "Feature",
  "properties": {
    "gn:admin1_code":"14.0",
    "gn:asciiname":"Xueduicun",
    "gn:country_code":"CN",
    "gn:dem":3864,
    "gn:feature_class":"P",
    "gn:feature_code":"PPL",
    "gn:name":"Xueduicun",
    "gn:population":0,
    "gn:timezone":"Asia/Urumqi",
    "iso:country":"CN",
    "name:zho_x_preferred":[
        "\u5b66\u5806\u6751"
    ],
    "wof:name":"Xueduicun",
    "wof:placetype":"locality"
},
  "geometry": {"coordinates":[97.05067,31.49307],"type":"Point"}
}