{
  "type": "Feature",
  "properties": {
    "gn:admin1_code":"29.0",
    "gn:asciiname":"Jiamashi",
    "gn:country_code":"CN",
    "gn:dem":1414,
    "gn:feature_class":"P",
    "gn:feature_code":"PPL",
    "gn:name":"Jiamashi",
    "gn:population":0,
    "gn:timezone":"Asia/Shanghai",
    "iso:country":"CN",
    "name:zho_x_preferred":[
        "\u5939\u9a6c\u77f3"
    ],
    "wof:name":"Jiamashi",
    "wof:placetype":"locality"
},
  "geometry": {"coordinates":[104.026,23.0888],"type":"Point"}
}