{
  "type": "Feature",
  "properties": {
    "gn:admin1_code":"18",
    "gn:asciiname":"Goujiabei",
    "gn:country_code":"CN",
    "gn:dem":693,
    "gn:feature_class":"P",
    "gn:feature_code":"PPL",
    "gn:name":"Goujiabei",
    "gn:population":0,
    "gn:timezone":"Asia/Shanghai",
    "iso:country":"CN",
    "name:zho_x_preferred":[
        "\u82df\u5bb6\u80cc"
    ],
    "wof:name":"Goujiabei",
    "wof:placetype":"locality"
},
  "geometry": {"coordinates":[106.614,27.9723],"type":"Point"}
}