{
  "type": "Feature",
  "properties": {
    "gn:admin1_code":"2.0",
    "gn:asciiname":"Shangwushan",
    "gn:country_code":"CN",
    "gn:dem":520,
    "gn:feature_class":"P",
    "gn:feature_code":"PPL",
    "gn:name":"Shangwushan",
    "gn:population":0,
    "gn:timezone":"Asia/Shanghai",
    "iso:country":"CN",
    "name:zho_x_preferred":[
        "\u4e0a\u5434\u5c71"
    ],
    "wof:name":"Shangwushan",
    "wof:placetype":"locality"
},
  "geometry": {"coordinates":[119.96046,28.519],"type":"Point"}
}