{
  "type": "Feature",
  "properties": {
    "gn:admin1_code":"16.0",
    "gn:asciiname":"Aipo",
    "gn:country_code":"CN",
    "gn:dem":296,
    "gn:feature_class":"P",
    "gn:feature_code":"PPL",
    "gn:name":"Aipo",
    "gn:population":0,
    "gn:timezone":"Asia/Shanghai",
    "iso:country":"CN",
    "name:zho_x_preferred":[
        "\u7231\u5761"
    ],
    "wof:name":"Aipo",
    "wof:placetype":"locality"
},
  "geometry": {"coordinates":[107.404,24.0162],"type":"Point"}
}