{
  "type": "Feature",
  "properties": {
    "gn:admin1_code":"9.0",
    "gn:asciiname":"Xiongzhuang",
    "gn:country_code":"CN",
    "gn:dem":105,
    "gn:feature_class":"P",
    "gn:feature_code":"PPL",
    "gn:name":"Xiongzhuang",
    "gn:population":0,
    "gn:timezone":"Asia/Shanghai",
    "iso:country":"CN",
    "name:zho_x_preferred":[
        "\u718a\u5e84"
    ],
    "wof:name":"Xiongzhuang",
    "wof:placetype":"locality"
},
  "geometry": {"coordinates":[114.06057,32.54744],"type":"Point"}
}