{
  "type": "Feature",
  "properties": {
    "gn:admin1_code":"7.0",
    "gn:asciiname":"Jundun",
    "gn:country_code":"CN",
    "gn:dem":435,
    "gn:feature_class":"P",
    "gn:feature_code":"PPL",
    "gn:name":"Jundun",
    "gn:population":0,
    "gn:timezone":"Asia/Shanghai",
    "iso:country":"CN",
    "name:zho_x_preferred":[
        "\u5747\u58a9"
    ],
    "wof:name":"Jundun",
    "wof:placetype":"locality"
},
  "geometry": {"coordinates":[118.3295,27.5633],"type":"Point"}
}