{
  "type": "Feature",
  "properties": {
    "gn:admin1_code":"14",
    "gn:asciiname":"Jiana",
    "gn:country_code":"CN",
    "gn:dem":3945,
    "gn:feature_class":"P",
    "gn:feature_code":"PPL",
    "gn:name":"Jiana",
    "gn:population":0,
    "gn:timezone":"Asia/Urumqi",
    "iso:country":"CN",
    "name:zho_x_preferred":[
        "\u52a0\u90a3"
    ],
    "wof:name":"Jiana",
    "wof:placetype":"locality"
},
  "geometry": {"coordinates":[89.4662,29.0506],"type":"Point"}
}