{
  "type": "Feature",
  "properties": {
    "gn:admin1_code":"1.0",
    "gn:asciiname":"Wanglaojiacun",
    "gn:country_code":"CN",
    "gn:dem":33,
    "gn:feature_class":"P",
    "gn:feature_code":"PPL",
    "gn:name":"Wanglaojiacun",
    "gn:population":0,
    "gn:timezone":"Asia/Shanghai",
    "iso:country":"CN",
    "name:zho_x_preferred":[
        "\u738b\u8001\u5bb6\u6751"
    ],
    "wof:name":"Wanglaojiacun",
    "wof:placetype":"locality"
},
  "geometry": {"coordinates":[116.38988999999999,33.50989000000001],"type":"Point"}
}