{
  "type": "Feature",
  "properties": {
    "gn:admin1_code":"32.0",
    "gn:asciiname":"Tangyoufang",
    "gn:country_code":"CN",
    "gn:dem":498,
    "gn:feature_class":"P",
    "gn:feature_code":"PPL",
    "gn:name":"Tangyoufang",
    "gn:population":0,
    "gn:timezone":"Asia/Shanghai",
    "iso:country":"CN",
    "name:zho_x_preferred":[
        "\u6c64\u6cb9\u623f"
    ],
    "wof:name":"Tangyoufang",
    "wof:placetype":"locality"
},
  "geometry": {"coordinates":[103.485,30.3986],"type":"Point"}
}