{
  "type": "Feature",
  "properties": {
    "gn:admin1_code":"15.0",
    "gn:asciiname":"Anmuquhu'ang",
    "gn:country_code":"CN",
    "gn:dem":3105,
    "gn:feature_class":"P",
    "gn:feature_code":"PPL",
    "gn:name":"Anmuquhu\u2019ang",
    "gn:population":0,
    "gn:timezone":"Asia/Shanghai",
    "iso:country":"CN",
    "name:und_x_variant":[
        "Anmuquhu\u2019ang"
    ],
    "name:zho_x_preferred":[
        "\u963f\u6728\u53bb\u4e4e\u6602"
    ],
    "wof:name":"Anmuquhu'ang",
    "wof:placetype":"locality"
},
  "geometry": {"coordinates":[102.639,34.7838],"type":"Point"}
}