{
  "type": "Feature",
  "properties": {
    "gn:admin1_code":"02",
    "gn:asciiname":"Dujiacun",
    "gn:country_code":"CN",
    "gn:dem":36,
    "gn:feature_class":"P",
    "gn:feature_code":"PPL",
    "gn:name":"Dujiacun",
    "gn:population":0,
    "gn:timezone":"Asia/Shanghai",
    "iso:country":"CN",
    "name:und_x_variant":[
        "Tu-chia",
        "Dujia",
        "Dujiacun"
    ],
    "name:zho_x_preferred":[
        "\u675c\u5bb6"
    ],
    "name:zho_x_variant":[
        "\u675c\u5bb6\u6751"
    ],
    "wof:name":"Dujiacun",
    "wof:placetype":"locality"
},
  "geometry": {"coordinates":[121.41417,29.58778],"type":"Point"}
}