{
  "type": "Feature",
  "properties": {
    "gn:admin1_code":"25",
    "gn:asciiname":"Qianxingzhuang",
    "gn:country_code":"CN",
    "gn:dem":165,
    "gn:feature_class":"P",
    "gn:feature_code":"PPL",
    "gn:name":"Qianxingzhuang",
    "gn:population":0,
    "gn:timezone":"Asia/Shanghai",
    "iso:country":"CN",
    "name:zho_x_preferred":[
        "\u5343\u884c\u5e84"
    ],
    "wof:name":"Qianxingzhuang",
    "wof:placetype":"locality"
},
  "geometry": {"coordinates":[117.80800000000001,35.3307],"type":"Point"}
}