{
  "type": "Feature",
  "properties": {
    "gn:admin1_code":"12.0",
    "gn:asciiname":"Laozhangwan",
    "gn:country_code":"CN",
    "gn:dem":131,
    "gn:feature_class":"P",
    "gn:feature_code":"PPL",
    "gn:name":"Laozhangwan",
    "gn:population":0,
    "gn:timezone":"Asia/Shanghai",
    "iso:country":"CN",
    "name:und_x_variant":[
        "\u8001\u5f20\u5846"
    ],
    "wof:name":"Laozhangwan",
    "wof:placetype":"locality"
},
  "geometry": {"coordinates":[115.47705999999999,30.38949],"type":"Point"}
}