{
  "type": "Feature",
  "properties": {
    "gn:admin1_code":"26.0",
    "gn:asciiname":"Tangjialin",
    "gn:country_code":"CN",
    "gn:dem":1144,
    "gn:feature_class":"P",
    "gn:feature_code":"PPL",
    "gn:name":"Tangjialin",
    "gn:population":0,
    "gn:timezone":"Asia/Shanghai",
    "iso:country":"CN",
    "name:und_x_variant":[
        "\u5510\u5bb6\u6797"
    ],
    "wof:name":"Tangjialin",
    "wof:placetype":"locality"
},
  "geometry": {"coordinates":[106.39669000000001,33.1488],"type":"Point"}
}