{
  "type": "Feature",
  "properties": {
    "gn:admin1_code":"8.0",
    "gn:asciiname":"Qingniancun",
    "gn:country_code":"CN",
    "gn:dem":121,
    "gn:feature_class":"P",
    "gn:feature_code":"PPL",
    "gn:name":"Qingniancun",
    "gn:population":0,
    "gn:timezone":"Asia/Shanghai",
    "iso:country":"CN",
    "name:zho_x_preferred":[
        "\u9752\u5e74\u6751"
    ],
    "wof:name":"Qingniancun",
    "wof:placetype":"locality"
},
  "geometry": {"coordinates":[126.34876,46.01586],"type":"Point"}
}