{
  "type": "Feature",
  "properties": {
    "gn:admin1_code":"16",
    "gn:asciiname":"Nanmenwan",
    "gn:country_code":"CN",
    "gn:dem":699,
    "gn:feature_class":"P",
    "gn:feature_code":"PPL",
    "gn:name":"Nanmenwan",
    "gn:population":0,
    "gn:timezone":"Asia/Shanghai",
    "iso:country":"CN",
    "name:zho_x_preferred":[
        "\u5357\u95e8\u6e7e"
    ],
    "wof:name":"Nanmenwan",
    "wof:placetype":"locality"
},
  "geometry": {"coordinates":[110.65300000000001,24.9864],"type":"Point"}
}