{
  "type": "Feature",
  "properties": {
    "gn:admin1_code":"02",
    "gn:asciiname":"Jinqingzhen",
    "gn:country_code":"CN",
    "gn:dem":8,
    "gn:feature_class":"P",
    "gn:feature_code":"PPL",
    "gn:name":"Jinqingzhen",
    "gn:population":0,
    "gn:timezone":"Asia/Shanghai",
    "iso:country":"CN",
    "name:und_x_variant":[
        "Jinqing",
        "Jinqingzhen"
    ],
    "name:zho_x_preferred":[
        "Chin-ch\u2019ing"
    ],
    "wof:name":"Jinqingzhen",
    "wof:placetype":"locality"
},
  "geometry": {"coordinates":[121.52097000000001,28.50533],"type":"Point"}
}