{
  "type": "Feature",
  "properties": {
    "gn:admin1_code":"26.0",
    "gn:asciiname":"Jiangyang Zhuangcun",
    "gn:country_code":"CN",
    "gn:dem":1712,
    "gn:feature_class":"P",
    "gn:feature_code":"PPL",
    "gn:name":"Jiangyang Zhuangcun",
    "gn:population":0,
    "gn:timezone":"Asia/Shanghai",
    "iso:country":"CN",
    "name:zho_x_preferred":[
        "\u848b\u9633\u5e84\u6751"
    ],
    "wof:name":"Jiangyang Zhuangcun",
    "wof:placetype":"locality"
},
  "geometry": {"coordinates":[107.489,37.1885],"type":"Point"}
}