{
  "type": "Feature",
  "properties": {
    "gn:admin1_code":"3.0",
    "gn:asciiname":"Zheqiao",
    "gn:country_code":"CN",
    "gn:dem":26,
    "gn:feature_class":"P",
    "gn:feature_code":"PPL",
    "gn:name":"Zheqiao",
    "gn:population":0,
    "gn:timezone":"Asia/Shanghai",
    "iso:country":"CN",
    "name:und_x_variant":[
        "\u54f2\u6865"
    ],
    "wof:name":"Zheqiao",
    "wof:placetype":"locality"
},
  "geometry": {"coordinates":[116.26051,29.32905],"type":"Point"}
}