{
  "type": "Feature",
  "properties": {
    "gn:admin1_code":"11.0",
    "gn:asciiname":"Xin'ao",
    "gn:country_code":"CN",
    "gn:dem":331,
    "gn:feature_class":"P",
    "gn:feature_code":"PPL",
    "gn:name":"Xin\u2019ao",
    "gn:population":0,
    "gn:timezone":"Asia/Shanghai",
    "iso:country":"CN",
    "name:und_x_variant":[
        "Xin\u2019ao"
    ],
    "name:zho_x_preferred":[
        "\u65b0\u5773"
    ],
    "wof:name":"Xin'ao",
    "wof:placetype":"locality"
},
  "geometry": {"coordinates":[113.59775,25.71955],"type":"Point"}
}