{
  "type": "Feature",
  "properties": {
    "gn:admin1_code":"29.0",
    "gn:asciiname":"Daxibai",
    "gn:country_code":"CN",
    "gn:dem":1641,
    "gn:feature_class":"P",
    "gn:feature_code":"PPL",
    "gn:name":"Daxibai",
    "gn:population":0,
    "gn:timezone":"Asia/Shanghai",
    "iso:country":"CN",
    "name:zho_x_preferred":[
        "\u5927\u7ec6\u767d"
    ],
    "wof:name":"Daxibai",
    "wof:placetype":"locality"
},
  "geometry": {"coordinates":[104.568,25.0825],"type":"Point"}
}