{
  "type": "Feature",
  "properties": {
    "gn:admin1_code":"32.0",
    "gn:asciiname":"Sinan Dacun",
    "gn:country_code":"CN",
    "gn:dem":2205,
    "gn:feature_class":"P",
    "gn:feature_code":"PPL",
    "gn:name":"Sinan Dacun",
    "gn:population":0,
    "gn:timezone":"Asia/Shanghai",
    "iso:country":"CN",
    "name:zho_x_preferred":[
        "\u56db\u5357\u5927\u6751"
    ],
    "wof:name":"Sinan Dacun",
    "wof:placetype":"locality"
},
  "geometry": {"coordinates":[103.051,31.4012],"type":"Point"}
}