{
  "type": "Feature",
  "properties": {
    "gn:admin1_code":"11",
    "gn:asciiname":"Dongmaoshan",
    "gn:country_code":"CN",
    "gn:dem":263,
    "gn:feature_class":"P",
    "gn:feature_code":"PPL",
    "gn:name":"Dongmaoshan",
    "gn:population":0,
    "gn:timezone":"Asia/Shanghai",
    "iso:country":"CN",
    "name:zho_x_preferred":[
        "\u4e1c\u6bdb\u5c71"
    ],
    "wof:name":"Dongmaoshan",
    "wof:placetype":"locality"
},
  "geometry": {"coordinates":[112.11351000000001,25.52806],"type":"Point"}
}