{
  "type": "Feature",
  "properties": {
    "gn:admin1_code":"12.0",
    "gn:asciiname":"Yixin",
    "gn:country_code":"CN",
    "gn:dem":1178,
    "gn:feature_class":"P",
    "gn:feature_code":"PPL",
    "gn:name":"Yixin",
    "gn:population":0,
    "gn:timezone":"Asia/Shanghai",
    "iso:country":"CN",
    "name:zho_x_preferred":[
        "\u4e00\u5fc3"
    ],
    "wof:name":"Yixin",
    "wof:placetype":"locality"
},
  "geometry": {"coordinates":[108.85651,30.44943],"type":"Point"}
}