{
  "type": "Feature",
  "properties": {
    "gn:admin1_code":"2.0",
    "gn:asciiname":"Xianyangxie",
    "gn:country_code":"CN",
    "gn:dem":9,
    "gn:feature_class":"P",
    "gn:feature_code":"PPL",
    "gn:name":"Xianyangxie",
    "gn:population":0,
    "gn:timezone":"Asia/Shanghai",
    "iso:country":"CN",
    "name:und_x_variant":[
        "\u4ed9\u579f\u8c22"
    ],
    "wof:name":"Xianyangxie",
    "wof:placetype":"locality"
},
  "geometry": {"coordinates":[120.36964,30.41559],"type":"Point"}
}