{
  "type": "Feature",
  "properties": {
    "gn:admin1_code":"5.0",
    "gn:asciiname":"Damaoshan",
    "gn:country_code":"CN",
    "gn:dem":289,
    "gn:feature_class":"P",
    "gn:feature_code":"PPL",
    "gn:name":"Damaoshan",
    "gn:population":0,
    "gn:timezone":"Asia/Shanghai",
    "iso:country":"CN",
    "name:zho_x_preferred":[
        "\u5927\u5e3d\u5c71"
    ],
    "wof:name":"Damaoshan",
    "wof:placetype":"locality"
},
  "geometry": {"coordinates":[125.88539,43.20327],"type":"Point"}
}