{
  "type": "Feature",
  "properties": {
    "gn:admin1_code":"26.0",
    "gn:asciiname":"Jiaoliucun",
    "gn:country_code":"CN",
    "gn:dem":663,
    "gn:feature_class":"P",
    "gn:feature_code":"PPL",
    "gn:name":"Jiaoliucun",
    "gn:population":0,
    "gn:timezone":"Asia/Shanghai",
    "iso:country":"CN",
    "name:zho_x_preferred":[
        "\u7126\u516d\u6751"
    ],
    "wof:name":"Jiaoliucun",
    "wof:placetype":"locality"
},
  "geometry": {"coordinates":[107.82299999999999,34.4497],"type":"Point"}
}