{
  "type": "Feature",
  "properties": {
    "gn:admin1_code":"24.0",
    "gn:asciiname":"Xicansi",
    "gn:country_code":"CN",
    "gn:dem":1549,
    "gn:feature_class":"P",
    "gn:feature_code":"PPL",
    "gn:name":"Xicansi",
    "gn:population":0,
    "gn:timezone":"Asia/Shanghai",
    "iso:country":"CN",
    "name:zho_x_preferred":[
        "\u897f\u8695\u5bfa"
    ],
    "wof:name":"Xicansi",
    "wof:placetype":"locality"
},
  "geometry": {"coordinates":[112.39270999999999,38.97669000000001],"type":"Point"}
}