{
  "type": "Feature",
  "properties": {
    "gn:admin1_code":"11.0",
    "gn:asciiname":"Miaopingli",
    "gn:country_code":"CN",
    "gn:dem":343,
    "gn:feature_class":"P",
    "gn:feature_code":"PPL",
    "gn:name":"Miaopingli",
    "gn:population":0,
    "gn:timezone":"Asia/Shanghai",
    "iso:country":"CN",
    "name:zho_x_preferred":[
        "\u5e99\u576a\u91cc"
    ],
    "wof:name":"Miaopingli",
    "wof:placetype":"locality"
},
  "geometry": {"coordinates":[111.34466,28.49556],"type":"Point"}
}