{
  "type": "Feature",
  "properties": {
    "gn:admin1_code":"11.0",
    "gn:asciiname":"Shifenjiao",
    "gn:country_code":"CN",
    "gn:dem":287,
    "gn:feature_class":"P",
    "gn:feature_code":"PPL",
    "gn:name":"Shifenjiao",
    "gn:population":0,
    "gn:timezone":"Asia/Shanghai",
    "iso:country":"CN",
    "name:zho_x_preferred":[
        "\u77f3\u575f\u811a"
    ],
    "wof:name":"Shifenjiao",
    "wof:placetype":"locality"
},
  "geometry": {"coordinates":[112.98882999999999,25.42957],"type":"Point"}
}