{
  "type": "Feature",
  "properties": {
    "gn:admin1_code":"4.0",
    "gn:asciiname":"Xiangfu Wuzu",
    "gn:country_code":"CN",
    "gn:dem":5,
    "gn:feature_class":"P",
    "gn:feature_code":"PPLF",
    "gn:name":"Xiangfu Wuzu",
    "gn:population":0,
    "gn:timezone":"Asia/Shanghai",
    "iso:country":"CN",
    "name:zho_x_preferred":[
        "\u7965\u9644\u4e94\u7ec4"
    ],
    "wof:name":"Xiangfu Wuzu",
    "wof:placetype":"locality"
},
  "geometry": {"coordinates":[120.524,33.1053],"type":"Point"}
}