{
  "type": "Feature",
  "properties": {
    "gn:admin1_code":"24.0",
    "gn:asciiname":"Zhaojiayao",
    "gn:cc2":"CN",
    "gn:country_code":"CN",
    "gn:dem":1119,
    "gn:feature_class":"P",
    "gn:feature_code":"PPL",
    "gn:name":"Zhaojiayao",
    "gn:population":0,
    "gn:timezone":"Asia/Shanghai",
    "iso:country":"CN",
    "name:und_x_variant":[
        "Chao-chia-yao",
        "Zhaojiayao"
    ],
    "wof:name":"Zhaojiayao",
    "wof:placetype":"locality"
},
  "geometry": {"coordinates":[112.10917000000001,37.04111],"type":"Point"}
}