{
  "type": "Feature",
  "properties": {
    "gn:admin1_code":"32.0",
    "gn:asciiname":"Zhaza",
    "gn:country_code":"CN",
    "gn:dem":2540,
    "gn:feature_class":"P",
    "gn:feature_code":"PPL",
    "gn:name":"Zhaza",
    "gn:population":0,
    "gn:timezone":"Asia/Shanghai",
    "iso:country":"CN",
    "name:zho_x_preferred":[
        "\u624e\u6742"
    ],
    "wof:name":"Zhaza",
    "wof:placetype":"locality"
},
  "geometry": {"coordinates":[99.3104,28.8561],"type":"Point"}
}