{
  "type": "Feature",
  "properties": {
    "gn:admin1_code":"7",
    "gn:asciiname":"Dingqian",
    "gn:country_code":"CN",
    "gn:dem":186,
    "gn:feature_class":"P",
    "gn:feature_code":"PPL",
    "gn:name":"Dingqian",
    "gn:population":0,
    "gn:timezone":"Asia/Shanghai",
    "iso:country":"CN",
    "name:und_x_variant":[
        "\u9876\u524d"
    ],
    "wof:name":"Dingqian",
    "wof:placetype":"locality"
},
  "geometry": {"coordinates":[118.74556,27.32611],"type":"Point"}
}