{
  "type": "Feature",
  "properties": {
    "gn:admin1_code":"29",
    "gn:asciiname":"Longyao",
    "gn:country_code":"CN",
    "gn:dem":1131,
    "gn:feature_class":"P",
    "gn:feature_code":"PPL",
    "gn:name":"Longyao",
    "gn:population":0,
    "gn:timezone":"Asia/Shanghai",
    "iso:country":"CN",
    "name:und_x_variant":[
        "Longme",
        "Longyao"
    ],
    "name:zho_x_preferred":[
        "\u9f99\u4e48"
    ],
    "wof:name":"Longyao",
    "wof:placetype":"locality"
},
  "geometry": {"coordinates":[105.026,24.1635],"type":"Point"}
}