{
  "type": "Feature",
  "properties": {
    "gn:admin1_code":"30.0",
    "gn:asciiname":"Caoduikeng",
    "gn:country_code":"CN",
    "gn:dem":512,
    "gn:feature_class":"P",
    "gn:feature_code":"PPL",
    "gn:name":"Caoduikeng",
    "gn:population":0,
    "gn:timezone":"Asia/Shanghai",
    "iso:country":"CN",
    "name:zho_x_preferred":[
        "Caoduikeng"
    ],
    "name:zho_x_variant":[
        "\u66f9\u7893\u5751"
    ],
    "wof:name":"Caoduikeng",
    "wof:placetype":"locality"
},
  "geometry": {"coordinates":[113.24722,25.21889],"type":"Point"}
}