{
  "type": "Feature",
  "properties": {
    "gn:admin1_code":"32.0",
    "gn:asciiname":"Yanshuitian",
    "gn:country_code":"CN",
    "gn:dem":312,
    "gn:feature_class":"P",
    "gn:feature_code":"PPL",
    "gn:name":"Yanshuitian",
    "gn:population":0,
    "gn:timezone":"Asia/Shanghai",
    "iso:country":"CN",
    "name:zho_x_preferred":[
        "\u5830\u6c34\u7530"
    ],
    "wof:name":"Yanshuitian",
    "wof:placetype":"locality"
},
  "geometry": {"coordinates":[106.88367,30.53972000000001],"type":"Point"}
}