{
  "type": "Feature",
  "properties": {
    "gn:admin1_code":"19.0",
    "gn:asciiname":"Dalaihecun",
    "gn:country_code":"CN",
    "gn:dem":487,
    "gn:feature_class":"P",
    "gn:feature_code":"PPL",
    "gn:name":"Dalaihecun",
    "gn:population":0,
    "gn:timezone":"Asia/Shanghai",
    "iso:country":"CN",
    "name:zho_x_preferred":[
        "\u5927\u83b1\u6cb3\u6751"
    ],
    "wof:name":"Dalaihecun",
    "wof:placetype":"locality"
},
  "geometry": {"coordinates":[124.744,41.8628],"type":"Point"}
}