{
  "type": "Feature",
  "properties": {
    "gn:admin1_code":"21.0",
    "gn:asciiname":"Xiaxiaoxigou",
    "gn:country_code":"CN",
    "gn:dem":2124,
    "gn:feature_class":"P",
    "gn:feature_code":"PPL",
    "gn:name":"Xiaxiaoxigou",
    "gn:population":0,
    "gn:timezone":"Asia/Shanghai",
    "iso:country":"CN",
    "name:zho_x_preferred":[
        "\u4e0b\u5c0f\u897f\u6c9f"
    ],
    "wof:name":"Xiaxiaoxigou",
    "wof:placetype":"locality"
},
  "geometry": {"coordinates":[105.51000000000001,36.2493],"type":"Point"}
}