{
  "type": "Feature",
  "properties": {
    "gn:admin1_code":"29.0",
    "gn:asciiname":"Majingzi",
    "gn:country_code":"CN",
    "gn:dem":1322,
    "gn:feature_class":"P",
    "gn:feature_code":"PPL",
    "gn:name":"Majingzi",
    "gn:population":0,
    "gn:timezone":"Asia/Shanghai",
    "iso:country":"CN",
    "name:zho_x_preferred":[
        "\u9a6c\u9888\u5b50"
    ],
    "wof:name":"Majingzi",
    "wof:placetype":"locality"
},
  "geometry": {"coordinates":[101.38,26.607],"type":"Point"}
}