{
  "type": "Feature",
  "properties": {
    "gn:admin1_code":"30.0",
    "gn:asciiname":"Sunwu",
    "gn:country_code":"CN",
    "gn:dem":95,
    "gn:feature_class":"P",
    "gn:feature_code":"PPL",
    "gn:name":"Sunwu",
    "gn:population":0,
    "gn:timezone":"Asia/Shanghai",
    "iso:country":"CN",
    "name:zho_x_preferred":[
        "Sunwu"
    ],
    "name:zho_x_variant":[
        "\u5b59\u5c4b"
    ],
    "wof:name":"Sunwu",
    "wof:placetype":"locality"
},
  "geometry": {"coordinates":[115.11694,24.28306],"type":"Point"}
}