{
  "type": "Feature",
  "properties": {
    "gn:admin1_code":"26.0",
    "gn:asciiname":"Hongxingcun",
    "gn:country_code":"CN",
    "gn:dem":1597,
    "gn:feature_class":"P",
    "gn:feature_code":"PPL",
    "gn:name":"Hongxingcun",
    "gn:population":0,
    "gn:timezone":"Asia/Shanghai",
    "iso:country":"CN",
    "name:und_x_variant":[
        "\u7ea2\u661f\u6751"
    ],
    "wof:name":"Hongxingcun",
    "wof:placetype":"locality"
},
  "geometry": {"coordinates":[107.32205,34.08002],"type":"Point"}
}