{
  "type": "Feature",
  "properties": {
    "gn:admin1_code":"11.0",
    "gn:asciiname":"Yanqiaoping",
    "gn:country_code":"CN",
    "gn:dem":71,
    "gn:feature_class":"P",
    "gn:feature_code":"PPL",
    "gn:name":"Yanqiaoping",
    "gn:population":0,
    "gn:timezone":"Asia/Shanghai",
    "iso:country":"CN",
    "name:zho_x_preferred":[
        "Yanqiaoping"
    ],
    "name:zho_x_variant":[
        "\u5ca9\u6865\u576a"
    ],
    "wof:name":"Yanqiaoping",
    "wof:placetype":"locality"
},
  "geometry": {"coordinates":[111.42668,29.24204000000001],"type":"Point"}
}