{
  "type": "Feature",
  "properties": {
    "gn:admin1_code":"02",
    "gn:asciiname":"Tangtoucun",
    "gn:country_code":"CN",
    "gn:dem":115,
    "gn:feature_class":"P",
    "gn:feature_code":"PPL",
    "gn:name":"Tangtoucun",
    "gn:population":0,
    "gn:timezone":"Asia/Shanghai",
    "iso:country":"CN",
    "name:und_x_variant":[
        "Tangtou",
        "\u5858\u5934",
        "Tangtoucun"
    ],
    "name:zho_x_preferred":[
        "\u5858\u5934\u6751"
    ],
    "wof:name":"Tangtoucun",
    "wof:placetype":"locality"
},
  "geometry": {"coordinates":[122.32474000000001,30.01889000000001],"type":"Point"}
}