{
  "type": "Feature",
  "properties": {
    "gn:admin1_code":"19.0",
    "gn:asciiname":"Fulongtun",
    "gn:country_code":"CN",
    "gn:dem":114,
    "gn:feature_class":"P",
    "gn:feature_code":"PPL",
    "gn:name":"Fulongtun",
    "gn:population":0,
    "gn:timezone":"Asia/Shanghai",
    "iso:country":"CN",
    "name:zho_x_preferred":[
        "\u798f\u9686\u5c6f"
    ],
    "wof:name":"Fulongtun",
    "wof:placetype":"locality"
},
  "geometry": {"coordinates":[122.751,39.8011],"type":"Point"}
}