{
  "type": "Feature",
  "properties": {
    "gn:admin1_code":"19.0",
    "gn:asciiname":"Qiansishilibu",
    "gn:country_code":"CN",
    "gn:dem":3,
    "gn:feature_class":"P",
    "gn:feature_code":"PPL",
    "gn:name":"Qiansishilibu",
    "gn:population":0,
    "gn:timezone":"Asia/Shanghai",
    "iso:country":"CN",
    "name:und_x_variant":[
        "Qiansishilibao",
        "Qiansishilibu"
    ],
    "name:zho_x_preferred":[
        "\u524d\u56db\u5341\u91cc\u5821"
    ],
    "wof:name":"Qiansishilibu",
    "wof:placetype":"locality"
},
  "geometry": {"coordinates":[122.17085,41.02611],"type":"Point"}
}