{
  "type": "Feature",
  "properties": {
    "gn:admin1_code":"14.0",
    "gn:asciiname":"Zongza",
    "gn:country_code":"CN",
    "gn:dem":3336,
    "gn:feature_class":"P",
    "gn:feature_code":"PPL",
    "gn:name":"Zongza",
    "gn:population":0,
    "gn:timezone":"Asia/Urumqi",
    "iso:country":"CN",
    "name:bod_x_preferred":[
        "Zongza"
    ],
    "name:zho_x_preferred":[
        "Zongzha"
    ],
    "name:zho_x_variant":[
        "\u5b97\u624e",
        "Xuzhong Gongshe",
        "\u5f90\u4e2d\u516c\u793e"
    ],
    "wof:name":"Zongza",
    "wof:placetype":"locality"
},
  "geometry": {"coordinates":[98.80200000000001,29.202],"type":"Point"}
}