{
  "type": "Feature",
  "properties": {
    "gn:admin1_code":"19.0",
    "gn:asciiname":"Houzhangzicun",
    "gn:country_code":"CN",
    "gn:dem":265,
    "gn:feature_class":"P",
    "gn:feature_code":"PPL",
    "gn:name":"Houzhangzicun",
    "gn:population":0,
    "gn:timezone":"Asia/Shanghai",
    "iso:country":"CN",
    "name:zho_x_preferred":[
        "\u539a\u6756\u5b50\u6751"
    ],
    "wof:name":"Houzhangzicun",
    "wof:placetype":"locality"
},
  "geometry": {"coordinates":[120.36651000000001,41.71492],"type":"Point"}
}