{
  "type": "Feature",
  "properties": {
    "gn:admin1_code":"29.0",
    "gn:asciiname":"Yujiazhai",
    "gn:country_code":"CN",
    "gn:dem":1727,
    "gn:feature_class":"P",
    "gn:feature_code":"PPL",
    "gn:name":"Yujiazhai",
    "gn:population":0,
    "gn:timezone":"Asia/Shanghai",
    "iso:country":"CN",
    "name:zho_x_preferred":[
        "\u4f59\u5bb6\u5be8"
    ],
    "wof:name":"Yujiazhai",
    "wof:placetype":"locality"
},
  "geometry": {"coordinates":[98.54510000000001,25.1877],"type":"Point"}
}