{
  "type": "Feature",
  "properties": {
    "gn:admin1_code":"29.0",
    "gn:asciiname":"Haigong",
    "gn:country_code":"CN",
    "gn:dem":1647,
    "gn:feature_class":"P",
    "gn:feature_code":"PPL",
    "gn:name":"Haigong",
    "gn:population":0,
    "gn:timezone":"Asia/Shanghai",
    "iso:country":"CN",
    "name:zho_x_preferred":[
        "\u4ea5\u516c"
    ],
    "wof:name":"Haigong",
    "wof:placetype":"locality"
},
  "geometry": {"coordinates":[99.97490000000001,23.6201],"type":"Point"}
}