{
  "type": "Feature",
  "properties": {
    "gn:admin1_code":"04",
    "gn:asciiname":"Nanmo",
    "gn:country_code":"CN",
    "gn:dem":4,
    "gn:feature_class":"P",
    "gn:feature_code":"PPLA4",
    "gn:name":"Nanmo",
    "gn:population":0,
    "gn:timezone":"Asia/Shanghai",
    "iso:country":"CN",
    "name:und_x_variant":[
        "Nanmozhuang",
        "Nanmo",
        "\u5357\u83ab",
        "Nanmo Zhen",
        "\u5357\u83ab\u9547"
    ],
    "wof:name":"Nanmo",
    "wof:placetype":"locality"
},
  "geometry": {"coordinates":[120.27691000000002,32.59484],"type":"Point"}
}