{
  "type": "Feature",
  "properties": {
    "gn:admin1_code":"4.0",
    "gn:asciiname":"Dazuzhuang",
    "gn:country_code":"CN",
    "gn:dem":5,
    "gn:feature_class":"P",
    "gn:feature_code":"PPL",
    "gn:name":"Dazuzhuang",
    "gn:population":0,
    "gn:timezone":"Asia/Shanghai",
    "iso:country":"CN",
    "name:zho_x_preferred":[
        "Dazuzhuang"
    ],
    "name:zho_x_variant":[
        "\u5927\u79df\u5e84"
    ],
    "wof:name":"Dazuzhuang",
    "wof:placetype":"locality"
},
  "geometry": {"coordinates":[119.27491999999999,33.97505],"type":"Point"}
}