{
  "type": "Feature",
  "properties": {
    "gn:admin1_code":"20.0",
    "gn:asciiname":"Minjuchuan",
    "gn:country_code":"CN",
    "gn:dem":265,
    "gn:feature_class":"P",
    "gn:feature_code":"PPL",
    "gn:name":"Minjuchuan",
    "gn:population":0,
    "gn:timezone":"Asia/Shanghai",
    "iso:country":"CN",
    "name:zho_x_preferred":[
        "\u6c11\u5de8\u5ddd"
    ],
    "wof:name":"Minjuchuan",
    "wof:placetype":"locality"
},
  "geometry": {"coordinates":[124.19061000000001,48.65912],"type":"Point"}
}