{
  "type": "Feature",
  "properties": {
    "gn:admin1_code":"10",
    "gn:asciiname":"Beitaizi",
    "gn:country_code":"CN",
    "gn:dem":1194,
    "gn:feature_class":"P",
    "gn:feature_code":"PPL",
    "gn:name":"Beitaizi",
    "gn:population":0,
    "gn:timezone":"Asia/Shanghai",
    "iso:country":"CN",
    "name:zho_x_preferred":[
        "\u5317\u53f0\u5b50"
    ],
    "wof:name":"Beitaizi",
    "wof:placetype":"locality"
},
  "geometry": {"coordinates":[116.71975,41.75723],"type":"Point"}
}