{
  "type": "Feature",
  "properties": {
    "gn:admin1_code":"14",
    "gn:asciiname":"Zhaxijicai",
    "gn:country_code":"CN",
    "gn:dem":3850,
    "gn:feature_class":"P",
    "gn:feature_code":"PPL",
    "gn:name":"Zhaxijicai",
    "gn:population":0,
    "gn:timezone":"Asia/Urumqi",
    "iso:country":"CN",
    "name:zho_x_preferred":[
        "\u624e\u897f\u5409\u5f69"
    ],
    "wof:name":"Zhaxijicai",
    "wof:placetype":"locality"
},
  "geometry": {"coordinates":[88.87779999999999,29.259],"type":"Point"}
}