{
  "type": "Feature",
  "properties": {
    "gn:admin1_code":"14.0",
    "gn:asciiname":"Xiawo",
    "gn:country_code":"CN",
    "gn:dem":3373,
    "gn:feature_class":"P",
    "gn:feature_code":"PPL",
    "gn:name":"Xiawo",
    "gn:population":0,
    "gn:timezone":"Asia/Urumqi",
    "iso:country":"CN",
    "name:zho_x_preferred":[
        "\u867e\u631d"
    ],
    "wof:name":"Xiawo",
    "wof:placetype":"locality"
},
  "geometry": {"coordinates":[98.36281,31.58],"type":"Point"}
}