{
  "type": "Feature",
  "properties": {
    "gn:admin1_code":"32.0",
    "gn:asciiname":"Longsheng",
    "gn:country_code":"CN",
    "gn:dem":432,
    "gn:feature_class":"P",
    "gn:feature_code":"PPL",
    "gn:name":"Longsheng",
    "gn:population":0,
    "gn:timezone":"Asia/Shanghai",
    "iso:country":"CN",
    "name:zho_x_preferred":[
        "\u9686\u80dc"
    ],
    "wof:name":"Longsheng",
    "wof:placetype":"locality"
},
  "geometry": {"coordinates":[104.86190000000001,30.9391],"type":"Point"}
}