{
  "type": "Feature",
  "properties": {
    "gn:admin1_code":"29.0",
    "gn:asciiname":"Fuqiancun",
    "gn:country_code":"CN",
    "gn:dem":1434,
    "gn:feature_class":"P",
    "gn:feature_code":"PPL",
    "gn:name":"Fuqiancun",
    "gn:population":0,
    "gn:timezone":"Asia/Shanghai",
    "iso:country":"CN",
    "name:zho_x_preferred":[
        "\u592b\u5343\u6751"
    ],
    "wof:name":"Fuqiancun",
    "wof:placetype":"locality"
},
  "geometry": {"coordinates":[98.8917,27.2106],"type":"Point"}
}