{
  "type": "Feature",
  "properties": {
    "gn:admin1_code":"26.0",
    "gn:asciiname":"Yaojiashan",
    "gn:country_code":"CN",
    "gn:dem":840,
    "gn:feature_class":"P",
    "gn:feature_code":"PPL",
    "gn:name":"Yaojiashan",
    "gn:population":0,
    "gn:timezone":"Asia/Shanghai",
    "iso:country":"CN",
    "name:und_x_variant":[
        "\u59da\u5bb6\u5c71"
    ],
    "wof:name":"Yaojiashan",
    "wof:placetype":"locality"
},
  "geometry": {"coordinates":[107.08514,34.52379000000001],"type":"Point"}
}