{
  "type": "Feature",
  "properties": {
    "gn:admin1_code":"29.0",
    "gn:asciiname":"Sijia",
    "gn:country_code":"CN",
    "gn:dem":1847,
    "gn:feature_class":"P",
    "gn:feature_code":"PPL",
    "gn:name":"Sijia",
    "gn:population":0,
    "gn:timezone":"Asia/Shanghai",
    "iso:country":"CN",
    "name:zho_x_preferred":[
        "\u56db\u5bb6"
    ],
    "wof:name":"Sijia",
    "wof:placetype":"locality"
},
  "geometry": {"coordinates":[100.37,25.7484],"type":"Point"}
}