{
  "type": "Feature",
  "properties": {
    "gn:admin1_code":"32.0",
    "gn:asciiname":"Chunguang",
    "gn:country_code":"CN",
    "gn:dem":714,
    "gn:feature_class":"P",
    "gn:feature_code":"PPL",
    "gn:name":"Chunguang",
    "gn:population":0,
    "gn:timezone":"Asia/Shanghai",
    "iso:country":"CN",
    "name:zho_x_preferred":[
        "\u6625\u5149"
    ],
    "wof:name":"Chunguang",
    "wof:placetype":"locality"
},
  "geometry": {"coordinates":[105.31699999999999,31.9328],"type":"Point"}
}