{
  "type": "Feature",
  "properties": {
    "gn:admin1_code":"11",
    "gn:asciiname":"Sanyantang",
    "gn:country_code":"CN",
    "gn:dem":67,
    "gn:feature_class":"P",
    "gn:feature_code":"PPL",
    "gn:name":"Sanyantang",
    "gn:population":0,
    "gn:timezone":"Asia/Shanghai",
    "iso:country":"CN",
    "name:zho_x_preferred":[
        "\u4e09\u773c\u5858\u9547"
    ],
    "wof:name":"Sanyantang",
    "wof:placetype":"locality"
},
  "geometry": {"coordinates":[113.03667,28.39528],"type":"Point"}
}