{
  "type": "Feature",
  "properties": {
    "gn:admin1_code":"07",
    "gn:asciiname":"Fuyangge",
    "gn:country_code":"CN",
    "gn:dem":836,
    "gn:feature_class":"P",
    "gn:feature_code":"PPL",
    "gn:name":"Fuyangge",
    "gn:population":0,
    "gn:timezone":"Asia/Shanghai",
    "iso:country":"CN",
    "name:zho_x_preferred":[
        "\u6d6e\u6d0b\u683c"
    ],
    "wof:name":"Fuyangge",
    "wof:placetype":"locality"
},
  "geometry": {"coordinates":[118.17448,25.86607],"type":"Point"}
}