{
  "type": "Feature",
  "properties": {
    "gn:admin1_code":"32.0",
    "gn:asciiname":"Luwei",
    "gn:country_code":"CN",
    "gn:dem":1709,
    "gn:feature_class":"P",
    "gn:feature_code":"PPL",
    "gn:name":"Luwei",
    "gn:population":0,
    "gn:timezone":"Asia/Shanghai",
    "iso:country":"CN",
    "name:zho_x_preferred":[
        "\u82a6\u56f4"
    ],
    "wof:name":"Luwei",
    "wof:placetype":"locality"
},
  "geometry": {"coordinates":[102.503,28.5887],"type":"Point"}
}