{
  "type": "Feature",
  "properties": {
    "gn:admin1_code":"3.0",
    "gn:asciiname":"Yuantangtou",
    "gn:country_code":"CN",
    "gn:dem":501,
    "gn:feature_class":"P",
    "gn:feature_code":"PPL",
    "gn:name":"Yuantangtou",
    "gn:population":0,
    "gn:timezone":"Asia/Shanghai",
    "iso:country":"CN",
    "name:und_x_variant":[
        "\u5706\u5858\u5934"
    ],
    "wof:name":"Yuantangtou",
    "wof:placetype":"locality"
},
  "geometry": {"coordinates":[115.72676,24.71629],"type":"Point"}
}