{
  "type": "Feature",
  "properties": {
    "gn:admin1_code":"9.0",
    "gn:asciiname":"Quanmenyang",
    "gn:country_code":"CN",
    "gn:dem":125,
    "gn:feature_class":"P",
    "gn:feature_code":"PPL",
    "gn:name":"Quanmenyang",
    "gn:population":0,
    "gn:timezone":"Asia/Shanghai",
    "iso:country":"CN",
    "name:zho_x_preferred":[
        "\u5238\u95e8\u6768"
    ],
    "wof:name":"Quanmenyang",
    "wof:placetype":"locality"
},
  "geometry": {"coordinates":[112.85037,32.79296],"type":"Point"}
}