{
  "type": "Feature",
  "properties": {
    "gn:admin1_code":"15.0",
    "gn:asciiname":"Chu'anzu",
    "gn:country_code":"CN",
    "gn:dem":2846,
    "gn:feature_class":"P",
    "gn:feature_code":"PPL",
    "gn:name":"Chu\u2019anzu",
    "gn:population":0,
    "gn:timezone":"Asia/Shanghai",
    "iso:country":"CN",
    "name:und_x_variant":[
        "Chu\u2019anzu",
        "\u521d\u5b89\u65cf"
    ],
    "wof:name":"Chu'anzu",
    "wof:placetype":"locality"
},
  "geometry": {"coordinates":[103.52451000000001,34.6588],"type":"Point"}
}