{
  "type": "Feature",
  "properties": {
    "gn:admin1_code":"5.0",
    "gn:asciiname":"Naoyucun",
    "gn:country_code":"CN",
    "gn:dem":178,
    "gn:feature_class":"P",
    "gn:feature_code":"PPL",
    "gn:name":"Naoyucun",
    "gn:population":0,
    "gn:timezone":"Asia/Shanghai",
    "iso:country":"CN",
    "name:zho_x_preferred":[
        "\u95f9\u7389\u6751"
    ],
    "wof:name":"Naoyucun",
    "wof:placetype":"locality"
},
  "geometry": {"coordinates":[123.78027,44.0777],"type":"Point"}
}