{
  "type": "Feature",
  "properties": {
    "gn:admin1_code":"30.0",
    "gn:asciiname":"Baishachong",
    "gn:country_code":"CN",
    "gn:dem":413,
    "gn:feature_class":"P",
    "gn:feature_code":"PPL",
    "gn:name":"Baishachong",
    "gn:population":0,
    "gn:timezone":"Asia/Shanghai",
    "iso:country":"CN",
    "name:zho_x_preferred":[
        "Baishachong"
    ],
    "name:zho_x_variant":[
        "\u767d\u6c99\u51b2"
    ],
    "wof:name":"Baishachong",
    "wof:placetype":"locality"
},
  "geometry": {"coordinates":[112.47693999999998,24.4825],"type":"Point"}
}