{
  "type": "Feature",
  "properties": {
    "gn:admin1_code":"33.0",
    "gn:asciiname":"Basan",
    "gn:country_code":"CN",
    "gn:dem":335,
    "gn:feature_class":"P",
    "gn:feature_code":"PPL",
    "gn:name":"Basan",
    "gn:population":0,
    "gn:timezone":"Asia/Shanghai",
    "iso:country":"CN",
    "name:zho_x_preferred":[
        "\u628a\u4f1e"
    ],
    "wof:name":"Basan",
    "wof:placetype":"locality"
},
  "geometry": {"coordinates":[106.02764000000001,30.13259],"type":"Point"}
}