{
  "type": "Feature",
  "properties": {
    "gn:admin1_code":"26.0",
    "gn:asciiname":"Gaoyicun",
    "gn:country_code":"CN",
    "gn:dem":473,
    "gn:feature_class":"P",
    "gn:feature_code":"PPL",
    "gn:name":"Gaoyicun",
    "gn:population":0,
    "gn:timezone":"Asia/Shanghai",
    "iso:country":"CN",
    "name:zho_x_preferred":[
        "\u9ad8\u4e49\u6751"
    ],
    "wof:name":"Gaoyicun",
    "wof:placetype":"locality"
},
  "geometry": {"coordinates":[109.34659000000001,34.86638],"type":"Point"}
}