{
  "type": "Feature",
  "properties": {
    "gn:admin1_code":"07",
    "gn:asciiname":"Paiji",
    "gn:country_code":"CN",
    "gn:dem":694,
    "gn:feature_class":"P",
    "gn:feature_code":"PPL",
    "gn:name":"Paiji",
    "gn:population":0,
    "gn:timezone":"Asia/Shanghai",
    "iso:country":"CN",
    "name:zho_x_preferred":[
        "\u6392\u5409"
    ],
    "wof:name":"Paiji",
    "wof:placetype":"locality"
},
  "geometry": {"coordinates":[117.62512,25.8209],"type":"Point"}
}