{
  "type": "Feature",
  "properties": {
    "gn:admin1_code":"30",
    "gn:asciiname":"Longwo",
    "gn:country_code":"CN",
    "gn:dem":295,
    "gn:feature_class":"P",
    "gn:feature_code":"PPLA4",
    "gn:name":"Longwo",
    "gn:population":0,
    "gn:timezone":"Asia/Shanghai",
    "iso:country":"CN",
    "name:und_x_variant":[
        "Lung-wo-hsu",
        "Lung-wo",
        "Longwo",
        "\u9f99\u7a9d",
        "Longwo Zhen",
        "\u9f99\u7a9d\u9547"
    ],
    "wof:name":"Longwo",
    "wof:placetype":"locality"
},
  "geometry": {"coordinates":[115.30179,23.4757],"type":"Point"}
}