{
  "type": "Feature",
  "properties": {
    "gn:admin1_code":"1.0",
    "gn:asciiname":"Youliancun",
    "gn:country_code":"CN",
    "gn:dem":49,
    "gn:feature_class":"P",
    "gn:feature_code":"PPL",
    "gn:name":"Youliancun",
    "gn:population":0,
    "gn:timezone":"Asia/Shanghai",
    "iso:country":"CN",
    "name:zho_x_preferred":[
        "\u53cb\u8054\u6751"
    ],
    "wof:name":"Youliancun",
    "wof:placetype":"locality"
},
  "geometry": {"coordinates":[116.05098999999998,32.04085],"type":"Point"}
}