{
  "type": "Feature",
  "properties": {
    "gn:admin1_code":"11",
    "gn:asciiname":"Luohanshan",
    "gn:country_code":"CN",
    "gn:dem":105,
    "gn:feature_class":"P",
    "gn:feature_code":"PPL",
    "gn:name":"Luohanshan",
    "gn:population":0,
    "gn:timezone":"Asia/Shanghai",
    "iso:country":"CN",
    "name:zho_x_preferred":[
        "\u7f57\u6c49\u5c71"
    ],
    "wof:name":"Luohanshan",
    "wof:placetype":"locality"
},
  "geometry": {"coordinates":[112.10465000000001,27.72535],"type":"Point"}
}