{
  "type": "Feature",
  "properties": {
    "gn:admin1_code":"13.0",
    "gn:asciiname":"Qiongkajizi",
    "gn:country_code":"CN",
    "gn:dem":3423,
    "gn:feature_class":"P",
    "gn:feature_code":"PPL",
    "gn:name":"Qiongkajizi",
    "gn:population":0,
    "gn:timezone":"Asia/Shanghai",
    "iso:country":"CN",
    "name:zho_x_preferred":[
        "\u743c\u5361\u53ca\u5b5c"
    ],
    "wof:name":"Qiongkajizi",
    "wof:placetype":"locality"
},
  "geometry": {"coordinates":[78.85254999999999,36.73757],"type":"Point"}
}