{
  "type": "Feature",
  "properties": {
    "gn:admin1_code":"12.0",
    "gn:asciiname":"Shiyuanzi",
    "gn:country_code":"CN",
    "gn:dem":49,
    "gn:feature_class":"P",
    "gn:feature_code":"PPL",
    "gn:name":"Shiyuanzi",
    "gn:population":0,
    "gn:timezone":"Asia/Shanghai",
    "iso:country":"CN",
    "name:zho_x_preferred":[
        "\u77f3\u9662\u5b50"
    ],
    "wof:name":"Shiyuanzi",
    "wof:placetype":"locality"
},
  "geometry": {"coordinates":[112.44710000000001,30.88389],"type":"Point"}
}