{
  "type": "Feature",
  "properties": {
    "gn:admin1_code":"14.0",
    "gn:asciiname":"Anduokangba",
    "gn:country_code":"CN",
    "gn:dem":5015,
    "gn:feature_class":"P",
    "gn:feature_code":"PPL",
    "gn:name":"Anduokangba",
    "gn:population":0,
    "gn:timezone":"Asia/Urumqi",
    "iso:country":"CN",
    "name:zho_x_preferred":[
        "\u5b89\u591a\u5eb7\u5df4"
    ],
    "wof:name":"Anduokangba",
    "wof:placetype":"locality"
},
  "geometry": {"coordinates":[89.89544000000002,31.42066],"type":"Point"}
}