{
  "type": "Feature",
  "properties": {
    "gn:admin1_code":"9",
    "gn:asciiname":"Yadoutun",
    "gn:country_code":"CN",
    "gn:dem":57,
    "gn:feature_class":"P",
    "gn:feature_code":"PPL",
    "gn:name":"Yadoutun",
    "gn:population":0,
    "gn:timezone":"Asia/Shanghai",
    "iso:country":"CN",
    "name:zho_x_preferred":[
        "\u82bd\u8c46\u5c6f"
    ],
    "wof:name":"Yadoutun",
    "wof:placetype":"locality"
},
  "geometry": {"coordinates":[115.24901,35.57925],"type":"Point"}
}