{
  "type": "Feature",
  "properties": {
    "gn:admin1_code":"7.0",
    "gn:asciiname":"Xiaqi",
    "gn:country_code":"CN",
    "gn:dem":825,
    "gn:feature_class":"P",
    "gn:feature_code":"PPL",
    "gn:name":"Xiaqi",
    "gn:population":0,
    "gn:timezone":"Asia/Shanghai",
    "iso:country":"CN",
    "name:zho_x_preferred":[
        "\u4e0b\u5c90"
    ],
    "wof:name":"Xiaqi",
    "wof:placetype":"locality"
},
  "geometry": {"coordinates":[118.44832,26.00818],"type":"Point"}
}