{
  "type": "Feature",
  "properties": {
    "gn:admin1_code":"20.0",
    "gn:asciiname":"Huangheshao",
    "gn:country_code":"CN",
    "gn:dem":1651,
    "gn:feature_class":"P",
    "gn:feature_code":"PPL",
    "gn:name":"Huangheshao",
    "gn:population":0,
    "gn:timezone":"Asia/Shanghai",
    "iso:country":"CN",
    "name:und_x_variant":[
        "\u9ec4\u5408\u5c11"
    ],
    "wof:name":"Huangheshao",
    "wof:placetype":"locality"
},
  "geometry": {"coordinates":[111.63261,41.22241],"type":"Point"}
}