{
  "type": "Feature",
  "properties": {
    "gn:admin1_code":"33.0",
    "gn:asciiname":"Dalanya",
    "gn:country_code":"CN",
    "gn:dem":531,
    "gn:feature_class":"P",
    "gn:feature_code":"PPL",
    "gn:name":"Dalanya",
    "gn:population":0,
    "gn:timezone":"Asia/Shanghai",
    "iso:country":"CN",
    "name:zho_x_preferred":[
        "\u5927\u5c9a\u57ad"
    ],
    "wof:name":"Dalanya",
    "wof:placetype":"locality"
},
  "geometry": {"coordinates":[106.642,28.8813],"type":"Point"}
}