{
  "type": "Feature",
  "properties": {
    "gn:admin1_code":"30.0",
    "gn:asciiname":"Longkengkou",
    "gn:country_code":"CN",
    "gn:dem":47,
    "gn:feature_class":"P",
    "gn:feature_code":"PPL",
    "gn:name":"Longkengkou",
    "gn:population":0,
    "gn:timezone":"Asia/Shanghai",
    "iso:country":"CN",
    "name:zho_x_preferred":[
        "\u9f99\u5751\u53e3"
    ],
    "wof:name":"Longkengkou",
    "wof:placetype":"locality"
},
  "geometry": {"coordinates":[112.70734,22.43014],"type":"Point"}
}