{
  "type": "Feature",
  "properties": {
    "gn:admin1_code":"9.0",
    "gn:asciiname":"Liusunzhuang",
    "gn:country_code":"CN",
    "gn:dem":42,
    "gn:feature_class":"P",
    "gn:feature_code":"PPL",
    "gn:name":"Liusunzhuang",
    "gn:population":0,
    "gn:timezone":"Asia/Shanghai",
    "iso:country":"CN",
    "name:zho_x_preferred":[
        "\u5218\u5b59\u5e84"
    ],
    "wof:name":"Liusunzhuang",
    "wof:placetype":"locality"
},
  "geometry": {"coordinates":[115.02647,32.45164],"type":"Point"}
}