{
  "type": "Feature",
  "properties": {
    "gn:admin1_code":"11.0",
    "gn:asciiname":"Shanzhutang",
    "gn:country_code":"CN",
    "gn:dem":87,
    "gn:feature_class":"P",
    "gn:feature_code":"PPL",
    "gn:name":"Shanzhutang",
    "gn:population":0,
    "gn:timezone":"Asia/Shanghai",
    "iso:country":"CN",
    "name:zho_x_preferred":[
        "\u5c71\u7af9\u5858"
    ],
    "wof:name":"Shanzhutang",
    "wof:placetype":"locality"
},
  "geometry": {"coordinates":[112.47515,28.11934],"type":"Point"}
}