{
  "type": "Feature",
  "properties": {
    "gn:admin1_code":"16",
    "gn:asciiname":"Caoping Huizuxiang",
    "gn:country_code":"CN",
    "gn:dem":134,
    "gn:feature_class":"P",
    "gn:feature_code":"PPL",
    "gn:name":"Caoping Huizuxiang",
    "gn:population":0,
    "gn:timezone":"Asia/Shanghai",
    "iso:country":"CN",
    "wof:name":"Caoping Huizuxiang",
    "wof:placetype":"locality"
},
  "geometry": {"coordinates":[110.44556,25.04944],"type":"Point"}
}