{
  "type": "Feature",
  "properties": {
    "gn:admin1_code":"18",
    "gn:asciiname":"Shaguozhai",
    "gn:country_code":"CN",
    "gn:dem":1475,
    "gn:feature_class":"P",
    "gn:feature_code":"PPL",
    "gn:name":"Shaguozhai",
    "gn:population":0,
    "gn:timezone":"Asia/Shanghai",
    "iso:country":"CN",
    "name:zho_x_preferred":[
        "\u6c99\u9505\u5be8"
    ],
    "wof:name":"Shaguozhai",
    "wof:placetype":"locality"
},
  "geometry": {"coordinates":[106.04000000000001,26.3502],"type":"Point"}
}