{
  "type": "Feature",
  "properties": {
    "gn:admin1_code":"30",
    "gn:asciiname":"Beipocun",
    "gn:country_code":"CN",
    "gn:dem":26,
    "gn:feature_class":"P",
    "gn:feature_code":"PPL",
    "gn:name":"Beipocun",
    "gn:population":0,
    "gn:timezone":"Asia/Urumqi",
    "iso:country":"CN",
    "name:zho_x_preferred":[
        "\u5317\u5761\u6751"
    ],
    "wof:name":"Beipocun",
    "wof:placetype":"locality"
},
  "geometry": {"coordinates":[109.92923999999999,21.23513],"type":"Point"}
}