{
  "type": "Feature",
  "properties": {
    "gn:admin1_code":"9.0",
    "gn:asciiname":"Dazhuyuan",
    "gn:country_code":"CN",
    "gn:dem":649,
    "gn:feature_class":"P",
    "gn:feature_code":"PPL",
    "gn:name":"Dazhuyuan",
    "gn:population":0,
    "gn:timezone":"Asia/Shanghai",
    "iso:country":"CN",
    "name:und_x_variant":[
        "\u5927\u7af9\u56ed",
        "Dazhuyuan"
    ],
    "wof:name":"Dazhuyuan",
    "wof:placetype":"locality"
},
  "geometry": {"coordinates":[112.13937,33.2818],"type":"Point"}
}