{
  "type": "Feature",
  "properties": {
    "gn:admin1_code":"12.0",
    "gn:asciiname":"Zhongjiahu",
    "gn:country_code":"CN",
    "gn:dem":21,
    "gn:feature_class":"P",
    "gn:feature_code":"PPL",
    "gn:name":"Zhongjiahu",
    "gn:population":0,
    "gn:timezone":"Asia/Shanghai",
    "iso:country":"CN",
    "name:zho_x_preferred":[
        "Zhongjiahu"
    ],
    "name:zho_x_variant":[
        "\u4e2d\u5bb6\u6e56"
    ],
    "wof:name":"Zhongjiahu",
    "wof:placetype":"locality"
},
  "geometry": {"coordinates":[115.05837,29.75959000000001],"type":"Point"}
}