{
  "type": "Feature",
  "properties": {
    "gn:admin1_code":"32",
    "gn:asciiname":"Daban Yakou",
    "gn:country_code":"CN",
    "gn:dem":378,
    "gn:feature_class":"P",
    "gn:feature_code":"PPL",
    "gn:name":"Daban Yakou",
    "gn:population":0,
    "gn:timezone":"Asia/Shanghai",
    "iso:country":"CN",
    "name:zho_x_preferred":[
        "\u5927\u677f\u57ad\u53e3"
    ],
    "wof:name":"Daban Yakou",
    "wof:placetype":"locality"
},
  "geometry": {"coordinates":[106.51040999999999,30.41178],"type":"Point"}
}