{
  "type": "Feature",
  "properties": {
    "gn:admin1_code":"18.0",
    "gn:asciiname":"Baiyuepo",
    "gn:country_code":"CN",
    "gn:dem":859,
    "gn:feature_class":"P",
    "gn:feature_code":"PPL",
    "gn:name":"Baiyuepo",
    "gn:population":0,
    "gn:timezone":"Asia/Shanghai",
    "iso:country":"CN",
    "name:zho_x_preferred":[
        "\u6446\u6708\u5761"
    ],
    "wof:name":"Baiyuepo",
    "wof:placetype":"locality"
},
  "geometry": {"coordinates":[108.783,27.7266],"type":"Point"}
}