{
  "type": "Feature",
  "properties": {
    "gn:admin1_code":"12.0",
    "gn:asciiname":"Baojiadang",
    "gn:country_code":"CN",
    "gn:dem":35,
    "gn:feature_class":"P",
    "gn:feature_code":"PPL",
    "gn:name":"Baojiadang",
    "gn:population":0,
    "gn:timezone":"Asia/Shanghai",
    "iso:country":"CN",
    "name:und_x_variant":[
        "\u6797\u5bb6\u57b1"
    ],
    "wof:name":"Baojiadang",
    "wof:placetype":"locality"
},
  "geometry": {"coordinates":[112.03964000000001,30.07204],"type":"Point"}
}