{
  "type": "Feature",
  "properties": {
    "gn:admin1_code":"15.0",
    "gn:asciiname":"Maqiying",
    "gn:country_code":"CN",
    "gn:dem":1886,
    "gn:feature_class":"P",
    "gn:feature_code":"PPL",
    "gn:name":"Maqiying",
    "gn:population":0,
    "gn:timezone":"Asia/Shanghai",
    "iso:country":"CN",
    "name:zho_x_preferred":[
        "\u9ebb\u542f\u8425"
    ],
    "wof:name":"Maqiying",
    "wof:placetype":"locality"
},
  "geometry": {"coordinates":[104.036,35.9321],"type":"Point"}
}