{
  "type": "Feature",
  "properties": {
    "gn:admin1_code":"12.0",
    "gn:asciiname":"Ansigou",
    "gn:country_code":"CN",
    "gn:dem":193,
    "gn:feature_class":"P",
    "gn:feature_code":"PPL",
    "gn:name":"Ansigou",
    "gn:population":0,
    "gn:timezone":"Asia/Shanghai",
    "iso:country":"CN",
    "name:zho_x_preferred":[
        "\u5b89\u5bfa\u6c9f"
    ],
    "wof:name":"Ansigou",
    "wof:placetype":"locality"
},
  "geometry": {"coordinates":[113.10098000000001,32.17858],"type":"Point"}
}