{
  "type": "Feature",
  "properties": {
    "gn:admin1_code":"8.0",
    "gn:asciiname":"Jiangxiaopu",
    "gn:country_code":"CN",
    "gn:dem":206,
    "gn:feature_class":"P",
    "gn:feature_code":"PPL",
    "gn:name":"Jiangxiaopu",
    "gn:population":0,
    "gn:timezone":"Asia/Shanghai",
    "iso:country":"CN",
    "name:zho_x_preferred":[
        "\u59dc\u5c0f\u94fa"
    ],
    "wof:name":"Jiangxiaopu",
    "wof:placetype":"locality"
},
  "geometry": {"coordinates":[126.71448999999998,47.41569000000001],"type":"Point"}
}