{
  "type": "Feature",
  "properties": {
    "gn:admin1_code":"10.0",
    "gn:asciiname":"Futu",
    "gn:country_code":"CN",
    "gn:dem":962,
    "gn:feature_class":"P",
    "gn:feature_code":"PPL",
    "gn:name":"Futu",
    "gn:population":0,
    "gn:timezone":"Asia/Shanghai",
    "iso:country":"CN",
    "name:zho_x_preferred":[
        "\u6d6e\u56fe"
    ],
    "wof:name":"Futu",
    "wof:placetype":"locality"
},
  "geometry": {"coordinates":[114.51242000000001,39.75118],"type":"Point"}
}