{
  "type": "Feature",
  "properties": {
    "gn:country":"CN",
    "gn:fcode":"PPL",
    "gn:pop":61087,
    "iso:country":"CN",
    "name:ceb_x_preferred":[
        "Xifeng"
    ],
    "name:deu_x_preferred":[
        "Xifeng"
    ],
    "name:eus_x_preferred":[
        "Xifeng"
    ],
    "name:fra_x_preferred":[
        "Xifeng"
    ],
    "name:mlg_x_preferred":[
        "Xifeng"
    ],
    "name:nor_x_preferred":[
        "Xifeng"
    ],
    "name:swe_x_preferred":[
        "Xifeng"
    ],
    "name:unk_x_variant":[
        "Sifeng"
    ],
    "qs:name":"Xifeng",
    "qs:photos_9r":0,
    "qs:photos_sr":0,
    "qs:pop_sr":"8",
    "wd:wordcount":51,
    "wof:name":"Xifeng",
    "wof:placetype":"locality",
    "wof:population":61087
},
  "geometry": {"coordinates":[124.72221999999999,42.73722],"type":"Point"}
}