{
  "type": "Feature",
  "properties": {
    "gn:admin1_code":"26.0",
    "gn:asciiname":"Beizhuangzi",
    "gn:country_code":"CN",
    "gn:dem":1172,
    "gn:feature_class":"P",
    "gn:feature_code":"PPL",
    "gn:name":"Beizhuangzi",
    "gn:population":0,
    "gn:timezone":"Asia/Shanghai",
    "iso:country":"CN",
    "name:zho_x_preferred":[
        "\u5317\u5e84\u5b50"
    ],
    "wof:name":"Beizhuangzi",
    "wof:placetype":"locality"
},
  "geometry": {"coordinates":[108.76656,35.6195],"type":"Point"}
}