{
  "type": "Feature",
  "properties": {
    "gn:admin1_code":"15.0",
    "gn:asciiname":"Wayaoxia",
    "gn:country_code":"CN",
    "gn:dem":2344,
    "gn:feature_class":"P",
    "gn:feature_code":"PPL",
    "gn:name":"Wayaoxia",
    "gn:population":0,
    "gn:timezone":"Asia/Shanghai",
    "iso:country":"CN",
    "name:und_x_variant":[
        "\u74e6\u7a91\u4e0b"
    ],
    "wof:name":"Wayaoxia",
    "wof:placetype":"locality"
},
  "geometry": {"coordinates":[104.49142000000001,34.73591],"type":"Point"}
}