{
  "type": "Feature",
  "properties": {
    "gn:admin1_code":"12",
    "gn:asciiname":"Caiyang",
    "gn:cc2":"CN",
    "gn:country_code":"CN",
    "gn:dem":82,
    "gn:feature_class":"P",
    "gn:feature_code":"PPL",
    "gn:name":"Caiyang",
    "gn:population":0,
    "gn:timezone":"Asia/Shanghai",
    "iso:country":"CN",
    "name:und_x_variant":[
        "Ts\u2019ai-yang-p\u2019u",
        "Caiyangpu",
        "Caiyang"
    ],
    "wof:name":"Caiyang",
    "wof:placetype":"locality"
},
  "geometry": {"coordinates":[112.51389,32.08],"type":"Point"}
}