{
  "type": "Feature",
  "properties": {
    "gn:admin1_code":"11.0",
    "gn:asciiname":"Leijiachong",
    "gn:country_code":"CN",
    "gn:dem":126,
    "gn:feature_class":"P",
    "gn:feature_code":"PPL",
    "gn:name":"Leijiachong",
    "gn:population":0,
    "gn:timezone":"Asia/Shanghai",
    "iso:country":"CN",
    "name:zho_x_preferred":[
        "\u96f7\u5bb6\u51b2"
    ],
    "wof:name":"Leijiachong",
    "wof:placetype":"locality"
},
  "geometry": {"coordinates":[112.44934000000001,27.52382],"type":"Point"}
}