{
  "type": "Feature",
  "properties": {
    "gn:admin1_code":"19.0",
    "gn:asciiname":"Baotun Donggou",
    "gn:country_code":"CN",
    "gn:dem":216,
    "gn:feature_class":"P",
    "gn:feature_code":"PPL",
    "gn:name":"Baotun Donggou",
    "gn:population":0,
    "gn:timezone":"Asia/Shanghai",
    "iso:country":"CN",
    "name:zho_x_preferred":[
        "\u9c8d\u5c6f\u4e1c\u6c9f"
    ],
    "wof:name":"Baotun Donggou",
    "wof:placetype":"locality"
},
  "geometry": {"coordinates":[120.373,40.8652],"type":"Point"}
}