{
  "type": "Feature",
  "properties": {
    "gn:admin1_code":"16.0",
    "gn:asciiname":"Tangbiao",
    "gn:country_code":"CN",
    "gn:dem":62,
    "gn:feature_class":"P",
    "gn:feature_code":"PPL",
    "gn:name":"Tangbiao",
    "gn:population":0,
    "gn:timezone":"Asia/Shanghai",
    "iso:country":"CN",
    "name:zho_x_preferred":[
        "\u5858\u8868"
    ],
    "wof:name":"Tangbiao",
    "wof:placetype":"locality"
},
  "geometry": {"coordinates":[109.93000000000001,23.3626],"type":"Point"}
}