{
  "type": "Feature",
  "properties": {
    "gn:admin1_code":"24.0",
    "gn:asciiname":"Gejiapocun",
    "gn:country_code":"CN",
    "gn:dem":1118,
    "gn:feature_class":"P",
    "gn:feature_code":"PPL",
    "gn:name":"Gejiapocun",
    "gn:population":0,
    "gn:timezone":"Asia/Shanghai",
    "iso:country":"CN",
    "name:zho_x_preferred":[
        "\u6208\u5bb6\u5761\u6751"
    ],
    "wof:name":"Gejiapocun",
    "wof:placetype":"locality"
},
  "geometry": {"coordinates":[114.21082,39.49644],"type":"Point"}
}