{
  "type": "Feature",
  "properties": {
    "gn:admin1_code":"2.0",
    "gn:asciiname":"Shitianmen",
    "gn:country_code":"CN",
    "gn:dem":129,
    "gn:feature_class":"P",
    "gn:feature_code":"PPL",
    "gn:name":"Shitianmen",
    "gn:population":0,
    "gn:timezone":"Asia/Shanghai",
    "iso:country":"CN",
    "name:zho_x_preferred":[
        "\u77f3\u5929\u95e8"
    ],
    "wof:name":"Shitianmen",
    "wof:placetype":"locality"
},
  "geometry": {"coordinates":[120.88708,29.48299],"type":"Point"}
}