{
  "type": "Feature",
  "properties": {
    "gn:admin1_code":"29.0",
    "gn:asciiname":"Dawanzi",
    "gn:country_code":"CN",
    "gn:dem":2082,
    "gn:feature_class":"P",
    "gn:feature_code":"PPL",
    "gn:name":"Dawanzi",
    "gn:population":0,
    "gn:timezone":"Asia/Shanghai",
    "iso:country":"CN",
    "name:zho_x_preferred":[
        "\u5927\u5f2f\u5b50"
    ],
    "wof:name":"Dawanzi",
    "wof:placetype":"locality"
},
  "geometry": {"coordinates":[101.331,25.2173],"type":"Point"}
}