{
  "type": "Feature",
  "properties": {
    "gn:admin1_code":"11.0",
    "gn:asciiname":"Xiuyutang",
    "gn:country_code":"CN",
    "gn:dem":379,
    "gn:feature_class":"P",
    "gn:feature_code":"PPL",
    "gn:name":"Xiuyutang",
    "gn:population":0,
    "gn:timezone":"Asia/Shanghai",
    "iso:country":"CN",
    "name:zho_x_preferred":[
        "\u79c0\u9c7c\u5858"
    ],
    "wof:name":"Xiuyutang",
    "wof:placetype":"locality"
},
  "geometry": {"coordinates":[111.55034999999999,24.75003],"type":"Point"}
}