{
  "type": "Feature",
  "properties": {
    "gn:admin1_code":"29.0",
    "gn:asciiname":"Bingmen",
    "gn:country_code":"CN",
    "gn:dem":1182,
    "gn:feature_class":"P",
    "gn:feature_code":"PPL",
    "gn:name":"Bingmen",
    "gn:population":0,
    "gn:timezone":"Asia/Shanghai",
    "iso:country":"CN",
    "name:zho_x_preferred":[
        "\u4e19\u95e8"
    ],
    "wof:name":"Bingmen",
    "wof:placetype":"locality"
},
  "geometry": {"coordinates":[98.655,24.7766],"type":"Point"}
}