{
  "type": "Feature",
  "properties": {
    "gn:admin1_code":"7.0",
    "gn:asciiname":"Liyuan",
    "gn:country_code":"CN",
    "gn:dem":134,
    "gn:feature_class":"P",
    "gn:feature_code":"PPL",
    "gn:name":"Liyuan",
    "gn:population":0,
    "gn:timezone":"Asia/Shanghai",
    "iso:country":"CN",
    "name:ceb_x_preferred":[
        "Liyuan"
    ],
    "name:swe_x_preferred":[
        "Liyuan"
    ],
    "name:zho_x_preferred":[
        "\u674e\u56ed"
    ],
    "wof:name":"Liyuan",
    "wof:placetype":"locality"
},
  "geometry": {"coordinates":[118.37851999999999,27.14908],"type":"Point"}
}