{
  "type": "Feature",
  "properties": {
    "gn:admin1_code":"29.0",
    "gn:asciiname":"Hongtu",
    "gn:country_code":"CN",
    "gn:dem":1293,
    "gn:feature_class":"P",
    "gn:feature_code":"PPL",
    "gn:name":"Hongtu",
    "gn:population":0,
    "gn:timezone":"Asia/Shanghai",
    "iso:country":"CN",
    "name:zho_x_preferred":[
        "\u7ea2\u571f"
    ],
    "wof:name":"Hongtu",
    "wof:placetype":"locality"
},
  "geometry": {"coordinates":[103.32599999999999,23.5761],"type":"Point"}
}