{
  "type": "Feature",
  "properties": {
    "gn:admin1_code":"15.0",
    "gn:asciiname":"Salatu",
    "gn:country_code":"CN",
    "gn:dem":2373,
    "gn:feature_class":"P",
    "gn:feature_code":"PPL",
    "gn:name":"Salatu",
    "gn:population":0,
    "gn:timezone":"Asia/Shanghai",
    "iso:country":"CN",
    "name:zho_x_preferred":[
        "\u6d12\u62c9\u571f"
    ],
    "wof:name":"Salatu",
    "wof:placetype":"locality"
},
  "geometry": {"coordinates":[103.41200000000001,35.6503],"type":"Point"}
}