{
  "type": "Feature",
  "properties": {
    "gn:admin1_code":"7.0",
    "gn:asciiname":"Wangjiaqi",
    "gn:country_code":"CN",
    "gn:dem":1074,
    "gn:feature_class":"P",
    "gn:feature_code":"PPL",
    "gn:name":"Wangjiaqi",
    "gn:population":0,
    "gn:timezone":"Asia/Shanghai",
    "iso:country":"CN",
    "name:zho_x_preferred":[
        "\u6d0b\u5bb6\u78dc"
    ],
    "wof:name":"Wangjiaqi",
    "wof:placetype":"locality"
},
  "geometry": {"coordinates":[117.0445,27.05683],"type":"Point"}
}