{
  "type": "Feature",
  "properties": {
    "gn:admin1_code":"10",
    "gn:asciiname":"Tiaogou",
    "gn:country_code":"CN",
    "gn:dem":391,
    "gn:feature_class":"P",
    "gn:feature_code":"PPL",
    "gn:name":"Tiaogou",
    "gn:population":0,
    "gn:timezone":"Asia/Shanghai",
    "iso:country":"CN",
    "name:zho_x_preferred":[
        "\u8df3\u6c9f"
    ],
    "wof:name":"Tiaogou",
    "wof:placetype":"locality"
},
  "geometry": {"coordinates":[118.19592,40.91163],"type":"Point"}
}