{
  "type": "Feature",
  "properties": {
    "gn:admin1_code":"11",
    "gn:asciiname":"Panshi",
    "gn:cc2":"CN",
    "gn:country_code":"CN",
    "gn:dem":98,
    "gn:feature_class":"P",
    "gn:feature_code":"PPL",
    "gn:name":"Panshi",
    "gn:population":0,
    "gn:timezone":"Asia/Shanghai",
    "iso:country":"CN",
    "name:ara_x_preferred":[
        "\u0628\u0627\u0646\u0634\u0649"
    ],
    "name:ceb_x_preferred":[
        "Panshi Shi"
    ],
    "name:deu_x_preferred":[
        "Panshi"
    ],
    "name:fas_x_preferred":[
        "\u067e\u0627\u0646\u0634\u06cc"
    ],
    "name:fra_x_preferred":[
        "Panshi"
    ],
    "name:heb_x_preferred":[
        "\u05e4\u05e0\u05e9\u05d9"
    ],
    "name:hun_x_preferred":[
        "Panshi"
    ],
    "name:ita_x_preferred":[
        "Panshi"
    ],
    "name:jpn_x_preferred":[
        "\u78d0\u77f3\u5e02"
    ],
    "name:kik_x_preferred":[
        "Panshi"
    ],
    "name:kor_x_preferred":[
        "\ud310\uc2a4\uc2dc"
    ],
    "name:mlg_x_preferred":[
        "Panshi"
    ],
    "name:nor_x_preferred":[
        "Panshi"
    ],
    "name:pol_x_preferred":[
        "Panshi"
    ],
    "name:rus_x_preferred":[
        "\u041f\u0430\u043d\u044c\u0448\u0438"
    ],
    "name:swe_x_preferred":[
        "Panshi"
    ],
    "name:und_x_variant":[
        "Panjiabu"
    ],
    "name:urd_x_preferred":[
        "\u067e\u0627\u0646\u0634\u06cc"
    ],
    "name:vie_x_preferred":[
        "B\u00e0n Th\u1ea1ch"
    ],
    "name:zho_x_preferred":[
        "\u78d0\u77f3\u5e02"
    ],
    "wof:name":"Panshi",
    "wof:placetype":"locality"
},
  "geometry": {"coordinates":[112.04111,26.48889],"type":"Point"}
}