{
  "type": "Feature",
  "properties": {
    "gn:admin1_code":"11",
    "gn:asciiname":"Panshi",
    "gn:cc2":"CN",
    "gn:country_code":"CN",
    "gn:dem":98,
    "gn:feature_class":"P",
    "gn:feature_code":"PPL",
    "gn:name":"Panshi",
    "gn:population":0,
    "gn:timezone":"Asia/Shanghai",
    "iso:country":"CN",
    "name:und_x_variant":[
        "Panjiabu",
        "Panshi"
    ],
    "wof:name":"Panshi",
    "wof:placetype":"locality"
},
  "geometry": {"coordinates":[112.04111,26.48889],"type":"Point"}
}