{
  "type": "Feature",
  "properties": {
    "gn:admin1_code":"2.0",
    "gn:asciiname":"Chijiashan",
    "gn:country_code":"CN",
    "gn:dem":430,
    "gn:feature_class":"P",
    "gn:feature_code":"PPL",
    "gn:name":"Chijiashan",
    "gn:population":0,
    "gn:timezone":"Asia/Shanghai",
    "iso:country":"CN",
    "name:zho_x_preferred":[
        "\u6c60\u5bb6\u5c71"
    ],
    "wof:name":"Chijiashan",
    "wof:placetype":"locality"
},
  "geometry": {"coordinates":[120.25048,29.50731],"type":"Point"}
}