{
  "type": "Feature",
  "properties": {
    "gn:admin1_code":"16.0",
    "gn:asciiname":"Cenqing",
    "gn:country_code":"CN",
    "gn:dem":498,
    "gn:feature_class":"P",
    "gn:feature_code":"PPL",
    "gn:name":"Cenqing",
    "gn:population":0,
    "gn:timezone":"Asia/Shanghai",
    "iso:country":"CN",
    "name:zho_x_preferred":[
        "\u5c91\u6e05"
    ],
    "wof:name":"Cenqing",
    "wof:placetype":"locality"
},
  "geometry": {"coordinates":[107.292,21.8331],"type":"Point"}
}