{
  "type": "Feature",
  "properties": {
    "gn:admin1_code":"19.0",
    "gn:asciiname":"Jijia Daying",
    "gn:country_code":"CN",
    "gn:dem":371,
    "gn:feature_class":"P",
    "gn:feature_code":"PPL",
    "gn:name":"Jijia Daying",
    "gn:population":0,
    "gn:timezone":"Asia/Shanghai",
    "iso:country":"CN",
    "name:und_x_variant":[
        "\u7eaa\u5bb6\u5927\u8425"
    ],
    "wof:name":"Jijia Daying",
    "wof:placetype":"locality"
},
  "geometry": {"coordinates":[124.42891000000002,41.04534],"type":"Point"}
}