{
  "type": "Feature",
  "properties": {
    "gn:admin1_code":"12.0",
    "gn:asciiname":"Wangbian Danwan",
    "gn:country_code":"CN",
    "gn:dem":26,
    "gn:feature_class":"P",
    "gn:feature_code":"PPL",
    "gn:name":"Wangbian Danwan",
    "gn:population":0,
    "gn:timezone":"Asia/Shanghai",
    "iso:country":"CN",
    "name:und_x_variant":[
        "\u738b\u6241\u62c5\u5846"
    ],
    "wof:name":"Wangbian Danwan",
    "wof:placetype":"locality"
},
  "geometry": {"coordinates":[114.19168000000001,30.79115],"type":"Point"}
}