{
  "type": "Feature",
  "properties": {
    "gn:admin1_code":"30",
    "gn:asciiname":"Xujia",
    "gn:cc2":"CN",
    "gn:country_code":"CN",
    "gn:dem":13,
    "gn:feature_class":"P",
    "gn:feature_code":"PPL",
    "gn:name":"Xujia",
    "gn:population":0,
    "gn:timezone":"Asia/Urumqi",
    "iso:country":"CN",
    "name:und_x_variant":[
        "Xujia"
    ],
    "name:zho_x_preferred":[
        "\u8bb8\u5bb6"
    ],
    "name:zho_x_variant":[
        "Hs\u00fc-chia"
    ],
    "wof:name":"Xujia",
    "wof:placetype":"locality"
},
  "geometry": {"coordinates":[109.88500000000001,20.38111],"type":"Point"}
}