{
  "type": "Feature",
  "properties": {
    "gn:admin1_code":"13",
    "gn:asciiname":"Shangmiao'ergou",
    "gn:country_code":"CN",
    "gn:dem":1078,
    "gn:feature_class":"P",
    "gn:feature_code":"PPL",
    "gn:name":"Shangmiao\u2019ergou",
    "gn:population":0,
    "gn:timezone":"Asia/Urumqi",
    "iso:country":"CN",
    "name:und_x_variant":[
        "Shangmiao\u2019ergou"
    ],
    "name:zho_x_preferred":[
        "\u4e0a\u5e99\u5c14\u6c9f"
    ],
    "wof:name":"Shangmiao'ergou",
    "wof:placetype":"locality"
},
  "geometry": {"coordinates":[93.94274,42.89374],"type":"Point"}
}