{
  "type": "Feature",
  "properties": {
    "gn:admin1_code":"7",
    "gn:asciiname":"Kaolong",
    "gn:country_code":"CN",
    "gn:dem":516,
    "gn:feature_class":"P",
    "gn:feature_code":"PPL",
    "gn:name":"Kaolong",
    "gn:population":0,
    "gn:timezone":"Asia/Shanghai",
    "iso:country":"CN",
    "name:zho_x_preferred":[
        "\u8003\u5784"
    ],
    "wof:name":"Kaolong",
    "wof:placetype":"locality"
},
  "geometry": {"coordinates":[118.77909,25.61928],"type":"Point"}
}