{
  "type": "Feature",
  "properties": {
    "gn:admin1_code":"32.0",
    "gn:asciiname":"Yanwu",
    "gn:country_code":"CN",
    "gn:dem":1204,
    "gn:feature_class":"P",
    "gn:feature_code":"PPL",
    "gn:name":"Yanwu",
    "gn:population":0,
    "gn:timezone":"Asia/Shanghai",
    "iso:country":"CN",
    "name:und_x_variant":[
        "\u71d5\u5348"
    ],
    "wof:name":"Yanwu",
    "wof:placetype":"locality"
},
  "geometry": {"coordinates":[106.14203999999999,32.44719],"type":"Point"}
}