{
  "type": "Feature",
  "properties": {
    "gn:admin1_code":"15.0",
    "gn:asciiname":"Zhangtiebu",
    "gn:country_code":"CN",
    "gn:dem":1688,
    "gn:feature_class":"P",
    "gn:feature_code":"PPL",
    "gn:name":"Zhangtiebu",
    "gn:population":0,
    "gn:timezone":"Asia/Shanghai",
    "iso:country":"CN",
    "name:zho_x_preferred":[
        "\u5f20\u94c1\u5821"
    ],
    "wof:name":"Zhangtiebu",
    "wof:placetype":"locality"
},
  "geometry": {"coordinates":[106.887,37.04],"type":"Point"}
}