{
  "type": "Feature",
  "properties": {
    "gn:admin1_code":"32.0",
    "gn:asciiname":"Datian'ao",
    "gn:country_code":"CN",
    "gn:dem":432,
    "gn:feature_class":"P",
    "gn:feature_code":"PPL",
    "gn:name":"Datian\u2019ao",
    "gn:population":0,
    "gn:timezone":"Asia/Shanghai",
    "iso:country":"CN",
    "name:zho_x_preferred":[
        "\u5927\u7530\u5773"
    ],
    "name:zho_x_variant":[
        "Datian\u2019ao"
    ],
    "wof:name":"Datian'ao",
    "wof:placetype":"locality"
},
  "geometry": {"coordinates":[103.9311,29.66646],"type":"Point"}
}