{
  "type": "Feature",
  "properties": {
    "gn:admin1_code":"6.0",
    "gn:asciiname":"Zheluoke",
    "gn:country_code":"CN",
    "gn:dem":3934,
    "gn:feature_class":"P",
    "gn:feature_code":"PPL",
    "gn:name":"Zheluoke",
    "gn:population":0,
    "gn:timezone":"Asia/Urumqi",
    "iso:country":"CN",
    "name:zho_x_preferred":[
        "\u7740\u843d\u53ef"
    ],
    "wof:name":"Zheluoke",
    "wof:placetype":"locality"
},
  "geometry": {"coordinates":[97.28767999999999,32.32618],"type":"Point"}
}