{
  "type": "Feature",
  "properties": {
    "gn:admin1_code":"31.0",
    "gn:asciiname":"Baoyin",
    "gn:country_code":"CN",
    "gn:dem":35,
    "gn:feature_class":"P",
    "gn:feature_code":"PPL",
    "gn:name":"Baoyin",
    "gn:population":0,
    "gn:timezone":"Asia/Shanghai",
    "iso:country":"CN",
    "name:und_x_variant":[
        "\u4fdd\u5f15"
    ],
    "wof:name":"Baoyin",
    "wof:placetype":"locality"
},
  "geometry": {"coordinates":[109.59059000000001,18.34294],"type":"Point"}
}