{
  "type": "Feature",
  "properties": {
    "gn:admin1_code":"7.0",
    "gn:asciiname":"Youmeikeng",
    "gn:country_code":"CN",
    "gn:dem":1025,
    "gn:feature_class":"P",
    "gn:feature_code":"PPL",
    "gn:name":"Youmeikeng",
    "gn:population":0,
    "gn:timezone":"Asia/Shanghai",
    "iso:country":"CN",
    "name:zho_x_preferred":[
        "Youmeikeng"
    ],
    "name:zho_x_variant":[
        "\u6cb9\u6885\u5751"
    ],
    "wof:name":"Youmeikeng",
    "wof:placetype":"locality"
},
  "geometry": {"coordinates":[118.60361,26.71667],"type":"Point"}
}