{
  "type": "Feature",
  "properties": {
    "gn:admin1_code":"8.0",
    "gn:asciiname":"Laodongcun",
    "gn:country_code":"CN",
    "gn:dem":149,
    "gn:feature_class":"P",
    "gn:feature_code":"PPL",
    "gn:name":"Laodongcun",
    "gn:population":0,
    "gn:timezone":"Asia/Shanghai",
    "iso:country":"CN",
    "name:zho_x_preferred":[
        "\u52b3\u52a8\u6751"
    ],
    "wof:name":"Laodongcun",
    "wof:placetype":"locality"
},
  "geometry": {"coordinates":[125.19355,46.24632],"type":"Point"}
}