{
  "type": "Feature",
  "properties": {
    "gn:admin1_code":"8.0",
    "gn:asciiname":"Shengchangcun",
    "gn:country_code":"CN",
    "gn:dem":53,
    "gn:feature_class":"P",
    "gn:feature_code":"PPL",
    "gn:name":"Shengchangcun",
    "gn:population":0,
    "gn:timezone":"Asia/Shanghai",
    "iso:country":"CN",
    "name:zho_x_preferred":[
        "\u80dc\u660c\u6751"
    ],
    "wof:name":"Shengchangcun",
    "wof:placetype":"locality"
},
  "geometry": {"coordinates":[132.55372,47.52281],"type":"Point"}
}