{
  "type": "Feature",
  "properties": {
    "gn:admin1_code":"29.0",
    "gn:asciiname":"Lutang",
    "gn:country_code":"CN",
    "gn:dem":1931,
    "gn:feature_class":"P",
    "gn:feature_code":"PPL",
    "gn:name":"Lutang",
    "gn:population":0,
    "gn:timezone":"Asia/Shanghai",
    "iso:country":"CN",
    "name:zho_x_preferred":[
        "\u9e7f\u5858"
    ],
    "wof:name":"Lutang",
    "wof:placetype":"locality"
},
  "geometry": {"coordinates":[99.69119999999999,24.6562],"type":"Point"}
}