{
  "type": "Feature",
  "properties": {
    "gn:admin1_code":"19.0",
    "gn:asciiname":"Dananpucun",
    "gn:country_code":"CN",
    "gn:dem":2,
    "gn:feature_class":"P",
    "gn:feature_code":"PPL",
    "gn:name":"Dananpucun",
    "gn:population":0,
    "gn:timezone":"Asia/Shanghai",
    "iso:country":"CN",
    "name:zho_x_preferred":[
        "\u5927\u5357\u94fa\u6751"
    ],
    "wof:name":"Dananpucun",
    "wof:placetype":"locality"
},
  "geometry": {"coordinates":[120.40022,40.20215],"type":"Point"}
}