{
  "type": "Feature",
  "properties": {
    "gn:admin1_code":"9",
    "gn:asciiname":"Fengyi",
    "gn:country_code":"CN",
    "gn:dem":116,
    "gn:feature_class":"P",
    "gn:feature_code":"PPL",
    "gn:name":"Fengyi",
    "gn:population":0,
    "gn:timezone":"Asia/Shanghai",
    "iso:country":"CN",
    "name:und_x_variant":[
        "Fengyicun"
    ],
    "name:zho_x_preferred":[
        "\u51af\u7fca"
    ],
    "wof:name":"Fengyi",
    "wof:placetype":"locality"
},
  "geometry": {"coordinates":[112.98963000000001,35.04363],"type":"Point"}
}