{
  "type": "Feature",
  "properties": {
    "gn:admin1_code":"11.0",
    "gn:asciiname":"Xinyintuan",
    "gn:country_code":"CN",
    "gn:dem":335,
    "gn:feature_class":"P",
    "gn:feature_code":"PPL",
    "gn:name":"Xinyintuan",
    "gn:population":0,
    "gn:timezone":"Asia/Shanghai",
    "iso:country":"CN",
    "name:zho_x_preferred":[
        "\u65b0\u97f3\u56e2"
    ],
    "wof:name":"Xinyintuan",
    "wof:placetype":"locality"
},
  "geometry": {"coordinates":[109.66376,26.60905],"type":"Point"}
}