{
  "type": "Feature",
  "properties": {
    "gn:admin1_code":"14",
    "gn:asciiname":"Nazong",
    "gn:country_code":"CN",
    "gn:dem":4729,
    "gn:feature_class":"P",
    "gn:feature_code":"PPL",
    "gn:name":"Nazong",
    "gn:population":0,
    "gn:timezone":"Asia/Urumqi",
    "iso:country":"CN",
    "name:zho_x_preferred":[
        "\u90a3\u5b97"
    ],
    "wof:name":"Nazong",
    "wof:placetype":"locality"
},
  "geometry": {"coordinates":[88.4585,30.9208],"type":"Point"}
}