{
  "type": "Feature",
  "properties": {
    "gn:admin1_code":"1.0",
    "gn:asciiname":"Shimiaocun",
    "gn:country_code":"CN",
    "gn:dem":33,
    "gn:feature_class":"P",
    "gn:feature_code":"PPL",
    "gn:name":"Shimiaocun",
    "gn:population":0,
    "gn:timezone":"Asia/Shanghai",
    "iso:country":"CN",
    "name:und_x_variant":[
        "Shimiao"
    ],
    "name:zho_x_preferred":[
        "\u53f2\u5e99\u6751"
    ],
    "wof:name":"Shimiaocun",
    "wof:placetype":"locality"
},
  "geometry": {"coordinates":[116.28834999999999,33.39162],"type":"Point"}
}