{
  "type": "Feature",
  "properties": {
    "gn:admin1_code":"4.0",
    "gn:asciiname":"Yudai",
    "gn:country_code":"CN",
    "gn:dem":8,
    "gn:feature_class":"P",
    "gn:feature_code":"PPLA4",
    "gn:name":"Yudai",
    "gn:population":0,
    "gn:timezone":"Asia/Shanghai",
    "iso:country":"CN",
    "name:und_x_variant":[
        "\u7389\u5e26",
        "Yudai Zhen"
    ],
    "name:zho_x_preferred":[
        "\u7389\u5e26\u9547"
    ],
    "wof:name":"Yudai",
    "wof:placetype":"locality"
},
  "geometry": {"coordinates":[118.90309999999999,32.2259],"type":"Point"}
}