{
  "type": "Feature",
  "properties": {
    "gn:admin1_code":"13.0",
    "gn:asciiname":"Tijikecaozhan",
    "gn:country_code":"CN",
    "gn:dem":2080,
    "gn:feature_class":"P",
    "gn:feature_code":"PPL",
    "gn:name":"Tijikecaozhan",
    "gn:population":0,
    "gn:timezone":"Asia/Shanghai",
    "iso:country":"CN",
    "name:zho_x_preferred":[
        "\u63d0\u5409\u514b\u8349\u7ad9"
    ],
    "wof:name":"Tijikecaozhan",
    "wof:placetype":"locality"
},
  "geometry": {"coordinates":[81.96992,36.57787],"type":"Point"}
}