{
  "type": "Feature",
  "properties": {
    "gn:admin1_code":"30.0",
    "gn:asciiname":"Luopu",
    "gn:country_code":"CN",
    "gn:dem":0,
    "gn:feature_class":"P",
    "gn:feature_code":"PPLA4",
    "gn:name":"Luopu",
    "gn:population":0,
    "gn:timezone":"Asia/Shanghai",
    "iso:country":"CN",
    "name:und_x_variant":[
        "Luopu Jiedao"
    ],
    "name:zho_x_preferred":[
        "\u6d1b\u6d66"
    ],
    "name:zho_x_variant":[
        "\u6d1b\u6d66\u8857\u9053"
    ],
    "wof:name":"Luopu",
    "wof:placetype":"locality"
},
  "geometry": {"coordinates":[113.29022999999999,23.0432],"type":"Point"}
}