{
  "type": "Feature",
  "properties": {
    "gn:admin1_code":"25",
    "gn:asciiname":"Zhuangjia",
    "gn:country_code":"CN",
    "gn:dem":17,
    "gn:feature_class":"P",
    "gn:feature_code":"PPL",
    "gn:name":"Zhuangjia",
    "gn:population":0,
    "gn:timezone":"Asia/Shanghai",
    "iso:country":"CN",
    "name:zho_x_preferred":[
        "\u5e84\u5bb6"
    ],
    "wof:name":"Zhuangjia",
    "wof:placetype":"locality"
},
  "geometry": {"coordinates":[117.68899999999999,37.1181],"type":"Point"}
}