{
  "type": "Feature",
  "properties": {
    "gn:admin1_code":"32.0",
    "gn:asciiname":"Longtuogeng",
    "gn:country_code":"CN",
    "gn:dem":419,
    "gn:feature_class":"P",
    "gn:feature_code":"PPL",
    "gn:name":"Longtuogeng",
    "gn:population":0,
    "gn:timezone":"Asia/Shanghai",
    "iso:country":"CN",
    "name:zho_x_preferred":[
        "\u9f99\u62d6\u57c2"
    ],
    "wof:name":"Longtuogeng",
    "wof:placetype":"locality"
},
  "geometry": {"coordinates":[103.866,29.1181],"type":"Point"}
}