{
  "type": "Feature",
  "properties": {
    "gn:admin1_code":"3.0",
    "gn:asciiname":"Hanshan",
    "gn:country_code":"CN",
    "gn:dem":148,
    "gn:feature_class":"P",
    "gn:feature_code":"PPL",
    "gn:name":"Hanshan",
    "gn:population":0,
    "gn:timezone":"Asia/Shanghai",
    "iso:country":"CN",
    "name:ceb_x_preferred":[
        "Hanshan"
    ],
    "name:deu_x_preferred":[
        "Hanshan"
    ],
    "name:fra_x_preferred":[
        "Hanshan"
    ],
    "name:nor_x_preferred":[
        "Hanshan"
    ],
    "name:spa_x_preferred":[
        "Hanshan"
    ],
    "name:und_x_variant":[
        "\u6c49\u5c71"
    ],
    "wof:name":"Hanshan",
    "wof:placetype":"locality"
},
  "geometry": {"coordinates":[114.101,27.0264],"type":"Point"}
}