{
  "type": "Feature",
  "properties": {
    "gn:admin1_code":"11",
    "gn:asciiname":"Wenshuilong",
    "gn:country_code":"CN",
    "gn:dem":587,
    "gn:feature_class":"P",
    "gn:feature_code":"PPL",
    "gn:name":"Wenshuilong",
    "gn:population":0,
    "gn:timezone":"Asia/Shanghai",
    "iso:country":"CN",
    "name:zho_x_preferred":[
        "\u6e29\u6c34\u5784"
    ],
    "wof:name":"Wenshuilong",
    "wof:placetype":"locality"
},
  "geometry": {"coordinates":[109.68889,27.59392],"type":"Point"}
}