{
  "type": "Feature",
  "properties": {
    "gn:admin1_code":"25.0",
    "gn:asciiname":"Yanggezhuang",
    "gn:country_code":"CN",
    "gn:dem":22,
    "gn:feature_class":"P",
    "gn:feature_code":"PPL",
    "gn:name":"Yanggezhuang",
    "gn:population":0,
    "gn:timezone":"Asia/Shanghai",
    "iso:country":"CN",
    "name:zho_x_preferred":[
        "\u6768\u683c\u5e84"
    ],
    "wof:name":"Yanggezhuang",
    "wof:placetype":"locality"
},
  "geometry": {"coordinates":[120.68789,36.69035],"type":"Point"}
}