{
  "type": "Feature",
  "properties": {
    "gn:admin1_code":"8.0",
    "gn:asciiname":"Xihulecun",
    "gn:country_code":"CN",
    "gn:dem":143,
    "gn:feature_class":"P",
    "gn:feature_code":"PPL",
    "gn:name":"Xihulecun",
    "gn:population":0,
    "gn:timezone":"Asia/Shanghai",
    "iso:country":"CN",
    "name:zho_x_preferred":[
        "\u897f\u80e1\u52d2\u6751"
    ],
    "wof:name":"Xihulecun",
    "wof:placetype":"locality"
},
  "geometry": {"coordinates":[123.66764000000001,46.61898],"type":"Point"}
}