{
  "type": "Feature",
  "properties": {
    "gn:admin1_code":"26.0",
    "gn:asciiname":"Wangcuncun",
    "gn:country_code":"CN",
    "gn:dem":717,
    "gn:feature_class":"P",
    "gn:feature_code":"PPL",
    "gn:name":"Wangcuncun",
    "gn:population":0,
    "gn:timezone":"Asia/Shanghai",
    "iso:country":"CN",
    "name:zho_x_preferred":[
        "\u738b\u6751\u6751"
    ],
    "wof:name":"Wangcuncun",
    "wof:placetype":"locality"
},
  "geometry": {"coordinates":[110.24214000000001,35.52426],"type":"Point"}
}