{
  "type": "Feature",
  "properties": {
    "gn:admin1_code":"32.0",
    "gn:asciiname":"Gari",
    "gn:country_code":"CN",
    "gn:dem":1446,
    "gn:feature_class":"P",
    "gn:feature_code":"PPL",
    "gn:name":"Gari",
    "gn:population":0,
    "gn:timezone":"Asia/Shanghai",
    "iso:country":"CN",
    "name:bul_x_preferred":[
        "\u0413\u0430\u0440\u0438"
    ],
    "name:ceb_x_preferred":[
        "Gari"
    ],
    "name:deu_x_preferred":[
        "Gari"
    ],
    "name:eus_x_preferred":[
        "Gari"
    ],
    "name:fra_x_preferred":[
        "Gari"
    ],
    "name:ita_x_preferred":[
        "Gari"
    ],
    "name:jpn_x_preferred":[
        "\u30ac\u30ea"
    ],
    "name:nld_x_preferred":[
        "Gari"
    ],
    "name:por_x_preferred":[
        "Gari"
    ],
    "name:rus_x_preferred":[
        "\u0413\u0430\u0440\u0438"
    ],
    "name:spa_x_preferred":[
        "Gari"
    ],
    "name:srp_x_preferred":[
        "\u0413\u0430\u0440\u0438"
    ],
    "name:swe_x_preferred":[
        "Gari"
    ],
    "name:ukr_x_preferred":[
        "\u0413\u0430\u0440\u0456"
    ],
    "name:vie_x_preferred":[
        "Gari"
    ],
    "name:zho_x_preferred":[
        "\u560e\u65e5"
    ],
    "wof:name":"Gari",
    "wof:placetype":"locality"
},
  "geometry": {"coordinates":[102.68701,28.87888],"type":"Point"}
}