{
  "type": "Feature",
  "properties": {
    "gn:admin1_code":"4.0",
    "gn:asciiname":"Kuahe",
    "gn:country_code":"CN",
    "gn:dem":10,
    "gn:feature_class":"P",
    "gn:feature_code":"PPL",
    "gn:name":"Kuahe",
    "gn:population":0,
    "gn:timezone":"Asia/Shanghai",
    "iso:country":"CN",
    "name:zho_x_preferred":[
        "Kuahe"
    ],
    "name:zho_x_variant":[
        "\u8de8\u6cb3"
    ],
    "wof:name":"Kuahe",
    "wof:placetype":"locality"
},
  "geometry": {"coordinates":[119.11078999999999,33.81034],"type":"Point"}
}