{
  "type": "Feature",
  "properties": {
    "gn:admin1_code":"33.0",
    "gn:asciiname":"Shanwangdong",
    "gn:country_code":"CN",
    "gn:dem":1467,
    "gn:feature_class":"P",
    "gn:feature_code":"PPL",
    "gn:name":"Shanwangdong",
    "gn:population":0,
    "gn:timezone":"Asia/Shanghai",
    "iso:country":"CN",
    "name:zho_x_preferred":[
        "\u5c71\u738b\u6d1e"
    ],
    "wof:name":"Shanwangdong",
    "wof:placetype":"locality"
},
  "geometry": {"coordinates":[107.96444,29.60712],"type":"Point"}
}