{
  "type": "Feature",
  "properties": {
    "gn:admin1_code":"16.0",
    "gn:asciiname":"Qinlian",
    "gn:country_code":"CN",
    "gn:dem":231,
    "gn:feature_class":"P",
    "gn:feature_code":"PPL",
    "gn:name":"Qinlian",
    "gn:population":0,
    "gn:timezone":"Asia/Shanghai",
    "iso:country":"CN",
    "name:zho_x_preferred":[
        "\u94a6\u8054"
    ],
    "wof:name":"Qinlian",
    "wof:placetype":"locality"
},
  "geometry": {"coordinates":[107.056,22.6177],"type":"Point"}
}