{
  "type": "Feature",
  "properties": {
    "gn:admin1_code":"18",
    "gn:asciiname":"Wentanggou",
    "gn:country_code":"CN",
    "gn:dem":1030,
    "gn:feature_class":"P",
    "gn:feature_code":"PPL",
    "gn:name":"Wentanggou",
    "gn:population":0,
    "gn:timezone":"Asia/Shanghai",
    "iso:country":"CN",
    "name:zho_x_preferred":[
        "\u6e29\u5858\u6c9f"
    ],
    "wof:name":"Wentanggou",
    "wof:placetype":"locality"
},
  "geometry": {"coordinates":[106.32899999999999,28.4375],"type":"Point"}
}