{
  "type": "Feature",
  "properties": {
    "gn:admin1_code":"29.0",
    "gn:asciiname":"Yalachong",
    "gn:country_code":"CN",
    "gn:dem":1639,
    "gn:feature_class":"P",
    "gn:feature_code":"PPL",
    "gn:name":"Yalachong",
    "gn:population":0,
    "gn:timezone":"Asia/Shanghai",
    "iso:country":"CN",
    "name:zho_x_preferred":[
        "\u4e9a\u62c9\u51b2"
    ],
    "wof:name":"Yalachong",
    "wof:placetype":"locality"
},
  "geometry": {"coordinates":[103.76600000000001,23.5361],"type":"Point"}
}