{
  "type": "Feature",
  "properties": {
    "gn:admin1_code":"12.0",
    "gn:asciiname":"Yangfuling",
    "gn:country_code":"CN",
    "gn:dem":665,
    "gn:feature_class":"P",
    "gn:feature_code":"PPL",
    "gn:name":"Yangfuling",
    "gn:population":0,
    "gn:timezone":"Asia/Shanghai",
    "iso:country":"CN",
    "name:zho_x_preferred":[
        "\u6768\u5bcc\u5cad"
    ],
    "wof:name":"Yangfuling",
    "wof:placetype":"locality"
},
  "geometry": {"coordinates":[111.57595000000001,31.7516],"type":"Point"}
}