{
  "type": "Feature",
  "properties": {
    "gn:admin1_code":"14.0",
    "gn:asciiname":"Gang'ane",
    "gn:country_code":"CN",
    "gn:dem":4321,
    "gn:feature_class":"P",
    "gn:feature_code":"PPL",
    "gn:name":"Gang\u2019ane",
    "gn:population":0,
    "gn:timezone":"Asia/Urumqi",
    "iso:country":"CN",
    "name:und_x_variant":[
        "Gang\u2019ane"
    ],
    "name:zho_x_preferred":[
        "\u5c97\u554a\u5462"
    ],
    "wof:name":"Gang'ane",
    "wof:placetype":"locality"
},
  "geometry": {"coordinates":[91.21841000000001,29.08506],"type":"Point"}
}