{
  "type": "Feature",
  "properties": {
    "gn:admin1_code":"12.0",
    "gn:asciiname":"Shanglijiapo",
    "gn:country_code":"CN",
    "gn:dem":84,
    "gn:feature_class":"P",
    "gn:feature_code":"PPL",
    "gn:name":"Shanglijiapo",
    "gn:population":0,
    "gn:timezone":"Asia/Shanghai",
    "iso:country":"CN",
    "name:zho_x_preferred":[
        "\u4e0a\u674e\u5bb6\u5761"
    ],
    "wof:name":"Shanglijiapo",
    "wof:placetype":"locality"
},
  "geometry": {"coordinates":[112.15768,31.35137000000001],"type":"Point"}
}