{
  "type": "Feature",
  "properties": {
    "gn:admin1_code":"8.0",
    "gn:asciiname":"Liufeng",
    "gn:country_code":"CN",
    "gn:dem":473,
    "gn:feature_class":"P",
    "gn:feature_code":"PPL",
    "gn:name":"Liufeng",
    "gn:population":0,
    "gn:timezone":"Asia/Shanghai",
    "iso:country":"CN",
    "name:und_x_variant":[
        "\u516d\u5cf0"
    ],
    "wof:name":"Liufeng",
    "wof:placetype":"locality"
},
  "geometry": {"coordinates":[130.18194,44.11817],"type":"Point"}
}