{
  "type": "Feature",
  "properties": {
    "gn:admin1_code":"3.0",
    "gn:asciiname":"Yuchikeng",
    "gn:country_code":"CN",
    "gn:dem":25,
    "gn:feature_class":"P",
    "gn:feature_code":"PPL",
    "gn:name":"Yuchikeng",
    "gn:population":0,
    "gn:timezone":"Asia/Shanghai",
    "iso:country":"CN",
    "name:und_x_variant":[
        "\u9c7c\u6c60\u5751"
    ],
    "wof:name":"Yuchikeng",
    "wof:placetype":"locality"
},
  "geometry": {"coordinates":[116.46192000000001,28.44998],"type":"Point"}
}