{
  "type": "Feature",
  "properties": {
    "gn:admin1_code":"29.0",
    "gn:asciiname":"Banlang Zhongzhai",
    "gn:country_code":"CN",
    "gn:dem":1373,
    "gn:feature_class":"P",
    "gn:feature_code":"PPL",
    "gn:name":"Banlang Zhongzhai",
    "gn:population":0,
    "gn:timezone":"Asia/Shanghai",
    "iso:country":"CN",
    "name:zho_x_preferred":[
        "\u677f\u6994\u4e2d\u5be8"
    ],
    "wof:name":"Banlang Zhongzhai",
    "wof:placetype":"locality"
},
  "geometry": {"coordinates":[104.616,23.553],"type":"Point"}
}