{
  "type": "Feature",
  "properties": {
    "gn:admin1_code":"29.0",
    "gn:asciiname":"Jiarong",
    "gn:country_code":"CN",
    "gn:dem":1805,
    "gn:feature_class":"P",
    "gn:feature_code":"PPL",
    "gn:name":"Jiarong",
    "gn:population":0,
    "gn:timezone":"Asia/Shanghai",
    "iso:country":"CN",
    "name:zho_x_preferred":[
        "\u67b6\u8363"
    ],
    "wof:name":"Jiarong",
    "wof:placetype":"locality"
},
  "geometry": {"coordinates":[104.07899999999999,24.5755],"type":"Point"}
}