{
  "type": "Feature",
  "properties": {
    "gn:admin1_code":"3.0",
    "gn:asciiname":"Longxingcun",
    "gn:country_code":"CN",
    "gn:dem":347,
    "gn:feature_class":"P",
    "gn:feature_code":"PPL",
    "gn:name":"Longxingcun",
    "gn:population":0,
    "gn:timezone":"Asia/Shanghai",
    "iso:country":"CN",
    "name:und_x_variant":[
        "\u9f99\u5174\u6751"
    ],
    "wof:name":"Longxingcun",
    "wof:placetype":"locality"
},
  "geometry": {"coordinates":[115.82058000000001,26.51405],"type":"Point"}
}