{
  "type": "Feature",
  "properties": {
    "gn:admin1_code":"7",
    "gn:asciiname":"Ma'an",
    "gn:country_code":"CN",
    "gn:dem":195,
    "gn:feature_class":"P",
    "gn:feature_code":"PPL",
    "gn:name":"Ma\u2019an",
    "gn:population":0,
    "gn:timezone":"Asia/Shanghai",
    "iso:country":"CN",
    "name:und_x_variant":[
        "Ma\u2019an",
        "\u9a6c\u5b89"
    ],
    "wof:name":"Ma'an",
    "wof:placetype":"locality"
},
  "geometry": {"coordinates":[118.60138999999999,27.13361],"type":"Point"}
}