{
  "type": "Feature",
  "properties": {
    "gn:admin1_code":"29.0",
    "gn:asciiname":"Shangdaqiao",
    "gn:country_code":"CN",
    "gn:dem":2081,
    "gn:feature_class":"P",
    "gn:feature_code":"PPL",
    "gn:name":"Shangdaqiao",
    "gn:population":0,
    "gn:timezone":"Asia/Shanghai",
    "iso:country":"CN",
    "name:zho_x_preferred":[
        "\u4e0a\u5927\u6865"
    ],
    "wof:name":"Shangdaqiao",
    "wof:placetype":"locality"
},
  "geometry": {"coordinates":[103.797,25.9248],"type":"Point"}
}