{
  "type": "Feature",
  "properties": {
    "gn:admin1_code":"26.0",
    "gn:asciiname":"Caojiazhaicun",
    "gn:country_code":"CN",
    "gn:dem":393,
    "gn:feature_class":"P",
    "gn:feature_code":"PPL",
    "gn:name":"Caojiazhaicun",
    "gn:population":0,
    "gn:timezone":"Asia/Shanghai",
    "iso:country":"CN",
    "name:zho_x_preferred":[
        "\u66f9\u5bb6\u5be8\u6751"
    ],
    "wof:name":"Caojiazhaicun",
    "wof:placetype":"locality"
},
  "geometry": {"coordinates":[108.67946000000001,34.29813],"type":"Point"}
}