{
  "type": "Feature",
  "properties": {
    "gn:admin1_code":"15.0",
    "gn:asciiname":"Ni'erdao",
    "gn:country_code":"CN",
    "gn:dem":3404,
    "gn:feature_class":"P",
    "gn:feature_code":"PPL",
    "gn:name":"Ni\u2019erdao",
    "gn:population":0,
    "gn:timezone":"Asia/Shanghai",
    "iso:country":"CN",
    "name:und_x_variant":[
        "Ni\u2019erdao"
    ],
    "name:zho_x_preferred":[
        "\u5c3c\u5c14\u5230"
    ],
    "wof:name":"Ni'erdao",
    "wof:placetype":"locality"
},
  "geometry": {"coordinates":[102.73699999999999,37.054],"type":"Point"}
}