{
  "type": "Feature",
  "properties": {
    "gn:admin1_code":"16.0",
    "gn:asciiname":"Shipailing",
    "gn:country_code":"CN",
    "gn:dem":193,
    "gn:feature_class":"P",
    "gn:feature_code":"PPL",
    "gn:name":"Shipailing",
    "gn:population":0,
    "gn:timezone":"Asia/Shanghai",
    "iso:country":"CN",
    "name:zho_x_preferred":[
        "\u77f3\u6392\u5cad"
    ],
    "wof:name":"Shipailing",
    "wof:placetype":"locality"
},
  "geometry": {"coordinates":[110.88800000000001,24.8391],"type":"Point"}
}