{
  "type": "Feature",
  "properties": {
    "gn:admin1_code":"5.0",
    "gn:asciiname":"Fushengcun",
    "gn:country_code":"CN",
    "gn:dem":138,
    "gn:feature_class":"P",
    "gn:feature_code":"PPL",
    "gn:name":"Fushengcun",
    "gn:population":0,
    "gn:timezone":"Asia/Shanghai",
    "iso:country":"CN",
    "name:zho_x_preferred":[
        "\u5bcc\u80dc\u6751"
    ],
    "wof:name":"Fushengcun",
    "wof:placetype":"locality"
},
  "geometry": {"coordinates":[123.58632,45.67977],"type":"Point"}
}