{
  "type": "Feature",
  "properties": {
    "gn:admin1_code":"12.0",
    "gn:asciiname":"Zhujiashan",
    "gn:country_code":"CN",
    "gn:dem":278,
    "gn:feature_class":"P",
    "gn:feature_code":"PPL",
    "gn:name":"Zhujiashan",
    "gn:population":0,
    "gn:timezone":"Asia/Shanghai",
    "iso:country":"CN",
    "name:zho_x_preferred":[
        "Zhujiashan"
    ],
    "name:zho_x_variant":[
        "\u6731\u5bb6\u5c71"
    ],
    "wof:name":"Zhujiashan",
    "wof:placetype":"locality"
},
  "geometry": {"coordinates":[115.10639999999999,30.90519],"type":"Point"}
}