{
  "type": "Feature",
  "properties": {
    "gn:admin1_code":"25.0",
    "gn:asciiname":"Shagou Dongcun",
    "gn:country_code":"CN",
    "gn:dem":54,
    "gn:feature_class":"P",
    "gn:feature_code":"PPL",
    "gn:name":"Shagou Dongcun",
    "gn:population":0,
    "gn:timezone":"Asia/Shanghai",
    "iso:country":"CN",
    "name:zho_x_preferred":[
        "\u6c99\u6c9f\u4e1c\u6751"
    ],
    "wof:name":"Shagou Dongcun",
    "wof:placetype":"locality"
},
  "geometry": {"coordinates":[120.00051999999999,36.01456],"type":"Point"}
}