{
  "type": "Feature",
  "properties": {
    "gn:admin1_code":"14.0",
    "gn:asciiname":"Ciugar",
    "gn:country_code":"CN",
    "gn:dem":5288,
    "gn:feature_class":"P",
    "gn:feature_code":"PPL",
    "gn:name":"Ciugar",
    "gn:population":0,
    "gn:timezone":"Asia/Urumqi",
    "iso:country":"CN",
    "name:bod_x_preferred":[
        "Ciugar"
    ],
    "name:zho_x_preferred":[
        "Cuiga"
    ],
    "name:zho_x_variant":[
        "\u7fe0\u560e",
        "Azha Qu",
        "\u963f\u624e\u533a"
    ],
    "wof:name":"Ciugar",
    "wof:placetype":"locality"
},
  "geometry": {"coordinates":[93.202,30.602],"type":"Point"}
}