{
  "type": "Feature",
  "properties": {
    "gn:admin1_code":"9.0",
    "gn:asciiname":"Daqinzhai",
    "gn:country_code":"CN",
    "gn:dem":49,
    "gn:feature_class":"P",
    "gn:feature_code":"PPL",
    "gn:name":"Daqinzhai",
    "gn:population":0,
    "gn:timezone":"Asia/Shanghai",
    "iso:country":"CN",
    "name:zho_x_preferred":[
        "\u5927\u79e6\u5be8"
    ],
    "wof:name":"Daqinzhai",
    "wof:placetype":"locality"
},
  "geometry": {"coordinates":[114.68331000000001,33.1394],"type":"Point"}
}