{
  "type": "Feature",
  "properties": {
    "gn:admin1_code":"9",
    "gn:asciiname":"Zhengzhai",
    "gn:country_code":"CN",
    "gn:dem":62,
    "gn:feature_class":"P",
    "gn:feature_code":"PPL",
    "gn:name":"Zhengzhai",
    "gn:population":0,
    "gn:timezone":"Asia/Shanghai",
    "iso:country":"CN",
    "name:zho_x_preferred":[
        "\u90d1\u5be8"
    ],
    "wof:name":"Zhengzhai",
    "wof:placetype":"locality"
},
  "geometry": {"coordinates":[114.992,34.5832],"type":"Point"}
}