{
  "type": "Feature",
  "properties": {
    "gn:admin1_code":"1.0",
    "gn:asciiname":"Ruijicun",
    "gn:country_code":"CN",
    "gn:dem":24,
    "gn:feature_class":"P",
    "gn:feature_code":"PPL",
    "gn:name":"Ruijicun",
    "gn:population":0,
    "gn:timezone":"Asia/Shanghai",
    "iso:country":"CN",
    "name:zho_x_preferred":[
        "\u82ae\u96c6\u6751"
    ],
    "wof:name":"Ruijicun",
    "wof:placetype":"locality"
},
  "geometry": {"coordinates":[116.70417999999999,32.74685],"type":"Point"}
}