{
  "type": "Feature",
  "properties": {
    "gn:admin1_code":"24.0",
    "gn:asciiname":"Xituoliang",
    "gn:country_code":"CN",
    "gn:dem":1618,
    "gn:feature_class":"P",
    "gn:feature_code":"PPL",
    "gn:name":"Xituoliang",
    "gn:population":0,
    "gn:timezone":"Asia/Shanghai",
    "iso:country":"CN",
    "name:und_x_variant":[
        "\u897f\u9a7c\u6881"
    ],
    "wof:name":"Xituoliang",
    "wof:placetype":"locality"
},
  "geometry": {"coordinates":[112.15989999999999,39.39419],"type":"Point"}
}