{
  "type": "Feature",
  "properties": {
    "gn:admin1_code":"32.0",
    "gn:asciiname":"Dajiao",
    "gn:country_code":"CN",
    "gn:dem":2186,
    "gn:feature_class":"P",
    "gn:feature_code":"PPL",
    "gn:name":"Dajiao",
    "gn:population":0,
    "gn:timezone":"Asia/Shanghai",
    "iso:country":"CN",
    "name:zho_x_preferred":[
        "\u8fbe\u811a"
    ],
    "wof:name":"Dajiao",
    "wof:placetype":"locality"
},
  "geometry": {"coordinates":[102.494,28.4607],"type":"Point"}
}