{
  "type": "Feature",
  "properties": {
    "gn:admin1_code":"24.0",
    "gn:asciiname":"Chijiata",
    "gn:country_code":"CN",
    "gn:dem":1296,
    "gn:feature_class":"P",
    "gn:feature_code":"PPL",
    "gn:name":"Chijiata",
    "gn:population":0,
    "gn:timezone":"Asia/Shanghai",
    "iso:country":"CN",
    "name:zho_x_preferred":[
        "\u6c60\u5bb6\u5854"
    ],
    "wof:name":"Chijiata",
    "wof:placetype":"locality"
},
  "geometry": {"coordinates":[111.66979000000001,39.56714],"type":"Point"}
}