{
  "type": "Feature",
  "properties": {
    "gn:admin1_code":"9.0",
    "gn:asciiname":"Dache Dongcun",
    "gn:country_code":"CN",
    "gn:dem":68,
    "gn:feature_class":"P",
    "gn:feature_code":"PPL",
    "gn:name":"Dache Dongcun",
    "gn:population":0,
    "gn:timezone":"Asia/Shanghai",
    "iso:country":"CN",
    "name:zho_x_preferred":[
        "\u5927\u8f66\u4e1c\u6751"
    ],
    "wof:name":"Dache Dongcun",
    "wof:placetype":"locality"
},
  "geometry": {"coordinates":[114.67796,35.08467],"type":"Point"}
}