{
  "type": "Feature",
  "properties": {
    "gn:admin1_code":"12.0",
    "gn:asciiname":"zuijiazui",
    "gn:country_code":"CN",
    "gn:dem":30,
    "gn:feature_class":"P",
    "gn:feature_code":"PPL",
    "gn:name":"zuijiazui",
    "gn:population":0,
    "gn:timezone":"Asia/Shanghai",
    "iso:country":"CN",
    "name:zho_x_preferred":[
        "\u97a0\u5bb6\u5480"
    ],
    "wof:name":"zuijiazui",
    "wof:placetype":"locality"
},
  "geometry": {"coordinates":[114.30274,30.74107],"type":"Point"}
}