{
  "type": "Feature",
  "properties": {
    "gn:admin1_code":"18.0",
    "gn:asciiname":"Jiaonong",
    "gn:country_code":"CN",
    "gn:dem":833,
    "gn:feature_class":"P",
    "gn:feature_code":"PPL",
    "gn:name":"Jiaonong",
    "gn:population":0,
    "gn:timezone":"Asia/Shanghai",
    "iso:country":"CN",
    "name:zho_x_preferred":[
        "\u4ea4\u519c"
    ],
    "wof:name":"Jiaonong",
    "wof:placetype":"locality"
},
  "geometry": {"coordinates":[107.81100000000001,25.791],"type":"Point"}
}