{
  "type": "Feature",
  "properties": {
    "gn:admin1_code":"33",
    "gn:asciiname":"Huangjia",
    "gn:country_code":"CN",
    "gn:dem":585,
    "gn:feature_class":"P",
    "gn:feature_code":"PPLA4",
    "gn:name":"Huangjia",
    "gn:population":0,
    "gn:timezone":"Asia/Shanghai",
    "iso:country":"CN",
    "name:und_x_variant":[
        "Huangjia Zhen",
        "Shangyanxi"
    ],
    "name:zho_x_preferred":[
        "\u9ec4\u5bb6"
    ],
    "name:zho_x_variant":[
        "\u9ec4\u5bb6\u9547",
        "\u4e0a\u5ca9\u897f"
    ],
    "wof:name":"Huangjia",
    "wof:placetype":"locality"
},
  "geometry": {"coordinates":[108.05694,29.12396],"type":"Point"}
}