{
  "type": "Feature",
  "properties": {
    "gn:admin1_code":"19.0",
    "gn:asciiname":"Choulitou",
    "gn:country_code":"CN",
    "gn:dem":578,
    "gn:feature_class":"P",
    "gn:feature_code":"PPL",
    "gn:name":"Choulitou",
    "gn:population":0,
    "gn:timezone":"Asia/Shanghai",
    "iso:country":"CN",
    "name:zho_x_preferred":[
        "\u81ed\u674e\u5934"
    ],
    "wof:name":"Choulitou",
    "wof:placetype":"locality"
},
  "geometry": {"coordinates":[125.002,41.2262],"type":"Point"}
}