{
  "type": "Feature",
  "properties": {
    "gn:admin1_code":"19.0",
    "gn:asciiname":"Shangjiatun",
    "gn:country_code":"CN",
    "gn:dem":118,
    "gn:feature_class":"P",
    "gn:feature_code":"PPL",
    "gn:name":"Shangjiatun",
    "gn:population":0,
    "gn:timezone":"Asia/Shanghai",
    "iso:country":"CN",
    "name:zho_x_preferred":[
        "\u5546\u5bb6\u5c6f"
    ],
    "wof:name":"Shangjiatun",
    "wof:placetype":"locality"
},
  "geometry": {"coordinates":[121.55409,41.68878],"type":"Point"}
}