{
  "type": "Feature",
  "properties": {
    "gn:admin1_code":"11.0",
    "gn:asciiname":"Yatangpu",
    "gn:country_code":"CN",
    "gn:dem":97,
    "gn:feature_class":"P",
    "gn:feature_code":"PPL",
    "gn:name":"Yatangpu",
    "gn:population":0,
    "gn:timezone":"Asia/Shanghai",
    "iso:country":"CN",
    "wof:name":"Yatangpu",
    "wof:placetype":"locality"
},
  "geometry": {"coordinates":[113.25,27.06667],"type":"Point"}
}