{
  "type": "Feature",
  "properties": {
    "gn:admin1_code":"31",
    "gn:asciiname":"Luowang",
    "gn:country_code":"CN",
    "gn:dem":70,
    "gn:feature_class":"P",
    "gn:feature_code":"PPL",
    "gn:name":"Luowang",
    "gn:population":0,
    "gn:timezone":"Asia/Shanghai",
    "iso:country":"CN",
    "name:und_x_variant":[
        "Lo-wang",
        "Luowang",
        "\u7f57\u65fa"
    ],
    "wof:name":"Luowang",
    "wof:placetype":"locality"
},
  "geometry": {"coordinates":[108.78100000000001,19.0218],"type":"Point"}
}