{
  "type": "Feature",
  "properties": {
    "gn:admin1_code":"29.0",
    "gn:asciiname":"Dongyao Shangzhai",
    "gn:country_code":"CN",
    "gn:dem":1429,
    "gn:feature_class":"P",
    "gn:feature_code":"PPL",
    "gn:name":"Dongyao Shangzhai",
    "gn:population":0,
    "gn:timezone":"Asia/Shanghai",
    "iso:country":"CN",
    "name:zho_x_preferred":[
        "\u4e1c\u5e7a\u4e0a\u5be8"
    ],
    "wof:name":"Dongyao Shangzhai",
    "wof:placetype":"locality"
},
  "geometry": {"coordinates":[97.8852,24.4619],"type":"Point"}
}