{
  "type": "Feature",
  "properties": {
    "gn:admin1_code":"07",
    "gn:asciiname":"Jukou",
    "gn:country_code":"CN",
    "gn:dem":171,
    "gn:feature_class":"P",
    "gn:feature_code":"PPL",
    "gn:name":"Jukou",
    "gn:population":0,
    "gn:timezone":"Asia/Shanghai",
    "iso:country":"CN",
    "name:zho_x_preferred":[
        "Ch\u00fc-k\u2019ou"
    ],
    "name:zho_x_variant":[
        "\u8392\u53e3"
    ],
    "wof:name":"Jukou",
    "wof:placetype":"locality"
},
  "geometry": {"coordinates":[117.94956000000001,27.36943],"type":"Point"}
}