{
  "type": "Feature",
  "properties": {
    "gn:admin1_code":"13.0",
    "gn:asciiname":"Kunas",
    "gn:cc2":"CN",
    "gn:country_code":"CN",
    "gn:dem":3295,
    "gn:feature_class":"P",
    "gn:feature_code":"PPL",
    "gn:name":"K\u00fcnas",
    "gn:population":0,
    "gn:timezone":"Asia/Urumqi",
    "iso:country":"CN",
    "name:uig_x_preferred":[
        "K\u00fcn\u0259s"
    ],
    "name:uig_x_variant":[
        "K\u00fcnes",
        "\u0643\u06c8\u0646\u06d5\u0633",
        "\u041a\u04af\u043d\u04d9\u0441"
    ],
    "name:und_x_variant":[
        "Kung-nai-ssu",
        "K\u00fcnas"
    ],
    "wof:name":"Kunas",
    "wof:placetype":"locality"
},
  "geometry": {"coordinates":[84.53333000000001,43.15],"type":"Point"}
}