{
  "type": "Feature",
  "properties": {
    "gn:admin1_code":"29.0",
    "gn:asciiname":"Zongshuzhai",
    "gn:country_code":"CN",
    "gn:dem":1769,
    "gn:feature_class":"P",
    "gn:feature_code":"PPL",
    "gn:name":"Zongshuzhai",
    "gn:population":0,
    "gn:timezone":"Asia/Shanghai",
    "iso:country":"CN",
    "name:zho_x_preferred":[
        "\u68d5\u6811\u5be8"
    ],
    "wof:name":"Zongshuzhai",
    "wof:placetype":"locality"
},
  "geometry": {"coordinates":[102.709,23.0942],"type":"Point"}
}