{
  "type": "Feature",
  "properties": {
    "gn:admin1_code":"30",
    "gn:asciiname":"Yuanshui",
    "gn:country_code":"CN",
    "gn:dem":11,
    "gn:feature_class":"P",
    "gn:feature_code":"PPL",
    "gn:name":"Yuanshui",
    "gn:population":0,
    "gn:timezone":"Asia/Urumqi",
    "iso:country":"CN",
    "name:zho_x_preferred":[
        "\u6e90\u6c34"
    ],
    "wof:name":"Yuanshui",
    "wof:placetype":"locality"
},
  "geometry": {"coordinates":[110.26797999999999,21.34603],"type":"Point"}
}