{
  "type": "Feature",
  "properties": {
    "gn:admin1_code":"1.0",
    "gn:asciiname":"Zhanyingcun",
    "gn:country_code":"CN",
    "gn:dem":35,
    "gn:feature_class":"P",
    "gn:feature_code":"PPL",
    "gn:name":"Zhanyingcun",
    "gn:population":0,
    "gn:timezone":"Asia/Shanghai",
    "iso:country":"CN",
    "name:zho_x_preferred":[
        "\u8a79\u8425\u6751"
    ],
    "wof:name":"Zhanyingcun",
    "wof:placetype":"locality"
},
  "geometry": {"coordinates":[115.20562,32.62331],"type":"Point"}
}