{
  "type": "Feature",
  "properties": {
    "gn:admin1_code":"2",
    "gn:asciiname":"Jixia",
    "gn:country_code":"CN",
    "gn:dem":1135,
    "gn:feature_class":"P",
    "gn:feature_code":"PPL",
    "gn:name":"Jixia",
    "gn:population":0,
    "gn:timezone":"Asia/Shanghai",
    "iso:country":"CN",
    "name:zho_x_preferred":[
        "\u6f08\u4e0b"
    ],
    "name:zho_x_variant":[
        "\u9645\u4e0b"
    ],
    "wof:name":"Jixia",
    "wof:placetype":"locality"
},
  "geometry": {"coordinates":[119.18626,27.69985],"type":"Point"}
}