{
  "type": "Feature",
  "properties": {
    "gn:admin1_code":"1.0",
    "gn:asciiname":"Chakouyin",
    "gn:country_code":"CN",
    "gn:dem":17,
    "gn:feature_class":"P",
    "gn:feature_code":"PPL",
    "gn:name":"Chakouyin",
    "gn:population":0,
    "gn:timezone":"Asia/Shanghai",
    "iso:country":"CN",
    "name:zho_x_preferred":[
        "\u5c94\u53e3\u5c39"
    ],
    "wof:name":"Chakouyin",
    "wof:placetype":"locality"
},
  "geometry": {"coordinates":[118.29573000000001,31.76816],"type":"Point"}
}