{
  "type": "Feature",
  "properties": {
    "gn:admin1_code":"10",
    "gn:asciiname":"Didong Goumen",
    "gn:country_code":"CN",
    "gn:dem":545,
    "gn:feature_class":"P",
    "gn:feature_code":"PPL",
    "gn:name":"Didong Goumen",
    "gn:population":0,
    "gn:timezone":"Asia/Shanghai",
    "iso:country":"CN",
    "name:zho_x_preferred":[
        "\u5730\u4e1c\u6c9f\u95e8"
    ],
    "wof:name":"Didong Goumen",
    "wof:placetype":"locality"
},
  "geometry": {"coordinates":[116.92203000000001,41.11346],"type":"Point"}
}