{
  "type": "Feature",
  "properties": {
    "gn:admin1_code":"12.0",
    "gn:asciiname":"Xiechang",
    "gn:country_code":"CN",
    "gn:dem":33,
    "gn:feature_class":"P",
    "gn:feature_code":"PPL",
    "gn:name":"Xiechang",
    "gn:population":0,
    "gn:timezone":"Asia/Shanghai",
    "iso:country":"CN",
    "name:und_x_variant":[
        "Xiechang Xiang"
    ],
    "name:zho_x_preferred":[
        "Xiechang"
    ],
    "name:zho_x_variant":[
        "\u8c22\u573a",
        "\u8c22\u573a\u4e61"
    ],
    "wof:name":"Xiechang",
    "wof:placetype":"locality"
},
  "geometry": {"coordinates":[112.99495,30.33918],"type":"Point"}
}