{
  "type": "Feature",
  "properties": {
    "gn:admin1_code":"16.0",
    "gn:asciiname":"Genghuai",
    "gn:country_code":"CN",
    "gn:dem":117,
    "gn:feature_class":"P",
    "gn:feature_code":"PPL",
    "gn:name":"Genghuai",
    "gn:population":0,
    "gn:timezone":"Asia/Shanghai",
    "iso:country":"CN",
    "name:zho_x_preferred":[
        "\u66f4\u6000"
    ],
    "wof:name":"Genghuai",
    "wof:placetype":"locality"
},
  "geometry": {"coordinates":[106.91500000000001,23.6447],"type":"Point"}
}