{
  "type": "Feature",
  "properties": {
    "gn:admin1_code":"29",
    "gn:asciiname":"Donggou Laozhai",
    "gn:country_code":"CN",
    "gn:dem":1152,
    "gn:feature_class":"P",
    "gn:feature_code":"PPL",
    "gn:name":"Donggou Laozhai",
    "gn:population":0,
    "gn:timezone":"Asia/Shanghai",
    "iso:country":"CN",
    "name:zho_x_preferred":[
        "\u6d1e\u6c9f\u8001\u5be8"
    ],
    "wof:name":"Donggou Laozhai",
    "wof:placetype":"locality"
},
  "geometry": {"coordinates":[105.502,23.6331],"type":"Point"}
}