{
  "type": "Feature",
  "properties": {
    "gn:admin1_code":"15.0",
    "gn:asciiname":"Zhangguojia",
    "gn:country_code":"CN",
    "gn:dem":2123,
    "gn:feature_class":"P",
    "gn:feature_code":"PPL",
    "gn:name":"Zhangguojia",
    "gn:population":0,
    "gn:timezone":"Asia/Shanghai",
    "iso:country":"CN",
    "name:und_x_variant":[
        "\u5f20\u90ed\u5bb6"
    ],
    "wof:name":"Zhangguojia",
    "wof:placetype":"locality"
},
  "geometry": {"coordinates":[102.88391,35.80067000000001],"type":"Point"}
}