{
  "type": "Feature",
  "properties": {
    "gn:admin1_code":"26.0",
    "gn:asciiname":"Shuimoliang",
    "gn:country_code":"CN",
    "gn:dem":1094,
    "gn:feature_class":"P",
    "gn:feature_code":"PPL",
    "gn:name":"Shuimoliang",
    "gn:population":0,
    "gn:timezone":"Asia/Shanghai",
    "iso:country":"CN",
    "name:zho_x_preferred":[
        "\u6c34\u78e8\u6881"
    ],
    "wof:name":"Shuimoliang",
    "wof:placetype":"locality"
},
  "geometry": {"coordinates":[109.69897,38.30335],"type":"Point"}
}