{
  "type": "Feature",
  "properties": {
    "gn:admin1_code":"3.0",
    "gn:asciiname":"Tianli",
    "gn:country_code":"CN",
    "gn:dem":79,
    "gn:feature_class":"P",
    "gn:feature_code":"PPL",
    "gn:name":"Tianli",
    "gn:population":0,
    "gn:timezone":"Asia/Shanghai",
    "iso:country":"CN",
    "name:zho_x_preferred":[
        "\u7530\u91cc"
    ],
    "wof:name":"Tianli",
    "wof:placetype":"locality"
},
  "geometry": {"coordinates":[115.06999999999999,28.1384],"type":"Point"}
}