{
  "type": "Feature",
  "properties": {
    "gn:admin1_code":"26.0",
    "gn:asciiname":"Qiushuba",
    "gn:country_code":"CN",
    "gn:dem":1273,
    "gn:feature_class":"P",
    "gn:feature_code":"PPL",
    "gn:name":"Qiushuba",
    "gn:population":0,
    "gn:timezone":"Asia/Shanghai",
    "iso:country":"CN",
    "name:und_x_variant":[
        "\u6978\u6811\u575d"
    ],
    "wof:name":"Qiushuba",
    "wof:placetype":"locality"
},
  "geometry": {"coordinates":[106.58973,33.71872],"type":"Point"}
}