{
  "type": "Feature",
  "properties": {
    "gn:admin1_code":"2",
    "gn:asciiname":"Shangchaxi",
    "gn:country_code":"CN",
    "gn:dem":666,
    "gn:feature_class":"P",
    "gn:feature_code":"PPL",
    "gn:name":"Shangchaxi",
    "gn:population":0,
    "gn:timezone":"Asia/Shanghai",
    "iso:country":"CN",
    "name:zho_x_preferred":[
        "\u4e0a\u5bdf\u6eaa"
    ],
    "wof:name":"Shangchaxi",
    "wof:placetype":"locality"
},
  "geometry": {"coordinates":[119.7625,27.50861],"type":"Point"}
}