{
  "type": "Feature",
  "properties": {
    "gn:admin1_code":"29.0",
    "gn:asciiname":"Dahuodi",
    "gn:country_code":"CN",
    "gn:dem":1711,
    "gn:feature_class":"P",
    "gn:feature_code":"PPL",
    "gn:name":"Dahuodi",
    "gn:population":0,
    "gn:timezone":"Asia/Shanghai",
    "iso:country":"CN",
    "name:zho_x_preferred":[
        "\u5927\u706b\u5730"
    ],
    "wof:name":"Dahuodi",
    "wof:placetype":"locality"
},
  "geometry": {"coordinates":[103.92,28.041],"type":"Point"}
}