{
  "type": "Feature",
  "properties": {
    "gn:admin1_code":"29.0",
    "gn:asciiname":"Wusu",
    "gn:country_code":"CN",
    "gn:dem":1398,
    "gn:feature_class":"P",
    "gn:feature_code":"PPL",
    "gn:name":"Wusu",
    "gn:population":0,
    "gn:timezone":"Asia/Shanghai",
    "iso:country":"CN",
    "name:zho_x_preferred":[
        "\u4e94\u7d20"
    ],
    "wof:name":"Wusu",
    "wof:placetype":"locality"
},
  "geometry": {"coordinates":[101.66200000000001,23.3661],"type":"Point"}
}