{
  "type": "Feature",
  "properties": {
    "gn:admin1_code":"15.0",
    "gn:asciiname":"Laowan",
    "gn:country_code":"CN",
    "gn:dem":1732,
    "gn:feature_class":"P",
    "gn:feature_code":"PPL",
    "gn:name":"Laowan",
    "gn:population":0,
    "gn:timezone":"Asia/Shanghai",
    "iso:country":"CN",
    "name:zho_x_preferred":[
        "\u8001\u6e7e"
    ],
    "wof:name":"Laowan",
    "wof:placetype":"locality"
},
  "geometry": {"coordinates":[105.76000000000001,34.9251],"type":"Point"}
}