{
  "type": "Feature",
  "properties": {
    "gn:admin1_code":"4.0",
    "gn:asciiname":"Mengzhou",
    "gn:country_code":"CN",
    "gn:dem":42,
    "gn:feature_class":"P",
    "gn:feature_code":"PPL",
    "gn:name":"Mengzhou",
    "gn:population":0,
    "gn:timezone":"Asia/Shanghai",
    "iso:country":"CN",
    "name:deu_x_preferred":[
        "Mengzhou"
    ],
    "name:fra_x_preferred":[
        "Mengzhou"
    ],
    "name:ita_x_preferred":[
        "Mengzhou"
    ],
    "name:jpn_x_preferred":[
        "\u5b5f\u5dde\u5e02"
    ],
    "name:kik_x_preferred":[
        "Mengzhou"
    ],
    "name:kor_x_preferred":[
        "\uba4d\uc800\uc6b0\uc2dc"
    ],
    "name:mlg_x_preferred":[
        "Mengzhou"
    ],
    "name:nor_x_preferred":[
        "Mengzhou"
    ],
    "name:pam_x_preferred":[
        "Mengzhou"
    ],
    "name:rus_x_preferred":[
        "\u041c\u044d\u043d\u0447\u0436\u043e\u0443"
    ],
    "name:swe_x_preferred":[
        "Mengzhou"
    ],
    "name:vie_x_preferred":[
        "M\u1ea1nh Ch\u00e2u"
    ],
    "name:zho_x_preferred":[
        "\u5b5f\u5468"
    ],
    "name:zho_x_variant":[
        "\u5b5f\u5dde\u5e02"
    ],
    "wof:name":"Mengzhou",
    "wof:placetype":"locality"
},
  "geometry": {"coordinates":[118.61272,32.58291],"type":"Point"}
}