{
  "type": "Feature",
  "properties": {
    "gn:admin1_code":"11.0",
    "gn:asciiname":"Laoxichong",
    "gn:country_code":"CN",
    "gn:dem":597,
    "gn:feature_class":"P",
    "gn:feature_code":"PPL",
    "gn:name":"Laoxichong",
    "gn:population":0,
    "gn:timezone":"Asia/Shanghai",
    "iso:country":"CN",
    "name:zho_x_preferred":[
        "\u8001\u6eaa\u51b2"
    ],
    "wof:name":"Laoxichong",
    "wof:placetype":"locality"
},
  "geometry": {"coordinates":[110.75418999999999,28.41656],"type":"Point"}
}