{
  "type": "Feature",
  "properties": {
    "gn:admin1_code":"26.0",
    "gn:asciiname":"Sishenmiao",
    "gn:country_code":"CN",
    "gn:dem":1613,
    "gn:feature_class":"P",
    "gn:feature_code":"PPL",
    "gn:name":"Sishenmiao",
    "gn:population":0,
    "gn:timezone":"Asia/Shanghai",
    "iso:country":"CN",
    "name:zho_x_preferred":[
        "\u56db\u795e\u5e99"
    ],
    "wof:name":"Sishenmiao",
    "wof:placetype":"locality"
},
  "geometry": {"coordinates":[109.9008,35.65375],"type":"Point"}
}