{
  "type": "Feature",
  "properties": {
    "gn:admin1_code":"02",
    "gn:asciiname":"Longdongcun",
    "gn:country_code":"CN",
    "gn:dem":9,
    "gn:feature_class":"P",
    "gn:feature_code":"PPL",
    "gn:name":"Longdongcun",
    "gn:population":0,
    "gn:timezone":"Asia/Shanghai",
    "iso:country":"CN",
    "name:und_x_variant":[
        "Longdong",
        "Longdongcun"
    ],
    "name:zho_x_preferred":[
        "\u9f99\u4e1c"
    ],
    "name:zho_x_variant":[
        "\u9f99\u4e1c\u6751"
    ],
    "wof:name":"Longdongcun",
    "wof:placetype":"locality"
},
  "geometry": {"coordinates":[120.80688000000001,27.9657],"type":"Point"}
}