{
  "type": "Feature",
  "properties": {
    "gn:admin1_code":"11.0",
    "gn:asciiname":"Meiqiao",
    "gn:country_code":"CN",
    "gn:dem":74,
    "gn:feature_class":"P",
    "gn:feature_code":"PPL",
    "gn:name":"Meiqiao",
    "gn:population":0,
    "gn:timezone":"Asia/Shanghai",
    "iso:country":"CN",
    "name:zho_x_preferred":[
        "\u6885\u6865"
    ],
    "wof:name":"Meiqiao",
    "wof:placetype":"locality"
},
  "geometry": {"coordinates":[112.76734999999999,27.19328],"type":"Point"}
}