{
  "type": "Feature",
  "properties": {
    "gn:admin1_code":"30.0",
    "gn:asciiname":"Jianzikeng",
    "gn:country_code":"CN",
    "gn:dem":199,
    "gn:feature_class":"P",
    "gn:feature_code":"PPL",
    "gn:name":"Jianzikeng",
    "gn:population":0,
    "gn:timezone":"Asia/Shanghai",
    "iso:country":"CN",
    "name:zho_x_preferred":[
        "Jianzikeng"
    ],
    "name:zho_x_variant":[
        "\u6da7\u5b50\u5751"
    ],
    "wof:name":"Jianzikeng",
    "wof:placetype":"locality"
},
  "geometry": {"coordinates":[115.25917,24.37556],"type":"Point"}
}