{
  "type": "Feature",
  "properties": {
    "gn:admin1_code":"14.0",
    "gn:asciiname":"Yarzhong",
    "gn:country_code":"CN",
    "gn:dem":4926,
    "gn:feature_class":"P",
    "gn:feature_code":"PPL",
    "gn:name":"Yarzhong",
    "gn:population":0,
    "gn:timezone":"Asia/Urumqi",
    "iso:country":"CN",
    "name:ara_x_preferred":[
        "\u064a\u0627\u0631\u0648\u062c\u0648\u0646\u063a"
    ],
    "name:bod_x_preferred":[
        "Yarzhong"
    ],
    "name:fas_x_preferred":[
        "\u06cc\u0627\u0631\u0698\u0648\u0646\u06af"
    ],
    "name:msa_x_preferred":[
        "Yarzhong"
    ],
    "name:urd_x_preferred":[
        "\u06cc\u0627\u0631\u0632\u06be\u0648\u0646\u06af"
    ],
    "name:zho_x_preferred":[
        "Yazhong"
    ],
    "name:zho_x_variant":[
        "\u4e9a\u4e2d",
        "Nienie Gongshe",
        "\u6d85\u6d85\u516c\u793e"
    ],
    "wof:name":"Yarzhong",
    "wof:placetype":"locality"
},
  "geometry": {"coordinates":[95.501,30.801],"type":"Point"}
}