{
  "type": "Feature",
  "properties": {
    "gn:admin1_code":"13",
    "gn:asciiname":"Youkuri Maili",
    "gn:country_code":"CN",
    "gn:dem":1316,
    "gn:feature_class":"P",
    "gn:feature_code":"PPL",
    "gn:name":"Youkuri Maili",
    "gn:population":0,
    "gn:timezone":"Asia/Shanghai",
    "iso:country":"CN",
    "name:und_x_variant":[
        "\u5c24\u5e93\u65e5\u4e70\u91cc"
    ],
    "wof:name":"Youkuri Maili",
    "wof:placetype":"locality"
},
  "geometry": {"coordinates":[76.07635000000001,39.51768],"type":"Point"}
}