{
  "type": "Feature",
  "properties": {
    "gn:admin1_code":"14.0",
    "gn:asciiname":"Damogure",
    "gn:country_code":"CN",
    "gn:dem":3943,
    "gn:feature_class":"P",
    "gn:feature_code":"PPL",
    "gn:name":"Damogure",
    "gn:population":0,
    "gn:timezone":"Asia/Urumqi",
    "iso:country":"CN",
    "name:zho_x_preferred":[
        "\u5927\u83ab\u8c37\u70ed"
    ],
    "wof:name":"Damogure",
    "wof:placetype":"locality"
},
  "geometry": {"coordinates":[94.18873000000001,29.04858],"type":"Point"}
}