{
  "type": "Feature",
  "properties": {
    "gn:admin1_code":"2.0",
    "gn:asciiname":"Lihongkeng",
    "gn:country_code":"CN",
    "gn:dem":256,
    "gn:feature_class":"P",
    "gn:feature_code":"PPL",
    "gn:name":"Lihongkeng",
    "gn:population":0,
    "gn:timezone":"Asia/Shanghai",
    "iso:country":"CN",
    "name:zho_x_preferred":[
        "\u91cc\u6d2a\u5751"
    ],
    "wof:name":"Lihongkeng",
    "wof:placetype":"locality"
},
  "geometry": {"coordinates":[119.11766,29.43255],"type":"Point"}
}