{
  "type": "Feature",
  "properties": {
    "gn:admin1_code":"5.0",
    "gn:asciiname":"Shipiban",
    "gn:country_code":"CN",
    "gn:dem":21,
    "gn:feature_class":"P",
    "gn:feature_code":"PPL",
    "gn:name":"Shipiban",
    "gn:population":0,
    "gn:timezone":"Asia/Shanghai",
    "iso:country":"CN",
    "name:und_x_variant":[
        "Shih-p\u2019i-pan"
    ],
    "wof:name":"Shipiban",
    "wof:placetype":"locality"
},
  "geometry": {"coordinates":[130.43696,42.58254],"type":"Point"}
}