{
  "type": "Feature",
  "properties": {
    "gn:admin1_code":"02",
    "gn:asciiname":"Xiaolingfeng",
    "gn:country_code":"CN",
    "gn:dem":5,
    "gn:feature_class":"P",
    "gn:feature_code":"PPL",
    "gn:name":"Xiaolingfeng",
    "gn:population":0,
    "gn:timezone":"Asia/Shanghai",
    "iso:country":"CN",
    "name:und_x_variant":[
        "\u5c0f\u7075\u5cf0"
    ],
    "wof:name":"Xiaolingfeng",
    "wof:placetype":"locality"
},
  "geometry": {"coordinates":[121.38921000000001,30.18551],"type":"Point"}
}