{
  "type": "Feature",
  "properties": {
    "gn:admin1_code":"6.0",
    "gn:asciiname":"Parxixingka",
    "gn:country_code":"CN",
    "gn:dem":3177,
    "gn:feature_class":"P",
    "gn:feature_code":"PPL",
    "gn:name":"Parxixingka",
    "gn:population":0,
    "gn:timezone":"Asia/Shanghai",
    "iso:country":"CN",
    "wof:name":"Parxixingka",
    "wof:placetype":"locality"
},
  "geometry": {"coordinates":[99.26667,36.46667],"type":"Point"}
}