{
  "type": "Feature",
  "properties": {
    "gn:admin1_code":"08",
    "gn:asciiname":"Sijiazi",
    "gn:country_code":"CN",
    "gn:dem":128,
    "gn:feature_class":"P",
    "gn:feature_code":"PPLA4",
    "gn:name":"Sijiazi",
    "gn:population":0,
    "gn:timezone":"Asia/Shanghai",
    "iso:country":"CN",
    "name:und_x_variant":[
        "Sijiazi Manzu Xiang"
    ],
    "name:zho_x_preferred":[
        "\u56db\u5609\u5b50"
    ],
    "name:zho_x_variant":[
        "\u56db\u5609\u5b50\u6ee1\u65cf\u4e61"
    ],
    "wof:name":"Sijiazi",
    "wof:placetype":"locality"
},
  "geometry": {"coordinates":[127.51183,50.17788],"type":"Point"}
}