{
  "type": "Feature",
  "properties": {
    "gn:admin1_code":"30.0",
    "gn:asciiname":"Dashanbeicun",
    "gn:country_code":"CN",
    "gn:dem":36,
    "gn:feature_class":"P",
    "gn:feature_code":"PPL",
    "gn:name":"Dashanbeicun",
    "gn:population":0,
    "gn:timezone":"Asia/Shanghai",
    "iso:country":"CN",
    "name:zho_x_preferred":[
        "\u5927\u5c71\u80cc\u6751"
    ],
    "wof:name":"Dashanbeicun",
    "wof:placetype":"locality"
},
  "geometry": {"coordinates":[116.18038,23.76606],"type":"Point"}
}