{
  "type": "Feature",
  "properties": {
    "gn:admin1_code":"18.0",
    "gn:asciiname":"Xiashaqin",
    "gn:country_code":"CN",
    "gn:dem":526,
    "gn:feature_class":"P",
    "gn:feature_code":"PPL",
    "gn:name":"Xiashaqin",
    "gn:population":0,
    "gn:timezone":"Asia/Shanghai",
    "iso:country":"CN",
    "name:zho_x_preferred":[
        "\u4e0b\u6c99\u82b9"
    ],
    "wof:name":"Xiashaqin",
    "wof:placetype":"locality"
},
  "geometry": {"coordinates":[107.765,25.9336],"type":"Point"}
}