{
  "type": "Feature",
  "properties": {
    "gn:admin1_code":"3.0",
    "gn:asciiname":"Miaobeikeng",
    "gn:country_code":"CN",
    "gn:dem":392,
    "gn:feature_class":"P",
    "gn:feature_code":"PPL",
    "gn:name":"Miaobeikeng",
    "gn:population":0,
    "gn:timezone":"Asia/Shanghai",
    "iso:country":"CN",
    "name:und_x_variant":[
        "\u5e99\u80cc\u5751"
    ],
    "wof:name":"Miaobeikeng",
    "wof:placetype":"locality"
},
  "geometry": {"coordinates":[115.90522,25.58155],"type":"Point"}
}