{
  "type": "Feature",
  "properties": {
    "gn:country":"CN",
    "gn:fcode":"PPLA3",
    "gn:population":0,
    "iso:country":"CN",
    "name:und_x_variant":[
        "Pingjianglu Jiedao"
    ],
    "name:zho_x_preferred":[
        "\u5e73\u6c5f\u8def"
    ],
    "name:zho_x_variant":[
        "\u5e73\u6c5f\u8def\u8857\u9053",
        "\u5e73\u6c5f\u533a"
    ],
    "qs:name":"Pingjianglu",
    "qs:photos_9r":0,
    "qs:photos_sr":0,
    "qs:pop_sr":"0",
    "wof:name":"Pingjianglu",
    "wof:placetype":"locality",
    "wof:population":0
},
  "geometry": {"coordinates":[120.62978,31.31469],"type":"Point"}
}