{
  "type": "Feature",
  "properties": {
    "gn:admin1_code":"5.0",
    "gn:asciiname":"Bao'ancun",
    "gn:country_code":"CN",
    "gn:dem":176,
    "gn:feature_class":"P",
    "gn:feature_code":"PPL",
    "gn:name":"Bao\u2019ancun",
    "gn:population":0,
    "gn:timezone":"Asia/Shanghai",
    "iso:country":"CN",
    "name:und_x_variant":[
        "Bao\u2019ancun"
    ],
    "name:zho_x_preferred":[
        "\u4fdd\u5b89\u6751"
    ],
    "wof:name":"Bao'ancun",
    "wof:placetype":"locality"
},
  "geometry": {"coordinates":[125.71735,44.99832],"type":"Point"}
}