{
  "type": "Feature",
  "properties": {
    "gn:admin1_code":"01",
    "gn:asciiname":"Tangnanji",
    "gn:cc2":"CN",
    "gn:country_code":"CN",
    "gn:dem":24,
    "gn:feature_class":"P",
    "gn:feature_code":"PPL",
    "gn:name":"Tangnanji",
    "gn:population":0,
    "gn:timezone":"Asia/Shanghai",
    "iso:country":"CN",
    "name:und_x_variant":[
        "T\u2019ang-nan",
        "T\u2019ang-nan-chi",
        "Tangnanji"
    ],
    "wof:name":"Tangnanji",
    "wof:placetype":"locality"
},
  "geometry": {"coordinates":[117.26667,33.36667],"type":"Point"}
}