{
  "type": "Feature",
  "properties": {
    "gn:admin1_code":"32.0",
    "gn:asciiname":"Mengge",
    "gn:country_code":"CN",
    "gn:dem":4352,
    "gn:feature_class":"P",
    "gn:feature_code":"PPL",
    "gn:name":"Mengge",
    "gn:population":0,
    "gn:timezone":"Asia/Shanghai",
    "iso:country":"CN",
    "name:zho_x_preferred":[
        "\u8499\u683c"
    ],
    "wof:name":"Mengge",
    "wof:placetype":"locality"
},
  "geometry": {"coordinates":[98.1966,32.8315],"type":"Point"}
}