{
  "type": "Feature",
  "properties": {
    "gn:admin1_code":"18",
    "gn:asciiname":"Angtao",
    "gn:country_code":"CN",
    "gn:dem":928,
    "gn:feature_class":"P",
    "gn:feature_code":"PPL",
    "gn:name":"Angtao",
    "gn:population":0,
    "gn:timezone":"Asia/Shanghai",
    "iso:country":"CN",
    "name:zho_x_preferred":[
        "\u6602\u6d9b"
    ],
    "wof:name":"Angtao",
    "wof:placetype":"locality"
},
  "geometry": {"coordinates":[105.84699999999999,24.8907],"type":"Point"}
}