{
  "type": "Feature",
  "properties": {
    "gn:admin1_code":"04",
    "gn:asciiname":"Liuqiao",
    "gn:country_code":"CN",
    "gn:dem":36,
    "gn:feature_class":"P",
    "gn:feature_code":"PPL",
    "gn:name":"Liuqiao",
    "gn:population":0,
    "gn:timezone":"Asia/Shanghai",
    "iso:country":"CN",
    "name:und_x_variant":[
        "Liu-ch\u2019iao",
        "Liuqiao"
    ],
    "name:zho_x_preferred":[
        "\u67f3\u6865"
    ],
    "wof:name":"Liuqiao",
    "wof:placetype":"locality"
},
  "geometry": {"coordinates":[119.17648,32.04551],"type":"Point"}
}