{
  "type": "Feature",
  "properties": {
    "gn:admin1_code":"10",
    "gn:asciiname":"Liqingu",
    "gn:cc2":"CN",
    "gn:country_code":"CN",
    "gn:dem":45,
    "gn:feature_class":"P",
    "gn:feature_code":"PPL",
    "gn:name":"Liqingu",
    "gn:population":0,
    "gn:timezone":"Asia/Shanghai",
    "iso:country":"CN",
    "name:und_x_variant":[
        "Li-ch\u2019in-ku",
        "Li-ch\u2019in-ku-chen",
        "Liqingu"
    ],
    "wof:name":"Liqingu",
    "wof:placetype":"locality"
},
  "geometry": {"coordinates":[115.09139,38.34333],"type":"Point"}
}