{
  "type": "Feature",
  "properties": {
    "gn:admin1_code":"29",
    "gn:asciiname":"Yafangzi",
    "gn:country_code":"CN",
    "gn:dem":1507,
    "gn:feature_class":"P",
    "gn:feature_code":"PPL",
    "gn:name":"Yafangzi",
    "gn:population":0,
    "gn:timezone":"Asia/Shanghai",
    "iso:country":"CN",
    "wof:name":"Yafangzi",
    "wof:placetype":"locality"
},
  "geometry": {"coordinates":[102.39139,23.80806],"type":"Point"}
}