{
  "type": "Feature",
  "properties": {
    "gn:admin1_code":"8.0",
    "gn:asciiname":"Liangzihecun",
    "gn:country_code":"CN",
    "gn:dem":124,
    "gn:feature_class":"P",
    "gn:feature_code":"PPL",
    "gn:name":"Liangzihecun",
    "gn:population":0,
    "gn:timezone":"Asia/Shanghai",
    "iso:country":"CN",
    "name:zho_x_preferred":[
        "\u4eae\u5b50\u6cb3\u6751"
    ],
    "wof:name":"Liangzihecun",
    "wof:placetype":"locality"
},
  "geometry": {"coordinates":[129.57884000000001,46.81909],"type":"Point"}
}