{
  "type": "Feature",
  "properties": {
    "gn:admin1_code":"14",
    "gn:asciiname":"Qabtang",
    "gn:country_code":"CN",
    "gn:dem":3879,
    "gn:feature_class":"P",
    "gn:feature_code":"PPL",
    "gn:name":"Qabtang",
    "gn:population":0,
    "gn:timezone":"Asia/Urumqi",
    "iso:country":"CN",
    "name:bod_x_preferred":[
        "\u0f46\u0f56\u0f0b\u0f50\u0f44"
    ],
    "wof:name":"Qabtang",
    "wof:placetype":"locality"
},
  "geometry": {"coordinates":[91.85214000000001,29.43212],"type":"Point"}
}