{
  "type": "Feature",
  "properties": {
    "gn:admin1_code":"25",
    "gn:asciiname":"Dalaoquan",
    "gn:country_code":"CN",
    "gn:dem":237,
    "gn:feature_class":"P",
    "gn:feature_code":"PPL",
    "gn:name":"Dalaoquan",
    "gn:population":0,
    "gn:timezone":"Asia/Shanghai",
    "iso:country":"CN",
    "name:zho_x_preferred":[
        "\u5927\u6d9d\u6cc9"
    ],
    "wof:name":"Dalaoquan",
    "wof:placetype":"locality"
},
  "geometry": {"coordinates":[117.536,35.3207],"type":"Point"}
}