{
  "type": "Feature",
  "properties": {
    "gn:admin1_code":"12.0",
    "gn:asciiname":"Shijiaping",
    "gn:country_code":"CN",
    "gn:dem":1073,
    "gn:feature_class":"P",
    "gn:feature_code":"PPL",
    "gn:name":"Shijiaping",
    "gn:population":0,
    "gn:timezone":"Asia/Shanghai",
    "iso:country":"CN",
    "name:zho_x_preferred":[
        "\u77f3\u5bb6\u576a"
    ],
    "wof:name":"Shijiaping",
    "wof:placetype":"locality"
},
  "geometry": {"coordinates":[111.22816,31.2903],"type":"Point"}
}