{
  "type": "Feature",
  "properties": {
    "gn:admin1_code":"24.0",
    "gn:asciiname":"Yulingoucun",
    "gn:country_code":"CN",
    "gn:dem":954,
    "gn:feature_class":"P",
    "gn:feature_code":"PPL",
    "gn:name":"Yulingoucun",
    "gn:population":0,
    "gn:timezone":"Asia/Shanghai",
    "iso:country":"CN",
    "name:zho_x_preferred":[
        "\u6986\u6797\u6c9f\u6751"
    ],
    "wof:name":"Yulingoucun",
    "wof:placetype":"locality"
},
  "geometry": {"coordinates":[114.29568999999999,39.24847000000001],"type":"Point"}
}