{
  "type": "Feature",
  "properties": {
    "gn:admin1_code":"1.0",
    "gn:asciiname":"Liumiaocun",
    "gn:country_code":"CN",
    "gn:dem":25,
    "gn:feature_class":"P",
    "gn:feature_code":"PPL",
    "gn:name":"Liumiaocun",
    "gn:population":0,
    "gn:timezone":"Asia/Shanghai",
    "iso:country":"CN",
    "name:zho_x_preferred":[
        "\u5218\u5e99\u6751"
    ],
    "wof:name":"Liumiaocun",
    "wof:placetype":"locality"
},
  "geometry": {"coordinates":[116.81777,33.45315],"type":"Point"}
}