{
  "type": "Feature",
  "properties": {
    "gn:admin1_code":"1.0",
    "gn:asciiname":"Dagangcun",
    "gn:country_code":"CN",
    "gn:dem":48,
    "gn:feature_class":"P",
    "gn:feature_code":"PPL",
    "gn:name":"Dagangcun",
    "gn:population":0,
    "gn:timezone":"Asia/Shanghai",
    "iso:country":"CN",
    "name:zho_x_preferred":[
        "\u5927\u5c97\u6751"
    ],
    "wof:name":"Dagangcun",
    "wof:placetype":"locality"
},
  "geometry": {"coordinates":[116.70314,31.85743],"type":"Point"}
}