{
  "type": "Feature",
  "properties": {
    "gn:admin1_code":"8.0",
    "gn:asciiname":"Kangdetun",
    "gn:country_code":"CN",
    "gn:dem":242,
    "gn:feature_class":"P",
    "gn:feature_code":"PPL",
    "gn:name":"Kangdetun",
    "gn:population":0,
    "gn:timezone":"Asia/Shanghai",
    "iso:country":"CN",
    "name:zho_x_preferred":[
        "\u5eb7\u5fb7\u5c6f"
    ],
    "wof:name":"Kangdetun",
    "wof:placetype":"locality"
},
  "geometry": {"coordinates":[122.76887000000001,47.44766],"type":"Point"}
}