{
  "type": "Feature",
  "properties": {
    "gn:admin1_code":"19.0",
    "gn:asciiname":"Xijingjiagouli",
    "gn:country_code":"CN",
    "gn:dem":472,
    "gn:feature_class":"P",
    "gn:feature_code":"PPL",
    "gn:name":"Xijingjiagouli",
    "gn:population":0,
    "gn:timezone":"Asia/Shanghai",
    "iso:country":"CN",
    "name:und_x_variant":[
        "Xijingjia Gouli"
    ],
    "name:zho_x_preferred":[
        "\u897f\u4e95\u5bb6\u6c9f\u91cc"
    ],
    "wof:name":"Xijingjiagouli",
    "wof:placetype":"locality"
},
  "geometry": {"coordinates":[124.94199999999999,42.2215],"type":"Point"}
}