{
  "type": "Feature",
  "properties": {
    "gn:admin1_code":"2.0",
    "gn:asciiname":"Qikeng",
    "gn:country_code":"CN",
    "gn:dem":79,
    "gn:feature_class":"P",
    "gn:feature_code":"PPL",
    "gn:name":"Qikeng",
    "gn:population":0,
    "gn:timezone":"Asia/Shanghai",
    "iso:country":"CN",
    "name:zho_x_preferred":[
        "\u9a91\u5751"
    ],
    "wof:name":"Qikeng",
    "wof:placetype":"locality"
},
  "geometry": {"coordinates":[119.68438999999999,28.25675],"type":"Point"}
}