{
  "type": "Feature",
  "properties": {
    "gn:admin1_code":"31",
    "gn:asciiname":"Poxin",
    "gn:country_code":"CN",
    "gn:dem":105,
    "gn:feature_class":"P",
    "gn:feature_code":"PPLA4",
    "gn:name":"Poxin",
    "gn:population":0,
    "gn:timezone":"Asia/Shanghai",
    "iso:country":"CN",
    "name:und_x_variant":[
        "\u5761\u5fc3",
        "Poxin Zhen",
        "\u5761\u5fc3\u9547"
    ],
    "wof:name":"Poxin",
    "wof:placetype":"locality"
},
  "geometry": {"coordinates":[110.08374000000001,19.30202],"type":"Point"}
}