{
  "type": "Feature",
  "properties": {
    "gn:admin1_code":"8.0",
    "gn:asciiname":"Xinghuacun",
    "gn:country_code":"CN",
    "gn:dem":252,
    "gn:feature_class":"P",
    "gn:feature_code":"PPL",
    "gn:name":"Xinghuacun",
    "gn:population":0,
    "gn:timezone":"Asia/Shanghai",
    "iso:country":"CN",
    "name:zho_x_preferred":[
        "\u5174\u534e\u6751"
    ],
    "wof:name":"Xinghuacun",
    "wof:placetype":"locality"
},
  "geometry": {"coordinates":[125.81570000000001,48.48433],"type":"Point"}
}