{
  "type": "Feature",
  "properties": {
    "gn:admin1_code":"13.0",
    "gn:asciiname":"Qingshuihe",
    "gn:cc2":"CN",
    "gn:country_code":"CN",
    "gn:dem":663,
    "gn:feature_class":"P",
    "gn:feature_code":"PPL",
    "gn:name":"Qingshuihe",
    "gn:population":0,
    "gn:timezone":"Asia/Shanghai",
    "iso:country":"CN",
    "name:und_x_variant":[
        "Ch\u2019ing-shui-ho",
        "Qingshuihezi",
        "Ch\u2019ing-shui-ho-tzu",
        "Qingshuihe"
    ],
    "wof:name":"Qingshuihe",
    "wof:placetype":"locality"
},
  "geometry": {"coordinates":[80.70111,44.15194],"type":"Point"}
}