{
  "type": "Feature",
  "properties": {
    "gn:admin1_code":"2.0",
    "gn:asciiname":"Qian'ao",
    "gn:country_code":"CN",
    "gn:dem":118,
    "gn:feature_class":"P",
    "gn:feature_code":"PPL",
    "gn:name":"Qian\u2019ao",
    "gn:population":0,
    "gn:timezone":"Asia/Shanghai",
    "iso:country":"CN",
    "name:und_x_variant":[
        "Qian\u2019ao"
    ],
    "name:zho_x_preferred":[
        "\u524d\u5c99"
    ],
    "wof:name":"Qian'ao",
    "wof:placetype":"locality"
},
  "geometry": {"coordinates":[119.18488000000001,29.39752],"type":"Point"}
}