{
  "type": "Feature",
  "properties": {
    "gn:admin1_code":"30.0",
    "gn:asciiname":"Chengzui",
    "gn:country_code":"CN",
    "gn:dem":76,
    "gn:feature_class":"P",
    "gn:feature_code":"PPL",
    "gn:name":"Chengzui",
    "gn:population":0,
    "gn:timezone":"Asia/Shanghai",
    "iso:country":"CN",
    "name:zho_x_preferred":[
        "Chengzui"
    ],
    "name:zho_x_variant":[
        "\u57ce\u5480"
    ],
    "wof:name":"Chengzui",
    "wof:placetype":"locality"
},
  "geometry": {"coordinates":[112.89444,23.90111],"type":"Point"}
}