{
  "type": "Feature",
  "properties": {
    "gn:admin1_code":"4.0",
    "gn:asciiname":"Chenlaoying",
    "gn:country_code":"CN",
    "gn:dem":50,
    "gn:feature_class":"P",
    "gn:feature_code":"PPL",
    "gn:name":"Chenlaoying",
    "gn:population":0,
    "gn:timezone":"Asia/Shanghai",
    "iso:country":"CN",
    "name:zho_x_preferred":[
        "\u9648\u8001\u90e2"
    ],
    "wof:name":"Chenlaoying",
    "wof:placetype":"locality"
},
  "geometry": {"coordinates":[118.55365,32.81799],"type":"Point"}
}