{
  "type": "Feature",
  "properties": {
    "gn:admin1_code":"7.0",
    "gn:asciiname":"Xiping",
    "gn:country_code":"CN",
    "gn:dem":319,
    "gn:feature_class":"P",
    "gn:feature_code":"PPLA4",
    "gn:name":"Xiping",
    "gn:population":0,
    "gn:timezone":"Asia/Shanghai",
    "iso:country":"CN",
    "name:ceb_x_preferred":[
        "Xiping"
    ],
    "name:deu_x_preferred":[
        "Xiping"
    ],
    "name:nor_x_preferred":[
        "Xiping"
    ],
    "name:und_x_variant":[
        "Hsi-p\u2019ing",
        "Xiyuan",
        "Xiping Zhen"
    ],
    "name:zho_x_preferred":[
        "\u897f\u576a"
    ],
    "name:zho_x_variant":[
        "\u897f\u539f",
        "\u897f\u576a\u9547"
    ],
    "wof:name":"Xiping",
    "wof:placetype":"locality"
},
  "geometry": {"coordinates":[117.93995,25.02514],"type":"Point"}
}