{
  "type": "Feature",
  "properties": {
    "gn:admin1_code":"20.0",
    "gn:asciiname":"Buduntaolai",
    "gn:country_code":"CN",
    "gn:dem":911,
    "gn:feature_class":"P",
    "gn:feature_code":"PPL",
    "gn:name":"Buduntaolai",
    "gn:population":0,
    "gn:timezone":"Asia/Shanghai",
    "iso:country":"CN",
    "name:zho_x_preferred":[
        "\u5e03\u6566\u9676\u6765"
    ],
    "wof:name":"Buduntaolai",
    "wof:placetype":"locality"
},
  "geometry": {"coordinates":[101.09415,42.27495],"type":"Point"}
}