{
  "type": "Feature",
  "properties": {
    "gn:admin1_code":"30.0",
    "gn:asciiname":"Xiaqidong",
    "gn:country_code":"CN",
    "gn:dem":84,
    "gn:feature_class":"P",
    "gn:feature_code":"PPL",
    "gn:name":"Xiaqidong",
    "gn:population":0,
    "gn:timezone":"Asia/Shanghai",
    "iso:country":"CN",
    "name:zho_x_preferred":[
        "\u4e0b\u4e03\u578c"
    ],
    "wof:name":"Xiaqidong",
    "wof:placetype":"locality"
},
  "geometry": {"coordinates":[112.01385999999999,22.58945],"type":"Point"}
}