{
  "type": "Feature",
  "properties": {
    "gn:admin1_code":"26.0",
    "gn:asciiname":"Shimengoukou",
    "gn:country_code":"CN",
    "gn:dem":699,
    "gn:feature_class":"P",
    "gn:feature_code":"PPL",
    "gn:name":"Shimengoukou",
    "gn:population":0,
    "gn:timezone":"Asia/Shanghai",
    "iso:country":"CN",
    "name:zho_x_preferred":[
        "\u77f3\u95e8\u6c9f\u53e3"
    ],
    "wof:name":"Shimengoukou",
    "wof:placetype":"locality"
},
  "geometry": {"coordinates":[109.66186,33.42269],"type":"Point"}
}