{
  "type": "Feature",
  "properties": {
    "gn:admin1_code":"9.0",
    "gn:asciiname":"Caomiaocun",
    "gn:country_code":"CN",
    "gn:dem":624,
    "gn:feature_class":"P",
    "gn:feature_code":"PPL",
    "gn:name":"Caomiaocun",
    "gn:population":0,
    "gn:timezone":"Asia/Shanghai",
    "iso:country":"CN",
    "name:und_x_variant":[
        "\u8349\u5e99\u6751",
        "Caomiaocun"
    ],
    "wof:name":"Caomiaocun",
    "wof:placetype":"locality"
},
  "geometry": {"coordinates":[112.16068,33.84699000000001],"type":"Point"}
}