{
  "type": "Feature",
  "properties": {
    "gn:admin1_code":"16.0",
    "gn:asciiname":"Shang'an",
    "gn:country_code":"CN",
    "gn:dem":37,
    "gn:feature_class":"P",
    "gn:feature_code":"PPL",
    "gn:name":"Shang\u2019an",
    "gn:population":0,
    "gn:timezone":"Asia/Shanghai",
    "iso:country":"CN",
    "name:und_x_variant":[
        "Shang\u2019an"
    ],
    "name:zho_x_preferred":[
        "\u4e0a\u5cb8"
    ],
    "wof:name":"Shang'an",
    "wof:placetype":"locality"
},
  "geometry": {"coordinates":[110.768,23.4876],"type":"Point"}
}