{
  "type": "Feature",
  "properties": {
    "gn:admin1_code":"12.0",
    "gn:asciiname":"Yujialiangzi",
    "gn:country_code":"CN",
    "gn:dem":660,
    "gn:feature_class":"P",
    "gn:feature_code":"PPL",
    "gn:name":"Yujialiangzi",
    "gn:population":0,
    "gn:timezone":"Asia/Shanghai",
    "iso:country":"CN",
    "name:zho_x_preferred":[
        "\u4f59\u5bb6\u6881\u5b50"
    ],
    "wof:name":"Yujialiangzi",
    "wof:placetype":"locality"
},
  "geometry": {"coordinates":[109.78433,32.95827],"type":"Point"}
}