{
  "type": "Feature",
  "properties": {
    "gn:admin1_code":"30",
    "gn:asciiname":"Yongfeng",
    "gn:country_code":"CN",
    "gn:dem":49,
    "gn:feature_class":"P",
    "gn:feature_code":"PPLA4",
    "gn:name":"Yongfeng",
    "gn:population":0,
    "gn:timezone":"Asia/Shanghai",
    "iso:country":"CN",
    "name:ceb_x_preferred":[
        "Yongfeng"
    ],
    "name:deu_x_preferred":[
        "Yongfeng"
    ],
    "name:und_x_variant":[
        "Yongfeng Zhen",
        "\u6c38\u4e30\u9547"
    ],
    "name:zho_x_preferred":[
        "\u6c38\u4e30"
    ],
    "wof:name":"Yongfeng",
    "wof:placetype":"locality"
},
  "geometry": {"coordinates":[112.12027999999999,23.34],"type":"Point"}
}