{
  "type": "Feature",
  "properties": {
    "gn:admin1_code":"18.0",
    "gn:asciiname":"Heishuixi",
    "gn:country_code":"CN",
    "gn:dem":692,
    "gn:feature_class":"P",
    "gn:feature_code":"PPL",
    "gn:name":"Heishuixi",
    "gn:population":0,
    "gn:timezone":"Asia/Shanghai",
    "iso:country":"CN",
    "name:zho_x_preferred":[
        "\u9ed1\u6c34\u6eaa"
    ],
    "wof:name":"Heishuixi",
    "wof:placetype":"locality"
},
  "geometry": {"coordinates":[108.88,28.1991],"type":"Point"}
}