{
  "type": "Feature",
  "properties": {
    "gn:admin1_code":"26.0",
    "gn:asciiname":"Lijiawancun",
    "gn:country_code":"CN",
    "gn:dem":1229,
    "gn:feature_class":"P",
    "gn:feature_code":"PPL",
    "gn:name":"Lijiawancun",
    "gn:population":0,
    "gn:timezone":"Asia/Shanghai",
    "iso:country":"CN",
    "name:zho_x_preferred":[
        "\u674e\u5bb6\u6e7e\u6751"
    ],
    "wof:name":"Lijiawancun",
    "wof:placetype":"locality"
},
  "geometry": {"coordinates":[110.07537000000001,33.62169],"type":"Point"}
}