{
  "type": "Feature",
  "properties": {
    "gn:admin1_code":"16",
    "gn:asciiname":"Shangmuyong",
    "gn:country_code":"CN",
    "gn:dem":662,
    "gn:feature_class":"P",
    "gn:feature_code":"PPL",
    "gn:name":"Shangmuyong",
    "gn:population":0,
    "gn:timezone":"Asia/Shanghai",
    "iso:country":"CN",
    "name:zho_x_preferred":[
        "\u4e0a\u6728\u52c7"
    ],
    "wof:name":"Shangmuyong",
    "wof:placetype":"locality"
},
  "geometry": {"coordinates":[109.822,25.4751],"type":"Point"}
}