{
  "type": "Feature",
  "properties": {
    "gn:admin1_code":"11.0",
    "gn:asciiname":"Zhoujialong",
    "gn:country_code":"CN",
    "gn:dem":344,
    "gn:feature_class":"P",
    "gn:feature_code":"PPL",
    "gn:name":"Zhoujialong",
    "gn:population":0,
    "gn:timezone":"Asia/Shanghai",
    "iso:country":"CN",
    "name:zho_x_preferred":[
        "\u5468\u5bb6\u5784"
    ],
    "wof:name":"Zhoujialong",
    "wof:placetype":"locality"
},
  "geometry": {"coordinates":[110.60888,26.74206],"type":"Point"}
}