{
  "type": "Feature",
  "properties": {
    "gn:admin1_code":"8.0",
    "gn:asciiname":"Qunzhongcun",
    "gn:country_code":"CN",
    "gn:dem":230,
    "gn:feature_class":"P",
    "gn:feature_code":"PPL",
    "gn:name":"Qunzhongcun",
    "gn:population":0,
    "gn:timezone":"Asia/Shanghai",
    "iso:country":"CN",
    "name:zho_x_preferred":[
        "\u7fa4\u4f17\u6751"
    ],
    "wof:name":"Qunzhongcun",
    "wof:placetype":"locality"
},
  "geometry": {"coordinates":[126.77688999999999,47.79922],"type":"Point"}
}