{
  "type": "Feature",
  "properties": {
    "gn:admin1_code":"19.0",
    "gn:asciiname":"Shi'ancun",
    "gn:country_code":"CN",
    "gn:dem":81,
    "gn:feature_class":"P",
    "gn:feature_code":"PPL",
    "gn:name":"Shi\u2019ancun",
    "gn:population":0,
    "gn:timezone":"Asia/Shanghai",
    "iso:country":"CN",
    "name:und_x_variant":[
        "Shi\u2019ancun"
    ],
    "name:zho_x_preferred":[
        "\u77f3\u5b89\u6751"
    ],
    "wof:name":"Shi'ancun",
    "wof:placetype":"locality"
},
  "geometry": {"coordinates":[124.14505,40.2606],"type":"Point"}
}