{
  "type": "Feature",
  "properties": {
    "gn:admin1_code":"15.0",
    "gn:asciiname":"Shangbanqiao",
    "gn:country_code":"CN",
    "gn:dem":1231,
    "gn:feature_class":"P",
    "gn:feature_code":"PPL",
    "gn:name":"Shangbanqiao",
    "gn:population":0,
    "gn:timezone":"Asia/Shanghai",
    "iso:country":"CN",
    "name:und_x_variant":[
        "\u4e0a\u677f\u6865"
    ],
    "name:zho_x_preferred":[
        "\u4e0a\u677f\u6865"
    ],
    "wof:name":"Shangbanqiao",
    "wof:placetype":"locality"
},
  "geometry": {"coordinates":[104.90236000000002,33.44402],"type":"Point"}
}