{
  "type": "Feature",
  "properties": {
    "gn:admin1_code":"24.0",
    "gn:asciiname":"Beiyijian",
    "gn:country_code":"CN",
    "gn:dem":935,
    "gn:feature_class":"P",
    "gn:feature_code":"PPL",
    "gn:name":"Beiyijian",
    "gn:population":0,
    "gn:timezone":"Asia/Shanghai",
    "iso:country":"CN",
    "name:zho_x_preferred":[
        "\u5317\u4f9d\u6da7"
    ],
    "wof:name":"Beiyijian",
    "wof:placetype":"locality"
},
  "geometry": {"coordinates":[112.32519000000001,37.2192],"type":"Point"}
}