{
  "type": "Feature",
  "properties": {
    "gn:admin1_code":"15.0",
    "gn:asciiname":"Yachali",
    "gn:country_code":"CN",
    "gn:dem":2120,
    "gn:feature_class":"P",
    "gn:feature_code":"PPL",
    "gn:name":"Yachali",
    "gn:population":0,
    "gn:timezone":"Asia/Shanghai",
    "iso:country":"CN",
    "name:und_x_variant":[
        "\u5d16\u5c94\u91cc"
    ],
    "wof:name":"Yachali",
    "wof:placetype":"locality"
},
  "geometry": {"coordinates":[104.89566000000001,34.80233],"type":"Point"}
}