{
  "type": "Feature",
  "properties": {
    "gn:admin1_code":"29",
    "gn:asciiname":"Longhushan",
    "gn:country_code":"CN",
    "gn:dem":2182,
    "gn:feature_class":"P",
    "gn:feature_code":"PPL",
    "gn:name":"Longhushan",
    "gn:population":0,
    "gn:timezone":"Asia/Shanghai",
    "iso:country":"CN",
    "name:zho_x_preferred":[
        "\u9f99\u864e\u5c71"
    ],
    "wof:name":"Longhushan",
    "wof:placetype":"locality"
},
  "geometry": {"coordinates":[102.94168000000001,24.47194],"type":"Point"}
}