{
  "type": "Feature",
  "properties": {
    "gn:admin1_code":"1.0",
    "gn:asciiname":"Huokeng",
    "gn:country_code":"CN",
    "gn:dem":434,
    "gn:feature_class":"P",
    "gn:feature_code":"PPL",
    "gn:name":"Huokeng",
    "gn:population":0,
    "gn:timezone":"Asia/Shanghai",
    "iso:country":"CN",
    "name:zho_x_preferred":[
        "\u4f19\u5751"
    ],
    "wof:name":"Huokeng",
    "wof:placetype":"locality"
},
  "geometry": {"coordinates":[118.18729999999999,29.8861],"type":"Point"}
}