{
  "type": "Feature",
  "properties": {
    "gn:admin1_code":"25",
    "gn:asciiname":"Liupanshi",
    "gn:country_code":"CN",
    "gn:dem":19,
    "gn:feature_class":"P",
    "gn:feature_code":"PPL",
    "gn:name":"Liupanshi",
    "gn:population":0,
    "gn:timezone":"Asia/Shanghai",
    "iso:country":"CN",
    "name:zho_x_preferred":[
        "\u5218\u78d0\u77f3"
    ],
    "wof:name":"Liupanshi",
    "wof:placetype":"locality"
},
  "geometry": {"coordinates":[117.536,37.2142],"type":"Point"}
}