{
  "type": "Feature",
  "properties": {
    "gn:admin1_code":"30",
    "gn:asciiname":"Xian'an",
    "gn:country_code":"CN",
    "gn:dem":58,
    "gn:feature_class":"P",
    "gn:feature_code":"PPL",
    "gn:name":"Xian\u2019an",
    "gn:population":0,
    "gn:timezone":"Asia/Urumqi",
    "iso:country":"CN",
    "name:und_x_variant":[
        "Hsien-an-hs\u00fc",
        "\u4ed9\u5b89"
    ],
    "name:zho_x_preferred":[
        "Xian\u2019an"
    ],
    "name:zho_x_variant":[
        "\u4ed9\u5b89",
        "Hsien-an-hs\u00fc"
    ],
    "wof:name":"Xian'an",
    "wof:placetype":"locality"
},
  "geometry": {"coordinates":[110.41500000000001,20.47278],"type":"Point"}
}