{
  "type": "Feature",
  "properties": {
    "gn:admin1_code":"3.0",
    "gn:asciiname":"Jianwu",
    "gn:country_code":"CN",
    "gn:dem":165,
    "gn:feature_class":"P",
    "gn:feature_code":"PPL",
    "gn:name":"Jianwu",
    "gn:population":0,
    "gn:timezone":"Asia/Shanghai",
    "iso:country":"CN",
    "name:zho_x_preferred":[
        "\u7b15\u575e"
    ],
    "wof:name":"Jianwu",
    "wof:placetype":"locality"
},
  "geometry": {"coordinates":[117.40132,28.67546],"type":"Point"}
}