{
  "type": "Feature",
  "properties": {
    "gn:admin1_code":"26.0",
    "gn:asciiname":"Huajiazhuang",
    "gn:country_code":"CN",
    "gn:dem":619,
    "gn:feature_class":"P",
    "gn:feature_code":"PPL",
    "gn:name":"Huajiazhuang",
    "gn:population":0,
    "gn:timezone":"Asia/Shanghai",
    "iso:country":"CN",
    "name:zho_x_preferred":[
        "\u534e\u5bb6\u5e84"
    ],
    "wof:name":"Huajiazhuang",
    "wof:placetype":"locality"
},
  "geometry": {"coordinates":[109.49057000000001,32.85194],"type":"Point"}
}