{
  "type": "Feature",
  "properties": {
    "gn:admin1_code":"32.0",
    "gn:asciiname":"Banjiucun",
    "gn:country_code":"CN",
    "gn:dem":3737,
    "gn:feature_class":"P",
    "gn:feature_code":"PPL",
    "gn:name":"Banjiucun",
    "gn:population":0,
    "gn:timezone":"Asia/Shanghai",
    "iso:country":"CN",
    "name:zho_x_preferred":[
        "\u73ed\u4e5d\u6751"
    ],
    "wof:name":"Banjiucun",
    "wof:placetype":"locality"
},
  "geometry": {"coordinates":[98.63809999999999,31.6679],"type":"Point"}
}