{
  "type": "Feature",
  "properties": {
    "gn:admin1_code":"4.0",
    "gn:asciiname":"Xuyang Jiuzu",
    "gn:country_code":"CN",
    "gn:dem":1,
    "gn:feature_class":"P",
    "gn:feature_code":"PPLF",
    "gn:name":"Xuyang Jiuzu",
    "gn:population":0,
    "gn:timezone":"Asia/Shanghai",
    "iso:country":"CN",
    "name:zho_x_preferred":[
        "\u5729\u6d0b\u4e5d\u7ec4"
    ],
    "wof:name":"Xuyang Jiuzu",
    "wof:placetype":"locality"
},
  "geometry": {"coordinates":[120.133,33.4331],"type":"Point"}
}