{
  "type": "Feature",
  "properties": {
    "gn:admin1_code":"7.0",
    "gn:asciiname":"Dengkeng",
    "gn:country_code":"CN",
    "gn:dem":219,
    "gn:feature_class":"P",
    "gn:feature_code":"PPL",
    "gn:name":"Dengkeng",
    "gn:population":0,
    "gn:timezone":"Asia/Shanghai",
    "iso:country":"CN",
    "name:zho_x_preferred":[
        "\u706f\u5751"
    ],
    "wof:name":"Dengkeng",
    "wof:placetype":"locality"
},
  "geometry": {"coordinates":[117.93158,26.6868],"type":"Point"}
}