{
  "type": "Feature",
  "properties": {
    "gn:admin1_code":"24.0",
    "gn:asciiname":"Dinantou",
    "gn:country_code":"CN",
    "gn:dem":1189,
    "gn:feature_class":"P",
    "gn:feature_code":"PPL",
    "gn:name":"Dinantou",
    "gn:population":0,
    "gn:timezone":"Asia/Shanghai",
    "iso:country":"CN",
    "name:zho_x_preferred":[
        "\u5730\u5357\u5934"
    ],
    "wof:name":"Dinantou",
    "wof:placetype":"locality"
},
  "geometry": {"coordinates":[113.1934,35.95019],"type":"Point"}
}