{
  "type": "Feature",
  "properties": {
    "gn:admin1_code":"12.0",
    "gn:asciiname":"Shuanglingkou",
    "gn:country_code":"CN",
    "gn:dem":26,
    "gn:feature_class":"P",
    "gn:feature_code":"PPL",
    "gn:name":"Shuanglingkou",
    "gn:population":0,
    "gn:timezone":"Asia/Shanghai",
    "iso:country":"CN",
    "name:zho_x_preferred":[
        "\u53cc\u5cad\u53e3"
    ],
    "wof:name":"Shuanglingkou",
    "wof:placetype":"locality"
},
  "geometry": {"coordinates":[113.26491,30.30555],"type":"Point"}
}