{
  "type": "Feature",
  "properties": {
    "gn:admin1_code":"25",
    "gn:asciiname":"Guoshancun",
    "gn:country_code":"CN",
    "gn:dem":106,
    "gn:feature_class":"P",
    "gn:feature_code":"PPL",
    "gn:name":"Guoshancun",
    "gn:population":0,
    "gn:timezone":"Asia/Shanghai",
    "iso:country":"CN",
    "name:zho_x_preferred":[
        "\u90ed\u5c71\u6751"
    ],
    "wof:name":"Guoshancun",
    "wof:placetype":"locality"
},
  "geometry": {"coordinates":[117.024,35.284],"type":"Point"}
}