{
  "type": "Feature",
  "properties": {
    "gn:admin1_code":"32.0",
    "gn:asciiname":"Yangtianwo",
    "gn:country_code":"CN",
    "gn:dem":2532,
    "gn:feature_class":"P",
    "gn:feature_code":"PPL",
    "gn:name":"Yangtianwo",
    "gn:population":0,
    "gn:timezone":"Asia/Shanghai",
    "iso:country":"CN",
    "name:zho_x_preferred":[
        "\u4ef0\u5929\u7a9d"
    ],
    "wof:name":"Yangtianwo",
    "wof:placetype":"locality"
},
  "geometry": {"coordinates":[101.94199999999999,27.1401],"type":"Point"}
}