{
  "type": "Feature",
  "properties": {
    "gn:admin1_code":"16",
    "gn:asciiname":"Sanpu",
    "gn:country_code":"CN",
    "gn:dem":855,
    "gn:feature_class":"P",
    "gn:feature_code":"PPL",
    "gn:name":"Sanpu",
    "gn:population":0,
    "gn:timezone":"Asia/Shanghai",
    "iso:country":"CN",
    "wof:name":"Sanpu",
    "wof:placetype":"locality"
},
  "geometry": {"coordinates":[107.09999999999999,25.36667000000001],"type":"Point"}
}