{
  "type": "Feature",
  "properties": {
    "gn:admin1_code":"10",
    "gn:asciiname":"Dongdamiao",
    "gn:country_code":"CN",
    "gn:dem":587,
    "gn:feature_class":"P",
    "gn:feature_code":"PPL",
    "gn:name":"Dongdamiao",
    "gn:population":0,
    "gn:timezone":"Asia/Shanghai",
    "iso:country":"CN",
    "name:zho_x_preferred":[
        "\u4e1c\u5927\u5e99"
    ],
    "wof:name":"Dongdamiao",
    "wof:placetype":"locality"
},
  "geometry": {"coordinates":[118.83131000000002,41.02241],"type":"Point"}
}