{
  "type": "Feature",
  "properties": {
    "gn:admin1_code":"8.0",
    "gn:asciiname":"Luoquanchezhan",
    "gn:country_code":"CN",
    "gn:dem":407,
    "gn:feature_class":"P",
    "gn:feature_code":"PPL",
    "gn:name":"Luoquanchezhan",
    "gn:population":0,
    "gn:timezone":"Asia/Shanghai",
    "iso:country":"CN",
    "name:zho_x_preferred":[
        "\u7f57\u5708\u8f66\u7ad9"
    ],
    "wof:name":"Luoquanchezhan",
    "wof:placetype":"locality"
},
  "geometry": {"coordinates":[130.93278999999998,43.7843],"type":"Point"}
}