{
  "type": "Feature",
  "properties": {
    "gn:admin1_code":"18",
    "gn:asciiname":"Wanjia Yakou",
    "gn:country_code":"CN",
    "gn:dem":1781,
    "gn:feature_class":"P",
    "gn:feature_code":"PPL",
    "gn:name":"Wanjia Yakou",
    "gn:population":0,
    "gn:timezone":"Asia/Shanghai",
    "iso:country":"CN",
    "name:zho_x_preferred":[
        "\u4e07\u5bb6\u57ad\u53e3"
    ],
    "wof:name":"Wanjia Yakou",
    "wof:placetype":"locality"
},
  "geometry": {"coordinates":[104.964,26.585],"type":"Point"}
}