{
  "type": "Feature",
  "properties": {
    "gn:admin1_code":"24.0",
    "gn:asciiname":"Shangsuocun",
    "gn:country_code":"CN",
    "gn:dem":1096,
    "gn:feature_class":"P",
    "gn:feature_code":"PPL",
    "gn:name":"Shangsuocun",
    "gn:population":0,
    "gn:timezone":"Asia/Shanghai",
    "iso:country":"CN",
    "name:zho_x_preferred":[
        "\u4e0a\u68ad\u6751"
    ],
    "wof:name":"Shangsuocun",
    "wof:placetype":"locality"
},
  "geometry": {"coordinates":[114.11162,39.46679],"type":"Point"}
}