{
  "type": "Feature",
  "properties": {
    "gn:admin1_code":"16.0",
    "gn:asciiname":"San'an",
    "gn:country_code":"CN",
    "gn:dem":46,
    "gn:feature_class":"P",
    "gn:feature_code":"PPL",
    "gn:name":"San\u2019an",
    "gn:population":0,
    "gn:timezone":"Asia/Shanghai",
    "iso:country":"CN",
    "name:und_x_variant":[
        "San\u2019an"
    ],
    "name:zho_x_preferred":[
        "\u4e09\u5cb8"
    ],
    "wof:name":"San'an",
    "wof:placetype":"locality"
},
  "geometry": {"coordinates":[109.613,23.0511],"type":"Point"}
}