{
  "type": "Feature",
  "properties": {
    "gn:admin1_code":"13",
    "gn:asciiname":"Yi'ertuan Erying",
    "gn:country_code":"CN",
    "gn:dem":1011,
    "gn:feature_class":"P",
    "gn:feature_code":"PPL",
    "gn:name":"Yi\u2019ertuan Erying",
    "gn:population":0,
    "gn:timezone":"Asia/Shanghai",
    "iso:country":"CN",
    "name:und_x_variant":[
        "Yi\u2019ertuan Erying",
        "\u4e00\u4e8c\u56e2\u4e8c\u8425"
    ],
    "wof:name":"Yi'ertuan Erying",
    "wof:placetype":"locality"
},
  "geometry": {"coordinates":[81.39431,40.55789],"type":"Point"}
}