{
  "type": "Feature",
  "properties": {
    "gn:admin1_code":"14.0",
    "gn:asciiname":"Mazha Gongmacun",
    "gn:country_code":"CN",
    "gn:dem":4759,
    "gn:feature_class":"P",
    "gn:feature_code":"PPL",
    "gn:name":"Mazha Gongmacun",
    "gn:population":0,
    "gn:timezone":"Asia/Urumqi",
    "iso:country":"CN",
    "name:zho_x_preferred":[
        "\u739b\u624e\u8d21\u739b\u6751"
    ],
    "wof:name":"Mazha Gongmacun",
    "wof:placetype":"locality"
},
  "geometry": {"coordinates":[92.52479,32.28013],"type":"Point"}
}