{
  "type": "Feature",
  "properties": {
    "gn:admin1_code":"7.0",
    "gn:asciiname":"Shanghuacun",
    "gn:country_code":"CN",
    "gn:dem":429,
    "gn:feature_class":"P",
    "gn:feature_code":"PPL",
    "gn:name":"Shanghuacun",
    "gn:population":0,
    "gn:timezone":"Asia/Shanghai",
    "iso:country":"CN",
    "name:und_x_variant":[
        "\u4e0a\u534e\u6751"
    ],
    "name:zho_x_preferred":[
        "\u4e0a\u534e\u6751"
    ],
    "wof:name":"Shanghuacun",
    "wof:placetype":"locality"
},
  "geometry": {"coordinates":[117.09516000000001,26.57663],"type":"Point"}
}