{
  "type": "Feature",
  "properties": {
    "gn:admin1_code":"32.0",
    "gn:asciiname":"Shima",
    "gn:country_code":"CN",
    "gn:dem":1318,
    "gn:feature_class":"P",
    "gn:feature_code":"PPL",
    "gn:name":"Shima",
    "gn:population":0,
    "gn:timezone":"Asia/Shanghai",
    "iso:country":"CN",
    "name:ceb_x_preferred":[
        "Shima"
    ],
    "name:deu_x_preferred":[
        "Shima"
    ],
    "name:fra_x_preferred":[
        "Shima"
    ],
    "name:heb_x_preferred":[
        "\u05e9\u05d9\u05de\u05d4"
    ],
    "name:mlg_x_preferred":[
        "Shima"
    ],
    "name:nds_x_preferred":[
        "Shima"
    ],
    "name:por_x_preferred":[
        "Shima"
    ],
    "name:ron_x_preferred":[
        "Shima"
    ],
    "name:swe_x_preferred":[
        "Shima"
    ],
    "name:zho_x_preferred":[
        "\u77f3\u9a6c"
    ],
    "wof:name":"Shima",
    "wof:placetype":"locality"
},
  "geometry": {"coordinates":[104.626,32.4141],"type":"Point"}
}