{
  "type": "Feature",
  "properties": {
    "gn:admin1_code":"19.0",
    "gn:asciiname":"Jinxingtun",
    "gn:country_code":"CN",
    "gn:dem":234,
    "gn:feature_class":"P",
    "gn:feature_code":"PPL",
    "gn:name":"Jinxingtun",
    "gn:population":0,
    "gn:timezone":"Asia/Shanghai",
    "iso:country":"CN",
    "name:und_x_variant":[
        "\u91d1\u661f\u5c6f"
    ],
    "name:zho_x_preferred":[
        "\u91d1\u661f\u5c6f"
    ],
    "wof:name":"Jinxingtun",
    "wof:placetype":"locality"
},
  "geometry": {"coordinates":[124.82679,42.65313],"type":"Point"}
}