{
  "type": "Feature",
  "properties": {
    "gn:admin1_code":"3",
    "gn:asciiname":"Shijietou",
    "gn:country_code":"CN",
    "gn:dem":1336,
    "gn:feature_class":"P",
    "gn:feature_code":"PPL",
    "gn:name":"Shijietou",
    "gn:population":0,
    "gn:timezone":"Asia/Shanghai",
    "iso:country":"CN",
    "name:zho_x_preferred":[
        "\u77f3\u8857\u5934"
    ],
    "wof:name":"Shijietou",
    "wof:placetype":"locality"
},
  "geometry": {"coordinates":[114.023,25.9713],"type":"Point"}
}