{
  "type": "Feature",
  "properties": {
    "gn:admin1_code":"15",
    "gn:asciiname":"Zhonghepu",
    "gn:country_code":"CN",
    "gn:dem":1316,
    "gn:feature_class":"P",
    "gn:feature_code":"PPL",
    "gn:name":"Zhonghepu",
    "gn:population":0,
    "gn:timezone":"Asia/Shanghai",
    "iso:country":"CN",
    "name:zho_x_preferred":[
        "\u4e2d\u5408\u94fa"
    ],
    "wof:name":"Zhonghepu",
    "wof:placetype":"locality"
},
  "geometry": {"coordinates":[107.408,35.9963],"type":"Point"}
}