{
  "type": "Feature",
  "properties": {
    "gn:admin1_code":"05",
    "gn:asciiname":"Diyingou Linchang",
    "gn:country_code":"CN",
    "gn:dem":760,
    "gn:feature_class":"P",
    "gn:feature_code":"PPLF",
    "gn:name":"Diyingou Linchang",
    "gn:population":0,
    "gn:timezone":"Asia/Shanghai",
    "iso:country":"CN",
    "name:und_x_variant":[
        "Ti-yin-kou",
        "Diyingou",
        "Diyingou Linchang",
        "\u5730\u836b\u6c9f\u6797\u573a",
        "\u5730\u836b\u6c9f"
    ],
    "wof:name":"Diyingou Linchang",
    "wof:placetype":"locality"
},
  "geometry": {"coordinates":[130.26424,43.45277],"type":"Point"}
}