{
  "type": "Feature",
  "properties": {
    "gn:admin1_code":"1.0",
    "gn:asciiname":"Honglingcun",
    "gn:country_code":"CN",
    "gn:dem":238,
    "gn:feature_class":"P",
    "gn:feature_code":"PPL",
    "gn:name":"Honglingcun",
    "gn:population":0,
    "gn:timezone":"Asia/Shanghai",
    "iso:country":"CN",
    "name:zho_x_preferred":[
        "\u7ea2\u5cad\u6751"
    ],
    "wof:name":"Honglingcun",
    "wof:placetype":"locality"
},
  "geometry": {"coordinates":[118.63672,30.60132],"type":"Point"}
}