{
  "type": "Feature",
  "properties": {
    "gn:admin1_code":"10",
    "gn:asciiname":"Licun",
    "gn:country_code":"CN",
    "gn:dem":11,
    "gn:feature_class":"P",
    "gn:feature_code":"PPL",
    "gn:name":"Licun",
    "gn:population":0,
    "gn:timezone":"Asia/Shanghai",
    "iso:country":"CN",
    "name:und_x_variant":[
        "Li-ts\u2019un-chen",
        "Li-ts\u2019un",
        "Licun"
    ],
    "name:zho_x_preferred":[
        "\u674e\u6751"
    ],
    "wof:name":"Licun",
    "wof:placetype":"locality"
},
  "geometry": {"coordinates":[117.13800000000001,38.5385],"type":"Point"}
}