{
  "type": "Feature",
  "properties": {
    "gn:admin1_code":"11",
    "gn:asciiname":"Shishanjiaoxia",
    "gn:country_code":"CN",
    "gn:dem":267,
    "gn:feature_class":"P",
    "gn:feature_code":"PPL",
    "gn:name":"Shishanjiaoxia",
    "gn:population":0,
    "gn:timezone":"Asia/Shanghai",
    "iso:country":"CN",
    "name:zho_x_preferred":[
        "\u77f3\u5c71\u811a\u4e0b"
    ],
    "wof:name":"Shishanjiaoxia",
    "wof:placetype":"locality"
},
  "geometry": {"coordinates":[111.04398999999999,26.69445],"type":"Point"}
}