{
  "type": "Feature",
  "properties": {
    "gn:admin1_code":"11.0",
    "gn:asciiname":"Guanjiatai",
    "gn:country_code":"CN",
    "gn:dem":151,
    "gn:feature_class":"P",
    "gn:feature_code":"PPL",
    "gn:name":"Guanjiatai",
    "gn:population":0,
    "gn:timezone":"Asia/Shanghai",
    "iso:country":"CN",
    "name:zho_x_preferred":[
        "Guanjiatai"
    ],
    "name:zho_x_variant":[
        "\u5173\u5bb6\u53f0"
    ],
    "wof:name":"Guanjiatai",
    "wof:placetype":"locality"
},
  "geometry": {"coordinates":[111.44231000000001,29.68936],"type":"Point"}
}