{
  "type": "Feature",
  "properties": {
    "gn:admin1_code":"3.0",
    "gn:asciiname":"Zhaixia",
    "gn:country_code":"CN",
    "gn:dem":106,
    "gn:feature_class":"P",
    "gn:feature_code":"PPL",
    "gn:name":"Zhaixia",
    "gn:population":0,
    "gn:timezone":"Asia/Shanghai",
    "iso:country":"CN",
    "name:und_x_variant":[
        "\u5be8\u4e0b"
    ],
    "wof:name":"Zhaixia",
    "wof:placetype":"locality"
},
  "geometry": {"coordinates":[114.42008,28.04203],"type":"Point"}
}