{
  "type": "Feature",
  "properties": {
    "gn:admin1_code":"31",
    "gn:asciiname":"Huwei Linchang",
    "gn:country_code":"CN",
    "gn:dem":36,
    "gn:feature_class":"P",
    "gn:feature_code":"PPLF",
    "gn:name":"Huwei Linchang",
    "gn:population":0,
    "gn:timezone":"Asia/Shanghai",
    "iso:country":"CN",
    "name:und_x_variant":[
        "Puqian Linchang",
        "Huwei Linchang",
        "\u864e\u5a01\u6797\u573a"
    ],
    "wof:name":"Huwei Linchang",
    "wof:placetype":"locality"
},
  "geometry": {"coordinates":[110.67972,20.15278],"type":"Point"}
}