{
  "type": "Feature",
  "properties": {
    "gn:admin1_code":"10",
    "gn:asciiname":"Daodi",
    "gn:cc2":"CN",
    "gn:country_code":"CN",
    "gn:dem":9,
    "gn:feature_class":"P",
    "gn:feature_code":"PPL",
    "gn:name":"Daodi",
    "gn:population":0,
    "gn:timezone":"Asia/Shanghai",
    "iso:country":"CN",
    "name:und_x_variant":[
        "Tao-ti",
        "Tao-ti-chen",
        "Daodi"
    ],
    "wof:name":"Daodi",
    "wof:placetype":"locality"
},
  "geometry": {"coordinates":[118.18333,39.53333],"type":"Point"}
}