{
  "type": "Feature",
  "properties": {
    "gn:admin1_code":"32.0",
    "gn:asciiname":"Goudi",
    "gn:country_code":"CN",
    "gn:dem":1506,
    "gn:feature_class":"P",
    "gn:feature_code":"PPL",
    "gn:name":"Goudi",
    "gn:population":0,
    "gn:timezone":"Asia/Shanghai",
    "iso:country":"CN",
    "name:deu_x_preferred":[
        "Goudi"
    ],
    "name:ell_x_preferred":[
        "\u0393\u03bf\u03c5\u03b4\u03ae"
    ],
    "name:fin_x_preferred":[
        "Goud\u00ed"
    ],
    "name:fra_x_preferred":[
        "Goud\u00ed"
    ],
    "name:rus_x_preferred":[
        "\u0413\u0443\u0434\u0438"
    ],
    "name:ukr_x_preferred":[
        "\u0413\u0443\u0434\u0456"
    ],
    "name:zho_x_preferred":[
        "\u6c9f\u5e95"
    ],
    "wof:name":"Goudi",
    "wof:placetype":"locality"
},
  "geometry": {"coordinates":[104.52401999999999,32.50865],"type":"Point"}
}