{
  "type": "Feature",
  "properties": {
    "gn:admin1_code":"15.0",
    "gn:asciiname":"Qigong",
    "gn:country_code":"CN",
    "gn:dem":1148,
    "gn:feature_class":"P",
    "gn:feature_code":"PPL",
    "gn:name":"Qigong",
    "gn:population":0,
    "gn:timezone":"Asia/Urumqi",
    "iso:country":"CN",
    "name:zho_x_preferred":[
        "\u4e03\u5de5"
    ],
    "wof:name":"Qigong",
    "wof:placetype":"locality"
},
  "geometry": {"coordinates":[95.6373,40.4009],"type":"Point"}
}