{
  "type": "Feature",
  "properties": {
    "gn:admin1_code":"15.0",
    "gn:asciiname":"Qigong",
    "gn:country_code":"CN",
    "gn:dem":1148,
    "gn:feature_class":"P",
    "gn:feature_code":"PPL",
    "gn:name":"Qigong",
    "gn:population":0,
    "gn:timezone":"Asia/Urumqi",
    "iso:country":"CN",
    "name:ara_x_preferred":[
        "\u062a\u0634\u064a \u0643\u0648\u0646\u063a"
    ],
    "name:ast_x_preferred":[
        "Qigong"
    ],
    "name:bul_x_preferred":[
        "\u0426\u0438 \u0433\u0443\u043d"
    ],
    "name:cat_x_preferred":[
        "Txikung"
    ],
    "name:ces_x_preferred":[
        "\u010cchi-kung"
    ],
    "name:dan_x_preferred":[
        "Qigong"
    ],
    "name:deu_x_preferred":[
        "Qigong"
    ],
    "name:ell_x_preferred":[
        "\u03a4\u03c3\u03b9 \u03ba\u03bf\u03c5\u03bd\u03b3\u03ba"
    ],
    "name:epo_x_preferred":[
        "\u0108igongo"
    ],
    "name:est_x_preferred":[
        "Qigong"
    ],
    "name:eus_x_preferred":[
        "Qigong"
    ],
    "name:fas_x_preferred":[
        "\u0686\u06cc \u06a9\u0648\u0646\u06af"
    ],
    "name:fin_x_preferred":[
        "Qigong"
    ],
    "name:fra_x_preferred":[
        "Qi gong"
    ],
    "name:heb_x_preferred":[
        "\u05e6'\u05d9 \u05e7\u05d5\u05e0\u05d2"
    ],
    "name:hrv_x_preferred":[
        "Chi Kung"
    ],
    "name:hun_x_preferred":[
        "Csikung"
    ],
    "name:ind_x_preferred":[
        "Qigong"
    ],
    "name:ita_x_preferred":[
        "Qi Gong"
    ],
    "name:jav_x_preferred":[
        "Qigong"
    ],
    "name:kor_x_preferred":[
        "\uae30\uacf5"
    ],
    "name:lav_x_preferred":[
        "Ciguns"
    ],
    "name:lit_x_preferred":[
        "\u010cigongas"
    ],
    "name:msa_x_preferred":[
        "Qigong"
    ],
    "name:mya_x_preferred":[
        "\u1001\u103b\u102d\u1000\u102f\u1014\u103a\u1038"
    ],
    "name:nld_x_preferred":[
        "Qi gong"
    ],
    "name:nno_x_preferred":[
        "Qigong"
    ],
    "name:nor_x_preferred":[
        "Qi gong"
    ],
    "name:oci_x_preferred":[
        "Q\u00ecg\u014dng"
    ],
    "name:pol_x_preferred":[
        "Qigong"
    ],
    "name:por_x_preferred":[
        "Qigong"
    ],
    "name:ron_x_preferred":[
        "Qigong"
    ],
    "name:rus_x_preferred":[
        "\u0426\u0438\u0433\u0443\u043d"
    ],
    "name:sco_x_preferred":[
        "Qigong"
    ],
    "name:slv_x_preferred":[
        "Qigong"
    ],
    "name:spa_x_preferred":[
        "Chi kung"
    ],
    "name:srp_x_preferred":[
        "\u0427\u0438 \u043a\u0443\u043d\u0433"
    ],
    "name:swe_x_preferred":[
        "Qigong"
    ],
    "name:tha_x_preferred":[
        "\u0e0a\u0e35\u0e48\u0e01\u0e07"
    ],
    "name:tur_x_preferred":[
        "\u00c7igong"
    ],
    "name:ukr_x_preferred":[
        "\u0426\u0456\u0491\u0443\u043d"
    ],
    "name:vie_x_preferred":[
        "Kh\u00ed c\u00f4ng"
    ],
    "name:zho_x_preferred":[
        "\u4e03\u5de5"
    ],
    "wof:name":"Qigong",
    "wof:placetype":"locality"
},
  "geometry": {"coordinates":[95.6373,40.4009],"type":"Point"}
}