{
  "type": "Feature",
  "properties": {
    "gn:admin1_code":"25.0",
    "gn:asciiname":"Daheyacun",
    "gn:country_code":"CN",
    "gn:dem":106,
    "gn:feature_class":"P",
    "gn:feature_code":"PPL",
    "gn:name":"Daheyacun",
    "gn:population":0,
    "gn:timezone":"Asia/Shanghai",
    "iso:country":"CN",
    "name:zho_x_preferred":[
        "\u5927\u6cb3\u5d16\u6751"
    ],
    "wof:name":"Daheyacun",
    "wof:placetype":"locality"
},
  "geometry": {"coordinates":[120.65889,37.22615],"type":"Point"}
}