{
  "type": "Feature",
  "properties": {
    "gn:admin1_code":"9.0",
    "gn:asciiname":"Taihoumiao",
    "gn:country_code":"CN",
    "gn:dem":422,
    "gn:feature_class":"P",
    "gn:feature_code":"PPL",
    "gn:name":"Taihoumiao",
    "gn:population":0,
    "gn:timezone":"Asia/Shanghai",
    "iso:country":"CN",
    "name:zho_x_preferred":[
        "\u592a\u540e\u5e99"
    ],
    "wof:name":"Taihoumiao",
    "wof:placetype":"locality"
},
  "geometry": {"coordinates":[112.94848,34.41893],"type":"Point"}
}