{
  "type": "Feature",
  "properties": {
    "gn:admin1_code":"11.0",
    "gn:asciiname":"Mao'aolong",
    "gn:country_code":"CN",
    "gn:dem":1147,
    "gn:feature_class":"P",
    "gn:feature_code":"PPL",
    "gn:name":"Mao\u2019aolong",
    "gn:population":0,
    "gn:timezone":"Asia/Shanghai",
    "iso:country":"CN",
    "name:und_x_variant":[
        "Mao\u2019aolong"
    ],
    "name:zho_x_preferred":[
        "\u8305\u5773\u5784"
    ],
    "wof:name":"Mao'aolong",
    "wof:placetype":"locality"
},
  "geometry": {"coordinates":[110.7354,27.57576],"type":"Point"}
}