{
  "type": "Feature",
  "properties": {
    "gn:admin1_code":"33.0",
    "gn:asciiname":"Huilongshan",
    "gn:country_code":"CN",
    "gn:dem":470,
    "gn:feature_class":"P",
    "gn:feature_code":"PPL",
    "gn:name":"Huilongshan",
    "gn:population":0,
    "gn:timezone":"Asia/Shanghai",
    "iso:country":"CN",
    "name:zho_x_preferred":[
        "\u56de\u9f99\u5c71"
    ],
    "wof:name":"Huilongshan",
    "wof:placetype":"locality"
},
  "geometry": {"coordinates":[107.83893999999999,30.75969000000001],"type":"Point"}
}