{
  "type": "Feature",
  "properties": {
    "gn:admin1_code":"25.0",
    "gn:asciiname":"Weiwan",
    "gn:cc2":"CN",
    "gn:country_code":"CN",
    "gn:dem":54,
    "gn:feature_class":"P",
    "gn:feature_code":"PPL",
    "gn:name":"Weiwan",
    "gn:population":0,
    "gn:timezone":"Asia/Shanghai",
    "iso:country":"CN",
    "name:und_x_variant":[
        "Wei-wan-chi",
        "Weiwan"
    ],
    "wof:name":"Weiwan",
    "wof:placetype":"locality"
},
  "geometry": {"coordinates":[115.34999999999999,34.88333],"type":"Point"}
}