{
  "type": "Feature",
  "properties": {
    "gn:admin1_code":"19.0",
    "gn:asciiname":"Lujiajie",
    "gn:country_code":"CN",
    "gn:dem":324,
    "gn:feature_class":"P",
    "gn:feature_code":"PPL",
    "gn:name":"Lujiajie",
    "gn:population":0,
    "gn:timezone":"Asia/Shanghai",
    "iso:country":"CN",
    "name:und_x_variant":[
        "\u9646\u5bb6\u8857"
    ],
    "wof:name":"Lujiajie",
    "wof:placetype":"locality"
},
  "geometry": {"coordinates":[123.76714,40.6745],"type":"Point"}
}