{
  "type": "Feature",
  "properties": {
    "gn:admin1_code":"14.0",
    "gn:asciiname":"Xiaquesuocun",
    "gn:country_code":"CN",
    "gn:dem":4570,
    "gn:feature_class":"P",
    "gn:feature_code":"PPL",
    "gn:name":"Xiaquesuocun",
    "gn:population":0,
    "gn:timezone":"Asia/Urumqi",
    "iso:country":"CN",
    "name:zho_x_preferred":[
        "\u4e0b\u7f3a\u6240\u6751"
    ],
    "wof:name":"Xiaquesuocun",
    "wof:placetype":"locality"
},
  "geometry": {"coordinates":[98.85984999999999,30.51772],"type":"Point"}
}