{
  "type": "Feature",
  "properties": {
    "gn:admin1_code":"30.0",
    "gn:asciiname":"Mianyangcun",
    "gn:country_code":"CN",
    "gn:dem":206,
    "gn:feature_class":"P",
    "gn:feature_code":"PPL",
    "gn:name":"Mianyangcun",
    "gn:population":0,
    "gn:timezone":"Asia/Shanghai",
    "iso:country":"CN",
    "name:zho_x_preferred":[
        "\u68c9\u7f8a\u6751"
    ],
    "wof:name":"Mianyangcun",
    "wof:placetype":"locality"
},
  "geometry": {"coordinates":[115.8717,24.50463],"type":"Point"}
}