{
  "type": "Feature",
  "properties": {
    "gn:admin1_code":"21.0",
    "gn:asciiname":"Xingshugou",
    "gn:country_code":"CN",
    "gn:dem":1821,
    "gn:feature_class":"P",
    "gn:feature_code":"PPL",
    "gn:name":"Xingshugou",
    "gn:population":0,
    "gn:timezone":"Asia/Shanghai",
    "iso:country":"CN",
    "name:zho_x_preferred":[
        "\u674f\u6811\u6c9f"
    ],
    "wof:name":"Xingshugou",
    "wof:placetype":"locality"
},
  "geometry": {"coordinates":[105.30500000000001,37.2507],"type":"Point"}
}