{
  "type": "Feature",
  "properties": {
    "gn:admin1_code":"10.0",
    "gn:asciiname":"Yudi",
    "gn:country_code":"CN",
    "gn:dem":93,
    "gn:feature_class":"P",
    "gn:feature_code":"PPL",
    "gn:name":"Yudi",
    "gn:population":0,
    "gn:timezone":"Asia/Shanghai",
    "iso:country":"CN",
    "name:und_x_variant":[
        "\u6de4\u5824"
    ],
    "wof:name":"Yudi",
    "wof:placetype":"locality"
},
  "geometry": {"coordinates":[114.6031,38.44334],"type":"Point"}
}