{
  "type": "Feature",
  "properties": {
    "gn:admin1_code":"16.0",
    "gn:asciiname":"Weinang",
    "gn:country_code":"CN",
    "gn:dem":685,
    "gn:feature_class":"P",
    "gn:feature_code":"PPL",
    "gn:name":"Weinang",
    "gn:population":0,
    "gn:timezone":"Asia/Shanghai",
    "iso:country":"CN",
    "name:zho_x_preferred":[
        "\u6e2d\u56ca"
    ],
    "wof:name":"Weinang",
    "wof:placetype":"locality"
},
  "geometry": {"coordinates":[106.148,24.2729],"type":"Point"}
}