{
  "type": "Feature",
  "properties": {
    "gn:admin1_code":"32.0",
    "gn:asciiname":"Shuangfengyuan",
    "gn:country_code":"CN",
    "gn:dem":1148,
    "gn:feature_class":"P",
    "gn:feature_code":"PPL",
    "gn:name":"Shuangfengyuan",
    "gn:population":0,
    "gn:timezone":"Asia/Shanghai",
    "iso:country":"CN",
    "name:zho_x_preferred":[
        "\u53cc\u51e4\u56ed"
    ],
    "wof:name":"Shuangfengyuan",
    "wof:placetype":"locality"
},
  "geometry": {"coordinates":[105.655,28.2172],"type":"Point"}
}