{
  "type": "Feature",
  "properties": {
    "gn:admin1_code":"7.0",
    "gn:asciiname":"Daling Xiacun",
    "gn:country_code":"CN",
    "gn:dem":256,
    "gn:feature_class":"P",
    "gn:feature_code":"PPL",
    "gn:name":"Daling Xiacun",
    "gn:population":0,
    "gn:timezone":"Asia/Shanghai",
    "iso:country":"CN",
    "name:zho_x_preferred":[
        "\u5927\u5cad\u4e0b\u6751"
    ],
    "wof:name":"Daling Xiacun",
    "wof:placetype":"locality"
},
  "geometry": {"coordinates":[116.51824000000001,24.64262],"type":"Point"}
}