{
  "type": "Feature",
  "properties": {
    "gn:admin1_code":"16.0",
    "gn:asciiname":"Wentan",
    "gn:country_code":"CN",
    "gn:dem":126,
    "gn:feature_class":"P",
    "gn:feature_code":"PPL",
    "gn:name":"Wentan",
    "gn:population":0,
    "gn:timezone":"Asia/Shanghai",
    "iso:country":"CN",
    "name:zho_x_preferred":[
        "\u6587\u575b"
    ],
    "wof:name":"Wentan",
    "wof:placetype":"locality"
},
  "geometry": {"coordinates":[108.366,23.1545],"type":"Point"}
}