{
  "type": "Feature",
  "properties": {
    "gn:admin1_code":"2",
    "gn:asciiname":"Yangjiaqing",
    "gn:country_code":"CN",
    "gn:dem":380,
    "gn:feature_class":"P",
    "gn:feature_code":"PPL",
    "gn:name":"Yangjiaqing",
    "gn:population":0,
    "gn:timezone":"Asia/Shanghai",
    "iso:country":"CN",
    "wof:name":"Yangjiaqing",
    "wof:placetype":"locality"
},
  "geometry": {"coordinates":[118.54555999999999,28.85639],"type":"Point"}
}