{
  "type": "Feature",
  "properties": {
    "gn:admin1_code":"4.0",
    "gn:asciiname":"Nijiaxiangcun",
    "gn:country_code":"CN",
    "gn:dem":6,
    "gn:feature_class":"P",
    "gn:feature_code":"PPL",
    "gn:name":"Nijiaxiangcun",
    "gn:population":0,
    "gn:timezone":"Asia/Shanghai",
    "iso:country":"CN",
    "name:zho_x_preferred":[
        "\u502a\u5bb6\u5df7\u6751"
    ],
    "wof:name":"Nijiaxiangcun",
    "wof:placetype":"locality"
},
  "geometry": {"coordinates":[120.38312000000001,31.87549000000001],"type":"Point"}
}