{
  "type": "Feature",
  "properties": {
    "gn:admin1_code":"25",
    "gn:asciiname":"Suizhuang",
    "gn:country_code":"CN",
    "gn:dem":25,
    "gn:feature_class":"P",
    "gn:feature_code":"PPL",
    "gn:name":"Suizhuang",
    "gn:population":0,
    "gn:timezone":"Asia/Shanghai",
    "iso:country":"CN",
    "name:zho_x_preferred":[
        "\u968b\u5e84"
    ],
    "wof:name":"Suizhuang",
    "wof:placetype":"locality"
},
  "geometry": {"coordinates":[116.515,37.0483],"type":"Point"}
}