{
  "type": "Feature",
  "properties": {
    "gn:admin1_code":"4.0",
    "gn:asciiname":"Cuizhuangcun",
    "gn:country_code":"CN",
    "gn:dem":34,
    "gn:feature_class":"P",
    "gn:feature_code":"PPL",
    "gn:name":"Cuizhuangcun",
    "gn:population":0,
    "gn:timezone":"Asia/Shanghai",
    "iso:country":"CN",
    "name:zho_x_preferred":[
        "\u5d14\u5e84\u6751"
    ],
    "wof:name":"Cuizhuangcun",
    "wof:placetype":"locality"
},
  "geometry": {"coordinates":[117.24408,34.20172],"type":"Point"}
}