{
  "type": "Feature",
  "properties": {
    "gn:admin1_code":"26.0",
    "gn:asciiname":"Zhoujia Taizi",
    "gn:country_code":"CN",
    "gn:dem":1672,
    "gn:feature_class":"P",
    "gn:feature_code":"PPL",
    "gn:name":"Zhoujia Taizi",
    "gn:population":0,
    "gn:timezone":"Asia/Shanghai",
    "iso:country":"CN",
    "name:und_x_variant":[
        "\u5468\u5bb6\u53f0\u5b50"
    ],
    "wof:name":"Zhoujia Taizi",
    "wof:placetype":"locality"
},
  "geometry": {"coordinates":[109.72074000000001,34.22045],"type":"Point"}
}