{
  "type": "Feature",
  "properties": {
    "gn:admin1_code":"11",
    "gn:asciiname":"Shuiyuantou",
    "gn:country_code":"CN",
    "gn:dem":211,
    "gn:feature_class":"P",
    "gn:feature_code":"PPL",
    "gn:name":"Shuiyuantou",
    "gn:population":0,
    "gn:timezone":"Asia/Shanghai",
    "iso:country":"CN",
    "name:zho_x_preferred":[
        "\u6c34\u6e90\u5934"
    ],
    "wof:name":"Shuiyuantou",
    "wof:placetype":"locality"
},
  "geometry": {"coordinates":[111.48177,25.55159],"type":"Point"}
}