{
  "type": "Feature",
  "properties": {
    "gn:admin1_code":"14.0",
    "gn:asciiname":"Dongjian",
    "gn:country_code":"CN",
    "gn:dem":4589,
    "gn:feature_class":"P",
    "gn:feature_code":"PPL",
    "gn:name":"Dongjian",
    "gn:population":0,
    "gn:timezone":"Asia/Urumqi",
    "iso:country":"CN",
    "name:zho_x_preferred":[
        "\u8463\u95f4"
    ],
    "wof:name":"Dongjian",
    "wof:placetype":"locality"
},
  "geometry": {"coordinates":[86.6074,29.4455],"type":"Point"}
}