{
  "type": "Feature",
  "properties": {
    "gn:admin1_code":"25",
    "gn:asciiname":"Qianqizhuang",
    "gn:country_code":"CN",
    "gn:dem":66,
    "gn:feature_class":"P",
    "gn:feature_code":"PPL",
    "gn:name":"Qianqizhuang",
    "gn:population":0,
    "gn:timezone":"Asia/Shanghai",
    "iso:country":"CN",
    "name:zho_x_preferred":[
        "\u524d\u9f50\u5e84"
    ],
    "wof:name":"Qianqizhuang",
    "wof:placetype":"locality"
},
  "geometry": {"coordinates":[118.60299999999999,35.0724],"type":"Point"}
}