{
  "type": "Feature",
  "properties": {
    "gn:admin1_code":"3.0",
    "gn:asciiname":"Tuchong",
    "gn:country_code":"CN",
    "gn:dem":283,
    "gn:feature_class":"P",
    "gn:feature_code":"PPL",
    "gn:name":"Tuchong",
    "gn:population":0,
    "gn:timezone":"Asia/Shanghai",
    "iso:country":"CN",
    "name:und_x_variant":[
        "\u571f\u51b2"
    ],
    "wof:name":"Tuchong",
    "wof:placetype":"locality"
},
  "geometry": {"coordinates":[114.03725,27.96965],"type":"Point"}
}