{
  "type": "Feature",
  "properties": {
    "gn:admin1_code":"26.0",
    "gn:asciiname":"Shangjucun",
    "gn:country_code":"CN",
    "gn:dem":683,
    "gn:feature_class":"P",
    "gn:feature_code":"PPL",
    "gn:name":"Shangjucun",
    "gn:population":0,
    "gn:timezone":"Asia/Shanghai",
    "iso:country":"CN",
    "name:und_x_variant":[
        "\u5c1a\u5de8\u6751"
    ],
    "wof:name":"Shangjucun",
    "wof:placetype":"locality"
},
  "geometry": {"coordinates":[107.37544,33.26866],"type":"Point"}
}