{
  "type": "Feature",
  "properties": {
    "gn:admin1_code":"4.0",
    "gn:asciiname":"Longwangdiandai",
    "gn:country_code":"CN",
    "gn:dem":1,
    "gn:feature_class":"P",
    "gn:feature_code":"PPL",
    "gn:name":"Longwangdiandai",
    "gn:population":0,
    "gn:timezone":"Asia/Shanghai",
    "iso:country":"CN",
    "name:zho_x_preferred":[
        "\u9f99\u738b\u6bbf\u5788"
    ],
    "wof:name":"Longwangdiandai",
    "wof:placetype":"locality"
},
  "geometry": {"coordinates":[120.24518999999999,32.04384],"type":"Point"}
}