{
  "type": "Feature",
  "properties": {
    "gn:admin1_code":"29.0",
    "gn:asciiname":"Maxianying",
    "gn:country_code":"CN",
    "gn:dem":1910,
    "gn:feature_class":"P",
    "gn:feature_code":"PPL",
    "gn:name":"Maxianying",
    "gn:population":0,
    "gn:timezone":"Asia/Shanghai",
    "iso:country":"CN",
    "name:zho_x_preferred":[
        "\u9ebb\u7ebf\u8425"
    ],
    "wof:name":"Maxianying",
    "wof:placetype":"locality"
},
  "geometry": {"coordinates":[102.729,25.066],"type":"Point"}
}