{
  "type": "Feature",
  "properties": {
    "gn:admin1_code":"9.0",
    "gn:asciiname":"Tongshukeng",
    "gn:country_code":"CN",
    "gn:dem":754,
    "gn:feature_class":"P",
    "gn:feature_code":"PPL",
    "gn:name":"Tongshukeng",
    "gn:population":0,
    "gn:timezone":"Asia/Shanghai",
    "iso:country":"CN",
    "name:zho_x_preferred":[
        "\u6850\u6811\u5751"
    ],
    "wof:name":"Tongshukeng",
    "wof:placetype":"locality"
},
  "geometry": {"coordinates":[111.7343,34.84808],"type":"Point"}
}