{
  "type": "Feature",
  "properties": {
    "gn:admin1_code":"25",
    "gn:asciiname":"Jiaonan",
    "gn:country_code":"CN",
    "gn:dem":189,
    "gn:feature_class":"P",
    "gn:feature_code":"PPL",
    "gn:name":"Jiaonan",
    "gn:population":0,
    "gn:timezone":"Asia/Shanghai",
    "iso:country":"CN",
    "name:zho_x_preferred":[
        "\u7126\u5357"
    ],
    "wof:name":"Jiaonan",
    "wof:placetype":"locality"
},
  "geometry": {"coordinates":[117.331,36.3052],"type":"Point"}
}