{
  "type": "Feature",
  "properties": {
    "gn:admin1_code":"25",
    "gn:asciiname":"Jiaonan",
    "gn:country_code":"CN",
    "gn:dem":189,
    "gn:feature_class":"P",
    "gn:feature_code":"PPL",
    "gn:name":"Jiaonan",
    "gn:population":0,
    "gn:timezone":"Asia/Shanghai",
    "iso:country":"CN",
    "name:ceb_x_preferred":[
        "Jiaonan Shi"
    ],
    "name:deu_x_preferred":[
        "Jiaonan"
    ],
    "name:fas_x_preferred":[
        "\u062c\u06cc\u0627\u0648\u0646\u0627\u0646"
    ],
    "name:fra_x_preferred":[
        "Jiaonan"
    ],
    "name:jpn_x_preferred":[
        "\u81a0\u5357\u5e02"
    ],
    "name:kor_x_preferred":[
        "\uc790\uc624\ub09c\uc2dc"
    ],
    "name:nor_x_preferred":[
        "Jiaonan"
    ],
    "name:swe_x_preferred":[
        "Jiaonan"
    ],
    "name:vie_x_preferred":[
        "Giao Nam"
    ],
    "name:zho_x_preferred":[
        "\u7126\u5357"
    ],
    "name:zho_x_variant":[
        "\u80f6\u5357\u5e02"
    ],
    "wof:name":"Jiaonan",
    "wof:placetype":"locality"
},
  "geometry": {"coordinates":[117.331,36.3052],"type":"Point"}
}