{
  "type": "Feature",
  "properties": {
    "gn:admin1_code":"29.0",
    "gn:asciiname":"Jiariding",
    "gn:country_code":"CN",
    "gn:dem":2773,
    "gn:feature_class":"P",
    "gn:feature_code":"PPL",
    "gn:name":"Jiariding",
    "gn:population":0,
    "gn:timezone":"Asia/Shanghai",
    "iso:country":"CN",
    "name:zho_x_preferred":[
        "\u7532\u65e5\u9876"
    ],
    "wof:name":"Jiariding",
    "wof:placetype":"locality"
},
  "geometry": {"coordinates":[98.85339999999999,28.1646],"type":"Point"}
}