{
  "type": "Feature",
  "properties": {
    "gn:admin1_code":"10",
    "gn:asciiname":"Fenshuiling",
    "gn:country_code":"CN",
    "gn:dem":461,
    "gn:feature_class":"P",
    "gn:feature_code":"PPL",
    "gn:name":"Fenshuiling",
    "gn:population":0,
    "gn:timezone":"Asia/Shanghai",
    "iso:country":"CN",
    "name:zho_x_preferred":[
        "\u5206\u6c34\u5cad"
    ],
    "wof:name":"Fenshuiling",
    "wof:placetype":"locality"
},
  "geometry": {"coordinates":[117.76222,40.30861],"type":"Point"}
}