{
  "type": "Feature",
  "properties": {
    "gn:admin1_code":"4.0",
    "gn:asciiname":"Huacang",
    "gn:country_code":"CN",
    "gn:dem":8,
    "gn:feature_class":"P",
    "gn:feature_code":"PPL",
    "gn:name":"Huacang",
    "gn:population":0,
    "gn:timezone":"Asia/Shanghai",
    "iso:country":"CN",
    "name:zho_x_preferred":[
        "\u534e\u85cf"
    ],
    "wof:name":"Huacang",
    "wof:placetype":"locality"
},
  "geometry": {"coordinates":[120.17206000000002,31.54363],"type":"Point"}
}