{
  "type": "Feature",
  "properties": {
    "gn:admin1_code":"29.0",
    "gn:asciiname":"Xianwang Laozhai",
    "gn:country_code":"CN",
    "gn:dem":1493,
    "gn:feature_class":"P",
    "gn:feature_code":"PPL",
    "gn:name":"Xianwang Laozhai",
    "gn:population":0,
    "gn:timezone":"Asia/Shanghai",
    "iso:country":"CN",
    "name:zho_x_preferred":[
        "\u5148\u5f80\u8001\u5be8"
    ],
    "wof:name":"Xianwang Laozhai",
    "wof:placetype":"locality"
},
  "geometry": {"coordinates":[100.255,21.8782],"type":"Point"}
}