{
  "type": "Feature",
  "properties": {
    "gn:admin1_code":"32.0",
    "gn:asciiname":"Waduanjing",
    "gn:country_code":"CN",
    "gn:dem":1146,
    "gn:feature_class":"P",
    "gn:feature_code":"PPL",
    "gn:name":"Waduanjing",
    "gn:population":0,
    "gn:timezone":"Asia/Shanghai",
    "iso:country":"CN",
    "name:zho_x_preferred":[
        "\u6316\u65ad\u4e95"
    ],
    "wof:name":"Waduanjing",
    "wof:placetype":"locality"
},
  "geometry": {"coordinates":[102.90852,29.81871],"type":"Point"}
}