{
  "type": "Feature",
  "properties": {
    "gn:admin1_code":"32.0",
    "gn:asciiname":"Zangqenrong",
    "gn:cc2":"CN",
    "gn:country_code":"CN",
    "gn:dem":4023,
    "gn:feature_class":"P",
    "gn:feature_code":"PPL",
    "gn:name":"Zangq\u00eanrong",
    "gn:population":0,
    "gn:timezone":"Asia/Shanghai",
    "iso:country":"CN",
    "name:und_x_variant":[
        "Chung-hsin-jung",
        "Zangq\u00eanrong"
    ],
    "wof:name":"Zangqenrong",
    "wof:placetype":"locality"
},
  "geometry": {"coordinates":[99.21666999999999,29.06667],"type":"Point"}
}