{
  "type": "Feature",
  "properties": {
    "gn:admin1_code":"10",
    "gn:asciiname":"Xibingzhuang",
    "gn:country_code":"CN",
    "gn:dem":37,
    "gn:feature_class":"P",
    "gn:feature_code":"PPL",
    "gn:name":"Xibingzhuang",
    "gn:population":0,
    "gn:timezone":"Asia/Shanghai",
    "iso:country":"CN",
    "name:zho_x_preferred":[
        "\u897f\u90b4\u5e84"
    ],
    "wof:name":"Xibingzhuang",
    "wof:placetype":"locality"
},
  "geometry": {"coordinates":[115.423,37.0751],"type":"Point"}
}