{
  "type": "Feature",
  "properties": {
    "gn:admin1_code":"18",
    "gn:asciiname":"Langshuijing",
    "gn:country_code":"CN",
    "gn:dem":1192,
    "gn:feature_class":"P",
    "gn:feature_code":"PPL",
    "gn:name":"Langshuijing",
    "gn:population":0,
    "gn:timezone":"Asia/Shanghai",
    "iso:country":"CN",
    "name:zho_x_preferred":[
        "\u6d6a\u6c34\u4e95"
    ],
    "wof:name":"Langshuijing",
    "wof:placetype":"locality"
},
  "geometry": {"coordinates":[106.411,25.3219],"type":"Point"}
}