{
  "type": "Feature",
  "properties": {
    "gn:admin1_code":"25",
    "gn:asciiname":"Shaojiazhuang",
    "gn:country_code":"CN",
    "gn:dem":231,
    "gn:feature_class":"P",
    "gn:feature_code":"PPL",
    "gn:name":"Shaojiazhuang",
    "gn:population":0,
    "gn:timezone":"Asia/Shanghai",
    "iso:country":"CN",
    "name:zho_x_preferred":[
        "\u90b5\u5bb6\u5e84"
    ],
    "wof:name":"Shaojiazhuang",
    "wof:placetype":"locality"
},
  "geometry": {"coordinates":[116.98399999999999,36.3066],"type":"Point"}
}