{
  "type": "Feature",
  "properties": {
    "gn:admin1_code":"2.0",
    "gn:asciiname":"Bailukou",
    "gn:country_code":"CN",
    "gn:dem":377,
    "gn:feature_class":"P",
    "gn:feature_code":"PPL",
    "gn:name":"Bailukou",
    "gn:population":0,
    "gn:timezone":"Asia/Shanghai",
    "iso:country":"CN",
    "name:zho_x_preferred":[
        "\u767d\u8def\u53e3"
    ],
    "wof:name":"Bailukou",
    "wof:placetype":"locality"
},
  "geometry": {"coordinates":[120.41428000000001,29.51088],"type":"Point"}
}