{
  "type": "Feature",
  "properties": {
    "gn:admin1_code":"7",
    "gn:asciiname":"Liantang",
    "gn:country_code":"CN",
    "gn:dem":238,
    "gn:feature_class":"P",
    "gn:feature_code":"PPLA4",
    "gn:name":"Liantang",
    "gn:population":0,
    "gn:timezone":"Asia/Shanghai",
    "iso:country":"CN",
    "name:und_x_variant":[
        "\u4e0b\u8fde\u5858",
        "Liantang",
        "Xialiantang",
        "Liantang Zhen"
    ],
    "name:zho_x_preferred":[
        "\u83b2\u5858\u9547"
    ],
    "name:zho_x_variant":[
        "\u83b2\u5858"
    ],
    "wof:name":"Liantang",
    "wof:placetype":"locality"
},
  "geometry": {"coordinates":[118.51611,27.92389],"type":"Point"}
}