{
  "type": "Feature",
  "properties": {
    "gn:admin1_code":"29.0",
    "gn:asciiname":"Duoli",
    "gn:country_code":"CN",
    "gn:dem":2239,
    "gn:feature_class":"P",
    "gn:feature_code":"PPL",
    "gn:name":"Duoli",
    "gn:population":0,
    "gn:timezone":"Asia/Shanghai",
    "iso:country":"CN",
    "name:zho_x_preferred":[
        "\u591a\u7acb"
    ],
    "wof:name":"Duoli",
    "wof:placetype":"locality"
},
  "geometry": {"coordinates":[102.386,25.9548],"type":"Point"}
}