{
  "type": "Feature",
  "properties": {
    "gn:admin1_code":"4.0",
    "gn:asciiname":"Yipingcun",
    "gn:country_code":"CN",
    "gn:dem":2,
    "gn:feature_class":"P",
    "gn:feature_code":"PPL",
    "gn:name":"Yipingcun",
    "gn:population":0,
    "gn:timezone":"Asia/Shanghai",
    "iso:country":"CN",
    "name:zho_x_preferred":[
        "\u4e00\u5e73\u6751"
    ],
    "wof:name":"Yipingcun",
    "wof:placetype":"locality"
},
  "geometry": {"coordinates":[119.58087,32.76971],"type":"Point"}
}