{
  "type": "Feature",
  "properties": {
    "gn:admin1_code":"14.0",
    "gn:asciiname":"Baoyaobini",
    "gn:country_code":"CN",
    "gn:dem":4254,
    "gn:feature_class":"P",
    "gn:feature_code":"PPL",
    "gn:name":"Baoyaobini",
    "gn:population":0,
    "gn:timezone":"Asia/Urumqi",
    "iso:country":"CN",
    "name:zho_x_preferred":[
        "\u5265\u4e48\u6bd4\u4f60"
    ],
    "wof:name":"Baoyaobini",
    "wof:placetype":"locality"
},
  "geometry": {"coordinates":[94.23933,29.43733],"type":"Point"}
}