{
  "type": "Feature",
  "properties": {
    "gn:admin1_code":"12.0",
    "gn:asciiname":"Laozhuanggou",
    "gn:country_code":"CN",
    "gn:dem":743,
    "gn:feature_class":"P",
    "gn:feature_code":"PPL",
    "gn:name":"Laozhuanggou",
    "gn:population":0,
    "gn:timezone":"Asia/Shanghai",
    "iso:country":"CN",
    "name:zho_x_preferred":[
        "\u8001\u5e84\u6c9f"
    ],
    "wof:name":"Laozhuanggou",
    "wof:placetype":"locality"
},
  "geometry": {"coordinates":[110.79225,33.12725],"type":"Point"}
}