{
  "type": "Feature",
  "properties": {
    "gn:admin1_code":"2.0",
    "gn:asciiname":"Liaolie",
    "gn:country_code":"CN",
    "gn:dem":424,
    "gn:feature_class":"P",
    "gn:feature_code":"PPL",
    "gn:name":"Liaolie",
    "gn:population":0,
    "gn:timezone":"Asia/Shanghai",
    "iso:country":"CN",
    "name:zho_x_preferred":[
        "\u4e86\u70c8"
    ],
    "wof:name":"Liaolie",
    "wof:placetype":"locality"
},
  "geometry": {"coordinates":[120.53424,28.34952],"type":"Point"}
}