{
  "type": "Feature",
  "properties": {
    "gn:admin1_code":"8.0",
    "gn:asciiname":"Yu'antun",
    "gn:country_code":"CN",
    "gn:dem":226,
    "gn:feature_class":"P",
    "gn:feature_code":"PPL",
    "gn:name":"Yu\u2019antun",
    "gn:population":0,
    "gn:timezone":"Asia/Shanghai",
    "iso:country":"CN",
    "name:und_x_variant":[
        "Yu\u2019antun"
    ],
    "name:zho_x_preferred":[
        "\u88d5\u5b89\u5c6f"
    ],
    "wof:name":"Yu'antun",
    "wof:placetype":"locality"
},
  "geometry": {"coordinates":[126.9483,47.76919],"type":"Point"}
}