{
  "type": "Feature",
  "properties": {
    "gn:admin1_code":"32",
    "gn:asciiname":"Yutan",
    "gn:country_code":"CN",
    "gn:dem":325,
    "gn:feature_class":"P",
    "gn:feature_code":"PPL",
    "gn:name":"Yutan",
    "gn:population":0,
    "gn:timezone":"Asia/Shanghai",
    "iso:country":"CN",
    "name:ceb_x_preferred":[
        "Yutan"
    ],
    "name:deu_x_preferred":[
        "Yutan"
    ],
    "name:swe_x_preferred":[
        "Yutan"
    ],
    "name:und_x_variant":[
        "Liangtan",
        "Yutan"
    ],
    "name:zho_x_preferred":[
        "\u96e8\u575b"
    ],
    "wof:name":"Yutan",
    "wof:placetype":"locality"
},
  "geometry": {"coordinates":[105.43071999999999,29.29973],"type":"Point"}
}