{
  "type": "Feature",
  "properties": {
    "gn:admin1_code":"01",
    "gn:asciiname":"Shuhong",
    "gn:cc2":"CN",
    "gn:country_code":"CN",
    "gn:dem":181,
    "gn:feature_class":"P",
    "gn:feature_code":"PPL",
    "gn:name":"Shuhong",
    "gn:population":0,
    "gn:timezone":"Asia/Shanghai",
    "iso:country":"CN",
    "name:und_x_variant":[
        "Shu-hung",
        "Shuhong",
        "\u8700\u6d2a"
    ],
    "wof:name":"Shuhong",
    "wof:placetype":"locality"
},
  "geometry": {"coordinates":[118.77556,30.31917],"type":"Point"}
}