{
  "type": "Feature",
  "properties": {
    "gn:admin1_code":"7",
    "gn:asciiname":"Songmaolin",
    "gn:country_code":"CN",
    "gn:dem":268,
    "gn:feature_class":"P",
    "gn:feature_code":"PPL",
    "gn:name":"Songmaolin",
    "gn:population":0,
    "gn:timezone":"Asia/Shanghai",
    "iso:country":"CN",
    "name:und_x_variant":[
        "\u677e\u8302\u6797"
    ],
    "wof:name":"Songmaolin",
    "wof:placetype":"locality"
},
  "geometry": {"coordinates":[119.73417000000001,27.21083],"type":"Point"}
}