{
  "type": "Feature",
  "properties": {
    "gn:admin1_code":"05",
    "gn:asciiname":"Kao-li-ch'eng",
    "gn:country_code":"CN",
    "gn:dem":32,
    "gn:feature_class":"P",
    "gn:feature_code":"PPL",
    "gn:name":"Kao-li-ch\u2019eng",
    "gn:population":0,
    "gn:timezone":"Asia/Shanghai",
    "iso:country":"CN",
    "wof:name":"Kao-li-ch'eng",
    "wof:placetype":"locality"
},
  "geometry": {"coordinates":[130.27083000000002,42.83778],"type":"Point"}
}