{
  "type": "Feature",
  "properties": {
    "gn:admin1_code":"4.0",
    "gn:asciiname":"Yucun",
    "gn:country_code":"CN",
    "gn:dem":26,
    "gn:feature_class":"P",
    "gn:feature_code":"PPL",
    "gn:name":"Yucun",
    "gn:population":0,
    "gn:timezone":"Asia/Shanghai",
    "iso:country":"CN",
    "wof:name":"Yucun",
    "wof:placetype":"locality"
},
  "geometry": {"coordinates":[118.89335,31.65824000000001],"type":"Point"}
}