{
  "type": "Feature",
  "properties": {
    "gn:admin1_code":"22.0",
    "gn:asciiname":"Beilicun",
    "gn:country_code":"CN",
    "gn:dem":807,
    "gn:feature_class":"P",
    "gn:feature_code":"PPL",
    "gn:name":"Beilicun",
    "gn:population":0,
    "gn:timezone":"Asia/Shanghai",
    "iso:country":"CN",
    "name:zho_x_preferred":[
        "\u5317\u5229\u6751"
    ],
    "wof:name":"Beilicun",
    "wof:placetype":"locality"
},
  "geometry": {"coordinates":[115.65667000000001,39.7141],"type":"Point"}
}