{
  "type": "Feature",
  "properties": {
    "gn:admin1_code":"32.0",
    "gn:asciiname":"Dayangjiaping",
    "gn:country_code":"CN",
    "gn:dem":673,
    "gn:feature_class":"P",
    "gn:feature_code":"PPL",
    "gn:name":"Dayangjiaping",
    "gn:population":0,
    "gn:timezone":"Asia/Shanghai",
    "iso:country":"CN",
    "name:zho_x_preferred":[
        "\u5927\u6768\u5bb6\u576a"
    ],
    "wof:name":"Dayangjiaping",
    "wof:placetype":"locality"
},
  "geometry": {"coordinates":[107.33413,31.40111],"type":"Point"}
}