{
  "type": "Feature",
  "properties": {
    "gn:admin1_code":"16.0",
    "gn:asciiname":"Gankun",
    "gn:country_code":"CN",
    "gn:dem":278,
    "gn:feature_class":"P",
    "gn:feature_code":"PPL",
    "gn:name":"Gankun",
    "gn:population":0,
    "gn:timezone":"Asia/Shanghai",
    "iso:country":"CN",
    "name:zho_x_preferred":[
        "\u5e72\u5764"
    ],
    "wof:name":"Gankun",
    "wof:placetype":"locality"
},
  "geometry": {"coordinates":[107.89400000000001,24.8895],"type":"Point"}
}