{
  "type": "Feature",
  "properties": {
    "gn:admin1_code":"11",
    "gn:asciiname":"Mayingtang",
    "gn:country_code":"CN",
    "gn:dem":258,
    "gn:feature_class":"P",
    "gn:feature_code":"PPL",
    "gn:name":"Mayingtang",
    "gn:population":0,
    "gn:timezone":"Asia/Shanghai",
    "iso:country":"CN",
    "wof:name":"Mayingtang",
    "wof:placetype":"locality"
},
  "geometry": {"coordinates":[109.69499999999999,27.4175],"type":"Point"}
}