{
  "type": "Feature",
  "properties": {
    "gn:admin1_code":"19.0",
    "gn:asciiname":"Dongsanjianfang",
    "gn:country_code":"CN",
    "gn:dem":82,
    "gn:feature_class":"P",
    "gn:feature_code":"PPL",
    "gn:name":"Dongsanjianfang",
    "gn:population":0,
    "gn:timezone":"Asia/Shanghai",
    "iso:country":"CN",
    "name:zho_x_preferred":[
        "\u4e1c\u4e09\u95f4\u623f"
    ],
    "wof:name":"Dongsanjianfang",
    "wof:placetype":"locality"
},
  "geometry": {"coordinates":[123.577,42.7974],"type":"Point"}
}