{
  "type": "Feature",
  "properties": {
    "gn:admin1_code":"33.0",
    "gn:asciiname":"Duanwuling",
    "gn:country_code":"CN",
    "gn:dem":589,
    "gn:feature_class":"P",
    "gn:feature_code":"PPL",
    "gn:name":"Duanwuling",
    "gn:population":0,
    "gn:timezone":"Asia/Shanghai",
    "iso:country":"CN",
    "name:zho_x_preferred":[
        "\u7aef\u5348\u5cad"
    ],
    "wof:name":"Duanwuling",
    "wof:placetype":"locality"
},
  "geometry": {"coordinates":[107.91771,30.48094],"type":"Point"}
}