{
  "type": "Feature",
  "properties": {
    "gn:admin1_code":"32.0",
    "gn:asciiname":"Dadiaolou",
    "gn:country_code":"CN",
    "gn:dem":765,
    "gn:feature_class":"P",
    "gn:feature_code":"PPL",
    "gn:name":"Dadiaolou",
    "gn:population":0,
    "gn:timezone":"Asia/Shanghai",
    "iso:country":"CN",
    "name:zho_x_preferred":[
        "\u5927\u7889\u697c"
    ],
    "wof:name":"Dadiaolou",
    "wof:placetype":"locality"
},
  "geometry": {"coordinates":[103.834,28.9942],"type":"Point"}
}