{
  "type": "Feature",
  "properties": {
    "gn:admin1_code":"20.0",
    "gn:asciiname":"Hayan Hudong",
    "gn:country_code":"CN",
    "gn:dem":1692,
    "gn:feature_class":"P",
    "gn:feature_code":"PPL",
    "gn:name":"Hayan Hudong",
    "gn:population":0,
    "gn:timezone":"Asia/Shanghai",
    "iso:country":"CN",
    "name:und_x_variant":[
        "\u54c8\u5f66\u5ffd\u6d1e"
    ],
    "wof:name":"Hayan Hudong",
    "wof:placetype":"locality"
},
  "geometry": {"coordinates":[110.30714,41.01615],"type":"Point"}
}