{
  "type": "Feature",
  "properties": {
    "gn:admin1_code":"14.0",
    "gn:asciiname":"Quyongma",
    "gn:country_code":"CN",
    "gn:dem":4525,
    "gn:feature_class":"P",
    "gn:feature_code":"PPL",
    "gn:name":"Quyongma",
    "gn:population":0,
    "gn:timezone":"Asia/Urumqi",
    "iso:country":"CN",
    "name:zho_x_preferred":[
        "\u9a71\u62e5\u739b"
    ],
    "wof:name":"Quyongma",
    "wof:placetype":"locality"
},
  "geometry": {"coordinates":[93.95319000000001,31.62215],"type":"Point"}
}