{
  "type": "Feature",
  "properties": {
    "gn:admin1_code":"3.0",
    "gn:asciiname":"Huaqi",
    "gn:country_code":"CN",
    "gn:dem":451,
    "gn:feature_class":"P",
    "gn:feature_code":"PPL",
    "gn:name":"Huaqi",
    "gn:population":0,
    "gn:timezone":"Asia/Shanghai",
    "iso:country":"CN",
    "name:und_x_variant":[
        "\u534e\u9f50"
    ],
    "wof:name":"Huaqi",
    "wof:placetype":"locality"
},
  "geometry": {"coordinates":[115.7818,25.10926],"type":"Point"}
}