{
  "type": "Feature",
  "properties": {
    "gn:admin1_code":"32.0",
    "gn:asciiname":"Waidi",
    "gn:country_code":"CN",
    "gn:dem":3030,
    "gn:feature_class":"P",
    "gn:feature_code":"PPL",
    "gn:name":"Waidi",
    "gn:population":0,
    "gn:timezone":"Asia/Shanghai",
    "iso:country":"CN",
    "name:zho_x_preferred":[
        "\u6b6a\u5730"
    ],
    "wof:name":"Waidi",
    "wof:placetype":"locality"
},
  "geometry": {"coordinates":[103.735,32.2137],"type":"Point"}
}