{
  "type": "Feature",
  "properties": {
    "gn:admin1_code":"21",
    "gn:asciiname":"Heicheng",
    "gn:country_code":"CN",
    "gn:dem":1524,
    "gn:feature_class":"P",
    "gn:feature_code":"PPLA4",
    "gn:name":"Heicheng",
    "gn:population":0,
    "gn:timezone":"Asia/Shanghai",
    "iso:country":"CN",
    "name:und_x_variant":[
        "Hei-ch\u2019eng-chen",
        "Heicheng Zhen",
        "Heicheng",
        "\u9ed1\u57ce",
        "\u9ed1\u57ce\u9547"
    ],
    "wof:name":"Heicheng",
    "wof:placetype":"locality"
},
  "geometry": {"coordinates":[106.08623,36.37019],"type":"Point"}
}