{
  "type": "Feature",
  "properties": {
    "gn:admin1_code":"29.0",
    "gn:asciiname":"Baichi Xiacun",
    "gn:country_code":"CN",
    "gn:dem":1854,
    "gn:feature_class":"P",
    "gn:feature_code":"PPL",
    "gn:name":"Baichi Xiacun",
    "gn:population":0,
    "gn:timezone":"Asia/Shanghai",
    "iso:country":"CN",
    "name:zho_x_preferred":[
        "\u767d\u6c60\u4e0b\u6751"
    ],
    "wof:name":"Baichi Xiacun",
    "wof:placetype":"locality"
},
  "geometry": {"coordinates":[100.09099999999999,25.1241],"type":"Point"}
}