{
  "type": "Feature",
  "properties": {
    "gn:admin1_code":"1.0",
    "gn:asciiname":"Fengjing",
    "gn:country_code":"CN",
    "gn:dem":276,
    "gn:feature_class":"P",
    "gn:feature_code":"PPL",
    "gn:name":"Fengjing",
    "gn:population":0,
    "gn:timezone":"Asia/Shanghai",
    "iso:country":"CN",
    "name:fra_x_preferred":[
        "Fengjing"
    ],
    "name:wuu_x_preferred":[
        "\u67ab\u6cfe\u9547"
    ],
    "name:zho_x_preferred":[
        "\u5cf0\u666f"
    ],
    "name:zho_x_variant":[
        "\u67ab\u6cfe\u9547"
    ],
    "wof:name":"Fengjing",
    "wof:placetype":"locality"
},
  "geometry": {"coordinates":[118.08076,30.16938],"type":"Point"}
}