{
  "type": "Feature",
  "properties": {
    "gn:admin1_code":"30.0",
    "gn:asciiname":"Lanshu'ao",
    "gn:country_code":"CN",
    "gn:dem":44,
    "gn:feature_class":"P",
    "gn:feature_code":"PPL",
    "gn:name":"Lanshu\u2019ao",
    "gn:population":0,
    "gn:timezone":"Asia/Shanghai",
    "iso:country":"CN",
    "name:zho_x_preferred":[
        "\u6984\u6811\u5773"
    ],
    "name:zho_x_variant":[
        "Lanshu\u2019ao"
    ],
    "wof:name":"Lanshu'ao",
    "wof:placetype":"locality"
},
  "geometry": {"coordinates":[112.68976000000001,22.88241],"type":"Point"}
}