{
  "type": "Feature",
  "properties": {
    "gn:admin1_code":"11.0",
    "gn:asciiname":"Mao'erping",
    "gn:country_code":"CN",
    "gn:dem":240,
    "gn:feature_class":"P",
    "gn:feature_code":"PPL",
    "gn:name":"Mao\u2019erping",
    "gn:population":0,
    "gn:timezone":"Asia/Shanghai",
    "iso:country":"CN",
    "name:und_x_variant":[
        "Mao\u2019erping"
    ],
    "name:zho_x_preferred":[
        "\u732b\u513f\u576a"
    ],
    "wof:name":"Mao'erping",
    "wof:placetype":"locality"
},
  "geometry": {"coordinates":[110.6382,27.68703],"type":"Point"}
}