{
  "type": "Feature",
  "properties": {
    "gn:admin1_code":"25.0",
    "gn:asciiname":"Hounanbucun",
    "gn:country_code":"CN",
    "gn:dem":28,
    "gn:feature_class":"P",
    "gn:feature_code":"PPL",
    "gn:name":"Hounanbucun",
    "gn:population":0,
    "gn:timezone":"Asia/Shanghai",
    "iso:country":"CN",
    "name:zho_x_preferred":[
        "\u540e\u5357\u57e0\u6751"
    ],
    "wof:name":"Hounanbucun",
    "wof:placetype":"locality"
},
  "geometry": {"coordinates":[120.19879,36.66051],"type":"Point"}
}