{
  "type": "Feature",
  "properties": {
    "gn:admin1_code":"12.0",
    "gn:asciiname":"Hejiayuan",
    "gn:country_code":"CN",
    "gn:dem":763,
    "gn:feature_class":"P",
    "gn:feature_code":"PPL",
    "gn:name":"Hejiayuan",
    "gn:population":0,
    "gn:timezone":"Asia/Shanghai",
    "iso:country":"CN",
    "name:zho_x_preferred":[
        "\u4f55\u5bb6\u9662"
    ],
    "wof:name":"Hejiayuan",
    "wof:placetype":"locality"
},
  "geometry": {"coordinates":[110.7478,32.98246],"type":"Point"}
}