{
  "type": "Feature",
  "properties": {
    "gn:admin1_code":"4.0",
    "gn:asciiname":"Guantianzhuang",
    "gn:country_code":"CN",
    "gn:dem":28,
    "gn:feature_class":"P",
    "gn:feature_code":"PPL",
    "gn:name":"Guantianzhuang",
    "gn:population":0,
    "gn:timezone":"Asia/Shanghai",
    "iso:country":"CN",
    "name:zho_x_preferred":[
        "\u5b98\u7530\u5e84"
    ],
    "wof:name":"Guantianzhuang",
    "wof:placetype":"locality"
},
  "geometry": {"coordinates":[118.70486,32.96975],"type":"Point"}
}