{
  "type": "Feature",
  "properties": {
    "gn:admin1_code":"4.0",
    "gn:asciiname":"Nanpan",
    "gn:country_code":"CN",
    "gn:dem":12,
    "gn:feature_class":"P",
    "gn:feature_code":"PPL",
    "gn:name":"Nanpan",
    "gn:population":0,
    "gn:timezone":"Asia/Shanghai",
    "iso:country":"CN",
    "name:zho_x_preferred":[
        "\u5357\u76d8"
    ],
    "wof:name":"Nanpan",
    "wof:placetype":"locality"
},
  "geometry": {"coordinates":[118.50552999999999,31.97159000000001],"type":"Point"}
}