{
  "type": "Feature",
  "properties": {
    "gn:admin1_code":"12.0",
    "gn:asciiname":"Tianwangou",
    "gn:country_code":"CN",
    "gn:dem":902,
    "gn:feature_class":"P",
    "gn:feature_code":"PPL",
    "gn:name":"Tianwangou",
    "gn:population":0,
    "gn:timezone":"Asia/Shanghai",
    "iso:country":"CN",
    "name:zho_x_preferred":[
        "\u7530\u5846\u6c9f"
    ],
    "wof:name":"Tianwangou",
    "wof:placetype":"locality"
},
  "geometry": {"coordinates":[109.39149999999999,29.64373],"type":"Point"}
}