{
  "type": "Feature",
  "properties": {
    "gn:admin1_code":"4.0",
    "gn:asciiname":"Shuanghucun",
    "gn:country_code":"CN",
    "gn:dem":58,
    "gn:feature_class":"P",
    "gn:feature_code":"PPL",
    "gn:name":"Shuanghucun",
    "gn:population":0,
    "gn:timezone":"Asia/Shanghai",
    "iso:country":"CN",
    "name:zho_x_preferred":[
        "\u53cc\u6e56\u6751"
    ],
    "wof:name":"Shuanghucun",
    "wof:placetype":"locality"
},
  "geometry": {"coordinates":[118.49048000000001,34.64691],"type":"Point"}
}