{
  "type": "Feature",
  "properties": {
    "gn:admin1_code":"26.0",
    "gn:asciiname":"Yangchangcun",
    "gn:country_code":"CN",
    "gn:dem":694,
    "gn:feature_class":"P",
    "gn:feature_code":"PPL",
    "gn:name":"Yangchangcun",
    "gn:population":0,
    "gn:timezone":"Asia/Shanghai",
    "iso:country":"CN",
    "name:zho_x_preferred":[
        "\u6768\u573a\u6751"
    ],
    "wof:name":"Yangchangcun",
    "wof:placetype":"locality"
},
  "geometry": {"coordinates":[110.35597,33.71386],"type":"Point"}
}