{
  "type": "Feature",
  "properties": {
    "gn:admin1_code":"16.0",
    "gn:asciiname":"Dalantang",
    "gn:country_code":"CN",
    "gn:dem":74,
    "gn:feature_class":"P",
    "gn:feature_code":"PPL",
    "gn:name":"Dalantang",
    "gn:population":0,
    "gn:timezone":"Asia/Shanghai",
    "iso:country":"CN",
    "name:zho_x_preferred":[
        "\u5927\u6984\u5858"
    ],
    "wof:name":"Dalantang",
    "wof:placetype":"locality"
},
  "geometry": {"coordinates":[110.26900000000001,23.3581],"type":"Point"}
}