{
  "type": "Feature",
  "properties": {
    "gn:admin1_code":"24.0",
    "gn:asciiname":"Liangguan",
    "gn:country_code":"CN",
    "gn:dem":1516,
    "gn:feature_class":"P",
    "gn:feature_code":"PPL",
    "gn:name":"Liangguan",
    "gn:population":0,
    "gn:timezone":"Asia/Shanghai",
    "iso:country":"CN",
    "name:und_x_variant":[
        "\u826f\u5173"
    ],
    "wof:name":"Liangguan",
    "wof:placetype":"locality"
},
  "geometry": {"coordinates":[112.17524,39.58009000000001],"type":"Point"}
}