{
  "type": "Feature",
  "properties": {
    "gn:admin1_code":"12.0",
    "gn:asciiname":"Jiefangling",
    "gn:country_code":"CN",
    "gn:dem":49,
    "gn:feature_class":"P",
    "gn:feature_code":"PPL",
    "gn:name":"Jiefangling",
    "gn:population":0,
    "gn:timezone":"Asia/Shanghai",
    "iso:country":"CN",
    "name:zho_x_preferred":[
        "Jiefangling"
    ],
    "name:zho_x_variant":[
        "\u89e3\u653e\u5cad"
    ],
    "wof:name":"Jiefangling",
    "wof:placetype":"locality"
},
  "geometry": {"coordinates":[112.39409000000001,30.58077],"type":"Point"}
}