{
  "type": "Feature",
  "properties": {
    "gn:admin1_code":"12.0",
    "gn:asciiname":"Shashukeng",
    "gn:country_code":"CN",
    "gn:dem":611,
    "gn:feature_class":"P",
    "gn:feature_code":"PPL",
    "gn:name":"Shashukeng",
    "gn:population":0,
    "gn:timezone":"Asia/Shanghai",
    "iso:country":"CN",
    "name:zho_x_preferred":[
        "Shashukeng"
    ],
    "name:zho_x_variant":[
        "\u6749\u6811\u5751"
    ],
    "wof:name":"Shashukeng",
    "wof:placetype":"locality"
},
  "geometry": {"coordinates":[111.14113,30.08822],"type":"Point"}
}