{
  "type": "Feature",
  "properties": {
    "gn:admin1_code":"32.0",
    "gn:asciiname":"Haluo Wucun",
    "gn:country_code":"CN",
    "gn:dem":2579,
    "gn:feature_class":"P",
    "gn:feature_code":"PPL",
    "gn:name":"Haluo Wucun",
    "gn:population":0,
    "gn:timezone":"Asia/Shanghai",
    "iso:country":"CN",
    "name:zho_x_preferred":[
        "\u54c8\u6d1b\u4e94\u6751"
    ],
    "wof:name":"Haluo Wucun",
    "wof:placetype":"locality"
},
  "geometry": {"coordinates":[102.869,28.269],"type":"Point"}
}