{
  "type": "Feature",
  "properties": {
    "gn:admin1_code":"25",
    "gn:asciiname":"Zhangjiaguanzhuang",
    "gn:country_code":"CN",
    "gn:dem":140,
    "gn:feature_class":"P",
    "gn:feature_code":"PPL",
    "gn:name":"Zhangjiaguanzhuang",
    "gn:population":0,
    "gn:timezone":"Asia/Shanghai",
    "iso:country":"CN",
    "name:und_x_variant":[
        "\u5f20\u5bb6\u5b98\u5e84"
    ],
    "wof:name":"Zhangjiaguanzhuang",
    "wof:placetype":"locality"
},
  "geometry": {"coordinates":[119.07438999999999,35.96546],"type":"Point"}
}