{
  "type": "Feature",
  "properties": {
    "gn:admin1_code":"30",
    "gn:asciiname":"Guitang",
    "gn:country_code":"CN",
    "gn:dem":30,
    "gn:feature_class":"P",
    "gn:feature_code":"PPL",
    "gn:name":"Guitang",
    "gn:population":0,
    "gn:timezone":"Asia/Shanghai",
    "iso:country":"CN",
    "name:zho_x_preferred":[
        "\u8d35\u5858"
    ],
    "name:zho_x_variant":[
        "\u572d\u5858\u8857\u9053"
    ],
    "wof:name":"Guitang",
    "wof:placetype":"locality"
},
  "geometry": {"coordinates":[111.57814,21.86742000000001],"type":"Point"}
}