{
  "type": "Feature",
  "properties": {
    "gn:admin1_code":"11",
    "gn:asciiname":"Shangtou Lijia",
    "gn:country_code":"CN",
    "gn:dem":93,
    "gn:feature_class":"P",
    "gn:feature_code":"PPL",
    "gn:name":"Shangtou Lijia",
    "gn:population":0,
    "gn:timezone":"Asia/Shanghai",
    "iso:country":"CN",
    "name:zho_x_preferred":[
        "\u4e0a\u5934\u674e\u5bb6"
    ],
    "wof:name":"Shangtou Lijia",
    "wof:placetype":"locality"
},
  "geometry": {"coordinates":[112.41240999999999,26.36324],"type":"Point"}
}