{
  "type": "Feature",
  "properties": {
    "gn:admin1_code":"14.0",
    "gn:asciiname":"Xitang",
    "gn:country_code":"CN",
    "gn:dem":3417,
    "gn:feature_class":"P",
    "gn:feature_code":"PPL",
    "gn:name":"Xitang",
    "gn:population":0,
    "gn:timezone":"Asia/Urumqi",
    "iso:country":"CN",
    "name:zho_x_preferred":[
        "\u5e0c\u5858"
    ],
    "wof:name":"Xitang",
    "wof:placetype":"locality"
},
  "geometry": {"coordinates":[96.3381,30.41053],"type":"Point"}
}