{
  "type": "Feature",
  "properties": {
    "gn:admin1_code":"26.0",
    "gn:asciiname":"Zhandaigou",
    "gn:country_code":"CN",
    "gn:dem":1190,
    "gn:feature_class":"P",
    "gn:feature_code":"PPL",
    "gn:name":"Zhandaigou",
    "gn:population":0,
    "gn:timezone":"Asia/Shanghai",
    "iso:country":"CN",
    "name:zho_x_preferred":[
        "\u7efd\u888b\u6c9f"
    ],
    "wof:name":"Zhandaigou",
    "wof:placetype":"locality"
},
  "geometry": {"coordinates":[109.93094000000001,34.2211],"type":"Point"}
}