{
  "type": "Feature",
  "properties": {
    "gn:admin1_code":"11.0",
    "gn:asciiname":"Zhaojia Aoshang",
    "gn:country_code":"CN",
    "gn:dem":99,
    "gn:feature_class":"P",
    "gn:feature_code":"PPL",
    "gn:name":"Zhaojia Aoshang",
    "gn:population":0,
    "gn:timezone":"Asia/Shanghai",
    "iso:country":"CN",
    "name:zho_x_preferred":[
        "\u8d75\u5bb6\u5773\u4e0a"
    ],
    "wof:name":"Zhaojia Aoshang",
    "wof:placetype":"locality"
},
  "geometry": {"coordinates":[112.75913,27.24413],"type":"Point"}
}