{
  "type": "Feature",
  "properties": {
    "gn:admin1_code":"02",
    "gn:asciiname":"Liuxia",
    "gn:country_code":"CN",
    "gn:dem":11,
    "gn:feature_class":"P",
    "gn:feature_code":"PPLA4",
    "gn:name":"Liuxia",
    "gn:population":0,
    "gn:timezone":"Asia/Shanghai",
    "iso:country":"CN",
    "name:und_x_variant":[
        "Liu-hsia",
        "Liu-hsia-chen",
        "Liuxia",
        "\u7559\u4e0b",
        "Liuxia Zhen",
        "Liuxia Jiedao",
        "\u7559\u4e0b\u9547",
        "\u7559\u4e0b\u8857\u9053"
    ],
    "wof:name":"Liuxia",
    "wof:placetype":"locality"
},
  "geometry": {"coordinates":[120.05287,30.24546],"type":"Point"}
}