{
  "type": "Feature",
  "properties": {
    "gn:admin1_code":"4.0",
    "gn:asciiname":"Guangzhongcun",
    "gn:country_code":"CN",
    "gn:dem":1,
    "gn:feature_class":"P",
    "gn:feature_code":"PPL",
    "gn:name":"Guangzhongcun",
    "gn:population":0,
    "gn:timezone":"Asia/Shanghai",
    "iso:country":"CN",
    "name:zho_x_preferred":[
        "\u5e7f\u4e2d\u6751"
    ],
    "wof:name":"Guangzhongcun",
    "wof:placetype":"locality"
},
  "geometry": {"coordinates":[121.325,31.9213],"type":"Point"}
}