{
  "type": "Feature",
  "properties": {
    "gn:admin1_code":"9.0",
    "gn:asciiname":"Nanbeidian",
    "gn:country_code":"CN",
    "gn:dem":82,
    "gn:feature_class":"P",
    "gn:feature_code":"PPL",
    "gn:name":"Nanbeidian",
    "gn:population":0,
    "gn:timezone":"Asia/Shanghai",
    "iso:country":"CN",
    "name:zho_x_preferred":[
        "\u5357\u5317\u5e97"
    ],
    "wof:name":"Nanbeidian",
    "wof:placetype":"locality"
},
  "geometry": {"coordinates":[114.4314,34.86245],"type":"Point"}
}