{
  "type": "Feature",
  "properties": {
    "gn:admin1_code":"11",
    "gn:asciiname":"Longmuzhi",
    "gn:country_code":"CN",
    "gn:dem":390,
    "gn:feature_class":"P",
    "gn:feature_code":"PPL",
    "gn:name":"Longmuzhi",
    "gn:population":0,
    "gn:timezone":"Asia/Shanghai",
    "iso:country":"CN",
    "name:zho_x_preferred":[
        "\u9f99\u6bcd\u81f4"
    ],
    "wof:name":"Longmuzhi",
    "wof:placetype":"locality"
},
  "geometry": {"coordinates":[111.42891000000002,25.20017],"type":"Point"}
}