{
  "type": "Feature",
  "properties": {
    "gn:admin1_code":"19.0",
    "gn:asciiname":"Shenglikuang Nongchang",
    "gn:country_code":"CN",
    "gn:dem":435,
    "gn:feature_class":"P",
    "gn:feature_code":"PPLF",
    "gn:name":"Shenglikuang Nongchang",
    "gn:population":0,
    "gn:timezone":"Asia/Shanghai",
    "iso:country":"CN",
    "name:und_x_variant":[
        "\u80dc\u5229\u77ff\u519c\u573a"
    ],
    "wof:name":"Shenglikuang Nongchang",
    "wof:placetype":"locality"
},
  "geometry": {"coordinates":[124.64995999999999,41.37902],"type":"Point"}
}