{
  "type": "Feature",
  "properties": {
    "gn:admin1_code":"15.0",
    "gn:asciiname":"Manjiashan",
    "gn:country_code":"CN",
    "gn:dem":2127,
    "gn:feature_class":"P",
    "gn:feature_code":"PPL",
    "gn:name":"Manjiashan",
    "gn:population":0,
    "gn:timezone":"Asia/Shanghai",
    "iso:country":"CN",
    "name:zho_x_preferred":[
        "\u6ee1\u5bb6\u5c71"
    ],
    "wof:name":"Manjiashan",
    "wof:placetype":"locality"
},
  "geometry": {"coordinates":[103.77800000000001,35.1366],"type":"Point"}
}