{
  "type": "Feature",
  "properties": {
    "gn:admin1_code":"26.0",
    "gn:asciiname":"Lijiazhuangzi",
    "gn:country_code":"CN",
    "gn:dem":1305,
    "gn:feature_class":"P",
    "gn:feature_code":"PPL",
    "gn:name":"Lijiazhuangzi",
    "gn:population":0,
    "gn:timezone":"Asia/Shanghai",
    "iso:country":"CN",
    "name:zho_x_preferred":[
        "\u674e\u5bb6\u5e84\u5b50"
    ],
    "wof:name":"Lijiazhuangzi",
    "wof:placetype":"locality"
},
  "geometry": {"coordinates":[108.22807,32.44427],"type":"Point"}
}