{
  "type": "Feature",
  "properties": {
    "gn:admin1_code":"9",
    "gn:asciiname":"Kongdian",
    "gn:country_code":"CN",
    "gn:dem":58,
    "gn:feature_class":"P",
    "gn:feature_code":"PPL",
    "gn:name":"Kongdian",
    "gn:population":0,
    "gn:timezone":"Asia/Shanghai",
    "iso:country":"CN",
    "name:zho_x_preferred":[
        "\u5b54\u5e97"
    ],
    "wof:name":"Kongdian",
    "wof:placetype":"locality"
},
  "geometry": {"coordinates":[115.15832,35.48302],"type":"Point"}
}