{
  "type": "Feature",
  "properties": {
    "gn:admin1_code":"18",
    "gn:asciiname":"Luopan",
    "gn:country_code":"CN",
    "gn:dem":1254,
    "gn:feature_class":"P",
    "gn:feature_code":"PPL",
    "gn:name":"Luopan",
    "gn:population":0,
    "gn:timezone":"Asia/Shanghai",
    "iso:country":"CN",
    "name:deu_x_preferred":[
        "Lo Pan"
    ],
    "name:fin_x_preferred":[
        "Luopan"
    ],
    "name:hrv_x_preferred":[
        "Luo Pan"
    ],
    "name:jpn_x_preferred":[
        "\u98a8\u6c34\u7f85\u76e4"
    ],
    "name:mkd_x_preferred":[
        "\u041b\u0443\u043e\u043f\u0430\u043d"
    ],
    "name:nor_x_preferred":[
        "Luopan"
    ],
    "name:pol_x_preferred":[
        "Kompas geomantyczny"
    ],
    "name:rus_x_preferred":[
        "\u041a\u0438\u0442\u0430\u0439\u0441\u043a\u0438\u0439 \u043a\u043e\u043c\u043f\u0430\u0441"
    ],
    "name:spa_x_preferred":[
        "Luopan"
    ],
    "name:ukr_x_preferred":[
        "\u041a\u0438\u0442\u0430\u0439\u0441\u044c\u043a\u0438\u0439 \u043a\u043e\u043c\u043f\u0430\u0441"
    ],
    "name:zho_x_preferred":[
        "\u843d\u6f58"
    ],
    "wof:name":"Luopan",
    "wof:placetype":"locality"
},
  "geometry": {"coordinates":[104.926,25.8669],"type":"Point"}
}