{
  "type": "Feature",
  "properties": {
    "gn:admin1_code":"09",
    "gn:asciiname":"Heyu",
    "gn:country_code":"CN",
    "gn:dem":663,
    "gn:feature_class":"P",
    "gn:feature_code":"PPL",
    "gn:name":"Heyu",
    "gn:population":0,
    "gn:timezone":"Asia/Shanghai",
    "iso:country":"CN",
    "name:und_x_variant":[
        "Ho-y\u00fc",
        "Heyu"
    ],
    "wof:name":"Heyu",
    "wof:placetype":"locality"
},
  "geometry": {"coordinates":[111.88722,33.83667],"type":"Point"}
}