{
  "type": "Feature",
  "properties": {
    "gn:admin1_code":"25",
    "gn:asciiname":"Dabiqing",
    "gn:country_code":"CN",
    "gn:dem":145,
    "gn:feature_class":"P",
    "gn:feature_code":"PPL",
    "gn:name":"Dabiqing",
    "gn:population":0,
    "gn:timezone":"Asia/Shanghai",
    "iso:country":"CN",
    "name:und_x_variant":[
        "\u5927\u859c\u5e86"
    ],
    "wof:name":"Dabiqing",
    "wof:placetype":"locality"
},
  "geometry": {"coordinates":[119.00823,35.34763],"type":"Point"}
}