{
  "type": "Feature",
  "properties": {
    "gn:admin1_code":"32.0",
    "gn:asciiname":"Mudong",
    "gn:country_code":"CN",
    "gn:dem":3679,
    "gn:feature_class":"P",
    "gn:feature_code":"PPL",
    "gn:name":"Mudong",
    "gn:population":0,
    "gn:timezone":"Asia/Shanghai",
    "iso:country":"CN",
    "name:zho_x_preferred":[
        "\u6728\u6d1e"
    ],
    "wof:name":"Mudong",
    "wof:placetype":"locality"
},
  "geometry": {"coordinates":[99.05110000000001,32.2678],"type":"Point"}
}