{
  "type": "Feature",
  "properties": {
    "gn:admin1_code":"26.0",
    "gn:asciiname":"Hou'erlintu",
    "gn:country_code":"CN",
    "gn:dem":1235,
    "gn:feature_class":"P",
    "gn:feature_code":"PPL",
    "gn:name":"Hou\u2019erlintu",
    "gn:population":0,
    "gn:timezone":"Asia/Shanghai",
    "iso:country":"CN",
    "name:und_x_variant":[
        "Hou\u2019erlintu"
    ],
    "name:zho_x_preferred":[
        "\u540e\u5c14\u6797\u5154"
    ],
    "wof:name":"Hou'erlintu",
    "wof:placetype":"locality"
},
  "geometry": {"coordinates":[109.87957,39.05015],"type":"Point"}
}