{
  "type": "Feature",
  "properties": {
    "gn:admin1_code":"32.0",
    "gn:asciiname":"Qunguang",
    "gn:country_code":"CN",
    "gn:dem":489,
    "gn:feature_class":"P",
    "gn:feature_code":"PPL",
    "gn:name":"Qunguang",
    "gn:population":0,
    "gn:timezone":"Asia/Shanghai",
    "iso:country":"CN",
    "name:zho_x_preferred":[
        "\u7fa4\u5149"
    ],
    "wof:name":"Qunguang",
    "wof:placetype":"locality"
},
  "geometry": {"coordinates":[103.589,29.939],"type":"Point"}
}