{
  "type": "Feature",
  "properties": {
    "gn:admin1_code":"8.0",
    "gn:asciiname":"Xuritun",
    "gn:country_code":"CN",
    "gn:dem":280,
    "gn:feature_class":"P",
    "gn:feature_code":"PPL",
    "gn:name":"Xuritun",
    "gn:population":0,
    "gn:timezone":"Asia/Shanghai",
    "iso:country":"CN",
    "name:und_x_variant":[
        "Hs\u00fc-jih-t\u2019un"
    ],
    "name:zho_x_preferred":[
        "\u65ed\u65e5\u5c6f"
    ],
    "wof:name":"Xuritun",
    "wof:placetype":"locality"
},
  "geometry": {"coordinates":[126.4397,48.57604],"type":"Point"}
}