{
  "type": "Feature",
  "properties": {
    "gn:admin1_code":"5.0",
    "gn:asciiname":"Gongsuotun",
    "gn:country_code":"CN",
    "gn:dem":335,
    "gn:feature_class":"P",
    "gn:feature_code":"PPL",
    "gn:name":"Gongsuotun",
    "gn:population":0,
    "gn:timezone":"Asia/Shanghai",
    "iso:country":"CN",
    "name:zho_x_preferred":[
        "\u516c\u6240\u5c6f"
    ],
    "wof:name":"Gongsuotun",
    "wof:placetype":"locality"
},
  "geometry": {"coordinates":[126.35612,42.97098],"type":"Point"}
}