{
  "type": "Feature",
  "properties": {
    "gn:admin1_code":"32.0",
    "gn:asciiname":"Linchang Sidui",
    "gn:country_code":"CN",
    "gn:dem":1699,
    "gn:feature_class":"P",
    "gn:feature_code":"PPLF",
    "gn:name":"Linchang Sidui",
    "gn:population":0,
    "gn:timezone":"Asia/Shanghai",
    "iso:country":"CN",
    "name:zho_x_preferred":[
        "\u6797\u573a\u56db\u961f"
    ],
    "wof:name":"Linchang Sidui",
    "wof:placetype":"locality"
},
  "geometry": {"coordinates":[104.28773,32.17973],"type":"Point"}
}