{
  "type": "Feature",
  "properties": {
    "gn:admin1_code":"25",
    "gn:asciiname":"Daboli",
    "gn:country_code":"CN",
    "gn:dem":14,
    "gn:feature_class":"P",
    "gn:feature_code":"PPL",
    "gn:name":"Daboli",
    "gn:population":0,
    "gn:timezone":"Asia/Shanghai",
    "iso:country":"CN",
    "name:zho_x_preferred":[
        "\u6253\u7b94\u674e"
    ],
    "wof:name":"Daboli",
    "wof:placetype":"locality"
},
  "geometry": {"coordinates":[117.411,37.4276],"type":"Point"}
}