{
  "type": "Feature",
  "properties": {
    "gn:admin1_code":"11.0",
    "gn:asciiname":"Maowu Chenjia",
    "gn:country_code":"CN",
    "gn:dem":301,
    "gn:feature_class":"P",
    "gn:feature_code":"PPL",
    "gn:name":"Maowu Chenjia",
    "gn:population":0,
    "gn:timezone":"Asia/Shanghai",
    "iso:country":"CN",
    "name:zho_x_preferred":[
        "\u8305\u5c4b\u9648\u5bb6"
    ],
    "wof:name":"Maowu Chenjia",
    "wof:placetype":"locality"
},
  "geometry": {"coordinates":[111.16629,27.19546],"type":"Point"}
}