{
  "type": "Feature",
  "properties": {
    "gn:admin1_code":"15.0",
    "gn:asciiname":"Niangxiu",
    "gn:country_code":"CN",
    "gn:dem":3132,
    "gn:feature_class":"P",
    "gn:feature_code":"PPL",
    "gn:name":"Niangxiu",
    "gn:population":0,
    "gn:timezone":"Asia/Shanghai",
    "iso:country":"CN",
    "name:und_x_variant":[
        "\u5a18\u4f11"
    ],
    "wof:name":"Niangxiu",
    "wof:placetype":"locality"
},
  "geometry": {"coordinates":[103.02007,34.96799],"type":"Point"}
}