{
  "type": "Feature",
  "properties": {
    "gn:admin1_code":"24.0",
    "gn:asciiname":"Youfangcun",
    "gn:country_code":"CN",
    "gn:dem":1410,
    "gn:feature_class":"P",
    "gn:feature_code":"PPL",
    "gn:name":"Youfangcun",
    "gn:population":0,
    "gn:timezone":"Asia/Shanghai",
    "iso:country":"CN",
    "name:zho_x_preferred":[
        "\u6cb9\u623f\u6751"
    ],
    "wof:name":"Youfangcun",
    "wof:placetype":"locality"
},
  "geometry": {"coordinates":[113.14404,37.35729],"type":"Point"}
}