{
  "type": "Feature",
  "properties": {
    "gn:admin1_code":"13.0",
    "gn:asciiname":"Lasite",
    "gn:country_code":"CN",
    "gn:dem":945,
    "gn:feature_class":"P",
    "gn:feature_code":"PPLA4",
    "gn:name":"Lasite",
    "gn:population":0,
    "gn:timezone":"Asia/Urumqi",
    "iso:country":"CN",
    "name:kaz_x_preferred":[
        "\u0644\u0627\u0633\u062a\u0649 \u0627\u06cb\u0649\u0644\u0649"
    ],
    "name:uig_x_preferred":[
        "\u0644\u0627\u0633\u062a\u0649 \u064a\u06d0\u0632\u0649\u0633\u0649"
    ],
    "name:und_x_variant":[
        "Lasite Xiang"
    ],
    "name:zho_x_preferred":[
        "\u62c9\u65af\u7279"
    ],
    "name:zho_x_variant":[
        "\u62c9\u65af\u7279\u4e61"
    ],
    "wof:name":"Lasite",
    "wof:placetype":"locality"
},
  "geometry": {"coordinates":[88.10956,47.89027],"type":"Point"}
}