{
  "type": "Feature",
  "properties": {
    "gn:admin1_code":"14.0",
    "gn:asciiname":"Gongbasaba",
    "gn:country_code":"CN",
    "gn:dem":4420,
    "gn:feature_class":"P",
    "gn:feature_code":"PPL",
    "gn:name":"Gongbasaba",
    "gn:population":0,
    "gn:timezone":"Asia/Urumqi",
    "iso:country":"CN",
    "name:zho_x_preferred":[
        "\u8d21\u5df4\u8428\u5df4"
    ],
    "wof:name":"Gongbasaba",
    "wof:placetype":"locality"
},
  "geometry": {"coordinates":[86.5502,28.5004],"type":"Point"}
}