{
  "type": "Feature",
  "properties": {
    "gn:admin1_code":"18",
    "gn:asciiname":"Changbashang",
    "gn:country_code":"CN",
    "gn:dem":1290,
    "gn:feature_class":"P",
    "gn:feature_code":"PPL",
    "gn:name":"Changbashang",
    "gn:population":0,
    "gn:timezone":"Asia/Shanghai",
    "iso:country":"CN",
    "name:zho_x_preferred":[
        "\u573a\u575d\u4e0a"
    ],
    "wof:name":"Changbashang",
    "wof:placetype":"locality"
},
  "geometry": {"coordinates":[106.521,26.8878],"type":"Point"}
}