{
  "type": "Feature",
  "properties": {
    "gn:admin1_code":"26.0",
    "gn:asciiname":"Pushangcun",
    "gn:country_code":"CN",
    "gn:dem":830,
    "gn:feature_class":"P",
    "gn:feature_code":"PPL",
    "gn:name":"Pushangcun",
    "gn:population":0,
    "gn:timezone":"Asia/Shanghai",
    "iso:country":"CN",
    "name:zho_x_preferred":[
        "\u94fa\u4e0a\u6751"
    ],
    "wof:name":"Pushangcun",
    "wof:placetype":"locality"
},
  "geometry": {"coordinates":[109.88163,33.93359],"type":"Point"}
}