{
  "type": "Feature",
  "properties": {
    "gn:admin1_code":"32.0",
    "gn:asciiname":"Azong",
    "gn:country_code":"CN",
    "gn:dem":2932,
    "gn:feature_class":"P",
    "gn:feature_code":"PPL",
    "gn:name":"Azong",
    "gn:population":0,
    "gn:timezone":"Asia/Shanghai",
    "iso:country":"CN",
    "name:zho_x_preferred":[
        "\u963f\u5b97"
    ],
    "wof:name":"Azong",
    "wof:placetype":"locality"
},
  "geometry": {"coordinates":[100.63,30.3722],"type":"Point"}
}