{
  "type": "Feature",
  "properties": {
    "gn:admin1_code":"10",
    "gn:asciiname":"Sihehao",
    "gn:country_code":"CN",
    "gn:dem":1513,
    "gn:feature_class":"P",
    "gn:feature_code":"PPL",
    "gn:name":"Sihehao",
    "gn:population":0,
    "gn:timezone":"Asia/Shanghai",
    "iso:country":"CN",
    "name:zho_x_preferred":[
        "\u56db\u5408\u53f7"
    ],
    "wof:name":"Sihehao",
    "wof:placetype":"locality"
},
  "geometry": {"coordinates":[116.26318000000001,41.74363],"type":"Point"}
}