{
  "type": "Feature",
  "properties": {
    "gn:admin1_code":"31.0",
    "gn:asciiname":"Pianshi",
    "gn:country_code":"CN",
    "gn:dem":52,
    "gn:feature_class":"P",
    "gn:feature_code":"PPL",
    "gn:name":"Pianshi",
    "gn:population":0,
    "gn:timezone":"Asia/Shanghai",
    "iso:country":"CN",
    "name:zho_x_preferred":[
        "\u7247\u77f3"
    ],
    "wof:name":"Pianshi",
    "wof:placetype":"locality"
},
  "geometry": {"coordinates":[109.29418,19.87229],"type":"Point"}
}