{
  "type": "Feature",
  "properties": {
    "gn:country":"CN",
    "gn:fcode":"PPL",
    "gn:pop":206,
    "iso:country":"CN",
    "qs:name":"Liangshuijing",
    "qs:photos_9r":0,
    "qs:photos_sr":0,
    "qs:pop_sr":"2",
    "wof:name":"Liangshuijing",
    "wof:placetype":"locality",
    "wof:population":206
},
  "geometry": {"coordinates":[108.32971999999999,27.96278],"type":"Point"}
}