{
  "type": "Feature",
  "properties": {
    "gn:admin1_code":"14",
    "gn:asciiname":"Gajiang",
    "gn:country_code":"CN",
    "gn:dem":4338,
    "gn:feature_class":"P",
    "gn:feature_code":"PPL",
    "gn:name":"Gajiang",
    "gn:population":0,
    "gn:timezone":"Asia/Urumqi",
    "iso:country":"CN",
    "name:zho_x_preferred":[
        "\u560e\u6c5f"
    ],
    "wof:name":"Gajiang",
    "wof:placetype":"locality"
},
  "geometry": {"coordinates":[89.6384,28.4586],"type":"Point"}
}