{
  "type": "Feature",
  "properties": {
    "gn:admin1_code":"16.0",
    "gn:asciiname":"Jianfu",
    "gn:country_code":"CN",
    "gn:dem":123,
    "gn:feature_class":"P",
    "gn:feature_code":"PPL",
    "gn:name":"Jianfu",
    "gn:population":0,
    "gn:timezone":"Asia/Shanghai",
    "iso:country":"CN",
    "name:zho_x_preferred":[
        "\u4fed\u592b"
    ],
    "wof:name":"Jianfu",
    "wof:placetype":"locality"
},
  "geometry": {"coordinates":[109.718,23.4409],"type":"Point"}
}