{
  "type": "Feature",
  "properties": {
    "gn:admin1_code":"5.0",
    "gn:asciiname":"Leshantun",
    "gn:country_code":"CN",
    "gn:dem":344,
    "gn:feature_class":"P",
    "gn:feature_code":"PPL",
    "gn:name":"Leshantun",
    "gn:population":0,
    "gn:timezone":"Asia/Shanghai",
    "iso:country":"CN",
    "name:zho_x_preferred":[
        "\u4e50\u5584\u5c6f"
    ],
    "wof:name":"Leshantun",
    "wof:placetype":"locality"
},
  "geometry": {"coordinates":[125.57461000000001,43.18102],"type":"Point"}
}