{
  "type": "Feature",
  "properties": {
    "gn:admin1_code":"32.0",
    "gn:asciiname":"Xiamushu",
    "gn:country_code":"CN",
    "gn:dem":2112,
    "gn:feature_class":"P",
    "gn:feature_code":"PPL",
    "gn:name":"Xiamushu",
    "gn:population":0,
    "gn:timezone":"Asia/Shanghai",
    "iso:country":"CN",
    "name:zho_x_preferred":[
        "\u4e0b\u6728\u68b3"
    ],
    "wof:name":"Xiamushu",
    "wof:placetype":"locality"
},
  "geometry": {"coordinates":[102.196,28.4289],"type":"Point"}
}