{
  "type": "Feature",
  "properties": {
    "gn:admin1_code":"11.0",
    "gn:asciiname":"Shenchongwan",
    "gn:country_code":"CN",
    "gn:dem":107,
    "gn:feature_class":"P",
    "gn:feature_code":"PPL",
    "gn:name":"Shenchongwan",
    "gn:population":0,
    "gn:timezone":"Asia/Shanghai",
    "iso:country":"CN",
    "name:zho_x_preferred":[
        "\u795e\u51b2\u6e7e"
    ],
    "wof:name":"Shenchongwan",
    "wof:placetype":"locality"
},
  "geometry": {"coordinates":[112.30061000000001,27.77863],"type":"Point"}
}