{
  "type": "Feature",
  "properties": {
    "gn:admin1_code":"10",
    "gn:asciiname":"Luoquangou",
    "gn:country_code":"CN",
    "gn:dem":523,
    "gn:feature_class":"P",
    "gn:feature_code":"PPL",
    "gn:name":"Luoquangou",
    "gn:population":0,
    "gn:timezone":"Asia/Shanghai",
    "iso:country":"CN",
    "name:zho_x_preferred":[
        "\u7f57\u5708\u6c9f"
    ],
    "wof:name":"Luoquangou",
    "wof:placetype":"locality"
},
  "geometry": {"coordinates":[119.51644,40.31548],"type":"Point"}
}