{
  "type": "Feature",
  "properties": {
    "gn:admin1_code":"15.0",
    "gn:asciiname":"Yanjialu",
    "gn:country_code":"CN",
    "gn:dem":2378,
    "gn:feature_class":"P",
    "gn:feature_code":"PPL",
    "gn:name":"Yanjialu",
    "gn:population":0,
    "gn:timezone":"Asia/Shanghai",
    "iso:country":"CN",
    "name:und_x_variant":[
        "\u4e25\u5bb6\u7089"
    ],
    "name:zho_x_preferred":[
        "\u4e25\u5bb6\u7089"
    ],
    "wof:name":"Yanjialu",
    "wof:placetype":"locality"
},
  "geometry": {"coordinates":[104.21498,33.80279],"type":"Point"}
}