{
  "type": "Feature",
  "properties": {
    "gn:admin1_code":"3",
    "gn:asciiname":"Liwengyuan",
    "gn:country_code":"CN",
    "gn:dem":118,
    "gn:feature_class":"P",
    "gn:feature_code":"PPL",
    "gn:name":"Liwengyuan",
    "gn:population":0,
    "gn:timezone":"Asia/Shanghai",
    "iso:country":"CN",
    "name:und_x_variant":[
        "\u91cc\u7fc1\u6e90"
    ],
    "wof:name":"Liwengyuan",
    "wof:placetype":"locality"
},
  "geometry": {"coordinates":[116.79719,27.81671],"type":"Point"}
}