{
  "type": "Feature",
  "properties": {
    "gn:admin1_code":"15.0",
    "gn:asciiname":"Majiaping",
    "gn:country_code":"CN",
    "gn:dem":1674,
    "gn:feature_class":"P",
    "gn:feature_code":"PPL",
    "gn:name":"Majiaping",
    "gn:population":0,
    "gn:timezone":"Asia/Shanghai",
    "iso:country":"CN",
    "name:und_x_variant":[
        "\u9a6c\u5bb6\u576a"
    ],
    "wof:name":"Majiaping",
    "wof:placetype":"locality"
},
  "geometry": {"coordinates":[105.33198,33.32957],"type":"Point"}
}