{
  "type": "Feature",
  "properties": {
    "gn:admin1_code":"25",
    "gn:asciiname":"Xiqilihe",
    "gn:country_code":"CN",
    "gn:dem":240,
    "gn:feature_class":"P",
    "gn:feature_code":"PPL",
    "gn:name":"Xiqilihe",
    "gn:population":0,
    "gn:timezone":"Asia/Shanghai",
    "iso:country":"CN",
    "name:zho_x_preferred":[
        "\u897f\u4e03\u91cc\u6cb3"
    ],
    "wof:name":"Xiqilihe",
    "wof:placetype":"locality"
},
  "geometry": {"coordinates":[117.55800000000001,35.1278],"type":"Point"}
}