{
  "type": "Feature",
  "properties": {
    "gn:admin1_code":"1.0",
    "gn:asciiname":"Luwafangcun",
    "gn:country_code":"CN",
    "gn:dem":25,
    "gn:feature_class":"P",
    "gn:feature_code":"PPL",
    "gn:name":"Luwafangcun",
    "gn:population":0,
    "gn:timezone":"Asia/Shanghai",
    "iso:country":"CN",
    "name:zho_x_preferred":[
        "\u9646\u74e6\u623f\u6751"
    ],
    "wof:name":"Luwafangcun",
    "wof:placetype":"locality"
},
  "geometry": {"coordinates":[116.65833000000001,33.07312],"type":"Point"}
}