{
  "type": "Feature",
  "properties": {
    "gn:admin1_code":"32.0",
    "gn:asciiname":"Baihoumiao",
    "gn:country_code":"CN",
    "gn:dem":405,
    "gn:feature_class":"P",
    "gn:feature_code":"PPL",
    "gn:name":"Baihoumiao",
    "gn:population":0,
    "gn:timezone":"Asia/Shanghai",
    "iso:country":"CN",
    "name:zho_x_preferred":[
        "\u767d\u4faf\u5e99"
    ],
    "wof:name":"Baihoumiao",
    "wof:placetype":"locality"
},
  "geometry": {"coordinates":[105.607,30.8773],"type":"Point"}
}