{
  "type": "Feature",
  "properties": {
    "gn:admin1_code":"30.0",
    "gn:asciiname":"Heqing",
    "gn:country_code":"CN",
    "gn:dem":3,
    "gn:feature_class":"P",
    "gn:feature_code":"PPL",
    "gn:name":"Heqing",
    "gn:population":0,
    "gn:timezone":"Asia/Shanghai",
    "iso:country":"CN",
    "name:deu_x_preferred":[
        "Heqing"
    ],
    "name:nor_x_preferred":[
        "Heqing"
    ],
    "name:zho_x_preferred":[
        "\u6cb3\u6e05"
    ],
    "wof:name":"Heqing",
    "wof:placetype":"locality"
},
  "geometry": {"coordinates":[112.81644,22.43857],"type":"Point"}
}