{
  "type": "Feature",
  "properties": {
    "gn:admin1_code":"19.0",
    "gn:asciiname":"Sanduancun",
    "gn:country_code":"CN",
    "gn:dem":15,
    "gn:feature_class":"P",
    "gn:feature_code":"PPL",
    "gn:name":"Sanduancun",
    "gn:population":0,
    "gn:timezone":"Asia/Shanghai",
    "iso:country":"CN",
    "name:zho_x_preferred":[
        "\u4e09\u6bb5\u6751"
    ],
    "wof:name":"Sanduancun",
    "wof:placetype":"locality"
},
  "geometry": {"coordinates":[121.45099999999999,41.1421],"type":"Point"}
}