{
  "type": "Feature",
  "properties": {
    "gn:admin1_code":"14.0",
    "gn:asciiname":"Wada'e",
    "gn:country_code":"CN",
    "gn:dem":3778,
    "gn:feature_class":"P",
    "gn:feature_code":"PPL",
    "gn:name":"Wada\u2019e",
    "gn:population":0,
    "gn:timezone":"Asia/Urumqi",
    "iso:country":"CN",
    "name:und_x_variant":[
        "Wada\u2019e"
    ],
    "name:zho_x_preferred":[
        "\u5a03\u6253\u4fc4"
    ],
    "wof:name":"Wada'e",
    "wof:placetype":"locality"
},
  "geometry": {"coordinates":[95.89619999999999,31.26323],"type":"Point"}
}