{
  "type": "Feature",
  "properties": {
    "gn:admin1_code":"29.0",
    "gn:asciiname":"Niujia Pingzi",
    "gn:country_code":"CN",
    "gn:dem":2436,
    "gn:feature_class":"P",
    "gn:feature_code":"PPL",
    "gn:name":"Niujia Pingzi",
    "gn:population":0,
    "gn:timezone":"Asia/Shanghai",
    "iso:country":"CN",
    "name:zho_x_preferred":[
        "\u725b\u5bb6\u576a\u5b50"
    ],
    "wof:name":"Niujia Pingzi",
    "wof:placetype":"locality"
},
  "geometry": {"coordinates":[103.42100000000001,26.3605],"type":"Point"}
}