{
  "type": "Feature",
  "properties": {
    "gn:admin1_code":"9.0",
    "gn:asciiname":"Zhuhe",
    "gn:country_code":"CN",
    "gn:dem":595,
    "gn:feature_class":"P",
    "gn:feature_code":"PPL",
    "gn:name":"Zhuhe",
    "gn:population":0,
    "gn:timezone":"Asia/Shanghai",
    "iso:country":"CN",
    "name:und_x_variant":[
        "\u70db\u6cb3",
        "Zhuhe"
    ],
    "wof:name":"Zhuhe",
    "wof:placetype":"locality"
},
  "geometry": {"coordinates":[112.16892,33.8954],"type":"Point"}
}