{
  "type": "Feature",
  "properties": {
    "gn:admin1_code":"8.0",
    "gn:asciiname":"Yinanhe Linchang",
    "gn:country_code":"CN",
    "gn:dem":419,
    "gn:feature_class":"P",
    "gn:feature_code":"PPLF",
    "gn:name":"Yinanhe Linchang",
    "gn:population":0,
    "gn:timezone":"Asia/Shanghai",
    "iso:country":"CN",
    "name:zho_x_preferred":[
        "\u4f0a\u5357\u6cb3\u6797\u573a"
    ],
    "wof:name":"Yinanhe Linchang",
    "wof:placetype":"locality"
},
  "geometry": {"coordinates":[128.22139000000001,48.63442],"type":"Point"}
}