{
  "type": "Feature",
  "properties": {
    "gn:admin1_code":"2.0",
    "gn:asciiname":"Damukeng",
    "gn:country_code":"CN",
    "gn:dem":376,
    "gn:feature_class":"P",
    "gn:feature_code":"PPL",
    "gn:name":"Damukeng",
    "gn:population":0,
    "gn:timezone":"Asia/Shanghai",
    "iso:country":"CN",
    "name:zho_x_preferred":[
        "\u5927\u59c6\u5751"
    ],
    "wof:name":"Damukeng",
    "wof:placetype":"locality"
},
  "geometry": {"coordinates":[120.70859,29.03957],"type":"Point"}
}