{
  "type": "Feature",
  "properties": {
    "gn:admin1_code":"14.0",
    "gn:asciiname":"Genacun",
    "gn:country_code":"CN",
    "gn:dem":4840,
    "gn:feature_class":"P",
    "gn:feature_code":"PPL",
    "gn:name":"Genacun",
    "gn:population":0,
    "gn:timezone":"Asia/Urumqi",
    "iso:country":"CN",
    "name:zho_x_preferred":[
        "\u683c\u90a3\u6751"
    ],
    "wof:name":"Genacun",
    "wof:placetype":"locality"
},
  "geometry": {"coordinates":[92.39363,32.05033],"type":"Point"}
}