{
  "type": "Feature",
  "properties": {
    "gn:admin1_code":"12.0",
    "gn:asciiname":"Mailangping",
    "gn:country_code":"CN",
    "gn:dem":436,
    "gn:feature_class":"P",
    "gn:feature_code":"PPL",
    "gn:name":"Mailangping",
    "gn:population":0,
    "gn:timezone":"Asia/Shanghai",
    "iso:country":"CN",
    "name:zho_x_preferred":[
        "\u9ea6\u6d6a\u576a"
    ],
    "wof:name":"Mailangping",
    "wof:placetype":"locality"
},
  "geometry": {"coordinates":[110.15894,31.98354],"type":"Point"}
}