{
  "type": "Feature",
  "properties": {
    "gn:admin1_code":"20.0",
    "gn:asciiname":"Tarigan",
    "gn:country_code":"CN",
    "gn:dem":683,
    "gn:feature_class":"P",
    "gn:feature_code":"PPL",
    "gn:name":"Tarigan",
    "gn:population":0,
    "gn:timezone":"Asia/Shanghai",
    "iso:country":"CN",
    "name:ind_x_preferred":[
        "Tarigan"
    ],
    "name:zho_x_preferred":[
        "\u5854\u65e5\u5e72"
    ],
    "wof:name":"Tarigan",
    "wof:placetype":"locality"
},
  "geometry": {"coordinates":[118.43192999999999,48.19268],"type":"Point"}
}