{
  "type": "Feature",
  "properties": {
    "gn:admin1_code":"5.0",
    "gn:asciiname":"Xixinmin",
    "gn:country_code":"CN",
    "gn:dem":213,
    "gn:feature_class":"P",
    "gn:feature_code":"PPL",
    "gn:name":"Xixinmin",
    "gn:population":0,
    "gn:timezone":"Asia/Shanghai",
    "iso:country":"CN",
    "name:zho_x_preferred":[
        "\u897f\u65b0\u6c11"
    ],
    "wof:name":"Xixinmin",
    "wof:placetype":"locality"
},
  "geometry": {"coordinates":[126.94674000000001,44.76695],"type":"Point"}
}