{
  "type": "Feature",
  "properties": {
    "gn:admin1_code":"29.0",
    "gn:asciiname":"Linyi",
    "gn:country_code":"CN",
    "gn:dem":1764,
    "gn:feature_class":"P",
    "gn:feature_code":"PPL",
    "gn:name":"Linyi",
    "gn:population":0,
    "gn:timezone":"Asia/Shanghai",
    "iso:country":"CN",
    "name:afr_x_preferred":[
        "Linyi"
    ],
    "name:ara_x_preferred":[
        "\u0644\u064a\u0646\u064a"
    ],
    "name:cat_x_preferred":[
        "Linyi"
    ],
    "name:cdo_x_preferred":[
        "L\u00ecng-g\u00ec"
    ],
    "name:ceb_x_preferred":[
        "Linyi"
    ],
    "name:ces_x_preferred":[
        "Lin-i"
    ],
    "name:dan_x_preferred":[
        "Linyi"
    ],
    "name:deu_x_preferred":[
        "Linyi"
    ],
    "name:eus_x_preferred":[
        "Linyi"
    ],
    "name:fas_x_preferred":[
        "\u0644\u06cc\u0646\u06cc\u0627\u06cc"
    ],
    "name:fin_x_preferred":[
        "Linyi"
    ],
    "name:fra_x_preferred":[
        "Linyi"
    ],
    "name:hun_x_preferred":[
        "Linji"
    ],
    "name:ita_x_preferred":[
        "Linyi"
    ],
    "name:jpn_x_preferred":[
        "\u81e8\u6c82\u5e02"
    ],
    "name:kik_x_preferred":[
        "Linyi"
    ],
    "name:kor_x_preferred":[
        "\ub9b0\uc774\uc2dc"
    ],
    "name:mlg_x_preferred":[
        "Linyi"
    ],
    "name:mon_x_preferred":[
        "\u041b\u0438\u043d\u044c\u0438"
    ],
    "name:nld_x_preferred":[
        "Linyi"
    ],
    "name:nno_x_preferred":[
        "Linyi"
    ],
    "name:nor_x_preferred":[
        "Linyi"
    ],
    "name:pol_x_preferred":[
        "Linyi"
    ],
    "name:rus_x_preferred":[
        "\u041b\u0438\u043d\u044c\u0438"
    ],
    "name:spa_x_preferred":[
        "Linyi"
    ],
    "name:srp_x_preferred":[
        "\u041b\u0438\u043d\u0458\u0438"
    ],
    "name:swe_x_preferred":[
        "Linyi"
    ],
    "name:tgl_x_preferred":[
        "Linyi"
    ],
    "name:tur_x_preferred":[
        "Linyi"
    ],
    "name:urd_x_preferred":[
        "\u0644\u0646\u06cc\u06cc"
    ],
    "name:vie_x_preferred":[
        "L\u00e2m Nghi"
    ],
    "name:war_x_preferred":[
        "Linyi"
    ],
    "name:wuu_x_preferred":[
        "\u4e34\u6c82\u5e02"
    ],
    "name:zho_x_preferred":[
        "\u6797\u76ca"
    ],
    "name:zho_x_variant":[
        "\u4e34\u6c82\u5e02"
    ],
    "wof:name":"Linyi",
    "wof:placetype":"locality"
},
  "geometry": {"coordinates":[103.67400000000001,24.4253],"type":"Point"}
}