{
  "type": "Feature",
  "properties": {
    "gn:admin1_code":"4.0",
    "gn:asciiname":"Xingfujie",
    "gn:country_code":"CN",
    "gn:dem":4,
    "gn:feature_class":"P",
    "gn:feature_code":"PPL",
    "gn:name":"Xingfujie",
    "gn:population":0,
    "gn:timezone":"Asia/Shanghai",
    "iso:country":"CN",
    "name:zho_x_preferred":[
        "\u4f0d\u80e5\u5e99"
    ],
    "wof:name":"Xingfujie",
    "wof:placetype":"locality"
},
  "geometry": {"coordinates":[121.07067000000001,31.66946],"type":"Point"}
}