{
  "type": "Feature",
  "properties": {
    "gn:admin1_code":"9",
    "gn:asciiname":"Tianqiao",
    "gn:country_code":"CN",
    "gn:dem":51,
    "gn:feature_class":"P",
    "gn:feature_code":"PPL",
    "gn:name":"Tianqiao",
    "gn:population":0,
    "gn:timezone":"Asia/Shanghai",
    "iso:country":"CN",
    "name:zho_x_preferred":[
        "\u7530\u6865"
    ],
    "wof:name":"Tianqiao",
    "wof:placetype":"locality"
},
  "geometry": {"coordinates":[115.04300000000001,33.9421],"type":"Point"}
}