{
  "type": "Feature",
  "properties": {
    "gn:admin1_code":"7.0",
    "gn:asciiname":"Shangzhoudun",
    "gn:country_code":"CN",
    "gn:dem":167,
    "gn:feature_class":"P",
    "gn:feature_code":"PPL",
    "gn:name":"Shangzhoudun",
    "gn:population":0,
    "gn:timezone":"Asia/Shanghai",
    "iso:country":"CN",
    "name:zho_x_preferred":[
        "\u4e0a\u5468\u58a9"
    ],
    "wof:name":"Shangzhoudun",
    "wof:placetype":"locality"
},
  "geometry": {"coordinates":[118.03513,27.31076],"type":"Point"}
}