{
  "type": "Feature",
  "properties": {
    "gn:admin1_code":"20.0",
    "gn:asciiname":"Bayan Hushu Jijing",
    "gn:country_code":"CN",
    "gn:dem":729,
    "gn:feature_class":"P",
    "gn:feature_code":"PPL",
    "gn:name":"Bayan Hushu Jijing",
    "gn:population":0,
    "gn:timezone":"Asia/Shanghai",
    "iso:country":"CN",
    "name:zho_x_preferred":[
        "\u5df4\u5f66\u547c\u8212\u673a\u4e95"
    ],
    "wof:name":"Bayan Hushu Jijing",
    "wof:placetype":"locality"
},
  "geometry": {"coordinates":[119.48188,48.65347],"type":"Point"}
}