{
  "type": "Feature",
  "properties": {
    "gn:admin1_code":"18.0",
    "gn:asciiname":"Gaobiao",
    "gn:country_code":"CN",
    "gn:dem":796,
    "gn:feature_class":"P",
    "gn:feature_code":"PPL",
    "gn:name":"Gaobiao",
    "gn:population":0,
    "gn:timezone":"Asia/Shanghai",
    "iso:country":"CN",
    "name:zho_x_preferred":[
        "\u9ad8\u8868"
    ],
    "wof:name":"Gaobiao",
    "wof:placetype":"locality"
},
  "geometry": {"coordinates":[108.98399999999999,26.4452],"type":"Point"}
}