{
  "type": "Feature",
  "properties": {
    "gn:admin1_code":"1.0",
    "gn:asciiname":"Yinqiaocun",
    "gn:country_code":"CN",
    "gn:dem":29,
    "gn:feature_class":"P",
    "gn:feature_code":"PPL",
    "gn:name":"Yinqiaocun",
    "gn:population":0,
    "gn:timezone":"Asia/Shanghai",
    "iso:country":"CN",
    "name:zho_x_preferred":[
        "\u6bb7\u6865\u6751"
    ],
    "wof:name":"Yinqiaocun",
    "wof:placetype":"locality"
},
  "geometry": {"coordinates":[118.04170000000001,33.05292],"type":"Point"}
}