{
  "type": "Feature",
  "properties": {
    "gn:admin1_code":"14.0",
    "gn:asciiname":"Ejiumai",
    "gn:country_code":"CN",
    "gn:dem":4975,
    "gn:feature_class":"P",
    "gn:feature_code":"PPL",
    "gn:name":"Ejiumai",
    "gn:population":0,
    "gn:timezone":"Asia/Urumqi",
    "iso:country":"CN",
    "name:zho_x_preferred":[
        "\u4fc4\u4e45\u5356"
    ],
    "wof:name":"Ejiumai",
    "wof:placetype":"locality"
},
  "geometry": {"coordinates":[86.8176,33.5769],"type":"Point"}
}