{
  "type": "Feature",
  "properties": {
    "gn:admin1_code":"18",
    "gn:asciiname":"Shejikeng",
    "gn:country_code":"CN",
    "gn:dem":1699,
    "gn:feature_class":"P",
    "gn:feature_code":"PPL",
    "gn:name":"Shejikeng",
    "gn:population":0,
    "gn:timezone":"Asia/Shanghai",
    "iso:country":"CN",
    "name:zho_x_preferred":[
        "\u5c04\u51fb\u5751"
    ],
    "wof:name":"Shejikeng",
    "wof:placetype":"locality"
},
  "geometry": {"coordinates":[104.717,25.4489],"type":"Point"}
}