{
  "type": "Feature",
  "properties": {
    "gn:admin1_code":"14.0",
    "gn:asciiname":"Mazacun",
    "gn:country_code":"CN",
    "gn:dem":4843,
    "gn:feature_class":"P",
    "gn:feature_code":"PPL",
    "gn:name":"Mazacun",
    "gn:population":0,
    "gn:timezone":"Asia/Urumqi",
    "iso:country":"CN",
    "name:zho_x_preferred":[
        "\u739b\u6742\u6751"
    ],
    "wof:name":"Mazacun",
    "wof:placetype":"locality"
},
  "geometry": {"coordinates":[92.81756,30.98324],"type":"Point"}
}