{
  "type": "Feature",
  "properties": {
    "gn:admin1_code":"25",
    "gn:asciiname":"Lihuantang",
    "gn:country_code":"CN",
    "gn:dem":70,
    "gn:feature_class":"P",
    "gn:feature_code":"PPL",
    "gn:name":"Lihuantang",
    "gn:population":0,
    "gn:timezone":"Asia/Shanghai",
    "iso:country":"CN",
    "name:zho_x_preferred":[
        "\u674e\u7115\u5802"
    ],
    "wof:name":"Lihuantang",
    "wof:placetype":"locality"
},
  "geometry": {"coordinates":[114.89,35.1209],"type":"Point"}
}