{
  "type": "Feature",
  "properties": {
    "gn:admin1_code":"16.0",
    "gn:asciiname":"Danzhujiang",
    "gn:country_code":"CN",
    "gn:dem":18,
    "gn:feature_class":"P",
    "gn:feature_code":"PPL",
    "gn:name":"Danzhujiang",
    "gn:population":0,
    "gn:timezone":"Asia/Shanghai",
    "iso:country":"CN",
    "name:zho_x_preferred":[
        "\u4e39\u7af9\u6c5f"
    ],
    "wof:name":"Danzhujiang",
    "wof:placetype":"locality"
},
  "geometry": {"coordinates":[108.718,22.0179],"type":"Point"}
}