{
  "type": "Feature",
  "properties": {
    "gn:admin1_code":"8.0",
    "gn:asciiname":"Feilishan",
    "gn:country_code":"CN",
    "gn:dem":344,
    "gn:feature_class":"P",
    "gn:feature_code":"PPLF",
    "gn:name":"Feilishan",
    "gn:population":0,
    "gn:timezone":"Asia/Shanghai",
    "iso:country":"CN",
    "name:und_x_variant":[
        "\u8d39\u529b\u5c71"
    ],
    "wof:name":"Feilishan",
    "wof:placetype":"locality"
},
  "geometry": {"coordinates":[126.95251,50.72278],"type":"Point"}
}