{
  "type": "Feature",
  "properties": {
    "gn:admin1_code":"4.0",
    "gn:asciiname":"Tanjiacun",
    "gn:country_code":"CN",
    "gn:dem":43,
    "gn:feature_class":"P",
    "gn:feature_code":"PPL",
    "gn:name":"Tanjiacun",
    "gn:population":0,
    "gn:timezone":"Asia/Shanghai",
    "iso:country":"CN",
    "name:und_x_variant":[
        "Tanjia",
        "Tanjiacun"
    ],
    "name:zho_x_preferred":[
        "\u8c2d\u5bb6"
    ],
    "name:zho_x_variant":[
        "\u8c2d\u5bb6\u6751"
    ],
    "wof:name":"Tanjiacun",
    "wof:placetype":"locality"
},
  "geometry": {"coordinates":[117.33868,34.53027],"type":"Point"}
}