{
  "type": "Feature",
  "properties": {
    "gn:admin1_code":"16.0",
    "gn:asciiname":"Diandong",
    "gn:country_code":"CN",
    "gn:dem":408,
    "gn:feature_class":"P",
    "gn:feature_code":"PPL",
    "gn:name":"Diandong",
    "gn:population":0,
    "gn:timezone":"Asia/Shanghai",
    "iso:country":"CN",
    "name:zho_x_preferred":[
        "\u5178\u5cd2"
    ],
    "wof:name":"Diandong",
    "wof:placetype":"locality"
},
  "geometry": {"coordinates":[108.059,24.8845],"type":"Point"}
}