{
  "type": "Feature",
  "properties": {
    "gn:admin1_code":"1.0",
    "gn:asciiname":"Ling'oucun",
    "gn:country_code":"CN",
    "gn:dem":18,
    "gn:feature_class":"P",
    "gn:feature_code":"PPL",
    "gn:name":"Ling\u2019oucun",
    "gn:population":0,
    "gn:timezone":"Asia/Shanghai",
    "iso:country":"CN",
    "name:und_x_variant":[
        "Ling\u2019oucun"
    ],
    "name:zho_x_preferred":[
        "\u51cc\u6b27\u6751"
    ],
    "wof:name":"Ling'oucun",
    "wof:placetype":"locality"
},
  "geometry": {"coordinates":[117.83148,33.0387],"type":"Point"}
}