{
  "type": "Feature",
  "properties": {
    "gn:admin1_code":"19.0",
    "gn:asciiname":"Maxigoucun",
    "gn:country_code":"CN",
    "gn:dem":630,
    "gn:feature_class":"P",
    "gn:feature_code":"PPL",
    "gn:name":"Maxigoucun",
    "gn:population":0,
    "gn:timezone":"Asia/Shanghai",
    "iso:country":"CN",
    "name:zho_x_preferred":[
        "\u9a6c\u897f\u6c9f\u6751"
    ],
    "wof:name":"Maxigoucun",
    "wof:placetype":"locality"
},
  "geometry": {"coordinates":[119.509,41.4551],"type":"Point"}
}