{
  "type": "Feature",
  "properties": {
    "gn:admin1_code":"25",
    "gn:asciiname":"Cangshan",
    "gn:country_code":"CN",
    "gn:dem":210,
    "gn:feature_class":"P",
    "gn:feature_code":"PPL",
    "gn:name":"Cangshan",
    "gn:population":0,
    "gn:timezone":"Asia/Shanghai",
    "iso:country":"CN",
    "name:zho_x_preferred":[
        "\u82cd\u5c71"
    ],
    "wof:name":"Cangshan",
    "wof:placetype":"locality"
},
  "geometry": {"coordinates":[117.621,35.1682],"type":"Point"}
}