{
  "type": "Feature",
  "properties": {
    "gn:admin1_code":"08",
    "gn:asciiname":"Li-hua-ma",
    "gn:country_code":"CN",
    "gn:dem":268,
    "gn:feature_class":"P",
    "gn:feature_code":"PPL",
    "gn:name":"Li-hua-ma",
    "gn:population":0,
    "gn:timezone":"Asia/Shanghai",
    "iso:country":"CN",
    "wof:name":"Li-hua-ma",
    "wof:placetype":"locality"
},
  "geometry": {"coordinates":[126.32639,48.3925],"type":"Point"}
}