{
  "type": "Feature",
  "properties": {
    "gn:admin1_code":"3.0",
    "gn:asciiname":"Wanfang Shujia",
    "gn:country_code":"CN",
    "gn:dem":181,
    "gn:feature_class":"P",
    "gn:feature_code":"PPL",
    "gn:name":"Wanfang Shujia",
    "gn:population":0,
    "gn:timezone":"Asia/Shanghai",
    "iso:country":"CN",
    "name:und_x_variant":[
        "\u4e07\u574a\u8212\u5bb6"
    ],
    "wof:name":"Wanfang Shujia",
    "wof:placetype":"locality"
},
  "geometry": {"coordinates":[115.19571999999999,28.91997000000001],"type":"Point"}
}