{
  "type": "Feature",
  "properties": {
    "gn:admin1_code":"15.0",
    "gn:asciiname":"Sujiamiao",
    "gn:country_code":"CN",
    "gn:dem":1466,
    "gn:feature_class":"P",
    "gn:feature_code":"PPL",
    "gn:name":"Sujiamiao",
    "gn:population":0,
    "gn:timezone":"Asia/Shanghai",
    "iso:country":"CN",
    "name:zho_x_preferred":[
        "\u82cf\u5bb6\u5e99"
    ],
    "wof:name":"Sujiamiao",
    "wof:placetype":"locality"
},
  "geometry": {"coordinates":[107.06,35.6343],"type":"Point"}
}