{
  "type": "Feature",
  "properties": {
    "gn:admin1_code":"26.0",
    "gn:asciiname":"Luoquanyan",
    "gn:country_code":"CN",
    "gn:dem":942,
    "gn:feature_class":"P",
    "gn:feature_code":"PPL",
    "gn:name":"Luoquanyan",
    "gn:population":0,
    "gn:timezone":"Asia/Shanghai",
    "iso:country":"CN",
    "name:und_x_variant":[
        "\u7f57\u5708\u5ca9"
    ],
    "wof:name":"Luoquanyan",
    "wof:placetype":"locality"
},
  "geometry": {"coordinates":[106.41667,33.17255],"type":"Point"}
}