{
  "type": "Feature",
  "properties": {
    "gn:admin1_code":"25",
    "gn:asciiname":"Guihe Yicun",
    "gn:country_code":"CN",
    "gn:dem":28,
    "gn:feature_class":"P",
    "gn:feature_code":"PPL",
    "gn:name":"Guihe Yicun",
    "gn:population":0,
    "gn:timezone":"Asia/Shanghai",
    "iso:country":"CN",
    "name:zho_x_preferred":[
        "\u6842\u6cb3\u4e00\u6751"
    ],
    "wof:name":"Guihe Yicun",
    "wof:placetype":"locality"
},
  "geometry": {"coordinates":[118.91369,36.76297],"type":"Point"}
}