{
  "type": "Feature",
  "properties": {
    "gn:admin1_code":"2.0",
    "gn:asciiname":"Kaoxiwan",
    "gn:country_code":"CN",
    "gn:dem":371,
    "gn:feature_class":"P",
    "gn:feature_code":"PPL",
    "gn:name":"Kaoxiwan",
    "gn:population":0,
    "gn:timezone":"Asia/Shanghai",
    "iso:country":"CN",
    "name:und_x_variant":[
        "\u9760\u897f\u5f2f"
    ],
    "wof:name":"Kaoxiwan",
    "wof:placetype":"locality"
},
  "geometry": {"coordinates":[119.35235,30.33934],"type":"Point"}
}