{
  "type": "Feature",
  "properties": {
    "gn:admin1_code":"02",
    "gn:asciiname":"Sijiao Liangting",
    "gn:country_code":"CN",
    "gn:dem":13,
    "gn:feature_class":"P",
    "gn:feature_code":"PPL",
    "gn:name":"Sijiao Liangting",
    "gn:population":0,
    "gn:timezone":"Asia/Shanghai",
    "iso:country":"CN",
    "name:und_x_variant":[
        "Liang-ting",
        "Sijiao Liangting"
    ],
    "wof:name":"Sijiao Liangting",
    "wof:placetype":"locality"
},
  "geometry": {"coordinates":[122.45999999999999,30.71417000000001],"type":"Point"}
}