{
  "type": "Feature",
  "properties": {
    "gn:admin1_code":"10.0",
    "gn:asciiname":"Lijiayao",
    "gn:country_code":"CN",
    "gn:dem":915,
    "gn:feature_class":"P",
    "gn:feature_code":"PPL",
    "gn:name":"Lijiayao",
    "gn:population":0,
    "gn:timezone":"Asia/Shanghai",
    "iso:country":"CN",
    "name:zho_x_preferred":[
        "\u674e\u5bb6\u7a91"
    ],
    "wof:name":"Lijiayao",
    "wof:placetype":"locality"
},
  "geometry": {"coordinates":[115.05052000000001,40.76694000000001],"type":"Point"}
}