{
  "type": "Feature",
  "properties": {
    "gn:admin1_code":"25",
    "gn:asciiname":"Guanzao",
    "gn:country_code":"CN",
    "gn:dem":9,
    "gn:feature_class":"P",
    "gn:feature_code":"PPL",
    "gn:name":"Guanzao",
    "gn:population":0,
    "gn:timezone":"Asia/Shanghai",
    "iso:country":"CN",
    "name:zho_x_preferred":[
        "\u5b98\u7076"
    ],
    "wof:name":"Guanzao",
    "wof:placetype":"locality"
},
  "geometry": {"coordinates":[118.30076,37.81983],"type":"Point"}
}