{
  "type": "Feature",
  "properties": {
    "gn:admin1_code":"11.0",
    "gn:asciiname":"Gaojiazhou",
    "gn:country_code":"CN",
    "gn:dem":72,
    "gn:feature_class":"P",
    "gn:feature_code":"PPL",
    "gn:name":"Gaojiazhou",
    "gn:population":0,
    "gn:timezone":"Asia/Shanghai",
    "iso:country":"CN",
    "name:zho_x_preferred":[
        "Gaojiazhou"
    ],
    "name:zho_x_variant":[
        "\u9ad8\u5bb6\u6d32"
    ],
    "wof:name":"Gaojiazhou",
    "wof:placetype":"locality"
},
  "geometry": {"coordinates":[111.08335,28.89525],"type":"Point"}
}