{
  "type": "Feature",
  "properties": {
    "gn:admin1_code":"8.0",
    "gn:asciiname":"Xiaoluocun",
    "gn:country_code":"CN",
    "gn:dem":132,
    "gn:feature_class":"P",
    "gn:feature_code":"PPL",
    "gn:name":"Xiaoluocun",
    "gn:population":0,
    "gn:timezone":"Asia/Shanghai",
    "iso:country":"CN",
    "name:zho_x_preferred":[
        "\u5c0f\u7f57\u6751"
    ],
    "wof:name":"Xiaoluocun",
    "wof:placetype":"locality"
},
  "geometry": {"coordinates":[126.79151,46.03074],"type":"Point"}
}