{
  "type": "Feature",
  "properties": {
    "gn:admin1_code":"5.0",
    "gn:asciiname":"Houyangjialing",
    "gn:country_code":"CN",
    "gn:dem":197,
    "gn:feature_class":"P",
    "gn:feature_code":"PPL",
    "gn:name":"Houyangjialing",
    "gn:population":0,
    "gn:timezone":"Asia/Shanghai",
    "iso:country":"CN",
    "name:zho_x_preferred":[
        "\u540e\u6768\u5bb6\u5cad"
    ],
    "wof:name":"Houyangjialing",
    "wof:placetype":"locality"
},
  "geometry": {"coordinates":[126.34086000000001,44.32104],"type":"Point"}
}