{
  "type": "Feature",
  "properties": {
    "gn:admin1_code":"30.0",
    "gn:asciiname":"Wangongying",
    "gn:country_code":"CN",
    "gn:dem":210,
    "gn:feature_class":"P",
    "gn:feature_code":"PPL",
    "gn:name":"Wangongying",
    "gn:population":0,
    "gn:timezone":"Asia/Shanghai",
    "iso:country":"CN",
    "name:zho_x_preferred":[
        "\u7897\u516c\u8425"
    ],
    "wof:name":"Wangongying",
    "wof:placetype":"locality"
},
  "geometry": {"coordinates":[114.58158,23.8572],"type":"Point"}
}