{
  "type": "Feature",
  "properties": {
    "gn:admin1_code":"19.0",
    "gn:asciiname":"Daniutuncun",
    "gn:country_code":"CN",
    "gn:dem":51,
    "gn:feature_class":"P",
    "gn:feature_code":"PPL",
    "gn:name":"Daniutuncun",
    "gn:population":0,
    "gn:timezone":"Asia/Shanghai",
    "iso:country":"CN",
    "name:zho_x_preferred":[
        "\u5927\u725b\u5c6f\u6751"
    ],
    "wof:name":"Daniutuncun",
    "wof:placetype":"locality"
},
  "geometry": {"coordinates":[120.96899999999999,41.1738],"type":"Point"}
}