{
  "type": "Feature",
  "properties": {
    "gn:admin1_code":"9.0",
    "gn:asciiname":"Sigou",
    "gn:country_code":"CN",
    "gn:dem":285,
    "gn:feature_class":"P",
    "gn:feature_code":"PPL",
    "gn:name":"Sigou",
    "gn:population":0,
    "gn:timezone":"Asia/Shanghai",
    "iso:country":"CN",
    "name:und_x_variant":[
        "\u5bfa\u6c9f",
        "Sigou"
    ],
    "wof:name":"Sigou",
    "wof:placetype":"locality"
},
  "geometry": {"coordinates":[112.62969,33.66168],"type":"Point"}
}