{
  "type": "Feature",
  "properties": {
    "gn:admin1_code":"30.0",
    "gn:asciiname":"Songshanjiao",
    "gn:country_code":"CN",
    "gn:dem":126,
    "gn:feature_class":"P",
    "gn:feature_code":"PPL",
    "gn:name":"Songshanjiao",
    "gn:population":0,
    "gn:timezone":"Asia/Shanghai",
    "iso:country":"CN",
    "name:zho_x_preferred":[
        "Songshanjiao"
    ],
    "name:zho_x_variant":[
        "\u677e\u5c71\u811a"
    ],
    "wof:name":"Songshanjiao",
    "wof:placetype":"locality"
},
  "geometry": {"coordinates":[112.55222000000001,24.365],"type":"Point"}
}