{
  "type": "Feature",
  "properties": {
    "gn:admin1_code":"30.0",
    "gn:asciiname":"Hepu",
    "gn:country_code":"CN",
    "gn:dem":2,
    "gn:feature_class":"P",
    "gn:feature_code":"PPL",
    "gn:name":"Hepu",
    "gn:population":0,
    "gn:timezone":"Asia/Shanghai",
    "iso:country":"CN",
    "name:zho_x_preferred":[
        "\u6cb3\u6d66"
    ],
    "wof:name":"Hepu",
    "wof:placetype":"locality"
},
  "geometry": {"coordinates":[115.251,22.84952],"type":"Point"}
}