{
  "type": "Feature",
  "properties": {
    "gn:admin1_code":"26.0",
    "gn:asciiname":"Huashecun",
    "gn:country_code":"CN",
    "gn:dem":1080,
    "gn:feature_class":"P",
    "gn:feature_code":"PPL",
    "gn:name":"Huashecun",
    "gn:population":0,
    "gn:timezone":"Asia/Shanghai",
    "iso:country":"CN",
    "name:zho_x_preferred":[
        "\u82b1\u820d\u6751"
    ],
    "wof:name":"Huashecun",
    "wof:placetype":"locality"
},
  "geometry": {"coordinates":[110.27509000000001,35.63989],"type":"Point"}
}