{
  "type": "Feature",
  "properties": {
    "gn:admin1_code":"30.0",
    "gn:asciiname":"Ganhucun",
    "gn:country_code":"CN",
    "gn:dem":20,
    "gn:feature_class":"P",
    "gn:feature_code":"PPL",
    "gn:name":"Ganhucun",
    "gn:population":0,
    "gn:timezone":"Asia/Shanghai",
    "iso:country":"CN",
    "name:und_x_variant":[
        "Gankeng"
    ],
    "name:zho_x_preferred":[
        "\u7518\u846b\u6751"
    ],
    "name:zho_x_variant":[
        "\u7518\u5751"
    ],
    "wof:name":"Ganhucun",
    "wof:placetype":"locality"
},
  "geometry": {"coordinates":[115.68022999999999,23.03732],"type":"Point"}
}