{
  "type": "Feature",
  "properties": {
    "gn:admin1_code":"24.0",
    "gn:asciiname":"Shipantou",
    "gn:country_code":"CN",
    "gn:dem":1257,
    "gn:feature_class":"P",
    "gn:feature_code":"PPL",
    "gn:name":"Shipantou",
    "gn:population":0,
    "gn:timezone":"Asia/Shanghai",
    "iso:country":"CN",
    "name:zho_x_preferred":[
        "\u77f3\u76d8\u5934"
    ],
    "wof:name":"Shipantou",
    "wof:placetype":"locality"
},
  "geometry": {"coordinates":[111.16231999999999,38.06644],"type":"Point"}
}