{
  "type": "Feature",
  "properties": {
    "gn:admin1_code":"7.0",
    "gn:asciiname":"Qishanqian",
    "gn:country_code":"CN",
    "gn:dem":184,
    "gn:feature_class":"P",
    "gn:feature_code":"PPL",
    "gn:name":"Qishanqian",
    "gn:population":0,
    "gn:timezone":"Asia/Shanghai",
    "iso:country":"CN",
    "name:zho_x_preferred":[
        "\u6b67\u5c71\u524d"
    ],
    "wof:name":"Qishanqian",
    "wof:placetype":"locality"
},
  "geometry": {"coordinates":[118.39702,27.66071],"type":"Point"}
}