{
  "type": "Feature",
  "properties": {
    "gn:admin1_code":"4.0",
    "gn:asciiname":"Yingdong",
    "gn:country_code":"CN",
    "gn:dem":7,
    "gn:feature_class":"P",
    "gn:feature_code":"PPL",
    "gn:name":"Yingdong",
    "gn:population":0,
    "gn:timezone":"Asia/Shanghai",
    "iso:country":"CN",
    "name:zho_x_preferred":[
        "\u8fce\u4e1c"
    ],
    "wof:name":"Yingdong",
    "wof:placetype":"locality"
},
  "geometry": {"coordinates":[119.78834000000001,32.16240999999999],"type":"Point"}
}