{
  "type": "Feature",
  "properties": {
    "gn:admin1_code":"12.0",
    "gn:asciiname":"Chengyongxing",
    "gn:country_code":"CN",
    "gn:dem":56,
    "gn:feature_class":"P",
    "gn:feature_code":"PPL",
    "gn:name":"Chengyongxing",
    "gn:population":0,
    "gn:timezone":"Asia/Shanghai",
    "iso:country":"CN",
    "name:zho_x_preferred":[
        "\u7a0b\u6c38\u5174"
    ],
    "wof:name":"Chengyongxing",
    "wof:placetype":"locality"
},
  "geometry": {"coordinates":[114.31265999999999,30.24706],"type":"Point"}
}