{
  "type": "Feature",
  "properties": {
    "gn:admin1_code":"3.0",
    "gn:asciiname":"Shiwoli",
    "gn:country_code":"CN",
    "gn:dem":584,
    "gn:feature_class":"P",
    "gn:feature_code":"PPL",
    "gn:name":"Shiwoli",
    "gn:population":0,
    "gn:timezone":"Asia/Shanghai",
    "iso:country":"CN",
    "name:und_x_variant":[
        "\u77f3\u7a9d\u91cc"
    ],
    "wof:name":"Shiwoli",
    "wof:placetype":"locality"
},
  "geometry": {"coordinates":[114.70187,28.99862000000001],"type":"Point"}
}