{
  "type": "Feature",
  "properties": {
    "gn:admin1_code":"15.0",
    "gn:asciiname":"Ta'erzui",
    "gn:country_code":"CN",
    "gn:dem":1359,
    "gn:feature_class":"P",
    "gn:feature_code":"PPL",
    "gn:name":"Ta\u2019erzui",
    "gn:population":0,
    "gn:timezone":"Asia/Shanghai",
    "iso:country":"CN",
    "name:und_x_variant":[
        "Ta\u2019erzui",
        "\u5854\u513f\u5480"
    ],
    "wof:name":"Ta'erzui",
    "wof:placetype":"locality"
},
  "geometry": {"coordinates":[107.679,36.51837],"type":"Point"}
}