{
  "type": "Feature",
  "properties": {
    "gn:admin1_code":"26.0",
    "gn:asciiname":"Xudaocun",
    "gn:country_code":"CN",
    "gn:dem":1066,
    "gn:feature_class":"P",
    "gn:feature_code":"PPL",
    "gn:name":"Xudaocun",
    "gn:population":0,
    "gn:timezone":"Asia/Shanghai",
    "iso:country":"CN",
    "name:zho_x_preferred":[
        "\u8bb8\u9053\u6751"
    ],
    "wof:name":"Xudaocun",
    "wof:placetype":"locality"
},
  "geometry": {"coordinates":[109.39512999999999,35.23397],"type":"Point"}
}