{
  "type": "Feature",
  "properties": {
    "gn:admin1_code":"29.0",
    "gn:asciiname":"Jipu",
    "gn:country_code":"CN",
    "gn:dem":1868,
    "gn:feature_class":"P",
    "gn:feature_code":"PPL",
    "gn:name":"Jipu",
    "gn:population":0,
    "gn:timezone":"Asia/Shanghai",
    "iso:country":"CN",
    "name:zho_x_preferred":[
        "\u5b63\u666e"
    ],
    "wof:name":"Jipu",
    "wof:placetype":"locality"
},
  "geometry": {"coordinates":[98.9016,26.8139],"type":"Point"}
}