{
  "type": "Feature",
  "properties": {
    "gn:admin1_code":"26",
    "gn:asciiname":"Donghe",
    "gn:cc2":"CN",
    "gn:country_code":"CN",
    "gn:dem":1251,
    "gn:feature_class":"P",
    "gn:feature_code":"PPL",
    "gn:name":"Donghe",
    "gn:population":0,
    "gn:timezone":"Asia/Shanghai",
    "iso:country":"CN",
    "name:ceb_x_preferred":[
        "Donghe"
    ],
    "name:deu_x_preferred":[
        "Donghe"
    ],
    "name:und_x_variant":[
        "Tung-ho",
        "Donghe"
    ],
    "wof:name":"Donghe",
    "wof:placetype":"locality"
},
  "geometry": {"coordinates":[109.98333,38.51667],"type":"Point"}
}