{
  "type": "Feature",
  "properties": {
    "gn:admin1_code":"4.0",
    "gn:asciiname":"Hedong",
    "gn:country_code":"CN",
    "gn:dem":22,
    "gn:feature_class":"P",
    "gn:feature_code":"PPL",
    "gn:name":"Hedong",
    "gn:population":0,
    "gn:timezone":"Asia/Shanghai",
    "iso:country":"CN",
    "name:zho_x_preferred":[
        "\u6cb3\u4e1c"
    ],
    "wof:name":"Hedong",
    "wof:placetype":"locality"
},
  "geometry": {"coordinates":[119.32706,31.89945],"type":"Point"}
}