{
  "type": "Feature",
  "properties": {
    "gn:admin1_code":"15.0",
    "gn:asciiname":"Lijia Xinzhuang",
    "gn:country_code":"CN",
    "gn:dem":1394,
    "gn:feature_class":"P",
    "gn:feature_code":"PPL",
    "gn:name":"Lijia Xinzhuang",
    "gn:population":0,
    "gn:timezone":"Asia/Shanghai",
    "iso:country":"CN",
    "name:und_x_variant":[
        "\u674e\u5bb6\u65b0\u5e84"
    ],
    "wof:name":"Lijia Xinzhuang",
    "wof:placetype":"locality"
},
  "geometry": {"coordinates":[107.985,36.4106],"type":"Point"}
}