{
  "type": "Feature",
  "properties": {
    "gn:admin1_code":"4.0",
    "gn:asciiname":"Shenjiachang",
    "gn:country_code":"CN",
    "gn:dem":5,
    "gn:feature_class":"P",
    "gn:feature_code":"PPL",
    "gn:name":"Shenjiachang",
    "gn:population":0,
    "gn:timezone":"Asia/Shanghai",
    "iso:country":"CN",
    "name:zho_x_preferred":[
        "\u6c88\u5bb6\u573a"
    ],
    "wof:name":"Shenjiachang",
    "wof:placetype":"locality"
},
  "geometry": {"coordinates":[120.8292,32.11681],"type":"Point"}
}