{
  "type": "Feature",
  "properties": {
    "gn:admin1_code":"33.0",
    "gn:asciiname":"Shuangfengyun",
    "gn:country_code":"CN",
    "gn:dem":501,
    "gn:feature_class":"P",
    "gn:feature_code":"PPL",
    "gn:name":"Shuangfengyun",
    "gn:population":0,
    "gn:timezone":"Asia/Shanghai",
    "iso:country":"CN",
    "name:zho_x_preferred":[
        "\u53cc\u51e4\u4e91"
    ],
    "wof:name":"Shuangfengyun",
    "wof:placetype":"locality"
},
  "geometry": {"coordinates":[108.98195,28.16927],"type":"Point"}
}