{
  "type": "Feature",
  "properties": {
    "gn:admin1_code":"3.0",
    "gn:asciiname":"Yangkengwei",
    "gn:country_code":"CN",
    "gn:dem":254,
    "gn:feature_class":"P",
    "gn:feature_code":"PPL",
    "gn:name":"Yangkengwei",
    "gn:population":0,
    "gn:timezone":"Asia/Shanghai",
    "iso:country":"CN",
    "name:und_x_variant":[
        "\u6d0b\u5751\u5c3e"
    ],
    "wof:name":"Yangkengwei",
    "wof:placetype":"locality"
},
  "geometry": {"coordinates":[115.8526,26.12402],"type":"Point"}
}