{
  "type": "Feature",
  "properties": {
    "gn:admin1_code":"12.0",
    "gn:asciiname":"Taishenmiao",
    "gn:country_code":"CN",
    "gn:dem":535,
    "gn:feature_class":"P",
    "gn:feature_code":"PPL",
    "gn:name":"Taishenmiao",
    "gn:population":0,
    "gn:timezone":"Asia/Shanghai",
    "iso:country":"CN",
    "name:zho_x_preferred":[
        "\u592a\u795e\u5e99"
    ],
    "wof:name":"Taishenmiao",
    "wof:placetype":"locality"
},
  "geometry": {"coordinates":[110.16728000000001,32.35129000000001],"type":"Point"}
}