{
  "type": "Feature",
  "properties": {
    "gn:admin1_code":"14.0",
    "gn:asciiname":"Zhebuqin",
    "gn:country_code":"CN",
    "gn:dem":4353,
    "gn:feature_class":"P",
    "gn:feature_code":"PPL",
    "gn:name":"Zhebuqin",
    "gn:population":0,
    "gn:timezone":"Asia/Urumqi",
    "iso:country":"CN",
    "name:zho_x_preferred":[
        "\u8005\u4e0d\u94a6"
    ],
    "wof:name":"Zhebuqin",
    "wof:placetype":"locality"
},
  "geometry": {"coordinates":[93.5924,31.41286],"type":"Point"}
}