{
  "type": "Feature",
  "properties": {
    "gn:admin1_code":"15.0",
    "gn:asciiname":"Fanjiaxiaozhang",
    "gn:country_code":"CN",
    "gn:dem":1752,
    "gn:feature_class":"P",
    "gn:feature_code":"PPL",
    "gn:name":"Fanjiaxiaozhang",
    "gn:population":0,
    "gn:timezone":"Asia/Shanghai",
    "iso:country":"CN",
    "name:und_x_variant":[
        "\u8303\u5bb6\u5c0f\u638c"
    ],
    "wof:name":"Fanjiaxiaozhang",
    "wof:placetype":"locality"
},
  "geometry": {"coordinates":[106.49643,36.28655],"type":"Point"}
}