{
  "type": "Feature",
  "properties": {
    "gn:admin1_code":"25",
    "gn:asciiname":"Nanzhaojiagou",
    "gn:country_code":"CN",
    "gn:dem":273,
    "gn:feature_class":"P",
    "gn:feature_code":"PPL",
    "gn:name":"Nanzhaojiagou",
    "gn:population":0,
    "gn:timezone":"Asia/Shanghai",
    "iso:country":"CN",
    "name:zho_x_preferred":[
        "\u5357\u8d75\u5bb6\u6c9f"
    ],
    "wof:name":"Nanzhaojiagou",
    "wof:placetype":"locality"
},
  "geometry": {"coordinates":[119.003,36.206],"type":"Point"}
}