{
  "type": "Feature",
  "properties": {
    "gn:admin1_code":"19",
    "gn:asciiname":"Tieyingzi",
    "gn:country_code":"CN",
    "gn:dem":602,
    "gn:feature_class":"P",
    "gn:feature_code":"PPL",
    "gn:name":"Tieyingzi",
    "gn:population":0,
    "gn:timezone":"Asia/Shanghai",
    "iso:country":"CN",
    "wof:name":"Tieyingzi",
    "wof:placetype":"locality"
},
  "geometry": {"coordinates":[119.88583,41.775],"type":"Point"}
}