{
  "type": "Feature",
  "properties": {
    "gn:admin1_code":"11",
    "gn:asciiname":"Shazitian",
    "gn:country_code":"CN",
    "gn:dem":384,
    "gn:feature_class":"P",
    "gn:feature_code":"PPL",
    "gn:name":"Shazitian",
    "gn:population":0,
    "gn:timezone":"Asia/Shanghai",
    "iso:country":"CN",
    "name:zho_x_preferred":[
        "\u6c99\u5b50\u7530"
    ],
    "wof:name":"Shazitian",
    "wof:placetype":"locality"
},
  "geometry": {"coordinates":[111.94499999999999,25.72444],"type":"Point"}
}