{
  "type": "Feature",
  "properties": {
    "gn:admin1_code":"10",
    "gn:asciiname":"Houlabadong",
    "gn:country_code":"CN",
    "gn:dem":983,
    "gn:feature_class":"P",
    "gn:feature_code":"PPL",
    "gn:name":"Houlabadong",
    "gn:population":0,
    "gn:timezone":"Asia/Shanghai",
    "iso:country":"CN",
    "name:zho_x_preferred":[
        "\u540e\u5587\u53ed\u6d1e"
    ],
    "wof:name":"Houlabadong",
    "wof:placetype":"locality"
},
  "geometry": {"coordinates":[116.81364000000001,41.39215],"type":"Point"}
}