{
  "type": "Feature",
  "properties": {
    "gn:admin1_code":"2.0",
    "gn:asciiname":"Kengmenli",
    "gn:country_code":"CN",
    "gn:dem":196,
    "gn:feature_class":"P",
    "gn:feature_code":"PPL",
    "gn:name":"Kengmenli",
    "gn:population":0,
    "gn:timezone":"Asia/Shanghai",
    "iso:country":"CN",
    "name:zho_x_preferred":[
        "\u5751\u95e8\u91cc"
    ],
    "wof:name":"Kengmenli",
    "wof:placetype":"locality"
},
  "geometry": {"coordinates":[120.44655,29.39052],"type":"Point"}
}