{
  "type": "Feature",
  "properties": {
    "gn:admin1_code":"1.0",
    "gn:asciiname":"Yanzhoucun",
    "gn:country_code":"CN",
    "gn:dem":25,
    "gn:feature_class":"P",
    "gn:feature_code":"PPL",
    "gn:name":"Yanzhoucun",
    "gn:population":0,
    "gn:timezone":"Asia/Shanghai",
    "iso:country":"CN",
    "name:zho_x_preferred":[
        "\u6df9\u5468\u6751"
    ],
    "wof:name":"Yanzhoucun",
    "wof:placetype":"locality"
},
  "geometry": {"coordinates":[117.46035000000001,33.51801],"type":"Point"}
}