{
  "type": "Feature",
  "properties": {
    "gn:admin1_code":"24.0",
    "gn:asciiname":"Shangpingwang",
    "gn:country_code":"CN",
    "gn:dem":426,
    "gn:feature_class":"P",
    "gn:feature_code":"PPL",
    "gn:name":"Shangpingwang",
    "gn:population":0,
    "gn:timezone":"Asia/Shanghai",
    "iso:country":"CN",
    "name:und_x_variant":[
        "\u4e0a\u5e73\u671b"
    ],
    "name:zho_x_preferred":[
        "\u4e0a\u5e73\u671b"
    ],
    "wof:name":"Shangpingwang",
    "wof:placetype":"locality"
},
  "geometry": {"coordinates":[111.30365,35.64323],"type":"Point"}
}