{
  "type": "Feature",
  "properties": {
    "gn:admin1_code":"16.0",
    "gn:asciiname":"Changhetang",
    "gn:country_code":"CN",
    "gn:dem":74,
    "gn:feature_class":"P",
    "gn:feature_code":"PPL",
    "gn:name":"Changhetang",
    "gn:population":0,
    "gn:timezone":"Asia/Shanghai",
    "iso:country":"CN",
    "name:zho_x_preferred":[
        "\u957f\u79be\u5858"
    ],
    "wof:name":"Changhetang",
    "wof:placetype":"locality"
},
  "geometry": {"coordinates":[109.051,22.1862],"type":"Point"}
}