{
  "type": "Feature",
  "properties": {
    "gn:admin1_code":"14.0",
    "gn:asciiname":"Gadacun",
    "gn:country_code":"CN",
    "gn:dem":4116,
    "gn:feature_class":"P",
    "gn:feature_code":"PPL",
    "gn:name":"Gadacun",
    "gn:population":0,
    "gn:timezone":"Asia/Urumqi",
    "iso:country":"CN",
    "name:zho_x_preferred":[
        "\u560e\u8fbe\u6751"
    ],
    "wof:name":"Gadacun",
    "wof:placetype":"locality"
},
  "geometry": {"coordinates":[94.25265,31.52571],"type":"Point"}
}