{
  "type": "Feature",
  "properties": {
    "gn:admin1_code":"19.0",
    "gn:asciiname":"Nailingaocun",
    "gn:country_code":"CN",
    "gn:dem":644,
    "gn:feature_class":"P",
    "gn:feature_code":"PPL",
    "gn:name":"Nailingaocun",
    "gn:population":0,
    "gn:timezone":"Asia/Shanghai",
    "iso:country":"CN",
    "name:zho_x_preferred":[
        "\u4e43\u6797\u768b\u6751"
    ],
    "wof:name":"Nailingaocun",
    "wof:placetype":"locality"
},
  "geometry": {"coordinates":[119.727,42.0034],"type":"Point"}
}