{
  "type": "Feature",
  "properties": {
    "gn:admin1_code":"8.0",
    "gn:asciiname":"Zhongxiantun",
    "gn:country_code":"CN",
    "gn:dem":143,
    "gn:feature_class":"P",
    "gn:feature_code":"PPL",
    "gn:name":"Zhongxiantun",
    "gn:population":0,
    "gn:timezone":"Asia/Shanghai",
    "iso:country":"CN",
    "name:zho_x_preferred":[
        "\u4e2d\u9c9c\u5c6f"
    ],
    "wof:name":"Zhongxiantun",
    "wof:placetype":"locality"
},
  "geometry": {"coordinates":[128.07641000000001,46.08476],"type":"Point"}
}