{
  "type": "Feature",
  "properties": {
    "gn:admin1_code":"1.0",
    "gn:asciiname":"Pandiancun",
    "gn:country_code":"CN",
    "gn:dem":28,
    "gn:feature_class":"P",
    "gn:feature_code":"PPL",
    "gn:name":"Pandiancun",
    "gn:population":0,
    "gn:timezone":"Asia/Shanghai",
    "iso:country":"CN",
    "name:und_x_variant":[
        "Pandian"
    ],
    "name:zho_x_preferred":[
        "\u6f58\u5e97\u6751"
    ],
    "wof:name":"Pandiancun",
    "wof:placetype":"locality"
},
  "geometry": {"coordinates":[115.94571999999999,32.49433],"type":"Point"}
}