{
  "type": "Feature",
  "properties": {
    "gn:admin1_code":"11.0",
    "gn:asciiname":"Tongzichong",
    "gn:country_code":"CN",
    "gn:dem":288,
    "gn:feature_class":"P",
    "gn:feature_code":"PPL",
    "gn:name":"Tongzichong",
    "gn:population":0,
    "gn:timezone":"Asia/Shanghai",
    "iso:country":"CN",
    "name:zho_x_preferred":[
        "\u6850\u5b50\u51b2"
    ],
    "wof:name":"Tongzichong",
    "wof:placetype":"locality"
},
  "geometry": {"coordinates":[110.85738000000001,27.03004],"type":"Point"}
}