{
  "type": "Feature",
  "properties": {
    "gn:admin1_code":"03",
    "gn:asciiname":"Kuimeishan",
    "gn:country_code":"CN",
    "gn:dem":305,
    "gn:feature_class":"P",
    "gn:feature_code":"PPLA4",
    "gn:name":"Kuimeishan",
    "gn:population":0,
    "gn:timezone":"Asia/Shanghai",
    "iso:country":"CN",
    "name:und_x_variant":[
        "\u5cbf\u7f8e\u5c71",
        "Kuimeishan Zhen",
        "\u5cbf\u7f8e\u5c71\u9547"
    ],
    "wof:name":"Kuimeishan",
    "wof:placetype":"locality"
},
  "geometry": {"coordinates":[114.88779,24.66898],"type":"Point"}
}