{
  "type": "Feature",
  "properties": {
    "gn:admin1_code":"9.0",
    "gn:asciiname":"Wangweizi",
    "gn:country_code":"CN",
    "gn:dem":61,
    "gn:feature_class":"P",
    "gn:feature_code":"PPL",
    "gn:name":"Wangweizi",
    "gn:population":0,
    "gn:timezone":"Asia/Shanghai",
    "iso:country":"CN",
    "name:zho_x_preferred":[
        "\u738b\u56f4\u5b5c"
    ],
    "wof:name":"Wangweizi",
    "wof:placetype":"locality"
},
  "geometry": {"coordinates":[114.59350000000001,32.44702],"type":"Point"}
}