{
  "type": "Feature",
  "properties": {
    "gn:admin1_code":"1.0",
    "gn:asciiname":"Yaoxi",
    "gn:country_code":"CN",
    "gn:dem":139,
    "gn:feature_class":"P",
    "gn:feature_code":"PPL",
    "gn:name":"Yaoxi",
    "gn:population":0,
    "gn:timezone":"Asia/Shanghai",
    "iso:country":"CN",
    "name:und_x_variant":[
        "Yao-ch\u2019i",
        "Yao-hsi",
        "Yaoxi",
        "\u7476\u6eaa"
    ],
    "name:zho_x_preferred":[
        "\u7476\u6eaa"
    ],
    "wof:name":"Yaoxi",
    "wof:placetype":"locality"
},
  "geometry": {"coordinates":[118.23671000000002,29.67554],"type":"Point"}
}