{
  "type": "Feature",
  "properties": {
    "gn:admin1_code":"4.0",
    "gn:asciiname":"Haowancun",
    "gn:country_code":"CN",
    "gn:dem":37,
    "gn:feature_class":"P",
    "gn:feature_code":"PPL",
    "gn:name":"Haowancun",
    "gn:population":0,
    "gn:timezone":"Asia/Shanghai",
    "iso:country":"CN",
    "name:zho_x_preferred":[
        "\u90dd\u6e7e\u6751"
    ],
    "wof:name":"Haowancun",
    "wof:placetype":"locality"
},
  "geometry": {"coordinates":[117.5213,34.08929000000001],"type":"Point"}
}