{
  "type": "Feature",
  "properties": {
    "gn:admin1_code":"19.0",
    "gn:asciiname":"Sujiabu",
    "gn:country_code":"CN",
    "gn:dem":325,
    "gn:feature_class":"P",
    "gn:feature_code":"PPL",
    "gn:name":"Sujiabu",
    "gn:population":0,
    "gn:timezone":"Asia/Shanghai",
    "iso:country":"CN",
    "name:und_x_variant":[
        "Sujiapu",
        "Sujiabu"
    ],
    "name:zho_x_preferred":[
        "\u82cf\u5bb6\u5821"
    ],
    "wof:name":"Sujiabu",
    "wof:placetype":"locality"
},
  "geometry": {"coordinates":[124.88366000000001,41.75475],"type":"Point"}
}