{
  "type": "Feature",
  "properties": {
    "gn:admin1_code":"32.0",
    "gn:asciiname":"Tingziba",
    "gn:country_code":"CN",
    "gn:dem":464,
    "gn:feature_class":"P",
    "gn:feature_code":"PPL",
    "gn:name":"Tingziba",
    "gn:population":0,
    "gn:timezone":"Asia/Shanghai",
    "iso:country":"CN",
    "name:zho_x_preferred":[
        "\u4ead\u5b50\u575d"
    ],
    "wof:name":"Tingziba",
    "wof:placetype":"locality"
},
  "geometry": {"coordinates":[104.32098000000001,30.80773],"type":"Point"}
}