{
  "type": "Feature",
  "properties": {
    "gn:admin1_code":"15.0",
    "gn:asciiname":"Langshetouwa",
    "gn:country_code":"CN",
    "gn:dem":1531,
    "gn:feature_class":"P",
    "gn:feature_code":"PPL",
    "gn:name":"Langshetouwa",
    "gn:population":0,
    "gn:timezone":"Asia/Shanghai",
    "iso:country":"CN",
    "name:zho_x_preferred":[
        "\u72fc\u820c\u5934\u6d3c"
    ],
    "wof:name":"Langshetouwa",
    "wof:placetype":"locality"
},
  "geometry": {"coordinates":[102.911,37.9169],"type":"Point"}
}