{
  "type": "Feature",
  "properties": {
    "gn:admin1_code":"26.0",
    "gn:asciiname":"Luojiahecun",
    "gn:country_code":"CN",
    "gn:dem":617,
    "gn:feature_class":"P",
    "gn:feature_code":"PPL",
    "gn:name":"Luojiahecun",
    "gn:population":0,
    "gn:timezone":"Asia/Shanghai",
    "iso:country":"CN",
    "name:und_x_variant":[
        "\u7f57\u5bb6\u6cb3\u6751"
    ],
    "wof:name":"Luojiahecun",
    "wof:placetype":"locality"
},
  "geometry": {"coordinates":[107.87042,32.99734],"type":"Point"}
}