{
  "type": "Feature",
  "properties": {
    "gn:admin1_code":"18",
    "gn:asciiname":"Chenjiazhai",
    "gn:country_code":"CN",
    "gn:dem":1722,
    "gn:feature_class":"P",
    "gn:feature_code":"PPL",
    "gn:name":"Chenjiazhai",
    "gn:population":0,
    "gn:timezone":"Asia/Shanghai",
    "iso:country":"CN",
    "name:zho_x_preferred":[
        "\u9648\u5bb6\u5be8"
    ],
    "wof:name":"Chenjiazhai",
    "wof:placetype":"locality"
},
  "geometry": {"coordinates":[104.764,26.0533],"type":"Point"}
}