{
  "type": "Feature",
  "properties": {
    "gn:admin1_code":"04",
    "gn:asciiname":"Pingqiao",
    "gn:country_code":"CN",
    "gn:dem":47,
    "gn:feature_class":"P",
    "gn:feature_code":"PPL",
    "gn:name":"Pingqiao",
    "gn:population":0,
    "gn:timezone":"Asia/Shanghai",
    "iso:country":"CN",
    "name:und_x_variant":[
        "P\u2019ing-ch\u2019iao",
        "Pingqiao"
    ],
    "name:zho_x_preferred":[
        "\u5e73\u6865"
    ],
    "wof:name":"Pingqiao",
    "wof:placetype":"locality"
},
  "geometry": {"coordinates":[119.43080999999999,31.22305],"type":"Point"}
}