{
  "type": "Feature",
  "properties": {
    "gn:admin1_code":"02",
    "gn:asciiname":"Longshancun",
    "gn:country_code":"CN",
    "gn:dem":18,
    "gn:feature_class":"P",
    "gn:feature_code":"PPL",
    "gn:name":"Longshancun",
    "gn:population":0,
    "gn:timezone":"Asia/Shanghai",
    "iso:country":"CN",
    "name:und_x_variant":[
        "Longshan",
        "Longshancun"
    ],
    "name:zho_x_preferred":[
        "\u9f99\u5c71"
    ],
    "name:zho_x_variant":[
        "\u9f99\u5c71\u6751"
    ],
    "wof:name":"Longshancun",
    "wof:placetype":"locality"
},
  "geometry": {"coordinates":[121.94092000000001,29.93072],"type":"Point"}
}