{
  "type": "Feature",
  "properties": {
    "gn:admin1_code":"10",
    "gn:asciiname":"Lishucao",
    "gn:country_code":"CN",
    "gn:dem":603,
    "gn:feature_class":"P",
    "gn:feature_code":"PPL",
    "gn:name":"Lishucao",
    "gn:population":0,
    "gn:timezone":"Asia/Shanghai",
    "iso:country":"CN",
    "wof:name":"Lishucao",
    "wof:placetype":"locality"
},
  "geometry": {"coordinates":[114.06389,38.69667000000001],"type":"Point"}
}