{
  "type": "Feature",
  "properties": {
    "gn:admin1_code":"11.0",
    "gn:asciiname":"Qiutang",
    "gn:country_code":"CN",
    "gn:dem":87,
    "gn:feature_class":"P",
    "gn:feature_code":"PPL",
    "gn:name":"Qiutang",
    "gn:population":0,
    "gn:timezone":"Asia/Shanghai",
    "iso:country":"CN",
    "name:zho_x_preferred":[
        "\u79cb\u5858"
    ],
    "wof:name":"Qiutang",
    "wof:placetype":"locality"
},
  "geometry": {"coordinates":[112.89149999999999,26.79997],"type":"Point"}
}