{
  "type": "Feature",
  "properties": {
    "gn:admin1_code":"10",
    "gn:asciiname":"Duanmugou",
    "gn:country_code":"CN",
    "gn:dem":1073,
    "gn:feature_class":"P",
    "gn:feature_code":"PPL",
    "gn:name":"Duanmugou",
    "gn:population":0,
    "gn:timezone":"Asia/Shanghai",
    "iso:country":"CN",
    "name:zho_x_preferred":[
        "\u6934\u6728\u6c9f"
    ],
    "wof:name":"Duanmugou",
    "wof:placetype":"locality"
},
  "geometry": {"coordinates":[115.71527,40.79049000000001],"type":"Point"}
}