{
  "type": "Feature",
  "properties": {
    "gn:admin1_code":"31.0",
    "gn:asciiname":"Lezhong Nongchang Shibadui",
    "gn:country_code":"CN",
    "gn:dem":461,
    "gn:feature_class":"P",
    "gn:feature_code":"PPLF",
    "gn:name":"Lezhong Nongchang Shibadui",
    "gn:population":0,
    "gn:timezone":"Asia/Shanghai",
    "iso:country":"CN",
    "name:und_x_variant":[
        "\u4e50\u4e2d\u519c\u573a\u5341\u516b\u961f"
    ],
    "wof:name":"Lezhong Nongchang Shibadui",
    "wof:placetype":"locality"
},
  "geometry": {"coordinates":[109.32017999999999,18.78259],"type":"Point"}
}