{
  "type": "Feature",
  "properties": {
    "gn:admin1_code":"32",
    "gn:asciiname":"Namda",
    "gn:cc2":"CN",
    "gn:country_code":"CN",
    "gn:dem":3373,
    "gn:feature_class":"P",
    "gn:feature_code":"PPL",
    "gn:name":"Namda",
    "gn:population":0,
    "gn:timezone":"Asia/Shanghai",
    "iso:country":"CN",
    "name:und_x_variant":[
        "Nan-mu-ta"
    ],
    "wof:name":"Namda",
    "wof:placetype":"locality"
},
  "geometry": {"coordinates":[101.07147000000001,32.4125],"type":"Point"}
}