{
  "type": "Feature",
  "properties": {
    "gn:admin1_code":"33.0",
    "gn:asciiname":"Dangyang",
    "gn:country_code":"CN",
    "gn:dem":784,
    "gn:feature_class":"P",
    "gn:feature_code":"PPLA4",
    "gn:name":"Dangyang",
    "gn:population":0,
    "gn:timezone":"Asia/Shanghai",
    "iso:country":"CN",
    "name:und_x_variant":[
        "Dangyang Xiang",
        "Reshuiba"
    ],
    "name:zho_x_preferred":[
        "\u5f53\u9633"
    ],
    "name:zho_x_variant":[
        "\u5f53\u9633\u4e61",
        "\u70ed\u6c34\u575d"
    ],
    "wof:name":"Dangyang",
    "wof:placetype":"locality"
},
  "geometry": {"coordinates":[109.97781000000001,31.4056],"type":"Point"}
}