{
  "type": "Feature",
  "properties": {
    "gn:admin1_code":"18",
    "gn:asciiname":"Hexin",
    "gn:country_code":"CN",
    "gn:dem":796,
    "gn:feature_class":"P",
    "gn:feature_code":"PPL",
    "gn:name":"Hexin",
    "gn:population":0,
    "gn:timezone":"Asia/Shanghai",
    "iso:country":"CN",
    "name:zho_x_preferred":[
        "\u6cb3\u5fc3"
    ],
    "wof:name":"Hexin",
    "wof:placetype":"locality"
},
  "geometry": {"coordinates":[107.232,27.6007],"type":"Point"}
}