{
  "type": "Feature",
  "properties": {
    "gn:admin1_code":"24.0",
    "gn:asciiname":"Zhangzhihuiying",
    "gn:country_code":"CN",
    "gn:dem":1335,
    "gn:feature_class":"P",
    "gn:feature_code":"PPL",
    "gn:name":"Zhangzhihuiying",
    "gn:population":0,
    "gn:timezone":"Asia/Shanghai",
    "iso:country":"CN",
    "name:zho_x_preferred":[
        "\u5f20\u6307\u6325\u8425"
    ],
    "wof:name":"Zhangzhihuiying",
    "wof:placetype":"locality"
},
  "geometry": {"coordinates":[113.41713,40.23657],"type":"Point"}
}