{
  "type": "Feature",
  "properties": {
    "gn:admin1_code":"12.0",
    "gn:asciiname":"Yingtaojing",
    "gn:country_code":"CN",
    "gn:dem":1146,
    "gn:feature_class":"P",
    "gn:feature_code":"PPL",
    "gn:name":"Yingtaojing",
    "gn:population":0,
    "gn:timezone":"Asia/Shanghai",
    "iso:country":"CN",
    "name:zho_x_preferred":[
        "\u6a31\u6843\u4e95"
    ],
    "wof:name":"Yingtaojing",
    "wof:placetype":"locality"
},
  "geometry": {"coordinates":[109.11373,30.37164000000001],"type":"Point"}
}