{
  "type": "Feature",
  "properties": {
    "gn:admin1_code":"32.0",
    "gn:asciiname":"Wangjia Wuji",
    "gn:country_code":"CN",
    "gn:dem":466,
    "gn:feature_class":"P",
    "gn:feature_code":"PPL",
    "gn:name":"Wangjia Wuji",
    "gn:population":0,
    "gn:timezone":"Asia/Shanghai",
    "iso:country":"CN",
    "name:zho_x_preferred":[
        "\u738b\u5bb6\u5c4b\u57fa"
    ],
    "wof:name":"Wangjia Wuji",
    "wof:placetype":"locality"
},
  "geometry": {"coordinates":[104.91476000000002,28.72103],"type":"Point"}
}