{
  "type": "Feature",
  "properties": {
    "gn:admin1_code":"10.0",
    "gn:asciiname":"Gongrenli",
    "gn:country_code":"CN",
    "gn:dem":6,
    "gn:feature_class":"P",
    "gn:feature_code":"PPL",
    "gn:name":"Gongrenli",
    "gn:population":0,
    "gn:timezone":"Asia/Shanghai",
    "iso:country":"CN",
    "name:zho_x_preferred":[
        "\u5de5\u4eba\u91cc"
    ],
    "wof:name":"Gongrenli",
    "wof:placetype":"locality"
},
  "geometry": {"coordinates":[119.62417000000001,39.92995],"type":"Point"}
}