{
  "type": "Feature",
  "properties": {
    "gn:admin1_code":"8.0",
    "gn:asciiname":"Jianshe Nongchang",
    "gn:country_code":"CN",
    "gn:dem":251,
    "gn:feature_class":"P",
    "gn:feature_code":"PPLF",
    "gn:name":"Jianshe Nongchang",
    "gn:population":0,
    "gn:timezone":"Asia/Shanghai",
    "iso:country":"CN",
    "name:zho_x_preferred":[
        "\u5efa\u8bbe\u519c\u573a"
    ],
    "wof:name":"Jianshe Nongchang",
    "wof:placetype":"locality"
},
  "geometry": {"coordinates":[127.0975,47.81703],"type":"Point"}
}