{
  "type": "Feature",
  "properties": {
    "gn:admin1_code":"4.0",
    "gn:asciiname":"Xinyang Wuzu",
    "gn:country_code":"CN",
    "gn:dem":1,
    "gn:feature_class":"P",
    "gn:feature_code":"PPLF",
    "gn:name":"Xinyang Wuzu",
    "gn:population":0,
    "gn:timezone":"Asia/Shanghai",
    "iso:country":"CN",
    "name:zho_x_preferred":[
        "\u65b0\u6d0b\u4e94\u7ec4"
    ],
    "wof:name":"Xinyang Wuzu",
    "wof:placetype":"locality"
},
  "geometry": {"coordinates":[120.18300000000001,33.4138],"type":"Point"}
}