{
  "type": "Feature",
  "properties": {
    "gn:admin1_code":"15",
    "gn:asciiname":"Yinbali",
    "gn:country_code":"CN",
    "gn:dem":711,
    "gn:feature_class":"P",
    "gn:feature_code":"PPL",
    "gn:name":"Yinbali",
    "gn:population":0,
    "gn:timezone":"Asia/Shanghai",
    "iso:country":"CN",
    "name:und_x_variant":[
        "\u9634\u575d\u91cc"
    ],
    "wof:name":"Yinbali",
    "wof:placetype":"locality"
},
  "geometry": {"coordinates":[105.81775,32.92107],"type":"Point"}
}