{
  "type": "Feature",
  "properties": {
    "gn:admin1_code":"11.0",
    "gn:asciiname":"Koutangwan",
    "gn:country_code":"CN",
    "gn:dem":71,
    "gn:feature_class":"P",
    "gn:feature_code":"PPL",
    "gn:name":"Koutangwan",
    "gn:population":0,
    "gn:timezone":"Asia/Shanghai",
    "iso:country":"CN",
    "name:zho_x_preferred":[
        "\u53e3\u5858\u6e7e"
    ],
    "wof:name":"Koutangwan",
    "wof:placetype":"locality"
},
  "geometry": {"coordinates":[112.73178,26.54698],"type":"Point"}
}