{
  "type": "Feature",
  "properties": {
    "gn:admin1_code":"11",
    "gn:asciiname":"Dukou",
    "gn:country_code":"CN",
    "gn:dem":291,
    "gn:feature_class":"P",
    "gn:feature_code":"PPL",
    "gn:name":"Dukou",
    "gn:population":0,
    "gn:timezone":"Asia/Shanghai",
    "iso:country":"CN",
    "wof:name":"Dukou",
    "wof:placetype":"locality"
},
  "geometry": {"coordinates":[110.13167,29.41972],"type":"Point"}
}