{
  "type": "Feature",
  "properties": {
    "gn:admin1_code":"7",
    "gn:asciiname":"Nanyang",
    "gn:country_code":"CN",
    "gn:dem":390,
    "gn:feature_class":"P",
    "gn:feature_code":"PPLA4",
    "gn:name":"Nanyang",
    "gn:population":0,
    "gn:timezone":"Asia/Shanghai",
    "iso:country":"CN",
    "name:und_x_variant":[
        "Hongfang",
        "Nanyang",
        "\u5357\u9633",
        "Hongfang Zhen",
        "\u7ea2\u574a"
    ],
    "name:zho_x_preferred":[
        "\u7ea2\u574a\u9547"
    ],
    "wof:name":"Nanyang",
    "wof:placetype":"locality"
},
  "geometry": {"coordinates":[116.95252000000001,25.02654],"type":"Point"}
}