{
  "type": "Feature",
  "properties": {
    "gn:admin1_code":"10.0",
    "gn:asciiname":"Zhanggeyu",
    "gn:country_code":"CN",
    "gn:dem":727,
    "gn:feature_class":"P",
    "gn:feature_code":"PPL",
    "gn:name":"Zhanggeyu",
    "gn:population":0,
    "gn:timezone":"Asia/Shanghai",
    "iso:country":"CN",
    "name:zho_x_preferred":[
        "\u5f20\u5404\u5cea"
    ],
    "wof:name":"Zhanggeyu",
    "wof:placetype":"locality"
},
  "geometry": {"coordinates":[115.18374,39.74772],"type":"Point"}
}