{
  "type": "Feature",
  "properties": {
    "gn:admin1_code":"3.0",
    "gn:asciiname":"Linhe",
    "gn:country_code":"CN",
    "gn:dem":53,
    "gn:feature_class":"P",
    "gn:feature_code":"PPL",
    "gn:name":"Linhe",
    "gn:population":0,
    "gn:timezone":"Asia/Shanghai",
    "iso:country":"CN",
    "name:ceb_x_preferred":[
        "Linhe"
    ],
    "name:deu_x_preferred":[
        "Linhe"
    ],
    "name:und_x_variant":[
        "\u4e34\u6cb3"
    ],
    "wof:name":"Linhe",
    "wof:placetype":"locality"
},
  "geometry": {"coordinates":[117.62430000000001,29.04474],"type":"Point"}
}