{
  "type": "Feature",
  "properties": {
    "gn:admin1_code":"3.0",
    "gn:asciiname":"Hanluoping",
    "gn:country_code":"CN",
    "gn:dem":643,
    "gn:feature_class":"P",
    "gn:feature_code":"PPL",
    "gn:name":"Hanluoping",
    "gn:population":0,
    "gn:timezone":"Asia/Shanghai",
    "iso:country":"CN",
    "name:und_x_variant":[
        "\u6c57\u7f57\u576a"
    ],
    "wof:name":"Hanluoping",
    "wof:placetype":"locality"
},
  "geometry": {"coordinates":[115.80301,27.12081],"type":"Point"}
}