{
  "type": "Feature",
  "properties": {
    "gn:admin1_code":"11.0",
    "gn:asciiname":"Shangpengjia",
    "gn:country_code":"CN",
    "gn:dem":82,
    "gn:feature_class":"P",
    "gn:feature_code":"PPL",
    "gn:name":"Shangpengjia",
    "gn:population":0,
    "gn:timezone":"Asia/Shanghai",
    "iso:country":"CN",
    "name:zho_x_preferred":[
        "\u4e0a\u5f6d\u5bb6"
    ],
    "wof:name":"Shangpengjia",
    "wof:placetype":"locality"
},
  "geometry": {"coordinates":[112.88330000000001,26.79017],"type":"Point"}
}