{
  "type": "Feature",
  "properties": {
    "gn:admin1_code":"7.0",
    "gn:asciiname":"Yiceng",
    "gn:country_code":"CN",
    "gn:dem":357,
    "gn:feature_class":"P",
    "gn:feature_code":"PPL",
    "gn:name":"Yiceng",
    "gn:population":0,
    "gn:timezone":"Asia/Shanghai",
    "iso:country":"CN",
    "name:zho_x_preferred":[
        "\u4e00\u5c42"
    ],
    "wof:name":"Yiceng",
    "wof:placetype":"locality"
},
  "geometry": {"coordinates":[120.22364,26.99454],"type":"Point"}
}