{
  "type": "Feature",
  "properties": {
    "gn:admin1_code":"14",
    "gn:asciiname":"Langbaji",
    "gn:country_code":"CN",
    "gn:dem":3947,
    "gn:feature_class":"P",
    "gn:feature_code":"PPL",
    "gn:name":"Langbaji",
    "gn:population":0,
    "gn:timezone":"Asia/Urumqi",
    "iso:country":"CN",
    "name:zho_x_preferred":[
        "\u6717\u5df4\u5409"
    ],
    "wof:name":"Langbaji",
    "wof:placetype":"locality"
},
  "geometry": {"coordinates":[88.49469999999999,29.1642],"type":"Point"}
}