{
  "type": "Feature",
  "properties": {
    "gn:admin1_code":"3.0",
    "gn:asciiname":"Yuanbu Zengjia",
    "gn:country_code":"CN",
    "gn:dem":48,
    "gn:feature_class":"P",
    "gn:feature_code":"PPL",
    "gn:name":"Yuanbu Zengjia",
    "gn:population":0,
    "gn:timezone":"Asia/Shanghai",
    "iso:country":"CN",
    "name:und_x_variant":[
        "\u6e90\u57e0\u66fe\u5bb6"
    ],
    "wof:name":"Yuanbu Zengjia",
    "wof:placetype":"locality"
},
  "geometry": {"coordinates":[115.51921000000002,29.36099],"type":"Point"}
}