{
  "type": "Feature",
  "properties": {
    "gn:admin1_code":"7.0",
    "gn:asciiname":"Tingyangzhong",
    "gn:country_code":"CN",
    "gn:dem":808,
    "gn:feature_class":"P",
    "gn:feature_code":"PPL",
    "gn:name":"Tingyangzhong",
    "gn:population":0,
    "gn:timezone":"Asia/Shanghai",
    "iso:country":"CN",
    "name:zho_x_preferred":[
        "\u5ef7\u6d0b\u4e2d"
    ],
    "wof:name":"Tingyangzhong",
    "wof:placetype":"locality"
},
  "geometry": {"coordinates":[119.41338,27.22123],"type":"Point"}
}