{
  "type": "Feature",
  "properties": {
    "gn:admin1_code":"12.0",
    "gn:asciiname":"Yezizui",
    "gn:country_code":"CN",
    "gn:dem":24,
    "gn:feature_class":"P",
    "gn:feature_code":"PPL",
    "gn:name":"Yezizui",
    "gn:population":0,
    "gn:timezone":"Asia/Shanghai",
    "iso:country":"CN",
    "name:zho_x_preferred":[
        "\u4e5f\u5b57\u5480"
    ],
    "wof:name":"Yezizui",
    "wof:placetype":"locality"
},
  "geometry": {"coordinates":[115.56197,29.96349],"type":"Point"}
}