{
  "type": "Feature",
  "properties": {
    "gn:admin1_code":"10",
    "gn:asciiname":"Xiliangzhuang",
    "gn:country_code":"CN",
    "gn:dem":55,
    "gn:feature_class":"P",
    "gn:feature_code":"PPL",
    "gn:name":"Xiliangzhuang",
    "gn:population":0,
    "gn:timezone":"Asia/Shanghai",
    "iso:country":"CN",
    "name:zho_x_preferred":[
        "\u897f\u826f\u5e84"
    ],
    "wof:name":"Xiliangzhuang",
    "wof:placetype":"locality"
},
  "geometry": {"coordinates":[114.557,37.6285],"type":"Point"}
}