{
  "type": "Feature",
  "properties": {
    "gn:admin1_code":"30.0",
    "gn:asciiname":"Xinruwu",
    "gn:country_code":"CN",
    "gn:dem":76,
    "gn:feature_class":"P",
    "gn:feature_code":"PPL",
    "gn:name":"Xinruwu",
    "gn:population":0,
    "gn:timezone":"Asia/Shanghai",
    "iso:country":"CN",
    "name:zho_x_preferred":[
        "\u65b0\u8339\u5c4b"
    ],
    "wof:name":"Xinruwu",
    "wof:placetype":"locality"
},
  "geometry": {"coordinates":[113.42261999999999,24.75034],"type":"Point"}
}