{
  "type": "Feature",
  "properties": {
    "gn:admin1_code":"11",
    "gn:asciiname":"Yelugang",
    "gn:country_code":"CN",
    "gn:dem":231,
    "gn:feature_class":"P",
    "gn:feature_code":"PPL",
    "gn:name":"Yelugang",
    "gn:population":0,
    "gn:timezone":"Asia/Shanghai",
    "iso:country":"CN",
    "name:und_x_variant":[
        "\u91ce\u9e7f\u5c97",
        "Yelugang"
    ],
    "wof:name":"Yelugang",
    "wof:placetype":"locality"
},
  "geometry": {"coordinates":[111.96722,25.64306],"type":"Point"}
}