{
  "type": "Feature",
  "properties": {
    "gn:admin1_code":"3.0",
    "gn:asciiname":"Shangzhongyuan",
    "gn:country_code":"CN",
    "gn:dem":123,
    "gn:feature_class":"P",
    "gn:feature_code":"PPL",
    "gn:name":"Shangzhongyuan",
    "gn:population":0,
    "gn:timezone":"Asia/Shanghai",
    "iso:country":"CN",
    "name:zho_x_preferred":[
        "\u4e0a\u4e2d\u6e90"
    ],
    "wof:name":"Shangzhongyuan",
    "wof:placetype":"locality"
},
  "geometry": {"coordinates":[117.13394,28.07344],"type":"Point"}
}