{
  "type": "Feature",
  "properties": {
    "gn:admin1_code":"12",
    "gn:asciiname":"Fangxian Chengguanzhen",
    "gn:country_code":"CN",
    "gn:dem":432,
    "gn:feature_class":"P",
    "gn:feature_code":"PPLA3",
    "gn:name":"Fangxian Chengguanzhen",
    "gn:population":0,
    "gn:timezone":"Asia/Shanghai",
    "iso:country":"CN",
    "name:und_x_variant":[
        "Fang-hsien",
        "Fang",
        "Fangxian",
        "Fangxian Chengguanzhen"
    ],
    "wof:name":"Fangxian Chengguanzhen",
    "wof:placetype":"locality"
},
  "geometry": {"coordinates":[110.73417000000001,32.055],"type":"Point"}
}