{
  "type": "Feature",
  "properties": {
    "gn:admin1_code":"14.0",
    "gn:asciiname":"Jutangmeng",
    "gn:country_code":"CN",
    "gn:dem":1399,
    "gn:feature_class":"P",
    "gn:feature_code":"PPL",
    "gn:name":"Jutangmeng",
    "gn:population":0,
    "gn:timezone":"Asia/Urumqi",
    "iso:country":"CN",
    "name:zho_x_preferred":[
        "\u83ca\u6c64\u8499"
    ],
    "wof:name":"Jutangmeng",
    "wof:placetype":"locality"
},
  "geometry": {"coordinates":[95.30822999999999,29.73962],"type":"Point"}
}