{
  "type": "Feature",
  "properties": {
    "gn:admin1_code":"7",
    "gn:asciiname":"Shuifenliu",
    "gn:country_code":"CN",
    "gn:dem":255,
    "gn:feature_class":"P",
    "gn:feature_code":"PPL",
    "gn:name":"Shuifenliu",
    "gn:population":0,
    "gn:timezone":"Asia/Shanghai",
    "iso:country":"CN",
    "name:zho_x_preferred":[
        "\u6c34\u5206\u6d41"
    ],
    "wof:name":"Shuifenliu",
    "wof:placetype":"locality"
},
  "geometry": {"coordinates":[117.6075,24.37028],"type":"Point"}
}