{
  "type": "Feature",
  "properties": {
    "gn:admin1_code":"3",
    "gn:asciiname":"Shangfang",
    "gn:country_code":"CN",
    "gn:dem":52,
    "gn:feature_class":"P",
    "gn:feature_code":"PPLA4",
    "gn:name":"Shangfang",
    "gn:population":0,
    "gn:timezone":"Asia/Shanghai",
    "iso:country":"CN",
    "name:und_x_variant":[
        "\u4e0a\u574a",
        "Shangfang Xiang",
        "\u4e0a\u574a\u4e61"
    ],
    "name:zho_x_preferred":[
        "\u4e0a\u65b9\u5c71\u56fd\u5bb6\u68ee\u6797\u516c\u56ed"
    ],
    "wof:name":"Shangfang",
    "wof:placetype":"locality"
},
  "geometry": {"coordinates":[117.04583,28.67833],"type":"Point"}
}