{
  "type": "Feature",
  "properties": {
    "gn:admin1_code":"09",
    "gn:asciiname":"Lianghekou",
    "gn:country_code":"CN",
    "gn:dem":604,
    "gn:feature_class":"P",
    "gn:feature_code":"PPL",
    "gn:name":"Lianghekou",
    "gn:population":0,
    "gn:timezone":"Asia/Shanghai",
    "iso:country":"CN",
    "name:und_x_variant":[
        "\u4e24\u6cb3\u53e3",
        "Lianghekou"
    ],
    "wof:name":"Lianghekou",
    "wof:placetype":"locality"
},
  "geometry": {"coordinates":[112.16015,33.8605],"type":"Point"}
}