{
  "type": "Feature",
  "properties": {
    "gn:admin1_code":"25.0",
    "gn:asciiname":"Moutuancun",
    "gn:country_code":"CN",
    "gn:dem":145,
    "gn:feature_class":"P",
    "gn:feature_code":"PPL",
    "gn:name":"Moutuancun",
    "gn:population":0,
    "gn:timezone":"Asia/Shanghai",
    "iso:country":"CN",
    "name:zho_x_preferred":[
        "\u725f\u7583\u6751"
    ],
    "wof:name":"Moutuancun",
    "wof:placetype":"locality"
},
  "geometry": {"coordinates":[120.50523,37.28124],"type":"Point"}
}