{
  "type": "Feature",
  "properties": {
    "gn:admin1_code":"32",
    "gn:asciiname":"Shawan",
    "gn:country_code":"CN",
    "gn:dem":407,
    "gn:feature_class":"P",
    "gn:feature_code":"PPLA3",
    "gn:name":"Shawan",
    "gn:population":0,
    "gn:timezone":"Asia/Shanghai",
    "iso:country":"CN",
    "name:ceb_x_preferred":[
        "Shawan"
    ],
    "name:deu_x_preferred":[
        "Shawan"
    ],
    "name:fra_x_preferred":[
        "Shawan"
    ],
    "name:nor_x_preferred":[
        "Shawan"
    ],
    "name:rus_x_preferred":[
        "\u0428\u0430\u0432\u0430\u043d\u044c"
    ],
    "name:swe_x_preferred":[
        "Shawan"
    ],
    "name:ukr_x_preferred":[
        "\u0428\u0430\u0432\u0430\u043d\u044c"
    ],
    "name:und_x_variant":[
        "Shawanzhen",
        "Sha-wan-chen"
    ],
    "name:zho_x_preferred":[
        "\u6c99\u6e7e"
    ],
    "wof:name":"Shawan",
    "wof:placetype":"locality"
},
  "geometry": {"coordinates":[103.54327000000001,29.41117],"type":"Point"}
}