{
  "type": "Feature",
  "properties": {
    "gn:admin1_code":"4.0",
    "gn:asciiname":"Wakoucun",
    "gn:country_code":"CN",
    "gn:dem":3,
    "gn:feature_class":"P",
    "gn:feature_code":"PPL",
    "gn:name":"Wakoucun",
    "gn:population":0,
    "gn:timezone":"Asia/Shanghai",
    "iso:country":"CN",
    "name:zho_x_preferred":[
        "\u74e6\u53e3\u6751"
    ],
    "wof:name":"Wakoucun",
    "wof:placetype":"locality"
},
  "geometry": {"coordinates":[119.08069,34.50348],"type":"Point"}
}