{
  "type": "Feature",
  "properties": {
    "gn:admin1_code":"8.0",
    "gn:asciiname":"Xiu'ertun",
    "gn:country_code":"CN",
    "gn:dem":236,
    "gn:feature_class":"P",
    "gn:feature_code":"PPL",
    "gn:name":"Xiu\u2019ertun",
    "gn:population":0,
    "gn:timezone":"Asia/Shanghai",
    "iso:country":"CN",
    "name:und_x_variant":[
        "Xiu\u2019ertun"
    ],
    "name:zho_x_preferred":[
        "\u79c0\u5c14\u5c6f"
    ],
    "wof:name":"Xiu'ertun",
    "wof:placetype":"locality"
},
  "geometry": {"coordinates":[124.59712,48.53317],"type":"Point"}
}