{
  "type": "Feature",
  "properties": {
    "gn:admin1_code":"18.0",
    "gn:asciiname":"Niupo",
    "gn:country_code":"CN",
    "gn:dem":1138,
    "gn:feature_class":"P",
    "gn:feature_code":"PPL",
    "gn:name":"Niupo",
    "gn:population":0,
    "gn:timezone":"Asia/Shanghai",
    "iso:country":"CN",
    "name:zho_x_preferred":[
        "\u725b\u5761"
    ],
    "wof:name":"Niupo",
    "wof:placetype":"locality"
},
  "geometry": {"coordinates":[107.61799999999999,27.0539],"type":"Point"}
}