{
  "type": "Feature",
  "properties": {
    "gn:admin1_code":"5.0",
    "gn:asciiname":"Shangluannitang",
    "gn:country_code":"CN",
    "gn:dem":901,
    "gn:feature_class":"P",
    "gn:feature_code":"PPL",
    "gn:name":"Shangluannitang",
    "gn:population":0,
    "gn:timezone":"Asia/Shanghai",
    "iso:country":"CN",
    "name:und_x_variant":[
        "\u4e0a\u4e71\u6ce5\u5858"
    ],
    "wof:name":"Shangluannitang",
    "wof:placetype":"locality"
},
  "geometry": {"coordinates":[127.23575,41.56374],"type":"Point"}
}