{
  "type": "Feature",
  "properties": {
    "gn:admin1_code":"30.0",
    "gn:asciiname":"Danmuwei",
    "gn:country_code":"CN",
    "gn:dem":-1,
    "gn:feature_class":"P",
    "gn:feature_code":"PPL",
    "gn:name":"Danmuwei",
    "gn:population":0,
    "gn:timezone":"Asia/Shanghai",
    "iso:country":"CN",
    "name:zho_x_preferred":[
        "\u6de1\u6728\u56f4"
    ],
    "wof:name":"Danmuwei",
    "wof:placetype":"locality"
},
  "geometry": {"coordinates":[113.42185000000001,22.28457],"type":"Point"}
}