{
  "type": "Feature",
  "properties": {
    "gn:admin1_code":"25.0",
    "gn:asciiname":"Andong Weidongcun",
    "gn:country_code":"CN",
    "gn:dem":8,
    "gn:feature_class":"P",
    "gn:feature_code":"PPL",
    "gn:name":"Andong Weidongcun",
    "gn:population":0,
    "gn:timezone":"Asia/Shanghai",
    "iso:country":"CN",
    "name:zho_x_preferred":[
        "\u5b89\u4e1c\u536b\u4e1c\u6751"
    ],
    "wof:name":"Andong Weidongcun",
    "wof:placetype":"locality"
},
  "geometry": {"coordinates":[119.31072,35.11334],"type":"Point"}
}