{
  "type": "Feature",
  "properties": {
    "gn:admin1_code":"25.0",
    "gn:asciiname":"Gupocun",
    "gn:country_code":"CN",
    "gn:dem":350,
    "gn:feature_class":"P",
    "gn:feature_code":"PPL",
    "gn:name":"Gupocun",
    "gn:population":0,
    "gn:timezone":"Asia/Shanghai",
    "iso:country":"CN",
    "name:zho_x_preferred":[
        "\u5d2e\u5761\u6751"
    ],
    "wof:name":"Gupocun",
    "wof:placetype":"locality"
},
  "geometry": {"coordinates":[118.02312000000001,36.11958],"type":"Point"}
}