{
  "type": "Feature",
  "properties": {
    "gn:admin1_code":"8.0",
    "gn:asciiname":"Hongdacun",
    "gn:country_code":"CN",
    "gn:dem":192,
    "gn:feature_class":"P",
    "gn:feature_code":"PPL",
    "gn:name":"Hongdacun",
    "gn:population":0,
    "gn:timezone":"Asia/Shanghai",
    "iso:country":"CN",
    "name:zho_x_preferred":[
        "\u5b8f\u5927\u6751"
    ],
    "wof:name":"Hongdacun",
    "wof:placetype":"locality"
},
  "geometry": {"coordinates":[127.20544,46.51954],"type":"Point"}
}