{
  "type": "Feature",
  "properties": {
    "gn:admin1_code":"1.0",
    "gn:asciiname":"Mingzhou",
    "gn:country_code":"CN",
    "gn:dem":240,
    "gn:feature_class":"P",
    "gn:feature_code":"PPL",
    "gn:name":"Mingzhou",
    "gn:population":0,
    "gn:timezone":"Asia/Shanghai",
    "iso:country":"CN",
    "name:zho_x_preferred":[
        "\u8317\u6d32"
    ],
    "wof:name":"Mingzhou",
    "wof:placetype":"locality"
},
  "geometry": {"coordinates":[117.80606,29.72577],"type":"Point"}
}