{
  "type": "Feature",
  "properties": {
    "gn:admin1_code":"2.0",
    "gn:asciiname":"Lubian",
    "gn:country_code":"CN",
    "gn:dem":69,
    "gn:feature_class":"P",
    "gn:feature_code":"PPL",
    "gn:name":"Lubian",
    "gn:population":0,
    "gn:timezone":"Asia/Shanghai",
    "iso:country":"CN",
    "name:fra_x_preferred":[
        "Lubian"
    ],
    "name:pol_x_preferred":[
        "Lubian"
    ],
    "name:ukr_x_preferred":[
        "\u041b\u044e\u0431\u044f\u043d"
    ],
    "name:zho_x_preferred":[
        "\u8def\u8fb9"
    ],
    "wof:name":"Lubian",
    "wof:placetype":"locality"
},
  "geometry": {"coordinates":[119.47729,29.58932],"type":"Point"}
}