{
  "type": "Feature",
  "properties": {
    "gn:admin1_code":"32.0",
    "gn:asciiname":"Yejiasi",
    "gn:country_code":"CN",
    "gn:dem":367,
    "gn:feature_class":"P",
    "gn:feature_code":"PPL",
    "gn:name":"Yejiasi",
    "gn:population":0,
    "gn:timezone":"Asia/Shanghai",
    "iso:country":"CN",
    "name:zho_x_preferred":[
        "\u53f6\u5bb6\u5bfa"
    ],
    "wof:name":"Yejiasi",
    "wof:placetype":"locality"
},
  "geometry": {"coordinates":[105.14711,29.35486],"type":"Point"}
}