{
  "type": "Feature",
  "properties": {
    "gn:admin1_code":"15.0",
    "gn:asciiname":"Wozitan",
    "gn:country_code":"CN",
    "gn:dem":1650,
    "gn:feature_class":"P",
    "gn:feature_code":"PPL",
    "gn:name":"Wozitan",
    "gn:population":0,
    "gn:timezone":"Asia/Shanghai",
    "iso:country":"CN",
    "name:zho_x_preferred":[
        "\u7a9d\u5b50\u6ee9"
    ],
    "wof:name":"Wozitan",
    "wof:placetype":"locality"
},
  "geometry": {"coordinates":[104.565,36.8907],"type":"Point"}
}