{
  "type": "Feature",
  "properties": {
    "gn:admin1_code":"4.0",
    "gn:asciiname":"Yangtanggang",
    "gn:country_code":"CN",
    "gn:dem":28,
    "gn:feature_class":"P",
    "gn:feature_code":"PPL",
    "gn:name":"Yangtanggang",
    "gn:population":0,
    "gn:timezone":"Asia/Shanghai",
    "iso:country":"CN",
    "name:zho_x_preferred":[
        "\u6768\u5858\u5c97"
    ],
    "wof:name":"Yangtanggang",
    "wof:placetype":"locality"
},
  "geometry": {"coordinates":[119.16553,31.97772],"type":"Point"}
}