{
  "type": "Feature",
  "properties": {
    "gn:admin1_code":"8.0",
    "gn:asciiname":"Xuquezigou",
    "gn:country_code":"CN",
    "gn:dem":221,
    "gn:feature_class":"P",
    "gn:feature_code":"PPL",
    "gn:name":"Xuquezigou",
    "gn:population":0,
    "gn:timezone":"Asia/Shanghai",
    "iso:country":"CN",
    "name:zho_x_preferred":[
        "\u5f90\u7638\u5b50\u6c9f"
    ],
    "wof:name":"Xuquezigou",
    "wof:placetype":"locality"
},
  "geometry": {"coordinates":[130.73259999999999,46.20485],"type":"Point"}
}