{
  "type": "Feature",
  "properties": {
    "gn:admin1_code":"02",
    "gn:asciiname":"Waipai",
    "gn:country_code":"CN",
    "gn:dem":538,
    "gn:feature_class":"P",
    "gn:feature_code":"PPL",
    "gn:name":"Waipai",
    "gn:population":0,
    "gn:timezone":"Asia/Shanghai",
    "iso:country":"CN",
    "name:zho_x_preferred":[
        "\u5916\u6392"
    ],
    "wof:name":"Waipai",
    "wof:placetype":"locality"
},
  "geometry": {"coordinates":[120.41997000000001,27.97725],"type":"Point"}
}