{
  "type": "Feature",
  "properties": {
    "gn:admin1_code":"18.0",
    "gn:asciiname":"Shanlan",
    "gn:country_code":"CN",
    "gn:dem":557,
    "gn:feature_class":"P",
    "gn:feature_code":"PPL",
    "gn:name":"Shanlan",
    "gn:population":0,
    "gn:timezone":"Asia/Shanghai",
    "iso:country":"CN",
    "name:zho_x_preferred":[
        "\u5c71\u680f"
    ],
    "wof:name":"Shanlan",
    "wof:placetype":"locality"
},
  "geometry": {"coordinates":[109.26900000000001,26.2448],"type":"Point"}
}