{
  "type": "Feature",
  "properties": {
    "gn:admin1_code":"8.0",
    "gn:asciiname":"Zhonghecun",
    "gn:country_code":"CN",
    "gn:dem":203,
    "gn:feature_class":"P",
    "gn:feature_code":"PPL",
    "gn:name":"Zhonghecun",
    "gn:population":0,
    "gn:timezone":"Asia/Shanghai",
    "iso:country":"CN",
    "name:zho_x_preferred":[
        "\u5fe0\u548c\u6751"
    ],
    "wof:name":"Zhonghecun",
    "wof:placetype":"locality"
},
  "geometry": {"coordinates":[124.64185000000001,48.57745],"type":"Point"}
}