{
  "type": "Feature",
  "properties": {
    "gn:admin1_code":"11.0",
    "gn:asciiname":"Yuhuangdian",
    "gn:country_code":"CN",
    "gn:dem":672,
    "gn:feature_class":"P",
    "gn:feature_code":"PPL",
    "gn:name":"Yuhuangdian",
    "gn:population":0,
    "gn:timezone":"Asia/Shanghai",
    "iso:country":"CN",
    "name:zho_x_preferred":[
        "\u79b9\u7687\u6bbf"
    ],
    "wof:name":"Yuhuangdian",
    "wof:placetype":"locality"
},
  "geometry": {"coordinates":[112.62931,27.11988],"type":"Point"}
}