{
  "type": "Feature",
  "properties": {
    "gn:admin1_code":"29.0",
    "gn:asciiname":"Xiayin",
    "gn:country_code":"CN",
    "gn:dem":2047,
    "gn:feature_class":"P",
    "gn:feature_code":"PPL",
    "gn:name":"Xiayin",
    "gn:population":0,
    "gn:timezone":"Asia/Shanghai",
    "iso:country":"CN",
    "name:zho_x_preferred":[
        "\u4e0b\u94f6"
    ],
    "wof:name":"Xiayin",
    "wof:placetype":"locality"
},
  "geometry": {"coordinates":[100.119,25.7428],"type":"Point"}
}