{
  "type": "Feature",
  "properties": {
    "gn:admin1_code":"26",
    "gn:asciiname":"Hanfeng",
    "gn:country_code":"CN",
    "gn:dem":978,
    "gn:feature_class":"P",
    "gn:feature_code":"PPLA4",
    "gn:name":"Hanfeng",
    "gn:population":0,
    "gn:timezone":"Asia/Shanghai",
    "iso:country":"CN",
    "name:und_x_variant":[
        "\u6c49\u5c01"
    ],
    "wof:name":"Hanfeng",
    "wof:placetype":"locality"
},
  "geometry": {"coordinates":[107.29743000000001,34.61931],"type":"Point"}
}