{
  "type": "Feature",
  "properties": {
    "gn:admin1_code":"12.0",
    "gn:asciiname":"Maotasi",
    "gn:country_code":"CN",
    "gn:dem":547,
    "gn:feature_class":"P",
    "gn:feature_code":"PPL",
    "gn:name":"Maotasi",
    "gn:population":0,
    "gn:timezone":"Asia/Shanghai",
    "iso:country":"CN",
    "name:zho_x_preferred":[
        "\u8305\u5854\u5bfa"
    ],
    "wof:name":"Maotasi",
    "wof:placetype":"locality"
},
  "geometry": {"coordinates":[110.1536,32.45397],"type":"Point"}
}