{
  "type": "Feature",
  "properties": {
    "gn:admin1_code":"26.0",
    "gn:asciiname":"Lijia Guacun",
    "gn:country_code":"CN",
    "gn:dem":1051,
    "gn:feature_class":"P",
    "gn:feature_code":"PPL",
    "gn:name":"Lijia Guacun",
    "gn:population":0,
    "gn:timezone":"Asia/Shanghai",
    "iso:country":"CN",
    "name:zho_x_preferred":[
        "\u674e\u5bb6\u576c\u6751"
    ],
    "wof:name":"Lijia Guacun",
    "wof:placetype":"locality"
},
  "geometry": {"coordinates":[109.636,37.6316],"type":"Point"}
}