{
  "type": "Feature",
  "properties": {
    "gn:admin1_code":"3.0",
    "gn:asciiname":"Tongshanxiang",
    "gn:country_code":"CN",
    "gn:dem":31,
    "gn:feature_class":"P",
    "gn:feature_code":"PPLA4",
    "gn:name":"Tongshanxiang",
    "gn:population":0,
    "gn:timezone":"Asia/Shanghai",
    "iso:country":"CN",
    "name:und_x_variant":[
        "\u6850\u5c71\u4e61"
    ],
    "wof:name":"Tongshanxiang",
    "wof:placetype":"locality"
},
  "geometry": {"coordinates":[116.79572,28.83985],"type":"Point"}
}