{
  "type": "Feature",
  "properties": {
    "gn:admin1_code":"10.0",
    "gn:asciiname":"Quanqiu",
    "gn:country_code":"CN",
    "gn:dem":40,
    "gn:feature_class":"P",
    "gn:feature_code":"PPL",
    "gn:name":"Quanqiu",
    "gn:population":0,
    "gn:timezone":"Asia/Shanghai",
    "iso:country":"CN",
    "name:zho_x_preferred":[
        "\u6cc9\u90b1"
    ],
    "wof:name":"Quanqiu",
    "wof:placetype":"locality"
},
  "geometry": {"coordinates":[115.218,38.5445],"type":"Point"}
}