{
  "type": "Feature",
  "properties": {
    "gn:admin1_code":"19.0",
    "gn:asciiname":"Yaojia Buzi",
    "gn:country_code":"CN",
    "gn:dem":395,
    "gn:feature_class":"P",
    "gn:feature_code":"PPL",
    "gn:name":"Yaojia Buzi",
    "gn:population":0,
    "gn:timezone":"Asia/Shanghai",
    "iso:country":"CN",
    "name:und_x_variant":[
        "Yaojia Puzi",
        "\u59da\u5bb6\u5821\u5b50",
        "Yaojia Buzi"
    ],
    "wof:name":"Yaojia Buzi",
    "wof:placetype":"locality"
},
  "geometry": {"coordinates":[122.80970000000001,40.30877],"type":"Point"}
}