{
  "type": "Feature",
  "properties": {
    "gn:admin1_code":"3.0",
    "gn:asciiname":"Changkengkou",
    "gn:country_code":"CN",
    "gn:dem":208,
    "gn:feature_class":"P",
    "gn:feature_code":"PPL",
    "gn:name":"Changkengkou",
    "gn:population":0,
    "gn:timezone":"Asia/Shanghai",
    "iso:country":"CN",
    "name:und_x_variant":[
        "\u957f\u5751\u53e3"
    ],
    "wof:name":"Changkengkou",
    "wof:placetype":"locality"
},
  "geometry": {"coordinates":[115.49536999999999,29.03349],"type":"Point"}
}