{
  "type": "Feature",
  "properties": {
    "gn:admin1_code":"19.0",
    "gn:asciiname":"Qianyao",
    "gn:country_code":"CN",
    "gn:dem":87,
    "gn:feature_class":"P",
    "gn:feature_code":"PPL",
    "gn:name":"Qianyao",
    "gn:population":0,
    "gn:timezone":"Asia/Shanghai",
    "iso:country":"CN",
    "name:und_x_variant":[
        "\u524d\u7a91"
    ],
    "wof:name":"Qianyao",
    "wof:placetype":"locality"
},
  "geometry": {"coordinates":[123.39946,40.27581],"type":"Point"}
}