{
  "type": "Feature",
  "properties": {
    "gn:admin1_code":"8.0",
    "gn:asciiname":"Wangjunlitun",
    "gn:country_code":"CN",
    "gn:dem":139,
    "gn:feature_class":"P",
    "gn:feature_code":"PPL",
    "gn:name":"Wangjunlitun",
    "gn:population":0,
    "gn:timezone":"Asia/Shanghai",
    "iso:country":"CN",
    "name:zho_x_preferred":[
        "\u738b\u519b\u793c\u5c6f"
    ],
    "wof:name":"Wangjunlitun",
    "wof:placetype":"locality"
},
  "geometry": {"coordinates":[126.34081,46.13924],"type":"Point"}
}