{
  "type": "Feature",
  "properties": {
    "gn:admin1_code":"18.0",
    "gn:asciiname":"Huangheling",
    "gn:country_code":"CN",
    "gn:dem":1160,
    "gn:feature_class":"P",
    "gn:feature_code":"PPL",
    "gn:name":"Huangheling",
    "gn:population":0,
    "gn:timezone":"Asia/Shanghai",
    "iso:country":"CN",
    "name:zho_x_preferred":[
        "\u9ec4\u6cb3\u5cad"
    ],
    "wof:name":"Huangheling",
    "wof:placetype":"locality"
},
  "geometry": {"coordinates":[108.78400000000001,28.0525],"type":"Point"}
}