{
  "type": "Feature",
  "properties": {
    "gn:admin1_code":"25",
    "gn:asciiname":"Wutongcun",
    "gn:country_code":"CN",
    "gn:dem":45,
    "gn:feature_class":"P",
    "gn:feature_code":"PPL",
    "gn:name":"Wutongcun",
    "gn:population":0,
    "gn:timezone":"Asia/Shanghai",
    "iso:country":"CN",
    "name:zho_x_preferred":[
        "\u68a7\u6850\u6751"
    ],
    "wof:name":"Wutongcun",
    "wof:placetype":"locality"
},
  "geometry": {"coordinates":[117.961,34.8496],"type":"Point"}
}