{
  "type": "Feature",
  "properties": {
    "gn:admin1_code":"4.0",
    "gn:asciiname":"Jiamiaoqiao",
    "gn:country_code":"CN",
    "gn:dem":3,
    "gn:feature_class":"P",
    "gn:feature_code":"PPL",
    "gn:name":"Jiamiaoqiao",
    "gn:population":0,
    "gn:timezone":"Asia/Shanghai",
    "iso:country":"CN",
    "name:und_x_variant":[
        "\u5bb6\u5e99\u6865"
    ],
    "wof:name":"Jiamiaoqiao",
    "wof:placetype":"locality"
},
  "geometry": {"coordinates":[120.99726,32.46106],"type":"Point"}
}