{
  "type": "Feature",
  "properties": {
    "gn:admin1_code":"15.0",
    "gn:asciiname":"Kuanzhanwan",
    "gn:country_code":"CN",
    "gn:dem":1350,
    "gn:feature_class":"P",
    "gn:feature_code":"PPL",
    "gn:name":"Kuanzhanwan",
    "gn:population":0,
    "gn:timezone":"Asia/Shanghai",
    "iso:country":"CN",
    "name:zho_x_preferred":[
        "\u5bbd\u5c55\u6e7e"
    ],
    "wof:name":"Kuanzhanwan",
    "wof:placetype":"locality"
},
  "geometry": {"coordinates":[107.313,35.8441],"type":"Point"}
}