{
  "type": "Feature",
  "properties": {
    "gn:admin1_code":"10",
    "gn:asciiname":"Xi'erdaowa",
    "gn:country_code":"CN",
    "gn:dem":1080,
    "gn:feature_class":"P",
    "gn:feature_code":"PPL",
    "gn:name":"Xi\u2019erdaowa",
    "gn:population":0,
    "gn:timezone":"Asia/Shanghai",
    "iso:country":"CN",
    "name:und_x_variant":[
        "Xi\u2019erdaowa"
    ],
    "name:zho_x_preferred":[
        "\u897f\u4e8c\u9053\u6d3c"
    ],
    "wof:name":"Xi'erdaowa",
    "wof:placetype":"locality"
},
  "geometry": {"coordinates":[115.55605,40.69721],"type":"Point"}
}