{
  "type": "Feature",
  "properties": {
    "gn:admin1_code":"5.0",
    "gn:asciiname":"Shoukaidong",
    "gn:country_code":"CN",
    "gn:dem":128,
    "gn:feature_class":"P",
    "gn:feature_code":"PPL",
    "gn:name":"Shoukaidong",
    "gn:population":0,
    "gn:timezone":"Asia/Shanghai",
    "iso:country":"CN",
    "name:und_x_variant":[
        "Shou-k\u2019ai-tung"
    ],
    "wof:name":"Shoukaidong",
    "wof:placetype":"locality"
},
  "geometry": {"coordinates":[130.28655000000001,42.7302],"type":"Point"}
}