{
  "type": "Feature",
  "properties": {
    "gn:admin1_code":"10.0",
    "gn:asciiname":"Xiliuquan",
    "gn:country_code":"CN",
    "gn:dem":91,
    "gn:feature_class":"P",
    "gn:feature_code":"PPL",
    "gn:name":"Xiliuquan",
    "gn:population":0,
    "gn:timezone":"Asia/Shanghai",
    "iso:country":"CN",
    "name:zho_x_preferred":[
        "\u897f\u67f3\u6cc9"
    ],
    "wof:name":"Xiliuquan",
    "wof:placetype":"locality"
},
  "geometry": {"coordinates":[115.33978999999999,39.21127],"type":"Point"}
}