{
  "type": "Feature",
  "properties": {
    "gn:admin1_code":"02",
    "gn:asciiname":"Tengshan",
    "gn:country_code":"CN",
    "gn:dem":12,
    "gn:feature_class":"P",
    "gn:feature_code":"PPL",
    "gn:name":"Tengshan",
    "gn:population":0,
    "gn:timezone":"Asia/Shanghai",
    "iso:country":"CN",
    "name:und_x_variant":[
        "\u6ed5\u5c71",
        "T\u2019eng-shan"
    ],
    "wof:name":"Tengshan",
    "wof:placetype":"locality"
},
  "geometry": {"coordinates":[121.57178999999999,30.03728],"type":"Point"}
}