{
  "type": "Feature",
  "properties": {
    "gn:admin1_code":"7.0",
    "gn:asciiname":"Nandu",
    "gn:country_code":"CN",
    "gn:dem":206,
    "gn:feature_class":"P",
    "gn:feature_code":"PPL",
    "gn:name":"Nandu",
    "gn:population":0,
    "gn:timezone":"Asia/Shanghai",
    "iso:country":"CN",
    "name:ceb_x_preferred":[
        "Nandu"
    ],
    "name:nld_x_preferred":[
        "Nandu"
    ],
    "name:por_x_preferred":[
        "Nandu"
    ],
    "name:zho_x_preferred":[
        "\u5357\u6e21"
    ],
    "wof:name":"Nandu",
    "wof:placetype":"locality"
},
  "geometry": {"coordinates":[117.88781000000002,27.03215],"type":"Point"}
}