{
  "type": "Feature",
  "properties": {
    "gn:admin1_code":"2.0",
    "gn:asciiname":"Suoqian",
    "gn:country_code":"CN",
    "gn:dem":10,
    "gn:feature_class":"P",
    "gn:feature_code":"PPLA4",
    "gn:name":"Suoqian",
    "gn:population":0,
    "gn:timezone":"Asia/Shanghai",
    "iso:country":"CN",
    "name:und_x_variant":[
        "\u6240\u524d",
        "Suoqian Zhen",
        "\u6240\u524d\u9547"
    ],
    "wof:name":"Suoqian",
    "wof:placetype":"locality"
},
  "geometry": {"coordinates":[120.27692,30.11356],"type":"Point"}
}