{
  "type": "Feature",
  "properties": {
    "gn:admin1_code":"10",
    "gn:asciiname":"Pijianggou",
    "gn:country_code":"CN",
    "gn:dem":383,
    "gn:feature_class":"P",
    "gn:feature_code":"PPL",
    "gn:name":"Pijianggou",
    "gn:population":0,
    "gn:timezone":"Asia/Shanghai",
    "iso:country":"CN",
    "name:zho_x_preferred":[
        "\u76ae\u5320\u6c9f"
    ],
    "wof:name":"Pijianggou",
    "wof:placetype":"locality"
},
  "geometry": {"coordinates":[118.21764,40.90124],"type":"Point"}
}