{
  "type": "Feature",
  "properties": {
    "gn:admin1_code":"11.0",
    "gn:asciiname":"Shijie",
    "gn:country_code":"CN",
    "gn:dem":262,
    "gn:feature_class":"P",
    "gn:feature_code":"PPL",
    "gn:name":"Shijie",
    "gn:population":0,
    "gn:timezone":"Asia/Shanghai",
    "iso:country":"CN",
    "name:deu_x_preferred":[
        "Shijie"
    ],
    "name:zho_x_preferred":[
        "\u77f3\u8857"
    ],
    "wof:name":"Shijie",
    "wof:placetype":"locality"
},
  "geometry": {"coordinates":[112.61199000000001,25.66791],"type":"Point"}
}