{
  "type": "Feature",
  "properties": {
    "gn:admin1_code":"11.0",
    "gn:asciiname":"Chayuanpo",
    "gn:country_code":"CN",
    "gn:dem":69,
    "gn:feature_class":"P",
    "gn:feature_code":"PPL",
    "gn:name":"Chayuanpo",
    "gn:population":0,
    "gn:timezone":"Asia/Shanghai",
    "iso:country":"CN",
    "name:zho_x_preferred":[
        "\u8336\u56ed\u5761"
    ],
    "wof:name":"Chayuanpo",
    "wof:placetype":"locality"
},
  "geometry": {"coordinates":[113.2127,28.21245],"type":"Point"}
}