{
  "type": "Feature",
  "properties": {
    "gn:admin1_code":"32.0",
    "gn:asciiname":"Ziliewo",
    "gn:country_code":"CN",
    "gn:dem":1500,
    "gn:feature_class":"P",
    "gn:feature_code":"PPL",
    "gn:name":"Ziliewo",
    "gn:population":0,
    "gn:timezone":"Asia/Shanghai",
    "iso:country":"CN",
    "name:zho_x_preferred":[
        "\u5b50\u5217\u6c83"
    ],
    "wof:name":"Ziliewo",
    "wof:placetype":"locality"
},
  "geometry": {"coordinates":[103.003,28.1302],"type":"Point"}
}