{
  "type": "Feature",
  "properties": {
    "gn:admin1_code":"18.0",
    "gn:asciiname":"Xinmachang",
    "gn:country_code":"CN",
    "gn:dem":1257,
    "gn:feature_class":"P",
    "gn:feature_code":"PPL",
    "gn:name":"Xinmachang",
    "gn:population":0,
    "gn:timezone":"Asia/Shanghai",
    "iso:country":"CN",
    "wof:name":"Xinmachang",
    "wof:placetype":"locality"
},
  "geometry": {"coordinates":[105.47499999999999,25.66667],"type":"Point"}
}