{
  "type": "Feature",
  "properties": {
    "gn:admin1_code":"04",
    "gn:asciiname":"Shangzui",
    "gn:cc2":"CN",
    "gn:country_code":"CN",
    "gn:dem":10,
    "gn:feature_class":"P",
    "gn:feature_code":"PPL",
    "gn:name":"Shangzui",
    "gn:population":0,
    "gn:timezone":"Asia/Shanghai",
    "iso:country":"CN",
    "name:und_x_variant":[
        "Shang-tsui",
        "Shangzui"
    ],
    "wof:name":"Shangzui",
    "wof:placetype":"locality"
},
  "geometry": {"coordinates":[118.66667,33.35],"type":"Point"}
}