{
  "type": "Feature",
  "properties": {
    "gn:admin1_code":"16",
    "gn:asciiname":"Beiliu Xincun",
    "gn:country_code":"CN",
    "gn:dem":240,
    "gn:feature_class":"P",
    "gn:feature_code":"PPL",
    "gn:name":"Beiliu Xincun",
    "gn:population":0,
    "gn:timezone":"Asia/Shanghai",
    "iso:country":"CN",
    "name:zho_x_preferred":[
        "\u5317\u6d41\u65b0\u6751"
    ],
    "wof:name":"Beiliu Xincun",
    "wof:placetype":"locality"
},
  "geometry": {"coordinates":[111.295,25.6658],"type":"Point"}
}