{
  "type": "Feature",
  "properties": {
    "gn:admin1_code":"4.0",
    "gn:asciiname":"Panlaozhuang",
    "gn:country_code":"CN",
    "gn:dem":6,
    "gn:feature_class":"P",
    "gn:feature_code":"PPL",
    "gn:name":"Panlaozhuang",
    "gn:population":0,
    "gn:timezone":"Asia/Shanghai",
    "iso:country":"CN",
    "name:zho_x_preferred":[
        "Panlaozhuang"
    ],
    "name:zho_x_variant":[
        "\u6f58\u8001\u5e84"
    ],
    "wof:name":"Panlaozhuang",
    "wof:placetype":"locality"
},
  "geometry": {"coordinates":[119.32211,33.94173],"type":"Point"}
}