{
  "type": "Feature",
  "properties": {
    "gn:admin1_code":"26.0",
    "gn:asciiname":"Qianyaomaoze",
    "gn:country_code":"CN",
    "gn:dem":1508,
    "gn:feature_class":"P",
    "gn:feature_code":"PPL",
    "gn:name":"Qianyaomaoze",
    "gn:population":0,
    "gn:timezone":"Asia/Shanghai",
    "iso:country":"CN",
    "name:zho_x_preferred":[
        "\u524d\u59da\u5cc1\u5219"
    ],
    "wof:name":"Qianyaomaoze",
    "wof:placetype":"locality"
},
  "geometry": {"coordinates":[108.29021000000002,37.2719],"type":"Point"}
}