{
  "type": "Feature",
  "properties": {
    "gn:admin1_code":"11.0",
    "gn:asciiname":"Shapingba",
    "gn:country_code":"CN",
    "gn:dem":656,
    "gn:feature_class":"P",
    "gn:feature_code":"PPL",
    "gn:name":"Shapingba",
    "gn:population":0,
    "gn:timezone":"Asia/Shanghai",
    "iso:country":"CN",
    "name:zho_x_preferred":[
        "\u6c99\u576a\u575d"
    ],
    "wof:name":"Shapingba",
    "wof:placetype":"locality"
},
  "geometry": {"coordinates":[109.40028999999998,29.16792],"type":"Point"}
}