{
  "type": "Feature",
  "properties": {
    "gn:admin1_code":"26.0",
    "gn:asciiname":"Kangjia Gelaocun",
    "gn:country_code":"CN",
    "gn:dem":1066,
    "gn:feature_class":"P",
    "gn:feature_code":"PPL",
    "gn:name":"Kangjia Gelaocun",
    "gn:population":0,
    "gn:timezone":"Asia/Shanghai",
    "iso:country":"CN",
    "name:zho_x_preferred":[
        "\u5eb7\u5bb6\u572a\u5d02\u6751"
    ],
    "wof:name":"Kangjia Gelaocun",
    "wof:placetype":"locality"
},
  "geometry": {"coordinates":[110.43300000000001,37.6054],"type":"Point"}
}