{
  "type": "Feature",
  "properties": {
    "gn:admin1_code":"13",
    "gn:asciiname":"Shangbaqiangzi",
    "gn:country_code":"CN",
    "gn:dem":2204,
    "gn:feature_class":"P",
    "gn:feature_code":"PPL",
    "gn:name":"Shangbaqiangzi",
    "gn:population":0,
    "gn:timezone":"Asia/Urumqi",
    "iso:country":"CN",
    "name:und_x_variant":[
        "\u4e0a\u516b\u5899\u5b50"
    ],
    "wof:name":"Shangbaqiangzi",
    "wof:placetype":"locality"
},
  "geometry": {"coordinates":[93.18894,43.88569],"type":"Point"}
}