{
  "type": "Feature",
  "properties": {
    "gn:admin1_code":"29",
    "gn:asciiname":"Taipingtian",
    "gn:country_code":"CN",
    "gn:dem":1672,
    "gn:feature_class":"P",
    "gn:feature_code":"PPL",
    "gn:name":"Taipingtian",
    "gn:population":0,
    "gn:timezone":"Asia/Shanghai",
    "iso:country":"CN",
    "name:zho_x_preferred":[
        "\u592a\u5e73\u7530"
    ],
    "wof:name":"Taipingtian",
    "wof:placetype":"locality"
},
  "geometry": {"coordinates":[103.24299999999999,24.7006],"type":"Point"}
}