{
  "type": "Feature",
  "properties": {
    "gn:admin1_code":"15",
    "gn:asciiname":"Lichuan",
    "gn:cc2":"CN",
    "gn:country_code":"CN",
    "gn:dem":2231,
    "gn:feature_class":"P",
    "gn:feature_code":"PPL",
    "gn:name":"Lichuan",
    "gn:population":0,
    "gn:timezone":"Asia/Shanghai",
    "iso:country":"CN",
    "name:und_x_variant":[
        "Li-ch\u2019uan-chen",
        "Lichuan"
    ],
    "wof:name":"Lichuan",
    "wof:placetype":"locality"
},
  "geometry": {"coordinates":[104.3175,34.24889],"type":"Point"}
}