{
  "type": "Feature",
  "properties": {
    "gn:admin1_code":"18.0",
    "gn:asciiname":"Wenggong",
    "gn:country_code":"CN",
    "gn:dem":950,
    "gn:feature_class":"P",
    "gn:feature_code":"PPL",
    "gn:name":"Wenggong",
    "gn:population":0,
    "gn:timezone":"Asia/Shanghai",
    "iso:country":"CN",
    "wof:name":"Wenggong",
    "wof:placetype":"locality"
},
  "geometry": {"coordinates":[106.54361000000002,27.30611],"type":"Point"}
}