{
  "type": "Feature",
  "properties": {
    "gn:admin1_code":"26.0",
    "gn:asciiname":"Jieshangcun",
    "gn:country_code":"CN",
    "gn:dem":434,
    "gn:feature_class":"P",
    "gn:feature_code":"PPL",
    "gn:name":"Jieshangcun",
    "gn:population":0,
    "gn:timezone":"Asia/Shanghai",
    "iso:country":"CN",
    "name:zho_x_preferred":[
        "\u754c\u4e0a\u6751"
    ],
    "wof:name":"Jieshangcun",
    "wof:placetype":"locality"
},
  "geometry": {"coordinates":[108.30474,34.11962],"type":"Point"}
}