{
  "type": "Feature",
  "properties": {
    "gn:admin1_code":"30.0",
    "gn:asciiname":"Jingjiaoxia",
    "gn:country_code":"CN",
    "gn:dem":49,
    "gn:feature_class":"P",
    "gn:feature_code":"PPL",
    "gn:name":"Jingjiaoxia",
    "gn:population":0,
    "gn:timezone":"Asia/Shanghai",
    "iso:country":"CN",
    "name:zho_x_preferred":[
        "\u8ff3\u811a\u4e0b"
    ],
    "wof:name":"Jingjiaoxia",
    "wof:placetype":"locality"
},
  "geometry": {"coordinates":[113.22528,24.22694],"type":"Point"}
}