{
  "type": "Feature",
  "properties": {
    "gn:admin1_code":"14.0",
    "gn:asciiname":"Langdui",
    "gn:country_code":"CN",
    "gn:dem":2333,
    "gn:feature_class":"P",
    "gn:feature_code":"PPL",
    "gn:name":"Langdui",
    "gn:population":0,
    "gn:timezone":"Asia/Urumqi",
    "iso:country":"CN",
    "name:zho_x_preferred":[
        "\u90ce\u5806"
    ],
    "wof:name":"Langdui",
    "wof:placetype":"locality"
},
  "geometry": {"coordinates":[97.47201,28.68481],"type":"Point"}
}