{
  "type": "Feature",
  "properties": {
    "gn:admin1_code":"30.0",
    "gn:asciiname":"Miaochong",
    "gn:country_code":"CN",
    "gn:dem":214,
    "gn:feature_class":"P",
    "gn:feature_code":"PPL",
    "gn:name":"Miaochong",
    "gn:population":0,
    "gn:timezone":"Asia/Shanghai",
    "iso:country":"CN",
    "name:zho_x_preferred":[
        "\u5e99\u51b2"
    ],
    "wof:name":"Miaochong",
    "wof:placetype":"locality"
},
  "geometry": {"coordinates":[111.87578999999999,22.84691],"type":"Point"}
}