{
  "type": "Feature",
  "properties": {
    "gn:admin1_code":"21.0",
    "gn:asciiname":"Shipozi",
    "gn:country_code":"CN",
    "gn:dem":1489,
    "gn:feature_class":"P",
    "gn:feature_code":"PPL",
    "gn:name":"Shipozi",
    "gn:population":0,
    "gn:timezone":"Asia/Shanghai",
    "iso:country":"CN",
    "name:zho_x_preferred":[
        "\u77f3\u5761\u5b50"
    ],
    "wof:name":"Shipozi",
    "wof:placetype":"locality"
},
  "geometry": {"coordinates":[105.91500000000001,37.254],"type":"Point"}
}