{
  "type": "Feature",
  "properties": {
    "gn:admin1_code":"14.0",
    "gn:asciiname":"Quzhong",
    "gn:country_code":"CN",
    "gn:dem":4339,
    "gn:feature_class":"P",
    "gn:feature_code":"PPL",
    "gn:name":"Quzhong",
    "gn:population":0,
    "gn:timezone":"Asia/Urumqi",
    "iso:country":"CN",
    "name:zho_x_preferred":[
        "\u53d6\u91cd"
    ],
    "wof:name":"Quzhong",
    "wof:placetype":"locality"
},
  "geometry": {"coordinates":[93.62893,31.89897],"type":"Point"}
}