{
  "type": "Feature",
  "properties": {
    "gn:admin1_code":"19.0",
    "gn:asciiname":"Houfangshencun",
    "gn:country_code":"CN",
    "gn:dem":199,
    "gn:feature_class":"P",
    "gn:feature_code":"PPL",
    "gn:name":"Houfangshencun",
    "gn:population":0,
    "gn:timezone":"Asia/Shanghai",
    "iso:country":"CN",
    "name:zho_x_preferred":[
        "\u540e\u623f\u8eab\u6751"
    ],
    "wof:name":"Houfangshencun",
    "wof:placetype":"locality"
},
  "geometry": {"coordinates":[122.124,42.6215],"type":"Point"}
}