{
  "type": "Feature",
  "properties": {
    "gn:admin1_code":"4.0",
    "gn:asciiname":"Nongxucun",
    "gn:country_code":"CN",
    "gn:dem":3,
    "gn:feature_class":"P",
    "gn:feature_code":"PPL",
    "gn:name":"Nongxucun",
    "gn:population":0,
    "gn:timezone":"Asia/Shanghai",
    "iso:country":"CN",
    "name:zho_x_preferred":[
        "\u519c\u65ed\u6751"
    ],
    "wof:name":"Nongxucun",
    "wof:placetype":"locality"
},
  "geometry": {"coordinates":[119.43451,34.33991],"type":"Point"}
}