{
  "type": "Feature",
  "properties": {
    "gn:admin1_code":"5.0",
    "gn:asciiname":"Wangzheng Wobu",
    "gn:country_code":"CN",
    "gn:dem":171,
    "gn:feature_class":"P",
    "gn:feature_code":"PPL",
    "gn:name":"Wangzheng Wobu",
    "gn:population":0,
    "gn:timezone":"Asia/Shanghai",
    "iso:country":"CN",
    "name:zho_x_preferred":[
        "\u738b\u653f\u7a9d\u5821"
    ],
    "wof:name":"Wangzheng Wobu",
    "wof:placetype":"locality"
},
  "geometry": {"coordinates":[125.48152,45.1041],"type":"Point"}
}