{
  "type": "Feature",
  "properties": {
    "gn:admin1_code":"7.0",
    "gn:asciiname":"Hengyuanwei",
    "gn:country_code":"CN",
    "gn:dem":290,
    "gn:feature_class":"P",
    "gn:feature_code":"PPL",
    "gn:name":"Hengyuanwei",
    "gn:population":0,
    "gn:timezone":"Asia/Shanghai",
    "iso:country":"CN",
    "name:zho_x_preferred":[
        "\u6a2a\u6e90\u5c3e"
    ],
    "wof:name":"Hengyuanwei",
    "wof:placetype":"locality"
},
  "geometry": {"coordinates":[118.47251,27.97067],"type":"Point"}
}