{
  "type": "Feature",
  "properties": {
    "gn:admin1_code":"2.0",
    "gn:asciiname":"Jinxi",
    "gn:country_code":"CN",
    "gn:dem":129,
    "gn:feature_class":"P",
    "gn:feature_code":"PPL",
    "gn:name":"Jinxi",
    "gn:population":0,
    "gn:timezone":"Asia/Shanghai",
    "iso:country":"CN",
    "name:ceb_x_preferred":[
        "Jinxi"
    ],
    "name:deu_x_preferred":[
        "Jinxi"
    ],
    "name:zho_x_preferred":[
        "\u9526\u6eaa"
    ],
    "wof:name":"Jinxi",
    "wof:placetype":"locality"
},
  "geometry": {"coordinates":[120.43908999999999,29.37126],"type":"Point"}
}