{
  "type": "Feature",
  "properties": {
    "gn:admin1_code":"11.0",
    "gn:asciiname":"Dalong'ao",
    "gn:country_code":"CN",
    "gn:dem":267,
    "gn:feature_class":"P",
    "gn:feature_code":"PPL",
    "gn:name":"Dalong\u2019ao",
    "gn:population":0,
    "gn:timezone":"Asia/Shanghai",
    "iso:country":"CN",
    "name:und_x_variant":[
        "Dalong\u2019ao"
    ],
    "name:zho_x_preferred":[
        "\u5927\u5784\u5773"
    ],
    "wof:name":"Dalong'ao",
    "wof:placetype":"locality"
},
  "geometry": {"coordinates":[109.55875,27.65808],"type":"Point"}
}