{
  "type": "Feature",
  "properties": {
    "gn:admin1_code":"16.0",
    "gn:asciiname":"Zhongtuan",
    "gn:country_code":"CN",
    "gn:dem":80,
    "gn:feature_class":"P",
    "gn:feature_code":"PPL",
    "gn:name":"Zhongtuan",
    "gn:population":0,
    "gn:timezone":"Asia/Shanghai",
    "iso:country":"CN",
    "name:zho_x_preferred":[
        "\u4e2d\u56e2"
    ],
    "wof:name":"Zhongtuan",
    "wof:placetype":"locality"
},
  "geometry": {"coordinates":[109.48999999999999,23.8922],"type":"Point"}
}