{
  "type": "Feature",
  "properties": {
    "gn:admin1_code":"19.0",
    "gn:asciiname":"Liudaguangou",
    "gn:country_code":"CN",
    "gn:dem":184,
    "gn:feature_class":"P",
    "gn:feature_code":"PPL",
    "gn:name":"Liudaguangou",
    "gn:population":0,
    "gn:timezone":"Asia/Shanghai",
    "iso:country":"CN",
    "name:und_x_variant":[
        "\u5218\u5927\u5b98\u6c9f"
    ],
    "wof:name":"Liudaguangou",
    "wof:placetype":"locality"
},
  "geometry": {"coordinates":[123.0459,40.73503],"type":"Point"}
}