{
  "type": "Feature",
  "properties": {
    "gn:admin1_code":"23.0",
    "gn:asciiname":"Wanli",
    "gn:country_code":"CN",
    "gn:dem":4,
    "gn:feature_class":"P",
    "gn:feature_code":"PPL",
    "gn:name":"Wanli",
    "gn:population":0,
    "gn:timezone":"Asia/Shanghai",
    "iso:country":"CN",
    "name:zho_x_preferred":[
        "Wanli"
    ],
    "name:zho_x_variant":[
        "\u4e07\u91cc"
    ],
    "wof:name":"Wanli",
    "wof:placetype":"locality"
},
  "geometry": {"coordinates":[121.52898,31.08516],"type":"Point"}
}