{
  "type": "Feature",
  "properties": {
    "gn:admin1_code":"32",
    "gn:asciiname":"Shuanghe",
    "gn:country_code":"CN",
    "gn:dem":1285,
    "gn:feature_class":"P",
    "gn:feature_code":"PPL",
    "gn:name":"Shuanghe",
    "gn:population":0,
    "gn:timezone":"Asia/Shanghai",
    "iso:country":"CN",
    "name:zho_x_preferred":[
        "\u53cc\u6cb3"
    ],
    "wof:name":"Shuanghe",
    "wof:placetype":"locality"
},
  "geometry": {"coordinates":[104.25403,33.1733],"type":"Point"}
}