{
  "type": "Feature",
  "properties": {
    "gn:admin1_code":"10",
    "gn:asciiname":"Qibozi",
    "gn:country_code":"CN",
    "gn:dem":368,
    "gn:feature_class":"P",
    "gn:feature_code":"PPL",
    "gn:name":"Qibozi",
    "gn:population":0,
    "gn:timezone":"Asia/Shanghai",
    "iso:country":"CN",
    "name:zho_x_preferred":[
        "\u4e03\u62e8\u5b50"
    ],
    "wof:name":"Qibozi",
    "wof:placetype":"locality"
},
  "geometry": {"coordinates":[118.73107,40.28983],"type":"Point"}
}