{
  "type": "Feature",
  "properties": {
    "gn:admin1_code":"11.0",
    "gn:asciiname":"Youcaotang",
    "gn:country_code":"CN",
    "gn:dem":96,
    "gn:feature_class":"P",
    "gn:feature_code":"PPL",
    "gn:name":"Youcaotang",
    "gn:population":0,
    "gn:timezone":"Asia/Shanghai",
    "iso:country":"CN",
    "name:und_x_variant":[
        "Youchachang"
    ],
    "name:zho_x_preferred":[
        "\u6cb9\u8349\u5858"
    ],
    "wof:name":"Youcaotang",
    "wof:placetype":"locality"
},
  "geometry": {"coordinates":[112.38928,27.12777],"type":"Point"}
}