{
  "type": "Feature",
  "properties": {
    "gn:admin1_code":"5.0",
    "gn:asciiname":"Xiaohongqi Hexi",
    "gn:country_code":"CN",
    "gn:dem":100,
    "gn:feature_class":"P",
    "gn:feature_code":"PPL",
    "gn:name":"Xiaohongqi Hexi",
    "gn:population":0,
    "gn:timezone":"Asia/Shanghai",
    "iso:country":"CN",
    "name:und_x_variant":[
        "\u5c0f\u7ea2\u65d7\u6cb3\u897f"
    ],
    "wof:name":"Xiaohongqi Hexi",
    "wof:placetype":"locality"
},
  "geometry": {"coordinates":[130.61234999999999,42.94131],"type":"Point"}
}