{
  "type": "Feature",
  "properties": {
    "gn:admin1_code":"2.0",
    "gn:asciiname":"Shangshenqiao",
    "gn:country_code":"CN",
    "gn:dem":5,
    "gn:feature_class":"P",
    "gn:feature_code":"PPL",
    "gn:name":"Shangshenqiao",
    "gn:population":0,
    "gn:timezone":"Asia/Shanghai",
    "iso:country":"CN",
    "name:und_x_variant":[
        "\u4e0a\u8398\u6865"
    ],
    "wof:name":"Shangshenqiao",
    "wof:placetype":"locality"
},
  "geometry": {"coordinates":[119.94268999999998,31.0141],"type":"Point"}
}