{
  "type": "Feature",
  "properties": {
    "gn:admin1_code":"16.0",
    "gn:asciiname":"Shangzouma",
    "gn:country_code":"CN",
    "gn:dem":121,
    "gn:feature_class":"P",
    "gn:feature_code":"PPL",
    "gn:name":"Shangzouma",
    "gn:population":0,
    "gn:timezone":"Asia/Shanghai",
    "iso:country":"CN",
    "name:zho_x_preferred":[
        "\u4e0a\u8d70\u9a6c"
    ],
    "wof:name":"Shangzouma",
    "wof:placetype":"locality"
},
  "geometry": {"coordinates":[109.43600000000001,24.4916],"type":"Point"}
}