{
  "type": "Feature",
  "properties": {
    "gn:admin1_code":"29.0",
    "gn:asciiname":"Caobazhai",
    "gn:country_code":"CN",
    "gn:dem":1710,
    "gn:feature_class":"P",
    "gn:feature_code":"PPL",
    "gn:name":"Caobazhai",
    "gn:population":0,
    "gn:timezone":"Asia/Shanghai",
    "iso:country":"CN",
    "name:zho_x_preferred":[
        "\u8349\u575d\u5be8"
    ],
    "wof:name":"Caobazhai",
    "wof:placetype":"locality"
},
  "geometry": {"coordinates":[99.1418,23.9107],"type":"Point"}
}