{
  "type": "Feature",
  "properties": {
    "gn:admin1_code":"7.0",
    "gn:asciiname":"Jiuyang",
    "gn:country_code":"CN",
    "gn:dem":746,
    "gn:feature_class":"P",
    "gn:feature_code":"PPL",
    "gn:name":"Jiuyang",
    "gn:population":0,
    "gn:timezone":"Asia/Shanghai",
    "iso:country":"CN",
    "name:zho_x_preferred":[
        "Jiuyang"
    ],
    "name:zho_x_variant":[
        "\u9152\u6d0b"
    ],
    "wof:name":"Jiuyang",
    "wof:placetype":"locality"
},
  "geometry": {"coordinates":[119.11861,26.73222],"type":"Point"}
}