{
  "type": "Feature",
  "properties": {
    "gn:admin1_code":"2.0",
    "gn:asciiname":"Wenqiao",
    "gn:country_code":"CN",
    "gn:dem":11,
    "gn:feature_class":"P",
    "gn:feature_code":"PPL",
    "gn:name":"Wenqiao",
    "gn:population":0,
    "gn:timezone":"Asia/Shanghai",
    "iso:country":"CN",
    "name:und_x_variant":[
        "Wenqiao Zhen"
    ],
    "name:zho_x_preferred":[
        "\u6e29\u5ce4"
    ],
    "name:zho_x_variant":[
        "\u6e29\u5ce4\u9547"
    ],
    "wof:name":"Wenqiao",
    "wof:placetype":"locality"
},
  "geometry": {"coordinates":[121.30255,28.38571],"type":"Point"}
}