{
  "type": "Feature",
  "properties": {
    "gn:admin1_code":"16.0",
    "gn:asciiname":"Shifenling",
    "gn:country_code":"CN",
    "gn:dem":33,
    "gn:feature_class":"P",
    "gn:feature_code":"PPL",
    "gn:name":"Shifenling",
    "gn:population":0,
    "gn:timezone":"Asia/Shanghai",
    "iso:country":"CN",
    "name:zho_x_preferred":[
        "\u5341\u4efd\u5cad"
    ],
    "wof:name":"Shifenling",
    "wof:placetype":"locality"
},
  "geometry": {"coordinates":[110.378,23.5191],"type":"Point"}
}