{
  "type": "Feature",
  "properties": {
    "gn:admin1_code":"32.0",
    "gn:asciiname":"Zhanglu",
    "gn:country_code":"CN",
    "gn:dem":456,
    "gn:feature_class":"P",
    "gn:feature_code":"PPL",
    "gn:name":"Zhanglu",
    "gn:population":0,
    "gn:timezone":"Asia/Shanghai",
    "iso:country":"CN",
    "name:zho_x_preferred":[
        "\u6a1f\u7984"
    ],
    "wof:name":"Zhanglu",
    "wof:placetype":"locality"
},
  "geometry": {"coordinates":[105.384,31.4001],"type":"Point"}
}