{
  "type": "Feature",
  "properties": {
    "gn:admin1_code":"12.0",
    "gn:asciiname":"Houhewan",
    "gn:country_code":"CN",
    "gn:dem":188,
    "gn:feature_class":"P",
    "gn:feature_code":"PPL",
    "gn:name":"Houhewan",
    "gn:population":0,
    "gn:timezone":"Asia/Shanghai",
    "iso:country":"CN",
    "name:zho_x_preferred":[
        "\u540e\u6cb3\u6e7e"
    ],
    "wof:name":"Houhewan",
    "wof:placetype":"locality"
},
  "geometry": {"coordinates":[111.06001999999999,32.62033],"type":"Point"}
}