{
  "type": "Feature",
  "properties": {
    "gn:admin1_code":"33.0",
    "gn:asciiname":"Liumaping",
    "gn:country_code":"CN",
    "gn:dem":769,
    "gn:feature_class":"P",
    "gn:feature_code":"PPL",
    "gn:name":"Liumaping",
    "gn:population":0,
    "gn:timezone":"Asia/Shanghai",
    "iso:country":"CN",
    "name:zho_x_preferred":[
        "\u67f3\u9a6c\u576a"
    ],
    "wof:name":"Liumaping",
    "wof:placetype":"locality"
},
  "geometry": {"coordinates":[108.79791000000002,28.55259],"type":"Point"}
}