{
  "type": "Feature",
  "properties": {
    "gn:admin1_code":"5.0",
    "gn:asciiname":"Fangcao",
    "gn:country_code":"CN",
    "gn:dem":313,
    "gn:feature_class":"P",
    "gn:feature_code":"PPL",
    "gn:name":"Fangcao",
    "gn:population":0,
    "gn:timezone":"Asia/Shanghai",
    "iso:country":"CN",
    "name:und_x_variant":[
        "\u82b3\u8349"
    ],
    "wof:name":"Fangcao",
    "wof:placetype":"locality"
},
  "geometry": {"coordinates":[129.43088,43.22949000000001],"type":"Point"}
}