{
  "type": "Feature",
  "properties": {
    "gn:admin1_code":"8.0",
    "gn:asciiname":"Hexiangtun",
    "gn:country_code":"CN",
    "gn:dem":170,
    "gn:feature_class":"P",
    "gn:feature_code":"PPL",
    "gn:name":"Hexiangtun",
    "gn:population":0,
    "gn:timezone":"Asia/Shanghai",
    "iso:country":"CN",
    "name:zho_x_preferred":[
        "\u4f55\u9999\u5c6f"
    ],
    "wof:name":"Hexiangtun",
    "wof:placetype":"locality"
},
  "geometry": {"coordinates":[126.98931,45.78963],"type":"Point"}
}