{
  "type": "Feature",
  "properties": {
    "gn:admin1_code":"26.0",
    "gn:asciiname":"Hejiayuancun",
    "gn:country_code":"CN",
    "gn:dem":1369,
    "gn:feature_class":"P",
    "gn:feature_code":"PPL",
    "gn:name":"Hejiayuancun",
    "gn:population":0,
    "gn:timezone":"Asia/Shanghai",
    "iso:country":"CN",
    "name:zho_x_preferred":[
        "\u4f55\u5bb6\u586c\u6751"
    ],
    "wof:name":"Hejiayuancun",
    "wof:placetype":"locality"
},
  "geometry": {"coordinates":[108.02406000000001,34.88206],"type":"Point"}
}