{
  "type": "Feature",
  "properties": {
    "gn:admin1_code":"32.0",
    "gn:asciiname":"Li'eryuan",
    "gn:country_code":"CN",
    "gn:dem":761,
    "gn:feature_class":"P",
    "gn:feature_code":"PPL",
    "gn:name":"Li\u2019eryuan",
    "gn:population":0,
    "gn:timezone":"Asia/Shanghai",
    "iso:country":"CN",
    "name:zho_x_preferred":[
        "\u68a8\u513f\u56ed"
    ],
    "name:zho_x_variant":[
        "Li\u2019eryuan"
    ],
    "wof:name":"Li'eryuan",
    "wof:placetype":"locality"
},
  "geometry": {"coordinates":[105.25482,32.13709],"type":"Point"}
}