{
  "type": "Feature",
  "properties": {
    "gn:admin1_code":"12",
    "gn:asciiname":"Jiangjiawan",
    "gn:country_code":"CN",
    "gn:dem":635,
    "gn:feature_class":"P",
    "gn:feature_code":"PPL",
    "gn:name":"Jiangjiawan",
    "gn:population":0,
    "gn:timezone":"Asia/Shanghai",
    "iso:country":"CN",
    "name:und_x_variant":[
        "Chiang-chia-ying",
        "Jiangjiawan"
    ],
    "name:zho_x_preferred":[
        "\u6c5f\u5bb6\u6e7e"
    ],
    "wof:name":"Jiangjiawan",
    "wof:placetype":"locality"
},
  "geometry": {"coordinates":[110.65107,32.44069],"type":"Point"}
}