{
  "type": "Feature",
  "properties": {
    "gn:admin1_code":"21.0",
    "gn:asciiname":"Shuiguansuo",
    "gn:country_code":"CN",
    "gn:dem":1412,
    "gn:feature_class":"P",
    "gn:feature_code":"PPL",
    "gn:name":"Shuiguansuo",
    "gn:population":0,
    "gn:timezone":"Asia/Shanghai",
    "iso:country":"CN",
    "name:zho_x_preferred":[
        "\u6c34\u7ba1\u6240"
    ],
    "wof:name":"Shuiguansuo",
    "wof:placetype":"locality"
},
  "geometry": {"coordinates":[105.929,36.8308],"type":"Point"}
}