{
  "type": "Feature",
  "properties": {
    "gn:admin1_code":"16.0",
    "gn:asciiname":"Shidong",
    "gn:country_code":"CN",
    "gn:dem":369,
    "gn:feature_class":"P",
    "gn:feature_code":"PPL",
    "gn:name":"Shidong",
    "gn:population":0,
    "gn:timezone":"Asia/Shanghai",
    "iso:country":"CN",
    "name:zho_x_preferred":[
        "\u6e7f\u6d1e"
    ],
    "name:zho_x_variant":[
        "\u8bd7\u6d1e\u9547"
    ],
    "wof:name":"Shidong",
    "wof:placetype":"locality"
},
  "geometry": {"coordinates":[108.18300000000001,25.355],"type":"Point"}
}