{
  "type": "Feature",
  "properties": {
    "gn:admin1_code":"13.0",
    "gn:asciiname":"Kalatongke",
    "gn:country_code":"CN",
    "gn:dem":919,
    "gn:feature_class":"P",
    "gn:feature_code":"PPLA4",
    "gn:name":"Kalatongke",
    "gn:population":0,
    "gn:timezone":"Asia/Urumqi",
    "iso:country":"CN",
    "name:und_x_variant":[
        "Ha-la-t\u2019ung-ku",
        "Ha-la-t\u2019ung-kou",
        "Karat\u00fcngg\u00fc",
        "Kalatongke",
        "Kalatongke Xiang"
    ],
    "name:zho_x_preferred":[
        "\u5580\u62c9\u901a\u514b"
    ],
    "name:zho_x_variant":[
        "\u5580\u62c9\u901a\u514b\u4e61"
    ],
    "wof:name":"Kalatongke",
    "wof:placetype":"locality"
},
  "geometry": {"coordinates":[89.69761,46.85591],"type":"Point"}
}