{
  "type": "Feature",
  "properties": {
    "gn:admin1_code":"30.0",
    "gn:asciiname":"Wanzaishan",
    "gn:country_code":"CN",
    "gn:dem":29,
    "gn:feature_class":"P",
    "gn:feature_code":"PPL",
    "gn:name":"Wanzaishan",
    "gn:population":0,
    "gn:timezone":"Asia/Shanghai",
    "iso:country":"CN",
    "name:zho_x_preferred":[
        "\u6e7e\u4ed4\u5c71"
    ],
    "wof:name":"Wanzaishan",
    "wof:placetype":"locality"
},
  "geometry": {"coordinates":[111.82453,23.11404],"type":"Point"}
}