{
  "type": "Feature",
  "properties": {
    "gn:admin1_code":"1.0",
    "gn:asciiname":"Xiangdongcun",
    "gn:country_code":"CN",
    "gn:dem":20,
    "gn:feature_class":"P",
    "gn:feature_code":"PPL",
    "gn:name":"Xiangdongcun",
    "gn:population":0,
    "gn:timezone":"Asia/Shanghai",
    "iso:country":"CN",
    "name:zho_x_preferred":[
        "\u5df7\u4e1c\u6751"
    ],
    "wof:name":"Xiangdongcun",
    "wof:placetype":"locality"
},
  "geometry": {"coordinates":[117.01093,32.72528],"type":"Point"}
}