{
  "type": "Feature",
  "properties": {
    "gn:admin1_code":"14.0",
    "gn:asciiname":"Mailong",
    "gn:country_code":"CN",
    "gn:dem":4144,
    "gn:feature_class":"P",
    "gn:feature_code":"PPL",
    "gn:name":"Mailong",
    "gn:population":0,
    "gn:timezone":"Asia/Urumqi",
    "iso:country":"CN",
    "name:zho_x_preferred":[
        "\u9ea6\u9f99"
    ],
    "wof:name":"Mailong",
    "wof:placetype":"locality"
},
  "geometry": {"coordinates":[91.17444999999999,30.04299],"type":"Point"}
}