{
  "type": "Feature",
  "properties": {
    "gn:admin1_code":"16",
    "gn:asciiname":"Zhaojiatu",
    "gn:country_code":"CN",
    "gn:dem":378,
    "gn:feature_class":"P",
    "gn:feature_code":"PPL",
    "gn:name":"Zhaojiatu",
    "gn:population":0,
    "gn:timezone":"Asia/Shanghai",
    "iso:country":"CN",
    "name:zho_x_preferred":[
        "\u8d75\u5bb6\u51f8"
    ],
    "wof:name":"Zhaojiatu",
    "wof:placetype":"locality"
},
  "geometry": {"coordinates":[110.68000000000001,26.185],"type":"Point"}
}