{
  "type": "Feature",
  "properties": {
    "gn:admin1_code":"32.0",
    "gn:asciiname":"Kuaihuo",
    "gn:country_code":"CN",
    "gn:dem":326,
    "gn:feature_class":"P",
    "gn:feature_code":"PPL",
    "gn:name":"Kuaihuo",
    "gn:population":0,
    "gn:timezone":"Asia/Shanghai",
    "iso:country":"CN",
    "name:zho_x_preferred":[
        "\u5feb\u6d3b"
    ],
    "wof:name":"Kuaihuo",
    "wof:placetype":"locality"
},
  "geometry": {"coordinates":[107.229,30.9307],"type":"Point"}
}