{
  "type": "Feature",
  "properties": {
    "gn:admin1_code":"24.0",
    "gn:asciiname":"Xiaolouze",
    "gn:country_code":"CN",
    "gn:dem":1507,
    "gn:feature_class":"P",
    "gn:feature_code":"PPL",
    "gn:name":"Xiaolouze",
    "gn:population":0,
    "gn:timezone":"Asia/Shanghai",
    "iso:country":"CN",
    "name:zho_x_preferred":[
        "\u5c0f\u5a04\u5219"
    ],
    "wof:name":"Xiaolouze",
    "wof:placetype":"locality"
},
  "geometry": {"coordinates":[111.79810999999999,37.95231],"type":"Point"}
}