{
  "type": "Feature",
  "properties": {
    "gn:admin1_code":"30.0",
    "gn:asciiname":"Taidongcun",
    "gn:country_code":"CN",
    "gn:dem":7,
    "gn:feature_class":"P",
    "gn:feature_code":"PPL",
    "gn:name":"Taidongcun",
    "gn:population":0,
    "gn:timezone":"Asia/Shanghai",
    "iso:country":"CN",
    "name:zho_x_preferred":[
        "\u53f0\u4e1c\u6751"
    ],
    "wof:name":"Taidongcun",
    "wof:placetype":"locality"
},
  "geometry": {"coordinates":[115.37163,23.01063],"type":"Point"}
}