{
  "type": "Feature",
  "properties": {
    "gn:admin1_code":"24.0",
    "gn:asciiname":"Weiyuanping",
    "gn:country_code":"CN",
    "gn:dem":1301,
    "gn:feature_class":"P",
    "gn:feature_code":"PPL",
    "gn:name":"Weiyuanping",
    "gn:population":0,
    "gn:timezone":"Asia/Shanghai",
    "iso:country":"CN",
    "name:zho_x_preferred":[
        "\u82c7\u9662\u576a"
    ],
    "wof:name":"Weiyuanping",
    "wof:placetype":"locality"
},
  "geometry": {"coordinates":[111.70019000000001,38.03215],"type":"Point"}
}