{
  "type": "Feature",
  "properties": {
    "gn:admin1_code":"04",
    "gn:asciiname":"Jinshu",
    "gn:country_code":"CN",
    "gn:dem":6,
    "gn:feature_class":"P",
    "gn:feature_code":"PPL",
    "gn:name":"Jinshu",
    "gn:population":0,
    "gn:timezone":"Asia/Shanghai",
    "iso:country":"CN",
    "name:und_x_variant":[
        "Chin-shu-chiang-chen",
        "Chin-shu-chiang",
        "Chin-shu-chen",
        "Chin-shu",
        "Jinshu",
        "\u91d1\u5885",
        "Jinshuzhen"
    ],
    "wof:name":"Jinshu",
    "wof:placetype":"locality"
},
  "geometry": {"coordinates":[120.40089,31.38017],"type":"Point"}
}