{
  "type": "Feature",
  "properties": {
    "gn:admin1_code":"2.0",
    "gn:asciiname":"Xiaxu",
    "gn:country_code":"CN",
    "gn:dem":277,
    "gn:feature_class":"P",
    "gn:feature_code":"PPL",
    "gn:name":"Xiaxu",
    "gn:population":0,
    "gn:timezone":"Asia/Shanghai",
    "iso:country":"CN",
    "name:und_x_variant":[
        "\u4e0b\u5f90",
        "Xiaxu"
    ],
    "wof:name":"Xiaxu",
    "wof:placetype":"locality"
},
  "geometry": {"coordinates":[119.41142000000001,29.42977],"type":"Point"}
}