{
  "type": "Feature",
  "properties": {
    "gn:admin1_code":"10",
    "gn:asciiname":"Shangguan",
    "gn:country_code":"CN",
    "gn:dem":242,
    "gn:feature_class":"P",
    "gn:feature_code":"PPL",
    "gn:name":"Shangguan",
    "gn:population":0,
    "gn:timezone":"Asia/Shanghai",
    "iso:country":"CN",
    "name:deu_x_preferred":[
        "Shangguan"
    ],
    "name:zho_x_preferred":[
        "\u4e0a\u5173"
    ],
    "wof:name":"Shangguan",
    "wof:placetype":"locality"
},
  "geometry": {"coordinates":[114.24299999999999,36.9003],"type":"Point"}
}