{
  "type": "Feature",
  "properties": {
    "gn:admin1_code":"4.0",
    "gn:asciiname":"Houlingjiabu",
    "gn:country_code":"CN",
    "gn:dem":6,
    "gn:feature_class":"P",
    "gn:feature_code":"PPL",
    "gn:name":"Houlingjiabu",
    "gn:population":0,
    "gn:timezone":"Asia/Shanghai",
    "iso:country":"CN",
    "name:zho_x_preferred":[
        "\u540e\u51cc\u5bb6\u57e0"
    ],
    "wof:name":"Houlingjiabu",
    "wof:placetype":"locality"
},
  "geometry": {"coordinates":[119.94483,32.18017],"type":"Point"}
}