{
  "type": "Feature",
  "properties": {
    "gn:admin1_code":"3.0",
    "gn:asciiname":"Pengfang",
    "gn:country_code":"CN",
    "gn:dem":367,
    "gn:feature_class":"P",
    "gn:feature_code":"PPL",
    "gn:name":"Pengfang",
    "gn:population":0,
    "gn:timezone":"Asia/Shanghai",
    "iso:country":"CN",
    "name:und_x_variant":[
        "\u5f6d\u574a"
    ],
    "wof:name":"Pengfang",
    "wof:placetype":"locality"
},
  "geometry": {"coordinates":[116.24464999999999,27.15252000000001],"type":"Point"}
}