{
  "type": "Feature",
  "properties": {
    "gn:admin1_code":"7.0",
    "gn:asciiname":"Shishi",
    "gn:country_code":"CN",
    "gn:dem":18,
    "gn:feature_class":"P",
    "gn:feature_code":"PPL",
    "gn:name":"Shishi",
    "gn:population":0,
    "gn:timezone":"Asia/Shanghai",
    "iso:country":"CN",
    "name:ceb_x_preferred":[
        "Shishi"
    ],
    "name:cym_x_preferred":[
        "Shishi"
    ],
    "name:deu_x_preferred":[
        "Shishi"
    ],
    "name:nor_x_preferred":[
        "Shishi"
    ],
    "name:swe_x_preferred":[
        "Shishi"
    ],
    "name:zho_x_preferred":[
        "\u77f3\u72ee"
    ],
    "wof:name":"Shishi",
    "wof:placetype":"locality"
},
  "geometry": {"coordinates":[119.17871,25.50863],"type":"Point"}
}