{
  "type": "Feature",
  "properties": {
    "gn:admin1_code":"19.0",
    "gn:asciiname":"Erdaohezi",
    "gn:country_code":"CN",
    "gn:dem":332,
    "gn:feature_class":"P",
    "gn:feature_code":"PPL",
    "gn:name":"Erdaohezi",
    "gn:population":0,
    "gn:timezone":"Asia/Shanghai",
    "iso:country":"CN",
    "name:und_x_variant":[
        "\u4e8c\u9053\u6cb3\u5b50"
    ],
    "wof:name":"Erdaohezi",
    "wof:placetype":"locality"
},
  "geometry": {"coordinates":[124.14005,41.18015],"type":"Point"}
}