{
  "type": "Feature",
  "properties": {
    "gn:admin1_code":"2.0",
    "gn:asciiname":"Hongtangli",
    "gn:country_code":"CN",
    "gn:dem":101,
    "gn:feature_class":"P",
    "gn:feature_code":"PPL",
    "gn:name":"Hongtangli",
    "gn:population":0,
    "gn:timezone":"Asia/Shanghai",
    "iso:country":"CN",
    "name:und_x_variant":[
        "\u6d2a\u5858\u91cc",
        "Hongtangli"
    ],
    "wof:name":"Hongtangli",
    "wof:placetype":"locality"
},
  "geometry": {"coordinates":[119.7154,29.36429],"type":"Point"}
}