{
  "type": "Feature",
  "properties": {
    "gn:admin1_code":"16.0",
    "gn:asciiname":"Faya",
    "gn:country_code":"CN",
    "gn:dem":118,
    "gn:feature_class":"P",
    "gn:feature_code":"PPL",
    "gn:name":"Faya",
    "gn:population":0,
    "gn:timezone":"Asia/Shanghai",
    "iso:country":"CN",
    "name:zho_x_preferred":[
        "\u53d1\u96c5"
    ],
    "wof:name":"Faya",
    "wof:placetype":"locality"
},
  "geometry": {"coordinates":[107.64,23.1194],"type":"Point"}
}