{
  "type": "Feature",
  "properties": {
    "gn:admin1_code":"19.0",
    "gn:asciiname":"Sunjia Wopu",
    "gn:country_code":"CN",
    "gn:dem":511,
    "gn:feature_class":"P",
    "gn:feature_code":"PPL",
    "gn:name":"Sunjia Wopu",
    "gn:population":0,
    "gn:timezone":"Asia/Shanghai",
    "iso:country":"CN",
    "name:zho_x_preferred":[
        "\u5b59\u5bb6\u7a9d\u94fa"
    ],
    "wof:name":"Sunjia Wopu",
    "wof:placetype":"locality"
},
  "geometry": {"coordinates":[119.35299999999999,42.2685],"type":"Point"}
}