{
  "type": "Feature",
  "properties": {
    "gn:admin1_code":"8.0",
    "gn:asciiname":"Shuishangcun",
    "gn:country_code":"CN",
    "gn:dem":143,
    "gn:feature_class":"P",
    "gn:feature_code":"PPL",
    "gn:name":"Shuishangcun",
    "gn:population":0,
    "gn:timezone":"Asia/Shanghai",
    "iso:country":"CN",
    "name:zho_x_preferred":[
        "\u6c34\u4e0a\u6751"
    ],
    "wof:name":"Shuishangcun",
    "wof:placetype":"locality"
},
  "geometry": {"coordinates":[123.3443,46.63159],"type":"Point"}
}