{
  "type": "Feature",
  "properties": {
    "gn:admin1_code":"3",
    "gn:asciiname":"Zhulaochong",
    "gn:country_code":"CN",
    "gn:dem":418,
    "gn:feature_class":"P",
    "gn:feature_code":"PPL",
    "gn:name":"Zhulaochong",
    "gn:population":0,
    "gn:timezone":"Asia/Shanghai",
    "iso:country":"CN",
    "name:zho_x_preferred":[
        "\u7af9\u8001\u51b2"
    ],
    "wof:name":"Zhulaochong",
    "wof:placetype":"locality"
},
  "geometry": {"coordinates":[114.07599999999999,26.8647],"type":"Point"}
}