{
  "type": "Feature",
  "properties": {
    "gn:admin1_code":"12.0",
    "gn:asciiname":"Mojiaxi",
    "gn:country_code":"CN",
    "gn:dem":748,
    "gn:feature_class":"P",
    "gn:feature_code":"PPL",
    "gn:name":"Mojiaxi",
    "gn:population":0,
    "gn:timezone":"Asia/Shanghai",
    "iso:country":"CN",
    "name:zho_x_preferred":[
        "\u83ab\u5bb6\u6eaa"
    ],
    "wof:name":"Mojiaxi",
    "wof:placetype":"locality"
},
  "geometry": {"coordinates":[110.42572,30.15807],"type":"Point"}
}