{
  "type": "Feature",
  "properties": {
    "gn:admin1_code":"29.0",
    "gn:asciiname":"Yingheng",
    "gn:country_code":"CN",
    "gn:dem":2567,
    "gn:feature_class":"P",
    "gn:feature_code":"PPL",
    "gn:name":"Yingheng",
    "gn:population":0,
    "gn:timezone":"Asia/Shanghai",
    "iso:country":"CN",
    "name:zho_x_preferred":[
        "\u5e94\u6052"
    ],
    "wof:name":"Yingheng",
    "wof:placetype":"locality"
},
  "geometry": {"coordinates":[99.2132,26.0074],"type":"Point"}
}