{
  "type": "Feature",
  "properties": {
    "gn:admin1_code":"02",
    "gn:asciiname":"Wuyancun",
    "gn:country_code":"CN",
    "gn:dem":69,
    "gn:feature_class":"P",
    "gn:feature_code":"PPL",
    "gn:name":"Wuyancun",
    "gn:population":0,
    "gn:timezone":"Asia/Shanghai",
    "iso:country":"CN",
    "name:und_x_variant":[
        "Wu-yen",
        "Wuyan",
        "Wuyancun"
    ],
    "name:zho_x_preferred":[
        "\u4e4c\u5ca9"
    ],
    "name:zho_x_variant":[
        "\u4e4c\u5ca9\u6751"
    ],
    "wof:name":"Wuyancun",
    "wof:placetype":"locality"
},
  "geometry": {"coordinates":[121.41607999999999,28.8891],"type":"Point"}
}