{
  "type": "Feature",
  "properties": {
    "gn:admin1_code":"03",
    "gn:asciiname":"Liushi",
    "gn:cc2":"CN",
    "gn:country_code":"CN",
    "gn:dem":537,
    "gn:feature_class":"P",
    "gn:feature_code":"PPL",
    "gn:name":"Liushi",
    "gn:population":0,
    "gn:timezone":"Asia/Shanghai",
    "iso:country":"CN",
    "name:und_x_variant":[
        "Liu-shih",
        "Liushi"
    ],
    "wof:name":"Liushi",
    "wof:placetype":"locality"
},
  "geometry": {"coordinates":[113.91667,27.38333],"type":"Point"}
}