{
  "type": "Feature",
  "properties": {
    "gn:admin1_code":"26.0",
    "gn:asciiname":"Lingaocun",
    "gn:country_code":"CN",
    "gn:dem":761,
    "gn:feature_class":"P",
    "gn:feature_code":"PPL",
    "gn:name":"Lingaocun",
    "gn:population":0,
    "gn:timezone":"Asia/Shanghai",
    "iso:country":"CN",
    "name:zho_x_preferred":[
        "\u4e34\u768b\u6751"
    ],
    "wof:name":"Lingaocun",
    "wof:placetype":"locality"
},
  "geometry": {"coordinates":[110.22874,35.24989],"type":"Point"}
}