{
  "type": "Feature",
  "properties": {
    "gn:admin1_code":"12.0",
    "gn:asciiname":"Guaping",
    "gn:country_code":"CN",
    "gn:dem":312,
    "gn:feature_class":"P",
    "gn:feature_code":"PPL",
    "gn:name":"Guaping",
    "gn:population":0,
    "gn:timezone":"Asia/Shanghai",
    "iso:country":"CN",
    "name:zho_x_preferred":[
        "Guaping"
    ],
    "name:zho_x_variant":[
        "\u74dc\u576a"
    ],
    "wof:name":"Guaping",
    "wof:placetype":"locality"
},
  "geometry": {"coordinates":[114.42102,29.43093],"type":"Point"}
}