{
  "type": "Feature",
  "properties": {
    "gn:admin1_code":"4.0",
    "gn:asciiname":"Niluocun",
    "gn:country_code":"CN",
    "gn:dem":0,
    "gn:feature_class":"P",
    "gn:feature_code":"PPL",
    "gn:name":"Niluocun",
    "gn:population":0,
    "gn:timezone":"Asia/Shanghai",
    "iso:country":"CN",
    "name:zho_x_preferred":[
        "\u6ce5\u87ba\u6751"
    ],
    "wof:name":"Niluocun",
    "wof:placetype":"locality"
},
  "geometry": {"coordinates":[120.14069000000001,33.9751],"type":"Point"}
}