{
  "type": "Feature",
  "properties": {
    "gn:admin1_code":"11.0",
    "gn:asciiname":"Suixiuwan",
    "gn:country_code":"CN",
    "gn:dem":32,
    "gn:feature_class":"P",
    "gn:feature_code":"PPL",
    "gn:name":"Suixiuwan",
    "gn:population":0,
    "gn:timezone":"Asia/Shanghai",
    "iso:country":"CN",
    "name:zho_x_preferred":[
        "\u5c81\u4fee\u6e7e"
    ],
    "wof:name":"Suixiuwan",
    "wof:placetype":"locality"
},
  "geometry": {"coordinates":[113.08257,28.27734],"type":"Point"}
}