{
  "type": "Feature",
  "properties": {
    "gn:admin1_code":"1.0",
    "gn:asciiname":"Xianhuacun",
    "gn:country_code":"CN",
    "gn:dem":28,
    "gn:feature_class":"P",
    "gn:feature_code":"PPL",
    "gn:name":"Xianhuacun",
    "gn:population":0,
    "gn:timezone":"Asia/Shanghai",
    "iso:country":"CN",
    "name:zho_x_preferred":[
        "\u663e\u5316\u6751"
    ],
    "wof:name":"Xianhuacun",
    "wof:placetype":"locality"
},
  "geometry": {"coordinates":[117.29598,30.4719],"type":"Point"}
}