{
  "type": "Feature",
  "properties": {
    "gn:admin1_code":"11.0",
    "gn:asciiname":"Maoziya",
    "gn:country_code":"CN",
    "gn:dem":909,
    "gn:feature_class":"P",
    "gn:feature_code":"PPL",
    "gn:name":"Maoziya",
    "gn:population":0,
    "gn:timezone":"Asia/Shanghai",
    "iso:country":"CN",
    "name:zho_x_preferred":[
        "\u732b\u5b50\u57ad"
    ],
    "wof:name":"Maoziya",
    "wof:placetype":"locality"
},
  "geometry": {"coordinates":[109.90273000000001,29.65565],"type":"Point"}
}