{
  "type": "Feature",
  "properties": {
    "gn:admin1_code":"5.0",
    "gn:asciiname":"Gaojia Weizicun",
    "gn:country_code":"CN",
    "gn:dem":203,
    "gn:feature_class":"P",
    "gn:feature_code":"PPL",
    "gn:name":"Gaojia Weizicun",
    "gn:population":0,
    "gn:timezone":"Asia/Shanghai",
    "iso:country":"CN",
    "name:zho_x_preferred":[
        "\u9ad8\u5bb6\u56f4\u5b50\u6751"
    ],
    "wof:name":"Gaojia Weizicun",
    "wof:placetype":"locality"
},
  "geometry": {"coordinates":[124.43523,44.51152],"type":"Point"}
}