{
  "type": "Feature",
  "properties": {
    "gn:admin1_code":"19.0",
    "gn:asciiname":"Dingjia Wopu",
    "gn:country_code":"CN",
    "gn:dem":6,
    "gn:feature_class":"P",
    "gn:feature_code":"PPL",
    "gn:name":"Dingjia Wopu",
    "gn:population":0,
    "gn:timezone":"Asia/Shanghai",
    "iso:country":"CN",
    "name:zho_x_preferred":[
        "\u4e01\u5bb6\u7a9d\u94fa"
    ],
    "wof:name":"Dingjia Wopu",
    "wof:placetype":"locality"
},
  "geometry": {"coordinates":[122.23,41.2431],"type":"Point"}
}