{
  "type": "Feature",
  "properties": {
    "gn:admin1_code":"30",
    "gn:asciiname":"Shuangba",
    "gn:country_code":"CN",
    "gn:dem":779,
    "gn:feature_class":"P",
    "gn:feature_code":"PPL",
    "gn:name":"Shuangba",
    "gn:population":0,
    "gn:timezone":"Asia/Shanghai",
    "iso:country":"CN",
    "name:und_x_variant":[
        "Shuangkeng",
        "Shuangba"
    ],
    "name:zho_x_preferred":[
        "\u53cc\u5751"
    ],
    "name:zho_x_variant":[
        "\u53cc\u575d"
    ],
    "wof:name":"Shuangba",
    "wof:placetype":"locality"
},
  "geometry": {"coordinates":[116.20135000000001,24.20955],"type":"Point"}
}