{
  "type": "Feature",
  "properties": {
    "gn:admin1_code":"4.0",
    "gn:asciiname":"Xi'erxu",
    "gn:country_code":"CN",
    "gn:dem":3,
    "gn:feature_class":"P",
    "gn:feature_code":"PPLF",
    "gn:name":"Xi\u2019erxu",
    "gn:population":0,
    "gn:timezone":"Asia/Shanghai",
    "iso:country":"CN",
    "name:und_x_variant":[
        "Xi\u2019erxu"
    ],
    "name:zho_x_preferred":[
        "\u897f\u4e8c\u5729"
    ],
    "wof:name":"Xi'erxu",
    "wof:placetype":"locality"
},
  "geometry": {"coordinates":[120.07736,32.02747],"type":"Point"}
}