{
  "type": "Feature",
  "properties": {
    "gn:admin1_code":"19.0",
    "gn:asciiname":"Nandalishugou",
    "gn:country_code":"CN",
    "gn:dem":136,
    "gn:feature_class":"P",
    "gn:feature_code":"PPL",
    "gn:name":"Nandalishugou",
    "gn:population":0,
    "gn:timezone":"Asia/Shanghai",
    "iso:country":"CN",
    "name:zho_x_preferred":[
        "\u5357\u5927\u68a8\u6811\u6c9f"
    ],
    "wof:name":"Nandalishugou",
    "wof:placetype":"locality"
},
  "geometry": {"coordinates":[122.205,42.4261],"type":"Point"}
}