{
  "type": "Feature",
  "properties": {
    "gn:admin1_code":"32.0",
    "gn:asciiname":"Zhongsancun",
    "gn:country_code":"CN",
    "gn:dem":352,
    "gn:feature_class":"P",
    "gn:feature_code":"PPL",
    "gn:name":"Zhongsancun",
    "gn:population":0,
    "gn:timezone":"Asia/Shanghai",
    "iso:country":"CN",
    "name:zho_x_preferred":[
        "\u4e2d\u4e09\u6751"
    ],
    "wof:name":"Zhongsancun",
    "wof:placetype":"locality"
},
  "geometry": {"coordinates":[105.09099999999999,30.7545],"type":"Point"}
}