{
  "type": "Feature",
  "properties": {
    "gn:admin1_code":"33.0",
    "gn:asciiname":"Yongfeng",
    "gn:country_code":"CN",
    "gn:dem":528,
    "gn:feature_class":"P",
    "gn:feature_code":"PPLA4",
    "gn:name":"Yongfeng",
    "gn:population":0,
    "gn:timezone":"Asia/Shanghai",
    "iso:country":"CN",
    "name:und_x_variant":[
        "Yung-feng-ch\u2019ang",
        "Yongfengchang",
        "Yongfeng",
        "Yongfeng Zhen"
    ],
    "name:zho_x_preferred":[
        "\u6c38\u4e30"
    ],
    "name:zho_x_variant":[
        "\u6c38\u4e30\u9547"
    ],
    "wof:name":"Yongfeng",
    "wof:placetype":"locality"
},
  "geometry": {"coordinates":[107.8194,30.31851],"type":"Point"}
}