{
  "type": "Feature",
  "properties": {
    "gn:admin1_code":"30.0",
    "gn:asciiname":"Wenzichong",
    "gn:country_code":"CN",
    "gn:dem":740,
    "gn:feature_class":"P",
    "gn:feature_code":"PPL",
    "gn:name":"Wenzichong",
    "gn:population":0,
    "gn:timezone":"Asia/Shanghai",
    "iso:country":"CN",
    "name:zho_x_preferred":[
        "Wenzichong"
    ],
    "name:zho_x_variant":[
        "\u868a\u5b50\u51b2"
    ],
    "wof:name":"Wenzichong",
    "wof:placetype":"locality"
},
  "geometry": {"coordinates":[112.4025,25.12111],"type":"Point"}
}