{
  "type": "Feature",
  "properties": {
    "gn:admin1_code":"3.0",
    "gn:asciiname":"Haohucun",
    "gn:country_code":"CN",
    "gn:dem":35,
    "gn:feature_class":"P",
    "gn:feature_code":"PPL",
    "gn:name":"Haohucun",
    "gn:population":0,
    "gn:timezone":"Asia/Shanghai",
    "iso:country":"CN",
    "name:und_x_variant":[
        "\u6fe0\u6e56\u6751"
    ],
    "wof:name":"Haohucun",
    "wof:placetype":"locality"
},
  "geometry": {"coordinates":[116.98754,28.29493],"type":"Point"}
}