{
  "type": "Feature",
  "properties": {
    "gn:admin1_code":"29.0",
    "gn:asciiname":"Yinshan",
    "gn:country_code":"CN",
    "gn:dem":1968,
    "gn:feature_class":"P",
    "gn:feature_code":"PPL",
    "gn:name":"Yinshan",
    "gn:population":0,
    "gn:timezone":"Asia/Shanghai",
    "iso:country":"CN",
    "name:zho_x_preferred":[
        "\u9634\u5c71"
    ],
    "wof:name":"Yinshan",
    "wof:placetype":"locality"
},
  "geometry": {"coordinates":[101.175,25.8734],"type":"Point"}
}