{
  "type": "Feature",
  "properties": {
    "gn:admin1_code":"30.0",
    "gn:asciiname":"Lingshuicun",
    "gn:country_code":"CN",
    "gn:dem":339,
    "gn:feature_class":"P",
    "gn:feature_code":"PPL",
    "gn:name":"Lingshuicun",
    "gn:population":0,
    "gn:timezone":"Asia/Shanghai",
    "iso:country":"CN",
    "name:zho_x_preferred":[
        "\u7075\u6c34\u6751"
    ],
    "wof:name":"Lingshuicun",
    "wof:placetype":"locality"
},
  "geometry": {"coordinates":[115.97554,24.71397],"type":"Point"}
}