{
  "type": "Feature",
  "properties": {
    "gn:admin1_code":"11",
    "gn:asciiname":"Wushi",
    "gn:country_code":"CN",
    "gn:dem":199,
    "gn:feature_class":"P",
    "gn:feature_code":"PPL",
    "gn:name":"Wushi",
    "gn:population":0,
    "gn:timezone":"Asia/Shanghai",
    "iso:country":"CN",
    "name:ceb_x_preferred":[
        "Wushi"
    ],
    "name:deu_x_preferred":[
        "Wushi"
    ],
    "name:fra_x_preferred":[
        "Wushi"
    ],
    "name:swe_x_preferred":[
        "Wushi"
    ],
    "name:und_x_variant":[
        "\u4e4c\u77f3"
    ],
    "wof:name":"Wushi",
    "wof:placetype":"locality"
},
  "geometry": {"coordinates":[114.09562,28.24651],"type":"Point"}
}