{
  "type": "Feature",
  "properties": {
    "gn:admin1_code":"14",
    "gn:asciiname":"Kangqiong",
    "gn:country_code":"CN",
    "gn:dem":4888,
    "gn:feature_class":"P",
    "gn:feature_code":"PPL",
    "gn:name":"Kangqiong",
    "gn:population":0,
    "gn:timezone":"Asia/Urumqi",
    "iso:country":"CN",
    "name:zho_x_preferred":[
        "\u5eb7\u743c"
    ],
    "wof:name":"Kangqiong",
    "wof:placetype":"locality"
},
  "geometry": {"coordinates":[87.9513,31.2112],"type":"Point"}
}