{
  "type": "Feature",
  "properties": {
    "gn:admin1_code":"14.0",
    "gn:asciiname":"Qiong'en",
    "gn:country_code":"CN",
    "gn:dem":4279,
    "gn:feature_class":"P",
    "gn:feature_code":"PPL",
    "gn:name":"Qiong\u2019en",
    "gn:population":0,
    "gn:timezone":"Asia/Urumqi",
    "iso:country":"CN",
    "name:und_x_variant":[
        "Qiong\u2019en"
    ],
    "name:zho_x_preferred":[
        "\u7a77\u6069"
    ],
    "wof:name":"Qiong'en",
    "wof:placetype":"locality"
},
  "geometry": {"coordinates":[95.15727,31.19914],"type":"Point"}
}