{
  "type": "Feature",
  "properties": {
    "gn:admin1_code":"10.0",
    "gn:asciiname":"Sanyanjing",
    "gn:country_code":"CN",
    "gn:dem":1201,
    "gn:feature_class":"P",
    "gn:feature_code":"PPL",
    "gn:name":"Sanyanjing",
    "gn:population":0,
    "gn:timezone":"Asia/Shanghai",
    "iso:country":"CN",
    "name:zho_x_preferred":[
        "\u4e09\u773c\u4e95"
    ],
    "wof:name":"Sanyanjing",
    "wof:placetype":"locality"
},
  "geometry": {"coordinates":[114.44053999999998,39.02814],"type":"Point"}
}