{
  "type": "Feature",
  "properties": {
    "gn:admin1_code":"30",
    "gn:asciiname":"Luoyuan",
    "gn:country_code":"CN",
    "gn:dem":86,
    "gn:feature_class":"P",
    "gn:feature_code":"PPLA4",
    "gn:name":"Luoyuan",
    "gn:population":0,
    "gn:timezone":"Asia/Shanghai",
    "iso:country":"CN",
    "name:und_x_variant":[
        "Luoyuan Zhen",
        "\u7f57\u6e90\u9547"
    ],
    "name:zho_x_preferred":[
        "\u7f57\u6e90"
    ],
    "wof:name":"Luoyuan",
    "wof:placetype":"locality"
},
  "geometry": {"coordinates":[112.75133,23.57891],"type":"Point"}
}