{
  "type": "Feature",
  "properties": {
    "gn:admin1_code":"19.0",
    "gn:asciiname":"Sandao Huoshigou",
    "gn:country_code":"CN",
    "gn:dem":565,
    "gn:feature_class":"P",
    "gn:feature_code":"PPL",
    "gn:name":"Sandao Huoshigou",
    "gn:population":0,
    "gn:timezone":"Asia/Shanghai",
    "iso:country":"CN",
    "name:und_x_variant":[
        "\u4e09\u9053\u706b\u77f3\u6c9f"
    ],
    "wof:name":"Sandao Huoshigou",
    "wof:placetype":"locality"
},
  "geometry": {"coordinates":[124.98273,41.88458],"type":"Point"}
}