{
  "type": "Feature",
  "properties": {
    "gn:admin1_code":"14.0",
    "gn:asciiname":"Qiaokuan'er",
    "gn:country_code":"CN",
    "gn:dem":3466,
    "gn:feature_class":"P",
    "gn:feature_code":"PPL",
    "gn:name":"Qiaokuan\u2019er",
    "gn:population":0,
    "gn:timezone":"Asia/Urumqi",
    "iso:country":"CN",
    "name:und_x_variant":[
        "Qiaokuan\u2019er"
    ],
    "name:zho_x_preferred":[
        "\u4e54\u5bbd\u513f"
    ],
    "wof:name":"Qiaokuan'er",
    "wof:placetype":"locality"
},
  "geometry": {"coordinates":[94.73994999999999,29.7204],"type":"Point"}
}