{
  "type": "Feature",
  "properties": {
    "gn:admin1_code":"32.0",
    "gn:asciiname":"Duomu",
    "gn:country_code":"CN",
    "gn:dem":2653,
    "gn:feature_class":"P",
    "gn:feature_code":"PPL",
    "gn:name":"Duomu",
    "gn:population":0,
    "gn:timezone":"Asia/Shanghai",
    "iso:country":"CN",
    "name:zho_x_preferred":[
        "\u591a\u6728"
    ],
    "wof:name":"Duomu",
    "wof:placetype":"locality"
},
  "geometry": {"coordinates":[102.97199999999999,27.7593],"type":"Point"}
}