{
  "type": "Feature",
  "properties": {
    "gn:admin1_code":"15.0",
    "gn:asciiname":"Miaoshanheba",
    "gn:country_code":"CN",
    "gn:dem":1922,
    "gn:feature_class":"P",
    "gn:feature_code":"PPL",
    "gn:name":"Miaoshanheba",
    "gn:population":0,
    "gn:timezone":"Asia/Shanghai",
    "iso:country":"CN",
    "name:zho_x_preferred":[
        "\u5e99\u5c71\u6cb3\u575d"
    ],
    "wof:name":"Miaoshanheba",
    "wof:placetype":"locality"
},
  "geometry": {"coordinates":[104.69015,33.16412],"type":"Point"}
}