{
  "type": "Feature",
  "properties": {
    "gn:admin1_code":"12.0",
    "gn:asciiname":"Maozizhuang",
    "gn:country_code":"CN",
    "gn:dem":989,
    "gn:feature_class":"P",
    "gn:feature_code":"PPL",
    "gn:name":"Maozizhuang",
    "gn:population":0,
    "gn:timezone":"Asia/Shanghai",
    "iso:country":"CN",
    "name:zho_x_preferred":[
        "\u732b\u5b50\u5e84"
    ],
    "wof:name":"Maozizhuang",
    "wof:placetype":"locality"
},
  "geometry": {"coordinates":[109.71841000000001,30.094],"type":"Point"}
}