{
  "type": "Feature",
  "properties": {
    "gn:admin1_code":"26.0",
    "gn:asciiname":"Juliancun",
    "gn:country_code":"CN",
    "gn:dem":449,
    "gn:feature_class":"P",
    "gn:feature_code":"PPL",
    "gn:name":"Juliancun",
    "gn:population":0,
    "gn:timezone":"Asia/Shanghai",
    "iso:country":"CN",
    "name:zho_x_preferred":[
        "\u5c40\u8fde\u6751"
    ],
    "wof:name":"Juliancun",
    "wof:placetype":"locality"
},
  "geometry": {"coordinates":[108.96745,34.13443],"type":"Point"}
}