{
  "type": "Feature",
  "properties": {
    "gn:admin1_code":"13",
    "gn:asciiname":"Egezi",
    "gn:country_code":"CN",
    "gn:dem":1519,
    "gn:feature_class":"P",
    "gn:feature_code":"PPL",
    "gn:name":"Egezi",
    "gn:population":0,
    "gn:timezone":"Asia/Urumqi",
    "iso:country":"CN",
    "name:zho_x_preferred":[
        "\u5384\u683c\u5b5c"
    ],
    "wof:name":"Egezi",
    "wof:placetype":"locality"
},
  "geometry": {"coordinates":[87.4599,41.37129],"type":"Point"}
}