{
  "type": "Feature",
  "properties": {
    "gn:admin1_code":"7.0",
    "gn:asciiname":"Gexikou",
    "gn:country_code":"CN",
    "gn:dem":450,
    "gn:feature_class":"P",
    "gn:feature_code":"PPL",
    "gn:name":"Gexikou",
    "gn:population":0,
    "gn:timezone":"Asia/Shanghai",
    "iso:country":"CN",
    "name:und_x_variant":[
        "\u5404\u6eaa\u53e3"
    ],
    "wof:name":"Gexikou",
    "wof:placetype":"locality"
},
  "geometry": {"coordinates":[116.5317,26.37172],"type":"Point"}
}