{
  "type": "Feature",
  "properties": {
    "gn:admin1_code":"8.0",
    "gn:asciiname":"Yongqiantun",
    "gn:country_code":"CN",
    "gn:dem":226,
    "gn:feature_class":"P",
    "gn:feature_code":"PPL",
    "gn:name":"Yongqiantun",
    "gn:population":0,
    "gn:timezone":"Asia/Shanghai",
    "iso:country":"CN",
    "name:zho_x_preferred":[
        "\u6c38\u5343\u5c6f"
    ],
    "wof:name":"Yongqiantun",
    "wof:placetype":"locality"
},
  "geometry": {"coordinates":[127.88142999999999,45.66574],"type":"Point"}
}