{
  "type": "Feature",
  "properties": {
    "gn:admin1_code":"29.0",
    "gn:asciiname":"Chahe",
    "gn:country_code":"CN",
    "gn:dem":1632,
    "gn:feature_class":"P",
    "gn:feature_code":"PPL",
    "gn:name":"Chahe",
    "gn:population":0,
    "gn:timezone":"Asia/Shanghai",
    "iso:country":"CN",
    "name:zho_x_preferred":[
        "\u5c94\u6cb3"
    ],
    "wof:name":"Chahe",
    "wof:placetype":"locality"
},
  "geometry": {"coordinates":[99.79170000000001,23.3103],"type":"Point"}
}