{
  "type": "Feature",
  "properties": {
    "gn:admin1_code":"24.0",
    "gn:asciiname":"Qiannangou",
    "gn:country_code":"CN",
    "gn:dem":1232,
    "gn:feature_class":"P",
    "gn:feature_code":"PPL",
    "gn:name":"Qiannangou",
    "gn:population":0,
    "gn:timezone":"Asia/Shanghai",
    "iso:country":"CN",
    "name:und_x_variant":[
        "\u524d\u5357\u6c9f"
    ],
    "wof:name":"Qiannangou",
    "wof:placetype":"locality"
},
  "geometry": {"coordinates":[112.44888,39.42638],"type":"Point"}
}