{
  "type": "Feature",
  "properties": {
    "gn:admin1_code":"26",
    "gn:asciiname":"Shuanghekou",
    "gn:country_code":"CN",
    "gn:dem":564,
    "gn:feature_class":"P",
    "gn:feature_code":"PPL",
    "gn:name":"Shuanghekou",
    "gn:population":0,
    "gn:timezone":"Asia/Shanghai",
    "iso:country":"CN",
    "name:und_x_variant":[
        "Shuang-ho-k\u2019ou",
        "Shuanghekou"
    ],
    "name:zho_x_preferred":[
        "\u53cc\u6cb3\u53e3"
    ],
    "wof:name":"Shuanghekou",
    "wof:placetype":"locality"
},
  "geometry": {"coordinates":[108.3518,32.381],"type":"Point"}
}