{
  "type": "Feature",
  "properties": {
    "gn:admin1_code":"30.0",
    "gn:asciiname":"Yueliao",
    "gn:country_code":"CN",
    "gn:dem":345,
    "gn:feature_class":"P",
    "gn:feature_code":"PPL",
    "gn:name":"Yueliao",
    "gn:population":0,
    "gn:timezone":"Asia/Shanghai",
    "iso:country":"CN",
    "name:zho_x_preferred":[
        "Yueliao"
    ],
    "name:zho_x_variant":[
        "\u6708\u5bee"
    ],
    "wof:name":"Yueliao",
    "wof:placetype":"locality"
},
  "geometry": {"coordinates":[112.74583,24.55389],"type":"Point"}
}