{
  "type": "Feature",
  "properties": {
    "gn:admin1_code":"19.0",
    "gn:asciiname":"Jiucaigangzi",
    "gn:country_code":"CN",
    "gn:dem":19,
    "gn:feature_class":"P",
    "gn:feature_code":"PPL",
    "gn:name":"Jiucaigangzi",
    "gn:population":0,
    "gn:timezone":"Asia/Shanghai",
    "iso:country":"CN",
    "name:und_x_variant":[
        "\u97ed\u83dc\u5c97\u5b50"
    ],
    "name:zho_x_preferred":[
        "\u97ed\u83dc\u5c97\u5b50"
    ],
    "wof:name":"Jiucaigangzi",
    "wof:placetype":"locality"
},
  "geometry": {"coordinates":[122.55567000000001,41.703],"type":"Point"}
}