{
  "type": "Feature",
  "properties": {
    "gn:admin1_code":"3",
    "gn:asciiname":"Sanbanqiao",
    "gn:country_code":"CN",
    "gn:dem":187,
    "gn:feature_class":"P",
    "gn:feature_code":"PPL",
    "gn:name":"Sanbanqiao",
    "gn:population":0,
    "gn:timezone":"Asia/Shanghai",
    "iso:country":"CN",
    "name:zho_x_preferred":[
        "\u4e09\u677f\u6865"
    ],
    "wof:name":"Sanbanqiao",
    "wof:placetype":"locality"
},
  "geometry": {"coordinates":[113.90907,26.98434],"type":"Point"}
}