{
  "type": "Feature",
  "properties": {
    "gn:admin1_code":"2",
    "gn:asciiname":"Chengshecun",
    "gn:country_code":"CN",
    "gn:dem":8,
    "gn:feature_class":"P",
    "gn:feature_code":"PPL",
    "gn:name":"Chengshecun",
    "gn:population":0,
    "gn:timezone":"Asia/Shanghai",
    "iso:country":"CN",
    "name:und_x_variant":[
        "Sheng-shan-shih",
        "Shengshe",
        "\u665f\u820d",
        "Chengshecun",
        "Chengshe"
    ],
    "name:zho_x_preferred":[
        "\u665f\u820d\u6751"
    ],
    "wof:name":"Chengshecun",
    "wof:placetype":"locality"
},
  "geometry": {"coordinates":[120.25232,30.84412],"type":"Point"}
}