{
  "type": "Feature",
  "properties": {
    "gn:admin1_code":"19.0",
    "gn:asciiname":"Houfangcun",
    "gn:country_code":"CN",
    "gn:dem":81,
    "gn:feature_class":"P",
    "gn:feature_code":"PPL",
    "gn:name":"Houfangcun",
    "gn:population":0,
    "gn:timezone":"Asia/Shanghai",
    "iso:country":"CN",
    "name:zho_x_preferred":[
        "\u540e\u623f\u6751"
    ],
    "wof:name":"Houfangcun",
    "wof:placetype":"locality"
},
  "geometry": {"coordinates":[122.449,39.8804],"type":"Point"}
}