{
  "type": "Feature",
  "properties": {
    "gn:admin1_code":"4.0",
    "gn:asciiname":"Fengmatou",
    "gn:country_code":"CN",
    "gn:dem":21,
    "gn:feature_class":"P",
    "gn:feature_code":"PPL",
    "gn:name":"Fengmatou",
    "gn:population":0,
    "gn:timezone":"Asia/Shanghai",
    "iso:country":"CN",
    "name:zho_x_preferred":[
        "\u51af\u7801\u5934"
    ],
    "wof:name":"Fengmatou",
    "wof:placetype":"locality"
},
  "geometry": {"coordinates":[118.783,33.5406],"type":"Point"}
}