{
  "type": "Feature",
  "properties": {
    "gn:admin1_code":"26",
    "gn:asciiname":"Xili",
    "gn:country_code":"CN",
    "gn:dem":419,
    "gn:feature_class":"P",
    "gn:feature_code":"PPL",
    "gn:name":"Xili",
    "gn:population":0,
    "gn:timezone":"Asia/Shanghai",
    "iso:country":"CN",
    "name:und_x_variant":[
        "\u897f\u674e",
        "Xili"
    ],
    "wof:name":"Xili",
    "wof:placetype":"locality"
},
  "geometry": {"coordinates":[109.14313,34.24627],"type":"Point"}
}