{
  "type": "Feature",
  "properties": {
    "gn:admin1_code":"11.0",
    "gn:asciiname":"Mawangxi",
    "gn:country_code":"CN",
    "gn:dem":301,
    "gn:feature_class":"P",
    "gn:feature_code":"PPL",
    "gn:name":"Mawangxi",
    "gn:population":0,
    "gn:timezone":"Asia/Shanghai",
    "iso:country":"CN",
    "name:zho_x_preferred":[
        "\u9a6c\u738b\u6eaa"
    ],
    "wof:name":"Mawangxi",
    "wof:placetype":"locality"
},
  "geometry": {"coordinates":[109.97384,28.15584],"type":"Point"}
}