{
  "type": "Feature",
  "properties": {
    "gn:admin1_code":"5.0",
    "gn:asciiname":"Jiudaogoumen",
    "gn:country_code":"CN",
    "gn:dem":644,
    "gn:feature_class":"P",
    "gn:feature_code":"PPL",
    "gn:name":"Jiudaogoumen",
    "gn:population":0,
    "gn:timezone":"Asia/Shanghai",
    "iso:country":"CN",
    "name:und_x_variant":[
        "\u4e5d\u9053\u6c9f\u95e8"
    ],
    "wof:name":"Jiudaogoumen",
    "wof:placetype":"locality"
},
  "geometry": {"coordinates":[125.76031,41.89023],"type":"Point"}
}