{
  "type": "Feature",
  "properties": {
    "gn:admin1_code":"18.0",
    "gn:asciiname":"Naiyan",
    "gn:country_code":"CN",
    "gn:dem":537,
    "gn:feature_class":"P",
    "gn:feature_code":"PPL",
    "gn:name":"Naiyan",
    "gn:population":0,
    "gn:timezone":"Asia/Shanghai",
    "iso:country":"CN",
    "name:zho_x_preferred":[
        "\u4e43\u8a00"
    ],
    "wof:name":"Naiyan",
    "wof:placetype":"locality"
},
  "geometry": {"coordinates":[105.84,24.7797],"type":"Point"}
}