{
  "type": "Feature",
  "properties": {
    "gn:admin1_code":"2.0",
    "gn:asciiname":"Wangshikeng",
    "gn:country_code":"CN",
    "gn:dem":121,
    "gn:feature_class":"P",
    "gn:feature_code":"PPL",
    "gn:name":"Wangshikeng",
    "gn:population":0,
    "gn:timezone":"Asia/Shanghai",
    "iso:country":"CN",
    "name:zho_x_preferred":[
        "\u671b\u77f3\u5751"
    ],
    "wof:name":"Wangshikeng",
    "wof:placetype":"locality"
},
  "geometry": {"coordinates":[120.44522000000001,27.93492],"type":"Point"}
}