{
  "type": "Feature",
  "properties": {
    "gn:admin1_code":"26.0",
    "gn:asciiname":"Wufan",
    "gn:country_code":"CN",
    "gn:dem":978,
    "gn:feature_class":"P",
    "gn:feature_code":"PPL",
    "gn:name":"Wufan",
    "gn:population":0,
    "gn:timezone":"Asia/Shanghai",
    "iso:country":"CN",
    "name:zho_x_preferred":[
        "\u609e\u996d"
    ],
    "name:zho_x_variant":[
        "\u8bef\u996d"
    ],
    "wof:name":"Wufan",
    "wof:placetype":"locality"
},
  "geometry": {"coordinates":[109.36136,34.27098],"type":"Point"}
}