{
  "type": "Feature",
  "properties": {
    "gn:admin1_code":"08",
    "gn:asciiname":"Xinglong",
    "gn:country_code":"CN",
    "gn:dem":189,
    "gn:feature_class":"P",
    "gn:feature_code":"PPLA4",
    "gn:name":"Xinglong",
    "gn:population":0,
    "gn:timezone":"Asia/Shanghai",
    "iso:country":"CN",
    "name:ceb_x_preferred":[
        "Xinglong"
    ],
    "name:deu_x_preferred":[
        "Xinglong"
    ],
    "name:und_x_variant":[
        "Xinglong Xiang"
    ],
    "name:zho_x_preferred":[
        "\u5174\u9686"
    ],
    "name:zho_x_variant":[
        "\u5174\u9686\u4e61"
    ],
    "wof:name":"Xinglong",
    "wof:placetype":"locality"
},
  "geometry": {"coordinates":[123.65713,48.03175],"type":"Point"}
}