{
  "type": "Feature",
  "properties": {
    "gn:admin1_code":"26.0",
    "gn:asciiname":"Guanduping",
    "gn:country_code":"CN",
    "gn:dem":326,
    "gn:feature_class":"P",
    "gn:feature_code":"PPL",
    "gn:name":"Guanduping",
    "gn:population":0,
    "gn:timezone":"Asia/Shanghai",
    "iso:country":"CN",
    "name:zho_x_preferred":[
        "\u5173\u6e21\u576a"
    ],
    "wof:name":"Guanduping",
    "wof:placetype":"locality"
},
  "geometry": {"coordinates":[110.75209,33.43528],"type":"Point"}
}