{
  "type": "Feature",
  "properties": {
    "gn:admin1_code":"5.0",
    "gn:asciiname":"Beizhaojiajiecun",
    "gn:country_code":"CN",
    "gn:dem":349,
    "gn:feature_class":"P",
    "gn:feature_code":"PPL",
    "gn:name":"Beizhaojiajiecun",
    "gn:population":0,
    "gn:timezone":"Asia/Shanghai",
    "iso:country":"CN",
    "name:zho_x_preferred":[
        "\u5317\u8d75\u5bb6\u8857\u6751"
    ],
    "wof:name":"Beizhaojiajiecun",
    "wof:placetype":"locality"
},
  "geometry": {"coordinates":[125.73569999999999,43.0065],"type":"Point"}
}