{
  "type": "Feature",
  "properties": {
    "gn:admin1_code":"15.0",
    "gn:asciiname":"Touguanmen",
    "gn:country_code":"CN",
    "gn:dem":1720,
    "gn:feature_class":"P",
    "gn:feature_code":"PPL",
    "gn:name":"Touguanmen",
    "gn:population":0,
    "gn:timezone":"Asia/Shanghai",
    "iso:country":"CN",
    "name:und_x_variant":[
        "\u900f\u5173\u95e8"
    ],
    "wof:name":"Touguanmen",
    "wof:placetype":"locality"
},
  "geometry": {"coordinates":[106.73576,36.50777],"type":"Point"}
}