{
  "type": "Feature",
  "properties": {
    "gn:admin1_code":"24.0",
    "gn:asciiname":"Taiqin",
    "gn:country_code":"CN",
    "gn:dem":431,
    "gn:feature_class":"P",
    "gn:feature_code":"PPL",
    "gn:name":"Taiqin",
    "gn:population":0,
    "gn:timezone":"Asia/Shanghai",
    "iso:country":"CN",
    "name:und_x_variant":[
        "\u592a\u79e6"
    ],
    "wof:name":"Taiqin",
    "wof:placetype":"locality"
},
  "geometry": {"coordinates":[111.40013999999999,35.68412],"type":"Point"}
}