{
  "type": "Feature",
  "properties": {
    "gn:admin1_code":"0.0",
    "gn:asciiname":"Lao-mien-chai",
    "gn:country_code":"CN",
    "gn:dem":1605,
    "gn:feature_class":"P",
    "gn:feature_code":"PPL",
    "gn:name":"Lao-mien-chai",
    "gn:population":0,
    "gn:timezone":"Asia/Shanghai",
    "iso:country":"CN",
    "wof:name":"Lao-mien-chai",
    "wof:placetype":"locality"
},
  "geometry": {"coordinates":[99.86593999999999,22.65691],"type":"Point"}
}