{
  "type": "Feature",
  "properties": {
    "gn:admin1_code":"4.0",
    "gn:asciiname":"Dougoucun",
    "gn:country_code":"CN",
    "gn:dem":24,
    "gn:feature_class":"P",
    "gn:feature_code":"PPL",
    "gn:name":"Dougoucun",
    "gn:population":0,
    "gn:timezone":"Asia/Shanghai",
    "iso:country":"CN",
    "name:zho_x_preferred":[
        "\u9661\u6c9f\u6751"
    ],
    "wof:name":"Dougoucun",
    "wof:placetype":"locality"
},
  "geometry": {"coordinates":[118.95929,34.93268],"type":"Point"}
}