{
  "type": "Feature",
  "properties": {
    "gn:admin1_code":"1.0",
    "gn:asciiname":"Hengtangcun",
    "gn:country_code":"CN",
    "gn:dem":58,
    "gn:feature_class":"P",
    "gn:feature_code":"PPL",
    "gn:name":"Hengtangcun",
    "gn:population":0,
    "gn:timezone":"Asia/Shanghai",
    "iso:country":"CN",
    "name:zho_x_preferred":[
        "\u6a2a\u5858\u6751"
    ],
    "wof:name":"Hengtangcun",
    "wof:placetype":"locality"
},
  "geometry": {"coordinates":[117.00669000000001,32.54575999999999],"type":"Point"}
}