{
  "type": "Feature",
  "properties": {
    "gn:admin1_code":"29",
    "gn:asciiname":"Yinzhutang Shangzhai",
    "gn:country_code":"CN",
    "gn:dem":1586,
    "gn:feature_class":"P",
    "gn:feature_code":"PPL",
    "gn:name":"Yinzhutang Shangzhai",
    "gn:population":0,
    "gn:timezone":"Asia/Shanghai",
    "iso:country":"CN",
    "name:zho_x_preferred":[
        "\u94f6\u67f1\u5858\u4e0a\u5be8"
    ],
    "wof:name":"Yinzhutang Shangzhai",
    "wof:placetype":"locality"
},
  "geometry": {"coordinates":[102.41800000000001,23.6704],"type":"Point"}
}