{
  "type": "Feature",
  "properties": {
    "gn:admin1_code":"19.0",
    "gn:asciiname":"Tongfotang",
    "gn:country_code":"CN",
    "gn:dem":33,
    "gn:feature_class":"P",
    "gn:feature_code":"PPL",
    "gn:name":"Tongfotang",
    "gn:population":0,
    "gn:timezone":"Asia/Shanghai",
    "iso:country":"CN",
    "name:zho_x_preferred":[
        "\u4f5f\u4f5b\u5802"
    ],
    "wof:name":"Tongfotang",
    "wof:placetype":"locality"
},
  "geometry": {"coordinates":[121.82335999999999,41.51083],"type":"Point"}
}