{
  "type": "Feature",
  "properties": {
    "gn:admin1_code":"32",
    "gn:asciiname":"Malongyizu",
    "gn:country_code":"CN",
    "gn:dem":1972,
    "gn:feature_class":"P",
    "gn:feature_code":"PPL",
    "gn:name":"Malongyizu",
    "gn:population":0,
    "gn:timezone":"Asia/Shanghai",
    "iso:country":"CN",
    "name:und_x_variant":[
        "Malong",
        "Malongyizu"
    ],
    "wof:name":"Malongyizu",
    "wof:placetype":"locality"
},
  "geometry": {"coordinates":[101.86736999999999,26.9261],"type":"Point"}
}