{
  "type": "Feature",
  "properties": {
    "gn:admin1_code":"21.0",
    "gn:asciiname":"Beimiao",
    "gn:country_code":"CN",
    "gn:dem":1100,
    "gn:feature_class":"P",
    "gn:feature_code":"PPL",
    "gn:name":"Beimiao",
    "gn:population":0,
    "gn:timezone":"Asia/Shanghai",
    "iso:country":"CN",
    "name:zho_x_preferred":[
        "\u5317\u5e99"
    ],
    "wof:name":"Beimiao",
    "wof:placetype":"locality"
},
  "geometry": {"coordinates":[106.29300000000001,38.7581],"type":"Point"}
}