{
  "type": "Feature",
  "properties": {
    "gn:admin1_code":"1.0",
    "gn:asciiname":"Jingnanncun",
    "gn:country_code":"CN",
    "gn:dem":91,
    "gn:feature_class":"P",
    "gn:feature_code":"PPL",
    "gn:name":"Jingnanncun",
    "gn:population":0,
    "gn:timezone":"Asia/Shanghai",
    "iso:country":"CN",
    "name:zho_x_preferred":[
        "\u4e95\u6960\u6751"
    ],
    "wof:name":"Jingnanncun",
    "wof:placetype":"locality"
},
  "geometry": {"coordinates":[118.1078,32.26717],"type":"Point"}
}