{
  "type": "Feature",
  "properties": {
    "gn:admin1_code":"24.0",
    "gn:asciiname":"Wujiayao",
    "gn:country_code":"CN",
    "gn:dem":1567,
    "gn:feature_class":"P",
    "gn:feature_code":"PPL",
    "gn:name":"Wujiayao",
    "gn:population":0,
    "gn:timezone":"Asia/Shanghai",
    "iso:country":"CN",
    "name:und_x_variant":[
        "\u6b66\u5bb6\u7a91"
    ],
    "wof:name":"Wujiayao",
    "wof:placetype":"locality"
},
  "geometry": {"coordinates":[112.08393,39.77267],"type":"Point"}
}