{
  "type": "Feature",
  "properties": {
    "gn:admin1_code":"5.0",
    "gn:asciiname":"Beixinglong",
    "gn:country_code":"CN",
    "gn:dem":336,
    "gn:feature_class":"P",
    "gn:feature_code":"PPL",
    "gn:name":"Beixinglong",
    "gn:population":0,
    "gn:timezone":"Asia/Shanghai",
    "iso:country":"CN",
    "name:zho_x_preferred":[
        "\u5317\u5174\u9686"
    ],
    "wof:name":"Beixinglong",
    "wof:placetype":"locality"
},
  "geometry": {"coordinates":[126.14803999999999,42.92311],"type":"Point"}
}