{
  "type": "Feature",
  "properties": {
    "gn:admin1_code":"4.0",
    "gn:asciiname":"Shiliang",
    "gn:country_code":"CN",
    "gn:dem":7,
    "gn:feature_class":"P",
    "gn:feature_code":"PPL",
    "gn:name":"Shiliang",
    "gn:population":0,
    "gn:timezone":"Asia/Shanghai",
    "iso:country":"CN",
    "name:und_x_variant":[
        "\u77f3\u826f"
    ],
    "wof:name":"Shiliang",
    "wof:placetype":"locality"
},
  "geometry": {"coordinates":[121.07550999999999,31.96301],"type":"Point"}
}