{
  "type": "Feature",
  "properties": {
    "gn:admin1_code":"32.0",
    "gn:asciiname":"Yangjiachang",
    "gn:country_code":"CN",
    "gn:dem":367,
    "gn:feature_class":"P",
    "gn:feature_code":"PPL",
    "gn:name":"Yangjiachang",
    "gn:population":0,
    "gn:timezone":"Asia/Shanghai",
    "iso:country":"CN",
    "name:zho_x_preferred":[
        "\u6768\u5bb6\u573a"
    ],
    "wof:name":"Yangjiachang",
    "wof:placetype":"locality"
},
  "geometry": {"coordinates":[105.077,30.57913],"type":"Point"}
}