{
  "type": "Feature",
  "properties": {
    "gn:admin1_code":"14.0",
    "gn:asciiname":"Chadong",
    "gn:country_code":"CN",
    "gn:dem":3274,
    "gn:feature_class":"P",
    "gn:feature_code":"PPL",
    "gn:name":"Chadong",
    "gn:population":0,
    "gn:timezone":"Asia/Urumqi",
    "iso:country":"CN",
    "name:zho_x_preferred":[
        "\u67e5\u4e1c"
    ],
    "wof:name":"Chadong",
    "wof:placetype":"locality"
},
  "geometry": {"coordinates":[98.12221,32.39781],"type":"Point"}
}