{
  "type": "Feature",
  "properties": {
    "gn:admin1_code":"29.0",
    "gn:asciiname":"Erlaba",
    "gn:country_code":"CN",
    "gn:dem":3055,
    "gn:feature_class":"P",
    "gn:feature_code":"PPL",
    "gn:name":"Erlaba",
    "gn:population":0,
    "gn:timezone":"Asia/Shanghai",
    "iso:country":"CN",
    "name:zho_x_preferred":[
        "\u4e8c\u62c9\u575d"
    ],
    "wof:name":"Erlaba",
    "wof:placetype":"locality"
},
  "geometry": {"coordinates":[101.05500000000001,27.0804],"type":"Point"}
}