{
  "type": "Feature",
  "properties": {
    "gn:admin1_code":"01",
    "gn:asciiname":"Tuqiao",
    "gn:cc2":"CN",
    "gn:country_code":"CN",
    "gn:dem":6,
    "gn:feature_class":"P",
    "gn:feature_code":"PPL",
    "gn:name":"Tuqiao",
    "gn:population":0,
    "gn:timezone":"Asia/Shanghai",
    "iso:country":"CN",
    "name:und_x_variant":[
        "T\u2019u-ch\u2019iao",
        "Tuqiao"
    ],
    "wof:name":"Tuqiao",
    "wof:placetype":"locality"
},
  "geometry": {"coordinates":[117.71666999999999,31.05],"type":"Point"}
}