{
  "type": "Feature",
  "properties": {
    "gn:admin1_code":"5.0",
    "gn:asciiname":"Qianhecun",
    "gn:country_code":"CN",
    "gn:dem":287,
    "gn:feature_class":"P",
    "gn:feature_code":"PPL",
    "gn:name":"Qianhecun",
    "gn:population":0,
    "gn:timezone":"Asia/Shanghai",
    "iso:country":"CN",
    "name:zho_x_preferred":[
        "\u524d\u6cb3\u6751"
    ],
    "wof:name":"Qianhecun",
    "wof:placetype":"locality"
},
  "geometry": {"coordinates":[129.45868000000002,43.41083],"type":"Point"}
}