{
  "type": "Feature",
  "properties": {
    "gn:admin1_code":"25",
    "gn:asciiname":"Laoshiwucun",
    "gn:country_code":"CN",
    "gn:dem":2,
    "gn:feature_class":"P",
    "gn:feature_code":"PPL",
    "gn:name":"Laoshiwucun",
    "gn:population":0,
    "gn:timezone":"Asia/Shanghai",
    "iso:country":"CN",
    "name:zho_x_preferred":[
        "\u8001\u5341\u4e94\u6751"
    ],
    "wof:name":"Laoshiwucun",
    "wof:placetype":"locality"
},
  "geometry": {"coordinates":[118.827,37.5378],"type":"Point"}
}