{
  "type": "Feature",
  "properties": {
    "gn:admin1_code":"30.0",
    "gn:asciiname":"Yangming",
    "gn:country_code":"CN",
    "gn:dem":148,
    "gn:feature_class":"P",
    "gn:feature_code":"PPLA4",
    "gn:name":"Yangming",
    "gn:population":0,
    "gn:timezone":"Asia/Shanghai",
    "iso:country":"CN",
    "name:und_x_variant":[
        "Yang-ming-chen",
        "Heping Xian",
        "Yangming",
        "\u548c\u5e73\u53bf",
        "Yangming Zhen",
        "\u9633\u660e\u9547"
    ],
    "name:zho_x_preferred":[
        "Ho-p\u2019ing-hsien"
    ],
    "name:zho_x_variant":[
        "Ho-p\u2019ing"
    ],
    "wof:name":"Yangming",
    "wof:placetype":"locality"
},
  "geometry": {"coordinates":[114.93456999999999,24.45328],"type":"Point"}
}