{
  "type": "Feature",
  "properties": {
    "gn:admin1_code":"29.0",
    "gn:asciiname":"Hechadi",
    "gn:country_code":"CN",
    "gn:dem":2151,
    "gn:feature_class":"P",
    "gn:feature_code":"PPL",
    "gn:name":"Hechadi",
    "gn:population":0,
    "gn:timezone":"Asia/Shanghai",
    "iso:country":"CN",
    "name:zho_x_preferred":[
        "\u6cb3\u5dee\u5e95"
    ],
    "wof:name":"Hechadi",
    "wof:placetype":"locality"
},
  "geometry": {"coordinates":[101.812,25.3314],"type":"Point"}
}