{
  "type": "Feature",
  "properties": {
    "gn:admin1_code":"24.0",
    "gn:asciiname":"Xilingbei",
    "gn:country_code":"CN",
    "gn:dem":1444,
    "gn:feature_class":"P",
    "gn:feature_code":"PPL",
    "gn:name":"Xilingbei",
    "gn:population":0,
    "gn:timezone":"Asia/Shanghai",
    "iso:country":"CN",
    "name:zho_x_preferred":[
        "\u897f\u5cad\u80cc"
    ],
    "wof:name":"Xilingbei",
    "wof:placetype":"locality"
},
  "geometry": {"coordinates":[113.32702999999999,36.89057],"type":"Point"}
}