{
  "type": "Feature",
  "properties": {
    "gn:admin1_code":"1.0",
    "gn:asciiname":"Mianchongcun",
    "gn:country_code":"CN",
    "gn:dem":159,
    "gn:feature_class":"P",
    "gn:feature_code":"PPL",
    "gn:name":"Mianchongcun",
    "gn:population":0,
    "gn:timezone":"Asia/Shanghai",
    "iso:country":"CN",
    "name:zho_x_preferred":[
        "\u9762\u51b2\u6751"
    ],
    "wof:name":"Mianchongcun",
    "wof:placetype":"locality"
},
  "geometry": {"coordinates":[116.01161,31.51818],"type":"Point"}
}