{
  "type": "Feature",
  "properties": {
    "gn:admin1_code":"26.0",
    "gn:asciiname":"Yangchengcun",
    "gn:country_code":"CN",
    "gn:dem":1165,
    "gn:feature_class":"P",
    "gn:feature_code":"PPL",
    "gn:name":"Yangchengcun",
    "gn:population":0,
    "gn:timezone":"Asia/Shanghai",
    "iso:country":"CN",
    "name:zho_x_preferred":[
        "\u6768\u57ce\u6751"
    ],
    "wof:name":"Yangchengcun",
    "wof:placetype":"locality"
},
  "geometry": {"coordinates":[108.74607,36.61987],"type":"Point"}
}