{
  "type": "Feature",
  "properties": {
    "gn:admin1_code":"07",
    "gn:asciiname":"Luofang",
    "gn:country_code":"CN",
    "gn:dem":427,
    "gn:feature_class":"P",
    "gn:feature_code":"PPLA4",
    "gn:name":"Luofang",
    "gn:population":0,
    "gn:timezone":"Asia/Shanghai",
    "iso:country":"CN",
    "name:und_x_variant":[
        "Lo-fang",
        "Luofang"
    ],
    "wof:name":"Luofang",
    "wof:placetype":"locality"
},
  "geometry": {"coordinates":[117.00778,25.9125],"type":"Point"}
}