{
  "type": "Feature",
  "properties": {
    "gn:admin1_code":"8.0",
    "gn:asciiname":"Laoshantou",
    "gn:country_code":"CN",
    "gn:dem":227,
    "gn:feature_class":"P",
    "gn:feature_code":"PPL",
    "gn:name":"Laoshantou",
    "gn:population":0,
    "gn:timezone":"Asia/Shanghai",
    "iso:country":"CN",
    "name:zho_x_preferred":[
        "\u8001\u5c71\u5934"
    ],
    "wof:name":"Laoshantou",
    "wof:placetype":"locality"
},
  "geometry": {"coordinates":[127.97862000000001,47.01036],"type":"Point"}
}