{
  "type": "Feature",
  "properties": {
    "gn:admin1_code":"15.0",
    "gn:asciiname":"Yangluwan",
    "gn:country_code":"CN",
    "gn:dem":1440,
    "gn:feature_class":"P",
    "gn:feature_code":"PPL",
    "gn:name":"Yangluwan",
    "gn:population":0,
    "gn:timezone":"Asia/Shanghai",
    "iso:country":"CN",
    "name:und_x_variant":[
        "\u6768\u8def\u6e7e"
    ],
    "wof:name":"Yangluwan",
    "wof:placetype":"locality"
},
  "geometry": {"coordinates":[107.52685,36.14734],"type":"Point"}
}