{
  "type": "Feature",
  "properties": {
    "gn:admin1_code":"19.0",
    "gn:asciiname":"Sunjiagou",
    "gn:country_code":"CN",
    "gn:dem":65,
    "gn:feature_class":"P",
    "gn:feature_code":"PPL",
    "gn:name":"Sunjiagou",
    "gn:population":0,
    "gn:timezone":"Asia/Shanghai",
    "iso:country":"CN",
    "name:und_x_variant":[
        "\u5b59\u5bb6\u6c9f"
    ],
    "name:zho_x_preferred":[
        "\u5b59\u5bb6\u6c9f"
    ],
    "wof:name":"Sunjiagou",
    "wof:placetype":"locality"
},
  "geometry": {"coordinates":[121.38047,41.42784],"type":"Point"}
}