{
  "type": "Feature",
  "properties": {
    "gn:admin1_code":"8.0",
    "gn:asciiname":"Jingshencun",
    "gn:country_code":"CN",
    "gn:dem":96,
    "gn:feature_class":"P",
    "gn:feature_code":"PPL",
    "gn:name":"Jingshencun",
    "gn:population":0,
    "gn:timezone":"Asia/Shanghai",
    "iso:country":"CN",
    "name:zho_x_preferred":[
        "\u7cbe\u795e\u6751"
    ],
    "wof:name":"Jingshencun",
    "wof:placetype":"locality"
},
  "geometry": {"coordinates":[131.03647000000001,46.77576],"type":"Point"}
}