{
  "type": "Feature",
  "properties": {
    "gn:admin1_code":"29.0",
    "gn:asciiname":"Jinyintang",
    "gn:country_code":"CN",
    "gn:dem":1781,
    "gn:feature_class":"P",
    "gn:feature_code":"PPL",
    "gn:name":"Jinyintang",
    "gn:population":0,
    "gn:timezone":"Asia/Shanghai",
    "iso:country":"CN",
    "name:zho_x_preferred":[
        "\u91d1\u94f6\u5858"
    ],
    "wof:name":"Jinyintang",
    "wof:placetype":"locality"
},
  "geometry": {"coordinates":[99.5475,24.4811],"type":"Point"}
}