{
  "type": "Feature",
  "properties": {
    "gn:admin1_code":"11.0",
    "gn:asciiname":"Zhuanshanpeng",
    "gn:country_code":"CN",
    "gn:dem":220,
    "gn:feature_class":"P",
    "gn:feature_code":"PPL",
    "gn:name":"Zhuanshanpeng",
    "gn:population":0,
    "gn:timezone":"Asia/Shanghai",
    "iso:country":"CN",
    "name:zho_x_preferred":[
        "Zhuanshanpeng"
    ],
    "name:zho_x_variant":[
        "\u4e13\u5c71\u68da"
    ],
    "wof:name":"Zhuanshanpeng",
    "wof:placetype":"locality"
},
  "geometry": {"coordinates":[111.09986000000001,29.97602],"type":"Point"}
}