{
  "type": "Feature",
  "properties": {
    "gn:admin1_code":"29.0",
    "gn:asciiname":"Pingtoushan",
    "gn:country_code":"CN",
    "gn:dem":1119,
    "gn:feature_class":"P",
    "gn:feature_code":"PPL",
    "gn:name":"Pingtoushan",
    "gn:population":0,
    "gn:timezone":"Asia/Shanghai",
    "iso:country":"CN",
    "name:zho_x_preferred":[
        "\u5e73\u5934\u5c71"
    ],
    "wof:name":"Pingtoushan",
    "wof:placetype":"locality"
},
  "geometry": {"coordinates":[104.22,28.3372],"type":"Point"}
}