{
  "type": "Feature",
  "properties": {
    "gn:admin1_code":"3.0",
    "gn:asciiname":"Baizhuling",
    "gn:country_code":"CN",
    "gn:dem":300,
    "gn:feature_class":"P",
    "gn:feature_code":"PPL",
    "gn:name":"Baizhuling",
    "gn:population":0,
    "gn:timezone":"Asia/Shanghai",
    "iso:country":"CN",
    "name:und_x_variant":[
        "\u767d\u7af9\u5cad"
    ],
    "wof:name":"Baizhuling",
    "wof:placetype":"locality"
},
  "geometry": {"coordinates":[115.69562000000001,26.78882],"type":"Point"}
}