{
  "type": "Feature",
  "properties": {
    "gn:admin1_code":"29.0",
    "gn:asciiname":"Xujiapo",
    "gn:country_code":"CN",
    "gn:dem":1674,
    "gn:feature_class":"P",
    "gn:feature_code":"PPL",
    "gn:name":"Xujiapo",
    "gn:population":0,
    "gn:timezone":"Asia/Shanghai",
    "iso:country":"CN",
    "name:zho_x_preferred":[
        "\u5f90\u5bb6\u5761"
    ],
    "wof:name":"Xujiapo",
    "wof:placetype":"locality"
},
  "geometry": {"coordinates":[99.2041,25.0257],"type":"Point"}
}