{
  "type": "Feature",
  "properties": {
    "gn:admin1_code":"26.0",
    "gn:asciiname":"Waiwan",
    "gn:country_code":"CN",
    "gn:dem":1469,
    "gn:feature_class":"P",
    "gn:feature_code":"PPL",
    "gn:name":"Waiwan",
    "gn:population":0,
    "gn:timezone":"Asia/Shanghai",
    "iso:country":"CN",
    "name:zho_x_preferred":[
        "\u5916\u6e7e"
    ],
    "wof:name":"Waiwan",
    "wof:placetype":"locality"
},
  "geometry": {"coordinates":[108.68398999999999,35.05875],"type":"Point"}
}