{
  "type": "Feature",
  "properties": {
    "gn:admin1_code":"07",
    "gn:asciiname":"Niugeshan",
    "gn:country_code":"CN",
    "gn:dem":718,
    "gn:feature_class":"P",
    "gn:feature_code":"PPL",
    "gn:name":"Niugeshan",
    "gn:population":0,
    "gn:timezone":"Asia/Shanghai",
    "iso:country":"CN",
    "name:zho_x_preferred":[
        "\u725b\u9694\u5c71"
    ],
    "wof:name":"Niugeshan",
    "wof:placetype":"locality"
},
  "geometry": {"coordinates":[117.39557000000001,25.46404],"type":"Point"}
}