{
  "type": "Feature",
  "properties": {
    "gn:admin1_code":"02",
    "gn:asciiname":"Changmen",
    "gn:country_code":"CN",
    "gn:dem":171,
    "gn:feature_class":"P",
    "gn:feature_code":"PPL",
    "gn:name":"Changmen",
    "gn:population":0,
    "gn:timezone":"Asia/Shanghai",
    "iso:country":"CN",
    "name:zho_x_preferred":[
        "\u5382\u95e8"
    ],
    "wof:name":"Changmen",
    "wof:placetype":"locality"
},
  "geometry": {"coordinates":[121.65465,28.34371],"type":"Point"}
}