{
  "type": "Feature",
  "properties": {
    "gn:admin1_code":"4.0",
    "gn:asciiname":"Weijia'ao",
    "gn:country_code":"CN",
    "gn:dem":23,
    "gn:feature_class":"P",
    "gn:feature_code":"PPL",
    "gn:name":"Weijia\u2019ao",
    "gn:population":0,
    "gn:timezone":"Asia/Shanghai",
    "iso:country":"CN",
    "name:und_x_variant":[
        "Weijia\u2019ao"
    ],
    "name:zho_x_preferred":[
        "\u9b4f\u5bb6\u51f9"
    ],
    "wof:name":"Weijia'ao",
    "wof:placetype":"locality"
},
  "geometry": {"coordinates":[119.13281000000001,32.3374],"type":"Point"}
}