{
  "type": "Feature",
  "properties": {
    "gn:admin1_code":"1.0",
    "gn:asciiname":"Gunlongcun",
    "gn:country_code":"CN",
    "gn:dem":45,
    "gn:feature_class":"P",
    "gn:feature_code":"PPL",
    "gn:name":"Gunlongcun",
    "gn:population":0,
    "gn:timezone":"Asia/Shanghai",
    "iso:country":"CN",
    "name:zho_x_preferred":[
        "\u6eda\u9f99\u6751"
    ],
    "wof:name":"Gunlongcun",
    "wof:placetype":"locality"
},
  "geometry": {"coordinates":[116.22615999999999,32.01172],"type":"Point"}
}