{
  "type": "Feature",
  "properties": {
    "gn:admin1_code":"30",
    "gn:asciiname":"Changxing",
    "gn:country_code":"CN",
    "gn:dem":7,
    "gn:feature_class":"P",
    "gn:feature_code":"PPL",
    "gn:name":"Changxing",
    "gn:population":0,
    "gn:timezone":"Asia/Urumqi",
    "iso:country":"CN",
    "name:zho_x_preferred":[
        "\u957f\u5174"
    ],
    "wof:name":"Changxing",
    "wof:placetype":"locality"
},
  "geometry": {"coordinates":[110.52777,21.13726],"type":"Point"}
}