{
  "type": "Feature",
  "properties": {
    "gn:admin1_code":"16.0",
    "gn:asciiname":"Lalun",
    "gn:country_code":"CN",
    "gn:dem":632,
    "gn:feature_class":"P",
    "gn:feature_code":"PPL",
    "gn:name":"Lalun",
    "gn:population":0,
    "gn:timezone":"Asia/Shanghai",
    "iso:country":"CN",
    "name:zho_x_preferred":[
        "\u62c9\u4f26"
    ],
    "wof:name":"Lalun",
    "wof:placetype":"locality"
},
  "geometry": {"coordinates":[107.084,24.6306],"type":"Point"}
}