{
  "type": "Feature",
  "properties": {
    "gn:admin1_code":"24.0",
    "gn:asciiname":"Xinmaying",
    "gn:country_code":"CN",
    "gn:dem":1035,
    "gn:feature_class":"P",
    "gn:feature_code":"PPL",
    "gn:name":"Xinmaying",
    "gn:population":0,
    "gn:timezone":"Asia/Shanghai",
    "iso:country":"CN",
    "name:und_x_variant":[
        "\u65b0\u9a6c\u8425"
    ],
    "wof:name":"Xinmaying",
    "wof:placetype":"locality"
},
  "geometry": {"coordinates":[113.00053,39.39105],"type":"Point"}
}