{
  "type": "Feature",
  "properties": {
    "gn:admin1_code":"19.0",
    "gn:asciiname":"Shirengou",
    "gn:country_code":"CN",
    "gn:dem":416,
    "gn:feature_class":"P",
    "gn:feature_code":"PPL",
    "gn:name":"Shirengou",
    "gn:population":0,
    "gn:timezone":"Asia/Shanghai",
    "iso:country":"CN",
    "name:und_x_variant":[
        "\u77f3\u4eba\u6c9f"
    ],
    "wof:name":"Shirengou",
    "wof:placetype":"locality"
},
  "geometry": {"coordinates":[124.53657,41.63645],"type":"Point"}
}