{
  "type": "Feature",
  "properties": {
    "gn:admin1_code":"28",
    "gn:asciiname":"Dasuzhuang",
    "gn:cc2":"CN",
    "gn:country_code":"CN",
    "gn:dem":4,
    "gn:feature_class":"P",
    "gn:feature_code":"PPL",
    "gn:name":"Dasuzhuang",
    "gn:population":0,
    "gn:timezone":"Asia/Shanghai",
    "iso:country":"CN",
    "name:und_x_variant":[
        "Ta-su-chuang",
        "T\u2019ai-su-chuang",
        "Taisuzhuang",
        "Dasuzhuang"
    ],
    "wof:name":"Dasuzhuang",
    "wof:placetype":"locality"
},
  "geometry": {"coordinates":[117.29111,38.66611],"type":"Point"}
}