{
  "type": "Feature",
  "properties": {
    "gn:admin1_code":"22.0",
    "gn:asciiname":"Shihu Xiacun",
    "gn:country_code":"CN",
    "gn:dem":202,
    "gn:feature_class":"P",
    "gn:feature_code":"PPL",
    "gn:name":"Shihu Xiacun",
    "gn:population":0,
    "gn:timezone":"Asia/Shanghai",
    "iso:country":"CN",
    "name:zho_x_preferred":[
        "\u77f3\u6e56\u4e0b\u6751"
    ],
    "wof:name":"Shihu Xiacun",
    "wof:placetype":"locality"
},
  "geometry": {"coordinates":[116.90743999999999,40.58839],"type":"Point"}
}