{
  "type": "Feature",
  "properties": {
    "gn:admin1_code":"18",
    "gn:asciiname":"Machong",
    "gn:country_code":"CN",
    "gn:dem":1852,
    "gn:feature_class":"P",
    "gn:feature_code":"PPL",
    "gn:name":"Machong",
    "gn:population":0,
    "gn:timezone":"Asia/Shanghai",
    "iso:country":"CN",
    "name:zho_x_preferred":[
        "\u9ebb\u51b2"
    ],
    "wof:name":"Machong",
    "wof:placetype":"locality"
},
  "geometry": {"coordinates":[105.458,27.0468],"type":"Point"}
}