{
  "type": "Feature",
  "properties": {
    "gn:admin1_code":"19.0",
    "gn:asciiname":"Xiaogaojiatun",
    "gn:country_code":"CN",
    "gn:dem":21,
    "gn:feature_class":"P",
    "gn:feature_code":"PPL",
    "gn:name":"Xiaogaojiatun",
    "gn:population":0,
    "gn:timezone":"Asia/Shanghai",
    "iso:country":"CN",
    "name:zho_x_preferred":[
        "\u5c0f\u9ad8\u5bb6\u5c6f"
    ],
    "wof:name":"Xiaogaojiatun",
    "wof:placetype":"locality"
},
  "geometry": {"coordinates":[121.551,39.5028],"type":"Point"}
}