{
  "type": "Feature",
  "properties": {
    "gn:admin1_code":"12.0",
    "gn:asciiname":"Tudigang",
    "gn:country_code":"CN",
    "gn:dem":38,
    "gn:feature_class":"P",
    "gn:feature_code":"PPL",
    "gn:name":"Tudigang",
    "gn:population":0,
    "gn:timezone":"Asia/Shanghai",
    "iso:country":"CN",
    "name:zho_x_preferred":[
        "Tudigang"
    ],
    "name:zho_x_variant":[
        "\u571f\u5730\u5c97"
    ],
    "wof:name":"Tudigang",
    "wof:placetype":"locality"
},
  "geometry": {"coordinates":[112.06196,29.75794],"type":"Point"}
}