{
  "type": "Feature",
  "properties": {
    "gn:admin1_code":"18.0",
    "gn:asciiname":"Lengshuihe",
    "gn:country_code":"CN",
    "gn:dem":1024,
    "gn:feature_class":"P",
    "gn:feature_code":"PPL",
    "gn:name":"Lengshuihe",
    "gn:population":0,
    "gn:timezone":"Asia/Shanghai",
    "iso:country":"CN",
    "name:zho_x_preferred":[
        "\u51b7\u6c34\u6cb3"
    ],
    "wof:name":"Lengshuihe",
    "wof:placetype":"locality"
},
  "geometry": {"coordinates":[107.255,26.5777],"type":"Point"}
}