{
  "type": "Feature",
  "properties": {
    "gn:admin1_code":"23.0",
    "gn:asciiname":"Yaogangxing",
    "gn:country_code":"CN",
    "gn:dem":6,
    "gn:feature_class":"P",
    "gn:feature_code":"PPL",
    "gn:name":"Yaogangxing",
    "gn:population":0,
    "gn:timezone":"Asia/Shanghai",
    "iso:country":"CN",
    "name:und_x_variant":[
        "\u59da\u6e2f\u884c"
    ],
    "wof:name":"Yaogangxing",
    "wof:placetype":"locality"
},
  "geometry": {"coordinates":[121.4349,30.90779],"type":"Point"}
}