{
  "type": "Feature",
  "properties": {
    "gn:admin1_code":"14",
    "gn:asciiname":"Cogu",
    "gn:country_code":"CN",
    "gn:dem":3811,
    "gn:feature_class":"P",
    "gn:feature_code":"PPL",
    "gn:name":"Cogu",
    "gn:population":0,
    "gn:timezone":"Asia/Urumqi",
    "iso:country":"CN",
    "name:bod_x_preferred":[
        "\u0f58\u0f5a\u0f7c\u0f0b\u0f51\u0f42\u0f74"
    ],
    "name:und_x_variant":[
        "Cuogu"
    ],
    "name:zho_x_preferred":[
        "\u63aa\u53e4"
    ],
    "wof:name":"Cogu",
    "wof:placetype":"locality"
},
  "geometry": {"coordinates":[92.51621,28.95739],"type":"Point"}
}