{
  "type": "Feature",
  "properties": {
    "gn:admin1_code":"8.0",
    "gn:asciiname":"Shihugoucun",
    "gn:country_code":"CN",
    "gn:dem":178,
    "gn:feature_class":"P",
    "gn:feature_code":"PPL",
    "gn:name":"Shihugoucun",
    "gn:population":0,
    "gn:timezone":"Asia/Shanghai",
    "iso:country":"CN",
    "name:zho_x_preferred":[
        "\u77f3\u864e\u6c9f\u6751"
    ],
    "wof:name":"Shihugoucun",
    "wof:placetype":"locality"
},
  "geometry": {"coordinates":[130.7841,47.89765],"type":"Point"}
}