{
  "type": "Feature",
  "properties": {
    "gn:admin1_code":"12.0",
    "gn:asciiname":"Hongjiawan",
    "gn:country_code":"CN",
    "gn:dem":1248,
    "gn:feature_class":"P",
    "gn:feature_code":"PPL",
    "gn:name":"Hongjiawan",
    "gn:population":0,
    "gn:timezone":"Asia/Shanghai",
    "iso:country":"CN",
    "name:zho_x_preferred":[
        "Hongjiawan"
    ],
    "name:zho_x_variant":[
        "\u6d2a\u5bb6\u6e7e"
    ],
    "wof:name":"Hongjiawan",
    "wof:placetype":"locality"
},
  "geometry": {"coordinates":[109.73841000000002,29.74039],"type":"Point"}
}