{
  "type": "Feature",
  "properties": {
    "gn:admin1_code":"30",
    "gn:asciiname":"Lintou",
    "gn:country_code":"CN",
    "gn:dem":23,
    "gn:feature_class":"P",
    "gn:feature_code":"PPLA4",
    "gn:name":"Lintou",
    "gn:population":0,
    "gn:timezone":"Asia/Urumqi",
    "iso:country":"CN",
    "name:und_x_variant":[
        "Lin-t\u2019ou",
        "Lin-t\u2019ou-hs\u00fc",
        "Lintouxu",
        "Lintou",
        "Lintou Zhen",
        "\u6797\u5934\u9547"
    ],
    "name:zho_x_preferred":[
        "\u6797\u5934"
    ],
    "wof:name":"Lintou",
    "wof:placetype":"locality"
},
  "geometry": {"coordinates":[111.04864999999999,21.66572],"type":"Point"}
}