{
  "type": "Feature",
  "properties": {
    "gn:admin1_code":"29.0",
    "gn:asciiname":"Yihei",
    "gn:country_code":"CN",
    "gn:dem":2087,
    "gn:feature_class":"P",
    "gn:feature_code":"PPL",
    "gn:name":"Yihei",
    "gn:population":0,
    "gn:timezone":"Asia/Shanghai",
    "iso:country":"CN",
    "name:zho_x_preferred":[
        "\u8fe4\u9ed1"
    ],
    "wof:name":"Yihei",
    "wof:placetype":"locality"
},
  "geometry": {"coordinates":[104.245,25.4338],"type":"Point"}
}