{
  "type": "Feature",
  "properties": {
    "gn:admin1_code":"4.0",
    "gn:asciiname":"Yuanxiaocun",
    "gn:country_code":"CN",
    "gn:dem":28,
    "gn:feature_class":"P",
    "gn:feature_code":"PPL",
    "gn:name":"Yuanxiaocun",
    "gn:population":0,
    "gn:timezone":"Asia/Shanghai",
    "iso:country":"CN",
    "name:zho_x_preferred":[
        "\u8881\u8096\u6751"
    ],
    "wof:name":"Yuanxiaocun",
    "wof:placetype":"locality"
},
  "geometry": {"coordinates":[117.79327000000001,33.7951],"type":"Point"}
}