{
  "type": "Feature",
  "properties": {
    "gn:admin1_code":"25",
    "gn:asciiname":"Houjiagou",
    "gn:country_code":"CN",
    "gn:dem":107,
    "gn:feature_class":"P",
    "gn:feature_code":"PPL",
    "gn:name":"Houjiagou",
    "gn:population":0,
    "gn:timezone":"Asia/Shanghai",
    "iso:country":"CN",
    "name:und_x_variant":[
        "\u4faf\u5bb6\u6c9f"
    ],
    "wof:name":"Houjiagou",
    "wof:placetype":"locality"
},
  "geometry": {"coordinates":[119.16285999999999,35.42263],"type":"Point"}
}