{
  "type": "Feature",
  "properties": {
    "gn:admin1_code":"4.0",
    "gn:asciiname":"Jiangqiao",
    "gn:country_code":"CN",
    "gn:dem":1,
    "gn:feature_class":"P",
    "gn:feature_code":"PPL",
    "gn:name":"Jiangqiao",
    "gn:population":0,
    "gn:timezone":"Asia/Shanghai",
    "iso:country":"CN",
    "name:zho_x_preferred":[
        "Jiangqiao"
    ],
    "name:zho_x_variant":[
        "\u848b\u6865"
    ],
    "wof:name":"Jiangqiao",
    "wof:placetype":"locality"
},
  "geometry": {"coordinates":[119.7595,33.63025],"type":"Point"}
}