{
  "type": "Feature",
  "properties": {
    "gn:admin1_code":"29.0",
    "gn:asciiname":"Sanguozhuang",
    "gn:country_code":"CN",
    "gn:dem":1420,
    "gn:feature_class":"P",
    "gn:feature_code":"PPL",
    "gn:name":"Sanguozhuang",
    "gn:population":0,
    "gn:timezone":"Asia/Shanghai",
    "iso:country":"CN",
    "name:zho_x_preferred":[
        "\u4e09\u9505\u6869"
    ],
    "wof:name":"Sanguozhuang",
    "wof:placetype":"locality"
},
  "geometry": {"coordinates":[104.577,27.7176],"type":"Point"}
}