{
  "type": "Feature",
  "properties": {
    "gn:admin1_code":"26.0",
    "gn:asciiname":"Xiachangxi",
    "gn:country_code":"CN",
    "gn:dem":1103,
    "gn:feature_class":"P",
    "gn:feature_code":"PPL",
    "gn:name":"Xiachangxi",
    "gn:population":0,
    "gn:timezone":"Asia/Shanghai",
    "iso:country":"CN",
    "name:zho_x_preferred":[
        "\u4e0b\u660c\u559c"
    ],
    "wof:name":"Xiachangxi",
    "wof:placetype":"locality"
},
  "geometry": {"coordinates":[110.0415,36.15604],"type":"Point"}
}