{
  "type": "Feature",
  "properties": {
    "gn:admin1_code":"19",
    "gn:asciiname":"Ch'eng-t'ou",
    "gn:country_code":"CN",
    "gn:dem":268,
    "gn:feature_class":"P",
    "gn:feature_code":"PPL",
    "gn:name":"Ch\u2019eng-t\u2019ou",
    "gn:population":0,
    "gn:timezone":"Asia/Shanghai",
    "iso:country":"CN",
    "wof:name":"Ch'eng-t'ou",
    "wof:placetype":"locality"
},
  "geometry": {"coordinates":[125.21861,41.19972],"type":"Point"}
}