{
  "type": "Feature",
  "properties": {
    "gn:admin1_code":"24.0",
    "gn:asciiname":"Zhanli",
    "gn:country_code":"CN",
    "gn:dem":521,
    "gn:feature_class":"P",
    "gn:feature_code":"PPL",
    "gn:name":"Zhanli",
    "gn:population":0,
    "gn:timezone":"Asia/Shanghai",
    "iso:country":"CN",
    "name:und_x_variant":[
        "\u7ad9\u674e"
    ],
    "wof:name":"Zhanli",
    "wof:placetype":"locality"
},
  "geometry": {"coordinates":[111.29707999999999,35.87158],"type":"Point"}
}