{
  "type": "Feature",
  "properties": {
    "gn:admin1_code":"19.0",
    "gn:asciiname":"Sifangtai",
    "gn:country_code":"CN",
    "gn:dem":77,
    "gn:feature_class":"P",
    "gn:feature_code":"PPL",
    "gn:name":"Sifangtai",
    "gn:population":0,
    "gn:timezone":"Asia/Shanghai",
    "iso:country":"CN",
    "name:und_x_variant":[
        "\u56db\u82b3\u53f0"
    ],
    "name:zho_x_preferred":[
        "\u56db\u82b3\u53f0"
    ],
    "wof:name":"Sifangtai",
    "wof:placetype":"locality"
},
  "geometry": {"coordinates":[122.06819,41.95475],"type":"Point"}
}