{
  "type": "Feature",
  "properties": {
    "gn:admin1_code":"15.0",
    "gn:asciiname":"Fengyangqu",
    "gn:country_code":"CN",
    "gn:dem":1571,
    "gn:feature_class":"P",
    "gn:feature_code":"PPL",
    "gn:name":"Fengyangqu",
    "gn:population":0,
    "gn:timezone":"Asia/Shanghai",
    "iso:country":"CN",
    "name:und_x_variant":[
        "\u51af\u9633\u6e20"
    ],
    "wof:name":"Fengyangqu",
    "wof:placetype":"locality"
},
  "geometry": {"coordinates":[107.06686999999999,36.93474000000001],"type":"Point"}
}