{
  "type": "Feature",
  "properties": {
    "gn:admin1_code":"10",
    "gn:asciiname":"Fengzhou",
    "gn:cc2":"CN",
    "gn:country_code":"CN",
    "gn:dem":33,
    "gn:feature_class":"P",
    "gn:feature_code":"PPL",
    "gn:name":"Fengzhou",
    "gn:population":0,
    "gn:timezone":"Asia/Shanghai",
    "iso:country":"CN",
    "name:und_x_variant":[
        "Pingxiang",
        "Qicun",
        "P\u2019ing-hsiang",
        "Ch\u2019i-tsun",
        "Fengzhou"
    ],
    "wof:name":"Fengzhou",
    "wof:placetype":"locality"
},
  "geometry": {"coordinates":[115.02472,37.06278],"type":"Point"}
}