{
  "type": "Feature",
  "properties": {
    "gn:admin1_code":"10",
    "gn:asciiname":"Hualougou",
    "gn:country_code":"CN",
    "gn:dem":1039,
    "gn:feature_class":"P",
    "gn:feature_code":"PPL",
    "gn:name":"Hualougou",
    "gn:population":0,
    "gn:timezone":"Asia/Shanghai",
    "iso:country":"CN",
    "name:zho_x_preferred":[
        "\u82b1\u697c\u6c9f"
    ],
    "wof:name":"Hualougou",
    "wof:placetype":"locality"
},
  "geometry": {"coordinates":[116.07001,40.91569000000001],"type":"Point"}
}