{
  "type": "Feature",
  "properties": {
    "gn:admin1_code":"9",
    "gn:asciiname":"Lidanzhuang",
    "gn:country_code":"CN",
    "gn:dem":33,
    "gn:feature_class":"P",
    "gn:feature_code":"PPL",
    "gn:name":"Lidanzhuang",
    "gn:population":0,
    "gn:timezone":"Asia/Shanghai",
    "iso:country":"CN",
    "name:zho_x_preferred":[
        "\u674e\u5355\u5e84"
    ],
    "wof:name":"Lidanzhuang",
    "wof:placetype":"locality"
},
  "geometry": {"coordinates":[116.327,33.8135],"type":"Point"}
}