{
  "type": "Feature",
  "properties": {
    "gn:admin1_code":"8.0",
    "gn:asciiname":"Xuguangcun",
    "gn:country_code":"CN",
    "gn:dem":174,
    "gn:feature_class":"P",
    "gn:feature_code":"PPL",
    "gn:name":"Xuguangcun",
    "gn:population":0,
    "gn:timezone":"Asia/Shanghai",
    "iso:country":"CN",
    "name:zho_x_preferred":[
        "\u65ed\u5149\u6751"
    ],
    "wof:name":"Xuguangcun",
    "wof:placetype":"locality"
},
  "geometry": {"coordinates":[126.12336999999999,45.43265],"type":"Point"}
}