{
  "type": "Feature",
  "properties": {
    "gn:admin1_code":"6.0",
    "gn:asciiname":"Dajieqie",
    "gn:country_code":"CN",
    "gn:dem":2902,
    "gn:feature_class":"P",
    "gn:feature_code":"PPL",
    "gn:name":"Dajieqie",
    "gn:population":0,
    "gn:timezone":"Asia/Shanghai",
    "iso:country":"CN",
    "name:zho_x_preferred":[
        "\u8fbe\u6770\u5207"
    ],
    "wof:name":"Dajieqie",
    "wof:placetype":"locality"
},
  "geometry": {"coordinates":[101.2222,36.19042],"type":"Point"}
}