{
  "type": "Feature",
  "properties": {
    "gn:admin1_code":"19.0",
    "gn:asciiname":"Renjiatun",
    "gn:country_code":"CN",
    "gn:dem":18,
    "gn:feature_class":"P",
    "gn:feature_code":"PPL",
    "gn:name":"Renjiatun",
    "gn:population":0,
    "gn:timezone":"Asia/Shanghai",
    "iso:country":"CN",
    "name:zho_x_preferred":[
        "\u4efb\u5bb6\u5c6f"
    ],
    "wof:name":"Renjiatun",
    "wof:placetype":"locality"
},
  "geometry": {"coordinates":[122.874,39.7162],"type":"Point"}
}