{
  "type": "Feature",
  "properties": {
    "gn:admin1_code":"8.0",
    "gn:asciiname":"Benloutou Yangfengchang",
    "gn:country_code":"CN",
    "gn:dem":351,
    "gn:feature_class":"P",
    "gn:feature_code":"PPLF",
    "gn:name":"Benloutou Yangfengchang",
    "gn:population":0,
    "gn:timezone":"Asia/Shanghai",
    "iso:country":"CN",
    "name:und_x_variant":[
        "\u5954\u697c\u5934\u517b\u8702\u573a"
    ],
    "wof:name":"Benloutou Yangfengchang",
    "wof:placetype":"locality"
},
  "geometry": {"coordinates":[130.76766000000001,43.89436],"type":"Point"}
}