{
  "type": "Feature",
  "properties": {
    "gn:admin1_code":"26",
    "gn:asciiname":"Fanjiazhai",
    "gn:country_code":"CN",
    "gn:dem":386,
    "gn:feature_class":"P",
    "gn:feature_code":"PPL",
    "gn:name":"Fanjiazhai",
    "gn:population":0,
    "gn:timezone":"Asia/Shanghai",
    "iso:country":"CN",
    "wof:name":"Fanjiazhai",
    "wof:placetype":"locality"
},
  "geometry": {"coordinates":[108.9025,34.32222],"type":"Point"}
}