{
  "type": "Feature",
  "properties": {
    "gn:admin1_code":"13.0",
    "gn:asciiname":"Xian Yangchang",
    "gn:country_code":"CN",
    "gn:dem":2620,
    "gn:feature_class":"P",
    "gn:feature_code":"PPLF",
    "gn:name":"Xian Yangchang",
    "gn:population":0,
    "gn:timezone":"Asia/Shanghai",
    "iso:country":"CN",
    "wof:name":"Xian Yangchang",
    "wof:placetype":"locality"
},
  "geometry": {"coordinates":[81.50333000000001,36.24139],"type":"Point"}
}