{
  "type": "Feature",
  "properties": {
    "gn:admin1_code":"7.0",
    "gn:asciiname":"Fuwu",
    "gn:country_code":"CN",
    "gn:dem":344,
    "gn:feature_class":"P",
    "gn:feature_code":"PPL",
    "gn:name":"Fuwu",
    "gn:population":0,
    "gn:timezone":"Asia/Shanghai",
    "iso:country":"CN",
    "name:und_x_variant":[
        "\u4ed8\u5c4b"
    ],
    "name:zho_x_preferred":[
        "\u4ed8\u5c4b"
    ],
    "wof:name":"Fuwu",
    "wof:placetype":"locality"
},
  "geometry": {"coordinates":[116.52992999999999,25.64334],"type":"Point"}
}