{
  "type": "Feature",
  "properties": {
    "gn:admin1_code":"15.0",
    "gn:asciiname":"Cuijia Jingzi",
    "gn:country_code":"CN",
    "gn:dem":1042,
    "gn:feature_class":"P",
    "gn:feature_code":"PPL",
    "gn:name":"Cuijia Jingzi",
    "gn:population":0,
    "gn:timezone":"Asia/Urumqi",
    "iso:country":"CN",
    "name:zho_x_preferred":[
        "\u5d14\u5bb6\u4e95\u5b50"
    ],
    "wof:name":"Cuijia Jingzi",
    "wof:placetype":"locality"
},
  "geometry": {"coordinates":[94.4843,40.4594],"type":"Point"}
}