{
  "type": "Feature",
  "properties": {
    "gn:admin1_code":"19.0",
    "gn:asciiname":"Xiaowulagou",
    "gn:country_code":"CN",
    "gn:dem":721,
    "gn:feature_class":"P",
    "gn:feature_code":"PPL",
    "gn:name":"Xiaowulagou",
    "gn:population":0,
    "gn:timezone":"Asia/Shanghai",
    "iso:country":"CN",
    "name:zho_x_preferred":[
        "\u5c0f\u52ff\u62c9\u6c9f"
    ],
    "wof:name":"Xiaowulagou",
    "wof:placetype":"locality"
},
  "geometry": {"coordinates":[119.81789999999999,41.70267],"type":"Point"}
}