{
  "type": "Feature",
  "properties": {
    "gn:admin1_code":"9",
    "gn:asciiname":"Xilanxi",
    "gn:country_code":"CN",
    "gn:dem":57,
    "gn:feature_class":"P",
    "gn:feature_code":"PPL",
    "gn:name":"Xilanxi",
    "gn:population":0,
    "gn:timezone":"Asia/Shanghai",
    "iso:country":"CN",
    "name:zho_x_preferred":[
        "\u897f\u5170\u6eaa"
    ],
    "wof:name":"Xilanxi",
    "wof:placetype":"locality"
},
  "geometry": {"coordinates":[115.24755,35.51652],"type":"Point"}
}