{
  "type": "Feature",
  "properties": {
    "gn:admin1_code":"33.0",
    "gn:asciiname":"Xuanshui",
    "gn:country_code":"CN",
    "gn:dem":872,
    "gn:feature_class":"P",
    "gn:feature_code":"PPL",
    "gn:name":"Xuanshui",
    "gn:population":0,
    "gn:timezone":"Asia/Shanghai",
    "iso:country":"CN",
    "name:zho_x_preferred":[
        "\u65cb\u6c34"
    ],
    "wof:name":"Xuanshui",
    "wof:placetype":"locality"
},
  "geometry": {"coordinates":[108.97441999999999,31.4206],"type":"Point"}
}