{
  "type": "Feature",
  "properties": {
    "gn:admin1_code":"5.0",
    "gn:asciiname":"Lijia Wazi",
    "gn:country_code":"CN",
    "gn:dem":239,
    "gn:feature_class":"P",
    "gn:feature_code":"PPL",
    "gn:name":"Lijia Wazi",
    "gn:population":0,
    "gn:timezone":"Asia/Shanghai",
    "iso:country":"CN",
    "name:zho_x_preferred":[
        "\u674e\u5bb6\u6d3c\u5b50"
    ],
    "wof:name":"Lijia Wazi",
    "wof:placetype":"locality"
},
  "geometry": {"coordinates":[125.42486,43.76604],"type":"Point"}
}