{
  "type": "Feature",
  "properties": {
    "gn:admin1_code":"30.0",
    "gn:asciiname":"Lixingcun",
    "gn:country_code":"CN",
    "gn:dem":23,
    "gn:feature_class":"P",
    "gn:feature_code":"PPL",
    "gn:name":"Lixingcun",
    "gn:population":0,
    "gn:timezone":"Asia/Shanghai",
    "iso:country":"CN",
    "name:und_x_variant":[
        "Lixing"
    ],
    "name:zho_x_preferred":[
        "\u91cc\u884c\u6751"
    ],
    "name:zho_x_variant":[
        "\u91cc\u884c"
    ],
    "wof:name":"Lixingcun",
    "wof:placetype":"locality"
},
  "geometry": {"coordinates":[116.46732,23.07091],"type":"Point"}
}