{
  "type": "Feature",
  "properties": {
    "gn:admin1_code":"19",
    "gn:asciiname":"Pei-hsin-ching",
    "gn:country_code":"CN",
    "gn:dem":515,
    "gn:feature_class":"P",
    "gn:feature_code":"PPL",
    "gn:name":"Pei-hsin-ching",
    "gn:population":0,
    "gn:timezone":"Asia/Shanghai",
    "iso:country":"CN",
    "wof:name":"Pei-hsin-ching",
    "wof:placetype":"locality"
},
  "geometry": {"coordinates":[119.44861000000002,42.2675],"type":"Point"}
}