{
  "type": "Feature",
  "properties": {
    "gn:admin1_code":"30.0",
    "gn:asciiname":"Shikeng",
    "gn:country_code":"CN",
    "gn:dem":746,
    "gn:feature_class":"P",
    "gn:feature_code":"PPL",
    "gn:name":"Shikeng",
    "gn:population":0,
    "gn:timezone":"Asia/Shanghai",
    "iso:country":"CN",
    "name:zho_x_preferred":[
        "Shikeng"
    ],
    "name:zho_x_variant":[
        "\u77f3\u5751"
    ],
    "wof:name":"Shikeng",
    "wof:placetype":"locality"
},
  "geometry": {"coordinates":[113.05052999999999,24.90056],"type":"Point"}
}