{
  "type": "Feature",
  "properties": {
    "gn:admin1_code":"16.0",
    "gn:asciiname":"Pansang",
    "gn:country_code":"CN",
    "gn:dem":1063,
    "gn:feature_class":"P",
    "gn:feature_code":"PPL",
    "gn:name":"Pansang",
    "gn:population":0,
    "gn:timezone":"Asia/Shanghai",
    "iso:country":"CN",
    "name:zho_x_preferred":[
        "\u76d8\u6851"
    ],
    "wof:name":"Pansang",
    "wof:placetype":"locality"
},
  "geometry": {"coordinates":[105.273,24.8568],"type":"Point"}
}