{
  "type": "Feature",
  "properties": {
    "gn:admin1_code":"24.0",
    "gn:asciiname":"Shijiadian",
    "gn:country_code":"CN",
    "gn:dem":834,
    "gn:feature_class":"P",
    "gn:feature_code":"PPL",
    "gn:name":"Shijiadian",
    "gn:population":0,
    "gn:timezone":"Asia/Shanghai",
    "iso:country":"CN",
    "name:zho_x_preferred":[
        "\u77f3\u5bb6\u5e97"
    ],
    "wof:name":"Shijiadian",
    "wof:placetype":"locality"
},
  "geometry": {"coordinates":[111.56177,36.67534000000001],"type":"Point"}
}