{
  "type": "Feature",
  "properties": {
    "gn:admin1_code":"8.0",
    "gn:asciiname":"Dongjincun",
    "gn:country_code":"CN",
    "gn:dem":275,
    "gn:feature_class":"P",
    "gn:feature_code":"PPL",
    "gn:name":"Dongjincun",
    "gn:population":0,
    "gn:timezone":"Asia/Shanghai",
    "iso:country":"CN",
    "name:zho_x_preferred":[
        "\u4e1c\u8fdb\u6751"
    ],
    "wof:name":"Dongjincun",
    "wof:placetype":"locality"
},
  "geometry": {"coordinates":[129.43996999999999,44.23247],"type":"Point"}
}