{
  "type": "Feature",
  "properties": {
    "gn:admin1_code":"24",
    "gn:asciiname":"Peihui",
    "gn:country_code":"CN",
    "gn:dem":743,
    "gn:feature_class":"P",
    "gn:feature_code":"PPL",
    "gn:name":"Peihui",
    "gn:population":0,
    "gn:timezone":"Asia/Shanghai",
    "iso:country":"CN",
    "wof:name":"Peihui",
    "wof:placetype":"locality"
},
  "geometry": {"coordinates":[112.01027999999999,37.29083],"type":"Point"}
}