{
  "type": "Feature",
  "properties": {
    "gn:admin1_code":"16",
    "gn:asciiname":"Pinghuang",
    "gn:country_code":"CN",
    "gn:dem":265,
    "gn:feature_class":"P",
    "gn:feature_code":"PPL",
    "gn:name":"Pinghuang",
    "gn:population":0,
    "gn:timezone":"Asia/Shanghai",
    "iso:country":"CN",
    "name:zho_x_preferred":[
        "\u5e73\u9ec4"
    ],
    "wof:name":"Pinghuang",
    "wof:placetype":"locality"
},
  "geometry": {"coordinates":[109.92400000000001,25.9129],"type":"Point"}
}