{
  "type": "Feature",
  "properties": {
    "gn:admin1_code":"8.0",
    "gn:asciiname":"Zhaocaitun",
    "gn:country_code":"CN",
    "gn:dem":143,
    "gn:feature_class":"P",
    "gn:feature_code":"PPL",
    "gn:name":"Zhaocaitun",
    "gn:population":0,
    "gn:timezone":"Asia/Shanghai",
    "iso:country":"CN",
    "name:zho_x_preferred":[
        "\u8d75\u624d\u5c6f"
    ],
    "wof:name":"Zhaocaitun",
    "wof:placetype":"locality"
},
  "geometry": {"coordinates":[127.92025,46.12973],"type":"Point"}
}