{
  "type": "Feature",
  "properties": {
    "gn:admin1_code":"30",
    "gn:asciiname":"Tazixia",
    "gn:country_code":"CN",
    "gn:dem":99,
    "gn:feature_class":"P",
    "gn:feature_code":"PPL",
    "gn:name":"Tazixia",
    "gn:population":0,
    "gn:timezone":"Asia/Shanghai",
    "iso:country":"CN",
    "name:zho_x_preferred":[
        "\u5854\u5b50\u4e0b"
    ],
    "wof:name":"Tazixia",
    "wof:placetype":"locality"
},
  "geometry": {"coordinates":[116.34175999999999,24.53276],"type":"Point"}
}