{
  "type": "Feature",
  "properties": {
    "gn:admin1_code":"11",
    "gn:asciiname":"Daju",
    "gn:country_code":"CN",
    "gn:dem":359,
    "gn:feature_class":"P",
    "gn:feature_code":"PPL",
    "gn:name":"Daju",
    "gn:population":0,
    "gn:timezone":"Asia/Shanghai",
    "iso:country":"CN",
    "name:und_x_variant":[
        "\u5927\u7820",
        "Daju"
    ],
    "wof:name":"Daju",
    "wof:placetype":"locality"
},
  "geometry": {"coordinates":[112.04389,25.64722],"type":"Point"}
}