{
  "type": "Feature",
  "properties": {
    "gn:admin1_code":"10.0",
    "gn:asciiname":"Dongsangengsheng",
    "gn:country_code":"CN",
    "gn:dem":26,
    "gn:feature_class":"P",
    "gn:feature_code":"PPL",
    "gn:name":"Dongsangengsheng",
    "gn:population":0,
    "gn:timezone":"Asia/Shanghai",
    "iso:country":"CN",
    "name:zho_x_preferred":[
        "\u4e1c\u4e09\u66f4\u751f"
    ],
    "wof:name":"Dongsangengsheng",
    "wof:placetype":"locality"
},
  "geometry": {"coordinates":[116.5258,39.47636],"type":"Point"}
}