{
  "type": "Feature",
  "properties": {
    "gn:admin1_code":"16.0",
    "gn:asciiname":"Shangdagu",
    "gn:country_code":"CN",
    "gn:dem":94,
    "gn:feature_class":"P",
    "gn:feature_code":"PPL",
    "gn:name":"Shangdagu",
    "gn:population":0,
    "gn:timezone":"Asia/Shanghai",
    "iso:country":"CN",
    "name:zho_x_preferred":[
        "\u4e0a\u6253\u53e4"
    ],
    "wof:name":"Shangdagu",
    "wof:placetype":"locality"
},
  "geometry": {"coordinates":[109.73399999999999,24.1986],"type":"Point"}
}