{
  "type": "Feature",
  "properties": {
    "gn:admin1_code":"19.0",
    "gn:asciiname":"Tundaogou",
    "gn:country_code":"CN",
    "gn:dem":133,
    "gn:feature_class":"P",
    "gn:feature_code":"PPL",
    "gn:name":"Tundaogou",
    "gn:population":0,
    "gn:timezone":"Asia/Shanghai",
    "iso:country":"CN",
    "name:und_x_variant":[
        "\u5c6f\u9053\u6c9f"
    ],
    "wof:name":"Tundaogou",
    "wof:placetype":"locality"
},
  "geometry": {"coordinates":[122.55316000000001,40.3717],"type":"Point"}
}