{
  "type": "Feature",
  "properties": {
    "gn:admin1_code":"4.0",
    "gn:asciiname":"Yanshe",
    "gn:country_code":"CN",
    "gn:dem":2,
    "gn:feature_class":"P",
    "gn:feature_code":"PPL",
    "gn:name":"Yanshe",
    "gn:population":0,
    "gn:timezone":"Asia/Shanghai",
    "iso:country":"CN",
    "name:zho_x_preferred":[
        "Yanshe"
    ],
    "name:zho_x_variant":[
        "\u4e25\u820d"
    ],
    "wof:name":"Yanshe",
    "wof:placetype":"locality"
},
  "geometry": {"coordinates":[119.71241000000001,33.20752],"type":"Point"}
}