{
  "type": "Feature",
  "properties": {
    "gn:admin1_code":"29.0",
    "gn:asciiname":"Banzhuqing",
    "gn:country_code":"CN",
    "gn:dem":1178,
    "gn:feature_class":"P",
    "gn:feature_code":"PPL",
    "gn:name":"Banzhuqing",
    "gn:population":0,
    "gn:timezone":"Asia/Shanghai",
    "iso:country":"CN",
    "name:zho_x_preferred":[
        "\u73ed\u7af9\u7b90"
    ],
    "wof:name":"Banzhuqing",
    "wof:placetype":"locality"
},
  "geometry": {"coordinates":[100.515,22.8494],"type":"Point"}
}