{
  "type": "Feature",
  "properties": {
    "gn:admin1_code":"2.0",
    "gn:asciiname":"Wang'ao",
    "gn:country_code":"CN",
    "gn:dem":273,
    "gn:feature_class":"P",
    "gn:feature_code":"PPL",
    "gn:name":"Wang\u2019ao",
    "gn:population":0,
    "gn:timezone":"Asia/Shanghai",
    "iso:country":"CN",
    "name:und_x_variant":[
        "Wang\u2019ao"
    ],
    "name:zho_x_preferred":[
        "\u738b\u5c99"
    ],
    "wof:name":"Wang'ao",
    "wof:placetype":"locality"
},
  "geometry": {"coordinates":[120.10263999999999,28.43604],"type":"Point"}
}