{
  "type": "Feature",
  "properties": {
    "gn:admin1_code":"14.0",
    "gn:asciiname":"Daxialu",
    "gn:country_code":"CN",
    "gn:dem":4328,
    "gn:feature_class":"P",
    "gn:feature_code":"PPL",
    "gn:name":"Daxialu",
    "gn:population":0,
    "gn:timezone":"Asia/Urumqi",
    "iso:country":"CN",
    "name:zho_x_preferred":[
        "\u8fbe\u867e\u9646"
    ],
    "wof:name":"Daxialu",
    "wof:placetype":"locality"
},
  "geometry": {"coordinates":[86.7486,29.2616],"type":"Point"}
}