{
  "type": "Feature",
  "properties": {
    "gn:admin1_code":"15.0",
    "gn:asciiname":"Tufenggou",
    "gn:country_code":"CN",
    "gn:dem":1123,
    "gn:feature_class":"P",
    "gn:feature_code":"PPL",
    "gn:name":"Tufenggou",
    "gn:population":0,
    "gn:timezone":"Asia/Shanghai",
    "iso:country":"CN",
    "name:und_x_variant":[
        "\u571f\u5cf0\u6c9f"
    ],
    "wof:name":"Tufenggou",
    "wof:placetype":"locality"
},
  "geometry": {"coordinates":[106.40188999999999,33.91692],"type":"Point"}
}