{
  "type": "Feature",
  "properties": {
    "gn:admin1_code":"18",
    "gn:asciiname":"Shangjianqing",
    "gn:country_code":"CN",
    "gn:dem":1169,
    "gn:feature_class":"P",
    "gn:feature_code":"PPL",
    "gn:name":"Shangjianqing",
    "gn:population":0,
    "gn:timezone":"Asia/Shanghai",
    "iso:country":"CN",
    "name:zho_x_preferred":[
        "\u4e0a\u7b80\u5e86"
    ],
    "wof:name":"Shangjianqing",
    "wof:placetype":"locality"
},
  "geometry": {"coordinates":[106.283,25.8216],"type":"Point"}
}