{
  "type": "Feature",
  "properties": {
    "gn:admin1_code":"32.0",
    "gn:asciiname":"Erzishan",
    "gn:country_code":"CN",
    "gn:dem":1585,
    "gn:feature_class":"P",
    "gn:feature_code":"PPL",
    "gn:name":"Erzishan",
    "gn:population":0,
    "gn:timezone":"Asia/Shanghai",
    "iso:country":"CN",
    "name:zho_x_preferred":[
        "\u8033\u5b50\u5c71"
    ],
    "wof:name":"Erzishan",
    "wof:placetype":"locality"
},
  "geometry": {"coordinates":[101.84099999999999,27.9015],"type":"Point"}
}