{
  "type": "Feature",
  "properties": {
    "gn:admin1_code":"26.0",
    "gn:asciiname":"Yecun",
    "gn:country_code":"CN",
    "gn:dem":620,
    "gn:feature_class":"P",
    "gn:feature_code":"PPL",
    "gn:name":"Yecun",
    "gn:population":0,
    "gn:timezone":"Asia/Shanghai",
    "iso:country":"CN",
    "name:und_x_variant":[
        "Yeh-ts\u2019un",
        "Yecun"
    ],
    "wof:name":"Yecun",
    "wof:placetype":"locality"
},
  "geometry": {"coordinates":[110.12528,33.76306],"type":"Point"}
}