{
  "type": "Feature",
  "properties": {
    "gn:admin1_code":"16.0",
    "gn:asciiname":"Muqiaodong",
    "gn:country_code":"CN",
    "gn:dem":171,
    "gn:feature_class":"P",
    "gn:feature_code":"PPL",
    "gn:name":"Muqiaodong",
    "gn:population":0,
    "gn:timezone":"Asia/Shanghai",
    "iso:country":"CN",
    "name:zho_x_preferred":[
        "\u6728\u6865\u6d1e"
    ],
    "wof:name":"Muqiaodong",
    "wof:placetype":"locality"
},
  "geometry": {"coordinates":[109.968,24.8072],"type":"Point"}
}