{
  "type": "Feature",
  "properties": {
    "gn:admin1_code":"29.0",
    "gn:asciiname":"Moye",
    "gn:country_code":"CN",
    "gn:dem":1280,
    "gn:feature_class":"P",
    "gn:feature_code":"PPL",
    "gn:name":"Moye",
    "gn:population":0,
    "gn:timezone":"Asia/Shanghai",
    "iso:country":"CN",
    "name:cat_x_preferred":[
        "Moye"
    ],
    "name:ceb_x_preferred":[
        "Moye"
    ],
    "name:deu_x_preferred":[
        "Moye"
    ],
    "name:eus_x_preferred":[
        "Moye"
    ],
    "name:fra_x_preferred":[
        "Moye"
    ],
    "name:hun_x_preferred":[
        "Moye"
    ],
    "name:ita_x_preferred":[
        "Moye"
    ],
    "name:lat_x_preferred":[
        "Mollia"
    ],
    "name:msa_x_preferred":[
        "Moye"
    ],
    "name:nld_x_preferred":[
        "Moye"
    ],
    "name:oci_x_preferred":[
        "Moye"
    ],
    "name:pol_x_preferred":[
        "Moye"
    ],
    "name:ron_x_preferred":[
        "Moye"
    ],
    "name:slk_x_preferred":[
        "Moye"
    ],
    "name:spa_x_preferred":[
        "Moye"
    ],
    "name:swe_x_preferred":[
        "Moye"
    ],
    "name:ukr_x_preferred":[
        "\u041c\u0443\u0430"
    ],
    "name:uzb_x_preferred":[
        "Moye"
    ],
    "name:vie_x_preferred":[
        "Moye"
    ],
    "name:vol_x_preferred":[
        "Moye"
    ],
    "name:war_x_preferred":[
        "Moye"
    ],
    "name:zho_x_preferred":[
        "\u78e8\u4e5f"
    ],
    "wof:name":"Moye",
    "wof:placetype":"locality"
},
  "geometry": {"coordinates":[100.81399999999999,23.6579],"type":"Point"}
}