{
  "type": "Feature",
  "properties": {
    "gn:admin1_code":"3.0",
    "gn:asciiname":"Bushe",
    "gn:country_code":"CN",
    "gn:dem":261,
    "gn:feature_class":"P",
    "gn:feature_code":"PPL",
    "gn:name":"Bushe",
    "gn:population":0,
    "gn:timezone":"Asia/Shanghai",
    "iso:country":"CN",
    "name:zho_x_preferred":[
        "\u5e03\u793e"
    ],
    "wof:name":"Bushe",
    "wof:placetype":"locality"
},
  "geometry": {"coordinates":[114.879,25.0566],"type":"Point"}
}