{
  "type": "Feature",
  "properties": {
    "gn:admin1_code":"30",
    "gn:asciiname":"Dashuilang",
    "gn:country_code":"CN",
    "gn:dem":220,
    "gn:feature_class":"P",
    "gn:feature_code":"PPL",
    "gn:name":"Dashuilang",
    "gn:population":0,
    "gn:timezone":"Asia/Shanghai",
    "iso:country":"CN",
    "name:zho_x_preferred":[
        "\u5927\u6c34\u5871"
    ],
    "wof:name":"Dashuilang",
    "wof:placetype":"locality"
},
  "geometry": {"coordinates":[111.92471999999999,22.87139],"type":"Point"}
}