{
  "type": "Feature",
  "properties": {
    "gn:admin1_code":"15.0",
    "gn:asciiname":"Mudao",
    "gn:country_code":"CN",
    "gn:dem":2880,
    "gn:feature_class":"P",
    "gn:feature_code":"PPL",
    "gn:name":"Mudao",
    "gn:population":0,
    "gn:timezone":"Asia/Shanghai",
    "iso:country":"CN",
    "name:und_x_variant":[
        "\u6728\u9053"
    ],
    "wof:name":"Mudao",
    "wof:placetype":"locality"
},
  "geometry": {"coordinates":[102.95817,34.68566],"type":"Point"}
}