{
  "type": "Feature",
  "properties": {
    "gn:admin1_code":"30",
    "gn:asciiname":"Langshang",
    "gn:country_code":"CN",
    "gn:dem":187,
    "gn:feature_class":"P",
    "gn:feature_code":"PPL",
    "gn:name":"Langshang",
    "gn:population":0,
    "gn:timezone":"Asia/Shanghai",
    "iso:country":"CN",
    "name:zho_x_preferred":[
        "\u5d00\u4e0a"
    ],
    "wof:name":"Langshang",
    "wof:placetype":"locality"
},
  "geometry": {"coordinates":[115.84061,23.88329],"type":"Point"}
}