{
  "type": "Feature",
  "properties": {
    "gn:admin1_code":"9.0",
    "gn:asciiname":"Houyanmen",
    "gn:country_code":"CN",
    "gn:dem":87,
    "gn:feature_class":"P",
    "gn:feature_code":"PPL",
    "gn:name":"Houyanmen",
    "gn:population":0,
    "gn:timezone":"Asia/Shanghai",
    "iso:country":"CN",
    "name:zho_x_preferred":[
        "\u540e\u96c1\u95e8"
    ],
    "wof:name":"Houyanmen",
    "wof:placetype":"locality"
},
  "geometry": {"coordinates":[113.49194,35.17025],"type":"Point"}
}