{
  "type": "Feature",
  "properties": {
    "gn:admin1_code":"11.0",
    "gn:asciiname":"Huixianqiao",
    "gn:country_code":"CN",
    "gn:dem":62,
    "gn:feature_class":"P",
    "gn:feature_code":"PPL",
    "gn:name":"Huixianqiao",
    "gn:population":0,
    "gn:timezone":"Asia/Shanghai",
    "iso:country":"CN",
    "name:zho_x_preferred":[
        "Huixianqiao"
    ],
    "name:zho_x_variant":[
        "\u4f1a\u4ed9\u6865"
    ],
    "wof:name":"Huixianqiao",
    "wof:placetype":"locality"
},
  "geometry": {"coordinates":[111.79980999999999,29.3812],"type":"Point"}
}