{
  "type": "Feature",
  "properties": {
    "gn:admin1_code":"18.0",
    "gn:asciiname":"Huailai",
    "gn:country_code":"CN",
    "gn:dem":357,
    "gn:feature_class":"P",
    "gn:feature_code":"PPL",
    "gn:name":"Huailai",
    "gn:population":0,
    "gn:timezone":"Asia/Shanghai",
    "iso:country":"CN",
    "name:zho_x_preferred":[
        "\u6000\u6765"
    ],
    "wof:name":"Huailai",
    "wof:placetype":"locality"
},
  "geometry": {"coordinates":[108.386,26.0471],"type":"Point"}
}