{
  "type": "Feature",
  "properties": {
    "gn:admin1_code":"5.0",
    "gn:asciiname":"Bataiji",
    "gn:country_code":"CN",
    "gn:dem":301,
    "gn:feature_class":"P",
    "gn:feature_code":"PPL",
    "gn:name":"Bataiji",
    "gn:population":0,
    "gn:timezone":"Asia/Shanghai",
    "iso:country":"CN",
    "name:zho_x_preferred":[
        "\u5df4\u53f0\u5409"
    ],
    "wof:name":"Bataiji",
    "wof:placetype":"locality"
},
  "geometry": {"coordinates":[121.78837,45.75852],"type":"Point"}
}