{
  "type": "Feature",
  "properties": {
    "gn:admin1_code":"19.0",
    "gn:asciiname":"Zhujia Buzi",
    "gn:country_code":"CN",
    "gn:dem":161,
    "gn:feature_class":"P",
    "gn:feature_code":"PPL",
    "gn:name":"Zhujia Buzi",
    "gn:population":0,
    "gn:timezone":"Asia/Shanghai",
    "iso:country":"CN",
    "name:und_x_variant":[
        "Zhujiabaozi",
        "\u6731\u5bb6\u5821\u5b50",
        "Zhujia Puzi",
        "Zhujia Buzi"
    ],
    "name:zho_x_preferred":[
        "\u6731\u5bb6\u5821\u5b50"
    ],
    "wof:name":"Zhujia Buzi",
    "wof:placetype":"locality"
},
  "geometry": {"coordinates":[123.35003,40.60095],"type":"Point"}
}