{
  "type": "Feature",
  "properties": {
    "gn:admin1_code":"12.0",
    "gn:asciiname":"Wangjiaya",
    "gn:country_code":"CN",
    "gn:dem":720,
    "gn:feature_class":"P",
    "gn:feature_code":"PPL",
    "gn:name":"Wangjiaya",
    "gn:population":0,
    "gn:timezone":"Asia/Shanghai",
    "iso:country":"CN",
    "name:zho_x_preferred":[
        "\u6c6a\u5bb6\u57ad"
    ],
    "wof:name":"Wangjiaya",
    "wof:placetype":"locality"
},
  "geometry": {"coordinates":[110.85332,32.39925],"type":"Point"}
}