{
  "type": "Feature",
  "properties": {
    "gn:admin1_code":"30.0",
    "gn:asciiname":"Tangkeng",
    "gn:country_code":"CN",
    "gn:dem":342,
    "gn:feature_class":"P",
    "gn:feature_code":"PPL",
    "gn:name":"Tangkeng",
    "gn:population":0,
    "gn:timezone":"Asia/Shanghai",
    "iso:country":"CN",
    "name:zho_x_preferred":[
        "Tangkeng"
    ],
    "name:zho_x_variant":[
        "\u5858\u5751",
        "\u6c64\u5751\u9547"
    ],
    "wof:name":"Tangkeng",
    "wof:placetype":"locality"
},
  "geometry": {"coordinates":[113.89388999999998,25.13056],"type":"Point"}
}