{
  "type": "Feature",
  "properties": {
    "gn:admin1_code":"30.0",
    "gn:asciiname":"Sitianwei",
    "gn:country_code":"CN",
    "gn:dem":64,
    "gn:feature_class":"P",
    "gn:feature_code":"PPL",
    "gn:name":"Sitianwei",
    "gn:population":0,
    "gn:timezone":"Asia/Shanghai",
    "iso:country":"CN",
    "name:zho_x_preferred":[
        "\u5bfa\u7530\u5c3e"
    ],
    "wof:name":"Sitianwei",
    "wof:placetype":"locality"
},
  "geometry": {"coordinates":[112.29474,23.93668],"type":"Point"}
}