{
  "type": "Feature",
  "properties": {
    "gn:admin1_code":"1.0",
    "gn:asciiname":"Huangloucun",
    "gn:country_code":"CN",
    "gn:dem":45,
    "gn:feature_class":"P",
    "gn:feature_code":"PPL",
    "gn:name":"Huangloucun",
    "gn:population":0,
    "gn:timezone":"Asia/Shanghai",
    "iso:country":"CN",
    "name:und_x_variant":[
        "Huanglou"
    ],
    "name:zho_x_preferred":[
        "\u9ec4\u697c\u6751"
    ],
    "wof:name":"Huangloucun",
    "wof:placetype":"locality"
},
  "geometry": {"coordinates":[116.31667,34.45],"type":"Point"}
}