{
  "type": "Feature",
  "properties": {
    "gn:admin1_code":"9.0",
    "gn:asciiname":"Yilihe",
    "gn:country_code":"CN",
    "gn:dem":489,
    "gn:feature_class":"P",
    "gn:feature_code":"PPL",
    "gn:name":"Yilihe",
    "gn:population":0,
    "gn:timezone":"Asia/Shanghai",
    "iso:country":"CN",
    "name:zho_x_preferred":[
        "\u4e00\u91cc\u6cb3"
    ],
    "wof:name":"Yilihe",
    "wof:placetype":"locality"
},
  "geometry": {"coordinates":[111.77288,34.75685],"type":"Point"}
}