{
  "type": "Feature",
  "properties": {
    "gn:admin1_code":"8.0",
    "gn:asciiname":"Kehoutun",
    "gn:country_code":"CN",
    "gn:dem":252,
    "gn:feature_class":"P",
    "gn:feature_code":"PPL",
    "gn:name":"Kehoutun",
    "gn:population":0,
    "gn:timezone":"Asia/Shanghai",
    "iso:country":"CN",
    "name:zho_x_preferred":[
        "\u79d1\u540e\u5c6f"
    ],
    "wof:name":"Kehoutun",
    "wof:placetype":"locality"
},
  "geometry": {"coordinates":[125.72338000000001,49.36818],"type":"Point"}
}