{
  "type": "Feature",
  "properties": {
    "gn:admin1_code":"24.0",
    "gn:asciiname":"Jianyang",
    "gn:country_code":"CN",
    "gn:dem":1465,
    "gn:feature_class":"P",
    "gn:feature_code":"PPL",
    "gn:name":"Jianyang",
    "gn:population":0,
    "gn:timezone":"Asia/Shanghai",
    "iso:country":"CN",
    "name:zho_x_preferred":[
        "\u5c16\u9633"
    ],
    "wof:name":"Jianyang",
    "wof:placetype":"locality"
},
  "geometry": {"coordinates":[111.96107000000001,36.53511],"type":"Point"}
}