{
  "type": "Feature",
  "properties": {
    "gn:admin1_code":"29",
    "gn:asciiname":"Hezui",
    "gn:country_code":"CN",
    "gn:dem":1730,
    "gn:feature_class":"P",
    "gn:feature_code":"PPL",
    "gn:name":"Hezui",
    "gn:population":0,
    "gn:timezone":"Asia/Shanghai",
    "iso:country":"CN",
    "name:zho_x_preferred":[
        "\u6cb3\u5480"
    ],
    "wof:name":"Hezui",
    "wof:placetype":"locality"
},
  "geometry": {"coordinates":[102.76166000000001,24.3064],"type":"Point"}
}