{
  "type": "Feature",
  "properties": {
    "gn:admin1_code":"32.0",
    "gn:asciiname":"Liupapo",
    "gn:country_code":"CN",
    "gn:dem":1744,
    "gn:feature_class":"P",
    "gn:feature_code":"PPL",
    "gn:name":"Liupapo",
    "gn:population":0,
    "gn:timezone":"Asia/Shanghai",
    "iso:country":"CN",
    "name:zho_x_preferred":[
        "\u6e9c\u722c\u5761"
    ],
    "wof:name":"Liupapo",
    "wof:placetype":"locality"
},
  "geometry": {"coordinates":[101.66383,27.16899],"type":"Point"}
}