{
  "type": "Feature",
  "properties": {
    "gn:admin1_code":"10",
    "gn:asciiname":"Xisigou",
    "gn:country_code":"CN",
    "gn:dem":1150,
    "gn:feature_class":"P",
    "gn:feature_code":"PPL",
    "gn:name":"Xisigou",
    "gn:population":0,
    "gn:timezone":"Asia/Shanghai",
    "iso:country":"CN",
    "name:zho_x_preferred":[
        "\u897f\u5bfa\u6c9f"
    ],
    "wof:name":"Xisigou",
    "wof:placetype":"locality"
},
  "geometry": {"coordinates":[115.63602,40.95015],"type":"Point"}
}