{
  "type": "Feature",
  "properties": {
    "gn:admin1_code":"26.0",
    "gn:asciiname":"Shuimowan",
    "gn:country_code":"CN",
    "gn:dem":594,
    "gn:feature_class":"P",
    "gn:feature_code":"PPL",
    "gn:name":"Shuimowan",
    "gn:population":0,
    "gn:timezone":"Asia/Shanghai",
    "iso:country":"CN",
    "name:und_x_variant":[
        "\u6c34\u78e8\u6e7e"
    ],
    "wof:name":"Shuimowan",
    "wof:placetype":"locality"
},
  "geometry": {"coordinates":[106.60629,33.16542],"type":"Point"}
}