{
  "type": "Feature",
  "properties": {
    "gn:admin1_code":"5.0",
    "gn:asciiname":"Laoyaoshan",
    "gn:country_code":"CN",
    "gn:dem":205,
    "gn:feature_class":"P",
    "gn:feature_code":"PPL",
    "gn:name":"Laoyaoshan",
    "gn:population":0,
    "gn:timezone":"Asia/Shanghai",
    "iso:country":"CN",
    "name:zho_x_preferred":[
        "\u8001\u9e5e\u5c71"
    ],
    "wof:name":"Laoyaoshan",
    "wof:placetype":"locality"
},
  "geometry": {"coordinates":[124.71671000000001,44.79216],"type":"Point"}
}