{
  "type": "Feature",
  "properties": {
    "gn:admin1_code":"5.0",
    "gn:asciiname":"Donghanjiatun",
    "gn:country_code":"CN",
    "gn:dem":345,
    "gn:feature_class":"P",
    "gn:feature_code":"PPL",
    "gn:name":"Donghanjiatun",
    "gn:population":0,
    "gn:timezone":"Asia/Shanghai",
    "iso:country":"CN",
    "name:zho_x_preferred":[
        "\u4e1c\u97e9\u5bb6\u5c6f"
    ],
    "wof:name":"Donghanjiatun",
    "wof:placetype":"locality"
},
  "geometry": {"coordinates":[126.19719000000001,42.97852],"type":"Point"}
}