{
  "type": "Feature",
  "properties": {
    "gn:admin1_code":"1.0",
    "gn:asciiname":"Huaiguangcun",
    "gn:country_code":"CN",
    "gn:dem":22,
    "gn:feature_class":"P",
    "gn:feature_code":"PPL",
    "gn:name":"Huaiguangcun",
    "gn:population":0,
    "gn:timezone":"Asia/Shanghai",
    "iso:country":"CN",
    "name:zho_x_preferred":[
        "\u6dee\u5149\u6751"
    ],
    "wof:name":"Huaiguangcun",
    "wof:placetype":"locality"
},
  "geometry": {"coordinates":[117.46081,32.94925],"type":"Point"}
}