{
  "type": "Feature",
  "properties": {
    "gn:admin1_code":"26.0",
    "gn:asciiname":"Liangpocun",
    "gn:country_code":"CN",
    "gn:dem":1430,
    "gn:feature_class":"P",
    "gn:feature_code":"PPL",
    "gn:name":"Liangpocun",
    "gn:population":0,
    "gn:timezone":"Asia/Shanghai",
    "iso:country":"CN",
    "name:zho_x_preferred":[
        "\u6881\u5761\u6751"
    ],
    "wof:name":"Liangpocun",
    "wof:placetype":"locality"
},
  "geometry": {"coordinates":[107.93812,37.03664000000001],"type":"Point"}
}