{
  "type": "Feature",
  "properties": {
    "gn:admin1_code":"9.0",
    "gn:asciiname":"Zhanghuaishu",
    "gn:country_code":"CN",
    "gn:dem":85,
    "gn:feature_class":"P",
    "gn:feature_code":"PPL",
    "gn:name":"Zhanghuaishu",
    "gn:population":0,
    "gn:timezone":"Asia/Shanghai",
    "iso:country":"CN",
    "name:zho_x_preferred":[
        "\u5f20\u69d0\u6811"
    ],
    "wof:name":"Zhanghuaishu",
    "wof:placetype":"locality"
},
  "geometry": {"coordinates":[113.66298999999999,35.09458],"type":"Point"}
}