{
  "type": "Feature",
  "properties": {
    "gn:admin1_code":"5",
    "gn:asciiname":"Banzi Wopeng Shangtun",
    "gn:country_code":"CN",
    "gn:dem":363,
    "gn:feature_class":"P",
    "gn:feature_code":"PPL",
    "gn:name":"Banzi Wopeng Shangtun",
    "gn:population":0,
    "gn:timezone":"Asia/Shanghai",
    "iso:country":"CN",
    "name:zho_x_preferred":[
        "\u62cc\u5b50\u7a9d\u68da\u4e0a\u5c6f"
    ],
    "wof:name":"Banzi Wopeng Shangtun",
    "wof:placetype":"locality"
},
  "geometry": {"coordinates":[127.321,43.4893],"type":"Point"}
}