{
  "type": "Feature",
  "properties": {
    "gn:admin1_code":"29.0",
    "gn:asciiname":"Mozuoba",
    "gn:country_code":"CN",
    "gn:dem":1062,
    "gn:feature_class":"P",
    "gn:feature_code":"PPL",
    "gn:name":"Mozuoba",
    "gn:population":0,
    "gn:timezone":"Asia/Shanghai",
    "iso:country":"CN",
    "name:zho_x_preferred":[
        "\u83ab\u4f5c\u575d"
    ],
    "wof:name":"Mozuoba",
    "wof:placetype":"locality"
},
  "geometry": {"coordinates":[101.673,22.5131],"type":"Point"}
}