{
  "type": "Feature",
  "properties": {
    "gn:admin1_code":"18.0",
    "gn:asciiname":"Wuxia",
    "gn:country_code":"CN",
    "gn:dem":1082,
    "gn:feature_class":"P",
    "gn:feature_code":"PPL",
    "gn:name":"Wuxia",
    "gn:population":0,
    "gn:timezone":"Asia/Shanghai",
    "iso:country":"CN",
    "name:zho_x_preferred":[
        "\u6c61\u4e0b"
    ],
    "wof:name":"Wuxia",
    "wof:placetype":"locality"
},
  "geometry": {"coordinates":[108.39100000000001,25.5507],"type":"Point"}
}