{
  "type": "Feature",
  "properties": {
    "gn:admin1_code":"18.0",
    "gn:asciiname":"Wuxia",
    "gn:country_code":"CN",
    "gn:dem":1082,
    "gn:feature_class":"P",
    "gn:feature_code":"PPL",
    "gn:name":"Wuxia",
    "gn:population":0,
    "gn:timezone":"Asia/Shanghai",
    "iso:country":"CN",
    "name:ast_x_preferred":[
        "Wuxia"
    ],
    "name:cat_x_preferred":[
        "Wuxia"
    ],
    "name:deu_x_preferred":[
        "Wuxia"
    ],
    "name:eus_x_preferred":[
        "Wuxia"
    ],
    "name:fas_x_preferred":[
        "\u0648\u0648\u0634\u06cc\u0627"
    ],
    "name:fin_x_preferred":[
        "Wuxia"
    ],
    "name:fra_x_preferred":[
        "Wuxia"
    ],
    "name:glg_x_preferred":[
        "Wuxia"
    ],
    "name:heb_x_preferred":[
        "\u05d5\u05d5\u05e9\u05d9\u05d4"
    ],
    "name:hun_x_preferred":[
        "Vu-hszia"
    ],
    "name:hye_x_preferred":[
        "\u0548\u0582\u057d\u0575\u0561"
    ],
    "name:ind_x_preferred":[
        "Cerita silat"
    ],
    "name:ita_x_preferred":[
        "Wuxia"
    ],
    "name:nor_x_preferred":[
        "Wuxia"
    ],
    "name:pol_x_preferred":[
        "Wuxia"
    ],
    "name:por_x_preferred":[
        "Wuxia"
    ],
    "name:rus_x_preferred":[
        "\u0423\u0441\u044f"
    ],
    "name:spa_x_preferred":[
        "Wuxia"
    ],
    "name:srp_x_preferred":[
        "Vusja"
    ],
    "name:swe_x_preferred":[
        "Wuxia"
    ],
    "name:tha_x_preferred":[
        "\u0e1a\u0e31\u0e19\u0e40\u0e17\u0e34\u0e07\u0e04\u0e14\u0e35\u0e01\u0e33\u0e25\u0e31\u0e07\u0e20\u0e32\u0e22\u0e43\u0e19"
    ],
    "name:ukr_x_preferred":[
        "\u0423\u0441\u044f"
    ],
    "name:vie_x_preferred":[
        "V\u00f5 hi\u1ec7p"
    ],
    "name:zho_x_preferred":[
        "\u6c61\u4e0b"
    ],
    "name:zho_x_variant":[
        "\u6b66\u4fa0\u6587\u5316"
    ],
    "wof:name":"Wuxia",
    "wof:placetype":"locality"
},
  "geometry": {"coordinates":[108.39100000000001,25.5507],"type":"Point"}
}