{
  "type": "Feature",
  "properties": {
    "gn:admin1_code":"12.0",
    "gn:asciiname":"Lejiawan",
    "gn:country_code":"CN",
    "gn:dem":10,
    "gn:feature_class":"P",
    "gn:feature_code":"PPL",
    "gn:name":"Lejiawan",
    "gn:population":0,
    "gn:timezone":"Asia/Shanghai",
    "iso:country":"CN",
    "name:und_x_variant":[
        "\u4e50\u5bb6\u5846"
    ],
    "wof:name":"Lejiawan",
    "wof:placetype":"locality"
},
  "geometry": {"coordinates":[115.07655,30.33861],"type":"Point"}
}