{
  "type": "Feature",
  "properties": {
    "gn:admin1_code":"02",
    "gn:asciiname":"Quexia",
    "gn:country_code":"CN",
    "gn:dem":411,
    "gn:feature_class":"P",
    "gn:feature_code":"PPL",
    "gn:name":"Quexia",
    "gn:population":0,
    "gn:timezone":"Asia/Shanghai",
    "iso:country":"CN",
    "name:und_x_variant":[
        "Huang-hsia-ts\u2019un",
        "Quexia"
    ],
    "name:zho_x_preferred":[
        "\u788f\u4e0b"
    ],
    "wof:name":"Quexia",
    "wof:placetype":"locality"
},
  "geometry": {"coordinates":[120.75621,28.62221],"type":"Point"}
}