{
  "type": "Feature",
  "properties": {
    "gn:admin1_code":"11.0",
    "gn:asciiname":"Zhoujia Hetou",
    "gn:country_code":"CN",
    "gn:dem":39,
    "gn:feature_class":"P",
    "gn:feature_code":"PPL",
    "gn:name":"Zhoujia Hetou",
    "gn:population":0,
    "gn:timezone":"Asia/Shanghai",
    "iso:country":"CN",
    "name:zho_x_preferred":[
        "\u5468\u5bb6\u6cb3\u5934"
    ],
    "wof:name":"Zhoujia Hetou",
    "wof:placetype":"locality"
},
  "geometry": {"coordinates":[112.88476,27.76121],"type":"Point"}
}