{
  "type": "Feature",
  "properties": {
    "gn:admin1_code":"16.0",
    "gn:asciiname":"Shuangfeng",
    "gn:country_code":"CN",
    "gn:dem":51,
    "gn:feature_class":"P",
    "gn:feature_code":"PPL",
    "gn:name":"Shuangfeng",
    "gn:population":0,
    "gn:timezone":"Asia/Shanghai",
    "iso:country":"CN",
    "name:ceb_x_preferred":[
        "Shuangfeng"
    ],
    "name:deu_x_preferred":[
        "Shuangfeng"
    ],
    "name:zho_x_preferred":[
        "\u53cc\u51e4"
    ],
    "wof:name":"Shuangfeng",
    "wof:placetype":"locality"
},
  "geometry": {"coordinates":[109.398,23.0827],"type":"Point"}
}