{
  "type": "Feature",
  "properties": {
    "gn:gn_country":"CN",
    "gn:gn_fcode":"PPL",
    "gn:gn_pop":0,
    "iso:country":"CN",
    "name:unk_x_variant":[
        "Sui-ch\u2019ang-hsien"
    ],
    "qs_pg:aaroncc":"CN",
    "qs_pg:gn_country":"CN",
    "qs_pg:gn_fcode":"PPL",
    "qs_pg:gn_pop":0,
    "qs_pg:name":"\u5999\u9ad8\u9547",
    "qs_pg:name_adm0":"\u4e2d\u570b",
    "qs_pg:name_adm1":"\u6d59\u6c5f\u7701",
    "qs_pg:photos_9k":1,
    "qs_pg:photos_9r":1,
    "qs_pg:photos_all":12,
    "qs_pg:photos_sr":0,
    "qs_pg:pop_sr":5,
    "qs_pg:qs_pg_placetype":"locality",
    "qs_pg:qs_pg_placetype_gp":"Town",
    "qs_pg:woe_adm0":23424781,
    "woe:adm0_id":23424781,
    "woe:name_adm0":"\u4e2d\u570b",
    "woe:name_adm1":"\u6d59\u6c5f\u7701",
    "woe:placetype":"Town",
    "wof:name":"\u5999\u9ad8\u9547",
    "wof:placetype":"locality"
},
  "geometry": {"coordinates":[119.26961,28.59709],"type":"Point"}
}