{
  "type": "Feature",
  "properties": {
    "gn:admin1_code":"12.0",
    "gn:asciiname":"Liujiahe",
    "gn:country_code":"CN",
    "gn:dem":54,
    "gn:feature_class":"P",
    "gn:feature_code":"PPL",
    "gn:name":"Liujiahe",
    "gn:population":0,
    "gn:timezone":"Asia/Shanghai",
    "iso:country":"CN",
    "name:zho_x_preferred":[
        "Liujiahe"
    ],
    "name:zho_x_variant":[
        "\u5218\u5bb6\u6cb3"
    ],
    "wof:name":"Liujiahe",
    "wof:placetype":"locality"
},
  "geometry": {"coordinates":[111.37908,30.41158],"type":"Point"}
}