{
  "type": "Feature",
  "properties": {
    "gn:admin1_code":"15.0",
    "gn:asciiname":"Xiaowuya'ersa",
    "gn:country_code":"CN",
    "gn:dem":3132,
    "gn:feature_class":"P",
    "gn:feature_code":"PPL",
    "gn:name":"Xiaowuya\u2019ersa",
    "gn:population":0,
    "gn:timezone":"Asia/Shanghai",
    "iso:country":"CN",
    "name:und_x_variant":[
        "Xiaowuya\u2019ersa",
        "\u8096\u543e\u4e9a\u5c14\u8428"
    ],
    "wof:name":"Xiaowuya'ersa",
    "wof:placetype":"locality"
},
  "geometry": {"coordinates":[102.65924,35.37300000000001],"type":"Point"}
}