{
  "type": "Feature",
  "properties": {
    "gn:admin1_code":"26.0",
    "gn:asciiname":"Wangdapancun",
    "gn:country_code":"CN",
    "gn:dem":1193,
    "gn:feature_class":"P",
    "gn:feature_code":"PPL",
    "gn:name":"Wangdapancun",
    "gn:population":0,
    "gn:timezone":"Asia/Shanghai",
    "iso:country":"CN",
    "name:zho_x_preferred":[
        "\u738b\u8fbe\u7554\u6751"
    ],
    "wof:name":"Wangdapancun",
    "wof:placetype":"locality"
},
  "geometry": {"coordinates":[110.16355,38.36657],"type":"Point"}
}