{
  "type": "Feature",
  "properties": {
    "gn:admin1_code":"19.0",
    "gn:asciiname":"Xinjiantun",
    "gn:country_code":"CN",
    "gn:dem":8,
    "gn:feature_class":"P",
    "gn:feature_code":"PPL",
    "gn:name":"Xinjiantun",
    "gn:population":0,
    "gn:timezone":"Asia/Shanghai",
    "iso:country":"CN",
    "name:zho_x_preferred":[
        "\u65b0\u5efa\u5c6f"
    ],
    "wof:name":"Xinjiantun",
    "wof:placetype":"locality"
},
  "geometry": {"coordinates":[121.77200000000001,39.281],"type":"Point"}
}