{
  "type": "Feature",
  "properties": {
    "gn:admin1_code":"9.0",
    "gn:asciiname":"Shangying",
    "gn:country_code":"CN",
    "gn:dem":200,
    "gn:feature_class":"P",
    "gn:feature_code":"PPL",
    "gn:name":"Shangying",
    "gn:population":0,
    "gn:timezone":"Asia/Shanghai",
    "iso:country":"CN",
    "name:und_x_variant":[
        "\u5c1a\u8425",
        "Shangying"
    ],
    "wof:name":"Shangying",
    "wof:placetype":"locality"
},
  "geometry": {"coordinates":[112.89181000000001,33.31199],"type":"Point"}
}