{
  "type": "Feature",
  "properties": {
    "gn:admin1_code":"31",
    "gn:asciiname":"Henglingcun",
    "gn:country_code":"CN",
    "gn:dem":151,
    "gn:feature_class":"P",
    "gn:feature_code":"PPL",
    "gn:name":"Henglingcun",
    "gn:population":0,
    "gn:timezone":"Asia/Shanghai",
    "iso:country":"CN",
    "name:und_x_variant":[
        "\u6a2a\u5cad\u6751",
        "Heluocun",
        "Heluo",
        "\u5408\u7f57"
    ],
    "wof:name":"Henglingcun",
    "wof:placetype":"locality"
},
  "geometry": {"coordinates":[109.59751,19.48616],"type":"Point"}
}