{
  "type": "Feature",
  "properties": {
    "gn:admin1_code":"1.0",
    "gn:asciiname":"Xiaoqingyingcun",
    "gn:country_code":"CN",
    "gn:dem":32,
    "gn:feature_class":"P",
    "gn:feature_code":"PPL",
    "gn:name":"Xiaoqingyingcun",
    "gn:population":0,
    "gn:timezone":"Asia/Shanghai",
    "iso:country":"CN",
    "name:zho_x_preferred":[
        "\u5c0f\u9752\u90e2\u6751"
    ],
    "wof:name":"Xiaoqingyingcun",
    "wof:placetype":"locality"
},
  "geometry": {"coordinates":[117.52464000000001,32.9022],"type":"Point"}
}