{
  "type": "Feature",
  "properties": {
    "gn:admin1_code":"26.0",
    "gn:asciiname":"Yantangya",
    "gn:country_code":"CN",
    "gn:dem":615,
    "gn:feature_class":"P",
    "gn:feature_code":"PPL",
    "gn:name":"Yantangya",
    "gn:population":0,
    "gn:timezone":"Asia/Shanghai",
    "iso:country":"CN",
    "name:zho_x_preferred":[
        "\u5830\u5858\u57ad"
    ],
    "wof:name":"Yantangya",
    "wof:placetype":"locality"
},
  "geometry": {"coordinates":[108.94602,32.5799],"type":"Point"}
}