{
  "type": "Feature",
  "properties": {
    "gn:admin1_code":"26.0",
    "gn:asciiname":"Wujiawan",
    "gn:country_code":"CN",
    "gn:dem":1160,
    "gn:feature_class":"P",
    "gn:feature_code":"PPL",
    "gn:name":"Wujiawan",
    "gn:population":0,
    "gn:timezone":"Asia/Shanghai",
    "iso:country":"CN",
    "name:und_x_variant":[
        "Wujiaya"
    ],
    "name:zho_x_preferred":[
        "\u5434\u5bb6\u6e7e"
    ],
    "wof:name":"Wujiawan",
    "wof:placetype":"locality"
},
  "geometry": {"coordinates":[109.00444,33.00729],"type":"Point"}
}