{
  "type": "Feature",
  "properties": {
    "gn:admin1_code":"11.0",
    "gn:asciiname":"Jinzitang",
    "gn:country_code":"CN",
    "gn:dem":83,
    "gn:feature_class":"P",
    "gn:feature_code":"PPL",
    "gn:name":"Jinzitang",
    "gn:population":0,
    "gn:timezone":"Asia/Shanghai",
    "iso:country":"CN",
    "name:zho_x_preferred":[
        "\u91d1\u5b50\u5858"
    ],
    "wof:name":"Jinzitang",
    "wof:placetype":"locality"
},
  "geometry": {"coordinates":[112.60263,26.67933],"type":"Point"}
}