{
  "type": "Feature",
  "properties": {
    "gn:admin1_code":"12.0",
    "gn:asciiname":"Zhoutuxiong",
    "gn:country_code":"CN",
    "gn:dem":36,
    "gn:feature_class":"P",
    "gn:feature_code":"PPL",
    "gn:name":"Zhoutuxiong",
    "gn:population":0,
    "gn:timezone":"Asia/Shanghai",
    "iso:country":"CN",
    "name:zho_x_preferred":[
        "\u5468\u6d82\u718a"
    ],
    "wof:name":"Zhoutuxiong",
    "wof:placetype":"locality"
},
  "geometry": {"coordinates":[113.71550999999999,31.05162],"type":"Point"}
}