{
  "type": "Feature",
  "properties": {
    "gn:admin1_code":"32.0",
    "gn:asciiname":"Jingtianba",
    "gn:country_code":"CN",
    "gn:dem":587,
    "gn:feature_class":"P",
    "gn:feature_code":"PPL",
    "gn:name":"Jingtianba",
    "gn:population":0,
    "gn:timezone":"Asia/Shanghai",
    "iso:country":"CN",
    "name:zho_x_preferred":[
        "\u4e95\u7530\u575d"
    ],
    "wof:name":"Jingtianba",
    "wof:placetype":"locality"
},
  "geometry": {"coordinates":[105.461,32.6761],"type":"Point"}
}