{
  "type": "Feature",
  "properties": {
    "gn:admin1_code":"26.0",
    "gn:asciiname":"Langhutoucun",
    "gn:country_code":"CN",
    "gn:dem":1129,
    "gn:feature_class":"P",
    "gn:feature_code":"PPL",
    "gn:name":"Langhutoucun",
    "gn:population":0,
    "gn:timezone":"Asia/Shanghai",
    "iso:country":"CN",
    "name:zho_x_preferred":[
        "\u72fc\u864e\u5934\u6751"
    ],
    "wof:name":"Langhutoucun",
    "wof:placetype":"locality"
},
  "geometry": {"coordinates":[109.22712,35.76325999999999],"type":"Point"}
}