{
  "type": "Feature",
  "properties": {
    "gn:admin1_code":"7.0",
    "gn:asciiname":"Xiachuan",
    "gn:country_code":"CN",
    "gn:dem":154,
    "gn:feature_class":"P",
    "gn:feature_code":"PPL",
    "gn:name":"Xiachuan",
    "gn:population":0,
    "gn:timezone":"Asia/Shanghai",
    "iso:country":"CN",
    "name:und_x_variant":[
        "\u4e0b\u5ddd"
    ],
    "name:zho_x_preferred":[
        "\u4e0b\u5ddd"
    ],
    "wof:name":"Xiachuan",
    "wof:placetype":"locality"
},
  "geometry": {"coordinates":[118.15638,26.04501],"type":"Point"}
}