{
  "type": "Feature",
  "properties": {
    "gn:admin1_code":"8.0",
    "gn:asciiname":"Housanjiazi",
    "gn:country_code":"CN",
    "gn:dem":191,
    "gn:feature_class":"P",
    "gn:feature_code":"PPL",
    "gn:name":"Housanjiazi",
    "gn:population":0,
    "gn:timezone":"Asia/Shanghai",
    "iso:country":"CN",
    "name:zho_x_preferred":[
        "\u540e\u4e09\u5bb6\u5b50"
    ],
    "wof:name":"Housanjiazi",
    "wof:placetype":"locality"
},
  "geometry": {"coordinates":[126.76752999999999,45.51736],"type":"Point"}
}