{
  "type": "Feature",
  "properties": {
    "gn:admin1_code":"18",
    "gn:asciiname":"Chijiao",
    "gn:country_code":"CN",
    "gn:dem":1069,
    "gn:feature_class":"P",
    "gn:feature_code":"PPL",
    "gn:name":"Chijiao",
    "gn:population":0,
    "gn:timezone":"Asia/Shanghai",
    "iso:country":"CN",
    "name:zho_x_preferred":[
        "\u6c60\u89d2"
    ],
    "wof:name":"Chijiao",
    "wof:placetype":"locality"
},
  "geometry": {"coordinates":[107.74299999999999,28.9773],"type":"Point"}
}