{
  "type": "Feature",
  "properties": {
    "gn:admin1_code":"33.0",
    "gn:asciiname":"Yuanhe",
    "gn:country_code":"CN",
    "gn:dem":238,
    "gn:feature_class":"P",
    "gn:feature_code":"PPL",
    "gn:name":"Yuanhe",
    "gn:population":0,
    "gn:timezone":"Asia/Shanghai",
    "iso:country":"CN",
    "name:zho_x_preferred":[
        "\u56ed\u6cb3"
    ],
    "wof:name":"Yuanhe",
    "wof:placetype":"locality"
},
  "geometry": {"coordinates":[108.64927,31.18498],"type":"Point"}
}