{
  "type": "Feature",
  "properties": {
    "gn:admin1_code":"1.0",
    "gn:asciiname":"Jinchongcun",
    "gn:country_code":"CN",
    "gn:dem":427,
    "gn:feature_class":"P",
    "gn:feature_code":"PPL",
    "gn:name":"Jinchongcun",
    "gn:population":0,
    "gn:timezone":"Asia/Shanghai",
    "iso:country":"CN",
    "name:zho_x_preferred":[
        "\u91d1\u51b2\u6751"
    ],
    "wof:name":"Jinchongcun",
    "wof:placetype":"locality"
},
  "geometry": {"coordinates":[116.01090000000001,31.29783],"type":"Point"}
}