{
  "type": "Feature",
  "properties": {
    "gn:admin1_code":"19.0",
    "gn:asciiname":"Wangbaokeng",
    "gn:country_code":"CN",
    "gn:dem":310,
    "gn:feature_class":"P",
    "gn:feature_code":"PPL",
    "gn:name":"Wangbaokeng",
    "gn:population":0,
    "gn:timezone":"Asia/Shanghai",
    "iso:country":"CN",
    "name:zho_x_preferred":[
        "\u738b\u5b9d\u5751"
    ],
    "wof:name":"Wangbaokeng",
    "wof:placetype":"locality"
},
  "geometry": {"coordinates":[125.05141999999999,41.03714],"type":"Point"}
}