{
  "type": "Feature",
  "properties": {
    "gn:admin1_code":"32.0",
    "gn:asciiname":"Yangpengzi",
    "gn:country_code":"CN",
    "gn:dem":2251,
    "gn:feature_class":"P",
    "gn:feature_code":"PPL",
    "gn:name":"Yangpengzi",
    "gn:population":0,
    "gn:timezone":"Asia/Shanghai",
    "iso:country":"CN",
    "name:zho_x_preferred":[
        "\u7f8a\u68da\u5b50"
    ],
    "wof:name":"Yangpengzi",
    "wof:placetype":"locality"
},
  "geometry": {"coordinates":[101.52800000000001,28.0422],"type":"Point"}
}