{
  "type": "Feature",
  "properties": {
    "gn:gn_country":"CN",
    "gn:gn_fcode":"ADM3",
    "gn:gn_pop":0,
    "iso:country":"CN",
    "name:unk_x_variant":[
        "\u4e1c\u5174\u5e02"
    ],
    "name:zho_x_preferred":[
        "Dongxing Shi"
    ],
    "qs_pg:aaroncc":"CN",
    "qs_pg:gn_country":"CN",
    "qs_pg:gn_fcode":"ADM3",
    "qs_pg:gn_pop":0,
    "qs_pg:name":"Dongxing Shi",
    "qs_pg:photos_9r":0,
    "qs_pg:photos_sr":0,
    "qs_pg:pop_sr":0,
    "qs_pg:qs_pg_placetype":"localadmin",
    "wof:name":"Dongxing Shi",
    "wof:placetype":"localadmin"
},
  "geometry": {"coordinates":[108.04843,21.61846],"type":"Point"}
}