{
  "type": "Feature",
  "properties": {
    "gn:admin1_code":"19.0",
    "gn:asciiname":"Hengdaojie",
    "gn:country_code":"CN",
    "gn:dem":3,
    "gn:feature_class":"P",
    "gn:feature_code":"PPL",
    "gn:name":"Hengdaojie",
    "gn:population":0,
    "gn:timezone":"Asia/Shanghai",
    "iso:country":"CN",
    "name:zho_x_preferred":[
        "\u8861\u9053\u8857"
    ],
    "wof:name":"Hengdaojie",
    "wof:placetype":"locality"
},
  "geometry": {"coordinates":[122.0437,41.30041],"type":"Point"}
}