{
  "type": "Feature",
  "properties": {
    "gn:admin1_code":"4.0",
    "gn:asciiname":"Xiaojuchengcun",
    "gn:country_code":"CN",
    "gn:dem":18,
    "gn:feature_class":"P",
    "gn:feature_code":"PPL",
    "gn:name":"Xiaojuchengcun",
    "gn:population":0,
    "gn:timezone":"Asia/Shanghai",
    "iso:country":"CN",
    "name:zho_x_preferred":[
        "\u5c0f\u8392\u57ce\u6751"
    ],
    "wof:name":"Xiaojuchengcun",
    "wof:placetype":"locality"
},
  "geometry": {"coordinates":[119.00653,34.90527],"type":"Point"}
}