{
  "type": "Feature",
  "properties": {
    "gn:admin1_code":"32.0",
    "gn:asciiname":"Masangba",
    "gn:country_code":"CN",
    "gn:dem":374,
    "gn:feature_class":"P",
    "gn:feature_code":"PPL",
    "gn:name":"Masangba",
    "gn:population":0,
    "gn:timezone":"Asia/Shanghai",
    "iso:country":"CN",
    "name:zho_x_preferred":[
        "\u9a6c\u6851\u575d"
    ],
    "wof:name":"Masangba",
    "wof:placetype":"locality"
},
  "geometry": {"coordinates":[105.54447999999999,30.87343],"type":"Point"}
}