{
  "type": "Feature",
  "properties": {
    "gn:admin1_code":"10",
    "gn:asciiname":"Tuoluozhai",
    "gn:country_code":"CN",
    "gn:dem":1350,
    "gn:feature_class":"P",
    "gn:feature_code":"PPL",
    "gn:name":"Tuoluozhai",
    "gn:population":0,
    "gn:timezone":"Asia/Shanghai",
    "iso:country":"CN",
    "name:zho_x_preferred":[
        "\u9a7c\u9a86\u7826"
    ],
    "wof:name":"Tuoluozhai",
    "wof:placetype":"locality"
},
  "geometry": {"coordinates":[115.97228,41.23073],"type":"Point"}
}