{
  "type": "Feature",
  "properties": {
    "gn:admin1_code":"32.0",
    "gn:asciiname":"Wenba",
    "gn:country_code":"CN",
    "gn:dem":455,
    "gn:feature_class":"P",
    "gn:feature_code":"PPL",
    "gn:name":"Wenba",
    "gn:population":0,
    "gn:timezone":"Asia/Shanghai",
    "iso:country":"CN",
    "name:zho_x_preferred":[
        "\u6587\u575d"
    ],
    "wof:name":"Wenba",
    "wof:placetype":"locality"
},
  "geometry": {"coordinates":[106.877,31.8816],"type":"Point"}
}