{
  "type": "Feature",
  "properties": {
    "gn:admin1_code":"16.0",
    "gn:asciiname":"Tongluo",
    "gn:country_code":"CN",
    "gn:dem":290,
    "gn:feature_class":"P",
    "gn:feature_code":"PPL",
    "gn:name":"Tongluo",
    "gn:population":0,
    "gn:timezone":"Asia/Shanghai",
    "iso:country":"CN",
    "name:fra_x_preferred":[
        "Tongluo"
    ],
    "name:hak_x_preferred":[
        "Th\u00f9ng-l\u00f2-hi\u00f4ng"
    ],
    "name:jpn_x_preferred":[
        "\u9285\u947c\u90f7"
    ],
    "name:kor_x_preferred":[
        "\ud241\ub904\ud5a5"
    ],
    "name:vie_x_preferred":[
        "\u0110\u1ed3ng La"
    ],
    "name:zho_x_preferred":[
        "\u94dc\u9523"
    ],
    "name:zho_x_variant":[
        "\u9285\u947c\u9109"
    ],
    "wof:name":"Tongluo",
    "wof:placetype":"locality"
},
  "geometry": {"coordinates":[111.24299999999999,24.066],"type":"Point"}
}