{
  "type": "Feature",
  "properties": {
    "gn:admin1_code":"21.0",
    "gn:asciiname":"Tonggui Wudui",
    "gn:country_code":"CN",
    "gn:dem":1109,
    "gn:feature_class":"P",
    "gn:feature_code":"PPLF",
    "gn:name":"Tonggui Wudui",
    "gn:population":0,
    "gn:timezone":"Asia/Shanghai",
    "iso:country":"CN",
    "name:zho_x_preferred":[
        "\u901a\u8d35\u4e94\u961f"
    ],
    "wof:name":"Tonggui Wudui",
    "wof:placetype":"locality"
},
  "geometry": {"coordinates":[106.51000000000001,38.4743],"type":"Point"}
}