{
  "type": "Feature",
  "properties": {
    "gn:admin1_code":"30.0",
    "gn:asciiname":"Yinglang",
    "gn:country_code":"CN",
    "gn:dem":15,
    "gn:feature_class":"P",
    "gn:feature_code":"PPL",
    "gn:name":"Yinglang",
    "gn:population":0,
    "gn:timezone":"Asia/Shanghai",
    "iso:country":"CN",
    "name:zho_x_preferred":[
        "\u9daf\u6717"
    ],
    "wof:name":"Yinglang",
    "wof:placetype":"locality"
},
  "geometry": {"coordinates":[112.93528000000001,22.76576],"type":"Point"}
}