{
  "type": "Feature",
  "properties": {
    "gn:admin1_code":"30",
    "gn:asciiname":"Dawan",
    "gn:country_code":"CN",
    "gn:dem":46,
    "gn:feature_class":"P",
    "gn:feature_code":"PPLA4",
    "gn:name":"Dawan",
    "gn:population":0,
    "gn:timezone":"Asia/Shanghai",
    "iso:country":"CN",
    "name:und_x_variant":[
        "Ta-wan",
        "Dawan",
        "\u5927\u6e7e",
        "Dawan Zhen",
        "\u5927\u6e7e\u9547"
    ],
    "wof:name":"Dawan",
    "wof:placetype":"locality"
},
  "geometry": {"coordinates":[112.93722,24.34139],"type":"Point"}
}