{
  "type": "Feature",
  "properties": {
    "gn:admin1_code":"15.0",
    "gn:asciiname":"Shashipo",
    "gn:country_code":"CN",
    "gn:dem":1280,
    "gn:feature_class":"P",
    "gn:feature_code":"PPL",
    "gn:name":"Shashipo",
    "gn:population":0,
    "gn:timezone":"Asia/Shanghai",
    "iso:country":"CN",
    "name:zho_x_preferred":[
        "\u6c99\u77f3\u5761"
    ],
    "wof:name":"Shashipo",
    "wof:placetype":"locality"
},
  "geometry": {"coordinates":[105.35599999999999,34.7314],"type":"Point"}
}