{
  "type": "Feature",
  "properties": {
    "gn:admin1_code":"29",
    "gn:asciiname":"Heiluya Xinzhai",
    "gn:country_code":"CN",
    "gn:dem":2041,
    "gn:feature_class":"P",
    "gn:feature_code":"PPL",
    "gn:name":"Heiluya Xinzhai",
    "gn:population":0,
    "gn:timezone":"Asia/Shanghai",
    "iso:country":"CN",
    "name:zho_x_preferred":[
        "\u9ed1\u8def\u4e2b\u65b0\u5be8"
    ],
    "wof:name":"Heiluya Xinzhai",
    "wof:placetype":"locality"
},
  "geometry": {"coordinates":[103.298,24.3667],"type":"Point"}
}