{
  "type": "Feature",
  "properties": {
    "gn:admin1_code":"02",
    "gn:asciiname":"Lingmencun",
    "gn:country_code":"CN",
    "gn:dem":9,
    "gn:feature_class":"P",
    "gn:feature_code":"PPL",
    "gn:name":"Lingmencun",
    "gn:population":0,
    "gn:timezone":"Asia/Shanghai",
    "iso:country":"CN",
    "name:und_x_variant":[
        "Lingmen",
        "Lingmencun"
    ],
    "name:zho_x_preferred":[
        "\u7075\u95e8"
    ],
    "name:zho_x_variant":[
        "\u7075\u95e8\u6751"
    ],
    "wof:name":"Lingmencun",
    "wof:placetype":"locality"
},
  "geometry": {"coordinates":[121.40531,28.23505],"type":"Point"}
}