{
  "type": "Feature",
  "properties": {
    "gn:admin1_code":"9.0",
    "gn:asciiname":"Dazhongyuan",
    "gn:country_code":"CN",
    "gn:dem":407,
    "gn:feature_class":"P",
    "gn:feature_code":"PPL",
    "gn:name":"Dazhongyuan",
    "gn:population":0,
    "gn:timezone":"Asia/Shanghai",
    "iso:country":"CN",
    "name:zho_x_preferred":[
        "\u5927\u4e2d\u539f"
    ],
    "wof:name":"Dazhongyuan",
    "wof:placetype":"locality"
},
  "geometry": {"coordinates":[110.91473999999999,34.5374],"type":"Point"}
}