{
  "type": "Feature",
  "properties": {
    "gn:admin1_code":"30.0",
    "gn:asciiname":"Liyuanpu",
    "gn:country_code":"CN",
    "gn:dem":30,
    "gn:feature_class":"P",
    "gn:feature_code":"PPL",
    "gn:name":"Liyuanpu",
    "gn:population":0,
    "gn:timezone":"Asia/Shanghai",
    "iso:country":"CN",
    "name:zho_x_preferred":[
        "\u7281\u56ed\u57d4"
    ],
    "wof:name":"Liyuanpu",
    "wof:placetype":"locality"
},
  "geometry": {"coordinates":[114.89493,22.8286],"type":"Point"}
}