{
  "type": "Feature",
  "properties": {
    "gn:admin1_code":"15.0",
    "gn:asciiname":"Laozhuangzi",
    "gn:country_code":"CN",
    "gn:dem":1371,
    "gn:feature_class":"P",
    "gn:feature_code":"PPL",
    "gn:name":"Laozhuangzi",
    "gn:population":0,
    "gn:timezone":"Asia/Shanghai",
    "iso:country":"CN",
    "name:und_x_variant":[
        "\u8001\u5e84\u5b50"
    ],
    "name:zho_x_preferred":[
        "\u8001\u5e84\u5b50"
    ],
    "wof:name":"Laozhuangzi",
    "wof:placetype":"locality"
},
  "geometry": {"coordinates":[104.56185000000001,33.65107],"type":"Point"}
}