{
  "type": "Feature",
  "properties": {
    "gn:admin1_code":"1.0",
    "gn:asciiname":"Wang'ancun",
    "gn:country_code":"CN",
    "gn:dem":20,
    "gn:feature_class":"P",
    "gn:feature_code":"PPL",
    "gn:name":"Wang\u2019ancun",
    "gn:population":0,
    "gn:timezone":"Asia/Shanghai",
    "iso:country":"CN",
    "name:und_x_variant":[
        "Wang\u2019ancun",
        "Wang\u2019an"
    ],
    "name:zho_x_preferred":[
        "\u738b\u5eb5\u6751"
    ],
    "wof:name":"Wang'ancun",
    "wof:placetype":"locality"
},
  "geometry": {"coordinates":[117.34999999999999,33.275],"type":"Point"}
}