{
  "type": "Feature",
  "properties": {
    "gn:admin1_code":"1.0",
    "gn:asciiname":"Changshancun",
    "gn:country_code":"CN",
    "gn:dem":183,
    "gn:feature_class":"P",
    "gn:feature_code":"PPL",
    "gn:name":"Changshancun",
    "gn:population":0,
    "gn:timezone":"Asia/Shanghai",
    "iso:country":"CN",
    "name:und_x_variant":[
        "Changshan",
        "Changshancun"
    ],
    "name:zho_x_preferred":[
        "\u957f\u5c71"
    ],
    "name:zho_x_variant":[
        "\u957f\u5c71\u6751"
    ],
    "wof:name":"Changshancun",
    "wof:placetype":"locality"
},
  "geometry": {"coordinates":[118.50771,32.54882],"type":"Point"}
}