{
  "type": "Feature",
  "properties": {
    "gn:admin1_code":"29.0",
    "gn:asciiname":"Xiaowaiji",
    "gn:country_code":"CN",
    "gn:dem":2049,
    "gn:feature_class":"P",
    "gn:feature_code":"PPL",
    "gn:name":"Xiaowaiji",
    "gn:population":0,
    "gn:timezone":"Asia/Shanghai",
    "iso:country":"CN",
    "name:zho_x_preferred":[
        "\u5c0f\u6b6a\u57fa"
    ],
    "wof:name":"Xiaowaiji",
    "wof:placetype":"locality"
},
  "geometry": {"coordinates":[104.21899999999999,26.1989],"type":"Point"}
}