{
  "type": "Feature",
  "properties": {
    "gn:admin1_code":"26.0",
    "gn:asciiname":"Liuluoyucun",
    "gn:country_code":"CN",
    "gn:dem":1234,
    "gn:feature_class":"P",
    "gn:feature_code":"PPL",
    "gn:name":"Liuluoyucun",
    "gn:population":0,
    "gn:timezone":"Asia/Shanghai",
    "iso:country":"CN",
    "name:zho_x_preferred":[
        "\u67f3\u6d1b\u5cea\u6751"
    ],
    "wof:name":"Liuluoyucun",
    "wof:placetype":"locality"
},
  "geometry": {"coordinates":[108.99018,36.4336],"type":"Point"}
}