{
  "type": "Feature",
  "properties": {
    "gn:admin1_code":"12.0",
    "gn:asciiname":"Hetiezui",
    "gn:country_code":"CN",
    "gn:dem":47,
    "gn:feature_class":"P",
    "gn:feature_code":"PPL",
    "gn:name":"Hetiezui",
    "gn:population":0,
    "gn:timezone":"Asia/Shanghai",
    "iso:country":"CN",
    "name:zho_x_preferred":[
        "\u4f55\u94c1\u5480"
    ],
    "wof:name":"Hetiezui",
    "wof:placetype":"locality"
},
  "geometry": {"coordinates":[113.89713,29.84619],"type":"Point"}
}