{
  "type": "Feature",
  "properties": {
    "gn:admin1_code":"7.0",
    "gn:asciiname":"Wuzhu",
    "gn:country_code":"CN",
    "gn:dem":39,
    "gn:feature_class":"P",
    "gn:feature_code":"PPL",
    "gn:name":"Wuzhu",
    "gn:population":0,
    "gn:timezone":"Asia/Shanghai",
    "iso:country":"CN",
    "name:rus_x_preferred":[
        "\u0412\u0430\u043d\u044c\u044f\u043d\u044c \u0423\u0447\u0436\u0443"
    ],
    "name:vie_x_preferred":[
        "Ng\u1ed9t Tru\u1eadt"
    ],
    "name:zho_x_preferred":[
        "\u4e94\u67f1"
    ],
    "wof:name":"Wuzhu",
    "wof:placetype":"locality"
},
  "geometry": {"coordinates":[118.47068,25.02263],"type":"Point"}
}