{
  "type": "Feature",
  "properties": {
    "gn:admin1_code":"12.0",
    "gn:asciiname":"Liujiabian",
    "gn:country_code":"CN",
    "gn:dem":24,
    "gn:feature_class":"P",
    "gn:feature_code":"PPL",
    "gn:name":"Liujiabian",
    "gn:population":0,
    "gn:timezone":"Asia/Shanghai",
    "iso:country":"CN",
    "name:und_x_variant":[
        "\u67f3\u5bb6\u8fb9"
    ],
    "wof:name":"Liujiabian",
    "wof:placetype":"locality"
},
  "geometry": {"coordinates":[114.38676,30.16183],"type":"Point"}
}