{
  "type": "Feature",
  "properties": {
    "gn:admin1_code":"30.0",
    "gn:asciiname":"Tubei",
    "gn:country_code":"CN",
    "gn:dem":54,
    "gn:feature_class":"P",
    "gn:feature_code":"PPL",
    "gn:name":"Tubei",
    "gn:population":0,
    "gn:timezone":"Asia/Shanghai",
    "iso:country":"CN",
    "name:und_x_variant":[
        "\u571f\u9642"
    ],
    "name:zho_x_preferred":[
        "\u571f\u9642"
    ],
    "wof:name":"Tubei",
    "wof:placetype":"locality"
},
  "geometry": {"coordinates":[115.09529000000001,23.95847],"type":"Point"}
}