{
  "type": "Feature",
  "properties": {
    "gn:admin1_code":"11.0",
    "gn:asciiname":"Jiuzhoubang",
    "gn:country_code":"CN",
    "gn:dem":68,
    "gn:feature_class":"P",
    "gn:feature_code":"PPL",
    "gn:name":"Jiuzhoubang",
    "gn:population":0,
    "gn:timezone":"Asia/Shanghai",
    "iso:country":"CN",
    "name:und_x_variant":[
        "\u4e5d\u6d32\u585d"
    ],
    "wof:name":"Jiuzhoubang",
    "wof:placetype":"locality"
},
  "geometry": {"coordinates":[111.67664000000001,29.34969],"type":"Point"}
}