{
  "type": "Feature",
  "properties": {
    "gn:admin1_code":"5.0",
    "gn:asciiname":"Shimiaogou",
    "gn:country_code":"CN",
    "gn:dem":507,
    "gn:feature_class":"P",
    "gn:feature_code":"PPL",
    "gn:name":"Shimiaogou",
    "gn:population":0,
    "gn:timezone":"Asia/Shanghai",
    "iso:country":"CN",
    "name:und_x_variant":[
        "\u77f3\u5e99\u6c9f"
    ],
    "wof:name":"Shimiaogou",
    "wof:placetype":"locality"
},
  "geometry": {"coordinates":[125.36162,41.77557],"type":"Point"}
}