{
  "type": "Feature",
  "properties": {
    "gn:admin1_code":"8.0",
    "gn:asciiname":"Huangmingshan",
    "gn:country_code":"CN",
    "gn:dem":370,
    "gn:feature_class":"P",
    "gn:feature_code":"PPL",
    "gn:name":"Huangmingshan",
    "gn:population":0,
    "gn:timezone":"Asia/Shanghai",
    "iso:country":"CN",
    "name:zho_x_preferred":[
        "\u9ec4\u660e\u5c71"
    ],
    "wof:name":"Huangmingshan",
    "wof:placetype":"locality"
},
  "geometry": {"coordinates":[126.67468,49.16667],"type":"Point"}
}