{
  "type": "Feature",
  "properties": {
    "gn:admin1_code":"14.0",
    "gn:asciiname":"Zongbakacun",
    "gn:country_code":"CN",
    "gn:dem":4053,
    "gn:feature_class":"P",
    "gn:feature_code":"PPL",
    "gn:name":"Zongbakacun",
    "gn:population":0,
    "gn:timezone":"Asia/Urumqi",
    "iso:country":"CN",
    "name:zho_x_preferred":[
        "\u5b97\u5df4\u5494\u6751"
    ],
    "wof:name":"Zongbakacun",
    "wof:placetype":"locality"
},
  "geometry": {"coordinates":[93.96832999999999,31.54109],"type":"Point"}
}