{
  "type": "Feature",
  "properties": {
    "gn:admin1_code":"4.0",
    "gn:asciiname":"Dalizhuangcun",
    "gn:country_code":"CN",
    "gn:dem":42,
    "gn:feature_class":"P",
    "gn:feature_code":"PPL",
    "gn:name":"Dalizhuangcun",
    "gn:population":0,
    "gn:timezone":"Asia/Shanghai",
    "iso:country":"CN",
    "name:und_x_variant":[
        "Dalizhuang",
        "Dalizhuangcun"
    ],
    "name:zho_x_preferred":[
        "\u5927\u674e\u5e84"
    ],
    "name:zho_x_variant":[
        "\u5927\u674e\u5e84\u6751"
    ],
    "wof:name":"Dalizhuangcun",
    "wof:placetype":"locality"
},
  "geometry": {"coordinates":[116.58289000000001,34.74231],"type":"Point"}
}