{
  "type": "Feature",
  "properties": {
    "gn:admin1_code":"6.0",
    "gn:asciiname":"Zhale Baji",
    "gn:country_code":"CN",
    "gn:dem":4124,
    "gn:feature_class":"P",
    "gn:feature_code":"PPL",
    "gn:name":"Zhale Baji",
    "gn:population":0,
    "gn:timezone":"Asia/Urumqi",
    "iso:country":"CN",
    "name:zho_x_preferred":[
        "\u624e\u52d2\u5df4\u5409"
    ],
    "wof:name":"Zhale Baji",
    "wof:placetype":"locality"
},
  "geometry": {"coordinates":[95.66249999999999,32.50131],"type":"Point"}
}