{
  "type": "Feature",
  "properties": {
    "gn:admin1_code":"32.0",
    "gn:asciiname":"Lake",
    "gn:country_code":"CN",
    "gn:dem":1821,
    "gn:feature_class":"P",
    "gn:feature_code":"PPL",
    "gn:name":"Lake",
    "gn:population":0,
    "gn:timezone":"Asia/Shanghai",
    "iso:country":"CN",
    "name:zho_x_preferred":[
        "\u62c9\u514b"
    ],
    "wof:name":"Lake",
    "wof:placetype":"locality"
},
  "geometry": {"coordinates":[102.35093000000001,28.34187],"type":"Point"}
}