{
  "type": "Feature",
  "properties": {
    "gn:admin1_code":"29.0",
    "gn:asciiname":"Zhongheying",
    "gn:cc2":"CN",
    "gn:country_code":"CN",
    "gn:dem":1594,
    "gn:feature_class":"P",
    "gn:feature_code":"PPL",
    "gn:name":"Zhongheying",
    "gn:population":0,
    "gn:timezone":"Asia/Shanghai",
    "iso:country":"CN",
    "name:und_x_variant":[
        "Chung-ho-ying",
        "Zhongheying"
    ],
    "wof:name":"Zhongheying",
    "wof:placetype":"locality"
},
  "geometry": {"coordinates":[103.66667,23.71667],"type":"Point"}
}