{
  "type": "Feature",
  "properties": {
    "gn:admin1_code":"4.0",
    "gn:asciiname":"Shengjiacun",
    "gn:country_code":"CN",
    "gn:dem":33,
    "gn:feature_class":"P",
    "gn:feature_code":"PPL",
    "gn:name":"Shengjiacun",
    "gn:population":0,
    "gn:timezone":"Asia/Shanghai",
    "iso:country":"CN",
    "name:zho_x_preferred":[
        "\u76db\u5bb6\u6751"
    ],
    "wof:name":"Shengjiacun",
    "wof:placetype":"locality"
},
  "geometry": {"coordinates":[117.89752,34.61493],"type":"Point"}
}