{
  "type": "Feature",
  "properties": {
    "gn:admin1_code":"25.0",
    "gn:asciiname":"Matoucun",
    "gn:country_code":"CN",
    "gn:dem":7,
    "gn:feature_class":"P",
    "gn:feature_code":"PPL",
    "gn:name":"Matoucun",
    "gn:population":0,
    "gn:timezone":"Asia/Shanghai",
    "iso:country":"CN",
    "name:zho_x_preferred":[
        "\u7801\u5934\u6751"
    ],
    "wof:name":"Matoucun",
    "wof:placetype":"locality"
},
  "geometry": {"coordinates":[122.37161,36.85123],"type":"Point"}
}