{
  "type": "Feature",
  "properties": {
    "gn:admin1_code":"5.0",
    "gn:asciiname":"Xiaoshiren Lamen",
    "gn:country_code":"CN",
    "gn:dem":580,
    "gn:feature_class":"P",
    "gn:feature_code":"PPL",
    "gn:name":"Xiaoshiren Lamen",
    "gn:population":0,
    "gn:timezone":"Asia/Shanghai",
    "iso:country":"CN",
    "name:und_x_variant":[
        "\u5c0f\u77f3\u4eba\u782c\u95e8"
    ],
    "wof:name":"Xiaoshiren Lamen",
    "wof:placetype":"locality"
},
  "geometry": {"coordinates":[126.56755,41.92395],"type":"Point"}
}