{
  "type": "Feature",
  "properties": {
    "gn:admin1_code":"32.0",
    "gn:asciiname":"Baixiayi",
    "gn:country_code":"CN",
    "gn:dem":2360,
    "gn:feature_class":"P",
    "gn:feature_code":"PPL",
    "gn:name":"Baixiayi",
    "gn:population":0,
    "gn:timezone":"Asia/Shanghai",
    "iso:country":"CN",
    "name:zho_x_preferred":[
        "\u767d\u5477\u8863"
    ],
    "wof:name":"Baixiayi",
    "wof:placetype":"locality"
},
  "geometry": {"coordinates":[101.88,30.8688],"type":"Point"}
}