{
  "type": "Feature",
  "properties": {
    "gn:admin1_code":"30.0",
    "gn:asciiname":"Gongnong",
    "gn:country_code":"CN",
    "gn:dem":13,
    "gn:feature_class":"P",
    "gn:feature_code":"PPLA4",
    "gn:name":"Gongnong",
    "gn:population":0,
    "gn:timezone":"Asia/Urumqi",
    "iso:country":"CN",
    "name:ceb_x_preferred":[
        "Gongnong"
    ],
    "name:deu_x_preferred":[
        "Gongnong"
    ],
    "name:und_x_variant":[
        "Gongnong Jiedao"
    ],
    "name:zho_x_preferred":[
        "\u5de5\u519c"
    ],
    "name:zho_x_variant":[
        "\u5de5\u519c\u8857\u9053"
    ],
    "wof:name":"Gongnong",
    "wof:placetype":"locality"
},
  "geometry": {"coordinates":[110.3948,21.19293],"type":"Point"}
}