{
  "type": "Feature",
  "properties": {
    "gn:admin1_code":"20.0",
    "gn:asciiname":"Wufuxianggou",
    "gn:country_code":"CN",
    "gn:dem":517,
    "gn:feature_class":"P",
    "gn:feature_code":"PPL",
    "gn:name":"Wufuxianggou",
    "gn:population":0,
    "gn:timezone":"Asia/Shanghai",
    "iso:country":"CN",
    "name:zho_x_preferred":[
        "\u5434\u798f\u7965\u6c9f"
    ],
    "wof:name":"Wufuxianggou",
    "wof:placetype":"locality"
},
  "geometry": {"coordinates":[122.70650000000001,48.31800000000001],"type":"Point"}
}