{
  "type": "Feature",
  "properties": {
    "gn:admin1_code":"19.0",
    "gn:asciiname":"Yizishan",
    "gn:country_code":"CN",
    "gn:dem":208,
    "gn:feature_class":"P",
    "gn:feature_code":"PPL",
    "gn:name":"Yizishan",
    "gn:population":0,
    "gn:timezone":"Asia/Shanghai",
    "iso:country":"CN",
    "name:und_x_variant":[
        "\u6905\u5b50\u5c71"
    ],
    "name:zho_x_preferred":[
        "\u6905\u5b50\u5c71"
    ],
    "wof:name":"Yizishan",
    "wof:placetype":"locality"
},
  "geometry": {"coordinates":[123.25342000000001,40.47791],"type":"Point"}
}