{
  "type": "Feature",
  "properties": {
    "gn:admin1_code":"11.0",
    "gn:asciiname":"Zhaojidong",
    "gn:country_code":"CN",
    "gn:dem":209,
    "gn:feature_class":"P",
    "gn:feature_code":"PPL",
    "gn:name":"Zhaojidong",
    "gn:population":0,
    "gn:timezone":"Asia/Shanghai",
    "iso:country":"CN",
    "name:zho_x_preferred":[
        "\u5146\u5409\u6d1e"
    ],
    "wof:name":"Zhaojidong",
    "wof:placetype":"locality"
},
  "geometry": {"coordinates":[113.03113,25.67124],"type":"Point"}
}