{
  "type": "Feature",
  "properties": {
    "gn:admin1_code":"31.0",
    "gn:asciiname":"Wentou",
    "gn:country_code":"CN",
    "gn:dem":32,
    "gn:feature_class":"P",
    "gn:feature_code":"PPL",
    "gn:name":"Wentou",
    "gn:population":0,
    "gn:timezone":"Asia/Shanghai",
    "iso:country":"CN",
    "name:zho_x_preferred":[
        "\u868a\u5934"
    ],
    "wof:name":"Wentou",
    "wof:placetype":"locality"
},
  "geometry": {"coordinates":[110.46415,19.7274],"type":"Point"}
}