{
  "type": "Feature",
  "properties": {
    "gn:admin1_code":"8.0",
    "gn:asciiname":"Zhengliangtun",
    "gn:country_code":"CN",
    "gn:dem":129,
    "gn:feature_class":"P",
    "gn:feature_code":"PPL",
    "gn:name":"Zhengliangtun",
    "gn:population":0,
    "gn:timezone":"Asia/Shanghai",
    "iso:country":"CN",
    "name:zho_x_preferred":[
        "\u90d1\u4eae\u5c6f"
    ],
    "wof:name":"Zhengliangtun",
    "wof:placetype":"locality"
},
  "geometry": {"coordinates":[127.51873000000001,46.0746],"type":"Point"}
}