{
  "type": "Feature",
  "properties": {
    "gn:admin1_code":"31.0",
    "gn:asciiname":"Kongpozui",
    "gn:country_code":"CN",
    "gn:dem":180,
    "gn:feature_class":"P",
    "gn:feature_code":"PPL",
    "gn:name":"Kongpozui",
    "gn:population":0,
    "gn:timezone":"Asia/Shanghai",
    "iso:country":"CN",
    "name:zho_x_preferred":[
        "\u7a7a\u5761\u6700"
    ],
    "wof:name":"Kongpozui",
    "wof:placetype":"locality"
},
  "geometry": {"coordinates":[109.05964,18.72907],"type":"Point"}
}