{
  "type": "Feature",
  "properties": {
    "gn:admin1_code":"3.0",
    "gn:asciiname":"Taoyuan",
    "gn:country_code":"CN",
    "gn:dem":123,
    "gn:feature_class":"P",
    "gn:feature_code":"PPL",
    "gn:name":"Taoyuan",
    "gn:population":0,
    "gn:timezone":"Asia/Shanghai",
    "iso:country":"CN",
    "name:und_x_variant":[
        "\u6843\u6e90"
    ],
    "wof:name":"Taoyuan",
    "wof:placetype":"locality"
},
  "geometry": {"coordinates":[114.32452000000001,28.12356],"type":"Point"}
}