{
  "type": "Feature",
  "properties": {
    "gn:admin1_code":"18",
    "gn:asciiname":"Tangren",
    "gn:cc2":"CN",
    "gn:country_code":"CN",
    "gn:dem":661,
    "gn:feature_class":"P",
    "gn:feature_code":"PPL",
    "gn:name":"Tangren",
    "gn:population":0,
    "gn:timezone":"Asia/Shanghai",
    "iso:country":"CN",
    "name:und_x_variant":[
        "T\u2019ang-jen",
        "Tangren"
    ],
    "wof:name":"Tangren",
    "wof:placetype":"locality"
},
  "geometry": {"coordinates":[109.34139,26.90667],"type":"Point"}
}