{
  "type": "Feature",
  "properties": {
    "gn:admin1_code":"3.0",
    "gn:asciiname":"Balishan",
    "gn:country_code":"CN",
    "gn:dem":405,
    "gn:feature_class":"P",
    "gn:feature_code":"PPL",
    "gn:name":"Balishan",
    "gn:population":0,
    "gn:timezone":"Asia/Shanghai",
    "iso:country":"CN",
    "name:und_x_variant":[
        "\u516b\u91cc\u5c71"
    ],
    "wof:name":"Balishan",
    "wof:placetype":"locality"
},
  "geometry": {"coordinates":[115.26691,29.53415],"type":"Point"}
}