{
  "type": "Feature",
  "properties": {
    "gn:admin1_code":"12.0",
    "gn:asciiname":"Wanghuang",
    "gn:country_code":"CN",
    "gn:dem":39,
    "gn:feature_class":"P",
    "gn:feature_code":"PPL",
    "gn:name":"Wanghuang",
    "gn:population":0,
    "gn:timezone":"Asia/Shanghai",
    "iso:country":"CN",
    "name:und_x_variant":[
        "\u6c6a\u9ec4"
    ],
    "wof:name":"Wanghuang",
    "wof:placetype":"locality"
},
  "geometry": {"coordinates":[114.66595,30.05296],"type":"Point"}
}