{
  "type": "Feature",
  "properties": {
    "gn:admin1_code":"8.0",
    "gn:asciiname":"Jiahuangtun",
    "gn:country_code":"CN",
    "gn:dem":274,
    "gn:feature_class":"P",
    "gn:feature_code":"PPL",
    "gn:name":"Jiahuangtun",
    "gn:population":0,
    "gn:timezone":"Asia/Shanghai",
    "iso:country":"CN",
    "name:zho_x_preferred":[
        "\u5939\u8352\u5c6f"
    ],
    "wof:name":"Jiahuangtun",
    "wof:placetype":"locality"
},
  "geometry": {"coordinates":[126.06467000000001,48.13062],"type":"Point"}
}