{
  "type": "Feature",
  "properties": {
    "gn:admin1_code":"7.0",
    "gn:asciiname":"Shangdi",
    "gn:country_code":"CN",
    "gn:dem":545,
    "gn:feature_class":"P",
    "gn:feature_code":"PPL",
    "gn:name":"Shangdi",
    "gn:population":0,
    "gn:timezone":"Asia/Shanghai",
    "iso:country":"CN",
    "name:bel_x_preferred":[
        "\u0428\u0430\u043d\u0434\u0437\u0456"
    ],
    "name:cat_x_preferred":[
        "Shangdi"
    ],
    "name:fas_x_preferred":[
        "\u0634\u0627\u0646\u06af\u062f\u06cc"
    ],
    "name:fra_x_preferred":[
        "Shang Di"
    ],
    "name:hun_x_preferred":[
        "Sang-ti"
    ],
    "name:ind_x_preferred":[
        "Shangdi"
    ],
    "name:ita_x_preferred":[
        "Shang Di"
    ],
    "name:msa_x_preferred":[
        "Shangdi"
    ],
    "name:nor_x_preferred":[
        "Shangdi"
    ],
    "name:pol_x_preferred":[
        "Shangdi"
    ],
    "name:por_x_preferred":[
        "Shangdi"
    ],
    "name:spa_x_preferred":[
        "Shangdi"
    ],
    "name:swe_x_preferred":[
        "Shang Di"
    ],
    "name:tur_x_preferred":[
        "Shangdi"
    ],
    "name:ukr_x_preferred":[
        "\u0428\u0430\u043d-\u0434\u0456"
    ],
    "name:vie_x_preferred":[
        "Th\u01b0\u1ee3ng \u0111\u1ebf"
    ],
    "name:zho_x_preferred":[
        "\u4e0a\u5730"
    ],
    "wof:name":"Shangdi",
    "wof:placetype":"locality"
},
  "geometry": {"coordinates":[116.05512,25.32916],"type":"Point"}
}