{
  "type": "Feature",
  "properties": {
    "gn:admin1_code":"26.0",
    "gn:asciiname":"Yangjiagou",
    "gn:country_code":"CN",
    "gn:dem":984,
    "gn:feature_class":"P",
    "gn:feature_code":"PPL",
    "gn:name":"Yangjiagou",
    "gn:population":0,
    "gn:timezone":"Asia/Shanghai",
    "iso:country":"CN",
    "name:zho_x_preferred":[
        "\u6768\u5bb6\u6c9f"
    ],
    "wof:name":"Yangjiagou",
    "wof:placetype":"locality"
},
  "geometry": {"coordinates":[109.88289,33.37572],"type":"Point"}
}