{
  "type": "Feature",
  "properties": {
    "gn:admin1_code":"29.0",
    "gn:asciiname":"Lijia Maidi",
    "gn:country_code":"CN",
    "gn:dem":2185,
    "gn:feature_class":"P",
    "gn:feature_code":"PPL",
    "gn:name":"Lijia Maidi",
    "gn:population":0,
    "gn:timezone":"Asia/Shanghai",
    "iso:country":"CN",
    "name:zho_x_preferred":[
        "\u674e\u5bb6\u9ea6\u5730"
    ],
    "wof:name":"Lijia Maidi",
    "wof:placetype":"locality"
},
  "geometry": {"coordinates":[103.43899999999999,25.8645],"type":"Point"}
}