{
  "type": "Feature",
  "properties": {
    "gn:admin1_code":"32.0",
    "gn:asciiname":"Qingshuzi",
    "gn:country_code":"CN",
    "gn:dem":614,
    "gn:feature_class":"P",
    "gn:feature_code":"PPL",
    "gn:name":"Qingshuzi",
    "gn:population":0,
    "gn:timezone":"Asia/Shanghai",
    "iso:country":"CN",
    "name:zho_x_preferred":[
        "\u9752\u6811\u5b50"
    ],
    "wof:name":"Qingshuzi",
    "wof:placetype":"locality"
},
  "geometry": {"coordinates":[105.46042,32.79087],"type":"Point"}
}