{
  "type": "Feature",
  "properties": {
    "gn:admin1_code":"14.0",
    "gn:asciiname":"Gemagongma",
    "gn:country_code":"CN",
    "gn:dem":4608,
    "gn:feature_class":"P",
    "gn:feature_code":"PPL",
    "gn:name":"Gemagongma",
    "gn:population":0,
    "gn:timezone":"Asia/Urumqi",
    "iso:country":"CN",
    "name:zho_x_preferred":[
        "\u683c\u9a6c\u8d21\u9a6c"
    ],
    "wof:name":"Gemagongma",
    "wof:placetype":"locality"
},
  "geometry": {"coordinates":[91.55486000000001,31.34311],"type":"Point"}
}