{
  "type": "Feature",
  "properties": {
    "gn:admin1_code":"29.0",
    "gn:asciiname":"Mu'aka",
    "gn:country_code":"CN",
    "gn:dem":1307,
    "gn:feature_class":"P",
    "gn:feature_code":"PPL",
    "gn:name":"Mu\u2019aka",
    "gn:population":0,
    "gn:timezone":"Asia/Shanghai",
    "iso:country":"CN",
    "name:und_x_variant":[
        "Mu\u2019aka"
    ],
    "name:zho_x_preferred":[
        "\u6728\u963f\u5361"
    ],
    "wof:name":"Mu'aka",
    "wof:placetype":"locality"
},
  "geometry": {"coordinates":[97.78449999999999,24.6432],"type":"Point"}
}