{
  "type": "Feature",
  "properties": {
    "gn:admin1_code":"11.0",
    "gn:asciiname":"Caoyuan",
    "gn:country_code":"CN",
    "gn:dem":306,
    "gn:feature_class":"P",
    "gn:feature_code":"PPL",
    "gn:name":"Caoyuan",
    "gn:population":0,
    "gn:timezone":"Asia/Shanghai",
    "iso:country":"CN",
    "name:zho_x_preferred":[
        "\u8349\u56ed"
    ],
    "wof:name":"Caoyuan",
    "wof:placetype":"locality"
},
  "geometry": {"coordinates":[109.64467999999999,26.56527],"type":"Point"}
}