{
  "type": "Feature",
  "properties": {
    "gn:admin1_code":"1.0",
    "gn:asciiname":"Xizhangcun",
    "gn:country_code":"CN",
    "gn:dem":73,
    "gn:feature_class":"P",
    "gn:feature_code":"PPL",
    "gn:name":"Xizhangcun",
    "gn:population":0,
    "gn:timezone":"Asia/Shanghai",
    "iso:country":"CN",
    "name:zho_x_preferred":[
        "\u897f\u5f20\u6751"
    ],
    "wof:name":"Xizhangcun",
    "wof:placetype":"locality"
},
  "geometry": {"coordinates":[117.88352999999999,32.18664],"type":"Point"}
}