{
  "type": "Feature",
  "properties": {
    "gn:admin1_code":"02",
    "gn:asciiname":"Gongqian",
    "gn:country_code":"CN",
    "gn:dem":14,
    "gn:feature_class":"P",
    "gn:feature_code":"PPLA4",
    "gn:name":"Gongqian",
    "gn:population":0,
    "gn:timezone":"Asia/Shanghai",
    "iso:country":"CN",
    "name:und_x_variant":[
        "Kuan-chien-ts\u2019un",
        "Gongqian",
        "\u516c\u524d",
        "Taohua Zhen",
        "Taohua",
        "\u6843\u82b1\u9547",
        "\u6843\u82b1"
    ],
    "wof:name":"Gongqian",
    "wof:placetype":"locality"
},
  "geometry": {"coordinates":[122.2765,29.83279000000001],"type":"Point"}
}