{
  "type": "Feature",
  "properties": {
    "gn:admin1_code":"24.0",
    "gn:asciiname":"Yangquanhui",
    "gn:cc2":"CN",
    "gn:country_code":"CN",
    "gn:dem":1630,
    "gn:feature_class":"P",
    "gn:feature_code":"PPL",
    "gn:name":"Yangquanhui",
    "gn:population":0,
    "gn:timezone":"Asia/Shanghai",
    "iso:country":"CN",
    "name:und_x_variant":[
        "Yang-ch\u2019\u00fcan-hui",
        "Yangquanhui"
    ],
    "wof:name":"Yangquanhui",
    "wof:placetype":"locality"
},
  "geometry": {"coordinates":[111.66667,38.76667],"type":"Point"}
}