{
  "type": "Feature",
  "properties": {
    "gn:admin1_code":"4.0",
    "gn:asciiname":"Xizhangxiacun",
    "gn:country_code":"CN",
    "gn:dem":16,
    "gn:feature_class":"P",
    "gn:feature_code":"PPL",
    "gn:name":"Xizhangxiacun",
    "gn:population":0,
    "gn:timezone":"Asia/Shanghai",
    "iso:country":"CN",
    "name:zho_x_preferred":[
        "\u897f\u5f20\u590f\u6751"
    ],
    "wof:name":"Xizhangxiacun",
    "wof:placetype":"locality"
},
  "geometry": {"coordinates":[119.04651,34.96728],"type":"Point"}
}