{
  "type": "Feature",
  "properties": {
    "gn:admin1_code":"21.0",
    "gn:asciiname":"Huangquwan",
    "gn:country_code":"CN",
    "gn:dem":1991,
    "gn:feature_class":"P",
    "gn:feature_code":"PPL",
    "gn:name":"Huangquwan",
    "gn:population":0,
    "gn:timezone":"Asia/Shanghai",
    "iso:country":"CN",
    "name:zho_x_preferred":[
        "\u9ec4\u6e20\u6e7e"
    ],
    "wof:name":"Huangquwan",
    "wof:placetype":"locality"
},
  "geometry": {"coordinates":[106.051,35.6822],"type":"Point"}
}