{
  "type": "Feature",
  "properties": {
    "gn:admin1_code":"11.0",
    "gn:asciiname":"Miaoguai",
    "gn:country_code":"CN",
    "gn:dem":33,
    "gn:feature_class":"P",
    "gn:feature_code":"PPL",
    "gn:name":"Miaoguai",
    "gn:population":0,
    "gn:timezone":"Asia/Shanghai",
    "iso:country":"CN",
    "name:zho_x_preferred":[
        "Miaoguai"
    ],
    "name:zho_x_variant":[
        "\u5e99\u62d0"
    ],
    "wof:name":"Miaoguai",
    "wof:placetype":"locality"
},
  "geometry": {"coordinates":[112.04498999999998,29.53697],"type":"Point"}
}