{
  "type": "Feature",
  "properties": {
    "gn:admin1_code":"8.0",
    "gn:asciiname":"Xiaogungou",
    "gn:country_code":"CN",
    "gn:dem":160,
    "gn:feature_class":"P",
    "gn:feature_code":"PPL",
    "gn:name":"Xiaogungou",
    "gn:population":0,
    "gn:timezone":"Asia/Shanghai",
    "iso:country":"CN",
    "name:zho_x_preferred":[
        "\u5c0f\u78d9\u6c9f"
    ],
    "wof:name":"Xiaogungou",
    "wof:placetype":"locality"
},
  "geometry": {"coordinates":[130.27767,48.8374],"type":"Point"}
}