{
  "type": "Feature",
  "properties": {
    "gn:admin1_code":"26.0",
    "gn:asciiname":"Guanjialing",
    "gn:country_code":"CN",
    "gn:dem":942,
    "gn:feature_class":"P",
    "gn:feature_code":"PPL",
    "gn:name":"Guanjialing",
    "gn:population":0,
    "gn:timezone":"Asia/Shanghai",
    "iso:country":"CN",
    "name:zho_x_preferred":[
        "\u5173\u5bb6\u5cad"
    ],
    "wof:name":"Guanjialing",
    "wof:placetype":"locality"
},
  "geometry": {"coordinates":[109.76743999999999,33.54254],"type":"Point"}
}