{
  "type": "Feature",
  "properties": {
    "gn:admin1_code":"14.0",
    "gn:asciiname":"Suo'ergang",
    "gn:country_code":"CN",
    "gn:dem":4316,
    "gn:feature_class":"P",
    "gn:feature_code":"PPL",
    "gn:name":"Suo\u2019ergang",
    "gn:population":0,
    "gn:timezone":"Asia/Shanghai",
    "iso:country":"CN",
    "name:und_x_variant":[
        "Suo\u2019ergang"
    ],
    "name:zho_x_preferred":[
        "\u7d22\u5c14\u5c97"
    ],
    "wof:name":"Suo'ergang",
    "wof:placetype":"locality"
},
  "geometry": {"coordinates":[79.6116,31.9125],"type":"Point"}
}