{
  "type": "Feature",
  "properties": {
    "gn:admin1_code":"07",
    "gn:asciiname":"Yangzhong",
    "gn:country_code":"CN",
    "gn:dem":839,
    "gn:feature_class":"P",
    "gn:feature_code":"PPL",
    "gn:name":"Yangzhong",
    "gn:population":0,
    "gn:timezone":"Asia/Shanghai",
    "iso:country":"CN",
    "name:zho_x_preferred":[
        "\u6d0b\u4e2d"
    ],
    "wof:name":"Yangzhong",
    "wof:placetype":"locality"
},
  "geometry": {"coordinates":[117.80970000000001,25.31742],"type":"Point"}
}