{
  "type": "Feature",
  "properties": {
    "gn:admin1_code":"30.0",
    "gn:asciiname":"Shinano",
    "gn:country_code":"CN",
    "gn:dem":27,
    "gn:feature_class":"P",
    "gn:feature_code":"PPL",
    "gn:name":"Shinano",
    "gn:population":0,
    "gn:timezone":"Asia/Shanghai",
    "iso:country":"CN",
    "name:bul_x_preferred":[
        "\u0428\u0438\u043d\u0430\u043d\u043e"
    ],
    "name:ceb_x_preferred":[
        "Shinano"
    ],
    "name:deu_x_preferred":[
        "Shinano"
    ],
    "name:fra_x_preferred":[
        "Shinano"
    ],
    "name:ita_x_preferred":[
        "Shinano"
    ],
    "name:nld_x_preferred":[
        "Shinano"
    ],
    "name:por_x_preferred":[
        "Shinano"
    ],
    "name:rus_x_preferred":[
        "\u0421\u0438\u043d\u0430\u043d\u043e"
    ],
    "name:slk_x_preferred":[
        "\u0160inano"
    ],
    "name:spa_x_preferred":[
        "Shinano"
    ],
    "name:ukr_x_preferred":[
        "\u0421\u0456\u043d\u0430\u043d\u043e"
    ],
    "name:vie_x_preferred":[
        "Shinano"
    ],
    "name:zho_x_preferred":[
        "\u72ee\u8111"
    ],
    "wof:name":"Shinano",
    "wof:placetype":"locality"
},
  "geometry": {"coordinates":[112.81578,23.4901],"type":"Point"}
}