{
  "type": "Feature",
  "properties": {
    "gn:admin1_code":"29.0",
    "gn:asciiname":"Laku",
    "gn:country_code":"CN",
    "gn:dem":2036,
    "gn:feature_class":"P",
    "gn:feature_code":"PPL",
    "gn:name":"Laku",
    "gn:population":0,
    "gn:timezone":"Asia/Shanghai",
    "iso:country":"CN",
    "name:zho_x_preferred":[
        "\u814a\u82e6"
    ],
    "wof:name":"Laku",
    "wof:placetype":"locality"
},
  "geometry": {"coordinates":[100.54000000000001,24.9392],"type":"Point"}
}