{
  "type": "Feature",
  "properties": {
    "gn:admin1_code":"32.0",
    "gn:asciiname":"Zhonghai",
    "gn:country_code":"CN",
    "gn:dem":1230,
    "gn:feature_class":"P",
    "gn:feature_code":"PPL",
    "gn:name":"Zhonghai",
    "gn:population":0,
    "gn:timezone":"Asia/Shanghai",
    "iso:country":"CN",
    "name:zho_x_preferred":[
        "\u4e2d\u6d77"
    ],
    "wof:name":"Zhonghai",
    "wof:placetype":"locality"
},
  "geometry": {"coordinates":[102.71299999999999,29.3338],"type":"Point"}
}