{
  "type": "Feature",
  "properties": {
    "gn:admin1_code":"20.0",
    "gn:asciiname":"Xilei",
    "gn:country_code":"CN",
    "gn:dem":1634,
    "gn:feature_class":"P",
    "gn:feature_code":"PPLA4",
    "gn:name":"Xilei",
    "gn:population":0,
    "gn:timezone":"Asia/Shanghai",
    "iso:country":"CN",
    "name:und_x_variant":[
        "\u9521\u52d2",
        "Yuanjiafang",
        "\u8881\u5bb6\u574a"
    ],
    "wof:name":"Xilei",
    "wof:placetype":"locality"
},
  "geometry": {"coordinates":[112.92104,41.28361],"type":"Point"}
}