{
  "type": "Feature",
  "properties": {
    "gn:admin1_code":"9",
    "gn:asciiname":"Zhangranfang",
    "gn:country_code":"CN",
    "gn:dem":41,
    "gn:feature_class":"P",
    "gn:feature_code":"PPL",
    "gn:name":"Zhangranfang",
    "gn:population":0,
    "gn:timezone":"Asia/Shanghai",
    "iso:country":"CN",
    "name:zho_x_preferred":[
        "\u5f20\u5189\u574a"
    ],
    "wof:name":"Zhangranfang",
    "wof:placetype":"locality"
},
  "geometry": {"coordinates":[116.364,34.1555],"type":"Point"}
}