{
  "type": "Feature",
  "properties": {
    "gn:admin1_code":"21.0",
    "gn:asciiname":"Qianwowo",
    "gn:country_code":"CN",
    "gn:dem":1658,
    "gn:feature_class":"P",
    "gn:feature_code":"PPL",
    "gn:name":"Qianwowo",
    "gn:population":0,
    "gn:timezone":"Asia/Shanghai",
    "iso:country":"CN",
    "name:und_x_variant":[
        "\u524d\u7a9d\u7a9d"
    ],
    "name:zho_x_preferred":[
        "\u524d\u7a9d\u7a9d"
    ],
    "wof:name":"Qianwowo",
    "wof:placetype":"locality"
},
  "geometry": {"coordinates":[106.53279999999999,36.11151],"type":"Point"}
}