{
  "type": "Feature",
  "properties": {
    "gn:admin1_code":"05",
    "gn:asciiname":"Jingsong Linchang",
    "gn:country_code":"CN",
    "gn:dem":619,
    "gn:feature_class":"P",
    "gn:feature_code":"PPLF",
    "gn:name":"Jingsong Linchang",
    "gn:population":0,
    "gn:timezone":"Asia/Shanghai",
    "iso:country":"CN",
    "name:und_x_variant":[
        "\u52b2\u677e\u6797\u573a"
    ],
    "wof:name":"Jingsong Linchang",
    "wof:placetype":"locality"
},
  "geometry": {"coordinates":[128.43868999999998,42.44846],"type":"Point"}
}