{
  "type": "Feature",
  "properties": {
    "gn:admin1_code":"8.0",
    "gn:asciiname":"Gonggucun",
    "gn:country_code":"CN",
    "gn:dem":283,
    "gn:feature_class":"P",
    "gn:feature_code":"PPL",
    "gn:name":"Gonggucun",
    "gn:population":0,
    "gn:timezone":"Asia/Shanghai",
    "iso:country":"CN",
    "name:zho_x_preferred":[
        "\u5de9\u56fa\u6751"
    ],
    "wof:name":"Gonggucun",
    "wof:placetype":"locality"
},
  "geometry": {"coordinates":[126.26833000000001,47.62338],"type":"Point"}
}