{
  "type": "Feature",
  "properties": {
    "gn:admin1_code":"8.0",
    "gn:asciiname":"Huanshan",
    "gn:country_code":"CN",
    "gn:dem":132,
    "gn:feature_class":"P",
    "gn:feature_code":"PPL",
    "gn:name":"Huanshan",
    "gn:population":0,
    "gn:timezone":"Asia/Shanghai",
    "iso:country":"CN",
    "name:zho_x_preferred":[
        "\u73af\u5c71"
    ],
    "wof:name":"Huanshan",
    "wof:placetype":"locality"
},
  "geometry": {"coordinates":[130.69533999999999,47.73621],"type":"Point"}
}