{
  "type": "Feature",
  "properties": {
    "gn:admin1_code":"29.0",
    "gn:asciiname":"Man'an",
    "gn:country_code":"CN",
    "gn:dem":544,
    "gn:feature_class":"P",
    "gn:feature_code":"PPL",
    "gn:name":"Man\u2019an",
    "gn:population":0,
    "gn:timezone":"Asia/Shanghai",
    "iso:country":"CN",
    "name:und_x_variant":[
        "Man\u2019an"
    ],
    "name:zho_x_preferred":[
        "\u66fc\u5b89"
    ],
    "wof:name":"Man'an",
    "wof:placetype":"locality"
},
  "geometry": {"coordinates":[101.262,21.9142],"type":"Point"}
}