{
  "type": "Feature",
  "properties": {
    "gn:admin1_code":"15.0",
    "gn:asciiname":"Waji Shanbali",
    "gn:country_code":"CN",
    "gn:dem":1332,
    "gn:feature_class":"P",
    "gn:feature_code":"PPL",
    "gn:name":"Waji Shanbali",
    "gn:population":0,
    "gn:timezone":"Asia/Shanghai",
    "iso:country":"CN",
    "name:zho_x_preferred":[
        "\u74e6\u5409\u5c71\u575d\u91cc"
    ],
    "wof:name":"Waji Shanbali",
    "wof:placetype":"locality"
},
  "geometry": {"coordinates":[105.08649,32.99171],"type":"Point"}
}