{
  "type": "Feature",
  "properties": {
    "gn:admin1_code":"10",
    "gn:asciiname":"Zhaozhangzi",
    "gn:country_code":"CN",
    "gn:dem":227,
    "gn:feature_class":"P",
    "gn:feature_code":"PPL",
    "gn:name":"Zhaozhangzi",
    "gn:population":0,
    "gn:timezone":"Asia/Shanghai",
    "iso:country":"CN",
    "name:zho_x_preferred":[
        "\u8d75\u6756\u5b50"
    ],
    "wof:name":"Zhaozhangzi",
    "wof:placetype":"locality"
},
  "geometry": {"coordinates":[118.07076000000001,40.36166],"type":"Point"}
}