{
  "type": "Feature",
  "properties": {
    "gn:admin1_code":"29.0",
    "gn:asciiname":"Niuxiechang",
    "gn:country_code":"CN",
    "gn:dem":1378,
    "gn:feature_class":"P",
    "gn:feature_code":"PPL",
    "gn:name":"Niuxiechang",
    "gn:population":0,
    "gn:timezone":"Asia/Shanghai",
    "iso:country":"CN",
    "name:zho_x_preferred":[
        "\u725b\u6b47\u573a"
    ],
    "wof:name":"Niuxiechang",
    "wof:placetype":"locality"
},
  "geometry": {"coordinates":[100.782,22.6089],"type":"Point"}
}