{
  "type": "Feature",
  "properties": {
    "gn:admin1_code":"14",
    "gn:asciiname":"Zhaxizong",
    "gn:country_code":"CN",
    "gn:dem":4047,
    "gn:feature_class":"P",
    "gn:feature_code":"PPL",
    "gn:name":"Zhaxizong",
    "gn:population":0,
    "gn:timezone":"Asia/Urumqi",
    "iso:country":"CN",
    "name:zho_x_preferred":[
        "\u624e\u897f\u5b97"
    ],
    "wof:name":"Zhaxizong",
    "wof:placetype":"locality"
},
  "geometry": {"coordinates":[89.3112,29.2291],"type":"Point"}
}