{
  "type": "Feature",
  "properties": {
    "gn:admin1_code":"3.0",
    "gn:asciiname":"Changluo",
    "gn:country_code":"CN",
    "gn:dem":115,
    "gn:feature_class":"P",
    "gn:feature_code":"PPL",
    "gn:name":"Changluo",
    "gn:population":0,
    "gn:timezone":"Asia/Shanghai",
    "iso:country":"CN",
    "name:und_x_variant":[
        "\u957f\u7f57"
    ],
    "wof:name":"Changluo",
    "wof:placetype":"locality"
},
  "geometry": {"coordinates":[115.63885000000001,27.2092],"type":"Point"}
}