{
  "type": "Feature",
  "properties": {
    "gn:admin1_code":"01",
    "gn:asciiname":"Songkou",
    "gn:country_code":"CN",
    "gn:dem":134,
    "gn:feature_class":"P",
    "gn:feature_code":"PPL",
    "gn:name":"Songkou",
    "gn:population":0,
    "gn:timezone":"Asia/Shanghai",
    "iso:country":"CN",
    "name:und_x_variant":[
        "Sung-k\u2019ou",
        "Sung-k\u2019ou-chen",
        "Songkou"
    ],
    "name:zho_x_preferred":[
        "\u7ae6\u53e3"
    ],
    "wof:name":"Songkou",
    "wof:placetype":"locality"
},
  "geometry": {"coordinates":[118.48441,29.9579],"type":"Point"}
}