{
  "type": "Feature",
  "properties": {
    "gn:admin1_code":"10.0",
    "gn:asciiname":"Xudongzhuang",
    "gn:country_code":"CN",
    "gn:dem":14,
    "gn:feature_class":"P",
    "gn:feature_code":"PPL",
    "gn:name":"Xudongzhuang",
    "gn:population":0,
    "gn:timezone":"Asia/Shanghai",
    "iso:country":"CN",
    "name:zho_x_preferred":[
        "\u8bb8\u4e1c\u5e84"
    ],
    "wof:name":"Xudongzhuang",
    "wof:placetype":"locality"
},
  "geometry": {"coordinates":[116.77488999999998,39.38414],"type":"Point"}
}