{
  "type": "Feature",
  "properties": {
    "gn:admin1_code":"14.0",
    "gn:asciiname":"Zenagongba",
    "gn:country_code":"CN",
    "gn:dem":3485,
    "gn:feature_class":"P",
    "gn:feature_code":"PPL",
    "gn:name":"Zenagongba",
    "gn:population":0,
    "gn:timezone":"Asia/Urumqi",
    "iso:country":"CN",
    "name:zho_x_preferred":[
        "\u5219\u90a3\u5171\u5df4"
    ],
    "wof:name":"Zenagongba",
    "wof:placetype":"locality"
},
  "geometry": {"coordinates":[94.50073999999999,29.2761],"type":"Point"}
}