{
  "type": "Feature",
  "properties": {
    "gn:admin1_code":"15.0",
    "gn:asciiname":"Mataizi",
    "gn:country_code":"CN",
    "gn:dem":1445,
    "gn:feature_class":"P",
    "gn:feature_code":"PPL",
    "gn:name":"Mataizi",
    "gn:population":0,
    "gn:timezone":"Asia/Shanghai",
    "iso:country":"CN",
    "name:zho_x_preferred":[
        "\u9a6c\u53f0\u5b50"
    ],
    "wof:name":"Mataizi",
    "wof:placetype":"locality"
},
  "geometry": {"coordinates":[105.988,34.2276],"type":"Point"}
}