{
  "type": "Feature",
  "properties": {
    "gn:admin1_code":"7",
    "gn:asciiname":"Zhangdun",
    "gn:country_code":"CN",
    "gn:dem":428,
    "gn:feature_class":"P",
    "gn:feature_code":"PPL",
    "gn:name":"Zhangdun",
    "gn:population":0,
    "gn:timezone":"Asia/Shanghai",
    "iso:country":"CN",
    "name:und_x_variant":[
        "\u6a1f\u58a9"
    ],
    "wof:name":"Zhangdun",
    "wof:placetype":"locality"
},
  "geometry": {"coordinates":[118.61221999999999,27.79389],"type":"Point"}
}