{
  "type": "Feature",
  "properties": {
    "gn:admin1_code":"3.0",
    "gn:asciiname":"Sheyuan",
    "gn:country_code":"CN",
    "gn:dem":119,
    "gn:feature_class":"P",
    "gn:feature_code":"PPL",
    "gn:name":"Sheyuan",
    "gn:population":0,
    "gn:timezone":"Asia/Shanghai",
    "iso:country":"CN",
    "name:und_x_variant":[
        "\u86c7\u6e90"
    ],
    "wof:name":"Sheyuan",
    "wof:placetype":"locality"
},
  "geometry": {"coordinates":[116.3836,27.64469],"type":"Point"}
}