{
  "type": "Feature",
  "properties": {
    "gn:admin1_code":"4.0",
    "gn:asciiname":"Xinli Jiuzu",
    "gn:country_code":"CN",
    "gn:dem":4,
    "gn:feature_class":"P",
    "gn:feature_code":"PPLF",
    "gn:name":"Xinli Jiuzu",
    "gn:population":0,
    "gn:timezone":"Asia/Shanghai",
    "iso:country":"CN",
    "name:zho_x_preferred":[
        "\u65b0\u5386\u4e5d\u7ec4"
    ],
    "wof:name":"Xinli Jiuzu",
    "wof:placetype":"locality"
},
  "geometry": {"coordinates":[121.21722,31.99837],"type":"Point"}
}