{
  "type": "Feature",
  "properties": {
    "gn:admin1_code":"31",
    "gn:asciiname":"Kuidou",
    "gn:country_code":"CN",
    "gn:dem":37,
    "gn:feature_class":"P",
    "gn:feature_code":"PPL",
    "gn:name":"Kuidou",
    "gn:population":0,
    "gn:timezone":"Asia/Shanghai",
    "iso:country":"CN",
    "name:und_x_variant":[
        "\u9b41\u6597"
    ],
    "wof:name":"Kuidou",
    "wof:placetype":"locality"
},
  "geometry": {"coordinates":[109.77406999999999,19.9144],"type":"Point"}
}