{
  "type": "Feature",
  "properties": {
    "gn:admin1_code":"1.0",
    "gn:asciiname":"Huipengcun",
    "gn:country_code":"CN",
    "gn:dem":39,
    "gn:feature_class":"P",
    "gn:feature_code":"PPL",
    "gn:name":"Huipengcun",
    "gn:population":0,
    "gn:timezone":"Asia/Shanghai",
    "iso:country":"CN",
    "name:zho_x_preferred":[
        "\u4f1a\u68da\u6751"
    ],
    "wof:name":"Huipengcun",
    "wof:placetype":"locality"
},
  "geometry": {"coordinates":[117.39015000000001,31.92317],"type":"Point"}
}