{
  "type": "Feature",
  "properties": {
    "gn:admin1_code":"26.0",
    "gn:asciiname":"Gaodongwan",
    "gn:country_code":"CN",
    "gn:dem":1135,
    "gn:feature_class":"P",
    "gn:feature_code":"PPL",
    "gn:name":"Gaodongwan",
    "gn:population":0,
    "gn:timezone":"Asia/Shanghai",
    "iso:country":"CN",
    "name:zho_x_preferred":[
        "\u9ad8\u6d1e\u6e7e"
    ],
    "wof:name":"Gaodongwan",
    "wof:placetype":"locality"
},
  "geometry": {"coordinates":[109.43212,32.29229],"type":"Point"}
}