{
  "type": "Feature",
  "properties": {
    "gn:admin1_code":"05",
    "gn:asciiname":"Lamadian",
    "gn:cc2":"CN",
    "gn:country_code":"CN",
    "gn:dem":140,
    "gn:feature_class":"P",
    "gn:feature_code":"PPL",
    "gn:name":"Lamadian",
    "gn:population":0,
    "gn:timezone":"Asia/Shanghai",
    "iso:country":"CN",
    "name:und_x_variant":[
        "La-ma-tien",
        "Lamadian"
    ],
    "wof:name":"Lamadian",
    "wof:placetype":"locality"
},
  "geometry": {"coordinates":[124.12389,43.28556],"type":"Point"}
}