{
  "type": "Feature",
  "properties": {
    "gn:admin1_code":"7",
    "gn:asciiname":"Shangchixi",
    "gn:country_code":"CN",
    "gn:dem":866,
    "gn:feature_class":"P",
    "gn:feature_code":"PPL",
    "gn:name":"Shangchixi",
    "gn:population":0,
    "gn:timezone":"Asia/Shanghai",
    "iso:country":"CN",
    "name:und_x_variant":[
        "\u4e0a\u8d64\u6eaa"
    ],
    "wof:name":"Shangchixi",
    "wof:placetype":"locality"
},
  "geometry": {"coordinates":[119.19528,27.39944],"type":"Point"}
}