{
  "type": "Feature",
  "properties": {
    "gn:admin1_code":"15.0",
    "gn:asciiname":"Chenjiazhuang",
    "gn:country_code":"CN",
    "gn:dem":2408,
    "gn:feature_class":"P",
    "gn:feature_code":"PPL",
    "gn:name":"Chenjiazhuang",
    "gn:population":0,
    "gn:timezone":"Asia/Shanghai",
    "iso:country":"CN",
    "name:zho_x_preferred":[
        "\u9648\u5bb6\u5e84"
    ],
    "wof:name":"Chenjiazhuang",
    "wof:placetype":"locality"
},
  "geometry": {"coordinates":[101.599,38.1868],"type":"Point"}
}