{
  "type": "Feature",
  "properties": {
    "gn:admin1_code":"29",
    "gn:asciiname":"Qimutang",
    "gn:country_code":"CN",
    "gn:dem":1319,
    "gn:feature_class":"P",
    "gn:feature_code":"PPL",
    "gn:name":"Qimutang",
    "gn:population":0,
    "gn:timezone":"Asia/Shanghai",
    "iso:country":"CN",
    "name:zho_x_preferred":[
        "\u675e\u6728\u5858"
    ],
    "wof:name":"Qimutang",
    "wof:placetype":"locality"
},
  "geometry": {"coordinates":[102.00514,24.84173],"type":"Point"}
}