{
  "type": "Feature",
  "properties": {
    "gn:admin1_code":"12.0",
    "gn:asciiname":"Nanlingkou",
    "gn:country_code":"CN",
    "gn:dem":129,
    "gn:feature_class":"P",
    "gn:feature_code":"PPL",
    "gn:name":"Nanlingkou",
    "gn:population":0,
    "gn:timezone":"Asia/Shanghai",
    "iso:country":"CN",
    "name:zho_x_preferred":[
        "Nanlingkou"
    ],
    "name:zho_x_variant":[
        "\u5357\u5cad\u53e3"
    ],
    "wof:name":"Nanlingkou",
    "wof:placetype":"locality"
},
  "geometry": {"coordinates":[114.7838,29.48501],"type":"Point"}
}