{
  "type": "Feature",
  "properties": {
    "gn:admin1_code":"32.0",
    "gn:asciiname":"Jieshaosi",
    "gn:country_code":"CN",
    "gn:dem":401,
    "gn:feature_class":"P",
    "gn:feature_code":"PPL",
    "gn:name":"Jieshaosi",
    "gn:population":0,
    "gn:timezone":"Asia/Shanghai",
    "iso:country":"CN",
    "name:zho_x_preferred":[
        "\u63a5\u7ecd\u5bfa"
    ],
    "wof:name":"Jieshaosi",
    "wof:placetype":"locality"
},
  "geometry": {"coordinates":[105.11499999999999,30.4294],"type":"Point"}
}