{
  "type": "Feature",
  "properties": {
    "gn:admin1_code":"15.0",
    "gn:asciiname":"Changgou'ao",
    "gn:country_code":"CN",
    "gn:dem":2501,
    "gn:feature_class":"P",
    "gn:feature_code":"PPL",
    "gn:name":"Changgou\u2019ao",
    "gn:population":0,
    "gn:timezone":"Asia/Shanghai",
    "iso:country":"CN",
    "name:und_x_variant":[
        "Changgou\u2019ao"
    ],
    "name:zho_x_preferred":[
        "\u957f\u6c9f\u51f9"
    ],
    "wof:name":"Changgou'ao",
    "wof:placetype":"locality"
},
  "geometry": {"coordinates":[101.211,38.4755],"type":"Point"}
}