{
  "type": "Feature",
  "properties": {
    "gn:admin1_code":"10.0",
    "gn:asciiname":"Duowa",
    "gn:country_code":"CN",
    "gn:dem":4,
    "gn:feature_class":"P",
    "gn:feature_code":"PPL",
    "gn:name":"Duowa",
    "gn:population":0,
    "gn:timezone":"Asia/Shanghai",
    "iso:country":"CN",
    "name:zho_x_preferred":[
        "\u579b\u74e6"
    ],
    "wof:name":"Duowa",
    "wof:placetype":"locality"
},
  "geometry": {"coordinates":[118.92765,39.25096],"type":"Point"}
}