{
  "type": "Feature",
  "properties": {
    "gn:admin1_code":"7.0",
    "gn:asciiname":"Shuijing'ao",
    "gn:country_code":"CN",
    "gn:dem":295,
    "gn:feature_class":"P",
    "gn:feature_code":"PPL",
    "gn:name":"Shuijing\u2019ao",
    "gn:population":0,
    "gn:timezone":"Asia/Shanghai",
    "iso:country":"CN",
    "name:und_x_variant":[
        "Shuijing\u2019ao"
    ],
    "name:zho_x_preferred":[
        "\u6c34\u4e95\u51f9"
    ],
    "wof:name":"Shuijing'ao",
    "wof:placetype":"locality"
},
  "geometry": {"coordinates":[116.54347,24.95318],"type":"Point"}
}