{
  "type": "Feature",
  "properties": {
    "gn:admin1_code":"32.0",
    "gn:asciiname":"Chenshan",
    "gn:country_code":"CN",
    "gn:dem":972,
    "gn:feature_class":"P",
    "gn:feature_code":"PPL",
    "gn:name":"Chenshan",
    "gn:population":0,
    "gn:timezone":"Asia/Shanghai",
    "iso:country":"CN",
    "name:zho_x_preferred":[
        "\u9648\u5c71"
    ],
    "wof:name":"Chenshan",
    "wof:placetype":"locality"
},
  "geometry": {"coordinates":[103.333,29.6464],"type":"Point"}
}