{
  "type": "Feature",
  "properties": {
    "gn:admin1_code":"5.0",
    "gn:asciiname":"Yonglitun",
    "gn:country_code":"CN",
    "gn:dem":142,
    "gn:feature_class":"P",
    "gn:feature_code":"PPL",
    "gn:name":"Yonglitun",
    "gn:population":0,
    "gn:timezone":"Asia/Shanghai",
    "iso:country":"CN",
    "name:zho_x_preferred":[
        "\u6c38\u7acb\u5c6f"
    ],
    "wof:name":"Yonglitun",
    "wof:placetype":"locality"
},
  "geometry": {"coordinates":[123.16667,45.5552],"type":"Point"}
}