{
  "type": "Feature",
  "properties": {
    "gn:admin1_code":"19.0",
    "gn:asciiname":"Dongnanling",
    "gn:country_code":"CN",
    "gn:dem":183,
    "gn:feature_class":"P",
    "gn:feature_code":"PPL",
    "gn:name":"Dongnanling",
    "gn:population":0,
    "gn:timezone":"Asia/Shanghai",
    "iso:country":"CN",
    "name:und_x_variant":[
        "\u4e1c\u5357\u5cad"
    ],
    "wof:name":"Dongnanling",
    "wof:placetype":"locality"
},
  "geometry": {"coordinates":[122.46095,40.08727],"type":"Point"}
}