{
  "type": "Feature",
  "properties": {
    "gn:admin1_code":"6.0",
    "gn:asciiname":"Muri",
    "gn:country_code":"CN",
    "gn:dem":4273,
    "gn:feature_class":"P",
    "gn:feature_code":"PPLA4",
    "gn:name":"Muri",
    "gn:population":0,
    "gn:timezone":"Asia/Urumqi",
    "iso:country":"CN",
    "name:als_x_preferred":[
        "Muri"
    ],
    "name:ceb_x_preferred":[
        "Muri"
    ],
    "name:ces_x_preferred":[
        "Muri"
    ],
    "name:deu_x_preferred":[
        "Muri"
    ],
    "name:epo_x_preferred":[
        "Muri"
    ],
    "name:est_x_preferred":[
        "Muri"
    ],
    "name:eus_x_preferred":[
        "Muri"
    ],
    "name:fra_x_preferred":[
        "Muri"
    ],
    "name:ita_x_preferred":[
        "Muri"
    ],
    "name:lat_x_preferred":[
        "Muri"
    ],
    "name:nld_x_preferred":[
        "Muri"
    ],
    "name:swe_x_preferred":[
        "Muri"
    ],
    "name:und_x_variant":[
        "Mo-li",
        "Muli",
        "Muli Xiang"
    ],
    "name:vol_x_preferred":[
        "Muri"
    ],
    "name:zho_x_preferred":[
        "\u6728\u91cc"
    ],
    "name:zho_x_variant":[
        "\u6728\u91cc\u4e61"
    ],
    "wof:name":"Muri",
    "wof:placetype":"locality"
},
  "geometry": {"coordinates":[99.06667,38.13333],"type":"Point"}
}