{
  "type": "Feature",
  "properties": {
    "gn:admin1_code":"5.0",
    "gn:asciiname":"Xibajiazi",
    "gn:country_code":"CN",
    "gn:dem":352,
    "gn:feature_class":"P",
    "gn:feature_code":"PPL",
    "gn:name":"Xibajiazi",
    "gn:population":0,
    "gn:timezone":"Asia/Shanghai",
    "iso:country":"CN",
    "name:und_x_variant":[
        "\u897f\u516b\u5bb6\u5b50"
    ],
    "wof:name":"Xibajiazi",
    "wof:placetype":"locality"
},
  "geometry": {"coordinates":[126.98808,43.01179000000001],"type":"Point"}
}