{
  "type": "Feature",
  "properties": {
    "gn:admin1_code":"18.0",
    "gn:asciiname":"Nan'ai",
    "gn:country_code":"CN",
    "gn:dem":536,
    "gn:feature_class":"P",
    "gn:feature_code":"PPL",
    "gn:name":"Nan\u2019ai",
    "gn:population":0,
    "gn:timezone":"Asia/Shanghai",
    "iso:country":"CN",
    "name:und_x_variant":[
        "Nan\u2019ai"
    ],
    "name:zho_x_preferred":[
        "\u5357\u57c3"
    ],
    "wof:name":"Nan'ai",
    "wof:placetype":"locality"
},
  "geometry": {"coordinates":[108.631,26.5939],"type":"Point"}
}