{
  "type": "Feature",
  "properties": {
    "gn:admin1_code":"25",
    "gn:asciiname":"Xifengjiazhuang",
    "gn:country_code":"CN",
    "gn:dem":119,
    "gn:feature_class":"P",
    "gn:feature_code":"PPL",
    "gn:name":"Xifengjiazhuang",
    "gn:population":0,
    "gn:timezone":"Asia/Shanghai",
    "iso:country":"CN",
    "name:zho_x_preferred":[
        "\u897f\u5c01\u5bb6\u5e84"
    ],
    "wof:name":"Xifengjiazhuang",
    "wof:placetype":"locality"
},
  "geometry": {"coordinates":[117.298,35.8938],"type":"Point"}
}