{
  "type": "Feature",
  "properties": {
    "gn:admin1_code":"22.0",
    "gn:asciiname":"Xinzhuangzicun",
    "gn:country_code":"CN",
    "gn:dem":71,
    "gn:feature_class":"P",
    "gn:feature_code":"PPL",
    "gn:name":"Xinzhuangzicun",
    "gn:population":0,
    "gn:timezone":"Asia/Shanghai",
    "iso:country":"CN",
    "name:zho_x_preferred":[
        "\u8f9b\u5e84\u5b50\u6751"
    ],
    "wof:name":"Xinzhuangzicun",
    "wof:placetype":"locality"
},
  "geometry": {"coordinates":[117.00485,40.24704000000001],"type":"Point"}
}