{
  "type": "Feature",
  "properties": {
    "gn:admin1_code":"7.0",
    "gn:asciiname":"Dayang",
    "gn:country_code":"CN",
    "gn:dem":529,
    "gn:feature_class":"P",
    "gn:feature_code":"PPL",
    "gn:name":"Dayang",
    "gn:population":0,
    "gn:timezone":"Asia/Shanghai",
    "iso:country":"CN",
    "name:zho_x_preferred":[
        "\u5927\u9633"
    ],
    "wof:name":"Dayang",
    "wof:placetype":"locality"
},
  "geometry": {"coordinates":[115.97572,25.20499],"type":"Point"}
}