{
  "type": "Feature",
  "properties": {
    "gn:admin1_code":"30.0",
    "gn:asciiname":"Mengshan",
    "gn:country_code":"CN",
    "gn:dem":434,
    "gn:feature_class":"P",
    "gn:feature_code":"PPL",
    "gn:name":"Mengshan",
    "gn:population":0,
    "gn:timezone":"Asia/Shanghai",
    "iso:country":"CN",
    "name:zho_x_preferred":[
        "Mengshan"
    ],
    "name:zho_x_variant":[
        "\u5b5f\u5c71"
    ],
    "wof:name":"Mengshan",
    "wof:placetype":"locality"
},
  "geometry": {"coordinates":[112.47611000000001,24.49667],"type":"Point"}
}