{
  "type": "Feature",
  "properties": {
    "gn:admin1_code":"3.0",
    "gn:asciiname":"Xikengli",
    "gn:country_code":"CN",
    "gn:dem":278,
    "gn:feature_class":"P",
    "gn:feature_code":"PPL",
    "gn:name":"Xikengli",
    "gn:population":0,
    "gn:timezone":"Asia/Shanghai",
    "iso:country":"CN",
    "name:und_x_variant":[
        "\u897f\u5751\u91cc"
    ],
    "wof:name":"Xikengli",
    "wof:placetype":"locality"
},
  "geometry": {"coordinates":[114.29989,27.26041],"type":"Point"}
}