{
  "type": "Feature",
  "properties": {
    "gn:admin1_code":"15.0",
    "gn:asciiname":"Wangjiaheli",
    "gn:country_code":"CN",
    "gn:dem":1636,
    "gn:feature_class":"P",
    "gn:feature_code":"PPL",
    "gn:name":"Wangjiaheli",
    "gn:population":0,
    "gn:timezone":"Asia/Shanghai",
    "iso:country":"CN",
    "name:und_x_variant":[
        "\u738b\u5bb6\u6cb3\u91cc"
    ],
    "wof:name":"Wangjiaheli",
    "wof:placetype":"locality"
},
  "geometry": {"coordinates":[105.4217,33.07530999999999],"type":"Point"}
}