{
  "type": "Feature",
  "properties": {
    "gn:admin1_code":"15.0",
    "gn:asciiname":"Xifangou",
    "gn:country_code":"CN",
    "gn:dem":2799,
    "gn:feature_class":"P",
    "gn:feature_code":"PPL",
    "gn:name":"Xifangou",
    "gn:population":0,
    "gn:timezone":"Asia/Shanghai",
    "iso:country":"CN",
    "name:zho_x_preferred":[
        "\u897f\u756a\u6c9f"
    ],
    "wof:name":"Xifangou",
    "wof:placetype":"locality"
},
  "geometry": {"coordinates":[102.944,36.8274],"type":"Point"}
}