{
  "type": "Feature",
  "properties": {
    "gn:admin1_code":"10.0",
    "gn:asciiname":"Mengguanying",
    "gn:country_code":"CN",
    "gn:dem":93,
    "gn:feature_class":"P",
    "gn:feature_code":"PPL",
    "gn:name":"Mengguanying",
    "gn:population":0,
    "gn:timezone":"Asia/Shanghai",
    "iso:country":"CN",
    "name:zho_x_preferred":[
        "\u5b5f\u5b98\u8425"
    ],
    "wof:name":"Mengguanying",
    "wof:placetype":"locality"
},
  "geometry": {"coordinates":[118.56784,40.04938],"type":"Point"}
}