{
  "type": "Feature",
  "properties": {
    "gn:admin1_code":"8.0",
    "gn:asciiname":"Zhongxiaocun",
    "gn:country_code":"CN",
    "gn:dem":219,
    "gn:feature_class":"P",
    "gn:feature_code":"PPL",
    "gn:name":"Zhongxiaocun",
    "gn:population":0,
    "gn:timezone":"Asia/Shanghai",
    "iso:country":"CN",
    "name:zho_x_preferred":[
        "\u5fe0\u5b5d\u6751"
    ],
    "wof:name":"Zhongxiaocun",
    "wof:placetype":"locality"
},
  "geometry": {"coordinates":[125.09439999999999,48.51477],"type":"Point"}
}