{
  "type": "Feature",
  "properties": {
    "gn:admin1_code":"14.0",
    "gn:asciiname":"Baorongcun",
    "gn:country_code":"CN",
    "gn:dem":4678,
    "gn:feature_class":"P",
    "gn:feature_code":"PPL",
    "gn:name":"Baorongcun",
    "gn:population":0,
    "gn:timezone":"Asia/Urumqi",
    "iso:country":"CN",
    "name:zho_x_preferred":[
        "\u4fdd\u8363\u6751"
    ],
    "wof:name":"Baorongcun",
    "wof:placetype":"locality"
},
  "geometry": {"coordinates":[90.10375999999999,31.475],"type":"Point"}
}