{
  "type": "Feature",
  "properties": {
    "gn:admin1_code":"8.0",
    "gn:asciiname":"Heguangtun",
    "gn:country_code":"CN",
    "gn:dem":298,
    "gn:feature_class":"P",
    "gn:feature_code":"PPL",
    "gn:name":"Heguangtun",
    "gn:population":0,
    "gn:timezone":"Asia/Shanghai",
    "iso:country":"CN",
    "name:und_x_variant":[
        "\u548c\u5149\u5c6f",
        "Heguang",
        "\u548c\u5149"
    ],
    "wof:name":"Heguangtun",
    "wof:placetype":"locality"
},
  "geometry": {"coordinates":[130.77785,43.73263],"type":"Point"}
}