{
  "type": "Feature",
  "properties": {
    "gn:admin1_code":"12.0",
    "gn:asciiname":"Kazi",
    "gn:country_code":"CN",
    "gn:dem":1735,
    "gn:feature_class":"P",
    "gn:feature_code":"PPL",
    "gn:name":"Kazi",
    "gn:population":0,
    "gn:timezone":"Asia/Shanghai",
    "iso:country":"CN",
    "name:ben_x_preferred":[
        "\u0995\u09be\u099c\u09c0"
    ],
    "name:ceb_x_preferred":[
        "Kazi"
    ],
    "name:deu_x_preferred":[
        "Kazi"
    ],
    "name:ita_x_preferred":[
        "Kazi"
    ],
    "name:swe_x_preferred":[
        "Kazi"
    ],
    "name:zho_x_preferred":[
        "\u5361\u5b50"
    ],
    "wof:name":"Kazi",
    "wof:placetype":"locality"
},
  "geometry": {"coordinates":[110.5714,30.77563],"type":"Point"}
}