{
  "type": "Feature",
  "properties": {
    "gn:admin1_code":"14.0",
    "gn:asciiname":"Yamacun",
    "gn:country_code":"CN",
    "gn:dem":3395,
    "gn:feature_class":"P",
    "gn:feature_code":"PPL",
    "gn:name":"Yamacun",
    "gn:population":0,
    "gn:timezone":"Asia/Urumqi",
    "iso:country":"CN",
    "name:zho_x_preferred":[
        "\u4e9a\u9a6c\u6751"
    ],
    "wof:name":"Yamacun",
    "wof:placetype":"locality"
},
  "geometry": {"coordinates":[97.34189000000001,31.04816],"type":"Point"}
}