{
  "type": "Feature",
  "properties": {
    "gn:admin1_code":"30.0",
    "gn:asciiname":"Yangjiao",
    "gn:country_code":"CN",
    "gn:dem":1,
    "gn:feature_class":"P",
    "gn:feature_code":"PPL",
    "gn:name":"Yangjiao",
    "gn:population":0,
    "gn:timezone":"Asia/Shanghai",
    "iso:country":"CN",
    "name:zho_x_preferred":[
        "\u694a\u7a96"
    ],
    "wof:name":"Yangjiao",
    "wof:placetype":"locality"
},
  "geometry": {"coordinates":[113.05063,22.93167],"type":"Point"}
}