{
  "type": "Feature",
  "properties": {
    "gn:admin1_code":"4.0",
    "gn:asciiname":"Hongyacun",
    "gn:country_code":"CN",
    "gn:dem":12,
    "gn:feature_class":"P",
    "gn:feature_code":"PPL",
    "gn:name":"Hongyacun",
    "gn:population":0,
    "gn:timezone":"Asia/Shanghai",
    "iso:country":"CN",
    "name:zho_x_preferred":[
        "\u6d2a\u6daf\u6751"
    ],
    "wof:name":"Hongyacun",
    "wof:placetype":"locality"
},
  "geometry": {"coordinates":[119.04668999999998,33.77008],"type":"Point"}
}