{
  "type": "Feature",
  "properties": {
    "gn:admin1_code":"26.0",
    "gn:asciiname":"Erdao Ling",
    "gn:country_code":"CN",
    "gn:dem":677,
    "gn:feature_class":"P",
    "gn:feature_code":"PPL",
    "gn:name":"Erdao Ling",
    "gn:population":0,
    "gn:timezone":"Asia/Shanghai",
    "iso:country":"CN",
    "name:und_x_variant":[
        "\u4e8c\u9053\u5cad"
    ],
    "wof:name":"Erdao Ling",
    "wof:placetype":"locality"
},
  "geometry": {"coordinates":[107.31518,32.96436],"type":"Point"}
}