{
  "type": "Feature",
  "properties": {
    "gn:admin1_code":"25",
    "gn:asciiname":"Nanlaodu",
    "gn:country_code":"CN",
    "gn:dem":71,
    "gn:feature_class":"P",
    "gn:feature_code":"PPL",
    "gn:name":"Nanlaodu",
    "gn:population":0,
    "gn:timezone":"Asia/Shanghai",
    "iso:country":"CN",
    "name:zho_x_preferred":[
        "\u5357\u6d9d\u90fd"
    ],
    "wof:name":"Nanlaodu",
    "wof:placetype":"locality"
},
  "geometry": {"coordinates":[121.157,37.1767],"type":"Point"}
}