{
  "type": "Feature",
  "properties": {
    "gn:admin1_code":"15.0",
    "gn:asciiname":"Xiaopingli",
    "gn:country_code":"CN",
    "gn:dem":1070,
    "gn:feature_class":"P",
    "gn:feature_code":"PPL",
    "gn:name":"Xiaopingli",
    "gn:population":0,
    "gn:timezone":"Asia/Shanghai",
    "iso:country":"CN",
    "name:zho_x_preferred":[
        "\u5c0f\u576a\u91cc"
    ],
    "wof:name":"Xiaopingli",
    "wof:placetype":"locality"
},
  "geometry": {"coordinates":[105.236,32.713],"type":"Point"}
}