{
  "type": "Feature",
  "properties": {
    "gn:admin1_code":"16",
    "gn:asciiname":"Dongmen",
    "gn:country_code":"CN",
    "gn:dem":348,
    "gn:feature_class":"P",
    "gn:feature_code":"PPLA3",
    "gn:name":"Dongmen",
    "gn:population":0,
    "gn:timezone":"Asia/Shanghai",
    "iso:country":"CN",
    "name:und_x_variant":[
        "Loshing-hsien",
        "Dongmen"
    ],
    "name:zho_x_preferred":[
        "Lo-ch\u2019eng-hsien"
    ],
    "name:zho_x_variant":[
        "Lo-ch\u2019eng",
        "\u4e1c\u95e8"
    ],
    "wof:name":"Dongmen",
    "wof:placetype":"locality"
},
  "geometry": {"coordinates":[108.90000000000001,24.79198],"type":"Point"}
}