{
  "type": "Feature",
  "properties": {
    "gn:admin1_code":"18.0",
    "gn:asciiname":"Nali",
    "gn:country_code":"CN",
    "gn:dem":1068,
    "gn:feature_class":"P",
    "gn:feature_code":"PPL",
    "gn:name":"Nali",
    "gn:population":0,
    "gn:timezone":"Asia/Shanghai",
    "iso:country":"CN",
    "name:zho_x_preferred":[
        "\u7eb3\u529b"
    ],
    "wof:name":"Nali",
    "wof:placetype":"locality"
},
  "geometry": {"coordinates":[105.72,25.2368],"type":"Point"}
}