{
  "type": "Feature",
  "properties": {
    "gn:admin1_code":"29.0",
    "gn:asciiname":"Zuofanggou",
    "gn:country_code":"CN",
    "gn:dem":1647,
    "gn:feature_class":"P",
    "gn:feature_code":"PPL",
    "gn:name":"Zuofanggou",
    "gn:population":0,
    "gn:timezone":"Asia/Shanghai",
    "iso:country":"CN",
    "name:zho_x_preferred":[
        "\u4f5c\u574a\u6c9f"
    ],
    "wof:name":"Zuofanggou",
    "wof:placetype":"locality"
},
  "geometry": {"coordinates":[104.127,27.6996],"type":"Point"}
}