{
  "type": "Feature",
  "properties": {
    "gn:admin1_code":"11.0",
    "gn:asciiname":"Weixilong",
    "gn:country_code":"CN",
    "gn:dem":480,
    "gn:feature_class":"P",
    "gn:feature_code":"PPL",
    "gn:name":"Weixilong",
    "gn:population":0,
    "gn:timezone":"Asia/Shanghai",
    "iso:country":"CN",
    "name:zho_x_preferred":[
        "\u6e2d\u6eaa\u9f99"
    ],
    "wof:name":"Weixilong",
    "wof:placetype":"locality"
},
  "geometry": {"coordinates":[110.97883,27.59788],"type":"Point"}
}