{
  "type": "Feature",
  "properties": {
    "gn:admin1_code":"25",
    "gn:asciiname":"Gangxin",
    "gn:country_code":"CN",
    "gn:dem":63,
    "gn:feature_class":"P",
    "gn:feature_code":"PPL",
    "gn:name":"Gangxin",
    "gn:population":0,
    "gn:timezone":"Asia/Shanghai",
    "iso:country":"CN",
    "name:zho_x_preferred":[
        "\u5c97\u8f9b"
    ],
    "wof:name":"Gangxin",
    "wof:placetype":"locality"
},
  "geometry": {"coordinates":[116.72799999999999,36.4636],"type":"Point"}
}