{
  "type": "Feature",
  "properties": {
    "gn:admin1_code":"29.0",
    "gn:asciiname":"Shuangfengkou",
    "gn:country_code":"CN",
    "gn:dem":2809,
    "gn:feature_class":"P",
    "gn:feature_code":"PPL",
    "gn:name":"Shuangfengkou",
    "gn:population":0,
    "gn:timezone":"Asia/Shanghai",
    "iso:country":"CN",
    "name:zho_x_preferred":[
        "\u53cc\u98ce\u53e3"
    ],
    "wof:name":"Shuangfengkou",
    "wof:placetype":"locality"
},
  "geometry": {"coordinates":[102.955,25.9718],"type":"Point"}
}