{
  "type": "Feature",
  "properties": {
    "gn:admin1_code":"11.0",
    "gn:asciiname":"Xintianping",
    "gn:country_code":"CN",
    "gn:dem":227,
    "gn:feature_class":"P",
    "gn:feature_code":"PPL",
    "gn:name":"Xintianping",
    "gn:population":0,
    "gn:timezone":"Asia/Shanghai",
    "iso:country":"CN",
    "name:zho_x_preferred":[
        "\u65b0\u7530\u576a"
    ],
    "wof:name":"Xintianping",
    "wof:placetype":"locality"
},
  "geometry": {"coordinates":[110.32962000000001,28.00358],"type":"Point"}
}