{
  "type": "Feature",
  "properties": {
    "gn:admin1_code":"15.0",
    "gn:asciiname":"Hongliuqiujing",
    "gn:country_code":"CN",
    "gn:dem":1760,
    "gn:feature_class":"P",
    "gn:feature_code":"PPL",
    "gn:name":"Hongliuqiujing",
    "gn:population":0,
    "gn:timezone":"Asia/Urumqi",
    "iso:country":"CN",
    "name:zho_x_preferred":[
        "\u7ea2\u67f3\u4e18\u4e95"
    ],
    "wof:name":"Hongliuqiujing",
    "wof:placetype":"locality"
},
  "geometry": {"coordinates":[97.2568,42.1552],"type":"Point"}
}