{
  "type": "Feature",
  "properties": {
    "gn:admin1_code":"16.0",
    "gn:asciiname":"Gugan",
    "gn:country_code":"CN",
    "gn:dem":840,
    "gn:feature_class":"P",
    "gn:feature_code":"PPL",
    "gn:name":"Gugan",
    "gn:population":0,
    "gn:timezone":"Asia/Shanghai",
    "iso:country":"CN",
    "name:ara_x_preferred":[
        "\u063a\u0648\u063a\u0627\u0646"
    ],
    "name:azb_x_preferred":[
        "\u06af\u0648\u06af\u0627\u0646"
    ],
    "name:aze_x_preferred":[
        "Gogan"
    ],
    "name:ceb_x_preferred":[
        "G\u016bg\u0101n"
    ],
    "name:fas_x_preferred":[
        "\u06af\u0648\u06af\u0627\u0646"
    ],
    "name:ita_x_preferred":[
        "Gugan"
    ],
    "name:mlg_x_preferred":[
        "Gugan"
    ],
    "name:msa_x_preferred":[
        "Gugan"
    ],
    "name:swe_x_preferred":[
        "G\u016bg\u0101n"
    ],
    "name:tur_x_preferred":[
        "Gogan"
    ],
    "name:urd_x_preferred":[
        "\u06af\u0648\u06af\u0627\u0646"
    ],
    "name:zho_x_preferred":[
        "\u53e4\u7518"
    ],
    "wof:name":"Gugan",
    "wof:placetype":"locality"
},
  "geometry": {"coordinates":[106.27500000000001,23.4304],"type":"Point"}
}