{
  "type": "Feature",
  "properties": {
    "gn:admin1_code":"4.0",
    "gn:asciiname":"Xiqixu",
    "gn:country_code":"CN",
    "gn:dem":5,
    "gn:feature_class":"P",
    "gn:feature_code":"PPL",
    "gn:name":"Xiqixu",
    "gn:population":0,
    "gn:timezone":"Asia/Shanghai",
    "iso:country":"CN",
    "name:zho_x_preferred":[
        "\u897f\u4e03\u5729"
    ],
    "wof:name":"Xiqixu",
    "wof:placetype":"locality"
},
  "geometry": {"coordinates":[120.70599,31.98406],"type":"Point"}
}