{
  "type": "Feature",
  "properties": {
    "gn:admin1_code":"8.0",
    "gn:asciiname":"Yulicun",
    "gn:country_code":"CN",
    "gn:dem":172,
    "gn:feature_class":"P",
    "gn:feature_code":"PPL",
    "gn:name":"Yulicun",
    "gn:population":0,
    "gn:timezone":"Asia/Shanghai",
    "iso:country":"CN",
    "name:zho_x_preferred":[
        "\u4e8e\u793c\u6751"
    ],
    "wof:name":"Yulicun",
    "wof:placetype":"locality"
},
  "geometry": {"coordinates":[127.02185,45.1426],"type":"Point"}
}