{
  "type": "Feature",
  "properties": {
    "gn:admin1_code":"1.0",
    "gn:asciiname":"Caoyingcun",
    "gn:country_code":"CN",
    "gn:dem":26,
    "gn:feature_class":"P",
    "gn:feature_code":"PPL",
    "gn:name":"Caoyingcun",
    "gn:population":0,
    "gn:timezone":"Asia/Shanghai",
    "iso:country":"CN",
    "name:zho_x_preferred":[
        "\u66f9\u90e2\u6751"
    ],
    "wof:name":"Caoyingcun",
    "wof:placetype":"locality"
},
  "geometry": {"coordinates":[116.39412,32.42744],"type":"Point"}
}