{
  "type": "Feature",
  "properties": {
    "gn:admin1_code":"09",
    "gn:asciiname":"Wangdian",
    "gn:country_code":"CN",
    "gn:dem":194,
    "gn:feature_class":"P",
    "gn:feature_code":"PPLA4",
    "gn:name":"Wangdian",
    "gn:population":0,
    "gn:timezone":"Asia/Shanghai",
    "iso:country":"CN",
    "name:ceb_x_preferred":[
        "Wangdian"
    ],
    "name:swe_x_preferred":[
        "Wangdian"
    ],
    "name:und_x_variant":[
        "Wang-tien"
    ],
    "name:zho_x_preferred":[
        "\u738b\u5e97"
    ],
    "wof:name":"Wangdian",
    "wof:placetype":"locality"
},
  "geometry": {"coordinates":[113.4734,32.8035],"type":"Point"}
}