{
  "type": "Feature",
  "properties": {
    "gn:admin1_code":"3.0",
    "gn:asciiname":"Zhutangcun",
    "gn:country_code":"CN",
    "gn:dem":24,
    "gn:feature_class":"P",
    "gn:feature_code":"PPL",
    "gn:name":"Zhutangcun",
    "gn:population":0,
    "gn:timezone":"Asia/Shanghai",
    "iso:country":"CN",
    "name:und_x_variant":[
        "\u73e0\u5858\u6751"
    ],
    "wof:name":"Zhutangcun",
    "wof:placetype":"locality"
},
  "geometry": {"coordinates":[115.63987,28.37018],"type":"Point"}
}