{
  "type": "Feature",
  "properties": {
    "gn:admin1_code":"15.0",
    "gn:asciiname":"Xuejiazui",
    "gn:country_code":"CN",
    "gn:dem":1210,
    "gn:feature_class":"P",
    "gn:feature_code":"PPL",
    "gn:name":"Xuejiazui",
    "gn:population":0,
    "gn:timezone":"Asia/Shanghai",
    "iso:country":"CN",
    "name:und_x_variant":[
        "\u859b\u5bb6\u5480"
    ],
    "wof:name":"Xuejiazui",
    "wof:placetype":"locality"
},
  "geometry": {"coordinates":[107.67211,36.06261],"type":"Point"}
}