{
  "type": "Feature",
  "properties": {
    "gn:admin1_code":"30",
    "gn:asciiname":"Yugonglou",
    "gn:country_code":"CN",
    "gn:dem":124,
    "gn:feature_class":"P",
    "gn:feature_code":"PPL",
    "gn:name":"Yugonglou",
    "gn:population":0,
    "gn:timezone":"Asia/Urumqi",
    "iso:country":"CN",
    "name:und_x_variant":[
        "Y\u00fc-kung-lou",
        "Yugonglou"
    ],
    "name:zho_x_preferred":[
        "Y\u00fc-kung-lou"
    ],
    "name:zho_x_variant":[
        "\u611a\u516c\u697c"
    ],
    "wof:name":"Yugonglou",
    "wof:placetype":"locality"
},
  "geometry": {"coordinates":[110.27752,20.40957],"type":"Point"}
}