{
  "type": "Feature",
  "properties": {
    "gn:admin1_code":"12.0",
    "gn:asciiname":"Lianziwan",
    "gn:country_code":"CN",
    "gn:dem":341,
    "gn:feature_class":"P",
    "gn:feature_code":"PPL",
    "gn:name":"Lianziwan",
    "gn:population":0,
    "gn:timezone":"Asia/Shanghai",
    "iso:country":"CN",
    "name:zho_x_preferred":[
        "\u83b2\u5b50\u6e7e"
    ],
    "wof:name":"Lianziwan",
    "wof:placetype":"locality"
},
  "geometry": {"coordinates":[111.46428,32.4334],"type":"Point"}
}