{
  "type": "Feature",
  "properties": {
    "gn:admin1_code":"9.0",
    "gn:asciiname":"Hutuo",
    "gn:country_code":"CN",
    "gn:dem":124,
    "gn:feature_class":"P",
    "gn:feature_code":"PPL",
    "gn:name":"Hutuo",
    "gn:population":0,
    "gn:timezone":"Asia/Shanghai",
    "iso:country":"CN",
    "name:zho_x_preferred":[
        "\u6ef9\u6cb1"
    ],
    "wof:name":"Hutuo",
    "wof:placetype":"locality"
},
  "geometry": {"coordinates":[113.19972,33.50959],"type":"Point"}
}