{
  "type": "Feature",
  "properties": {
    "gn:admin1_code":"8.0",
    "gn:asciiname":"Qianjincun",
    "gn:country_code":"CN",
    "gn:dem":60,
    "gn:feature_class":"P",
    "gn:feature_code":"PPL",
    "gn:name":"Qianjincun",
    "gn:population":0,
    "gn:timezone":"Asia/Shanghai",
    "iso:country":"CN",
    "name:zho_x_preferred":[
        "\u524d\u8fdb\u6751"
    ],
    "wof:name":"Qianjincun",
    "wof:placetype":"locality"
},
  "geometry": {"coordinates":[131.56225000000001,47.35227],"type":"Point"}
}