{
  "type": "Feature",
  "properties": {
    "gn:admin1_code":"10.0",
    "gn:asciiname":"Dongshagou",
    "gn:country_code":"CN",
    "gn:dem":842,
    "gn:feature_class":"P",
    "gn:feature_code":"PPL",
    "gn:name":"Dongshagou",
    "gn:population":0,
    "gn:timezone":"Asia/Shanghai",
    "iso:country":"CN",
    "name:zho_x_preferred":[
        "\u4e1c\u6c99\u6c9f"
    ],
    "wof:name":"Dongshagou",
    "wof:placetype":"locality"
},
  "geometry": {"coordinates":[114.56806,40.18036],"type":"Point"}
}