{
  "type": "Feature",
  "properties": {
    "gn:admin1_code":"07",
    "gn:asciiname":"Longxi",
    "gn:cc2":"CN",
    "gn:country_code":"CN",
    "gn:dem":422,
    "gn:feature_class":"P",
    "gn:feature_code":"PPL",
    "gn:name":"Longxi",
    "gn:population":0,
    "gn:timezone":"Asia/Shanghai",
    "iso:country":"CN",
    "name:ceb_x_preferred":[
        "Longxi"
    ],
    "name:deu_x_preferred":[
        "Longxi"
    ],
    "name:und_x_variant":[
        "Lung-hsi",
        "Longxi",
        "\u9f99\u6eaa"
    ],
    "name:zho_x_preferred":[
        "Lung-ch\u2019i"
    ],
    "wof:name":"Longxi",
    "wof:placetype":"locality"
},
  "geometry": {"coordinates":[115.89333000000001,25.10472],"type":"Point"}
}