{
  "type": "Feature",
  "properties": {
    "gn:admin1_code":"29.0",
    "gn:asciiname":"Shanluqing",
    "gn:country_code":"CN",
    "gn:dem":2077,
    "gn:feature_class":"P",
    "gn:feature_code":"PPL",
    "gn:name":"Shanluqing",
    "gn:population":0,
    "gn:timezone":"Asia/Shanghai",
    "iso:country":"CN",
    "name:zho_x_preferred":[
        "\u5c71\u9a74\u7b90"
    ],
    "wof:name":"Shanluqing",
    "wof:placetype":"locality"
},
  "geometry": {"coordinates":[99.90779999999999,24.7836],"type":"Point"}
}