{
  "type": "Feature",
  "properties": {
    "gn:admin1_code":"14.0",
    "gn:asciiname":"Ngamda",
    "gn:cc2":"CN",
    "gn:country_code":"CN",
    "gn:dem":4589,
    "gn:feature_class":"P",
    "gn:feature_code":"PPL",
    "gn:name":"Ngamda",
    "gn:population":0,
    "gn:timezone":"Asia/Urumqi",
    "iso:country":"CN",
    "name:msa_x_preferred":[
        "Ngamda"
    ],
    "name:und_x_variant":[
        "Em-ga",
        "Ngenda",
        "En-ta-hsien",
        "Ngemda",
        "En-ko-pen-ta",
        "En-ta",
        "Enda",
        "En-ko-mu-ta"
    ],
    "wof:name":"Ngamda",
    "wof:placetype":"locality"
},
  "geometry": {"coordinates":[96.71666999999999,31.08333],"type":"Point"}
}