{
  "type": "Feature",
  "properties": {
    "gn:admin1_code":"2.0",
    "gn:asciiname":"Xizhongxi",
    "gn:country_code":"CN",
    "gn:dem":48,
    "gn:feature_class":"P",
    "gn:feature_code":"PPL",
    "gn:name":"Xizhongxi",
    "gn:population":0,
    "gn:timezone":"Asia/Shanghai",
    "iso:country":"CN",
    "name:zho_x_preferred":[
        "\u6eaa\u4e2d\u6eaa"
    ],
    "wof:name":"Xizhongxi",
    "wof:placetype":"locality"
},
  "geometry": {"coordinates":[120.47136,28.01566],"type":"Point"}
}