{
  "type": "Feature",
  "properties": {
    "gn:admin1_code":"29.0",
    "gn:asciiname":"Xiazhaipo",
    "gn:country_code":"CN",
    "gn:dem":2548,
    "gn:feature_class":"P",
    "gn:feature_code":"PPL",
    "gn:name":"Xiazhaipo",
    "gn:population":0,
    "gn:timezone":"Asia/Shanghai",
    "iso:country":"CN",
    "name:zho_x_preferred":[
        "\u4e0b\u7a84\u5761"
    ],
    "wof:name":"Xiazhaipo",
    "wof:placetype":"locality"
},
  "geometry": {"coordinates":[99.54470000000001,26.2122],"type":"Point"}
}