{
  "type": "Feature",
  "properties": {
    "gn:admin1_code":"9",
    "gn:asciiname":"Qinjiangzhuang",
    "gn:country_code":"CN",
    "gn:dem":58,
    "gn:feature_class":"P",
    "gn:feature_code":"PPL",
    "gn:name":"Qinjiangzhuang",
    "gn:population":0,
    "gn:timezone":"Asia/Shanghai",
    "iso:country":"CN",
    "name:zho_x_preferred":[
        "\u79e6\u59dc\u5e84"
    ],
    "wof:name":"Qinjiangzhuang",
    "wof:placetype":"locality"
},
  "geometry": {"coordinates":[115.13,34.3226],"type":"Point"}
}