{
  "type": "Feature",
  "properties": {
    "gn:admin1_code":"03",
    "gn:asciiname":"Songshan",
    "gn:country_code":"CN",
    "gn:dem":141,
    "gn:feature_class":"P",
    "gn:feature_code":"PPLA4",
    "gn:name":"Songshan",
    "gn:population":0,
    "gn:timezone":"Asia/Shanghai",
    "iso:country":"CN",
    "name:ceb_x_preferred":[
        "Songshan"
    ],
    "name:deu_x_preferred":[
        "Songshan"
    ],
    "name:fra_x_preferred":[
        "Songshan"
    ],
    "name:pol_x_preferred":[
        "Songshan"
    ],
    "name:rus_x_preferred":[
        "\u0421\u0443\u043d\u0448\u0430\u043d\u044c"
    ],
    "name:sco_x_preferred":[
        "Songshan"
    ],
    "name:und_x_variant":[
        "Sung-shan",
        "Sung-shan-li",
        "Songshan",
        "\u677e\u5c71",
        "Songshan Zhen",
        "\u677e\u5c71\u9547"
    ],
    "wof:name":"Songshan",
    "wof:placetype":"locality"
},
  "geometry": {"coordinates":[114.65938,27.63234000000001],"type":"Point"}
}