{
  "type": "Feature",
  "properties": {
    "gn:admin1_code":"18.0",
    "gn:asciiname":"Yaozhan",
    "gn:country_code":"CN",
    "gn:dem":2386,
    "gn:feature_class":"P",
    "gn:feature_code":"PPL",
    "gn:name":"Yaozhan",
    "gn:population":0,
    "gn:timezone":"Asia/Shanghai",
    "iso:country":"CN",
    "wof:name":"Yaozhan",
    "wof:placetype":"locality"
},
  "geometry": {"coordinates":[104.23333,26.76667],"type":"Point"}
}