{
  "type": "Feature",
  "properties": {
    "gn:admin1_code":"13.0",
    "gn:asciiname":"Tuowanku Zimale",
    "gn:country_code":"CN",
    "gn:dem":1330,
    "gn:feature_class":"P",
    "gn:feature_code":"PPL",
    "gn:name":"Tuowanku Zimale",
    "gn:population":0,
    "gn:timezone":"Asia/Shanghai",
    "iso:country":"CN",
    "name:und_x_variant":[
        "\u6258\u4e07\u5e93\u5b5c\u739b\u52d2"
    ],
    "wof:name":"Tuowanku Zimale",
    "wof:placetype":"locality"
},
  "geometry": {"coordinates":[77.02436999999998,38.19022],"type":"Point"}
}