{
  "type": "Feature",
  "properties": {
    "gn:admin1_code":"4.0",
    "gn:asciiname":"Jiangjiadun",
    "gn:country_code":"CN",
    "gn:dem":0,
    "gn:feature_class":"P",
    "gn:feature_code":"PPL",
    "gn:name":"Jiangjiadun",
    "gn:population":0,
    "gn:timezone":"Asia/Shanghai",
    "iso:country":"CN",
    "name:zho_x_preferred":[
        "Jiangjiadun"
    ],
    "name:zho_x_variant":[
        "\u848b\u5bb6\u58a9"
    ],
    "wof:name":"Jiangjiadun",
    "wof:placetype":"locality"
},
  "geometry": {"coordinates":[119.90852,33.24845],"type":"Point"}
}