{
  "type": "Feature",
  "properties": {
    "gn:admin1_code":"16.0",
    "gn:asciiname":"Yuanmenbian",
    "gn:country_code":"CN",
    "gn:dem":367,
    "gn:feature_class":"P",
    "gn:feature_code":"PPL",
    "gn:name":"Yuanmenbian",
    "gn:population":0,
    "gn:timezone":"Asia/Shanghai",
    "iso:country":"CN",
    "name:zho_x_preferred":[
        "\u56ed\u95e8\u8fb9"
    ],
    "wof:name":"Yuanmenbian",
    "wof:placetype":"locality"
},
  "geometry": {"coordinates":[107.392,24.2172],"type":"Point"}
}