{
  "type": "Feature",
  "properties": {
    "gn:admin1_code":"24.0",
    "gn:asciiname":"Hanqucun",
    "gn:country_code":"CN",
    "gn:dem":879,
    "gn:feature_class":"P",
    "gn:feature_code":"PPL",
    "gn:name":"Hanqucun",
    "gn:population":0,
    "gn:timezone":"Asia/Shanghai",
    "iso:country":"CN",
    "name:und_x_variant":[
        "\u97e9\u66f2\u6751"
    ],
    "name:zho_x_preferred":[
        "\u97e9\u66f2\u6751"
    ],
    "wof:name":"Hanqucun",
    "wof:placetype":"locality"
},
  "geometry": {"coordinates":[112.9723,39.09129],"type":"Point"}
}