{
  "type": "Feature",
  "properties": {
    "gn:admin1_code":"12.0",
    "gn:asciiname":"Linjiagou",
    "gn:country_code":"CN",
    "gn:dem":1140,
    "gn:feature_class":"P",
    "gn:feature_code":"PPL",
    "gn:name":"Linjiagou",
    "gn:population":0,
    "gn:timezone":"Asia/Shanghai",
    "iso:country":"CN",
    "name:zho_x_preferred":[
        "\u6797\u5bb6\u6c9f"
    ],
    "wof:name":"Linjiagou",
    "wof:placetype":"locality"
},
  "geometry": {"coordinates":[110.40058999999999,31.8443],"type":"Point"}
}