{
  "type": "Feature",
  "properties": {
    "gn:admin1_code":"32.0",
    "gn:asciiname":"Hongminyizu",
    "gn:country_code":"CN",
    "gn:dem":1743,
    "gn:feature_class":"P",
    "gn:feature_code":"PPL",
    "gn:name":"Hongminyizu",
    "gn:population":0,
    "gn:timezone":"Asia/Shanghai",
    "iso:country":"CN",
    "name:zho_x_preferred":[
        "\u7ea2\u6c11\u5f5d\u65cf"
    ],
    "wof:name":"Hongminyizu",
    "wof:placetype":"locality"
},
  "geometry": {"coordinates":[101.6962,26.83503],"type":"Point"}
}