{
  "type": "Feature",
  "properties": {
    "gn:admin1_code":"32.0",
    "gn:asciiname":"Huajiaoping",
    "gn:country_code":"CN",
    "gn:dem":1333,
    "gn:feature_class":"P",
    "gn:feature_code":"PPL",
    "gn:name":"Huajiaoping",
    "gn:population":0,
    "gn:timezone":"Asia/Shanghai",
    "iso:country":"CN",
    "name:zho_x_preferred":[
        "\u82b1\u6912\u576a"
    ],
    "wof:name":"Huajiaoping",
    "wof:placetype":"locality"
},
  "geometry": {"coordinates":[102.20399999999999,29.2295],"type":"Point"}
}