{
  "type": "Feature",
  "properties": {
    "gn:admin1_code":"1.0",
    "gn:asciiname":"Zhulingcun",
    "gn:country_code":"CN",
    "gn:dem":130,
    "gn:feature_class":"P",
    "gn:feature_code":"PPL",
    "gn:name":"Zhulingcun",
    "gn:population":0,
    "gn:timezone":"Asia/Shanghai",
    "iso:country":"CN",
    "name:zho_x_preferred":[
        "\u6731\u5cad\u6751"
    ],
    "wof:name":"Zhulingcun",
    "wof:placetype":"locality"
},
  "geometry": {"coordinates":[116.13464999999999,30.49046],"type":"Point"}
}