{
  "type": "Feature",
  "properties": {
    "gn:admin1_code":"26.0",
    "gn:asciiname":"Dangjia Dianzi",
    "gn:country_code":"CN",
    "gn:dem":1618,
    "gn:feature_class":"P",
    "gn:feature_code":"PPL",
    "gn:name":"Dangjia Dianzi",
    "gn:population":0,
    "gn:timezone":"Asia/Shanghai",
    "iso:country":"CN",
    "name:zho_x_preferred":[
        "\u5f53\u5bb6\u5e97\u5b50"
    ],
    "wof:name":"Dangjia Dianzi",
    "wof:placetype":"locality"
},
  "geometry": {"coordinates":[108.83132000000001,35.33876],"type":"Point"}
}