{
  "type": "Feature",
  "properties": {
    "gn:admin1_code":"9.0",
    "gn:asciiname":"Gangang",
    "gn:country_code":"CN",
    "gn:dem":50,
    "gn:feature_class":"P",
    "gn:feature_code":"PPL",
    "gn:name":"Gangang",
    "gn:population":0,
    "gn:timezone":"Asia/Shanghai",
    "iso:country":"CN",
    "name:zho_x_preferred":[
        "\u7518\u6e2f"
    ],
    "wof:name":"Gangang",
    "wof:placetype":"locality"
},
  "geometry": {"coordinates":[114.49258,32.89533],"type":"Point"}
}