{
  "type": "Feature",
  "properties": {
    "gn:admin1_code":"22.0",
    "gn:asciiname":"Beidingfuzhuangcun",
    "gn:country_code":"CN",
    "gn:dem":30,
    "gn:feature_class":"P",
    "gn:feature_code":"PPL",
    "gn:name":"Beidingfuzhuangcun",
    "gn:population":0,
    "gn:timezone":"Asia/Shanghai",
    "iso:country":"CN",
    "name:zho_x_preferred":[
        "\u5317\u5b9a\u798f\u5e84\u6751"
    ],
    "wof:name":"Beidingfuzhuangcun",
    "wof:placetype":"locality"
},
  "geometry": {"coordinates":[117.00914,40.13499],"type":"Point"}
}