{
  "type": "Feature",
  "properties": {
    "gn:admin1_code":"7.0",
    "gn:asciiname":"Dongyuan",
    "gn:country_code":"CN",
    "gn:dem":713,
    "gn:feature_class":"P",
    "gn:feature_code":"PPL",
    "gn:name":"Dongyuan",
    "gn:population":0,
    "gn:timezone":"Asia/Shanghai",
    "iso:country":"CN",
    "name:ceb_x_preferred":[
        "Dongyuan"
    ],
    "name:deu_x_preferred":[
        "Dongyuan"
    ],
    "name:nor_x_preferred":[
        "Dongyuan"
    ],
    "name:zho_x_preferred":[
        "\u4e1c\u6e90"
    ],
    "wof:name":"Dongyuan",
    "wof:placetype":"locality"
},
  "geometry": {"coordinates":[119.46407000000001,27.16215],"type":"Point"}
}