{
  "type": "Feature",
  "properties": {
    "gn:admin1_code":"32.0",
    "gn:asciiname":"Huanglianping",
    "gn:country_code":"CN",
    "gn:dem":1408,
    "gn:feature_class":"P",
    "gn:feature_code":"PPL",
    "gn:name":"Huanglianping",
    "gn:population":0,
    "gn:timezone":"Asia/Shanghai",
    "iso:country":"CN",
    "name:zho_x_preferred":[
        "\u9ec4\u8fde\u576a"
    ],
    "wof:name":"Huanglianping",
    "wof:placetype":"locality"
},
  "geometry": {"coordinates":[103.721,28.4542],"type":"Point"}
}