{
  "type": "Feature",
  "properties": {
    "gn:admin1_code":"14",
    "gn:asciiname":"Niangcun",
    "gn:country_code":"CN",
    "gn:dem":4515,
    "gn:feature_class":"P",
    "gn:feature_code":"PPL",
    "gn:name":"Niangcun",
    "gn:population":0,
    "gn:timezone":"Asia/Urumqi",
    "iso:country":"CN",
    "name:zho_x_preferred":[
        "\u5a18\u6751"
    ],
    "wof:name":"Niangcun",
    "wof:placetype":"locality"
},
  "geometry": {"coordinates":[89.9019,29.0615],"type":"Point"}
}