{
  "type": "Feature",
  "properties": {
    "gn:admin1_code":"16",
    "gn:asciiname":"Nan'ao",
    "gn:country_code":"CN",
    "gn:dem":544,
    "gn:feature_class":"P",
    "gn:feature_code":"PPL",
    "gn:name":"Nan\u2019ao",
    "gn:population":0,
    "gn:timezone":"Asia/Shanghai",
    "iso:country":"CN",
    "name:und_x_variant":[
        "Nan\u2019ao"
    ],
    "name:zho_x_preferred":[
        "\u5357\u5773"
    ],
    "wof:name":"Nan'ao",
    "wof:placetype":"locality"
},
  "geometry": {"coordinates":[110.154,25.6258],"type":"Point"}
}