{
  "type": "Feature",
  "properties": {
    "gn:admin1_code":"19.0",
    "gn:asciiname":"Xujiahu",
    "gn:country_code":"CN",
    "gn:dem":56,
    "gn:feature_class":"P",
    "gn:feature_code":"PPL",
    "gn:name":"Xujiahu",
    "gn:population":0,
    "gn:timezone":"Asia/Shanghai",
    "iso:country":"CN",
    "name:und_x_variant":[
        "\u5f90\u5bb6\u6e56"
    ],
    "name:zho_x_preferred":[
        "\u5f90\u5bb6\u6e56"
    ],
    "wof:name":"Xujiahu",
    "wof:placetype":"locality"
},
  "geometry": {"coordinates":[123.62881000000002,42.15848],"type":"Point"}
}