{
  "type": "Feature",
  "properties": {
    "gn:admin1_code":"4.0",
    "gn:asciiname":"Shenghong",
    "gn:country_code":"CN",
    "gn:dem":4,
    "gn:feature_class":"P",
    "gn:feature_code":"PPL",
    "gn:name":"Shenghong",
    "gn:population":0,
    "gn:timezone":"Asia/Shanghai",
    "iso:country":"CN",
    "name:zho_x_preferred":[
        "\u80dc\u5b8f"
    ],
    "wof:name":"Shenghong",
    "wof:placetype":"locality"
},
  "geometry": {"coordinates":[121.29273000000001,32.02929],"type":"Point"}
}