{
  "type": "Feature",
  "properties": {
    "gn:admin1_code":"1.0",
    "gn:asciiname":"Hexiyuancun",
    "gn:country_code":"CN",
    "gn:dem":39,
    "gn:feature_class":"P",
    "gn:feature_code":"PPL",
    "gn:name":"Hexiyuancun",
    "gn:population":0,
    "gn:timezone":"Asia/Shanghai",
    "iso:country":"CN",
    "name:zho_x_preferred":[
        "\u6cb3\u897f\u56ed\u6751"
    ],
    "wof:name":"Hexiyuancun",
    "wof:placetype":"locality"
},
  "geometry": {"coordinates":[116.01488999999999,33.64400999999999],"type":"Point"}
}