{
  "type": "Feature",
  "properties": {
    "gn:admin1_code":"2.0",
    "gn:asciiname":"Tongkengwu",
    "gn:country_code":"CN",
    "gn:dem":143,
    "gn:feature_class":"P",
    "gn:feature_code":"PPL",
    "gn:name":"Tongkengwu",
    "gn:population":0,
    "gn:timezone":"Asia/Shanghai",
    "iso:country":"CN",
    "name:und_x_variant":[
        "\u94dc\u5751\u575e"
    ],
    "wof:name":"Tongkengwu",
    "wof:placetype":"locality"
},
  "geometry": {"coordinates":[119.60612,30.71182],"type":"Point"}
}