{
  "type": "Feature",
  "properties": {
    "gn:admin1_code":"32.0",
    "gn:asciiname":"Zhuangzishan",
    "gn:country_code":"CN",
    "gn:dem":1090,
    "gn:feature_class":"P",
    "gn:feature_code":"PPL",
    "gn:name":"Zhuangzishan",
    "gn:population":0,
    "gn:timezone":"Asia/Shanghai",
    "iso:country":"CN",
    "name:zho_x_preferred":[
        "\u5e84\u5b50\u5c71"
    ],
    "wof:name":"Zhuangzishan",
    "wof:placetype":"locality"
},
  "geometry": {"coordinates":[105.48999999999999,32.6148],"type":"Point"}
}