{
  "type": "Feature",
  "properties": {
    "gn:admin1_code":"18",
    "gn:asciiname":"Liangshuijing",
    "gn:country_code":"CN",
    "gn:dem":1450,
    "gn:feature_class":"P",
    "gn:feature_code":"PPL",
    "gn:name":"Liangshuijing",
    "gn:population":0,
    "gn:timezone":"Asia/Shanghai",
    "iso:country":"CN",
    "name:zho_x_preferred":[
        "\u51c9\u6c34\u4e95"
    ],
    "wof:name":"Liangshuijing",
    "wof:placetype":"locality"
},
  "geometry": {"coordinates":[105.502,26.0455],"type":"Point"}
}