{
  "type": "Feature",
  "properties": {
    "gn:admin1_code":"24.0",
    "gn:asciiname":"Chilin",
    "gn:country_code":"CN",
    "gn:dem":1172,
    "gn:feature_class":"P",
    "gn:feature_code":"PPL",
    "gn:name":"Chilin",
    "gn:population":0,
    "gn:timezone":"Asia/Shanghai",
    "iso:country":"CN",
    "name:zho_x_preferred":[
        "\u8d64\u6797"
    ],
    "wof:name":"Chilin",
    "wof:placetype":"locality"
},
  "geometry": {"coordinates":[113.5381,36.30651],"type":"Point"}
}