{
  "type": "Feature",
  "properties": {
    "gn:admin1_code":"4.0",
    "gn:asciiname":"Xinhaicun Liuzu",
    "gn:country_code":"CN",
    "gn:dem":6,
    "gn:feature_class":"P",
    "gn:feature_code":"PPLF",
    "gn:name":"Xinhaicun Liuzu",
    "gn:population":0,
    "gn:timezone":"Asia/Shanghai",
    "iso:country":"CN",
    "name:zho_x_preferred":[
        "\u65b0\u6d77\u6751\u516d\u7ec4"
    ],
    "wof:name":"Xinhaicun Liuzu",
    "wof:placetype":"locality"
},
  "geometry": {"coordinates":[120.75158,32.91285],"type":"Point"}
}