{
  "type": "Feature",
  "properties": {
    "gn:admin1_code":"19.0",
    "gn:asciiname":"Qianshenjingzi",
    "gn:country_code":"CN",
    "gn:dem":30,
    "gn:feature_class":"P",
    "gn:feature_code":"PPL",
    "gn:name":"Qianshenjingzi",
    "gn:population":0,
    "gn:timezone":"Asia/Shanghai",
    "iso:country":"CN",
    "name:zho_x_preferred":[
        "\u524d\u6df1\u4e95\u5b50"
    ],
    "wof:name":"Qianshenjingzi",
    "wof:placetype":"locality"
},
  "geometry": {"coordinates":[123.01000000000001,42.1048],"type":"Point"}
}