{
  "type": "Feature",
  "properties": {
    "gn:admin1_code":"5.0",
    "gn:asciiname":"Yongquancun",
    "gn:country_code":"CN",
    "gn:dem":106,
    "gn:feature_class":"P",
    "gn:feature_code":"PPL",
    "gn:name":"Yongquancun",
    "gn:population":0,
    "gn:timezone":"Asia/Shanghai",
    "iso:country":"CN",
    "name:zho_x_preferred":[
        "\u6d8c\u6cc9\u6751"
    ],
    "wof:name":"Yongquancun",
    "wof:placetype":"locality"
},
  "geometry": {"coordinates":[130.43114,42.95915],"type":"Point"}
}