{
  "type": "Feature",
  "properties": {
    "gn:admin1_code":"4.0",
    "gn:asciiname":"Wangrizhuang",
    "gn:country_code":"CN",
    "gn:dem":1,
    "gn:feature_class":"P",
    "gn:feature_code":"PPL",
    "gn:name":"Wangrizhuang",
    "gn:population":0,
    "gn:timezone":"Asia/Shanghai",
    "iso:country":"CN",
    "name:zho_x_preferred":[
        "\u738b\u65e5\u5e84"
    ],
    "wof:name":"Wangrizhuang",
    "wof:placetype":"locality"
},
  "geometry": {"coordinates":[119.48821,33.5072],"type":"Point"}
}