{
  "type": "Feature",
  "properties": {
    "gn:admin1_code":"33.0",
    "gn:asciiname":"Liuhe",
    "gn:country_code":"CN",
    "gn:dem":617,
    "gn:feature_class":"P",
    "gn:feature_code":"PPL",
    "gn:name":"Liuhe",
    "gn:population":0,
    "gn:timezone":"Asia/Shanghai",
    "iso:country":"CN",
    "name:zho_x_preferred":[
        "\u516d\u5408"
    ],
    "wof:name":"Liuhe",
    "wof:placetype":"locality"
},
  "geometry": {"coordinates":[108.64995999999999,31.23714],"type":"Point"}
}