{
  "type": "Feature",
  "properties": {
    "gn:admin1_code":"29",
    "gn:asciiname":"Nasheng Shangzhai",
    "gn:country_code":"CN",
    "gn:dem":1525,
    "gn:feature_class":"P",
    "gn:feature_code":"PPL",
    "gn:name":"Nasheng Shangzhai",
    "gn:population":0,
    "gn:timezone":"Asia/Shanghai",
    "iso:country":"CN",
    "name:zho_x_preferred":[
        "\u90a3\u7701\u4e0a\u5be8"
    ],
    "wof:name":"Nasheng Shangzhai",
    "wof:placetype":"locality"
},
  "geometry": {"coordinates":[104.937,24.1605],"type":"Point"}
}