{
  "type": "Feature",
  "properties": {
    "gn:admin1_code":"29.0",
    "gn:asciiname":"Xiaoyanfang",
    "gn:country_code":"CN",
    "gn:dem":1882,
    "gn:feature_class":"P",
    "gn:feature_code":"PPL",
    "gn:name":"Xiaoyanfang",
    "gn:population":0,
    "gn:timezone":"Asia/Shanghai",
    "iso:country":"CN",
    "name:zho_x_preferred":[
        "\u5c0f\u5ca9\u574a"
    ],
    "wof:name":"Xiaoyanfang",
    "wof:placetype":"locality"
},
  "geometry": {"coordinates":[104.339,27.7888],"type":"Point"}
}