{
  "type": "Feature",
  "properties": {
    "gn:admin1_code":"3.0",
    "gn:asciiname":"Xianghu",
    "gn:country_code":"CN",
    "gn:dem":311,
    "gn:feature_class":"P",
    "gn:feature_code":"PPL",
    "gn:name":"Xianghu",
    "gn:population":0,
    "gn:timezone":"Asia/Shanghai",
    "iso:country":"CN",
    "name:und_x_variant":[
        "\u8c61\u6e56"
    ],
    "wof:name":"Xianghu",
    "wof:placetype":"locality"
},
  "geometry": {"coordinates":[115.25945,25.81738],"type":"Point"}
}