{
  "type": "Feature",
  "properties": {
    "gn:admin1_code":"25.0",
    "gn:asciiname":"Yazhuang",
    "gn:cc2":"CN",
    "gn:country_code":"CN",
    "gn:dem":345,
    "gn:feature_class":"P",
    "gn:feature_code":"PPL",
    "gn:name":"Yazhuang",
    "gn:population":0,
    "gn:timezone":"Asia/Shanghai",
    "iso:country":"CN",
    "name:und_x_variant":[
        "Ya-chuang",
        "Yazhuang"
    ],
    "wof:name":"Yazhuang",
    "wof:placetype":"locality"
},
  "geometry": {"coordinates":[118.56667,36.06667],"type":"Point"}
}