{
  "type": "Feature",
  "properties": {
    "gn:admin1_code":"2.0",
    "gn:asciiname":"Yanggong'ao",
    "gn:country_code":"CN",
    "gn:dem":9,
    "gn:feature_class":"P",
    "gn:feature_code":"PPL",
    "gn:name":"Yanggong\u2019ao",
    "gn:population":0,
    "gn:timezone":"Asia/Shanghai",
    "iso:country":"CN",
    "name:und_x_variant":[
        "Yanggong\u2019ao"
    ],
    "name:zho_x_preferred":[
        "\u6768\u516c\u5c99"
    ],
    "wof:name":"Yanggong'ao",
    "wof:placetype":"locality"
},
  "geometry": {"coordinates":[121.21295000000001,28.37003],"type":"Point"}
}