{
  "type": "Feature",
  "properties": {
    "gn:admin1_code":"32.0",
    "gn:asciiname":"Jiangzha",
    "gn:country_code":"CN",
    "gn:dem":3059,
    "gn:feature_class":"P",
    "gn:feature_code":"PPL",
    "gn:name":"Jiangzha",
    "gn:population":0,
    "gn:timezone":"Asia/Shanghai",
    "iso:country":"CN",
    "name:zho_x_preferred":[
        "\u964d\u624e"
    ],
    "wof:name":"Jiangzha",
    "wof:placetype":"locality"
},
  "geometry": {"coordinates":[102.80687,34.15798],"type":"Point"}
}