{
  "type": "Feature",
  "properties": {
    "iso:country":"CN",
    "ne:ADM0CAP":0.0,
    "ne:ADM0NAME":"China",
    "ne:ADM0_A3":"CHN",
    "ne:ADM1NAME":"Guizhou",
    "ne:ADMIN1_COD":0,
    "ne:CAPALT":0,
    "ne:CHANGED":0,
    "ne:CHECKME":0,
    "ne:COMPARE":0,
    "ne:DIFFASCII":0,
    "ne:ELEVATION":0.0,
    "ne:FEATURECLA":"Populated place",
    "ne:GEONAMEID":-1123,
    "ne:GEONAMESNO":"Top 50 ranks with no GeoNames match due to small population, not in GeoNames, or poor NEV placement.",
    "ne:GN_POP":0,
    "ne:GTOPO30":0.0,
    "ne:ISO_A2":"CN",
    "ne:LABELRANK":1,
    "ne:LATITUDE":26.594435,
    "ne:LONGITUDE":104.833332,
    "ne:LS_MATCH":1,
    "ne:LS_NAME":"Lupanshui",
    "ne:MAX_AREAKM":300.0,
    "ne:MAX_AREAMI":116.0,
    "ne:MAX_BBXMAX":105.291667,
    "ne:MAX_BBXMIN":104.716667,
    "ne:MAX_BBYMAX":26.666667,
    "ne:MAX_BBYMIN":26.275,
    "ne:MAX_NATSCA":50.0,
    "ne:MAX_PERKM":317.0,
    "ne:MAX_PERMI":197.0,
    "ne:MAX_POP10":551512,
    "ne:MAX_POP20":551512,
    "ne:MAX_POP300":0,
    "ne:MAX_POP310":0,
    "ne:MAX_POP50":551512,
    "ne:MEAN_BBXC":105.010838,
    "ne:MEAN_BBYC":26.506234,
    "ne:MEGACITY":0,
    "ne:MEGANAME":"Liupanshui",
    "ne:MIN_AREAKM":300.0,
    "ne:MIN_AREAMI":116.0,
    "ne:MIN_BBXMAX":105.291667,
    "ne:MIN_BBXMIN":104.716667,
    "ne:MIN_BBYMAX":26.666667,
    "ne:MIN_BBYMIN":26.275,
    "ne:MIN_PERKM":317.0,
    "ne:MIN_PERMI":197.0,
    "ne:NAME":"Lupanshui",
    "ne:NAMEASCII":"Lupanshui",
    "ne:NAMEDIFF":0,
    "ne:NATSCALE":50,
    "ne:POP1950":405,
    "ne:POP1955":443,
    "ne:POP1960":484,
    "ne:POP1965":530,
    "ne:POP1970":579,
    "ne:POP1975":633,
    "ne:POP1980":692,
    "ne:POP1985":757,
    "ne:POP1990":827,
    "ne:POP1995":905,
    "ne:POP2000":989,
    "ne:POP2005":1149,
    "ne:POP2010":1221,
    "ne:POP2015":1329,
    "ne:POP2020":1493,
    "ne:POP2025":1632,
    "ne:POP2050":1745,
    "ne:POP_MAX":1221000,
    "ne:POP_MIN":551512,
    "ne:POP_OTHER":538534,
    "ne:RANK_MAX":12,
    "ne:RANK_MIN":11,
    "ne:SCALERANK":4,
    "ne:SOV0NAME":"China",
    "ne:SOV_A3":"CHN",
    "ne:UN_ADM0":"China",
    "ne:UN_FID":78,
    "ne:UN_LAT":26.59,
    "ne:UN_LONG":104.83,
    "ne:WORLDCITY":0,
    "ne:min_zoom":5.6,
    "wof:name":"Lupanshui",
    "wof:placetype":"locality"
},
  "geometry": {"coordinates":[104.83138621233201,26.59638069239469],"type":"Point"}
}