{
  "type": "Feature",
  "properties": {
    "gn:country":"CN",
    "gn:fcode":"PPL",
    "gn:pop":820,
    "iso:country":"CN",
    "name:deu_x_preferred":[
        "Conghua"
    ],
    "name:eus_x_preferred":[
        "Conghua"
    ],
    "name:fas_x_preferred":[
        "\u06a9\u0627\u0646\u06af\u0647\u0648\u0627"
    ],
    "name:fra_x_preferred":[
        "Conghua"
    ],
    "name:hak_x_preferred":[
        "Chhi\u00f9ng-fa-s\u1e73"
    ],
    "name:jpn_x_preferred":[
        "\u5f93\u5316\u533a"
    ],
    "name:kor_x_preferred":[
        "\ucda9\ud654\uad6c"
    ],
    "name:mwl_x_preferred":[
        "Conghua"
    ],
    "name:nld_x_preferred":[
        "Conghua"
    ],
    "name:nor_x_preferred":[
        "Conghua"
    ],
    "name:pam_x_preferred":[
        "Conghua"
    ],
    "name:pnb_x_preferred":[
        "\u06a9\u0648\u0646\u06af\u06be\u0648\u0622"
    ],
    "name:spa_x_preferred":[
        "Conghua"
    ],
    "name:swe_x_preferred":[
        "Conghua"
    ],
    "name:vie_x_preferred":[
        "T\u00f9ng H\u00f3a"
    ],
    "name:zho_x_preferred":[
        "\u6fb3\u5934"
    ],
    "name:zho_x_variant":[
        "\u4ece\u5316\u533a"
    ],
    "qs:name":"Aotou",
    "qs:photos_9r":0,
    "qs:photos_sr":0,
    "qs:pop_sr":"2",
    "wd:wordcount":263,
    "wof:name":"Aotou",
    "wof:placetype":"locality",
    "wof:population":820
},
  "geometry": {"coordinates":[118.22945,24.51999],"type":"Point"}
}