{
  "type": "Feature",
  "properties": {
    "gn:country":"CN",
    "gn:fcode":"PPL",
    "gn:pop":820,
    "iso:country":"CN",
    "name:zho_x_preferred":[
        "\u6fb3\u5934"
    ],
    "qs:name":"Aotou",
    "qs:photos_9r":0,
    "qs:photos_sr":0,
    "qs:pop_sr":"2",
    "wd:wordcount":263,
    "wof:name":"Aotou",
    "wof:placetype":"locality",
    "wof:population":820
},
  "geometry": {"coordinates":[118.22945,24.51999],"type":"Point"}
}