{
  "type": "Feature",
  "properties": {
    "gn:admin1_code":"02",
    "gn:asciiname":"Daxie",
    "gn:country_code":"CN",
    "gn:dem":47,
    "gn:feature_class":"P",
    "gn:feature_code":"PPL",
    "gn:name":"Daxie",
    "gn:population":0,
    "gn:timezone":"Asia/Shanghai",
    "iso:country":"CN",
    "name:und_x_variant":[
        "Daxie Jiedao",
        "Daxie"
    ],
    "name:zho_x_preferred":[
        "\u5927\u69ad"
    ],
    "name:zho_x_variant":[
        "\u5927\u69ad\u8857\u9053"
    ],
    "wof:name":"Daxie",
    "wof:placetype":"locality"
},
  "geometry": {"coordinates":[121.95157,29.90124],"type":"Point"}
}