{
  "type": "Feature",
  "properties": {
    "gn:admin1_code":"14.0",
    "gn:asciiname":"Qusuola",
    "gn:country_code":"CN",
    "gn:dem":4137,
    "gn:feature_class":"P",
    "gn:feature_code":"PPL",
    "gn:name":"Qusuola",
    "gn:population":0,
    "gn:timezone":"Asia/Urumqi",
    "iso:country":"CN",
    "name:zho_x_preferred":[
        "\u66f2\u7d22\u62c9"
    ],
    "wof:name":"Qusuola",
    "wof:placetype":"locality"
},
  "geometry": {"coordinates":[97.20553,29.34776],"type":"Point"}
}