{
  "type": "Feature",
  "properties": {
    "gn:admin1_code":"9.0",
    "gn:asciiname":"Shangtianyuan",
    "gn:country_code":"CN",
    "gn:dem":307,
    "gn:feature_class":"P",
    "gn:feature_code":"PPL",
    "gn:name":"Shangtianyuan",
    "gn:population":0,
    "gn:timezone":"Asia/Shanghai",
    "iso:country":"CN",
    "name:zho_x_preferred":[
        "\u4e0a\u5929\u9662"
    ],
    "wof:name":"Shangtianyuan",
    "wof:placetype":"locality"
},
  "geometry": {"coordinates":[112.51466000000001,34.41925999999999],"type":"Point"}
}