{
  "type": "Feature",
  "properties": {
    "gn:admin1_code":"4.0",
    "gn:asciiname":"Wenjun Wuzu",
    "gn:country_code":"CN",
    "gn:dem":6,
    "gn:feature_class":"P",
    "gn:feature_code":"PPLF",
    "gn:name":"Wenjun Wuzu",
    "gn:population":0,
    "gn:timezone":"Asia/Shanghai",
    "iso:country":"CN",
    "name:zho_x_preferred":[
        "\u6587\u4fca\u4e94\u7ec4"
    ],
    "wof:name":"Wenjun Wuzu",
    "wof:placetype":"locality"
},
  "geometry": {"coordinates":[120.84157,32.08245],"type":"Point"}
}