{
  "type": "Feature",
  "properties": {
    "gn:admin1_code":"12.0",
    "gn:asciiname":"Zhongfenguo",
    "gn:country_code":"CN",
    "gn:dem":47,
    "gn:feature_class":"P",
    "gn:feature_code":"PPL",
    "gn:name":"Zhongfenguo",
    "gn:population":0,
    "gn:timezone":"Asia/Shanghai",
    "iso:country":"CN",
    "name:zho_x_preferred":[
        "\u4e2d\u4efd\u90ed"
    ],
    "wof:name":"Zhongfenguo",
    "wof:placetype":"locality"
},
  "geometry": {"coordinates":[113.79087,31.07888],"type":"Point"}
}