{
  "type": "Feature",
  "properties": {
    "gn:admin1_code":"6.0",
    "gn:asciiname":"Changweiliang",
    "gn:country_code":"CN",
    "gn:dem":2721,
    "gn:feature_class":"P",
    "gn:feature_code":"PPL",
    "gn:name":"Changweiliang",
    "gn:population":0,
    "gn:timezone":"Asia/Urumqi",
    "iso:country":"CN",
    "wof:name":"Changweiliang",
    "wof:placetype":"locality"
},
  "geometry": {"coordinates":[92.11667,38.31667],"type":"Point"}
}