{
  "type": "Feature",
  "properties": {
    "gn:admin1_code":"18",
    "gn:asciiname":"Yanziyan",
    "gn:country_code":"CN",
    "gn:dem":834,
    "gn:feature_class":"P",
    "gn:feature_code":"PPL",
    "gn:name":"Yanziyan",
    "gn:population":0,
    "gn:timezone":"Asia/Shanghai",
    "iso:country":"CN",
    "name:zho_x_preferred":[
        "\u71d5\u5b50\u5ca9"
    ],
    "wof:name":"Yanziyan",
    "wof:placetype":"locality"
},
  "geometry": {"coordinates":[107.28400000000001,28.0673],"type":"Point"}
}