{
  "type": "Feature",
  "properties": {
    "gn:admin1_code":"12.0",
    "gn:asciiname":"Longjiawan",
    "gn:country_code":"CN",
    "gn:dem":841,
    "gn:feature_class":"P",
    "gn:feature_code":"PPL",
    "gn:name":"Longjiawan",
    "gn:population":0,
    "gn:timezone":"Asia/Shanghai",
    "iso:country":"CN",
    "name:zho_x_preferred":[
        "Longjiawan"
    ],
    "name:zho_x_variant":[
        "\u9f99\u5bb6\u6e7e"
    ],
    "wof:name":"Longjiawan",
    "wof:placetype":"locality"
},
  "geometry": {"coordinates":[109.71165999999999,29.86745],"type":"Point"}
}