{
  "type": "Feature",
  "properties": {
    "gn:admin1_code":"2",
    "gn:asciiname":"Fengmen",
    "gn:country_code":"CN",
    "gn:dem":572,
    "gn:feature_class":"P",
    "gn:feature_code":"PPLA4",
    "gn:name":"Fengmen",
    "gn:population":0,
    "gn:timezone":"Asia/Shanghai",
    "iso:country":"CN",
    "name:und_x_variant":[
        "Waiyang",
        "Fengmen",
        "\u5cf0\u95e8",
        "Fengmen Xiang"
    ],
    "name:zho_x_preferred":[
        "\u5916\u579f"
    ],
    "name:zho_x_variant":[
        "\u5cf0\u95e8\u4e61"
    ],
    "wof:name":"Fengmen",
    "wof:placetype":"locality"
},
  "geometry": {"coordinates":[119.85917000000001,27.69833],"type":"Point"}
}