{
  "type": "Feature",
  "properties": {
    "gn:admin1_code":"14.0",
    "gn:asciiname":"Kangsha",
    "gn:country_code":"CN",
    "gn:dem":4153,
    "gn:feature_class":"P",
    "gn:feature_code":"PPL",
    "gn:name":"Kangsha",
    "gn:population":0,
    "gn:timezone":"Asia/Urumqi",
    "iso:country":"CN",
    "name:zho_x_preferred":[
        "\u5eb7\u6c99"
    ],
    "wof:name":"Kangsha",
    "wof:placetype":"locality"
},
  "geometry": {"coordinates":[87.3638,29.3756],"type":"Point"}
}