{
  "type": "Feature",
  "properties": {
    "gn:admin1_code":"1.0",
    "gn:asciiname":"Qidouwangcun",
    "gn:country_code":"CN",
    "gn:dem":156,
    "gn:feature_class":"P",
    "gn:feature_code":"PPL",
    "gn:name":"Qidouwangcun",
    "gn:population":0,
    "gn:timezone":"Asia/Shanghai",
    "iso:country":"CN",
    "name:zho_x_preferred":[
        "\u4e03\u90fd\u6c6a\u6751"
    ],
    "wof:name":"Qidouwangcun",
    "wof:placetype":"locality"
},
  "geometry": {"coordinates":[119.21991,30.57928],"type":"Point"}
}