{
  "type": "Feature",
  "properties": {
    "gn:admin1_code":"16",
    "gn:asciiname":"Santang",
    "gn:country_code":"CN",
    "gn:dem":150,
    "gn:feature_class":"P",
    "gn:feature_code":"PPL",
    "gn:name":"Santang",
    "gn:population":0,
    "gn:timezone":"Asia/Shanghai",
    "iso:country":"CN",
    "name:ceb_x_preferred":[
        "Santang"
    ],
    "name:swe_x_preferred":[
        "Santang"
    ],
    "name:zho_x_preferred":[
        "\u4e09\u5858"
    ],
    "wof:name":"Santang",
    "wof:placetype":"locality"
},
  "geometry": {"coordinates":[110.286,25.1511],"type":"Point"}
}