{
  "type": "Feature",
  "properties": {
    "gn:admin1_code":"07",
    "gn:asciiname":"Fozaige",
    "gn:country_code":"CN",
    "gn:dem":783,
    "gn:feature_class":"P",
    "gn:feature_code":"PPL",
    "gn:name":"Fozaige",
    "gn:population":0,
    "gn:timezone":"Asia/Shanghai",
    "iso:country":"CN",
    "name:und_x_variant":[
        "Fuzige"
    ],
    "name:zho_x_preferred":[
        "\u4f5b\u4ed4\u683c"
    ],
    "wof:name":"Fozaige",
    "wof:placetype":"locality"
},
  "geometry": {"coordinates":[118.09062,25.36491],"type":"Point"}
}