{
  "type": "Feature",
  "properties": {
    "gn:admin1_code":"15.0",
    "gn:asciiname":"Wangping",
    "gn:country_code":"CN",
    "gn:dem":1701,
    "gn:feature_class":"P",
    "gn:feature_code":"PPL",
    "gn:name":"Wangping",
    "gn:population":0,
    "gn:timezone":"Asia/Shanghai",
    "iso:country":"CN",
    "name:zho_x_preferred":[
        "\u6c6a\u576a"
    ],
    "wof:name":"Wangping",
    "wof:placetype":"locality"
},
  "geometry": {"coordinates":[105.15900000000001,34.8615],"type":"Point"}
}