{
  "type": "Feature",
  "properties": {
    "gn:admin1_code":"16",
    "gn:asciiname":"Woguitang",
    "gn:country_code":"CN",
    "gn:dem":163,
    "gn:feature_class":"P",
    "gn:feature_code":"PPL",
    "gn:name":"Woguitang",
    "gn:population":0,
    "gn:timezone":"Asia/Shanghai",
    "iso:country":"CN",
    "name:zho_x_preferred":[
        "\u5367\u9f9f\u5858"
    ],
    "wof:name":"Woguitang",
    "wof:placetype":"locality"
},
  "geometry": {"coordinates":[110.66800000000001,24.6588],"type":"Point"}
}