{
  "type": "Feature",
  "properties": {
    "gn:admin1_code":"24.0",
    "gn:asciiname":"Luyagou",
    "gn:country_code":"CN",
    "gn:dem":995,
    "gn:feature_class":"P",
    "gn:feature_code":"PPL",
    "gn:name":"Luyagou",
    "gn:population":0,
    "gn:timezone":"Asia/Shanghai",
    "iso:country":"CN",
    "name:zho_x_preferred":[
        "\u82a6\u82bd\u6c9f"
    ],
    "wof:name":"Luyagou",
    "wof:placetype":"locality"
},
  "geometry": {"coordinates":[113.43782,38.34242],"type":"Point"}
}