{
  "type": "Feature",
  "properties": {
    "gn:admin1_code":"29.0",
    "gn:asciiname":"Kouyao",
    "gn:country_code":"CN",
    "gn:dem":1264,
    "gn:feature_class":"P",
    "gn:feature_code":"PPL",
    "gn:name":"Kouyao",
    "gn:population":0,
    "gn:timezone":"Asia/Shanghai",
    "iso:country":"CN",
    "name:und_x_variant":[
        "Koume",
        "Kouyao"
    ],
    "name:zho_x_preferred":[
        "\u6263\u4e48"
    ],
    "wof:name":"Kouyao",
    "wof:placetype":"locality"
},
  "geometry": {"coordinates":[101.23999999999999,24.0878],"type":"Point"}
}