{
  "type": "Feature",
  "properties": {
    "gn:admin1_code":"30.0",
    "gn:asciiname":"Dengwo",
    "gn:country_code":"CN",
    "gn:dem":152,
    "gn:feature_class":"P",
    "gn:feature_code":"PPL",
    "gn:name":"Dengwo",
    "gn:population":0,
    "gn:timezone":"Asia/Shanghai",
    "iso:country":"CN",
    "name:zho_x_preferred":[
        "\u9093\u7a9d"
    ],
    "wof:name":"Dengwo",
    "wof:placetype":"locality"
},
  "geometry": {"coordinates":[114.86727,23.51361],"type":"Point"}
}