{
  "type": "Feature",
  "properties": {
    "gn:admin1_code":"16.0",
    "gn:asciiname":"Xiadengdong",
    "gn:country_code":"CN",
    "gn:dem":425,
    "gn:feature_class":"P",
    "gn:feature_code":"PPL",
    "gn:name":"Xiadengdong",
    "gn:population":0,
    "gn:timezone":"Asia/Shanghai",
    "iso:country":"CN",
    "name:zho_x_preferred":[
        "\u4e0b\u9093\u6d1e"
    ],
    "wof:name":"Xiadengdong",
    "wof:placetype":"locality"
},
  "geometry": {"coordinates":[108.889,25.3131],"type":"Point"}
}