{
  "type": "Feature",
  "properties": {
    "gn:admin1_code":"32.0",
    "gn:asciiname":"Gediqiu",
    "gn:country_code":"CN",
    "gn:dem":3204,
    "gn:feature_class":"P",
    "gn:feature_code":"PPL",
    "gn:name":"Gediqiu",
    "gn:population":0,
    "gn:timezone":"Asia/Shanghai",
    "iso:country":"CN",
    "name:zho_x_preferred":[
        "\u683c\u5730\u79cb"
    ],
    "wof:name":"Gediqiu",
    "wof:placetype":"locality"
},
  "geometry": {"coordinates":[102.01882000000001,32.30185],"type":"Point"}
}