{
  "type": "Feature",
  "properties": {
    "gn:admin1_code":"15.0",
    "gn:asciiname":"Azitan",
    "gn:country_code":"CN",
    "gn:dem":2881,
    "gn:feature_class":"P",
    "gn:feature_code":"PPL",
    "gn:name":"Azitan",
    "gn:population":0,
    "gn:timezone":"Asia/Shanghai",
    "iso:country":"CN",
    "name:und_x_variant":[
        "\u963f\u5b50\u6ee9"
    ],
    "wof:name":"Azitan",
    "wof:placetype":"locality"
},
  "geometry": {"coordinates":[103.27472,34.70505],"type":"Point"}
}