{
  "type": "Feature",
  "properties": {
    "gn:admin1_code":"10.0",
    "gn:asciiname":"Houxinzhuang",
    "gn:country_code":"CN",
    "gn:dem":26,
    "gn:feature_class":"P",
    "gn:feature_code":"PPL",
    "gn:name":"Houxinzhuang",
    "gn:population":0,
    "gn:timezone":"Asia/Shanghai",
    "iso:country":"CN",
    "name:zho_x_preferred":[
        "\u4faf\u8f9b\u5e84"
    ],
    "wof:name":"Houxinzhuang",
    "wof:placetype":"locality"
},
  "geometry": {"coordinates":[116.01036000000001,39.34962],"type":"Point"}
}