{
  "type": "Feature",
  "properties": {
    "gn:admin1_code":"26.0",
    "gn:asciiname":"Yangwancun",
    "gn:country_code":"CN",
    "gn:dem":1675,
    "gn:feature_class":"P",
    "gn:feature_code":"PPL",
    "gn:name":"Yangwancun",
    "gn:population":0,
    "gn:timezone":"Asia/Shanghai",
    "iso:country":"CN",
    "name:zho_x_preferred":[
        "\u9633\u6e7e\u6751"
    ],
    "wof:name":"Yangwancun",
    "wof:placetype":"locality"
},
  "geometry": {"coordinates":[107.99114,37.27399000000001],"type":"Point"}
}