{
  "type": "Feature",
  "properties": {
    "gn:admin1_code":"11.0",
    "gn:asciiname":"Damiaoqian",
    "gn:country_code":"CN",
    "gn:dem":39,
    "gn:feature_class":"P",
    "gn:feature_code":"PPL",
    "gn:name":"Damiaoqian",
    "gn:population":0,
    "gn:timezone":"Asia/Shanghai",
    "iso:country":"CN",
    "name:zho_x_preferred":[
        "\u5927\u5e99\u524d"
    ],
    "wof:name":"Damiaoqian",
    "wof:placetype":"locality"
},
  "geometry": {"coordinates":[113.14537,27.54362],"type":"Point"}
}