{
  "type": "Feature",
  "properties": {
    "gn:admin1_code":"31.0",
    "gn:asciiname":"Jindui",
    "gn:country_code":"CN",
    "gn:dem":19,
    "gn:feature_class":"P",
    "gn:feature_code":"PPL",
    "gn:name":"Jindui",
    "gn:population":0,
    "gn:timezone":"Asia/Shanghai",
    "iso:country":"CN",
    "name:zho_x_preferred":[
        "Jindui"
    ],
    "name:zho_x_variant":[
        "\u91d1\u5806"
    ],
    "wof:name":"Jindui",
    "wof:placetype":"locality"
},
  "geometry": {"coordinates":[110.66905,19.85234],"type":"Point"}
}