{
  "type": "Feature",
  "properties": {
    "gn:admin1_code":"07",
    "gn:asciiname":"Hongkeng",
    "gn:country_code":"CN",
    "gn:dem":55,
    "gn:feature_class":"P",
    "gn:feature_code":"PPL",
    "gn:name":"Hongkeng",
    "gn:population":0,
    "gn:timezone":"Asia/Shanghai",
    "iso:country":"CN",
    "name:und_x_variant":[
        "\u7ea2\u5751"
    ],
    "name:zho_x_preferred":[
        "\u7ea2\u5751"
    ],
    "wof:name":"Hongkeng",
    "wof:placetype":"locality"
},
  "geometry": {"coordinates":[118.51778,25.18056],"type":"Point"}
}