{
  "type": "Feature",
  "properties": {
    "gn:admin1_code":"5",
    "gn:asciiname":"Houshengtun",
    "gn:country_code":"CN",
    "gn:dem":320,
    "gn:feature_class":"P",
    "gn:feature_code":"PPL",
    "gn:name":"Houshengtun",
    "gn:population":0,
    "gn:timezone":"Asia/Shanghai",
    "iso:country":"CN",
    "name:zho_x_preferred":[
        "\u540e\u751f\u5c6f"
    ],
    "wof:name":"Houshengtun",
    "wof:placetype":"locality"
},
  "geometry": {"coordinates":[127.58,43.8691],"type":"Point"}
}