{
  "type": "Feature",
  "properties": {
    "gn:admin1_code":"18",
    "gn:asciiname":"Xiajiaben",
    "gn:country_code":"CN",
    "gn:dem":1017,
    "gn:feature_class":"P",
    "gn:feature_code":"PPL",
    "gn:name":"Xiajiaben",
    "gn:population":0,
    "gn:timezone":"Asia/Shanghai",
    "iso:country":"CN",
    "name:zho_x_preferred":[
        "\u4e0b\u7532\u672c"
    ],
    "wof:name":"Xiajiaben",
    "wof:placetype":"locality"
},
  "geometry": {"coordinates":[107.176,25.8796],"type":"Point"}
}