{
  "type": "Feature",
  "properties": {
    "gn:admin1_code":"29.0",
    "gn:asciiname":"Manganzhai",
    "gn:country_code":"CN",
    "gn:dem":1511,
    "gn:feature_class":"P",
    "gn:feature_code":"PPL",
    "gn:name":"Manganzhai",
    "gn:population":0,
    "gn:timezone":"Asia/Shanghai",
    "iso:country":"CN",
    "name:zho_x_preferred":[
        "\u66fc\u5e72\u5be8"
    ],
    "wof:name":"Manganzhai",
    "wof:placetype":"locality"
},
  "geometry": {"coordinates":[101.458,22.8801],"type":"Point"}
}