{
  "type": "Feature",
  "properties": {
    "gn:admin1_code":"24.0",
    "gn:asciiname":"Chaigeta",
    "gn:country_code":"CN",
    "gn:dem":1415,
    "gn:feature_class":"P",
    "gn:feature_code":"PPL",
    "gn:name":"Chaigeta",
    "gn:population":0,
    "gn:timezone":"Asia/Shanghai",
    "iso:country":"CN",
    "name:zho_x_preferred":[
        "\u67f4\u572a\u5854"
    ],
    "wof:name":"Chaigeta",
    "wof:placetype":"locality"
},
  "geometry": {"coordinates":[111.33716,36.98611],"type":"Point"}
}