{
  "type": "Feature",
  "properties": {
    "gn:admin1_code":"18.0",
    "gn:asciiname":"Shangqinluo",
    "gn:country_code":"CN",
    "gn:dem":798,
    "gn:feature_class":"P",
    "gn:feature_code":"PPL",
    "gn:name":"Shangqinluo",
    "gn:population":0,
    "gn:timezone":"Asia/Shanghai",
    "iso:country":"CN",
    "name:zho_x_preferred":[
        "\u4e0a\u79e6\u7f57"
    ],
    "wof:name":"Shangqinluo",
    "wof:placetype":"locality"
},
  "geometry": {"coordinates":[109.02800000000001,26.3488],"type":"Point"}
}