{
  "type": "Feature",
  "properties": {
    "gn:admin1_code":"3.0",
    "gn:asciiname":"Yinkeng",
    "gn:country_code":"CN",
    "gn:dem":177,
    "gn:feature_class":"P",
    "gn:feature_code":"PPL",
    "gn:name":"Yinkeng",
    "gn:population":0,
    "gn:timezone":"Asia/Shanghai",
    "iso:country":"CN",
    "name:und_x_variant":[
        "\u9634\u5751"
    ],
    "wof:name":"Yinkeng",
    "wof:placetype":"locality"
},
  "geometry": {"coordinates":[115.36403,26.1578],"type":"Point"}
}