{
  "type": "Feature",
  "properties": {
    "gn:admin1_code":"7.0",
    "gn:asciiname":"Pingsha",
    "gn:country_code":"CN",
    "gn:dem":389,
    "gn:feature_class":"P",
    "gn:feature_code":"PPL",
    "gn:name":"Pingsha",
    "gn:population":0,
    "gn:timezone":"Asia/Shanghai",
    "iso:country":"CN",
    "name:zho_x_preferred":[
        "Pingsha"
    ],
    "name:zho_x_variant":[
        "\u5e73\u6c99"
    ],
    "wof:name":"Pingsha",
    "wof:placetype":"locality"
},
  "geometry": {"coordinates":[118.75278,26.67111],"type":"Point"}
}