{
  "type": "Feature",
  "properties": {
    "gn:admin1_code":"16.0",
    "gn:asciiname":"Honglai",
    "gn:country_code":"CN",
    "gn:dem":383,
    "gn:feature_class":"P",
    "gn:feature_code":"PPL",
    "gn:name":"Honglai",
    "gn:population":0,
    "gn:timezone":"Asia/Shanghai",
    "iso:country":"CN",
    "name:zho_x_preferred":[
        "\u7ea2\u6765"
    ],
    "wof:name":"Honglai",
    "wof:placetype":"locality"
},
  "geometry": {"coordinates":[107.72799999999999,24.7181],"type":"Point"}
}