{
  "type": "Feature",
  "properties": {
    "gn:admin1_code":"08",
    "gn:asciiname":"Wangjiang",
    "gn:country_code":"CN",
    "gn:dem":82,
    "gn:feature_class":"P",
    "gn:feature_code":"PPLA4",
    "gn:name":"Wangjiang",
    "gn:population":0,
    "gn:timezone":"Asia/Shanghai",
    "iso:country":"CN",
    "name:und_x_variant":[
        "Wangjiang Zhen"
    ],
    "name:zho_x_preferred":[
        "\u671b\u6c5f"
    ],
    "name:zho_x_variant":[
        "\u671b\u6c5f\u9547"
    ],
    "wof:name":"Wangjiang",
    "wof:placetype":"locality"
},
  "geometry": {"coordinates":[130.16071000000002,46.85436],"type":"Point"}
}