{
  "type": "Feature",
  "properties": {
    "gn:admin1_code":"10.0",
    "gn:asciiname":"Liuwuying",
    "gn:country_code":"CN",
    "gn:dem":17,
    "gn:feature_class":"P",
    "gn:feature_code":"PPL",
    "gn:name":"Liuwuying",
    "gn:population":0,
    "gn:timezone":"Asia/Shanghai",
    "iso:country":"CN",
    "name:zho_x_preferred":[
        "\u5218\u6b66\u8425"
    ],
    "wof:name":"Liuwuying",
    "wof:placetype":"locality"
},
  "geometry": {"coordinates":[116.63670999999999,39.32081],"type":"Point"}
}