{
  "type": "Feature",
  "properties": {
    "gn:admin1_code":"16.0",
    "gn:asciiname":"Changji",
    "gn:country_code":"CN",
    "gn:dem":56,
    "gn:feature_class":"P",
    "gn:feature_code":"PPL",
    "gn:name":"Changji",
    "gn:population":0,
    "gn:timezone":"Asia/Shanghai",
    "iso:country":"CN",
    "name:ara_x_preferred":[
        "\u062a\u0634\u0627\u0646\u063a\u062c\u0649"
    ],
    "name:deu_x_preferred":[
        "Changji"
    ],
    "name:ell_x_preferred":[
        "\u03a4\u03c3\u03b1\u03bd\u03b3\u03ba\u03c4\u03b6\u03af"
    ],
    "name:fas_x_preferred":[
        "\u0686\u0627\u0646\u06af\u200c\u062c\u06cc"
    ],
    "name:fin_x_preferred":[
        "Changji"
    ],
    "name:fra_x_preferred":[
        "Changji"
    ],
    "name:ind_x_preferred":[
        "Changji"
    ],
    "name:ita_x_preferred":[
        "Changji"
    ],
    "name:jpn_x_preferred":[
        "\u660c\u5409\u5e02"
    ],
    "name:kik_x_preferred":[
        "Changji"
    ],
    "name:kor_x_preferred":[
        "\ucc3d\uc9c0\uc2dc"
    ],
    "name:lit_x_preferred":[
        "\u010cangdzi"
    ],
    "name:mlg_x_preferred":[
        "Changji"
    ],
    "name:nor_x_preferred":[
        "Changji"
    ],
    "name:pol_x_preferred":[
        "Changji"
    ],
    "name:por_x_preferred":[
        "Changji"
    ],
    "name:rus_x_preferred":[
        "\u0427\u0430\u043d\u0446\u0437\u0438"
    ],
    "name:spa_x_preferred":[
        "Changji"
    ],
    "name:swe_x_preferred":[
        "Changji"
    ],
    "name:tur_x_preferred":[
        "Sanci"
    ],
    "name:uig_x_preferred":[
        "\u0633\u0627\u0646\u062c\u0649 \u0634\u06d5\u06be\u0649\u0631\u0649"
    ],
    "name:urd_x_preferred":[
        "\u0686\u0627\u0646\u06af\u062c\u06cc"
    ],
    "name:vie_x_preferred":[
        "X\u01b0\u01a1ng C\u00e1t"
    ],
    "name:war_x_preferred":[
        "Changji"
    ],
    "name:zho_x_preferred":[
        "\u957f\u57fa"
    ],
    "name:zho_x_variant":[
        "\u660c\u5409\u5e02"
    ],
    "wof:name":"Changji",
    "wof:placetype":"locality"
},
  "geometry": {"coordinates":[108.95699999999999,22.4199],"type":"Point"}
}