{
  "type": "Feature",
  "properties": {
    "gn:admin1_code":"32.0",
    "gn:asciiname":"Gangda",
    "gn:country_code":"CN",
    "gn:dem":2415,
    "gn:feature_class":"P",
    "gn:feature_code":"PPL",
    "gn:name":"Gangda",
    "gn:population":0,
    "gn:timezone":"Asia/Urumqi",
    "iso:country":"CN",
    "name:zho_x_preferred":[
        "\u5c97\u8fbe"
    ],
    "wof:name":"Gangda",
    "wof:placetype":"locality"
},
  "geometry": {"coordinates":[99.0504,29.491],"type":"Point"}
}