{
  "type": "Feature",
  "properties": {
    "gn:admin1_code":"32.0",
    "gn:asciiname":"Ese'erma",
    "gn:country_code":"CN",
    "gn:dem":3341,
    "gn:feature_class":"P",
    "gn:feature_code":"PPL",
    "gn:name":"Ese\u2019erma",
    "gn:population":0,
    "gn:timezone":"Asia/Shanghai",
    "iso:country":"CN",
    "name:zho_x_preferred":[
        "\u989d\u8272\u5c14\u739b"
    ],
    "name:zho_x_variant":[
        "Ese\u2019erma"
    ],
    "wof:name":"Ese'erma",
    "wof:placetype":"locality"
},
  "geometry": {"coordinates":[102.09809,32.6449],"type":"Point"}
}