{
  "type": "Feature",
  "properties": {
    "gn:admin1_code":"29.0",
    "gn:asciiname":"Cijiao",
    "gn:country_code":"CN",
    "gn:dem":2602,
    "gn:feature_class":"P",
    "gn:feature_code":"PPL",
    "gn:name":"Cijiao",
    "gn:population":0,
    "gn:timezone":"Asia/Shanghai",
    "iso:country":"CN",
    "name:zho_x_preferred":[
        "\u523a\u89d2"
    ],
    "wof:name":"Cijiao",
    "wof:placetype":"locality"
},
  "geometry": {"coordinates":[99.38590000000001,26.9316],"type":"Point"}
}