{
  "type": "Feature",
  "properties": {
    "gn:admin1_code":"10",
    "gn:asciiname":"Longyao",
    "gn:cc2":"CN",
    "gn:country_code":"CN",
    "gn:dem":38,
    "gn:feature_class":"P",
    "gn:feature_code":"PPL",
    "gn:name":"Longyao",
    "gn:population":0,
    "gn:timezone":"Asia/Shanghai",
    "iso:country":"CN",
    "name:und_x_variant":[
        "Lung-p\u2019ing",
        "Lunpin",
        "Lung-yao-ch\u2019eng-kuan",
        "Lung-p\u2019ing-hsien",
        "Lung-yao",
        "Longyao"
    ],
    "wof:name":"Longyao",
    "wof:placetype":"locality"
},
  "geometry": {"coordinates":[114.77249999999999,37.35194],"type":"Point"}
}