{
  "type": "Feature",
  "properties": {
    "gn:admin1_code":"32.0",
    "gn:asciiname":"Tuzhumiao",
    "gn:country_code":"CN",
    "gn:dem":1021,
    "gn:feature_class":"P",
    "gn:feature_code":"PPL",
    "gn:name":"Tuzhumiao",
    "gn:population":0,
    "gn:timezone":"Asia/Shanghai",
    "iso:country":"CN",
    "name:zho_x_preferred":[
        "\u571f\u4e3b\u5e99"
    ],
    "wof:name":"Tuzhumiao",
    "wof:placetype":"locality"
},
  "geometry": {"coordinates":[102.62862,29.77761],"type":"Point"}
}