{
  "type": "Feature",
  "properties": {
    "gn:admin1_code":"30.0",
    "gn:asciiname":"Madao",
    "gn:country_code":"CN",
    "gn:dem":134,
    "gn:feature_class":"P",
    "gn:feature_code":"PPL",
    "gn:name":"Madao",
    "gn:population":0,
    "gn:timezone":"Asia/Shanghai",
    "iso:country":"CN",
    "name:und_x_variant":[
        "\u9a6c\u9053"
    ],
    "name:zho_x_preferred":[
        "\u9a6c\u9053"
    ],
    "wof:name":"Madao",
    "wof:placetype":"locality"
},
  "geometry": {"coordinates":[114.80691000000002,23.3672],"type":"Point"}
}