{
  "type": "Feature",
  "properties": {
    "gn:admin1_code":"01",
    "gn:asciiname":"Tongchengmiao",
    "gn:country_code":"CN",
    "gn:dem":13,
    "gn:feature_class":"P",
    "gn:feature_code":"PPL",
    "gn:name":"Tongchengmiao",
    "gn:population":0,
    "gn:timezone":"Asia/Shanghai",
    "iso:country":"CN",
    "name:und_x_variant":[
        "T\u2019ung-ch\u2019eng-chen",
        "T\u2019ung-ch\u2019eng-miao-chen",
        "Tongchengzhen",
        "Tongmiao",
        "Tongchengmiao"
    ],
    "name:zho_x_preferred":[
        "\u94dc\u57ce\u5e99"
    ],
    "wof:name":"Tongchengmiao",
    "wof:placetype":"locality"
},
  "geometry": {"coordinates":[118.09666,31.52081],"type":"Point"}
}