{
  "type": "Feature",
  "properties": {
    "gn:admin1_code":"11.0",
    "gn:asciiname":"Banqiaoyu",
    "gn:country_code":"CN",
    "gn:dem":513,
    "gn:feature_class":"P",
    "gn:feature_code":"PPL",
    "gn:name":"Banqiaoyu",
    "gn:population":0,
    "gn:timezone":"Asia/Shanghai",
    "iso:country":"CN",
    "name:zho_x_preferred":[
        "\u677f\u6865\u5cea"
    ],
    "wof:name":"Banqiaoyu",
    "wof:placetype":"locality"
},
  "geometry": {"coordinates":[110.68984,29.33643],"type":"Point"}
}