{
  "type": "Feature",
  "properties": {
    "gn:admin1_code":"24.0",
    "gn:asciiname":"Niunita",
    "gn:country_code":"CN",
    "gn:dem":1243,
    "gn:feature_class":"P",
    "gn:feature_code":"PPL",
    "gn:name":"Niunita",
    "gn:population":0,
    "gn:timezone":"Asia/Shanghai",
    "iso:country":"CN",
    "name:zho_x_preferred":[
        "\u725b\u6ce5\u5854"
    ],
    "wof:name":"Niunita",
    "wof:placetype":"locality"
},
  "geometry": {"coordinates":[111.59956,39.4663],"type":"Point"}
}