{
  "type": "Feature",
  "properties": {
    "gn:admin1_code":"15.0",
    "gn:asciiname":"Tongmushan",
    "gn:country_code":"CN",
    "gn:dem":1851,
    "gn:feature_class":"P",
    "gn:feature_code":"PPL",
    "gn:name":"Tongmushan",
    "gn:population":0,
    "gn:timezone":"Asia/Shanghai",
    "iso:country":"CN",
    "name:zho_x_preferred":[
        "\u901a\u6728\u5c71"
    ],
    "wof:name":"Tongmushan",
    "wof:placetype":"locality"
},
  "geometry": {"coordinates":[104.98285,33.10092],"type":"Point"}
}