{
  "type": "Feature",
  "properties": {
    "gn:admin1_code":"3.0",
    "gn:asciiname":"Tongluoping",
    "gn:country_code":"CN",
    "gn:dem":174,
    "gn:feature_class":"P",
    "gn:feature_code":"PPL",
    "gn:name":"Tongluoping",
    "gn:population":0,
    "gn:timezone":"Asia/Shanghai",
    "iso:country":"CN",
    "name:zho_x_preferred":[
        "\u94dc\u9523\u576a"
    ],
    "wof:name":"Tongluoping",
    "wof:placetype":"locality"
},
  "geometry": {"coordinates":[115.40000000000001,26.3318],"type":"Point"}
}