{
  "type": "Feature",
  "properties": {
    "gn:admin1_code":"14.0",
    "gn:asciiname":"Jiarecun",
    "gn:country_code":"CN",
    "gn:dem":3699,
    "gn:feature_class":"P",
    "gn:feature_code":"PPL",
    "gn:name":"Jiarecun",
    "gn:population":0,
    "gn:timezone":"Asia/Urumqi",
    "iso:country":"CN",
    "name:zho_x_preferred":[
        "\u8d3e\u70ed\u6751"
    ],
    "wof:name":"Jiarecun",
    "wof:placetype":"locality"
},
  "geometry": {"coordinates":[90.93113,29.6538],"type":"Point"}
}