{
  "type": "Feature",
  "properties": {
    "gn:admin1_code":"14.0",
    "gn:asciiname":"Laricun",
    "gn:country_code":"CN",
    "gn:dem":3780,
    "gn:feature_class":"P",
    "gn:feature_code":"PPL",
    "gn:name":"Laricun",
    "gn:population":0,
    "gn:timezone":"Asia/Urumqi",
    "iso:country":"CN",
    "name:zho_x_preferred":[
        "\u62c9\u65e5\u6751"
    ],
    "wof:name":"Laricun",
    "wof:placetype":"locality"
},
  "geometry": {"coordinates":[96.9579,31.7368],"type":"Point"}
}