{
  "type": "Feature",
  "properties": {
    "gn:admin1_code":"29.0",
    "gn:asciiname":"Dagunpo",
    "gn:country_code":"CN",
    "gn:dem":715,
    "gn:feature_class":"P",
    "gn:feature_code":"PPL",
    "gn:name":"Dagunpo",
    "gn:population":0,
    "gn:timezone":"Asia/Shanghai",
    "iso:country":"CN",
    "name:zho_x_preferred":[
        "\u6253\u6eda\u5761"
    ],
    "wof:name":"Dagunpo",
    "wof:placetype":"locality"
},
  "geometry": {"coordinates":[104.23099999999999,28.1482],"type":"Point"}
}