{
  "type": "Feature",
  "properties": {
    "gn:admin1_code":"19.0",
    "gn:asciiname":"Nanhaitou",
    "gn:country_code":"CN",
    "gn:dem":4,
    "gn:feature_class":"P",
    "gn:feature_code":"PPL",
    "gn:name":"Nanhaitou",
    "gn:population":0,
    "gn:timezone":"Asia/Shanghai",
    "iso:country":"CN",
    "name:und_x_variant":[
        "\u5357\u6d77\u5934"
    ],
    "name:zho_x_preferred":[
        "\u5357\u6d77\u5934"
    ],
    "wof:name":"Nanhaitou",
    "wof:placetype":"locality"
},
  "geometry": {"coordinates":[121.39473999999998,39.36418],"type":"Point"}
}