{
  "type": "Feature",
  "properties": {
    "gn:admin1_code":"26.0",
    "gn:asciiname":"Laodian",
    "gn:country_code":"CN",
    "gn:dem":1789,
    "gn:feature_class":"P",
    "gn:feature_code":"PPL",
    "gn:name":"Laodian",
    "gn:population":0,
    "gn:timezone":"Asia/Shanghai",
    "iso:country":"CN",
    "name:und_x_variant":[
        "\u8001\u5e97"
    ],
    "wof:name":"Laodian",
    "wof:placetype":"locality"
},
  "geometry": {"coordinates":[107.14138,34.10661],"type":"Point"}
}