{
  "type": "Feature",
  "properties": {
    "gn:admin1_code":"32.0",
    "gn:asciiname":"Liangjia Yankou",
    "gn:country_code":"CN",
    "gn:dem":728,
    "gn:feature_class":"P",
    "gn:feature_code":"PPL",
    "gn:name":"Liangjia Yankou",
    "gn:population":0,
    "gn:timezone":"Asia/Shanghai",
    "iso:country":"CN",
    "name:zho_x_preferred":[
        "\u6881\u5bb6\u5ca9\u53e3"
    ],
    "wof:name":"Liangjia Yankou",
    "wof:placetype":"locality"
},
  "geometry": {"coordinates":[107.67126,30.88014],"type":"Point"}
}