{
  "type": "Feature",
  "properties": {
    "gn:admin1_code":"19.0",
    "gn:asciiname":"Wengquandongtun",
    "gn:country_code":"CN",
    "gn:dem":94,
    "gn:feature_class":"P",
    "gn:feature_code":"PPL",
    "gn:name":"Wengquandongtun",
    "gn:population":0,
    "gn:timezone":"Asia/Shanghai",
    "iso:country":"CN",
    "name:zho_x_preferred":[
        "\u74ee\u6cc9\u4e1c\u5c6f"
    ],
    "wof:name":"Wengquandongtun",
    "wof:placetype":"locality"
},
  "geometry": {"coordinates":[120.006,40.2975],"type":"Point"}
}