{
  "type": "Feature",
  "properties": {
    "gn:admin1_code":"11",
    "gn:asciiname":"Caoxieping",
    "gn:country_code":"CN",
    "gn:dem":796,
    "gn:feature_class":"P",
    "gn:feature_code":"PPL",
    "gn:name":"Caoxieping",
    "gn:population":0,
    "gn:timezone":"Asia/Shanghai",
    "iso:country":"CN",
    "name:zho_x_preferred":[
        "\u8349\u978b\u576a"
    ],
    "wof:name":"Caoxieping",
    "wof:placetype":"locality"
},
  "geometry": {"coordinates":[112.19368,25.19835],"type":"Point"}
}