{
  "type": "Feature",
  "properties": {
    "gn:admin1_code":"13",
    "gn:asciiname":"Bulusi Taichahan",
    "gn:country_code":"CN",
    "gn:dem":2607,
    "gn:feature_class":"P",
    "gn:feature_code":"PPL",
    "gn:name":"Bulusi Taichahan",
    "gn:population":0,
    "gn:timezone":"Asia/Urumqi",
    "iso:country":"CN",
    "name:und_x_variant":[
        "\u5e03\u9c81\u65af\u53f0\u67e5\u6c57"
    ],
    "wof:name":"Bulusi Taichahan",
    "wof:placetype":"locality"
},
  "geometry": {"coordinates":[86.54748000000002,42.96301],"type":"Point"}
}