{
  "type": "Feature",
  "properties": {
    "gn:admin1_code":"30",
    "gn:asciiname":"Dayuan",
    "gn:country_code":"CN",
    "gn:dem":43,
    "gn:feature_class":"P",
    "gn:feature_code":"PPL",
    "gn:name":"Dayuan",
    "gn:population":0,
    "gn:timezone":"Asia/Urumqi",
    "iso:country":"CN",
    "name:zho_x_preferred":[
        "\u5927\u56ed"
    ],
    "wof:name":"Dayuan",
    "wof:placetype":"locality"
},
  "geometry": {"coordinates":[111.17622,21.79981],"type":"Point"}
}