{
  "type": "Feature",
  "properties": {
    "gn:admin1_code":"03",
    "gn:asciiname":"Lusi",
    "gn:country_code":"CN",
    "gn:dem":47,
    "gn:feature_class":"P",
    "gn:feature_code":"PPLA4",
    "gn:name":"Lusi",
    "gn:population":0,
    "gn:timezone":"Asia/Shanghai",
    "iso:country":"CN",
    "name:ceb_x_preferred":[
        "Lusi"
    ],
    "name:deu_x_preferred":[
        "Lusi"
    ],
    "name:fra_x_preferred":[
        "Lusi"
    ],
    "name:ita_x_preferred":[
        "Lusi"
    ],
    "name:swe_x_preferred":[
        "Lusi"
    ],
    "name:und_x_variant":[
        "Lusibu",
        "\u9e2c\u9e5a",
        "Lusi Xiang",
        "\u9e2c\u9e5a\u57e0",
        "\u9e2c\u9e5a\u4e61"
    ],
    "wof:name":"Lusi",
    "wof:placetype":"locality"
},
  "geometry": {"coordinates":[117.30338,28.89874],"type":"Point"}
}