{
  "type": "Feature",
  "properties": {
    "gn:admin1_code":"10",
    "gn:asciiname":"Bashisanhao",
    "gn:country_code":"CN",
    "gn:dem":1212,
    "gn:feature_class":"P",
    "gn:feature_code":"PPLF",
    "gn:name":"Bashisanhao",
    "gn:population":0,
    "gn:timezone":"Asia/Shanghai",
    "iso:country":"CN",
    "name:und_x_variant":[
        "Pa-shih-san-hao"
    ],
    "name:zho_x_preferred":[
        "\u516b\u5341\u4e09\u53f7"
    ],
    "wof:name":"Bashisanhao",
    "wof:placetype":"locality"
},
  "geometry": {"coordinates":[117.49597,42.24394],"type":"Point"}
}