{
  "type": "Feature",
  "properties": {
    "gn:admin1_code":"15.0",
    "gn:asciiname":"Songshuba",
    "gn:country_code":"CN",
    "gn:dem":1327,
    "gn:feature_class":"P",
    "gn:feature_code":"PPL",
    "gn:name":"Songshuba",
    "gn:population":0,
    "gn:timezone":"Asia/Shanghai",
    "iso:country":"CN",
    "name:und_x_variant":[
        "\u677e\u6811\u575d"
    ],
    "wof:name":"Songshuba",
    "wof:placetype":"locality"
},
  "geometry": {"coordinates":[105.40031,33.08874],"type":"Point"}
}