{
  "type": "Feature",
  "properties": {
    "gn:admin1_code":"32.0",
    "gn:asciiname":"Dadugou",
    "gn:country_code":"CN",
    "gn:dem":439,
    "gn:feature_class":"P",
    "gn:feature_code":"PPL",
    "gn:name":"Dadugou",
    "gn:population":0,
    "gn:timezone":"Asia/Shanghai",
    "iso:country":"CN",
    "name:zho_x_preferred":[
        "\u5927\u675c\u6c9f"
    ],
    "wof:name":"Dadugou",
    "wof:placetype":"locality"
},
  "geometry": {"coordinates":[103.741,29.7994],"type":"Point"}
}