{
  "type": "Feature",
  "properties": {
    "gn:admin1_code":"3.0",
    "gn:asciiname":"Gaoshanjiao",
    "gn:country_code":"CN",
    "gn:dem":280,
    "gn:feature_class":"P",
    "gn:feature_code":"PPL",
    "gn:name":"Gaoshanjiao",
    "gn:population":0,
    "gn:timezone":"Asia/Shanghai",
    "iso:country":"CN",
    "name:und_x_variant":[
        "\u9ad8\u5c71\u89d2"
    ],
    "wof:name":"Gaoshanjiao",
    "wof:placetype":"locality"
},
  "geometry": {"coordinates":[115.68035,26.21523],"type":"Point"}
}