{
  "type": "Feature",
  "properties": {
    "gn:admin1_code":"32.0",
    "gn:asciiname":"Yuying",
    "gn:country_code":"CN",
    "gn:dem":513,
    "gn:feature_class":"P",
    "gn:feature_code":"PPL",
    "gn:name":"Yuying",
    "gn:population":0,
    "gn:timezone":"Asia/Shanghai",
    "iso:country":"CN",
    "name:zho_x_preferred":[
        "\u5fa1\u8425"
    ],
    "wof:name":"Yuying",
    "wof:placetype":"locality"
},
  "geometry": {"coordinates":[104.55656999999999,31.32072],"type":"Point"}
}