{
  "type": "Feature",
  "properties": {
    "gn:admin1_code":"3.0",
    "gn:asciiname":"Dujiang",
    "gn:country_code":"CN",
    "gn:dem":88,
    "gn:feature_class":"P",
    "gn:feature_code":"PPL",
    "gn:name":"Dujiang",
    "gn:population":0,
    "gn:timezone":"Asia/Shanghai",
    "iso:country":"CN",
    "name:und_x_variant":[
        "\u6e21\u6c5f"
    ],
    "wof:name":"Dujiang",
    "wof:placetype":"locality"
},
  "geometry": {"coordinates":[116.57896,29.6542],"type":"Point"}
}