{
  "type": "Feature",
  "properties": {
    "gn:admin1_code":"32.0",
    "gn:asciiname":"Guandaoyan",
    "gn:country_code":"CN",
    "gn:dem":376,
    "gn:feature_class":"P",
    "gn:feature_code":"PPL",
    "gn:name":"Guandaoyan",
    "gn:population":0,
    "gn:timezone":"Asia/Shanghai",
    "iso:country":"CN",
    "name:zho_x_preferred":[
        "\u5173\u5200\u5ca9"
    ],
    "wof:name":"Guandaoyan",
    "wof:placetype":"locality"
},
  "geometry": {"coordinates":[104.09206,28.99532],"type":"Point"}
}