{
  "type": "Feature",
  "properties": {
    "gn:admin1_code":"02",
    "gn:asciiname":"Hebaotian",
    "gn:country_code":"CN",
    "gn:dem":120,
    "gn:feature_class":"P",
    "gn:feature_code":"PPL",
    "gn:name":"Hebaotian",
    "gn:population":0,
    "gn:timezone":"Asia/Shanghai",
    "iso:country":"CN",
    "name:zho_x_preferred":[
        "\u8377\u5305\u7530"
    ],
    "wof:name":"Hebaotian",
    "wof:placetype":"locality"
},
  "geometry": {"coordinates":[120.52903000000001,27.24052],"type":"Point"}
}