{
  "type": "Feature",
  "properties": {
    "gn:admin1_code":"30.0",
    "gn:asciiname":"Duohetan",
    "gn:country_code":"CN",
    "gn:dem":221,
    "gn:feature_class":"P",
    "gn:feature_code":"PPL",
    "gn:name":"Duohetan",
    "gn:population":0,
    "gn:timezone":"Asia/Shanghai",
    "iso:country":"CN",
    "name:und_x_variant":[
        "\u591a\u79be\u6ee9"
    ],
    "name:zho_x_preferred":[
        "\u591a\u79be\u6ee9"
    ],
    "wof:name":"Duohetan",
    "wof:placetype":"locality"
},
  "geometry": {"coordinates":[115.36485999999999,23.41021],"type":"Point"}
}