{
  "type": "Feature",
  "properties": {
    "gn:admin1_code":"25.0",
    "gn:asciiname":"Zongtangcun",
    "gn:country_code":"CN",
    "gn:dem":36,
    "gn:feature_class":"P",
    "gn:feature_code":"PPL",
    "gn:name":"Zongtangcun",
    "gn:population":0,
    "gn:timezone":"Asia/Shanghai",
    "iso:country":"CN",
    "name:zho_x_preferred":[
        "\u5b97\u5802\u6751"
    ],
    "wof:name":"Zongtangcun",
    "wof:placetype":"locality"
},
  "geometry": {"coordinates":[115.75603999999998,36.5928],"type":"Point"}
}