{
  "type": "Feature",
  "properties": {
    "gn:admin1_code":"16.0",
    "gn:asciiname":"Baduo",
    "gn:country_code":"CN",
    "gn:dem":545,
    "gn:feature_class":"P",
    "gn:feature_code":"PPL",
    "gn:name":"Baduo",
    "gn:population":0,
    "gn:timezone":"Asia/Shanghai",
    "iso:country":"CN",
    "name:zho_x_preferred":[
        "\u5c9c\u6735"
    ],
    "wof:name":"Baduo",
    "wof:placetype":"locality"
},
  "geometry": {"coordinates":[108.94199999999999,25.5165],"type":"Point"}
}