{
  "type": "Feature",
  "properties": {
    "gn:admin1_code":"30.0",
    "gn:asciiname":"Luosha",
    "gn:country_code":"CN",
    "gn:dem":65,
    "gn:feature_class":"P",
    "gn:feature_code":"PPL",
    "gn:name":"Luosha",
    "gn:population":0,
    "gn:timezone":"Asia/Shanghai",
    "iso:country":"CN",
    "name:zho_x_preferred":[
        "\u7f57\u6c99"
    ],
    "wof:name":"Luosha",
    "wof:placetype":"locality"
},
  "geometry": {"coordinates":[112.06798999999999,22.94952],"type":"Point"}
}