{
  "type": "Feature",
  "properties": {
    "gn:admin1_code":"12.0",
    "gn:asciiname":"Zhangjiagang",
    "gn:country_code":"CN",
    "gn:dem":35,
    "gn:feature_class":"P",
    "gn:feature_code":"PPL",
    "gn:name":"Zhangjiagang",
    "gn:population":0,
    "gn:timezone":"Asia/Shanghai",
    "iso:country":"CN",
    "name:zho_x_preferred":[
        "Zhangjiagang"
    ],
    "name:zho_x_variant":[
        "\u5f20\u5bb6\u5c97"
    ],
    "wof:name":"Zhangjiagang",
    "wof:placetype":"locality"
},
  "geometry": {"coordinates":[111.93608,30.01221],"type":"Point"}
}