{
  "type": "Feature",
  "properties": {
    "gn:admin1_code":"14.0",
    "gn:asciiname":"Qabka",
    "gn:country_code":"CN",
    "gn:dem":3909,
    "gn:feature_class":"P",
    "gn:feature_code":"PPLF",
    "gn:name":"Qabka",
    "gn:population":0,
    "gn:timezone":"Asia/Urumqi",
    "iso:country":"CN",
    "name:bod_x_preferred":[
        "Qabka"
    ],
    "name:zho_x_preferred":[
        "Qiaga"
    ],
    "name:zho_x_variant":[
        "\u6070\u560e"
    ],
    "wof:name":"Qabka",
    "wof:placetype":"locality"
},
  "geometry": {"coordinates":[88.20299999999997,29.403],"type":"Point"}
}