{
  "type": "Feature",
  "properties": {
    "gn:admin1_code":"8.0",
    "gn:asciiname":"Laoniuquan",
    "gn:country_code":"CN",
    "gn:dem":81,
    "gn:feature_class":"P",
    "gn:feature_code":"PPL",
    "gn:name":"Laoniuquan",
    "gn:population":0,
    "gn:timezone":"Asia/Shanghai",
    "iso:country":"CN",
    "name:zho_x_preferred":[
        "\u8001\u725b\u5708"
    ],
    "wof:name":"Laoniuquan",
    "wof:placetype":"locality"
},
  "geometry": {"coordinates":[132.55893999999998,45.40298],"type":"Point"}
}