{
  "type": "Feature",
  "properties": {
    "gn:admin1_code":"19.0",
    "gn:asciiname":"Bolizhai",
    "gn:country_code":"CN",
    "gn:dem":35,
    "gn:feature_class":"P",
    "gn:feature_code":"PPL",
    "gn:name":"Bolizhai",
    "gn:population":0,
    "gn:timezone":"Asia/Shanghai",
    "iso:country":"CN",
    "name:zho_x_preferred":[
        "\u62e8\u7acb\u5be8"
    ],
    "wof:name":"Bolizhai",
    "wof:placetype":"locality"
},
  "geometry": {"coordinates":[123.29783,41.33893],"type":"Point"}
}