{
  "type": "Feature",
  "properties": {
    "gn:admin1_code":"19.0",
    "gn:asciiname":"Shanghanjia Buzi",
    "gn:country_code":"CN",
    "gn:dem":376,
    "gn:feature_class":"P",
    "gn:feature_code":"PPL",
    "gn:name":"Shanghanjia Buzi",
    "gn:population":0,
    "gn:timezone":"Asia/Shanghai",
    "iso:country":"CN",
    "name:und_x_variant":[
        "Shanghanjiabaozi",
        "Shanghanjia Buzi"
    ],
    "name:zho_x_preferred":[
        "\u4e0a\u97e9\u5bb6\u5821\u5b50"
    ],
    "wof:name":"Shanghanjia Buzi",
    "wof:placetype":"locality"
},
  "geometry": {"coordinates":[123.56176000000001,40.90076],"type":"Point"}
}