{
  "type": "Feature",
  "properties": {
    "gn:admin1_code":"15.0",
    "gn:asciiname":"Daliaopo",
    "gn:country_code":"CN",
    "gn:dem":2086,
    "gn:feature_class":"P",
    "gn:feature_code":"PPL",
    "gn:name":"Daliaopo",
    "gn:population":0,
    "gn:timezone":"Asia/Shanghai",
    "iso:country":"CN",
    "name:zho_x_preferred":[
        "\u5927\u8fbd\u5761"
    ],
    "wof:name":"Daliaopo",
    "wof:placetype":"locality"
},
  "geometry": {"coordinates":[104.59999999999999,35.8252],"type":"Point"}
}