{
  "type": "Feature",
  "properties": {
    "gn:admin1_code":"29.0",
    "gn:asciiname":"Daguan",
    "gn:country_code":"CN",
    "gn:dem":1530,
    "gn:feature_class":"P",
    "gn:feature_code":"PPL",
    "gn:name":"Daguan",
    "gn:population":0,
    "gn:timezone":"Asia/Shanghai",
    "iso:country":"CN",
    "name:ceb_x_preferred":[
        "Daguan"
    ],
    "name:deu_x_preferred":[
        "Daguan"
    ],
    "name:fra_x_preferred":[
        "Daguan"
    ],
    "name:nor_x_preferred":[
        "Daguan"
    ],
    "name:rus_x_preferred":[
        "\u0414\u0430\u0433\u0443\u0430\u043d\u044c"
    ],
    "name:swe_x_preferred":[
        "Daguan"
    ],
    "name:zho_x_preferred":[
        "\u5927\u5173"
    ],
    "wof:name":"Daguan",
    "wof:placetype":"locality"
},
  "geometry": {"coordinates":[102.765,23.7033],"type":"Point"}
}