{
  "type": "Feature",
  "properties": {
    "gn:admin1_code":"4.0",
    "gn:asciiname":"Yanglianyuan",
    "gn:country_code":"CN",
    "gn:dem":8,
    "gn:feature_class":"P",
    "gn:feature_code":"PPL",
    "gn:name":"Yanglianyuan",
    "gn:population":0,
    "gn:timezone":"Asia/Shanghai",
    "iso:country":"CN",
    "name:zho_x_preferred":[
        "\u6768\u695d\u56ed"
    ],
    "wof:name":"Yanglianyuan",
    "wof:placetype":"locality"
},
  "geometry": {"coordinates":[119.46458,31.89901],"type":"Point"}
}