{
  "type": "Feature",
  "properties": {
    "gn:admin1_code":"09",
    "gn:asciiname":"Guandaokou",
    "gn:cc2":"CN",
    "gn:country_code":"CN",
    "gn:dem":965,
    "gn:feature_class":"P",
    "gn:feature_code":"PPL",
    "gn:name":"Guandaokou",
    "gn:population":0,
    "gn:timezone":"Asia/Shanghai",
    "iso:country":"CN",
    "name:und_x_variant":[
        "Kuan-tao-k\u2019ou",
        "Kwantaokow",
        "Kung-tao-k\u2019ou",
        "Guandaokou"
    ],
    "wof:name":"Guandaokou",
    "wof:placetype":"locality"
},
  "geometry": {"coordinates":[111.04583,34.30806],"type":"Point"}
}