{
  "type": "Feature",
  "properties": {
    "gn:admin1_code":"19.0",
    "gn:asciiname":"Damiaogoumen",
    "gn:country_code":"CN",
    "gn:dem":193,
    "gn:feature_class":"P",
    "gn:feature_code":"PPL",
    "gn:name":"Damiaogoumen",
    "gn:population":0,
    "gn:timezone":"Asia/Shanghai",
    "iso:country":"CN",
    "name:zho_x_preferred":[
        "\u5927\u5e99\u6c9f\u95e8"
    ],
    "wof:name":"Damiaogoumen",
    "wof:placetype":"locality"
},
  "geometry": {"coordinates":[124.111,40.8209],"type":"Point"}
}