{
  "type": "Feature",
  "properties": {
    "gn:admin1_code":"25.0",
    "gn:asciiname":"Xilucun",
    "gn:country_code":"CN",
    "gn:dem":257,
    "gn:feature_class":"P",
    "gn:feature_code":"PPL",
    "gn:name":"Xilucun",
    "gn:population":0,
    "gn:timezone":"Asia/Shanghai",
    "iso:country":"CN",
    "name:zho_x_preferred":[
        "\u897f\u9c81\u6751"
    ],
    "wof:name":"Xilucun",
    "wof:placetype":"locality"
},
  "geometry": {"coordinates":[117.70869999999999,35.75888],"type":"Point"}
}