{
  "type": "Feature",
  "properties": {
    "gn:admin1_code":"24.0",
    "gn:asciiname":"Wanghuazhuang",
    "gn:country_code":"CN",
    "gn:dem":1299,
    "gn:feature_class":"P",
    "gn:feature_code":"PPL",
    "gn:name":"Wanghuazhuang",
    "gn:population":0,
    "gn:timezone":"Asia/Shanghai",
    "iso:country":"CN",
    "name:und_x_variant":[
        "\u738b\u5316\u5e84"
    ],
    "name:zho_x_preferred":[
        "\u738b\u5316\u5e84"
    ],
    "wof:name":"Wanghuazhuang",
    "wof:placetype":"locality"
},
  "geometry": {"coordinates":[112.69324,39.16814],"type":"Point"}
}