{
  "type": "Feature",
  "properties": {
    "gn:admin1_code":"25.0",
    "gn:asciiname":"Dongfangcun",
    "gn:country_code":"CN",
    "gn:dem":80,
    "gn:feature_class":"P",
    "gn:feature_code":"PPL",
    "gn:name":"Dongfangcun",
    "gn:population":0,
    "gn:timezone":"Asia/Shanghai",
    "iso:country":"CN",
    "name:zho_x_preferred":[
        "\u8463\u574a\u6751"
    ],
    "wof:name":"Dongfangcun",
    "wof:placetype":"locality"
},
  "geometry": {"coordinates":[119.27093000000001,36.66019],"type":"Point"}
}