{
  "type": "Feature",
  "properties": {
    "gn:admin1_code":"5.0",
    "gn:asciiname":"Yifakancun",
    "gn:country_code":"CN",
    "gn:dem":222,
    "gn:feature_class":"P",
    "gn:feature_code":"PPL",
    "gn:name":"Yifakancun",
    "gn:population":0,
    "gn:timezone":"Asia/Shanghai",
    "iso:country":"CN",
    "name:zho_x_preferred":[
        "\u4e49\u53d1\u574e\u6751"
    ],
    "wof:name":"Yifakancun",
    "wof:placetype":"locality"
},
  "geometry": {"coordinates":[124.52737,44.30079],"type":"Point"}
}