{
  "type": "Feature",
  "properties": {
    "gn:admin1_code":"06",
    "gn:asciiname":"Reshui",
    "gn:cc2":"CN",
    "gn:country_code":"CN",
    "gn:dem":3688,
    "gn:feature_class":"P",
    "gn:feature_code":"PPL",
    "gn:name":"Reshui",
    "gn:population":0,
    "gn:timezone":"Asia/Shanghai",
    "iso:country":"CN",
    "name:und_x_variant":[
        "Je-shui",
        "Reshui",
        "\u70ed\u6c34"
    ],
    "wof:name":"Reshui",
    "wof:placetype":"locality"
},
  "geometry": {"coordinates":[100.51667,37.48333],"type":"Point"}
}