{
  "type": "Feature",
  "properties": {
    "gn:admin1_code":"32.0",
    "gn:asciiname":"Zhuangfangli",
    "gn:country_code":"CN",
    "gn:dem":890,
    "gn:feature_class":"P",
    "gn:feature_code":"PPL",
    "gn:name":"Zhuangfangli",
    "gn:population":0,
    "gn:timezone":"Asia/Shanghai",
    "iso:country":"CN",
    "name:zho_x_preferred":[
        "\u5e84\u623f\u91cc"
    ],
    "wof:name":"Zhuangfangli",
    "wof:placetype":"locality"
},
  "geometry": {"coordinates":[105.11199999999999,32.1648],"type":"Point"}
}