{
  "type": "Feature",
  "properties": {
    "gn:admin1_code":"7",
    "gn:asciiname":"Tangzainei",
    "gn:country_code":"CN",
    "gn:dem":30,
    "gn:feature_class":"P",
    "gn:feature_code":"PPL",
    "gn:name":"Tangzainei",
    "gn:population":0,
    "gn:timezone":"Asia/Shanghai",
    "iso:country":"CN",
    "name:zho_x_preferred":[
        "\u5858\u4ed4\u5185"
    ],
    "wof:name":"Tangzainei",
    "wof:placetype":"locality"
},
  "geometry": {"coordinates":[117.78668,24.69856],"type":"Point"}
}