{
  "type": "Feature",
  "properties": {
    "gn:admin1_code":"1.0",
    "gn:asciiname":"Zhaotancun",
    "gn:country_code":"CN",
    "gn:dem":33,
    "gn:feature_class":"P",
    "gn:feature_code":"PPL",
    "gn:name":"Zhaotancun",
    "gn:population":0,
    "gn:timezone":"Asia/Shanghai",
    "iso:country":"CN",
    "name:zho_x_preferred":[
        "\u8d75\u6ee9\u6751"
    ],
    "wof:name":"Zhaotancun",
    "wof:placetype":"locality"
},
  "geometry": {"coordinates":[116.88505000000001,33.86517],"type":"Point"}
}