{
  "type": "Feature",
  "properties": {
    "gn:admin1_code":"24.0",
    "gn:asciiname":"Qijiayan",
    "gn:country_code":"CN",
    "gn:dem":1510,
    "gn:feature_class":"P",
    "gn:feature_code":"PPL",
    "gn:name":"Qijiayan",
    "gn:population":0,
    "gn:timezone":"Asia/Shanghai",
    "iso:country":"CN",
    "name:zho_x_preferred":[
        "\u7941\u5bb6\u5ca9"
    ],
    "wof:name":"Qijiayan",
    "wof:placetype":"locality"
},
  "geometry": {"coordinates":[113.19189,37.00257],"type":"Point"}
}