{
  "type": "Feature",
  "properties": {
    "gn:admin1_code":"25.0",
    "gn:asciiname":"Tanzi",
    "gn:country_code":"CN",
    "gn:dem":6,
    "gn:feature_class":"P",
    "gn:feature_code":"PPL",
    "gn:name":"Tanzi",
    "gn:population":0,
    "gn:timezone":"Asia/Shanghai",
    "iso:country":"CN",
    "name:zho_x_preferred":[
        "\u6ee9\u5b50"
    ],
    "wof:name":"Tanzi",
    "wof:placetype":"locality"
},
  "geometry": {"coordinates":[119.45547999999999,36.98868],"type":"Point"}
}