{
  "type": "Feature",
  "properties": {
    "gn:admin1_code":"18",
    "gn:asciiname":"Maocaochong",
    "gn:country_code":"CN",
    "gn:dem":1060,
    "gn:feature_class":"P",
    "gn:feature_code":"PPL",
    "gn:name":"Maocaochong",
    "gn:population":0,
    "gn:timezone":"Asia/Shanghai",
    "iso:country":"CN",
    "name:zho_x_preferred":[
        "\u8305\u8349\u51b2"
    ],
    "wof:name":"Maocaochong",
    "wof:placetype":"locality"
},
  "geometry": {"coordinates":[106.505,26.0581],"type":"Point"}
}