{
  "type": "Feature",
  "properties": {
    "gn:admin1_code":"32.0",
    "gn:asciiname":"Kaobangling",
    "gn:country_code":"CN",
    "gn:dem":1444,
    "gn:feature_class":"P",
    "gn:feature_code":"PPL",
    "gn:name":"Kaobangling",
    "gn:population":0,
    "gn:timezone":"Asia/Shanghai",
    "iso:country":"CN",
    "name:zho_x_preferred":[
        "\u62f7\u6886\u5cad"
    ],
    "wof:name":"Kaobangling",
    "wof:placetype":"locality"
},
  "geometry": {"coordinates":[104.38168,32.00739],"type":"Point"}
}