{
  "type": "Feature",
  "properties": {
    "gn:admin1_code":"10.0",
    "gn:asciiname":"Cuozheqiangma",
    "gn:country_code":"CN",
    "gn:dem":5079,
    "gn:feature_class":"P",
    "gn:feature_code":"PPLA4",
    "gn:name":"Cuozheqiangma",
    "gn:population":0,
    "gn:timezone":"Asia/Urumqi",
    "iso:country":"CN",
    "name:und_x_variant":[
        "\u63aa\u6298\u5f3a\u739b"
    ],
    "wof:name":"Cuozheqiangma",
    "wof:placetype":"locality"
},
  "geometry": {"coordinates":[87.75466999999998,33.30987],"type":"Point"}
}