{
  "type": "Feature",
  "properties": {
    "gn:admin1_code":"18",
    "gn:asciiname":"Huajiaoguan",
    "gn:country_code":"CN",
    "gn:dem":1253,
    "gn:feature_class":"P",
    "gn:feature_code":"PPL",
    "gn:name":"Huajiaoguan",
    "gn:population":0,
    "gn:timezone":"Asia/Shanghai",
    "iso:country":"CN",
    "name:zho_x_preferred":[
        "\u82b1\u4ea4\u5173"
    ],
    "wof:name":"Huajiaoguan",
    "wof:placetype":"locality"
},
  "geometry": {"coordinates":[106.41,26.4156],"type":"Point"}
}