{
  "type": "Feature",
  "properties": {
    "gn:admin1_code":"30",
    "gn:asciiname":"Qincun",
    "gn:country_code":"CN",
    "gn:dem":17,
    "gn:feature_class":"P",
    "gn:feature_code":"PPL",
    "gn:name":"Qincun",
    "gn:population":0,
    "gn:timezone":"Asia/Urumqi",
    "iso:country":"CN",
    "name:zho_x_preferred":[
        "\u8983\u6751"
    ],
    "wof:name":"Qincun",
    "wof:placetype":"locality"
},
  "geometry": {"coordinates":[110.75518999999998,21.56475],"type":"Point"}
}