{
  "type": "Feature",
  "properties": {
    "gn:admin1_code":"13",
    "gn:asciiname":"Mengluke",
    "gn:country_code":"CN",
    "gn:dem":1313,
    "gn:feature_class":"P",
    "gn:feature_code":"PPL",
    "gn:name":"Mengluke",
    "gn:population":0,
    "gn:timezone":"Asia/Shanghai",
    "iso:country":"CN",
    "name:und_x_variant":[
        "\u8499\u9c81\u514b"
    ],
    "wof:name":"Mengluke",
    "wof:placetype":"locality"
},
  "geometry": {"coordinates":[77.206,38.12993],"type":"Point"}
}