{
  "type": "Feature",
  "properties": {
    "gn:admin1_code":"21.0",
    "gn:asciiname":"Haodiwan",
    "gn:country_code":"CN",
    "gn:dem":1993,
    "gn:feature_class":"P",
    "gn:feature_code":"PPL",
    "gn:name":"Haodiwan",
    "gn:population":0,
    "gn:timezone":"Asia/Shanghai",
    "iso:country":"CN",
    "name:zho_x_preferred":[
        "\u84bf\u5730\u6e7e"
    ],
    "wof:name":"Haodiwan",
    "wof:placetype":"locality"
},
  "geometry": {"coordinates":[105.78100000000001,36.0179],"type":"Point"}
}