{
  "type": "Feature",
  "properties": {
    "gn:admin1_code":"7.0",
    "gn:asciiname":"Qitou",
    "gn:country_code":"CN",
    "gn:dem":549,
    "gn:feature_class":"P",
    "gn:feature_code":"PPL",
    "gn:name":"Qitou",
    "gn:population":0,
    "gn:timezone":"Asia/Shanghai",
    "iso:country":"CN",
    "name:zho_x_preferred":[
        "\u78dc\u5934"
    ],
    "wof:name":"Qitou",
    "wof:placetype":"locality"
},
  "geometry": {"coordinates":[117.45578,24.85502],"type":"Point"}
}