{
  "type": "Feature",
  "properties": {
    "gn:admin1_code":"8.0",
    "gn:asciiname":"Sanyibu",
    "gn:country_code":"CN",
    "gn:dem":177,
    "gn:feature_class":"P",
    "gn:feature_code":"PPL",
    "gn:name":"Sanyibu",
    "gn:population":0,
    "gn:timezone":"Asia/Shanghai",
    "iso:country":"CN",
    "name:zho_x_preferred":[
        "\u4e09\u4e49\u5821"
    ],
    "wof:name":"Sanyibu",
    "wof:placetype":"locality"
},
  "geometry": {"coordinates":[125.61778,46.27135],"type":"Point"}
}