{
  "type": "Feature",
  "properties": {
    "gn:admin1_code":"3.0",
    "gn:asciiname":"Hongmuliao",
    "gn:country_code":"CN",
    "gn:dem":570,
    "gn:feature_class":"P",
    "gn:feature_code":"PPL",
    "gn:name":"Hongmuliao",
    "gn:population":0,
    "gn:timezone":"Asia/Shanghai",
    "iso:country":"CN",
    "name:und_x_variant":[
        "\u6d2a\u6728\u5bee"
    ],
    "wof:name":"Hongmuliao",
    "wof:placetype":"locality"
},
  "geometry": {"coordinates":[115.7657,26.86441],"type":"Point"}
}