{
  "type": "Feature",
  "properties": {
    "gn:admin1_code":"24.0",
    "gn:asciiname":"Xiashuangjing",
    "gn:country_code":"CN",
    "gn:dem":1680,
    "gn:feature_class":"P",
    "gn:feature_code":"PPL",
    "gn:name":"Xiashuangjing",
    "gn:population":0,
    "gn:timezone":"Asia/Shanghai",
    "iso:country":"CN",
    "name:und_x_variant":[
        "Hsia-shuang-ching",
        "Xiashuangjing"
    ],
    "name:zho_x_preferred":[
        "\u4e0b\u53cc\u4e95"
    ],
    "wof:name":"Xiashuangjing",
    "wof:placetype":"locality"
},
  "geometry": {"coordinates":[112.10722,38.25726],"type":"Point"}
}