{
  "type": "Feature",
  "properties": {
    "gn:admin1_code":"29",
    "gn:asciiname":"Laobenzhai",
    "gn:country_code":"CN",
    "gn:dem":1308,
    "gn:feature_class":"P",
    "gn:feature_code":"PPL",
    "gn:name":"Laobenzhai",
    "gn:population":0,
    "gn:timezone":"Asia/Shanghai",
    "iso:country":"CN",
    "name:zho_x_preferred":[
        "\u8001\u672c\u5be8"
    ],
    "wof:name":"Laobenzhai",
    "wof:placetype":"locality"
},
  "geometry": {"coordinates":[103.095,24.2807],"type":"Point"}
}