{
  "type": "Feature",
  "properties": {
    "gn:admin1_code":"25.0",
    "gn:asciiname":"Dalianchi",
    "gn:country_code":"CN",
    "gn:dem":55,
    "gn:feature_class":"P",
    "gn:feature_code":"PPL",
    "gn:name":"Dalianchi",
    "gn:population":0,
    "gn:timezone":"Asia/Shanghai",
    "iso:country":"CN",
    "name:zho_x_preferred":[
        "\u5927\u83b2\u6c60"
    ],
    "wof:name":"Dalianchi",
    "wof:placetype":"locality"
},
  "geometry": {"coordinates":[119.36405999999999,36.38228],"type":"Point"}
}