{
  "type": "Feature",
  "properties": {
    "gn:admin1_code":"25.0",
    "gn:asciiname":"Banpocun",
    "gn:country_code":"CN",
    "gn:dem":117,
    "gn:feature_class":"P",
    "gn:feature_code":"PPL",
    "gn:name":"Banpocun",
    "gn:population":0,
    "gn:timezone":"Asia/Shanghai",
    "iso:country":"CN",
    "name:zho_x_preferred":[
        "\u534a\u5761\u6751"
    ],
    "wof:name":"Banpocun",
    "wof:placetype":"locality"
},
  "geometry": {"coordinates":[120.66524,37.05613],"type":"Point"}
}