{
  "type": "Feature",
  "properties": {
    "gn:admin1_code":"19.0",
    "gn:asciiname":"Xiareshui",
    "gn:country_code":"CN",
    "gn:dem":487,
    "gn:feature_class":"P",
    "gn:feature_code":"PPL",
    "gn:name":"Xiareshui",
    "gn:population":0,
    "gn:timezone":"Asia/Shanghai",
    "iso:country":"CN",
    "name:zho_x_preferred":[
        "\u4e0b\u70ed\u6c34"
    ],
    "wof:name":"Xiareshui",
    "wof:placetype":"locality"
},
  "geometry": {"coordinates":[119.29606,42.15909],"type":"Point"}
}