{
  "type": "Feature",
  "properties": {
    "gn:admin1_code":"7.0",
    "gn:asciiname":"Shangqianpu",
    "gn:country_code":"CN",
    "gn:dem":34,
    "gn:feature_class":"P",
    "gn:feature_code":"PPL",
    "gn:name":"Shangqianpu",
    "gn:population":0,
    "gn:timezone":"Asia/Shanghai",
    "iso:country":"CN",
    "name:zho_x_preferred":[
        "\u4e0a\u524d\u57d4"
    ],
    "wof:name":"Shangqianpu",
    "wof:placetype":"locality"
},
  "geometry": {"coordinates":[119.2274,25.24051],"type":"Point"}
}