{
  "type": "Feature",
  "properties": {
    "gn:admin1_code":"19",
    "gn:asciiname":"Zhaoquanhe",
    "gn:country_code":"CN",
    "gn:dem":0,
    "gn:feature_class":"P",
    "gn:feature_code":"PPL",
    "gn:name":"Zhaoquanhe",
    "gn:population":0,
    "gn:timezone":"Asia/Shanghai",
    "iso:country":"CN",
    "wof:name":"Zhaoquanhe",
    "wof:placetype":"locality"
},
  "geometry": {"coordinates":[121.92306000000001,41.02889],"type":"Point"}
}