{
  "type": "Feature",
  "properties": {
    "gn:admin1_code":"24",
    "gn:asciiname":"Jiheng",
    "gn:country_code":"CN",
    "gn:dem":561,
    "gn:feature_class":"P",
    "gn:feature_code":"PPL",
    "gn:name":"Jiheng",
    "gn:population":0,
    "gn:timezone":"Asia/Shanghai",
    "iso:country":"CN",
    "name:und_x_variant":[
        "Chi-heng",
        "Chi-heng-ts\u2019un",
        "Jiheng"
    ],
    "name:zho_x_preferred":[
        "\u5409\u6052"
    ],
    "wof:name":"Jiheng",
    "wof:placetype":"locality"
},
  "geometry": {"coordinates":[111.73511000000001,36.15776],"type":"Point"}
}