{
  "type": "Feature",
  "properties": {
    "gn:admin1_code":"30",
    "gn:asciiname":"Fanguogang",
    "gn:country_code":"CN",
    "gn:dem":19,
    "gn:feature_class":"P",
    "gn:feature_code":"PPL",
    "gn:name":"Fanguogang",
    "gn:population":0,
    "gn:timezone":"Asia/Shanghai",
    "iso:country":"CN",
    "name:zho_x_preferred":[
        "\u996d\u679c\u5c97"
    ],
    "wof:name":"Fanguogang",
    "wof:placetype":"locality"
},
  "geometry": {"coordinates":[111.81778,22.23277],"type":"Point"}
}