{
  "type": "Feature",
  "properties": {
    "gn:admin1_code":"7.0",
    "gn:asciiname":"Xiaoqiao",
    "gn:country_code":"CN",
    "gn:dem":145,
    "gn:feature_class":"P",
    "gn:feature_code":"PPLA4",
    "gn:name":"Xiaoqiao",
    "gn:population":0,
    "gn:timezone":"Asia/Shanghai",
    "iso:country":"CN",
    "name:und_x_variant":[
        "Hsiao-ch\u2019iao",
        "Xiaoqiao",
        "\u5c0f\u6865",
        "Xiaoqiao Zhen",
        "\u5c0f\u6865\u9547"
    ],
    "wof:name":"Xiaoqiao",
    "wof:placetype":"locality"
},
  "geometry": {"coordinates":[118.46607,26.95385],"type":"Point"}
}