{
  "type": "Feature",
  "properties": {
    "gn:admin1_code":"19.0",
    "gn:asciiname":"Qianjiawa",
    "gn:country_code":"CN",
    "gn:dem":633,
    "gn:feature_class":"P",
    "gn:feature_code":"PPL",
    "gn:name":"Qianjiawa",
    "gn:population":0,
    "gn:timezone":"Asia/Shanghai",
    "iso:country":"CN",
    "name:zho_x_preferred":[
        "\u94b1\u5bb6\u6d3c"
    ],
    "name:zho_x_variant":[
        "\u524d\u5bb6\u6d3c"
    ],
    "wof:name":"Qianjiawa",
    "wof:placetype":"locality"
},
  "geometry": {"coordinates":[119.94499999999999,41.8452],"type":"Point"}
}