{
  "type": "Feature",
  "properties": {
    "gn:admin1_code":"32.0",
    "gn:asciiname":"Laohuangtian",
    "gn:country_code":"CN",
    "gn:dem":373,
    "gn:feature_class":"P",
    "gn:feature_code":"PPL",
    "gn:name":"Laohuangtian",
    "gn:population":0,
    "gn:timezone":"Asia/Shanghai",
    "iso:country":"CN",
    "name:zho_x_preferred":[
        "\u8001\u8352\u7530"
    ],
    "wof:name":"Laohuangtian",
    "wof:placetype":"locality"
},
  "geometry": {"coordinates":[105.42849,28.36615],"type":"Point"}
}