{
  "type": "Feature",
  "properties": {
    "gn:admin1_code":"4.0",
    "gn:asciiname":"Linyang",
    "gn:country_code":"CN",
    "gn:dem":1,
    "gn:feature_class":"P",
    "gn:feature_code":"PPL",
    "gn:name":"Linyang",
    "gn:population":0,
    "gn:timezone":"Asia/Shanghai",
    "iso:country":"CN",
    "name:zho_x_preferred":[
        "Linyang"
    ],
    "name:zho_x_variant":[
        "\u6797\u9633"
    ],
    "wof:name":"Linyang",
    "wof:placetype":"locality"
},
  "geometry": {"coordinates":[120.00799000000001,34.26234],"type":"Point"}
}