{
  "type": "Feature",
  "properties": {
    "gn:admin1_code":"8.0",
    "gn:asciiname":"Laoshatun",
    "gn:country_code":"CN",
    "gn:dem":220,
    "gn:feature_class":"P",
    "gn:feature_code":"PPL",
    "gn:name":"Laoshatun",
    "gn:population":0,
    "gn:timezone":"Asia/Shanghai",
    "iso:country":"CN",
    "name:zho_x_preferred":[
        "\u8001\u6c99\u5c6f"
    ],
    "wof:name":"Laoshatun",
    "wof:placetype":"locality"
},
  "geometry": {"coordinates":[124.6906,48.62977],"type":"Point"}
}