{
  "type": "Feature",
  "properties": {
    "gn:admin1_code":"2.0",
    "gn:asciiname":"Xiakou",
    "gn:cc2":"CN",
    "gn:country_code":"CN",
    "gn:dem":193,
    "gn:feature_class":"P",
    "gn:feature_code":"PPL",
    "gn:name":"Xiakou",
    "gn:population":0,
    "gn:timezone":"Asia/Shanghai",
    "iso:country":"CN",
    "name:und_x_variant":[
        "Siukowchen",
        "Hsia-k\u2019ou",
        "Xiakou",
        "\u5ce1\u53e3"
    ],
    "name:zho_x_preferred":[
        "\u5ce1\u53e3"
    ],
    "wof:name":"Xiakou",
    "wof:placetype":"locality"
},
  "geometry": {"coordinates":[118.53333000000001,28.46667],"type":"Point"}
}