{
  "type": "Feature",
  "properties": {
    "gn:admin1_code":"14.0",
    "gn:asciiname":"Dongzhong",
    "gn:country_code":"CN",
    "gn:dem":3962,
    "gn:feature_class":"P",
    "gn:feature_code":"PPL",
    "gn:name":"Dongzhong",
    "gn:population":0,
    "gn:timezone":"Asia/Urumqi",
    "iso:country":"CN",
    "name:zho_x_preferred":[
        "\u4e1c\u4e2d"
    ],
    "wof:name":"Dongzhong",
    "wof:placetype":"locality"
},
  "geometry": {"coordinates":[95.07021,31.19383],"type":"Point"}
}