{
  "type": "Feature",
  "properties": {
    "gn:admin1_code":"11.0",
    "gn:asciiname":"Duimenjie",
    "gn:country_code":"CN",
    "gn:dem":942,
    "gn:feature_class":"P",
    "gn:feature_code":"PPL",
    "gn:name":"Duimenjie",
    "gn:population":0,
    "gn:timezone":"Asia/Shanghai",
    "iso:country":"CN",
    "name:zho_x_preferred":[
        "\u5bf9\u95e8\u754c"
    ],
    "wof:name":"Duimenjie",
    "wof:placetype":"locality"
},
  "geometry": {"coordinates":[110.53904,26.5186],"type":"Point"}
}