{
  "type": "Feature",
  "properties": {
    "gn:admin1_code":"5.0",
    "gn:asciiname":"Shanwanzi",
    "gn:country_code":"CN",
    "gn:dem":152,
    "gn:feature_class":"P",
    "gn:feature_code":"PPL",
    "gn:name":"Shanwanzi",
    "gn:population":0,
    "gn:timezone":"Asia/Shanghai",
    "iso:country":"CN",
    "name:zho_x_preferred":[
        "\u5c71\u6e7e\u5b50"
    ],
    "wof:name":"Shanwanzi",
    "wof:placetype":"locality"
},
  "geometry": {"coordinates":[126.5399,45.19334],"type":"Point"}
}