{
  "type": "Feature",
  "properties": {
    "gn:admin1_code":"19.0",
    "gn:asciiname":"Xinxing",
    "gn:country_code":"CN",
    "gn:dem":4,
    "gn:feature_class":"P",
    "gn:feature_code":"PPLA4",
    "gn:name":"Xinxing",
    "gn:population":0,
    "gn:timezone":"Asia/Shanghai",
    "iso:country":"CN",
    "name:ceb_x_preferred":[
        "Xinxing"
    ],
    "name:deu_x_preferred":[
        "Xinxing"
    ],
    "name:eus_x_preferred":[
        "Xinxing"
    ],
    "name:fra_x_preferred":[
        "Xinxing"
    ],
    "name:nor_x_preferred":[
        "Xinxing"
    ],
    "name:rus_x_preferred":[
        "\u0421\u0438\u043d\u044c\u0441\u0438\u043d"
    ],
    "name:swe_x_preferred":[
        "Xinxing"
    ],
    "name:und_x_variant":[
        "\u65b0\u5174",
        "\u65b0\u5174\u8857\u9053",
        "Xinxing Jiedao"
    ],
    "wof:name":"Xinxing",
    "wof:placetype":"locality"
},
  "geometry": {"coordinates":[122.25624000000001,40.71841],"type":"Point"}
}