{
  "type": "Feature",
  "properties": {
    "gn:admin1_code":"32.0",
    "gn:asciiname":"Neijiangtang",
    "gn:country_code":"CN",
    "gn:dem":310,
    "gn:feature_class":"P",
    "gn:feature_code":"PPL",
    "gn:name":"Neijiangtang",
    "gn:population":0,
    "gn:timezone":"Asia/Shanghai",
    "iso:country":"CN",
    "name:zho_x_preferred":[
        "\u5185\u6c5f\u7cd6"
    ],
    "wof:name":"Neijiangtang",
    "wof:placetype":"locality"
},
  "geometry": {"coordinates":[105.09690999999999,29.52915],"type":"Point"}
}