{
  "type": "Feature",
  "properties": {
    "gn:admin1_code":"7",
    "gn:asciiname":"Shiluo",
    "gn:country_code":"CN",
    "gn:dem":633,
    "gn:feature_class":"P",
    "gn:feature_code":"PPL",
    "gn:name":"Shiluo",
    "gn:population":0,
    "gn:timezone":"Asia/Shanghai",
    "iso:country":"CN",
    "name:und_x_variant":[
        "\u77f3\u843d",
        "Shiluo"
    ],
    "wof:name":"Shiluo",
    "wof:placetype":"locality"
},
  "geometry": {"coordinates":[119.39694,27.41633],"type":"Point"}
}