{
  "type": "Feature",
  "properties": {
    "gn:admin1_code":"11.0",
    "gn:asciiname":"Chonghengpo",
    "gn:country_code":"CN",
    "gn:dem":831,
    "gn:feature_class":"P",
    "gn:feature_code":"PPL",
    "gn:name":"Chonghengpo",
    "gn:population":0,
    "gn:timezone":"Asia/Shanghai",
    "iso:country":"CN",
    "name:zho_x_preferred":[
        "\u51b2\u4ea8\u5761"
    ],
    "wof:name":"Chonghengpo",
    "wof:placetype":"locality"
},
  "geometry": {"coordinates":[108.85375000000001,27.06092],"type":"Point"}
}