{
  "type": "Feature",
  "properties": {
    "gn:admin1_code":"30.0",
    "gn:asciiname":"Huashan",
    "gn:country_code":"CN",
    "gn:dem":391,
    "gn:feature_class":"P",
    "gn:feature_code":"PPL",
    "gn:name":"Huashan",
    "gn:population":0,
    "gn:timezone":"Asia/Urumqi",
    "iso:country":"CN",
    "name:zho_x_preferred":[
        "\u534e\u5c71"
    ],
    "wof:name":"Huashan",
    "wof:placetype":"locality"
},
  "geometry": {"coordinates":[110.88482999999999,22.56714],"type":"Point"}
}