{
  "type": "Feature",
  "properties": {
    "gn:admin1_code":"33.0",
    "gn:asciiname":"Pingkan",
    "gn:country_code":"CN",
    "gn:dem":274,
    "gn:feature_class":"P",
    "gn:feature_code":"PPL",
    "gn:name":"Pingkan",
    "gn:population":0,
    "gn:timezone":"Asia/Shanghai",
    "iso:country":"CN",
    "name:zho_x_preferred":[
        "\u576a\u574e"
    ],
    "wof:name":"Pingkan",
    "wof:placetype":"locality"
},
  "geometry": {"coordinates":[106.02097000000001,29.91961],"type":"Point"}
}