{
  "type": "Feature",
  "properties": {
    "gn:country":"CN",
    "gn:fcode":"PPLA3",
    "gn:population":0,
    "iso:country":"CN",
    "name:deu_x_preferred":[
        "Qian'an"
    ],
    "name:eng_x_preferred":[
        "Qian'an County"
    ],
    "name:fas_x_preferred":[
        "\u0634\u0647\u0631\u0633\u062a\u0627\u0646 \u0686\u06cc\u0627\u0646\u0627\u0646"
    ],
    "name:gan_x_preferred":[
        "\u4e7e\u5b89\u53bf"
    ],
    "name:jpn_x_preferred":[
        "\u4e7e\u5b89\u770c"
    ],
    "name:kor_x_preferred":[
        "\uccb8\uc548\ud604"
    ],
    "name:nan_x_preferred":[
        "Khi\u00e2n-an-ko\u0101n"
    ],
    "name:nld_x_preferred":[
        "Qian'an"
    ],
    "name:nob_x_preferred":[
        "Qian'an"
    ],
    "name:pol_x_preferred":[
        "Qian'an"
    ],
    "name:rus_x_preferred":[
        "\u0426\u044f\u043d\u044c\u0430\u043d\u044c"
    ],
    "name:swe_x_preferred":[
        "Qian'an"
    ],
    "name:vie_x_preferred":[
        "Ki\u1ec1n An"
    ],
    "name:wuu_x_preferred":[
        "\u4e7e\u5b89\u53bf"
    ],
    "name:zho_x_preferred":[
        "Ch\u2019ien-an-chen"
    ],
    "name:zho_x_variant":[
        "Tsyan\u2019an",
        "Ch\u2019ien-an",
        "Ch\u2019ang-fa-t\u2019un",
        "Qian\u2019an",
        "\u4e7e\u5b89\u53bf"
    ],
    "qs:name":"\u4e7e\u5b89\u53bf",
    "qs:name_adm0":"\u4e2d\u570b",
    "qs:name_adm1":"\u5409\u6797\u7701",
    "qs:photos":1,
    "qs:photos_1k":1,
    "qs:photos_9k":1,
    "qs:photos_9r":1,
    "qs:photos_all":1,
    "qs:photos_sr":1,
    "qs:placetype":"LocalAdmin",
    "qs:pop_sr":"6",
    "wd:wordcount":92,
    "wof:name":"\u4e7e\u5b89\u53bf",
    "wof:placetype":"localadmin",
    "wof:population":0
},
  "geometry": {"coordinates":[124.05811,44.99324],"type":"Point"}
}