{
  "type": "Feature",
  "properties": {
    "gn:country":"CN",
    "gn:fcode":"PPLA3",
    "gn:pop":0,
    "iso:country":"CN",
    "name:zho_x_preferred":[
        "Ch\u2019ien-an-chen"
    ],
    "name:zho_x_variant":[
        "Tsyan\u2019an",
        "Ch\u2019ien-an",
        "Ch\u2019ang-fa-t\u2019un",
        "Qian\u2019an"
    ],
    "qs:name":"\u4e7e\u5b89\u53bf",
    "qs:name_adm0":"\u4e2d\u570b",
    "qs:name_adm1":"\u5409\u6797\u7701",
    "qs:photos":1,
    "qs:photos_1k":1,
    "qs:photos_9k":1,
    "qs:photos_9r":1,
    "qs:photos_all":1,
    "qs:photos_sr":1,
    "qs:placetype":"LocalAdmin",
    "qs:pop_sr":"6",
    "wd:wordcount":92,
    "wof:name":"\u4e7e\u5b89\u53bf",
    "wof:placetype":"localadmin",
    "wof:population":0
},
  "geometry": {"coordinates":[124.05811,44.99324],"type":"Point"}
}