{
  "type": "Feature",
  "properties": {
    "gn:admin1_code":"26.0",
    "gn:asciiname":"Cuijia Hedicun",
    "gn:country_code":"CN",
    "gn:dem":862,
    "gn:feature_class":"P",
    "gn:feature_code":"PPL",
    "gn:name":"Cuijia Hedicun",
    "gn:population":0,
    "gn:timezone":"Asia/Shanghai",
    "iso:country":"CN",
    "name:zho_x_preferred":[
        "\u5d14\u5bb6\u6cb3\u5e95\u6751"
    ],
    "wof:name":"Cuijia Hedicun",
    "wof:placetype":"locality"
},
  "geometry": {"coordinates":[110.449,38.0639],"type":"Point"}
}