{
  "type": "Feature",
  "properties": {
    "gn:admin1_code":"25",
    "gn:asciiname":"Tianzhen",
    "gn:cc2":"CN",
    "gn:country_code":"CN",
    "gn:dem":12,
    "gn:feature_class":"P",
    "gn:feature_code":"PPL",
    "gn:name":"Tianzhen",
    "gn:population":0,
    "gn:timezone":"Asia/Shanghai",
    "iso:country":"CN",
    "name:deu_x_preferred":[
        "Gaoqing"
    ],
    "name:fas_x_preferred":[
        "\u0634\u0647\u0631\u0633\u062a\u0627\u0646 \u06af\u0627\u0626\u0648\u0686\u06cc\u0646\u06af"
    ],
    "name:jpn_x_preferred":[
        "\u9ad8\u9752\u770c"
    ],
    "name:kor_x_preferred":[
        "\uac00\uc624\uce6d\ud604"
    ],
    "name:nor_x_preferred":[
        "Gaoqing"
    ],
    "name:rus_x_preferred":[
        "\u0413\u0430\u043e\u0446\u0438\u043d"
    ],
    "name:swe_x_preferred":[
        "Gaoqing"
    ],
    "name:und_x_variant":[
        "Gaoqing",
        "T\u2019ien-chen",
        "Kao-ch\u2019ing",
        "Tianzhencun",
        "Tianzhen"
    ],
    "name:vie_x_preferred":[
        "Cao Thanh"
    ],
    "name:zho_x_preferred":[
        "\u9ad8\u9752\u53bf"
    ],
    "wof:name":"Tianzhen",
    "wof:placetype":"locality"
},
  "geometry": {"coordinates":[117.83083000000001,37.17278],"type":"Point"}
}