{
  "type": "Feature",
  "properties": {
    "gn:admin1_code":"26.0",
    "gn:asciiname":"Tiantijie",
    "gn:country_code":"CN",
    "gn:dem":1542,
    "gn:feature_class":"P",
    "gn:feature_code":"PPL",
    "gn:name":"Tiantijie",
    "gn:population":0,
    "gn:timezone":"Asia/Shanghai",
    "iso:country":"CN",
    "name:zho_x_preferred":[
        "\u5929\u8e22\u754c"
    ],
    "wof:name":"Tiantijie",
    "wof:placetype":"locality"
},
  "geometry": {"coordinates":[108.68718,37.38964],"type":"Point"}
}