{
  "type": "Feature",
  "properties": {
    "gn:admin1_code":"24.0",
    "gn:asciiname":"Haojiagoucun",
    "gn:country_code":"CN",
    "gn:dem":977,
    "gn:feature_class":"P",
    "gn:feature_code":"PPL",
    "gn:name":"Haojiagoucun",
    "gn:population":0,
    "gn:timezone":"Asia/Shanghai",
    "iso:country":"CN",
    "name:zho_x_preferred":[
        "\u90dd\u5bb6\u6c9f\u6751"
    ],
    "wof:name":"Haojiagoucun",
    "wof:placetype":"locality"
},
  "geometry": {"coordinates":[110.69047999999999,37.98811],"type":"Point"}
}