{
  "type": "Feature",
  "properties": {
    "gn:admin1_code":"04",
    "gn:asciiname":"Shajiazhuang",
    "gn:cc2":"CN",
    "gn:country_code":"CN",
    "gn:dem":5,
    "gn:feature_class":"P",
    "gn:feature_code":"PPL",
    "gn:name":"Shajiazhuang",
    "gn:population":0,
    "gn:timezone":"Asia/Shanghai",
    "iso:country":"CN",
    "name:und_x_variant":[
        "Sha-hsin-chuang",
        "Shajiazhuang"
    ],
    "wof:name":"Shajiazhuang",
    "wof:placetype":"locality"
},
  "geometry": {"coordinates":[120.58360999999999,32.22861],"type":"Point"}
}