{
  "type": "Feature",
  "properties": {
    "gn:admin1_code":"7",
    "gn:asciiname":"Longjinggang",
    "gn:country_code":"CN",
    "gn:dem":913,
    "gn:feature_class":"P",
    "gn:feature_code":"PPL",
    "gn:name":"Longjinggang",
    "gn:population":0,
    "gn:timezone":"Asia/Shanghai",
    "iso:country":"CN",
    "name:und_x_variant":[
        "\u9f99\u4e95\u5c97"
    ],
    "wof:name":"Longjinggang",
    "wof:placetype":"locality"
},
  "geometry": {"coordinates":[119.94417,27.22944],"type":"Point"}
}