{
  "type": "Feature",
  "properties": {
    "gn:admin1_code":"32.0",
    "gn:asciiname":"Tianwangsi",
    "gn:country_code":"CN",
    "gn:dem":499,
    "gn:feature_class":"P",
    "gn:feature_code":"PPL",
    "gn:name":"Tianwangsi",
    "gn:population":0,
    "gn:timezone":"Asia/Shanghai",
    "iso:country":"CN",
    "name:zho_x_preferred":[
        "\u5929\u738b\u5bfa"
    ],
    "wof:name":"Tianwangsi",
    "wof:placetype":"locality"
},
  "geometry": {"coordinates":[104.14987000000001,30.98767],"type":"Point"}
}