{
  "type": "Feature",
  "properties": {
    "gn:admin1_code":"9.0",
    "gn:asciiname":"Xiwanglou",
    "gn:country_code":"CN",
    "gn:dem":200,
    "gn:feature_class":"P",
    "gn:feature_code":"PPL",
    "gn:name":"Xiwanglou",
    "gn:population":0,
    "gn:timezone":"Asia/Shanghai",
    "iso:country":"CN",
    "name:zho_x_preferred":[
        "\u897f\u738b\u697c"
    ],
    "wof:name":"Xiwanglou",
    "wof:placetype":"locality"
},
  "geometry": {"coordinates":[113.64279000000001,32.80484000000001],"type":"Point"}
}