{
  "type": "Feature",
  "properties": {
    "gn:admin1_code":"02",
    "gn:asciiname":"Zheng'ao",
    "gn:country_code":"CN",
    "gn:dem":106,
    "gn:feature_class":"P",
    "gn:feature_code":"PPL",
    "gn:name":"Zheng\u2019ao",
    "gn:population":0,
    "gn:timezone":"Asia/Shanghai",
    "iso:country":"CN",
    "name:zho_x_preferred":[
        "Zheng\u2019ao"
    ],
    "wof:name":"Zheng'ao",
    "wof:placetype":"locality"
},
  "geometry": {"coordinates":[121.02261,27.84495],"type":"Point"}
}