{
  "type": "Feature",
  "properties": {
    "gn:admin1_code":"26.0",
    "gn:asciiname":"Daliushucun",
    "gn:country_code":"CN",
    "gn:dem":1199,
    "gn:feature_class":"P",
    "gn:feature_code":"PPL",
    "gn:name":"Daliushucun",
    "gn:population":0,
    "gn:timezone":"Asia/Shanghai",
    "iso:country":"CN",
    "name:zho_x_preferred":[
        "\u5927\u67f3\u6811\u6751"
    ],
    "wof:name":"Daliushucun",
    "wof:placetype":"locality"
},
  "geometry": {"coordinates":[106.7735,34.8212],"type":"Point"}
}