{
  "type": "Feature",
  "properties": {
    "gn:admin1_code":"8.0",
    "gn:asciiname":"Houkule",
    "gn:country_code":"CN",
    "gn:dem":158,
    "gn:feature_class":"P",
    "gn:feature_code":"PPL",
    "gn:name":"Houkule",
    "gn:population":0,
    "gn:timezone":"Asia/Shanghai",
    "iso:country":"CN",
    "name:zho_x_preferred":[
        "\u540e\u5e93\u52d2"
    ],
    "wof:name":"Houkule",
    "wof:placetype":"locality"
},
  "geometry": {"coordinates":[123.53727000000001,47.28676],"type":"Point"}
}