{
  "type": "Feature",
  "properties": {
    "gn:admin1_code":"3.0",
    "gn:asciiname":"Gaofu",
    "gn:country_code":"CN",
    "gn:dem":554,
    "gn:feature_class":"P",
    "gn:feature_code":"PPL",
    "gn:name":"Gaofu",
    "gn:population":0,
    "gn:timezone":"Asia/Shanghai",
    "iso:country":"CN",
    "name:und_x_variant":[
        "\u9ad8\u5bcc"
    ],
    "wof:name":"Gaofu",
    "wof:placetype":"locality"
},
  "geometry": {"coordinates":[114.50856,27.64168],"type":"Point"}
}