{
  "type": "Feature",
  "properties": {
    "gn:admin1_code":"32.0",
    "gn:asciiname":"Waziping",
    "gn:country_code":"CN",
    "gn:dem":920,
    "gn:feature_class":"P",
    "gn:feature_code":"PPL",
    "gn:name":"Waziping",
    "gn:population":0,
    "gn:timezone":"Asia/Shanghai",
    "iso:country":"CN",
    "name:zho_x_preferred":[
        "\u74e6\u5b50\u576a"
    ],
    "wof:name":"Waziping",
    "wof:placetype":"locality"
},
  "geometry": {"coordinates":[108.11386,31.86153],"type":"Point"}
}