{
  "type": "Feature",
  "properties": {
    "gn:admin1_code":"10.0",
    "gn:asciiname":"Cuigezhuang",
    "gn:country_code":"CN",
    "gn:dem":19,
    "gn:feature_class":"P",
    "gn:feature_code":"PPL",
    "gn:name":"Cuigezhuang",
    "gn:population":0,
    "gn:timezone":"Asia/Shanghai",
    "iso:country":"CN",
    "name:zho_x_preferred":[
        "\u5d14\u5404\u5e84"
    ],
    "wof:name":"Cuigezhuang",
    "wof:placetype":"locality"
},
  "geometry": {"coordinates":[119.46084,39.83953],"type":"Point"}
}