{
  "type": "Feature",
  "properties": {
    "gn:admin1_code":"29.0",
    "gn:asciiname":"Xinjie",
    "gn:cc2":"CN",
    "gn:country_code":"CN",
    "gn:dem":1105,
    "gn:feature_class":"P",
    "gn:feature_code":"PPL",
    "gn:name":"Xinjie",
    "gn:population":0,
    "gn:timezone":"Asia/Shanghai",
    "iso:country":"CN",
    "name:und_x_variant":[
        "Hsi-ch\u2019ou-hsin-chieh",
        "Ch\u2019ou-yang-hsin-chieh",
        "Hsin-chieh",
        "Ch\u2019ou-yang",
        "Ch\u2019ou-yang-chieh",
        "Ch\u2019ou-yang-chia",
        "Ch\u2019ou-yang-chai",
        "Xinjie"
    ],
    "wof:name":"Xinjie",
    "wof:placetype":"locality"
},
  "geometry": {"coordinates":[104.59,23.2425],"type":"Point"}
}