{
  "type": "Feature",
  "properties": {
    "gn:admin1_code":"4.0",
    "gn:asciiname":"Jinsha",
    "gn:country_code":"CN",
    "gn:dem":4,
    "gn:feature_class":"P",
    "gn:feature_code":"PPL",
    "gn:name":"Jinsha",
    "gn:population":0,
    "gn:timezone":"Asia/Shanghai",
    "iso:country":"CN",
    "name:ara_x_preferred":[
        "\u062c\u064a\u0646\u0634\u0627"
    ],
    "name:ceb_x_preferred":[
        "Jinsha"
    ],
    "name:deu_x_preferred":[
        "Jinsha-Fluss"
    ],
    "name:deu_x_variant":[
        "Jinsha"
    ],
    "name:ell_x_preferred":[
        "\u0393\u03af\u03bd\u03c3\u03b1"
    ],
    "name:fas_x_preferred":[
        "\u062c\u06cc\u0646\u0634\u0627"
    ],
    "name:fra_x_preferred":[
        "Jinsha"
    ],
    "name:heb_x_preferred":[
        "\u05d2'\u05d9\u05e0\u05e9\u05d4"
    ],
    "name:hin_x_preferred":[
        "\u091c\u093f\u0902\u0936\u093e"
    ],
    "name:hun_x_preferred":[
        "Jinsha"
    ],
    "name:ind_x_preferred":[
        "Jinsha"
    ],
    "name:ita_x_preferred":[
        "Jinsha"
    ],
    "name:nor_x_preferred":[
        "Jinsha"
    ],
    "name:pol_x_preferred":[
        "Jinsha"
    ],
    "name:por_x_preferred":[
        "Jinsha"
    ],
    "name:swe_x_preferred":[
        "Jinsha"
    ],
    "name:tur_x_preferred":[
        "Jinsha"
    ],
    "name:ukr_x_preferred":[
        "\u0426\u0437\u0438\u043d\u044c\u0448\u0430"
    ],
    "name:urd_x_preferred":[
        "\u062c\u0646\u0634\u0627"
    ],
    "name:zho_x_preferred":[
        "\u91d1\u6c99"
    ],
    "wof:name":"Jinsha",
    "wof:placetype":"locality"
},
  "geometry": {"coordinates":[120.01357,32.1289],"type":"Point"}
}