{
  "type": "Feature",
  "properties": {
    "gn:admin1_code":"4.0",
    "gn:asciiname":"Jinsha",
    "gn:country_code":"CN",
    "gn:dem":4,
    "gn:feature_class":"P",
    "gn:feature_code":"PPL",
    "gn:name":"Jinsha",
    "gn:population":0,
    "gn:timezone":"Asia/Shanghai",
    "iso:country":"CN",
    "name:ceb_x_preferred":[
        "Jinsha"
    ],
    "name:deu_x_preferred":[
        "Jinsha"
    ],
    "name:fra_x_preferred":[
        "Jinsha"
    ],
    "name:ita_x_preferred":[
        "Jinsha"
    ],
    "name:nor_x_preferred":[
        "Jinsha"
    ],
    "name:swe_x_preferred":[
        "Jinsha"
    ],
    "name:zho_x_preferred":[
        "\u91d1\u6c99"
    ],
    "wof:name":"Jinsha",
    "wof:placetype":"locality"
},
  "geometry": {"coordinates":[120.01357,32.1289],"type":"Point"}
}