{
  "type": "Feature",
  "properties": {
    "gn:admin1_code":"11.0",
    "gn:asciiname":"Laomatou",
    "gn:country_code":"CN",
    "gn:dem":391,
    "gn:feature_class":"P",
    "gn:feature_code":"PPL",
    "gn:name":"Laomatou",
    "gn:population":0,
    "gn:timezone":"Asia/Shanghai",
    "iso:country":"CN",
    "name:zho_x_preferred":[
        "\u8001\u9a6c\u5934"
    ],
    "wof:name":"Laomatou",
    "wof:placetype":"locality"
},
  "geometry": {"coordinates":[111.1181,28.54299],"type":"Point"}
}