{
  "type": "Feature",
  "properties": {
    "gn:admin1_code":"12.0",
    "gn:asciiname":"Shabadi",
    "gn:country_code":"CN",
    "gn:dem":688,
    "gn:feature_class":"P",
    "gn:feature_code":"PPL",
    "gn:name":"Shabadi",
    "gn:population":0,
    "gn:timezone":"Asia/Shanghai",
    "iso:country":"CN",
    "name:zho_x_preferred":[
        "\u6c99\u6252\u5730"
    ],
    "wof:name":"Shabadi",
    "wof:placetype":"locality"
},
  "geometry": {"coordinates":[110.86727999999999,32.12684],"type":"Point"}
}