{
  "type": "Feature",
  "properties": {
    "gn:admin1_code":"11.0",
    "gn:asciiname":"Hewan",
    "gn:country_code":"CN",
    "gn:dem":96,
    "gn:feature_class":"P",
    "gn:feature_code":"PPL",
    "gn:name":"Hewan",
    "gn:population":0,
    "gn:timezone":"Asia/Shanghai",
    "iso:country":"CN",
    "name:zho_x_preferred":[
        "Hewan"
    ],
    "name:zho_x_variant":[
        "\u548c\u6e7e"
    ],
    "wof:name":"Hewan",
    "wof:placetype":"locality"
},
  "geometry": {"coordinates":[111.56047,29.17216],"type":"Point"}
}