{
  "type": "Feature",
  "properties": {
    "gn:admin1_code":"12.0",
    "gn:asciiname":"Wangren",
    "gn:country_code":"CN",
    "gn:dem":32,
    "gn:feature_class":"P",
    "gn:feature_code":"PPLA4",
    "gn:name":"Wangren",
    "gn:population":0,
    "gn:timezone":"Asia/Shanghai",
    "iso:country":"CN",
    "name:und_x_variant":[
        "Wang-jen-p\u2019u",
        "Wang-jen",
        "Wangren",
        "\u6c6a\u4ec1",
        "Wangren Zhen",
        "\u6c6a\u4ec1\u9547"
    ],
    "wof:name":"Wangren",
    "wof:placetype":"locality"
},
  "geometry": {"coordinates":[115.12350000000001,30.15372],"type":"Point"}
}