{
  "type": "Feature",
  "properties": {
    "gn:admin1_code":"29.0",
    "gn:asciiname":"Damaidi",
    "gn:country_code":"CN",
    "gn:dem":2157,
    "gn:feature_class":"P",
    "gn:feature_code":"PPL",
    "gn:name":"Damaidi",
    "gn:population":0,
    "gn:timezone":"Asia/Shanghai",
    "iso:country":"CN",
    "name:epo_x_preferred":[
        "Damaidi"
    ],
    "name:fra_x_preferred":[
        "Damaidi"
    ],
    "name:ind_x_preferred":[
        "Damaidi"
    ],
    "name:zho_x_preferred":[
        "\u5927\u9ea6\u5730"
    ],
    "name:zho_x_variant":[
        "\u5927\u9ea5\u5730\u6587\u5316"
    ],
    "wof:name":"Damaidi",
    "wof:placetype":"locality"
},
  "geometry": {"coordinates":[100.244,25.5133],"type":"Point"}
}