{
  "type": "Feature",
  "properties": {
    "gn:admin1_code":"3",
    "gn:asciiname":"Dalingbei",
    "gn:country_code":"CN",
    "gn:dem":369,
    "gn:feature_class":"P",
    "gn:feature_code":"PPL",
    "gn:name":"Dalingbei",
    "gn:population":0,
    "gn:timezone":"Asia/Shanghai",
    "iso:country":"CN",
    "name:zho_x_preferred":[
        "\u5927\u5cad\u80cc"
    ],
    "wof:name":"Dalingbei",
    "wof:placetype":"locality"
},
  "geometry": {"coordinates":[114.617,26.0444],"type":"Point"}
}