{
  "type": "Feature",
  "properties": {
    "gn:admin1_code":"29.0",
    "gn:asciiname":"Shandao",
    "gn:country_code":"CN",
    "gn:dem":1785,
    "gn:feature_class":"P",
    "gn:feature_code":"PPL",
    "gn:name":"Shandao",
    "gn:population":0,
    "gn:timezone":"Asia/Shanghai",
    "iso:country":"CN",
    "name:fra_x_preferred":[
        "Shandao"
    ],
    "name:pol_x_preferred":[
        "Shandao"
    ],
    "name:rus_x_preferred":[
        "\u0428\u0430\u043d\u044c\u0434\u0430\u043e"
    ],
    "name:swe_x_preferred":[
        "Shan-tao"
    ],
    "name:zho_x_preferred":[
        "\u5584\u5bfc"
    ],
    "wof:name":"Shandao",
    "wof:placetype":"locality"
},
  "geometry": {"coordinates":[103.77800000000001,24.5984],"type":"Point"}
}