{
  "type": "Feature",
  "properties": {
    "gn:admin1_code":"12.0",
    "gn:asciiname":"Xiejia Dawan",
    "gn:country_code":"CN",
    "gn:dem":30,
    "gn:feature_class":"P",
    "gn:feature_code":"PPL",
    "gn:name":"Xiejia Dawan",
    "gn:population":0,
    "gn:timezone":"Asia/Shanghai",
    "iso:country":"CN",
    "name:und_x_variant":[
        "\u8c22\u5bb6\u5927\u5846"
    ],
    "wof:name":"Xiejia Dawan",
    "wof:placetype":"locality"
},
  "geometry": {"coordinates":[114.96021,30.51028],"type":"Point"}
}