{
  "type": "Feature",
  "properties": {
    "gn:admin1_code":"19",
    "gn:asciiname":"Tashantun",
    "gn:country_code":"CN",
    "gn:dem":5,
    "gn:feature_class":"P",
    "gn:feature_code":"PPLA4",
    "gn:name":"Tashantun",
    "gn:population":0,
    "gn:timezone":"Asia/Shanghai",
    "iso:country":"CN",
    "name:und_x_variant":[
        "Tashantun Zhen",
        "Tashantun"
    ],
    "name:zho_x_preferred":[
        "\u5854\u5c71\u5c6f"
    ],
    "name:zho_x_variant":[
        "\u5854\u5c71\u5c6f\u9547"
    ],
    "wof:name":"Tashantun",
    "wof:placetype":"locality"
},
  "geometry": {"coordinates":[120.39549,40.25494000000001],"type":"Point"}
}