{
  "type": "Feature",
  "properties": {
    "gn:admin1_code":"7.0",
    "gn:asciiname":"Shatan",
    "gn:country_code":"CN",
    "gn:dem":539,
    "gn:feature_class":"P",
    "gn:feature_code":"PPL",
    "gn:name":"Shatan",
    "gn:population":0,
    "gn:timezone":"Asia/Shanghai",
    "iso:country":"CN",
    "name:ceb_x_preferred":[
        "Shatan"
    ],
    "name:swe_x_preferred":[
        "Shatan"
    ],
    "name:zho_x_preferred":[
        "\u6c99\u6f6d"
    ],
    "wof:name":"Shatan",
    "wof:placetype":"locality"
},
  "geometry": {"coordinates":[119.36673,27.4338],"type":"Point"}
}