{
  "type": "Feature",
  "properties": {
    "gn:admin1_code":"26.0",
    "gn:asciiname":"Liujialingcun",
    "gn:country_code":"CN",
    "gn:dem":687,
    "gn:feature_class":"P",
    "gn:feature_code":"PPL",
    "gn:name":"Liujialingcun",
    "gn:population":0,
    "gn:timezone":"Asia/Shanghai",
    "iso:country":"CN",
    "name:zho_x_preferred":[
        "\u5218\u5bb6\u5cad\u6751"
    ],
    "wof:name":"Liujialingcun",
    "wof:placetype":"locality"
},
  "geometry": {"coordinates":[110.18331000000001,35.17149000000001],"type":"Point"}
}