{
  "type": "Feature",
  "properties": {
    "gn:admin1_code":"26.0",
    "gn:asciiname":"Yuanjia'aba",
    "gn:country_code":"CN",
    "gn:dem":1350,
    "gn:feature_class":"P",
    "gn:feature_code":"PPL",
    "gn:name":"Yuanjia\u2019aba",
    "gn:population":0,
    "gn:timezone":"Asia/Shanghai",
    "iso:country":"CN",
    "name:und_x_variant":[
        "Yuanjia\u2019aba",
        "\u8881\u5bb6\u963f\u575d"
    ],
    "wof:name":"Yuanjia'aba",
    "wof:placetype":"locality"
},
  "geometry": {"coordinates":[106.61174,33.30394],"type":"Point"}
}