{
  "type": "Feature",
  "properties": {
    "gn:admin1_code":"19.0",
    "gn:asciiname":"Dasitai",
    "gn:country_code":"CN",
    "gn:dem":103,
    "gn:feature_class":"P",
    "gn:feature_code":"PPL",
    "gn:name":"Dasitai",
    "gn:population":0,
    "gn:timezone":"Asia/Shanghai",
    "iso:country":"CN",
    "name:zho_x_preferred":[
        "\u5927\u56db\u53f0"
    ],
    "wof:name":"Dasitai",
    "wof:placetype":"locality"
},
  "geometry": {"coordinates":[120.8318,40.89239],"type":"Point"}
}