{
  "type": "Feature",
  "properties": {
    "gn:admin1_code":"8.0",
    "gn:asciiname":"Erpailiucun",
    "gn:country_code":"CN",
    "gn:dem":189,
    "gn:feature_class":"P",
    "gn:feature_code":"PPL",
    "gn:name":"Erpailiucun",
    "gn:population":0,
    "gn:timezone":"Asia/Shanghai",
    "iso:country":"CN",
    "name:zho_x_preferred":[
        "\u4e8c\u6392\u516d\u6751"
    ],
    "wof:name":"Erpailiucun",
    "wof:placetype":"locality"
},
  "geometry": {"coordinates":[125.69311999999999,46.82371],"type":"Point"}
}