{
  "type": "Feature",
  "properties": {
    "gn:admin1_code":"19.0",
    "gn:asciiname":"Shaoguodi",
    "gn:country_code":"CN",
    "gn:dem":483,
    "gn:feature_class":"P",
    "gn:feature_code":"PPL",
    "gn:name":"Shaoguodi",
    "gn:population":0,
    "gn:timezone":"Asia/Shanghai",
    "iso:country":"CN",
    "name:zho_x_preferred":[
        "\u70e7\u9505\u5730"
    ],
    "wof:name":"Shaoguodi",
    "wof:placetype":"locality"
},
  "geometry": {"coordinates":[119.20021,40.80607],"type":"Point"}
}