{
  "type": "Feature",
  "properties": {
    "gn:admin1_code":"3.0",
    "gn:asciiname":"Nankengwei",
    "gn:country_code":"CN",
    "gn:dem":168,
    "gn:feature_class":"P",
    "gn:feature_code":"PPL",
    "gn:name":"Nankengwei",
    "gn:population":0,
    "gn:timezone":"Asia/Shanghai",
    "iso:country":"CN",
    "name:und_x_variant":[
        "\u5357\u5751\u5c3e"
    ],
    "wof:name":"Nankengwei",
    "wof:placetype":"locality"
},
  "geometry": {"coordinates":[115.04618000000001,25.28891],"type":"Point"}
}