{
  "type": "Feature",
  "properties": {
    "gn:admin1_code":"5.0",
    "gn:asciiname":"Beidalingcun",
    "gn:country_code":"CN",
    "gn:dem":155,
    "gn:feature_class":"P",
    "gn:feature_code":"PPL",
    "gn:name":"Beidalingcun",
    "gn:population":0,
    "gn:timezone":"Asia/Shanghai",
    "iso:country":"CN",
    "name:zho_x_preferred":[
        "\u5317\u5927\u5cad\u6751"
    ],
    "wof:name":"Beidalingcun",
    "wof:placetype":"locality"
},
  "geometry": {"coordinates":[122.78565999999999,45.75756],"type":"Point"}
}