{
  "type": "Feature",
  "properties": {
    "gn:admin1_code":"6.0",
    "gn:asciiname":"Beiga",
    "gn:country_code":"CN",
    "gn:dem":4166,
    "gn:feature_class":"P",
    "gn:feature_code":"PPL",
    "gn:name":"Beiga",
    "gn:population":0,
    "gn:timezone":"Asia/Urumqi",
    "iso:country":"CN",
    "name:zho_x_preferred":[
        "\u80cc\u5c15"
    ],
    "wof:name":"Beiga",
    "wof:placetype":"locality"
},
  "geometry": {"coordinates":[96.41656999999999,33.35562],"type":"Point"}
}