{
  "type": "Feature",
  "properties": {
    "gn:admin1_code":"8.0",
    "gn:asciiname":"Lihengtun",
    "gn:country_code":"CN",
    "gn:dem":266,
    "gn:feature_class":"P",
    "gn:feature_code":"PPL",
    "gn:name":"Lihengtun",
    "gn:population":0,
    "gn:timezone":"Asia/Shanghai",
    "iso:country":"CN",
    "name:zho_x_preferred":[
        "\u674e\u6052\u5c6f"
    ],
    "wof:name":"Lihengtun",
    "wof:placetype":"locality"
},
  "geometry": {"coordinates":[128.04312999999999,45.72283],"type":"Point"}
}