{
  "type": "Feature",
  "properties": {
    "gn:admin1_code":"10.0",
    "gn:asciiname":"Wanghewan",
    "gn:country_code":"CN",
    "gn:dem":709,
    "gn:feature_class":"P",
    "gn:feature_code":"PPL",
    "gn:name":"Wanghewan",
    "gn:population":0,
    "gn:timezone":"Asia/Shanghai",
    "iso:country":"CN",
    "name:zho_x_preferred":[
        "\u738b\u6cb3\u6e7e"
    ],
    "wof:name":"Wanghewan",
    "wof:placetype":"locality"
},
  "geometry": {"coordinates":[115.02727,40.65756],"type":"Point"}
}