{
  "type": "Feature",
  "properties": {
    "gn:admin1_code":"6.0",
    "gn:asciiname":"Bi Qu",
    "gn:country_code":"CN",
    "gn:dem":4582,
    "gn:feature_class":"P",
    "gn:feature_code":"PPL",
    "gn:name":"Bi Qu",
    "gn:population":0,
    "gn:timezone":"Asia/Urumqi",
    "iso:country":"CN",
    "wof:name":"Bi Qu",
    "wof:placetype":"locality"
},
  "geometry": {"coordinates":[92.33333,33.88333],"type":"Point"}
}