{
  "type": "Feature",
  "properties": {
    "gn:admin1_code":"19.0",
    "gn:asciiname":"Daguojiatun",
    "gn:country_code":"CN",
    "gn:dem":12,
    "gn:feature_class":"P",
    "gn:feature_code":"PPL",
    "gn:name":"Daguojiatun",
    "gn:population":0,
    "gn:timezone":"Asia/Shanghai",
    "iso:country":"CN",
    "name:zho_x_preferred":[
        "\u5927\u90ed\u5bb6\u5c6f"
    ],
    "wof:name":"Daguojiatun",
    "wof:placetype":"locality"
},
  "geometry": {"coordinates":[123.518,39.8049],"type":"Point"}
}