{
  "type": "Feature",
  "properties": {
    "gn:admin1_code":"25.0",
    "gn:asciiname":"Darongcun",
    "gn:country_code":"CN",
    "gn:dem":55,
    "gn:feature_class":"P",
    "gn:feature_code":"PPL",
    "gn:name":"Darongcun",
    "gn:population":0,
    "gn:timezone":"Asia/Shanghai",
    "iso:country":"CN",
    "name:zho_x_preferred":[
        "\u5927\u8363\u6751"
    ],
    "wof:name":"Darongcun",
    "wof:placetype":"locality"
},
  "geometry": {"coordinates":[119.40358000000001,36.08691],"type":"Point"}
}