{
  "type": "Feature",
  "properties": {
    "gn:admin1_code":"07",
    "gn:asciiname":"Banshan",
    "gn:country_code":"CN",
    "gn:dem":374,
    "gn:feature_class":"P",
    "gn:feature_code":"PPL",
    "gn:name":"Banshan",
    "gn:population":0,
    "gn:timezone":"Asia/Shanghai",
    "iso:country":"CN",
    "name:zho_x_preferred":[
        "\u534a\u5c71"
    ],
    "wof:name":"Banshan",
    "wof:placetype":"locality"
},
  "geometry": {"coordinates":[120.23914000000001,27.21242],"type":"Point"}
}