{
  "type": "Feature",
  "properties": {
    "gn:admin1_code":"32.0",
    "gn:asciiname":"Saijin",
    "gn:country_code":"CN",
    "gn:dem":382,
    "gn:feature_class":"P",
    "gn:feature_code":"PPL",
    "gn:name":"Saijin",
    "gn:population":0,
    "gn:timezone":"Asia/Shanghai",
    "iso:country":"CN",
    "name:zho_x_preferred":[
        "\u8d5b\u91d1"
    ],
    "wof:name":"Saijin",
    "wof:placetype":"locality"
},
  "geometry": {"coordinates":[106.39295,31.38542],"type":"Point"}
}