{
  "type": "Feature",
  "properties": {
    "gn:admin1_code":"10",
    "gn:asciiname":"Azhanggou",
    "gn:country_code":"CN",
    "gn:dem":1007,
    "gn:feature_class":"P",
    "gn:feature_code":"PPL",
    "gn:name":"Azhanggou",
    "gn:population":0,
    "gn:timezone":"Asia/Shanghai",
    "iso:country":"CN",
    "name:zho_x_preferred":[
        "\u963f\u7ae0\u6c9f"
    ],
    "wof:name":"Azhanggou",
    "wof:placetype":"locality"
},
  "geometry": {"coordinates":[116.8051,41.41018],"type":"Point"}
}