{
  "type": "Feature",
  "properties": {
    "gn:admin1_code":"14.0",
    "gn:asciiname":"Ruoli",
    "gn:country_code":"CN",
    "gn:dem":3215,
    "gn:feature_class":"P",
    "gn:feature_code":"PPL",
    "gn:name":"Ruoli",
    "gn:population":0,
    "gn:timezone":"Asia/Urumqi",
    "iso:country":"CN",
    "name:zho_x_preferred":[
        "\u82e5\u91cc"
    ],
    "wof:name":"Ruoli",
    "wof:placetype":"locality"
},
  "geometry": {"coordinates":[98.46208,28.85991],"type":"Point"}
}