{
  "type": "Feature",
  "properties": {
    "gn:admin1_code":"4.0",
    "gn:asciiname":"Huatu",
    "gn:country_code":"CN",
    "gn:dem":3,
    "gn:feature_class":"P",
    "gn:feature_code":"PPL",
    "gn:name":"Huatu",
    "gn:population":0,
    "gn:timezone":"Asia/Shanghai",
    "iso:country":"CN",
    "name:und_x_variant":[
        "\u82b1\u56fe"
    ],
    "name:zho_x_preferred":[
        "\u82b1\u56fe"
    ],
    "wof:name":"Huatu",
    "wof:placetype":"locality"
},
  "geometry": {"coordinates":[120.49405,31.42682000000001],"type":"Point"}
}