{
  "type": "Feature",
  "properties": {
    "gn:admin1_code":"3",
    "gn:asciiname":"Xiebeidi",
    "gn:country_code":"CN",
    "gn:dem":248,
    "gn:feature_class":"P",
    "gn:feature_code":"PPL",
    "gn:name":"Xiebeidi",
    "gn:population":0,
    "gn:timezone":"Asia/Shanghai",
    "iso:country":"CN",
    "name:zho_x_preferred":[
        "\u8c22\u80cc\u5730"
    ],
    "wof:name":"Xiebeidi",
    "wof:placetype":"locality"
},
  "geometry": {"coordinates":[114.509,25.4156],"type":"Point"}
}