{
  "type": "Feature",
  "properties": {
    "gn:admin1_code":"11.0",
    "gn:asciiname":"Xijiawan",
    "gn:country_code":"CN",
    "gn:dem":1054,
    "gn:feature_class":"P",
    "gn:feature_code":"PPL",
    "gn:name":"Xijiawan",
    "gn:population":0,
    "gn:timezone":"Asia/Shanghai",
    "iso:country":"CN",
    "name:zho_x_preferred":[
        "\u6eaa\u5bb6\u6e7e"
    ],
    "wof:name":"Xijiawan",
    "wof:placetype":"locality"
},
  "geometry": {"coordinates":[109.70676,29.61056],"type":"Point"}
}