{
  "type": "Feature",
  "properties": {
    "gn:admin1_code":"21.0",
    "gn:asciiname":"Huangjiawannao",
    "gn:country_code":"CN",
    "gn:dem":1690,
    "gn:feature_class":"P",
    "gn:feature_code":"PPL",
    "gn:name":"Huangjiawannao",
    "gn:population":0,
    "gn:timezone":"Asia/Shanghai",
    "iso:country":"CN",
    "name:zho_x_preferred":[
        "\u9ec4\u5bb6\u6e7e\u8111"
    ],
    "wof:name":"Huangjiawannao",
    "wof:placetype":"locality"
},
  "geometry": {"coordinates":[106.48354999999999,36.02752],"type":"Point"}
}