{
  "type": "Feature",
  "properties": {
    "gn:admin1_code":"29.0",
    "gn:asciiname":"Xiashulinjiao",
    "gn:country_code":"CN",
    "gn:dem":2264,
    "gn:feature_class":"P",
    "gn:feature_code":"PPL",
    "gn:name":"Xiashulinjiao",
    "gn:population":0,
    "gn:timezone":"Asia/Shanghai",
    "iso:country":"CN",
    "name:zho_x_preferred":[
        "\u4e0b\u6811\u6797\u811a"
    ],
    "wof:name":"Xiashulinjiao",
    "wof:placetype":"locality"
},
  "geometry": {"coordinates":[100.116,24.5836],"type":"Point"}
}