{
  "type": "Feature",
  "properties": {
    "gn:admin1_code":"3.0",
    "gn:asciiname":"Dalong",
    "gn:country_code":"CN",
    "gn:dem":45,
    "gn:feature_class":"P",
    "gn:feature_code":"PPLA4",
    "gn:name":"Dalong",
    "gn:population":0,
    "gn:timezone":"Asia/Shanghai",
    "iso:country":"CN",
    "name:und_x_variant":[
        "\u5927\u5784",
        "Dalong Xiang",
        "\u5927\u5784\u4e61",
        "\u5927\u5785\u4e61"
    ],
    "wof:name":"Dalong",
    "wof:placetype":"locality"
},
  "geometry": {"coordinates":[116.38433000000001,29.74413],"type":"Point"}
}