{
  "type": "Feature",
  "properties": {
    "gn:admin1_code":"11.0",
    "gn:asciiname":"Haijiaoxi",
    "gn:country_code":"CN",
    "gn:dem":362,
    "gn:feature_class":"P",
    "gn:feature_code":"PPL",
    "gn:name":"Haijiaoxi",
    "gn:population":0,
    "gn:timezone":"Asia/Shanghai",
    "iso:country":"CN",
    "name:zho_x_preferred":[
        "\u6d77\u89d2\u6eaa"
    ],
    "wof:name":"Haijiaoxi",
    "wof:placetype":"locality"
},
  "geometry": {"coordinates":[109.94273,29.39451],"type":"Point"}
}