{
  "type": "Feature",
  "properties": {
    "gn:admin1_code":"29.0",
    "gn:asciiname":"Xiaofakuai",
    "gn:country_code":"CN",
    "gn:dem":2114,
    "gn:feature_class":"P",
    "gn:feature_code":"PPL",
    "gn:name":"Xiaofakuai",
    "gn:population":0,
    "gn:timezone":"Asia/Shanghai",
    "iso:country":"CN",
    "name:zho_x_preferred":[
        "\u5c0f\u6cd5\u5757"
    ],
    "wof:name":"Xiaofakuai",
    "wof:placetype":"locality"
},
  "geometry": {"coordinates":[104.17400000000001,24.6596],"type":"Point"}
}