{
  "type": "Feature",
  "properties": {
    "gn:admin1_code":"18",
    "gn:asciiname":"Lishanxi",
    "gn:country_code":"CN",
    "gn:dem":715,
    "gn:feature_class":"P",
    "gn:feature_code":"PPL",
    "gn:name":"Lishanxi",
    "gn:population":0,
    "gn:timezone":"Asia/Shanghai",
    "iso:country":"CN",
    "name:zho_x_preferred":[
        "\u68a8\u5c71\u6eaa"
    ],
    "wof:name":"Lishanxi",
    "wof:placetype":"locality"
},
  "geometry": {"coordinates":[107.309,28.4204],"type":"Point"}
}