{
  "type": "Feature",
  "properties": {
    "gn:admin1_code":"14.0",
    "gn:asciiname":"Qujang",
    "gn:country_code":"CN",
    "gn:dem":4085,
    "gn:feature_class":"P",
    "gn:feature_code":"PPLF",
    "gn:name":"Qujang",
    "gn:population":0,
    "gn:timezone":"Asia/Urumqi",
    "iso:country":"CN",
    "name:bod_x_preferred":[
        "Qujang"
    ],
    "name:msa_x_preferred":[
        "Qujang"
    ],
    "name:zho_x_preferred":[
        "Qujiang"
    ],
    "name:zho_x_variant":[
        "\u66f2\u6c5f",
        "Chonggang",
        "\u5145\u5c97"
    ],
    "wof:name":"Qujang",
    "wof:placetype":"locality"
},
  "geometry": {"coordinates":[92.901,29.101],"type":"Point"}
}