{
  "type": "Feature",
  "properties": {
    "gn:admin1_code":"32.0",
    "gn:asciiname":"Maidiwan",
    "gn:country_code":"CN",
    "gn:dem":1752,
    "gn:feature_class":"P",
    "gn:feature_code":"PPL",
    "gn:name":"Maidiwan",
    "gn:population":0,
    "gn:timezone":"Asia/Shanghai",
    "iso:country":"CN",
    "name:zho_x_preferred":[
        "\u9ea6\u5730\u6e7e"
    ],
    "wof:name":"Maidiwan",
    "wof:placetype":"locality"
},
  "geometry": {"coordinates":[102.14400000000001,26.3651],"type":"Point"}
}