{
  "type": "Feature",
  "properties": {
    "gn:admin1_code":"19.0",
    "gn:asciiname":"Qiankanzicun",
    "gn:country_code":"CN",
    "gn:dem":22,
    "gn:feature_class":"P",
    "gn:feature_code":"PPL",
    "gn:name":"Qiankanzicun",
    "gn:population":0,
    "gn:timezone":"Asia/Shanghai",
    "iso:country":"CN",
    "name:zho_x_preferred":[
        "\u524d\u574e\u5b50\u6751"
    ],
    "wof:name":"Qiankanzicun",
    "wof:placetype":"locality"
},
  "geometry": {"coordinates":[122.46998000000001,40.67878],"type":"Point"}
}