{
  "type": "Feature",
  "properties": {
    "gn:admin1_code":"15.0",
    "gn:asciiname":"Yinlu",
    "gn:country_code":"CN",
    "gn:dem":1851,
    "gn:feature_class":"P",
    "gn:feature_code":"PPL",
    "gn:name":"Yinlu",
    "gn:population":0,
    "gn:timezone":"Asia/Shanghai",
    "iso:country":"CN",
    "name:zho_x_preferred":[
        "\u6bb7\u9c81"
    ],
    "wof:name":"Yinlu",
    "wof:placetype":"locality"
},
  "geometry": {"coordinates":[103.123,35.7386],"type":"Point"}
}