{
  "type": "Feature",
  "properties": {
    "gn:admin1_code":"11",
    "gn:asciiname":"Sheshandong",
    "gn:country_code":"CN",
    "gn:dem":908,
    "gn:feature_class":"P",
    "gn:feature_code":"PPL",
    "gn:name":"Sheshandong",
    "gn:population":0,
    "gn:timezone":"Asia/Shanghai",
    "iso:country":"CN",
    "name:zho_x_preferred":[
        "\u793e\u5c71\u6d1e"
    ],
    "wof:name":"Sheshandong",
    "wof:placetype":"locality"
},
  "geometry": {"coordinates":[111.8528,25.21147],"type":"Point"}
}