{
  "type": "Feature",
  "properties": {
    "gn:admin1_code":"19.0",
    "gn:asciiname":"Wazigoucun",
    "gn:country_code":"CN",
    "gn:dem":580,
    "gn:feature_class":"P",
    "gn:feature_code":"PPL",
    "gn:name":"Wazigoucun",
    "gn:population":0,
    "gn:timezone":"Asia/Shanghai",
    "iso:country":"CN",
    "name:zho_x_preferred":[
        "\u6d3c\u5b50\u6c9f\u6751"
    ],
    "wof:name":"Wazigoucun",
    "wof:placetype":"locality"
},
  "geometry": {"coordinates":[119.45713000000001,41.69709],"type":"Point"}
}