{
  "type": "Feature",
  "properties": {
    "gn:admin1_code":"30",
    "gn:asciiname":"Cangbancun",
    "gn:country_code":"CN",
    "gn:dem":69,
    "gn:feature_class":"P",
    "gn:feature_code":"PPL",
    "gn:name":"Cangbancun",
    "gn:population":0,
    "gn:timezone":"Asia/Urumqi",
    "iso:country":"CN",
    "name:zho_x_preferred":[
        "\u82cd\u677f\u6751"
    ],
    "wof:name":"Cangbancun",
    "wof:placetype":"locality"
},
  "geometry": {"coordinates":[110.68749,22.15729],"type":"Point"}
}