{
  "type": "Feature",
  "properties": {
    "gn:admin1_code":"18",
    "gn:asciiname":"Caizi Tianba",
    "gn:country_code":"CN",
    "gn:dem":1216,
    "gn:feature_class":"P",
    "gn:feature_code":"PPL",
    "gn:name":"Caizi Tianba",
    "gn:population":0,
    "gn:timezone":"Asia/Shanghai",
    "iso:country":"CN",
    "name:zho_x_preferred":[
        "\u83dc\u5b50\u7530\u575d"
    ],
    "wof:name":"Caizi Tianba",
    "wof:placetype":"locality"
},
  "geometry": {"coordinates":[106.307,26.9493],"type":"Point"}
}