{
  "type": "Feature",
  "properties": {
    "gn:admin1_code":"2.0",
    "gn:asciiname":"Qianxu",
    "gn:country_code":"CN",
    "gn:dem":21,
    "gn:feature_class":"P",
    "gn:feature_code":"PPL",
    "gn:name":"Qianxu",
    "gn:population":0,
    "gn:timezone":"Asia/Shanghai",
    "iso:country":"CN",
    "name:zho_x_preferred":[
        "\u94b1\u5f90"
    ],
    "wof:name":"Qianxu",
    "wof:placetype":"locality"
},
  "geometry": {"coordinates":[120.99518999999999,28.8625],"type":"Point"}
}