{
  "type": "Feature",
  "properties": {
    "gn:admin1_code":"8.0",
    "gn:asciiname":"Dapandaocun",
    "gn:country_code":"CN",
    "gn:dem":181,
    "gn:feature_class":"P",
    "gn:feature_code":"PPL",
    "gn:name":"Dapandaocun",
    "gn:population":0,
    "gn:timezone":"Asia/Shanghai",
    "iso:country":"CN",
    "name:zho_x_preferred":[
        "\u5927\u76d8\u9053\u6751"
    ],
    "wof:name":"Dapandaocun",
    "wof:placetype":"locality"
},
  "geometry": {"coordinates":[130.05945,45.63936],"type":"Point"}
}