{
  "type": "Feature",
  "properties": {
    "gn:admin1_code":"24",
    "gn:asciiname":"Shunhua",
    "gn:cc2":"CN",
    "gn:country_code":"CN",
    "gn:dem":1164,
    "gn:feature_class":"P",
    "gn:feature_code":"PPL",
    "gn:name":"Shunhua",
    "gn:population":0,
    "gn:timezone":"Asia/Shanghai",
    "iso:country":"CN",
    "name:und_x_variant":[
        "Shun-hua-ts\u2019un",
        "Shunhua"
    ],
    "wof:name":"Shunhua",
    "wof:placetype":"locality"
},
  "geometry": {"coordinates":[113.30777999999999,37.71],"type":"Point"}
}