{
  "type": "Feature",
  "properties": {
    "gn:admin1_code":"32.0",
    "gn:asciiname":"Gaohekan",
    "gn:country_code":"CN",
    "gn:dem":510,
    "gn:feature_class":"P",
    "gn:feature_code":"PPL",
    "gn:name":"Gaohekan",
    "gn:population":0,
    "gn:timezone":"Asia/Shanghai",
    "iso:country":"CN",
    "name:zho_x_preferred":[
        "\u9ad8\u6cb3\u574e"
    ],
    "wof:name":"Gaohekan",
    "wof:placetype":"locality"
},
  "geometry": {"coordinates":[103.553,29.9685],"type":"Point"}
}