{
  "type": "Feature",
  "properties": {
    "gn:admin1_code":"3.0",
    "gn:asciiname":"Yandao",
    "gn:country_code":"CN",
    "gn:dem":88,
    "gn:feature_class":"P",
    "gn:feature_code":"PPL",
    "gn:name":"Yandao",
    "gn:population":0,
    "gn:timezone":"Asia/Shanghai",
    "iso:country":"CN",
    "name:zho_x_preferred":[
        "\u70df\u5230"
    ],
    "wof:name":"Yandao",
    "wof:placetype":"locality"
},
  "geometry": {"coordinates":[114.804,27.9362],"type":"Point"}
}