{
  "type": "Feature",
  "properties": {
    "gn:admin1_code":"10.0",
    "gn:asciiname":"Nanjiuchang",
    "gn:country_code":"CN",
    "gn:dem":953,
    "gn:feature_class":"P",
    "gn:feature_code":"PPL",
    "gn:name":"Nanjiuchang",
    "gn:population":0,
    "gn:timezone":"Asia/Shanghai",
    "iso:country":"CN",
    "name:zho_x_preferred":[
        "\u5357\u4e5d\u573a"
    ],
    "wof:name":"Nanjiuchang",
    "wof:placetype":"locality"
},
  "geometry": {"coordinates":[114.63006,40.55843],"type":"Point"}
}