{
  "type": "Feature",
  "properties": {
    "gn:admin1_code":"15.0",
    "gn:asciiname":"Hongliugou",
    "gn:country_code":"CN",
    "gn:dem":1773,
    "gn:feature_class":"P",
    "gn:feature_code":"PPL",
    "gn:name":"Hongliugou",
    "gn:population":0,
    "gn:timezone":"Asia/Shanghai",
    "iso:country":"CN",
    "name:zho_x_preferred":[
        "\u7ea2\u67f3\u6c9f"
    ],
    "wof:name":"Hongliugou",
    "wof:placetype":"locality"
},
  "geometry": {"coordinates":[98.09310000000001,39.8385],"type":"Point"}
}