{
  "type": "Feature",
  "properties": {
    "gn:admin1_code":"24.0",
    "gn:asciiname":"Sanghouyu",
    "gn:country_code":"CN",
    "gn:dem":1195,
    "gn:feature_class":"P",
    "gn:feature_code":"PPL",
    "gn:name":"Sanghouyu",
    "gn:population":0,
    "gn:timezone":"Asia/Shanghai",
    "iso:country":"CN",
    "name:zho_x_preferred":[
        "\u6851\u540e\u5cea"
    ],
    "wof:name":"Sanghouyu",
    "wof:placetype":"locality"
},
  "geometry": {"coordinates":[111.38413,37.01312],"type":"Point"}
}