{
  "type": "Feature",
  "properties": {
    "gn:admin1_code":"29.0",
    "gn:asciiname":"Weiping",
    "gn:country_code":"CN",
    "gn:dem":1297,
    "gn:feature_class":"P",
    "gn:feature_code":"PPL",
    "gn:name":"Weiping",
    "gn:population":0,
    "gn:timezone":"Asia/Shanghai",
    "iso:country":"CN",
    "name:zho_x_preferred":[
        "\u536b\u5e73"
    ],
    "wof:name":"Weiping",
    "wof:placetype":"locality"
},
  "geometry": {"coordinates":[100.36,23.9147],"type":"Point"}
}