{
  "type": "Feature",
  "properties": {
    "gn:admin1_code":"26.0",
    "gn:asciiname":"Yujiecun",
    "gn:country_code":"CN",
    "gn:dem":486,
    "gn:feature_class":"P",
    "gn:feature_code":"PPL",
    "gn:name":"Yujiecun",
    "gn:population":0,
    "gn:timezone":"Asia/Shanghai",
    "iso:country":"CN",
    "name:zho_x_preferred":[
        "\u4f59\u59d0\u6751"
    ],
    "wof:name":"Yujiecun",
    "wof:placetype":"locality"
},
  "geometry": {"coordinates":[108.83638000000001,32.79918],"type":"Point"}
}