{
  "type": "Feature",
  "properties": {
    "gn:admin1_code":"22.0",
    "gn:asciiname":"Wanggezhuangcun",
    "gn:country_code":"CN",
    "gn:dem":40,
    "gn:feature_class":"P",
    "gn:feature_code":"PPL",
    "gn:name":"Wanggezhuangcun",
    "gn:population":0,
    "gn:timezone":"Asia/Shanghai",
    "iso:country":"CN",
    "name:zho_x_preferred":[
        "\u738b\u5404\u5e84\u6751"
    ],
    "wof:name":"Wanggezhuangcun",
    "wof:placetype":"locality"
},
  "geometry": {"coordinates":[116.80181,40.07014],"type":"Point"}
}