{
  "type": "Feature",
  "properties": {
    "gn:admin1_code":"3.0",
    "gn:asciiname":"Banqian Liujia",
    "gn:country_code":"CN",
    "gn:dem":65,
    "gn:feature_class":"P",
    "gn:feature_code":"PPL",
    "gn:name":"Banqian Liujia",
    "gn:population":0,
    "gn:timezone":"Asia/Shanghai",
    "iso:country":"CN",
    "name:zho_x_preferred":[
        "\u5742\u524d\u5218\u5bb6"
    ],
    "wof:name":"Banqian Liujia",
    "wof:placetype":"locality"
},
  "geometry": {"coordinates":[117.62557,28.31018],"type":"Point"}
}