{
  "type": "Feature",
  "properties": {
    "gn:admin1_code":"29.0",
    "gn:asciiname":"Zhanmatian",
    "gn:country_code":"CN",
    "gn:dem":1572,
    "gn:feature_class":"P",
    "gn:feature_code":"PPL",
    "gn:name":"Zhanmatian",
    "gn:population":0,
    "gn:timezone":"Asia/Shanghai",
    "iso:country":"CN",
    "name:zho_x_preferred":[
        "\u5360\u9a6c\u7530"
    ],
    "wof:name":"Zhanmatian",
    "wof:placetype":"locality"
},
  "geometry": {"coordinates":[103.54300000000001,24.4529],"type":"Point"}
}