{
  "type": "Feature",
  "properties": {
    "gn:admin1_code":"14",
    "gn:asciiname":"Xuemai",
    "gn:country_code":"CN",
    "gn:dem":4141,
    "gn:feature_class":"P",
    "gn:feature_code":"PPL",
    "gn:name":"Xuemai",
    "gn:population":0,
    "gn:timezone":"Asia/Urumqi",
    "iso:country":"CN",
    "name:zho_x_preferred":[
        "\u96ea\u9ea6"
    ],
    "wof:name":"Xuemai",
    "wof:placetype":"locality"
},
  "geometry": {"coordinates":[89.2925,28.877],"type":"Point"}
}