{
  "type": "Feature",
  "properties": {
    "gn:admin1_code":"10",
    "gn:asciiname":"Shuangtang",
    "gn:cc2":"CN",
    "gn:country_code":"CN",
    "gn:dem":9,
    "gn:feature_class":"P",
    "gn:feature_code":"PPL",
    "gn:name":"Shuangtang",
    "gn:population":0,
    "gn:timezone":"Asia/Shanghai",
    "iso:country":"CN",
    "name:und_x_variant":[
        "Shuang-t\u2019ang-chen",
        "Shuangtang"
    ],
    "wof:name":"Shuangtang",
    "wof:placetype":"locality"
},
  "geometry": {"coordinates":[116.27861,39.05722],"type":"Point"}
}