{
  "type": "Feature",
  "properties": {
    "gn:admin1_code":"4.0",
    "gn:asciiname":"Xinan",
    "gn:country_code":"CN",
    "gn:dem":6,
    "gn:feature_class":"P",
    "gn:feature_code":"PPL",
    "gn:name":"Xinan",
    "gn:population":0,
    "gn:timezone":"Asia/Shanghai",
    "iso:country":"CN",
    "name:ceb_x_preferred":[
        "Xinan"
    ],
    "name:deu_x_preferred":[
        "Xinan"
    ],
    "name:swe_x_preferred":[
        "Xinan"
    ],
    "name:zho_x_preferred":[
        "\u6eaa\u5357"
    ],
    "wof:name":"Xinan",
    "wof:placetype":"locality"
},
  "geometry": {"coordinates":[120.18254,32.21165999999999],"type":"Point"}
}