{
  "type": "Feature",
  "properties": {
    "gn:admin1_code":"7.0",
    "gn:asciiname":"Rudi",
    "gn:country_code":"CN",
    "gn:dem":390,
    "gn:feature_class":"P",
    "gn:feature_code":"PPL",
    "gn:name":"Rudi",
    "gn:population":0,
    "gn:timezone":"Asia/Shanghai",
    "iso:country":"CN",
    "name:und_x_variant":[
        "\u5112\u5730"
    ],
    "name:zho_x_preferred":[
        "\u5112\u5730"
    ],
    "wof:name":"Rudi",
    "wof:placetype":"locality"
},
  "geometry": {"coordinates":[116.78745000000001,26.45104000000001],"type":"Point"}
}