{
  "type": "Feature",
  "properties": {
    "gn:admin1_code":"9.0",
    "gn:asciiname":"Wangtang",
    "gn:country_code":"CN",
    "gn:dem":206,
    "gn:feature_class":"P",
    "gn:feature_code":"PPL",
    "gn:name":"Wangtang",
    "gn:population":0,
    "gn:timezone":"Asia/Shanghai",
    "iso:country":"CN",
    "name:nld_x_preferred":[
        "Wangtang"
    ],
    "name:zho_x_preferred":[
        "\u738b\u5802"
    ],
    "wof:name":"Wangtang",
    "wof:placetype":"locality"
},
  "geometry": {"coordinates":[111.75069000000001,33.18271],"type":"Point"}
}