{
  "type": "Feature",
  "properties": {
    "gn:admin1_code":"8.0",
    "gn:asciiname":"Geming Qidui",
    "gn:country_code":"CN",
    "gn:dem":292,
    "gn:feature_class":"P",
    "gn:feature_code":"PPLF",
    "gn:name":"Geming Qidui",
    "gn:population":0,
    "gn:timezone":"Asia/Shanghai",
    "iso:country":"CN",
    "name:zho_x_preferred":[
        "\u9769\u547d\u4e03\u961f"
    ],
    "wof:name":"Geming Qidui",
    "wof:placetype":"locality"
},
  "geometry": {"coordinates":[125.15053,48.71585],"type":"Point"}
}