{
  "type": "Feature",
  "properties": {
    "gn:admin1_code":"32.0",
    "gn:asciiname":"Zhangjia Yanjiao",
    "gn:country_code":"CN",
    "gn:dem":955,
    "gn:feature_class":"P",
    "gn:feature_code":"PPL",
    "gn:name":"Zhangjia Yanjiao",
    "gn:population":0,
    "gn:timezone":"Asia/Shanghai",
    "iso:country":"CN",
    "name:zho_x_preferred":[
        "\u5f20\u5bb6\u5ca9\u811a"
    ],
    "wof:name":"Zhangjia Yanjiao",
    "wof:placetype":"locality"
},
  "geometry": {"coordinates":[108.29671999999999,32.11672],"type":"Point"}
}