{
  "type": "Feature",
  "properties": {
    "gn:admin1_code":"3",
    "gn:asciiname":"Longfu'an",
    "gn:country_code":"CN",
    "gn:dem":309,
    "gn:feature_class":"P",
    "gn:feature_code":"PPL",
    "gn:name":"Longfu\u2019an",
    "gn:population":0,
    "gn:timezone":"Asia/Shanghai",
    "iso:country":"CN",
    "name:und_x_variant":[
        "Longfu\u2019an"
    ],
    "name:zho_x_preferred":[
        "\u9f99\u798f\u5eb5"
    ],
    "wof:name":"Longfu'an",
    "wof:placetype":"locality"
},
  "geometry": {"coordinates":[114.416,25.4602],"type":"Point"}
}