{
  "type": "Feature",
  "properties": {
    "gn:admin1_code":"32.0",
    "gn:asciiname":"Shangre'er",
    "gn:country_code":"CN",
    "gn:dem":3580,
    "gn:feature_class":"P",
    "gn:feature_code":"PPL",
    "gn:name":"Shangre\u2019er",
    "gn:population":0,
    "gn:timezone":"Asia/Shanghai",
    "iso:country":"CN",
    "name:und_x_variant":[
        "Shangre\u2019er"
    ],
    "name:zho_x_preferred":[
        "\u4e0a\u70ed\u5c14"
    ],
    "wof:name":"Shangre'er",
    "wof:placetype":"locality"
},
  "geometry": {"coordinates":[102.974,33.9129],"type":"Point"}
}