{
  "type": "Feature",
  "properties": {
    "gn:admin1_code":"12.0",
    "gn:asciiname":"Tudishu",
    "gn:country_code":"CN",
    "gn:dem":126,
    "gn:feature_class":"P",
    "gn:feature_code":"PPL",
    "gn:name":"Tudishu",
    "gn:population":0,
    "gn:timezone":"Asia/Shanghai",
    "iso:country":"CN",
    "name:zho_x_preferred":[
        "\u571f\u5730\u6811"
    ],
    "wof:name":"Tudishu",
    "wof:placetype":"locality"
},
  "geometry": {"coordinates":[113.73575,29.24413],"type":"Point"}
}