{
  "type": "Feature",
  "properties": {
    "gn:admin1_code":"10.0",
    "gn:asciiname":"Ximen",
    "gn:country_code":"CN",
    "gn:dem":61,
    "gn:feature_class":"P",
    "gn:feature_code":"PPL",
    "gn:name":"Ximen",
    "gn:population":0,
    "gn:timezone":"Asia/Shanghai",
    "iso:country":"CN",
    "name:und_x_variant":[
        "\u897f\u95e8"
    ],
    "name:zho_x_preferred":[
        "\u897f\u9580\u59d3"
    ],
    "wof:name":"Ximen",
    "wof:placetype":"locality"
},
  "geometry": {"coordinates":[114.80888,38.25473],"type":"Point"}
}