{
  "type": "Feature",
  "properties": {
    "gn:admin1_code":"8.0",
    "gn:asciiname":"Liulipenyao",
    "gn:country_code":"CN",
    "gn:dem":232,
    "gn:feature_class":"P",
    "gn:feature_code":"PPL",
    "gn:name":"Liulipenyao",
    "gn:population":0,
    "gn:timezone":"Asia/Shanghai",
    "iso:country":"CN",
    "name:zho_x_preferred":[
        "\u7409\u7483\u76c6\u7a91"
    ],
    "wof:name":"Liulipenyao",
    "wof:placetype":"locality"
},
  "geometry": {"coordinates":[126.4374,47.50518],"type":"Point"}
}