{
  "type": "Feature",
  "properties": {
    "gn:admin1_code":"32.0",
    "gn:asciiname":"Cilingou",
    "gn:country_code":"CN",
    "gn:dem":358,
    "gn:feature_class":"P",
    "gn:feature_code":"PPL",
    "gn:name":"Cilingou",
    "gn:population":0,
    "gn:timezone":"Asia/Shanghai",
    "iso:country":"CN",
    "name:zho_x_preferred":[
        "\u523a\u6797\u6c9f"
    ],
    "wof:name":"Cilingou",
    "wof:placetype":"locality"
},
  "geometry": {"coordinates":[104.316,29.3958],"type":"Point"}
}