{
  "type": "Feature",
  "properties": {
    "gn:admin1_code":"9.0",
    "gn:asciiname":"Malin",
    "gn:country_code":"CN",
    "gn:dem":87,
    "gn:feature_class":"P",
    "gn:feature_code":"PPL",
    "gn:name":"Malin",
    "gn:population":0,
    "gn:timezone":"Asia/Shanghai",
    "iso:country":"CN",
    "name:bel_x_preferred":[
        "\u041c\u0430\u043b\u0456\u043d"
    ],
    "name:ceb_x_preferred":[
        "Malin"
    ],
    "name:ces_x_preferred":[
        "Mal\u00edn"
    ],
    "name:deu_x_preferred":[
        "Malin"
    ],
    "name:fas_x_preferred":[
        "\u0645\u0627\u0644\u06cc\u0646"
    ],
    "name:heb_x_preferred":[
        "\u05de\u05d0\u05dc\u05d9\u05df"
    ],
    "name:hun_x_preferred":[
        "Malin"
    ],
    "name:ita_x_preferred":[
        "Malin"
    ],
    "name:nld_x_preferred":[
        "Malin"
    ],
    "name:pol_x_preferred":[
        "Malin"
    ],
    "name:rus_x_preferred":[
        "\u041c\u0430\u043b\u0438\u043d"
    ],
    "name:swe_x_preferred":[
        "Malin"
    ],
    "name:ukr_x_preferred":[
        "\u041c\u0430\u043b\u0438\u043d"
    ],
    "name:zho_x_preferred":[
        "\u9a6c\u6797"
    ],
    "wof:name":"Malin",
    "wof:placetype":"locality"
},
  "geometry": {"coordinates":[113.74811,34.8394],"type":"Point"}
}