{
  "type": "Feature",
  "properties": {
    "gn:admin1_code":"19.0",
    "gn:asciiname":"Niujiagou",
    "gn:country_code":"CN",
    "gn:dem":187,
    "gn:feature_class":"P",
    "gn:feature_code":"PPL",
    "gn:name":"Niujiagou",
    "gn:population":0,
    "gn:timezone":"Asia/Shanghai",
    "iso:country":"CN",
    "name:zho_x_preferred":[
        "\u725b\u5bb6\u6c9f"
    ],
    "wof:name":"Niujiagou",
    "wof:placetype":"locality"
},
  "geometry": {"coordinates":[123.295,42.5772],"type":"Point"}
}