{
  "type": "Feature",
  "properties": {
    "gn:admin1_code":"30.0",
    "gn:asciiname":"Taihucun",
    "gn:country_code":"CN",
    "gn:dem":126,
    "gn:feature_class":"P",
    "gn:feature_code":"PPL",
    "gn:name":"Taihucun",
    "gn:population":0,
    "gn:timezone":"Asia/Shanghai",
    "iso:country":"CN",
    "name:zho_x_preferred":[
        "\u592a\u6e56\u6751"
    ],
    "wof:name":"Taihucun",
    "wof:placetype":"locality"
},
  "geometry": {"coordinates":[115.93026999999999,24.05648],"type":"Point"}
}