{
  "type": "Feature",
  "properties": {
    "gn:admin1_code":"30.0",
    "gn:asciiname":"Qianhe",
    "gn:country_code":"CN",
    "gn:dem":377,
    "gn:feature_class":"P",
    "gn:feature_code":"PPL",
    "gn:name":"Qianhe",
    "gn:population":0,
    "gn:timezone":"Asia/Urumqi",
    "iso:country":"CN",
    "name:zho_x_preferred":[
        "\u4e7e\u548c"
    ],
    "wof:name":"Qianhe",
    "wof:placetype":"locality"
},
  "geometry": {"coordinates":[110.85129999999999,22.45129],"type":"Point"}
}