{
  "type": "Feature",
  "properties": {
    "gn:admin1_code":"33.0",
    "gn:asciiname":"Wailang",
    "gn:country_code":"CN",
    "gn:dem":205,
    "gn:feature_class":"P",
    "gn:feature_code":"PPLA4",
    "gn:name":"Wailang",
    "gn:population":0,
    "gn:timezone":"Asia/Shanghai",
    "iso:country":"CN",
    "name:und_x_variant":[
        "Wailang Xiang"
    ],
    "name:zho_x_preferred":[
        "\u5916\u6717"
    ],
    "name:zho_x_variant":[
        "\u5916\u6717\u4e61"
    ],
    "wof:name":"Wailang",
    "wof:placetype":"locality"
},
  "geometry": {"coordinates":[108.76611,30.77467],"type":"Point"}
}