{
  "type": "Feature",
  "properties": {
    "gn:admin1_code":"19",
    "gn:asciiname":"Tung-hu-lu-tou",
    "gn:country_code":"CN",
    "gn:dem":486,
    "gn:feature_class":"P",
    "gn:feature_code":"PPL",
    "gn:name":"Tung-hu-lu-tou",
    "gn:population":0,
    "gn:timezone":"Asia/Shanghai",
    "iso:country":"CN",
    "wof:name":"Tung-hu-lu-tou",
    "wof:placetype":"locality"
},
  "geometry": {"coordinates":[125.11388999999998,41.48278],"type":"Point"}
}