{
  "type": "Feature",
  "properties": {
    "gn:admin1_code":"10",
    "gn:asciiname":"Yingpan",
    "gn:country_code":"CN",
    "gn:dem":18,
    "gn:feature_class":"P",
    "gn:feature_code":"PPL",
    "gn:name":"Yingpan",
    "gn:population":0,
    "gn:timezone":"Asia/Shanghai",
    "iso:country":"CN",
    "name:ceb_x_preferred":[
        "Yingpan"
    ],
    "name:deu_x_preferred":[
        "Yingpan"
    ],
    "name:swe_x_preferred":[
        "Yingpan"
    ],
    "name:zho_x_preferred":[
        "\u8425\u76d8"
    ],
    "name:zho_x_variant":[
        "\u8425\u76d8\u9547"
    ],
    "wof:name":"Yingpan",
    "wof:placetype":"locality"
},
  "geometry": {"coordinates":[116.35391,37.8803],"type":"Point"}
}