{
  "type": "Feature",
  "properties": {
    "gn:admin1_code":"12.0",
    "gn:asciiname":"Zhonghuitai",
    "gn:country_code":"CN",
    "gn:dem":32,
    "gn:feature_class":"P",
    "gn:feature_code":"PPL",
    "gn:name":"Zhonghuitai",
    "gn:population":0,
    "gn:timezone":"Asia/Shanghai",
    "iso:country":"CN",
    "name:zho_x_preferred":[
        "\u4e2d\u7070\u53f0"
    ],
    "wof:name":"Zhonghuitai",
    "wof:placetype":"locality"
},
  "geometry": {"coordinates":[112.64104,30.49047],"type":"Point"}
}