{
  "type": "Feature",
  "properties": {
    "gn:admin1_code":"19.0",
    "gn:asciiname":"Lagu",
    "gn:country_code":"CN",
    "gn:dem":65,
    "gn:feature_class":"P",
    "gn:feature_code":"PPL",
    "gn:name":"Lagu",
    "gn:population":0,
    "gn:timezone":"Asia/Shanghai",
    "iso:country":"CN",
    "name:rus_x_preferred":[
        "\u041b\u0430\u0433\u0443"
    ],
    "name:und_x_variant":[
        "\u62c9\u53e4"
    ],
    "wof:name":"Lagu",
    "wof:placetype":"locality"
},
  "geometry": {"coordinates":[122.72964,40.75825],"type":"Point"}
}