{
  "type": "Feature",
  "properties": {
    "gn:admin1_code":"18",
    "gn:asciiname":"Banmianjie",
    "gn:country_code":"CN",
    "gn:dem":1179,
    "gn:feature_class":"P",
    "gn:feature_code":"PPL",
    "gn:name":"Banmianjie",
    "gn:population":0,
    "gn:timezone":"Asia/Shanghai",
    "iso:country":"CN",
    "name:zho_x_preferred":[
        "\u534a\u9762\u8857"
    ],
    "wof:name":"Banmianjie",
    "wof:placetype":"locality"
},
  "geometry": {"coordinates":[105.764,26.907],"type":"Point"}
}