{
  "type": "Feature",
  "properties": {
    "gn:admin1_code":"19.0",
    "gn:asciiname":"Tazigou",
    "gn:country_code":"CN",
    "gn:dem":232,
    "gn:feature_class":"P",
    "gn:feature_code":"PPL",
    "gn:name":"Tazigou",
    "gn:population":0,
    "gn:timezone":"Asia/Shanghai",
    "iso:country":"CN",
    "name:und_x_variant":[
        "\u5854\u5b50\u6c9f"
    ],
    "name:zho_x_preferred":[
        "\u5854\u5b50\u6c9f"
    ],
    "wof:name":"Tazigou",
    "wof:placetype":"locality"
},
  "geometry": {"coordinates":[121.75905,41.98557],"type":"Point"}
}