{
  "type": "Feature",
  "properties": {
    "gn:admin1_code":"16",
    "gn:asciiname":"Hecangshi",
    "gn:country_code":"CN",
    "gn:dem":1332,
    "gn:feature_class":"P",
    "gn:feature_code":"PPL",
    "gn:name":"Hecangshi",
    "gn:population":0,
    "gn:timezone":"Asia/Shanghai",
    "iso:country":"CN",
    "name:zho_x_preferred":[
        "\u79be\u4ed3\u77f3"
    ],
    "wof:name":"Hecangshi",
    "wof:placetype":"locality"
},
  "geometry": {"coordinates":[110.953,25.6457],"type":"Point"}
}