{
  "type": "Feature",
  "properties": {
    "gn:admin1_code":"19.0",
    "gn:asciiname":"Baiqicun",
    "gn:country_code":"CN",
    "gn:dem":339,
    "gn:feature_class":"P",
    "gn:feature_code":"PPL",
    "gn:name":"Baiqicun",
    "gn:population":0,
    "gn:timezone":"Asia/Shanghai",
    "iso:country":"CN",
    "name:und_x_variant":[
        "Pai-ch\u2019i-p\u2019u"
    ],
    "name:zho_x_preferred":[
        "\u767d\u65d7\u6751"
    ],
    "wof:name":"Baiqicun",
    "wof:placetype":"locality"
},
  "geometry": {"coordinates":[125.10635000000001,41.70571],"type":"Point"}
}