{
  "type": "Feature",
  "properties": {
    "gn:admin1_code":"15.0",
    "gn:asciiname":"Laofenchang",
    "gn:country_code":"CN",
    "gn:dem":1296,
    "gn:feature_class":"P",
    "gn:feature_code":"PPL",
    "gn:name":"Laofenchang",
    "gn:population":0,
    "gn:timezone":"Asia/Shanghai",
    "iso:country":"CN",
    "name:zho_x_preferred":[
        "\u8001\u5206\u573a"
    ],
    "wof:name":"Laofenchang",
    "wof:placetype":"locality"
},
  "geometry": {"coordinates":[108.363,36.2213],"type":"Point"}
}