{
  "type": "Feature",
  "properties": {
    "gn:admin1_code":"11.0",
    "gn:asciiname":"Zijiatang",
    "gn:country_code":"CN",
    "gn:dem":94,
    "gn:feature_class":"P",
    "gn:feature_code":"PPL",
    "gn:name":"Zijiatang",
    "gn:population":0,
    "gn:timezone":"Asia/Shanghai",
    "iso:country":"CN",
    "name:zho_x_preferred":[
        "\u8d44\u5bb6\u5858"
    ],
    "wof:name":"Zijiatang",
    "wof:placetype":"locality"
},
  "geometry": {"coordinates":[112.6437,26.37124],"type":"Point"}
}