{
  "type": "Feature",
  "properties": {
    "gn:admin1_code":"7.0",
    "gn:asciiname":"Jiewen",
    "gn:country_code":"CN",
    "gn:dem":539,
    "gn:feature_class":"P",
    "gn:feature_code":"PPL",
    "gn:name":"Jiewen",
    "gn:population":0,
    "gn:timezone":"Asia/Shanghai",
    "iso:country":"CN",
    "name:zho_x_preferred":[
        "\u6377\u6587"
    ],
    "wof:name":"Jiewen",
    "wof:placetype":"locality"
},
  "geometry": {"coordinates":[116.04787,25.1717],"type":"Point"}
}