{
  "type": "Feature",
  "properties": {
    "gn:admin1_code":"3.0",
    "gn:asciiname":"Tangkouzhujia",
    "gn:country_code":"CN",
    "gn:dem":17,
    "gn:feature_class":"P",
    "gn:feature_code":"PPL",
    "gn:name":"Tangkouzhujia",
    "gn:population":0,
    "gn:timezone":"Asia/Shanghai",
    "iso:country":"CN",
    "name:und_x_variant":[
        "\u5858\u53e3\u6731\u5bb6"
    ],
    "wof:name":"Tangkouzhujia",
    "wof:placetype":"locality"
},
  "geometry": {"coordinates":[116.25234,28.6982],"type":"Point"}
}