{
  "type": "Feature",
  "properties": {
    "gn:admin1_code":"4.0",
    "gn:asciiname":"Zhangdazhuang",
    "gn:country_code":"CN",
    "gn:dem":21,
    "gn:feature_class":"P",
    "gn:feature_code":"PPL",
    "gn:name":"Zhangdazhuang",
    "gn:population":0,
    "gn:timezone":"Asia/Shanghai",
    "iso:country":"CN",
    "name:zho_x_preferred":[
        "\u5f20\u5927\u5e84"
    ],
    "wof:name":"Zhangdazhuang",
    "wof:placetype":"locality"
},
  "geometry": {"coordinates":[118.51000000000001,34.0522],"type":"Point"}
}