{
  "type": "Feature",
  "properties": {
    "gn:admin1_code":"4.0",
    "gn:asciiname":"Beipingcun",
    "gn:country_code":"CN",
    "gn:dem":3,
    "gn:feature_class":"P",
    "gn:feature_code":"PPL",
    "gn:name":"Beipingcun",
    "gn:population":0,
    "gn:timezone":"Asia/Shanghai",
    "iso:country":"CN",
    "name:zho_x_preferred":[
        "\u5317\u5c4f\u6751"
    ],
    "wof:name":"Beipingcun",
    "wof:placetype":"locality"
},
  "geometry": {"coordinates":[119.74487000000001,32.79132],"type":"Point"}
}