{
  "type": "Feature",
  "properties": {
    "gn:admin1_code":"25",
    "gn:asciiname":"Xiaoguojia",
    "gn:country_code":"CN",
    "gn:dem":9,
    "gn:feature_class":"P",
    "gn:feature_code":"PPL",
    "gn:name":"Xiaoguojia",
    "gn:population":0,
    "gn:timezone":"Asia/Shanghai",
    "iso:country":"CN",
    "name:zho_x_preferred":[
        "\u5c0f\u90ed\u5bb6"
    ],
    "wof:name":"Xiaoguojia",
    "wof:placetype":"locality"
},
  "geometry": {"coordinates":[117.578,37.7868],"type":"Point"}
}