{
  "type": "Feature",
  "properties": {
    "gn:admin1_code":"11.0",
    "gn:asciiname":"Chuanzigou",
    "gn:country_code":"CN",
    "gn:dem":506,
    "gn:feature_class":"P",
    "gn:feature_code":"PPL",
    "gn:name":"Chuanzigou",
    "gn:population":0,
    "gn:timezone":"Asia/Shanghai",
    "iso:country":"CN",
    "name:zho_x_preferred":[
        "Chuanzigou"
    ],
    "name:zho_x_variant":[
        "\u5ddd\u5b50\u6c9f"
    ],
    "wof:name":"Chuanzigou",
    "wof:placetype":"locality"
},
  "geometry": {"coordinates":[111.09893,29.88698],"type":"Point"}
}