{
  "type": "Feature",
  "properties": {
    "gn:admin1_code":"19",
    "gn:asciiname":"Wangluodi",
    "gn:country_code":"CN",
    "gn:dem":533,
    "gn:feature_class":"P",
    "gn:feature_code":"PPL",
    "gn:name":"Wangluodi",
    "gn:population":0,
    "gn:timezone":"Asia/Shanghai",
    "iso:country":"CN",
    "name:und_x_variant":[
        "Qingfengshan"
    ],
    "name:zho_x_preferred":[
        "\u738b\u6d1b\u5730"
    ],
    "name:zho_x_variant":[
        "\u9752\u5cf0\u5c71\u9547"
    ],
    "wof:name":"Wangluodi",
    "wof:placetype":"locality"
},
  "geometry": {"coordinates":[119.58565,41.50095],"type":"Point"}
}