{
  "type": "Feature",
  "properties": {
    "gn:admin1_code":"24.0",
    "gn:asciiname":"Xiaobaiyangwa",
    "gn:country_code":"CN",
    "gn:dem":1434,
    "gn:feature_class":"P",
    "gn:feature_code":"PPL",
    "gn:name":"Xiaobaiyangwa",
    "gn:population":0,
    "gn:timezone":"Asia/Shanghai",
    "iso:country":"CN",
    "name:und_x_variant":[
        "\u5c0f\u767d\u7f8a\u6d3c"
    ],
    "name:zho_x_preferred":[
        "\u5c0f\u767d\u7f8a\u6d3c"
    ],
    "wof:name":"Xiaobaiyangwa",
    "wof:placetype":"locality"
},
  "geometry": {"coordinates":[112.24858999999999,39.57182],"type":"Point"}
}