{
  "type": "Feature",
  "properties": {
    "gn:admin1_code":"6.0",
    "gn:asciiname":"Qiancang",
    "gn:country_code":"CN",
    "gn:dem":2634,
    "gn:feature_class":"P",
    "gn:feature_code":"PPL",
    "gn:name":"Qiancang",
    "gn:population":0,
    "gn:timezone":"Asia/Shanghai",
    "iso:country":"CN",
    "name:zho_x_preferred":[
        "\u5343\u85cf"
    ],
    "wof:name":"Qiancang",
    "wof:placetype":"locality"
},
  "geometry": {"coordinates":[101.92017,35.98652],"type":"Point"}
}