{
  "type": "Feature",
  "properties": {
    "gn:admin1_code":"15.0",
    "gn:asciiname":"Gongqiaoyuan",
    "gn:country_code":"CN",
    "gn:dem":1499,
    "gn:feature_class":"P",
    "gn:feature_code":"PPL",
    "gn:name":"Gongqiaoyuan",
    "gn:population":0,
    "gn:timezone":"Asia/Shanghai",
    "iso:country":"CN",
    "name:zho_x_preferred":[
        "\u62f1\u6865\u586c"
    ],
    "wof:name":"Gongqiaoyuan",
    "wof:placetype":"locality"
},
  "geometry": {"coordinates":[108.07599999999999,36.3035],"type":"Point"}
}