{
  "type": "Feature",
  "properties": {
    "gn:admin1_code":"07",
    "gn:asciiname":"Hetian",
    "gn:country_code":"CN",
    "gn:dem":280,
    "gn:feature_class":"P",
    "gn:feature_code":"PPLA4",
    "gn:name":"Hetian",
    "gn:population":0,
    "gn:timezone":"Asia/Shanghai",
    "iso:country":"CN",
    "name:und_x_variant":[
        "Ho-t\u2019ien-hs\u00fcn",
        "Hotein",
        "Ho-t\u2019ien",
        "Hetian",
        "\u6cb3\u7530",
        "Hetian Zhen",
        "\u6cb3\u7530\u9547"
    ],
    "wof:name":"Hetian",
    "wof:placetype":"locality"
},
  "geometry": {"coordinates":[116.41543,25.667],"type":"Point"}
}