{
  "type": "Feature",
  "properties": {
    "gn:admin1_code":"12.0",
    "gn:asciiname":"Liangjiaping",
    "gn:country_code":"CN",
    "gn:dem":1438,
    "gn:feature_class":"P",
    "gn:feature_code":"PPL",
    "gn:name":"Liangjiaping",
    "gn:population":0,
    "gn:timezone":"Asia/Shanghai",
    "iso:country":"CN",
    "name:zho_x_preferred":[
        "\u6881\u5bb6\u576a"
    ],
    "wof:name":"Liangjiaping",
    "wof:placetype":"locality"
},
  "geometry": {"coordinates":[111.00705000000001,32.21558],"type":"Point"}
}