{
  "type": "Feature",
  "properties": {
    "gn:admin1_code":"29.0",
    "gn:asciiname":"Luohei",
    "gn:country_code":"CN",
    "gn:dem":1568,
    "gn:feature_class":"P",
    "gn:feature_code":"PPL",
    "gn:name":"Luohei",
    "gn:population":0,
    "gn:timezone":"Asia/Shanghai",
    "iso:country":"CN",
    "name:zho_x_preferred":[
        "\u502e\u9ed1"
    ],
    "wof:name":"Luohei",
    "wof:placetype":"locality"
},
  "geometry": {"coordinates":[104.303,23.9766],"type":"Point"}
}