{
  "type": "Feature",
  "properties": {
    "gn:admin1_code":"24.0",
    "gn:asciiname":"Xi'antoucun",
    "gn:country_code":"CN",
    "gn:dem":360,
    "gn:feature_class":"P",
    "gn:feature_code":"PPL",
    "gn:name":"Xi\u2019antoucun",
    "gn:population":0,
    "gn:timezone":"Asia/Shanghai",
    "iso:country":"CN",
    "name:und_x_variant":[
        "Xi\u2019antoucun"
    ],
    "name:zho_x_preferred":[
        "\u897f\u5b89\u5934\u6751"
    ],
    "wof:name":"Xi'antoucun",
    "wof:placetype":"locality"
},
  "geometry": {"coordinates":[110.73522,35.0021],"type":"Point"}
}