{
  "type": "Feature",
  "properties": {
    "gn:admin1_code":"30",
    "gn:asciiname":"Baoxicun",
    "gn:country_code":"CN",
    "gn:dem":15,
    "gn:feature_class":"P",
    "gn:feature_code":"PPL",
    "gn:name":"Baoxicun",
    "gn:population":0,
    "gn:timezone":"Asia/Urumqi",
    "iso:country":"CN",
    "name:zho_x_preferred":[
        "\u5305\u897f\u6751"
    ],
    "wof:name":"Baoxicun",
    "wof:placetype":"locality"
},
  "geometry": {"coordinates":[109.9443,20.31377],"type":"Point"}
}