{
  "type": "Feature",
  "properties": {
    "gn:admin1_code":"23.0",
    "gn:asciiname":"Xishe",
    "gn:country_code":"CN",
    "gn:dem":4,
    "gn:feature_class":"P",
    "gn:feature_code":"PPL",
    "gn:name":"Xishe",
    "gn:population":0,
    "gn:timezone":"Asia/Shanghai",
    "iso:country":"CN",
    "name:zho_x_preferred":[
        "Xishe"
    ],
    "name:zho_x_variant":[
        "\u897f\u538d"
    ],
    "wof:name":"Xishe",
    "wof:placetype":"locality"
},
  "geometry": {"coordinates":[121.26262,31.15774],"type":"Point"}
}