{
  "type": "Feature",
  "properties": {
    "gn:admin1_code":"7.0",
    "gn:asciiname":"Jingshui",
    "gn:country_code":"CN",
    "gn:dem":47,
    "gn:feature_class":"P",
    "gn:feature_code":"PPL",
    "gn:name":"Jingshui",
    "gn:population":0,
    "gn:timezone":"Asia/Shanghai",
    "iso:country":"CN",
    "name:zho_x_preferred":[
        "\u4e95\u6c34"
    ],
    "wof:name":"Jingshui",
    "wof:placetype":"locality"
},
  "geometry": {"coordinates":[119.7841,26.56057],"type":"Point"}
}