{
  "type": "Feature",
  "properties": {
    "gn:admin1_code":"10",
    "gn:asciiname":"Chuanxindian",
    "gn:cc2":"CN",
    "gn:country_code":"CN",
    "gn:dem":1781,
    "gn:feature_class":"P",
    "gn:feature_code":"PPL",
    "gn:name":"Chuanxindian",
    "gn:population":0,
    "gn:timezone":"Asia/Shanghai",
    "iso:country":"CN",
    "name:und_x_variant":[
        "Ch\u2019uan-hsin-tien",
        "Chuanxindian"
    ],
    "wof:name":"Chuanxindian",
    "wof:placetype":"locality"
},
  "geometry": {"coordinates":[117.61667,42.55],"type":"Point"}
}