{
  "type": "Feature",
  "properties": {
    "gn:admin1_code":"30",
    "gn:asciiname":"Chengxiangwu",
    "gn:country_code":"CN",
    "gn:dem":125,
    "gn:feature_class":"P",
    "gn:feature_code":"PPL",
    "gn:name":"Chengxiangwu",
    "gn:population":0,
    "gn:timezone":"Asia/Shanghai",
    "iso:country":"CN",
    "name:zho_x_preferred":[
        "\u7a0b\u9999\u5c4b"
    ],
    "wof:name":"Chengxiangwu",
    "wof:placetype":"locality"
},
  "geometry": {"coordinates":[116.20605999999999,23.98114],"type":"Point"}
}