{
  "type": "Feature",
  "properties": {
    "gn:admin1_code":"19.0",
    "gn:asciiname":"Jiuhuafenchang",
    "gn:country_code":"CN",
    "gn:dem":52,
    "gn:feature_class":"P",
    "gn:feature_code":"PPL",
    "gn:name":"Jiuhuafenchang",
    "gn:population":0,
    "gn:timezone":"Asia/Shanghai",
    "iso:country":"CN",
    "name:zho_x_preferred":[
        "\u9152\u82b1\u5206\u573a"
    ],
    "wof:name":"Jiuhuafenchang",
    "wof:placetype":"locality"
},
  "geometry": {"coordinates":[122.333,42.0446],"type":"Point"}
}