{
  "type": "Feature",
  "properties": {
    "gn:admin1_code":"3.0",
    "gn:asciiname":"Zhicheng",
    "gn:country_code":"CN",
    "gn:dem":82,
    "gn:feature_class":"P",
    "gn:feature_code":"PPL",
    "gn:name":"Zhicheng",
    "gn:population":0,
    "gn:timezone":"Asia/Shanghai",
    "iso:country":"CN",
    "name:ceb_x_preferred":[
        "Zhicheng"
    ],
    "name:mlg_x_preferred":[
        "Zhicheng"
    ],
    "name:nor_x_preferred":[
        "Zhicheng"
    ],
    "name:swe_x_preferred":[
        "Zhicheng"
    ],
    "name:und_x_variant":[
        "\u6cbb\u57ce"
    ],
    "name:zho_x_preferred":[
        "\u679d\u57ce\u9547"
    ],
    "wof:name":"Zhicheng",
    "wof:placetype":"locality"
},
  "geometry": {"coordinates":[115.03706,28.67808],"type":"Point"}
}