{
  "type": "Feature",
  "properties": {
    "gn:admin1_code":"9.0",
    "gn:asciiname":"Caizhuangji",
    "gn:country_code":"CN",
    "gn:dem":47,
    "gn:feature_class":"P",
    "gn:feature_code":"PPL",
    "gn:name":"Caizhuangji",
    "gn:population":0,
    "gn:timezone":"Asia/Shanghai",
    "iso:country":"CN",
    "name:zho_x_preferred":[
        "\u8521\u5e84\u96c6"
    ],
    "wof:name":"Caizhuangji",
    "wof:placetype":"locality"
},
  "geometry": {"coordinates":[114.68836,33.32183],"type":"Point"}
}