{
  "type": "Feature",
  "properties": {
    "gn:admin1_code":"12.0",
    "gn:asciiname":"Yangjiaokeng",
    "gn:country_code":"CN",
    "gn:dem":247,
    "gn:feature_class":"P",
    "gn:feature_code":"PPL",
    "gn:name":"Yangjiaokeng",
    "gn:population":0,
    "gn:timezone":"Asia/Shanghai",
    "iso:country":"CN",
    "name:zho_x_preferred":[
        "Yangjiaokeng"
    ],
    "name:zho_x_variant":[
        "\u7f8a\u89d2\u5751"
    ],
    "wof:name":"Yangjiaokeng",
    "wof:placetype":"locality"
},
  "geometry": {"coordinates":[114.00702,29.2761],"type":"Point"}
}