{
  "type": "Feature",
  "properties": {
    "gn:admin1_code":"19.0",
    "gn:asciiname":"Xidacha",
    "gn:country_code":"CN",
    "gn:dem":331,
    "gn:feature_class":"P",
    "gn:feature_code":"PPL",
    "gn:name":"Xidacha",
    "gn:population":0,
    "gn:timezone":"Asia/Shanghai",
    "iso:country":"CN",
    "name:und_x_variant":[
        "\u897f\u5927\u5c94"
    ],
    "wof:name":"Xidacha",
    "wof:placetype":"locality"
},
  "geometry": {"coordinates":[123.25193,40.70739],"type":"Point"}
}