{
  "type": "Feature",
  "properties": {
    "gn:admin1_code":"4.0",
    "gn:asciiname":"Mudan Liuzu",
    "gn:country_code":"CN",
    "gn:dem":-2,
    "gn:feature_class":"P",
    "gn:feature_code":"PPLF",
    "gn:name":"Mudan Liuzu",
    "gn:population":0,
    "gn:timezone":"Asia/Shanghai",
    "iso:country":"CN",
    "name:zho_x_preferred":[
        "\u7261\u4e39\u516d\u7ec4"
    ],
    "wof:name":"Mudan Liuzu",
    "wof:placetype":"locality"
},
  "geometry": {"coordinates":[120.133,33.8952],"type":"Point"}
}