{
  "type": "Feature",
  "properties": {
    "gn:admin1_code":"13",
    "gn:asciiname":"Yilingertuan Erlinglian",
    "gn:country_code":"CN",
    "gn:dem":449,
    "gn:feature_class":"P",
    "gn:feature_code":"PPL",
    "gn:name":"Yilingertuan Erlinglian",
    "gn:population":0,
    "gn:timezone":"Asia/Urumqi",
    "iso:country":"CN",
    "name:zho_x_preferred":[
        "\u4e00\u96f6\u4e8c\u56e2\u4e8c\u96f6\u8fde"
    ],
    "wof:name":"Yilingertuan Erlinglian",
    "wof:placetype":"locality"
},
  "geometry": {"coordinates":[87.75333000000001,44.34226],"type":"Point"}
}