{
  "type": "Feature",
  "properties": {
    "gn:admin1_code":"32.0",
    "gn:asciiname":"Gelaji",
    "gn:country_code":"CN",
    "gn:dem":3465,
    "gn:feature_class":"P",
    "gn:feature_code":"PPL",
    "gn:name":"Gelaji",
    "gn:population":0,
    "gn:timezone":"Asia/Shanghai",
    "iso:country":"CN",
    "name:zho_x_preferred":[
        "\u683c\u62c9\u57fa"
    ],
    "wof:name":"Gelaji",
    "wof:placetype":"locality"
},
  "geometry": {"coordinates":[101.19199999999999,30.4446],"type":"Point"}
}