{
  "type": "Feature",
  "properties": {
    "gn:admin1_code":"5.0",
    "gn:asciiname":"Bacuotun",
    "gn:country_code":"CN",
    "gn:dem":159,
    "gn:feature_class":"P",
    "gn:feature_code":"PPL",
    "gn:name":"Bacuotun",
    "gn:population":0,
    "gn:timezone":"Asia/Shanghai",
    "iso:country":"CN",
    "name:zho_x_preferred":[
        "\u516b\u64ae\u5c6f"
    ],
    "wof:name":"Bacuotun",
    "wof:placetype":"locality"
},
  "geometry": {"coordinates":[122.7159,44.66476],"type":"Point"}
}