{
  "type": "Feature",
  "properties": {
    "gn:admin1_code":"32.0",
    "gn:asciiname":"Sunjiahe",
    "gn:country_code":"CN",
    "gn:dem":1090,
    "gn:feature_class":"P",
    "gn:feature_code":"PPL",
    "gn:name":"Sunjiahe",
    "gn:population":0,
    "gn:timezone":"Asia/Shanghai",
    "iso:country":"CN",
    "name:zho_x_preferred":[
        "\u5b59\u5bb6\u6cb3"
    ],
    "wof:name":"Sunjiahe",
    "wof:placetype":"locality"
},
  "geometry": {"coordinates":[107.896,31.9522],"type":"Point"}
}