{
  "type": "Feature",
  "properties": {
    "gn:admin1_code":"2.0",
    "gn:asciiname":"Xintongming",
    "gn:country_code":"CN",
    "gn:dem":9,
    "gn:feature_class":"P",
    "gn:feature_code":"PPL",
    "gn:name":"Xintongming",
    "gn:population":0,
    "gn:timezone":"Asia/Shanghai",
    "iso:country":"CN",
    "name:zho_x_preferred":[
        "\u65b0\u901a\u660e"
    ],
    "wof:name":"Xintongming",
    "wof:placetype":"locality"
},
  "geometry": {"coordinates":[121.00338000000001,29.97678],"type":"Point"}
}