{
  "type": "Feature",
  "properties": {
    "gn:admin1_code":"9.0",
    "gn:asciiname":"Nanmazhuang",
    "gn:country_code":"CN",
    "gn:dem":96,
    "gn:feature_class":"P",
    "gn:feature_code":"PPL",
    "gn:name":"Nanmazhuang",
    "gn:population":0,
    "gn:timezone":"Asia/Shanghai",
    "iso:country":"CN",
    "name:zho_x_preferred":[
        "\u5357\u9a6c\u5e84"
    ],
    "wof:name":"Nanmazhuang",
    "wof:placetype":"locality"
},
  "geometry": {"coordinates":[112.59778,32.62432],"type":"Point"}
}