{
  "type": "Feature",
  "properties": {
    "gn:admin1_code":"30.0",
    "gn:asciiname":"Ma'nan",
    "gn:country_code":"CN",
    "gn:dem":8,
    "gn:feature_class":"P",
    "gn:feature_code":"PPL",
    "gn:name":"Ma\u2019nan",
    "gn:population":0,
    "gn:timezone":"Asia/Shanghai",
    "iso:country":"CN",
    "name:und_x_variant":[
        "Ma\u2019nan"
    ],
    "name:zho_x_preferred":[
        "\u9a6c\u5357"
    ],
    "wof:name":"Ma'nan",
    "wof:placetype":"locality"
},
  "geometry": {"coordinates":[113.24166,22.78481],"type":"Point"}
}