{
  "type": "Feature",
  "properties": {
    "gn:admin1_code":"18",
    "gn:asciiname":"Yandong",
    "gn:country_code":"CN",
    "gn:dem":842,
    "gn:feature_class":"P",
    "gn:feature_code":"PPL",
    "gn:name":"Yandong",
    "gn:population":0,
    "gn:timezone":"Asia/Shanghai",
    "iso:country":"CN",
    "wof:name":"Yandong",
    "wof:placetype":"locality"
},
  "geometry": {"coordinates":[108.91472,26.62861],"type":"Point"}
}