{
  "type": "Feature",
  "properties": {
    "gn:admin1_code":"10",
    "gn:asciiname":"Yincaizhuang",
    "gn:country_code":"CN",
    "gn:dem":35,
    "gn:feature_class":"P",
    "gn:feature_code":"PPL",
    "gn:name":"Yincaizhuang",
    "gn:population":0,
    "gn:timezone":"Asia/Shanghai",
    "iso:country":"CN",
    "name:zho_x_preferred":[
        "\u5c39\u624d\u5e84"
    ],
    "wof:name":"Yincaizhuang",
    "wof:placetype":"locality"
},
  "geometry": {"coordinates":[115.57899999999999,37.0861],"type":"Point"}
}