{
  "type": "Feature",
  "properties": {
    "gn:admin1_code":"32.0",
    "gn:asciiname":"Tianjingba",
    "gn:country_code":"CN",
    "gn:dem":859,
    "gn:feature_class":"P",
    "gn:feature_code":"PPL",
    "gn:name":"Tianjingba",
    "gn:population":0,
    "gn:timezone":"Asia/Shanghai",
    "iso:country":"CN",
    "name:zho_x_preferred":[
        "\u5929\u4e95\u575d"
    ],
    "wof:name":"Tianjingba",
    "wof:placetype":"locality"
},
  "geometry": {"coordinates":[107.20699999999999,32.2721],"type":"Point"}
}