{
  "type": "Feature",
  "properties": {
    "gn:admin1_code":"32.0",
    "gn:asciiname":"Changtianbang",
    "gn:country_code":"CN",
    "gn:dem":349,
    "gn:feature_class":"P",
    "gn:feature_code":"PPL",
    "gn:name":"Changtianbang",
    "gn:population":0,
    "gn:timezone":"Asia/Shanghai",
    "iso:country":"CN",
    "name:zho_x_preferred":[
        "\u957f\u7530\u585d"
    ],
    "wof:name":"Changtianbang",
    "wof:placetype":"locality"
},
  "geometry": {"coordinates":[105.25915999999999,28.58957],"type":"Point"}
}