{
  "type": "Feature",
  "properties": {
    "gn:admin1_code":"11",
    "gn:asciiname":"Caoxijie",
    "gn:country_code":"CN",
    "gn:dem":204,
    "gn:feature_class":"P",
    "gn:feature_code":"PPL",
    "gn:name":"Caoxijie",
    "gn:population":0,
    "gn:timezone":"Asia/Shanghai",
    "iso:country":"CN",
    "name:zho_x_preferred":[
        "\u66f9\u6eaa\u8857"
    ],
    "wof:name":"Caoxijie",
    "wof:placetype":"locality"
},
  "geometry": {"coordinates":[111.93819000000001,27.83373],"type":"Point"}
}