{
  "type": "Feature",
  "properties": {
    "gn:admin1_code":"11",
    "gn:asciiname":"Chachong'aoshang",
    "gn:country_code":"CN",
    "gn:dem":161,
    "gn:feature_class":"P",
    "gn:feature_code":"PPL",
    "gn:name":"Chachong\u2019aoshang",
    "gn:population":0,
    "gn:timezone":"Asia/Shanghai",
    "iso:country":"CN",
    "name:und_x_variant":[
        "Chachong\u2019aoshang"
    ],
    "name:zho_x_preferred":[
        "\u8336\u51b2\u5773\u4e0a"
    ],
    "wof:name":"Chachong'aoshang",
    "wof:placetype":"locality"
},
  "geometry": {"coordinates":[112.18519999999999,27.63443],"type":"Point"}
}