{
  "type": "Feature",
  "properties": {
    "gn:admin1_code":"25",
    "gn:asciiname":"Shimiao",
    "gn:cc2":"CN",
    "gn:country_code":"CN",
    "gn:dem":11,
    "gn:feature_class":"P",
    "gn:feature_code":"PPL",
    "gn:name":"Shimiao",
    "gn:population":0,
    "gn:timezone":"Asia/Shanghai",
    "iso:country":"CN",
    "name:und_x_variant":[
        "Shih-miao",
        "Shimiao"
    ],
    "wof:name":"Shimiao",
    "wof:placetype":"locality"
},
  "geometry": {"coordinates":[117.36667,37.45],"type":"Point"}
}