{
  "type": "Feature",
  "properties": {
    "gn:admin1_code":"11.0",
    "gn:asciiname":"Chengxiacun",
    "gn:country_code":"CN",
    "gn:dem":211,
    "gn:feature_class":"P",
    "gn:feature_code":"PPL",
    "gn:name":"Chengxiacun",
    "gn:population":0,
    "gn:timezone":"Asia/Shanghai",
    "iso:country":"CN",
    "name:zho_x_preferred":[
        "\u57ce\u4e0b\u6751"
    ],
    "wof:name":"Chengxiacun",
    "wof:placetype":"locality"
},
  "geometry": {"coordinates":[111.04002,25.10222000000001],"type":"Point"}
}