{
  "type": "Feature",
  "properties": {
    "gn:admin1_code":"32.0",
    "gn:asciiname":"Boda",
    "gn:country_code":"CN",
    "gn:dem":2311,
    "gn:feature_class":"P",
    "gn:feature_code":"PPL",
    "gn:name":"Boda",
    "gn:population":0,
    "gn:timezone":"Asia/Shanghai",
    "iso:country":"CN",
    "name:ben_x_preferred":[
        "\u09ac\u09cb\u09a6"
    ],
    "name:bpy_x_preferred":[
        "\u09ac\u09cb\u09a6"
    ],
    "name:ceb_x_preferred":[
        "Boda"
    ],
    "name:deu_x_preferred":[
        "Boda"
    ],
    "name:fin_x_preferred":[
        "Boda"
    ],
    "name:fra_x_preferred":[
        "Boda"
    ],
    "name:ita_x_preferred":[
        "Boda"
    ],
    "name:nld_x_preferred":[
        "Boda"
    ],
    "name:oci_x_preferred":[
        "Boda"
    ],
    "name:pol_x_preferred":[
        "Boda"
    ],
    "name:por_x_preferred":[
        "Boda"
    ],
    "name:rus_x_preferred":[
        "\u0411\u043e\u0434\u0430"
    ],
    "name:spa_x_preferred":[
        "Boda"
    ],
    "name:swe_x_preferred":[
        "Boda"
    ],
    "name:zho_x_preferred":[
        "\u535a\u5927"
    ],
    "wof:name":"Boda",
    "wof:placetype":"locality"
},
  "geometry": {"coordinates":[101.22619,27.39535],"type":"Point"}
}