{
  "type": "Feature",
  "properties": {
    "gn:admin1_code":"18",
    "gn:asciiname":"Bumu",
    "gn:country_code":"CN",
    "gn:dem":871,
    "gn:feature_class":"P",
    "gn:feature_code":"PPL",
    "gn:name":"Bumu",
    "gn:population":0,
    "gn:timezone":"Asia/Shanghai",
    "iso:country":"CN",
    "name:zho_x_preferred":[
        "\u8865\u6bcd"
    ],
    "wof:name":"Bumu",
    "wof:placetype":"locality"
},
  "geometry": {"coordinates":[104.98099999999999,26.0934],"type":"Point"}
}