{
  "type": "Feature",
  "properties": {
    "gn:admin1_code":"20.0",
    "gn:asciiname":"Wenjiaqu",
    "gn:country_code":"CN",
    "gn:dem":1324,
    "gn:feature_class":"P",
    "gn:feature_code":"PPL",
    "gn:name":"Wenjiaqu",
    "gn:population":0,
    "gn:timezone":"Asia/Shanghai",
    "iso:country":"CN",
    "name:und_x_variant":[
        "\u6e29\u5bb6\u6e20"
    ],
    "wof:name":"Wenjiaqu",
    "wof:placetype":"locality"
},
  "geometry": {"coordinates":[109.92766,40.90096],"type":"Point"}
}