{
  "type": "Feature",
  "properties": {
    "gn:admin1_code":"32.0",
    "gn:asciiname":"Momogou",
    "gn:country_code":"CN",
    "gn:dem":2247,
    "gn:feature_class":"P",
    "gn:feature_code":"PPL",
    "gn:name":"Momogou",
    "gn:population":0,
    "gn:timezone":"Asia/Shanghai",
    "iso:country":"CN",
    "name:zho_x_preferred":[
        "\u83ab\u83ab\u6c9f"
    ],
    "wof:name":"Momogou",
    "wof:placetype":"locality"
},
  "geometry": {"coordinates":[101.047,29.2777],"type":"Point"}
}