{
  "type": "Feature",
  "properties": {
    "gn:admin1_code":"20.0",
    "gn:asciiname":"Zhongshengla",
    "gn:country_code":"CN",
    "gn:dem":1675,
    "gn:feature_class":"P",
    "gn:feature_code":"PPL",
    "gn:name":"Zhongshengla",
    "gn:population":0,
    "gn:timezone":"Asia/Shanghai",
    "iso:country":"CN",
    "name:und_x_variant":[
        "\u4e2d\u5347\u62c9"
    ],
    "wof:name":"Zhongshengla",
    "wof:placetype":"locality"
},
  "geometry": {"coordinates":[112.18411999999999,41.529],"type":"Point"}
}