{
  "type": "Feature",
  "properties": {
    "gn:admin1_code":"11.0",
    "gn:asciiname":"Taozhutan",
    "gn:country_code":"CN",
    "gn:dem":182,
    "gn:feature_class":"P",
    "gn:feature_code":"PPL",
    "gn:name":"Taozhutan",
    "gn:population":0,
    "gn:timezone":"Asia/Shanghai",
    "iso:country":"CN",
    "name:zho_x_preferred":[
        "\u6843\u7af9\u6f6d"
    ],
    "wof:name":"Taozhutan",
    "wof:placetype":"locality"
},
  "geometry": {"coordinates":[109.97411,28.28666],"type":"Point"}
}