{
  "type": "Feature",
  "properties": {
    "gn:admin1_code":"30.0",
    "gn:asciiname":"Qingke",
    "gn:country_code":"CN",
    "gn:dem":11,
    "gn:feature_class":"P",
    "gn:feature_code":"PPL",
    "gn:name":"Qingke",
    "gn:population":0,
    "gn:timezone":"Asia/Shanghai",
    "iso:country":"CN",
    "name:zho_x_preferred":[
        "\u9752\u67ef"
    ],
    "wof:name":"Qingke",
    "wof:placetype":"locality"
},
  "geometry": {"coordinates":[113.08008,23.02136],"type":"Point"}
}