{
  "type": "Feature",
  "properties": {
    "gn:admin1_code":"12.0",
    "gn:asciiname":"Jinjibu",
    "gn:country_code":"CN",
    "gn:dem":25,
    "gn:feature_class":"P",
    "gn:feature_code":"PPL",
    "gn:name":"Jinjibu",
    "gn:population":0,
    "gn:timezone":"Asia/Shanghai",
    "iso:country":"CN",
    "name:zho_x_preferred":[
        "\u91d1\u9e21\u5821"
    ],
    "wof:name":"Jinjibu",
    "wof:placetype":"locality"
},
  "geometry": {"coordinates":[113.93259999999999,30.08299],"type":"Point"}
}