{
  "type": "Feature",
  "properties": {
    "gn:admin1_code":"20",
    "gn:asciiname":"Wu-shih-chia-tzu",
    "gn:country_code":"CN",
    "gn:dem":478,
    "gn:feature_class":"P",
    "gn:feature_code":"PPL",
    "gn:name":"Wu-shih-chia-tzu",
    "gn:population":0,
    "gn:timezone":"Asia/Shanghai",
    "iso:country":"CN",
    "wof:name":"Wu-shih-chia-tzu",
    "wof:placetype":"locality"
},
  "geometry": {"coordinates":[119.43528000000001,42.5025],"type":"Point"}
}