{
  "type": "Feature",
  "properties": {
    "gn:admin1_code":"29",
    "gn:asciiname":"Muzhulong",
    "gn:country_code":"CN",
    "gn:dem":1873,
    "gn:feature_class":"P",
    "gn:feature_code":"PPL",
    "gn:name":"Muzhulong",
    "gn:population":0,
    "gn:timezone":"Asia/Shanghai",
    "iso:country":"CN",
    "name:zho_x_preferred":[
        "\u6bcd\u732a\u9f99"
    ],
    "wof:name":"Muzhulong",
    "wof:placetype":"locality"
},
  "geometry": {"coordinates":[103.06592999999999,24.53017],"type":"Point"}
}