{
  "type": "Feature",
  "properties": {
    "gn:admin1_code":"7",
    "gn:asciiname":"Xujianong",
    "gn:country_code":"CN",
    "gn:dem":45,
    "gn:feature_class":"P",
    "gn:feature_code":"PPL",
    "gn:name":"Xujianong",
    "gn:population":0,
    "gn:timezone":"Asia/Shanghai",
    "iso:country":"CN",
    "name:zho_x_preferred":[
        "\u8bb8\u5bb6\u5f04"
    ],
    "wof:name":"Xujianong",
    "wof:placetype":"locality"
},
  "geometry": {"coordinates":[118.57156999999999,24.73079],"type":"Point"}
}