{
  "type": "Feature",
  "properties": {
    "gn:admin1_code":"8.0",
    "gn:asciiname":"Yinbucun",
    "gn:country_code":"CN",
    "gn:dem":127,
    "gn:feature_class":"P",
    "gn:feature_code":"PPL",
    "gn:name":"Yinbucun",
    "gn:population":0,
    "gn:timezone":"Asia/Shanghai",
    "iso:country":"CN",
    "name:zho_x_preferred":[
        "\u5c39\u5821\u6751"
    ],
    "wof:name":"Yinbucun",
    "wof:placetype":"locality"
},
  "geometry": {"coordinates":[126.61022,46.11516],"type":"Point"}
}