{
  "type": "Feature",
  "properties": {
    "gn:admin1_code":"29.0",
    "gn:asciiname":"Jiumang",
    "gn:country_code":"CN",
    "gn:dem":1925,
    "gn:feature_class":"P",
    "gn:feature_code":"PPL",
    "gn:name":"Jiumang",
    "gn:population":0,
    "gn:timezone":"Asia/Shanghai",
    "iso:country":"CN",
    "name:zho_x_preferred":[
        "\u65e7\u87d2"
    ],
    "wof:name":"Jiumang",
    "wof:placetype":"locality"
},
  "geometry": {"coordinates":[101.292,24.0835],"type":"Point"}
}