{
  "type": "Feature",
  "properties": {
    "gn:admin1_code":"26",
    "gn:asciiname":"Nanhancun",
    "gn:country_code":"CN",
    "gn:dem":494,
    "gn:feature_class":"P",
    "gn:feature_code":"PPL",
    "gn:name":"Nanhancun",
    "gn:population":0,
    "gn:timezone":"Asia/Shanghai",
    "iso:country":"CN",
    "name:und_x_variant":[
        "Nanhan",
        "Nanhancun"
    ],
    "name:zho_x_preferred":[
        "\u5357\u97e9"
    ],
    "name:zho_x_variant":[
        "\u5357\u97e9\u6751"
    ],
    "wof:name":"Nanhancun",
    "wof:placetype":"locality"
},
  "geometry": {"coordinates":[108.51461,34.3457],"type":"Point"}
}