{
  "type": "Feature",
  "properties": {
    "gn:admin1_code":"26.0",
    "gn:asciiname":"Wazigou",
    "gn:country_code":"CN",
    "gn:dem":1335,
    "gn:feature_class":"P",
    "gn:feature_code":"PPL",
    "gn:name":"Wazigou",
    "gn:population":0,
    "gn:timezone":"Asia/Shanghai",
    "iso:country":"CN",
    "name:und_x_variant":[
        "Wa-tzu-kou",
        "Wazigou"
    ],
    "name:zho_x_preferred":[
        "\u74e6\u5b50\u6c9f"
    ],
    "wof:name":"Wazigou",
    "wof:placetype":"locality"
},
  "geometry": {"coordinates":[108.51309999999999,33.75538],"type":"Point"}
}