{
  "type": "Feature",
  "properties": {
    "gn:admin1_code":"29.0",
    "gn:asciiname":"Xiaojia'ao",
    "gn:country_code":"CN",
    "gn:dem":1931,
    "gn:feature_class":"P",
    "gn:feature_code":"PPL",
    "gn:name":"Xiaojia\u2019ao",
    "gn:population":0,
    "gn:timezone":"Asia/Shanghai",
    "iso:country":"CN",
    "name:und_x_variant":[
        "Xiaojia\u2019ao"
    ],
    "name:zho_x_preferred":[
        "\u8096\u5bb6\u51f9"
    ],
    "wof:name":"Xiaojia'ao",
    "wof:placetype":"locality"
},
  "geometry": {"coordinates":[101.212,25.7994],"type":"Point"}
}