{
  "type": "Feature",
  "properties": {
    "gn:admin1_code":"10",
    "gn:asciiname":"Nandayue",
    "gn:country_code":"CN",
    "gn:dem":77,
    "gn:feature_class":"P",
    "gn:feature_code":"PPLA4",
    "gn:name":"Nandayue",
    "gn:population":0,
    "gn:timezone":"Asia/Shanghai",
    "iso:country":"CN",
    "name:fas_x_preferred":[
        "\u0646\u0627\u0646\u062f\u0627\u06cc\u0648\u0626\u0647"
    ],
    "name:und_x_variant":[
        "\u5357\u5927\u5cb3",
        "Nandayue Zhen"
    ],
    "name:zho_x_preferred":[
        "\u5357\u5927\u5cb3\u9547"
    ],
    "wof:name":"Nandayue",
    "wof:placetype":"locality"
},
  "geometry": {"coordinates":[114.79125000000001,38.4749],"type":"Point"}
}