{
  "type": "Feature",
  "properties": {
    "gn:admin1_code":"30.0",
    "gn:asciiname":"Xudong",
    "gn:country_code":"CN",
    "gn:dem":54,
    "gn:feature_class":"P",
    "gn:feature_code":"PPL",
    "gn:name":"Xudong",
    "gn:population":0,
    "gn:timezone":"Asia/Shanghai",
    "iso:country":"CN",
    "name:und_x_variant":[
        "\u5f90\u6d1e"
    ],
    "name:zho_x_preferred":[
        "\u5f90\u6d1e"
    ],
    "wof:name":"Xudong",
    "wof:placetype":"locality"
},
  "geometry": {"coordinates":[114.74163,23.80852],"type":"Point"}
}