{
  "type": "Feature",
  "properties": {
    "gn:admin1_code":"29.0",
    "gn:asciiname":"Niudou",
    "gn:country_code":"CN",
    "gn:dem":1514,
    "gn:feature_class":"P",
    "gn:feature_code":"PPL",
    "gn:name":"Niudou",
    "gn:population":0,
    "gn:timezone":"Asia/Shanghai",
    "iso:country":"CN",
    "name:zho_x_preferred":[
        "\u725b\u6597"
    ],
    "wof:name":"Niudou",
    "wof:placetype":"locality"
},
  "geometry": {"coordinates":[102.619,23.1011],"type":"Point"}
}