{
  "type": "Feature",
  "properties": {
    "gn:admin1_code":"26.0",
    "gn:asciiname":"Caoyaoxiancun",
    "gn:country_code":"CN",
    "gn:dem":1491,
    "gn:feature_class":"P",
    "gn:feature_code":"PPL",
    "gn:name":"Caoyaoxiancun",
    "gn:population":0,
    "gn:timezone":"Asia/Shanghai",
    "iso:country":"CN",
    "name:zho_x_preferred":[
        "\u66f9\u5d3e\u5d04\u6751"
    ],
    "wof:name":"Caoyaoxiancun",
    "wof:placetype":"locality"
},
  "geometry": {"coordinates":[108.48607,37.40063],"type":"Point"}
}