{
  "type": "Feature",
  "properties": {
    "gn:admin1_code":"30.0",
    "gn:asciiname":"Dunbei",
    "gn:country_code":"CN",
    "gn:dem":182,
    "gn:feature_class":"P",
    "gn:feature_code":"PPL",
    "gn:name":"Dunbei",
    "gn:population":0,
    "gn:timezone":"Asia/Urumqi",
    "iso:country":"CN",
    "name:zho_x_preferred":[
        "\u58a9\u80cc"
    ],
    "wof:name":"Dunbei",
    "wof:placetype":"locality"
},
  "geometry": {"coordinates":[111.55379000000001,22.49858],"type":"Point"}
}