{
  "type": "Feature",
  "properties": {
    "gn:admin1_code":"3.0",
    "gn:asciiname":"Hejiacunshang",
    "gn:country_code":"CN",
    "gn:dem":548,
    "gn:feature_class":"P",
    "gn:feature_code":"PPL",
    "gn:name":"Hejiacunshang",
    "gn:population":0,
    "gn:timezone":"Asia/Shanghai",
    "iso:country":"CN",
    "name:zho_x_preferred":[
        "\u4f55\u5bb6\u6751\u4e0a"
    ],
    "wof:name":"Hejiacunshang",
    "wof:placetype":"locality"
},
  "geometry": {"coordinates":[117.34066,27.86671],"type":"Point"}
}