{
  "type": "Feature",
  "properties": {
    "gn:admin1_code":"14.0",
    "gn:asciiname":"Chagonglaka",
    "gn:country_code":"CN",
    "gn:dem":4512,
    "gn:feature_class":"P",
    "gn:feature_code":"PPL",
    "gn:name":"Chagonglaka",
    "gn:population":0,
    "gn:timezone":"Asia/Urumqi",
    "iso:country":"CN",
    "name:zho_x_preferred":[
        "\u5dee\u4f9b\u62c9\u5361"
    ],
    "wof:name":"Chagonglaka",
    "wof:placetype":"locality"
},
  "geometry": {"coordinates":[96.05891,30.93935],"type":"Point"}
}