{
  "type": "Feature",
  "properties": {
    "gn:admin1_code":"25",
    "gn:asciiname":"Xitaiji",
    "gn:country_code":"CN",
    "gn:dem":58,
    "gn:feature_class":"P",
    "gn:feature_code":"PPL",
    "gn:name":"Xitaiji",
    "gn:population":0,
    "gn:timezone":"Asia/Shanghai",
    "iso:country":"CN",
    "name:zho_x_preferred":[
        "\u897f\u53f0\u96c6"
    ],
    "wof:name":"Xitaiji",
    "wof:placetype":"locality"
},
  "geometry": {"coordinates":[115.11799999999999,35.3428],"type":"Point"}
}