{
  "type": "Feature",
  "properties": {
    "gn:admin1_code":"26.0",
    "gn:asciiname":"Yangjia Huopan",
    "gn:country_code":"CN",
    "gn:dem":1160,
    "gn:feature_class":"P",
    "gn:feature_code":"PPL",
    "gn:name":"Yangjia Huopan",
    "gn:population":0,
    "gn:timezone":"Asia/Shanghai",
    "iso:country":"CN",
    "name:zho_x_preferred":[
        "\u6768\u5bb6\u4f19\u76d8"
    ],
    "wof:name":"Yangjia Huopan",
    "wof:placetype":"locality"
},
  "geometry": {"coordinates":[110.51600000000001,39.0463],"type":"Point"}
}