{
  "type": "Feature",
  "properties": {
    "gn:admin1_code":"8.0",
    "gn:asciiname":"Wujing",
    "gn:country_code":"CN",
    "gn:dem":198,
    "gn:feature_class":"P",
    "gn:feature_code":"PPL",
    "gn:name":"Wujing",
    "gn:population":0,
    "gn:timezone":"Asia/Shanghai",
    "iso:country":"CN",
    "name:deu_x_preferred":[
        "Wujing"
    ],
    "name:swe_x_preferred":[
        "Wujing"
    ],
    "name:zho_x_preferred":[
        "\u4e94\u4e95"
    ],
    "wof:name":"Wujing",
    "wof:placetype":"locality"
},
  "geometry": {"coordinates":[125.61449,46.06102],"type":"Point"}
}