{
  "type": "Feature",
  "properties": {
    "gn:admin1_code":"26.0",
    "gn:asciiname":"Hezhuanggou",
    "gn:country_code":"CN",
    "gn:dem":1420,
    "gn:feature_class":"P",
    "gn:feature_code":"PPL",
    "gn:name":"Hezhuanggou",
    "gn:population":0,
    "gn:timezone":"Asia/Shanghai",
    "iso:country":"CN",
    "name:zho_x_preferred":[
        "\u4f55\u5e84\u6c9f"
    ],
    "wof:name":"Hezhuanggou",
    "wof:placetype":"locality"
},
  "geometry": {"coordinates":[108.19144,36.66991],"type":"Point"}
}