{
  "type": "Feature",
  "properties": {
    "gn:admin1_code":"15.0",
    "gn:asciiname":"Yawan",
    "gn:country_code":"CN",
    "gn:dem":1751,
    "gn:feature_class":"P",
    "gn:feature_code":"PPL",
    "gn:name":"Yawan",
    "gn:population":0,
    "gn:timezone":"Asia/Shanghai",
    "iso:country":"CN",
    "name:ceb_x_preferred":[
        "Yawan"
    ],
    "name:swe_x_preferred":[
        "Yawan"
    ],
    "name:und_x_variant":[
        "\u5d16\u6e7e"
    ],
    "wof:name":"Yawan",
    "wof:placetype":"locality"
},
  "geometry": {"coordinates":[105.55461,35.41467],"type":"Point"}
}