{
  "type": "Feature",
  "properties": {
    "gn:admin1_code":"3.0",
    "gn:asciiname":"Xiachengkou",
    "gn:country_code":"CN",
    "gn:dem":35,
    "gn:feature_class":"P",
    "gn:feature_code":"PPL",
    "gn:name":"Xiachengkou",
    "gn:population":0,
    "gn:timezone":"Asia/Shanghai",
    "iso:country":"CN",
    "name:und_x_variant":[
        "\u4e0b\u57ce\u53e3"
    ],
    "wof:name":"Xiachengkou",
    "wof:placetype":"locality"
},
  "geometry": {"coordinates":[116.77333,29.18665],"type":"Point"}
}