{
  "type": "Feature",
  "properties": {
    "gn:admin1_code":"29.0",
    "gn:asciiname":"Hanban",
    "gn:country_code":"CN",
    "gn:dem":750,
    "gn:feature_class":"P",
    "gn:feature_code":"PPL",
    "gn:name":"Hanban",
    "gn:population":0,
    "gn:timezone":"Asia/Yangon",
    "iso:country":"CN",
    "name:zho_x_preferred":[
        "\u558a\u677f"
    ],
    "wof:name":"Hanban",
    "wof:placetype":"locality"
},
  "geometry": {"coordinates":[97.63720000000001,23.8799],"type":"Point"}
}