{
  "type": "Feature",
  "properties": {
    "gn:admin1_code":"4.0",
    "gn:asciiname":"Zhanglaomiao",
    "gn:country_code":"CN",
    "gn:dem":24,
    "gn:feature_class":"P",
    "gn:feature_code":"PPL",
    "gn:name":"Zhanglaomiao",
    "gn:population":0,
    "gn:timezone":"Asia/Shanghai",
    "iso:country":"CN",
    "name:zho_x_preferred":[
        "\u5f20\u8001\u5e99"
    ],
    "wof:name":"Zhanglaomiao",
    "wof:placetype":"locality"
},
  "geometry": {"coordinates":[118.07599999999999,33.8488],"type":"Point"}
}