{
  "type": "Feature",
  "properties": {
    "gn:admin1_code":"21.0",
    "gn:asciiname":"Shangyayao",
    "gn:country_code":"CN",
    "gn:dem":1746,
    "gn:feature_class":"P",
    "gn:feature_code":"PPL",
    "gn:name":"Shangyayao",
    "gn:population":0,
    "gn:timezone":"Asia/Shanghai",
    "iso:country":"CN",
    "name:und_x_variant":[
        "\u4e0a\u5d16\u5d3e"
    ],
    "name:zho_x_preferred":[
        "\u4e0a\u5d16\u5d3e"
    ],
    "wof:name":"Shangyayao",
    "wof:placetype":"locality"
},
  "geometry": {"coordinates":[106.61669000000001,36.2071],"type":"Point"}
}