{
  "type": "Feature",
  "properties": {
    "gn:admin1_code":"32.0",
    "gn:asciiname":"Sanjiangda",
    "gn:country_code":"CN",
    "gn:dem":2627,
    "gn:feature_class":"P",
    "gn:feature_code":"PPL",
    "gn:name":"Sanjiangda",
    "gn:population":0,
    "gn:timezone":"Asia/Shanghai",
    "iso:country":"CN",
    "name:zho_x_preferred":[
        "\u4e09\u6c5f\u8fbe"
    ],
    "wof:name":"Sanjiangda",
    "wof:placetype":"locality"
},
  "geometry": {"coordinates":[101.73446,32.1488],"type":"Point"}
}