{
  "type": "Feature",
  "properties": {
    "gn:admin1_code":"3.0",
    "gn:asciiname":"Huangnikou",
    "gn:country_code":"CN",
    "gn:dem":582,
    "gn:feature_class":"P",
    "gn:feature_code":"PPL",
    "gn:name":"Huangnikou",
    "gn:population":0,
    "gn:timezone":"Asia/Shanghai",
    "iso:country":"CN",
    "name:und_x_variant":[
        "\u9ec4\u6ce5\u53e3"
    ],
    "wof:name":"Huangnikou",
    "wof:placetype":"locality"
},
  "geometry": {"coordinates":[115.34241000000002,25.65252000000001],"type":"Point"}
}