{
  "type": "Feature",
  "properties": {
    "gn:admin1_code":"26.0",
    "gn:asciiname":"Dongxinmaocun",
    "gn:country_code":"CN",
    "gn:dem":1188,
    "gn:feature_class":"P",
    "gn:feature_code":"PPL",
    "gn:name":"Dongxinmaocun",
    "gn:population":0,
    "gn:timezone":"Asia/Shanghai",
    "iso:country":"CN",
    "name:zho_x_preferred":[
        "\u4e1c\u65b0\u8302\u6751"
    ],
    "wof:name":"Dongxinmaocun",
    "wof:placetype":"locality"
},
  "geometry": {"coordinates":[109.37291999999999,36.45588],"type":"Point"}
}