{
  "type": "Feature",
  "properties": {
    "gn:admin1_code":"14",
    "gn:asciiname":"Sidui",
    "gn:country_code":"CN",
    "gn:dem":4079,
    "gn:feature_class":"P",
    "gn:feature_code":"PPL",
    "gn:name":"Sidui",
    "gn:population":0,
    "gn:timezone":"Asia/Urumqi",
    "iso:country":"CN",
    "name:zho_x_preferred":[
        "\u601d\u5806"
    ],
    "wof:name":"Sidui",
    "wof:placetype":"locality"
},
  "geometry": {"coordinates":[89.1645,28.9002],"type":"Point"}
}