{
  "type": "Feature",
  "properties": {
    "gn:admin1_code":"14",
    "gn:asciiname":"Zibulie",
    "gn:country_code":"CN",
    "gn:dem":4726,
    "gn:feature_class":"P",
    "gn:feature_code":"PPL",
    "gn:name":"Zibulie",
    "gn:population":0,
    "gn:timezone":"Asia/Urumqi",
    "iso:country":"CN",
    "name:zho_x_preferred":[
        "\u5b50\u5e03\u5217"
    ],
    "wof:name":"Zibulie",
    "wof:placetype":"locality"
},
  "geometry": {"coordinates":[87.6255,31.1421],"type":"Point"}
}