{
  "type": "Feature",
  "properties": {
    "gn:admin1_code":"01",
    "gn:asciiname":"Qifangdong",
    "gn:country_code":"CN",
    "gn:dem":50,
    "gn:feature_class":"P",
    "gn:feature_code":"PPL",
    "gn:name":"Qifangdong",
    "gn:population":0,
    "gn:timezone":"Asia/Shanghai",
    "iso:country":"CN",
    "name:und_x_variant":[
        "Ch\u2019i-fang-tung",
        "Qifangdong"
    ],
    "name:zho_x_preferred":[
        "\u4e03\u623f\u8463"
    ],
    "wof:name":"Qifangdong",
    "wof:placetype":"locality"
},
  "geometry": {"coordinates":[118.60856,31.08273],"type":"Point"}
}