{
  "type": "Feature",
  "properties": {
    "gn:admin1_code":"32.0",
    "gn:asciiname":"Qiulin",
    "gn:country_code":"CN",
    "gn:dem":2224,
    "gn:feature_class":"P",
    "gn:feature_code":"PPL",
    "gn:name":"Qiulin",
    "gn:population":0,
    "gn:timezone":"Asia/Shanghai",
    "iso:country":"CN",
    "name:zho_x_preferred":[
        "\u79cb\u6797"
    ],
    "wof:name":"Qiulin",
    "wof:placetype":"locality"
},
  "geometry": {"coordinates":[102.47,28.7414],"type":"Point"}
}