{
  "type": "Feature",
  "properties": {
    "gn:admin1_code":"26.0",
    "gn:asciiname":"Dongpocun",
    "gn:country_code":"CN",
    "gn:dem":1200,
    "gn:feature_class":"P",
    "gn:feature_code":"PPL",
    "gn:name":"Dongpocun",
    "gn:population":0,
    "gn:timezone":"Asia/Shanghai",
    "iso:country":"CN",
    "name:zho_x_preferred":[
        "\u4e1c\u5761\u6751"
    ],
    "wof:name":"Dongpocun",
    "wof:placetype":"locality"
},
  "geometry": {"coordinates":[108.16148,35.14463],"type":"Point"}
}