{
  "type": "Feature",
  "properties": {
    "gn:admin1_code":"8.0",
    "gn:asciiname":"Jiaojiatun",
    "gn:country_code":"CN",
    "gn:dem":244,
    "gn:feature_class":"P",
    "gn:feature_code":"PPL",
    "gn:name":"Jiaojiatun",
    "gn:population":0,
    "gn:timezone":"Asia/Shanghai",
    "iso:country":"CN",
    "name:zho_x_preferred":[
        "\u7126\u5bb6\u5c6f"
    ],
    "wof:name":"Jiaojiatun",
    "wof:placetype":"locality"
},
  "geometry": {"coordinates":[126.04292,47.62302],"type":"Point"}
}