{
  "type": "Feature",
  "properties": {
    "gn:admin1_code":"02",
    "gn:asciiname":"Wandong",
    "gn:country_code":"CN",
    "gn:dem":8,
    "gn:feature_class":"P",
    "gn:feature_code":"PPL",
    "gn:name":"Wandong",
    "gn:population":0,
    "gn:timezone":"Asia/Shanghai",
    "iso:country":"CN",
    "name:und_x_variant":[
        "\u6e7e\u4e1c"
    ],
    "wof:name":"Wandong",
    "wof:placetype":"locality"
},
  "geometry": {"coordinates":[121.19542,30.29495],"type":"Point"}
}