{
  "type": "Feature",
  "properties": {
    "gn:admin1_code":"9.0",
    "gn:asciiname":"Hengdalu",
    "gn:country_code":"CN",
    "gn:dem":69,
    "gn:feature_class":"P",
    "gn:feature_code":"PPL",
    "gn:name":"Hengdalu",
    "gn:population":0,
    "gn:timezone":"Asia/Shanghai",
    "iso:country":"CN",
    "name:zho_x_preferred":[
        "\u6a2a\u5927\u8def"
    ],
    "wof:name":"Hengdalu",
    "wof:placetype":"locality"
},
  "geometry": {"coordinates":[114.85008000000001,32.04538],"type":"Point"}
}