{
  "type": "Feature",
  "properties": {
    "gn:admin1_code":"10.0",
    "gn:asciiname":"Pangxinzhuang",
    "gn:country_code":"CN",
    "gn:dem":12,
    "gn:feature_class":"P",
    "gn:feature_code":"PPL",
    "gn:name":"Pangxinzhuang",
    "gn:population":0,
    "gn:timezone":"Asia/Shanghai",
    "iso:country":"CN",
    "name:zho_x_preferred":[
        "\u5e9e\u8f9b\u5e84"
    ],
    "wof:name":"Pangxinzhuang",
    "wof:placetype":"locality"
},
  "geometry": {"coordinates":[116.673,38.3463],"type":"Point"}
}