{
  "type": "Feature",
  "properties": {
    "gn:admin1_code":"19.0",
    "gn:asciiname":"Lisantuncun",
    "gn:country_code":"CN",
    "gn:dem":158,
    "gn:feature_class":"P",
    "gn:feature_code":"PPL",
    "gn:name":"Lisantuncun",
    "gn:population":0,
    "gn:timezone":"Asia/Shanghai",
    "iso:country":"CN",
    "name:zho_x_preferred":[
        "\u674e\u4e09\u5c6f\u6751"
    ],
    "wof:name":"Lisantuncun",
    "wof:placetype":"locality"
},
  "geometry": {"coordinates":[120.96675,41.35088],"type":"Point"}
}