{
  "type": "Feature",
  "properties": {
    "gn:admin1_code":"25.0",
    "gn:asciiname":"Lujiayuancun",
    "gn:country_code":"CN",
    "gn:dem":39,
    "gn:feature_class":"P",
    "gn:feature_code":"PPL",
    "gn:name":"Lujiayuancun",
    "gn:population":0,
    "gn:timezone":"Asia/Shanghai",
    "iso:country":"CN",
    "name:zho_x_preferred":[
        "\u9c81\u5bb6\u56ed\u6751"
    ],
    "wof:name":"Lujiayuancun",
    "wof:placetype":"locality"
},
  "geometry": {"coordinates":[119.78523,36.20709],"type":"Point"}
}