{
  "type": "Feature",
  "properties": {
    "gn:admin1_code":"12",
    "gn:asciiname":"Tongyang",
    "gn:country_code":"CN",
    "gn:dem":314,
    "gn:feature_class":"P",
    "gn:feature_code":"PPLA3",
    "gn:name":"Tongyang",
    "gn:population":0,
    "gn:timezone":"Asia/Shanghai",
    "iso:country":"CN",
    "name:ceb_x_preferred":[
        "Tongyang"
    ],
    "name:swe_x_preferred":[
        "Tongyang"
    ],
    "name:und_x_variant":[
        "Tongshan"
    ],
    "name:zho_x_preferred":[
        "T\u2019ung-shan"
    ],
    "name:zho_x_variant":[
        "T\u2019ung-shan-hsien",
        "\u901a\u7f8a"
    ],
    "wof:name":"Tongyang",
    "wof:placetype":"locality"
},
  "geometry": {"coordinates":[114.59694,29.67054000000001],"type":"Point"}
}