{
  "type": "Feature",
  "properties": {
    "gn:admin1_code":"12.0",
    "gn:asciiname":"Zhuheyang",
    "gn:country_code":"CN",
    "gn:dem":236,
    "gn:feature_class":"P",
    "gn:feature_code":"PPL",
    "gn:name":"Zhuheyang",
    "gn:population":0,
    "gn:timezone":"Asia/Shanghai",
    "iso:country":"CN",
    "name:zho_x_preferred":[
        "Zhuheyang"
    ],
    "name:zho_x_variant":[
        "\u6731\u4f55\u6768"
    ],
    "wof:name":"Zhuheyang",
    "wof:placetype":"locality"
},
  "geometry": {"coordinates":[114.98103999999999,29.76875],"type":"Point"}
}