{
  "type": "Feature",
  "properties": {
    "gn:admin1_code":"19.0",
    "gn:asciiname":"Xinlibu",
    "gn:country_code":"CN",
    "gn:dem":136,
    "gn:feature_class":"P",
    "gn:feature_code":"PPL",
    "gn:name":"Xinlibu",
    "gn:population":0,
    "gn:timezone":"Asia/Shanghai",
    "iso:country":"CN",
    "name:und_x_variant":[
        "Xinlibao",
        "Xinlibu"
    ],
    "name:zho_x_preferred":[
        "\u65b0\u7acb\u5821"
    ],
    "wof:name":"Xinlibu",
    "wof:placetype":"locality"
},
  "geometry": {"coordinates":[124.11216,42.75241],"type":"Point"}
}