{
  "type": "Feature",
  "properties": {
    "gn:admin1_code":"11.0",
    "gn:asciiname":"Zhaitian",
    "gn:country_code":"CN",
    "gn:dem":238,
    "gn:feature_class":"P",
    "gn:feature_code":"PPL",
    "gn:name":"Zhaitian",
    "gn:population":0,
    "gn:timezone":"Asia/Shanghai",
    "iso:country":"CN",
    "name:zho_x_preferred":[
        "\u5b85\u7530"
    ],
    "wof:name":"Zhaitian",
    "wof:placetype":"locality"
},
  "geometry": {"coordinates":[111.27034999999999,26.03729],"type":"Point"}
}