{
  "type": "Feature",
  "properties": {
    "gn:admin1_code":"11.0",
    "gn:asciiname":"Tongmuzhai",
    "gn:country_code":"CN",
    "gn:dem":596,
    "gn:feature_class":"P",
    "gn:feature_code":"PPL",
    "gn:name":"Tongmuzhai",
    "gn:population":0,
    "gn:timezone":"Asia/Shanghai",
    "iso:country":"CN",
    "name:zho_x_preferred":[
        "\u6850\u6728\u5be8"
    ],
    "wof:name":"Tongmuzhai",
    "wof:placetype":"locality"
},
  "geometry": {"coordinates":[109.6049,28.35184000000001],"type":"Point"}
}