{
  "type": "Feature",
  "properties": {
    "gn:admin1_code":"16.0",
    "gn:asciiname":"Kuaile",
    "gn:country_code":"CN",
    "gn:dem":863,
    "gn:feature_class":"P",
    "gn:feature_code":"PPL",
    "gn:name":"Kuaile",
    "gn:population":0,
    "gn:timezone":"Asia/Shanghai",
    "iso:country":"CN",
    "name:zho_x_preferred":[
        "\u5feb\u4e50"
    ],
    "wof:name":"Kuaile",
    "wof:placetype":"locality"
},
  "geometry": {"coordinates":[105.411,24.8095],"type":"Point"}
}