{
  "type": "Feature",
  "properties": {
    "gn:admin1_code":"30.0",
    "gn:asciiname":"Dalutou",
    "gn:country_code":"CN",
    "gn:dem":13,
    "gn:feature_class":"P",
    "gn:feature_code":"PPL",
    "gn:name":"Dalutou",
    "gn:population":0,
    "gn:timezone":"Asia/Shanghai",
    "iso:country":"CN",
    "name:zho_x_preferred":[
        "\u5927\u8f05\u5934"
    ],
    "wof:name":"Dalutou",
    "wof:placetype":"locality"
},
  "geometry": {"coordinates":[112.52488999999998,22.99775],"type":"Point"}
}