{
  "type": "Feature",
  "properties": {
    "gn:admin1_code":"26.0",
    "gn:asciiname":"Miaodonggoucun",
    "gn:country_code":"CN",
    "gn:dem":972,
    "gn:feature_class":"P",
    "gn:feature_code":"PPL",
    "gn:name":"Miaodonggoucun",
    "gn:population":0,
    "gn:timezone":"Asia/Shanghai",
    "iso:country":"CN",
    "name:zho_x_preferred":[
        "\u5e99\u4e1c\u6c9f\u6751"
    ],
    "wof:name":"Miaodonggoucun",
    "wof:placetype":"locality"
},
  "geometry": {"coordinates":[109.61839000000001,33.6212],"type":"Point"}
}