{
  "type": "Feature",
  "properties": {
    "gn:admin1_code":"4.0",
    "gn:asciiname":"Xiaoyongjiaxia",
    "gn:country_code":"CN",
    "gn:dem":4,
    "gn:feature_class":"P",
    "gn:feature_code":"PPL",
    "gn:name":"Xiaoyongjiaxia",
    "gn:population":0,
    "gn:timezone":"Asia/Shanghai",
    "iso:country":"CN",
    "name:zho_x_preferred":[
        "\u5c0f\u96cd\u5bb6\u53a6"
    ],
    "wof:name":"Xiaoyongjiaxia",
    "wof:placetype":"locality"
},
  "geometry": {"coordinates":[119.54397,32.89647],"type":"Point"}
}