{
  "type": "Feature",
  "properties": {
    "gn:admin1_code":"30.0",
    "gn:asciiname":"Huanqiu",
    "gn:country_code":"CN",
    "gn:dem":189,
    "gn:feature_class":"P",
    "gn:feature_code":"PPL",
    "gn:name":"Huanqiu",
    "gn:population":0,
    "gn:timezone":"Asia/Urumqi",
    "iso:country":"CN",
    "name:zho_x_preferred":[
        "\u73af\u7403"
    ],
    "wof:name":"Huanqiu",
    "wof:placetype":"locality"
},
  "geometry": {"coordinates":[110.82229,22.52351],"type":"Point"}
}