{
  "type": "Feature",
  "properties": {
    "gn:admin1_code":"4.0",
    "gn:asciiname":"Xijiangxiang",
    "gn:country_code":"CN",
    "gn:dem":21,
    "gn:feature_class":"P",
    "gn:feature_code":"PPL",
    "gn:name":"Xijiangxiang",
    "gn:population":0,
    "gn:timezone":"Asia/Shanghai",
    "iso:country":"CN",
    "name:zho_x_preferred":[
        "\u897f\u59dc\u5df7"
    ],
    "wof:name":"Xijiangxiang",
    "wof:placetype":"locality"
},
  "geometry": {"coordinates":[119.07149,31.71256],"type":"Point"}
}