{
  "type": "Feature",
  "properties": {
    "gn:admin1_code":"19.0",
    "gn:asciiname":"Xidasi",
    "gn:country_code":"CN",
    "gn:dem":10,
    "gn:feature_class":"P",
    "gn:feature_code":"PPL",
    "gn:name":"Xidasi",
    "gn:population":0,
    "gn:timezone":"Asia/Shanghai",
    "iso:country":"CN",
    "name:und_x_variant":[
        "\u897f\u5927\u5bfa"
    ],
    "name:zho_x_preferred":[
        "\u897f\u5927\u5bfa"
    ],
    "wof:name":"Xidasi",
    "wof:placetype":"locality"
},
  "geometry": {"coordinates":[122.866,41.303],"type":"Point"}
}