{
  "type": "Feature",
  "properties": {
    "gn:admin1_code":"20.0",
    "gn:asciiname":"Bilitu",
    "gn:country_code":"CN",
    "gn:dem":423,
    "gn:feature_class":"P",
    "gn:feature_code":"PPL",
    "gn:name":"Bilitu",
    "gn:population":0,
    "gn:timezone":"Asia/Shanghai",
    "iso:country":"CN",
    "name:zho_x_preferred":[
        "\u5fc5\u91cc\u5154"
    ],
    "wof:name":"Bilitu",
    "wof:placetype":"locality"
},
  "geometry": {"coordinates":[122.07619,47.68626],"type":"Point"}
}