{
  "type": "Feature",
  "properties": {
    "gn:admin1_code":"14.0",
    "gn:asciiname":"Segongcun",
    "gn:country_code":"CN",
    "gn:dem":3196,
    "gn:feature_class":"P",
    "gn:feature_code":"PPL",
    "gn:name":"Segongcun",
    "gn:population":0,
    "gn:timezone":"Asia/Urumqi",
    "iso:country":"CN",
    "name:zho_x_preferred":[
        "\u8272\u8d21\u6751"
    ],
    "wof:name":"Segongcun",
    "wof:placetype":"locality"
},
  "geometry": {"coordinates":[93.81395999999999,29.78349],"type":"Point"}
}