{
  "type": "Feature",
  "properties": {
    "gn:admin1_code":"4.0",
    "gn:asciiname":"Yanhe",
    "gn:country_code":"CN",
    "gn:dem":7,
    "gn:feature_class":"P",
    "gn:feature_code":"PPL",
    "gn:name":"Yanhe",
    "gn:population":0,
    "gn:timezone":"Asia/Shanghai",
    "iso:country":"CN",
    "name:ceb_x_preferred":[
        "Yanhe"
    ],
    "name:deu_x_preferred":[
        "Yanhe"
    ],
    "name:fra_x_preferred":[
        "Yanhe"
    ],
    "name:und_x_variant":[
        "\u76d0\u6cb3"
    ],
    "wof:name":"Yanhe",
    "wof:placetype":"locality"
},
  "geometry": {"coordinates":[121.08561,32.19948],"type":"Point"}
}