{
  "type": "Feature",
  "properties": {
    "gn:admin1_code":"14.0",
    "gn:asciiname":"Debuchule",
    "gn:country_code":"CN",
    "gn:dem":4634,
    "gn:feature_class":"P",
    "gn:feature_code":"PPL",
    "gn:name":"Debuchule",
    "gn:population":0,
    "gn:timezone":"Asia/Urumqi",
    "iso:country":"CN",
    "name:zho_x_preferred":[
        "\u5f97\u5e03\u51fa\u52d2"
    ],
    "wof:name":"Debuchule",
    "wof:placetype":"locality"
},
  "geometry": {"coordinates":[83.76299999999998,31.8377],"type":"Point"}
}