{
  "type": "Feature",
  "properties": {
    "gn:admin1_code":"25.0",
    "gn:asciiname":"Zhalantou",
    "gn:country_code":"CN",
    "gn:dem":98,
    "gn:feature_class":"P",
    "gn:feature_code":"PPL",
    "gn:name":"Zhalantou",
    "gn:population":0,
    "gn:timezone":"Asia/Shanghai",
    "iso:country":"CN",
    "name:zho_x_preferred":[
        "\u67de\u5c9a\u5934"
    ],
    "wof:name":"Zhalantou",
    "wof:placetype":"locality"
},
  "geometry": {"coordinates":[120.65776,37.20858],"type":"Point"}
}