{
  "type": "Feature",
  "properties": {
    "gn:admin1_code":"5.0",
    "gn:asciiname":"Sanpingshancun",
    "gn:country_code":"CN",
    "gn:dem":187,
    "gn:feature_class":"P",
    "gn:feature_code":"PPL",
    "gn:name":"Sanpingshancun",
    "gn:population":0,
    "gn:timezone":"Asia/Shanghai",
    "iso:country":"CN",
    "name:zho_x_preferred":[
        "\u4e09\u5e73\u5c71\u6751"
    ],
    "wof:name":"Sanpingshancun",
    "wof:placetype":"locality"
},
  "geometry": {"coordinates":[123.99112,44.35592000000001],"type":"Point"}
}