{
  "type": "Feature",
  "properties": {
    "gn:admin1_code":"29.0",
    "gn:asciiname":"Yaopengzi",
    "gn:country_code":"CN",
    "gn:dem":2809,
    "gn:feature_class":"P",
    "gn:feature_code":"PPL",
    "gn:name":"Yaopengzi",
    "gn:population":0,
    "gn:timezone":"Asia/Shanghai",
    "iso:country":"CN",
    "name:zho_x_preferred":[
        "\u8170\u68da\u5b50"
    ],
    "wof:name":"Yaopengzi",
    "wof:placetype":"locality"
},
  "geometry": {"coordinates":[103.018,26.2926],"type":"Point"}
}