{
  "type": "Feature",
  "properties": {
    "gn:admin1_code":"26.0",
    "gn:asciiname":"Dachenjiagoucun",
    "gn:country_code":"CN",
    "gn:dem":978,
    "gn:feature_class":"P",
    "gn:feature_code":"PPL",
    "gn:name":"Dachenjiagoucun",
    "gn:population":0,
    "gn:timezone":"Asia/Shanghai",
    "iso:country":"CN",
    "name:zho_x_preferred":[
        "\u5927\u9648\u5bb6\u6c9f\u6751"
    ],
    "wof:name":"Dachenjiagoucun",
    "wof:placetype":"locality"
},
  "geometry": {"coordinates":[110.03288999999999,37.16381],"type":"Point"}
}