{
  "type": "Feature",
  "properties": {
    "gn:admin1_code":"16.0",
    "gn:asciiname":"Changpojiang",
    "gn:country_code":"CN",
    "gn:dem":21,
    "gn:feature_class":"P",
    "gn:feature_code":"PPL",
    "gn:name":"Changpojiang",
    "gn:population":0,
    "gn:timezone":"Asia/Shanghai",
    "iso:country":"CN",
    "name:zho_x_preferred":[
        "\u957f\u5761\u6c5f"
    ],
    "wof:name":"Changpojiang",
    "wof:placetype":"locality"
},
  "geometry": {"coordinates":[109.444,21.5849],"type":"Point"}
}