{
  "type": "Feature",
  "properties": {
    "gn:admin1_code":"15.0",
    "gn:asciiname":"Taishi",
    "gn:country_code":"CN",
    "gn:dem":1578,
    "gn:feature_class":"P",
    "gn:feature_code":"PPL",
    "gn:name":"Taishi",
    "gn:population":0,
    "gn:timezone":"Asia/Shanghai",
    "iso:country":"CN",
    "name:zho_x_preferred":[
        "\u592a\u77f3"
    ],
    "wof:name":"Taishi",
    "wof:placetype":"locality"
},
  "geometry": {"coordinates":[106.238,34.684],"type":"Point"}
}