{
  "type": "Feature",
  "properties": {
    "gn:admin1_code":"26.0",
    "gn:asciiname":"Huodiwan",
    "gn:country_code":"CN",
    "gn:dem":1356,
    "gn:feature_class":"P",
    "gn:feature_code":"PPL",
    "gn:name":"Huodiwan",
    "gn:population":0,
    "gn:timezone":"Asia/Shanghai",
    "iso:country":"CN",
    "name:und_x_variant":[
        "\u706b\u5730\u6e7e"
    ],
    "wof:name":"Huodiwan",
    "wof:placetype":"locality"
},
  "geometry": {"coordinates":[106.20775999999999,33.24501],"type":"Point"}
}