{
  "type": "Feature",
  "properties": {
    "gn:admin1_code":"11.0",
    "gn:asciiname":"Jigongshixia",
    "gn:country_code":"CN",
    "gn:dem":702,
    "gn:feature_class":"P",
    "gn:feature_code":"PPL",
    "gn:name":"Jigongshixia",
    "gn:population":0,
    "gn:timezone":"Asia/Shanghai",
    "iso:country":"CN",
    "name:zho_x_preferred":[
        "\u9e21\u516c\u77f3\u4e0b"
    ],
    "wof:name":"Jigongshixia",
    "wof:placetype":"locality"
},
  "geometry": {"coordinates":[112.72826999999999,25.5095],"type":"Point"}
}