{
  "type": "Feature",
  "properties": {
    "gn:admin1_code":"33.0",
    "gn:asciiname":"Pingtang",
    "gn:country_code":"CN",
    "gn:dem":946,
    "gn:feature_class":"P",
    "gn:feature_code":"PPL",
    "gn:name":"Pingtang",
    "gn:population":0,
    "gn:timezone":"Asia/Shanghai",
    "iso:country":"CN",
    "name:zho_x_preferred":[
        "\u576a\u6dcc"
    ],
    "wof:name":"Pingtang",
    "wof:placetype":"locality"
},
  "geometry": {"coordinates":[109.48875,30.9571],"type":"Point"}
}