{
  "type": "Feature",
  "properties": {
    "gn:admin1_code":"26.0",
    "gn:asciiname":"Gaojia Lengcun",
    "gn:country_code":"CN",
    "gn:dem":980,
    "gn:feature_class":"P",
    "gn:feature_code":"PPL",
    "gn:name":"Gaojia Lengcun",
    "gn:population":0,
    "gn:timezone":"Asia/Shanghai",
    "iso:country":"CN",
    "name:zho_x_preferred":[
        "\u9ad8\u5bb6\u5844\u6751"
    ],
    "wof:name":"Gaojia Lengcun",
    "wof:placetype":"locality"
},
  "geometry": {"coordinates":[110.517,37.76300000000001],"type":"Point"}
}