{
  "type": "Feature",
  "properties": {
    "gn:admin1_code":"15.0",
    "gn:asciiname":"Tugou",
    "gn:country_code":"CN",
    "gn:dem":1921,
    "gn:feature_class":"P",
    "gn:feature_code":"PPL",
    "gn:name":"Tugou",
    "gn:population":0,
    "gn:timezone":"Asia/Shanghai",
    "iso:country":"CN",
    "name:zho_x_preferred":[
        "\u571f\u6c9f"
    ],
    "wof:name":"Tugou",
    "wof:placetype":"locality"
},
  "geometry": {"coordinates":[103.44,37.4525],"type":"Point"}
}