{
  "type": "Feature",
  "properties": {
    "gn:admin1_code":"33.0",
    "gn:asciiname":"Guan'erkan",
    "gn:country_code":"CN",
    "gn:dem":201,
    "gn:feature_class":"P",
    "gn:feature_code":"PPL",
    "gn:name":"Guan\u2019erkan",
    "gn:population":0,
    "gn:timezone":"Asia/Shanghai",
    "iso:country":"CN",
    "name:und_x_variant":[
        "Guan\u2019erkan"
    ],
    "name:zho_x_preferred":[
        "\u5b98\u8033\u574e"
    ],
    "wof:name":"Guan'erkan",
    "wof:placetype":"locality"
},
  "geometry": {"coordinates":[107.61911000000001,30.07707000000001],"type":"Point"}
}