{
  "type": "Feature",
  "properties": {
    "gn:admin1_code":"33.0",
    "gn:asciiname":"Qiuguping",
    "gn:country_code":"CN",
    "gn:dem":863,
    "gn:feature_class":"P",
    "gn:feature_code":"PPL",
    "gn:name":"Qiuguping",
    "gn:population":0,
    "gn:timezone":"Asia/Shanghai",
    "iso:country":"CN",
    "name:zho_x_preferred":[
        "\u79cb\u8c37\u576a"
    ],
    "wof:name":"Qiuguping",
    "wof:placetype":"locality"
},
  "geometry": {"coordinates":[108.80137000000001,28.65712000000001],"type":"Point"}
}