{
  "type": "Feature",
  "properties": {
    "gn:admin1_code":"16.0",
    "gn:asciiname":"Na'an",
    "gn:country_code":"CN",
    "gn:dem":519,
    "gn:feature_class":"P",
    "gn:feature_code":"PPL",
    "gn:name":"Na\u2019an",
    "gn:population":0,
    "gn:timezone":"Asia/Shanghai",
    "iso:country":"CN",
    "name:ces_x_preferred":[
        "Na'an"
    ],
    "name:deu_x_preferred":[
        "Na\u02bfan"
    ],
    "name:fra_x_preferred":[
        "Na'an"
    ],
    "name:heb_x_preferred":[
        "\u05e0\u05e2\u05df"
    ],
    "name:nno_x_preferred":[
        "Na'an"
    ],
    "name:pol_x_preferred":[
        "Na\u2019an"
    ],
    "name:rus_x_preferred":[
        "\u041d\u0430\u0430\u043d"
    ],
    "name:zho_x_preferred":[
        "\u90a3\u5b89"
    ],
    "wof:name":"Na'an",
    "wof:placetype":"locality"
},
  "geometry": {"coordinates":[105.435,24.9202],"type":"Point"}
}