{
  "type": "Feature",
  "properties": {
    "gn:admin1_code":"33.0",
    "gn:asciiname":"Wenhua",
    "gn:country_code":"CN",
    "gn:dem":460,
    "gn:feature_class":"P",
    "gn:feature_code":"PPLA4",
    "gn:name":"Wenhua",
    "gn:population":0,
    "gn:timezone":"Asia/Shanghai",
    "iso:country":"CN",
    "name:und_x_variant":[
        "Wenhua Zhen",
        "Luosidian"
    ],
    "name:zho_x_preferred":[
        "\u6587\u5316"
    ],
    "name:zho_x_variant":[
        "\u6587\u5316\u9547",
        "\u87ba\u86f3\u5e97"
    ],
    "wof:name":"Wenhua",
    "wof:placetype":"locality"
},
  "geometry": {"coordinates":[107.77436000000002,30.81436],"type":"Point"}
}