{
  "type": "Feature",
  "properties": {
    "gn:admin1_code":"29.0",
    "gn:asciiname":"Yulepingzhai",
    "gn:country_code":"CN",
    "gn:dem":1136,
    "gn:feature_class":"P",
    "gn:feature_code":"PPL",
    "gn:name":"Yulepingzhai",
    "gn:population":0,
    "gn:timezone":"Asia/Shanghai",
    "iso:country":"CN",
    "name:zho_x_preferred":[
        "\u79b9\u4e50\u5e73\u5be8"
    ],
    "wof:name":"Yulepingzhai",
    "wof:placetype":"locality"
},
  "geometry": {"coordinates":[103.96299999999999,24.403],"type":"Point"}
}