{
  "type": "Feature",
  "properties": {
    "gn:admin1_code":"7.0",
    "gn:asciiname":"Changtan Famuchang",
    "gn:country_code":"CN",
    "gn:dem":311,
    "gn:feature_class":"P",
    "gn:feature_code":"PPL",
    "gn:name":"Changtan Famuchang",
    "gn:population":0,
    "gn:timezone":"Asia/Shanghai",
    "iso:country":"CN",
    "name:zho_x_preferred":[
        "\u957f\u6ee9\u4f10\u6728\u573a"
    ],
    "wof:name":"Changtan Famuchang",
    "wof:placetype":"locality"
},
  "geometry": {"coordinates":[117.87860000000001,27.77154],"type":"Point"}
}