{
  "type": "Feature",
  "properties": {
    "gn:admin1_code":"4.0",
    "gn:asciiname":"Houwang",
    "gn:country_code":"CN",
    "gn:dem":1,
    "gn:feature_class":"P",
    "gn:feature_code":"PPL",
    "gn:name":"Houwang",
    "gn:population":0,
    "gn:timezone":"Asia/Shanghai",
    "iso:country":"CN",
    "name:zho_x_preferred":[
        "Houwang"
    ],
    "name:zho_x_variant":[
        "\u540e\u738b"
    ],
    "wof:name":"Houwang",
    "wof:placetype":"locality"
},
  "geometry": {"coordinates":[119.53094,33.45123],"type":"Point"}
}