{
  "type": "Feature",
  "properties": {
    "gn:admin1_code":"23.0",
    "gn:asciiname":"Shengxin",
    "gn:country_code":"CN",
    "gn:dem":4,
    "gn:feature_class":"P",
    "gn:feature_code":"PPL",
    "gn:name":"Shengxin",
    "gn:population":0,
    "gn:timezone":"Asia/Shanghai",
    "iso:country":"CN",
    "name:und_x_variant":[
        "\u80dc\u65b0"
    ],
    "wof:name":"Shengxin",
    "wof:placetype":"locality"
},
  "geometry": {"coordinates":[121.15618000000001,31.26517],"type":"Point"}
}