{
  "type": "Feature",
  "properties": {
    "gn:admin1_code":"30",
    "gn:asciiname":"Zhagang",
    "gn:country_code":"CN",
    "gn:dem":78,
    "gn:feature_class":"P",
    "gn:feature_code":"PPLA4",
    "gn:name":"Zhagang",
    "gn:population":0,
    "gn:timezone":"Asia/Shanghai",
    "iso:country":"CN",
    "name:und_x_variant":[
        "Zhagang Zhen",
        "\u95f8\u5c97\u9547"
    ],
    "wof:name":"Zhagang",
    "wof:placetype":"locality"
},
  "geometry": {"coordinates":[112.10035000000001,23.83235],"type":"Point"}
}