{
  "type": "Feature",
  "properties": {
    "gn:admin1_code":"26.0",
    "gn:asciiname":"Qiao'erwan",
    "gn:country_code":"CN",
    "gn:dem":1034,
    "gn:feature_class":"P",
    "gn:feature_code":"PPL",
    "gn:name":"Qiao\u2019erwan",
    "gn:population":0,
    "gn:timezone":"Asia/Shanghai",
    "iso:country":"CN",
    "name:und_x_variant":[
        "Qiao\u2019erwan"
    ],
    "name:zho_x_preferred":[
        "\u4e54\u513f\u6e7e"
    ],
    "wof:name":"Qiao'erwan",
    "wof:placetype":"locality"
},
  "geometry": {"coordinates":[108.11667,32.95967],"type":"Point"}
}