{
  "type": "Feature",
  "properties": {
    "gn:admin1_code":"26.0",
    "gn:asciiname":"Qinyuancun",
    "gn:country_code":"CN",
    "gn:dem":1042,
    "gn:feature_class":"P",
    "gn:feature_code":"PPL",
    "gn:name":"Qinyuancun",
    "gn:population":0,
    "gn:timezone":"Asia/Shanghai",
    "iso:country":"CN",
    "name:zho_x_preferred":[
        "\u82b9\u56ed\u6751"
    ],
    "wof:name":"Qinyuancun",
    "wof:placetype":"locality"
},
  "geometry": {"coordinates":[109.6434,37.53837],"type":"Point"}
}