{
  "type": "Feature",
  "properties": {
    "gn:admin1_code":"33",
    "gn:asciiname":"Baisha",
    "gn:country_code":"CN",
    "gn:dem":233,
    "gn:feature_class":"P",
    "gn:feature_code":"PPLA4",
    "gn:name":"Baisha",
    "gn:population":0,
    "gn:timezone":"Asia/Shanghai",
    "iso:country":"CN",
    "name:und_x_variant":[
        "Pai-sha",
        "Baisha",
        "Baisha Zhen"
    ],
    "name:zho_x_preferred":[
        "\u767d\u6c99"
    ],
    "name:zho_x_variant":[
        "\u767d\u6c99\u9547"
    ],
    "wof:name":"Baisha",
    "wof:placetype":"locality"
},
  "geometry": {"coordinates":[106.1189,29.06226],"type":"Point"}
}