{
  "type": "Feature",
  "properties": {
    "gn:admin1_code":"29.0",
    "gn:asciiname":"Ganjiapingzi",
    "gn:country_code":"CN",
    "gn:dem":1493,
    "gn:feature_class":"P",
    "gn:feature_code":"PPL",
    "gn:name":"Ganjiapingzi",
    "gn:population":0,
    "gn:timezone":"Asia/Shanghai",
    "iso:country":"CN",
    "name:zho_x_preferred":[
        "\u7518\u5bb6\u576a\u5b50"
    ],
    "wof:name":"Ganjiapingzi",
    "wof:placetype":"locality"
},
  "geometry": {"coordinates":[100.06,25.2525],"type":"Point"}
}