{
  "type": "Feature",
  "properties": {
    "gn:admin1_code":"16.0",
    "gn:asciiname":"Liangyou Xiazhai",
    "gn:country_code":"CN",
    "gn:dem":327,
    "gn:feature_class":"P",
    "gn:feature_code":"PPL",
    "gn:name":"Liangyou Xiazhai",
    "gn:population":0,
    "gn:timezone":"Asia/Shanghai",
    "iso:country":"CN",
    "name:zho_x_preferred":[
        "\u826f\u53cb\u4e0b\u5be8"
    ],
    "wof:name":"Liangyou Xiazhai",
    "wof:placetype":"locality"
},
  "geometry": {"coordinates":[109.166,25.5521],"type":"Point"}
}