{
  "type": "Feature",
  "properties": {
    "gn:admin1_code":"4.0",
    "gn:asciiname":"Tongzhu",
    "gn:country_code":"CN",
    "gn:dem":33,
    "gn:feature_class":"P",
    "gn:feature_code":"PPL",
    "gn:name":"Tongzhu",
    "gn:population":0,
    "gn:timezone":"Asia/Shanghai",
    "iso:country":"CN",
    "name:zho_x_preferred":[
        "\u6f7c\u6e1a"
    ],
    "wof:name":"Tongzhu",
    "wof:placetype":"locality"
},
  "geometry": {"coordinates":[119.32137,31.63606],"type":"Point"}
}