{
  "type": "Feature",
  "properties": {
    "gn:admin1_code":"4.0",
    "gn:asciiname":"Kaiyicun",
    "gn:country_code":"CN",
    "gn:dem":6,
    "gn:feature_class":"P",
    "gn:feature_code":"PPL",
    "gn:name":"Kaiyicun",
    "gn:population":0,
    "gn:timezone":"Asia/Shanghai",
    "iso:country":"CN",
    "name:zho_x_preferred":[
        "\u5f00\u4e00\u6751"
    ],
    "wof:name":"Kaiyicun",
    "wof:placetype":"locality"
},
  "geometry": {"coordinates":[120.13312000000001,32.6831],"type":"Point"}
}