{
  "type": "Feature",
  "properties": {
    "gn:admin1_code":"18",
    "gn:asciiname":"Guoshizhai",
    "gn:country_code":"CN",
    "gn:dem":598,
    "gn:feature_class":"P",
    "gn:feature_code":"PPL",
    "gn:name":"Guoshizhai",
    "gn:population":0,
    "gn:timezone":"Asia/Shanghai",
    "iso:country":"CN",
    "name:zho_x_preferred":[
        "\u8fc7\u77f3\u5be8"
    ],
    "wof:name":"Guoshizhai",
    "wof:placetype":"locality"
},
  "geometry": {"coordinates":[106.541,25.3128],"type":"Point"}
}