{
  "type": "Feature",
  "properties": {
    "gn:admin1_code":"15.0",
    "gn:asciiname":"Huigoutaizi",
    "gn:country_code":"CN",
    "gn:dem":2817,
    "gn:feature_class":"P",
    "gn:feature_code":"PPL",
    "gn:name":"Huigoutaizi",
    "gn:population":0,
    "gn:timezone":"Asia/Shanghai",
    "iso:country":"CN",
    "name:und_x_variant":[
        "\u56de\u6c9f\u53f0\u5b50"
    ],
    "wof:name":"Huigoutaizi",
    "wof:placetype":"locality"
},
  "geometry": {"coordinates":[103.89371,34.57944000000001],"type":"Point"}
}