{
  "type": "Feature",
  "properties": {
    "gn:admin1_code":"6.0",
    "gn:asciiname":"Jiaolangge",
    "gn:country_code":"CN",
    "gn:dem":3865,
    "gn:feature_class":"P",
    "gn:feature_code":"PPL",
    "gn:name":"Jiaolangge",
    "gn:population":0,
    "gn:timezone":"Asia/Urumqi",
    "iso:country":"CN",
    "name:zho_x_preferred":[
        "\u89d2\u90ce\u683c"
    ],
    "wof:name":"Jiaolangge",
    "wof:placetype":"locality"
},
  "geometry": {"coordinates":[97.25242,32.1941],"type":"Point"}
}