{
  "type": "Feature",
  "properties": {
    "gn:admin1_code":"29.0",
    "gn:asciiname":"Wuzugou",
    "gn:country_code":"CN",
    "gn:dem":1990,
    "gn:feature_class":"P",
    "gn:feature_code":"PPL",
    "gn:name":"Wuzugou",
    "gn:population":0,
    "gn:timezone":"Asia/Shanghai",
    "iso:country":"CN",
    "name:zho_x_preferred":[
        "\u4e94\u79df\u6c9f"
    ],
    "wof:name":"Wuzugou",
    "wof:placetype":"locality"
},
  "geometry": {"coordinates":[103.881,24.2086],"type":"Point"}
}