{
  "type": "Feature",
  "properties": {
    "gn:admin1_code":"9.0",
    "gn:asciiname":"Lizhuang",
    "gn:country_code":"CN",
    "gn:dem":124,
    "gn:feature_class":"P",
    "gn:feature_code":"PPL",
    "gn:name":"Lizhuang",
    "gn:population":0,
    "gn:timezone":"Asia/Shanghai",
    "iso:country":"CN",
    "name:zho_x_preferred":[
        "\u674e\u5e84"
    ],
    "wof:name":"Lizhuang",
    "wof:placetype":"locality"
},
  "geometry": {"coordinates":[112.47356000000001,32.93658],"type":"Point"}
}