{
  "type": "Feature",
  "properties": {
    "gn:admin1_code":"25",
    "gn:asciiname":"Dayiji",
    "gn:cc2":"CN",
    "gn:country_code":"CN",
    "gn:dem":53,
    "gn:feature_class":"P",
    "gn:feature_code":"PPL",
    "gn:name":"Dayiji",
    "gn:population":0,
    "gn:timezone":"Asia/Shanghai",
    "iso:country":"CN",
    "name:und_x_variant":[
        "Ta-i-chi",
        "Dayiji"
    ],
    "wof:name":"Dayiji",
    "wof:placetype":"locality"
},
  "geometry": {"coordinates":[115.61667,34.71667],"type":"Point"}
}