{
  "type": "Feature",
  "properties": {
    "gn:admin1_code":"3.0",
    "gn:asciiname":"Shanlilei",
    "gn:country_code":"CN",
    "gn:dem":120,
    "gn:feature_class":"P",
    "gn:feature_code":"PPL",
    "gn:name":"Shanlilei",
    "gn:population":0,
    "gn:timezone":"Asia/Shanghai",
    "iso:country":"CN",
    "name:und_x_variant":[
        "\u5c71\u91cc\u96f7"
    ],
    "wof:name":"Shanlilei",
    "wof:placetype":"locality"
},
  "geometry": {"coordinates":[115.49842,29.51845],"type":"Point"}
}