{
  "type": "Feature",
  "properties": {
    "gn:admin1_code":"11.0",
    "gn:asciiname":"Shuangyantang",
    "gn:country_code":"CN",
    "gn:dem":177,
    "gn:feature_class":"P",
    "gn:feature_code":"PPL",
    "gn:name":"Shuangyantang",
    "gn:population":0,
    "gn:timezone":"Asia/Shanghai",
    "iso:country":"CN",
    "name:zho_x_preferred":[
        "Shuangyantang"
    ],
    "name:zho_x_variant":[
        "\u53cc\u5830\u5858"
    ],
    "wof:name":"Shuangyantang",
    "wof:placetype":"locality"
},
  "geometry": {"coordinates":[111.47105999999999,29.85058],"type":"Point"}
}