{
  "type": "Feature",
  "properties": {
    "gn:admin1_code":"4.0",
    "gn:asciiname":"Jiexi",
    "gn:country_code":"CN",
    "gn:dem":1,
    "gn:feature_class":"P",
    "gn:feature_code":"PPL",
    "gn:name":"Jiexi",
    "gn:population":0,
    "gn:timezone":"Asia/Shanghai",
    "iso:country":"CN",
    "name:zho_x_preferred":[
        "\u6377\u897f"
    ],
    "wof:name":"Jiexi",
    "wof:placetype":"locality"
},
  "geometry": {"coordinates":[120.17014,32.99804],"type":"Point"}
}