{
  "type": "Feature",
  "properties": {
    "gn:admin1_code":"10",
    "gn:asciiname":"Malianqu",
    "gn:country_code":"CN",
    "gn:dem":1473,
    "gn:feature_class":"P",
    "gn:feature_code":"PPL",
    "gn:name":"Malianqu",
    "gn:population":0,
    "gn:timezone":"Asia/Shanghai",
    "iso:country":"CN",
    "name:und_x_variant":[
        "Ma-lien-ch\u2019\u00fc",
        "Malianqu"
    ],
    "name:zho_x_preferred":[
        "\u9a6c\u8fde\u6e20"
    ],
    "wof:name":"Malianqu",
    "wof:placetype":"locality"
},
  "geometry": {"coordinates":[114.54318000000001,41.09911],"type":"Point"}
}