{
  "type": "Feature",
  "properties": {
    "gn:admin1_code":"10.0",
    "gn:asciiname":"Erchang Wudui",
    "gn:country_code":"CN",
    "gn:dem":3,
    "gn:feature_class":"P",
    "gn:feature_code":"PPLF",
    "gn:name":"Erchang Wudui",
    "gn:population":0,
    "gn:timezone":"Asia/Shanghai",
    "iso:country":"CN",
    "name:zho_x_preferred":[
        "\u4e8c\u573a\u4e94\u961f"
    ],
    "wof:name":"Erchang Wudui",
    "wof:placetype":"locality"
},
  "geometry": {"coordinates":[118.39315999999999,39.31447],"type":"Point"}
}