{
  "type": "Feature",
  "properties": {
    "gn:admin1_code":"26.0",
    "gn:asciiname":"Huawuchang",
    "gn:country_code":"CN",
    "gn:dem":814,
    "gn:feature_class":"P",
    "gn:feature_code":"PPL",
    "gn:name":"Huawuchang",
    "gn:population":0,
    "gn:timezone":"Asia/Shanghai",
    "iso:country":"CN",
    "name:zho_x_preferred":[
        "\u82b1\u5c4b\u573a"
    ],
    "wof:name":"Huawuchang",
    "wof:placetype":"locality"
},
  "geometry": {"coordinates":[109.41875,33.35914],"type":"Point"}
}