{
  "type": "Feature",
  "properties": {
    "gn:admin1_code":"29",
    "gn:asciiname":"Xinghuacun",
    "gn:country_code":"CN",
    "gn:dem":1760,
    "gn:feature_class":"P",
    "gn:feature_code":"PPL",
    "gn:name":"Xinghuacun",
    "gn:population":0,
    "gn:timezone":"Asia/Shanghai",
    "iso:country":"CN",
    "name:zho_x_preferred":[
        "\u674f\u82b1\u6751"
    ],
    "wof:name":"Xinghuacun",
    "wof:placetype":"locality"
},
  "geometry": {"coordinates":[102.22873,24.86402],"type":"Point"}
}