{
  "type": "Feature",
  "properties": {
    "gn:admin1_code":"15.0",
    "gn:asciiname":"Nuanshuiba",
    "gn:country_code":"CN",
    "gn:dem":2577,
    "gn:feature_class":"P",
    "gn:feature_code":"PPL",
    "gn:name":"Nuanshuiba",
    "gn:population":0,
    "gn:timezone":"Asia/Shanghai",
    "iso:country":"CN",
    "name:zho_x_preferred":[
        "\u6696\u6c34\u575d"
    ],
    "wof:name":"Nuanshuiba",
    "wof:placetype":"locality"
},
  "geometry": {"coordinates":[104.75845,33.63017],"type":"Point"}
}