{
  "type": "Feature",
  "properties": {
    "gn:admin1_code":"15.0",
    "gn:asciiname":"Sijiagou",
    "gn:country_code":"CN",
    "gn:dem":1261,
    "gn:feature_class":"P",
    "gn:feature_code":"PPL",
    "gn:name":"Sijiagou",
    "gn:population":0,
    "gn:timezone":"Asia/Shanghai",
    "iso:country":"CN",
    "name:zho_x_preferred":[
        "\u5bfa\u5bb6\u6c9f"
    ],
    "wof:name":"Sijiagou",
    "wof:placetype":"locality"
},
  "geometry": {"coordinates":[106.974,35.6907],"type":"Point"}
}