{
  "type": "Feature",
  "properties": {
    "gn:admin1_code":"19.0",
    "gn:asciiname":"Qianbucun",
    "gn:country_code":"CN",
    "gn:dem":109,
    "gn:feature_class":"P",
    "gn:feature_code":"PPL",
    "gn:name":"Qianbucun",
    "gn:population":0,
    "gn:timezone":"Asia/Shanghai",
    "iso:country":"CN",
    "name:zho_x_preferred":[
        "\u524d\u5821\u6751"
    ],
    "wof:name":"Qianbucun",
    "wof:placetype":"locality"
},
  "geometry": {"coordinates":[123.47234,40.52559],"type":"Point"}
}