{
  "type": "Feature",
  "properties": {
    "gn:admin1_code":"3.0",
    "gn:asciiname":"Dingbei",
    "gn:country_code":"CN",
    "gn:dem":180,
    "gn:feature_class":"P",
    "gn:feature_code":"PPLA4",
    "gn:name":"Dingbei",
    "gn:population":0,
    "gn:timezone":"Asia/Shanghai",
    "iso:country":"CN",
    "name:und_x_variant":[
        "\u4e01\u9642",
        "Dingbei Xiang",
        "\u4e01\u9642\u4e61"
    ],
    "wof:name":"Dingbei",
    "wof:placetype":"locality"
},
  "geometry": {"coordinates":[115.8535,26.25924],"type":"Point"}
}