{
  "type": "Feature",
  "properties": {
    "gn:admin1_code":"15.0",
    "gn:asciiname":"Jiuzhuang",
    "gn:country_code":"CN",
    "gn:dem":1826,
    "gn:feature_class":"P",
    "gn:feature_code":"PPL",
    "gn:name":"Jiuzhuang",
    "gn:population":0,
    "gn:timezone":"Asia/Shanghai",
    "iso:country":"CN",
    "name:und_x_variant":[
        "\u65e7\u5e84"
    ],
    "wof:name":"Jiuzhuang",
    "wof:placetype":"locality"
},
  "geometry": {"coordinates":[105.53606000000001,35.21444],"type":"Point"}
}