{
  "type": "Feature",
  "properties": {
    "gn:admin1_code":"22.0",
    "gn:asciiname":"Huangshiyancun",
    "gn:country_code":"CN",
    "gn:dem":291,
    "gn:feature_class":"P",
    "gn:feature_code":"PPL",
    "gn:name":"Huangshiyancun",
    "gn:population":0,
    "gn:timezone":"Asia/Shanghai",
    "iso:country":"CN",
    "name:zho_x_preferred":[
        "\u9ec4\u77f3\u5ca9\u6751"
    ],
    "wof:name":"Huangshiyancun",
    "wof:placetype":"locality"
},
  "geometry": {"coordinates":[115.82836,39.78458],"type":"Point"}
}