{
  "type": "Feature",
  "properties": {
    "gn:admin1_code":"18.0",
    "gn:asciiname":"Tianbatang",
    "gn:country_code":"CN",
    "gn:dem":1040,
    "gn:feature_class":"P",
    "gn:feature_code":"PPL",
    "gn:name":"Tianbatang",
    "gn:population":0,
    "gn:timezone":"Asia/Shanghai",
    "iso:country":"CN",
    "name:zho_x_preferred":[
        "\u5929\u575d\u5858"
    ],
    "wof:name":"Tianbatang",
    "wof:placetype":"locality"
},
  "geometry": {"coordinates":[107.367,26.515],"type":"Point"}
}