{
  "type": "Feature",
  "properties": {
    "gn:admin1_code":"18",
    "gn:asciiname":"Yingjiao",
    "gn:country_code":"CN",
    "gn:dem":1752,
    "gn:feature_class":"P",
    "gn:feature_code":"PPL",
    "gn:name":"Yingjiao",
    "gn:population":0,
    "gn:timezone":"Asia/Shanghai",
    "iso:country":"CN",
    "name:zho_x_preferred":[
        "\u8425\u811a"
    ],
    "wof:name":"Yingjiao",
    "wof:placetype":"locality"
},
  "geometry": {"coordinates":[105.694,27.2652],"type":"Point"}
}