{
  "type": "Feature",
  "properties": {
    "gn:admin1_code":"8.0",
    "gn:asciiname":"Kunnanhoucun",
    "gn:country_code":"CN",
    "gn:dem":131,
    "gn:feature_class":"P",
    "gn:feature_code":"PPL",
    "gn:name":"Kunnanhoucun",
    "gn:population":0,
    "gn:timezone":"Asia/Shanghai",
    "iso:country":"CN",
    "name:zho_x_preferred":[
        "\u5764\u5357\u540e\u6751"
    ],
    "wof:name":"Kunnanhoucun",
    "wof:placetype":"locality"
},
  "geometry": {"coordinates":[126.37221,46.60173],"type":"Point"}
}