{
  "type": "Feature",
  "properties": {
    "gn:admin1_code":"32",
    "gn:asciiname":"Wenjia Liangzi",
    "gn:country_code":"CN",
    "gn:dem":299,
    "gn:feature_class":"P",
    "gn:feature_code":"PPL",
    "gn:name":"Wenjia Liangzi",
    "gn:population":0,
    "gn:timezone":"Asia/Shanghai",
    "iso:country":"CN",
    "name:zho_x_preferred":[
        "\u6587\u5bb6\u6881\u5b50"
    ],
    "wof:name":"Wenjia Liangzi",
    "wof:placetype":"locality"
},
  "geometry": {"coordinates":[106.29774999999999,30.32437],"type":"Point"}
}