{
  "type": "Feature",
  "properties": {
    "gn:admin1_code":"8.0",
    "gn:asciiname":"Qingyang Canchang",
    "gn:country_code":"CN",
    "gn:dem":333,
    "gn:feature_class":"P",
    "gn:feature_code":"PPLF",
    "gn:name":"Qingyang Canchang",
    "gn:population":0,
    "gn:timezone":"Asia/Shanghai",
    "iso:country":"CN",
    "name:zho_x_preferred":[
        "\u9752\u9633\u53c2\u573a"
    ],
    "wof:name":"Qingyang Canchang",
    "wof:placetype":"locality"
},
  "geometry": {"coordinates":[128.01058,45.60189],"type":"Point"}
}