{
  "type": "Feature",
  "properties": {
    "gn:admin1_code":"16.0",
    "gn:asciiname":"Tongyu",
    "gn:country_code":"CN",
    "gn:dem":138,
    "gn:feature_class":"P",
    "gn:feature_code":"PPL",
    "gn:name":"Tongyu",
    "gn:population":0,
    "gn:timezone":"Asia/Shanghai",
    "iso:country":"CN",
    "name:zho_x_preferred":[
        "\u540c\u88d5"
    ],
    "wof:name":"Tongyu",
    "wof:placetype":"locality"
},
  "geometry": {"coordinates":[109.28700000000001,24.6245],"type":"Point"}
}