{
  "type": "Feature",
  "properties": {
    "gn:admin1_code":"02",
    "gn:asciiname":"Changchan",
    "gn:country_code":"CN",
    "gn:dem":286,
    "gn:feature_class":"P",
    "gn:feature_code":"PPL",
    "gn:name":"Changchan",
    "gn:population":0,
    "gn:timezone":"Asia/Shanghai",
    "iso:country":"CN",
    "name:zho_x_preferred":[
        "Ch\u2019ang-ch\u2019an-chung-ao"
    ],
    "wof:name":"Changchan",
    "wof:placetype":"locality"
},
  "geometry": {"coordinates":[120.41897,27.38086],"type":"Point"}
}