{
  "type": "Feature",
  "properties": {
    "gn:admin1_code":"25",
    "gn:asciiname":"Xiguxiancun",
    "gn:country_code":"CN",
    "gn:dem":170,
    "gn:feature_class":"P",
    "gn:feature_code":"PPL",
    "gn:name":"Xiguxiancun",
    "gn:population":0,
    "gn:timezone":"Asia/Shanghai",
    "iso:country":"CN",
    "name:und_x_variant":[
        "Guxian"
    ],
    "name:zho_x_preferred":[
        "\u897f\u6545\u53bf\u6751"
    ],
    "wof:name":"Xiguxiancun",
    "wof:placetype":"locality"
},
  "geometry": {"coordinates":[117.65282000000001,35.16747],"type":"Point"}
}