{
  "type": "Feature",
  "properties": {
    "gn:admin1_code":"25",
    "gn:asciiname":"Beichouquan",
    "gn:country_code":"CN",
    "gn:dem":93,
    "gn:feature_class":"P",
    "gn:feature_code":"PPL",
    "gn:name":"Beichouquan",
    "gn:population":0,
    "gn:timezone":"Asia/Shanghai",
    "iso:country":"CN",
    "name:zho_x_preferred":[
        "\u5317\u81ed\u6cc9"
    ],
    "wof:name":"Beichouquan",
    "wof:placetype":"locality"
},
  "geometry": {"coordinates":[117.048,36.0151],"type":"Point"}
}