{
  "type": "Feature",
  "properties": {
    "gn:admin1_code":"26.0",
    "gn:asciiname":"Luojiapan",
    "gn:country_code":"CN",
    "gn:dem":1205,
    "gn:feature_class":"P",
    "gn:feature_code":"PPL",
    "gn:name":"Luojiapan",
    "gn:population":0,
    "gn:timezone":"Asia/Shanghai",
    "iso:country":"CN",
    "name:zho_x_preferred":[
        "\u7f57\u5bb6\u7554"
    ],
    "wof:name":"Luojiapan",
    "wof:placetype":"locality"
},
  "geometry": {"coordinates":[109.03180999999999,35.53184],"type":"Point"}
}