{
  "type": "Feature",
  "properties": {
    "gn:admin1_code":"11.0",
    "gn:asciiname":"Tangtoufeng",
    "gn:country_code":"CN",
    "gn:dem":114,
    "gn:feature_class":"P",
    "gn:feature_code":"PPL",
    "gn:name":"Tangtoufeng",
    "gn:population":0,
    "gn:timezone":"Asia/Shanghai",
    "iso:country":"CN",
    "name:zho_x_preferred":[
        "\u5858\u5934\u51e4"
    ],
    "wof:name":"Tangtoufeng",
    "wof:placetype":"locality"
},
  "geometry": {"coordinates":[112.71753,27.21604],"type":"Point"}
}