{
  "type": "Feature",
  "properties": {
    "gn:admin1_code":"11",
    "gn:asciiname":"Liangchaxi",
    "gn:country_code":"CN",
    "gn:dem":115,
    "gn:feature_class":"P",
    "gn:feature_code":"PPL",
    "gn:name":"Liangchaxi",
    "gn:population":0,
    "gn:timezone":"Asia/Shanghai",
    "iso:country":"CN",
    "name:zho_x_preferred":[
        "\u4e24\u5c94\u6eaa"
    ],
    "wof:name":"Liangchaxi",
    "wof:placetype":"locality"
},
  "geometry": {"coordinates":[110.24576999999999,28.49463],"type":"Point"}
}