{
  "type": "Feature",
  "properties": {
    "gn:admin1_code":"32.0",
    "gn:asciiname":"Feifeng",
    "gn:country_code":"CN",
    "gn:dem":428,
    "gn:feature_class":"P",
    "gn:feature_code":"PPL",
    "gn:name":"Feifeng",
    "gn:population":0,
    "gn:timezone":"Asia/Shanghai",
    "iso:country":"CN",
    "name:zho_x_preferred":[
        "\u98de\u51e4"
    ],
    "wof:name":"Feifeng",
    "wof:placetype":"locality"
},
  "geometry": {"coordinates":[104.568,30.567],"type":"Point"}
}