{
  "type": "Feature",
  "properties": {
    "gn:admin1_code":"26.0",
    "gn:asciiname":"Fangwan",
    "gn:country_code":"CN",
    "gn:dem":740,
    "gn:feature_class":"P",
    "gn:feature_code":"PPL",
    "gn:name":"Fangwan",
    "gn:population":0,
    "gn:timezone":"Asia/Shanghai",
    "iso:country":"CN",
    "name:und_x_variant":[
        "\u90a1\u6e7e"
    ],
    "wof:name":"Fangwan",
    "wof:placetype":"locality"
},
  "geometry": {"coordinates":[106.34726999999999,33.3468],"type":"Point"}
}