{
  "type": "Feature",
  "properties": {
    "gn:admin1_code":"22",
    "gn:asciiname":"Nanfaxin",
    "gn:country_code":"CN",
    "gn:dem":36,
    "gn:feature_class":"P",
    "gn:feature_code":"PPLA4",
    "gn:name":"Nanfaxin",
    "gn:population":0,
    "gn:timezone":"Asia/Shanghai",
    "iso:country":"CN",
    "name:und_x_variant":[
        "Nanfaxin Zhen"
    ],
    "name:zho_x_preferred":[
        "\u5357\u6cd5\u4fe1"
    ],
    "name:zho_x_variant":[
        "\u5357\u6cd5\u4fe1\u9547"
    ],
    "wof:name":"Nanfaxin",
    "wof:placetype":"locality"
},
  "geometry": {"coordinates":[116.60250000000001,40.12088],"type":"Point"}
}