{
  "type": "Feature",
  "properties": {
    "gn:admin1_code":"15.0",
    "gn:asciiname":"Zhifang",
    "gn:country_code":"CN",
    "gn:dem":2364,
    "gn:feature_class":"P",
    "gn:feature_code":"PPL",
    "gn:name":"Zhifang",
    "gn:population":0,
    "gn:timezone":"Asia/Shanghai",
    "iso:country":"CN",
    "name:und_x_variant":[
        "\u7eb8\u574a"
    ],
    "wof:name":"Zhifang",
    "wof:placetype":"locality"
},
  "geometry": {"coordinates":[104.07143000000001,34.41549000000001],"type":"Point"}
}