{
  "type": "Feature",
  "properties": {
    "gn:admin1_code":"3.0",
    "gn:asciiname":"Huangbaiyang",
    "gn:country_code":"CN",
    "gn:dem":31,
    "gn:feature_class":"P",
    "gn:feature_code":"PPL",
    "gn:name":"Huangbaiyang",
    "gn:population":0,
    "gn:timezone":"Asia/Shanghai",
    "iso:country":"CN",
    "name:und_x_variant":[
        "\u9ec4\u67cf\u6d0b"
    ],
    "wof:name":"Huangbaiyang",
    "wof:placetype":"locality"
},
  "geometry": {"coordinates":[115.41423,28.16188],"type":"Point"}
}