{
  "type": "Feature",
  "properties": {
    "gn:admin1_code":"2.0",
    "gn:asciiname":"Hua'ao",
    "gn:country_code":"CN",
    "gn:dem":34,
    "gn:feature_class":"P",
    "gn:feature_code":"PPL",
    "gn:name":"Hua\u2019ao",
    "gn:population":0,
    "gn:timezone":"Asia/Shanghai",
    "iso:country":"CN",
    "name:und_x_variant":[
        "Hua\u2019ao"
    ],
    "name:zho_x_preferred":[
        "\u82b1\u5c99"
    ],
    "wof:name":"Hua'ao",
    "wof:placetype":"locality"
},
  "geometry": {"coordinates":[121.81507000000001,29.06762],"type":"Point"}
}