{
  "type": "Feature",
  "properties": {
    "gn:admin1_code":"24.0",
    "gn:asciiname":"Yuli",
    "gn:country_code":"CN",
    "gn:dem":602,
    "gn:feature_class":"P",
    "gn:feature_code":"PPL",
    "gn:name":"Yuli",
    "gn:population":0,
    "gn:timezone":"Asia/Shanghai",
    "iso:country":"CN",
    "name:ceb_x_preferred":[
        "Yuli"
    ],
    "name:deu_x_preferred":[
        "Yuli"
    ],
    "name:fra_x_preferred":[
        "Yuli"
    ],
    "name:zho_x_preferred":[
        "\u5cea\u91cc"
    ],
    "wof:name":"Yuli",
    "wof:placetype":"locality"
},
  "geometry": {"coordinates":[111.32787999999999,36.05958],"type":"Point"}
}