{
  "type": "Feature",
  "properties": {
    "gn:admin1_code":"11.0",
    "gn:asciiname":"Bitiexi",
    "gn:country_code":"CN",
    "gn:dem":455,
    "gn:feature_class":"P",
    "gn:feature_code":"PPL",
    "gn:name":"Bitiexi",
    "gn:population":0,
    "gn:timezone":"Asia/Shanghai",
    "iso:country":"CN",
    "name:zho_x_preferred":[
        "\u6bd4\u94c1\u6eaa"
    ],
    "wof:name":"Bitiexi",
    "wof:placetype":"locality"
},
  "geometry": {"coordinates":[109.78216999999999,29.30835],"type":"Point"}
}