{
  "type": "Feature",
  "properties": {
    "gn:admin1_code":"10",
    "gn:asciiname":"Houquhuangdian",
    "gn:country_code":"CN",
    "gn:dem":9,
    "gn:feature_class":"P",
    "gn:feature_code":"PPL",
    "gn:name":"Houquhuangdian",
    "gn:population":0,
    "gn:timezone":"Asia/Shanghai",
    "iso:country":"CN",
    "name:und_x_variant":[
        "Hou-ch\u2019\u00fc-huang-chuang",
        "Hou-ch\u2019\u00fc-huang-tien",
        "Houquhuangdian"
    ],
    "name:zho_x_preferred":[
        "\u540e\u66f2\u8352\u5e97"
    ],
    "wof:name":"Houquhuangdian",
    "wof:placetype":"locality"
},
  "geometry": {"coordinates":[118.65125,39.45454],"type":"Point"}
}