{
  "type": "Feature",
  "properties": {
    "gn:admin1_code":"12.0",
    "gn:asciiname":"Ganyan",
    "gn:country_code":"CN",
    "gn:dem":1143,
    "gn:feature_class":"P",
    "gn:feature_code":"PPL",
    "gn:name":"Ganyan",
    "gn:population":0,
    "gn:timezone":"Asia/Shanghai",
    "iso:country":"CN",
    "name:zho_x_preferred":[
        "\u5e72\u5830"
    ],
    "wof:name":"Ganyan",
    "wof:placetype":"locality"
},
  "geometry": {"coordinates":[108.76415,30.41104],"type":"Point"}
}