{
  "type": "Feature",
  "properties": {
    "gn:admin1_code":"2.0",
    "gn:asciiname":"Shifeng",
    "gn:country_code":"CN",
    "gn:dem":328,
    "gn:feature_class":"P",
    "gn:feature_code":"PPL",
    "gn:name":"Shifeng",
    "gn:population":0,
    "gn:timezone":"Asia/Shanghai",
    "iso:country":"CN",
    "name:zho_x_preferred":[
        "\u72ee\u5cf0"
    ],
    "wof:name":"Shifeng",
    "wof:placetype":"locality"
},
  "geometry": {"coordinates":[119.38963,29.70027],"type":"Point"}
}