{
  "type": "Feature",
  "properties": {
    "gn:admin1_code":"8.0",
    "gn:asciiname":"Gaojuntun",
    "gn:country_code":"CN",
    "gn:dem":274,
    "gn:feature_class":"P",
    "gn:feature_code":"PPL",
    "gn:name":"Gaojuntun",
    "gn:population":0,
    "gn:timezone":"Asia/Shanghai",
    "iso:country":"CN",
    "name:zho_x_preferred":[
        "\u9ad8\u519b\u5c6f"
    ],
    "wof:name":"Gaojuntun",
    "wof:placetype":"locality"
},
  "geometry": {"coordinates":[125.15172,48.38892],"type":"Point"}
}