{
  "type": "Feature",
  "properties": {
    "gn:admin1_code":"20",
    "gn:asciiname":"Ta-wu-chia-tzu",
    "gn:country_code":"CN",
    "gn:dem":585,
    "gn:feature_class":"P",
    "gn:feature_code":"PPL",
    "gn:name":"Ta-wu-chia-tzu",
    "gn:population":0,
    "gn:timezone":"Asia/Shanghai",
    "iso:country":"CN",
    "wof:name":"Ta-wu-chia-tzu",
    "wof:placetype":"locality"
},
  "geometry": {"coordinates":[119.08389,42.60611],"type":"Point"}
}