{
  "type": "Feature",
  "properties": {
    "gn:admin1_code":"18",
    "gn:asciiname":"Laomaochong",
    "gn:country_code":"CN",
    "gn:dem":1823,
    "gn:feature_class":"P",
    "gn:feature_code":"PPL",
    "gn:name":"Laomaochong",
    "gn:population":0,
    "gn:timezone":"Asia/Shanghai",
    "iso:country":"CN",
    "name:zho_x_preferred":[
        "\u8001\u732b\u51b2"
    ],
    "wof:name":"Laomaochong",
    "wof:placetype":"locality"
},
  "geometry": {"coordinates":[104.896,26.7674],"type":"Point"}
}