{
  "type": "Feature",
  "properties": {
    "gn:admin1_code":"14.0",
    "gn:asciiname":"Moinda",
    "gn:country_code":"CN",
    "gn:dem":4294,
    "gn:feature_class":"P",
    "gn:feature_code":"PPLF",
    "gn:name":"Moinda",
    "gn:population":0,
    "gn:timezone":"Asia/Urumqi",
    "iso:country":"CN",
    "name:bod_x_preferred":[
        "Moinda"
    ],
    "name:und_x_variant":[
        "Mengda"
    ],
    "name:zho_x_preferred":[
        "\u8499\u8fbe"
    ],
    "wof:name":"Moinda",
    "wof:placetype":"locality"
},
  "geometry": {"coordinates":[90.62517,28.36373],"type":"Point"}
}