{
  "type": "Feature",
  "properties": {
    "gn:admin1_code":"4.0",
    "gn:asciiname":"Dalicun",
    "gn:country_code":"CN",
    "gn:dem":23,
    "gn:feature_class":"P",
    "gn:feature_code":"PPL",
    "gn:name":"Dalicun",
    "gn:population":0,
    "gn:timezone":"Asia/Shanghai",
    "iso:country":"CN",
    "name:zho_x_preferred":[
        "\u5927\u674e\u6751"
    ],
    "wof:name":"Dalicun",
    "wof:placetype":"locality"
},
  "geometry": {"coordinates":[118.01208,33.83929000000001],"type":"Point"}
}