{
  "type": "Feature",
  "properties": {
    "gn:admin1_code":"32.0",
    "gn:asciiname":"Laolingzi",
    "gn:country_code":"CN",
    "gn:dem":2927,
    "gn:feature_class":"P",
    "gn:feature_code":"PPL",
    "gn:name":"Laolingzi",
    "gn:population":0,
    "gn:timezone":"Asia/Shanghai",
    "iso:country":"CN",
    "name:zho_x_preferred":[
        "\u8001\u5cad\u5b50"
    ],
    "wof:name":"Laolingzi",
    "wof:placetype":"locality"
},
  "geometry": {"coordinates":[102.755,27.2502],"type":"Point"}
}