{
  "type": "Feature",
  "properties": {
    "gn:admin1_code":"15",
    "gn:asciiname":"Liushu",
    "gn:country_code":"CN",
    "gn:dem":2029,
    "gn:feature_class":"P",
    "gn:feature_code":"PPL",
    "gn:name":"Liushu",
    "gn:population":0,
    "gn:timezone":"Asia/Shanghai",
    "iso:country":"CN",
    "wof:name":"Liushu",
    "wof:placetype":"locality"
},
  "geometry": {"coordinates":[103.28778,36.67361],"type":"Point"}
}