{
  "type": "Feature",
  "properties": {
    "gn:admin1_code":"25",
    "gn:asciiname":"Diaoyutai",
    "gn:country_code":"CN",
    "gn:dem":79,
    "gn:feature_class":"P",
    "gn:feature_code":"PPL",
    "gn:name":"Diaoyutai",
    "gn:population":0,
    "gn:timezone":"Asia/Shanghai",
    "iso:country":"CN",
    "name:zho_x_preferred":[
        "\u9493\u9c7c\u53f0"
    ],
    "wof:name":"Diaoyutai",
    "wof:placetype":"locality"
},
  "geometry": {"coordinates":[118.441,35.2088],"type":"Point"}
}