{
  "type": "Feature",
  "properties": {
    "gn:admin1_code":"16",
    "gn:asciiname":"Dekang",
    "gn:country_code":"CN",
    "gn:dem":613,
    "gn:feature_class":"P",
    "gn:feature_code":"PPL",
    "gn:name":"Dekang",
    "gn:population":0,
    "gn:timezone":"Asia/Shanghai",
    "iso:country":"CN",
    "name:und_x_variant":[
        "Te-k\u2019ang",
        "Dekang"
    ],
    "name:zho_x_preferred":[
        "\u5fb7\u5eb7"
    ],
    "wof:name":"Dekang",
    "wof:placetype":"locality"
},
  "geometry": {"coordinates":[105.867,23.2372],"type":"Point"}
}