{
  "type": "Feature",
  "properties": {
    "gn:admin1_code":"2",
    "gn:asciiname":"Shigeli",
    "gn:country_code":"CN",
    "gn:dem":8,
    "gn:feature_class":"P",
    "gn:feature_code":"PPL",
    "gn:name":"Shigeli",
    "gn:population":0,
    "gn:timezone":"Asia/Shanghai",
    "iso:country":"CN",
    "name:und_x_variant":[
        "\u77f3\u9e3d\u91cc"
    ],
    "wof:name":"Shigeli",
    "wof:placetype":"locality"
},
  "geometry": {"coordinates":[119.92528,30.24333],"type":"Point"}
}