{
  "type": "Feature",
  "properties": {
    "gn:admin1_code":"7",
    "gn:asciiname":"Gaoshanlou",
    "gn:country_code":"CN",
    "gn:dem":114,
    "gn:feature_class":"P",
    "gn:feature_code":"PPL",
    "gn:name":"Gaoshanlou",
    "gn:population":0,
    "gn:timezone":"Asia/Shanghai",
    "iso:country":"CN",
    "name:zho_x_preferred":[
        "\u9ad8\u5c71\u697c"
    ],
    "wof:name":"Gaoshanlou",
    "wof:placetype":"locality"
},
  "geometry": {"coordinates":[117.41585000000001,23.85631],"type":"Point"}
}