{
  "type": "Feature",
  "properties": {
    "gn:admin1_code":"7.0",
    "gn:asciiname":"Weicuo",
    "gn:country_code":"CN",
    "gn:dem":11,
    "gn:feature_class":"P",
    "gn:feature_code":"PPL",
    "gn:name":"Weicuo",
    "gn:population":0,
    "gn:timezone":"Asia/Shanghai",
    "iso:country":"CN",
    "name:zho_x_preferred":[
        "\u9b4f\u539d"
    ],
    "wof:name":"Weicuo",
    "wof:placetype":"locality"
},
  "geometry": {"coordinates":[119.11647000000001,25.27507],"type":"Point"}
}