{
  "type": "Feature",
  "properties": {
    "gn:admin1_code":"16",
    "gn:asciiname":"Jiaotang",
    "gn:country_code":"CN",
    "gn:dem":169,
    "gn:feature_class":"P",
    "gn:feature_code":"PPL",
    "gn:name":"Jiaotang",
    "gn:population":0,
    "gn:timezone":"Asia/Shanghai",
    "iso:country":"CN",
    "name:zho_x_preferred":[
        "\u86df\u5858"
    ],
    "wof:name":"Jiaotang",
    "wof:placetype":"locality"
},
  "geometry": {"coordinates":[110.345,25.4544],"type":"Point"}
}