{
  "type": "Feature",
  "properties": {
    "gn:admin1_code":"26",
    "gn:asciiname":"Maiwang",
    "gn:country_code":"CN",
    "gn:dem":385,
    "gn:feature_class":"P",
    "gn:feature_code":"PPL",
    "gn:name":"Maiwang",
    "gn:population":0,
    "gn:timezone":"Asia/Shanghai",
    "iso:country":"CN",
    "name:und_x_variant":[
        "\u9ea6\u738b",
        "Maiwang"
    ],
    "wof:name":"Maiwang",
    "wof:placetype":"locality"
},
  "geometry": {"coordinates":[109.06843000000001,34.36492],"type":"Point"}
}