{
  "type": "Feature",
  "properties": {
    "gn:admin1_code":"5.0",
    "gn:asciiname":"Chidi",
    "gn:country_code":"CN",
    "gn:dem":110,
    "gn:feature_class":"P",
    "gn:feature_code":"PPL",
    "gn:name":"Chidi",
    "gn:population":0,
    "gn:timezone":"Asia/Pyongyang",
    "iso:country":"CN",
    "name:zho_x_preferred":[
        "\u6c60\u5730"
    ],
    "wof:name":"Chidi",
    "wof:placetype":"locality"
},
  "geometry": {"coordinates":[129.86391,42.92049],"type":"Point"}
}