{
  "type": "Feature",
  "properties": {
    "gn:admin1_code":"32.0",
    "gn:asciiname":"Longshengyizu",
    "gn:country_code":"CN",
    "gn:dem":1848,
    "gn:feature_class":"P",
    "gn:feature_code":"PPL",
    "gn:name":"Longshengyizu",
    "gn:population":0,
    "gn:timezone":"Asia/Shanghai",
    "iso:country":"CN",
    "name:zho_x_preferred":[
        "\u9f99\u80dc\u5f5d\u65cf"
    ],
    "wof:name":"Longshengyizu",
    "wof:placetype":"locality"
},
  "geometry": {"coordinates":[101.60767,27.04941],"type":"Point"}
}