{
  "type": "Feature",
  "properties": {
    "gn:admin1_code":"03",
    "gn:asciiname":"Gaojiaqiao",
    "gn:country_code":"CN",
    "gn:dem":31,
    "gn:feature_class":"P",
    "gn:feature_code":"PPL",
    "gn:name":"Gaojiaqiao",
    "gn:population":0,
    "gn:timezone":"Asia/Shanghai",
    "iso:country":"CN",
    "name:und_x_variant":[
        "\u9ad8\u5bb6\u6865"
    ],
    "wof:name":"Gaojiaqiao",
    "wof:placetype":"locality"
},
  "geometry": {"coordinates":[116.18735,29.5306],"type":"Point"}
}