{
  "type": "Feature",
  "properties": {
    "gn:admin1_code":"18",
    "gn:asciiname":"Taizitian",
    "gn:country_code":"CN",
    "gn:dem":1759,
    "gn:feature_class":"P",
    "gn:feature_code":"PPL",
    "gn:name":"Taizitian",
    "gn:population":0,
    "gn:timezone":"Asia/Shanghai",
    "iso:country":"CN",
    "name:zho_x_preferred":[
        "\u53f0\u5b50\u7530"
    ],
    "wof:name":"Taizitian",
    "wof:placetype":"locality"
},
  "geometry": {"coordinates":[105.185,27.2213],"type":"Point"}
}