{
  "type": "Feature",
  "properties": {
    "gn:admin1_code":"25",
    "gn:asciiname":"Yingdong",
    "gn:country_code":"CN",
    "gn:dem":50,
    "gn:feature_class":"P",
    "gn:feature_code":"PPL",
    "gn:name":"Yingdong",
    "gn:population":0,
    "gn:timezone":"Asia/Shanghai",
    "iso:country":"CN",
    "name:zho_x_preferred":[
        "\u6a31\u4e1c"
    ],
    "wof:name":"Yingdong",
    "wof:placetype":"locality"
},
  "geometry": {"coordinates":[115.48999999999999,35.8948],"type":"Point"}
}