{
  "type": "Feature",
  "properties": {
    "gn:admin1_code":"31",
    "gn:asciiname":"Chengdong",
    "gn:country_code":"CN",
    "gn:dem":222,
    "gn:feature_class":"P",
    "gn:feature_code":"PPL",
    "gn:name":"Chengdong",
    "gn:population":0,
    "gn:timezone":"Asia/Shanghai",
    "iso:country":"CN",
    "name:und_x_variant":[
        "\u6210\u680b"
    ],
    "wof:name":"Chengdong",
    "wof:placetype":"locality"
},
  "geometry": {"coordinates":[109.28100000000001,18.6397],"type":"Point"}
}