{
  "type": "Feature",
  "properties": {
    "gn:admin1_code":"32.0",
    "gn:asciiname":"Baopingqiao",
    "gn:country_code":"CN",
    "gn:dem":379,
    "gn:feature_class":"P",
    "gn:feature_code":"PPL",
    "gn:name":"Baopingqiao",
    "gn:population":0,
    "gn:timezone":"Asia/Shanghai",
    "iso:country":"CN",
    "name:zho_x_preferred":[
        "\u4fdd\u5e73\u6865"
    ],
    "wof:name":"Baopingqiao",
    "wof:placetype":"locality"
},
  "geometry": {"coordinates":[106.511,31.3436],"type":"Point"}
}