{
  "type": "Feature",
  "properties": {
    "gn:admin1_code":"25.0",
    "gn:asciiname":"Dazhaike",
    "gn:cc2":"CN",
    "gn:country_code":"CN",
    "gn:dem":75,
    "gn:feature_class":"P",
    "gn:feature_code":"PPL",
    "gn:name":"Dazhaike",
    "gn:population":0,
    "gn:timezone":"Asia/Shanghai",
    "iso:country":"CN",
    "name:zho_x_preferred":[
        "\u5927\u5b85\u79d1"
    ],
    "wof:name":"Dazhaike",
    "wof:placetype":"locality"
},
  "geometry": {"coordinates":[119.36618,35.54288],"type":"Point"}
}