{
  "type": "Feature",
  "properties": {
    "gn:admin1_code":"4.0",
    "gn:asciiname":"Qiaokoucun",
    "gn:country_code":"CN",
    "gn:dem":7,
    "gn:feature_class":"P",
    "gn:feature_code":"PPL",
    "gn:name":"Qiaokoucun",
    "gn:population":0,
    "gn:timezone":"Asia/Shanghai",
    "iso:country":"CN",
    "name:zho_x_preferred":[
        "\u4e54\u53e3\u6751"
    ],
    "wof:name":"Qiaokoucun",
    "wof:placetype":"locality"
},
  "geometry": {"coordinates":[118.76971,34.27448],"type":"Point"}
}