{
  "type": "Feature",
  "properties": {
    "gn:admin1_code":"2",
    "gn:asciiname":"Huangshuangling",
    "gn:country_code":"CN",
    "gn:dem":171,
    "gn:feature_class":"P",
    "gn:feature_code":"PPL",
    "gn:name":"Huangshuangling",
    "gn:population":0,
    "gn:timezone":"Asia/Shanghai",
    "iso:country":"CN",
    "name:zho_x_preferred":[
        "\u9ec4\u53cc\u5cad"
    ],
    "wof:name":"Huangshuangling",
    "wof:placetype":"locality"
},
  "geometry": {"coordinates":[120.71876,29.42041],"type":"Point"}
}