{
  "type": "Feature",
  "properties": {
    "gn:admin1_code":"19",
    "gn:asciiname":"Fangjiacun",
    "gn:country_code":"CN",
    "gn:dem":21,
    "gn:feature_class":"P",
    "gn:feature_code":"PPL",
    "gn:name":"Fangjiacun",
    "gn:population":0,
    "gn:timezone":"Asia/Shanghai",
    "iso:country":"CN",
    "name:zho_x_preferred":[
        "\u65b9\u5bb6\u6751"
    ],
    "wof:name":"Fangjiacun",
    "wof:placetype":"locality"
},
  "geometry": {"coordinates":[121.16200000000001,38.815],"type":"Point"}
}