{
  "type": "Feature",
  "properties": {
    "gn:admin1_code":"16.0",
    "gn:asciiname":"Lujiu",
    "gn:country_code":"CN",
    "gn:dem":202,
    "gn:feature_class":"P",
    "gn:feature_code":"PPL",
    "gn:name":"L\u00fcjiu",
    "gn:population":0,
    "gn:timezone":"Asia/Shanghai",
    "iso:country":"CN",
    "name:und_x_variant":[
        "L\u00fcjiu"
    ],
    "name:zho_x_preferred":[
        "\u7eff\u7396"
    ],
    "wof:name":"Lujiu",
    "wof:placetype":"locality"
},
  "geometry": {"coordinates":[109.98999999999999,22.8395],"type":"Point"}
}