{
  "type": "Feature",
  "properties": {
    "gn:admin1_code":"12.0",
    "gn:asciiname":"Nanmukeng",
    "gn:country_code":"CN",
    "gn:dem":126,
    "gn:feature_class":"P",
    "gn:feature_code":"PPL",
    "gn:name":"Nanmukeng",
    "gn:population":0,
    "gn:timezone":"Asia/Shanghai",
    "iso:country":"CN",
    "name:zho_x_preferred":[
        "Nanmukeng"
    ],
    "name:zho_x_variant":[
        "\u5357\u6728\u5751"
    ],
    "wof:name":"Nanmukeng",
    "wof:placetype":"locality"
},
  "geometry": {"coordinates":[114.05578,29.33732],"type":"Point"}
}