{
  "type": "Feature",
  "properties": {
    "gn:admin1_code":"26.0",
    "gn:asciiname":"Dalengba",
    "gn:country_code":"CN",
    "gn:dem":1866,
    "gn:feature_class":"P",
    "gn:feature_code":"PPL",
    "gn:name":"Dalengba",
    "gn:population":0,
    "gn:timezone":"Asia/Shanghai",
    "iso:country":"CN",
    "name:und_x_variant":[
        "\u5927\u51b7\u575d"
    ],
    "wof:name":"Dalengba",
    "wof:placetype":"locality"
},
  "geometry": {"coordinates":[106.55837,32.71157],"type":"Point"}
}