{
  "type": "Feature",
  "properties": {
    "gn:admin1_code":"8.0",
    "gn:asciiname":"Fanjiayingzi",
    "gn:country_code":"CN",
    "gn:dem":250,
    "gn:feature_class":"P",
    "gn:feature_code":"PPL",
    "gn:name":"Fanjiayingzi",
    "gn:population":0,
    "gn:timezone":"Asia/Shanghai",
    "iso:country":"CN",
    "name:zho_x_preferred":[
        "\u8303\u5bb6\u8425\u5b50"
    ],
    "wof:name":"Fanjiayingzi",
    "wof:placetype":"locality"
},
  "geometry": {"coordinates":[125.04308,48.06154],"type":"Point"}
}