{
  "type": "Feature",
  "properties": {
    "gn:admin1_code":"12.0",
    "gn:asciiname":"Lashumiaowan",
    "gn:country_code":"CN",
    "gn:dem":109,
    "gn:feature_class":"P",
    "gn:feature_code":"PPL",
    "gn:name":"Lashumiaowan",
    "gn:population":0,
    "gn:timezone":"Asia/Shanghai",
    "iso:country":"CN",
    "name:zho_x_preferred":[
        "\u814a\u6811\u5e99\u6e7e"
    ],
    "wof:name":"Lashumiaowan",
    "wof:placetype":"locality"
},
  "geometry": {"coordinates":[112.27784,30.84648],"type":"Point"}
}