{
  "type": "Feature",
  "properties": {
    "gn:admin1_code":"16.0",
    "gn:asciiname":"Nongdang",
    "gn:country_code":"CN",
    "gn:dem":1526,
    "gn:feature_class":"P",
    "gn:feature_code":"PPL",
    "gn:name":"Nongdang",
    "gn:population":0,
    "gn:timezone":"Asia/Shanghai",
    "iso:country":"CN",
    "name:zho_x_preferred":[
        "\u5f04\u5f53"
    ],
    "wof:name":"Nongdang",
    "wof:placetype":"locality"
},
  "geometry": {"coordinates":[105.273,24.5962],"type":"Point"}
}