{
  "type": "Feature",
  "properties": {
    "gn:admin1_code":"1.0",
    "gn:asciiname":"Suiwancun",
    "gn:country_code":"CN",
    "gn:dem":41,
    "gn:feature_class":"P",
    "gn:feature_code":"PPL",
    "gn:name":"Suiwancun",
    "gn:population":0,
    "gn:timezone":"Asia/Shanghai",
    "iso:country":"CN",
    "name:zho_x_preferred":[
        "\u968f\u6e7e\u6751"
    ],
    "wof:name":"Suiwancun",
    "wof:placetype":"locality"
},
  "geometry": {"coordinates":[115.41619,33.22564000000001],"type":"Point"}
}