{
  "type": "Feature",
  "properties": {
    "gn:admin1_code":"24.0",
    "gn:asciiname":"Houtianjingcun",
    "gn:country_code":"CN",
    "gn:dem":1941,
    "gn:feature_class":"P",
    "gn:feature_code":"PPL",
    "gn:name":"Houtianjingcun",
    "gn:population":0,
    "gn:timezone":"Asia/Shanghai",
    "iso:country":"CN",
    "name:zho_x_preferred":[
        "\u540e\u5929\u4e95\u6751"
    ],
    "wof:name":"Houtianjingcun",
    "wof:placetype":"locality"
},
  "geometry": {"coordinates":[113.38509000000001,39.08902],"type":"Point"}
}