{
  "type": "Feature",
  "properties": {
    "gn:admin1_code":"9.0",
    "gn:asciiname":"Liwangying",
    "gn:country_code":"CN",
    "gn:dem":34,
    "gn:feature_class":"P",
    "gn:feature_code":"PPL",
    "gn:name":"Liwangying",
    "gn:population":0,
    "gn:timezone":"Asia/Shanghai",
    "iso:country":"CN",
    "name:zho_x_preferred":[
        "\u674e\u738b\u8425"
    ],
    "wof:name":"Liwangying",
    "wof:placetype":"locality"
},
  "geometry": {"coordinates":[115.47162,32.51197],"type":"Point"}
}