{
  "type": "Feature",
  "properties": {
    "gn:admin1_code":"12",
    "gn:asciiname":"Shanpo",
    "gn:country_code":"CN",
    "gn:dem":37,
    "gn:feature_class":"P",
    "gn:feature_code":"PPL",
    "gn:name":"Shanpo",
    "gn:population":0,
    "gn:timezone":"Asia/Shanghai",
    "iso:country":"CN",
    "name:und_x_variant":[
        "\u5c71\u5761",
        "Shanpo Xiang",
        "\u5c71\u5761\u4e61"
    ],
    "wof:name":"Shanpo",
    "wof:placetype":"locality"
},
  "geometry": {"coordinates":[114.34465,30.09127],"type":"Point"}
}