{
  "type": "Feature",
  "properties": {
    "gn:admin1_code":"24.0",
    "gn:asciiname":"Chouniuyan",
    "gn:country_code":"CN",
    "gn:dem":1491,
    "gn:feature_class":"P",
    "gn:feature_code":"PPL",
    "gn:name":"Chouniuyan",
    "gn:population":0,
    "gn:timezone":"Asia/Shanghai",
    "iso:country":"CN",
    "name:zho_x_preferred":[
        "\u62bd\u725b\u5ca9"
    ],
    "wof:name":"Chouniuyan",
    "wof:placetype":"locality"
},
  "geometry": {"coordinates":[112.34735999999999,38.47031],"type":"Point"}
}