{
  "type": "Feature",
  "properties": {
    "gn:admin1_code":"10",
    "gn:asciiname":"Wangzhangzi",
    "gn:country_code":"CN",
    "gn:dem":174,
    "gn:feature_class":"P",
    "gn:feature_code":"PPL",
    "gn:name":"Wangzhangzi",
    "gn:population":0,
    "gn:timezone":"Asia/Shanghai",
    "iso:country":"CN",
    "name:zho_x_preferred":[
        "\u738b\u6756\u5b50"
    ],
    "wof:name":"Wangzhangzi",
    "wof:placetype":"locality"
},
  "geometry": {"coordinates":[119.01761,40.35328],"type":"Point"}
}