{
  "type": "Feature",
  "properties": {
    "gn:admin1_code":"9.0",
    "gn:asciiname":"Qianleqiao",
    "gn:country_code":"CN",
    "gn:dem":63,
    "gn:feature_class":"P",
    "gn:feature_code":"PPL",
    "gn:name":"Qianleqiao",
    "gn:population":0,
    "gn:timezone":"Asia/Shanghai",
    "iso:country":"CN",
    "name:und_x_variant":[
        "\u4e7e\u52d2\u6865"
    ],
    "name:zho_x_preferred":[
        "\u4e7e\u52d2\u6865"
    ],
    "wof:name":"Qianleqiao",
    "wof:placetype":"locality"
},
  "geometry": {"coordinates":[113.94083000000001,33.68875999999999],"type":"Point"}
}