{
  "type": "Feature",
  "properties": {
    "gn:admin1_code":"32.0",
    "gn:asciiname":"Yuquan",
    "gn:country_code":"CN",
    "gn:dem":309,
    "gn:feature_class":"P",
    "gn:feature_code":"PPL",
    "gn:name":"Yuquan",
    "gn:population":0,
    "gn:timezone":"Asia/Shanghai",
    "iso:country":"CN",
    "name:ceb_x_preferred":[
        "Yuquan"
    ],
    "name:deu_x_preferred":[
        "Yuquan"
    ],
    "name:swe_x_preferred":[
        "Yuquan"
    ],
    "name:zho_x_preferred":[
        "\u9c7c\u6cc9"
    ],
    "wof:name":"Yuquan",
    "wof:placetype":"locality"
},
  "geometry": {"coordinates":[105.636,29.9831],"type":"Point"}
}