{
  "type": "Feature",
  "properties": {
    "gn:admin1_code":"8.0",
    "gn:asciiname":"Qilincun",
    "gn:country_code":"CN",
    "gn:dem":171,
    "gn:feature_class":"P",
    "gn:feature_code":"PPL",
    "gn:name":"Qilincun",
    "gn:population":0,
    "gn:timezone":"Asia/Shanghai",
    "iso:country":"CN",
    "name:zho_x_preferred":[
        "\u4f01\u6797\u6751"
    ],
    "wof:name":"Qilincun",
    "wof:placetype":"locality"
},
  "geometry": {"coordinates":[132.06611000000001,45.48295],"type":"Point"}
}