{
  "type": "Feature",
  "properties": {
    "gn:admin1_code":"8.0",
    "gn:asciiname":"Xuande",
    "gn:country_code":"CN",
    "gn:dem":191,
    "gn:feature_class":"P",
    "gn:feature_code":"PPL",
    "gn:name":"Xuande",
    "gn:population":0,
    "gn:timezone":"Asia/Shanghai",
    "iso:country":"CN",
    "name:zho_x_preferred":[
        "\u5ba3\u5fb7"
    ],
    "wof:name":"Xuande",
    "wof:placetype":"locality"
},
  "geometry": {"coordinates":[127.90611,45.70438],"type":"Point"}
}