{
  "type": "Feature",
  "properties": {
    "gn:admin1_code":"32.0",
    "gn:asciiname":"Zhuokeji",
    "gn:cc2":"CN",
    "gn:country_code":"CN",
    "gn:dem":2689,
    "gn:feature_class":"P",
    "gn:feature_code":"PPL",
    "gn:name":"Zhuokeji",
    "gn:population":0,
    "gn:timezone":"Asia/Shanghai",
    "iso:country":"CN",
    "name:und_x_variant":[
        "Chzhoketszi",
        "Cho-k'o-chi"
    ],
    "wof:name":"Zhuokeji",
    "wof:placetype":"locality"
},
  "geometry": {"coordinates":[102.28924000000001,31.86852],"type":"Point"}
}