{
  "type": "Feature",
  "properties": {
    "gn:admin1_code":"3.0",
    "gn:asciiname":"Huawu",
    "gn:country_code":"CN",
    "gn:dem":242,
    "gn:feature_class":"P",
    "gn:feature_code":"PPL",
    "gn:name":"Huawu",
    "gn:population":0,
    "gn:timezone":"Asia/Shanghai",
    "iso:country":"CN",
    "name:zho_x_preferred":[
        "\u534e\u5c4b"
    ],
    "wof:name":"Huawu",
    "wof:placetype":"locality"
},
  "geometry": {"coordinates":[116.13800000000001,25.8898],"type":"Point"}
}