{
  "type": "Feature",
  "properties": {
    "gn:admin1_code":"9.0",
    "gn:asciiname":"Beizhangzhuang",
    "gn:country_code":"CN",
    "gn:dem":83,
    "gn:feature_class":"P",
    "gn:feature_code":"PPL",
    "gn:name":"Beizhangzhuang",
    "gn:population":0,
    "gn:timezone":"Asia/Shanghai",
    "iso:country":"CN",
    "name:zho_x_preferred":[
        "\u5317\u5f20\u5e84"
    ],
    "wof:name":"Beizhangzhuang",
    "wof:placetype":"locality"
},
  "geometry": {"coordinates":[113.66159,35.16982],"type":"Point"}
}