{
  "type": "Feature",
  "properties": {
    "gn:admin1_code":"26.0",
    "gn:asciiname":"Mao'ergounao",
    "gn:country_code":"CN",
    "gn:dem":792,
    "gn:feature_class":"P",
    "gn:feature_code":"PPL",
    "gn:name":"Mao\u2019ergounao",
    "gn:population":0,
    "gn:timezone":"Asia/Shanghai",
    "iso:country":"CN",
    "name:und_x_variant":[
        "Mao\u2019ergounao"
    ],
    "name:zho_x_preferred":[
        "\u732b\u8033\u6c9f\u8111"
    ],
    "wof:name":"Mao'ergounao",
    "wof:placetype":"locality"
},
  "geometry": {"coordinates":[108.96943,33.34954],"type":"Point"}
}