{
  "type": "Feature",
  "properties": {
    "gn:admin1_code":"12",
    "gn:asciiname":"Baishiping",
    "gn:country_code":"CN",
    "gn:dem":137,
    "gn:feature_class":"P",
    "gn:feature_code":"PPL",
    "gn:name":"Baishiping",
    "gn:population":0,
    "gn:timezone":"Asia/Shanghai",
    "iso:country":"CN",
    "name:und_x_variant":[
        "\u767d\u6c0f\u576a"
    ],
    "wof:name":"Baishiping",
    "wof:placetype":"locality"
},
  "geometry": {"coordinates":[111.23367,30.52119],"type":"Point"}
}