{
  "type": "Feature",
  "properties": {
    "gn:admin1_code":"12.0",
    "gn:asciiname":"Longtoushan",
    "gn:country_code":"CN",
    "gn:dem":481,
    "gn:feature_class":"P",
    "gn:feature_code":"PPL",
    "gn:name":"Longtoushan",
    "gn:population":0,
    "gn:timezone":"Asia/Shanghai",
    "iso:country":"CN",
    "name:zho_x_preferred":[
        "\u9f99\u5934\u5c71"
    ],
    "wof:name":"Longtoushan",
    "wof:placetype":"locality"
},
  "geometry": {"coordinates":[110.49044000000001,29.71501],"type":"Point"}
}