{
  "type": "Feature",
  "properties": {
    "gn:admin1_code":"18.0",
    "gn:asciiname":"Xideng",
    "gn:country_code":"CN",
    "gn:dem":1098,
    "gn:feature_class":"P",
    "gn:feature_code":"PPL",
    "gn:name":"Xideng",
    "gn:population":0,
    "gn:timezone":"Asia/Shanghai",
    "iso:country":"CN",
    "name:zho_x_preferred":[
        "\u7ec6\u767b"
    ],
    "wof:name":"Xideng",
    "wof:placetype":"locality"
},
  "geometry": {"coordinates":[108.411,26.5744],"type":"Point"}
}