{
  "type": "Feature",
  "properties": {
    "gn:admin1_code":"7.0",
    "gn:asciiname":"Linjiaping",
    "gn:country_code":"CN",
    "gn:dem":519,
    "gn:feature_class":"P",
    "gn:feature_code":"PPL",
    "gn:name":"Linjiaping",
    "gn:population":0,
    "gn:timezone":"Asia/Shanghai",
    "iso:country":"CN",
    "name:und_x_variant":[
        "\u6797\u5bb6\u576a"
    ],
    "name:zho_x_preferred":[
        "\u6797\u5bb6\u576a"
    ],
    "wof:name":"Linjiaping",
    "wof:placetype":"locality"
},
  "geometry": {"coordinates":[116.60401,25.52194],"type":"Point"}
}