{
  "type": "Feature",
  "properties": {
    "gn:admin1_code":"9.0",
    "gn:asciiname":"Zhanggouya",
    "gn:country_code":"CN",
    "gn:dem":42,
    "gn:feature_class":"P",
    "gn:feature_code":"PPL",
    "gn:name":"Zhanggouya",
    "gn:population":0,
    "gn:timezone":"Asia/Shanghai",
    "iso:country":"CN",
    "name:zho_x_preferred":[
        "\u5f20\u6c9f\u6daf"
    ],
    "wof:name":"Zhanggouya",
    "wof:placetype":"locality"
},
  "geometry": {"coordinates":[115.47235000000001,33.63244],"type":"Point"}
}