{
  "type": "Feature",
  "properties": {
    "gn:admin1_code":"26",
    "gn:asciiname":"Longquan",
    "gn:country_code":"CN",
    "gn:dem":453,
    "gn:feature_class":"P",
    "gn:feature_code":"PPLA4",
    "gn:name":"Longquan",
    "gn:population":0,
    "gn:timezone":"Asia/Shanghai",
    "iso:country":"CN",
    "name:zho_x_preferred":[
        "\u9f99\u6cc9"
    ],
    "wof:name":"Longquan",
    "wof:placetype":"locality"
},
  "geometry": {"coordinates":[108.86806,34.68472],"type":"Point"}
}