{
  "type": "Feature",
  "properties": {
    "gn:admin1_code":"33.0",
    "gn:asciiname":"Pangwu",
    "gn:country_code":"CN",
    "gn:dem":333,
    "gn:feature_class":"P",
    "gn:feature_code":"PPL",
    "gn:name":"Pangwu",
    "gn:population":0,
    "gn:timezone":"Asia/Shanghai",
    "iso:country":"CN",
    "name:zho_x_preferred":[
        "\u8783\u5c4b"
    ],
    "wof:name":"Pangwu",
    "wof:placetype":"locality"
},
  "geometry": {"coordinates":[105.78834999999999,29.95562],"type":"Point"}
}