{
  "type": "Feature",
  "properties": {
    "gn:admin1_code":"9.0",
    "gn:asciiname":"Chenggaocun",
    "gn:country_code":"CN",
    "gn:dem":69,
    "gn:feature_class":"P",
    "gn:feature_code":"PPL",
    "gn:name":"Chenggaocun",
    "gn:population":0,
    "gn:timezone":"Asia/Shanghai",
    "iso:country":"CN",
    "name:zho_x_preferred":[
        "\u57ce\u9ad8\u6751"
    ],
    "wof:name":"Chenggaocun",
    "wof:placetype":"locality"
},
  "geometry": {"coordinates":[113.82937,33.74588],"type":"Point"}
}