{
  "type": "Feature",
  "properties": {
    "gn:admin1_code":"4.0",
    "gn:asciiname":"Yuangengshang",
    "gn:country_code":"CN",
    "gn:dem":8,
    "gn:feature_class":"P",
    "gn:feature_code":"PPL",
    "gn:name":"Yuangengshang",
    "gn:population":0,
    "gn:timezone":"Asia/Shanghai",
    "iso:country":"CN",
    "name:und_x_variant":[
        "\u8881\u57c2\u4e0a"
    ],
    "name:zho_x_preferred":[
        "\u8881\u57c2\u4e0a"
    ],
    "wof:name":"Yuangengshang",
    "wof:placetype":"locality"
},
  "geometry": {"coordinates":[120.51371,31.65667],"type":"Point"}
}