{
  "type": "Feature",
  "properties": {
    "gn:admin1_code":"11",
    "gn:asciiname":"Liangjiangkou",
    "gn:country_code":"CN",
    "gn:dem":577,
    "gn:feature_class":"P",
    "gn:feature_code":"PPL",
    "gn:name":"Liangjiangkou",
    "gn:population":0,
    "gn:timezone":"Asia/Shanghai",
    "iso:country":"CN",
    "name:und_x_variant":[
        "\u4e24\u6c5f\u53e3",
        "Liangjiangkou"
    ],
    "wof:name":"Liangjiangkou",
    "wof:placetype":"locality"
},
  "geometry": {"coordinates":[111.89556,25.84444],"type":"Point"}
}