{
  "type": "Feature",
  "properties": {
    "gn:admin1_code":"11.0",
    "gn:asciiname":"Yanjiayu",
    "gn:country_code":"CN",
    "gn:dem":110,
    "gn:feature_class":"P",
    "gn:feature_code":"PPL",
    "gn:name":"Yanjiayu",
    "gn:population":0,
    "gn:timezone":"Asia/Shanghai",
    "iso:country":"CN",
    "name:und_x_variant":[
        "\u9122\u5bb6\u5809"
    ],
    "wof:name":"Yanjiayu",
    "wof:placetype":"locality"
},
  "geometry": {"coordinates":[111.25156,29.14456],"type":"Point"}
}