{
  "type": "Feature",
  "properties": {
    "gn:admin1_code":"4.0",
    "gn:asciiname":"Chenggang Sizu",
    "gn:country_code":"CN",
    "gn:dem":4,
    "gn:feature_class":"P",
    "gn:feature_code":"PPLF",
    "gn:name":"Chenggang Sizu",
    "gn:population":0,
    "gn:timezone":"Asia/Shanghai",
    "iso:country":"CN",
    "name:zho_x_preferred":[
        "\u57ce\u6e2f\u56db\u7ec4"
    ],
    "wof:name":"Chenggang Sizu",
    "wof:placetype":"locality"
},
  "geometry": {"coordinates":[120.83493,32.02395],"type":"Point"}
}