{
  "type": "Feature",
  "properties": {
    "gn:admin1_code":"18",
    "gn:asciiname":"Laowuji",
    "gn:country_code":"CN",
    "gn:dem":764,
    "gn:feature_class":"P",
    "gn:feature_code":"PPL",
    "gn:name":"Laowuji",
    "gn:population":0,
    "gn:timezone":"Asia/Shanghai",
    "iso:country":"CN",
    "name:zho_x_preferred":[
        "\u8001\u5c4b\u57fa"
    ],
    "wof:name":"Laowuji",
    "wof:placetype":"locality"
},
  "geometry": {"coordinates":[108.01600000000001,27.9647],"type":"Point"}
}