{
  "type": "Feature",
  "properties": {
    "gn:admin1_code":"4.0",
    "gn:asciiname":"Nanzhaozhuang",
    "gn:country_code":"CN",
    "gn:dem":7,
    "gn:feature_class":"P",
    "gn:feature_code":"PPL",
    "gn:name":"Nanzhaozhuang",
    "gn:population":0,
    "gn:timezone":"Asia/Shanghai",
    "iso:country":"CN",
    "name:zho_x_preferred":[
        "\u5357\u8d75\u5e84"
    ],
    "wof:name":"Nanzhaozhuang",
    "wof:placetype":"locality"
},
  "geometry": {"coordinates":[120.34023000000001,32.23856],"type":"Point"}
}