{
  "type": "Feature",
  "properties": {
    "gn:admin1_code":"25",
    "gn:asciiname":"Quanzi",
    "gn:country_code":"CN",
    "gn:dem":210,
    "gn:feature_class":"P",
    "gn:feature_code":"PPL",
    "gn:name":"Quanzi",
    "gn:population":0,
    "gn:timezone":"Asia/Shanghai",
    "iso:country":"CN",
    "name:zho_x_preferred":[
        "\u6cc9\u5b50"
    ],
    "wof:name":"Quanzi",
    "wof:placetype":"locality"
},
  "geometry": {"coordinates":[117.72799999999999,36.2104],"type":"Point"}
}