{
  "type": "Feature",
  "properties": {
    "gn:admin1_code":"02",
    "gn:asciiname":"Yuchicun",
    "gn:country_code":"CN",
    "gn:dem":7,
    "gn:feature_class":"P",
    "gn:feature_code":"PPL",
    "gn:name":"Yuchicun",
    "gn:population":0,
    "gn:timezone":"Asia/Shanghai",
    "iso:country":"CN",
    "name:und_x_variant":[
        "Y\u00fc-tung",
        "Yuchidang",
        "Yuchi",
        "Yuchicun"
    ],
    "name:zho_x_preferred":[
        "\u9c7c\u6c60"
    ],
    "name:zho_x_variant":[
        "Y\u00fc-tung",
        "\u6e14\u6c60\u6751"
    ],
    "wof:name":"Yuchicun",
    "wof:placetype":"locality"
},
  "geometry": {"coordinates":[120.84851,27.89866],"type":"Point"}
}