{
  "type": "Feature",
  "properties": {
    "gn:admin1_code":"19.0",
    "gn:asciiname":"Yong'anqiao",
    "gn:country_code":"CN",
    "gn:dem":42,
    "gn:feature_class":"P",
    "gn:feature_code":"PPL",
    "gn:name":"Yong\u2019anqiao",
    "gn:population":0,
    "gn:timezone":"Asia/Shanghai",
    "iso:country":"CN",
    "name:und_x_variant":[
        "\u6c38\u5b89\u6865"
    ],
    "name:zho_x_preferred":[
        "Yong\u2019anqiao"
    ],
    "name:zho_x_variant":[
        "\u6c38\u5b89\u6865"
    ],
    "wof:name":"Yong'anqiao",
    "wof:placetype":"locality"
},
  "geometry": {"coordinates":[123.2933,41.86494],"type":"Point"}
}