{
  "type": "Feature",
  "properties": {
    "gn:admin1_code":"11.0",
    "gn:asciiname":"Congshushan",
    "gn:country_code":"CN",
    "gn:dem":50,
    "gn:feature_class":"P",
    "gn:feature_code":"PPL",
    "gn:name":"Congshushan",
    "gn:population":0,
    "gn:timezone":"Asia/Shanghai",
    "iso:country":"CN",
    "name:zho_x_preferred":[
        "\u4e1b\u6811\u5c71"
    ],
    "wof:name":"Congshushan",
    "wof:placetype":"locality"
},
  "geometry": {"coordinates":[112.89472000000001,28.36283],"type":"Point"}
}