{
  "type": "Feature",
  "properties": {
    "gn:admin1_code":"7.0",
    "gn:asciiname":"Tangzhangkeng",
    "gn:country_code":"CN",
    "gn:dem":402,
    "gn:feature_class":"P",
    "gn:feature_code":"PPL",
    "gn:name":"Tangzhangkeng",
    "gn:population":0,
    "gn:timezone":"Asia/Shanghai",
    "iso:country":"CN",
    "name:und_x_variant":[
        "\u6c64\u6a1f\u5751"
    ],
    "name:zho_x_preferred":[
        "\u6c64\u6a1f\u5751"
    ],
    "wof:name":"Tangzhangkeng",
    "wof:placetype":"locality"
},
  "geometry": {"coordinates":[117.56143,26.37529],"type":"Point"}
}