{
  "type": "Feature",
  "properties": {
    "gn:admin1_code":"11",
    "gn:asciiname":"Longtou",
    "gn:country_code":"CN",
    "gn:dem":735,
    "gn:feature_class":"P",
    "gn:feature_code":"PPL",
    "gn:name":"Longtou",
    "gn:population":0,
    "gn:timezone":"Asia/Shanghai",
    "iso:country":"CN",
    "wof:name":"Longtou",
    "wof:placetype":"locality"
},
  "geometry": {"coordinates":[113.83333,25.78333],"type":"Point"}
}