{
  "type": "Feature",
  "properties": {
    "gn:admin1_code":"14.0",
    "gn:asciiname":"Rema",
    "gn:country_code":"CN",
    "gn:dem":3124,
    "gn:feature_class":"P",
    "gn:feature_code":"PPL",
    "gn:name":"Rema",
    "gn:population":0,
    "gn:timezone":"Asia/Urumqi",
    "iso:country":"CN",
    "name:zho_x_preferred":[
        "\u70ed\u739b"
    ],
    "wof:name":"Rema",
    "wof:placetype":"locality"
},
  "geometry": {"coordinates":[85.22369999999999,28.459],"type":"Point"}
}