{
  "type": "Feature",
  "properties": {
    "gn:admin1_code":"19.0",
    "gn:asciiname":"Houdaizitun",
    "gn:country_code":"CN",
    "gn:dem":75,
    "gn:feature_class":"P",
    "gn:feature_code":"PPL",
    "gn:name":"Houdaizitun",
    "gn:population":0,
    "gn:timezone":"Asia/Shanghai",
    "iso:country":"CN",
    "name:und_x_variant":[
        "\u540e\u4ee3\u5b50\u5c6f"
    ],
    "name:zho_x_preferred":[
        "\u540e\u4ee3\u5b50\u5c6f"
    ],
    "wof:name":"Houdaizitun",
    "wof:placetype":"locality"
},
  "geometry": {"coordinates":[122.32783999999999,42.22806],"type":"Point"}
}