{
  "type": "Feature",
  "properties": {
    "gn:admin1_code":"1.0",
    "gn:asciiname":"Wujiagangcun",
    "gn:country_code":"CN",
    "gn:dem":44,
    "gn:feature_class":"P",
    "gn:feature_code":"PPL",
    "gn:name":"Wujiagangcun",
    "gn:population":0,
    "gn:timezone":"Asia/Shanghai",
    "iso:country":"CN",
    "name:zho_x_preferred":[
        "\u5434\u5bb6\u5c97\u6751"
    ],
    "wof:name":"Wujiagangcun",
    "wof:placetype":"locality"
},
  "geometry": {"coordinates":[116.40184000000001,32.12871],"type":"Point"}
}