{
  "type": "Feature",
  "properties": {
    "gn:admin1_code":"29.0",
    "gn:asciiname":"Xiananzhuang",
    "gn:country_code":"CN",
    "gn:dem":1470,
    "gn:feature_class":"P",
    "gn:feature_code":"PPL",
    "gn:name":"Xiananzhuang",
    "gn:population":0,
    "gn:timezone":"Asia/Shanghai",
    "iso:country":"CN",
    "name:zho_x_preferred":[
        "\u4e0b\u5357\u5e84"
    ],
    "wof:name":"Xiananzhuang",
    "wof:placetype":"locality"
},
  "geometry": {"coordinates":[100.57599999999999,26.002],"type":"Point"}
}