{
  "type": "Feature",
  "properties": {
    "gn:admin1_code":"12.0",
    "gn:asciiname":"Jiaozhuang",
    "gn:country_code":"CN",
    "gn:dem":647,
    "gn:feature_class":"P",
    "gn:feature_code":"PPL",
    "gn:name":"Jiaozhuang",
    "gn:population":0,
    "gn:timezone":"Asia/Shanghai",
    "iso:country":"CN",
    "name:zho_x_preferred":[
        "\u7126\u6869"
    ],
    "wof:name":"Jiaozhuang",
    "wof:placetype":"locality"
},
  "geometry": {"coordinates":[109.73367,30.44324000000001],"type":"Point"}
}