{
  "type": "Feature",
  "properties": {
    "gn:admin1_code":"30.0",
    "gn:asciiname":"Shangpailing",
    "gn:country_code":"CN",
    "gn:dem":31,
    "gn:feature_class":"P",
    "gn:feature_code":"PPL",
    "gn:name":"Shangpailing",
    "gn:population":0,
    "gn:timezone":"Asia/Shanghai",
    "iso:country":"CN",
    "name:zho_x_preferred":[
        "\u4e0a\u6392\u5cad"
    ],
    "wof:name":"Shangpailing",
    "wof:placetype":"locality"
},
  "geometry": {"coordinates":[114.7697,23.02187],"type":"Point"}
}