{
  "type": "Feature",
  "properties": {
    "gn:admin1_code":"3",
    "gn:asciiname":"Li'oudu",
    "gn:country_code":"CN",
    "gn:dem":98,
    "gn:feature_class":"P",
    "gn:feature_code":"PPL",
    "gn:name":"Li\u2019oudu",
    "gn:population":0,
    "gn:timezone":"Asia/Shanghai",
    "iso:country":"CN",
    "name:und_x_variant":[
        "Li\u2019oudu"
    ],
    "name:zho_x_preferred":[
        "\u9ca4\u9e25\u6e21"
    ],
    "wof:name":"Li'oudu",
    "wof:placetype":"locality"
},
  "geometry": {"coordinates":[114.89700000000001,27.002],"type":"Point"}
}