{
  "type": "Feature",
  "properties": {
    "gn:admin1_code":"32.0",
    "gn:asciiname":"Nigu",
    "gn:country_code":"CN",
    "gn:dem":2199,
    "gn:feature_class":"P",
    "gn:feature_code":"PPL",
    "gn:name":"Nigu",
    "gn:population":0,
    "gn:timezone":"Asia/Shanghai",
    "iso:country":"CN",
    "name:zho_x_preferred":[
        "\u5c3c\u8c37"
    ],
    "wof:name":"Nigu",
    "wof:placetype":"locality"
},
  "geometry": {"coordinates":[102.88200000000001,27.8731],"type":"Point"}
}