{
  "type": "Feature",
  "properties": {
    "gn:admin1_code":"2.0",
    "gn:asciiname":"Dalebang",
    "gn:country_code":"CN",
    "gn:dem":7,
    "gn:feature_class":"P",
    "gn:feature_code":"PPL",
    "gn:name":"Dalebang",
    "gn:population":0,
    "gn:timezone":"Asia/Shanghai",
    "iso:country":"CN",
    "name:und_x_variant":[
        "\u5927\u4e50\u6d5c"
    ],
    "wof:name":"Dalebang",
    "wof:placetype":"locality"
},
  "geometry": {"coordinates":[120.69217999999999,30.57368],"type":"Point"}
}