{
  "type": "Feature",
  "properties": {
    "gn:admin1_code":"26.0",
    "gn:asciiname":"Huajiaoshu",
    "gn:country_code":"CN",
    "gn:dem":1446,
    "gn:feature_class":"P",
    "gn:feature_code":"PPL",
    "gn:name":"Huajiaoshu",
    "gn:population":0,
    "gn:timezone":"Asia/Shanghai",
    "iso:country":"CN",
    "name:und_x_variant":[
        "\u82b1\u6912\u6811"
    ],
    "wof:name":"Huajiaoshu",
    "wof:placetype":"locality"
},
  "geometry": {"coordinates":[106.84887000000001,33.94228],"type":"Point"}
}