{
  "type": "Feature",
  "properties": {
    "gn:admin1_code":"26",
    "gn:asciiname":"Yangjiatai",
    "gn:country_code":"CN",
    "gn:dem":1731,
    "gn:feature_class":"P",
    "gn:feature_code":"PPL",
    "gn:name":"Yangjiatai",
    "gn:population":0,
    "gn:timezone":"Asia/Shanghai",
    "iso:country":"CN",
    "wof:name":"Yangjiatai",
    "wof:placetype":"locality"
},
  "geometry": {"coordinates":[108.5625,35.09583],"type":"Point"}
}