{
  "type": "Feature",
  "properties": {
    "gn:admin1_code":"26.0",
    "gn:asciiname":"Quanjiahe",
    "gn:country_code":"CN",
    "gn:dem":984,
    "gn:feature_class":"P",
    "gn:feature_code":"PPL",
    "gn:name":"Quanjiahe",
    "gn:population":0,
    "gn:timezone":"Asia/Shanghai",
    "iso:country":"CN",
    "name:zho_x_preferred":[
        "\u5168\u5bb6\u6cb3"
    ],
    "wof:name":"Quanjiahe",
    "wof:placetype":"locality"
},
  "geometry": {"coordinates":[107.95169,35.18322],"type":"Point"}
}