{
  "type": "Feature",
  "properties": {
    "gn:admin1_code":"5.0",
    "gn:asciiname":"Hongtiancun",
    "gn:country_code":"CN",
    "gn:dem":226,
    "gn:feature_class":"P",
    "gn:feature_code":"PPL",
    "gn:name":"Hongtiancun",
    "gn:population":0,
    "gn:timezone":"Asia/Shanghai",
    "iso:country":"CN",
    "name:zho_x_preferred":[
        "\u7ea2\u7530\u6751"
    ],
    "wof:name":"Hongtiancun",
    "wof:placetype":"locality"
},
  "geometry": {"coordinates":[125.36803999999999,43.59546],"type":"Point"}
}