{
  "type": "Feature",
  "properties": {
    "gn:admin1_code":"30.0",
    "gn:asciiname":"Jinshishui",
    "gn:country_code":"CN",
    "gn:dem":390,
    "gn:feature_class":"P",
    "gn:feature_code":"PPL",
    "gn:name":"Jinshishui",
    "gn:population":0,
    "gn:timezone":"Asia/Shanghai",
    "iso:country":"CN",
    "name:zho_x_preferred":[
        "\u91d1\u77f3\u6c34"
    ],
    "wof:name":"Jinshishui",
    "wof:placetype":"locality"
},
  "geometry": {"coordinates":[115.11794999999999,23.1949],"type":"Point"}
}