{
  "type": "Feature",
  "properties": {
    "gn:admin1_code":"24",
    "gn:asciiname":"Fanshi",
    "gn:country_code":"CN",
    "gn:dem":925,
    "gn:feature_class":"P",
    "gn:feature_code":"PPLA3",
    "gn:name":"Fanshi",
    "gn:population":0,
    "gn:timezone":"Asia/Shanghai",
    "iso:country":"CN",
    "name:und_x_variant":[
        "Chiu-fan-chih",
        "Fantzehsien",
        "Fan-chih-hsien",
        "Fan-shih",
        "Fansze",
        "Fan-chih",
        "Fanzhi Xian",
        "Fancheng",
        "Fancheng Zhen",
        "\u7e41\u57ce\u9547",
        "\u7e41\u5cd9\u53bf"
    ],
    "name:zho_x_preferred":[
        "Fan-chih-ch\u2019eng"
    ],
    "name:zho_x_variant":[
        "\u7e41\u57ce"
    ],
    "wof:name":"Fanshi",
    "wof:placetype":"locality"
},
  "geometry": {"coordinates":[113.26401,39.18992],"type":"Point"}
}