{
  "type": "Feature",
  "properties": {
    "gn:admin1_code":"15.0",
    "gn:asciiname":"Dicang",
    "gn:country_code":"CN",
    "gn:dem":3028,
    "gn:feature_class":"P",
    "gn:feature_code":"PPL",
    "gn:name":"Dicang",
    "gn:population":0,
    "gn:timezone":"Asia/Shanghai",
    "iso:country":"CN",
    "name:und_x_variant":[
        "\u5730\u4ed3"
    ],
    "wof:name":"Dicang",
    "wof:placetype":"locality"
},
  "geometry": {"coordinates":[102.44316000000001,35.14554],"type":"Point"}
}