{
  "type": "Feature",
  "properties": {
    "gn:admin1_code":"25",
    "gn:asciiname":"Houhaizhuang",
    "gn:country_code":"CN",
    "gn:dem":8,
    "gn:feature_class":"P",
    "gn:feature_code":"PPL",
    "gn:name":"Houhaizhuang",
    "gn:population":0,
    "gn:timezone":"Asia/Shanghai",
    "iso:country":"CN",
    "name:zho_x_preferred":[
        "\u540e\u6d77\u5e84"
    ],
    "wof:name":"Houhaizhuang",
    "wof:placetype":"locality"
},
  "geometry": {"coordinates":[120.062,36.1783],"type":"Point"}
}