{
  "type": "Feature",
  "properties": {
    "gn:admin1_code":"16.0",
    "gn:asciiname":"Xiajinpao",
    "gn:country_code":"CN",
    "gn:dem":142,
    "gn:feature_class":"P",
    "gn:feature_code":"PPL",
    "gn:name":"Xiajinpao",
    "gn:population":0,
    "gn:timezone":"Asia/Shanghai",
    "iso:country":"CN",
    "name:zho_x_preferred":[
        "\u4e0b\u91d1\u888d"
    ],
    "wof:name":"Xiajinpao",
    "wof:placetype":"locality"
},
  "geometry": {"coordinates":[109.944,24.4841],"type":"Point"}
}