{
  "type": "Feature",
  "properties": {
    "gn:admin1_code":"14.0",
    "gn:asciiname":"Daguicun",
    "gn:country_code":"CN",
    "gn:dem":4014,
    "gn:feature_class":"P",
    "gn:feature_code":"PPL",
    "gn:name":"Daguicun",
    "gn:population":0,
    "gn:timezone":"Asia/Urumqi",
    "iso:country":"CN",
    "name:zho_x_preferred":[
        "\u8fbe\u8d35\u6751"
    ],
    "wof:name":"Daguicun",
    "wof:placetype":"locality"
},
  "geometry": {"coordinates":[92.88827000000001,28.93881],"type":"Point"}
}