{
  "type": "Feature",
  "properties": {
    "gn:admin1_code":"12.0",
    "gn:asciiname":"Yangjiashan",
    "gn:country_code":"CN",
    "gn:dem":536,
    "gn:feature_class":"P",
    "gn:feature_code":"PPL",
    "gn:name":"Yangjiashan",
    "gn:population":0,
    "gn:timezone":"Asia/Shanghai",
    "iso:country":"CN",
    "name:zho_x_preferred":[
        "\u6768\u5bb6\u5c71"
    ],
    "wof:name":"Yangjiashan",
    "wof:placetype":"locality"
},
  "geometry": {"coordinates":[111.87251999999999,31.48892],"type":"Point"}
}