{
  "type": "Feature",
  "properties": {
    "gn:admin1_code":"18",
    "gn:asciiname":"Xiaojia Zhaizi",
    "gn:country_code":"CN",
    "gn:dem":1907,
    "gn:feature_class":"P",
    "gn:feature_code":"PPL",
    "gn:name":"Xiaojia Zhaizi",
    "gn:population":0,
    "gn:timezone":"Asia/Shanghai",
    "iso:country":"CN",
    "name:zho_x_preferred":[
        "\u8096\u5bb6\u5be8\u5b50"
    ],
    "wof:name":"Xiaojia Zhaizi",
    "wof:placetype":"locality"
},
  "geometry": {"coordinates":[104.893,26.8985],"type":"Point"}
}