{
  "type": "Feature",
  "properties": {
    "gn:admin1_code":"20.0",
    "gn:asciiname":"Xiaozhaogou",
    "gn:country_code":"CN",
    "gn:dem":1514,
    "gn:feature_class":"P",
    "gn:feature_code":"PPL",
    "gn:name":"Xiaozhaogou",
    "gn:population":0,
    "gn:timezone":"Asia/Shanghai",
    "iso:country":"CN",
    "name:und_x_variant":[
        "\u5c0f\u53ec\u6c9f"
    ],
    "wof:name":"Xiaozhaogou",
    "wof:placetype":"locality"
},
  "geometry": {"coordinates":[109.85218,41.01854],"type":"Point"}
}