{
  "type": "Feature",
  "properties": {
    "gn:admin1_code":"16.0",
    "gn:asciiname":"Wanlie",
    "gn:country_code":"CN",
    "gn:dem":866,
    "gn:feature_class":"P",
    "gn:feature_code":"PPL",
    "gn:name":"Wanlie",
    "gn:population":0,
    "gn:timezone":"Asia/Shanghai",
    "iso:country":"CN",
    "name:zho_x_preferred":[
        "\u633d\u5217"
    ],
    "wof:name":"Wanlie",
    "wof:placetype":"locality"
},
  "geometry": {"coordinates":[107.404,25.1649],"type":"Point"}
}