{
  "type": "Feature",
  "properties": {
    "gn:admin1_code":"03",
    "gn:asciiname":"Longgang Shezu",
    "gn:country_code":"CN",
    "gn:dem":146,
    "gn:feature_class":"P",
    "gn:feature_code":"PPLA4",
    "gn:name":"Longgang Shezu",
    "gn:population":0,
    "gn:timezone":"Asia/Shanghai",
    "iso:country":"CN",
    "name:und_x_variant":[
        "Lung-kang-hs\u00fc",
        "Lung-kang",
        "Longgang Shezu",
        "\u9f99\u5188\u7572\u65cf",
        "Longgang",
        "Longgang Shezu Xiang",
        "\u9f99\u5188\u7572\u65cf\u4e61"
    ],
    "wof:name":"Longgang Shezu",
    "wof:placetype":"locality"
},
  "geometry": {"coordinates":[115.58308999999998,26.73842],"type":"Point"}
}