{
  "type": "Feature",
  "properties": {
    "gn:admin1_code":"1.0",
    "gn:asciiname":"Zhaozhaicun",
    "gn:country_code":"CN",
    "gn:dem":49,
    "gn:feature_class":"P",
    "gn:feature_code":"PPL",
    "gn:name":"Zhaozhaicun",
    "gn:population":0,
    "gn:timezone":"Asia/Shanghai",
    "iso:country":"CN",
    "name:zho_x_preferred":[
        "\u8d75\u5be8\u6751"
    ],
    "wof:name":"Zhaozhaicun",
    "wof:placetype":"locality"
},
  "geometry": {"coordinates":[116.66573,31.81727],"type":"Point"}
}