{
  "type": "Feature",
  "properties": {
    "gn:admin1_code":"8.0",
    "gn:asciiname":"Wolongshan Nongchang",
    "gn:country_code":"CN",
    "gn:dem":188,
    "gn:feature_class":"P",
    "gn:feature_code":"PPLF",
    "gn:name":"Wolongshan Nongchang",
    "gn:population":0,
    "gn:timezone":"Asia/Shanghai",
    "iso:country":"CN",
    "name:zho_x_preferred":[
        "\u5367\u9f99\u5c71\u519c\u573a"
    ],
    "wof:name":"Wolongshan Nongchang",
    "wof:placetype":"locality"
},
  "geometry": {"coordinates":[130.42433,47.39682],"type":"Point"}
}