{
  "type": "Feature",
  "properties": {
    "gn:admin1_code":"31.0",
    "gn:asciiname":"Liujiaoling",
    "gn:country_code":"CN",
    "gn:dem":33,
    "gn:feature_class":"P",
    "gn:feature_code":"PPL",
    "gn:name":"Liujiaoling",
    "gn:population":0,
    "gn:timezone":"Asia/Shanghai",
    "iso:country":"CN",
    "name:zho_x_preferred":[
        "\u516d\u89d2\u5cad"
    ],
    "wof:name":"Liujiaoling",
    "wof:placetype":"locality"
},
  "geometry": {"coordinates":[110.29257,18.91304],"type":"Point"}
}