{
  "type": "Feature",
  "properties": {
    "gn:admin1_code":"16",
    "gn:asciiname":"Jiangshan",
    "gn:country_code":"CN",
    "gn:dem":40,
    "gn:feature_class":"P",
    "gn:feature_code":"PPL",
    "gn:name":"Jiangshan",
    "gn:population":0,
    "gn:timezone":"Asia/Shanghai",
    "iso:country":"CN",
    "name:deu_x_preferred":[
        "Jiangshan"
    ],
    "name:fra_x_preferred":[
        "Jiangshan"
    ],
    "name:ita_x_preferred":[
        "Jiangshan"
    ],
    "name:jpn_x_preferred":[
        "\u6c5f\u5c71\u5e02"
    ],
    "name:kik_x_preferred":[
        "Jiangshan"
    ],
    "name:kor_x_preferred":[
        "\uc7a5\uc0b0\uc2dc"
    ],
    "name:mlg_x_preferred":[
        "Jiangshan"
    ],
    "name:nor_x_preferred":[
        "Jiangshan"
    ],
    "name:swe_x_preferred":[
        "Jiangshan"
    ],
    "name:tgl_x_preferred":[
        "Jiangshan"
    ],
    "name:vie_x_preferred":[
        "Giang S\u01a1n"
    ],
    "name:war_x_preferred":[
        "Jiangshan"
    ],
    "name:wuu_x_preferred":[
        "\u6c5f\u5c71\u5e02"
    ],
    "name:zho_x_preferred":[
        "\u6c5f\u5c71\u5e02"
    ],
    "wof:name":"Jiangshan",
    "wof:placetype":"locality"
},
  "geometry": {"coordinates":[108.25,21.65],"type":"Point"}
}