{
  "type": "Feature",
  "properties": {
    "gn:admin1_code":"32.0",
    "gn:asciiname":"Siguanzhai",
    "gn:country_code":"CN",
    "gn:dem":423,
    "gn:feature_class":"P",
    "gn:feature_code":"PPL",
    "gn:name":"Siguanzhai",
    "gn:population":0,
    "gn:timezone":"Asia/Shanghai",
    "iso:country":"CN",
    "name:zho_x_preferred":[
        "\u56db\u5173\u5be8"
    ],
    "wof:name":"Siguanzhai",
    "wof:placetype":"locality"
},
  "geometry": {"coordinates":[106.59506,30.72544000000001],"type":"Point"}
}