{
  "type": "Feature",
  "properties": {
    "gn:admin1_code":"30",
    "gn:asciiname":"Tianzili",
    "gn:country_code":"CN",
    "gn:dem":411,
    "gn:feature_class":"P",
    "gn:feature_code":"PPL",
    "gn:name":"Tianzili",
    "gn:population":0,
    "gn:timezone":"Asia/Shanghai",
    "iso:country":"CN",
    "name:zho_x_preferred":[
        "\u7530\u5b50\u91cc"
    ],
    "wof:name":"Tianzili",
    "wof:placetype":"locality"
},
  "geometry": {"coordinates":[116.41953999999998,24.22267],"type":"Point"}
}