{
  "type": "Feature",
  "properties": {
    "gn:admin1_code":"32.0",
    "gn:asciiname":"Penggu",
    "gn:country_code":"CN",
    "gn:dem":2996,
    "gn:feature_class":"P",
    "gn:feature_code":"PPL",
    "gn:name":"Penggu",
    "gn:population":0,
    "gn:timezone":"Asia/Shanghai",
    "iso:country":"CN",
    "name:zho_x_preferred":[
        "\u5f6d\u53e4"
    ],
    "wof:name":"Penggu",
    "wof:placetype":"locality"
},
  "geometry": {"coordinates":[101.023,29.2866],"type":"Point"}
}