{
  "type": "Feature",
  "properties": {
    "gn:admin1_code":"32.0",
    "gn:asciiname":"Bailinzi",
    "gn:country_code":"CN",
    "gn:dem":400,
    "gn:feature_class":"P",
    "gn:feature_code":"PPL",
    "gn:name":"Bailinzi",
    "gn:population":0,
    "gn:timezone":"Asia/Shanghai",
    "iso:country":"CN",
    "name:zho_x_preferred":[
        "\u67cf\u6797\u5b50"
    ],
    "wof:name":"Bailinzi",
    "wof:placetype":"locality"
},
  "geometry": {"coordinates":[105.929,31.2532],"type":"Point"}
}