{
  "type": "Feature",
  "properties": {
    "gn:admin1_code":"4.0",
    "gn:asciiname":"Zuitougang",
    "gn:country_code":"CN",
    "gn:dem":6,
    "gn:feature_class":"P",
    "gn:feature_code":"PPL",
    "gn:name":"Zuitougang",
    "gn:population":0,
    "gn:timezone":"Asia/Shanghai",
    "iso:country":"CN",
    "name:zho_x_preferred":[
        "\u5634\u5934\u6e2f"
    ],
    "wof:name":"Zuitougang",
    "wof:placetype":"locality"
},
  "geometry": {"coordinates":[119.26711,32.31965],"type":"Point"}
}