{
  "type": "Feature",
  "properties": {
    "gn:admin1_code":"22.0",
    "gn:asciiname":"Longyugoumen",
    "gn:country_code":"CN",
    "gn:dem":241,
    "gn:feature_class":"P",
    "gn:feature_code":"PPL",
    "gn:name":"Longyugoumen",
    "gn:population":0,
    "gn:timezone":"Asia/Shanghai",
    "iso:country":"CN",
    "name:zho_x_preferred":[
        "\u9f99\u5cea\u6c9f\u95e8"
    ],
    "wof:name":"Longyugoumen",
    "wof:placetype":"locality"
},
  "geometry": {"coordinates":[117.18598,40.67526],"type":"Point"}
}