{
  "type": "Feature",
  "properties": {
    "gn:admin1_code":"19.0",
    "gn:asciiname":"Shuangshanzicun",
    "gn:country_code":"CN",
    "gn:dem":685,
    "gn:feature_class":"P",
    "gn:feature_code":"PPL",
    "gn:name":"Shuangshanzicun",
    "gn:population":0,
    "gn:timezone":"Asia/Shanghai",
    "iso:country":"CN",
    "name:zho_x_preferred":[
        "\u53cc\u5c71\u5b50\u6751"
    ],
    "wof:name":"Shuangshanzicun",
    "wof:placetype":"locality"
},
  "geometry": {"coordinates":[119.53400000000001,41.9423],"type":"Point"}
}