{
  "type": "Feature",
  "properties": {
    "gn:admin1_code":"29.0",
    "gn:asciiname":"Tiantou",
    "gn:country_code":"CN",
    "gn:dem":1900,
    "gn:feature_class":"P",
    "gn:feature_code":"PPL",
    "gn:name":"Tiantou",
    "gn:population":0,
    "gn:timezone":"Asia/Shanghai",
    "iso:country":"CN",
    "name:zho_x_preferred":[
        "\u7530\u5934"
    ],
    "wof:name":"Tiantou",
    "wof:placetype":"locality"
},
  "geometry": {"coordinates":[100.021,23.1009],"type":"Point"}
}