{
  "type": "Feature",
  "properties": {
    "gn:admin1_code":"25.0",
    "gn:asciiname":"Shanghui",
    "gn:country_code":"CN",
    "gn:dem":124,
    "gn:feature_class":"P",
    "gn:feature_code":"PPL",
    "gn:name":"Shanghui",
    "gn:population":0,
    "gn:timezone":"Asia/Shanghai",
    "iso:country":"CN",
    "name:zho_x_preferred":[
        "\u4e0a\u6d04"
    ],
    "wof:name":"Shanghui",
    "wof:placetype":"locality"
},
  "geometry": {"coordinates":[119.95131000000001,36.9195],"type":"Point"}
}