{
  "type": "Feature",
  "properties": {
    "gn:admin1_code":"2.0",
    "gn:asciiname":"Lingyin",
    "gn:country_code":"CN",
    "gn:dem":47,
    "gn:feature_class":"P",
    "gn:feature_code":"PPL",
    "gn:name":"Lingyin",
    "gn:population":0,
    "gn:timezone":"Asia/Shanghai",
    "iso:country":"CN",
    "name:und_x_variant":[
        "\u7075\u9690"
    ],
    "wof:name":"Lingyin",
    "wof:placetype":"locality"
},
  "geometry": {"coordinates":[120.10132,30.2453],"type":"Point"}
}