{
  "type": "Feature",
  "properties": {
    "gn:admin1_code":"19.0",
    "gn:asciiname":"Xiaogacha",
    "gn:country_code":"CN",
    "gn:dem":457,
    "gn:feature_class":"P",
    "gn:feature_code":"PPL",
    "gn:name":"Xiaogacha",
    "gn:population":0,
    "gn:timezone":"Asia/Shanghai",
    "iso:country":"CN",
    "name:zho_x_preferred":[
        "\u5c0f\u560e\u5c94"
    ],
    "wof:name":"Xiaogacha",
    "wof:placetype":"locality"
},
  "geometry": {"coordinates":[119.50472000000001,42.35979],"type":"Point"}
}