{
  "type": "Feature",
  "properties": {
    "gn:admin1_code":"02",
    "gn:asciiname":"Wuhaoqiao",
    "gn:country_code":"CN",
    "gn:dem":5,
    "gn:feature_class":"P",
    "gn:feature_code":"PPL",
    "gn:name":"Wuhaoqiao",
    "gn:population":0,
    "gn:timezone":"Asia/Shanghai",
    "iso:country":"CN",
    "name:und_x_variant":[
        "\u4e94\u53f7\u6865"
    ],
    "wof:name":"Wuhaoqiao",
    "wof:placetype":"locality"
},
  "geometry": {"coordinates":[121.18653999999999,30.77239],"type":"Point"}
}