{
  "type": "Feature",
  "properties": {
    "gn:admin1_code":"18",
    "gn:asciiname":"Jiangyou",
    "gn:country_code":"CN",
    "gn:dem":716,
    "gn:feature_class":"P",
    "gn:feature_code":"PPL",
    "gn:name":"Jiangyou",
    "gn:population":0,
    "gn:timezone":"Asia/Shanghai",
    "iso:country":"CN",
    "name:ara_x_preferred":[
        "\u062c\u064a\u0627\u0646\u063a\u064a\u0648"
    ],
    "name:deu_x_preferred":[
        "Jiangyou"
    ],
    "name:epo_x_preferred":[
        "Jiangyou"
    ],
    "name:fas_x_preferred":[
        "\u062c\u06cc\u0627\u0646\u06af\u06cc\u0648"
    ],
    "name:fra_x_preferred":[
        "Jiangyou"
    ],
    "name:ita_x_preferred":[
        "Jiangyou"
    ],
    "name:jpn_x_preferred":[
        "\u6c5f\u6cb9\u5e02"
    ],
    "name:kik_x_preferred":[
        "Jiangyou"
    ],
    "name:kor_x_preferred":[
        "\uc7a5\uc720\uc2dc"
    ],
    "name:mlg_x_preferred":[
        "Jiangyou"
    ],
    "name:nor_x_preferred":[
        "Jiangyou"
    ],
    "name:rus_x_preferred":[
        "\u0426\u0437\u044f\u043d\u044a\u044e"
    ],
    "name:swe_x_preferred":[
        "Jiangyou"
    ],
    "name:urd_x_preferred":[
        "\u062c\u06cc\u0627\u0646\u06af\u06cc\u0648\u0648"
    ],
    "name:vie_x_preferred":[
        "Giang Du"
    ],
    "name:war_x_preferred":[
        "Jiangyou"
    ],
    "name:zho_x_preferred":[
        "\u6c5f\u7531"
    ],
    "name:zho_x_variant":[
        "\u6c5f\u6cb9\u5e02"
    ],
    "wof:name":"Jiangyou",
    "wof:placetype":"locality"
},
  "geometry": {"coordinates":[105.82599999999999,25.3575],"type":"Point"}
}