{
  "type": "Feature",
  "properties": {
    "gn:admin1_code":"22.0",
    "gn:asciiname":"Donglujiaocun",
    "gn:country_code":"CN",
    "gn:dem":32,
    "gn:feature_class":"P",
    "gn:feature_code":"PPL",
    "gn:name":"Donglujiaocun",
    "gn:population":0,
    "gn:timezone":"Asia/Shanghai",
    "iso:country":"CN",
    "name:zho_x_preferred":[
        "\u4e1c\u9e7f\u89d2\u6751"
    ],
    "wof:name":"Donglujiaocun",
    "wof:placetype":"locality"
},
  "geometry": {"coordinates":[117.08651999999999,40.1221],"type":"Point"}
}