{
  "type": "Feature",
  "properties": {
    "gn:admin1_code":"30.0",
    "gn:asciiname":"Wengyangcun",
    "gn:country_code":"CN",
    "gn:dem":7,
    "gn:feature_class":"P",
    "gn:feature_code":"PPL",
    "gn:name":"Wengyangcun",
    "gn:population":0,
    "gn:timezone":"Asia/Shanghai",
    "iso:country":"CN",
    "name:zho_x_preferred":[
        "\u7fc1\u6d0b\u6751"
    ],
    "wof:name":"Wengyangcun",
    "wof:placetype":"locality"
},
  "geometry": {"coordinates":[116.48254,23.58524],"type":"Point"}
}