{
  "type": "Feature",
  "properties": {
    "gn:admin1_code":"04",
    "gn:asciiname":"Houqiao",
    "gn:country_code":"CN",
    "gn:dem":8,
    "gn:feature_class":"P",
    "gn:feature_code":"PPL",
    "gn:name":"Houqiao",
    "gn:population":0,
    "gn:timezone":"Asia/Shanghai",
    "iso:country":"CN",
    "name:und_x_variant":[
        "Hou-ch\u2019iao-chen",
        "Hou-ch\u2019iao",
        "Houqiao"
    ],
    "wof:name":"Houqiao",
    "wof:placetype":"locality"
},
  "geometry": {"coordinates":[120.50239000000001,31.57164],"type":"Point"}
}