{
  "type": "Feature",
  "properties": {
    "gn:admin1_code":"26.0",
    "gn:asciiname":"Mayangta",
    "gn:country_code":"CN",
    "gn:dem":1542,
    "gn:feature_class":"P",
    "gn:feature_code":"PPL",
    "gn:name":"Mayangta",
    "gn:population":0,
    "gn:timezone":"Asia/Shanghai",
    "iso:country":"CN",
    "name:zho_x_preferred":[
        "\u9a6c\u9633\u5854"
    ],
    "wof:name":"Mayangta",
    "wof:placetype":"locality"
},
  "geometry": {"coordinates":[108.42477,37.02775],"type":"Point"}
}