{
  "type": "Feature",
  "properties": {
    "gn:admin1_code":"14.0",
    "gn:asciiname":"Enla",
    "gn:country_code":"CN",
    "gn:dem":3573,
    "gn:feature_class":"P",
    "gn:feature_code":"PPL",
    "gn:name":"Enla",
    "gn:population":0,
    "gn:timezone":"Asia/Urumqi",
    "iso:country":"CN",
    "name:zho_x_preferred":[
        "\u6069\u62c9"
    ],
    "wof:name":"Enla",
    "wof:placetype":"locality"
},
  "geometry": {"coordinates":[97.95560999999999,30.49902],"type":"Point"}
}