{
  "type": "Feature",
  "properties": {
    "gn:admin1_code":"32.0",
    "gn:asciiname":"Waziling",
    "gn:country_code":"CN",
    "gn:dem":460,
    "gn:feature_class":"P",
    "gn:feature_code":"PPL",
    "gn:name":"Waziling",
    "gn:population":0,
    "gn:timezone":"Asia/Shanghai",
    "iso:country":"CN",
    "name:zho_x_preferred":[
        "\u6d3c\u5b50\u5cad"
    ],
    "wof:name":"Waziling",
    "wof:placetype":"locality"
},
  "geometry": {"coordinates":[104.346,30.9583],"type":"Point"}
}