{
  "type": "Feature",
  "properties": {
    "gn:admin1_code":"23.0",
    "gn:asciiname":"Gongjiazhai",
    "gn:country_code":"CN",
    "gn:dem":6,
    "gn:feature_class":"P",
    "gn:feature_code":"PPL",
    "gn:name":"Gongjiazhai",
    "gn:population":0,
    "gn:timezone":"Asia/Shanghai",
    "iso:country":"CN",
    "name:zho_x_preferred":[
        "Gongjiazhai"
    ],
    "name:zho_x_variant":[
        "\u9f9a\u5bb6\u5b85"
    ],
    "wof:name":"Gongjiazhai",
    "wof:placetype":"locality"
},
  "geometry": {"coordinates":[121.67186,31.17071],"type":"Point"}
}