{
  "type": "Feature",
  "properties": {
    "gn:admin1_code":"26.0",
    "gn:asciiname":"Shangxifang",
    "gn:country_code":"CN",
    "gn:dem":1171,
    "gn:feature_class":"P",
    "gn:feature_code":"PPL",
    "gn:name":"Shangxifang",
    "gn:population":0,
    "gn:timezone":"Asia/Shanghai",
    "iso:country":"CN",
    "name:und_x_variant":[
        "\u4e0a\u897f\u574a"
    ],
    "wof:name":"Shangxifang",
    "wof:placetype":"locality"
},
  "geometry": {"coordinates":[107.72083000000001,34.64262],"type":"Point"}
}