{
  "type": "Feature",
  "properties": {
    "gn:admin1_code":"07",
    "gn:asciiname":"Baitu",
    "gn:country_code":"CN",
    "gn:dem":398,
    "gn:feature_class":"P",
    "gn:feature_code":"PPL",
    "gn:name":"Baitu",
    "gn:population":0,
    "gn:timezone":"Asia/Shanghai",
    "iso:country":"CN",
    "name:zho_x_preferred":[
        "Pai-t\u2019u"
    ],
    "wof:name":"Baitu",
    "wof:placetype":"locality"
},
  "geometry": {"coordinates":[117.01635,25.02969],"type":"Point"}
}