{
  "type": "Feature",
  "properties": {
    "gn:admin1_code":"1.0",
    "gn:asciiname":"Liusicun",
    "gn:country_code":"CN",
    "gn:dem":19,
    "gn:feature_class":"P",
    "gn:feature_code":"PPL",
    "gn:name":"Liusicun",
    "gn:population":0,
    "gn:timezone":"Asia/Shanghai",
    "iso:country":"CN",
    "name:und_x_variant":[
        "Liusi"
    ],
    "name:zho_x_preferred":[
        "\u67f3\u5bfa\u6751"
    ],
    "wof:name":"Liusicun",
    "wof:placetype":"locality"
},
  "geometry": {"coordinates":[117.33203,30.95907],"type":"Point"}
}