{
  "type": "Feature",
  "properties": {
    "gn:admin1_code":"19.0",
    "gn:asciiname":"Zhushalacun",
    "gn:country_code":"CN",
    "gn:dem":180,
    "gn:feature_class":"P",
    "gn:feature_code":"PPL",
    "gn:name":"Zhushalacun",
    "gn:population":0,
    "gn:timezone":"Asia/Shanghai",
    "iso:country":"CN",
    "name:zho_x_preferred":[
        "\u6731\u6c99\u62c9\u6751"
    ],
    "wof:name":"Zhushalacun",
    "wof:placetype":"locality"
},
  "geometry": {"coordinates":[121.994,42.3185],"type":"Point"}
}