{
  "type": "Feature",
  "properties": {
    "gn:admin1_code":"30",
    "gn:asciiname":"Jiekeng",
    "gn:country_code":"CN",
    "gn:dem":228,
    "gn:feature_class":"P",
    "gn:feature_code":"PPL",
    "gn:name":"Jiekeng",
    "gn:population":0,
    "gn:timezone":"Asia/Shanghai",
    "iso:country":"CN",
    "wof:name":"Jiekeng",
    "wof:placetype":"locality"
},
  "geometry": {"coordinates":[115.59583000000001,23.725],"type":"Point"}
}