{
  "type": "Feature",
  "properties": {
    "gn:admin1_code":"12.0",
    "gn:asciiname":"Hongyingjie",
    "gn:country_code":"CN",
    "gn:dem":44,
    "gn:feature_class":"P",
    "gn:feature_code":"PPL",
    "gn:name":"Hongyingjie",
    "gn:population":0,
    "gn:timezone":"Asia/Shanghai",
    "iso:country":"CN",
    "name:zho_x_preferred":[
        "\u7ea2\u82f1\u8857"
    ],
    "wof:name":"Hongyingjie",
    "wof:placetype":"locality"
},
  "geometry": {"coordinates":[112.60253,31.04767],"type":"Point"}
}