{
  "type": "Feature",
  "properties": {
    "gn:admin1_code":"20",
    "gn:asciiname":"Hsiao-ma-chia-tzu",
    "gn:country_code":"CN",
    "gn:dem":714,
    "gn:feature_class":"P",
    "gn:feature_code":"PPL",
    "gn:name":"Hsiao-ma-chia-tzu",
    "gn:population":0,
    "gn:timezone":"Asia/Shanghai",
    "iso:country":"CN",
    "wof:name":"Hsiao-ma-chia-tzu",
    "wof:placetype":"locality"
},
  "geometry": {"coordinates":[118.93138999999999,42.69139000000001],"type":"Point"}
}