{
  "type": "Feature",
  "properties": {
    "gn:admin1_code":"13.0",
    "gn:asciiname":"Anjihai",
    "gn:country_code":"CN",
    "gn:dem":516,
    "gn:feature_class":"P",
    "gn:feature_code":"PPLA4",
    "gn:name":"Anjihai",
    "gn:population":0,
    "gn:timezone":"Asia/Urumqi",
    "iso:country":"CN",
    "name:und_x_variant":[
        "Anchikhai",
        "An-chi-hai",
        "Anchihaitai",
        "Yantszykhay",
        "Anjihai",
        "Anjihai Zhen"
    ],
    "name:zho_x_preferred":[
        "\u5b89\u96c6\u6d77"
    ],
    "name:zho_x_variant":[
        "\u5b89\u96c6\u6d77\u9547"
    ],
    "wof:name":"Anjihai",
    "wof:placetype":"locality"
},
  "geometry": {"coordinates":[85.35189,44.35787],"type":"Point"}
}