{
  "type": "Feature",
  "properties": {
    "gn:admin1_code":"26.0",
    "gn:asciiname":"Yangsiling",
    "gn:country_code":"CN",
    "gn:dem":761,
    "gn:feature_class":"P",
    "gn:feature_code":"PPL",
    "gn:name":"Yangsiling",
    "gn:population":0,
    "gn:timezone":"Asia/Shanghai",
    "iso:country":"CN",
    "name:und_x_variant":[
        "\u6768\u4e1d\u5cad"
    ],
    "wof:name":"Yangsiling",
    "wof:placetype":"locality"
},
  "geometry": {"coordinates":[106.95208,33.34156],"type":"Point"}
}