{
  "type": "Feature",
  "properties": {
    "gn:admin1_code":"4.0",
    "gn:asciiname":"Zongjiaqiao",
    "gn:country_code":"CN",
    "gn:dem":-2,
    "gn:feature_class":"P",
    "gn:feature_code":"PPL",
    "gn:name":"Zongjiaqiao",
    "gn:population":0,
    "gn:timezone":"Asia/Shanghai",
    "iso:country":"CN",
    "name:zho_x_preferred":[
        "\u5b97\u5bb6\u6865"
    ],
    "wof:name":"Zongjiaqiao",
    "wof:placetype":"locality"
},
  "geometry": {"coordinates":[120.059,33.7087],"type":"Point"}
}