{
  "type": "Feature",
  "properties": {
    "gn:admin1_code":"14.0",
    "gn:asciiname":"Qoixinub",
    "gn:country_code":"CN",
    "gn:dem":4771,
    "gn:feature_class":"P",
    "gn:feature_code":"PPL",
    "gn:name":"Qoixinub",
    "gn:population":0,
    "gn:timezone":"Asia/Urumqi",
    "iso:country":"CN",
    "name:bod_x_preferred":[
        "Qoixinub"
    ],
    "name:zho_x_preferred":[
        "Quxinu"
    ],
    "name:zho_x_variant":[
        "\u66f2\u559c\u52aa",
        "Quxi Gongshe",
        "\u66f2\u559c\u516c\u793e"
    ],
    "wof:name":"Qoixinub",
    "wof:placetype":"locality"
},
  "geometry": {"coordinates":[90.80200000000001,28.202],"type":"Point"}
}