{
  "type": "Feature",
  "properties": {
    "gn:admin1_code":"16.0",
    "gn:asciiname":"Sanhong",
    "gn:country_code":"CN",
    "gn:dem":875,
    "gn:feature_class":"P",
    "gn:feature_code":"PPL",
    "gn:name":"Sanhong",
    "gn:population":0,
    "gn:timezone":"Asia/Shanghai",
    "iso:country":"CN",
    "name:zho_x_preferred":[
        "\u4e09\u54c4"
    ],
    "wof:name":"Sanhong",
    "wof:placetype":"locality"
},
  "geometry": {"coordinates":[107.462,24.3369],"type":"Point"}
}