{
  "type": "Feature",
  "properties": {
    "gn:admin1_code":"32.0",
    "gn:asciiname":"Yena",
    "gn:country_code":"CN",
    "gn:dem":3091,
    "gn:feature_class":"P",
    "gn:feature_code":"PPL",
    "gn:name":"Yena",
    "gn:population":0,
    "gn:timezone":"Asia/Urumqi",
    "iso:country":"CN",
    "name:zho_x_preferred":[
        "\u91ce\u90a3"
    ],
    "wof:name":"Yena",
    "wof:placetype":"locality"
},
  "geometry": {"coordinates":[98.4597,31.7876],"type":"Point"}
}