{
  "type": "Feature",
  "properties": {
    "gn:admin1_code":"6.0",
    "gn:asciiname":"Dagelexiang",
    "gn:country_code":"CN",
    "gn:dem":2785,
    "gn:feature_class":"P",
    "gn:feature_code":"PPL",
    "gn:name":"Dagelexiang",
    "gn:population":0,
    "gn:timezone":"Asia/Urumqi",
    "iso:country":"CN",
    "name:und_x_variant":[
        "\u5927\u683c\u52d2\u4e61"
    ],
    "wof:name":"Dagelexiang",
    "wof:placetype":"locality"
},
  "geometry": {"coordinates":[95.75023,36.44325],"type":"Point"}
}