{
  "type": "Feature",
  "properties": {
    "gn:admin1_code":"19.0",
    "gn:asciiname":"Laoyelingcun",
    "gn:country_code":"CN",
    "gn:dem":157,
    "gn:feature_class":"P",
    "gn:feature_code":"PPL",
    "gn:name":"Laoyelingcun",
    "gn:population":0,
    "gn:timezone":"Asia/Shanghai",
    "iso:country":"CN",
    "name:zho_x_preferred":[
        "\u8001\u7237\u5cad\u6751"
    ],
    "wof:name":"Laoyelingcun",
    "wof:placetype":"locality"
},
  "geometry": {"coordinates":[123.26600000000001,41.0636],"type":"Point"}
}