{
  "type": "Feature",
  "properties": {
    "gn:admin1_code":"29.0",
    "gn:asciiname":"Wazizhai",
    "gn:country_code":"CN",
    "gn:dem":1462,
    "gn:feature_class":"P",
    "gn:feature_code":"PPL",
    "gn:name":"Wazizhai",
    "gn:population":0,
    "gn:timezone":"Asia/Shanghai",
    "iso:country":"CN",
    "name:zho_x_preferred":[
        "\u6d3c\u5b50\u5be8"
    ],
    "wof:name":"Wazizhai",
    "wof:placetype":"locality"
},
  "geometry": {"coordinates":[99.2938,24.0563],"type":"Point"}
}