{
  "type": "Feature",
  "properties": {
    "gn:admin1_code":"10",
    "gn:asciiname":"Wenjiazhuang",
    "gn:country_code":"CN",
    "gn:dem":92,
    "gn:feature_class":"P",
    "gn:feature_code":"PPL",
    "gn:name":"Wenjiazhuang",
    "gn:population":0,
    "gn:timezone":"Asia/Shanghai",
    "iso:country":"CN",
    "name:und_x_variant":[
        "\u6e29\u5bb6\u5e84"
    ],
    "wof:name":"Wenjiazhuang",
    "wof:placetype":"locality"
},
  "geometry": {"coordinates":[114.85419,38.68619],"type":"Point"}
}