{
  "type": "Feature",
  "properties": {
    "gn:admin1_code":"9.0",
    "gn:asciiname":"Laopogou",
    "gn:country_code":"CN",
    "gn:dem":1136,
    "gn:feature_class":"P",
    "gn:feature_code":"PPL",
    "gn:name":"Laopogou",
    "gn:population":0,
    "gn:timezone":"Asia/Shanghai",
    "iso:country":"CN",
    "name:zho_x_preferred":[
        "\u8001\u5a46\u6c9f"
    ],
    "wof:name":"Laopogou",
    "wof:placetype":"locality"
},
  "geometry": {"coordinates":[110.89605,33.76923],"type":"Point"}
}