{
  "type": "Feature",
  "properties": {
    "gn:admin1_code":"8.0",
    "gn:asciiname":"Baoxiangcun",
    "gn:country_code":"CN",
    "gn:dem":79,
    "gn:feature_class":"P",
    "gn:feature_code":"PPL",
    "gn:name":"Baoxiangcun",
    "gn:population":0,
    "gn:timezone":"Asia/Shanghai",
    "iso:country":"CN",
    "name:zho_x_preferred":[
        "\u4fdd\u7965\u6751"
    ],
    "wof:name":"Baoxiangcun",
    "wof:placetype":"locality"
},
  "geometry": {"coordinates":[130.37698999999998,47.00225],"type":"Point"}
}