{
  "type": "Feature",
  "properties": {
    "gn:admin1_code":"32.0",
    "gn:asciiname":"Tieliu",
    "gn:country_code":"CN",
    "gn:dem":1749,
    "gn:feature_class":"P",
    "gn:feature_code":"PPL",
    "gn:name":"Tieliu",
    "gn:population":0,
    "gn:timezone":"Asia/Shanghai",
    "iso:country":"CN",
    "name:zho_x_preferred":[
        "\u94c1\u67f3"
    ],
    "wof:name":"Tieliu",
    "wof:placetype":"locality"
},
  "geometry": {"coordinates":[102.51572,26.44082],"type":"Point"}
}