{
  "type": "Feature",
  "properties": {
    "gn:admin1_code":"24.0",
    "gn:asciiname":"Qingshiyicun",
    "gn:country_code":"CN",
    "gn:dem":763,
    "gn:feature_class":"P",
    "gn:feature_code":"PPL",
    "gn:name":"Qingshiyicun",
    "gn:population":0,
    "gn:timezone":"Asia/Shanghai",
    "iso:country":"CN",
    "name:zho_x_preferred":[
        "\u9752\u77f3\u4e00\u6751"
    ],
    "wof:name":"Qingshiyicun",
    "wof:placetype":"locality"
},
  "geometry": {"coordinates":[113.09327999999999,38.5685],"type":"Point"}
}