{
  "type": "Feature",
  "properties": {
    "gn:admin1_code":"10",
    "gn:asciiname":"Toumugoumen",
    "gn:country_code":"CN",
    "gn:dem":386,
    "gn:feature_class":"P",
    "gn:feature_code":"PPL",
    "gn:name":"Toumugoumen",
    "gn:population":0,
    "gn:timezone":"Asia/Shanghai",
    "iso:country":"CN",
    "name:zho_x_preferred":[
        "\u5934\u6728\u6c9f\u95e8"
    ],
    "wof:name":"Toumugoumen",
    "wof:placetype":"locality"
},
  "geometry": {"coordinates":[118.94998,40.67965],"type":"Point"}
}