{
  "type": "Feature",
  "properties": {
    "gn:admin1_code":"12.0",
    "gn:asciiname":"Kenjiawan",
    "gn:country_code":"CN",
    "gn:dem":559,
    "gn:feature_class":"P",
    "gn:feature_code":"PPL",
    "gn:name":"Kenjiawan",
    "gn:population":0,
    "gn:timezone":"Asia/Shanghai",
    "iso:country":"CN",
    "name:zho_x_preferred":[
        "\u80af\u5bb6\u5846"
    ],
    "wof:name":"Kenjiawan",
    "wof:placetype":"locality"
},
  "geometry": {"coordinates":[113.70005,32.06211],"type":"Point"}
}