{
  "type": "Feature",
  "properties": {
    "gn:admin1_code":"11.0",
    "gn:asciiname":"Yangquan",
    "gn:cc2":"CN",
    "gn:country_code":"CN",
    "gn:dem":192,
    "gn:feature_class":"P",
    "gn:feature_code":"PPL",
    "gn:name":"Yangquan",
    "gn:population":0,
    "gn:timezone":"Asia/Shanghai",
    "iso:country":"CN",
    "name:und_x_variant":[
        "Yang-ch\u2019\u00fcan",
        "Yangquan"
    ],
    "wof:name":"Yangquan",
    "wof:placetype":"locality"
},
  "geometry": {"coordinates":[112.38333,26.26667],"type":"Point"}
}