{
  "type": "Feature",
  "properties": {
    "gn:admin1_code":"9.0",
    "gn:asciiname":"Dongtielu",
    "gn:country_code":"CN",
    "gn:dem":198,
    "gn:feature_class":"P",
    "gn:feature_code":"PPL",
    "gn:name":"Dongtielu",
    "gn:population":0,
    "gn:timezone":"Asia/Shanghai",
    "iso:country":"CN",
    "name:zho_x_preferred":[
        "\u4e1c\u94c1\u7089"
    ],
    "wof:name":"Dongtielu",
    "wof:placetype":"locality"
},
  "geometry": {"coordinates":[112.21578999999998,34.52311],"type":"Point"}
}