{
  "type": "Feature",
  "properties": {
    "gn:admin1_code":"9.0",
    "gn:asciiname":"Zaozhuang",
    "gn:country_code":"CN",
    "gn:dem":140,
    "gn:feature_class":"P",
    "gn:feature_code":"PPL",
    "gn:name":"Zaozhuang",
    "gn:population":0,
    "gn:timezone":"Asia/Shanghai",
    "iso:country":"CN",
    "name:und_x_variant":[
        "\u67a3\u5e84"
    ],
    "name:zho_x_preferred":[
        "\u67a3\u5e84"
    ],
    "wof:name":"Zaozhuang",
    "wof:placetype":"locality"
},
  "geometry": {"coordinates":[113.06083,32.95295],"type":"Point"}
}