{
  "type": "Feature",
  "properties": {
    "gn:admin1_code":"30.0",
    "gn:asciiname":"Zizhulin",
    "gn:country_code":"CN",
    "gn:dem":59,
    "gn:feature_class":"P",
    "gn:feature_code":"PPL",
    "gn:name":"Zizhulin",
    "gn:population":0,
    "gn:timezone":"Asia/Shanghai",
    "iso:country":"CN",
    "name:zho_x_preferred":[
        "\u7d2b\u7af9\u6797"
    ],
    "wof:name":"Zizhulin",
    "wof:placetype":"locality"
},
  "geometry": {"coordinates":[113.15279,23.69742],"type":"Point"}
}