{
  "type": "Feature",
  "properties": {
    "gn:admin1_code":"2.0",
    "gn:asciiname":"Jincun",
    "gn:country_code":"CN",
    "gn:dem":133,
    "gn:feature_class":"P",
    "gn:feature_code":"PPL",
    "gn:name":"Jincun",
    "gn:population":0,
    "gn:timezone":"Asia/Shanghai",
    "iso:country":"CN",
    "name:und_x_variant":[
        "\u91d1\u6751",
        "Jincun"
    ],
    "wof:name":"Jincun",
    "wof:placetype":"locality"
},
  "geometry": {"coordinates":[119.78287,29.36955],"type":"Point"}
}