{
  "type": "Feature",
  "properties": {
    "gn:admin1_code":"3.0",
    "gn:asciiname":"Changqing",
    "gn:country_code":"CN",
    "gn:dem":68,
    "gn:feature_class":"P",
    "gn:feature_code":"PPL",
    "gn:name":"Changqing",
    "gn:population":0,
    "gn:timezone":"Asia/Shanghai",
    "iso:country":"CN",
    "name:und_x_variant":[
        "\u957f\u9752"
    ],
    "wof:name":"Changqing",
    "wof:placetype":"locality"
},
  "geometry": {"coordinates":[116.20565000000001,27.81112000000001],"type":"Point"}
}