{
  "type": "Feature",
  "properties": {
    "gn:admin1_code":"11.0",
    "gn:asciiname":"Liaojiaduan",
    "gn:country_code":"CN",
    "gn:dem":175,
    "gn:feature_class":"P",
    "gn:feature_code":"PPL",
    "gn:name":"Liaojiaduan",
    "gn:population":0,
    "gn:timezone":"Asia/Shanghai",
    "iso:country":"CN",
    "name:zho_x_preferred":[
        "Liaojiaduan"
    ],
    "name:zho_x_variant":[
        "\u5ed6\u5bb6\u5845"
    ],
    "wof:name":"Liaojiaduan",
    "wof:placetype":"locality"
},
  "geometry": {"coordinates":[114.06171999999999,28.46768],"type":"Point"}
}