{
  "type": "Feature",
  "properties": {
    "gn:admin1_code":"25",
    "gn:asciiname":"Wanghuajia",
    "gn:country_code":"CN",
    "gn:dem":22,
    "gn:feature_class":"P",
    "gn:feature_code":"PPL",
    "gn:name":"Wanghuajia",
    "gn:population":0,
    "gn:timezone":"Asia/Shanghai",
    "iso:country":"CN",
    "name:zho_x_preferred":[
        "\u738b\u82b1\u5bb6"
    ],
    "wof:name":"Wanghuajia",
    "wof:placetype":"locality"
},
  "geometry": {"coordinates":[116.755,37.0563],"type":"Point"}
}