{
  "type": "Feature",
  "properties": {
    "gn:admin1_code":"24.0",
    "gn:asciiname":"Zuiliutun",
    "gn:country_code":"CN",
    "gn:dem":1336,
    "gn:feature_class":"P",
    "gn:feature_code":"PPL",
    "gn:name":"Zuiliutun",
    "gn:population":0,
    "gn:timezone":"Asia/Shanghai",
    "iso:country":"CN",
    "name:zho_x_preferred":[
        "\u5480\u6d41\u5c6f"
    ],
    "wof:name":"Zuiliutun",
    "wof:placetype":"locality"
},
  "geometry": {"coordinates":[112.40327000000001,40.05528],"type":"Point"}
}