{
  "type": "Feature",
  "properties": {
    "gn:admin1_code":"10.0",
    "gn:asciiname":"Shuaijialiang",
    "gn:country_code":"CN",
    "gn:dem":1005,
    "gn:feature_class":"P",
    "gn:feature_code":"PPL",
    "gn:name":"Shuaijialiang",
    "gn:population":0,
    "gn:timezone":"Asia/Shanghai",
    "iso:country":"CN",
    "name:zho_x_preferred":[
        "\u5e05\u5bb6\u6881"
    ],
    "wof:name":"Shuaijialiang",
    "wof:placetype":"locality"
},
  "geometry": {"coordinates":[114.13424000000001,39.94878],"type":"Point"}
}