{
  "type": "Feature",
  "properties": {
    "gn:admin1_code":"25.0",
    "gn:asciiname":"Zhutai",
    "gn:cc2":"CN",
    "gn:country_code":"CN",
    "gn:dem":23,
    "gn:feature_class":"P",
    "gn:feature_code":"PPL",
    "gn:name":"Zhutai",
    "gn:population":0,
    "gn:timezone":"Asia/Shanghai",
    "iso:country":"CN",
    "name:und_x_variant":[
        "Chu-t\u2019ai",
        "Zhutai"
    ],
    "wof:name":"Zhutai",
    "wof:placetype":"locality"
},
  "geometry": {"coordinates":[118.25,36.95],"type":"Point"}
}