{
  "type": "Feature",
  "properties": {
    "gn:admin1_code":"1.0",
    "gn:asciiname":"Wulizhangcun",
    "gn:country_code":"CN",
    "gn:dem":26,
    "gn:feature_class":"P",
    "gn:feature_code":"PPL",
    "gn:name":"Wulizhangcun",
    "gn:population":0,
    "gn:timezone":"Asia/Shanghai",
    "iso:country":"CN",
    "name:zho_x_preferred":[
        "\u4e94\u91cc\u5f20\u6751"
    ],
    "wof:name":"Wulizhangcun",
    "wof:placetype":"locality"
},
  "geometry": {"coordinates":[116.68142,32.98523],"type":"Point"}
}