{
  "type": "Feature",
  "properties": {
    "gn:admin1_code":"2.0",
    "gn:asciiname":"Paizhuang",
    "gn:country_code":"CN",
    "gn:dem":45,
    "gn:feature_class":"P",
    "gn:feature_code":"PPL",
    "gn:name":"Paizhuang",
    "gn:population":0,
    "gn:timezone":"Asia/Shanghai",
    "iso:country":"CN",
    "name:zho_x_preferred":[
        "\u6d3e\u5e84"
    ],
    "wof:name":"Paizhuang",
    "wof:placetype":"locality"
},
  "geometry": {"coordinates":[120.66437000000001,28.27744],"type":"Point"}
}