{
  "type": "Feature",
  "properties": {
    "gn:admin1_code":"7",
    "gn:asciiname":"Cuoshizai",
    "gn:country_code":"CN",
    "gn:dem":102,
    "gn:feature_class":"P",
    "gn:feature_code":"PPL",
    "gn:name":"Cuoshizai",
    "gn:population":0,
    "gn:timezone":"Asia/Shanghai",
    "iso:country":"CN",
    "name:zho_x_preferred":[
        "\u539d\u5e02\u4ed4"
    ],
    "wof:name":"Cuoshizai",
    "wof:placetype":"locality"
},
  "geometry": {"coordinates":[117.28897000000001,24.42386],"type":"Point"}
}