{
  "type": "Feature",
  "properties": {
    "gn:admin1_code":"19.0",
    "gn:asciiname":"Wangniutai",
    "gn:country_code":"CN",
    "gn:dem":35,
    "gn:feature_class":"P",
    "gn:feature_code":"PPL",
    "gn:name":"Wangniutai",
    "gn:population":0,
    "gn:timezone":"Asia/Shanghai",
    "iso:country":"CN",
    "name:zho_x_preferred":[
        "\u671b\u725b\u53f0"
    ],
    "wof:name":"Wangniutai",
    "wof:placetype":"locality"
},
  "geometry": {"coordinates":[121.97123999999999,41.67817],"type":"Point"}
}