{
  "type": "Feature",
  "properties": {
    "gn:admin1_code":"25.0",
    "gn:asciiname":"Baimiaozi",
    "gn:cc2":"CN",
    "gn:country_code":"CN",
    "gn:dem":49,
    "gn:feature_class":"P",
    "gn:feature_code":"PPL",
    "gn:name":"Baimiaozi",
    "gn:population":0,
    "gn:timezone":"Asia/Shanghai",
    "iso:country":"CN",
    "name:zho_x_preferred":[
        "\u767d\u5e99\u5b50"
    ],
    "wof:name":"Baimiaozi",
    "wof:placetype":"locality"
},
  "geometry": {"coordinates":[119.84923999999999,36.13902],"type":"Point"}
}