{
  "type": "Feature",
  "properties": {
    "gn:admin1_code":"12",
    "gn:asciiname":"Wachenggou",
    "gn:country_code":"CN",
    "gn:dem":194,
    "gn:feature_class":"P",
    "gn:feature_code":"PPL",
    "gn:name":"Wachenggou",
    "gn:population":0,
    "gn:timezone":"Asia/Shanghai",
    "iso:country":"CN",
    "name:zho_x_preferred":[
        "\u74e6\u57ce\u6c9f"
    ],
    "wof:name":"Wachenggou",
    "wof:placetype":"locality"
},
  "geometry": {"coordinates":[111.63715000000001,32.57433],"type":"Point"}
}