{
  "type": "Feature",
  "properties": {
    "gn:admin1_code":"1.0",
    "gn:asciiname":"Shanbeicun",
    "gn:country_code":"CN",
    "gn:dem":27,
    "gn:feature_class":"P",
    "gn:feature_code":"PPL",
    "gn:name":"Shanbeicun",
    "gn:population":0,
    "gn:timezone":"Asia/Shanghai",
    "iso:country":"CN",
    "name:zho_x_preferred":[
        "\u5c71\u5317\u6751"
    ],
    "wof:name":"Shanbeicun",
    "wof:placetype":"locality"
},
  "geometry": {"coordinates":[118.13039000000001,33.01082],"type":"Point"}
}