{
  "type": "Feature",
  "properties": {
    "gn:admin1_code":"3.0",
    "gn:asciiname":"Mingkeng",
    "gn:country_code":"CN",
    "gn:dem":224,
    "gn:feature_class":"P",
    "gn:feature_code":"PPL",
    "gn:name":"Mingkeng",
    "gn:population":0,
    "gn:timezone":"Asia/Shanghai",
    "iso:country":"CN",
    "name:und_x_variant":[
        "\u660e\u5751"
    ],
    "wof:name":"Mingkeng",
    "wof:placetype":"locality"
},
  "geometry": {"coordinates":[116.13849,26.36056],"type":"Point"}
}