{
  "type": "Feature",
  "properties": {
    "gn:admin1_code":"11.0",
    "gn:asciiname":"Yetang",
    "gn:country_code":"CN",
    "gn:dem":434,
    "gn:feature_class":"P",
    "gn:feature_code":"PPL",
    "gn:name":"Yetang",
    "gn:population":0,
    "gn:timezone":"Asia/Shanghai",
    "iso:country":"CN",
    "name:zho_x_preferred":[
        "\u91ce\u5858"
    ],
    "wof:name":"Yetang",
    "wof:placetype":"locality"
},
  "geometry": {"coordinates":[109.75609,26.74799],"type":"Point"}
}