{
  "type": "Feature",
  "properties": {
    "gn:admin1_code":"14.0",
    "gn:asciiname":"Palai",
    "gn:country_code":"CN",
    "gn:dem":4371,
    "gn:feature_class":"P",
    "gn:feature_code":"PPL",
    "gn:name":"Palai",
    "gn:population":0,
    "gn:timezone":"Asia/Urumqi",
    "iso:country":"CN",
    "name:zho_x_preferred":[
        "\u5e15\u6765"
    ],
    "wof:name":"Palai",
    "wof:placetype":"locality"
},
  "geometry": {"coordinates":[87.0929,28.658],"type":"Point"}
}