{
  "type": "Feature",
  "properties": {
    "gn:admin1_code":"20",
    "gn:asciiname":"Bayan Ewenke Minzu",
    "gn:country_code":"CN",
    "gn:dem":257,
    "gn:feature_class":"P",
    "gn:feature_code":"PPLA4",
    "gn:name":"Bayan Ewenke Minzu",
    "gn:population":0,
    "gn:timezone":"Asia/Shanghai",
    "iso:country":"CN",
    "name:und_x_variant":[
        "Man-tu-hu-ch\u2019ien",
        "Bayan Ewenke Minzu",
        "Bayan Ewenke Minzu Xiang"
    ],
    "name:zho_x_preferred":[
        "\u5df4\u5f66\u9102\u6e29\u514b\u6c11\u65cf"
    ],
    "name:zho_x_variant":[
        "\u5df4\u5f66\u9102\u6e29\u514b\u6c11\u65cf\u4e61"
    ],
    "wof:name":"Bayan Ewenke Minzu",
    "wof:placetype":"locality"
},
  "geometry": {"coordinates":[124.76606,49.46229],"type":"Point"}
}