{
  "type": "Feature",
  "properties": {
    "gn:admin1_code":"32.0",
    "gn:asciiname":"Liaojia Tianba",
    "gn:country_code":"CN",
    "gn:dem":1657,
    "gn:feature_class":"P",
    "gn:feature_code":"PPL",
    "gn:name":"Liaojia Tianba",
    "gn:population":0,
    "gn:timezone":"Asia/Shanghai",
    "iso:country":"CN",
    "name:zho_x_preferred":[
        "\u5ed6\u5bb6\u7530\u575d"
    ],
    "wof:name":"Liaojia Tianba",
    "wof:placetype":"locality"
},
  "geometry": {"coordinates":[101.72083000000001,26.97198],"type":"Point"}
}