{
  "type": "Feature",
  "properties": {
    "gn:admin1_code":"2.0",
    "gn:asciiname":"Lusi Lingxia",
    "gn:country_code":"CN",
    "gn:dem":218,
    "gn:feature_class":"P",
    "gn:feature_code":"PPL",
    "gn:name":"Lusi Lingxia",
    "gn:population":0,
    "gn:timezone":"Asia/Shanghai",
    "iso:country":"CN",
    "name:zho_x_preferred":[
        "\u9e6d\u9e36\u5cad\u4e0b"
    ],
    "wof:name":"Lusi Lingxia",
    "wof:placetype":"locality"
},
  "geometry": {"coordinates":[120.37367,29.43928],"type":"Point"}
}