{
  "type": "Feature",
  "properties": {
    "gn:admin1_code":"29.0",
    "gn:asciiname":"Wuludi",
    "gn:country_code":"CN",
    "gn:dem":3518,
    "gn:feature_class":"P",
    "gn:feature_code":"PPL",
    "gn:name":"Wuludi",
    "gn:population":0,
    "gn:timezone":"Asia/Shanghai",
    "iso:country":"CN",
    "name:zho_x_preferred":[
        "\u96fe\u9732\u5e95"
    ],
    "wof:name":"Wuludi",
    "wof:placetype":"locality"
},
  "geometry": {"coordinates":[98.9156,28.4448],"type":"Point"}
}