{
  "type": "Feature",
  "properties": {
    "gn:admin1_code":"26.0",
    "gn:asciiname":"Si'erhe",
    "gn:country_code":"CN",
    "gn:dem":1181,
    "gn:feature_class":"P",
    "gn:feature_code":"PPL",
    "gn:name":"Si\u2019erhe",
    "gn:population":0,
    "gn:timezone":"Asia/Shanghai",
    "iso:country":"CN",
    "name:und_x_variant":[
        "Si\u2019erhe"
    ],
    "name:zho_x_preferred":[
        "\u5bfa\u8033\u6cb3"
    ],
    "wof:name":"Si'erhe",
    "wof:placetype":"locality"
},
  "geometry": {"coordinates":[109.66021000000001,35.76463],"type":"Point"}
}