{
  "type": "Feature",
  "properties": {
    "gn:admin1_code":"29.0",
    "gn:asciiname":"Songshan",
    "gn:country_code":"CN",
    "gn:dem":2297,
    "gn:feature_class":"P",
    "gn:feature_code":"PPL",
    "gn:name":"Songshan",
    "gn:population":0,
    "gn:timezone":"Asia/Shanghai",
    "iso:country":"CN",
    "name:ceb_x_preferred":[
        "Songshan"
    ],
    "name:deu_x_preferred":[
        "Songshan"
    ],
    "name:fra_x_preferred":[
        "Songshan"
    ],
    "name:pol_x_preferred":[
        "Songshan"
    ],
    "name:rus_x_preferred":[
        "\u0421\u0443\u043d\u0448\u0430\u043d\u044c"
    ],
    "name:sco_x_preferred":[
        "Songshan"
    ],
    "name:und_x_variant":[
        "\u677e\u5c71"
    ],
    "wof:name":"Songshan",
    "wof:placetype":"locality"
},
  "geometry": {"coordinates":[103.19840000000001,26.37147],"type":"Point"}
}