{
  "type": "Feature",
  "properties": {
    "gn:admin1_code":"07",
    "gn:asciiname":"Zhaixiapai",
    "gn:country_code":"CN",
    "gn:dem":240,
    "gn:feature_class":"P",
    "gn:feature_code":"PPL",
    "gn:name":"Zhaixiapai",
    "gn:population":0,
    "gn:timezone":"Asia/Shanghai",
    "iso:country":"CN",
    "name:zho_x_preferred":[
        "\u5be8\u4e0b\u6392"
    ],
    "wof:name":"Zhaixiapai",
    "wof:placetype":"locality"
},
  "geometry": {"coordinates":[116.19781999999999,24.99582],"type":"Point"}
}