{
  "type": "Feature",
  "properties": {
    "gn:admin1_code":"4.0",
    "gn:asciiname":"Yuanxing Liuzu",
    "gn:country_code":"CN",
    "gn:dem":2,
    "gn:feature_class":"P",
    "gn:feature_code":"PPL",
    "gn:name":"Yuanxing Liuzu",
    "gn:population":0,
    "gn:timezone":"Asia/Shanghai",
    "iso:country":"CN",
    "name:zho_x_preferred":[
        "\u5143\u5174\u516d\u7ec4"
    ],
    "wof:name":"Yuanxing Liuzu",
    "wof:placetype":"locality"
},
  "geometry": {"coordinates":[120.45272,32.81082],"type":"Point"}
}