{
  "type": "Feature",
  "properties": {
    "gn:admin1_code":"4.0",
    "gn:asciiname":"Shixicun",
    "gn:country_code":"CN",
    "gn:dem":1,
    "gn:feature_class":"P",
    "gn:feature_code":"PPL",
    "gn:name":"Shixicun",
    "gn:population":0,
    "gn:timezone":"Asia/Shanghai",
    "iso:country":"CN",
    "name:zho_x_preferred":[
        "\u65bd\u6eaa\u6751"
    ],
    "wof:name":"Shixicun",
    "wof:placetype":"locality"
},
  "geometry": {"coordinates":[120.27446999999999,32.65973],"type":"Point"}
}