{
  "type": "Feature",
  "properties": {
    "gn:admin1_code":"10",
    "gn:asciiname":"Gangou",
    "gn:country_code":"CN",
    "gn:dem":1073,
    "gn:feature_class":"P",
    "gn:feature_code":"PPL",
    "gn:name":"Gangou",
    "gn:population":0,
    "gn:timezone":"Asia/Shanghai",
    "iso:country":"CN",
    "name:zho_x_preferred":[
        "\u5e72\u6c9f"
    ],
    "wof:name":"Gangou",
    "wof:placetype":"locality"
},
  "geometry": {"coordinates":[116.0257,41.10346],"type":"Point"}
}