{
  "type": "Feature",
  "properties": {
    "gn:admin1_code":"26.0",
    "gn:asciiname":"Zhengjiabacun",
    "gn:country_code":"CN",
    "gn:dem":640,
    "gn:feature_class":"P",
    "gn:feature_code":"PPL",
    "gn:name":"Zhengjiabacun",
    "gn:population":0,
    "gn:timezone":"Asia/Shanghai",
    "iso:country":"CN",
    "name:zho_x_preferred":[
        "\u90d1\u5bb6\u575d\u6751"
    ],
    "wof:name":"Zhengjiabacun",
    "wof:placetype":"locality"
},
  "geometry": {"coordinates":[107.00700999999999,32.85289],"type":"Point"}
}