{
  "type": "Feature",
  "properties": {
    "gn:admin1_code":"9.0",
    "gn:asciiname":"Tieluotou",
    "gn:country_code":"CN",
    "gn:dem":93,
    "gn:feature_class":"P",
    "gn:feature_code":"PPL",
    "gn:name":"Tieluotou",
    "gn:population":0,
    "gn:timezone":"Asia/Shanghai",
    "iso:country":"CN",
    "name:zho_x_preferred":[
        "\u94c1\u7f57\u5934"
    ],
    "wof:name":"Tieluotou",
    "wof:placetype":"locality"
},
  "geometry": {"coordinates":[113.27392,35.15226],"type":"Point"}
}