{
  "type": "Feature",
  "properties": {
    "gn:admin1_code":"26.0",
    "gn:asciiname":"Hujiahao",
    "gn:country_code":"CN",
    "gn:dem":1281,
    "gn:feature_class":"P",
    "gn:feature_code":"PPL",
    "gn:name":"Hujiahao",
    "gn:population":0,
    "gn:timezone":"Asia/Shanghai",
    "iso:country":"CN",
    "name:zho_x_preferred":[
        "\u547c\u5bb6\u58d5"
    ],
    "wof:name":"Hujiahao",
    "wof:placetype":"locality"
},
  "geometry": {"coordinates":[110.03455,39.08283],"type":"Point"}
}