{
  "type": "Feature",
  "properties": {
    "gn:admin1_code":"3",
    "gn:asciiname":"Wuzhifeng",
    "gn:country_code":"CN",
    "gn:dem":740,
    "gn:feature_class":"P",
    "gn:feature_code":"PPL",
    "gn:name":"Wuzhifeng",
    "gn:population":0,
    "gn:timezone":"Asia/Shanghai",
    "iso:country":"CN",
    "name:zho_x_preferred":[
        "\u4e94\u6307\u5cf0"
    ],
    "wof:name":"Wuzhifeng",
    "wof:placetype":"locality"
},
  "geometry": {"coordinates":[114.21062999999999,26.36494],"type":"Point"}
}