{
  "type": "Feature",
  "properties": {
    "gn:admin1_code":"19.0",
    "gn:asciiname":"Dachegou",
    "gn:country_code":"CN",
    "gn:dem":159,
    "gn:feature_class":"P",
    "gn:feature_code":"PPL",
    "gn:name":"Dachegou",
    "gn:population":0,
    "gn:timezone":"Asia/Shanghai",
    "iso:country":"CN",
    "name:und_x_variant":[
        "\u6253\u8f66\u6c9f"
    ],
    "name:zho_x_preferred":[
        "\u6253\u8f66\u6c9f"
    ],
    "wof:name":"Dachegou",
    "wof:placetype":"locality"
},
  "geometry": {"coordinates":[124.26866,42.57332],"type":"Point"}
}