{
  "type": "Feature",
  "properties": {
    "gn:admin1_code":"7.0",
    "gn:asciiname":"Yaoli",
    "gn:country_code":"CN",
    "gn:dem":719,
    "gn:feature_class":"P",
    "gn:feature_code":"PPL",
    "gn:name":"Yaoli",
    "gn:population":0,
    "gn:timezone":"Asia/Shanghai",
    "iso:country":"CN",
    "name:und_x_variant":[
        "\u7476\u91cc"
    ],
    "name:zho_x_preferred":[
        "\u7476\u91cc"
    ],
    "wof:name":"Yaoli",
    "wof:placetype":"locality"
},
  "geometry": {"coordinates":[116.56258,25.4459],"type":"Point"}
}