{
  "type": "Feature",
  "properties": {
    "gn:admin1_code":"16.0",
    "gn:asciiname":"Fubian",
    "gn:country_code":"CN",
    "gn:dem":345,
    "gn:feature_class":"P",
    "gn:feature_code":"PPL",
    "gn:name":"Fubian",
    "gn:population":0,
    "gn:timezone":"Asia/Shanghai",
    "iso:country":"CN",
    "name:zho_x_preferred":[
        "\u798f\u8fb9"
    ],
    "wof:name":"Fubian",
    "wof:placetype":"locality"
},
  "geometry": {"coordinates":[111.254,25.0838],"type":"Point"}
}