{
  "type": "Feature",
  "properties": {
    "gn:admin1_code":"09",
    "gn:asciiname":"Dahe",
    "gn:country_code":"CN",
    "gn:dem":238,
    "gn:feature_class":"P",
    "gn:feature_code":"PPL",
    "gn:name":"Dahe",
    "gn:population":0,
    "gn:timezone":"Asia/Shanghai",
    "iso:country":"CN",
    "name:ceb_x_preferred":[
        "Dahe"
    ],
    "name:deu_x_preferred":[
        "Dahe"
    ],
    "name:swe_x_preferred":[
        "Dahe"
    ],
    "wof:name":"Dahe",
    "wof:placetype":"locality"
},
  "geometry": {"coordinates":[113.36944,32.4975],"type":"Point"}
}