{
  "type": "Feature",
  "properties": {
    "gn:admin1_code":"24.0",
    "gn:asciiname":"Sihoucun",
    "gn:country_code":"CN",
    "gn:dem":503,
    "gn:feature_class":"P",
    "gn:feature_code":"PPL",
    "gn:name":"Sihoucun",
    "gn:population":0,
    "gn:timezone":"Asia/Shanghai",
    "iso:country":"CN",
    "name:zho_x_preferred":[
        "\u5bfa\u540e\u6751"
    ],
    "wof:name":"Sihoucun",
    "wof:placetype":"locality"
},
  "geometry": {"coordinates":[110.59443,35.1367],"type":"Point"}
}