{
  "type": "Feature",
  "properties": {
    "gn:admin1_code":"32.0",
    "gn:asciiname":"Shixianggou",
    "gn:country_code":"CN",
    "gn:dem":1120,
    "gn:feature_class":"P",
    "gn:feature_code":"PPL",
    "gn:name":"Shixianggou",
    "gn:population":0,
    "gn:timezone":"Asia/Shanghai",
    "iso:country":"CN",
    "name:zho_x_preferred":[
        "\u77f3\u9999\u6c9f"
    ],
    "wof:name":"Shixianggou",
    "wof:placetype":"locality"
},
  "geometry": {"coordinates":[103.446,30.7709],"type":"Point"}
}