{
  "type": "Feature",
  "properties": {
    "gn:admin1_code":"14.0",
    "gn:asciiname":"Gaiba",
    "gn:country_code":"CN",
    "gn:dem":3262,
    "gn:feature_class":"P",
    "gn:feature_code":"PPL",
    "gn:name":"Gaiba",
    "gn:population":0,
    "gn:timezone":"Asia/Urumqi",
    "iso:country":"CN",
    "name:bod_x_preferred":[
        "Gaiba"
    ],
    "name:zho_x_preferred":[
        "Geba"
    ],
    "name:zho_x_variant":[
        "\u683c\u5df4"
    ],
    "wof:name":"Gaiba",
    "wof:placetype":"locality"
},
  "geometry": {"coordinates":[98.06256999999999,28.96273],"type":"Point"}
}