{
  "type": "Feature",
  "properties": {
    "gn:admin1_code":"14.0",
    "gn:asciiname":"Gaiba",
    "gn:country_code":"CN",
    "gn:dem":3262,
    "gn:feature_class":"P",
    "gn:feature_code":"PPL",
    "gn:name":"Gaiba",
    "gn:population":0,
    "gn:timezone":"Asia/Urumqi",
    "iso:country":"CN",
    "name:azb_x_preferred":[
        "\u062c\u0627\u06cc\u0628\u0627"
    ],
    "name:bel_x_preferred":[
        "\u0413\u0430\u0439\u0431\u0430"
    ],
    "name:bod_x_preferred":[
        "Gaiba"
    ],
    "name:bul_x_preferred":[
        "\u0413\u0430\u0439\u0431\u0430"
    ],
    "name:cat_x_preferred":[
        "Gaiba"
    ],
    "name:ceb_x_preferred":[
        "Gaiba"
    ],
    "name:deu_x_preferred":[
        "Gaiba"
    ],
    "name:eml_x_preferred":[
        "G\u00e0iba"
    ],
    "name:epo_x_preferred":[
        "Gaiba"
    ],
    "name:eus_x_preferred":[
        "Gaiba"
    ],
    "name:fas_x_preferred":[
        "\u062c\u0627\u06cc\u0628\u0627"
    ],
    "name:fra_x_preferred":[
        "Gaiba"
    ],
    "name:hun_x_preferred":[
        "Gaiba"
    ],
    "name:hye_x_preferred":[
        "\u0533\u0561\u0575\u0562\u0561"
    ],
    "name:ita_x_preferred":[
        "Gaiba"
    ],
    "name:jpn_x_preferred":[
        "\u30ac\u30a4\u30d0"
    ],
    "name:kaz_x_preferred":[
        "\u0413\u0430\u0439\u0431\u0430"
    ],
    "name:kor_x_preferred":[
        "\uac00\uc774\ubc14"
    ],
    "name:lat_x_preferred":[
        "Gaiba"
    ],
    "name:lmo_x_preferred":[
        "Gaiba"
    ],
    "name:msa_x_preferred":[
        "Gaiba"
    ],
    "name:nap_x_preferred":[
        "Gaiba"
    ],
    "name:nld_x_preferred":[
        "Gaiba"
    ],
    "name:pms_x_preferred":[
        "Gaiba"
    ],
    "name:pol_x_preferred":[
        "Gaiba"
    ],
    "name:por_x_preferred":[
        "Gaiba"
    ],
    "name:ron_x_preferred":[
        "Gaiba"
    ],
    "name:rus_x_preferred":[
        "\u0413\u0430\u0439\u0431\u0430"
    ],
    "name:scn_x_preferred":[
        "Gaiba"
    ],
    "name:spa_x_preferred":[
        "Gaiba"
    ],
    "name:srp_x_preferred":[
        "\u0413\u0430\u0438\u0431\u0430"
    ],
    "name:tgl_x_preferred":[
        "Gaiba"
    ],
    "name:ukr_x_preferred":[
        "\u0413\u0430\u0457\u0431\u0430"
    ],
    "name:uzb_x_preferred":[
        "Gaiba"
    ],
    "name:vec_x_preferred":[
        "Gaiba"
    ],
    "name:vie_x_preferred":[
        "Gaiba"
    ],
    "name:vol_x_preferred":[
        "Gaiba"
    ],
    "name:war_x_preferred":[
        "Gaiba"
    ],
    "name:zho_x_preferred":[
        "Geba"
    ],
    "name:zho_x_variant":[
        "\u683c\u5df4",
        "\u52a0\u4f0a\u5df4"
    ],
    "wof:name":"Gaiba",
    "wof:placetype":"locality"
},
  "geometry": {"coordinates":[98.06256999999999,28.96273],"type":"Point"}
}