{
  "type": "Feature",
  "properties": {
    "gn:admin1_code":"2",
    "gn:asciiname":"Quyuan",
    "gn:country_code":"CN",
    "gn:dem":411,
    "gn:feature_class":"P",
    "gn:feature_code":"PPL",
    "gn:name":"Quyuan",
    "gn:population":0,
    "gn:timezone":"Asia/Shanghai",
    "iso:country":"CN",
    "name:zho_x_preferred":[
        "\u77bf\u6e90"
    ],
    "wof:name":"Quyuan",
    "wof:placetype":"locality"
},
  "geometry": {"coordinates":[119.17556,27.99556],"type":"Point"}
}