{
  "type": "Feature",
  "properties": {
    "gn:admin1_code":"19.0",
    "gn:asciiname":"Shangduodao",
    "gn:country_code":"CN",
    "gn:dem":315,
    "gn:feature_class":"P",
    "gn:feature_code":"PPL",
    "gn:name":"Shangduodao",
    "gn:population":0,
    "gn:timezone":"Asia/Shanghai",
    "iso:country":"CN",
    "name:und_x_variant":[
        "\u4e0a\u579b\u9053"
    ],
    "wof:name":"Shangduodao",
    "wof:placetype":"locality"
},
  "geometry": {"coordinates":[125.39561999999999,40.95927],"type":"Point"}
}