{
  "type": "Feature",
  "properties": {
    "gn:admin1_code":"18",
    "gn:asciiname":"Shaoguantian",
    "gn:country_code":"CN",
    "gn:dem":1264,
    "gn:feature_class":"P",
    "gn:feature_code":"PPL",
    "gn:name":"Shaoguantian",
    "gn:population":0,
    "gn:timezone":"Asia/Shanghai",
    "iso:country":"CN",
    "name:zho_x_preferred":[
        "\u54e8\u5173\u7530"
    ],
    "wof:name":"Shaoguantian",
    "wof:placetype":"locality"
},
  "geometry": {"coordinates":[106.91200000000001,26.4816],"type":"Point"}
}