{
  "type": "Feature",
  "properties": {
    "gn:admin1_code":"18",
    "gn:asciiname":"Xiaomiaozhai",
    "gn:country_code":"CN",
    "gn:dem":1331,
    "gn:feature_class":"P",
    "gn:feature_code":"PPL",
    "gn:name":"Xiaomiaozhai",
    "gn:population":0,
    "gn:timezone":"Asia/Shanghai",
    "iso:country":"CN",
    "name:zho_x_preferred":[
        "\u5c0f\u82d7\u5be8"
    ],
    "wof:name":"Xiaomiaozhai",
    "wof:placetype":"locality"
},
  "geometry": {"coordinates":[105.105,26.3605],"type":"Point"}
}