{
  "type": "Feature",
  "properties": {
    "gn:admin1_code":"32.0",
    "gn:asciiname":"Wasigou",
    "gn:cc2":"CN",
    "gn:country_code":"CN",
    "gn:dem":1785,
    "gn:feature_class":"P",
    "gn:feature_code":"PPL",
    "gn:name":"Wasigou",
    "gn:population":0,
    "gn:timezone":"Asia/Shanghai",
    "iso:country":"CN",
    "name:und_x_variant":[
        "Vas\u00f6gou",
        "Wa-ssu-kou",
        "Waszekow",
        "Wasigou"
    ],
    "wof:name":"Wasigou",
    "wof:placetype":"locality"
},
  "geometry": {"coordinates":[102.16667,30.06667],"type":"Point"}
}