{
  "type": "Feature",
  "properties": {
    "gn:admin1_code":"21.0",
    "gn:asciiname":"Sanhezhuang",
    "gn:country_code":"CN",
    "gn:dem":1792,
    "gn:feature_class":"P",
    "gn:feature_code":"PPL",
    "gn:name":"Sanhezhuang",
    "gn:population":0,
    "gn:timezone":"Asia/Shanghai",
    "iso:country":"CN",
    "name:zho_x_preferred":[
        "\u4e09\u5408\u5e84"
    ],
    "wof:name":"Sanhezhuang",
    "wof:placetype":"locality"
},
  "geometry": {"coordinates":[106.408,35.3564],"type":"Point"}
}