{
  "type": "Feature",
  "properties": {
    "gn:admin1_code":"8.0",
    "gn:asciiname":"Junlecun",
    "gn:country_code":"CN",
    "gn:dem":198,
    "gn:feature_class":"P",
    "gn:feature_code":"PPL",
    "gn:name":"Junlecun",
    "gn:population":0,
    "gn:timezone":"Asia/Shanghai",
    "iso:country":"CN",
    "name:zho_x_preferred":[
        "\u5747\u4e50\u6751"
    ],
    "wof:name":"Junlecun",
    "wof:placetype":"locality"
},
  "geometry": {"coordinates":[126.6536,47.44654],"type":"Point"}
}