{
  "type": "Feature",
  "properties": {
    "gn:admin1_code":"32.0",
    "gn:asciiname":"Lajiajia",
    "gn:country_code":"CN",
    "gn:dem":2623,
    "gn:feature_class":"P",
    "gn:feature_code":"PPL",
    "gn:name":"Lajiajia",
    "gn:population":0,
    "gn:timezone":"Asia/Shanghai",
    "iso:country":"CN",
    "name:zho_x_preferred":[
        "\u814a\u7532\u7532"
    ],
    "wof:name":"Lajiajia",
    "wof:placetype":"locality"
},
  "geometry": {"coordinates":[102.0489,28.78552],"type":"Point"}
}