{
  "type": "Feature",
  "properties": {
    "gn:admin1_code":"15.0",
    "gn:asciiname":"Shijiashan Yicun",
    "gn:country_code":"CN",
    "gn:dem":2205,
    "gn:feature_class":"P",
    "gn:feature_code":"PPL",
    "gn:name":"Shijiashan Yicun",
    "gn:population":0,
    "gn:timezone":"Asia/Shanghai",
    "iso:country":"CN",
    "name:zho_x_preferred":[
        "\u77f3\u5bb6\u5c71\u4e00\u6751"
    ],
    "wof:name":"Shijiashan Yicun",
    "wof:placetype":"locality"
},
  "geometry": {"coordinates":[104.46733999999999,33.73196],"type":"Point"}
}