{
  "type": "Feature",
  "properties": {
    "gn:admin1_code":"7.0",
    "gn:asciiname":"Cunlicun",
    "gn:country_code":"CN",
    "gn:dem":282,
    "gn:feature_class":"P",
    "gn:feature_code":"PPL",
    "gn:name":"Cunlicun",
    "gn:population":0,
    "gn:timezone":"Asia/Shanghai",
    "iso:country":"CN",
    "name:zho_x_preferred":[
        "\u6751\u91cc\u6751"
    ],
    "wof:name":"Cunlicun",
    "wof:placetype":"locality"
},
  "geometry": {"coordinates":[116.42574999999999,24.88604],"type":"Point"}
}