{
  "type": "Feature",
  "properties": {
    "gn:admin1_code":"29.0",
    "gn:asciiname":"Pianyan",
    "gn:country_code":"CN",
    "gn:dem":1347,
    "gn:feature_class":"P",
    "gn:feature_code":"PPL",
    "gn:name":"Pianyan",
    "gn:population":0,
    "gn:timezone":"Asia/Shanghai",
    "iso:country":"CN",
    "name:zho_x_preferred":[
        "\u504f\u5ca9"
    ],
    "wof:name":"Pianyan",
    "wof:placetype":"locality"
},
  "geometry": {"coordinates":[104.34699999999999,22.9061],"type":"Point"}
}