{
  "type": "Feature",
  "properties": {
    "gn:admin1_code":"2.0",
    "gn:asciiname":"Datongqiao",
    "gn:country_code":"CN",
    "gn:dem":437,
    "gn:feature_class":"P",
    "gn:feature_code":"PPL",
    "gn:name":"Datongqiao",
    "gn:population":0,
    "gn:timezone":"Asia/Shanghai",
    "iso:country":"CN",
    "name:zho_x_preferred":[
        "\u5927\u901a\u6865"
    ],
    "wof:name":"Datongqiao",
    "wof:placetype":"locality"
},
  "geometry": {"coordinates":[120.99955,29.22483],"type":"Point"}
}