{
  "type": "Feature",
  "properties": {
    "gn:admin1_code":"18",
    "gn:asciiname":"Xiaoluomai",
    "gn:country_code":"CN",
    "gn:dem":1138,
    "gn:feature_class":"P",
    "gn:feature_code":"PPL",
    "gn:name":"Xiaoluomai",
    "gn:population":0,
    "gn:timezone":"Asia/Shanghai",
    "iso:country":"CN",
    "name:zho_x_preferred":[
        "\u5c0f\u6d1b\u9ea6"
    ],
    "wof:name":"Xiaoluomai",
    "wof:placetype":"locality"
},
  "geometry": {"coordinates":[106.282,25.9109],"type":"Point"}
}