{
  "type": "Feature",
  "properties": {
    "gn:admin1_code":"29.0",
    "gn:asciiname":"Shahe Yakou",
    "gn:country_code":"CN",
    "gn:dem":1874,
    "gn:feature_class":"P",
    "gn:feature_code":"PPL",
    "gn:name":"Shahe Yakou",
    "gn:population":0,
    "gn:timezone":"Asia/Shanghai",
    "iso:country":"CN",
    "name:zho_x_preferred":[
        "\u6c99\u6cb3\u57ad\u53e3"
    ],
    "wof:name":"Shahe Yakou",
    "wof:placetype":"locality"
},
  "geometry": {"coordinates":[102.398,25.4736],"type":"Point"}
}