{
  "type": "Feature",
  "properties": {
    "gn:admin1_code":"3.0",
    "gn:asciiname":"Meilin",
    "gn:country_code":"CN",
    "gn:dem":96,
    "gn:feature_class":"P",
    "gn:feature_code":"PPL",
    "gn:name":"Meilin",
    "gn:population":0,
    "gn:timezone":"Asia/Shanghai",
    "iso:country":"CN",
    "name:ceb_x_preferred":[
        "Meilin"
    ],
    "name:deu_x_preferred":[
        "Meilin"
    ],
    "name:swe_x_preferred":[
        "Meilin"
    ],
    "name:und_x_variant":[
        "\u6885\u6797"
    ],
    "wof:name":"Meilin",
    "wof:placetype":"locality"
},
  "geometry": {"coordinates":[115.52437,29.05434],"type":"Point"}
}