{
  "type": "Feature",
  "properties": {
    "gn:admin1_code":"16.0",
    "gn:asciiname":"Luolou",
    "gn:country_code":"CN",
    "gn:dem":160,
    "gn:feature_class":"P",
    "gn:feature_code":"PPL",
    "gn:name":"Luolou",
    "gn:population":0,
    "gn:timezone":"Asia/Shanghai",
    "iso:country":"CN",
    "name:zho_x_preferred":[
        "\u6d1b\u6f0f"
    ],
    "wof:name":"Luolou",
    "wof:placetype":"locality"
},
  "geometry": {"coordinates":[108.751,24.5507],"type":"Point"}
}