{
  "type": "Feature",
  "properties": {
    "gn:admin1_code":"4.0",
    "gn:asciiname":"Xuzhuangcun",
    "gn:country_code":"CN",
    "gn:dem":7,
    "gn:feature_class":"P",
    "gn:feature_code":"PPL",
    "gn:name":"Xuzhuangcun",
    "gn:population":0,
    "gn:timezone":"Asia/Shanghai",
    "iso:country":"CN",
    "name:zho_x_preferred":[
        "\u5f90\u5e84\u6751"
    ],
    "wof:name":"Xuzhuangcun",
    "wof:placetype":"locality"
},
  "geometry": {"coordinates":[119.26891999999999,34.10570999999999],"type":"Point"}
}