{
  "type": "Feature",
  "properties": {
    "gn:admin1_code":"9.0",
    "gn:asciiname":"Xiaohanzhuang",
    "gn:country_code":"CN",
    "gn:dem":147,
    "gn:feature_class":"P",
    "gn:feature_code":"PPL",
    "gn:name":"Xiaohanzhuang",
    "gn:population":0,
    "gn:timezone":"Asia/Shanghai",
    "iso:country":"CN",
    "name:zho_x_preferred":[
        "\u5c0f\u97e9\u5e84"
    ],
    "wof:name":"Xiaohanzhuang",
    "wof:placetype":"locality"
},
  "geometry": {"coordinates":[113.80504999999999,34.58561],"type":"Point"}
}