{
  "type": "Feature",
  "properties": {
    "gn:admin1_code":"8.0",
    "gn:asciiname":"Meiman",
    "gn:country_code":"CN",
    "gn:dem":196,
    "gn:feature_class":"P",
    "gn:feature_code":"PPL",
    "gn:name":"Meiman",
    "gn:population":0,
    "gn:timezone":"Asia/Shanghai",
    "iso:country":"CN",
    "name:zho_x_preferred":[
        "\u7f8e\u6ee1"
    ],
    "wof:name":"Meiman",
    "wof:placetype":"locality"
},
  "geometry": {"coordinates":[123.49254000000001,47.89045],"type":"Point"}
}