{
  "type": "Feature",
  "properties": {
    "gn:admin1_code":"11.0",
    "gn:asciiname":"Huangshadian",
    "gn:country_code":"CN",
    "gn:dem":191,
    "gn:feature_class":"P",
    "gn:feature_code":"PPL",
    "gn:name":"Huangshadian",
    "gn:population":0,
    "gn:timezone":"Asia/Shanghai",
    "iso:country":"CN",
    "name:zho_x_preferred":[
        "\u9ec4\u6c99\u5e97"
    ],
    "wof:name":"Huangshadian",
    "wof:placetype":"locality"
},
  "geometry": {"coordinates":[113.85487000000001,28.09692],"type":"Point"}
}