{
  "type": "Feature",
  "properties": {
    "gn:admin1_code":"1.0",
    "gn:asciiname":"Huangyaodiancun",
    "gn:country_code":"CN",
    "gn:dem":35,
    "gn:feature_class":"P",
    "gn:feature_code":"PPL",
    "gn:name":"Huangyaodiancun",
    "gn:population":0,
    "gn:timezone":"Asia/Shanghai",
    "iso:country":"CN",
    "name:zho_x_preferred":[
        "\u9ec4\u836f\u5e97\u6751"
    ],
    "wof:name":"Huangyaodiancun",
    "wof:placetype":"locality"
},
  "geometry": {"coordinates":[116.66791000000001,34.04441],"type":"Point"}
}