{
  "type": "Feature",
  "properties": {
    "gn:admin1_code":"10",
    "gn:asciiname":"Maquanzi",
    "gn:country_code":"CN",
    "gn:dem":647,
    "gn:feature_class":"P",
    "gn:feature_code":"PPL",
    "gn:name":"Maquanzi",
    "gn:population":0,
    "gn:timezone":"Asia/Shanghai",
    "iso:country":"CN",
    "name:zho_x_preferred":[
        "\u9a6c\u6cc9\u5b50"
    ],
    "wof:name":"Maquanzi",
    "wof:placetype":"locality"
},
  "geometry": {"coordinates":[118.81310000000001,41.30378],"type":"Point"}
}