{
  "type": "Feature",
  "properties": {
    "gn:admin1_code":"32.0",
    "gn:asciiname":"Pagu",
    "gn:country_code":"CN",
    "gn:dem":2250,
    "gn:feature_class":"P",
    "gn:feature_code":"PPL",
    "gn:name":"Pagu",
    "gn:population":0,
    "gn:timezone":"Asia/Shanghai",
    "iso:country":"CN",
    "name:fra_x_preferred":[
        "Pagu"
    ],
    "name:ita_x_preferred":[
        "Pagu"
    ],
    "name:por_x_preferred":[
        "Pagu"
    ],
    "name:rus_x_preferred":[
        "\u041f\u0430\u0433\u0443"
    ],
    "name:spa_x_preferred":[
        "Pagu"
    ],
    "name:zho_x_preferred":[
        "\u5e15\u53e4"
    ],
    "wof:name":"Pagu",
    "wof:placetype":"locality"
},
  "geometry": {"coordinates":[103.139,28.4112],"type":"Point"}
}